Workbook
Name _LockStatus: 账户数据!$B$23
Name _AccountRiskLimit: 账户数据!$B$7
Name _TrackRule: 持仓跟踪!$AC$2:$AC$157
Name _TrackTradeId: 持仓跟踪!$B$2:$B$157
Name _TrackType: 持仓跟踪!$A$2:$A$157
Name _TradeIds: 单次交易!$A$2:$A$98
Name 技术指标列表: 技术指标!$A$2:$A$201

Sheet 单次交易
A1: 交易编号 | B1: 股票代码 | C1: 买入时账户金额 | D1: 本次允许亏损比例 | E1: 第一批买入价 | F1: 买入建议股数 | G1: 开仓风险告警 | H1: 第一批买入股数 | I1: 首次买入日期 | J1: 期望卖出价 | K1: 实际卖出价 | L1: 卖出股数 | M1: 卖出日期 | N1: 止损价 | O1: 买入总费用 | P1: 卖出费用 | Q1: 买入价的由来 | R1: 止损价的由来 | S1: 期望卖出价的由来 | T1: 实际卖出价的由来 | U1: 期望盈利比例 | V1: 期望止损比例 | W1: 盈亏比 | X1: 实际盈亏金额 | Y1: 单笔仓位收益率 | Z1: 账户收益率与平均盈利率差值 | AA1: 持有天数 | AB1: 复利容许平均亏损上限 | AC1: 复利风险判断 | AD1: 交易打分评价 | AE1: 实际账户收益率 | AF1: 列1 | AG1: 交易预期类型 | AH1: 预期持有周期 | AI1: 预期选择理由 | AJ1: 周期匹配检查 | AK1: 第二批买入价 | AL1: 第二批买入股数 | AM1: 第三批买入价 | AN1: 第三批买入股数 | AO1: 实际加权买入价 | AP1: 累计买入股数 | AQ1: 当前持仓风险 | AR1: 分仓规则检查
A2: 1 | B2: 节电风能 | C2: 100000 | D2: 0.02 | E2: 3.9 | F2: =IF(OR(C2="",D2="",E2="",N2="",C2<=0,D2<=0,E2<=N2),"",ROUNDDOWN((C2*D2)/(E2-N2)/100,0)*100) -> 10000 | G2: =IF(A2="","",IF(H2<>"","已开仓",IF(账户数据!$B$23="已锁仓","禁止开仓：连续亏损达到上限",IF(账户数据!$B$23="解锁信息不完整","禁止开仓：请完整填写解锁信息",IF(OR(F2="",E2="",N2="",E2<=N2,账户数据!$B$7=""),"",IF(OR(AG2="",AH2="",AI2=""),"禁止开仓：交易预期未填写完整",IF(COUNTIFS(持仓跟踪!$A$2:$A$157,"止损计划",持仓跟踪!$B$2:$B$157,A2,持仓跟踪!$AC$2:$AC$157,"计划有效")=0,"禁止开仓：请先填写止损计划",IF(账户数据!$B$9+F2*(E2-N2)>=账户数据!$B$7,"禁止开仓：风险额度不足",IF(AJ2="周期与交易预期不匹配，请重新确认",IF(账户数据!$B$23="接近锁仓","允许开仓（接近锁仓；周期需复核）","允许开仓（周期需复核）"),IF(账户数据!$B$23="接近锁仓","允许开仓（接近锁仓）","允许开仓")))))))))) -> 已开仓 | H2: 5000 | I2: 42570 | J2: 4 | K2: 3.68 | L2: 5000 | M2: =IF(A2="","",IFERROR(LOOKUP(2,1/((持仓跟踪!$B$2:$B$157=A2)*(持仓跟踪!$X$2:$X$157="执行卖出")*(持仓跟踪!$H$2:$H$157<>"")),持仓跟踪!$H$2:$H$157),"")) -> 42578 | N2: 3.7 | P2: =IF(A2="","",IFERROR(LOOKUP(2,1/((持仓跟踪!$B$2:$B$157=A2)*(持仓跟踪!$X$2:$X$157="执行卖出")*(持仓跟踪!$AA$2:$AA$157<>"")),持仓跟踪!$AA$2:$AA$157),"")) | U2: =IF(OR(AO2="",J2="",AO2<=0),"",(J2-AO2)/AO2) -> 0.025641026 | V2: =IF(OR(AO2="",N2="",AO2<=0),"",(AO2-N2)/AO2) -> 0.051282051 | W2: =IF(OR(U2="",V2="",V2<=0),"",U2/V2) -> 0.5 | X2: =IF(OR(K2="",L2="",AP2=""),"",K2*L2-(E2*H2+IF(AND(AK2<>"",AL2<>""),AK2*AL2,0)+IF(AND(AM2<>"",AN2<>""),AM2*AN2,0))-IF(O2="",0,O2)-IF(P2="",0,P2)) -> -1100 | Y2: =IF(OR(X2="",AP2=""),"",IF((E2*H2+IF(AND(AK2<>"",AL2<>""),AK2*AL2,0)+IF(AND(AM2<>"",AN2<>""),AM2*AN2,0))+IF(O2="",0,O2)<=0,"",X2/((E2*H2+IF(AND(AK2<>"",AL2<>""),AK2*AL2,0)+IF(AND(AM2<>"",AN2<>""),AM2*AN2,0))+IF(O2="",0,O2)))) -> -0.056410256 | Z2: =IF(OR(AE2="",多次统计数据!$B$8=""),"",AE2-多次统计数据!$B$8) -> -0.083548627 | AA2: =IF(OR(I2="",M2="",M2<I2),"",M2-I2) -> 8 | AB2: =IF(OR(A2="",多次统计数据!$B$8="",多次统计数据!$B$6<=0,多次统计数据!$B$6>=1),"",1-POWER(1+多次统计数据!$B$8,-多次统计数据!$B$6/(1-多次统计数据!$B$6))) -> 0.053016657 | AC2: =IF(OR(AB2="",多次统计数据!$B$9=""),"",IF(多次统计数据!$B$9<AB2,"低于上限","达到或超过上限")) -> 低于上限 | AD2: 4-良好 | AE2: =IF(OR(X2="",C2="",C2<=0),"",X2/C2) -> -0.011 | AG2: 短期博反弹 | AH2: 4～10个交易日 | AI2: 不一定能冲到4块，但是最近交易量上来了 | AJ2: =IF(OR(AG2="",AH2=""),"",IF(OR(AND(AG2="短期博反弹",OR(AH2="1～3个交易日",AH2="4～10个交易日")),AND(AG2="突破冲新高",OR(AH2="4～10个交易日",AH2="11～20个交易日")),AND(AG2="趋势波段",OR(AH2="11～20个交易日",AH2="21～60个交易日",AH2="60个交易日以上"))),"匹配","周期与交易预期不匹配，请重新确认")) -> 匹配 | AO2: =IF(OR(A2="",H2="",H2<=0),"",(E2*H2+IF(AND(AK2<>"",AL2<>""),AK2*AL2,0)+IF(AND(AM2<>"",AN2<>""),AM2*AN2,0))/AP2) -> 3.9 | AP2: =IF(OR(A2="",H2="",H2<=0),"",H2+IF(AL2="",0,AL2)+IF(AN2="",0,AN2)) -> 5000 | AQ2: =IF(A2="","",IF(M2<>"",0,IF(OR(H2="",N2=""),"",MAX(E2-MAX(N2,IFERROR(SUMPRODUCT(MAX(((持仓跟踪!$A$2:$A$157="每日跟踪")*(持仓跟踪!$B$2:$B$157=A2))*持仓跟踪!$S$2:$S$157)),0)),0)*H2+IF(OR(AK2="",AL2=""),0,MAX(AK2-MAX(N2,IFERROR(SUMPRODUCT(MAX(((持仓跟踪!$A$2:$A$157="每日跟踪")*(持仓跟踪!$B$2:$B$157=A2))*持仓跟踪!$S$2:$S$157)),0)),0)*AL2)+IF(OR(AM2="",AN2=""),0,MAX(AM2-MAX(N2,IFERROR(SUMPRODUCT(MAX(((持仓跟踪!$A$2:$A$157="每日跟踪")*(持仓跟踪!$B$2:$B$157=A2))*持仓跟踪!$S$2:$S$157)),0)),0)*AN2)))) -> 0 | AR2: =IF(A2="","",IF(OR(E2="",H2=""),"违规：第一批价格或股数缺失",IF(OR(AND(AK2="",AL2<>""),AND(AK2<>"",AL2="")),"违规：第二批价格与股数须成对填写",IF(OR(AND(AM2="",AN2<>""),AND(AM2<>"",AN2="")),"违规：第三批价格与股数须成对填写",IF(AND(OR(AM2<>"",AN2<>""),OR(AK2="",AL2="")),"违规：必须先完成第二批",IF(OR(H2<=0,H2<>INT(H2),MOD(H2,100)<>0,AND(AL2<>"",OR(AL2<=0,AL2<>INT(AL2),MOD(AL2,100)<>0)),AND(AN2<>"",OR(AN2<=0,AN2<>INT(AN2),MOD(AN2,100)<>0))),"违规：股数须为100股整数倍",IF(AND(OR(AL2<>"",AN2<>""),OR(_LockStatus="已锁仓",_LockStatus="解锁信息不完整")),"违规：锁仓期间禁止加仓",IF(AQ2>C2*D2,"违规：超过单笔风险上限",IF(SUM($AQ$2:$AQ$98)>账户数据!$B$7,"违规：超过账户风险上限","通过"))))))))) -> 通过
A3: 2 | B3: 节电风能 | C3: 98900 | D3: 0.02 | E3: 3.7 | F3: =IF(OR(C3="",D3="",E3="",N3="",C3<=0,D3<=0,E3<=N3),"",ROUNDDOWN((C3*D3)/(E3-N3)/100,0)*100) -> 9800 | G3: =IF(A3="","",IF(H3<>"","已开仓",IF(账户数据!$B$23="已锁仓","禁止开仓：连续亏损达到上限",IF(账户数据!$B$23="解锁信息不完整","禁止开仓：请完整填写解锁信息",IF(OR(F3="",E3="",N3="",E3<=N3,账户数据!$B$7=""),"",IF(OR(AG3="",AH3="",AI3=""),"禁止开仓：交易预期未填写完整",IF(COUNTIFS(持仓跟踪!$A$2:$A$157,"止损计划",持仓跟踪!$B$2:$B$157,A3,持仓跟踪!$AC$2:$AC$157,"计划有效")=0,"禁止开仓：请先填写止损计划",IF(账户数据!$B$9+F3*(E3-N3)>=账户数据!$B$7,"禁止开仓：风险额度不足",IF(AJ3="周期与交易预期不匹配，请重新确认",IF(账户数据!$B$23="接近锁仓","允许开仓（接近锁仓；周期需复核）","允许开仓（周期需复核）"),IF(账户数据!$B$23="接近锁仓","允许开仓（接近锁仓）","允许开仓")))))))))) -> 已开仓 | H3: 9800 | I3: 42653 | J3: 4 | K3: 4.22 | L3: 9800 | M3: =IF(A3="","",IFERROR(LOOKUP(2,1/((持仓跟踪!$B$2:$B$157=A3)*(持仓跟踪!$X$2:$X$157="执行卖出")*(持仓跟踪!$H$2:$H$157<>"")),持仓跟踪!$H$2:$H$157),"")) -> 42663 | N3: 3.5 | P3: =IF(A3="","",IFERROR(LOOKUP(2,1/((持仓跟踪!$B$2:$B$157=A3)*(持仓跟踪!$X$2:$X$157="执行卖出")*(持仓跟踪!$AA$2:$AA$157<>"")),持仓跟踪!$AA$2:$AA$157),"")) | U3: =IF(OR(AO3="",J3="",AO3<=0),"",(J3-AO3)/AO3) -> 0.081081081 | V3: =IF(OR(AO3="",N3="",AO3<=0),"",(AO3-N3)/AO3) -> 0.054054054 | W3: =IF(OR(U3="",V3="",V3<=0),"",U3/V3) -> 1.5 | X3: =IF(OR(K3="",L3="",AP3=""),"",K3*L3-(E3*H3+IF(AND(AK3<>"",AL3<>""),AK3*AL3,0)+IF(AND(AM3<>"",AN3<>""),AM3*AN3,0))-IF(O3="",0,O3)-IF(P3="",0,P3)) -> 5096 | Y3: =IF(OR(X3="",AP3=""),"",IF((E3*H3+IF(AND(AK3<>"",AL3<>""),AK3*AL3,0)+IF(AND(AM3<>"",AN3<>""),AM3*AN3,0))+IF(O3="",0,O3)<=0,"",X3/((E3*H3+IF(AND(AK3<>"",AL3<>""),AK3*AL3,0)+IF(AND(AM3<>"",AN3<>""),AM3*AN3,0))+IF(O3="",0,O3)))) -> 0.14054054 | Z3: =IF(OR(AE3="",多次统计数据!$B$8=""),"",AE3-多次统计数据!$B$8) -> -0.021021832 | AA3: =IF(OR(I3="",M3="",M3<I3),"",M3-I3) -> 10 | AB3: =IF(OR(A3="",多次统计数据!$B$8="",多次统计数据!$B$6<=0,多次统计数据!$B$6>=1),"",1-POWER(1+多次统计数据!$B$8,-多次统计数据!$B$6/(1-多次统计数据!$B$6))) -> 0.053016657 | AC3: =IF(OR(AB3="",多次统计数据!$B$9=""),"",IF(多次统计数据!$B$9<AB3,"低于上限","达到或超过上限")) -> 低于上限 | AD3: 4-良好 | AE3: =IF(OR(X3="",C3="",C3<=0),"",X3/C3) -> 0.051526795 | AG3: 短期博反弹 | AH3: 4～10个交易日 | AI3: 4块压力很大 | AJ3: =IF(OR(AG3="",AH3=""),"",IF(OR(AND(AG3="短期博反弹",OR(AH3="1～3个交易日",AH3="4～10个交易日")),AND(AG3="突破冲新高",OR(AH3="4～10个交易日",AH3="11～20个交易日")),AND(AG3="趋势波段",OR(AH3="11～20个交易日",AH3="21～60个交易日",AH3="60个交易日以上"))),"匹配","周期与交易预期不匹配，请重新确认")) -> 匹配 | AO3: =IF(OR(A3="",H3="",H3<=0),"",(E3*H3+IF(AND(AK3<>"",AL3<>""),AK3*AL3,0)+IF(AND(AM3<>"",AN3<>""),AM3*AN3,0))/AP3) -> 3.7 | AP3: =IF(OR(A3="",H3="",H3<=0),"",H3+IF(AL3="",0,AL3)+IF(AN3="",0,AN3)) -> 9800 | AQ3: =IF(A3="","",IF(M3<>"",0,IF(OR(H3="",N3=""),"",MAX(E3-MAX(N3,IFERROR(SUMPRODUCT(MAX(((持仓跟踪!$A$2:$A$157="每日跟踪")*(持仓跟踪!$B$2:$B$157=A3))*持仓跟踪!$S$2:$S$157)),0)),0)*H3+IF(OR(AK3="",AL3=""),0,MAX(AK3-MAX(N3,IFERROR(SUMPRODUCT(MAX(((持仓跟踪!$A$2:$A$157="每日跟踪")*(持仓跟踪!$B$2:$B$157=A3))*持仓跟踪!$S$2:$S$157)),0)),0)*AL3)+IF(OR(AM3="",AN3=""),0,MAX(AM3-MAX(N3,IFERROR(SUMPRODUCT(MAX(((持仓跟踪!$A$2:$A$157="每日跟踪")*(持仓跟踪!$B$2:$B$157=A3))*持仓跟踪!$S$2:$S$157)),0)),0)*AN3)))) -> 0 | AR3: =IF(A3="","",IF(OR(E3="",H3=""),"违规：第一批价格或股数缺失",IF(OR(AND(AK3="",AL3<>""),AND(AK3<>"",AL3="")),"违规：第二批价格与股数须成对填写",IF(OR(AND(AM3="",AN3<>""),AND(AM3<>"",AN3="")),"违规：第三批价格与股数须成对填写",IF(AND(OR(AM3<>"",AN3<>""),OR(AK3="",AL3="")),"违规：必须先完成第二批",IF(OR(H3<=0,H3<>INT(H3),MOD(H3,100)<>0,AND(AL3<>"",OR(AL3<=0,AL3<>INT(AL3),MOD(AL3,100)<>0)),AND(AN3<>"",OR(AN3<=0,AN3<>INT(AN3),MOD(AN3,100)<>0))),"违规：股数须为100股整数倍",IF(AND(OR(AL3<>"",AN3<>""),OR(_LockStatus="已锁仓",_LockStatus="解锁信息不完整")),"违规：锁仓期间禁止加仓",IF(AQ3>C3*D3,"违规：超过单笔风险上限",IF(SUM($AQ$2:$AQ$98)>账户数据!$B$7,"违规：超过账户风险上限","通过"))))))))) -> 通过
A4: 3 | B4: 节电风能 | C4: 103996 | D4: 0.02 | E4: 3.93 | F4: =IF(OR(C4="",D4="",E4="",N4="",C4<=0,D4<=0,E4<=N4),"",ROUNDDOWN((C4*D4)/(E4-N4)/100,0)*100) -> 9000 | G4: =IF(A4="","",IF(H4<>"","已开仓",IF(账户数据!$B$23="已锁仓","禁止开仓：连续亏损达到上限",IF(账户数据!$B$23="解锁信息不完整","禁止开仓：请完整填写解锁信息",IF(OR(F4="",E4="",N4="",E4<=N4,账户数据!$B$7=""),"",IF(OR(AG4="",AH4="",AI4=""),"禁止开仓：交易预期未填写完整",IF(COUNTIFS(持仓跟踪!$A$2:$A$157,"止损计划",持仓跟踪!$B$2:$B$157,A4,持仓跟踪!$AC$2:$AC$157,"计划有效")=0,"禁止开仓：请先填写止损计划",IF(账户数据!$B$9+F4*(E4-N4)>=账户数据!$B$7,"禁止开仓：风险额度不足",IF(AJ4="周期与交易预期不匹配，请重新确认",IF(账户数据!$B$23="接近锁仓","允许开仓（接近锁仓；周期需复核）","允许开仓（周期需复核）"),IF(账户数据!$B$23="接近锁仓","允许开仓（接近锁仓）","允许开仓")))))))))) -> 已开仓 | H4: 9000 | I4: 42684 | J4: 4.5 | K4: =IF(A4="","",IFERROR(LOOKUP(2,1/((持仓跟踪!$B$2:$B$157=A4)*(持仓跟踪!$X$2:$X$157="执行卖出")*(持仓跟踪!$Y$2:$Y$157<>"")),持仓跟踪!$Y$2:$Y$157),"")) -> 3.69 | L4: =IF(A4="","",IFERROR(LOOKUP(2,1/((持仓跟踪!$B$2:$B$157=A4)*(持仓跟踪!$X$2:$X$157="执行卖出")*(持仓跟踪!$Z$2:$Z$157<>"")),持仓跟踪!$Z$2:$Z$157),"")) -> 9000 | M4: =IF(A4="","",IFERROR(LOOKUP(2,1/((持仓跟踪!$B$2:$B$157=A4)*(持仓跟踪!$X$2:$X$157="执行卖出")*(持仓跟踪!$H$2:$H$157<>"")),持仓跟踪!$H$2:$H$157),"")) -> 42716 | N4: 3.7 | P4: =IF(A4="","",IFERROR(LOOKUP(2,1/((持仓跟踪!$B$2:$B$157=A4)*(持仓跟踪!$X$2:$X$157="执行卖出")*(持仓跟踪!$AA$2:$AA$157<>"")),持仓跟踪!$AA$2:$AA$157),"")) | U4: =IF(OR(AO4="",J4="",AO4<=0),"",(J4-AO4)/AO4) -> 0.14503817 | V4: =IF(OR(AO4="",N4="",AO4<=0),"",(AO4-N4)/AO4) -> 0.058524173 | W4: =IF(OR(U4="",V4="",V4<=0),"",U4/V4) -> 2.4782609 | X4: =IF(OR(K4="",L4="",AP4=""),"",K4*L4-(E4*H4+IF(AND(AK4<>"",AL4<>""),AK4*AL4,0)+IF(AND(AM4<>"",AN4<>""),AM4*AN4,0))-IF(O4="",0,O4)-IF(P4="",0,P4)) -> -2160 | Y4: =IF(OR(X4="",AP4=""),"",IF((E4*H4+IF(AND(AK4<>"",AL4<>""),AK4*AL4,0)+IF(AND(AM4<>"",AN4<>""),AM4*AN4,0))+IF(O4="",0,O4)<=0,"",X4/((E4*H4+IF(AND(AK4<>"",AL4<>""),AK4*AL4,0)+IF(AND(AM4<>"",AN4<>""),AM4*AN4,0))+IF(O4="",0,O4)))) -> -0.061068702 | Z4: =IF(OR(AE4="",多次统计数据!$B$8=""),"",AE4-多次统计数据!$B$8) -> -0.093318657 | AA4: =IF(OR(I4="",M4="",M4<I4),"",M4-I4) -> 32 | AB4: =IF(OR(A4="",多次统计数据!$B$8="",多次统计数据!$B$6<=0,多次统计数据!$B$6>=1),"",1-POWER(1+多次统计数据!$B$8,-多次统计数据!$B$6/(1-多次统计数据!$B$6))) -> 0.053016657 | AC4: =IF(OR(AB4="",多次统计数据!$B$9=""),"",IF(多次统计数据!$B$9<AB4,"低于上限","达到或超过上限")) -> 低于上限 | AD4: 4-良好 | AE4: =IF(OR(X4="",C4="",C4<=0),"",X4/C4) -> -0.02077003 | AG4: 短期博反弹 | AH4: 4～10个交易日 | AI4: 4块压力很大 | AJ4: =IF(OR(AG4="",AH4=""),"",IF(OR(AND(AG4="短期博反弹",OR(AH4="1～3个交易日",AH4="4～10个交易日")),AND(AG4="突破冲新高",OR(AH4="4～10个交易日",AH4="11～20个交易日")),AND(AG4="趋势波段",OR(AH4="11～20个交易日",AH4="21～60个交易日",AH4="60个交易日以上"))),"匹配","周期与交易预期不匹配，请重新确认")) -> 匹配 | AO4: =IF(OR(A4="",H4="",H4<=0),"",(E4*H4+IF(AND(AK4<>"",AL4<>""),AK4*AL4,0)+IF(AND(AM4<>"",AN4<>""),AM4*AN4,0))/AP4) -> 3.93 | AP4: =IF(OR(A4="",H4="",H4<=0),"",H4+IF(AL4="",0,AL4)+IF(AN4="",0,AN4)) -> 9000 | AQ4: =IF(A4="","",IF(M4<>"",0,IF(OR(H4="",N4=""),"",MAX(E4-MAX(N4,IFERROR(SUMPRODUCT(MAX(((持仓跟踪!$A$2:$A$157="每日跟踪")*(持仓跟踪!$B$2:$B$157=A4))*持仓跟踪!$S$2:$S$157)),0)),0)*H4+IF(OR(AK4="",AL4=""),0,MAX(AK4-MAX(N4,IFERROR(SUMPRODUCT(MAX(((持仓跟踪!$A$2:$A$157="每日跟踪")*(持仓跟踪!$B$2:$B$157=A4))*持仓跟踪!$S$2:$S$157)),0)),0)*AL4)+IF(OR(AM4="",AN4=""),0,MAX(AM4-MAX(N4,IFERROR(SUMPRODUCT(MAX(((持仓跟踪!$A$2:$A$157="每日跟踪")*(持仓跟踪!$B$2:$B$157=A4))*持仓跟踪!$S$2:$S$157)),0)),0)*AN4)))) -> 0 | AR4: =IF(A4="","",IF(OR(E4="",H4=""),"违规：第一批价格或股数缺失",IF(OR(AND(AK4="",AL4<>""),AND(AK4<>"",AL4="")),"违规：第二批价格与股数须成对填写",IF(OR(AND(AM4="",AN4<>""),AND(AM4<>"",AN4="")),"违规：第三批价格与股数须成对填写",IF(AND(OR(AM4<>"",AN4<>""),OR(AK4="",AL4="")),"违规：必须先完成第二批",IF(OR(H4<=0,H4<>INT(H4),MOD(H4,100)<>0,AND(AL4<>"",OR(AL4<=0,AL4<>INT(AL4),MOD(AL4,100)<>0)),AND(AN4<>"",OR(AN4<=0,AN4<>INT(AN4),MOD(AN4,100)<>0))),"违规：股数须为100股整数倍",IF(AND(OR(AL4<>"",AN4<>""),OR(_LockStatus="已锁仓",_LockStatus="解锁信息不完整")),"违规：锁仓期间禁止加仓",IF(AQ4>C4*D4,"违规：超过单笔风险上限",IF(SUM($AQ$2:$AQ$98)>账户数据!$B$7,"违规：超过账户风险上限","通过"))))))))) -> 通过
A5: 4 | B5: 节电风能 | C5: 101836 | D5: 0.02 | E5: 3.4 | F5: =IF(OR(C5="",D5="",E5="",N5="",C5<=0,D5<=0,E5<=N5),"",ROUNDDOWN((C5*D5)/(E5-N5)/100,0)*100) -> 10100 | G5: =IF(A5="","",IF(H5<>"","已开仓",IF(账户数据!$B$23="已锁仓","禁止开仓：连续亏损达到上限",IF(账户数据!$B$23="解锁信息不完整","禁止开仓：请完整填写解锁信息",IF(OR(F5="",E5="",N5="",E5<=N5,账户数据!$B$7=""),"",IF(OR(AG5="",AH5="",AI5=""),"禁止开仓：交易预期未填写完整",IF(COUNTIFS(持仓跟踪!$A$2:$A$157,"止损计划",持仓跟踪!$B$2:$B$157,A5,持仓跟踪!$AC$2:$AC$157,"计划有效")=0,"禁止开仓：请先填写止损计划",IF(账户数据!$B$9+F5*(E5-N5)>=账户数据!$B$7,"禁止开仓：风险额度不足",IF(AJ5="周期与交易预期不匹配，请重新确认",IF(账户数据!$B$23="接近锁仓","允许开仓（接近锁仓；周期需复核）","允许开仓（周期需复核）"),IF(账户数据!$B$23="接近锁仓","允许开仓（接近锁仓）","允许开仓")))))))))) -> 已开仓 | H5: 10100 | I5: 42825 | J5: 3.7 | K5: 3.49 | L5: =IF(A5="","",IFERROR(LOOKUP(2,1/((持仓跟踪!$B$2:$B$157=A5)*(持仓跟踪!$X$2:$X$157="执行卖出")*(持仓跟踪!$Z$2:$Z$157<>"")),持仓跟踪!$Z$2:$Z$157),"")) -> 10100 | M5: =IF(A5="","",IFERROR(LOOKUP(2,1/((持仓跟踪!$B$2:$B$157=A5)*(持仓跟踪!$X$2:$X$157="执行卖出")*(持仓跟踪!$H$2:$H$157<>"")),持仓跟踪!$H$2:$H$157),"")) -> 42838 | N5: 3.2 | P5: =IF(A5="","",IFERROR(LOOKUP(2,1/((持仓跟踪!$B$2:$B$157=A5)*(持仓跟踪!$X$2:$X$157="执行卖出")*(持仓跟踪!$AA$2:$AA$157<>"")),持仓跟踪!$AA$2:$AA$157),"")) | U5: =IF(OR(AO5="",J5="",AO5<=0),"",(J5-AO5)/AO5) -> 0.088235294 | V5: =IF(OR(AO5="",N5="",AO5<=0),"",(AO5-N5)/AO5) -> 0.058823529 | W5: =IF(OR(U5="",V5="",V5<=0),"",U5/V5) -> 1.5 | X5: =IF(OR(K5="",L5="",AP5=""),"",K5*L5-(E5*H5+IF(AND(AK5<>"",AL5<>""),AK5*AL5,0)+IF(AND(AM5<>"",AN5<>""),AM5*AN5,0))-IF(O5="",0,O5)-IF(P5="",0,P5)) -> 909 | Y5: =IF(OR(X5="",AP5=""),"",IF((E5*H5+IF(AND(AK5<>"",AL5<>""),AK5*AL5,0)+IF(AND(AM5<>"",AN5<>""),AM5*AN5,0))+IF(O5="",0,O5)<=0,"",X5/((E5*H5+IF(AND(AK5<>"",AL5<>""),AK5*AL5,0)+IF(AND(AM5<>"",AN5<>""),AM5*AN5,0))+IF(O5="",0,O5)))) -> 0.026470588 | Z5: =IF(OR(AE5="",多次统计数据!$B$8=""),"",AE5-多次统计数据!$B$8) -> -0.06362251 | AA5: =IF(OR(I5="",M5="",M5<I5),"",M5-I5) -> 13 | AB5: =IF(OR(A5="",多次统计数据!$B$8="",多次统计数据!$B$6<=0,多次统计数据!$B$6>=1),"",1-POWER(1+多次统计数据!$B$8,-多次统计数据!$B$6/(1-多次统计数据!$B$6))) -> 0.053016657 | AC5: =IF(OR(AB5="",多次统计数据!$B$9=""),"",IF(多次统计数据!$B$9<AB5,"低于上限","达到或超过上限")) -> 低于上限 | AD5: 3-一般 | AE5: =IF(OR(X5="",C5="",C5<=0),"",X5/C5) -> 0.0089261165 | AG5: 短期博反弹 | AH5: 4～10个交易日 | AI5: 4块压力很大 | AJ5: =IF(OR(AG5="",AH5=""),"",IF(OR(AND(AG5="短期博反弹",OR(AH5="1～3个交易日",AH5="4～10个交易日")),AND(AG5="突破冲新高",OR(AH5="4～10个交易日",AH5="11～20个交易日")),AND(AG5="趋势波段",OR(AH5="11～20个交易日",AH5="21～60个交易日",AH5="60个交易日以上"))),"匹配","周期与交易预期不匹配，请重新确认")) -> 匹配 | AO5: =IF(OR(A5="",H5="",H5<=0),"",(E5*H5+IF(AND(AK5<>"",AL5<>""),AK5*AL5,0)+IF(AND(AM5<>"",AN5<>""),AM5*AN5,0))/AP5) -> 3.4 | AP5: =IF(OR(A5="",H5="",H5<=0),"",H5+IF(AL5="",0,AL5)+IF(AN5="",0,AN5)) -> 10100 | AQ5: =IF(A5="","",IF(M5<>"",0,IF(OR(H5="",N5=""),"",MAX(E5-MAX(N5,IFERROR(SUMPRODUCT(MAX(((持仓跟踪!$A$2:$A$157="每日跟踪")*(持仓跟踪!$B$2:$B$157=A5))*持仓跟踪!$S$2:$S$157)),0)),0)*H5+IF(OR(AK5="",AL5=""),0,MAX(AK5-MAX(N5,IFERROR(SUMPRODUCT(MAX(((持仓跟踪!$A$2:$A$157="每日跟踪")*(持仓跟踪!$B$2:$B$157=A5))*持仓跟踪!$S$2:$S$157)),0)),0)*AL5)+IF(OR(AM5="",AN5=""),0,MAX(AM5-MAX(N5,IFERROR(SUMPRODUCT(MAX(((持仓跟踪!$A$2:$A$157="每日跟踪")*(持仓跟踪!$B$2:$B$157=A5))*持仓跟踪!$S$2:$S$157)),0)),0)*AN5)))) -> 0 | AR5: =IF(A5="","",IF(OR(E5="",H5=""),"违规：第一批价格或股数缺失",IF(OR(AND(AK5="",AL5<>""),AND(AK5<>"",AL5="")),"违规：第二批价格与股数须成对填写",IF(OR(AND(AM5="",AN5<>""),AND(AM5<>"",AN5="")),"违规：第三批价格与股数须成对填写",IF(AND(OR(AM5<>"",AN5<>""),OR(AK5="",AL5="")),"违规：必须先完成第二批",IF(OR(H5<=0,H5<>INT(H5),MOD(H5,100)<>0,AND(AL5<>"",OR(AL5<=0,AL5<>INT(AL5),MOD(AL5,100)<>0)),AND(AN5<>"",OR(AN5<=0,AN5<>INT(AN5),MOD(AN5,100)<>0))),"违规：股数须为100股整数倍",IF(AND(OR(AL5<>"",AN5<>""),OR(_LockStatus="已锁仓",_LockStatus="解锁信息不完整")),"违规：锁仓期间禁止加仓",IF(AQ5>C5*D5,"违规：超过单笔风险上限",IF(SUM($AQ$2:$AQ$98)>账户数据!$B$7,"违规：超过账户风险上限","通过"))))))))) -> 通过
A6: 5 | B6: 节电风能 | C6: 102745 | D6: 0.02 | E6: 2.87 | F6: =IF(OR(C6="",D6="",E6="",N6="",C6<=0,D6<=0,E6<=N6),"",ROUNDDOWN((C6*D6)/(E6-N6)/100,0)*100) -> 17100 | G6: =IF(A6="","",IF(H6<>"","已开仓",IF(账户数据!$B$23="已锁仓","禁止开仓：连续亏损达到上限",IF(账户数据!$B$23="解锁信息不完整","禁止开仓：请完整填写解锁信息",IF(OR(F6="",E6="",N6="",E6<=N6,账户数据!$B$7=""),"",IF(OR(AG6="",AH6="",AI6=""),"禁止开仓：交易预期未填写完整",IF(COUNTIFS(持仓跟踪!$A$2:$A$157,"止损计划",持仓跟踪!$B$2:$B$157,A6,持仓跟踪!$AC$2:$AC$157,"计划有效")=0,"禁止开仓：请先填写止损计划",IF(账户数据!$B$9+F6*(E6-N6)>=账户数据!$B$7,"禁止开仓：风险额度不足",IF(AJ6="周期与交易预期不匹配，请重新确认",IF(账户数据!$B$23="接近锁仓","允许开仓（接近锁仓；周期需复核）","允许开仓（周期需复核）"),IF(账户数据!$B$23="接近锁仓","允许开仓（接近锁仓）","允许开仓")))))))))) -> 已开仓 | H6: 17100 | I6: 43060 | J6: 3.2 | K6: 2.74 | L6: 17100 | M6: =IF(A6="","",IFERROR(LOOKUP(2,1/((持仓跟踪!$B$2:$B$157=A6)*(持仓跟踪!$X$2:$X$157="执行卖出")*(持仓跟踪!$H$2:$H$157<>"")),持仓跟踪!$H$2:$H$157),"")) -> 43074 | N6: 2.75 | P6: =IF(A6="","",IFERROR(LOOKUP(2,1/((持仓跟踪!$B$2:$B$157=A6)*(持仓跟踪!$X$2:$X$157="执行卖出")*(持仓跟踪!$AA$2:$AA$157<>"")),持仓跟踪!$AA$2:$AA$157),"")) | U6: =IF(OR(AO6="",J6="",AO6<=0),"",(J6-AO6)/AO6) -> 0.11498258 | V6: =IF(OR(AO6="",N6="",AO6<=0),"",(AO6-N6)/AO6) -> 0.041811847 | W6: =IF(OR(U6="",V6="",V6<=0),"",U6/V6) -> 2.75 | X6: =IF(OR(K6="",L6="",AP6=""),"",K6*L6-(E6*H6+IF(AND(AK6<>"",AL6<>""),AK6*AL6,0)+IF(AND(AM6<>"",AN6<>""),AM6*AN6,0))-IF(O6="",0,O6)-IF(P6="",0,P6)) -> -2223 | Y6: =IF(OR(X6="",AP6=""),"",IF((E6*H6+IF(AND(AK6<>"",AL6<>""),AK6*AL6,0)+IF(AND(AM6<>"",AN6<>""),AM6*AN6,0))+IF(O6="",0,O6)<=0,"",X6/((E6*H6+IF(AND(AK6<>"",AL6<>""),AK6*AL6,0)+IF(AND(AM6<>"",AN6<>""),AM6*AN6,0))+IF(O6="",0,O6)))) -> -0.045296167 | Z6: =IF(OR(AE6="",多次统计数据!$B$8=""),"",AE6-多次统计数据!$B$8) -> -0.094184716 | AA6: =IF(OR(I6="",M6="",M6<I6),"",M6-I6) -> 14 | AB6: =IF(OR(A6="",多次统计数据!$B$8="",多次统计数据!$B$6<=0,多次统计数据!$B$6>=1),"",1-POWER(1+多次统计数据!$B$8,-多次统计数据!$B$6/(1-多次统计数据!$B$6))) -> 0.053016657 | AC6: =IF(OR(AB6="",多次统计数据!$B$9=""),"",IF(多次统计数据!$B$9<AB6,"低于上限","达到或超过上限")) -> 低于上限 | AD6: 3-一般 | AE6: =IF(OR(X6="",C6="",C6<=0),"",X6/C6) -> -0.021636089 | AG6: 短期博反弹 | AH6: 4～10个交易日 | AI6: 3.3有压力，甚至3都有压力 | AJ6: =IF(OR(AG6="",AH6=""),"",IF(OR(AND(AG6="短期博反弹",OR(AH6="1～3个交易日",AH6="4～10个交易日")),AND(AG6="突破冲新高",OR(AH6="4～10个交易日",AH6="11～20个交易日")),AND(AG6="趋势波段",OR(AH6="11～20个交易日",AH6="21～60个交易日",AH6="60个交易日以上"))),"匹配","周期与交易预期不匹配，请重新确认")) -> 匹配 | AO6: =IF(OR(A6="",H6="",H6<=0),"",(E6*H6+IF(AND(AK6<>"",AL6<>""),AK6*AL6,0)+IF(AND(AM6<>"",AN6<>""),AM6*AN6,0))/AP6) -> 2.87 | AP6: =IF(OR(A6="",H6="",H6<=0),"",H6+IF(AL6="",0,AL6)+IF(AN6="",0,AN6)) -> 17100 | AQ6: =IF(A6="","",IF(M6<>"",0,IF(OR(H6="",N6=""),"",MAX(E6-MAX(N6,IFERROR(SUMPRODUCT(MAX(((持仓跟踪!$A$2:$A$157="每日跟踪")*(持仓跟踪!$B$2:$B$157=A6))*持仓跟踪!$S$2:$S$157)),0)),0)*H6+IF(OR(AK6="",AL6=""),0,MAX(AK6-MAX(N6,IFERROR(SUMPRODUCT(MAX(((持仓跟踪!$A$2:$A$157="每日跟踪")*(持仓跟踪!$B$2:$B$157=A6))*持仓跟踪!$S$2:$S$157)),0)),0)*AL6)+IF(OR(AM6="",AN6=""),0,MAX(AM6-MAX(N6,IFERROR(SUMPRODUCT(MAX(((持仓跟踪!$A$2:$A$157="每日跟踪")*(持仓跟踪!$B$2:$B$157=A6))*持仓跟踪!$S$2:$S$157)),0)),0)*AN6)))) -> 0 | AR6: =IF(A6="","",IF(OR(E6="",H6=""),"违规：第一批价格或股数缺失",IF(OR(AND(AK6="",AL6<>""),AND(AK6<>"",AL6="")),"违规：第二批价格与股数须成对填写",IF(OR(AND(AM6="",AN6<>""),AND(AM6<>"",AN6="")),"违规：第三批价格与股数须成对填写",IF(AND(OR(AM6<>"",AN6<>""),OR(AK6="",AL6="")),"违规：必须先完成第二批",IF(OR(H6<=0,H6<>INT(H6),MOD(H6,100)<>0,AND(AL6<>"",OR(AL6<=0,AL6<>INT(AL6),MOD(AL6,100)<>0)),AND(AN6<>"",OR(AN6<=0,AN6<>INT(AN6),MOD(AN6,100)<>0))),"违规：股数须为100股整数倍",IF(AND(OR(AL6<>"",AN6<>""),OR(_LockStatus="已锁仓",_LockStatus="解锁信息不完整")),"违规：锁仓期间禁止加仓",IF(AQ6>C6*D6,"违规：超过单笔风险上限",IF(SUM($AQ$2:$AQ$98)>账户数据!$B$7,"违规：超过账户风险上限","通过"))))))))) -> 通过
A7: 6 | B7: 节电风能 | C7: 100522 | D7: 0.02 | E7: 2.57 | F7: =IF(OR(C7="",D7="",E7="",N7="",C7<=0,D7<=0,E7<=N7),"",ROUNDDOWN((C7*D7)/(E7-N7)/100,0)*100) -> 11800 | G7: =IF(A7="","",IF(H7<>"","已开仓",IF(账户数据!$B$23="已锁仓","禁止开仓：连续亏损达到上限",IF(账户数据!$B$23="解锁信息不完整","禁止开仓：请完整填写解锁信息",IF(OR(F7="",E7="",N7="",E7<=N7,账户数据!$B$7=""),"",IF(OR(AG7="",AH7="",AI7=""),"禁止开仓：交易预期未填写完整",IF(COUNTIFS(持仓跟踪!$A$2:$A$157,"止损计划",持仓跟踪!$B$2:$B$157,A7,持仓跟踪!$AC$2:$AC$157,"计划有效")=0,"禁止开仓：请先填写止损计划",IF(账户数据!$B$9+F7*(E7-N7)>=账户数据!$B$7,"禁止开仓：风险额度不足",IF(AJ7="周期与交易预期不匹配，请重新确认",IF(账户数据!$B$23="接近锁仓","允许开仓（接近锁仓；周期需复核）","允许开仓（周期需复核）"),IF(账户数据!$B$23="接近锁仓","允许开仓（接近锁仓）","允许开仓")))))))))) -> 已开仓 | H7: 11800 | I7: 43173 | J7: 3 | K7: =IF(A7="","",IFERROR(LOOKUP(2,1/((持仓跟踪!$B$2:$B$157=A7)*(持仓跟踪!$X$2:$X$157="执行卖出")*(持仓跟踪!$Y$2:$Y$157<>"")),持仓跟踪!$Y$2:$Y$157),"")) -> 2.38 | L7: =IF(A7="","",IFERROR(LOOKUP(2,1/((持仓跟踪!$B$2:$B$157=A7)*(持仓跟踪!$X$2:$X$157="执行卖出")*(持仓跟踪!$Z$2:$Z$157<>"")),持仓跟踪!$Z$2:$Z$157),"")) -> 11800 | M7: =IF(A7="","",IFERROR(LOOKUP(2,1/((持仓跟踪!$B$2:$B$157=A7)*(持仓跟踪!$X$2:$X$157="执行卖出")*(持仓跟踪!$H$2:$H$157<>"")),持仓跟踪!$H$2:$H$157),"")) -> 43182 | N7: 2.4 | P7: =IF(A7="","",IFERROR(LOOKUP(2,1/((持仓跟踪!$B$2:$B$157=A7)*(持仓跟踪!$X$2:$X$157="执行卖出")*(持仓跟踪!$AA$2:$AA$157<>"")),持仓跟踪!$AA$2:$AA$157),"")) | U7: =IF(OR(AO7="",J7="",AO7<=0),"",(J7-AO7)/AO7) -> 0.16731518 | V7: =IF(OR(AO7="",N7="",AO7<=0),"",(AO7-N7)/AO7) -> 0.06614786 | W7: =IF(OR(U7="",V7="",V7<=0),"",U7/V7) -> 2.5294118 | X7: =IF(OR(K7="",L7="",AP7=""),"",K7*L7-(E7*H7+IF(AND(AK7<>"",AL7<>""),AK7*AL7,0)+IF(AND(AM7<>"",AN7<>""),AM7*AN7,0))-IF(O7="",0,O7)-IF(P7="",0,P7)) -> -2242 | Y7: =IF(OR(X7="",AP7=""),"",IF((E7*H7+IF(AND(AK7<>"",AL7<>""),AK7*AL7,0)+IF(AND(AM7<>"",AN7<>""),AM7*AN7,0))+IF(O7="",0,O7)<=0,"",X7/((E7*H7+IF(AND(AK7<>"",AL7<>""),AK7*AL7,0)+IF(AND(AM7<>"",AN7<>""),AM7*AN7,0))+IF(O7="",0,O7)))) -> -0.073929961 | Z7: =IF(OR(AE7="",多次统计数据!$B$8=""),"",AE7-多次统计数据!$B$8) -> -0.094852202 | AA7: =IF(OR(I7="",M7="",M7<I7),"",M7-I7) -> 9 | AB7: =IF(OR(A7="",多次统计数据!$B$8="",多次统计数据!$B$6<=0,多次统计数据!$B$6>=1),"",1-POWER(1+多次统计数据!$B$8,-多次统计数据!$B$6/(1-多次统计数据!$B$6))) -> 0.053016657 | AC7: =IF(OR(AB7="",多次统计数据!$B$9=""),"",IF(多次统计数据!$B$9<AB7,"低于上限","达到或超过上限")) -> 低于上限 | AD7: 3-一般 | AE7: =IF(OR(X7="",C7="",C7<=0),"",X7/C7) -> -0.022303575 | AG7: 短期博反弹 | AH7: 4～10个交易日 | AI7: 3块有压力 | AJ7: =IF(OR(AG7="",AH7=""),"",IF(OR(AND(AG7="短期博反弹",OR(AH7="1～3个交易日",AH7="4～10个交易日")),AND(AG7="突破冲新高",OR(AH7="4～10个交易日",AH7="11～20个交易日")),AND(AG7="趋势波段",OR(AH7="11～20个交易日",AH7="21～60个交易日",AH7="60个交易日以上"))),"匹配","周期与交易预期不匹配，请重新确认")) -> 匹配 | AO7: =IF(OR(A7="",H7="",H7<=0),"",(E7*H7+IF(AND(AK7<>"",AL7<>""),AK7*AL7,0)+IF(AND(AM7<>"",AN7<>""),AM7*AN7,0))/AP7) -> 2.57 | AP7: =IF(OR(A7="",H7="",H7<=0),"",H7+IF(AL7="",0,AL7)+IF(AN7="",0,AN7)) -> 11800 | AQ7: =IF(A7="","",IF(M7<>"",0,IF(OR(H7="",N7=""),"",MAX(E7-MAX(N7,IFERROR(SUMPRODUCT(MAX(((持仓跟踪!$A$2:$A$157="每日跟踪")*(持仓跟踪!$B$2:$B$157=A7))*持仓跟踪!$S$2:$S$157)),0)),0)*H7+IF(OR(AK7="",AL7=""),0,MAX(AK7-MAX(N7,IFERROR(SUMPRODUCT(MAX(((持仓跟踪!$A$2:$A$157="每日跟踪")*(持仓跟踪!$B$2:$B$157=A7))*持仓跟踪!$S$2:$S$157)),0)),0)*AL7)+IF(OR(AM7="",AN7=""),0,MAX(AM7-MAX(N7,IFERROR(SUMPRODUCT(MAX(((持仓跟踪!$A$2:$A$157="每日跟踪")*(持仓跟踪!$B$2:$B$157=A7))*持仓跟踪!$S$2:$S$157)),0)),0)*AN7)))) -> 0 | AR7: =IF(A7="","",IF(OR(E7="",H7=""),"违规：第一批价格或股数缺失",IF(OR(AND(AK7="",AL7<>""),AND(AK7<>"",AL7="")),"违规：第二批价格与股数须成对填写",IF(OR(AND(AM7="",AN7<>""),AND(AM7<>"",AN7="")),"违规：第三批价格与股数须成对填写",IF(AND(OR(AM7<>"",AN7<>""),OR(AK7="",AL7="")),"违规：必须先完成第二批",IF(OR(H7<=0,H7<>INT(H7),MOD(H7,100)<>0,AND(AL7<>"",OR(AL7<=0,AL7<>INT(AL7),MOD(AL7,100)<>0)),AND(AN7<>"",OR(AN7<=0,AN7<>INT(AN7),MOD(AN7,100)<>0))),"违规：股数须为100股整数倍",IF(AND(OR(AL7<>"",AN7<>""),OR(_LockStatus="已锁仓",_LockStatus="解锁信息不完整")),"违规：锁仓期间禁止加仓",IF(AQ7>C7*D7,"违规：超过单笔风险上限",IF(SUM($AQ$2:$AQ$98)>账户数据!$B$7,"违规：超过账户风险上限","通过"))))))))) -> 通过
A8: 7 | B8: 节电风能 | C8: 98280 | D8: 0.02 | E8: 1.91 | F8: =IF(OR(C8="",D8="",E8="",N8="",C8<=0,D8<=0,E8<=N8),"",ROUNDDOWN((C8*D8)/(E8-N8)/100,0)*100) -> 32700 | G8: =IF(A8="","",IF(H8<>"","已开仓",IF(账户数据!$B$23="已锁仓","禁止开仓：连续亏损达到上限",IF(账户数据!$B$23="解锁信息不完整","禁止开仓：请完整填写解锁信息",IF(OR(F8="",E8="",N8="",E8<=N8,账户数据!$B$7=""),"",IF(OR(AG8="",AH8="",AI8=""),"禁止开仓：交易预期未填写完整",IF(COUNTIFS(持仓跟踪!$A$2:$A$157,"止损计划",持仓跟踪!$B$2:$B$157,A8,持仓跟踪!$AC$2:$AC$157,"计划有效")=0,"禁止开仓：请先填写止损计划",IF(账户数据!$B$9+F8*(E8-N8)>=账户数据!$B$7,"禁止开仓：风险额度不足",IF(AJ8="周期与交易预期不匹配，请重新确认",IF(账户数据!$B$23="接近锁仓","允许开仓（接近锁仓；周期需复核）","允许开仓（周期需复核）"),IF(账户数据!$B$23="接近锁仓","允许开仓（接近锁仓）","允许开仓")))))))))) -> 已开仓 | H8: 32700 | I8: 43790 | J8: 2 | K8: 2.14 | L8: =IF(A8="","",IFERROR(LOOKUP(2,1/((持仓跟踪!$B$2:$B$157=A8)*(持仓跟踪!$X$2:$X$157="执行卖出")*(持仓跟踪!$Z$2:$Z$157<>"")),持仓跟踪!$Z$2:$Z$157),"")) -> 32700 | M8: 44391 | N8: 1.85 | P8: =IF(A8="","",IFERROR(LOOKUP(2,1/((持仓跟踪!$B$2:$B$157=A8)*(持仓跟踪!$X$2:$X$157="执行卖出")*(持仓跟踪!$AA$2:$AA$157<>"")),持仓跟踪!$AA$2:$AA$157),"")) | U8: =IF(OR(AO8="",J8="",AO8<=0),"",(J8-AO8)/AO8) -> 0.047120419 | V8: =IF(OR(AO8="",N8="",AO8<=0),"",(AO8-N8)/AO8) -> 0.031413613 | W8: =IF(OR(U8="",V8="",V8<=0),"",U8/V8) -> 1.5 | X8: =IF(OR(K8="",L8="",AP8=""),"",K8*L8-(E8*H8+IF(AND(AK8<>"",AL8<>""),AK8*AL8,0)+IF(AND(AM8<>"",AN8<>""),AM8*AN8,0))-IF(O8="",0,O8)-IF(P8="",0,P8)) -> 7521 | Y8: =IF(OR(X8="",AP8=""),"",IF((E8*H8+IF(AND(AK8<>"",AL8<>""),AK8*AL8,0)+IF(AND(AM8<>"",AN8<>""),AM8*AN8,0))+IF(O8="",0,O8)<=0,"",X8/((E8*H8+IF(AND(AK8<>"",AL8<>""),AK8*AL8,0)+IF(AND(AM8<>"",AN8<>""),AM8*AN8,0))+IF(O8="",0,O8)))) -> 0.12041885 | Z8: =IF(OR(AE8="",多次统计数据!$B$8=""),"",AE8-多次统计数据!$B$8) -> 0.0039776246 | AA8: =IF(OR(I8="",M8="",M8<I8),"",M8-I8) -> 601 | AB8: =IF(OR(A8="",多次统计数据!$B$8="",多次统计数据!$B$6<=0,多次统计数据!$B$6>=1),"",1-POWER(1+多次统计数据!$B$8,-多次统计数据!$B$6/(1-多次统计数据!$B$6))) -> 0.053016657 | AC8: =IF(OR(AB8="",多次统计数据!$B$9=""),"",IF(多次统计数据!$B$9<AB8,"低于上限","达到或超过上限")) -> 低于上限 | AD8: 1-差 | AE8: =IF(OR(X8="",C8="",C8<=0),"",X8/C8) -> 0.076526252 | AF8: 贪婪 | AG8: 短期博反弹 | AH8: 4～10个交易日 | AI8: 2块有压力 | AJ8: =IF(OR(AG8="",AH8=""),"",IF(OR(AND(AG8="短期博反弹",OR(AH8="1～3个交易日",AH8="4～10个交易日")),AND(AG8="突破冲新高",OR(AH8="4～10个交易日",AH8="11～20个交易日")),AND(AG8="趋势波段",OR(AH8="11～20个交易日",AH8="21～60个交易日",AH8="60个交易日以上"))),"匹配","周期与交易预期不匹配，请重新确认")) -> 匹配 | AO8: =IF(OR(A8="",H8="",H8<=0),"",(E8*H8+IF(AND(AK8<>"",AL8<>""),AK8*AL8,0)+IF(AND(AM8<>"",AN8<>""),AM8*AN8,0))/AP8) -> 1.91 | AP8: =IF(OR(A8="",H8="",H8<=0),"",H8+IF(AL8="",0,AL8)+IF(AN8="",0,AN8)) -> 32700 | AQ8: =IF(A8="","",IF(M8<>"",0,IF(OR(H8="",N8=""),"",MAX(E8-MAX(N8,IFERROR(SUMPRODUCT(MAX(((持仓跟踪!$A$2:$A$157="每日跟踪")*(持仓跟踪!$B$2:$B$157=A8))*持仓跟踪!$S$2:$S$157)),0)),0)*H8+IF(OR(AK8="",AL8=""),0,MAX(AK8-MAX(N8,IFERROR(SUMPRODUCT(MAX(((持仓跟踪!$A$2:$A$157="每日跟踪")*(持仓跟踪!$B$2:$B$157=A8))*持仓跟踪!$S$2:$S$157)),0)),0)*AL8)+IF(OR(AM8="",AN8=""),0,MAX(AM8-MAX(N8,IFERROR(SUMPRODUCT(MAX(((持仓跟踪!$A$2:$A$157="每日跟踪")*(持仓跟踪!$B$2:$B$157=A8))*持仓跟踪!$S$2:$S$157)),0)),0)*AN8)))) -> 0 | AR8: =IF(A8="","",IF(OR(E8="",H8=""),"违规：第一批价格或股数缺失",IF(OR(AND(AK8="",AL8<>""),AND(AK8<>"",AL8="")),"违规：第二批价格与股数须成对填写",IF(OR(AND(AM8="",AN8<>""),AND(AM8<>"",AN8="")),"违规：第三批价格与股数须成对填写",IF(AND(OR(AM8<>"",AN8<>""),OR(AK8="",AL8="")),"违规：必须先完成第二批",IF(OR(H8<=0,H8<>INT(H8),MOD(H8,100)<>0,AND(AL8<>"",OR(AL8<=0,AL8<>INT(AL8),MOD(AL8,100)<>0)),AND(AN8<>"",OR(AN8<=0,AN8<>INT(AN8),MOD(AN8,100)<>0))),"违规：股数须为100股整数倍",IF(AND(OR(AL8<>"",AN8<>""),OR(_LockStatus="已锁仓",_LockStatus="解锁信息不完整")),"违规：锁仓期间禁止加仓",IF(AQ8>C8*D8,"违规：超过单笔风险上限",IF(SUM($AQ$2:$AQ$98)>账户数据!$B$7,"违规：超过账户风险上限","通过"))))))))) -> 通过
A9: 8 | B9: 节电风能 | C9: 105801 | D9: 0.02 | E9: 3.83 | F9: =IF(OR(C9="",D9="",E9="",N9="",C9<=0,D9<=0,E9<=N9),"",ROUNDDOWN((C9*D9)/(E9-N9)/100,0)*100) -> 6400 | G9: =IF(A9="","",IF(H9<>"","已开仓",IF(账户数据!$B$23="已锁仓","禁止开仓：连续亏损达到上限",IF(账户数据!$B$23="解锁信息不完整","禁止开仓：请完整填写解锁信息",IF(OR(F9="",E9="",N9="",E9<=N9,账户数据!$B$7=""),"",IF(OR(AG9="",AH9="",AI9=""),"禁止开仓：交易预期未填写完整",IF(COUNTIFS(持仓跟踪!$A$2:$A$157,"止损计划",持仓跟踪!$B$2:$B$157,A9,持仓跟踪!$AC$2:$AC$157,"计划有效")=0,"禁止开仓：请先填写止损计划",IF(账户数据!$B$9+F9*(E9-N9)>=账户数据!$B$7,"禁止开仓：风险额度不足",IF(AJ9="周期与交易预期不匹配，请重新确认",IF(账户数据!$B$23="接近锁仓","允许开仓（接近锁仓；周期需复核）","允许开仓（周期需复核）"),IF(账户数据!$B$23="接近锁仓","允许开仓（接近锁仓）","允许开仓")))))))))) -> 已开仓 | H9: 6400 | I9: 44900 | J9: 4.5 | K9: =IF(A9="","",IFERROR(LOOKUP(2,1/((持仓跟踪!$B$2:$B$157=A9)*(持仓跟踪!$X$2:$X$157="执行卖出")*(持仓跟踪!$Y$2:$Y$157<>"")),持仓跟踪!$Y$2:$Y$157),"")) -> 3.47 | L9: =IF(A9="","",IFERROR(LOOKUP(2,1/((持仓跟踪!$B$2:$B$157=A9)*(持仓跟踪!$X$2:$X$157="执行卖出")*(持仓跟踪!$Z$2:$Z$157<>"")),持仓跟踪!$Z$2:$Z$157),"")) -> 6400 | M9: =IF(A9="","",IFERROR(LOOKUP(2,1/((持仓跟踪!$B$2:$B$157=A9)*(持仓跟踪!$X$2:$X$157="执行卖出")*(持仓跟踪!$H$2:$H$157<>"")),持仓跟踪!$H$2:$H$157),"")) -> 44914 | N9: 3.5 | P9: =IF(A9="","",IFERROR(LOOKUP(2,1/((持仓跟踪!$B$2:$B$157=A9)*(持仓跟踪!$X$2:$X$157="执行卖出")*(持仓跟踪!$AA$2:$AA$157<>"")),持仓跟踪!$AA$2:$AA$157),"")) | U9: =IF(OR(AO9="",J9="",AO9<=0),"",(J9-AO9)/AO9) -> 0.17493473 | V9: =IF(OR(AO9="",N9="",AO9<=0),"",(AO9-N9)/AO9) -> 0.08616188 | W9: =IF(OR(U9="",V9="",V9<=0),"",U9/V9) -> 2.030303 | X9: =IF(OR(K9="",L9="",AP9=""),"",K9*L9-(E9*H9+IF(AND(AK9<>"",AL9<>""),AK9*AL9,0)+IF(AND(AM9<>"",AN9<>""),AM9*AN9,0))-IF(O9="",0,O9)-IF(P9="",0,P9)) -> -2304 | Y9: =IF(OR(X9="",AP9=""),"",IF((E9*H9+IF(AND(AK9<>"",AL9<>""),AK9*AL9,0)+IF(AND(AM9<>"",AN9<>""),AM9*AN9,0))+IF(O9="",0,O9)<=0,"",X9/((E9*H9+IF(AND(AK9<>"",AL9<>""),AK9*AL9,0)+IF(AND(AM9<>"",AN9<>""),AM9*AN9,0))+IF(O9="",0,O9)))) -> -0.093994778 | Z9: =IF(OR(AE9="",多次统计数据!$B$8=""),"",AE9-多次统计数据!$B$8) -> -0.094325359 | AA9: =IF(OR(I9="",M9="",M9<I9),"",M9-I9) -> 14 | AB9: =IF(OR(A9="",多次统计数据!$B$8="",多次统计数据!$B$6<=0,多次统计数据!$B$6>=1),"",1-POWER(1+多次统计数据!$B$8,-多次统计数据!$B$6/(1-多次统计数据!$B$6))) -> 0.053016657 | AC9: =IF(OR(AB9="",多次统计数据!$B$9=""),"",IF(多次统计数据!$B$9<AB9,"低于上限","达到或超过上限")) -> 低于上限 | AD9: 3-一般 | AE9: =IF(OR(X9="",C9="",C9<=0),"",X9/C9) -> -0.021776732 | AG9: 短期博反弹 | AH9: 4～10个交易日 | AI9: 4块压力很大 | AJ9: =IF(OR(AG9="",AH9=""),"",IF(OR(AND(AG9="短期博反弹",OR(AH9="1～3个交易日",AH9="4～10个交易日")),AND(AG9="突破冲新高",OR(AH9="4～10个交易日",AH9="11～20个交易日")),AND(AG9="趋势波段",OR(AH9="11～20个交易日",AH9="21～60个交易日",AH9="60个交易日以上"))),"匹配","周期与交易预期不匹配，请重新确认")) -> 匹配 | AO9: =IF(OR(A9="",H9="",H9<=0),"",(E9*H9+IF(AND(AK9<>"",AL9<>""),AK9*AL9,0)+IF(AND(AM9<>"",AN9<>""),AM9*AN9,0))/AP9) -> 3.83 | AP9: =IF(OR(A9="",H9="",H9<=0),"",H9+IF(AL9="",0,AL9)+IF(AN9="",0,AN9)) -> 6400 | AQ9: =IF(A9="","",IF(M9<>"",0,IF(OR(H9="",N9=""),"",MAX(E9-MAX(N9,IFERROR(SUMPRODUCT(MAX(((持仓跟踪!$A$2:$A$157="每日跟踪")*(持仓跟踪!$B$2:$B$157=A9))*持仓跟踪!$S$2:$S$157)),0)),0)*H9+IF(OR(AK9="",AL9=""),0,MAX(AK9-MAX(N9,IFERROR(SUMPRODUCT(MAX(((持仓跟踪!$A$2:$A$157="每日跟踪")*(持仓跟踪!$B$2:$B$157=A9))*持仓跟踪!$S$2:$S$157)),0)),0)*AL9)+IF(OR(AM9="",AN9=""),0,MAX(AM9-MAX(N9,IFERROR(SUMPRODUCT(MAX(((持仓跟踪!$A$2:$A$157="每日跟踪")*(持仓跟踪!$B$2:$B$157=A9))*持仓跟踪!$S$2:$S$157)),0)),0)*AN9)))) -> 0 | AR9: =IF(A9="","",IF(OR(E9="",H9=""),"违规：第一批价格或股数缺失",IF(OR(AND(AK9="",AL9<>""),AND(AK9<>"",AL9="")),"违规：第二批价格与股数须成对填写",IF(OR(AND(AM9="",AN9<>""),AND(AM9<>"",AN9="")),"违规：第三批价格与股数须成对填写",IF(AND(OR(AM9<>"",AN9<>""),OR(AK9="",AL9="")),"违规：必须先完成第二批",IF(OR(H9<=0,H9<>INT(H9),MOD(H9,100)<>0,AND(AL9<>"",OR(AL9<=0,AL9<>INT(AL9),MOD(AL9,100)<>0)),AND(AN9<>"",OR(AN9<=0,AN9<>INT(AN9),MOD(AN9,100)<>0))),"违规：股数须为100股整数倍",IF(AND(OR(AL9<>"",AN9<>""),OR(_LockStatus="已锁仓",_LockStatus="解锁信息不完整")),"违规：锁仓期间禁止加仓",IF(AQ9>C9*D9,"违规：超过单笔风险上限",IF(SUM($AQ$2:$AQ$98)>账户数据!$B$7,"违规：超过账户风险上限","通过"))))))))) -> 通过
A10: 9 | B10: 节电风能 | C10: 103497 | D10: 0.02 | E10: 3.68 | F10: =IF(OR(C10="",D10="",E10="",N10="",C10<=0,D10<=0,E10<=N10),"",ROUNDDOWN((C10*D10)/(E10-N10)/100,0)*100) -> 11400 | G10: =IF(A10="","",IF(H10<>"","已开仓",IF(账户数据!$B$23="已锁仓","禁止开仓：连续亏损达到上限",IF(账户数据!$B$23="解锁信息不完整","禁止开仓：请完整填写解锁信息",IF(OR(F10="",E10="",N10="",E10<=N10,账户数据!$B$7=""),"",IF(OR(AG10="",AH10="",AI10=""),"禁止开仓：交易预期未填写完整",IF(COUNTIFS(持仓跟踪!$A$2:$A$157,"止损计划",持仓跟踪!$B$2:$B$157,A10,持仓跟踪!$AC$2:$AC$157,"计划有效")=0,"禁止开仓：请先填写止损计划",IF(账户数据!$B$9+F10*(E10-N10)>=账户数据!$B$7,"禁止开仓：风险额度不足",IF(AJ10="周期与交易预期不匹配，请重新确认",IF(账户数据!$B$23="接近锁仓","允许开仓（接近锁仓；周期需复核）","允许开仓（周期需复核）"),IF(账户数据!$B$23="接近锁仓","允许开仓（接近锁仓）","允许开仓")))))))))) -> 已开仓 | H10: 11400 | I10: 45000 | J10: 4 | K10: =IF(A10="","",IFERROR(LOOKUP(2,1/((持仓跟踪!$B$2:$B$157=A10)*(持仓跟踪!$X$2:$X$157="执行卖出")*(持仓跟踪!$Y$2:$Y$157<>"")),持仓跟踪!$Y$2:$Y$157),"")) -> 3.46 | L10: =IF(A10="","",IFERROR(LOOKUP(2,1/((持仓跟踪!$B$2:$B$157=A10)*(持仓跟踪!$X$2:$X$157="执行卖出")*(持仓跟踪!$Z$2:$Z$157<>"")),持仓跟踪!$Z$2:$Z$157),"")) -> 11400 | M10: =IF(A10="","",IFERROR(LOOKUP(2,1/((持仓跟踪!$B$2:$B$157=A10)*(持仓跟踪!$X$2:$X$157="执行卖出")*(持仓跟踪!$H$2:$H$157<>"")),持仓跟踪!$H$2:$H$157),"")) -> 45041 | N10: 3.5 | P10: =IF(A10="","",IFERROR(LOOKUP(2,1/((持仓跟踪!$B$2:$B$157=A10)*(持仓跟踪!$X$2:$X$157="执行卖出")*(持仓跟踪!$AA$2:$AA$157<>"")),持仓跟踪!$AA$2:$AA$157),"")) | U10: =IF(OR(AO10="",J10="",AO10<=0),"",(J10-AO10)/AO10) -> 0.086956522 | V10: =IF(OR(AO10="",N10="",AO10<=0),"",(AO10-N10)/AO10) -> 0.048913043 | W10: =IF(OR(U10="",V10="",V10<=0),"",U10/V10) -> 1.7777778 | X10: =IF(OR(K10="",L10="",AP10=""),"",K10*L10-(E10*H10+IF(AND(AK10<>"",AL10<>""),AK10*AL10,0)+IF(AND(AM10<>"",AN10<>""),AM10*AN10,0))-IF(O10="",0,O10)-IF(P10="",0,P10)) -> -2508 | Y10: =IF(OR(X10="",AP10=""),"",IF((E10*H10+IF(AND(AK10<>"",AL10<>""),AK10*AL10,0)+IF(AND(AM10<>"",AN10<>""),AM10*AN10,0))+IF(O10="",0,O10)<=0,"",X10/((E10*H10+IF(AND(AK10<>"",AL10<>""),AK10*AL10,0)+IF(AND(AM10<>"",AN10<>""),AM10*AN10,0))+IF(O10="",0,O10)))) -> -0.059782609 | Z10: =IF(OR(AE10="",多次统计数据!$B$8=""),"",AE10-多次统计数据!$B$8) -> -0.096781213 | AA10: =IF(OR(I10="",M10="",M10<I10),"",M10-I10) -> 41 | AB10: =IF(OR(A10="",多次统计数据!$B$8="",多次统计数据!$B$6<=0,多次统计数据!$B$6>=1),"",1-POWER(1+多次统计数据!$B$8,-多次统计数据!$B$6/(1-多次统计数据!$B$6))) -> 0.053016657 | AC10: =IF(OR(AB10="",多次统计数据!$B$9=""),"",IF(多次统计数据!$B$9<AB10,"低于上限","达到或超过上限")) -> 低于上限 | AD10: 2-较差 | AE10: =IF(OR(X10="",C10="",C10<=0),"",X10/C10) -> -0.024232586 | AG10: 短期博反弹 | AH10: 4～10个交易日 | AJ10: =IF(OR(AG10="",AH10=""),"",IF(OR(AND(AG10="短期博反弹",OR(AH10="1～3个交易日",AH10="4～10个交易日")),AND(AG10="突破冲新高",OR(AH10="4～10个交易日",AH10="11～20个交易日")),AND(AG10="趋势波段",OR(AH10="11～20个交易日",AH10="21～60个交易日",AH10="60个交易日以上"))),"匹配","周期与交易预期不匹配，请重新确认")) -> 匹配 | AO10: =IF(OR(A10="",H10="",H10<=0),"",(E10*H10+IF(AND(AK10<>"",AL10<>""),AK10*AL10,0)+IF(AND(AM10<>"",AN10<>""),AM10*AN10,0))/AP10) -> 3.68 | AP10: =IF(OR(A10="",H10="",H10<=0),"",H10+IF(AL10="",0,AL10)+IF(AN10="",0,AN10)) -> 11400 | AQ10: =IF(A10="","",IF(M10<>"",0,IF(OR(H10="",N10=""),"",MAX(E10-MAX(N10,IFERROR(SUMPRODUCT(MAX(((持仓跟踪!$A$2:$A$157="每日跟踪")*(持仓跟踪!$B$2:$B$157=A10))*持仓跟踪!$S$2:$S$157)),0)),0)*H10+IF(OR(AK10="",AL10=""),0,MAX(AK10-MAX(N10,IFERROR(SUMPRODUCT(MAX(((持仓跟踪!$A$2:$A$157="每日跟踪")*(持仓跟踪!$B$2:$B$157=A10))*持仓跟踪!$S$2:$S$157)),0)),0)*AL10)+IF(OR(AM10="",AN10=""),0,MAX(AM10-MAX(N10,IFERROR(SUMPRODUCT(MAX(((持仓跟踪!$A$2:$A$157="每日跟踪")*(持仓跟踪!$B$2:$B$157=A10))*持仓跟踪!$S$2:$S$157)),0)),0)*AN10)))) -> 0 | AR10: =IF(A10="","",IF(OR(E10="",H10=""),"违规：第一批价格或股数缺失",IF(OR(AND(AK10="",AL10<>""),AND(AK10<>"",AL10="")),"违规：第二批价格与股数须成对填写",IF(OR(AND(AM10="",AN10<>""),AND(AM10<>"",AN10="")),"违规：第三批价格与股数须成对填写",IF(AND(OR(AM10<>"",AN10<>""),OR(AK10="",AL10="")),"违规：必须先完成第二批",IF(OR(H10<=0,H10<>INT(H10),MOD(H10,100)<>0,AND(AL10<>"",OR(AL10<=0,AL10<>INT(AL10),MOD(AL10,100)<>0)),AND(AN10<>"",OR(AN10<=0,AN10<>INT(AN10),MOD(AN10,100)<>0))),"违规：股数须为100股整数倍",IF(AND(OR(AL10<>"",AN10<>""),OR(_LockStatus="已锁仓",_LockStatus="解锁信息不完整")),"违规：锁仓期间禁止加仓",IF(AQ10>C10*D10,"违规：超过单笔风险上限",IF(SUM($AQ$2:$AQ$98)>账户数据!$B$7,"违规：超过账户风险上限","通过"))))))))) -> 通过
A11: 10 | B11: 节电风能 | C11: 100989 | D11: 0.02 | E11: 2.86 | F11: =IF(OR(C11="",D11="",E11="",N11="",C11<=0,D11<=0,E11<=N11),"",ROUNDDOWN((C11*D11)/(E11-N11)/100,0)*100) -> 18300 | G11: =IF(A11="","",IF(H11<>"","已开仓",IF(账户数据!$B$23="已锁仓","禁止开仓：连续亏损达到上限",IF(账户数据!$B$23="解锁信息不完整","禁止开仓：请完整填写解锁信息",IF(OR(F11="",E11="",N11="",E11<=N11,账户数据!$B$7=""),"",IF(OR(AG11="",AH11="",AI11=""),"禁止开仓：交易预期未填写完整",IF(COUNTIFS(持仓跟踪!$A$2:$A$157,"止损计划",持仓跟踪!$B$2:$B$157,A11,持仓跟踪!$AC$2:$AC$157,"计划有效")=0,"禁止开仓：请先填写止损计划",IF(账户数据!$B$9+F11*(E11-N11)>=账户数据!$B$7,"禁止开仓：风险额度不足",IF(AJ11="周期与交易预期不匹配，请重新确认",IF(账户数据!$B$23="接近锁仓","允许开仓（接近锁仓；周期需复核）","允许开仓（周期需复核）"),IF(账户数据!$B$23="接近锁仓","允许开仓（接近锁仓）","允许开仓")))))))))) -> 已开仓 | H11: 18300 | I11: 45357 | J11: 3 | K11: =IF(A11="","",IFERROR(LOOKUP(2,1/((持仓跟踪!$B$2:$B$157=A11)*(持仓跟踪!$X$2:$X$157="执行卖出")*(持仓跟踪!$Y$2:$Y$157<>"")),持仓跟踪!$Y$2:$Y$157),"")) -> 2.78 | L11: =IF(A11="","",IFERROR(LOOKUP(2,1/((持仓跟踪!$B$2:$B$157=A11)*(持仓跟踪!$X$2:$X$157="执行卖出")*(持仓跟踪!$Z$2:$Z$157<>"")),持仓跟踪!$Z$2:$Z$157),"")) -> 18300 | M11: =IF(A11="","",IFERROR(LOOKUP(2,1/((持仓跟踪!$B$2:$B$157=A11)*(持仓跟踪!$X$2:$X$157="执行卖出")*(持仓跟踪!$H$2:$H$157<>"")),持仓跟踪!$H$2:$H$157),"")) -> 45373 | N11: 2.75 | P11: =IF(A11="","",IFERROR(LOOKUP(2,1/((持仓跟踪!$B$2:$B$157=A11)*(持仓跟踪!$X$2:$X$157="执行卖出")*(持仓跟踪!$AA$2:$AA$157<>"")),持仓跟踪!$AA$2:$AA$157),"")) | U11: =IF(OR(AO11="",J11="",AO11<=0),"",(J11-AO11)/AO11) -> 0.048951049 | V11: =IF(OR(AO11="",N11="",AO11<=0),"",(AO11-N11)/AO11) -> 0.038461538 | W11: =IF(OR(U11="",V11="",V11<=0),"",U11/V11) -> 1.2727273 | X11: =IF(OR(K11="",L11="",AP11=""),"",K11*L11-(E11*H11+IF(AND(AK11<>"",AL11<>""),AK11*AL11,0)+IF(AND(AM11<>"",AN11<>""),AM11*AN11,0))-IF(O11="",0,O11)-IF(P11="",0,P11)) -> -1464 | Y11: =IF(OR(X11="",AP11=""),"",IF((E11*H11+IF(AND(AK11<>"",AL11<>""),AK11*AL11,0)+IF(AND(AM11<>"",AN11<>""),AM11*AN11,0))+IF(O11="",0,O11)<=0,"",X11/((E11*H11+IF(AND(AK11<>"",AL11<>""),AK11*AL11,0)+IF(AND(AM11<>"",AN11<>""),AM11*AN11,0))+IF(O11="",0,O11)))) -> -0.027972028 | Z11: =IF(OR(AE11="",多次统计数据!$B$8=""),"",AE11-多次统计数据!$B$8) -> -0.087045255 | AA11: =IF(OR(I11="",M11="",M11<I11),"",M11-I11) -> 16 | AB11: =IF(OR(A11="",多次统计数据!$B$8="",多次统计数据!$B$6<=0,多次统计数据!$B$6>=1),"",1-POWER(1+多次统计数据!$B$8,-多次统计数据!$B$6/(1-多次统计数据!$B$6))) -> 0.053016657 | AC11: =IF(OR(AB11="",多次统计数据!$B$9=""),"",IF(多次统计数据!$B$9<AB11,"低于上限","达到或超过上限")) -> 低于上限 | AD11: 3-一般 | AE11: =IF(OR(X11="",C11="",C11<=0),"",X11/C11) -> -0.014496628 | AG11: 趋势波段 | AH11: 21～60个交易日 | AJ11: =IF(OR(AG11="",AH11=""),"",IF(OR(AND(AG11="短期博反弹",OR(AH11="1～3个交易日",AH11="4～10个交易日")),AND(AG11="突破冲新高",OR(AH11="4～10个交易日",AH11="11～20个交易日")),AND(AG11="趋势波段",OR(AH11="11～20个交易日",AH11="21～60个交易日",AH11="60个交易日以上"))),"匹配","周期与交易预期不匹配，请重新确认")) -> 匹配 | AO11: =IF(OR(A11="",H11="",H11<=0),"",(E11*H11+IF(AND(AK11<>"",AL11<>""),AK11*AL11,0)+IF(AND(AM11<>"",AN11<>""),AM11*AN11,0))/AP11) -> 2.86 | AP11: =IF(OR(A11="",H11="",H11<=0),"",H11+IF(AL11="",0,AL11)+IF(AN11="",0,AN11)) -> 18300 | AQ11: =IF(A11="","",IF(M11<>"",0,IF(OR(H11="",N11=""),"",MAX(E11-MAX(N11,IFERROR(SUMPRODUCT(MAX(((持仓跟踪!$A$2:$A$157="每日跟踪")*(持仓跟踪!$B$2:$B$157=A11))*持仓跟踪!$S$2:$S$157)),0)),0)*H11+IF(OR(AK11="",AL11=""),0,MAX(AK11-MAX(N11,IFERROR(SUMPRODUCT(MAX(((持仓跟踪!$A$2:$A$157="每日跟踪")*(持仓跟踪!$B$2:$B$157=A11))*持仓跟踪!$S$2:$S$157)),0)),0)*AL11)+IF(OR(AM11="",AN11=""),0,MAX(AM11-MAX(N11,IFERROR(SUMPRODUCT(MAX(((持仓跟踪!$A$2:$A$157="每日跟踪")*(持仓跟踪!$B$2:$B$157=A11))*持仓跟踪!$S$2:$S$157)),0)),0)*AN11)))) -> 0 | AR11: =IF(A11="","",IF(OR(E11="",H11=""),"违规：第一批价格或股数缺失",IF(OR(AND(AK11="",AL11<>""),AND(AK11<>"",AL11="")),"违规：第二批价格与股数须成对填写",IF(OR(AND(AM11="",AN11<>""),AND(AM11<>"",AN11="")),"违规：第三批价格与股数须成对填写",IF(AND(OR(AM11<>"",AN11<>""),OR(AK11="",AL11="")),"违规：必须先完成第二批",IF(OR(H11<=0,H11<>INT(H11),MOD(H11,100)<>0,AND(AL11<>"",OR(AL11<=0,AL11<>INT(AL11),MOD(AL11,100)<>0)),AND(AN11<>"",OR(AN11<=0,AN11<>INT(AN11),MOD(AN11,100)<>0))),"违规：股数须为100股整数倍",IF(AND(OR(AL11<>"",AN11<>""),OR(_LockStatus="已锁仓",_LockStatus="解锁信息不完整")),"违规：锁仓期间禁止加仓",IF(AQ11>C11*D11,"违规：超过单笔风险上限",IF(SUM($AQ$2:$AQ$98)>账户数据!$B$7,"违规：超过账户风险上限","通过"))))))))) -> 通过
A12: 11 | B12: 恒瑞医药 | C12: 99525 | D12: 0.02 | E12: 20.5 | F12: =IF(OR(C12="",D12="",E12="",N12="",C12<=0,D12<=0,E12<=N12),"",ROUNDDOWN((C12*D12)/(E12-N12)/100,0)*100) -> 1900 | G12: =IF(A12="","",IF(H12<>"","已开仓",IF(账户数据!$B$23="已锁仓","禁止开仓：连续亏损达到上限",IF(账户数据!$B$23="解锁信息不完整","禁止开仓：请完整填写解锁信息",IF(OR(F12="",E12="",N12="",E12<=N12,账户数据!$B$7=""),"",IF(OR(AG12="",AH12="",AI12=""),"禁止开仓：交易预期未填写完整",IF(COUNTIFS(持仓跟踪!$A$2:$A$157,"止损计划",持仓跟踪!$B$2:$B$157,A12,持仓跟踪!$AC$2:$AC$157,"计划有效")=0,"禁止开仓：请先填写止损计划",IF(账户数据!$B$9+F12*(E12-N12)>=账户数据!$B$7,"禁止开仓：风险额度不足",IF(AJ12="周期与交易预期不匹配，请重新确认",IF(账户数据!$B$23="接近锁仓","允许开仓（接近锁仓；周期需复核）","允许开仓（周期需复核）"),IF(账户数据!$B$23="接近锁仓","允许开仓（接近锁仓）","允许开仓")))))))))) -> 已开仓 | H12: 1900 | I12: 42815 | J12: 23 | K12: =IF(A12="","",IFERROR(LOOKUP(2,1/((持仓跟踪!$B$2:$B$157=A12)*(持仓跟踪!$X$2:$X$157="执行卖出")*(持仓跟踪!$Y$2:$Y$157<>"")),持仓跟踪!$Y$2:$Y$157),"")) -> 29.25 | L12: =IF(A12="","",IFERROR(LOOKUP(2,1/((持仓跟踪!$B$2:$B$157=A12)*(持仓跟踪!$X$2:$X$157="执行卖出")*(持仓跟踪!$Z$2:$Z$157<>"")),持仓跟踪!$Z$2:$Z$157),"")) -> 1900 | M12: =IF(A12="","",IFERROR(LOOKUP(2,1/((持仓跟踪!$B$2:$B$157=A12)*(持仓跟踪!$X$2:$X$157="执行卖出")*(持仓跟踪!$H$2:$H$157<>"")),持仓跟踪!$H$2:$H$157),"")) -> 43059 | N12: 19.5 | P12: =IF(A12="","",IFERROR(LOOKUP(2,1/((持仓跟踪!$B$2:$B$157=A12)*(持仓跟踪!$X$2:$X$157="执行卖出")*(持仓跟踪!$AA$2:$AA$157<>"")),持仓跟踪!$AA$2:$AA$157),"")) | U12: =IF(OR(AO12="",J12="",AO12<=0),"",(J12-AO12)/AO12) -> 0.12195122 | V12: =IF(OR(AO12="",N12="",AO12<=0),"",(AO12-N12)/AO12) -> 0.048780488 | W12: =IF(OR(U12="",V12="",V12<=0),"",U12/V12) -> 2.5 | X12: =IF(OR(K12="",L12="",AP12=""),"",K12*L12-(E12*H12+IF(AND(AK12<>"",AL12<>""),AK12*AL12,0)+IF(AND(AM12<>"",AN12<>""),AM12*AN12,0))-IF(O12="",0,O12)-IF(P12="",0,P12)) -> 16625 | Y12: =IF(OR(X12="",AP12=""),"",IF((E12*H12+IF(AND(AK12<>"",AL12<>""),AK12*AL12,0)+IF(AND(AM12<>"",AN12<>""),AM12*AN12,0))+IF(O12="",0,O12)<=0,"",X12/((E12*H12+IF(AND(AK12<>"",AL12<>""),AK12*AL12,0)+IF(AND(AM12<>"",AN12<>""),AM12*AN12,0))+IF(O12="",0,O12)))) -> 0.42682927 | Z12: =IF(OR(AE12="",多次统计数据!$B$8=""),"",AE12-多次统计数据!$B$8) -> 0.094494829 | AA12: =IF(OR(I12="",M12="",M12<I12),"",M12-I12) -> 244 | AB12: =IF(OR(A12="",多次统计数据!$B$8="",多次统计数据!$B$6<=0,多次统计数据!$B$6>=1),"",1-POWER(1+多次统计数据!$B$8,-多次统计数据!$B$6/(1-多次统计数据!$B$6))) -> 0.053016657 | AC12: =IF(OR(AB12="",多次统计数据!$B$9=""),"",IF(多次统计数据!$B$9<AB12,"低于上限","达到或超过上限")) -> 低于上限 | AE12: =IF(OR(X12="",C12="",C12<=0),"",X12/C12) -> 0.16704346 | AG12: 突破冲新高 | AH12: 11～20个交易日 | AI12: 上方有卖压，但是消耗了，获利的已经走了 | AJ12: =IF(OR(AG12="",AH12=""),"",IF(OR(AND(AG12="短期博反弹",OR(AH12="1～3个交易日",AH12="4～10个交易日")),AND(AG12="突破冲新高",OR(AH12="4～10个交易日",AH12="11～20个交易日")),AND(AG12="趋势波段",OR(AH12="11～20个交易日",AH12="21～60个交易日",AH12="60个交易日以上"))),"匹配","周期与交易预期不匹配，请重新确认")) -> 匹配 | AO12: =IF(OR(A12="",H12="",H12<=0),"",(E12*H12+IF(AND(AK12<>"",AL12<>""),AK12*AL12,0)+IF(AND(AM12<>"",AN12<>""),AM12*AN12,0))/AP12) -> 20.5 | AP12: =IF(OR(A12="",H12="",H12<=0),"",H12+IF(AL12="",0,AL12)+IF(AN12="",0,AN12)) -> 1900 | AQ12: =IF(A12="","",IF(M12<>"",0,IF(OR(H12="",N12=""),"",MAX(E12-MAX(N12,IFERROR(SUMPRODUCT(MAX(((持仓跟踪!$A$2:$A$157="每日跟踪")*(持仓跟踪!$B$2:$B$157=A12))*持仓跟踪!$S$2:$S$157)),0)),0)*H12+IF(OR(AK12="",AL12=""),0,MAX(AK12-MAX(N12,IFERROR(SUMPRODUCT(MAX(((持仓跟踪!$A$2:$A$157="每日跟踪")*(持仓跟踪!$B$2:$B$157=A12))*持仓跟踪!$S$2:$S$157)),0)),0)*AL12)+IF(OR(AM12="",AN12=""),0,MAX(AM12-MAX(N12,IFERROR(SUMPRODUCT(MAX(((持仓跟踪!$A$2:$A$157="每日跟踪")*(持仓跟踪!$B$2:$B$157=A12))*持仓跟踪!$S$2:$S$157)),0)),0)*AN12)))) -> 0 | AR12: =IF(A12="","",IF(OR(E12="",H12=""),"违规：第一批价格或股数缺失",IF(OR(AND(AK12="",AL12<>""),AND(AK12<>"",AL12="")),"违规：第二批价格与股数须成对填写",IF(OR(AND(AM12="",AN12<>""),AND(AM12<>"",AN12="")),"违规：第三批价格与股数须成对填写",IF(AND(OR(AM12<>"",AN12<>""),OR(AK12="",AL12="")),"违规：必须先完成第二批",IF(OR(H12<=0,H12<>INT(H12),MOD(H12,100)<>0,AND(AL12<>"",OR(AL12<=0,AL12<>INT(AL12),MOD(AL12,100)<>0)),AND(AN12<>"",OR(AN12<=0,AN12<>INT(AN12),MOD(AN12,100)<>0))),"违规：股数须为100股整数倍",IF(AND(OR(AL12<>"",AN12<>""),OR(_LockStatus="已锁仓",_LockStatus="解锁信息不完整")),"违规：锁仓期间禁止加仓",IF(AQ12>C12*D12,"违规：超过单笔风险上限",IF(SUM($AQ$2:$AQ$98)>账户数据!$B$7,"违规：超过账户风险上限","通过"))))))))) -> 通过
A13: 12 | B13: 恒瑞医药 | C13: 116150 | D13: 0.02 | E13: 31.91 | F13: =IF(OR(C13="",D13="",E13="",N13="",C13<=0,D13<=0,E13<=N13),"",ROUNDDOWN((C13*D13)/(E13-N13)/100,0)*100) -> 1200 | G13: =IF(A13="","",IF(H13<>"","已开仓",IF(账户数据!$B$23="已锁仓","禁止开仓：连续亏损达到上限",IF(账户数据!$B$23="解锁信息不完整","禁止开仓：请完整填写解锁信息",IF(OR(F13="",E13="",N13="",E13<=N13,账户数据!$B$7=""),"",IF(OR(AG13="",AH13="",AI13=""),"禁止开仓：交易预期未填写完整",IF(COUNTIFS(持仓跟踪!$A$2:$A$157,"止损计划",持仓跟踪!$B$2:$B$157,A13,持仓跟踪!$AC$2:$AC$157,"计划有效")=0,"禁止开仓：请先填写止损计划",IF(账户数据!$B$9+F13*(E13-N13)>=账户数据!$B$7,"禁止开仓：风险额度不足",IF(AJ13="周期与交易预期不匹配，请重新确认",IF(账户数据!$B$23="接近锁仓","允许开仓（接近锁仓；周期需复核）","允许开仓（周期需复核）"),IF(账户数据!$B$23="接近锁仓","允许开仓（接近锁仓）","允许开仓")))))))))) -> 已开仓 | H13: 1200 | I13: 43110 | J13: 35 | K13: 29.29 | L13: =IF(A13="","",IFERROR(LOOKUP(2,1/((持仓跟踪!$B$2:$B$157=A13)*(持仓跟踪!$X$2:$X$157="执行卖出")*(持仓跟踪!$Z$2:$Z$157<>"")),持仓跟踪!$Z$2:$Z$157),"")) -> 1200 | M13: =IF(A13="","",IFERROR(LOOKUP(2,1/((持仓跟踪!$B$2:$B$157=A13)*(持仓跟踪!$X$2:$X$157="执行卖出")*(持仓跟踪!$H$2:$H$157<>"")),持仓跟踪!$H$2:$H$157),"")) -> 43311 | N13: 30 | P13: =IF(A13="","",IFERROR(LOOKUP(2,1/((持仓跟踪!$B$2:$B$157=A13)*(持仓跟踪!$X$2:$X$157="执行卖出")*(持仓跟踪!$AA$2:$AA$157<>"")),持仓跟踪!$AA$2:$AA$157),"")) | U13: =IF(OR(AO13="",J13="",AO13<=0),"",(J13-AO13)/AO13) -> 0.096834848 | V13: =IF(OR(AO13="",N13="",AO13<=0),"",(AO13-N13)/AO13) -> 0.059855845 | W13: =IF(OR(U13="",V13="",V13<=0),"",U13/V13) -> 1.617801 | X13: =IF(OR(K13="",L13="",AP13=""),"",K13*L13-(E13*H13+IF(AND(AK13<>"",AL13<>""),AK13*AL13,0)+IF(AND(AM13<>"",AN13<>""),AM13*AN13,0))-IF(O13="",0,O13)-IF(P13="",0,P13)) -> -3144 | Y13: =IF(OR(X13="",AP13=""),"",IF((E13*H13+IF(AND(AK13<>"",AL13<>""),AK13*AL13,0)+IF(AND(AM13<>"",AN13<>""),AM13*AN13,0))+IF(O13="",0,O13)<=0,"",X13/((E13*H13+IF(AND(AK13<>"",AL13<>""),AK13*AL13,0)+IF(AND(AM13<>"",AN13<>""),AM13*AN13,0))+IF(O13="",0,O13)))) -> -0.082105923 | Z13: =IF(OR(AE13="",多次统计数据!$B$8=""),"",AE13-多次统计数据!$B$8) -> -0.099617073 | AA13: =IF(OR(I13="",M13="",M13<I13),"",M13-I13) -> 201 | AB13: =IF(OR(A13="",多次统计数据!$B$8="",多次统计数据!$B$6<=0,多次统计数据!$B$6>=1),"",1-POWER(1+多次统计数据!$B$8,-多次统计数据!$B$6/(1-多次统计数据!$B$6))) -> 0.053016657 | AC13: =IF(OR(AB13="",多次统计数据!$B$9=""),"",IF(多次统计数据!$B$9<AB13,"低于上限","达到或超过上限")) -> 低于上限 | AE13: =IF(OR(X13="",C13="",C13<=0),"",X13/C13) -> -0.027068446 | AG13: 突破冲新高 | AH13: 11～20个交易日 | AJ13: =IF(OR(AG13="",AH13=""),"",IF(OR(AND(AG13="短期博反弹",OR(AH13="1～3个交易日",AH13="4～10个交易日")),AND(AG13="突破冲新高",OR(AH13="4～10个交易日",AH13="11～20个交易日")),AND(AG13="趋势波段",OR(AH13="11～20个交易日",AH13="21～60个交易日",AH13="60个交易日以上"))),"匹配","周期与交易预期不匹配，请重新确认")) -> 匹配 | AO13: =IF(OR(A13="",H13="",H13<=0),"",(E13*H13+IF(AND(AK13<>"",AL13<>""),AK13*AL13,0)+IF(AND(AM13<>"",AN13<>""),AM13*AN13,0))/AP13) -> 31.91 | AP13: =IF(OR(A13="",H13="",H13<=0),"",H13+IF(AL13="",0,AL13)+IF(AN13="",0,AN13)) -> 1200 | AQ13: =IF(A13="","",IF(M13<>"",0,IF(OR(H13="",N13=""),"",MAX(E13-MAX(N13,IFERROR(SUMPRODUCT(MAX(((持仓跟踪!$A$2:$A$157="每日跟踪")*(持仓跟踪!$B$2:$B$157=A13))*持仓跟踪!$S$2:$S$157)),0)),0)*H13+IF(OR(AK13="",AL13=""),0,MAX(AK13-MAX(N13,IFERROR(SUMPRODUCT(MAX(((持仓跟踪!$A$2:$A$157="每日跟踪")*(持仓跟踪!$B$2:$B$157=A13))*持仓跟踪!$S$2:$S$157)),0)),0)*AL13)+IF(OR(AM13="",AN13=""),0,MAX(AM13-MAX(N13,IFERROR(SUMPRODUCT(MAX(((持仓跟踪!$A$2:$A$157="每日跟踪")*(持仓跟踪!$B$2:$B$157=A13))*持仓跟踪!$S$2:$S$157)),0)),0)*AN13)))) -> 0 | AR13: =IF(A13="","",IF(OR(E13="",H13=""),"违规：第一批价格或股数缺失",IF(OR(AND(AK13="",AL13<>""),AND(AK13<>"",AL13="")),"违规：第二批价格与股数须成对填写",IF(OR(AND(AM13="",AN13<>""),AND(AM13<>"",AN13="")),"违规：第三批价格与股数须成对填写",IF(AND(OR(AM13<>"",AN13<>""),OR(AK13="",AL13="")),"违规：必须先完成第二批",IF(OR(H13<=0,H13<>INT(H13),MOD(H13,100)<>0,AND(AL13<>"",OR(AL13<=0,AL13<>INT(AL13),MOD(AL13,100)<>0)),AND(AN13<>"",OR(AN13<=0,AN13<>INT(AN13),MOD(AN13,100)<>0))),"违规：股数须为100股整数倍",IF(AND(OR(AL13<>"",AN13<>""),OR(_LockStatus="已锁仓",_LockStatus="解锁信息不完整")),"违规：锁仓期间禁止加仓",IF(AQ13>C13*D13,"违规：超过单笔风险上限",IF(SUM($AQ$2:$AQ$98)>账户数据!$B$7,"违规：超过账户风险上限","通过"))))))))) -> 通过
A14: 13 | B14: 恒瑞医药 | C14: 113006 | D14: 0.02 | E14: 41.91 | F14: =IF(OR(C14="",D14="",E14="",N14="",C14<=0,D14<=0,E14<=N14),"",ROUNDDOWN((C14*D14)/(E14-N14)/100,0)*100) -> 700 | G14: =IF(A14="","",IF(H14<>"","已开仓",IF(账户数据!$B$23="已锁仓","禁止开仓：连续亏损达到上限",IF(账户数据!$B$23="解锁信息不完整","禁止开仓：请完整填写解锁信息",IF(OR(F14="",E14="",N14="",E14<=N14,账户数据!$B$7=""),"",IF(OR(AG14="",AH14="",AI14=""),"禁止开仓：交易预期未填写完整",IF(COUNTIFS(持仓跟踪!$A$2:$A$157,"止损计划",持仓跟踪!$B$2:$B$157,A14,持仓跟踪!$AC$2:$AC$157,"计划有效")=0,"禁止开仓：请先填写止损计划",IF(账户数据!$B$9+F14*(E14-N14)>=账户数据!$B$7,"禁止开仓：风险额度不足",IF(AJ14="周期与交易预期不匹配，请重新确认",IF(账户数据!$B$23="接近锁仓","允许开仓（接近锁仓；周期需复核）","允许开仓（周期需复核）"),IF(账户数据!$B$23="接近锁仓","允许开仓（接近锁仓）","允许开仓")))))))))) -> 已开仓 | H14: 700 | I14: 43245 | J14: 50 | K14: 38.49 | L14: 700 | M14: 43311 | N14: 39 | P14: =IF(A14="","",IFERROR(LOOKUP(2,1/((持仓跟踪!$B$2:$B$157=A14)*(持仓跟踪!$X$2:$X$157="执行卖出")*(持仓跟踪!$AA$2:$AA$157<>"")),持仓跟踪!$AA$2:$AA$157),"")) | U14: =IF(OR(AO14="",J14="",AO14<=0),"",(J14-AO14)/AO14) -> 0.19303269 | V14: =IF(OR(AO14="",N14="",AO14<=0),"",(AO14-N14)/AO14) -> 0.069434503 | W14: =IF(OR(U14="",V14="",V14<=0),"",U14/V14) -> 2.7800687 | X14: =IF(OR(K14="",L14="",AP14=""),"",K14*L14-(E14*H14+IF(AND(AK14<>"",AL14<>""),AK14*AL14,0)+IF(AND(AM14<>"",AN14<>""),AM14*AN14,0))-IF(O14="",0,O14)-IF(P14="",0,P14)) -> -2394 | Y14: =IF(OR(X14="",AP14=""),"",IF((E14*H14+IF(AND(AK14<>"",AL14<>""),AK14*AL14,0)+IF(AND(AM14<>"",AN14<>""),AM14*AN14,0))+IF(O14="",0,O14)<=0,"",X14/((E14*H14+IF(AND(AK14<>"",AL14<>""),AK14*AL14,0)+IF(AND(AM14<>"",AN14<>""),AM14*AN14,0))+IF(O14="",0,O14)))) -> -0.081603436 | Z14: =IF(OR(AE14="",多次统计数据!$B$8=""),"",AE14-多次统计数据!$B$8) -> -0.093733343 | AA14: =IF(OR(I14="",M14="",M14<I14),"",M14-I14) -> 66 | AB14: =IF(OR(A14="",多次统计数据!$B$8="",多次统计数据!$B$6<=0,多次统计数据!$B$6>=1),"",1-POWER(1+多次统计数据!$B$8,-多次统计数据!$B$6/(1-多次统计数据!$B$6))) -> 0.053016657 | AC14: =IF(OR(AB14="",多次统计数据!$B$9=""),"",IF(多次统计数据!$B$9<AB14,"低于上限","达到或超过上限")) -> 低于上限 | AE14: =IF(OR(X14="",C14="",C14<=0),"",X14/C14) -> -0.021184716 | AG14: 突破冲新高 | AH14: 11～20个交易日 | AJ14: =IF(OR(AG14="",AH14=""),"",IF(OR(AND(AG14="短期博反弹",OR(AH14="1～3个交易日",AH14="4～10个交易日")),AND(AG14="突破冲新高",OR(AH14="4～10个交易日",AH14="11～20个交易日")),AND(AG14="趋势波段",OR(AH14="11～20个交易日",AH14="21～60个交易日",AH14="60个交易日以上"))),"匹配","周期与交易预期不匹配，请重新确认")) -> 匹配 | AO14: =IF(OR(A14="",H14="",H14<=0),"",(E14*H14+IF(AND(AK14<>"",AL14<>""),AK14*AL14,0)+IF(AND(AM14<>"",AN14<>""),AM14*AN14,0))/AP14) -> 41.91 | AP14: =IF(OR(A14="",H14="",H14<=0),"",H14+IF(AL14="",0,AL14)+IF(AN14="",0,AN14)) -> 700 | AQ14: =IF(A14="","",IF(M14<>"",0,IF(OR(H14="",N14=""),"",MAX(E14-MAX(N14,IFERROR(SUMPRODUCT(MAX(((持仓跟踪!$A$2:$A$157="每日跟踪")*(持仓跟踪!$B$2:$B$157=A14))*持仓跟踪!$S$2:$S$157)),0)),0)*H14+IF(OR(AK14="",AL14=""),0,MAX(AK14-MAX(N14,IFERROR(SUMPRODUCT(MAX(((持仓跟踪!$A$2:$A$157="每日跟踪")*(持仓跟踪!$B$2:$B$157=A14))*持仓跟踪!$S$2:$S$157)),0)),0)*AL14)+IF(OR(AM14="",AN14=""),0,MAX(AM14-MAX(N14,IFERROR(SUMPRODUCT(MAX(((持仓跟踪!$A$2:$A$157="每日跟踪")*(持仓跟踪!$B$2:$B$157=A14))*持仓跟踪!$S$2:$S$157)),0)),0)*AN14)))) -> 0 | AR14: =IF(A14="","",IF(OR(E14="",H14=""),"违规：第一批价格或股数缺失",IF(OR(AND(AK14="",AL14<>""),AND(AK14<>"",AL14="")),"违规：第二批价格与股数须成对填写",IF(OR(AND(AM14="",AN14<>""),AND(AM14<>"",AN14="")),"违规：第三批价格与股数须成对填写",IF(AND(OR(AM14<>"",AN14<>""),OR(AK14="",AL14="")),"违规：必须先完成第二批",IF(OR(H14<=0,H14<>INT(H14),MOD(H14,100)<>0,AND(AL14<>"",OR(AL14<=0,AL14<>INT(AL14),MOD(AL14,100)<>0)),AND(AN14<>"",OR(AN14<=0,AN14<>INT(AN14),MOD(AN14,100)<>0))),"违规：股数须为100股整数倍",IF(AND(OR(AL14<>"",AN14<>""),OR(_LockStatus="已锁仓",_LockStatus="解锁信息不完整")),"违规：锁仓期间禁止加仓",IF(AQ14>C14*D14,"违规：超过单笔风险上限",IF(SUM($AQ$2:$AQ$98)>账户数据!$B$7,"违规：超过账户风险上限","通过"))))))))) -> 通过
A15: 14 | B15: 恒瑞医药 | C15: 110612 | D15: 0.02 | E15: 42.06 | F15: =IF(OR(C15="",D15="",E15="",N15="",C15<=0,D15<=0,E15<=N15),"",ROUNDDOWN((C15*D15)/(E15-N15)/100,0)*100) -> 700 | G15: =IF(A15="","",IF(H15<>"","已开仓",IF(账户数据!$B$23="已锁仓","禁止开仓：连续亏损达到上限",IF(账户数据!$B$23="解锁信息不完整","禁止开仓：请完整填写解锁信息",IF(OR(F15="",E15="",N15="",E15<=N15,账户数据!$B$7=""),"",IF(OR(AG15="",AH15="",AI15=""),"禁止开仓：交易预期未填写完整",IF(COUNTIFS(持仓跟踪!$A$2:$A$157,"止损计划",持仓跟踪!$B$2:$B$157,A15,持仓跟踪!$AC$2:$AC$157,"计划有效")=0,"禁止开仓：请先填写止损计划",IF(账户数据!$B$9+F15*(E15-N15)>=账户数据!$B$7,"禁止开仓：风险额度不足",IF(AJ15="周期与交易预期不匹配，请重新确认",IF(账户数据!$B$23="接近锁仓","允许开仓（接近锁仓；周期需复核）","允许开仓（周期需复核）"),IF(账户数据!$B$23="接近锁仓","允许开仓（接近锁仓）","允许开仓")))))))))) -> 已开仓 | H15: 700 | I15: 43542 | J15: 48 | K15: 41.91 | L15: =IF(A15="","",IFERROR(LOOKUP(2,1/((持仓跟踪!$B$2:$B$157=A15)*(持仓跟踪!$X$2:$X$157="执行卖出")*(持仓跟踪!$Z$2:$Z$157<>"")),持仓跟踪!$Z$2:$Z$157),"")) -> 700 | M15: =IF(A15="","",IFERROR(LOOKUP(2,1/((持仓跟踪!$B$2:$B$157=A15)*(持仓跟踪!$X$2:$X$157="执行卖出")*(持仓跟踪!$H$2:$H$157<>"")),持仓跟踪!$H$2:$H$157),"")) -> 43577 | N15: 39 | P15: =IF(A15="","",IFERROR(LOOKUP(2,1/((持仓跟踪!$B$2:$B$157=A15)*(持仓跟踪!$X$2:$X$157="执行卖出")*(持仓跟踪!$AA$2:$AA$157<>"")),持仓跟踪!$AA$2:$AA$157),"")) | U15: =IF(OR(AO15="",J15="",AO15<=0),"",(J15-AO15)/AO15) -> 0.14122682 | V15: =IF(OR(AO15="",N15="",AO15<=0),"",(AO15-N15)/AO15) -> 0.07275321 | W15: =IF(OR(U15="",V15="",V15<=0),"",U15/V15) -> 1.9411765 | X15: =IF(OR(K15="",L15="",AP15=""),"",K15*L15-(E15*H15+IF(AND(AK15<>"",AL15<>""),AK15*AL15,0)+IF(AND(AM15<>"",AN15<>""),AM15*AN15,0))-IF(O15="",0,O15)-IF(P15="",0,P15)) -> -105 | Y15: =IF(OR(X15="",AP15=""),"",IF((E15*H15+IF(AND(AK15<>"",AL15<>""),AK15*AL15,0)+IF(AND(AM15<>"",AN15<>""),AM15*AN15,0))+IF(O15="",0,O15)<=0,"",X15/((E15*H15+IF(AND(AK15<>"",AL15<>""),AK15*AL15,0)+IF(AND(AM15<>"",AN15<>""),AM15*AN15,0))+IF(O15="",0,O15)))) -> -0.0035663338 | Z15: =IF(OR(AE15="",多次统计数据!$B$8=""),"",AE15-多次统计数据!$B$8) -> -0.073497891 | AA15: =IF(OR(I15="",M15="",M15<I15),"",M15-I15) -> 35 | AB15: =IF(OR(A15="",多次统计数据!$B$8="",多次统计数据!$B$6<=0,多次统计数据!$B$6>=1),"",1-POWER(1+多次统计数据!$B$8,-多次统计数据!$B$6/(1-多次统计数据!$B$6))) -> 0.053016657 | AC15: =IF(OR(AB15="",多次统计数据!$B$9=""),"",IF(多次统计数据!$B$9<AB15,"低于上限","达到或超过上限")) -> 低于上限 | AE15: =IF(OR(X15="",C15="",C15<=0),"",X15/C15) -> -0.00094926409 | AG15: 突破冲新高 | AH15: 11～20个交易日 | AJ15: =IF(OR(AG15="",AH15=""),"",IF(OR(AND(AG15="短期博反弹",OR(AH15="1～3个交易日",AH15="4～10个交易日")),AND(AG15="突破冲新高",OR(AH15="4～10个交易日",AH15="11～20个交易日")),AND(AG15="趋势波段",OR(AH15="11～20个交易日",AH15="21～60个交易日",AH15="60个交易日以上"))),"匹配","周期与交易预期不匹配，请重新确认")) -> 匹配 | AO15: =IF(OR(A15="",H15="",H15<=0),"",(E15*H15+IF(AND(AK15<>"",AL15<>""),AK15*AL15,0)+IF(AND(AM15<>"",AN15<>""),AM15*AN15,0))/AP15) -> 42.06 | AP15: =IF(OR(A15="",H15="",H15<=0),"",H15+IF(AL15="",0,AL15)+IF(AN15="",0,AN15)) -> 700 | AQ15: =IF(A15="","",IF(M15<>"",0,IF(OR(H15="",N15=""),"",MAX(E15-MAX(N15,IFERROR(SUMPRODUCT(MAX(((持仓跟踪!$A$2:$A$157="每日跟踪")*(持仓跟踪!$B$2:$B$157=A15))*持仓跟踪!$S$2:$S$157)),0)),0)*H15+IF(OR(AK15="",AL15=""),0,MAX(AK15-MAX(N15,IFERROR(SUMPRODUCT(MAX(((持仓跟踪!$A$2:$A$157="每日跟踪")*(持仓跟踪!$B$2:$B$157=A15))*持仓跟踪!$S$2:$S$157)),0)),0)*AL15)+IF(OR(AM15="",AN15=""),0,MAX(AM15-MAX(N15,IFERROR(SUMPRODUCT(MAX(((持仓跟踪!$A$2:$A$157="每日跟踪")*(持仓跟踪!$B$2:$B$157=A15))*持仓跟踪!$S$2:$S$157)),0)),0)*AN15)))) -> 0 | AR15: =IF(A15="","",IF(OR(E15="",H15=""),"违规：第一批价格或股数缺失",IF(OR(AND(AK15="",AL15<>""),AND(AK15<>"",AL15="")),"违规：第二批价格与股数须成对填写",IF(OR(AND(AM15="",AN15<>""),AND(AM15<>"",AN15="")),"违规：第三批价格与股数须成对填写",IF(AND(OR(AM15<>"",AN15<>""),OR(AK15="",AL15="")),"违规：必须先完成第二批",IF(OR(H15<=0,H15<>INT(H15),MOD(H15,100)<>0,AND(AL15<>"",OR(AL15<=0,AL15<>INT(AL15),MOD(AL15,100)<>0)),AND(AN15<>"",OR(AN15<=0,AN15<>INT(AN15),MOD(AN15,100)<>0))),"违规：股数须为100股整数倍",IF(AND(OR(AL15<>"",AN15<>""),OR(_LockStatus="已锁仓",_LockStatus="解锁信息不完整")),"违规：锁仓期间禁止加仓",IF(AQ15>C15*D15,"违规：超过单笔风险上限",IF(SUM($AQ$2:$AQ$98)>账户数据!$B$7,"违规：超过账户风险上限","通过"))))))))) -> 通过
A16: 15 | B16: 恒瑞医药 | C16: 110507 | D16: 0.02 | E16: 48.86 | F16: =IF(OR(C16="",D16="",E16="",N16="",C16<=0,D16<=0,E16<=N16),"",ROUNDDOWN((C16*D16)/(E16-N16)/100,0)*100) -> 1600 | G16: =IF(A16="","",IF(H16<>"","已开仓",IF(账户数据!$B$23="已锁仓","禁止开仓：连续亏损达到上限",IF(账户数据!$B$23="解锁信息不完整","禁止开仓：请完整填写解锁信息",IF(OR(F16="",E16="",N16="",E16<=N16,账户数据!$B$7=""),"",IF(OR(AG16="",AH16="",AI16=""),"禁止开仓：交易预期未填写完整",IF(COUNTIFS(持仓跟踪!$A$2:$A$157,"止损计划",持仓跟踪!$B$2:$B$157,A16,持仓跟踪!$AC$2:$AC$157,"计划有效")=0,"禁止开仓：请先填写止损计划",IF(账户数据!$B$9+F16*(E16-N16)>=账户数据!$B$7,"禁止开仓：风险额度不足",IF(AJ16="周期与交易预期不匹配，请重新确认",IF(账户数据!$B$23="接近锁仓","允许开仓（接近锁仓；周期需复核）","允许开仓（周期需复核）"),IF(账户数据!$B$23="接近锁仓","允许开仓（接近锁仓）","允许开仓")))))))))) -> 已开仓 | H16: 1600 | I16: 43696 | J16: 50 | K16: =IF(A16="","",IFERROR(LOOKUP(2,1/((持仓跟踪!$B$2:$B$157=A16)*(持仓跟踪!$X$2:$X$157="执行卖出")*(持仓跟踪!$Y$2:$Y$157<>"")),持仓跟踪!$Y$2:$Y$157),"")) -> 58.41 | L16: =IF(A16="","",IFERROR(LOOKUP(2,1/((持仓跟踪!$B$2:$B$157=A16)*(持仓跟踪!$X$2:$X$157="执行卖出")*(持仓跟踪!$Z$2:$Z$157<>"")),持仓跟踪!$Z$2:$Z$157),"")) -> 1600 | M16: =IF(A16="","",IFERROR(LOOKUP(2,1/((持仓跟踪!$B$2:$B$157=A16)*(持仓跟踪!$X$2:$X$157="执行卖出")*(持仓跟踪!$H$2:$H$157<>"")),持仓跟踪!$H$2:$H$157),"")) -> 43798 | N16: 47.5 | P16: =IF(A16="","",IFERROR(LOOKUP(2,1/((持仓跟踪!$B$2:$B$157=A16)*(持仓跟踪!$X$2:$X$157="执行卖出")*(持仓跟踪!$AA$2:$AA$157<>"")),持仓跟踪!$AA$2:$AA$157),"")) | U16: =IF(OR(AO16="",J16="",AO16<=0),"",(J16-AO16)/AO16) -> 0.023331969 | V16: =IF(OR(AO16="",N16="",AO16<=0),"",(AO16-N16)/AO16) -> 0.02783463 | W16: =IF(OR(U16="",V16="",V16<=0),"",U16/V16) -> 0.83823529 | X16: =IF(OR(K16="",L16="",AP16=""),"",K16*L16-(E16*H16+IF(AND(AK16<>"",AL16<>""),AK16*AL16,0)+IF(AND(AM16<>"",AN16<>""),AM16*AN16,0))-IF(O16="",0,O16)-IF(P16="",0,P16)) -> 15280 | Y16: =IF(OR(X16="",AP16=""),"",IF((E16*H16+IF(AND(AK16<>"",AL16<>""),AK16*AL16,0)+IF(AND(AM16<>"",AN16<>""),AM16*AN16,0))+IF(O16="",0,O16)<=0,"",X16/((E16*H16+IF(AND(AK16<>"",AL16<>""),AK16*AL16,0)+IF(AND(AM16<>"",AN16<>""),AM16*AN16,0))+IF(O16="",0,O16)))) -> 0.19545641 | Z16: =IF(OR(AE16="",多次统计数据!$B$8=""),"",AE16-多次统计数据!$B$8) -> 0.065723157 | AA16: =IF(OR(I16="",M16="",M16<I16),"",M16-I16) -> 102 | AB16: =IF(OR(A16="",多次统计数据!$B$8="",多次统计数据!$B$6<=0,多次统计数据!$B$6>=1),"",1-POWER(1+多次统计数据!$B$8,-多次统计数据!$B$6/(1-多次统计数据!$B$6))) -> 0.053016657 | AC16: =IF(OR(AB16="",多次统计数据!$B$9=""),"",IF(多次统计数据!$B$9<AB16,"低于上限","达到或超过上限")) -> 低于上限 | AD16: 4-良好 | AE16: =IF(OR(X16="",C16="",C16<=0),"",X16/C16) -> 0.13827178 | AG16: 突破冲新高 | AH16: 4～10个交易日 | AJ16: =IF(OR(AG16="",AH16=""),"",IF(OR(AND(AG16="短期博反弹",OR(AH16="1～3个交易日",AH16="4～10个交易日")),AND(AG16="突破冲新高",OR(AH16="4～10个交易日",AH16="11～20个交易日")),AND(AG16="趋势波段",OR(AH16="11～20个交易日",AH16="21～60个交易日",AH16="60个交易日以上"))),"匹配","周期与交易预期不匹配，请重新确认")) -> 匹配 | AO16: =IF(OR(A16="",H16="",H16<=0),"",(E16*H16+IF(AND(AK16<>"",AL16<>""),AK16*AL16,0)+IF(AND(AM16<>"",AN16<>""),AM16*AN16,0))/AP16) -> 48.86 | AP16: =IF(OR(A16="",H16="",H16<=0),"",H16+IF(AL16="",0,AL16)+IF(AN16="",0,AN16)) -> 1600 | AQ16: =IF(A16="","",IF(M16<>"",0,IF(OR(H16="",N16=""),"",MAX(E16-MAX(N16,IFERROR(SUMPRODUCT(MAX(((持仓跟踪!$A$2:$A$157="每日跟踪")*(持仓跟踪!$B$2:$B$157=A16))*持仓跟踪!$S$2:$S$157)),0)),0)*H16+IF(OR(AK16="",AL16=""),0,MAX(AK16-MAX(N16,IFERROR(SUMPRODUCT(MAX(((持仓跟踪!$A$2:$A$157="每日跟踪")*(持仓跟踪!$B$2:$B$157=A16))*持仓跟踪!$S$2:$S$157)),0)),0)*AL16)+IF(OR(AM16="",AN16=""),0,MAX(AM16-MAX(N16,IFERROR(SUMPRODUCT(MAX(((持仓跟踪!$A$2:$A$157="每日跟踪")*(持仓跟踪!$B$2:$B$157=A16))*持仓跟踪!$S$2:$S$157)),0)),0)*AN16)))) -> 0 | AR16: =IF(A16="","",IF(OR(E16="",H16=""),"违规：第一批价格或股数缺失",IF(OR(AND(AK16="",AL16<>""),AND(AK16<>"",AL16="")),"违规：第二批价格与股数须成对填写",IF(OR(AND(AM16="",AN16<>""),AND(AM16<>"",AN16="")),"违规：第三批价格与股数须成对填写",IF(AND(OR(AM16<>"",AN16<>""),OR(AK16="",AL16="")),"违规：必须先完成第二批",IF(OR(H16<=0,H16<>INT(H16),MOD(H16,100)<>0,AND(AL16<>"",OR(AL16<=0,AL16<>INT(AL16),MOD(AL16,100)<>0)),AND(AN16<>"",OR(AN16<=0,AN16<>INT(AN16),MOD(AN16,100)<>0))),"违规：股数须为100股整数倍",IF(AND(OR(AL16<>"",AN16<>""),OR(_LockStatus="已锁仓",_LockStatus="解锁信息不完整")),"违规：锁仓期间禁止加仓",IF(AQ16>C16*D16,"违规：超过单笔风险上限",IF(SUM($AQ$2:$AQ$98)>账户数据!$B$7,"违规：超过账户风险上限","通过"))))))))) -> 通过
A17: 16 | B17: 恒瑞医药 | C17: 125787 | D17: 0.02 | E17: 62.26 | F17: =IF(OR(C17="",D17="",E17="",N17="",C17<=0,D17<=0,E17<=N17),"",ROUNDDOWN((C17*D17)/(E17-N17)/100,0)*100) -> 1100 | G17: =IF(A17="","",IF(H17<>"","已开仓",IF(账户数据!$B$23="已锁仓","禁止开仓：连续亏损达到上限",IF(账户数据!$B$23="解锁信息不完整","禁止开仓：请完整填写解锁信息",IF(OR(F17="",E17="",N17="",E17<=N17,账户数据!$B$7=""),"",IF(OR(AG17="",AH17="",AI17=""),"禁止开仓：交易预期未填写完整",IF(COUNTIFS(持仓跟踪!$A$2:$A$157,"止损计划",持仓跟踪!$B$2:$B$157,A17,持仓跟踪!$AC$2:$AC$157,"计划有效")=0,"禁止开仓：请先填写止损计划",IF(账户数据!$B$9+F17*(E17-N17)>=账户数据!$B$7,"禁止开仓：风险额度不足",IF(AJ17="周期与交易预期不匹配，请重新确认",IF(账户数据!$B$23="接近锁仓","允许开仓（接近锁仓；周期需复核）","允许开仓（周期需复核）"),IF(账户数据!$B$23="接近锁仓","允许开仓（接近锁仓）","允许开仓")))))))))) -> 已开仓 | H17: 1100 | I17: 43874 | J17: 70 | K17: =IF(A17="","",IFERROR(LOOKUP(2,1/((持仓跟踪!$B$2:$B$157=A17)*(持仓跟踪!$X$2:$X$157="执行卖出")*(持仓跟踪!$Y$2:$Y$157<>"")),持仓跟踪!$Y$2:$Y$157),"")) -> 58.95 | L17: =IF(A17="","",IFERROR(LOOKUP(2,1/((持仓跟踪!$B$2:$B$157=A17)*(持仓跟踪!$X$2:$X$157="执行卖出")*(持仓跟踪!$Z$2:$Z$157<>"")),持仓跟踪!$Z$2:$Z$157),"")) -> 1100 | M17: =IF(A17="","",IFERROR(LOOKUP(2,1/((持仓跟踪!$B$2:$B$157=A17)*(持仓跟踪!$X$2:$X$157="执行卖出")*(持仓跟踪!$H$2:$H$157<>"")),持仓跟踪!$H$2:$H$157),"")) -> 43887 | N17: 60 | P17: =IF(A17="","",IFERROR(LOOKUP(2,1/((持仓跟踪!$B$2:$B$157=A17)*(持仓跟踪!$X$2:$X$157="执行卖出")*(持仓跟踪!$AA$2:$AA$157<>"")),持仓跟踪!$AA$2:$AA$157),"")) | U17: =IF(OR(AO17="",J17="",AO17<=0),"",(J17-AO17)/AO17) -> 0.12431738 | V17: =IF(OR(AO17="",N17="",AO17<=0),"",(AO17-N17)/AO17) -> 0.03629939 | W17: =IF(OR(U17="",V17="",V17<=0),"",U17/V17) -> 3.4247788 | X17: =IF(OR(K17="",L17="",AP17=""),"",K17*L17-(E17*H17+IF(AND(AK17<>"",AL17<>""),AK17*AL17,0)+IF(AND(AM17<>"",AN17<>""),AM17*AN17,0))-IF(O17="",0,O17)-IF(P17="",0,P17)) -> -3641 | Y17: =IF(OR(X17="",AP17=""),"",IF((E17*H17+IF(AND(AK17<>"",AL17<>""),AK17*AL17,0)+IF(AND(AM17<>"",AN17<>""),AM17*AN17,0))+IF(O17="",0,O17)<=0,"",X17/((E17*H17+IF(AND(AK17<>"",AL17<>""),AK17*AL17,0)+IF(AND(AM17<>"",AN17<>""),AM17*AN17,0))+IF(O17="",0,O17)))) -> -0.05316415 | Z17: =IF(OR(AE17="",多次统计数据!$B$8=""),"",AE17-多次统计数据!$B$8) -> -0.10149438 | AA17: =IF(OR(I17="",M17="",M17<I17),"",M17-I17) -> 13 | AB17: =IF(OR(A17="",多次统计数据!$B$8="",多次统计数据!$B$6<=0,多次统计数据!$B$6>=1),"",1-POWER(1+多次统计数据!$B$8,-多次统计数据!$B$6/(1-多次统计数据!$B$6))) -> 0.053016657 | AC17: =IF(OR(AB17="",多次统计数据!$B$9=""),"",IF(多次统计数据!$B$9<AB17,"低于上限","达到或超过上限")) -> 低于上限 | AD17: 3-一般 | AE17: =IF(OR(X17="",C17="",C17<=0),"",X17/C17) -> -0.028945758 | AG17: 突破冲新高 | AH17: 4～10个交易日 | AJ17: =IF(OR(AG17="",AH17=""),"",IF(OR(AND(AG17="短期博反弹",OR(AH17="1～3个交易日",AH17="4～10个交易日")),AND(AG17="突破冲新高",OR(AH17="4～10个交易日",AH17="11～20个交易日")),AND(AG17="趋势波段",OR(AH17="11～20个交易日",AH17="21～60个交易日",AH17="60个交易日以上"))),"匹配","周期与交易预期不匹配，请重新确认")) -> 匹配 | AO17: =IF(OR(A17="",H17="",H17<=0),"",(E17*H17+IF(AND(AK17<>"",AL17<>""),AK17*AL17,0)+IF(AND(AM17<>"",AN17<>""),AM17*AN17,0))/AP17) -> 62.26 | AP17: =IF(OR(A17="",H17="",H17<=0),"",H17+IF(AL17="",0,AL17)+IF(AN17="",0,AN17)) -> 1100 | AQ17: =IF(A17="","",IF(M17<>"",0,IF(OR(H17="",N17=""),"",MAX(E17-MAX(N17,IFERROR(SUMPRODUCT(MAX(((持仓跟踪!$A$2:$A$157="每日跟踪")*(持仓跟踪!$B$2:$B$157=A17))*持仓跟踪!$S$2:$S$157)),0)),0)*H17+IF(OR(AK17="",AL17=""),0,MAX(AK17-MAX(N17,IFERROR(SUMPRODUCT(MAX(((持仓跟踪!$A$2:$A$157="每日跟踪")*(持仓跟踪!$B$2:$B$157=A17))*持仓跟踪!$S$2:$S$157)),0)),0)*AL17)+IF(OR(AM17="",AN17=""),0,MAX(AM17-MAX(N17,IFERROR(SUMPRODUCT(MAX(((持仓跟踪!$A$2:$A$157="每日跟踪")*(持仓跟踪!$B$2:$B$157=A17))*持仓跟踪!$S$2:$S$157)),0)),0)*AN17)))) -> 0 | AR17: =IF(A17="","",IF(OR(E17="",H17=""),"违规：第一批价格或股数缺失",IF(OR(AND(AK17="",AL17<>""),AND(AK17<>"",AL17="")),"违规：第二批价格与股数须成对填写",IF(OR(AND(AM17="",AN17<>""),AND(AM17<>"",AN17="")),"违规：第三批价格与股数须成对填写",IF(AND(OR(AM17<>"",AN17<>""),OR(AK17="",AL17="")),"违规：必须先完成第二批",IF(OR(H17<=0,H17<>INT(H17),MOD(H17,100)<>0,AND(AL17<>"",OR(AL17<=0,AL17<>INT(AL17),MOD(AL17,100)<>0)),AND(AN17<>"",OR(AN17<=0,AN17<>INT(AN17),MOD(AN17,100)<>0))),"违规：股数须为100股整数倍",IF(AND(OR(AL17<>"",AN17<>""),OR(_LockStatus="已锁仓",_LockStatus="解锁信息不完整")),"违规：锁仓期间禁止加仓",IF(AQ17>C17*D17,"违规：超过单笔风险上限",IF(SUM($AQ$2:$AQ$98)>账户数据!$B$7,"违规：超过账户风险上限","通过"))))))))) -> 通过
A18: 17 | B18: 恒瑞医药 | C18: 122416 | D18: 0.02 | E18: 65.41 | F18: =IF(OR(C18="",D18="",E18="",N18="",C18<=0,D18<=0,E18<=N18),"",ROUNDDOWN((C18*D18)/(E18-N18)/100,0)*100) -> 1200 | G18: =IF(A18="","",IF(H18<>"","已开仓",IF(账户数据!$B$23="已锁仓","禁止开仓：连续亏损达到上限",IF(账户数据!$B$23="解锁信息不完整","禁止开仓：请完整填写解锁信息",IF(OR(F18="",E18="",N18="",E18<=N18,账户数据!$B$7=""),"",IF(OR(AG18="",AH18="",AI18=""),"禁止开仓：交易预期未填写完整",IF(COUNTIFS(持仓跟踪!$A$2:$A$157,"止损计划",持仓跟踪!$B$2:$B$157,A18,持仓跟踪!$AC$2:$AC$157,"计划有效")=0,"禁止开仓：请先填写止损计划",IF(账户数据!$B$9+F18*(E18-N18)>=账户数据!$B$7,"禁止开仓：风险额度不足",IF(AJ18="周期与交易预期不匹配，请重新确认",IF(账户数据!$B$23="接近锁仓","允许开仓（接近锁仓；周期需复核）","允许开仓（周期需复核）"),IF(账户数据!$B$23="接近锁仓","允许开仓（接近锁仓）","允许开仓")))))))))) -> 已开仓 | H18: 1200 | I18: 43928 | J18: 70 | K18: =IF(A18="","",IFERROR(LOOKUP(2,1/((持仓跟踪!$B$2:$B$157=A18)*(持仓跟踪!$X$2:$X$157="执行卖出")*(持仓跟踪!$Y$2:$Y$157<>"")),持仓跟踪!$Y$2:$Y$157),"")) -> 63.61 | L18: =IF(A18="","",IFERROR(LOOKUP(2,1/((持仓跟踪!$B$2:$B$157=A18)*(持仓跟踪!$X$2:$X$157="执行卖出")*(持仓跟踪!$Z$2:$Z$157<>"")),持仓跟踪!$Z$2:$Z$157),"")) -> 1200 | M18: =IF(A18="","",IFERROR(LOOKUP(2,1/((持仓跟踪!$B$2:$B$157=A18)*(持仓跟踪!$X$2:$X$157="执行卖出")*(持仓跟踪!$H$2:$H$157<>"")),持仓跟踪!$H$2:$H$157),"")) -> 43950 | N18: 63.5 | P18: =IF(A18="","",IFERROR(LOOKUP(2,1/((持仓跟踪!$B$2:$B$157=A18)*(持仓跟踪!$X$2:$X$157="执行卖出")*(持仓跟踪!$AA$2:$AA$157<>"")),持仓跟踪!$AA$2:$AA$157),"")) | U18: =IF(OR(AO18="",J18="",AO18<=0),"",(J18-AO18)/AO18) -> 0.070172756 | V18: =IF(OR(AO18="",N18="",AO18<=0),"",(AO18-N18)/AO18) -> 0.029200428 | W18: =IF(OR(U18="",V18="",V18<=0),"",U18/V18) -> 2.4031414 | X18: =IF(OR(K18="",L18="",AP18=""),"",K18*L18-(E18*H18+IF(AND(AK18<>"",AL18<>""),AK18*AL18,0)+IF(AND(AM18<>"",AN18<>""),AM18*AN18,0))-IF(O18="",0,O18)-IF(P18="",0,P18)) -> -2160 | Y18: =IF(OR(X18="",AP18=""),"",IF((E18*H18+IF(AND(AK18<>"",AL18<>""),AK18*AL18,0)+IF(AND(AM18<>"",AN18<>""),AM18*AN18,0))+IF(O18="",0,O18)<=0,"",X18/((E18*H18+IF(AND(AK18<>"",AL18<>""),AK18*AL18,0)+IF(AND(AM18<>"",AN18<>""),AM18*AN18,0))+IF(O18="",0,O18)))) -> -0.027518728 | Z18: =IF(OR(AE18="",多次统计数据!$B$8=""),"",AE18-多次统计数据!$B$8) -> -0.090193379 | AA18: =IF(OR(I18="",M18="",M18<I18),"",M18-I18) -> 22 | AB18: =IF(OR(A18="",多次统计数据!$B$8="",多次统计数据!$B$6<=0,多次统计数据!$B$6>=1),"",1-POWER(1+多次统计数据!$B$8,-多次统计数据!$B$6/(1-多次统计数据!$B$6))) -> 0.053016657 | AC18: =IF(OR(AB18="",多次统计数据!$B$9=""),"",IF(多次统计数据!$B$9<AB18,"低于上限","达到或超过上限")) -> 低于上限 | AE18: =IF(OR(X18="",C18="",C18<=0),"",X18/C18) -> -0.017644752 | AG18: 突破冲新高 | AH18: 4～10个交易日 | AJ18: =IF(OR(AG18="",AH18=""),"",IF(OR(AND(AG18="短期博反弹",OR(AH18="1～3个交易日",AH18="4～10个交易日")),AND(AG18="突破冲新高",OR(AH18="4～10个交易日",AH18="11～20个交易日")),AND(AG18="趋势波段",OR(AH18="11～20个交易日",AH18="21～60个交易日",AH18="60个交易日以上"))),"匹配","周期与交易预期不匹配，请重新确认")) -> 匹配 | AO18: =IF(OR(A18="",H18="",H18<=0),"",(E18*H18+IF(AND(AK18<>"",AL18<>""),AK18*AL18,0)+IF(AND(AM18<>"",AN18<>""),AM18*AN18,0))/AP18) -> 65.41 | AP18: =IF(OR(A18="",H18="",H18<=0),"",H18+IF(AL18="",0,AL18)+IF(AN18="",0,AN18)) -> 1200 | AQ18: =IF(A18="","",IF(M18<>"",0,IF(OR(H18="",N18=""),"",MAX(E18-MAX(N18,IFERROR(SUMPRODUCT(MAX(((持仓跟踪!$A$2:$A$157="每日跟踪")*(持仓跟踪!$B$2:$B$157=A18))*持仓跟踪!$S$2:$S$157)),0)),0)*H18+IF(OR(AK18="",AL18=""),0,MAX(AK18-MAX(N18,IFERROR(SUMPRODUCT(MAX(((持仓跟踪!$A$2:$A$157="每日跟踪")*(持仓跟踪!$B$2:$B$157=A18))*持仓跟踪!$S$2:$S$157)),0)),0)*AL18)+IF(OR(AM18="",AN18=""),0,MAX(AM18-MAX(N18,IFERROR(SUMPRODUCT(MAX(((持仓跟踪!$A$2:$A$157="每日跟踪")*(持仓跟踪!$B$2:$B$157=A18))*持仓跟踪!$S$2:$S$157)),0)),0)*AN18)))) -> 0 | AR18: =IF(A18="","",IF(OR(E18="",H18=""),"违规：第一批价格或股数缺失",IF(OR(AND(AK18="",AL18<>""),AND(AK18<>"",AL18="")),"违规：第二批价格与股数须成对填写",IF(OR(AND(AM18="",AN18<>""),AND(AM18<>"",AN18="")),"违规：第三批价格与股数须成对填写",IF(AND(OR(AM18<>"",AN18<>""),OR(AK18="",AL18="")),"违规：必须先完成第二批",IF(OR(H18<=0,H18<>INT(H18),MOD(H18,100)<>0,AND(AL18<>"",OR(AL18<=0,AL18<>INT(AL18),MOD(AL18,100)<>0)),AND(AN18<>"",OR(AN18<=0,AN18<>INT(AN18),MOD(AN18,100)<>0))),"违规：股数须为100股整数倍",IF(AND(OR(AL18<>"",AN18<>""),OR(_LockStatus="已锁仓",_LockStatus="解锁信息不完整")),"违规：锁仓期间禁止加仓",IF(AQ18>C18*D18,"违规：超过单笔风险上限",IF(SUM($AQ$2:$AQ$98)>账户数据!$B$7,"违规：超过账户风险上限","通过"))))))))) -> 通过
A19: 18 | B19: 恒瑞医药 | C19: 119986 | D19: 0.02 | E19: 69.36 | F19: =IF(OR(C19="",D19="",E19="",N19="",C19<=0,D19<=0,E19<=N19),"",ROUNDDOWN((C19*D19)/(E19-N19)/100,0)*100) -> 1700 | G19: =IF(A19="","",IF(H19<>"","已开仓",IF(账户数据!$B$23="已锁仓","禁止开仓：连续亏损达到上限",IF(账户数据!$B$23="解锁信息不完整","禁止开仓：请完整填写解锁信息",IF(OR(F19="",E19="",N19="",E19<=N19,账户数据!$B$7=""),"",IF(OR(AG19="",AH19="",AI19=""),"禁止开仓：交易预期未填写完整",IF(COUNTIFS(持仓跟踪!$A$2:$A$157,"止损计划",持仓跟踪!$B$2:$B$157,A19,持仓跟踪!$AC$2:$AC$157,"计划有效")=0,"禁止开仓：请先填写止损计划",IF(账户数据!$B$9+F19*(E19-N19)>=账户数据!$B$7,"禁止开仓：风险额度不足",IF(AJ19="周期与交易预期不匹配，请重新确认",IF(账户数据!$B$23="接近锁仓","允许开仓（接近锁仓；周期需复核）","允许开仓（周期需复核）"),IF(账户数据!$B$23="接近锁仓","允许开仓（接近锁仓）","允许开仓")))))))))) -> 已开仓 | H19: 500 | I19: 43992 | J19: 80 | K19: =IF(A19="","",IFERROR(LOOKUP(2,1/((持仓跟踪!$B$2:$B$157=A19)*(持仓跟踪!$X$2:$X$157="执行卖出")*(持仓跟踪!$Y$2:$Y$157<>"")),持仓跟踪!$Y$2:$Y$157),"")) -> 79.21 | L19: =IF(A19="","",IFERROR(LOOKUP(2,1/((持仓跟踪!$B$2:$B$157=A19)*(持仓跟踪!$X$2:$X$157="执行卖出")*(持仓跟踪!$Z$2:$Z$157<>"")),持仓跟踪!$Z$2:$Z$157),"")) -> 500 | M19: =IF(A19="","",IFERROR(LOOKUP(2,1/((持仓跟踪!$B$2:$B$157=A19)*(持仓跟踪!$X$2:$X$157="执行卖出")*(持仓跟踪!$H$2:$H$157<>"")),持仓跟踪!$H$2:$H$157),"")) -> 44028 | N19: 68 | P19: =IF(A19="","",IFERROR(LOOKUP(2,1/((持仓跟踪!$B$2:$B$157=A19)*(持仓跟踪!$X$2:$X$157="执行卖出")*(持仓跟踪!$AA$2:$AA$157<>"")),持仓跟踪!$AA$2:$AA$157),"")) | U19: =IF(OR(AO19="",J19="",AO19<=0),"",(J19-AO19)/AO19) -> 0.15340254 | V19: =IF(OR(AO19="",N19="",AO19<=0),"",(AO19-N19)/AO19) -> 0.019607843 | W19: =IF(OR(U19="",V19="",V19<=0),"",U19/V19) -> 7.8235294 | X19: =IF(OR(K19="",L19="",AP19=""),"",K19*L19-(E19*H19+IF(AND(AK19<>"",AL19<>""),AK19*AL19,0)+IF(AND(AM19<>"",AN19<>""),AM19*AN19,0))-IF(O19="",0,O19)-IF(P19="",0,P19)) -> 4925 | Y19: =IF(OR(X19="",AP19=""),"",IF((E19*H19+IF(AND(AK19<>"",AL19<>""),AK19*AL19,0)+IF(AND(AM19<>"",AN19<>""),AM19*AN19,0))+IF(O19="",0,O19)<=0,"",X19/((E19*H19+IF(AND(AK19<>"",AL19<>""),AK19*AL19,0)+IF(AND(AM19<>"",AN19<>""),AM19*AN19,0))+IF(O19="",0,O19)))) -> 0.14201269 | Z19: =IF(OR(AE19="",多次统计数据!$B$8=""),"",AE19-多次统计数据!$B$8) -> -0.031502172 | AA19: =IF(OR(I19="",M19="",M19<I19),"",M19-I19) -> 36 | AB19: =IF(OR(A19="",多次统计数据!$B$8="",多次统计数据!$B$6<=0,多次统计数据!$B$6>=1),"",1-POWER(1+多次统计数据!$B$8,-多次统计数据!$B$6/(1-多次统计数据!$B$6))) -> 0.053016657 | AC19: =IF(OR(AB19="",多次统计数据!$B$9=""),"",IF(多次统计数据!$B$9<AB19,"低于上限","达到或超过上限")) -> 低于上限 | AD19: 5-优秀 | AE19: =IF(OR(X19="",C19="",C19<=0),"",X19/C19) -> 0.041046455 | AG19: 突破冲新高 | AH19: 11～20个交易日 | AJ19: =IF(OR(AG19="",AH19=""),"",IF(OR(AND(AG19="短期博反弹",OR(AH19="1～3个交易日",AH19="4～10个交易日")),AND(AG19="突破冲新高",OR(AH19="4～10个交易日",AH19="11～20个交易日")),AND(AG19="趋势波段",OR(AH19="11～20个交易日",AH19="21～60个交易日",AH19="60个交易日以上"))),"匹配","周期与交易预期不匹配，请重新确认")) -> 匹配 | AO19: =IF(OR(A19="",H19="",H19<=0),"",(E19*H19+IF(AND(AK19<>"",AL19<>""),AK19*AL19,0)+IF(AND(AM19<>"",AN19<>""),AM19*AN19,0))/AP19) -> 69.36 | AP19: =IF(OR(A19="",H19="",H19<=0),"",H19+IF(AL19="",0,AL19)+IF(AN19="",0,AN19)) -> 500 | AQ19: =IF(A19="","",IF(M19<>"",0,IF(OR(H19="",N19=""),"",MAX(E19-MAX(N19,IFERROR(SUMPRODUCT(MAX(((持仓跟踪!$A$2:$A$157="每日跟踪")*(持仓跟踪!$B$2:$B$157=A19))*持仓跟踪!$S$2:$S$157)),0)),0)*H19+IF(OR(AK19="",AL19=""),0,MAX(AK19-MAX(N19,IFERROR(SUMPRODUCT(MAX(((持仓跟踪!$A$2:$A$157="每日跟踪")*(持仓跟踪!$B$2:$B$157=A19))*持仓跟踪!$S$2:$S$157)),0)),0)*AL19)+IF(OR(AM19="",AN19=""),0,MAX(AM19-MAX(N19,IFERROR(SUMPRODUCT(MAX(((持仓跟踪!$A$2:$A$157="每日跟踪")*(持仓跟踪!$B$2:$B$157=A19))*持仓跟踪!$S$2:$S$157)),0)),0)*AN19)))) -> 0 | AR19: =IF(A19="","",IF(OR(E19="",H19=""),"违规：第一批价格或股数缺失",IF(OR(AND(AK19="",AL19<>""),AND(AK19<>"",AL19="")),"违规：第二批价格与股数须成对填写",IF(OR(AND(AM19="",AN19<>""),AND(AM19<>"",AN19="")),"违规：第三批价格与股数须成对填写",IF(AND(OR(AM19<>"",AN19<>""),OR(AK19="",AL19="")),"违规：必须先完成第二批",IF(OR(H19<=0,H19<>INT(H19),MOD(H19,100)<>0,AND(AL19<>"",OR(AL19<=0,AL19<>INT(AL19),MOD(AL19,100)<>0)),AND(AN19<>"",OR(AN19<=0,AN19<>INT(AN19),MOD(AN19,100)<>0))),"违规：股数须为100股整数倍",IF(AND(OR(AL19<>"",AN19<>""),OR(_LockStatus="已锁仓",_LockStatus="解锁信息不完整")),"违规：锁仓期间禁止加仓",IF(AQ19>C19*D19,"违规：超过单笔风险上限",IF(SUM($AQ$2:$AQ$98)>账户数据!$B$7,"违规：超过账户风险上限","通过"))))))))) -> 通过
A20: 19 | B20: 恒瑞医药 | C20: 124911 | D20: 0.02 | E20: 92.83 | F20: =IF(OR(C20="",D20="",E20="",N20="",C20<=0,D20<=0,E20<=N20),"",ROUNDDOWN((C20*D20)/(E20-N20)/100,0)*100) -> 300 | G20: =IF(A20="","",IF(H20<>"","已开仓",IF(账户数据!$B$23="已锁仓","禁止开仓：连续亏损达到上限",IF(账户数据!$B$23="解锁信息不完整","禁止开仓：请完整填写解锁信息",IF(OR(F20="",E20="",N20="",E20<=N20,账户数据!$B$7=""),"",IF(OR(AG20="",AH20="",AI20=""),"禁止开仓：交易预期未填写完整",IF(COUNTIFS(持仓跟踪!$A$2:$A$157,"止损计划",持仓跟踪!$B$2:$B$157,A20,持仓跟踪!$AC$2:$AC$157,"计划有效")=0,"禁止开仓：请先填写止损计划",IF(账户数据!$B$9+F20*(E20-N20)>=账户数据!$B$7,"禁止开仓：风险额度不足",IF(AJ20="周期与交易预期不匹配，请重新确认",IF(账户数据!$B$23="接近锁仓","允许开仓（接近锁仓；周期需复核）","允许开仓（周期需复核）"),IF(账户数据!$B$23="接近锁仓","允许开仓（接近锁仓）","允许开仓")))))))))) -> 已开仓 | H20: 300 | I20: 44195 | J20: 100 | K20: =IF(A20="","",IFERROR(LOOKUP(2,1/((持仓跟踪!$B$2:$B$157=A20)*(持仓跟踪!$X$2:$X$157="执行卖出")*(持仓跟踪!$Y$2:$Y$157<>"")),持仓跟踪!$Y$2:$Y$157),"")) -> 85.38 | L20: =IF(A20="","",IFERROR(LOOKUP(2,1/((持仓跟踪!$B$2:$B$157=A20)*(持仓跟踪!$X$2:$X$157="执行卖出")*(持仓跟踪!$Z$2:$Z$157<>"")),持仓跟踪!$Z$2:$Z$157),"")) -> 300 | M20: =IF(A20="","",IFERROR(LOOKUP(2,1/((持仓跟踪!$B$2:$B$157=A20)*(持仓跟踪!$X$2:$X$157="执行卖出")*(持仓跟踪!$H$2:$H$157<>"")),持仓跟踪!$H$2:$H$157),"")) -> 44225 | N20: 86 | P20: =IF(A20="","",IFERROR(LOOKUP(2,1/((持仓跟踪!$B$2:$B$157=A20)*(持仓跟踪!$X$2:$X$157="执行卖出")*(持仓跟踪!$AA$2:$AA$157<>"")),持仓跟踪!$AA$2:$AA$157),"")) | U20: =IF(OR(AO20="",J20="",AO20<=0),"",(J20-AO20)/AO20) -> 0.077237962 | V20: =IF(OR(AO20="",N20="",AO20<=0),"",(AO20-N20)/AO20) -> 0.073575353 | W20: =IF(OR(U20="",V20="",V20<=0),"",U20/V20) -> 1.0497804 | X20: =IF(OR(K20="",L20="",AP20=""),"",K20*L20-(E20*H20+IF(AND(AK20<>"",AL20<>""),AK20*AL20,0)+IF(AND(AM20<>"",AN20<>""),AM20*AN20,0))-IF(O20="",0,O20)-IF(P20="",0,P20)) -> -2235 | Y20: =IF(OR(X20="",AP20=""),"",IF((E20*H20+IF(AND(AK20<>"",AL20<>""),AK20*AL20,0)+IF(AND(AM20<>"",AN20<>""),AM20*AN20,0))+IF(O20="",0,O20)<=0,"",X20/((E20*H20+IF(AND(AK20<>"",AL20<>""),AK20*AL20,0)+IF(AND(AM20<>"",AN20<>""),AM20*AN20,0))+IF(O20="",0,O20)))) -> -0.080254228 | Z20: =IF(OR(AE20="",多次统计数据!$B$8=""),"",AE20-多次统计数据!$B$8) -> -0.090441367 | AA20: =IF(OR(I20="",M20="",M20<I20),"",M20-I20) -> 30 | AB20: =IF(OR(A20="",多次统计数据!$B$8="",多次统计数据!$B$6<=0,多次统计数据!$B$6>=1),"",1-POWER(1+多次统计数据!$B$8,-多次统计数据!$B$6/(1-多次统计数据!$B$6))) -> 0.053016657 | AC20: =IF(OR(AB20="",多次统计数据!$B$9=""),"",IF(多次统计数据!$B$9<AB20,"低于上限","达到或超过上限")) -> 低于上限 | AE20: =IF(OR(X20="",C20="",C20<=0),"",X20/C20) -> -0.01789274 | AG20: 突破冲新高 | AH20: 4～10个交易日 | AJ20: =IF(OR(AG20="",AH20=""),"",IF(OR(AND(AG20="短期博反弹",OR(AH20="1～3个交易日",AH20="4～10个交易日")),AND(AG20="突破冲新高",OR(AH20="4～10个交易日",AH20="11～20个交易日")),AND(AG20="趋势波段",OR(AH20="11～20个交易日",AH20="21～60个交易日",AH20="60个交易日以上"))),"匹配","周期与交易预期不匹配，请重新确认")) -> 匹配 | AO20: =IF(OR(A20="",H20="",H20<=0),"",(E20*H20+IF(AND(AK20<>"",AL20<>""),AK20*AL20,0)+IF(AND(AM20<>"",AN20<>""),AM20*AN20,0))/AP20) -> 92.83 | AP20: =IF(OR(A20="",H20="",H20<=0),"",H20+IF(AL20="",0,AL20)+IF(AN20="",0,AN20)) -> 300 | AQ20: =IF(A20="","",IF(M20<>"",0,IF(OR(H20="",N20=""),"",MAX(E20-MAX(N20,IFERROR(SUMPRODUCT(MAX(((持仓跟踪!$A$2:$A$157="每日跟踪")*(持仓跟踪!$B$2:$B$157=A20))*持仓跟踪!$S$2:$S$157)),0)),0)*H20+IF(OR(AK20="",AL20=""),0,MAX(AK20-MAX(N20,IFERROR(SUMPRODUCT(MAX(((持仓跟踪!$A$2:$A$157="每日跟踪")*(持仓跟踪!$B$2:$B$157=A20))*持仓跟踪!$S$2:$S$157)),0)),0)*AL20)+IF(OR(AM20="",AN20=""),0,MAX(AM20-MAX(N20,IFERROR(SUMPRODUCT(MAX(((持仓跟踪!$A$2:$A$157="每日跟踪")*(持仓跟踪!$B$2:$B$157=A20))*持仓跟踪!$S$2:$S$157)),0)),0)*AN20)))) -> 0 | AR20: =IF(A20="","",IF(OR(E20="",H20=""),"违规：第一批价格或股数缺失",IF(OR(AND(AK20="",AL20<>""),AND(AK20<>"",AL20="")),"违规：第二批价格与股数须成对填写",IF(OR(AND(AM20="",AN20<>""),AND(AM20<>"",AN20="")),"违规：第三批价格与股数须成对填写",IF(AND(OR(AM20<>"",AN20<>""),OR(AK20="",AL20="")),"违规：必须先完成第二批",IF(OR(H20<=0,H20<>INT(H20),MOD(H20,100)<>0,AND(AL20<>"",OR(AL20<=0,AL20<>INT(AL20),MOD(AL20,100)<>0)),AND(AN20<>"",OR(AN20<=0,AN20<>INT(AN20),MOD(AN20,100)<>0))),"违规：股数须为100股整数倍",IF(AND(OR(AL20<>"",AN20<>""),OR(_LockStatus="已锁仓",_LockStatus="解锁信息不完整")),"违规：锁仓期间禁止加仓",IF(AQ20>C20*D20,"违规：超过单笔风险上限",IF(SUM($AQ$2:$AQ$98)>账户数据!$B$7,"违规：超过账户风险上限","通过"))))))))) -> 通过
A21: 20 | B21: 恒瑞医药 | C21: 122676 | D21: 0.02 | E21: 52.45 | F21: =IF(OR(C21="",D21="",E21="",N21="",C21<=0,D21<=0,E21<=N21),"",ROUNDDOWN((C21*D21)/(E21-N21)/100,0)*100) -> 1000 | G21: =IF(A21="","",IF(H21<>"","已开仓",IF(账户数据!$B$23="已锁仓","禁止开仓：连续亏损达到上限",IF(账户数据!$B$23="解锁信息不完整","禁止开仓：请完整填写解锁信息",IF(OR(F21="",E21="",N21="",E21<=N21,账户数据!$B$7=""),"",IF(OR(AG21="",AH21="",AI21=""),"禁止开仓：交易预期未填写完整",IF(COUNTIFS(持仓跟踪!$A$2:$A$157,"止损计划",持仓跟踪!$B$2:$B$157,A21,持仓跟踪!$AC$2:$AC$157,"计划有效")=0,"禁止开仓：请先填写止损计划",IF(账户数据!$B$9+F21*(E21-N21)>=账户数据!$B$7,"禁止开仓：风险额度不足",IF(AJ21="周期与交易预期不匹配，请重新确认",IF(账户数据!$B$23="接近锁仓","允许开仓（接近锁仓；周期需复核）","允许开仓（周期需复核）"),IF(账户数据!$B$23="接近锁仓","允许开仓（接近锁仓）","允许开仓")))))))))) -> 已开仓 | H21: 1000 | I21: 44501 | J21: 58 | K21: =IF(A21="","",IFERROR(LOOKUP(2,1/((持仓跟踪!$B$2:$B$157=A21)*(持仓跟踪!$X$2:$X$157="执行卖出")*(持仓跟踪!$Y$2:$Y$157<>"")),持仓跟踪!$Y$2:$Y$157),"")) -> 49.25 | L21: =IF(A21="","",IFERROR(LOOKUP(2,1/((持仓跟踪!$B$2:$B$157=A21)*(持仓跟踪!$X$2:$X$157="执行卖出")*(持仓跟踪!$Z$2:$Z$157<>"")),持仓跟踪!$Z$2:$Z$157),"")) -> 1000 | M21: =IF(A21="","",IFERROR(LOOKUP(2,1/((持仓跟踪!$B$2:$B$157=A21)*(持仓跟踪!$X$2:$X$157="执行卖出")*(持仓跟踪!$H$2:$H$157<>"")),持仓跟踪!$H$2:$H$157),"")) -> 44530 | N21: 50 | P21: =IF(A21="","",IFERROR(LOOKUP(2,1/((持仓跟踪!$B$2:$B$157=A21)*(持仓跟踪!$X$2:$X$157="执行卖出")*(持仓跟踪!$AA$2:$AA$157<>"")),持仓跟踪!$AA$2:$AA$157),"")) | U21: =IF(OR(AO21="",J21="",AO21<=0),"",(J21-AO21)/AO21) -> 0.10581506 | V21: =IF(OR(AO21="",N21="",AO21<=0),"",(AO21-N21)/AO21) -> 0.046711153 | W21: =IF(OR(U21="",V21="",V21<=0),"",U21/V21) -> 2.2653061 | X21: =IF(OR(K21="",L21="",AP21=""),"",K21*L21-(E21*H21+IF(AND(AK21<>"",AL21<>""),AK21*AL21,0)+IF(AND(AM21<>"",AN21<>""),AM21*AN21,0))-IF(O21="",0,O21)-IF(P21="",0,P21)) -> -3200 | Y21: =IF(OR(X21="",AP21=""),"",IF((E21*H21+IF(AND(AK21<>"",AL21<>""),AK21*AL21,0)+IF(AND(AM21<>"",AN21<>""),AM21*AN21,0))+IF(O21="",0,O21)<=0,"",X21/((E21*H21+IF(AND(AK21<>"",AL21<>""),AK21*AL21,0)+IF(AND(AM21<>"",AN21<>""),AM21*AN21,0))+IF(O21="",0,O21)))) -> -0.061010486 | Z21: =IF(OR(AE21="",多次统计数据!$B$8=""),"",AE21-多次统计数据!$B$8) -> -0.098633599 | AA21: =IF(OR(I21="",M21="",M21<I21),"",M21-I21) -> 29 | AB21: =IF(OR(A21="",多次统计数据!$B$8="",多次统计数据!$B$6<=0,多次统计数据!$B$6>=1),"",1-POWER(1+多次统计数据!$B$8,-多次统计数据!$B$6/(1-多次统计数据!$B$6))) -> 0.053016657 | AC21: =IF(OR(AB21="",多次统计数据!$B$9=""),"",IF(多次统计数据!$B$9<AB21,"低于上限","达到或超过上限")) -> 低于上限 | AE21: =IF(OR(X21="",C21="",C21<=0),"",X21/C21) -> -0.026084972 | AG21: 短期博反弹 | AH21: 4～10个交易日 | AJ21: =IF(OR(AG21="",AH21=""),"",IF(OR(AND(AG21="短期博反弹",OR(AH21="1～3个交易日",AH21="4～10个交易日")),AND(AG21="突破冲新高",OR(AH21="4～10个交易日",AH21="11～20个交易日")),AND(AG21="趋势波段",OR(AH21="11～20个交易日",AH21="21～60个交易日",AH21="60个交易日以上"))),"匹配","周期与交易预期不匹配，请重新确认")) -> 匹配 | AO21: =IF(OR(A21="",H21="",H21<=0),"",(E21*H21+IF(AND(AK21<>"",AL21<>""),AK21*AL21,0)+IF(AND(AM21<>"",AN21<>""),AM21*AN21,0))/AP21) -> 52.45 | AP21: =IF(OR(A21="",H21="",H21<=0),"",H21+IF(AL21="",0,AL21)+IF(AN21="",0,AN21)) -> 1000 | AQ21: =IF(A21="","",IF(M21<>"",0,IF(OR(H21="",N21=""),"",MAX(E21-MAX(N21,IFERROR(SUMPRODUCT(MAX(((持仓跟踪!$A$2:$A$157="每日跟踪")*(持仓跟踪!$B$2:$B$157=A21))*持仓跟踪!$S$2:$S$157)),0)),0)*H21+IF(OR(AK21="",AL21=""),0,MAX(AK21-MAX(N21,IFERROR(SUMPRODUCT(MAX(((持仓跟踪!$A$2:$A$157="每日跟踪")*(持仓跟踪!$B$2:$B$157=A21))*持仓跟踪!$S$2:$S$157)),0)),0)*AL21)+IF(OR(AM21="",AN21=""),0,MAX(AM21-MAX(N21,IFERROR(SUMPRODUCT(MAX(((持仓跟踪!$A$2:$A$157="每日跟踪")*(持仓跟踪!$B$2:$B$157=A21))*持仓跟踪!$S$2:$S$157)),0)),0)*AN21)))) -> 0 | AR21: =IF(A21="","",IF(OR(E21="",H21=""),"违规：第一批价格或股数缺失",IF(OR(AND(AK21="",AL21<>""),AND(AK21<>"",AL21="")),"违规：第二批价格与股数须成对填写",IF(OR(AND(AM21="",AN21<>""),AND(AM21<>"",AN21="")),"违规：第三批价格与股数须成对填写",IF(AND(OR(AM21<>"",AN21<>""),OR(AK21="",AL21="")),"违规：必须先完成第二批",IF(OR(H21<=0,H21<>INT(H21),MOD(H21,100)<>0,AND(AL21<>"",OR(AL21<=0,AL21<>INT(AL21),MOD(AL21,100)<>0)),AND(AN21<>"",OR(AN21<=0,AN21<>INT(AN21),MOD(AN21,100)<>0))),"违规：股数须为100股整数倍",IF(AND(OR(AL21<>"",AN21<>""),OR(_LockStatus="已锁仓",_LockStatus="解锁信息不完整")),"违规：锁仓期间禁止加仓",IF(AQ21>C21*D21,"违规：超过单笔风险上限",IF(SUM($AQ$2:$AQ$98)>账户数据!$B$7,"违规：超过账户风险上限","通过"))))))))) -> 通过
A22: 21 | B22: 恒瑞医药 | C22: 119476 | D22: 0.02 | E22: 36.17 | F22: =IF(OR(C22="",D22="",E22="",N22="",C22<=0,D22<=0,E22<=N22),"",ROUNDDOWN((C22*D22)/(E22-N22)/100,0)*100) -> 2000 | G22: =IF(A22="","",IF(H22<>"","已开仓",IF(账户数据!$B$23="已锁仓","禁止开仓：连续亏损达到上限",IF(账户数据!$B$23="解锁信息不完整","禁止开仓：请完整填写解锁信息",IF(OR(F22="",E22="",N22="",E22<=N22,账户数据!$B$7=""),"",IF(OR(AG22="",AH22="",AI22=""),"禁止开仓：交易预期未填写完整",IF(COUNTIFS(持仓跟踪!$A$2:$A$157,"止损计划",持仓跟踪!$B$2:$B$157,A22,持仓跟踪!$AC$2:$AC$157,"计划有效")=0,"禁止开仓：请先填写止损计划",IF(账户数据!$B$9+F22*(E22-N22)>=账户数据!$B$7,"禁止开仓：风险额度不足",IF(AJ22="周期与交易预期不匹配，请重新确认",IF(账户数据!$B$23="接近锁仓","允许开仓（接近锁仓；周期需复核）","允许开仓（周期需复核）"),IF(账户数据!$B$23="接近锁仓","允许开仓（接近锁仓）","允许开仓")))))))))) -> 已开仓 | H22: 2000 | I22: 44743 | J22: 40 | K22: =IF(A22="","",IFERROR(LOOKUP(2,1/((持仓跟踪!$B$2:$B$157=A22)*(持仓跟踪!$X$2:$X$157="执行卖出")*(持仓跟踪!$Y$2:$Y$157<>"")),持仓跟踪!$Y$2:$Y$157),"")) -> 37.19 | L22: =IF(A22="","",IFERROR(LOOKUP(2,1/((持仓跟踪!$B$2:$B$157=A22)*(持仓跟踪!$X$2:$X$157="执行卖出")*(持仓跟踪!$Z$2:$Z$157<>"")),持仓跟踪!$Z$2:$Z$157),"")) -> 2000 | M22: =IF(A22="","",IFERROR(LOOKUP(2,1/((持仓跟踪!$B$2:$B$157=A22)*(持仓跟踪!$X$2:$X$157="执行卖出")*(持仓跟踪!$H$2:$H$157<>"")),持仓跟踪!$H$2:$H$157),"")) -> 44760 | N22: 35 | P22: =IF(A22="","",IFERROR(LOOKUP(2,1/((持仓跟踪!$B$2:$B$157=A22)*(持仓跟踪!$X$2:$X$157="执行卖出")*(持仓跟踪!$AA$2:$AA$157<>"")),持仓跟踪!$AA$2:$AA$157),"")) | U22: =IF(OR(AO22="",J22="",AO22<=0),"",(J22-AO22)/AO22) -> 0.10588886 | V22: =IF(OR(AO22="",N22="",AO22<=0),"",(AO22-N22)/AO22) -> 0.032347249 | W22: =IF(OR(U22="",V22="",V22<=0),"",U22/V22) -> 3.2735043 | X22: =IF(OR(K22="",L22="",AP22=""),"",K22*L22-(E22*H22+IF(AND(AK22<>"",AL22<>""),AK22*AL22,0)+IF(AND(AM22<>"",AN22<>""),AM22*AN22,0))-IF(O22="",0,O22)-IF(P22="",0,P22)) -> 2040 | Y22: =IF(OR(X22="",AP22=""),"",IF((E22*H22+IF(AND(AK22<>"",AL22<>""),AK22*AL22,0)+IF(AND(AM22<>"",AN22<>""),AM22*AN22,0))+IF(O22="",0,O22)<=0,"",X22/((E22*H22+IF(AND(AK22<>"",AL22<>""),AK22*AL22,0)+IF(AND(AM22<>"",AN22<>""),AM22*AN22,0))+IF(O22="",0,O22)))) -> 0.028200166 | Z22: =IF(OR(AE22="",多次统计数据!$B$8=""),"",AE22-多次统计数据!$B$8) -> -0.055474068 | AA22: =IF(OR(I22="",M22="",M22<I22),"",M22-I22) -> 17 | AB22: =IF(OR(A22="",多次统计数据!$B$8="",多次统计数据!$B$6<=0,多次统计数据!$B$6>=1),"",1-POWER(1+多次统计数据!$B$8,-多次统计数据!$B$6/(1-多次统计数据!$B$6))) -> 0.053016657 | AC22: =IF(OR(AB22="",多次统计数据!$B$9=""),"",IF(多次统计数据!$B$9<AB22,"低于上限","达到或超过上限")) -> 低于上限 | AD22: 4-良好 | AE22: =IF(OR(X22="",C22="",C22<=0),"",X22/C22) -> 0.017074559 | AG22: 短期博反弹 | AH22: 4～10个交易日 | AJ22: =IF(OR(AG22="",AH22=""),"",IF(OR(AND(AG22="短期博反弹",OR(AH22="1～3个交易日",AH22="4～10个交易日")),AND(AG22="突破冲新高",OR(AH22="4～10个交易日",AH22="11～20个交易日")),AND(AG22="趋势波段",OR(AH22="11～20个交易日",AH22="21～60个交易日",AH22="60个交易日以上"))),"匹配","周期与交易预期不匹配，请重新确认")) -> 匹配 | AO22: =IF(OR(A22="",H22="",H22<=0),"",(E22*H22+IF(AND(AK22<>"",AL22<>""),AK22*AL22,0)+IF(AND(AM22<>"",AN22<>""),AM22*AN22,0))/AP22) -> 36.17 | AP22: =IF(OR(A22="",H22="",H22<=0),"",H22+IF(AL22="",0,AL22)+IF(AN22="",0,AN22)) -> 2000 | AQ22: =IF(A22="","",IF(M22<>"",0,IF(OR(H22="",N22=""),"",MAX(E22-MAX(N22,IFERROR(SUMPRODUCT(MAX(((持仓跟踪!$A$2:$A$157="每日跟踪")*(持仓跟踪!$B$2:$B$157=A22))*持仓跟踪!$S$2:$S$157)),0)),0)*H22+IF(OR(AK22="",AL22=""),0,MAX(AK22-MAX(N22,IFERROR(SUMPRODUCT(MAX(((持仓跟踪!$A$2:$A$157="每日跟踪")*(持仓跟踪!$B$2:$B$157=A22))*持仓跟踪!$S$2:$S$157)),0)),0)*AL22)+IF(OR(AM22="",AN22=""),0,MAX(AM22-MAX(N22,IFERROR(SUMPRODUCT(MAX(((持仓跟踪!$A$2:$A$157="每日跟踪")*(持仓跟踪!$B$2:$B$157=A22))*持仓跟踪!$S$2:$S$157)),0)),0)*AN22)))) -> 0 | AR22: =IF(A22="","",IF(OR(E22="",H22=""),"违规：第一批价格或股数缺失",IF(OR(AND(AK22="",AL22<>""),AND(AK22<>"",AL22="")),"违规：第二批价格与股数须成对填写",IF(OR(AND(AM22="",AN22<>""),AND(AM22<>"",AN22="")),"违规：第三批价格与股数须成对填写",IF(AND(OR(AM22<>"",AN22<>""),OR(AK22="",AL22="")),"违规：必须先完成第二批",IF(OR(H22<=0,H22<>INT(H22),MOD(H22,100)<>0,AND(AL22<>"",OR(AL22<=0,AL22<>INT(AL22),MOD(AL22,100)<>0)),AND(AN22<>"",OR(AN22<=0,AN22<>INT(AN22),MOD(AN22,100)<>0))),"违规：股数须为100股整数倍",IF(AND(OR(AL22<>"",AN22<>""),OR(_LockStatus="已锁仓",_LockStatus="解锁信息不完整")),"违规：锁仓期间禁止加仓",IF(AQ22>C22*D22,"违规：超过单笔风险上限",IF(SUM($AQ$2:$AQ$98)>账户数据!$B$7,"违规：超过账户风险上限","通过"))))))))) -> 通过
A23: 22 | B23: 恒瑞医药 | C23: 121516 | D23: 0.02 | E23: 48.37 | F23: =IF(OR(C23="",D23="",E23="",N23="",C23<=0,D23<=0,E23<=N23),"",ROUNDDOWN((C23*D23)/(E23-N23)/100,0)*100) -> 1700 | G23: =IF(A23="","",IF(H23<>"","已开仓",IF(账户数据!$B$23="已锁仓","禁止开仓：连续亏损达到上限",IF(账户数据!$B$23="解锁信息不完整","禁止开仓：请完整填写解锁信息",IF(OR(F23="",E23="",N23="",E23<=N23,账户数据!$B$7=""),"",IF(OR(AG23="",AH23="",AI23=""),"禁止开仓：交易预期未填写完整",IF(COUNTIFS(持仓跟踪!$A$2:$A$157,"止损计划",持仓跟踪!$B$2:$B$157,A23,持仓跟踪!$AC$2:$AC$157,"计划有效")=0,"禁止开仓：请先填写止损计划",IF(账户数据!$B$9+F23*(E23-N23)>=账户数据!$B$7,"禁止开仓：风险额度不足",IF(AJ23="周期与交易预期不匹配，请重新确认",IF(账户数据!$B$23="接近锁仓","允许开仓（接近锁仓；周期需复核）","允许开仓（周期需复核）"),IF(账户数据!$B$23="接近锁仓","允许开仓（接近锁仓）","允许开仓")))))))))) -> 已开仓 | H23: 1700 | I23: 45065 | J23: 50 | K23: =IF(A23="","",IFERROR(LOOKUP(2,1/((持仓跟踪!$B$2:$B$157=A23)*(持仓跟踪!$X$2:$X$157="执行卖出")*(持仓跟踪!$Y$2:$Y$157<>"")),持仓跟踪!$Y$2:$Y$157),"")) -> 44.79 | L23: 1700 | M23: =IF(A23="","",IFERROR(LOOKUP(2,1/((持仓跟踪!$B$2:$B$157=A23)*(持仓跟踪!$X$2:$X$157="执行卖出")*(持仓跟踪!$H$2:$H$157<>"")),持仓跟踪!$H$2:$H$157),"")) -> 45077 | N23: 47 | P23: =IF(A23="","",IFERROR(LOOKUP(2,1/((持仓跟踪!$B$2:$B$157=A23)*(持仓跟踪!$X$2:$X$157="执行卖出")*(持仓跟踪!$AA$2:$AA$157<>"")),持仓跟踪!$AA$2:$AA$157),"")) | U23: =IF(OR(AO23="",J23="",AO23<=0),"",(J23-AO23)/AO23) -> 0.033698573 | V23: =IF(OR(AO23="",N23="",AO23<=0),"",(AO23-N23)/AO23) -> 0.028323341 | W23: =IF(OR(U23="",V23="",V23<=0),"",U23/V23) -> 1.189781 | X23: =IF(OR(K23="",L23="",AP23=""),"",K23*L23-(E23*H23+IF(AND(AK23<>"",AL23<>""),AK23*AL23,0)+IF(AND(AM23<>"",AN23<>""),AM23*AN23,0))-IF(O23="",0,O23)-IF(P23="",0,P23)) -> -6086 | Y23: =IF(OR(X23="",AP23=""),"",IF((E23*H23+IF(AND(AK23<>"",AL23<>""),AK23*AL23,0)+IF(AND(AM23<>"",AN23<>""),AM23*AN23,0))+IF(O23="",0,O23)<=0,"",X23/((E23*H23+IF(AND(AK23<>"",AL23<>""),AK23*AL23,0)+IF(AND(AM23<>"",AN23<>""),AM23*AN23,0))+IF(O23="",0,O23)))) -> -0.074012818 | Z23: =IF(OR(AE23="",多次统计数据!$B$8=""),"",AE23-多次统计数据!$B$8) -> -0.12263257 | AA23: =IF(OR(I23="",M23="",M23<I23),"",M23-I23) -> 12 | AB23: =IF(OR(A23="",多次统计数据!$B$8="",多次统计数据!$B$6<=0,多次统计数据!$B$6>=1),"",1-POWER(1+多次统计数据!$B$8,-多次统计数据!$B$6/(1-多次统计数据!$B$6))) -> 0.053016657 | AC23: =IF(OR(AB23="",多次统计数据!$B$9=""),"",IF(多次统计数据!$B$9<AB23,"低于上限","达到或超过上限")) -> 低于上限 | AD23: 3-一般 | AE23: =IF(OR(X23="",C23="",C23<=0),"",X23/C23) -> -0.05008394 | AG23: 突破冲新高 | AH23: 4～10个交易日 | AJ23: =IF(OR(AG23="",AH23=""),"",IF(OR(AND(AG23="短期博反弹",OR(AH23="1～3个交易日",AH23="4～10个交易日")),AND(AG23="突破冲新高",OR(AH23="4～10个交易日",AH23="11～20个交易日")),AND(AG23="趋势波段",OR(AH23="11～20个交易日",AH23="21～60个交易日",AH23="60个交易日以上"))),"匹配","周期与交易预期不匹配，请重新确认")) -> 匹配 | AO23: =IF(OR(A23="",H23="",H23<=0),"",(E23*H23+IF(AND(AK23<>"",AL23<>""),AK23*AL23,0)+IF(AND(AM23<>"",AN23<>""),AM23*AN23,0))/AP23) -> 48.37 | AP23: =IF(OR(A23="",H23="",H23<=0),"",H23+IF(AL23="",0,AL23)+IF(AN23="",0,AN23)) -> 1700 | AQ23: =IF(A23="","",IF(M23<>"",0,IF(OR(H23="",N23=""),"",MAX(E23-MAX(N23,IFERROR(SUMPRODUCT(MAX(((持仓跟踪!$A$2:$A$157="每日跟踪")*(持仓跟踪!$B$2:$B$157=A23))*持仓跟踪!$S$2:$S$157)),0)),0)*H23+IF(OR(AK23="",AL23=""),0,MAX(AK23-MAX(N23,IFERROR(SUMPRODUCT(MAX(((持仓跟踪!$A$2:$A$157="每日跟踪")*(持仓跟踪!$B$2:$B$157=A23))*持仓跟踪!$S$2:$S$157)),0)),0)*AL23)+IF(OR(AM23="",AN23=""),0,MAX(AM23-MAX(N23,IFERROR(SUMPRODUCT(MAX(((持仓跟踪!$A$2:$A$157="每日跟踪")*(持仓跟踪!$B$2:$B$157=A23))*持仓跟踪!$S$2:$S$157)),0)),0)*AN23)))) -> 0 | AR23: =IF(A23="","",IF(OR(E23="",H23=""),"违规：第一批价格或股数缺失",IF(OR(AND(AK23="",AL23<>""),AND(AK23<>"",AL23="")),"违规：第二批价格与股数须成对填写",IF(OR(AND(AM23="",AN23<>""),AND(AM23<>"",AN23="")),"违规：第三批价格与股数须成对填写",IF(AND(OR(AM23<>"",AN23<>""),OR(AK23="",AL23="")),"违规：必须先完成第二批",IF(OR(H23<=0,H23<>INT(H23),MOD(H23,100)<>0,AND(AL23<>"",OR(AL23<=0,AL23<>INT(AL23),MOD(AL23,100)<>0)),AND(AN23<>"",OR(AN23<=0,AN23<>INT(AN23),MOD(AN23,100)<>0))),"违规：股数须为100股整数倍",IF(AND(OR(AL23<>"",AN23<>""),OR(_LockStatus="已锁仓",_LockStatus="解锁信息不完整")),"违规：锁仓期间禁止加仓",IF(AQ23>C23*D23,"违规：超过单笔风险上限",IF(SUM($AQ$2:$AQ$98)>账户数据!$B$7,"违规：超过账户风险上限","通过"))))))))) -> 通过
A24: 23 | B24: 恒瑞医药 | C24: 115430 | D24: 0.02 | E24: 46.76 | F24: =IF(OR(C24="",D24="",E24="",N24="",C24<=0,D24<=0,E24<=N24),"",ROUNDDOWN((C24*D24)/(E24-N24)/100,0)*100) -> 1300 | G24: =IF(A24="","",IF(H24<>"","已开仓",IF(账户数据!$B$23="已锁仓","禁止开仓：连续亏损达到上限",IF(账户数据!$B$23="解锁信息不完整","禁止开仓：请完整填写解锁信息",IF(OR(F24="",E24="",N24="",E24<=N24,账户数据!$B$7=""),"",IF(OR(AG24="",AH24="",AI24=""),"禁止开仓：交易预期未填写完整",IF(COUNTIFS(持仓跟踪!$A$2:$A$157,"止损计划",持仓跟踪!$B$2:$B$157,A24,持仓跟踪!$AC$2:$AC$157,"计划有效")=0,"禁止开仓：请先填写止损计划",IF(账户数据!$B$9+F24*(E24-N24)>=账户数据!$B$7,"禁止开仓：风险额度不足",IF(AJ24="周期与交易预期不匹配，请重新确认",IF(账户数据!$B$23="接近锁仓","允许开仓（接近锁仓；周期需复核）","允许开仓（周期需复核）"),IF(账户数据!$B$23="接近锁仓","允许开仓（接近锁仓）","允许开仓")))))))))) -> 已开仓 | H24: 1300 | I24: 45110 | J24: 50 | K24: =IF(A24="","",IFERROR(LOOKUP(2,1/((持仓跟踪!$B$2:$B$157=A24)*(持仓跟踪!$X$2:$X$157="执行卖出")*(持仓跟踪!$Y$2:$Y$157<>"")),持仓跟踪!$Y$2:$Y$157),"")) -> 48.59 | L24: =IF(A24="","",IFERROR(LOOKUP(2,1/((持仓跟踪!$B$2:$B$157=A24)*(持仓跟踪!$X$2:$X$157="执行卖出")*(持仓跟踪!$Z$2:$Z$157<>"")),持仓跟踪!$Z$2:$Z$157),"")) -> 1300 | M24: =IF(A24="","",IFERROR(LOOKUP(2,1/((持仓跟踪!$B$2:$B$157=A24)*(持仓跟踪!$X$2:$X$157="执行卖出")*(持仓跟踪!$H$2:$H$157<>"")),持仓跟踪!$H$2:$H$157),"")) -> 45112 | N24: 45 | P24: =IF(A24="","",IFERROR(LOOKUP(2,1/((持仓跟踪!$B$2:$B$157=A24)*(持仓跟踪!$X$2:$X$157="执行卖出")*(持仓跟踪!$AA$2:$AA$157<>"")),持仓跟踪!$AA$2:$AA$157),"")) | U24: =IF(OR(AO24="",J24="",AO24<=0),"",(J24-AO24)/AO24) -> 0.069289991 | V24: =IF(OR(AO24="",N24="",AO24<=0),"",(AO24-N24)/AO24) -> 0.037639008 | W24: =IF(OR(U24="",V24="",V24<=0),"",U24/V24) -> 1.8409091 | X24: =IF(OR(K24="",L24="",AP24=""),"",K24*L24-(E24*H24+IF(AND(AK24<>"",AL24<>""),AK24*AL24,0)+IF(AND(AM24<>"",AN24<>""),AM24*AN24,0))-IF(O24="",0,O24)-IF(P24="",0,P24)) -> 2379 | Y24: =IF(OR(X24="",AP24=""),"",IF((E24*H24+IF(AND(AK24<>"",AL24<>""),AK24*AL24,0)+IF(AND(AM24<>"",AN24<>""),AM24*AN24,0))+IF(O24="",0,O24)<=0,"",X24/((E24*H24+IF(AND(AK24<>"",AL24<>""),AK24*AL24,0)+IF(AND(AM24<>"",AN24<>""),AM24*AN24,0))+IF(O24="",0,O24)))) -> 0.039136014 | Z24: =IF(OR(AE24="",多次统计数据!$B$8=""),"",AE24-多次统计数据!$B$8) -> -0.051938733 | AA24: =IF(OR(I24="",M24="",M24<I24),"",M24-I24) -> 2 | AB24: =IF(OR(A24="",多次统计数据!$B$8="",多次统计数据!$B$6<=0,多次统计数据!$B$6>=1),"",1-POWER(1+多次统计数据!$B$8,-多次统计数据!$B$6/(1-多次统计数据!$B$6))) -> 0.053016657 | AC24: =IF(OR(AB24="",多次统计数据!$B$9=""),"",IF(多次统计数据!$B$9<AB24,"低于上限","达到或超过上限")) -> 低于上限 | AD24: 4-良好 | AE24: =IF(OR(X24="",C24="",C24<=0),"",X24/C24) -> 0.020609893 | AG24: 突破冲新高 | AH24: 4～10个交易日 | AJ24: =IF(OR(AG24="",AH24=""),"",IF(OR(AND(AG24="短期博反弹",OR(AH24="1～3个交易日",AH24="4～10个交易日")),AND(AG24="突破冲新高",OR(AH24="4～10个交易日",AH24="11～20个交易日")),AND(AG24="趋势波段",OR(AH24="11～20个交易日",AH24="21～60个交易日",AH24="60个交易日以上"))),"匹配","周期与交易预期不匹配，请重新确认")) -> 匹配 | AO24: =IF(OR(A24="",H24="",H24<=0),"",(E24*H24+IF(AND(AK24<>"",AL24<>""),AK24*AL24,0)+IF(AND(AM24<>"",AN24<>""),AM24*AN24,0))/AP24) -> 46.76 | AP24: =IF(OR(A24="",H24="",H24<=0),"",H24+IF(AL24="",0,AL24)+IF(AN24="",0,AN24)) -> 1300 | AQ24: =IF(A24="","",IF(M24<>"",0,IF(OR(H24="",N24=""),"",MAX(E24-MAX(N24,IFERROR(SUMPRODUCT(MAX(((持仓跟踪!$A$2:$A$157="每日跟踪")*(持仓跟踪!$B$2:$B$157=A24))*持仓跟踪!$S$2:$S$157)),0)),0)*H24+IF(OR(AK24="",AL24=""),0,MAX(AK24-MAX(N24,IFERROR(SUMPRODUCT(MAX(((持仓跟踪!$A$2:$A$157="每日跟踪")*(持仓跟踪!$B$2:$B$157=A24))*持仓跟踪!$S$2:$S$157)),0)),0)*AL24)+IF(OR(AM24="",AN24=""),0,MAX(AM24-MAX(N24,IFERROR(SUMPRODUCT(MAX(((持仓跟踪!$A$2:$A$157="每日跟踪")*(持仓跟踪!$B$2:$B$157=A24))*持仓跟踪!$S$2:$S$157)),0)),0)*AN24)))) -> 0 | AR24: =IF(A24="","",IF(OR(E24="",H24=""),"违规：第一批价格或股数缺失",IF(OR(AND(AK24="",AL24<>""),AND(AK24<>"",AL24="")),"违规：第二批价格与股数须成对填写",IF(OR(AND(AM24="",AN24<>""),AND(AM24<>"",AN24="")),"违规：第三批价格与股数须成对填写",IF(AND(OR(AM24<>"",AN24<>""),OR(AK24="",AL24="")),"违规：必须先完成第二批",IF(OR(H24<=0,H24<>INT(H24),MOD(H24,100)<>0,AND(AL24<>"",OR(AL24<=0,AL24<>INT(AL24),MOD(AL24,100)<>0)),AND(AN24<>"",OR(AN24<=0,AN24<>INT(AN24),MOD(AN24,100)<>0))),"违规：股数须为100股整数倍",IF(AND(OR(AL24<>"",AN24<>""),OR(_LockStatus="已锁仓",_LockStatus="解锁信息不完整")),"违规：锁仓期间禁止加仓",IF(AQ24>C24*D24,"违规：超过单笔风险上限",IF(SUM($AQ$2:$AQ$98)>账户数据!$B$7,"违规：超过账户风险上限","通过"))))))))) -> 通过
A25: 24 | B25: 恒瑞医药 | C25: 117809 | D25: 0.02 | E25: 46.69 | F25: =IF(OR(C25="",D25="",E25="",N25="",C25<=0,D25<=0,E25<=N25),"",ROUNDDOWN((C25*D25)/(E25-N25)/100,0)*100) -> 1300 | G25: =IF(A25="","",IF(H25<>"","已开仓",IF(账户数据!$B$23="已锁仓","禁止开仓：连续亏损达到上限",IF(账户数据!$B$23="解锁信息不完整","禁止开仓：请完整填写解锁信息",IF(OR(F25="",E25="",N25="",E25<=N25,账户数据!$B$7=""),"",IF(OR(AG25="",AH25="",AI25=""),"禁止开仓：交易预期未填写完整",IF(COUNTIFS(持仓跟踪!$A$2:$A$157,"止损计划",持仓跟踪!$B$2:$B$157,A25,持仓跟踪!$AC$2:$AC$157,"计划有效")=0,"禁止开仓：请先填写止损计划",IF(账户数据!$B$9+F25*(E25-N25)>=账户数据!$B$7,"禁止开仓：风险额度不足",IF(AJ25="周期与交易预期不匹配，请重新确认",IF(账户数据!$B$23="接近锁仓","允许开仓（接近锁仓；周期需复核）","允许开仓（周期需复核）"),IF(账户数据!$B$23="接近锁仓","允许开仓（接近锁仓）","允许开仓")))))))))) -> 已开仓 | H25: 1300 | I25: 45131 | J25: 50 | K25: =IF(A25="","",IFERROR(LOOKUP(2,1/((持仓跟踪!$B$2:$B$157=A25)*(持仓跟踪!$X$2:$X$157="执行卖出")*(持仓跟踪!$Y$2:$Y$157<>"")),持仓跟踪!$Y$2:$Y$157),"")) -> 47.16 | L25: =IF(A25="","",IFERROR(LOOKUP(2,1/((持仓跟踪!$B$2:$B$157=A25)*(持仓跟踪!$X$2:$X$157="执行卖出")*(持仓跟踪!$Z$2:$Z$157<>"")),持仓跟踪!$Z$2:$Z$157),"")) -> 1300 | M25: =IF(A25="","",IFERROR(LOOKUP(2,1/((持仓跟踪!$B$2:$B$157=A25)*(持仓跟踪!$X$2:$X$157="执行卖出")*(持仓跟踪!$H$2:$H$157<>"")),持仓跟踪!$H$2:$H$157),"")) -> 45132 | N25: 45 | P25: =IF(A25="","",IFERROR(LOOKUP(2,1/((持仓跟踪!$B$2:$B$157=A25)*(持仓跟踪!$X$2:$X$157="执行卖出")*(持仓跟踪!$AA$2:$AA$157<>"")),持仓跟踪!$AA$2:$AA$157),"")) | U25: =IF(OR(AO25="",J25="",AO25<=0),"",(J25-AO25)/AO25) -> 0.070893125 | V25: =IF(OR(AO25="",N25="",AO25<=0),"",(AO25-N25)/AO25) -> 0.036196188 | W25: =IF(OR(U25="",V25="",V25<=0),"",U25/V25) -> 1.9585799 | X25: =IF(OR(K25="",L25="",AP25=""),"",K25*L25-(E25*H25+IF(AND(AK25<>"",AL25<>""),AK25*AL25,0)+IF(AND(AM25<>"",AN25<>""),AM25*AN25,0))-IF(O25="",0,O25)-IF(P25="",0,P25)) -> 611 | Y25: =IF(OR(X25="",AP25=""),"",IF((E25*H25+IF(AND(AK25<>"",AL25<>""),AK25*AL25,0)+IF(AND(AM25<>"",AN25<>""),AM25*AN25,0))+IF(O25="",0,O25)<=0,"",X25/((E25*H25+IF(AND(AK25<>"",AL25<>""),AK25*AL25,0)+IF(AND(AM25<>"",AN25<>""),AM25*AN25,0))+IF(O25="",0,O25)))) -> 0.010066395 | Z25: =IF(OR(AE25="",多次统计数据!$B$8=""),"",AE25-多次统计数据!$B$8) -> -0.067362266 | AA25: =IF(OR(I25="",M25="",M25<I25),"",M25-I25) -> 1 | AB25: =IF(OR(A25="",多次统计数据!$B$8="",多次统计数据!$B$6<=0,多次统计数据!$B$6>=1),"",1-POWER(1+多次统计数据!$B$8,-多次统计数据!$B$6/(1-多次统计数据!$B$6))) -> 0.053016657 | AC25: =IF(OR(AB25="",多次统计数据!$B$9=""),"",IF(多次统计数据!$B$9<AB25,"低于上限","达到或超过上限")) -> 低于上限 | AD25: 4-良好 | AE25: =IF(OR(X25="",C25="",C25<=0),"",X25/C25) -> 0.005186361 | AG25: 突破冲新高 | AH25: 4～10个交易日 | AJ25: =IF(OR(AG25="",AH25=""),"",IF(OR(AND(AG25="短期博反弹",OR(AH25="1～3个交易日",AH25="4～10个交易日")),AND(AG25="突破冲新高",OR(AH25="4～10个交易日",AH25="11～20个交易日")),AND(AG25="趋势波段",OR(AH25="11～20个交易日",AH25="21～60个交易日",AH25="60个交易日以上"))),"匹配","周期与交易预期不匹配，请重新确认")) -> 匹配 | AO25: =IF(OR(A25="",H25="",H25<=0),"",(E25*H25+IF(AND(AK25<>"",AL25<>""),AK25*AL25,0)+IF(AND(AM25<>"",AN25<>""),AM25*AN25,0))/AP25) -> 46.69 | AP25: =IF(OR(A25="",H25="",H25<=0),"",H25+IF(AL25="",0,AL25)+IF(AN25="",0,AN25)) -> 1300 | AQ25: =IF(A25="","",IF(M25<>"",0,IF(OR(H25="",N25=""),"",MAX(E25-MAX(N25,IFERROR(SUMPRODUCT(MAX(((持仓跟踪!$A$2:$A$157="每日跟踪")*(持仓跟踪!$B$2:$B$157=A25))*持仓跟踪!$S$2:$S$157)),0)),0)*H25+IF(OR(AK25="",AL25=""),0,MAX(AK25-MAX(N25,IFERROR(SUMPRODUCT(MAX(((持仓跟踪!$A$2:$A$157="每日跟踪")*(持仓跟踪!$B$2:$B$157=A25))*持仓跟踪!$S$2:$S$157)),0)),0)*AL25)+IF(OR(AM25="",AN25=""),0,MAX(AM25-MAX(N25,IFERROR(SUMPRODUCT(MAX(((持仓跟踪!$A$2:$A$157="每日跟踪")*(持仓跟踪!$B$2:$B$157=A25))*持仓跟踪!$S$2:$S$157)),0)),0)*AN25)))) -> 0 | AR25: =IF(A25="","",IF(OR(E25="",H25=""),"违规：第一批价格或股数缺失",IF(OR(AND(AK25="",AL25<>""),AND(AK25<>"",AL25="")),"违规：第二批价格与股数须成对填写",IF(OR(AND(AM25="",AN25<>""),AND(AM25<>"",AN25="")),"违规：第三批价格与股数须成对填写",IF(AND(OR(AM25<>"",AN25<>""),OR(AK25="",AL25="")),"违规：必须先完成第二批",IF(OR(H25<=0,H25<>INT(H25),MOD(H25,100)<>0,AND(AL25<>"",OR(AL25<=0,AL25<>INT(AL25),MOD(AL25,100)<>0)),AND(AN25<>"",OR(AN25<=0,AN25<>INT(AN25),MOD(AN25,100)<>0))),"违规：股数须为100股整数倍",IF(AND(OR(AL25<>"",AN25<>""),OR(_LockStatus="已锁仓",_LockStatus="解锁信息不完整")),"违规：锁仓期间禁止加仓",IF(AQ25>C25*D25,"违规：超过单笔风险上限",IF(SUM($AQ$2:$AQ$98)>账户数据!$B$7,"违规：超过账户风险上限","通过"))))))))) -> 通过
A26: 25 | B26: 恒瑞医药 | C26: 118420 | D26: 0.02 | E26: 48.45 | F26: =IF(OR(C26="",D26="",E26="",N26="",C26<=0,D26<=0,E26<=N26),"",ROUNDDOWN((C26*D26)/(E26-N26)/100,0)*100) -> 1600 | G26: =IF(A26="","",IF(H26<>"","已开仓",IF(账户数据!$B$23="已锁仓","禁止开仓：连续亏损达到上限",IF(账户数据!$B$23="解锁信息不完整","禁止开仓：请完整填写解锁信息",IF(OR(F26="",E26="",N26="",E26<=N26,账户数据!$B$7=""),"",IF(OR(AG26="",AH26="",AI26=""),"禁止开仓：交易预期未填写完整",IF(COUNTIFS(持仓跟踪!$A$2:$A$157,"止损计划",持仓跟踪!$B$2:$B$157,A26,持仓跟踪!$AC$2:$AC$157,"计划有效")=0,"禁止开仓：请先填写止损计划",IF(账户数据!$B$9+F26*(E26-N26)>=账户数据!$B$7,"禁止开仓：风险额度不足",IF(AJ26="周期与交易预期不匹配，请重新确认",IF(账户数据!$B$23="接近锁仓","允许开仓（接近锁仓；周期需复核）","允许开仓（周期需复核）"),IF(账户数据!$B$23="接近锁仓","允许开仓（接近锁仓）","允许开仓")))))))))) -> 已开仓 | H26: 1600 | I26: 45135 | J26: 50 | K26: =IF(A26="","",IFERROR(LOOKUP(2,1/((持仓跟踪!$B$2:$B$157=A26)*(持仓跟踪!$X$2:$X$157="执行卖出")*(持仓跟踪!$Y$2:$Y$157<>"")),持仓跟踪!$Y$2:$Y$157),"")) -> 43.98 | L26: =IF(A26="","",IFERROR(LOOKUP(2,1/((持仓跟踪!$B$2:$B$157=A26)*(持仓跟踪!$X$2:$X$157="执行卖出")*(持仓跟踪!$Z$2:$Z$157<>"")),持仓跟踪!$Z$2:$Z$157),"")) -> 1600 | M26: =IF(A26="","",IFERROR(LOOKUP(2,1/((持仓跟踪!$B$2:$B$157=A26)*(持仓跟踪!$X$2:$X$157="执行卖出")*(持仓跟踪!$H$2:$H$157<>"")),持仓跟踪!$H$2:$H$157),"")) -> 45138 | N26: 47 | P26: =IF(A26="","",IFERROR(LOOKUP(2,1/((持仓跟踪!$B$2:$B$157=A26)*(持仓跟踪!$X$2:$X$157="执行卖出")*(持仓跟踪!$AA$2:$AA$157<>"")),持仓跟踪!$AA$2:$AA$157),"")) | U26: =IF(OR(AO26="",J26="",AO26<=0),"",(J26-AO26)/AO26) -> 0.031991744 | V26: =IF(OR(AO26="",N26="",AO26<=0),"",(AO26-N26)/AO26) -> 0.029927761 | W26: =IF(OR(U26="",V26="",V26<=0),"",U26/V26) -> 1.0689655 | X26: =IF(OR(K26="",L26="",AP26=""),"",K26*L26-(E26*H26+IF(AND(AK26<>"",AL26<>""),AK26*AL26,0)+IF(AND(AM26<>"",AN26<>""),AM26*AN26,0))-IF(O26="",0,O26)-IF(P26="",0,P26)) -> -7152 | Y26: =IF(OR(X26="",AP26=""),"",IF((E26*H26+IF(AND(AK26<>"",AL26<>""),AK26*AL26,0)+IF(AND(AM26<>"",AN26<>""),AM26*AN26,0))+IF(O26="",0,O26)<=0,"",X26/((E26*H26+IF(AND(AK26<>"",AL26<>""),AK26*AL26,0)+IF(AND(AM26<>"",AN26<>""),AM26*AN26,0))+IF(O26="",0,O26)))) -> -0.092260062 | Z26: =IF(OR(AE26="",多次统计数据!$B$8=""),"",AE26-多次统计数据!$B$8) -> -0.13294383 | AA26: =IF(OR(I26="",M26="",M26<I26),"",M26-I26) -> 3 | AB26: =IF(OR(A26="",多次统计数据!$B$8="",多次统计数据!$B$6<=0,多次统计数据!$B$6>=1),"",1-POWER(1+多次统计数据!$B$8,-多次统计数据!$B$6/(1-多次统计数据!$B$6))) -> 0.053016657 | AC26: =IF(OR(AB26="",多次统计数据!$B$9=""),"",IF(多次统计数据!$B$9<AB26,"低于上限","达到或超过上限")) -> 低于上限 | AD26: 3-一般 | AE26: =IF(OR(X26="",C26="",C26<=0),"",X26/C26) -> -0.060395204 | AG26: 突破冲新高 | AH26: 4～10个交易日 | AJ26: =IF(OR(AG26="",AH26=""),"",IF(OR(AND(AG26="短期博反弹",OR(AH26="1～3个交易日",AH26="4～10个交易日")),AND(AG26="突破冲新高",OR(AH26="4～10个交易日",AH26="11～20个交易日")),AND(AG26="趋势波段",OR(AH26="11～20个交易日",AH26="21～60个交易日",AH26="60个交易日以上"))),"匹配","周期与交易预期不匹配，请重新确认")) -> 匹配 | AO26: =IF(OR(A26="",H26="",H26<=0),"",(E26*H26+IF(AND(AK26<>"",AL26<>""),AK26*AL26,0)+IF(AND(AM26<>"",AN26<>""),AM26*AN26,0))/AP26) -> 48.45 | AP26: =IF(OR(A26="",H26="",H26<=0),"",H26+IF(AL26="",0,AL26)+IF(AN26="",0,AN26)) -> 1600 | AQ26: =IF(A26="","",IF(M26<>"",0,IF(OR(H26="",N26=""),"",MAX(E26-MAX(N26,IFERROR(SUMPRODUCT(MAX(((持仓跟踪!$A$2:$A$157="每日跟踪")*(持仓跟踪!$B$2:$B$157=A26))*持仓跟踪!$S$2:$S$157)),0)),0)*H26+IF(OR(AK26="",AL26=""),0,MAX(AK26-MAX(N26,IFERROR(SUMPRODUCT(MAX(((持仓跟踪!$A$2:$A$157="每日跟踪")*(持仓跟踪!$B$2:$B$157=A26))*持仓跟踪!$S$2:$S$157)),0)),0)*AL26)+IF(OR(AM26="",AN26=""),0,MAX(AM26-MAX(N26,IFERROR(SUMPRODUCT(MAX(((持仓跟踪!$A$2:$A$157="每日跟踪")*(持仓跟踪!$B$2:$B$157=A26))*持仓跟踪!$S$2:$S$157)),0)),0)*AN26)))) -> 0 | AR26: =IF(A26="","",IF(OR(E26="",H26=""),"违规：第一批价格或股数缺失",IF(OR(AND(AK26="",AL26<>""),AND(AK26<>"",AL26="")),"违规：第二批价格与股数须成对填写",IF(OR(AND(AM26="",AN26<>""),AND(AM26<>"",AN26="")),"违规：第三批价格与股数须成对填写",IF(AND(OR(AM26<>"",AN26<>""),OR(AK26="",AL26="")),"违规：必须先完成第二批",IF(OR(H26<=0,H26<>INT(H26),MOD(H26,100)<>0,AND(AL26<>"",OR(AL26<=0,AL26<>INT(AL26),MOD(AL26,100)<>0)),AND(AN26<>"",OR(AN26<=0,AN26<>INT(AN26),MOD(AN26,100)<>0))),"违规：股数须为100股整数倍",IF(AND(OR(AL26<>"",AN26<>""),OR(_LockStatus="已锁仓",_LockStatus="解锁信息不完整")),"违规：锁仓期间禁止加仓",IF(AQ26>C26*D26,"违规：超过单笔风险上限",IF(SUM($AQ$2:$AQ$98)>账户数据!$B$7,"违规：超过账户风险上限","通过"))))))))) -> 通过
A27: 26 | B27: 恒瑞医药 | C27: 111268 | D27: 0.02 | E27: 43 | F27: =IF(OR(C27="",D27="",E27="",N27="",C27<=0,D27<=0,E27<=N27),"",ROUNDDOWN((C27*D27)/(E27-N27)/100,0)*100) -> 1400 | G27: =IF(A27="","",IF(H27<>"","已开仓",IF(账户数据!$B$23="已锁仓","禁止开仓：连续亏损达到上限",IF(账户数据!$B$23="解锁信息不完整","禁止开仓：请完整填写解锁信息",IF(OR(F27="",E27="",N27="",E27<=N27,账户数据!$B$7=""),"",IF(OR(AG27="",AH27="",AI27=""),"禁止开仓：交易预期未填写完整",IF(COUNTIFS(持仓跟踪!$A$2:$A$157,"止损计划",持仓跟踪!$B$2:$B$157,A27,持仓跟踪!$AC$2:$AC$157,"计划有效")=0,"禁止开仓：请先填写止损计划",IF(账户数据!$B$9+F27*(E27-N27)>=账户数据!$B$7,"禁止开仓：风险额度不足",IF(AJ27="周期与交易预期不匹配，请重新确认",IF(账户数据!$B$23="接近锁仓","允许开仓（接近锁仓；周期需复核）","允许开仓（周期需复核）"),IF(账户数据!$B$23="接近锁仓","允许开仓（接近锁仓）","允许开仓")))))))))) -> 已开仓 | H27: 1400 | I27: 45184 | J27: 45 | K27: =IF(A27="","",IFERROR(LOOKUP(2,1/((持仓跟踪!$B$2:$B$157=A27)*(持仓跟踪!$X$2:$X$157="执行卖出")*(持仓跟踪!$Y$2:$Y$157<>"")),持仓跟踪!$Y$2:$Y$157),"")) -> 43.63 | L27: =IF(A27="","",IFERROR(LOOKUP(2,1/((持仓跟踪!$B$2:$B$157=A27)*(持仓跟踪!$X$2:$X$157="执行卖出")*(持仓跟踪!$Z$2:$Z$157<>"")),持仓跟踪!$Z$2:$Z$157),"")) -> 1400 | M27: =IF(A27="","",IFERROR(LOOKUP(2,1/((持仓跟踪!$B$2:$B$157=A27)*(持仓跟踪!$X$2:$X$157="执行卖出")*(持仓跟踪!$H$2:$H$157<>"")),持仓跟踪!$H$2:$H$157),"")) -> 45215 | N27: 41.5 | P27: =IF(A27="","",IFERROR(LOOKUP(2,1/((持仓跟踪!$B$2:$B$157=A27)*(持仓跟踪!$X$2:$X$157="执行卖出")*(持仓跟踪!$AA$2:$AA$157<>"")),持仓跟踪!$AA$2:$AA$157),"")) | U27: =IF(OR(AO27="",J27="",AO27<=0),"",(J27-AO27)/AO27) -> 0.046511628 | V27: =IF(OR(AO27="",N27="",AO27<=0),"",(AO27-N27)/AO27) -> 0.034883721 | W27: =IF(OR(U27="",V27="",V27<=0),"",U27/V27) -> 1.3333333 | X27: =IF(OR(K27="",L27="",AP27=""),"",K27*L27-(E27*H27+IF(AND(AK27<>"",AL27<>""),AK27*AL27,0)+IF(AND(AM27<>"",AN27<>""),AM27*AN27,0))-IF(O27="",0,O27)-IF(P27="",0,P27)) -> 882 | Y27: =IF(OR(X27="",AP27=""),"",IF((E27*H27+IF(AND(AK27<>"",AL27<>""),AK27*AL27,0)+IF(AND(AM27<>"",AN27<>""),AM27*AN27,0))+IF(O27="",0,O27)<=0,"",X27/((E27*H27+IF(AND(AK27<>"",AL27<>""),AK27*AL27,0)+IF(AND(AM27<>"",AN27<>""),AM27*AN27,0))+IF(O27="",0,O27)))) -> 0.014651163 | Z27: =IF(OR(AE27="",多次统计数据!$B$8=""),"",AE27-多次统计数据!$B$8) -> -0.06462182 | AA27: =IF(OR(I27="",M27="",M27<I27),"",M27-I27) -> 31 | AB27: =IF(OR(A27="",多次统计数据!$B$8="",多次统计数据!$B$6<=0,多次统计数据!$B$6>=1),"",1-POWER(1+多次统计数据!$B$8,-多次统计数据!$B$6/(1-多次统计数据!$B$6))) -> 0.053016657 | AC27: =IF(OR(AB27="",多次统计数据!$B$9=""),"",IF(多次统计数据!$B$9<AB27,"低于上限","达到或超过上限")) -> 低于上限 | AD27: 3-一般 | AE27: =IF(OR(X27="",C27="",C27<=0),"",X27/C27) -> 0.0079268073 | AG27: 突破冲新高 | AH27: 4～10个交易日 | AJ27: =IF(OR(AG27="",AH27=""),"",IF(OR(AND(AG27="短期博反弹",OR(AH27="1～3个交易日",AH27="4～10个交易日")),AND(AG27="突破冲新高",OR(AH27="4～10个交易日",AH27="11～20个交易日")),AND(AG27="趋势波段",OR(AH27="11～20个交易日",AH27="21～60个交易日",AH27="60个交易日以上"))),"匹配","周期与交易预期不匹配，请重新确认")) -> 匹配 | AO27: =IF(OR(A27="",H27="",H27<=0),"",(E27*H27+IF(AND(AK27<>"",AL27<>""),AK27*AL27,0)+IF(AND(AM27<>"",AN27<>""),AM27*AN27,0))/AP27) -> 43 | AP27: =IF(OR(A27="",H27="",H27<=0),"",H27+IF(AL27="",0,AL27)+IF(AN27="",0,AN27)) -> 1400 | AQ27: =IF(A27="","",IF(M27<>"",0,IF(OR(H27="",N27=""),"",MAX(E27-MAX(N27,IFERROR(SUMPRODUCT(MAX(((持仓跟踪!$A$2:$A$157="每日跟踪")*(持仓跟踪!$B$2:$B$157=A27))*持仓跟踪!$S$2:$S$157)),0)),0)*H27+IF(OR(AK27="",AL27=""),0,MAX(AK27-MAX(N27,IFERROR(SUMPRODUCT(MAX(((持仓跟踪!$A$2:$A$157="每日跟踪")*(持仓跟踪!$B$2:$B$157=A27))*持仓跟踪!$S$2:$S$157)),0)),0)*AL27)+IF(OR(AM27="",AN27=""),0,MAX(AM27-MAX(N27,IFERROR(SUMPRODUCT(MAX(((持仓跟踪!$A$2:$A$157="每日跟踪")*(持仓跟踪!$B$2:$B$157=A27))*持仓跟踪!$S$2:$S$157)),0)),0)*AN27)))) -> 0 | AR27: =IF(A27="","",IF(OR(E27="",H27=""),"违规：第一批价格或股数缺失",IF(OR(AND(AK27="",AL27<>""),AND(AK27<>"",AL27="")),"违规：第二批价格与股数须成对填写",IF(OR(AND(AM27="",AN27<>""),AND(AM27<>"",AN27="")),"违规：第三批价格与股数须成对填写",IF(AND(OR(AM27<>"",AN27<>""),OR(AK27="",AL27="")),"违规：必须先完成第二批",IF(OR(H27<=0,H27<>INT(H27),MOD(H27,100)<>0,AND(AL27<>"",OR(AL27<=0,AL27<>INT(AL27),MOD(AL27,100)<>0)),AND(AN27<>"",OR(AN27<=0,AN27<>INT(AN27),MOD(AN27,100)<>0))),"违规：股数须为100股整数倍",IF(AND(OR(AL27<>"",AN27<>""),OR(_LockStatus="已锁仓",_LockStatus="解锁信息不完整")),"违规：锁仓期间禁止加仓",IF(AQ27>C27*D27,"违规：超过单笔风险上限",IF(SUM($AQ$2:$AQ$98)>账户数据!$B$7,"违规：超过账户风险上限","通过"))))))))) -> 通过
A28: 27 | B28: 恒瑞医药 | C28: 112510 | D28: 0.02 | E28: 46.73 | F28: =IF(OR(C28="",D28="",E28="",N28="",C28<=0,D28<=0,E28<=N28),"",ROUNDDOWN((C28*D28)/(E28-N28)/100,0)*100) -> 3000 | G28: =IF(A28="","",IF(H28<>"","已开仓",IF(账户数据!$B$23="已锁仓","禁止开仓：连续亏损达到上限",IF(账户数据!$B$23="解锁信息不完整","禁止开仓：请完整填写解锁信息",IF(OR(F28="",E28="",N28="",E28<=N28,账户数据!$B$7=""),"",IF(OR(AG28="",AH28="",AI28=""),"禁止开仓：交易预期未填写完整",IF(COUNTIFS(持仓跟踪!$A$2:$A$157,"止损计划",持仓跟踪!$B$2:$B$157,A28,持仓跟踪!$AC$2:$AC$157,"计划有效")=0,"禁止开仓：请先填写止损计划",IF(账户数据!$B$9+F28*(E28-N28)>=账户数据!$B$7,"禁止开仓：风险额度不足",IF(AJ28="周期与交易预期不匹配，请重新确认",IF(账户数据!$B$23="接近锁仓","允许开仓（接近锁仓；周期需复核）","允许开仓（周期需复核）"),IF(账户数据!$B$23="接近锁仓","允许开仓（接近锁仓）","允许开仓")))))))))) -> 已开仓 | H28: 3000 | I28: 45245 | J28: 50 | K28: =IF(A28="","",IFERROR(LOOKUP(2,1/((持仓跟踪!$B$2:$B$157=A28)*(持仓跟踪!$X$2:$X$157="执行卖出")*(持仓跟踪!$Y$2:$Y$157<>"")),持仓跟踪!$Y$2:$Y$157),"")) -> 45.39 | L28: =IF(A28="","",IFERROR(LOOKUP(2,1/((持仓跟踪!$B$2:$B$157=A28)*(持仓跟踪!$X$2:$X$157="执行卖出")*(持仓跟踪!$Z$2:$Z$157<>"")),持仓跟踪!$Z$2:$Z$157),"")) -> 3000 | M28: =IF(A28="","",IFERROR(LOOKUP(2,1/((持仓跟踪!$B$2:$B$157=A28)*(持仓跟踪!$X$2:$X$157="执行卖出")*(持仓跟踪!$H$2:$H$157<>"")),持仓跟踪!$H$2:$H$157),"")) -> 45264 | N28: 46 | P28: =IF(A28="","",IFERROR(LOOKUP(2,1/((持仓跟踪!$B$2:$B$157=A28)*(持仓跟踪!$X$2:$X$157="执行卖出")*(持仓跟踪!$AA$2:$AA$157<>"")),持仓跟踪!$AA$2:$AA$157),"")) | U28: =IF(OR(AO28="",J28="",AO28<=0),"",(J28-AO28)/AO28) -> 0.069976461 | V28: =IF(OR(AO28="",N28="",AO28<=0),"",(AO28-N28)/AO28) -> 0.015621656 | W28: =IF(OR(U28="",V28="",V28<=0),"",U28/V28) -> 4.4794521 | X28: =IF(OR(K28="",L28="",AP28=""),"",K28*L28-(E28*H28+IF(AND(AK28<>"",AL28<>""),AK28*AL28,0)+IF(AND(AM28<>"",AN28<>""),AM28*AN28,0))-IF(O28="",0,O28)-IF(P28="",0,P28)) -> -4020 | Y28: =IF(OR(X28="",AP28=""),"",IF((E28*H28+IF(AND(AK28<>"",AL28<>""),AK28*AL28,0)+IF(AND(AM28<>"",AN28<>""),AM28*AN28,0))+IF(O28="",0,O28)<=0,"",X28/((E28*H28+IF(AND(AK28<>"",AL28<>""),AK28*AL28,0)+IF(AND(AM28<>"",AN28<>""),AM28*AN28,0))+IF(O28="",0,O28)))) -> -0.028675369 | Z28: =IF(OR(AE28="",多次统计数据!$B$8=""),"",AE28-多次统计数据!$B$8) -> -0.10827878 | AA28: =IF(OR(I28="",M28="",M28<I28),"",M28-I28) -> 19 | AB28: =IF(OR(A28="",多次统计数据!$B$8="",多次统计数据!$B$6<=0,多次统计数据!$B$6>=1),"",1-POWER(1+多次统计数据!$B$8,-多次统计数据!$B$6/(1-多次统计数据!$B$6))) -> 0.053016657 | AC28: =IF(OR(AB28="",多次统计数据!$B$9=""),"",IF(多次统计数据!$B$9<AB28,"低于上限","达到或超过上限")) -> 低于上限 | AD28: 3-一般 | AE28: =IF(OR(X28="",C28="",C28<=0),"",X28/C28) -> -0.035730157 | AG28: 突破冲新高 | AH28: 4～10个交易日 | AJ28: =IF(OR(AG28="",AH28=""),"",IF(OR(AND(AG28="短期博反弹",OR(AH28="1～3个交易日",AH28="4～10个交易日")),AND(AG28="突破冲新高",OR(AH28="4～10个交易日",AH28="11～20个交易日")),AND(AG28="趋势波段",OR(AH28="11～20个交易日",AH28="21～60个交易日",AH28="60个交易日以上"))),"匹配","周期与交易预期不匹配，请重新确认")) -> 匹配 | AO28: =IF(OR(A28="",H28="",H28<=0),"",(E28*H28+IF(AND(AK28<>"",AL28<>""),AK28*AL28,0)+IF(AND(AM28<>"",AN28<>""),AM28*AN28,0))/AP28) -> 46.73 | AP28: =IF(OR(A28="",H28="",H28<=0),"",H28+IF(AL28="",0,AL28)+IF(AN28="",0,AN28)) -> 3000 | AQ28: =IF(A28="","",IF(M28<>"",0,IF(OR(H28="",N28=""),"",MAX(E28-MAX(N28,IFERROR(SUMPRODUCT(MAX(((持仓跟踪!$A$2:$A$157="每日跟踪")*(持仓跟踪!$B$2:$B$157=A28))*持仓跟踪!$S$2:$S$157)),0)),0)*H28+IF(OR(AK28="",AL28=""),0,MAX(AK28-MAX(N28,IFERROR(SUMPRODUCT(MAX(((持仓跟踪!$A$2:$A$157="每日跟踪")*(持仓跟踪!$B$2:$B$157=A28))*持仓跟踪!$S$2:$S$157)),0)),0)*AL28)+IF(OR(AM28="",AN28=""),0,MAX(AM28-MAX(N28,IFERROR(SUMPRODUCT(MAX(((持仓跟踪!$A$2:$A$157="每日跟踪")*(持仓跟踪!$B$2:$B$157=A28))*持仓跟踪!$S$2:$S$157)),0)),0)*AN28)))) -> 0 | AR28: =IF(A28="","",IF(OR(E28="",H28=""),"违规：第一批价格或股数缺失",IF(OR(AND(AK28="",AL28<>""),AND(AK28<>"",AL28="")),"违规：第二批价格与股数须成对填写",IF(OR(AND(AM28="",AN28<>""),AND(AM28<>"",AN28="")),"违规：第三批价格与股数须成对填写",IF(AND(OR(AM28<>"",AN28<>""),OR(AK28="",AL28="")),"违规：必须先完成第二批",IF(OR(H28<=0,H28<>INT(H28),MOD(H28,100)<>0,AND(AL28<>"",OR(AL28<=0,AL28<>INT(AL28),MOD(AL28,100)<>0)),AND(AN28<>"",OR(AN28<=0,AN28<>INT(AN28),MOD(AN28,100)<>0))),"违规：股数须为100股整数倍",IF(AND(OR(AL28<>"",AN28<>""),OR(_LockStatus="已锁仓",_LockStatus="解锁信息不完整")),"违规：锁仓期间禁止加仓",IF(AQ28>C28*D28,"违规：超过单笔风险上限",IF(SUM($AQ$2:$AQ$98)>账户数据!$B$7,"违规：超过账户风险上限","通过"))))))))) -> 通过
A29: 28 | B29: 恒瑞医药 | C29: 108130 | D29: 0.02 | E29: 46.56 | F29: =IF(OR(C29="",D29="",E29="",N29="",C29<=0,D29<=0,E29<=N29),"",ROUNDDOWN((C29*D29)/(E29-N29)/100,0)*100) -> 3800 | G29: =IF(A29="","",IF(H29<>"","已开仓",IF(账户数据!$B$23="已锁仓","禁止开仓：连续亏损达到上限",IF(账户数据!$B$23="解锁信息不完整","禁止开仓：请完整填写解锁信息",IF(OR(F29="",E29="",N29="",E29<=N29,账户数据!$B$7=""),"",IF(OR(AG29="",AH29="",AI29=""),"禁止开仓：交易预期未填写完整",IF(COUNTIFS(持仓跟踪!$A$2:$A$157,"止损计划",持仓跟踪!$B$2:$B$157,A29,持仓跟踪!$AC$2:$AC$157,"计划有效")=0,"禁止开仓：请先填写止损计划",IF(账户数据!$B$9+F29*(E29-N29)>=账户数据!$B$7,"禁止开仓：风险额度不足",IF(AJ29="周期与交易预期不匹配，请重新确认",IF(账户数据!$B$23="接近锁仓","允许开仓（接近锁仓；周期需复核）","允许开仓（周期需复核）"),IF(账户数据!$B$23="接近锁仓","允许开仓（接近锁仓）","允许开仓")))))))))) -> 已开仓 | H29: 3800 | I29: 45418 | J29: 50 | K29: =IF(A29="","",IFERROR(LOOKUP(2,1/((持仓跟踪!$B$2:$B$157=A29)*(持仓跟踪!$X$2:$X$157="执行卖出")*(持仓跟踪!$Y$2:$Y$157<>"")),持仓跟踪!$Y$2:$Y$157),"")) -> 44.73 | L29: =IF(A29="","",IFERROR(LOOKUP(2,1/((持仓跟踪!$B$2:$B$157=A29)*(持仓跟踪!$X$2:$X$157="执行卖出")*(持仓跟踪!$Z$2:$Z$157<>"")),持仓跟踪!$Z$2:$Z$157),"")) -> 3800 | M29: =IF(A29="","",IFERROR(LOOKUP(2,1/((持仓跟踪!$B$2:$B$157=A29)*(持仓跟踪!$X$2:$X$157="执行卖出")*(持仓跟踪!$H$2:$H$157<>"")),持仓跟踪!$H$2:$H$157),"")) -> 45060 | N29: 46 | P29: =IF(A29="","",IFERROR(LOOKUP(2,1/((持仓跟踪!$B$2:$B$157=A29)*(持仓跟踪!$X$2:$X$157="执行卖出")*(持仓跟踪!$AA$2:$AA$157<>"")),持仓跟踪!$AA$2:$AA$157),"")) | U29: =IF(OR(AO29="",J29="",AO29<=0),"",(J29-AO29)/AO29) -> 0.073883162 | V29: =IF(OR(AO29="",N29="",AO29<=0),"",(AO29-N29)/AO29) -> 0.012027491 | W29: =IF(OR(U29="",V29="",V29<=0),"",U29/V29) -> 6.1428571 | X29: =IF(OR(K29="",L29="",AP29=""),"",K29*L29-(E29*H29+IF(AND(AK29<>"",AL29<>""),AK29*AL29,0)+IF(AND(AM29<>"",AN29<>""),AM29*AN29,0))-IF(O29="",0,O29)-IF(P29="",0,P29)) -> -6954 | Y29: =IF(OR(X29="",AP29=""),"",IF((E29*H29+IF(AND(AK29<>"",AL29<>""),AK29*AL29,0)+IF(AND(AM29<>"",AN29<>""),AM29*AN29,0))+IF(O29="",0,O29)<=0,"",X29/((E29*H29+IF(AND(AK29<>"",AL29<>""),AK29*AL29,0)+IF(AND(AM29<>"",AN29<>""),AM29*AN29,0))+IF(O29="",0,O29)))) -> -0.039304124 | Z29: =IF(OR(AE29="",多次统计数据!$B$8=""),"",AE29-多次统计数据!$B$8) -> -0.1368601 | AA29: =IF(OR(I29="",M29="",M29<I29),"",M29-I29) | AB29: =IF(OR(A29="",多次统计数据!$B$8="",多次统计数据!$B$6<=0,多次统计数据!$B$6>=1),"",1-POWER(1+多次统计数据!$B$8,-多次统计数据!$B$6/(1-多次统计数据!$B$6))) -> 0.053016657 | AC29: =IF(OR(AB29="",多次统计数据!$B$9=""),"",IF(多次统计数据!$B$9<AB29,"低于上限","达到或超过上限")) -> 低于上限 | AE29: =IF(OR(X29="",C29="",C29<=0),"",X29/C29) -> -0.064311477 | AG29: 突破冲新高 | AH29: 4～10个交易日 | AJ29: =IF(OR(AG29="",AH29=""),"",IF(OR(AND(AG29="短期博反弹",OR(AH29="1～3个交易日",AH29="4～10个交易日")),AND(AG29="突破冲新高",OR(AH29="4～10个交易日",AH29="11～20个交易日")),AND(AG29="趋势波段",OR(AH29="11～20个交易日",AH29="21～60个交易日",AH29="60个交易日以上"))),"匹配","周期与交易预期不匹配，请重新确认")) -> 匹配 | AO29: =IF(OR(A29="",H29="",H29<=0),"",(E29*H29+IF(AND(AK29<>"",AL29<>""),AK29*AL29,0)+IF(AND(AM29<>"",AN29<>""),AM29*AN29,0))/AP29) -> 46.56 | AP29: =IF(OR(A29="",H29="",H29<=0),"",H29+IF(AL29="",0,AL29)+IF(AN29="",0,AN29)) -> 3800 | AQ29: =IF(A29="","",IF(M29<>"",0,IF(OR(H29="",N29=""),"",MAX(E29-MAX(N29,IFERROR(SUMPRODUCT(MAX(((持仓跟踪!$A$2:$A$157="每日跟踪")*(持仓跟踪!$B$2:$B$157=A29))*持仓跟踪!$S$2:$S$157)),0)),0)*H29+IF(OR(AK29="",AL29=""),0,MAX(AK29-MAX(N29,IFERROR(SUMPRODUCT(MAX(((持仓跟踪!$A$2:$A$157="每日跟踪")*(持仓跟踪!$B$2:$B$157=A29))*持仓跟踪!$S$2:$S$157)),0)),0)*AL29)+IF(OR(AM29="",AN29=""),0,MAX(AM29-MAX(N29,IFERROR(SUMPRODUCT(MAX(((持仓跟踪!$A$2:$A$157="每日跟踪")*(持仓跟踪!$B$2:$B$157=A29))*持仓跟踪!$S$2:$S$157)),0)),0)*AN29)))) -> 0 | AR29: =IF(A29="","",IF(OR(E29="",H29=""),"违规：第一批价格或股数缺失",IF(OR(AND(AK29="",AL29<>""),AND(AK29<>"",AL29="")),"违规：第二批价格与股数须成对填写",IF(OR(AND(AM29="",AN29<>""),AND(AM29<>"",AN29="")),"违规：第三批价格与股数须成对填写",IF(AND(OR(AM29<>"",AN29<>""),OR(AK29="",AL29="")),"违规：必须先完成第二批",IF(OR(H29<=0,H29<>INT(H29),MOD(H29,100)<>0,AND(AL29<>"",OR(AL29<=0,AL29<>INT(AL29),MOD(AL29,100)<>0)),AND(AN29<>"",OR(AN29<=0,AN29<>INT(AN29),MOD(AN29,100)<>0))),"违规：股数须为100股整数倍",IF(AND(OR(AL29<>"",AN29<>""),OR(_LockStatus="已锁仓",_LockStatus="解锁信息不完整")),"违规：锁仓期间禁止加仓",IF(AQ29>C29*D29,"违规：超过单笔风险上限",IF(SUM($AQ$2:$AQ$98)>账户数据!$B$7,"违规：超过账户风险上限","通过"))))))))) -> 通过
A30: 29 | B30: 五粮液 | C30: 101176 | D30: 0.02 | E30: 39.99 | F30: =IF(OR(C30="",D30="",E30="",N30="",C30<=0,D30<=0,E30<=N30),"",ROUNDDOWN((C30*D30)/(E30-N30)/100,0)*100) -> 1000 | G30: =IF(A30="","",IF(H30<>"","已开仓",IF(账户数据!$B$23="已锁仓","禁止开仓：连续亏损达到上限",IF(账户数据!$B$23="解锁信息不完整","禁止开仓：请完整填写解锁信息",IF(OR(F30="",E30="",N30="",E30<=N30,账户数据!$B$7=""),"",IF(OR(AG30="",AH30="",AI30=""),"禁止开仓：交易预期未填写完整",IF(COUNTIFS(持仓跟踪!$A$2:$A$157,"止损计划",持仓跟踪!$B$2:$B$157,A30,持仓跟踪!$AC$2:$AC$157,"计划有效")=0,"禁止开仓：请先填写止损计划",IF(账户数据!$B$9+F30*(E30-N30)>=账户数据!$B$7,"禁止开仓：风险额度不足",IF(AJ30="周期与交易预期不匹配，请重新确认",IF(账户数据!$B$23="接近锁仓","允许开仓（接近锁仓；周期需复核）","允许开仓（周期需复核）"),IF(账户数据!$B$23="接近锁仓","允许开仓（接近锁仓）","允许开仓")))))))))) -> 已开仓 | H30: 1000 | I30: 43045 | J30: 45 | K30: =IF(A30="","",IFERROR(LOOKUP(2,1/((持仓跟踪!$B$2:$B$157=A30)*(持仓跟踪!$X$2:$X$157="执行卖出")*(持仓跟踪!$Y$2:$Y$157<>"")),持仓跟踪!$Y$2:$Y$157),"")) -> 41.74 | L30: =IF(A30="","",IFERROR(LOOKUP(2,1/((持仓跟踪!$B$2:$B$157=A30)*(持仓跟踪!$X$2:$X$157="执行卖出")*(持仓跟踪!$Z$2:$Z$157<>"")),持仓跟踪!$Z$2:$Z$157),"")) -> 1000 | M30: =IF(A30="","",IFERROR(LOOKUP(2,1/((持仓跟踪!$B$2:$B$157=A30)*(持仓跟踪!$X$2:$X$157="执行卖出")*(持仓跟踪!$H$2:$H$157<>"")),持仓跟踪!$H$2:$H$157),"")) -> 43061 | N30: 38 | P30: =IF(A30="","",IFERROR(LOOKUP(2,1/((持仓跟踪!$B$2:$B$157=A30)*(持仓跟踪!$X$2:$X$157="执行卖出")*(持仓跟踪!$AA$2:$AA$157<>"")),持仓跟踪!$AA$2:$AA$157),"")) | U30: =IF(OR(AO30="",J30="",AO30<=0),"",(J30-AO30)/AO30) -> 0.12528132 | V30: =IF(OR(AO30="",N30="",AO30<=0),"",(AO30-N30)/AO30) -> 0.049762441 | W30: =IF(OR(U30="",V30="",V30<=0),"",U30/V30) -> 2.5175879 | X30: =IF(OR(K30="",L30="",AP30=""),"",K30*L30-(E30*H30+IF(AND(AK30<>"",AL30<>""),AK30*AL30,0)+IF(AND(AM30<>"",AN30<>""),AM30*AN30,0))-IF(O30="",0,O30)-IF(P30="",0,P30)) -> 1750 | Y30: =IF(OR(X30="",AP30=""),"",IF((E30*H30+IF(AND(AK30<>"",AL30<>""),AK30*AL30,0)+IF(AND(AM30<>"",AN30<>""),AM30*AN30,0))+IF(O30="",0,O30)<=0,"",X30/((E30*H30+IF(AND(AK30<>"",AL30<>""),AK30*AL30,0)+IF(AND(AM30<>"",AN30<>""),AM30*AN30,0))+IF(O30="",0,O30)))) -> 0.04376094 | Z30: =IF(OR(AE30="",多次统计数据!$B$8=""),"",AE30-多次统计数据!$B$8) -> -0.055252035 | AA30: =IF(OR(I30="",M30="",M30<I30),"",M30-I30) -> 16 | AB30: =IF(OR(A30="",多次统计数据!$B$8="",多次统计数据!$B$6<=0,多次统计数据!$B$6>=1),"",1-POWER(1+多次统计数据!$B$8,-多次统计数据!$B$6/(1-多次统计数据!$B$6))) -> 0.053016657 | AC30: =IF(OR(AB30="",多次统计数据!$B$9=""),"",IF(多次统计数据!$B$9<AB30,"低于上限","达到或超过上限")) -> 低于上限 | AD30: 2-较差 | AE30: =IF(OR(X30="",C30="",C30<=0),"",X30/C30) -> 0.017296592 | AF30: 不分析 | AG30: 突破冲新高 | AH30: 4～10个交易日 | AJ30: =IF(OR(AG30="",AH30=""),"",IF(OR(AND(AG30="短期博反弹",OR(AH30="1～3个交易日",AH30="4～10个交易日")),AND(AG30="突破冲新高",OR(AH30="4～10个交易日",AH30="11～20个交易日")),AND(AG30="趋势波段",OR(AH30="11～20个交易日",AH30="21～60个交易日",AH30="60个交易日以上"))),"匹配","周期与交易预期不匹配，请重新确认")) -> 匹配 | AO30: =IF(OR(A30="",H30="",H30<=0),"",(E30*H30+IF(AND(AK30<>"",AL30<>""),AK30*AL30,0)+IF(AND(AM30<>"",AN30<>""),AM30*AN30,0))/AP30) -> 39.99 | AP30: =IF(OR(A30="",H30="",H30<=0),"",H30+IF(AL30="",0,AL30)+IF(AN30="",0,AN30)) -> 1000 | AQ30: =IF(A30="","",IF(M30<>"",0,IF(OR(H30="",N30=""),"",MAX(E30-MAX(N30,IFERROR(SUMPRODUCT(MAX(((持仓跟踪!$A$2:$A$157="每日跟踪")*(持仓跟踪!$B$2:$B$157=A30))*持仓跟踪!$S$2:$S$157)),0)),0)*H30+IF(OR(AK30="",AL30=""),0,MAX(AK30-MAX(N30,IFERROR(SUMPRODUCT(MAX(((持仓跟踪!$A$2:$A$157="每日跟踪")*(持仓跟踪!$B$2:$B$157=A30))*持仓跟踪!$S$2:$S$157)),0)),0)*AL30)+IF(OR(AM30="",AN30=""),0,MAX(AM30-MAX(N30,IFERROR(SUMPRODUCT(MAX(((持仓跟踪!$A$2:$A$157="每日跟踪")*(持仓跟踪!$B$2:$B$157=A30))*持仓跟踪!$S$2:$S$157)),0)),0)*AN30)))) -> 0 | AR30: =IF(A30="","",IF(OR(E30="",H30=""),"违规：第一批价格或股数缺失",IF(OR(AND(AK30="",AL30<>""),AND(AK30<>"",AL30="")),"违规：第二批价格与股数须成对填写",IF(OR(AND(AM30="",AN30<>""),AND(AM30<>"",AN30="")),"违规：第三批价格与股数须成对填写",IF(AND(OR(AM30<>"",AN30<>""),OR(AK30="",AL30="")),"违规：必须先完成第二批",IF(OR(H30<=0,H30<>INT(H30),MOD(H30,100)<>0,AND(AL30<>"",OR(AL30<=0,AL30<>INT(AL30),MOD(AL30,100)<>0)),AND(AN30<>"",OR(AN30<=0,AN30<>INT(AN30),MOD(AN30,100)<>0))),"违规：股数须为100股整数倍",IF(AND(OR(AL30<>"",AN30<>""),OR(_LockStatus="已锁仓",_LockStatus="解锁信息不完整")),"违规：锁仓期间禁止加仓",IF(AQ30>C30*D30,"违规：超过单笔风险上限",IF(SUM($AQ$2:$AQ$98)>账户数据!$B$7,"违规：超过账户风险上限","通过"))))))))) -> 通过
A31: 30 | B31: 五粮液 | C31: 102920 | D31: 0.02 | E31: 38.3 | F31: =IF(OR(C31="",D31="",E31="",N31="",C31<=0,D31<=0,E31<=N31),"",ROUNDDOWN((C31*D31)/(E31-N31)/100,0)*100) -> 600 | G31: =IF(A31="","",IF(H31<>"","已开仓",IF(账户数据!$B$23="已锁仓","禁止开仓：连续亏损达到上限",IF(账户数据!$B$23="解锁信息不完整","禁止开仓：请完整填写解锁信息",IF(OR(F31="",E31="",N31="",E31<=N31,账户数据!$B$7=""),"",IF(OR(AG31="",AH31="",AI31=""),"禁止开仓：交易预期未填写完整",IF(COUNTIFS(持仓跟踪!$A$2:$A$157,"止损计划",持仓跟踪!$B$2:$B$157,A31,持仓跟踪!$AC$2:$AC$157,"计划有效")=0,"禁止开仓：请先填写止损计划",IF(账户数据!$B$9+F31*(E31-N31)>=账户数据!$B$7,"禁止开仓：风险额度不足",IF(AJ31="周期与交易预期不匹配，请重新确认",IF(账户数据!$B$23="接近锁仓","允许开仓（接近锁仓；周期需复核）","允许开仓（周期需复核）"),IF(账户数据!$B$23="接近锁仓","允许开仓（接近锁仓）","允许开仓")))))))))) -> 已开仓 | H31: 600 | I31: 43063 | J31: 40 | K31: =IF(A31="","",IFERROR(LOOKUP(2,1/((持仓跟踪!$B$2:$B$157=A31)*(持仓跟踪!$X$2:$X$157="执行卖出")*(持仓跟踪!$Y$2:$Y$157<>"")),持仓跟踪!$Y$2:$Y$157),"")) -> 44.53 | L31: =IF(A31="","",IFERROR(LOOKUP(2,1/((持仓跟踪!$B$2:$B$157=A31)*(持仓跟踪!$X$2:$X$157="执行卖出")*(持仓跟踪!$Z$2:$Z$157<>"")),持仓跟踪!$Z$2:$Z$157),"")) -> 600 | M31: =IF(A31="","",IFERROR(LOOKUP(2,1/((持仓跟踪!$B$2:$B$157=A31)*(持仓跟踪!$X$2:$X$157="执行卖出")*(持仓跟踪!$H$2:$H$157<>"")),持仓跟踪!$H$2:$H$157),"")) -> 43083 | N31: 35 | P31: =IF(A31="","",IFERROR(LOOKUP(2,1/((持仓跟踪!$B$2:$B$157=A31)*(持仓跟踪!$X$2:$X$157="执行卖出")*(持仓跟踪!$AA$2:$AA$157<>"")),持仓跟踪!$AA$2:$AA$157),"")) | U31: =IF(OR(AO31="",J31="",AO31<=0),"",(J31-AO31)/AO31) -> 0.044386423 | V31: =IF(OR(AO31="",N31="",AO31<=0),"",(AO31-N31)/AO31) -> 0.08616188 | W31: =IF(OR(U31="",V31="",V31<=0),"",U31/V31) -> 0.51515152 | X31: =IF(OR(K31="",L31="",AP31=""),"",K31*L31-(E31*H31+IF(AND(AK31<>"",AL31<>""),AK31*AL31,0)+IF(AND(AM31<>"",AN31<>""),AM31*AN31,0))-IF(O31="",0,O31)-IF(P31="",0,P31)) -> 3738 | Y31: =IF(OR(X31="",AP31=""),"",IF((E31*H31+IF(AND(AK31<>"",AL31<>""),AK31*AL31,0)+IF(AND(AM31<>"",AN31<>""),AM31*AN31,0))+IF(O31="",0,O31)<=0,"",X31/((E31*H31+IF(AND(AK31<>"",AL31<>""),AK31*AL31,0)+IF(AND(AM31<>"",AN31<>""),AM31*AN31,0))+IF(O31="",0,O31)))) -> 0.16266319 | Z31: =IF(OR(AE31="",多次统计数据!$B$8=""),"",AE31-多次统计数据!$B$8) -> -0.036229155 | AA31: =IF(OR(I31="",M31="",M31<I31),"",M31-I31) -> 20 | AB31: =IF(OR(A31="",多次统计数据!$B$8="",多次统计数据!$B$6<=0,多次统计数据!$B$6>=1),"",1-POWER(1+多次统计数据!$B$8,-多次统计数据!$B$6/(1-多次统计数据!$B$6))) -> 0.053016657 | AC31: =IF(OR(AB31="",多次统计数据!$B$9=""),"",IF(多次统计数据!$B$9<AB31,"低于上限","达到或超过上限")) -> 低于上限 | AE31: =IF(OR(X31="",C31="",C31<=0),"",X31/C31) -> 0.036319471 | AG31: 短期博反弹 | AH31: 1～3个交易日 | AJ31: =IF(OR(AG31="",AH31=""),"",IF(OR(AND(AG31="短期博反弹",OR(AH31="1～3个交易日",AH31="4～10个交易日")),AND(AG31="突破冲新高",OR(AH31="4～10个交易日",AH31="11～20个交易日")),AND(AG31="趋势波段",OR(AH31="11～20个交易日",AH31="21～60个交易日",AH31="60个交易日以上"))),"匹配","周期与交易预期不匹配，请重新确认")) -> 匹配 | AO31: =IF(OR(A31="",H31="",H31<=0),"",(E31*H31+IF(AND(AK31<>"",AL31<>""),AK31*AL31,0)+IF(AND(AM31<>"",AN31<>""),AM31*AN31,0))/AP31) -> 38.3 | AP31: =IF(OR(A31="",H31="",H31<=0),"",H31+IF(AL31="",0,AL31)+IF(AN31="",0,AN31)) -> 600 | AQ31: =IF(A31="","",IF(M31<>"",0,IF(OR(H31="",N31=""),"",MAX(E31-MAX(N31,IFERROR(SUMPRODUCT(MAX(((持仓跟踪!$A$2:$A$157="每日跟踪")*(持仓跟踪!$B$2:$B$157=A31))*持仓跟踪!$S$2:$S$157)),0)),0)*H31+IF(OR(AK31="",AL31=""),0,MAX(AK31-MAX(N31,IFERROR(SUMPRODUCT(MAX(((持仓跟踪!$A$2:$A$157="每日跟踪")*(持仓跟踪!$B$2:$B$157=A31))*持仓跟踪!$S$2:$S$157)),0)),0)*AL31)+IF(OR(AM31="",AN31=""),0,MAX(AM31-MAX(N31,IFERROR(SUMPRODUCT(MAX(((持仓跟踪!$A$2:$A$157="每日跟踪")*(持仓跟踪!$B$2:$B$157=A31))*持仓跟踪!$S$2:$S$157)),0)),0)*AN31)))) -> 0 | AR31: =IF(A31="","",IF(OR(E31="",H31=""),"违规：第一批价格或股数缺失",IF(OR(AND(AK31="",AL31<>""),AND(AK31<>"",AL31="")),"违规：第二批价格与股数须成对填写",IF(OR(AND(AM31="",AN31<>""),AND(AM31<>"",AN31="")),"违规：第三批价格与股数须成对填写",IF(AND(OR(AM31<>"",AN31<>""),OR(AK31="",AL31="")),"违规：必须先完成第二批",IF(OR(H31<=0,H31<>INT(H31),MOD(H31,100)<>0,AND(AL31<>"",OR(AL31<=0,AL31<>INT(AL31),MOD(AL31,100)<>0)),AND(AN31<>"",OR(AN31<=0,AN31<>INT(AN31),MOD(AN31,100)<>0))),"违规：股数须为100股整数倍",IF(AND(OR(AL31<>"",AN31<>""),OR(_LockStatus="已锁仓",_LockStatus="解锁信息不完整")),"违规：锁仓期间禁止加仓",IF(AQ31>C31*D31,"违规：超过单笔风险上限",IF(SUM($AQ$2:$AQ$98)>账户数据!$B$7,"违规：超过账户风险上限","通过"))))))))) -> 通过
A32: 31 | B32: 五粮液 | C32: 106664 | D32: 0.02 | E32: 50.7 | F32: =IF(OR(C32="",D32="",E32="",N32="",C32<=0,D32<=0,E32<=N32),"",ROUNDDOWN((C32*D32)/(E32-N32)/100,0)*100) -> 700 | G32: =IF(A32="","",IF(H32<>"","已开仓",IF(账户数据!$B$23="已锁仓","禁止开仓：连续亏损达到上限",IF(账户数据!$B$23="解锁信息不完整","禁止开仓：请完整填写解锁信息",IF(OR(F32="",E32="",N32="",E32<=N32,账户数据!$B$7=""),"",IF(OR(AG32="",AH32="",AI32=""),"禁止开仓：交易预期未填写完整",IF(COUNTIFS(持仓跟踪!$A$2:$A$157,"止损计划",持仓跟踪!$B$2:$B$157,A32,持仓跟踪!$AC$2:$AC$157,"计划有效")=0,"禁止开仓：请先填写止损计划",IF(账户数据!$B$9+F32*(E32-N32)>=账户数据!$B$7,"禁止开仓：风险额度不足",IF(AJ32="周期与交易预期不匹配，请重新确认",IF(账户数据!$B$23="接近锁仓","允许开仓（接近锁仓；周期需复核）","允许开仓（周期需复核）"),IF(账户数据!$B$23="接近锁仓","允许开仓（接近锁仓）","允许开仓")))))))))) -> 已开仓 | H32: 700 | I32: 43097 | J32: 60 | K32: =IF(A32="","",IFERROR(LOOKUP(2,1/((持仓跟踪!$B$2:$B$157=A32)*(持仓跟踪!$X$2:$X$157="执行卖出")*(持仓跟踪!$Y$2:$Y$157<>"")),持仓跟踪!$Y$2:$Y$157),"")) -> 54.22 | L32: =IF(A32="","",IFERROR(LOOKUP(2,1/((持仓跟踪!$B$2:$B$157=A32)*(持仓跟踪!$X$2:$X$157="执行卖出")*(持仓跟踪!$Z$2:$Z$157<>"")),持仓跟踪!$Z$2:$Z$157),"")) -> 700 | M32: =IF(A32="","",IFERROR(LOOKUP(2,1/((持仓跟踪!$B$2:$B$157=A32)*(持仓跟踪!$X$2:$X$157="执行卖出")*(持仓跟踪!$H$2:$H$157<>"")),持仓跟踪!$H$2:$H$157),"")) -> 43131 | N32: 48 | P32: =IF(A32="","",IFERROR(LOOKUP(2,1/((持仓跟踪!$B$2:$B$157=A32)*(持仓跟踪!$X$2:$X$157="执行卖出")*(持仓跟踪!$AA$2:$AA$157<>"")),持仓跟踪!$AA$2:$AA$157),"")) | U32: =IF(OR(AO32="",J32="",AO32<=0),"",(J32-AO32)/AO32) -> 0.18343195 | V32: =IF(OR(AO32="",N32="",AO32<=0),"",(AO32-N32)/AO32) -> 0.053254438 | W32: =IF(OR(U32="",V32="",V32<=0),"",U32/V32) -> 3.4444444 | X32: =IF(OR(K32="",L32="",AP32=""),"",K32*L32-(E32*H32+IF(AND(AK32<>"",AL32<>""),AK32*AL32,0)+IF(AND(AM32<>"",AN32<>""),AM32*AN32,0))-IF(O32="",0,O32)-IF(P32="",0,P32)) -> 2464 | Y32: =IF(OR(X32="",AP32=""),"",IF((E32*H32+IF(AND(AK32<>"",AL32<>""),AK32*AL32,0)+IF(AND(AM32<>"",AN32<>""),AM32*AN32,0))+IF(O32="",0,O32)<=0,"",X32/((E32*H32+IF(AND(AK32<>"",AL32<>""),AK32*AL32,0)+IF(AND(AM32<>"",AN32<>""),AM32*AN32,0))+IF(O32="",0,O32)))) -> 0.069428008 | Z32: =IF(OR(AE32="",多次统计数据!$B$8=""),"",AE32-多次统计数据!$B$8) -> -0.049448049 | AA32: =IF(OR(I32="",M32="",M32<I32),"",M32-I32) -> 34 | AB32: =IF(OR(A32="",多次统计数据!$B$8="",多次统计数据!$B$6<=0,多次统计数据!$B$6>=1),"",1-POWER(1+多次统计数据!$B$8,-多次统计数据!$B$6/(1-多次统计数据!$B$6))) -> 0.053016657 | AC32: =IF(OR(AB32="",多次统计数据!$B$9=""),"",IF(多次统计数据!$B$9<AB32,"低于上限","达到或超过上限")) -> 低于上限 | AD32: 4-良好 | AE32: =IF(OR(X32="",C32="",C32<=0),"",X32/C32) -> 0.023100578 | AG32: 突破冲新高 | AH32: 4～10个交易日 | AJ32: =IF(OR(AG32="",AH32=""),"",IF(OR(AND(AG32="短期博反弹",OR(AH32="1～3个交易日",AH32="4～10个交易日")),AND(AG32="突破冲新高",OR(AH32="4～10个交易日",AH32="11～20个交易日")),AND(AG32="趋势波段",OR(AH32="11～20个交易日",AH32="21～60个交易日",AH32="60个交易日以上"))),"匹配","周期与交易预期不匹配，请重新确认")) -> 匹配 | AO32: =IF(OR(A32="",H32="",H32<=0),"",(E32*H32+IF(AND(AK32<>"",AL32<>""),AK32*AL32,0)+IF(AND(AM32<>"",AN32<>""),AM32*AN32,0))/AP32) -> 50.7 | AP32: =IF(OR(A32="",H32="",H32<=0),"",H32+IF(AL32="",0,AL32)+IF(AN32="",0,AN32)) -> 700 | AQ32: =IF(A32="","",IF(M32<>"",0,IF(OR(H32="",N32=""),"",MAX(E32-MAX(N32,IFERROR(SUMPRODUCT(MAX(((持仓跟踪!$A$2:$A$157="每日跟踪")*(持仓跟踪!$B$2:$B$157=A32))*持仓跟踪!$S$2:$S$157)),0)),0)*H32+IF(OR(AK32="",AL32=""),0,MAX(AK32-MAX(N32,IFERROR(SUMPRODUCT(MAX(((持仓跟踪!$A$2:$A$157="每日跟踪")*(持仓跟踪!$B$2:$B$157=A32))*持仓跟踪!$S$2:$S$157)),0)),0)*AL32)+IF(OR(AM32="",AN32=""),0,MAX(AM32-MAX(N32,IFERROR(SUMPRODUCT(MAX(((持仓跟踪!$A$2:$A$157="每日跟踪")*(持仓跟踪!$B$2:$B$157=A32))*持仓跟踪!$S$2:$S$157)),0)),0)*AN32)))) -> 0 | AR32: =IF(A32="","",IF(OR(E32="",H32=""),"违规：第一批价格或股数缺失",IF(OR(AND(AK32="",AL32<>""),AND(AK32<>"",AL32="")),"违规：第二批价格与股数须成对填写",IF(OR(AND(AM32="",AN32<>""),AND(AM32<>"",AN32="")),"违规：第三批价格与股数须成对填写",IF(AND(OR(AM32<>"",AN32<>""),OR(AK32="",AL32="")),"违规：必须先完成第二批",IF(OR(H32<=0,H32<>INT(H32),MOD(H32,100)<>0,AND(AL32<>"",OR(AL32<=0,AL32<>INT(AL32),MOD(AL32,100)<>0)),AND(AN32<>"",OR(AN32<=0,AN32<>INT(AN32),MOD(AN32,100)<>0))),"违规：股数须为100股整数倍",IF(AND(OR(AL32<>"",AN32<>""),OR(_LockStatus="已锁仓",_LockStatus="解锁信息不完整")),"违规：锁仓期间禁止加仓",IF(AQ32>C32*D32,"违规：超过单笔风险上限",IF(SUM($AQ$2:$AQ$98)>账户数据!$B$7,"违规：超过账户风险上限","通过"))))))))) -> 通过
A33: 32 | B33: 五粮液 | C33: 109128 | D33: 0.02 | E33: 52.32 | F33: =IF(OR(C33="",D33="",E33="",N33="",C33<=0,D33<=0,E33<=N33),"",ROUNDDOWN((C33*D33)/(E33-N33)/100,0)*100) -> 900 | G33: =IF(A33="","",IF(H33<>"","已开仓",IF(账户数据!$B$23="已锁仓","禁止开仓：连续亏损达到上限",IF(账户数据!$B$23="解锁信息不完整","禁止开仓：请完整填写解锁信息",IF(OR(F33="",E33="",N33="",E33<=N33,账户数据!$B$7=""),"",IF(OR(AG33="",AH33="",AI33=""),"禁止开仓：交易预期未填写完整",IF(COUNTIFS(持仓跟踪!$A$2:$A$157,"止损计划",持仓跟踪!$B$2:$B$157,A33,持仓跟踪!$AC$2:$AC$157,"计划有效")=0,"禁止开仓：请先填写止损计划",IF(账户数据!$B$9+F33*(E33-N33)>=账户数据!$B$7,"禁止开仓：风险额度不足",IF(AJ33="周期与交易预期不匹配，请重新确认",IF(账户数据!$B$23="接近锁仓","允许开仓（接近锁仓；周期需复核）","允许开仓（周期需复核）"),IF(账户数据!$B$23="接近锁仓","允许开仓（接近锁仓）","允许开仓")))))))))) -> 已开仓 | H33: 900 | I33: 43262 | J33: 60 | K33: =IF(A33="","",IFERROR(LOOKUP(2,1/((持仓跟踪!$B$2:$B$157=A33)*(持仓跟踪!$X$2:$X$157="执行卖出")*(持仓跟踪!$Y$2:$Y$157<>"")),持仓跟踪!$Y$2:$Y$157),"")) -> 46.39 | L33: =IF(A33="","",IFERROR(LOOKUP(2,1/((持仓跟踪!$B$2:$B$157=A33)*(持仓跟踪!$X$2:$X$157="执行卖出")*(持仓跟踪!$Z$2:$Z$157<>"")),持仓跟踪!$Z$2:$Z$157),"")) -> 900 | M33: =IF(A33="","",IFERROR(LOOKUP(2,1/((持仓跟踪!$B$2:$B$157=A33)*(持仓跟踪!$X$2:$X$157="执行卖出")*(持仓跟踪!$H$2:$H$157<>"")),持仓跟踪!$H$2:$H$157),"")) -> 43278 | N33: 50 | P33: =IF(A33="","",IFERROR(LOOKUP(2,1/((持仓跟踪!$B$2:$B$157=A33)*(持仓跟踪!$X$2:$X$157="执行卖出")*(持仓跟踪!$AA$2:$AA$157<>"")),持仓跟踪!$AA$2:$AA$157),"")) | U33: =IF(OR(AO33="",J33="",AO33<=0),"",(J33-AO33)/AO33) -> 0.14678899 | V33: =IF(OR(AO33="",N33="",AO33<=0),"",(AO33-N33)/AO33) -> 0.044342508 | W33: =IF(OR(U33="",V33="",V33<=0),"",U33/V33) -> 3.3103448 | X33: =IF(OR(K33="",L33="",AP33=""),"",K33*L33-(E33*H33+IF(AND(AK33<>"",AL33<>""),AK33*AL33,0)+IF(AND(AM33<>"",AN33<>""),AM33*AN33,0))-IF(O33="",0,O33)-IF(P33="",0,P33)) -> -5337 | Y33: =IF(OR(X33="",AP33=""),"",IF((E33*H33+IF(AND(AK33<>"",AL33<>""),AK33*AL33,0)+IF(AND(AM33<>"",AN33<>""),AM33*AN33,0))+IF(O33="",0,O33)<=0,"",X33/((E33*H33+IF(AND(AK33<>"",AL33<>""),AK33*AL33,0)+IF(AND(AM33<>"",AN33<>""),AM33*AN33,0))+IF(O33="",0,O33)))) -> -0.11334098 | Z33: =IF(OR(AE33="",多次统计数据!$B$8=""),"",AE33-多次统计数据!$B$8) -> -0.1214545 | AA33: =IF(OR(I33="",M33="",M33<I33),"",M33-I33) -> 16 | AB33: =IF(OR(A33="",多次统计数据!$B$8="",多次统计数据!$B$6<=0,多次统计数据!$B$6>=1),"",1-POWER(1+多次统计数据!$B$8,-多次统计数据!$B$6/(1-多次统计数据!$B$6))) -> 0.053016657 | AC33: =IF(OR(AB33="",多次统计数据!$B$9=""),"",IF(多次统计数据!$B$9<AB33,"低于上限","达到或超过上限")) -> 低于上限 | AE33: =IF(OR(X33="",C33="",C33<=0),"",X33/C33) -> -0.048905872 | AG33: 突破冲新高 | AH33: 4～10个交易日 | AJ33: =IF(OR(AG33="",AH33=""),"",IF(OR(AND(AG33="短期博反弹",OR(AH33="1～3个交易日",AH33="4～10个交易日")),AND(AG33="突破冲新高",OR(AH33="4～10个交易日",AH33="11～20个交易日")),AND(AG33="趋势波段",OR(AH33="11～20个交易日",AH33="21～60个交易日",AH33="60个交易日以上"))),"匹配","周期与交易预期不匹配，请重新确认")) -> 匹配 | AO33: =IF(OR(A33="",H33="",H33<=0),"",(E33*H33+IF(AND(AK33<>"",AL33<>""),AK33*AL33,0)+IF(AND(AM33<>"",AN33<>""),AM33*AN33,0))/AP33) -> 52.32 | AP33: =IF(OR(A33="",H33="",H33<=0),"",H33+IF(AL33="",0,AL33)+IF(AN33="",0,AN33)) -> 900 | AQ33: =IF(A33="","",IF(M33<>"",0,IF(OR(H33="",N33=""),"",MAX(E33-MAX(N33,IFERROR(SUMPRODUCT(MAX(((持仓跟踪!$A$2:$A$157="每日跟踪")*(持仓跟踪!$B$2:$B$157=A33))*持仓跟踪!$S$2:$S$157)),0)),0)*H33+IF(OR(AK33="",AL33=""),0,MAX(AK33-MAX(N33,IFERROR(SUMPRODUCT(MAX(((持仓跟踪!$A$2:$A$157="每日跟踪")*(持仓跟踪!$B$2:$B$157=A33))*持仓跟踪!$S$2:$S$157)),0)),0)*AL33)+IF(OR(AM33="",AN33=""),0,MAX(AM33-MAX(N33,IFERROR(SUMPRODUCT(MAX(((持仓跟踪!$A$2:$A$157="每日跟踪")*(持仓跟踪!$B$2:$B$157=A33))*持仓跟踪!$S$2:$S$157)),0)),0)*AN33)))) -> 0 | AR33: =IF(A33="","",IF(OR(E33="",H33=""),"违规：第一批价格或股数缺失",IF(OR(AND(AK33="",AL33<>""),AND(AK33<>"",AL33="")),"违规：第二批价格与股数须成对填写",IF(OR(AND(AM33="",AN33<>""),AND(AM33<>"",AN33="")),"违规：第三批价格与股数须成对填写",IF(AND(OR(AM33<>"",AN33<>""),OR(AK33="",AL33="")),"违规：必须先完成第二批",IF(OR(H33<=0,H33<>INT(H33),MOD(H33,100)<>0,AND(AL33<>"",OR(AL33<=0,AL33<>INT(AL33),MOD(AL33,100)<>0)),AND(AN33<>"",OR(AN33<=0,AN33<>INT(AN33),MOD(AN33,100)<>0))),"违规：股数须为100股整数倍",IF(AND(OR(AL33<>"",AN33<>""),OR(_LockStatus="已锁仓",_LockStatus="解锁信息不完整")),"违规：锁仓期间禁止加仓",IF(AQ33>C33*D33,"违规：超过单笔风险上限",IF(SUM($AQ$2:$AQ$98)>账户数据!$B$7,"违规：超过账户风险上限","通过"))))))))) -> 通过
A34: 33 | B34: 五粮液 | C34: 103791 | D34: 0.02 | E34: 42.64 | F34: =IF(OR(C34="",D34="",E34="",N34="",C34<=0,D34<=0,E34<=N34),"",ROUNDDOWN((C34*D34)/(E34-N34)/100,0)*100) -> 700 | G34: =IF(A34="","",IF(H34<>"","已开仓",IF(账户数据!$B$23="已锁仓","禁止开仓：连续亏损达到上限",IF(账户数据!$B$23="解锁信息不完整","禁止开仓：请完整填写解锁信息",IF(OR(F34="",E34="",N34="",E34<=N34,账户数据!$B$7=""),"",IF(OR(AG34="",AH34="",AI34=""),"禁止开仓：交易预期未填写完整",IF(COUNTIFS(持仓跟踪!$A$2:$A$157,"止损计划",持仓跟踪!$B$2:$B$157,A34,持仓跟踪!$AC$2:$AC$157,"计划有效")=0,"禁止开仓：请先填写止损计划",IF(账户数据!$B$9+F34*(E34-N34)>=账户数据!$B$7,"禁止开仓：风险额度不足",IF(AJ34="周期与交易预期不匹配，请重新确认",IF(账户数据!$B$23="接近锁仓","允许开仓（接近锁仓；周期需复核）","允许开仓（周期需复核）"),IF(账户数据!$B$23="接近锁仓","允许开仓（接近锁仓）","允许开仓")))))))))) -> 已开仓 | H34: 700 | I34: 43504 | J34: 50 | K34: =IF(A34="","",IFERROR(LOOKUP(2,1/((持仓跟踪!$B$2:$B$157=A34)*(持仓跟踪!$X$2:$X$157="执行卖出")*(持仓跟踪!$Y$2:$Y$157<>"")),持仓跟踪!$Y$2:$Y$157),"")) -> 72.6 | L34: =IF(A34="","",IFERROR(LOOKUP(2,1/((持仓跟踪!$B$2:$B$157=A34)*(持仓跟踪!$X$2:$X$157="执行卖出")*(持仓跟踪!$Z$2:$Z$157<>"")),持仓跟踪!$Z$2:$Z$157),"")) -> 700 | M34: =IF(A34="","",IFERROR(LOOKUP(2,1/((持仓跟踪!$B$2:$B$157=A34)*(持仓跟踪!$X$2:$X$157="执行卖出")*(持仓跟踪!$H$2:$H$157<>"")),持仓跟踪!$H$2:$H$157),"")) -> 43619 | N34: 40 | P34: =IF(A34="","",IFERROR(LOOKUP(2,1/((持仓跟踪!$B$2:$B$157=A34)*(持仓跟踪!$X$2:$X$157="执行卖出")*(持仓跟踪!$AA$2:$AA$157<>"")),持仓跟踪!$AA$2:$AA$157),"")) | U34: =IF(OR(AO34="",J34="",AO34<=0),"",(J34-AO34)/AO34) -> 0.17260788 | V34: =IF(OR(AO34="",N34="",AO34<=0),"",(AO34-N34)/AO34) -> 0.061913696 | W34: =IF(OR(U34="",V34="",V34<=0),"",U34/V34) -> 2.7878788 | X34: =IF(OR(K34="",L34="",AP34=""),"",K34*L34-(E34*H34+IF(AND(AK34<>"",AL34<>""),AK34*AL34,0)+IF(AND(AM34<>"",AN34<>""),AM34*AN34,0))-IF(O34="",0,O34)-IF(P34="",0,P34)) -> 20972 | Y34: =IF(OR(X34="",AP34=""),"",IF((E34*H34+IF(AND(AK34<>"",AL34<>""),AK34*AL34,0)+IF(AND(AM34<>"",AN34<>""),AM34*AN34,0))+IF(O34="",0,O34)<=0,"",X34/((E34*H34+IF(AND(AK34<>"",AL34<>""),AK34*AL34,0)+IF(AND(AM34<>"",AN34<>""),AM34*AN34,0))+IF(O34="",0,O34)))) -> 0.70262664 | Z34: =IF(OR(AE34="",多次统计数据!$B$8=""),"",AE34-多次统计数据!$B$8) -> 0.12951128 | AA34: =IF(OR(I34="",M34="",M34<I34),"",M34-I34) -> 115 | AB34: =IF(OR(A34="",多次统计数据!$B$8="",多次统计数据!$B$6<=0,多次统计数据!$B$6>=1),"",1-POWER(1+多次统计数据!$B$8,-多次统计数据!$B$6/(1-多次统计数据!$B$6))) -> 0.053016657 | AC34: =IF(OR(AB34="",多次统计数据!$B$9=""),"",IF(多次统计数据!$B$9<AB34,"低于上限","达到或超过上限")) -> 低于上限 | AE34: =IF(OR(X34="",C34="",C34<=0),"",X34/C34) -> 0.20205991 | AJ34: =IF(OR(AG34="",AH34=""),"",IF(OR(AND(AG34="短期博反弹",OR(AH34="1～3个交易日",AH34="4～10个交易日")),AND(AG34="突破冲新高",OR(AH34="4～10个交易日",AH34="11～20个交易日")),AND(AG34="趋势波段",OR(AH34="11～20个交易日",AH34="21～60个交易日",AH34="60个交易日以上"))),"匹配","周期与交易预期不匹配，请重新确认")) | AO34: =IF(OR(A34="",H34="",H34<=0),"",(E34*H34+IF(AND(AK34<>"",AL34<>""),AK34*AL34,0)+IF(AND(AM34<>"",AN34<>""),AM34*AN34,0))/AP34) -> 42.64 | AP34: =IF(OR(A34="",H34="",H34<=0),"",H34+IF(AL34="",0,AL34)+IF(AN34="",0,AN34)) -> 700 | AQ34: =IF(A34="","",IF(M34<>"",0,IF(OR(H34="",N34=""),"",MAX(E34-MAX(N34,IFERROR(SUMPRODUCT(MAX(((持仓跟踪!$A$2:$A$157="每日跟踪")*(持仓跟踪!$B$2:$B$157=A34))*持仓跟踪!$S$2:$S$157)),0)),0)*H34+IF(OR(AK34="",AL34=""),0,MAX(AK34-MAX(N34,IFERROR(SUMPRODUCT(MAX(((持仓跟踪!$A$2:$A$157="每日跟踪")*(持仓跟踪!$B$2:$B$157=A34))*持仓跟踪!$S$2:$S$157)),0)),0)*AL34)+IF(OR(AM34="",AN34=""),0,MAX(AM34-MAX(N34,IFERROR(SUMPRODUCT(MAX(((持仓跟踪!$A$2:$A$157="每日跟踪")*(持仓跟踪!$B$2:$B$157=A34))*持仓跟踪!$S$2:$S$157)),0)),0)*AN34)))) -> 0 | AR34: =IF(A34="","",IF(OR(E34="",H34=""),"违规：第一批价格或股数缺失",IF(OR(AND(AK34="",AL34<>""),AND(AK34<>"",AL34="")),"违规：第二批价格与股数须成对填写",IF(OR(AND(AM34="",AN34<>""),AND(AM34<>"",AN34="")),"违规：第三批价格与股数须成对填写",IF(AND(OR(AM34<>"",AN34<>""),OR(AK34="",AL34="")),"违规：必须先完成第二批",IF(OR(H34<=0,H34<>INT(H34),MOD(H34,100)<>0,AND(AL34<>"",OR(AL34<=0,AL34<>INT(AL34),MOD(AL34,100)<>0)),AND(AN34<>"",OR(AN34<=0,AN34<>INT(AN34),MOD(AN34,100)<>0))),"违规：股数须为100股整数倍",IF(AND(OR(AL34<>"",AN34<>""),OR(_LockStatus="已锁仓",_LockStatus="解锁信息不完整")),"违规：锁仓期间禁止加仓",IF(AQ34>C34*D34,"违规：超过单笔风险上限",IF(SUM($AQ$2:$AQ$98)>账户数据!$B$7,"违规：超过账户风险上限","通过"))))))))) -> 通过
A35: 34 | B35: 五粮液 | C35: 124763 | D35: 0.02 | E35: 102.65 | F35: =IF(OR(C35="",D35="",E35="",N35="",C35<=0,D35<=0,E35<=N35),"",ROUNDDOWN((C35*D35)/(E35-N35)/100,0)*100) -> 900 | G35: =IF(A35="","",IF(H35<>"","已开仓",IF(账户数据!$B$23="已锁仓","禁止开仓：连续亏损达到上限",IF(账户数据!$B$23="解锁信息不完整","禁止开仓：请完整填写解锁信息",IF(OR(F35="",E35="",N35="",E35<=N35,账户数据!$B$7=""),"",IF(OR(AG35="",AH35="",AI35=""),"禁止开仓：交易预期未填写完整",IF(COUNTIFS(持仓跟踪!$A$2:$A$157,"止损计划",持仓跟踪!$B$2:$B$157,A35,持仓跟踪!$AC$2:$AC$157,"计划有效")=0,"禁止开仓：请先填写止损计划",IF(账户数据!$B$9+F35*(E35-N35)>=账户数据!$B$7,"禁止开仓：风险额度不足",IF(AJ35="周期与交易预期不匹配，请重新确认",IF(账户数据!$B$23="接近锁仓","允许开仓（接近锁仓；周期需复核）","允许开仓（周期需复核）"),IF(账户数据!$B$23="接近锁仓","允许开仓（接近锁仓）","允许开仓")))))))))) -> 已开仓 | H35: 900 | I35: 43651 | J35: 110 | K35: =IF(A35="","",IFERROR(LOOKUP(2,1/((持仓跟踪!$B$2:$B$157=A35)*(持仓跟踪!$X$2:$X$157="执行卖出")*(持仓跟踪!$Y$2:$Y$157<>"")),持仓跟踪!$Y$2:$Y$157),"")) -> 93.44 | L35: =IF(A35="","",IFERROR(LOOKUP(2,1/((持仓跟踪!$B$2:$B$157=A35)*(持仓跟踪!$X$2:$X$157="执行卖出")*(持仓跟踪!$Z$2:$Z$157<>"")),持仓跟踪!$Z$2:$Z$157),"")) -> 900 | M35: =IF(A35="","",IFERROR(LOOKUP(2,1/((持仓跟踪!$B$2:$B$157=A35)*(持仓跟踪!$X$2:$X$157="执行卖出")*(持仓跟踪!$H$2:$H$157<>"")),持仓跟踪!$H$2:$H$157),"")) -> 43889 | N35: 100 | P35: =IF(A35="","",IFERROR(LOOKUP(2,1/((持仓跟踪!$B$2:$B$157=A35)*(持仓跟踪!$X$2:$X$157="执行卖出")*(持仓跟踪!$AA$2:$AA$157<>"")),持仓跟踪!$AA$2:$AA$157),"")) | U35: =IF(OR(AO35="",J35="",AO35<=0),"",(J35-AO35)/AO35) -> 0.071602533 | V35: =IF(OR(AO35="",N35="",AO35<=0),"",(AO35-N35)/AO35) -> 0.025815879 | W35: =IF(OR(U35="",V35="",V35<=0),"",U35/V35) -> 2.7735849 | X35: =IF(OR(K35="",L35="",AP35=""),"",K35*L35-(E35*H35+IF(AND(AK35<>"",AL35<>""),AK35*AL35,0)+IF(AND(AM35<>"",AN35<>""),AM35*AN35,0))-IF(O35="",0,O35)-IF(P35="",0,P35)) -> -8289 | Y35: =IF(OR(X35="",AP35=""),"",IF((E35*H35+IF(AND(AK35<>"",AL35<>""),AK35*AL35,0)+IF(AND(AM35<>"",AN35<>""),AM35*AN35,0))+IF(O35="",0,O35)<=0,"",X35/((E35*H35+IF(AND(AK35<>"",AL35<>""),AK35*AL35,0)+IF(AND(AM35<>"",AN35<>""),AM35*AN35,0))+IF(O35="",0,O35)))) -> -0.089722358 | Z35: =IF(OR(AE35="",多次统计数据!$B$8=""),"",AE35-多次统计数据!$B$8) -> -0.13898659 | AA35: =IF(OR(I35="",M35="",M35<I35),"",M35-I35) -> 238 | AB35: =IF(OR(A35="",多次统计数据!$B$8="",多次统计数据!$B$6<=0,多次统计数据!$B$6>=1),"",1-POWER(1+多次统计数据!$B$8,-多次统计数据!$B$6/(1-多次统计数据!$B$6))) -> 0.053016657 | AC35: =IF(OR(AB35="",多次统计数据!$B$9=""),"",IF(多次统计数据!$B$9<AB35,"低于上限","达到或超过上限")) -> 低于上限 | AE35: =IF(OR(X35="",C35="",C35<=0),"",X35/C35) -> -0.066437966 | AJ35: =IF(OR(AG35="",AH35=""),"",IF(OR(AND(AG35="短期博反弹",OR(AH35="1～3个交易日",AH35="4～10个交易日")),AND(AG35="突破冲新高",OR(AH35="4～10个交易日",AH35="11～20个交易日")),AND(AG35="趋势波段",OR(AH35="11～20个交易日",AH35="21～60个交易日",AH35="60个交易日以上"))),"匹配","周期与交易预期不匹配，请重新确认")) | AO35: =IF(OR(A35="",H35="",H35<=0),"",(E35*H35+IF(AND(AK35<>"",AL35<>""),AK35*AL35,0)+IF(AND(AM35<>"",AN35<>""),AM35*AN35,0))/AP35) -> 102.65 | AP35: =IF(OR(A35="",H35="",H35<=0),"",H35+IF(AL35="",0,AL35)+IF(AN35="",0,AN35)) -> 900 | AQ35: =IF(A35="","",IF(M35<>"",0,IF(OR(H35="",N35=""),"",MAX(E35-MAX(N35,IFERROR(SUMPRODUCT(MAX(((持仓跟踪!$A$2:$A$157="每日跟踪")*(持仓跟踪!$B$2:$B$157=A35))*持仓跟踪!$S$2:$S$157)),0)),0)*H35+IF(OR(AK35="",AL35=""),0,MAX(AK35-MAX(N35,IFERROR(SUMPRODUCT(MAX(((持仓跟踪!$A$2:$A$157="每日跟踪")*(持仓跟踪!$B$2:$B$157=A35))*持仓跟踪!$S$2:$S$157)),0)),0)*AL35)+IF(OR(AM35="",AN35=""),0,MAX(AM35-MAX(N35,IFERROR(SUMPRODUCT(MAX(((持仓跟踪!$A$2:$A$157="每日跟踪")*(持仓跟踪!$B$2:$B$157=A35))*持仓跟踪!$S$2:$S$157)),0)),0)*AN35)))) -> 0 | AR35: =IF(A35="","",IF(OR(E35="",H35=""),"违规：第一批价格或股数缺失",IF(OR(AND(AK35="",AL35<>""),AND(AK35<>"",AL35="")),"违规：第二批价格与股数须成对填写",IF(OR(AND(AM35="",AN35<>""),AND(AM35<>"",AN35="")),"违规：第三批价格与股数须成对填写",IF(AND(OR(AM35<>"",AN35<>""),OR(AK35="",AL35="")),"违规：必须先完成第二批",IF(OR(H35<=0,H35<>INT(H35),MOD(H35,100)<>0,AND(AL35<>"",OR(AL35<=0,AL35<>INT(AL35),MOD(AL35,100)<>0)),AND(AN35<>"",OR(AN35<=0,AN35<>INT(AN35),MOD(AN35,100)<>0))),"违规：股数须为100股整数倍",IF(AND(OR(AL35<>"",AN35<>""),OR(_LockStatus="已锁仓",_LockStatus="解锁信息不完整")),"违规：锁仓期间禁止加仓",IF(AQ35>C35*D35,"违规：超过单笔风险上限",IF(SUM($AQ$2:$AQ$98)>账户数据!$B$7,"违规：超过账户风险上限","通过"))))))))) -> 通过
A36: 35 | B36: 五粮液 | C36: 116474 | D36: 0.02 | E36: 118.06 | F36: =IF(OR(C36="",D36="",E36="",N36="",C36<=0,D36<=0,E36<=N36),"",ROUNDDOWN((C36*D36)/(E36-N36)/100,0)*100) -> 700 | G36: =IF(A36="","",IF(H36<>"","已开仓",IF(账户数据!$B$23="已锁仓","禁止开仓：连续亏损达到上限",IF(账户数据!$B$23="解锁信息不完整","禁止开仓：请完整填写解锁信息",IF(OR(F36="",E36="",N36="",E36<=N36,账户数据!$B$7=""),"",IF(OR(AG36="",AH36="",AI36=""),"禁止开仓：交易预期未填写完整",IF(COUNTIFS(持仓跟踪!$A$2:$A$157,"止损计划",持仓跟踪!$B$2:$B$157,A36,持仓跟踪!$AC$2:$AC$157,"计划有效")=0,"禁止开仓：请先填写止损计划",IF(账户数据!$B$9+F36*(E36-N36)>=账户数据!$B$7,"禁止开仓：风险额度不足",IF(AJ36="周期与交易预期不匹配，请重新确认",IF(账户数据!$B$23="接近锁仓","允许开仓（接近锁仓；周期需复核）","允许开仓（周期需复核）"),IF(账户数据!$B$23="接近锁仓","允许开仓（接近锁仓）","允许开仓")))))))))) -> 已开仓 | H36: 700 | I36: 43966 | J36: 130 | K36: =IF(A36="","",IFERROR(LOOKUP(2,1/((持仓跟踪!$B$2:$B$157=A36)*(持仓跟踪!$X$2:$X$157="执行卖出")*(持仓跟踪!$Y$2:$Y$157<>"")),持仓跟踪!$Y$2:$Y$157),"")) -> 192.04 | L36: =IF(A36="","",IFERROR(LOOKUP(2,1/((持仓跟踪!$B$2:$B$157=A36)*(持仓跟踪!$X$2:$X$157="执行卖出")*(持仓跟踪!$Z$2:$Z$157<>"")),持仓跟踪!$Z$2:$Z$157),"")) -> 700 | M36: =IF(A36="","",IFERROR(LOOKUP(2,1/((持仓跟踪!$B$2:$B$157=A36)*(持仓跟踪!$X$2:$X$157="执行卖出")*(持仓跟踪!$H$2:$H$157<>"")),持仓跟踪!$H$2:$H$157),"")) -> 44083 | N36: 115 | P36: =IF(A36="","",IFERROR(LOOKUP(2,1/((持仓跟踪!$B$2:$B$157=A36)*(持仓跟踪!$X$2:$X$157="执行卖出")*(持仓跟踪!$AA$2:$AA$157<>"")),持仓跟踪!$AA$2:$AA$157),"")) | U36: =IF(OR(AO36="",J36="",AO36<=0),"",(J36-AO36)/AO36) -> 0.10113502 | V36: =IF(OR(AO36="",N36="",AO36<=0),"",(AO36-N36)/AO36) -> 0.025919024 | W36: =IF(OR(U36="",V36="",V36<=0),"",U36/V36) -> 3.9019608 | X36: =IF(OR(K36="",L36="",AP36=""),"",K36*L36-(E36*H36+IF(AND(AK36<>"",AL36<>""),AK36*AL36,0)+IF(AND(AM36<>"",AN36<>""),AM36*AN36,0))-IF(O36="",0,O36)-IF(P36="",0,P36)) -> 51786 | Y36: =IF(OR(X36="",AP36=""),"",IF((E36*H36+IF(AND(AK36<>"",AL36<>""),AK36*AL36,0)+IF(AND(AM36<>"",AN36<>""),AM36*AN36,0))+IF(O36="",0,O36)<=0,"",X36/((E36*H36+IF(AND(AK36<>"",AL36<>""),AK36*AL36,0)+IF(AND(AM36<>"",AN36<>""),AM36*AN36,0))+IF(O36="",0,O36)))) -> 0.62663053 | Z36: =IF(OR(AE36="",多次统计数据!$B$8=""),"",AE36-多次统计数据!$B$8) -> 0.37206562 | AA36: =IF(OR(I36="",M36="",M36<I36),"",M36-I36) -> 117 | AB36: =IF(OR(A36="",多次统计数据!$B$8="",多次统计数据!$B$6<=0,多次统计数据!$B$6>=1),"",1-POWER(1+多次统计数据!$B$8,-多次统计数据!$B$6/(1-多次统计数据!$B$6))) -> 0.053016657 | AC36: =IF(OR(AB36="",多次统计数据!$B$9=""),"",IF(多次统计数据!$B$9<AB36,"低于上限","达到或超过上限")) -> 低于上限 | AE36: =IF(OR(X36="",C36="",C36<=0),"",X36/C36) -> 0.44461425 | AG36: 突破冲新高 | AH36: 4～10个交易日 | AJ36: =IF(OR(AG36="",AH36=""),"",IF(OR(AND(AG36="短期博反弹",OR(AH36="1～3个交易日",AH36="4～10个交易日")),AND(AG36="突破冲新高",OR(AH36="4～10个交易日",AH36="11～20个交易日")),AND(AG36="趋势波段",OR(AH36="11～20个交易日",AH36="21～60个交易日",AH36="60个交易日以上"))),"匹配","周期与交易预期不匹配，请重新确认")) -> 匹配 | AO36: =IF(OR(A36="",H36="",H36<=0),"",(E36*H36+IF(AND(AK36<>"",AL36<>""),AK36*AL36,0)+IF(AND(AM36<>"",AN36<>""),AM36*AN36,0))/AP36) -> 118.06 | AP36: =IF(OR(A36="",H36="",H36<=0),"",H36+IF(AL36="",0,AL36)+IF(AN36="",0,AN36)) -> 700 | AQ36: =IF(A36="","",IF(M36<>"",0,IF(OR(H36="",N36=""),"",MAX(E36-MAX(N36,IFERROR(SUMPRODUCT(MAX(((持仓跟踪!$A$2:$A$157="每日跟踪")*(持仓跟踪!$B$2:$B$157=A36))*持仓跟踪!$S$2:$S$157)),0)),0)*H36+IF(OR(AK36="",AL36=""),0,MAX(AK36-MAX(N36,IFERROR(SUMPRODUCT(MAX(((持仓跟踪!$A$2:$A$157="每日跟踪")*(持仓跟踪!$B$2:$B$157=A36))*持仓跟踪!$S$2:$S$157)),0)),0)*AL36)+IF(OR(AM36="",AN36=""),0,MAX(AM36-MAX(N36,IFERROR(SUMPRODUCT(MAX(((持仓跟踪!$A$2:$A$157="每日跟踪")*(持仓跟踪!$B$2:$B$157=A36))*持仓跟踪!$S$2:$S$157)),0)),0)*AN36)))) -> 0 | AR36: =IF(A36="","",IF(OR(E36="",H36=""),"违规：第一批价格或股数缺失",IF(OR(AND(AK36="",AL36<>""),AND(AK36<>"",AL36="")),"违规：第二批价格与股数须成对填写",IF(OR(AND(AM36="",AN36<>""),AND(AM36<>"",AN36="")),"违规：第三批价格与股数须成对填写",IF(AND(OR(AM36<>"",AN36<>""),OR(AK36="",AL36="")),"违规：必须先完成第二批",IF(OR(H36<=0,H36<>INT(H36),MOD(H36,100)<>0,AND(AL36<>"",OR(AL36<=0,AL36<>INT(AL36),MOD(AL36,100)<>0)),AND(AN36<>"",OR(AN36<=0,AN36<>INT(AN36),MOD(AN36,100)<>0))),"违规：股数须为100股整数倍",IF(AND(OR(AL36<>"",AN36<>""),OR(_LockStatus="已锁仓",_LockStatus="解锁信息不完整")),"违规：锁仓期间禁止加仓",IF(AQ36>C36*D36,"违规：超过单笔风险上限",IF(SUM($AQ$2:$AQ$98)>账户数据!$B$7,"违规：超过账户风险上限","通过"))))))))) -> 通过
A37: 36 | B37: 五粮液 | C37: 168260 | D37: 0.02 | E37: 214.44 | F37: =IF(OR(C37="",D37="",E37="",N37="",C37<=0,D37<=0,E37<=N37),"",ROUNDDOWN((C37*D37)/(E37-N37)/100,0)*100) -> 300 | G37: =IF(A37="","",IF(H37<>"","已开仓",IF(账户数据!$B$23="已锁仓","禁止开仓：连续亏损达到上限",IF(账户数据!$B$23="解锁信息不完整","禁止开仓：请完整填写解锁信息",IF(OR(F37="",E37="",N37="",E37<=N37,账户数据!$B$7=""),"",IF(OR(AG37="",AH37="",AI37=""),"禁止开仓：交易预期未填写完整",IF(COUNTIFS(持仓跟踪!$A$2:$A$157,"止损计划",持仓跟踪!$B$2:$B$157,A37,持仓跟踪!$AC$2:$AC$157,"计划有效")=0,"禁止开仓：请先填写止损计划",IF(账户数据!$B$9+F37*(E37-N37)>=账户数据!$B$7,"禁止开仓：风险额度不足",IF(AJ37="周期与交易预期不匹配，请重新确认",IF(账户数据!$B$23="接近锁仓","允许开仓（接近锁仓；周期需复核）","允许开仓（周期需复核）"),IF(账户数据!$B$23="接近锁仓","允许开仓（接近锁仓）","允许开仓")))))))))) -> 已开仓 | H37: 300 | I37: 44118 | J37: 230 | K37: =IF(A37="","",IFERROR(LOOKUP(2,1/((持仓跟踪!$B$2:$B$157=A37)*(持仓跟踪!$X$2:$X$157="执行卖出")*(持仓跟踪!$Y$2:$Y$157<>"")),持仓跟踪!$Y$2:$Y$157),"")) -> 238.76 | L37: =IF(A37="","",IFERROR(LOOKUP(2,1/((持仓跟踪!$B$2:$B$157=A37)*(持仓跟踪!$X$2:$X$157="执行卖出")*(持仓跟踪!$Z$2:$Z$157<>"")),持仓跟踪!$Z$2:$Z$157),"")) -> 300 | M37: =IF(A37="","",IFERROR(LOOKUP(2,1/((持仓跟踪!$B$2:$B$157=A37)*(持仓跟踪!$X$2:$X$157="执行卖出")*(持仓跟踪!$H$2:$H$157<>"")),持仓跟踪!$H$2:$H$157),"")) -> 44153 | N37: 205 | P37: =IF(A37="","",IFERROR(LOOKUP(2,1/((持仓跟踪!$B$2:$B$157=A37)*(持仓跟踪!$X$2:$X$157="执行卖出")*(持仓跟踪!$AA$2:$AA$157<>"")),持仓跟踪!$AA$2:$AA$157),"")) | U37: =IF(OR(AO37="",J37="",AO37<=0),"",(J37-AO37)/AO37) -> 0.072561089 | V37: =IF(OR(AO37="",N37="",AO37<=0),"",(AO37-N37)/AO37) -> 0.044021638 | W37: =IF(OR(U37="",V37="",V37<=0),"",U37/V37) -> 1.6483051 | X37: =IF(OR(K37="",L37="",AP37=""),"",K37*L37-(E37*H37+IF(AND(AK37<>"",AL37<>""),AK37*AL37,0)+IF(AND(AM37<>"",AN37<>""),AM37*AN37,0))-IF(O37="",0,O37)-IF(P37="",0,P37)) -> 7296 | Y37: =IF(OR(X37="",AP37=""),"",IF((E37*H37+IF(AND(AK37<>"",AL37<>""),AK37*AL37,0)+IF(AND(AM37<>"",AN37<>""),AM37*AN37,0))+IF(O37="",0,O37)<=0,"",X37/((E37*H37+IF(AND(AK37<>"",AL37<>""),AK37*AL37,0)+IF(AND(AM37<>"",AN37<>""),AM37*AN37,0))+IF(O37="",0,O37)))) -> 0.11341168 | Z37: =IF(OR(AE37="",多次统计数据!$B$8=""),"",AE37-多次统计数据!$B$8) -> -0.029187163 | AA37: =IF(OR(I37="",M37="",M37<I37),"",M37-I37) -> 35 | AB37: =IF(OR(A37="",多次统计数据!$B$8="",多次统计数据!$B$6<=0,多次统计数据!$B$6>=1),"",1-POWER(1+多次统计数据!$B$8,-多次统计数据!$B$6/(1-多次统计数据!$B$6))) -> 0.053016657 | AC37: =IF(OR(AB37="",多次统计数据!$B$9=""),"",IF(多次统计数据!$B$9<AB37,"低于上限","达到或超过上限")) -> 低于上限 | AE37: =IF(OR(X37="",C37="",C37<=0),"",X37/C37) -> 0.043361464 | AG37: 突破冲新高 | AH37: 4～10个交易日 | AJ37: =IF(OR(AG37="",AH37=""),"",IF(OR(AND(AG37="短期博反弹",OR(AH37="1～3个交易日",AH37="4～10个交易日")),AND(AG37="突破冲新高",OR(AH37="4～10个交易日",AH37="11～20个交易日")),AND(AG37="趋势波段",OR(AH37="11～20个交易日",AH37="21～60个交易日",AH37="60个交易日以上"))),"匹配","周期与交易预期不匹配，请重新确认")) -> 匹配 | AO37: =IF(OR(A37="",H37="",H37<=0),"",(E37*H37+IF(AND(AK37<>"",AL37<>""),AK37*AL37,0)+IF(AND(AM37<>"",AN37<>""),AM37*AN37,0))/AP37) -> 214.44 | AP37: =IF(OR(A37="",H37="",H37<=0),"",H37+IF(AL37="",0,AL37)+IF(AN37="",0,AN37)) -> 300 | AQ37: =IF(A37="","",IF(M37<>"",0,IF(OR(H37="",N37=""),"",MAX(E37-MAX(N37,IFERROR(SUMPRODUCT(MAX(((持仓跟踪!$A$2:$A$157="每日跟踪")*(持仓跟踪!$B$2:$B$157=A37))*持仓跟踪!$S$2:$S$157)),0)),0)*H37+IF(OR(AK37="",AL37=""),0,MAX(AK37-MAX(N37,IFERROR(SUMPRODUCT(MAX(((持仓跟踪!$A$2:$A$157="每日跟踪")*(持仓跟踪!$B$2:$B$157=A37))*持仓跟踪!$S$2:$S$157)),0)),0)*AL37)+IF(OR(AM37="",AN37=""),0,MAX(AM37-MAX(N37,IFERROR(SUMPRODUCT(MAX(((持仓跟踪!$A$2:$A$157="每日跟踪")*(持仓跟踪!$B$2:$B$157=A37))*持仓跟踪!$S$2:$S$157)),0)),0)*AN37)))) -> 0 | AR37: =IF(A37="","",IF(OR(E37="",H37=""),"违规：第一批价格或股数缺失",IF(OR(AND(AK37="",AL37<>""),AND(AK37<>"",AL37="")),"违规：第二批价格与股数须成对填写",IF(OR(AND(AM37="",AN37<>""),AND(AM37<>"",AN37="")),"违规：第三批价格与股数须成对填写",IF(AND(OR(AM37<>"",AN37<>""),OR(AK37="",AL37="")),"违规：必须先完成第二批",IF(OR(H37<=0,H37<>INT(H37),MOD(H37,100)<>0,AND(AL37<>"",OR(AL37<=0,AL37<>INT(AL37),MOD(AL37,100)<>0)),AND(AN37<>"",OR(AN37<=0,AN37<>INT(AN37),MOD(AN37,100)<>0))),"违规：股数须为100股整数倍",IF(AND(OR(AL37<>"",AN37<>""),OR(_LockStatus="已锁仓",_LockStatus="解锁信息不完整")),"违规：锁仓期间禁止加仓",IF(AQ37>C37*D37,"违规：超过单笔风险上限",IF(SUM($AQ$2:$AQ$98)>账户数据!$B$7,"违规：超过账户风险上限","通过"))))))))) -> 通过
A38: 37 | B38: 五粮液 | C38: 175556 | D38: 0.02 | E38: 257.02 | F38: =IF(OR(C38="",D38="",E38="",N38="",C38<=0,D38<=0,E38<=N38),"",ROUNDDOWN((C38*D38)/(E38-N38)/100,0)*100) -> 500 | G38: =IF(A38="","",IF(H38<>"","已开仓",IF(账户数据!$B$23="已锁仓","禁止开仓：连续亏损达到上限",IF(账户数据!$B$23="解锁信息不完整","禁止开仓：请完整填写解锁信息",IF(OR(F38="",E38="",N38="",E38<=N38,账户数据!$B$7=""),"",IF(OR(AG38="",AH38="",AI38=""),"禁止开仓：交易预期未填写完整",IF(COUNTIFS(持仓跟踪!$A$2:$A$157,"止损计划",持仓跟踪!$B$2:$B$157,A38,持仓跟踪!$AC$2:$AC$157,"计划有效")=0,"禁止开仓：请先填写止损计划",IF(账户数据!$B$9+F38*(E38-N38)>=账户数据!$B$7,"禁止开仓：风险额度不足",IF(AJ38="周期与交易预期不匹配，请重新确认",IF(账户数据!$B$23="接近锁仓","允许开仓（接近锁仓；周期需复核）","允许开仓（周期需复核）"),IF(账户数据!$B$23="接近锁仓","允许开仓（接近锁仓）","允许开仓")))))))))) -> 已开仓 | H38: 500 | I38: 44186 | J38: 270 | K38: =IF(A38="","",IFERROR(LOOKUP(2,1/((持仓跟踪!$B$2:$B$157=A38)*(持仓跟踪!$X$2:$X$157="执行卖出")*(持仓跟踪!$Y$2:$Y$157<>"")),持仓跟踪!$Y$2:$Y$157),"")) -> 303.34 | L38: =IF(A38="","",IFERROR(LOOKUP(2,1/((持仓跟踪!$B$2:$B$157=A38)*(持仓跟踪!$X$2:$X$157="执行卖出")*(持仓跟踪!$Z$2:$Z$157<>"")),持仓跟踪!$Z$2:$Z$157),"")) -> 500 | M38: =IF(A38="","",IFERROR(LOOKUP(2,1/((持仓跟踪!$B$2:$B$157=A38)*(持仓跟踪!$X$2:$X$157="执行卖出")*(持仓跟踪!$H$2:$H$157<>"")),持仓跟踪!$H$2:$H$157),"")) -> 44202 | N38: 250 | P38: =IF(A38="","",IFERROR(LOOKUP(2,1/((持仓跟踪!$B$2:$B$157=A38)*(持仓跟踪!$X$2:$X$157="执行卖出")*(持仓跟踪!$AA$2:$AA$157<>"")),持仓跟踪!$AA$2:$AA$157),"")) | U38: =IF(OR(AO38="",J38="",AO38<=0),"",(J38-AO38)/AO38) -> 0.050501906 | V38: =IF(OR(AO38="",N38="",AO38<=0),"",(AO38-N38)/AO38) -> 0.02731305 | W38: =IF(OR(U38="",V38="",V38<=0),"",U38/V38) -> 1.8490028 | X38: =IF(OR(K38="",L38="",AP38=""),"",K38*L38-(E38*H38+IF(AND(AK38<>"",AL38<>""),AK38*AL38,0)+IF(AND(AM38<>"",AN38<>""),AM38*AN38,0))-IF(O38="",0,O38)-IF(P38="",0,P38)) -> 23160 | Y38: =IF(OR(X38="",AP38=""),"",IF((E38*H38+IF(AND(AK38<>"",AL38<>""),AK38*AL38,0)+IF(AND(AM38<>"",AN38<>""),AM38*AN38,0))+IF(O38="",0,O38)<=0,"",X38/((E38*H38+IF(AND(AK38<>"",AL38<>""),AK38*AL38,0)+IF(AND(AM38<>"",AN38<>""),AM38*AN38,0))+IF(O38="",0,O38)))) -> 0.18021944 | Z38: =IF(OR(AE38="",多次统计数据!$B$8=""),"",AE38-多次统计数据!$B$8) -> 0.05937509 | AA38: =IF(OR(I38="",M38="",M38<I38),"",M38-I38) -> 16 | AB38: =IF(OR(A38="",多次统计数据!$B$8="",多次统计数据!$B$6<=0,多次统计数据!$B$6>=1),"",1-POWER(1+多次统计数据!$B$8,-多次统计数据!$B$6/(1-多次统计数据!$B$6))) -> 0.053016657 | AC38: =IF(OR(AB38="",多次统计数据!$B$9=""),"",IF(多次统计数据!$B$9<AB38,"低于上限","达到或超过上限")) -> 低于上限 | AE38: =IF(OR(X38="",C38="",C38<=0),"",X38/C38) -> 0.13192372 | AG38: 突破冲新高 | AH38: 4～10个交易日 | AJ38: =IF(OR(AG38="",AH38=""),"",IF(OR(AND(AG38="短期博反弹",OR(AH38="1～3个交易日",AH38="4～10个交易日")),AND(AG38="突破冲新高",OR(AH38="4～10个交易日",AH38="11～20个交易日")),AND(AG38="趋势波段",OR(AH38="11～20个交易日",AH38="21～60个交易日",AH38="60个交易日以上"))),"匹配","周期与交易预期不匹配，请重新确认")) -> 匹配 | AO38: =IF(OR(A38="",H38="",H38<=0),"",(E38*H38+IF(AND(AK38<>"",AL38<>""),AK38*AL38,0)+IF(AND(AM38<>"",AN38<>""),AM38*AN38,0))/AP38) -> 257.02 | AP38: =IF(OR(A38="",H38="",H38<=0),"",H38+IF(AL38="",0,AL38)+IF(AN38="",0,AN38)) -> 500 | AQ38: =IF(A38="","",IF(M38<>"",0,IF(OR(H38="",N38=""),"",MAX(E38-MAX(N38,IFERROR(SUMPRODUCT(MAX(((持仓跟踪!$A$2:$A$157="每日跟踪")*(持仓跟踪!$B$2:$B$157=A38))*持仓跟踪!$S$2:$S$157)),0)),0)*H38+IF(OR(AK38="",AL38=""),0,MAX(AK38-MAX(N38,IFERROR(SUMPRODUCT(MAX(((持仓跟踪!$A$2:$A$157="每日跟踪")*(持仓跟踪!$B$2:$B$157=A38))*持仓跟踪!$S$2:$S$157)),0)),0)*AL38)+IF(OR(AM38="",AN38=""),0,MAX(AM38-MAX(N38,IFERROR(SUMPRODUCT(MAX(((持仓跟踪!$A$2:$A$157="每日跟踪")*(持仓跟踪!$B$2:$B$157=A38))*持仓跟踪!$S$2:$S$157)),0)),0)*AN38)))) -> 0 | AR38: =IF(A38="","",IF(OR(E38="",H38=""),"违规：第一批价格或股数缺失",IF(OR(AND(AK38="",AL38<>""),AND(AK38<>"",AL38="")),"违规：第二批价格与股数须成对填写",IF(OR(AND(AM38="",AN38<>""),AND(AM38<>"",AN38="")),"违规：第三批价格与股数须成对填写",IF(AND(OR(AM38<>"",AN38<>""),OR(AK38="",AL38="")),"违规：必须先完成第二批",IF(OR(H38<=0,H38<>INT(H38),MOD(H38,100)<>0,AND(AL38<>"",OR(AL38<=0,AL38<>INT(AL38),MOD(AL38,100)<>0)),AND(AN38<>"",OR(AN38<=0,AN38<>INT(AN38),MOD(AN38,100)<>0))),"违规：股数须为100股整数倍",IF(AND(OR(AL38<>"",AN38<>""),OR(_LockStatus="已锁仓",_LockStatus="解锁信息不完整")),"违规：锁仓期间禁止加仓",IF(AQ38>C38*D38,"违规：超过单笔风险上限",IF(SUM($AQ$2:$AQ$98)>账户数据!$B$7,"违规：超过账户风险上限","通过"))))))))) -> 通过
A39: 38 | B39: 五粮液 | C39: 198716 | D39: 0.02 | E39: 171.71 | F39: =IF(OR(C39="",D39="",E39="",N39="",C39<=0,D39<=0,E39<=N39),"",ROUNDDOWN((C39*D39)/(E39-N39)/100,0)*100) -> 500 | G39: =IF(A39="","",IF(H39<>"","已开仓",IF(账户数据!$B$23="已锁仓","禁止开仓：连续亏损达到上限",IF(账户数据!$B$23="解锁信息不完整","禁止开仓：请完整填写解锁信息",IF(OR(F39="",E39="",N39="",E39<=N39,账户数据!$B$7=""),"",IF(OR(AG39="",AH39="",AI39=""),"禁止开仓：交易预期未填写完整",IF(COUNTIFS(持仓跟踪!$A$2:$A$157,"止损计划",持仓跟踪!$B$2:$B$157,A39,持仓跟踪!$AC$2:$AC$157,"计划有效")=0,"禁止开仓：请先填写止损计划",IF(账户数据!$B$9+F39*(E39-N39)>=账户数据!$B$7,"禁止开仓：风险额度不足",IF(AJ39="周期与交易预期不匹配，请重新确认",IF(账户数据!$B$23="接近锁仓","允许开仓（接近锁仓；周期需复核）","允许开仓（周期需复核）"),IF(账户数据!$B$23="接近锁仓","允许开仓（接近锁仓）","允许开仓")))))))))) -> 已开仓 | H39: 500 | I39: 44908 | J39: 180 | K39: =IF(A39="","",IFERROR(LOOKUP(2,1/((持仓跟踪!$B$2:$B$157=A39)*(持仓跟踪!$X$2:$X$157="执行卖出")*(持仓跟踪!$Y$2:$Y$157<>"")),持仓跟踪!$Y$2:$Y$157),"")) -> 193.16 | L39: =IF(A39="","",IFERROR(LOOKUP(2,1/((持仓跟踪!$B$2:$B$157=A39)*(持仓跟踪!$X$2:$X$157="执行卖出")*(持仓跟踪!$Z$2:$Z$157<>"")),持仓跟踪!$Z$2:$Z$157),"")) -> 500 | M39: =IF(A39="","",IFERROR(LOOKUP(2,1/((持仓跟踪!$B$2:$B$157=A39)*(持仓跟踪!$X$2:$X$157="执行卖出")*(持仓跟踪!$H$2:$H$157<>"")),持仓跟踪!$H$2:$H$157),"")) -> 44959 | N39: 165 | P39: =IF(A39="","",IFERROR(LOOKUP(2,1/((持仓跟踪!$B$2:$B$157=A39)*(持仓跟踪!$X$2:$X$157="执行卖出")*(持仓跟踪!$AA$2:$AA$157<>"")),持仓跟踪!$AA$2:$AA$157),"")) | U39: =IF(OR(AO39="",J39="",AO39<=0),"",(J39-AO39)/AO39) -> 0.048279075 | V39: =IF(OR(AO39="",N39="",AO39<=0),"",(AO39-N39)/AO39) -> 0.039077514 | W39: =IF(OR(U39="",V39="",V39<=0),"",U39/V39) -> 1.2354694 | X39: =IF(OR(K39="",L39="",AP39=""),"",K39*L39-(E39*H39+IF(AND(AK39<>"",AL39<>""),AK39*AL39,0)+IF(AND(AM39<>"",AN39<>""),AM39*AN39,0))-IF(O39="",0,O39)-IF(P39="",0,P39)) -> 10725 | Y39: =IF(OR(X39="",AP39=""),"",IF((E39*H39+IF(AND(AK39<>"",AL39<>""),AK39*AL39,0)+IF(AND(AM39<>"",AN39<>""),AM39*AN39,0))+IF(O39="",0,O39)<=0,"",X39/((E39*H39+IF(AND(AK39<>"",AL39<>""),AK39*AL39,0)+IF(AND(AM39<>"",AN39<>""),AM39*AN39,0))+IF(O39="",0,O39)))) -> 0.12491992 | Z39: =IF(OR(AE39="",多次统计数据!$B$8=""),"",AE39-多次统计数据!$B$8) -> -0.01857713 | AA39: =IF(OR(I39="",M39="",M39<I39),"",M39-I39) -> 51 | AB39: =IF(OR(A39="",多次统计数据!$B$8="",多次统计数据!$B$6<=0,多次统计数据!$B$6>=1),"",1-POWER(1+多次统计数据!$B$8,-多次统计数据!$B$6/(1-多次统计数据!$B$6))) -> 0.053016657 | AC39: =IF(OR(AB39="",多次统计数据!$B$9=""),"",IF(多次统计数据!$B$9<AB39,"低于上限","达到或超过上限")) -> 低于上限 | AE39: =IF(OR(X39="",C39="",C39<=0),"",X39/C39) -> 0.053971497 | AG39: 短期博反弹 | AH39: 4～10个交易日 | AJ39: =IF(OR(AG39="",AH39=""),"",IF(OR(AND(AG39="短期博反弹",OR(AH39="1～3个交易日",AH39="4～10个交易日")),AND(AG39="突破冲新高",OR(AH39="4～10个交易日",AH39="11～20个交易日")),AND(AG39="趋势波段",OR(AH39="11～20个交易日",AH39="21～60个交易日",AH39="60个交易日以上"))),"匹配","周期与交易预期不匹配，请重新确认")) -> 匹配 | AO39: =IF(OR(A39="",H39="",H39<=0),"",(E39*H39+IF(AND(AK39<>"",AL39<>""),AK39*AL39,0)+IF(AND(AM39<>"",AN39<>""),AM39*AN39,0))/AP39) -> 171.71 | AP39: =IF(OR(A39="",H39="",H39<=0),"",H39+IF(AL39="",0,AL39)+IF(AN39="",0,AN39)) -> 500 | AQ39: =IF(A39="","",IF(M39<>"",0,IF(OR(H39="",N39=""),"",MAX(E39-MAX(N39,IFERROR(SUMPRODUCT(MAX(((持仓跟踪!$A$2:$A$157="每日跟踪")*(持仓跟踪!$B$2:$B$157=A39))*持仓跟踪!$S$2:$S$157)),0)),0)*H39+IF(OR(AK39="",AL39=""),0,MAX(AK39-MAX(N39,IFERROR(SUMPRODUCT(MAX(((持仓跟踪!$A$2:$A$157="每日跟踪")*(持仓跟踪!$B$2:$B$157=A39))*持仓跟踪!$S$2:$S$157)),0)),0)*AL39)+IF(OR(AM39="",AN39=""),0,MAX(AM39-MAX(N39,IFERROR(SUMPRODUCT(MAX(((持仓跟踪!$A$2:$A$157="每日跟踪")*(持仓跟踪!$B$2:$B$157=A39))*持仓跟踪!$S$2:$S$157)),0)),0)*AN39)))) -> 0 | AR39: =IF(A39="","",IF(OR(E39="",H39=""),"违规：第一批价格或股数缺失",IF(OR(AND(AK39="",AL39<>""),AND(AK39<>"",AL39="")),"违规：第二批价格与股数须成对填写",IF(OR(AND(AM39="",AN39<>""),AND(AM39<>"",AN39="")),"违规：第三批价格与股数须成对填写",IF(AND(OR(AM39<>"",AN39<>""),OR(AK39="",AL39="")),"违规：必须先完成第二批",IF(OR(H39<=0,H39<>INT(H39),MOD(H39,100)<>0,AND(AL39<>"",OR(AL39<=0,AL39<>INT(AL39),MOD(AL39,100)<>0)),AND(AN39<>"",OR(AN39<=0,AN39<>INT(AN39),MOD(AN39,100)<>0))),"违规：股数须为100股整数倍",IF(AND(OR(AL39<>"",AN39<>""),OR(_LockStatus="已锁仓",_LockStatus="解锁信息不完整")),"违规：锁仓期间禁止加仓",IF(AQ39>C39*D39,"违规：超过单笔风险上限",IF(SUM($AQ$2:$AQ$98)>账户数据!$B$7,"违规：超过账户风险上限","通过"))))))))) -> 通过
A40: 39 | B40: 五粮液 | C40: 209441 | D40: 0.02 | E40: 162.89 | F40: =IF(OR(C40="",D40="",E40="",N40="",C40<=0,D40<=0,E40<=N40),"",ROUNDDOWN((C40*D40)/(E40-N40)/100,0)*100) -> 800 | G40: =IF(A40="","",IF(H40<>"","已开仓",IF(账户数据!$B$23="已锁仓","禁止开仓：连续亏损达到上限",IF(账户数据!$B$23="解锁信息不完整","禁止开仓：请完整填写解锁信息",IF(OR(F40="",E40="",N40="",E40<=N40,账户数据!$B$7=""),"",IF(OR(AG40="",AH40="",AI40=""),"禁止开仓：交易预期未填写完整",IF(COUNTIFS(持仓跟踪!$A$2:$A$157,"止损计划",持仓跟踪!$B$2:$B$157,A40,持仓跟踪!$AC$2:$AC$157,"计划有效")=0,"禁止开仓：请先填写止损计划",IF(账户数据!$B$9+F40*(E40-N40)>=账户数据!$B$7,"禁止开仓：风险额度不足",IF(AJ40="周期与交易预期不匹配，请重新确认",IF(账户数据!$B$23="接近锁仓","允许开仓（接近锁仓；周期需复核）","允许开仓（周期需复核）"),IF(账户数据!$B$23="接近锁仓","允许开仓（接近锁仓）","允许开仓")))))))))) -> 已开仓 | H40: 800 | I40: 45134 | J40: 170 | K40: =IF(A40="","",IFERROR(LOOKUP(2,1/((持仓跟踪!$B$2:$B$157=A40)*(持仓跟踪!$X$2:$X$157="执行卖出")*(持仓跟踪!$Y$2:$Y$157<>"")),持仓跟踪!$Y$2:$Y$157),"")) -> 165.43 | L40: =IF(A40="","",IFERROR(LOOKUP(2,1/((持仓跟踪!$B$2:$B$157=A40)*(持仓跟踪!$X$2:$X$157="执行卖出")*(持仓跟踪!$Z$2:$Z$157<>"")),持仓跟踪!$Z$2:$Z$157),"")) -> 800 | M40: =IF(A40="","",IFERROR(LOOKUP(2,1/((持仓跟踪!$B$2:$B$157=A40)*(持仓跟踪!$X$2:$X$157="执行卖出")*(持仓跟踪!$H$2:$H$157<>"")),持仓跟踪!$H$2:$H$157),"")) -> 45138 | N40: 158 | P40: =IF(A40="","",IFERROR(LOOKUP(2,1/((持仓跟踪!$B$2:$B$157=A40)*(持仓跟踪!$X$2:$X$157="执行卖出")*(持仓跟踪!$AA$2:$AA$157<>"")),持仓跟踪!$AA$2:$AA$157),"")) | U40: =IF(OR(AO40="",J40="",AO40<=0),"",(J40-AO40)/AO40) -> 0.043649088 | V40: =IF(OR(AO40="",N40="",AO40<=0),"",(AO40-N40)/AO40) -> 0.030020259 | W40: =IF(OR(U40="",V40="",V40<=0),"",U40/V40) -> 1.4539877 | X40: =IF(OR(K40="",L40="",AP40=""),"",K40*L40-(E40*H40+IF(AND(AK40<>"",AL40<>""),AK40*AL40,0)+IF(AND(AM40<>"",AN40<>""),AM40*AN40,0))-IF(O40="",0,O40)-IF(P40="",0,P40)) -> 2032 | Y40: =IF(OR(X40="",AP40=""),"",IF((E40*H40+IF(AND(AK40<>"",AL40<>""),AK40*AL40,0)+IF(AND(AM40<>"",AN40<>""),AM40*AN40,0))+IF(O40="",0,O40)<=0,"",X40/((E40*H40+IF(AND(AK40<>"",AL40<>""),AK40*AL40,0)+IF(AND(AM40<>"",AN40<>""),AM40*AN40,0))+IF(O40="",0,O40)))) -> 0.015593345 | Z40: =IF(OR(AE40="",多次统计数据!$B$8=""),"",AE40-多次统计数据!$B$8) -> -0.062846611 | AA40: =IF(OR(I40="",M40="",M40<I40),"",M40-I40) -> 4 | AB40: =IF(OR(A40="",多次统计数据!$B$8="",多次统计数据!$B$6<=0,多次统计数据!$B$6>=1),"",1-POWER(1+多次统计数据!$B$8,-多次统计数据!$B$6/(1-多次统计数据!$B$6))) -> 0.053016657 | AC40: =IF(OR(AB40="",多次统计数据!$B$9=""),"",IF(多次统计数据!$B$9<AB40,"低于上限","达到或超过上限")) -> 低于上限 | AE40: =IF(OR(X40="",C40="",C40<=0),"",X40/C40) -> 0.0097020163 | AG40: 短期博反弹 | AH40: 4～10个交易日 | AJ40: =IF(OR(AG40="",AH40=""),"",IF(OR(AND(AG40="短期博反弹",OR(AH40="1～3个交易日",AH40="4～10个交易日")),AND(AG40="突破冲新高",OR(AH40="4～10个交易日",AH40="11～20个交易日")),AND(AG40="趋势波段",OR(AH40="11～20个交易日",AH40="21～60个交易日",AH40="60个交易日以上"))),"匹配","周期与交易预期不匹配，请重新确认")) -> 匹配 | AO40: =IF(OR(A40="",H40="",H40<=0),"",(E40*H40+IF(AND(AK40<>"",AL40<>""),AK40*AL40,0)+IF(AND(AM40<>"",AN40<>""),AM40*AN40,0))/AP40) -> 162.89 | AP40: =IF(OR(A40="",H40="",H40<=0),"",H40+IF(AL40="",0,AL40)+IF(AN40="",0,AN40)) -> 800 | AQ40: =IF(A40="","",IF(M40<>"",0,IF(OR(H40="",N40=""),"",MAX(E40-MAX(N40,IFERROR(SUMPRODUCT(MAX(((持仓跟踪!$A$2:$A$157="每日跟踪")*(持仓跟踪!$B$2:$B$157=A40))*持仓跟踪!$S$2:$S$157)),0)),0)*H40+IF(OR(AK40="",AL40=""),0,MAX(AK40-MAX(N40,IFERROR(SUMPRODUCT(MAX(((持仓跟踪!$A$2:$A$157="每日跟踪")*(持仓跟踪!$B$2:$B$157=A40))*持仓跟踪!$S$2:$S$157)),0)),0)*AL40)+IF(OR(AM40="",AN40=""),0,MAX(AM40-MAX(N40,IFERROR(SUMPRODUCT(MAX(((持仓跟踪!$A$2:$A$157="每日跟踪")*(持仓跟踪!$B$2:$B$157=A40))*持仓跟踪!$S$2:$S$157)),0)),0)*AN40)))) -> 0 | AR40: =IF(A40="","",IF(OR(E40="",H40=""),"违规：第一批价格或股数缺失",IF(OR(AND(AK40="",AL40<>""),AND(AK40<>"",AL40="")),"违规：第二批价格与股数须成对填写",IF(OR(AND(AM40="",AN40<>""),AND(AM40<>"",AN40="")),"违规：第三批价格与股数须成对填写",IF(AND(OR(AM40<>"",AN40<>""),OR(AK40="",AL40="")),"违规：必须先完成第二批",IF(OR(H40<=0,H40<>INT(H40),MOD(H40,100)<>0,AND(AL40<>"",OR(AL40<=0,AL40<>INT(AL40),MOD(AL40,100)<>0)),AND(AN40<>"",OR(AN40<=0,AN40<>INT(AN40),MOD(AN40,100)<>0))),"违规：股数须为100股整数倍",IF(AND(OR(AL40<>"",AN40<>""),OR(_LockStatus="已锁仓",_LockStatus="解锁信息不完整")),"违规：锁仓期间禁止加仓",IF(AQ40>C40*D40,"违规：超过单笔风险上限",IF(SUM($AQ$2:$AQ$98)>账户数据!$B$7,"违规：超过账户风险上限","通过"))))))))) -> 通过
A41: 40 | B41: 五粮液 | C41: 211473 | D41: 0.02 | E41: 133.99 | F41: =IF(OR(C41="",D41="",E41="",N41="",C41<=0,D41<=0,E41<=N41),"",ROUNDDOWN((C41*D41)/(E41-N41)/100,0)*100) -> 400 | G41: =IF(A41="","",IF(H41<>"","已开仓",IF(账户数据!$B$23="已锁仓","禁止开仓：连续亏损达到上限",IF(账户数据!$B$23="解锁信息不完整","禁止开仓：请完整填写解锁信息",IF(OR(F41="",E41="",N41="",E41<=N41,账户数据!$B$7=""),"",IF(OR(AG41="",AH41="",AI41=""),"禁止开仓：交易预期未填写完整",IF(COUNTIFS(持仓跟踪!$A$2:$A$157,"止损计划",持仓跟踪!$B$2:$B$157,A41,持仓跟踪!$AC$2:$AC$157,"计划有效")=0,"禁止开仓：请先填写止损计划",IF(账户数据!$B$9+F41*(E41-N41)>=账户数据!$B$7,"禁止开仓：风险额度不足",IF(AJ41="周期与交易预期不匹配，请重新确认",IF(账户数据!$B$23="接近锁仓","允许开仓（接近锁仓；周期需复核）","允许开仓（周期需复核）"),IF(账户数据!$B$23="接近锁仓","允许开仓（接近锁仓）","允许开仓")))))))))) -> 已开仓 | H41: 400 | I41: 45365 | J41: 150 | K41: =IF(A41="","",IFERROR(LOOKUP(2,1/((持仓跟踪!$B$2:$B$157=A41)*(持仓跟踪!$X$2:$X$157="执行卖出")*(持仓跟踪!$Y$2:$Y$157<>"")),持仓跟踪!$Y$2:$Y$157),"")) -> 137.86 | L41: =IF(A41="","",IFERROR(LOOKUP(2,1/((持仓跟踪!$B$2:$B$157=A41)*(持仓跟踪!$X$2:$X$157="执行卖出")*(持仓跟踪!$Z$2:$Z$157<>"")),持仓跟踪!$Z$2:$Z$157),"")) -> 400 | M41: =IF(A41="","",IFERROR(LOOKUP(2,1/((持仓跟踪!$B$2:$B$157=A41)*(持仓跟踪!$X$2:$X$157="执行卖出")*(持仓跟踪!$H$2:$H$157<>"")),持仓跟踪!$H$2:$H$157),"")) -> 45373 | N41: 125 | P41: =IF(A41="","",IFERROR(LOOKUP(2,1/((持仓跟踪!$B$2:$B$157=A41)*(持仓跟踪!$X$2:$X$157="执行卖出")*(持仓跟踪!$AA$2:$AA$157<>"")),持仓跟踪!$AA$2:$AA$157),"")) | U41: =IF(OR(AO41="",J41="",AO41<=0),"",(J41-AO41)/AO41) -> 0.11948653 | V41: =IF(OR(AO41="",N41="",AO41<=0),"",(AO41-N41)/AO41) -> 0.067094559 | W41: =IF(OR(U41="",V41="",V41<=0),"",U41/V41) -> 1.7808676 | X41: =IF(OR(K41="",L41="",AP41=""),"",K41*L41-(E41*H41+IF(AND(AK41<>"",AL41<>""),AK41*AL41,0)+IF(AND(AM41<>"",AN41<>""),AM41*AN41,0))-IF(O41="",0,O41)-IF(P41="",0,P41)) -> 1548 | Y41: =IF(OR(X41="",AP41=""),"",IF((E41*H41+IF(AND(AK41<>"",AL41<>""),AK41*AL41,0)+IF(AND(AM41<>"",AN41<>""),AM41*AN41,0))+IF(O41="",0,O41)<=0,"",X41/((E41*H41+IF(AND(AK41<>"",AL41<>""),AK41*AL41,0)+IF(AND(AM41<>"",AN41<>""),AM41*AN41,0))+IF(O41="",0,O41)))) -> 0.028882752 | Z41: =IF(OR(AE41="",多次统计数据!$B$8=""),"",AE41-多次统计数据!$B$8) -> -0.065228544 | AA41: =IF(OR(I41="",M41="",M41<I41),"",M41-I41) -> 8 | AB41: =IF(OR(A41="",多次统计数据!$B$8="",多次统计数据!$B$6<=0,多次统计数据!$B$6>=1),"",1-POWER(1+多次统计数据!$B$8,-多次统计数据!$B$6/(1-多次统计数据!$B$6))) -> 0.053016657 | AC41: =IF(OR(AB41="",多次统计数据!$B$9=""),"",IF(多次统计数据!$B$9<AB41,"低于上限","达到或超过上限")) -> 低于上限 | AE41: =IF(OR(X41="",C41="",C41<=0),"",X41/C41) -> 0.0073200834 | AJ41: =IF(OR(AG41="",AH41=""),"",IF(OR(AND(AG41="短期博反弹",OR(AH41="1～3个交易日",AH41="4～10个交易日")),AND(AG41="突破冲新高",OR(AH41="4～10个交易日",AH41="11～20个交易日")),AND(AG41="趋势波段",OR(AH41="11～20个交易日",AH41="21～60个交易日",AH41="60个交易日以上"))),"匹配","周期与交易预期不匹配，请重新确认")) | AO41: =IF(OR(A41="",H41="",H41<=0),"",(E41*H41+IF(AND(AK41<>"",AL41<>""),AK41*AL41,0)+IF(AND(AM41<>"",AN41<>""),AM41*AN41,0))/AP41) -> 133.99 | AP41: =IF(OR(A41="",H41="",H41<=0),"",H41+IF(AL41="",0,AL41)+IF(AN41="",0,AN41)) -> 400 | AQ41: =IF(A41="","",IF(M41<>"",0,IF(OR(H41="",N41=""),"",MAX(E41-MAX(N41,IFERROR(SUMPRODUCT(MAX(((持仓跟踪!$A$2:$A$157="每日跟踪")*(持仓跟踪!$B$2:$B$157=A41))*持仓跟踪!$S$2:$S$157)),0)),0)*H41+IF(OR(AK41="",AL41=""),0,MAX(AK41-MAX(N41,IFERROR(SUMPRODUCT(MAX(((持仓跟踪!$A$2:$A$157="每日跟踪")*(持仓跟踪!$B$2:$B$157=A41))*持仓跟踪!$S$2:$S$157)),0)),0)*AL41)+IF(OR(AM41="",AN41=""),0,MAX(AM41-MAX(N41,IFERROR(SUMPRODUCT(MAX(((持仓跟踪!$A$2:$A$157="每日跟踪")*(持仓跟踪!$B$2:$B$157=A41))*持仓跟踪!$S$2:$S$157)),0)),0)*AN41)))) -> 0 | AR41: =IF(A41="","",IF(OR(E41="",H41=""),"违规：第一批价格或股数缺失",IF(OR(AND(AK41="",AL41<>""),AND(AK41<>"",AL41="")),"违规：第二批价格与股数须成对填写",IF(OR(AND(AM41="",AN41<>""),AND(AM41<>"",AN41="")),"违规：第三批价格与股数须成对填写",IF(AND(OR(AM41<>"",AN41<>""),OR(AK41="",AL41="")),"违规：必须先完成第二批",IF(OR(H41<=0,H41<>INT(H41),MOD(H41,100)<>0,AND(AL41<>"",OR(AL41<=0,AL41<>INT(AL41),MOD(AL41,100)<>0)),AND(AN41<>"",OR(AN41<=0,AN41<>INT(AN41),MOD(AN41,100)<>0))),"违规：股数须为100股整数倍",IF(AND(OR(AL41<>"",AN41<>""),OR(_LockStatus="已锁仓",_LockStatus="解锁信息不完整")),"违规：锁仓期间禁止加仓",IF(AQ41>C41*D41,"违规：超过单笔风险上限",IF(SUM($AQ$2:$AQ$98)>账户数据!$B$7,"违规：超过账户风险上限","通过"))))))))) -> 通过
A42: 41 | B42: 京东方 | C42: 213021 | D42: 0.02 | E42: 1.75 | F42: =IF(OR(C42="",D42="",E42="",N42="",C42<=0,D42<=0,E42<=N42),"",ROUNDDOWN((C42*D42)/(E42-N42)/100,0)*100) -> 42600 | G42: =IF(A42="","",IF(H42<>"","已开仓",IF(账户数据!$B$23="已锁仓","禁止开仓：连续亏损达到上限",IF(账户数据!$B$23="解锁信息不完整","禁止开仓：请完整填写解锁信息",IF(OR(F42="",E42="",N42="",E42<=N42,账户数据!$B$7=""),"",IF(OR(AG42="",AH42="",AI42=""),"禁止开仓：交易预期未填写完整",IF(COUNTIFS(持仓跟踪!$A$2:$A$157,"止损计划",持仓跟踪!$B$2:$B$157,A42,持仓跟踪!$AC$2:$AC$157,"计划有效")=0,"禁止开仓：请先填写止损计划",IF(账户数据!$B$9+F42*(E42-N42)>=账户数据!$B$7,"禁止开仓：风险额度不足",IF(AJ42="周期与交易预期不匹配，请重新确认",IF(账户数据!$B$23="接近锁仓","允许开仓（接近锁仓；周期需复核）","允许开仓（周期需复核）"),IF(账户数据!$B$23="接近锁仓","允许开仓（接近锁仓）","允许开仓")))))))))) -> 已开仓 | H42: 42600 | I42: 44942 | J42: 2 | K42: =IF(A42="","",IFERROR(LOOKUP(2,1/((持仓跟踪!$B$2:$B$157=A42)*(持仓跟踪!$X$2:$X$157="执行卖出")*(持仓跟踪!$Y$2:$Y$157<>"")),持仓跟踪!$Y$2:$Y$157),"")) -> 1.68 | L42: =IF(A42="","",IFERROR(LOOKUP(2,1/((持仓跟踪!$B$2:$B$157=A42)*(持仓跟踪!$X$2:$X$157="执行卖出")*(持仓跟踪!$Z$2:$Z$157<>"")),持仓跟踪!$Z$2:$Z$157),"")) -> 42600 | M42: =IF(A42="","",IFERROR(LOOKUP(2,1/((持仓跟踪!$B$2:$B$157=A42)*(持仓跟踪!$X$2:$X$157="执行卖出")*(持仓跟踪!$H$2:$H$157<>"")),持仓跟踪!$H$2:$H$157),"")) -> 41298 | N42: 1.65 | P42: =IF(A42="","",IFERROR(LOOKUP(2,1/((持仓跟踪!$B$2:$B$157=A42)*(持仓跟踪!$X$2:$X$157="执行卖出")*(持仓跟踪!$AA$2:$AA$157<>"")),持仓跟踪!$AA$2:$AA$157),"")) | U42: =IF(OR(AO42="",J42="",AO42<=0),"",(J42-AO42)/AO42) -> 0.14285714 | V42: =IF(OR(AO42="",N42="",AO42<=0),"",(AO42-N42)/AO42) -> 0.057142857 | W42: =IF(OR(U42="",V42="",V42<=0),"",U42/V42) -> 2.5 | X42: =IF(OR(K42="",L42="",AP42=""),"",K42*L42-(E42*H42+IF(AND(AK42<>"",AL42<>""),AK42*AL42,0)+IF(AND(AM42<>"",AN42<>""),AM42*AN42,0))-IF(O42="",0,O42)-IF(P42="",0,P42)) -> -2982 | Y42: =IF(OR(X42="",AP42=""),"",IF((E42*H42+IF(AND(AK42<>"",AL42<>""),AK42*AL42,0)+IF(AND(AM42<>"",AN42<>""),AM42*AN42,0))+IF(O42="",0,O42)<=0,"",X42/((E42*H42+IF(AND(AK42<>"",AL42<>""),AK42*AL42,0)+IF(AND(AM42<>"",AN42<>""),AM42*AN42,0))+IF(O42="",0,O42)))) -> -0.04 | Z42: =IF(OR(AE42="",多次统计数据!$B$8=""),"",AE42-多次统计数据!$B$8) -> -0.086547247 | AA42: =IF(OR(I42="",M42="",M42<I42),"",M42-I42) | AB42: =IF(OR(A42="",多次统计数据!$B$8="",多次统计数据!$B$6<=0,多次统计数据!$B$6>=1),"",1-POWER(1+多次统计数据!$B$8,-多次统计数据!$B$6/(1-多次统计数据!$B$6))) -> 0.053016657 | AC42: =IF(OR(AB42="",多次统计数据!$B$9=""),"",IF(多次统计数据!$B$9<AB42,"低于上限","达到或超过上限")) -> 低于上限 | AE42: =IF(OR(X42="",C42="",C42<=0),"",X42/C42) -> -0.01399862 | AJ42: =IF(OR(AG42="",AH42=""),"",IF(OR(AND(AG42="短期博反弹",OR(AH42="1～3个交易日",AH42="4～10个交易日")),AND(AG42="突破冲新高",OR(AH42="4～10个交易日",AH42="11～20个交易日")),AND(AG42="趋势波段",OR(AH42="11～20个交易日",AH42="21～60个交易日",AH42="60个交易日以上"))),"匹配","周期与交易预期不匹配，请重新确认")) | AO42: =IF(OR(A42="",H42="",H42<=0),"",(E42*H42+IF(AND(AK42<>"",AL42<>""),AK42*AL42,0)+IF(AND(AM42<>"",AN42<>""),AM42*AN42,0))/AP42) -> 1.75 | AP42: =IF(OR(A42="",H42="",H42<=0),"",H42+IF(AL42="",0,AL42)+IF(AN42="",0,AN42)) -> 42600 | AQ42: =IF(A42="","",IF(M42<>"",0,IF(OR(H42="",N42=""),"",MAX(E42-MAX(N42,IFERROR(SUMPRODUCT(MAX(((持仓跟踪!$A$2:$A$157="每日跟踪")*(持仓跟踪!$B$2:$B$157=A42))*持仓跟踪!$S$2:$S$157)),0)),0)*H42+IF(OR(AK42="",AL42=""),0,MAX(AK42-MAX(N42,IFERROR(SUMPRODUCT(MAX(((持仓跟踪!$A$2:$A$157="每日跟踪")*(持仓跟踪!$B$2:$B$157=A42))*持仓跟踪!$S$2:$S$157)),0)),0)*AL42)+IF(OR(AM42="",AN42=""),0,MAX(AM42-MAX(N42,IFERROR(SUMPRODUCT(MAX(((持仓跟踪!$A$2:$A$157="每日跟踪")*(持仓跟踪!$B$2:$B$157=A42))*持仓跟踪!$S$2:$S$157)),0)),0)*AN42)))) -> 0 | AR42: =IF(A42="","",IF(OR(E42="",H42=""),"违规：第一批价格或股数缺失",IF(OR(AND(AK42="",AL42<>""),AND(AK42<>"",AL42="")),"违规：第二批价格与股数须成对填写",IF(OR(AND(AM42="",AN42<>""),AND(AM42<>"",AN42="")),"违规：第三批价格与股数须成对填写",IF(AND(OR(AM42<>"",AN42<>""),OR(AK42="",AL42="")),"违规：必须先完成第二批",IF(OR(H42<=0,H42<>INT(H42),MOD(H42,100)<>0,AND(AL42<>"",OR(AL42<=0,AL42<>INT(AL42),MOD(AL42,100)<>0)),AND(AN42<>"",OR(AN42<=0,AN42<>INT(AN42),MOD(AN42,100)<>0))),"违规：股数须为100股整数倍",IF(AND(OR(AL42<>"",AN42<>""),OR(_LockStatus="已锁仓",_LockStatus="解锁信息不完整")),"违规：锁仓期间禁止加仓",IF(AQ42>C42*D42,"违规：超过单笔风险上限",IF(SUM($AQ$2:$AQ$98)>账户数据!$B$7,"违规：超过账户风险上限","通过"))))))))) -> 通过
A43: 42 | B43: 京东方 | C43: 210039 | D43: 0.02 | E43: 1.8 | F43: =IF(OR(C43="",D43="",E43="",N43="",C43<=0,D43<=0,E43<=N43),"",ROUNDDOWN((C43*D43)/(E43-N43)/100,0)*100) -> 42000 | G43: =IF(A43="","",IF(H43<>"","已开仓",IF(账户数据!$B$23="已锁仓","禁止开仓：连续亏损达到上限",IF(账户数据!$B$23="解锁信息不完整","禁止开仓：请完整填写解锁信息",IF(OR(F43="",E43="",N43="",E43<=N43,账户数据!$B$7=""),"",IF(OR(AG43="",AH43="",AI43=""),"禁止开仓：交易预期未填写完整",IF(COUNTIFS(持仓跟踪!$A$2:$A$157,"止损计划",持仓跟踪!$B$2:$B$157,A43,持仓跟踪!$AC$2:$AC$157,"计划有效")=0,"禁止开仓：请先填写止损计划",IF(账户数据!$B$9+F43*(E43-N43)>=账户数据!$B$7,"禁止开仓：风险额度不足",IF(AJ43="周期与交易预期不匹配，请重新确认",IF(账户数据!$B$23="接近锁仓","允许开仓（接近锁仓；周期需复核）","允许开仓（周期需复核）"),IF(账户数据!$B$23="接近锁仓","允许开仓（接近锁仓）","允许开仓")))))))))) -> 已开仓 | H43: 42000 | I43: 41346 | J43: 2 | K43: =IF(A43="","",IFERROR(LOOKUP(2,1/((持仓跟踪!$B$2:$B$157=A43)*(持仓跟踪!$X$2:$X$157="执行卖出")*(持仓跟踪!$Y$2:$Y$157<>"")),持仓跟踪!$Y$2:$Y$157),"")) -> 1.89 | L43: =IF(A43="","",IFERROR(LOOKUP(2,1/((持仓跟踪!$B$2:$B$157=A43)*(持仓跟踪!$X$2:$X$157="执行卖出")*(持仓跟踪!$Z$2:$Z$157<>"")),持仓跟踪!$Z$2:$Z$157),"")) -> 42000 | M43: =IF(A43="","",IFERROR(LOOKUP(2,1/((持仓跟踪!$B$2:$B$157=A43)*(持仓跟踪!$X$2:$X$157="执行卖出")*(持仓跟踪!$H$2:$H$157<>"")),持仓跟踪!$H$2:$H$157),"")) -> 41428 | N43: 1.7 | P43: =IF(A43="","",IFERROR(LOOKUP(2,1/((持仓跟踪!$B$2:$B$157=A43)*(持仓跟踪!$X$2:$X$157="执行卖出")*(持仓跟踪!$AA$2:$AA$157<>"")),持仓跟踪!$AA$2:$AA$157),"")) | U43: =IF(OR(AO43="",J43="",AO43<=0),"",(J43-AO43)/AO43) -> 0.11111111 | V43: =IF(OR(AO43="",N43="",AO43<=0),"",(AO43-N43)/AO43) -> 0.055555556 | W43: =IF(OR(U43="",V43="",V43<=0),"",U43/V43) -> 2 | X43: =IF(OR(K43="",L43="",AP43=""),"",K43*L43-(E43*H43+IF(AND(AK43<>"",AL43<>""),AK43*AL43,0)+IF(AND(AM43<>"",AN43<>""),AM43*AN43,0))-IF(O43="",0,O43)-IF(P43="",0,P43)) -> 3780 | Y43: =IF(OR(X43="",AP43=""),"",IF((E43*H43+IF(AND(AK43<>"",AL43<>""),AK43*AL43,0)+IF(AND(AM43<>"",AN43<>""),AM43*AN43,0))+IF(O43="",0,O43)<=0,"",X43/((E43*H43+IF(AND(AK43<>"",AL43<>""),AK43*AL43,0)+IF(AND(AM43<>"",AN43<>""),AM43*AN43,0))+IF(O43="",0,O43)))) -> 0.05 | Z43: =IF(OR(AE43="",多次统计数据!$B$8=""),"",AE43-多次统计数据!$B$8) -> -0.054551969 | AA43: =IF(OR(I43="",M43="",M43<I43),"",M43-I43) -> 82 | AB43: =IF(OR(A43="",多次统计数据!$B$8="",多次统计数据!$B$6<=0,多次统计数据!$B$6>=1),"",1-POWER(1+多次统计数据!$B$8,-多次统计数据!$B$6/(1-多次统计数据!$B$6))) -> 0.053016657 | AC43: =IF(OR(AB43="",多次统计数据!$B$9=""),"",IF(多次统计数据!$B$9<AB43,"低于上限","达到或超过上限")) -> 低于上限 | AE43: =IF(OR(X43="",C43="",C43<=0),"",X43/C43) -> 0.017996658 | AG43: 突破冲新高 | AH43: 4～10个交易日 | AJ43: =IF(OR(AG43="",AH43=""),"",IF(OR(AND(AG43="短期博反弹",OR(AH43="1～3个交易日",AH43="4～10个交易日")),AND(AG43="突破冲新高",OR(AH43="4～10个交易日",AH43="11～20个交易日")),AND(AG43="趋势波段",OR(AH43="11～20个交易日",AH43="21～60个交易日",AH43="60个交易日以上"))),"匹配","周期与交易预期不匹配，请重新确认")) -> 匹配 | AO43: =IF(OR(A43="",H43="",H43<=0),"",(E43*H43+IF(AND(AK43<>"",AL43<>""),AK43*AL43,0)+IF(AND(AM43<>"",AN43<>""),AM43*AN43,0))/AP43) -> 1.8 | AP43: =IF(OR(A43="",H43="",H43<=0),"",H43+IF(AL43="",0,AL43)+IF(AN43="",0,AN43)) -> 42000 | AQ43: =IF(A43="","",IF(M43<>"",0,IF(OR(H43="",N43=""),"",MAX(E43-MAX(N43,IFERROR(SUMPRODUCT(MAX(((持仓跟踪!$A$2:$A$157="每日跟踪")*(持仓跟踪!$B$2:$B$157=A43))*持仓跟踪!$S$2:$S$157)),0)),0)*H43+IF(OR(AK43="",AL43=""),0,MAX(AK43-MAX(N43,IFERROR(SUMPRODUCT(MAX(((持仓跟踪!$A$2:$A$157="每日跟踪")*(持仓跟踪!$B$2:$B$157=A43))*持仓跟踪!$S$2:$S$157)),0)),0)*AL43)+IF(OR(AM43="",AN43=""),0,MAX(AM43-MAX(N43,IFERROR(SUMPRODUCT(MAX(((持仓跟踪!$A$2:$A$157="每日跟踪")*(持仓跟踪!$B$2:$B$157=A43))*持仓跟踪!$S$2:$S$157)),0)),0)*AN43)))) -> 0 | AR43: =IF(A43="","",IF(OR(E43="",H43=""),"违规：第一批价格或股数缺失",IF(OR(AND(AK43="",AL43<>""),AND(AK43<>"",AL43="")),"违规：第二批价格与股数须成对填写",IF(OR(AND(AM43="",AN43<>""),AND(AM43<>"",AN43="")),"违规：第三批价格与股数须成对填写",IF(AND(OR(AM43<>"",AN43<>""),OR(AK43="",AL43="")),"违规：必须先完成第二批",IF(OR(H43<=0,H43<>INT(H43),MOD(H43,100)<>0,AND(AL43<>"",OR(AL43<=0,AL43<>INT(AL43),MOD(AL43,100)<>0)),AND(AN43<>"",OR(AN43<=0,AN43<>INT(AN43),MOD(AN43,100)<>0))),"违规：股数须为100股整数倍",IF(AND(OR(AL43<>"",AN43<>""),OR(_LockStatus="已锁仓",_LockStatus="解锁信息不完整")),"违规：锁仓期间禁止加仓",IF(AQ43>C43*D43,"违规：超过单笔风险上限",IF(SUM($AQ$2:$AQ$98)>账户数据!$B$7,"违规：超过账户风险上限","通过"))))))))) -> 通过
A44: 43 | B44: 京东方 | C44: 213819 | D44: 0.02 | E44: 1.59 | F44: =IF(OR(C44="",D44="",E44="",N44="",C44<=0,D44<=0,E44<=N44),"",ROUNDDOWN((C44*D44)/(E44-N44)/100,0)*100) -> 47500 | G44: =IF(A44="","",IF(H44<>"","已开仓",IF(账户数据!$B$23="已锁仓","禁止开仓：连续亏损达到上限",IF(账户数据!$B$23="解锁信息不完整","禁止开仓：请完整填写解锁信息",IF(OR(F44="",E44="",N44="",E44<=N44,账户数据!$B$7=""),"",IF(OR(AG44="",AH44="",AI44=""),"禁止开仓：交易预期未填写完整",IF(COUNTIFS(持仓跟踪!$A$2:$A$157,"止损计划",持仓跟踪!$B$2:$B$157,A44,持仓跟踪!$AC$2:$AC$157,"计划有效")=0,"禁止开仓：请先填写止损计划",IF(账户数据!$B$9+F44*(E44-N44)>=账户数据!$B$7,"禁止开仓：风险额度不足",IF(AJ44="周期与交易预期不匹配，请重新确认",IF(账户数据!$B$23="接近锁仓","允许开仓（接近锁仓；周期需复核）","允许开仓（周期需复核）"),IF(账户数据!$B$23="接近锁仓","允许开仓（接近锁仓）","允许开仓")))))))))) -> 已开仓 | H44: 47500 | I44: 41687 | J44: 1.8 | K44: =IF(A44="","",IFERROR(LOOKUP(2,1/((持仓跟踪!$B$2:$B$157=A44)*(持仓跟踪!$X$2:$X$157="执行卖出")*(持仓跟踪!$Y$2:$Y$157<>"")),持仓跟踪!$Y$2:$Y$157),"")) -> 1.77 | L44: =IF(A44="","",IFERROR(LOOKUP(2,1/((持仓跟踪!$B$2:$B$157=A44)*(持仓跟踪!$X$2:$X$157="执行卖出")*(持仓跟踪!$Z$2:$Z$157<>"")),持仓跟踪!$Z$2:$Z$157),"")) -> 47500 | M44: =IF(A44="","",IFERROR(LOOKUP(2,1/((持仓跟踪!$B$2:$B$157=A44)*(持仓跟踪!$X$2:$X$157="执行卖出")*(持仓跟踪!$H$2:$H$157<>"")),持仓跟踪!$H$2:$H$157),"")) -> 41696 | N44: 1.5 | P44: =IF(A44="","",IFERROR(LOOKUP(2,1/((持仓跟踪!$B$2:$B$157=A44)*(持仓跟踪!$X$2:$X$157="执行卖出")*(持仓跟踪!$AA$2:$AA$157<>"")),持仓跟踪!$AA$2:$AA$157),"")) | U44: =IF(OR(AO44="",J44="",AO44<=0),"",(J44-AO44)/AO44) -> 0.13207547 | V44: =IF(OR(AO44="",N44="",AO44<=0),"",(AO44-N44)/AO44) -> 0.056603774 | W44: =IF(OR(U44="",V44="",V44<=0),"",U44/V44) -> 2.3333333 | X44: =IF(OR(K44="",L44="",AP44=""),"",K44*L44-(E44*H44+IF(AND(AK44<>"",AL44<>""),AK44*AL44,0)+IF(AND(AM44<>"",AN44<>""),AM44*AN44,0))-IF(O44="",0,O44)-IF(P44="",0,P44)) -> 8550 | Y44: =IF(OR(X44="",AP44=""),"",IF((E44*H44+IF(AND(AK44<>"",AL44<>""),AK44*AL44,0)+IF(AND(AM44<>"",AN44<>""),AM44*AN44,0))+IF(O44="",0,O44)<=0,"",X44/((E44*H44+IF(AND(AK44<>"",AL44<>""),AK44*AL44,0)+IF(AND(AM44<>"",AN44<>""),AM44*AN44,0))+IF(O44="",0,O44)))) -> 0.11320755 | Z44: =IF(OR(AE44="",多次统计数据!$B$8=""),"",AE44-多次统计数据!$B$8) -> -0.032561535 | AA44: =IF(OR(I44="",M44="",M44<I44),"",M44-I44) -> 9 | AB44: =IF(OR(A44="",多次统计数据!$B$8="",多次统计数据!$B$6<=0,多次统计数据!$B$6>=1),"",1-POWER(1+多次统计数据!$B$8,-多次统计数据!$B$6/(1-多次统计数据!$B$6))) -> 0.053016657 | AC44: =IF(OR(AB44="",多次统计数据!$B$9=""),"",IF(多次统计数据!$B$9<AB44,"低于上限","达到或超过上限")) -> 低于上限 | AE44: =IF(OR(X44="",C44="",C44<=0),"",X44/C44) -> 0.039987092 | AG44: 突破冲新高 | AH44: 4～10个交易日 | AJ44: =IF(OR(AG44="",AH44=""),"",IF(OR(AND(AG44="短期博反弹",OR(AH44="1～3个交易日",AH44="4～10个交易日")),AND(AG44="突破冲新高",OR(AH44="4～10个交易日",AH44="11～20个交易日")),AND(AG44="趋势波段",OR(AH44="11～20个交易日",AH44="21～60个交易日",AH44="60个交易日以上"))),"匹配","周期与交易预期不匹配，请重新确认")) -> 匹配 | AO44: =IF(OR(A44="",H44="",H44<=0),"",(E44*H44+IF(AND(AK44<>"",AL44<>""),AK44*AL44,0)+IF(AND(AM44<>"",AN44<>""),AM44*AN44,0))/AP44) -> 1.59 | AP44: =IF(OR(A44="",H44="",H44<=0),"",H44+IF(AL44="",0,AL44)+IF(AN44="",0,AN44)) -> 47500 | AQ44: =IF(A44="","",IF(M44<>"",0,IF(OR(H44="",N44=""),"",MAX(E44-MAX(N44,IFERROR(SUMPRODUCT(MAX(((持仓跟踪!$A$2:$A$157="每日跟踪")*(持仓跟踪!$B$2:$B$157=A44))*持仓跟踪!$S$2:$S$157)),0)),0)*H44+IF(OR(AK44="",AL44=""),0,MAX(AK44-MAX(N44,IFERROR(SUMPRODUCT(MAX(((持仓跟踪!$A$2:$A$157="每日跟踪")*(持仓跟踪!$B$2:$B$157=A44))*持仓跟踪!$S$2:$S$157)),0)),0)*AL44)+IF(OR(AM44="",AN44=""),0,MAX(AM44-MAX(N44,IFERROR(SUMPRODUCT(MAX(((持仓跟踪!$A$2:$A$157="每日跟踪")*(持仓跟踪!$B$2:$B$157=A44))*持仓跟踪!$S$2:$S$157)),0)),0)*AN44)))) -> 0 | AR44: =IF(A44="","",IF(OR(E44="",H44=""),"违规：第一批价格或股数缺失",IF(OR(AND(AK44="",AL44<>""),AND(AK44<>"",AL44="")),"违规：第二批价格与股数须成对填写",IF(OR(AND(AM44="",AN44<>""),AND(AM44<>"",AN44="")),"违规：第三批价格与股数须成对填写",IF(AND(OR(AM44<>"",AN44<>""),OR(AK44="",AL44="")),"违规：必须先完成第二批",IF(OR(H44<=0,H44<>INT(H44),MOD(H44,100)<>0,AND(AL44<>"",OR(AL44<=0,AL44<>INT(AL44),MOD(AL44,100)<>0)),AND(AN44<>"",OR(AN44<=0,AN44<>INT(AN44),MOD(AN44,100)<>0))),"违规：股数须为100股整数倍",IF(AND(OR(AL44<>"",AN44<>""),OR(_LockStatus="已锁仓",_LockStatus="解锁信息不完整")),"违规：锁仓期间禁止加仓",IF(AQ44>C44*D44,"违规：超过单笔风险上限",IF(SUM($AQ$2:$AQ$98)>账户数据!$B$7,"违规：超过账户风险上限","通过"))))))))) -> 通过
A45: 44 | B45: 京东方 | C45: 222369 | D45: 0.02 | E45: 1.68 | F45: =IF(OR(C45="",D45="",E45="",N45="",C45<=0,D45<=0,E45<=N45),"",ROUNDDOWN((C45*D45)/(E45-N45)/100,0)*100) -> 148200 | G45: =IF(A45="","",IF(H45<>"","已开仓",IF(账户数据!$B$23="已锁仓","禁止开仓：连续亏损达到上限",IF(账户数据!$B$23="解锁信息不完整","禁止开仓：请完整填写解锁信息",IF(OR(F45="",E45="",N45="",E45<=N45,账户数据!$B$7=""),"",IF(OR(AG45="",AH45="",AI45=""),"禁止开仓：交易预期未填写完整",IF(COUNTIFS(持仓跟踪!$A$2:$A$157,"止损计划",持仓跟踪!$B$2:$B$157,A45,持仓跟踪!$AC$2:$AC$157,"计划有效")=0,"禁止开仓：请先填写止损计划",IF(账户数据!$B$9+F45*(E45-N45)>=账户数据!$B$7,"禁止开仓：风险额度不足",IF(AJ45="周期与交易预期不匹配，请重新确认",IF(账户数据!$B$23="接近锁仓","允许开仓（接近锁仓；周期需复核）","允许开仓（周期需复核）"),IF(账户数据!$B$23="接近锁仓","允许开仓（接近锁仓）","允许开仓")))))))))) -> 已开仓 | H45: 60000 | I45: 41723 | J45: 1.8 | K45: =IF(A45="","",IFERROR(LOOKUP(2,1/((持仓跟踪!$B$2:$B$157=A45)*(持仓跟踪!$X$2:$X$157="执行卖出")*(持仓跟踪!$Y$2:$Y$157<>"")),持仓跟踪!$Y$2:$Y$157),"")) -> 1.61 | L45: =IF(A45="","",IFERROR(LOOKUP(2,1/((持仓跟踪!$B$2:$B$157=A45)*(持仓跟踪!$X$2:$X$157="执行卖出")*(持仓跟踪!$Z$2:$Z$157<>"")),持仓跟踪!$Z$2:$Z$157),"")) -> 60000 | M45: =IF(A45="","",IFERROR(LOOKUP(2,1/((持仓跟踪!$B$2:$B$157=A45)*(持仓跟踪!$X$2:$X$157="执行卖出")*(持仓跟踪!$H$2:$H$157<>"")),持仓跟踪!$H$2:$H$157),"")) -> 41731 | N45: 1.65 | P45: =IF(A45="","",IFERROR(LOOKUP(2,1/((持仓跟踪!$B$2:$B$157=A45)*(持仓跟踪!$X$2:$X$157="执行卖出")*(持仓跟踪!$AA$2:$AA$157<>"")),持仓跟踪!$AA$2:$AA$157),"")) | U45: =IF(OR(AO45="",J45="",AO45<=0),"",(J45-AO45)/AO45) -> 0.071428571 | V45: =IF(OR(AO45="",N45="",AO45<=0),"",(AO45-N45)/AO45) -> 0.017857143 | W45: =IF(OR(U45="",V45="",V45<=0),"",U45/V45) -> 4 | X45: =IF(OR(K45="",L45="",AP45=""),"",K45*L45-(E45*H45+IF(AND(AK45<>"",AL45<>""),AK45*AL45,0)+IF(AND(AM45<>"",AN45<>""),AM45*AN45,0))-IF(O45="",0,O45)-IF(P45="",0,P45)) -> -4200 | Y45: =IF(OR(X45="",AP45=""),"",IF((E45*H45+IF(AND(AK45<>"",AL45<>""),AK45*AL45,0)+IF(AND(AM45<>"",AN45<>""),AM45*AN45,0))+IF(O45="",0,O45)<=0,"",X45/((E45*H45+IF(AND(AK45<>"",AL45<>""),AK45*AL45,0)+IF(AND(AM45<>"",AN45<>""),AM45*AN45,0))+IF(O45="",0,O45)))) -> -0.041666667 | Z45: =IF(OR(AE45="",多次统计数据!$B$8=""),"",AE45-多次统计数据!$B$8) -> -0.091436152 | AA45: =IF(OR(I45="",M45="",M45<I45),"",M45-I45) -> 8 | AB45: =IF(OR(A45="",多次统计数据!$B$8="",多次统计数据!$B$6<=0,多次统计数据!$B$6>=1),"",1-POWER(1+多次统计数据!$B$8,-多次统计数据!$B$6/(1-多次统计数据!$B$6))) -> 0.053016657 | AC45: =IF(OR(AB45="",多次统计数据!$B$9=""),"",IF(多次统计数据!$B$9<AB45,"低于上限","达到或超过上限")) -> 低于上限 | AE45: =IF(OR(X45="",C45="",C45<=0),"",X45/C45) -> -0.018887525 | AJ45: =IF(OR(AG45="",AH45=""),"",IF(OR(AND(AG45="短期博反弹",OR(AH45="1～3个交易日",AH45="4～10个交易日")),AND(AG45="突破冲新高",OR(AH45="4～10个交易日",AH45="11～20个交易日")),AND(AG45="趋势波段",OR(AH45="11～20个交易日",AH45="21～60个交易日",AH45="60个交易日以上"))),"匹配","周期与交易预期不匹配，请重新确认")) | AO45: =IF(OR(A45="",H45="",H45<=0),"",(E45*H45+IF(AND(AK45<>"",AL45<>""),AK45*AL45,0)+IF(AND(AM45<>"",AN45<>""),AM45*AN45,0))/AP45) -> 1.68 | AP45: =IF(OR(A45="",H45="",H45<=0),"",H45+IF(AL45="",0,AL45)+IF(AN45="",0,AN45)) -> 60000 | AQ45: =IF(A45="","",IF(M45<>"",0,IF(OR(H45="",N45=""),"",MAX(E45-MAX(N45,IFERROR(SUMPRODUCT(MAX(((持仓跟踪!$A$2:$A$157="每日跟踪")*(持仓跟踪!$B$2:$B$157=A45))*持仓跟踪!$S$2:$S$157)),0)),0)*H45+IF(OR(AK45="",AL45=""),0,MAX(AK45-MAX(N45,IFERROR(SUMPRODUCT(MAX(((持仓跟踪!$A$2:$A$157="每日跟踪")*(持仓跟踪!$B$2:$B$157=A45))*持仓跟踪!$S$2:$S$157)),0)),0)*AL45)+IF(OR(AM45="",AN45=""),0,MAX(AM45-MAX(N45,IFERROR(SUMPRODUCT(MAX(((持仓跟踪!$A$2:$A$157="每日跟踪")*(持仓跟踪!$B$2:$B$157=A45))*持仓跟踪!$S$2:$S$157)),0)),0)*AN45)))) -> 0 | AR45: =IF(A45="","",IF(OR(E45="",H45=""),"违规：第一批价格或股数缺失",IF(OR(AND(AK45="",AL45<>""),AND(AK45<>"",AL45="")),"违规：第二批价格与股数须成对填写",IF(OR(AND(AM45="",AN45<>""),AND(AM45<>"",AN45="")),"违规：第三批价格与股数须成对填写",IF(AND(OR(AM45<>"",AN45<>""),OR(AK45="",AL45="")),"违规：必须先完成第二批",IF(OR(H45<=0,H45<>INT(H45),MOD(H45,100)<>0,AND(AL45<>"",OR(AL45<=0,AL45<>INT(AL45),MOD(AL45,100)<>0)),AND(AN45<>"",OR(AN45<=0,AN45<>INT(AN45),MOD(AN45,100)<>0))),"违规：股数须为100股整数倍",IF(AND(OR(AL45<>"",AN45<>""),OR(_LockStatus="已锁仓",_LockStatus="解锁信息不完整")),"违规：锁仓期间禁止加仓",IF(AQ45>C45*D45,"违规：超过单笔风险上限",IF(SUM($AQ$2:$AQ$98)>账户数据!$B$7,"违规：超过账户风险上限","通过"))))))))) -> 通过
A46: 45 | B46: 京东方 | C46: 218169 | D46: 0.02 | E46: 1.65 | F46: =IF(OR(C46="",D46="",E46="",N46="",C46<=0,D46<=0,E46<=N46),"",ROUNDDOWN((C46*D46)/(E46-N46)/100,0)*100) -> 87200 | G46: =IF(A46="","",IF(H46<>"","已开仓",IF(账户数据!$B$23="已锁仓","禁止开仓：连续亏损达到上限",IF(账户数据!$B$23="解锁信息不完整","禁止开仓：请完整填写解锁信息",IF(OR(F46="",E46="",N46="",E46<=N46,账户数据!$B$7=""),"",IF(OR(AG46="",AH46="",AI46=""),"禁止开仓：交易预期未填写完整",IF(COUNTIFS(持仓跟踪!$A$2:$A$157,"止损计划",持仓跟踪!$B$2:$B$157,A46,持仓跟踪!$AC$2:$AC$157,"计划有效")=0,"禁止开仓：请先填写止损计划",IF(账户数据!$B$9+F46*(E46-N46)>=账户数据!$B$7,"禁止开仓：风险额度不足",IF(AJ46="周期与交易预期不匹配，请重新确认",IF(账户数据!$B$23="接近锁仓","允许开仓（接近锁仓；周期需复核）","允许开仓（周期需复核）"),IF(账户数据!$B$23="接近锁仓","允许开仓（接近锁仓）","允许开仓")))))))))) -> 已开仓 | H46: 87200 | I46: 41743 | J46: 1.8 | K46: =IF(A46="","",IFERROR(LOOKUP(2,1/((持仓跟踪!$B$2:$B$157=A46)*(持仓跟踪!$X$2:$X$157="执行卖出")*(持仓跟踪!$Y$2:$Y$157<>"")),持仓跟踪!$Y$2:$Y$157),"")) -> 1.46 | L46: =IF(A46="","",IFERROR(LOOKUP(2,1/((持仓跟踪!$B$2:$B$157=A46)*(持仓跟踪!$X$2:$X$157="执行卖出")*(持仓跟踪!$Z$2:$Z$157<>"")),持仓跟踪!$Z$2:$Z$157),"")) -> 87200 | M46: =IF(A46="","",IFERROR(LOOKUP(2,1/((持仓跟踪!$B$2:$B$157=A46)*(持仓跟踪!$X$2:$X$157="执行卖出")*(持仓跟踪!$H$2:$H$157<>"")),持仓跟踪!$H$2:$H$157),"")) -> 41757 | N46: 1.6 | P46: =IF(A46="","",IFERROR(LOOKUP(2,1/((持仓跟踪!$B$2:$B$157=A46)*(持仓跟踪!$X$2:$X$157="执行卖出")*(持仓跟踪!$AA$2:$AA$157<>"")),持仓跟踪!$AA$2:$AA$157),"")) | U46: =IF(OR(AO46="",J46="",AO46<=0),"",(J46-AO46)/AO46) -> 0.090909091 | V46: =IF(OR(AO46="",N46="",AO46<=0),"",(AO46-N46)/AO46) -> 0.03030303 | W46: =IF(OR(U46="",V46="",V46<=0),"",U46/V46) -> 3 | X46: =IF(OR(K46="",L46="",AP46=""),"",K46*L46-(E46*H46+IF(AND(AK46<>"",AL46<>""),AK46*AL46,0)+IF(AND(AM46<>"",AN46<>""),AM46*AN46,0))-IF(O46="",0,O46)-IF(P46="",0,P46)) -> -16568 | Y46: =IF(OR(X46="",AP46=""),"",IF((E46*H46+IF(AND(AK46<>"",AL46<>""),AK46*AL46,0)+IF(AND(AM46<>"",AN46<>""),AM46*AN46,0))+IF(O46="",0,O46)<=0,"",X46/((E46*H46+IF(AND(AK46<>"",AL46<>""),AK46*AL46,0)+IF(AND(AM46<>"",AN46<>""),AM46*AN46,0))+IF(O46="",0,O46)))) -> -0.11515152 | Z46: =IF(OR(AE46="",多次统计数据!$B$8=""),"",AE46-多次统计数据!$B$8) -> -0.14848976 | AA46: =IF(OR(I46="",M46="",M46<I46),"",M46-I46) -> 14 | AB46: =IF(OR(A46="",多次统计数据!$B$8="",多次统计数据!$B$6<=0,多次统计数据!$B$6>=1),"",1-POWER(1+多次统计数据!$B$8,-多次统计数据!$B$6/(1-多次统计数据!$B$6))) -> 0.053016657 | AC46: =IF(OR(AB46="",多次统计数据!$B$9=""),"",IF(多次统计数据!$B$9<AB46,"低于上限","达到或超过上限")) -> 低于上限 | AD46: 1-差 | AE46: =IF(OR(X46="",C46="",C46<=0),"",X46/C46) -> -0.075941128 | AF46: 没有及时止顺 | AJ46: =IF(OR(AG46="",AH46=""),"",IF(OR(AND(AG46="短期博反弹",OR(AH46="1～3个交易日",AH46="4～10个交易日")),AND(AG46="突破冲新高",OR(AH46="4～10个交易日",AH46="11～20个交易日")),AND(AG46="趋势波段",OR(AH46="11～20个交易日",AH46="21～60个交易日",AH46="60个交易日以上"))),"匹配","周期与交易预期不匹配，请重新确认")) | AO46: =IF(OR(A46="",H46="",H46<=0),"",(E46*H46+IF(AND(AK46<>"",AL46<>""),AK46*AL46,0)+IF(AND(AM46<>"",AN46<>""),AM46*AN46,0))/AP46) -> 1.65 | AP46: =IF(OR(A46="",H46="",H46<=0),"",H46+IF(AL46="",0,AL46)+IF(AN46="",0,AN46)) -> 87200 | AQ46: =IF(A46="","",IF(M46<>"",0,IF(OR(H46="",N46=""),"",MAX(E46-MAX(N46,IFERROR(SUMPRODUCT(MAX(((持仓跟踪!$A$2:$A$157="每日跟踪")*(持仓跟踪!$B$2:$B$157=A46))*持仓跟踪!$S$2:$S$157)),0)),0)*H46+IF(OR(AK46="",AL46=""),0,MAX(AK46-MAX(N46,IFERROR(SUMPRODUCT(MAX(((持仓跟踪!$A$2:$A$157="每日跟踪")*(持仓跟踪!$B$2:$B$157=A46))*持仓跟踪!$S$2:$S$157)),0)),0)*AL46)+IF(OR(AM46="",AN46=""),0,MAX(AM46-MAX(N46,IFERROR(SUMPRODUCT(MAX(((持仓跟踪!$A$2:$A$157="每日跟踪")*(持仓跟踪!$B$2:$B$157=A46))*持仓跟踪!$S$2:$S$157)),0)),0)*AN46)))) -> 0 | AR46: =IF(A46="","",IF(OR(E46="",H46=""),"违规：第一批价格或股数缺失",IF(OR(AND(AK46="",AL46<>""),AND(AK46<>"",AL46="")),"违规：第二批价格与股数须成对填写",IF(OR(AND(AM46="",AN46<>""),AND(AM46<>"",AN46="")),"违规：第三批价格与股数须成对填写",IF(AND(OR(AM46<>"",AN46<>""),OR(AK46="",AL46="")),"违规：必须先完成第二批",IF(OR(H46<=0,H46<>INT(H46),MOD(H46,100)<>0,AND(AL46<>"",OR(AL46<=0,AL46<>INT(AL46),MOD(AL46,100)<>0)),AND(AN46<>"",OR(AN46<=0,AN46<>INT(AN46),MOD(AN46,100)<>0))),"违规：股数须为100股整数倍",IF(AND(OR(AL46<>"",AN46<>""),OR(_LockStatus="已锁仓",_LockStatus="解锁信息不完整")),"违规：锁仓期间禁止加仓",IF(AQ46>C46*D46,"违规：超过单笔风险上限",IF(SUM($AQ$2:$AQ$98)>账户数据!$B$7,"违规：超过账户风险上限","通过"))))))))) -> 通过
A47: 46 | B47: 京东方 | C47: 201061 | D47: 0.02 | E47: 1.64 | F47: =IF(OR(C47="",D47="",E47="",N47="",C47<=0,D47<=0,E47<=N47),"",ROUNDDOWN((C47*D47)/(E47-N47)/100,0)*100) -> 100500 | G47: =IF(A47="","",IF(H47<>"","已开仓",IF(账户数据!$B$23="已锁仓","禁止开仓：连续亏损达到上限",IF(账户数据!$B$23="解锁信息不完整","禁止开仓：请完整填写解锁信息",IF(OR(F47="",E47="",N47="",E47<=N47,账户数据!$B$7=""),"",IF(OR(AG47="",AH47="",AI47=""),"禁止开仓：交易预期未填写完整",IF(COUNTIFS(持仓跟踪!$A$2:$A$157,"止损计划",持仓跟踪!$B$2:$B$157,A47,持仓跟踪!$AC$2:$AC$157,"计划有效")=0,"禁止开仓：请先填写止损计划",IF(账户数据!$B$9+F47*(E47-N47)>=账户数据!$B$7,"禁止开仓：风险额度不足",IF(AJ47="周期与交易预期不匹配，请重新确认",IF(账户数据!$B$23="接近锁仓","允许开仓（接近锁仓；周期需复核）","允许开仓（周期需复核）"),IF(账户数据!$B$23="接近锁仓","允许开仓（接近锁仓）","允许开仓")))))))))) -> 已开仓 | H47: 100500 | I47: 41859 | J47: 1.8 | K47: =IF(A47="","",IFERROR(LOOKUP(2,1/((持仓跟踪!$B$2:$B$157=A47)*(持仓跟踪!$X$2:$X$157="执行卖出")*(持仓跟踪!$Y$2:$Y$157<>"")),持仓跟踪!$Y$2:$Y$157),"")) -> 1.7 | L47: =IF(A47="","",IFERROR(LOOKUP(2,1/((持仓跟踪!$B$2:$B$157=A47)*(持仓跟踪!$X$2:$X$157="执行卖出")*(持仓跟踪!$Z$2:$Z$157<>"")),持仓跟踪!$Z$2:$Z$157),"")) -> 100500 | M47: =IF(A47="","",IFERROR(LOOKUP(2,1/((持仓跟踪!$B$2:$B$157=A47)*(持仓跟踪!$X$2:$X$157="执行卖出")*(持仓跟踪!$H$2:$H$157<>"")),持仓跟踪!$H$2:$H$157),"")) -> 41869 | N47: 1.6 | P47: =IF(A47="","",IFERROR(LOOKUP(2,1/((持仓跟踪!$B$2:$B$157=A47)*(持仓跟踪!$X$2:$X$157="执行卖出")*(持仓跟踪!$AA$2:$AA$157<>"")),持仓跟踪!$AA$2:$AA$157),"")) | U47: =IF(OR(AO47="",J47="",AO47<=0),"",(J47-AO47)/AO47) -> 0.097560976 | V47: =IF(OR(AO47="",N47="",AO47<=0),"",(AO47-N47)/AO47) -> 0.024390244 | W47: =IF(OR(U47="",V47="",V47<=0),"",U47/V47) -> 4 | X47: =IF(OR(K47="",L47="",AP47=""),"",K47*L47-(E47*H47+IF(AND(AK47<>"",AL47<>""),AK47*AL47,0)+IF(AND(AM47<>"",AN47<>""),AM47*AN47,0))-IF(O47="",0,O47)-IF(P47="",0,P47)) -> 6030 | Y47: =IF(OR(X47="",AP47=""),"",IF((E47*H47+IF(AND(AK47<>"",AL47<>""),AK47*AL47,0)+IF(AND(AM47<>"",AN47<>""),AM47*AN47,0))+IF(O47="",0,O47)<=0,"",X47/((E47*H47+IF(AND(AK47<>"",AL47<>""),AK47*AL47,0)+IF(AND(AM47<>"",AN47<>""),AM47*AN47,0))+IF(O47="",0,O47)))) -> 0.036585366 | Z47: =IF(OR(AE47="",多次统计数据!$B$8=""),"",AE47-多次统计数据!$B$8) -> -0.042557729 | AA47: =IF(OR(I47="",M47="",M47<I47),"",M47-I47) -> 10 | AB47: =IF(OR(A47="",多次统计数据!$B$8="",多次统计数据!$B$6<=0,多次统计数据!$B$6>=1),"",1-POWER(1+多次统计数据!$B$8,-多次统计数据!$B$6/(1-多次统计数据!$B$6))) -> 0.053016657 | AC47: =IF(OR(AB47="",多次统计数据!$B$9=""),"",IF(多次统计数据!$B$9<AB47,"低于上限","达到或超过上限")) -> 低于上限 | AE47: =IF(OR(X47="",C47="",C47<=0),"",X47/C47) -> 0.029990898 | AJ47: =IF(OR(AG47="",AH47=""),"",IF(OR(AND(AG47="短期博反弹",OR(AH47="1～3个交易日",AH47="4～10个交易日")),AND(AG47="突破冲新高",OR(AH47="4～10个交易日",AH47="11～20个交易日")),AND(AG47="趋势波段",OR(AH47="11～20个交易日",AH47="21～60个交易日",AH47="60个交易日以上"))),"匹配","周期与交易预期不匹配，请重新确认")) | AO47: =IF(OR(A47="",H47="",H47<=0),"",(E47*H47+IF(AND(AK47<>"",AL47<>""),AK47*AL47,0)+IF(AND(AM47<>"",AN47<>""),AM47*AN47,0))/AP47) -> 1.64 | AP47: =IF(OR(A47="",H47="",H47<=0),"",H47+IF(AL47="",0,AL47)+IF(AN47="",0,AN47)) -> 100500 | AQ47: =IF(A47="","",IF(M47<>"",0,IF(OR(H47="",N47=""),"",MAX(E47-MAX(N47,IFERROR(SUMPRODUCT(MAX(((持仓跟踪!$A$2:$A$157="每日跟踪")*(持仓跟踪!$B$2:$B$157=A47))*持仓跟踪!$S$2:$S$157)),0)),0)*H47+IF(OR(AK47="",AL47=""),0,MAX(AK47-MAX(N47,IFERROR(SUMPRODUCT(MAX(((持仓跟踪!$A$2:$A$157="每日跟踪")*(持仓跟踪!$B$2:$B$157=A47))*持仓跟踪!$S$2:$S$157)),0)),0)*AL47)+IF(OR(AM47="",AN47=""),0,MAX(AM47-MAX(N47,IFERROR(SUMPRODUCT(MAX(((持仓跟踪!$A$2:$A$157="每日跟踪")*(持仓跟踪!$B$2:$B$157=A47))*持仓跟踪!$S$2:$S$157)),0)),0)*AN47)))) -> 0 | AR47: =IF(A47="","",IF(OR(E47="",H47=""),"违规：第一批价格或股数缺失",IF(OR(AND(AK47="",AL47<>""),AND(AK47<>"",AL47="")),"违规：第二批价格与股数须成对填写",IF(OR(AND(AM47="",AN47<>""),AND(AM47<>"",AN47="")),"违规：第三批价格与股数须成对填写",IF(AND(OR(AM47<>"",AN47<>""),OR(AK47="",AL47="")),"违规：必须先完成第二批",IF(OR(H47<=0,H47<>INT(H47),MOD(H47,100)<>0,AND(AL47<>"",OR(AL47<=0,AL47<>INT(AL47),MOD(AL47,100)<>0)),AND(AN47<>"",OR(AN47<=0,AN47<>INT(AN47),MOD(AN47,100)<>0))),"违规：股数须为100股整数倍",IF(AND(OR(AL47<>"",AN47<>""),OR(_LockStatus="已锁仓",_LockStatus="解锁信息不完整")),"违规：锁仓期间禁止加仓",IF(AQ47>C47*D47,"违规：超过单笔风险上限",IF(SUM($AQ$2:$AQ$98)>账户数据!$B$7,"违规：超过账户风险上限","通过"))))))))) -> 通过
A48: 47 | B48: 京东方 | C48: 207631 | D48: 0.02 | E48: 1.8 | F48: =IF(OR(C48="",D48="",E48="",N48="",C48<=0,D48<=0,E48<=N48),"",ROUNDDOWN((C48*D48)/(E48-N48)/100,0)*100) -> 41500 | G48: =IF(A48="","",IF(H48<>"","已开仓",IF(账户数据!$B$23="已锁仓","禁止开仓：连续亏损达到上限",IF(账户数据!$B$23="解锁信息不完整","禁止开仓：请完整填写解锁信息",IF(OR(F48="",E48="",N48="",E48<=N48,账户数据!$B$7=""),"",IF(OR(AG48="",AH48="",AI48=""),"禁止开仓：交易预期未填写完整",IF(COUNTIFS(持仓跟踪!$A$2:$A$157,"止损计划",持仓跟踪!$B$2:$B$157,A48,持仓跟踪!$AC$2:$AC$157,"计划有效")=0,"禁止开仓：请先填写止损计划",IF(账户数据!$B$9+F48*(E48-N48)>=账户数据!$B$7,"禁止开仓：风险额度不足",IF(AJ48="周期与交易预期不匹配，请重新确认",IF(账户数据!$B$23="接近锁仓","允许开仓（接近锁仓；周期需复核）","允许开仓（周期需复核）"),IF(账户数据!$B$23="接近锁仓","允许开仓（接近锁仓）","允许开仓")))))))))) -> 已开仓 | H48: 41500 | I48: 41908 | J48: 2 | K48: =IF(A48="","",IFERROR(LOOKUP(2,1/((持仓跟踪!$B$2:$B$157=A48)*(持仓跟踪!$X$2:$X$157="执行卖出")*(持仓跟踪!$Y$2:$Y$157<>"")),持仓跟踪!$Y$2:$Y$157),"")) -> 2.38 | L48: =IF(A48="","",IFERROR(LOOKUP(2,1/((持仓跟踪!$B$2:$B$157=A48)*(持仓跟踪!$X$2:$X$157="执行卖出")*(持仓跟踪!$Z$2:$Z$157<>"")),持仓跟踪!$Z$2:$Z$157),"")) -> 41500 | M48: =IF(A48="","",IFERROR(LOOKUP(2,1/((持仓跟踪!$B$2:$B$157=A48)*(持仓跟踪!$X$2:$X$157="执行卖出")*(持仓跟踪!$H$2:$H$157<>"")),持仓跟踪!$H$2:$H$157),"")) -> 41982 | N48: 1.7 | P48: =IF(A48="","",IFERROR(LOOKUP(2,1/((持仓跟踪!$B$2:$B$157=A48)*(持仓跟踪!$X$2:$X$157="执行卖出")*(持仓跟踪!$AA$2:$AA$157<>"")),持仓跟踪!$AA$2:$AA$157),"")) | U48: =IF(OR(AO48="",J48="",AO48<=0),"",(J48-AO48)/AO48) -> 0.11111111 | V48: =IF(OR(AO48="",N48="",AO48<=0),"",(AO48-N48)/AO48) -> 0.055555556 | W48: =IF(OR(U48="",V48="",V48<=0),"",U48/V48) -> 2 | X48: =IF(OR(K48="",L48="",AP48=""),"",K48*L48-(E48*H48+IF(AND(AK48<>"",AL48<>""),AK48*AL48,0)+IF(AND(AM48<>"",AN48<>""),AM48*AN48,0))-IF(O48="",0,O48)-IF(P48="",0,P48)) -> 24070 | Y48: =IF(OR(X48="",AP48=""),"",IF((E48*H48+IF(AND(AK48<>"",AL48<>""),AK48*AL48,0)+IF(AND(AM48<>"",AN48<>""),AM48*AN48,0))+IF(O48="",0,O48)<=0,"",X48/((E48*H48+IF(AND(AK48<>"",AL48<>""),AK48*AL48,0)+IF(AND(AM48<>"",AN48<>""),AM48*AN48,0))+IF(O48="",0,O48)))) -> 0.32222222 | Z48: =IF(OR(AE48="",多次统计数据!$B$8=""),"",AE48-多次统计数据!$B$8) -> 0.043378186 | AA48: =IF(OR(I48="",M48="",M48<I48),"",M48-I48) -> 74 | AB48: =IF(OR(A48="",多次统计数据!$B$8="",多次统计数据!$B$6<=0,多次统计数据!$B$6>=1),"",1-POWER(1+多次统计数据!$B$8,-多次统计数据!$B$6/(1-多次统计数据!$B$6))) -> 0.053016657 | AC48: =IF(OR(AB48="",多次统计数据!$B$9=""),"",IF(多次统计数据!$B$9<AB48,"低于上限","达到或超过上限")) -> 低于上限 | AE48: =IF(OR(X48="",C48="",C48<=0),"",X48/C48) -> 0.11592681 | AJ48: =IF(OR(AG48="",AH48=""),"",IF(OR(AND(AG48="短期博反弹",OR(AH48="1～3个交易日",AH48="4～10个交易日")),AND(AG48="突破冲新高",OR(AH48="4～10个交易日",AH48="11～20个交易日")),AND(AG48="趋势波段",OR(AH48="11～20个交易日",AH48="21～60个交易日",AH48="60个交易日以上"))),"匹配","周期与交易预期不匹配，请重新确认")) | AO48: =IF(OR(A48="",H48="",H48<=0),"",(E48*H48+IF(AND(AK48<>"",AL48<>""),AK48*AL48,0)+IF(AND(AM48<>"",AN48<>""),AM48*AN48,0))/AP48) -> 1.8 | AP48: =IF(OR(A48="",H48="",H48<=0),"",H48+IF(AL48="",0,AL48)+IF(AN48="",0,AN48)) -> 41500 | AQ48: =IF(A48="","",IF(M48<>"",0,IF(OR(H48="",N48=""),"",MAX(E48-MAX(N48,IFERROR(SUMPRODUCT(MAX(((持仓跟踪!$A$2:$A$157="每日跟踪")*(持仓跟踪!$B$2:$B$157=A48))*持仓跟踪!$S$2:$S$157)),0)),0)*H48+IF(OR(AK48="",AL48=""),0,MAX(AK48-MAX(N48,IFERROR(SUMPRODUCT(MAX(((持仓跟踪!$A$2:$A$157="每日跟踪")*(持仓跟踪!$B$2:$B$157=A48))*持仓跟踪!$S$2:$S$157)),0)),0)*AL48)+IF(OR(AM48="",AN48=""),0,MAX(AM48-MAX(N48,IFERROR(SUMPRODUCT(MAX(((持仓跟踪!$A$2:$A$157="每日跟踪")*(持仓跟踪!$B$2:$B$157=A48))*持仓跟踪!$S$2:$S$157)),0)),0)*AN48)))) -> 0 | AR48: =IF(A48="","",IF(OR(E48="",H48=""),"违规：第一批价格或股数缺失",IF(OR(AND(AK48="",AL48<>""),AND(AK48<>"",AL48="")),"违规：第二批价格与股数须成对填写",IF(OR(AND(AM48="",AN48<>""),AND(AM48<>"",AN48="")),"违规：第三批价格与股数须成对填写",IF(AND(OR(AM48<>"",AN48<>""),OR(AK48="",AL48="")),"违规：必须先完成第二批",IF(OR(H48<=0,H48<>INT(H48),MOD(H48,100)<>0,AND(AL48<>"",OR(AL48<=0,AL48<>INT(AL48),MOD(AL48,100)<>0)),AND(AN48<>"",OR(AN48<=0,AN48<>INT(AN48),MOD(AN48,100)<>0))),"违规：股数须为100股整数倍",IF(AND(OR(AL48<>"",AN48<>""),OR(_LockStatus="已锁仓",_LockStatus="解锁信息不完整")),"违规：锁仓期间禁止加仓",IF(AQ48>C48*D48,"违规：超过单笔风险上限",IF(SUM($AQ$2:$AQ$98)>账户数据!$B$7,"违规：超过账户风险上限","通过"))))))))) -> 通过
A49: 48 | B49: 京东方 | C49: 231701 | D49: 0.02 | E49: 2.57 | F49: =IF(OR(C49="",D49="",E49="",N49="",C49<=0,D49<=0,E49<=N49),"",ROUNDDOWN((C49*D49)/(E49-N49)/100,0)*100) -> 17100 | G49: =IF(A49="","",IF(H49<>"","已开仓",IF(账户数据!$B$23="已锁仓","禁止开仓：连续亏损达到上限",IF(账户数据!$B$23="解锁信息不完整","禁止开仓：请完整填写解锁信息",IF(OR(F49="",E49="",N49="",E49<=N49,账户数据!$B$7=""),"",IF(OR(AG49="",AH49="",AI49=""),"禁止开仓：交易预期未填写完整",IF(COUNTIFS(持仓跟踪!$A$2:$A$157,"止损计划",持仓跟踪!$B$2:$B$157,A49,持仓跟踪!$AC$2:$AC$157,"计划有效")=0,"禁止开仓：请先填写止损计划",IF(账户数据!$B$9+F49*(E49-N49)>=账户数据!$B$7,"禁止开仓：风险额度不足",IF(AJ49="周期与交易预期不匹配，请重新确认",IF(账户数据!$B$23="接近锁仓","允许开仓（接近锁仓；周期需复核）","允许开仓（周期需复核）"),IF(账户数据!$B$23="接近锁仓","允许开仓（接近锁仓）","允许开仓")))))))))) -> 已开仓 | H49: 17100 | I49: 41989 | J49: 3 | K49: =IF(A49="","",IFERROR(LOOKUP(2,1/((持仓跟踪!$B$2:$B$157=A49)*(持仓跟踪!$X$2:$X$157="执行卖出")*(持仓跟踪!$Y$2:$Y$157<>"")),持仓跟踪!$Y$2:$Y$157),"")) -> 2.56 | L49: =IF(A49="","",IFERROR(LOOKUP(2,1/((持仓跟踪!$B$2:$B$157=A49)*(持仓跟踪!$X$2:$X$157="执行卖出")*(持仓跟踪!$Z$2:$Z$157<>"")),持仓跟踪!$Z$2:$Z$157),"")) -> 17100 | M49: =IF(A49="","",IFERROR(LOOKUP(2,1/((持仓跟踪!$B$2:$B$157=A49)*(持仓跟踪!$X$2:$X$157="执行卖出")*(持仓跟踪!$H$2:$H$157<>"")),持仓跟踪!$H$2:$H$157),"")) -> 42016 | N49: 2.3 | P49: =IF(A49="","",IFERROR(LOOKUP(2,1/((持仓跟踪!$B$2:$B$157=A49)*(持仓跟踪!$X$2:$X$157="执行卖出")*(持仓跟踪!$AA$2:$AA$157<>"")),持仓跟踪!$AA$2:$AA$157),"")) | U49: =IF(OR(AO49="",J49="",AO49<=0),"",(J49-AO49)/AO49) -> 0.16731518 | V49: =IF(OR(AO49="",N49="",AO49<=0),"",(AO49-N49)/AO49) -> 0.10505837 | W49: =IF(OR(U49="",V49="",V49<=0),"",U49/V49) -> 1.5925926 | X49: =IF(OR(K49="",L49="",AP49=""),"",K49*L49-(E49*H49+IF(AND(AK49<>"",AL49<>""),AK49*AL49,0)+IF(AND(AM49<>"",AN49<>""),AM49*AN49,0))-IF(O49="",0,O49)-IF(P49="",0,P49)) -> -171 | Y49: =IF(OR(X49="",AP49=""),"",IF((E49*H49+IF(AND(AK49<>"",AL49<>""),AK49*AL49,0)+IF(AND(AM49<>"",AN49<>""),AM49*AN49,0))+IF(O49="",0,O49)<=0,"",X49/((E49*H49+IF(AND(AK49<>"",AL49<>""),AK49*AL49,0)+IF(AND(AM49<>"",AN49<>""),AM49*AN49,0))+IF(O49="",0,O49)))) -> -0.0038910506 | Z49: =IF(OR(AE49="",多次统计数据!$B$8=""),"",AE49-多次统计数据!$B$8) -> -0.073286647 | AA49: =IF(OR(I49="",M49="",M49<I49),"",M49-I49) -> 27 | AB49: =IF(OR(A49="",多次统计数据!$B$8="",多次统计数据!$B$6<=0,多次统计数据!$B$6>=1),"",1-POWER(1+多次统计数据!$B$8,-多次统计数据!$B$6/(1-多次统计数据!$B$6))) -> 0.053016657 | AC49: =IF(OR(AB49="",多次统计数据!$B$9=""),"",IF(多次统计数据!$B$9<AB49,"低于上限","达到或超过上限")) -> 低于上限 | AE49: =IF(OR(X49="",C49="",C49<=0),"",X49/C49) -> -0.00073802012 | AG49: 趋势波段 | AH49: 11～20个交易日 | AJ49: =IF(OR(AG49="",AH49=""),"",IF(OR(AND(AG49="短期博反弹",OR(AH49="1～3个交易日",AH49="4～10个交易日")),AND(AG49="突破冲新高",OR(AH49="4～10个交易日",AH49="11～20个交易日")),AND(AG49="趋势波段",OR(AH49="11～20个交易日",AH49="21～60个交易日",AH49="60个交易日以上"))),"匹配","周期与交易预期不匹配，请重新确认")) -> 匹配 | AO49: =IF(OR(A49="",H49="",H49<=0),"",(E49*H49+IF(AND(AK49<>"",AL49<>""),AK49*AL49,0)+IF(AND(AM49<>"",AN49<>""),AM49*AN49,0))/AP49) -> 2.57 | AP49: =IF(OR(A49="",H49="",H49<=0),"",H49+IF(AL49="",0,AL49)+IF(AN49="",0,AN49)) -> 17100 | AQ49: =IF(A49="","",IF(M49<>"",0,IF(OR(H49="",N49=""),"",MAX(E49-MAX(N49,IFERROR(SUMPRODUCT(MAX(((持仓跟踪!$A$2:$A$157="每日跟踪")*(持仓跟踪!$B$2:$B$157=A49))*持仓跟踪!$S$2:$S$157)),0)),0)*H49+IF(OR(AK49="",AL49=""),0,MAX(AK49-MAX(N49,IFERROR(SUMPRODUCT(MAX(((持仓跟踪!$A$2:$A$157="每日跟踪")*(持仓跟踪!$B$2:$B$157=A49))*持仓跟踪!$S$2:$S$157)),0)),0)*AL49)+IF(OR(AM49="",AN49=""),0,MAX(AM49-MAX(N49,IFERROR(SUMPRODUCT(MAX(((持仓跟踪!$A$2:$A$157="每日跟踪")*(持仓跟踪!$B$2:$B$157=A49))*持仓跟踪!$S$2:$S$157)),0)),0)*AN49)))) -> 0 | AR49: =IF(A49="","",IF(OR(E49="",H49=""),"违规：第一批价格或股数缺失",IF(OR(AND(AK49="",AL49<>""),AND(AK49<>"",AL49="")),"违规：第二批价格与股数须成对填写",IF(OR(AND(AM49="",AN49<>""),AND(AM49<>"",AN49="")),"违规：第三批价格与股数须成对填写",IF(AND(OR(AM49<>"",AN49<>""),OR(AK49="",AL49="")),"违规：必须先完成第二批",IF(OR(H49<=0,H49<>INT(H49),MOD(H49,100)<>0,AND(AL49<>"",OR(AL49<=0,AL49<>INT(AL49),MOD(AL49,100)<>0)),AND(AN49<>"",OR(AN49<=0,AN49<>INT(AN49),MOD(AN49,100)<>0))),"违规：股数须为100股整数倍",IF(AND(OR(AL49<>"",AN49<>""),OR(_LockStatus="已锁仓",_LockStatus="解锁信息不完整")),"违规：锁仓期间禁止加仓",IF(AQ49>C49*D49,"违规：超过单笔风险上限",IF(SUM($AQ$2:$AQ$98)>账户数据!$B$7,"违规：超过账户风险上限","通过"))))))))) -> 通过
A50: 49 | B50: 京东方 | C50: 231530 | D50: 0.02 | E50: 4.06 | F50: =IF(OR(C50="",D50="",E50="",N50="",C50<=0,D50<=0,E50<=N50),"",ROUNDDOWN((C50*D50)/(E50-N50)/100,0)*100) -> 12800 | G50: =IF(A50="","",IF(H50<>"","已开仓",IF(账户数据!$B$23="已锁仓","禁止开仓：连续亏损达到上限",IF(账户数据!$B$23="解锁信息不完整","禁止开仓：请完整填写解锁信息",IF(OR(F50="",E50="",N50="",E50<=N50,账户数据!$B$7=""),"",IF(OR(AG50="",AH50="",AI50=""),"禁止开仓：交易预期未填写完整",IF(COUNTIFS(持仓跟踪!$A$2:$A$157,"止损计划",持仓跟踪!$B$2:$B$157,A50,持仓跟踪!$AC$2:$AC$157,"计划有效")=0,"禁止开仓：请先填写止损计划",IF(账户数据!$B$9+F50*(E50-N50)>=账户数据!$B$7,"禁止开仓：风险额度不足",IF(AJ50="周期与交易预期不匹配，请重新确认",IF(账户数据!$B$23="接近锁仓","允许开仓（接近锁仓；周期需复核）","允许开仓（周期需复核）"),IF(账户数据!$B$23="接近锁仓","允许开仓（接近锁仓）","允许开仓")))))))))) -> 已开仓 | H50: 12800 | I50: 42032 | J50: 4.5 | K50: =IF(A50="","",IFERROR(LOOKUP(2,1/((持仓跟踪!$B$2:$B$157=A50)*(持仓跟踪!$X$2:$X$157="执行卖出")*(持仓跟踪!$Y$2:$Y$157<>"")),持仓跟踪!$Y$2:$Y$157),"")) -> 3.63 | L50: =IF(A50="","",IFERROR(LOOKUP(2,1/((持仓跟踪!$B$2:$B$157=A50)*(持仓跟踪!$X$2:$X$157="执行卖出")*(持仓跟踪!$Z$2:$Z$157<>"")),持仓跟踪!$Z$2:$Z$157),"")) -> 12800 | M50: =IF(A50="","",IFERROR(LOOKUP(2,1/((持仓跟踪!$B$2:$B$157=A50)*(持仓跟踪!$X$2:$X$157="执行卖出")*(持仓跟踪!$H$2:$H$157<>"")),持仓跟踪!$H$2:$H$157),"")) -> 42131 | N50: 3.7 | P50: =IF(A50="","",IFERROR(LOOKUP(2,1/((持仓跟踪!$B$2:$B$157=A50)*(持仓跟踪!$X$2:$X$157="执行卖出")*(持仓跟踪!$AA$2:$AA$157<>"")),持仓跟踪!$AA$2:$AA$157),"")) | U50: =IF(OR(AO50="",J50="",AO50<=0),"",(J50-AO50)/AO50) -> 0.10837438 | V50: =IF(OR(AO50="",N50="",AO50<=0),"",(AO50-N50)/AO50) -> 0.088669951 | W50: =IF(OR(U50="",V50="",V50<=0),"",U50/V50) -> 1.2222222 | X50: =IF(OR(K50="",L50="",AP50=""),"",K50*L50-(E50*H50+IF(AND(AK50<>"",AL50<>""),AK50*AL50,0)+IF(AND(AM50<>"",AN50<>""),AM50*AN50,0))-IF(O50="",0,O50)-IF(P50="",0,P50)) -> -5504 | Y50: =IF(OR(X50="",AP50=""),"",IF((E50*H50+IF(AND(AK50<>"",AL50<>""),AK50*AL50,0)+IF(AND(AM50<>"",AN50<>""),AM50*AN50,0))+IF(O50="",0,O50)<=0,"",X50/((E50*H50+IF(AND(AK50<>"",AL50<>""),AK50*AL50,0)+IF(AND(AM50<>"",AN50<>""),AM50*AN50,0))+IF(O50="",0,O50)))) -> -0.10591133 | Z50: =IF(OR(AE50="",多次统计数据!$B$8=""),"",AE50-多次统计数据!$B$8) -> -0.096320924 | AA50: =IF(OR(I50="",M50="",M50<I50),"",M50-I50) -> 99 | AB50: =IF(OR(A50="",多次统计数据!$B$8="",多次统计数据!$B$6<=0,多次统计数据!$B$6>=1),"",1-POWER(1+多次统计数据!$B$8,-多次统计数据!$B$6/(1-多次统计数据!$B$6))) -> 0.053016657 | AC50: =IF(OR(AB50="",多次统计数据!$B$9=""),"",IF(多次统计数据!$B$9<AB50,"低于上限","达到或超过上限")) -> 低于上限 | AE50: =IF(OR(X50="",C50="",C50<=0),"",X50/C50) -> -0.023772297 | AJ50: =IF(OR(AG50="",AH50=""),"",IF(OR(AND(AG50="短期博反弹",OR(AH50="1～3个交易日",AH50="4～10个交易日")),AND(AG50="突破冲新高",OR(AH50="4～10个交易日",AH50="11～20个交易日")),AND(AG50="趋势波段",OR(AH50="11～20个交易日",AH50="21～60个交易日",AH50="60个交易日以上"))),"匹配","周期与交易预期不匹配，请重新确认")) | AO50: =IF(OR(A50="",H50="",H50<=0),"",(E50*H50+IF(AND(AK50<>"",AL50<>""),AK50*AL50,0)+IF(AND(AM50<>"",AN50<>""),AM50*AN50,0))/AP50) -> 4.06 | AP50: =IF(OR(A50="",H50="",H50<=0),"",H50+IF(AL50="",0,AL50)+IF(AN50="",0,AN50)) -> 12800 | AQ50: =IF(A50="","",IF(M50<>"",0,IF(OR(H50="",N50=""),"",MAX(E50-MAX(N50,IFERROR(SUMPRODUCT(MAX(((持仓跟踪!$A$2:$A$157="每日跟踪")*(持仓跟踪!$B$2:$B$157=A50))*持仓跟踪!$S$2:$S$157)),0)),0)*H50+IF(OR(AK50="",AL50=""),0,MAX(AK50-MAX(N50,IFERROR(SUMPRODUCT(MAX(((持仓跟踪!$A$2:$A$157="每日跟踪")*(持仓跟踪!$B$2:$B$157=A50))*持仓跟踪!$S$2:$S$157)),0)),0)*AL50)+IF(OR(AM50="",AN50=""),0,MAX(AM50-MAX(N50,IFERROR(SUMPRODUCT(MAX(((持仓跟踪!$A$2:$A$157="每日跟踪")*(持仓跟踪!$B$2:$B$157=A50))*持仓跟踪!$S$2:$S$157)),0)),0)*AN50)))) -> 0 | AR50: =IF(A50="","",IF(OR(E50="",H50=""),"违规：第一批价格或股数缺失",IF(OR(AND(AK50="",AL50<>""),AND(AK50<>"",AL50="")),"违规：第二批价格与股数须成对填写",IF(OR(AND(AM50="",AN50<>""),AND(AM50<>"",AN50="")),"违规：第三批价格与股数须成对填写",IF(AND(OR(AM50<>"",AN50<>""),OR(AK50="",AL50="")),"违规：必须先完成第二批",IF(OR(H50<=0,H50<>INT(H50),MOD(H50,100)<>0,AND(AL50<>"",OR(AL50<=0,AL50<>INT(AL50),MOD(AL50,100)<>0)),AND(AN50<>"",OR(AN50<=0,AN50<>INT(AN50),MOD(AN50,100)<>0))),"违规：股数须为100股整数倍",IF(AND(OR(AL50<>"",AN50<>""),OR(_LockStatus="已锁仓",_LockStatus="解锁信息不完整")),"违规：锁仓期间禁止加仓",IF(AQ50>C50*D50,"违规：超过单笔风险上限",IF(SUM($AQ$2:$AQ$98)>账户数据!$B$7,"违规：超过账户风险上限","通过"))))))))) -> 通过
A51: 50 | B51: 京东方 | C51: 226026 | D51: 0.02 | E51: 4.44 | F51: =IF(OR(C51="",D51="",E51="",N51="",C51<=0,D51<=0,E51<=N51),"",ROUNDDOWN((C51*D51)/(E51-N51)/100,0)*100) -> 18800 | G51: =IF(A51="","",IF(H51<>"","已开仓",IF(账户数据!$B$23="已锁仓","禁止开仓：连续亏损达到上限",IF(账户数据!$B$23="解锁信息不完整","禁止开仓：请完整填写解锁信息",IF(OR(F51="",E51="",N51="",E51<=N51,账户数据!$B$7=""),"",IF(OR(AG51="",AH51="",AI51=""),"禁止开仓：交易预期未填写完整",IF(COUNTIFS(持仓跟踪!$A$2:$A$157,"止损计划",持仓跟踪!$B$2:$B$157,A51,持仓跟踪!$AC$2:$AC$157,"计划有效")=0,"禁止开仓：请先填写止损计划",IF(账户数据!$B$9+F51*(E51-N51)>=账户数据!$B$7,"禁止开仓：风险额度不足",IF(AJ51="周期与交易预期不匹配，请重新确认",IF(账户数据!$B$23="接近锁仓","允许开仓（接近锁仓；周期需复核）","允许开仓（周期需复核）"),IF(账户数据!$B$23="接近锁仓","允许开仓（接近锁仓）","允许开仓")))))))))) -> 已开仓 | H51: 18800 | I51: 42159 | J51: 5 | K51: =IF(A51="","",IFERROR(LOOKUP(2,1/((持仓跟踪!$B$2:$B$157=A51)*(持仓跟踪!$X$2:$X$157="执行卖出")*(持仓跟踪!$Y$2:$Y$157<>"")),持仓跟踪!$Y$2:$Y$157),"")) -> 3.03 | L51: =IF(A51="","",IFERROR(LOOKUP(2,1/((持仓跟踪!$B$2:$B$157=A51)*(持仓跟踪!$X$2:$X$157="执行卖出")*(持仓跟踪!$Z$2:$Z$157<>"")),持仓跟踪!$Z$2:$Z$157),"")) -> 18800 | M51: =IF(A51="","",IFERROR(LOOKUP(2,1/((持仓跟踪!$B$2:$B$157=A51)*(持仓跟踪!$X$2:$X$157="执行卖出")*(持仓跟踪!$H$2:$H$157<>"")),持仓跟踪!$H$2:$H$157),"")) -> 42221 | N51: 4.2 | P51: =IF(A51="","",IFERROR(LOOKUP(2,1/((持仓跟踪!$B$2:$B$157=A51)*(持仓跟踪!$X$2:$X$157="执行卖出")*(持仓跟踪!$AA$2:$AA$157<>"")),持仓跟踪!$AA$2:$AA$157),"")) | U51: =IF(OR(AO51="",J51="",AO51<=0),"",(J51-AO51)/AO51) -> 0.12612613 | V51: =IF(OR(AO51="",N51="",AO51<=0),"",(AO51-N51)/AO51) -> 0.054054054 | W51: =IF(OR(U51="",V51="",V51<=0),"",U51/V51) -> 2.3333333 | X51: =IF(OR(K51="",L51="",AP51=""),"",K51*L51-(E51*H51+IF(AND(AK51<>"",AL51<>""),AK51*AL51,0)+IF(AND(AM51<>"",AN51<>""),AM51*AN51,0))-IF(O51="",0,O51)-IF(P51="",0,P51)) -> -26508 | Y51: =IF(OR(X51="",AP51=""),"",IF((E51*H51+IF(AND(AK51<>"",AL51<>""),AK51*AL51,0)+IF(AND(AM51<>"",AN51<>""),AM51*AN51,0))+IF(O51="",0,O51)<=0,"",X51/((E51*H51+IF(AND(AK51<>"",AL51<>""),AK51*AL51,0)+IF(AND(AM51<>"",AN51<>""),AM51*AN51,0))+IF(O51="",0,O51)))) -> -0.31756757 | Z51: =IF(OR(AE51="",多次统计数据!$B$8=""),"",AE51-多次统计数据!$B$8) -> -0.18982717 | AA51: =IF(OR(I51="",M51="",M51<I51),"",M51-I51) -> 62 | AB51: =IF(OR(A51="",多次统计数据!$B$8="",多次统计数据!$B$6<=0,多次统计数据!$B$6>=1),"",1-POWER(1+多次统计数据!$B$8,-多次统计数据!$B$6/(1-多次统计数据!$B$6))) -> 0.053016657 | AC51: =IF(OR(AB51="",多次统计数据!$B$9=""),"",IF(多次统计数据!$B$9<AB51,"低于上限","达到或超过上限")) -> 低于上限 | AE51: =IF(OR(X51="",C51="",C51<=0),"",X51/C51) -> -0.11727854 | AG51: 突破冲新高 | AH51: 4～10个交易日 | AJ51: =IF(OR(AG51="",AH51=""),"",IF(OR(AND(AG51="短期博反弹",OR(AH51="1～3个交易日",AH51="4～10个交易日")),AND(AG51="突破冲新高",OR(AH51="4～10个交易日",AH51="11～20个交易日")),AND(AG51="趋势波段",OR(AH51="11～20个交易日",AH51="21～60个交易日",AH51="60个交易日以上"))),"匹配","周期与交易预期不匹配，请重新确认")) -> 匹配 | AO51: =IF(OR(A51="",H51="",H51<=0),"",(E51*H51+IF(AND(AK51<>"",AL51<>""),AK51*AL51,0)+IF(AND(AM51<>"",AN51<>""),AM51*AN51,0))/AP51) -> 4.44 | AP51: =IF(OR(A51="",H51="",H51<=0),"",H51+IF(AL51="",0,AL51)+IF(AN51="",0,AN51)) -> 18800 | AQ51: =IF(A51="","",IF(M51<>"",0,IF(OR(H51="",N51=""),"",MAX(E51-MAX(N51,IFERROR(SUMPRODUCT(MAX(((持仓跟踪!$A$2:$A$157="每日跟踪")*(持仓跟踪!$B$2:$B$157=A51))*持仓跟踪!$S$2:$S$157)),0)),0)*H51+IF(OR(AK51="",AL51=""),0,MAX(AK51-MAX(N51,IFERROR(SUMPRODUCT(MAX(((持仓跟踪!$A$2:$A$157="每日跟踪")*(持仓跟踪!$B$2:$B$157=A51))*持仓跟踪!$S$2:$S$157)),0)),0)*AL51)+IF(OR(AM51="",AN51=""),0,MAX(AM51-MAX(N51,IFERROR(SUMPRODUCT(MAX(((持仓跟踪!$A$2:$A$157="每日跟踪")*(持仓跟踪!$B$2:$B$157=A51))*持仓跟踪!$S$2:$S$157)),0)),0)*AN51)))) -> 0 | AR51: =IF(A51="","",IF(OR(E51="",H51=""),"违规：第一批价格或股数缺失",IF(OR(AND(AK51="",AL51<>""),AND(AK51<>"",AL51="")),"违规：第二批价格与股数须成对填写",IF(OR(AND(AM51="",AN51<>""),AND(AM51<>"",AN51="")),"违规：第三批价格与股数须成对填写",IF(AND(OR(AM51<>"",AN51<>""),OR(AK51="",AL51="")),"违规：必须先完成第二批",IF(OR(H51<=0,H51<>INT(H51),MOD(H51,100)<>0,AND(AL51<>"",OR(AL51<=0,AL51<>INT(AL51),MOD(AL51,100)<>0)),AND(AN51<>"",OR(AN51<=0,AN51<>INT(AN51),MOD(AN51,100)<>0))),"违规：股数须为100股整数倍",IF(AND(OR(AL51<>"",AN51<>""),OR(_LockStatus="已锁仓",_LockStatus="解锁信息不完整")),"违规：锁仓期间禁止加仓",IF(AQ51>C51*D51,"违规：超过单笔风险上限",IF(SUM($AQ$2:$AQ$98)>账户数据!$B$7,"违规：超过账户风险上限","通过"))))))))) -> 通过
