Workbook
Name _LockStatus: 账户数据!$B$23
Name _AccountRiskLimit: 账户数据!$B$7
Name _TrackRule: 持仓跟踪!$AC$2:$AC$497
Name _TrackTradeId: 持仓跟踪!$B$2:$B$497
Name _TrackType: 持仓跟踪!$A$2:$A$497
Name _TradeIds: 单次交易!$A$2:$A$201
Name 技术指标列表: 技术指标!$A$2:$A$201

Sheet 单次交易
A1: 交易编号 | B1: 股票代码 | C1: 买入时账户金额 | D1: 本次允许亏损比例 | E1: 第一批买入价 | F1: 买入建议股数 | G1: 开仓风险告警 | H1: 第一批买入股数 | I1: 首次买入日期 | J1: 期望卖出价 | K1: 实际卖出价 | L1: 卖出股数 | M1: 卖出日期 | N1: 止损价 | O1: 买入总费用 | P1: 卖出费用 | Q1: 买入价的由来 | R1: 止损价的由来 | S1: 期望卖出价的由来 | T1: 实际卖出价的由来 | U1: 期望盈利比例 | V1: 期望止损比例 | W1: 盈亏比 | X1: 实际盈亏金额 | Y1: 单笔仓位收益率 | Z1: 账户收益率与平均盈利率差值 | AA1: 持有天数 | AB1: 复利容许平均亏损上限 | AC1: 复利风险判断 | AD1: 交易打分评价 | AE1: 实际账户收益率 | AF1: 列1 | AG1: 交易预期类型 | AH1: 预期持有周期 | AI1: 预期选择理由 | AJ1: 周期匹配检查 | AK1: 第二批买入价 | AL1: 第二批买入股数 | AM1: 第三批买入价 | AN1: 第三批买入股数 | AO1: 实际加权买入价 | AP1: 累计买入股数 | AQ1: 当前持仓风险 | AR1: 分仓规则检查
F2: =IF(OR(C2="",D2="",E2="",N2="",C2<=0,D2<=0,E2<=N2),"",ROUNDDOWN((C2*D2)/(E2-N2)/100,0)*100) | G2: =IF(A2="","",IF(H2<>"","已开仓",IF(账户数据!$B$23="已锁仓","禁止开仓：连续亏损达到上限",IF(账户数据!$B$23="解锁信息不完整","禁止开仓：请完整填写解锁信息",IF(OR(F2="",E2="",N2="",E2<=N2,账户数据!$B$7=""),"",IF(OR(AG2="",AH2="",AI2=""),"禁止开仓：交易预期未填写完整",IF(COUNTIFS(持仓跟踪!$A$2:$A$497,"止损计划",持仓跟踪!$B$2:$B$497,A2,持仓跟踪!$AC$2:$AC$497,"计划有效")=0,"禁止开仓：请先填写止损计划",IF(账户数据!$B$9+F2*(E2-N2)>=账户数据!$B$7,"禁止开仓：风险额度不足",IF(AJ2="周期与交易预期不匹配，请重新确认",IF(账户数据!$B$23="接近锁仓","允许开仓（接近锁仓；周期需复核）","允许开仓（周期需复核）"),IF(账户数据!$B$23="接近锁仓","允许开仓（接近锁仓）","允许开仓")))))))))) | L2: =IF(K2="","",H2) | U2: =IF(OR(AO2="",J2="",AO2<=0),"",(J2-AO2)/AO2) | V2: =IF(OR(AO2="",N2="",AO2<=0),"",(AO2-N2)/AO2) | W2: =IF(OR(U2="",V2="",V2<=0),"",U2/V2) | X2: =IF(OR(K2="",L2="",AP2=""),"",K2*L2-(E2*H2+IF(AND(AK2<>"",AL2<>""),AK2*AL2,0)+IF(AND(AM2<>"",AN2<>""),AM2*AN2,0))-IF(O2="",0,O2)-IF(P2="",0,P2)) | Y2: =IF(OR(X2="",AP2=""),"",IF((E2*H2+IF(AND(AK2<>"",AL2<>""),AK2*AL2,0)+IF(AND(AM2<>"",AN2<>""),AM2*AN2,0))+IF(O2="",0,O2)<=0,"",X2/((E2*H2+IF(AND(AK2<>"",AL2<>""),AK2*AL2,0)+IF(AND(AM2<>"",AN2<>""),AM2*AN2,0))+IF(O2="",0,O2)))) | Z2: =IF(OR(AE2="",多次统计数据!$B$8=""),"",AE2-多次统计数据!$B$8) | AA2: =IF(OR(I2="",M2="",M2<I2),"",M2-I2) | AB2: =IF(OR(A2="",多次统计数据!$B$8="",多次统计数据!$B$6<=0,多次统计数据!$B$6>=1),"",1-POWER(1+多次统计数据!$B$8,-多次统计数据!$B$6/(1-多次统计数据!$B$6))) | AC2: =IF(OR(AB2="",多次统计数据!$B$9=""),"",IF(多次统计数据!$B$9<AB2,"低于上限","达到或超过上限")) | AE2: =IF(OR(X2="",C2="",C2<=0),"",X2/C2) | AJ2: =IF(OR(AG2="",AH2=""),"",IF(OR(AND(AG2="短期博反弹",OR(AH2="1～3个交易日",AH2="4～10个交易日")),AND(AG2="突破冲新高",OR(AH2="4～10个交易日",AH2="11～20个交易日")),AND(AG2="趋势波段",OR(AH2="11～20个交易日",AH2="21～60个交易日",AH2="60个交易日以上"))),"匹配","周期与交易预期不匹配，请重新确认")) | AO2: =IF(OR(A2="",H2="",H2<=0),"",(E2*H2+IF(AND(AK2<>"",AL2<>""),AK2*AL2,0)+IF(AND(AM2<>"",AN2<>""),AM2*AN2,0))/AP2) | AP2: =IF(OR(A2="",H2="",H2<=0),"",H2+IF(AL2="",0,AL2)+IF(AN2="",0,AN2)) | AQ2: =IF(A2="","",IF(M2<>"",0,IF(OR(H2="",N2=""),"",MAX(E2-MAX(N2,IFERROR(SUMPRODUCT(MAX(((持仓跟踪!$A$2:$A$497="每日跟踪")*(持仓跟踪!$B$2:$B$497=A2))*持仓跟踪!$S$2:$S$497)),0)),0)*H2+IF(OR(AK2="",AL2=""),0,MAX(AK2-MAX(N2,IFERROR(SUMPRODUCT(MAX(((持仓跟踪!$A$2:$A$497="每日跟踪")*(持仓跟踪!$B$2:$B$497=A2))*持仓跟踪!$S$2:$S$497)),0)),0)*AL2)+IF(OR(AM2="",AN2=""),0,MAX(AM2-MAX(N2,IFERROR(SUMPRODUCT(MAX(((持仓跟踪!$A$2:$A$497="每日跟踪")*(持仓跟踪!$B$2:$B$497=A2))*持仓跟踪!$S$2:$S$497)),0)),0)*AN2)))) | AR2: =IF(A2="","",IF(OR(E2="",H2=""),"违规：第一批价格或股数缺失",IF(OR(AND(AK2="",AL2<>""),AND(AK2<>"",AL2="")),"违规：第二批价格与股数须成对填写",IF(OR(AND(AM2="",AN2<>""),AND(AM2<>"",AN2="")),"违规：第三批价格与股数须成对填写",IF(AND(OR(AM2<>"",AN2<>""),OR(AK2="",AL2="")),"违规：必须先完成第二批",IF(OR(H2<=0,H2<>INT(H2),MOD(H2,100)<>0,AND(AL2<>"",OR(AL2<=0,AL2<>INT(AL2),MOD(AL2,100)<>0)),AND(AN2<>"",OR(AN2<=0,AN2<>INT(AN2),MOD(AN2,100)<>0))),"违规：股数须为100股整数倍",IF(AND(OR(AL2<>"",AN2<>""),OR(_LockStatus="已锁仓",_LockStatus="解锁信息不完整")),"违规：锁仓期间禁止加仓",IF(AQ2>C2*D2,"违规：超过单笔风险上限",IF(SUM($AQ$2:$AQ$201)>账户数据!$B$7,"违规：超过账户风险上限","通过")))))))))
C3: =IF(C2="","",C2+SUM(单次交易!Y2:Y201)) | F3: =IF(OR(C3="",D3="",E3="",N3="",C3<=0,D3<=0,E3<=N3),"",ROUNDDOWN((C3*D3)/(E3-N3)/100,0)*100) | G3: =IF(A3="","",IF(H3<>"","已开仓",IF(账户数据!$B$23="已锁仓","禁止开仓：连续亏损达到上限",IF(账户数据!$B$23="解锁信息不完整","禁止开仓：请完整填写解锁信息",IF(OR(F3="",E3="",N3="",E3<=N3,账户数据!$B$7=""),"",IF(OR(AG3="",AH3="",AI3=""),"禁止开仓：交易预期未填写完整",IF(COUNTIFS(持仓跟踪!$A$2:$A$497,"止损计划",持仓跟踪!$B$2:$B$497,A3,持仓跟踪!$AC$2:$AC$497,"计划有效")=0,"禁止开仓：请先填写止损计划",IF(账户数据!$B$9+F3*(E3-N3)>=账户数据!$B$7,"禁止开仓：风险额度不足",IF(AJ3="周期与交易预期不匹配，请重新确认",IF(账户数据!$B$23="接近锁仓","允许开仓（接近锁仓；周期需复核）","允许开仓（周期需复核）"),IF(账户数据!$B$23="接近锁仓","允许开仓（接近锁仓）","允许开仓")))))))))) | L3: =IF(K3="","",H3) | U3: =IF(OR(AO3="",J3="",AO3<=0),"",(J3-AO3)/AO3) | V3: =IF(OR(AO3="",N3="",AO3<=0),"",(AO3-N3)/AO3) | W3: =IF(OR(U3="",V3="",V3<=0),"",U3/V3) | X3: =IF(OR(K3="",L3="",AP3=""),"",K3*L3-(E3*H3+IF(AND(AK3<>"",AL3<>""),AK3*AL3,0)+IF(AND(AM3<>"",AN3<>""),AM3*AN3,0))-IF(O3="",0,O3)-IF(P3="",0,P3)) | Y3: =IF(OR(X3="",AP3=""),"",IF((E3*H3+IF(AND(AK3<>"",AL3<>""),AK3*AL3,0)+IF(AND(AM3<>"",AN3<>""),AM3*AN3,0))+IF(O3="",0,O3)<=0,"",X3/((E3*H3+IF(AND(AK3<>"",AL3<>""),AK3*AL3,0)+IF(AND(AM3<>"",AN3<>""),AM3*AN3,0))+IF(O3="",0,O3)))) | Z3: =IF(OR(AE3="",多次统计数据!$B$8=""),"",AE3-多次统计数据!$B$8) | AA3: =IF(OR(I3="",M3="",M3<I3),"",M3-I3) | AB3: =IF(OR(A3="",多次统计数据!$B$8="",多次统计数据!$B$6<=0,多次统计数据!$B$6>=1),"",1-POWER(1+多次统计数据!$B$8,-多次统计数据!$B$6/(1-多次统计数据!$B$6))) | AC3: =IF(OR(AB3="",多次统计数据!$B$9=""),"",IF(多次统计数据!$B$9<AB3,"低于上限","达到或超过上限")) | AE3: =IF(OR(X3="",C3="",C3<=0),"",X3/C3) | AJ3: =IF(OR(AG3="",AH3=""),"",IF(OR(AND(AG3="短期博反弹",OR(AH3="1～3个交易日",AH3="4～10个交易日")),AND(AG3="突破冲新高",OR(AH3="4～10个交易日",AH3="11～20个交易日")),AND(AG3="趋势波段",OR(AH3="11～20个交易日",AH3="21～60个交易日",AH3="60个交易日以上"))),"匹配","周期与交易预期不匹配，请重新确认")) | AO3: =IF(OR(A3="",H3="",H3<=0),"",(E3*H3+IF(AND(AK3<>"",AL3<>""),AK3*AL3,0)+IF(AND(AM3<>"",AN3<>""),AM3*AN3,0))/AP3) | AP3: =IF(OR(A3="",H3="",H3<=0),"",H3+IF(AL3="",0,AL3)+IF(AN3="",0,AN3)) | AQ3: =IF(A3="","",IF(M3<>"",0,IF(OR(H3="",N3=""),"",MAX(E3-MAX(N3,IFERROR(SUMPRODUCT(MAX(((持仓跟踪!$A$2:$A$497="每日跟踪")*(持仓跟踪!$B$2:$B$497=A3))*持仓跟踪!$S$2:$S$497)),0)),0)*H3+IF(OR(AK3="",AL3=""),0,MAX(AK3-MAX(N3,IFERROR(SUMPRODUCT(MAX(((持仓跟踪!$A$2:$A$497="每日跟踪")*(持仓跟踪!$B$2:$B$497=A3))*持仓跟踪!$S$2:$S$497)),0)),0)*AL3)+IF(OR(AM3="",AN3=""),0,MAX(AM3-MAX(N3,IFERROR(SUMPRODUCT(MAX(((持仓跟踪!$A$2:$A$497="每日跟踪")*(持仓跟踪!$B$2:$B$497=A3))*持仓跟踪!$S$2:$S$497)),0)),0)*AN3)))) | AR3: =IF(A3="","",IF(OR(E3="",H3=""),"违规：第一批价格或股数缺失",IF(OR(AND(AK3="",AL3<>""),AND(AK3<>"",AL3="")),"违规：第二批价格与股数须成对填写",IF(OR(AND(AM3="",AN3<>""),AND(AM3<>"",AN3="")),"违规：第三批价格与股数须成对填写",IF(AND(OR(AM3<>"",AN3<>""),OR(AK3="",AL3="")),"违规：必须先完成第二批",IF(OR(H3<=0,H3<>INT(H3),MOD(H3,100)<>0,AND(AL3<>"",OR(AL3<=0,AL3<>INT(AL3),MOD(AL3,100)<>0)),AND(AN3<>"",OR(AN3<=0,AN3<>INT(AN3),MOD(AN3,100)<>0))),"违规：股数须为100股整数倍",IF(AND(OR(AL3<>"",AN3<>""),OR(_LockStatus="已锁仓",_LockStatus="解锁信息不完整")),"违规：锁仓期间禁止加仓",IF(AQ3>C3*D3,"违规：超过单笔风险上限",IF(SUM($AQ$2:$AQ$201)>账户数据!$B$7,"违规：超过账户风险上限","通过")))))))))
F4: =IF(OR(C4="",D4="",E4="",N4="",C4<=0,D4<=0,E4<=N4),"",ROUNDDOWN((C4*D4)/(E4-N4)/100,0)*100) | G4: =IF(A4="","",IF(H4<>"","已开仓",IF(账户数据!$B$23="已锁仓","禁止开仓：连续亏损达到上限",IF(账户数据!$B$23="解锁信息不完整","禁止开仓：请完整填写解锁信息",IF(OR(F4="",E4="",N4="",E4<=N4,账户数据!$B$7=""),"",IF(OR(AG4="",AH4="",AI4=""),"禁止开仓：交易预期未填写完整",IF(COUNTIFS(持仓跟踪!$A$2:$A$497,"止损计划",持仓跟踪!$B$2:$B$497,A4,持仓跟踪!$AC$2:$AC$497,"计划有效")=0,"禁止开仓：请先填写止损计划",IF(账户数据!$B$9+F4*(E4-N4)>=账户数据!$B$7,"禁止开仓：风险额度不足",IF(AJ4="周期与交易预期不匹配，请重新确认",IF(账户数据!$B$23="接近锁仓","允许开仓（接近锁仓；周期需复核）","允许开仓（周期需复核）"),IF(账户数据!$B$23="接近锁仓","允许开仓（接近锁仓）","允许开仓")))))))))) | L4: =IF(K4="","",H4) | U4: =IF(OR(AO4="",J4="",AO4<=0),"",(J4-AO4)/AO4) | V4: =IF(OR(AO4="",N4="",AO4<=0),"",(AO4-N4)/AO4) | W4: =IF(OR(U4="",V4="",V4<=0),"",U4/V4) | X4: =IF(OR(K4="",L4="",AP4=""),"",K4*L4-(E4*H4+IF(AND(AK4<>"",AL4<>""),AK4*AL4,0)+IF(AND(AM4<>"",AN4<>""),AM4*AN4,0))-IF(O4="",0,O4)-IF(P4="",0,P4)) | Y4: =IF(OR(X4="",AP4=""),"",IF((E4*H4+IF(AND(AK4<>"",AL4<>""),AK4*AL4,0)+IF(AND(AM4<>"",AN4<>""),AM4*AN4,0))+IF(O4="",0,O4)<=0,"",X4/((E4*H4+IF(AND(AK4<>"",AL4<>""),AK4*AL4,0)+IF(AND(AM4<>"",AN4<>""),AM4*AN4,0))+IF(O4="",0,O4)))) | Z4: =IF(OR(AE4="",多次统计数据!$B$8=""),"",AE4-多次统计数据!$B$8) | AA4: =IF(OR(I4="",M4="",M4<I4),"",M4-I4) | AB4: =IF(OR(A4="",多次统计数据!$B$8="",多次统计数据!$B$6<=0,多次统计数据!$B$6>=1),"",1-POWER(1+多次统计数据!$B$8,-多次统计数据!$B$6/(1-多次统计数据!$B$6))) | AC4: =IF(OR(AB4="",多次统计数据!$B$9=""),"",IF(多次统计数据!$B$9<AB4,"低于上限","达到或超过上限")) | AE4: =IF(OR(X4="",C4="",C4<=0),"",X4/C4) | AJ4: =IF(OR(AG4="",AH4=""),"",IF(OR(AND(AG4="短期博反弹",OR(AH4="1～3个交易日",AH4="4～10个交易日")),AND(AG4="突破冲新高",OR(AH4="4～10个交易日",AH4="11～20个交易日")),AND(AG4="趋势波段",OR(AH4="11～20个交易日",AH4="21～60个交易日",AH4="60个交易日以上"))),"匹配","周期与交易预期不匹配，请重新确认")) | AO4: =IF(OR(A4="",H4="",H4<=0),"",(E4*H4+IF(AND(AK4<>"",AL4<>""),AK4*AL4,0)+IF(AND(AM4<>"",AN4<>""),AM4*AN4,0))/AP4) | AP4: =IF(OR(A4="",H4="",H4<=0),"",H4+IF(AL4="",0,AL4)+IF(AN4="",0,AN4)) | AQ4: =IF(A4="","",IF(M4<>"",0,IF(OR(H4="",N4=""),"",MAX(E4-MAX(N4,IFERROR(SUMPRODUCT(MAX(((持仓跟踪!$A$2:$A$497="每日跟踪")*(持仓跟踪!$B$2:$B$497=A4))*持仓跟踪!$S$2:$S$497)),0)),0)*H4+IF(OR(AK4="",AL4=""),0,MAX(AK4-MAX(N4,IFERROR(SUMPRODUCT(MAX(((持仓跟踪!$A$2:$A$497="每日跟踪")*(持仓跟踪!$B$2:$B$497=A4))*持仓跟踪!$S$2:$S$497)),0)),0)*AL4)+IF(OR(AM4="",AN4=""),0,MAX(AM4-MAX(N4,IFERROR(SUMPRODUCT(MAX(((持仓跟踪!$A$2:$A$497="每日跟踪")*(持仓跟踪!$B$2:$B$497=A4))*持仓跟踪!$S$2:$S$497)),0)),0)*AN4)))) | AR4: =IF(A4="","",IF(OR(E4="",H4=""),"违规：第一批价格或股数缺失",IF(OR(AND(AK4="",AL4<>""),AND(AK4<>"",AL4="")),"违规：第二批价格与股数须成对填写",IF(OR(AND(AM4="",AN4<>""),AND(AM4<>"",AN4="")),"违规：第三批价格与股数须成对填写",IF(AND(OR(AM4<>"",AN4<>""),OR(AK4="",AL4="")),"违规：必须先完成第二批",IF(OR(H4<=0,H4<>INT(H4),MOD(H4,100)<>0,AND(AL4<>"",OR(AL4<=0,AL4<>INT(AL4),MOD(AL4,100)<>0)),AND(AN4<>"",OR(AN4<=0,AN4<>INT(AN4),MOD(AN4,100)<>0))),"违规：股数须为100股整数倍",IF(AND(OR(AL4<>"",AN4<>""),OR(_LockStatus="已锁仓",_LockStatus="解锁信息不完整")),"违规：锁仓期间禁止加仓",IF(AQ4>C4*D4,"违规：超过单笔风险上限",IF(SUM($AQ$2:$AQ$201)>账户数据!$B$7,"违规：超过账户风险上限","通过")))))))))
F5: =IF(OR(C5="",D5="",E5="",N5="",C5<=0,D5<=0,E5<=N5),"",ROUNDDOWN((C5*D5)/(E5-N5)/100,0)*100) | G5: =IF(A5="","",IF(H5<>"","已开仓",IF(账户数据!$B$23="已锁仓","禁止开仓：连续亏损达到上限",IF(账户数据!$B$23="解锁信息不完整","禁止开仓：请完整填写解锁信息",IF(OR(F5="",E5="",N5="",E5<=N5,账户数据!$B$7=""),"",IF(OR(AG5="",AH5="",AI5=""),"禁止开仓：交易预期未填写完整",IF(COUNTIFS(持仓跟踪!$A$2:$A$497,"止损计划",持仓跟踪!$B$2:$B$497,A5,持仓跟踪!$AC$2:$AC$497,"计划有效")=0,"禁止开仓：请先填写止损计划",IF(账户数据!$B$9+F5*(E5-N5)>=账户数据!$B$7,"禁止开仓：风险额度不足",IF(AJ5="周期与交易预期不匹配，请重新确认",IF(账户数据!$B$23="接近锁仓","允许开仓（接近锁仓；周期需复核）","允许开仓（周期需复核）"),IF(账户数据!$B$23="接近锁仓","允许开仓（接近锁仓）","允许开仓")))))))))) | L5: =IF(K5="","",H5) | U5: =IF(OR(AO5="",J5="",AO5<=0),"",(J5-AO5)/AO5) | V5: =IF(OR(AO5="",N5="",AO5<=0),"",(AO5-N5)/AO5) | W5: =IF(OR(U5="",V5="",V5<=0),"",U5/V5) | X5: =IF(OR(K5="",L5="",AP5=""),"",K5*L5-(E5*H5+IF(AND(AK5<>"",AL5<>""),AK5*AL5,0)+IF(AND(AM5<>"",AN5<>""),AM5*AN5,0))-IF(O5="",0,O5)-IF(P5="",0,P5)) | Y5: =IF(OR(X5="",AP5=""),"",IF((E5*H5+IF(AND(AK5<>"",AL5<>""),AK5*AL5,0)+IF(AND(AM5<>"",AN5<>""),AM5*AN5,0))+IF(O5="",0,O5)<=0,"",X5/((E5*H5+IF(AND(AK5<>"",AL5<>""),AK5*AL5,0)+IF(AND(AM5<>"",AN5<>""),AM5*AN5,0))+IF(O5="",0,O5)))) | Z5: =IF(OR(AE5="",多次统计数据!$B$8=""),"",AE5-多次统计数据!$B$8) | AA5: =IF(OR(I5="",M5="",M5<I5),"",M5-I5) | AB5: =IF(OR(A5="",多次统计数据!$B$8="",多次统计数据!$B$6<=0,多次统计数据!$B$6>=1),"",1-POWER(1+多次统计数据!$B$8,-多次统计数据!$B$6/(1-多次统计数据!$B$6))) | AC5: =IF(OR(AB5="",多次统计数据!$B$9=""),"",IF(多次统计数据!$B$9<AB5,"低于上限","达到或超过上限")) | AE5: =IF(OR(X5="",C5="",C5<=0),"",X5/C5) | AJ5: =IF(OR(AG5="",AH5=""),"",IF(OR(AND(AG5="短期博反弹",OR(AH5="1～3个交易日",AH5="4～10个交易日")),AND(AG5="突破冲新高",OR(AH5="4～10个交易日",AH5="11～20个交易日")),AND(AG5="趋势波段",OR(AH5="11～20个交易日",AH5="21～60个交易日",AH5="60个交易日以上"))),"匹配","周期与交易预期不匹配，请重新确认")) | AO5: =IF(OR(A5="",H5="",H5<=0),"",(E5*H5+IF(AND(AK5<>"",AL5<>""),AK5*AL5,0)+IF(AND(AM5<>"",AN5<>""),AM5*AN5,0))/AP5) | AP5: =IF(OR(A5="",H5="",H5<=0),"",H5+IF(AL5="",0,AL5)+IF(AN5="",0,AN5)) | AQ5: =IF(A5="","",IF(M5<>"",0,IF(OR(H5="",N5=""),"",MAX(E5-MAX(N5,IFERROR(SUMPRODUCT(MAX(((持仓跟踪!$A$2:$A$497="每日跟踪")*(持仓跟踪!$B$2:$B$497=A5))*持仓跟踪!$S$2:$S$497)),0)),0)*H5+IF(OR(AK5="",AL5=""),0,MAX(AK5-MAX(N5,IFERROR(SUMPRODUCT(MAX(((持仓跟踪!$A$2:$A$497="每日跟踪")*(持仓跟踪!$B$2:$B$497=A5))*持仓跟踪!$S$2:$S$497)),0)),0)*AL5)+IF(OR(AM5="",AN5=""),0,MAX(AM5-MAX(N5,IFERROR(SUMPRODUCT(MAX(((持仓跟踪!$A$2:$A$497="每日跟踪")*(持仓跟踪!$B$2:$B$497=A5))*持仓跟踪!$S$2:$S$497)),0)),0)*AN5)))) | AR5: =IF(A5="","",IF(OR(E5="",H5=""),"违规：第一批价格或股数缺失",IF(OR(AND(AK5="",AL5<>""),AND(AK5<>"",AL5="")),"违规：第二批价格与股数须成对填写",IF(OR(AND(AM5="",AN5<>""),AND(AM5<>"",AN5="")),"违规：第三批价格与股数须成对填写",IF(AND(OR(AM5<>"",AN5<>""),OR(AK5="",AL5="")),"违规：必须先完成第二批",IF(OR(H5<=0,H5<>INT(H5),MOD(H5,100)<>0,AND(AL5<>"",OR(AL5<=0,AL5<>INT(AL5),MOD(AL5,100)<>0)),AND(AN5<>"",OR(AN5<=0,AN5<>INT(AN5),MOD(AN5,100)<>0))),"违规：股数须为100股整数倍",IF(AND(OR(AL5<>"",AN5<>""),OR(_LockStatus="已锁仓",_LockStatus="解锁信息不完整")),"违规：锁仓期间禁止加仓",IF(AQ5>C5*D5,"违规：超过单笔风险上限",IF(SUM($AQ$2:$AQ$201)>账户数据!$B$7,"违规：超过账户风险上限","通过")))))))))
F6: =IF(OR(C6="",D6="",E6="",N6="",C6<=0,D6<=0,E6<=N6),"",ROUNDDOWN((C6*D6)/(E6-N6)/100,0)*100) | G6: =IF(A6="","",IF(H6<>"","已开仓",IF(账户数据!$B$23="已锁仓","禁止开仓：连续亏损达到上限",IF(账户数据!$B$23="解锁信息不完整","禁止开仓：请完整填写解锁信息",IF(OR(F6="",E6="",N6="",E6<=N6,账户数据!$B$7=""),"",IF(OR(AG6="",AH6="",AI6=""),"禁止开仓：交易预期未填写完整",IF(COUNTIFS(持仓跟踪!$A$2:$A$497,"止损计划",持仓跟踪!$B$2:$B$497,A6,持仓跟踪!$AC$2:$AC$497,"计划有效")=0,"禁止开仓：请先填写止损计划",IF(账户数据!$B$9+F6*(E6-N6)>=账户数据!$B$7,"禁止开仓：风险额度不足",IF(AJ6="周期与交易预期不匹配，请重新确认",IF(账户数据!$B$23="接近锁仓","允许开仓（接近锁仓；周期需复核）","允许开仓（周期需复核）"),IF(账户数据!$B$23="接近锁仓","允许开仓（接近锁仓）","允许开仓")))))))))) | L6: =IF(K6="","",H6) | U6: =IF(OR(AO6="",J6="",AO6<=0),"",(J6-AO6)/AO6) | V6: =IF(OR(AO6="",N6="",AO6<=0),"",(AO6-N6)/AO6) | W6: =IF(OR(U6="",V6="",V6<=0),"",U6/V6) | X6: =IF(OR(K6="",L6="",AP6=""),"",K6*L6-(E6*H6+IF(AND(AK6<>"",AL6<>""),AK6*AL6,0)+IF(AND(AM6<>"",AN6<>""),AM6*AN6,0))-IF(O6="",0,O6)-IF(P6="",0,P6)) | Y6: =IF(OR(X6="",AP6=""),"",IF((E6*H6+IF(AND(AK6<>"",AL6<>""),AK6*AL6,0)+IF(AND(AM6<>"",AN6<>""),AM6*AN6,0))+IF(O6="",0,O6)<=0,"",X6/((E6*H6+IF(AND(AK6<>"",AL6<>""),AK6*AL6,0)+IF(AND(AM6<>"",AN6<>""),AM6*AN6,0))+IF(O6="",0,O6)))) | Z6: =IF(OR(AE6="",多次统计数据!$B$8=""),"",AE6-多次统计数据!$B$8) | AA6: =IF(OR(I6="",M6="",M6<I6),"",M6-I6) | AB6: =IF(OR(A6="",多次统计数据!$B$8="",多次统计数据!$B$6<=0,多次统计数据!$B$6>=1),"",1-POWER(1+多次统计数据!$B$8,-多次统计数据!$B$6/(1-多次统计数据!$B$6))) | AC6: =IF(OR(AB6="",多次统计数据!$B$9=""),"",IF(多次统计数据!$B$9<AB6,"低于上限","达到或超过上限")) | AE6: =IF(OR(X6="",C6="",C6<=0),"",X6/C6) | AJ6: =IF(OR(AG6="",AH6=""),"",IF(OR(AND(AG6="短期博反弹",OR(AH6="1～3个交易日",AH6="4～10个交易日")),AND(AG6="突破冲新高",OR(AH6="4～10个交易日",AH6="11～20个交易日")),AND(AG6="趋势波段",OR(AH6="11～20个交易日",AH6="21～60个交易日",AH6="60个交易日以上"))),"匹配","周期与交易预期不匹配，请重新确认")) | AO6: =IF(OR(A6="",H6="",H6<=0),"",(E6*H6+IF(AND(AK6<>"",AL6<>""),AK6*AL6,0)+IF(AND(AM6<>"",AN6<>""),AM6*AN6,0))/AP6) | AP6: =IF(OR(A6="",H6="",H6<=0),"",H6+IF(AL6="",0,AL6)+IF(AN6="",0,AN6)) | AQ6: =IF(A6="","",IF(M6<>"",0,IF(OR(H6="",N6=""),"",MAX(E6-MAX(N6,IFERROR(SUMPRODUCT(MAX(((持仓跟踪!$A$2:$A$497="每日跟踪")*(持仓跟踪!$B$2:$B$497=A6))*持仓跟踪!$S$2:$S$497)),0)),0)*H6+IF(OR(AK6="",AL6=""),0,MAX(AK6-MAX(N6,IFERROR(SUMPRODUCT(MAX(((持仓跟踪!$A$2:$A$497="每日跟踪")*(持仓跟踪!$B$2:$B$497=A6))*持仓跟踪!$S$2:$S$497)),0)),0)*AL6)+IF(OR(AM6="",AN6=""),0,MAX(AM6-MAX(N6,IFERROR(SUMPRODUCT(MAX(((持仓跟踪!$A$2:$A$497="每日跟踪")*(持仓跟踪!$B$2:$B$497=A6))*持仓跟踪!$S$2:$S$497)),0)),0)*AN6)))) | AR6: =IF(A6="","",IF(OR(E6="",H6=""),"违规：第一批价格或股数缺失",IF(OR(AND(AK6="",AL6<>""),AND(AK6<>"",AL6="")),"违规：第二批价格与股数须成对填写",IF(OR(AND(AM6="",AN6<>""),AND(AM6<>"",AN6="")),"违规：第三批价格与股数须成对填写",IF(AND(OR(AM6<>"",AN6<>""),OR(AK6="",AL6="")),"违规：必须先完成第二批",IF(OR(H6<=0,H6<>INT(H6),MOD(H6,100)<>0,AND(AL6<>"",OR(AL6<=0,AL6<>INT(AL6),MOD(AL6,100)<>0)),AND(AN6<>"",OR(AN6<=0,AN6<>INT(AN6),MOD(AN6,100)<>0))),"违规：股数须为100股整数倍",IF(AND(OR(AL6<>"",AN6<>""),OR(_LockStatus="已锁仓",_LockStatus="解锁信息不完整")),"违规：锁仓期间禁止加仓",IF(AQ6>C6*D6,"违规：超过单笔风险上限",IF(SUM($AQ$2:$AQ$201)>账户数据!$B$7,"违规：超过账户风险上限","通过")))))))))
F7: =IF(OR(C7="",D7="",E7="",N7="",C7<=0,D7<=0,E7<=N7),"",ROUNDDOWN((C7*D7)/(E7-N7)/100,0)*100) | G7: =IF(A7="","",IF(H7<>"","已开仓",IF(账户数据!$B$23="已锁仓","禁止开仓：连续亏损达到上限",IF(账户数据!$B$23="解锁信息不完整","禁止开仓：请完整填写解锁信息",IF(OR(F7="",E7="",N7="",E7<=N7,账户数据!$B$7=""),"",IF(OR(AG7="",AH7="",AI7=""),"禁止开仓：交易预期未填写完整",IF(COUNTIFS(持仓跟踪!$A$2:$A$497,"止损计划",持仓跟踪!$B$2:$B$497,A7,持仓跟踪!$AC$2:$AC$497,"计划有效")=0,"禁止开仓：请先填写止损计划",IF(账户数据!$B$9+F7*(E7-N7)>=账户数据!$B$7,"禁止开仓：风险额度不足",IF(AJ7="周期与交易预期不匹配，请重新确认",IF(账户数据!$B$23="接近锁仓","允许开仓（接近锁仓；周期需复核）","允许开仓（周期需复核）"),IF(账户数据!$B$23="接近锁仓","允许开仓（接近锁仓）","允许开仓")))))))))) | L7: =IF(K7="","",H7) | U7: =IF(OR(AO7="",J7="",AO7<=0),"",(J7-AO7)/AO7) | V7: =IF(OR(AO7="",N7="",AO7<=0),"",(AO7-N7)/AO7) | W7: =IF(OR(U7="",V7="",V7<=0),"",U7/V7) | X7: =IF(OR(K7="",L7="",AP7=""),"",K7*L7-(E7*H7+IF(AND(AK7<>"",AL7<>""),AK7*AL7,0)+IF(AND(AM7<>"",AN7<>""),AM7*AN7,0))-IF(O7="",0,O7)-IF(P7="",0,P7)) | Y7: =IF(OR(X7="",AP7=""),"",IF((E7*H7+IF(AND(AK7<>"",AL7<>""),AK7*AL7,0)+IF(AND(AM7<>"",AN7<>""),AM7*AN7,0))+IF(O7="",0,O7)<=0,"",X7/((E7*H7+IF(AND(AK7<>"",AL7<>""),AK7*AL7,0)+IF(AND(AM7<>"",AN7<>""),AM7*AN7,0))+IF(O7="",0,O7)))) | Z7: =IF(OR(AE7="",多次统计数据!$B$8=""),"",AE7-多次统计数据!$B$8) | AA7: =IF(OR(I7="",M7="",M7<I7),"",M7-I7) | AB7: =IF(OR(A7="",多次统计数据!$B$8="",多次统计数据!$B$6<=0,多次统计数据!$B$6>=1),"",1-POWER(1+多次统计数据!$B$8,-多次统计数据!$B$6/(1-多次统计数据!$B$6))) | AC7: =IF(OR(AB7="",多次统计数据!$B$9=""),"",IF(多次统计数据!$B$9<AB7,"低于上限","达到或超过上限")) | AE7: =IF(OR(X7="",C7="",C7<=0),"",X7/C7) | AJ7: =IF(OR(AG7="",AH7=""),"",IF(OR(AND(AG7="短期博反弹",OR(AH7="1～3个交易日",AH7="4～10个交易日")),AND(AG7="突破冲新高",OR(AH7="4～10个交易日",AH7="11～20个交易日")),AND(AG7="趋势波段",OR(AH7="11～20个交易日",AH7="21～60个交易日",AH7="60个交易日以上"))),"匹配","周期与交易预期不匹配，请重新确认")) | AO7: =IF(OR(A7="",H7="",H7<=0),"",(E7*H7+IF(AND(AK7<>"",AL7<>""),AK7*AL7,0)+IF(AND(AM7<>"",AN7<>""),AM7*AN7,0))/AP7) | AP7: =IF(OR(A7="",H7="",H7<=0),"",H7+IF(AL7="",0,AL7)+IF(AN7="",0,AN7)) | AQ7: =IF(A7="","",IF(M7<>"",0,IF(OR(H7="",N7=""),"",MAX(E7-MAX(N7,IFERROR(SUMPRODUCT(MAX(((持仓跟踪!$A$2:$A$497="每日跟踪")*(持仓跟踪!$B$2:$B$497=A7))*持仓跟踪!$S$2:$S$497)),0)),0)*H7+IF(OR(AK7="",AL7=""),0,MAX(AK7-MAX(N7,IFERROR(SUMPRODUCT(MAX(((持仓跟踪!$A$2:$A$497="每日跟踪")*(持仓跟踪!$B$2:$B$497=A7))*持仓跟踪!$S$2:$S$497)),0)),0)*AL7)+IF(OR(AM7="",AN7=""),0,MAX(AM7-MAX(N7,IFERROR(SUMPRODUCT(MAX(((持仓跟踪!$A$2:$A$497="每日跟踪")*(持仓跟踪!$B$2:$B$497=A7))*持仓跟踪!$S$2:$S$497)),0)),0)*AN7)))) | AR7: =IF(A7="","",IF(OR(E7="",H7=""),"违规：第一批价格或股数缺失",IF(OR(AND(AK7="",AL7<>""),AND(AK7<>"",AL7="")),"违规：第二批价格与股数须成对填写",IF(OR(AND(AM7="",AN7<>""),AND(AM7<>"",AN7="")),"违规：第三批价格与股数须成对填写",IF(AND(OR(AM7<>"",AN7<>""),OR(AK7="",AL7="")),"违规：必须先完成第二批",IF(OR(H7<=0,H7<>INT(H7),MOD(H7,100)<>0,AND(AL7<>"",OR(AL7<=0,AL7<>INT(AL7),MOD(AL7,100)<>0)),AND(AN7<>"",OR(AN7<=0,AN7<>INT(AN7),MOD(AN7,100)<>0))),"违规：股数须为100股整数倍",IF(AND(OR(AL7<>"",AN7<>""),OR(_LockStatus="已锁仓",_LockStatus="解锁信息不完整")),"违规：锁仓期间禁止加仓",IF(AQ7>C7*D7,"违规：超过单笔风险上限",IF(SUM($AQ$2:$AQ$201)>账户数据!$B$7,"违规：超过账户风险上限","通过")))))))))
F8: =IF(OR(C8="",D8="",E8="",N8="",C8<=0,D8<=0,E8<=N8),"",ROUNDDOWN((C8*D8)/(E8-N8)/100,0)*100) | G8: =IF(A8="","",IF(H8<>"","已开仓",IF(账户数据!$B$23="已锁仓","禁止开仓：连续亏损达到上限",IF(账户数据!$B$23="解锁信息不完整","禁止开仓：请完整填写解锁信息",IF(OR(F8="",E8="",N8="",E8<=N8,账户数据!$B$7=""),"",IF(OR(AG8="",AH8="",AI8=""),"禁止开仓：交易预期未填写完整",IF(COUNTIFS(持仓跟踪!$A$2:$A$497,"止损计划",持仓跟踪!$B$2:$B$497,A8,持仓跟踪!$AC$2:$AC$497,"计划有效")=0,"禁止开仓：请先填写止损计划",IF(账户数据!$B$9+F8*(E8-N8)>=账户数据!$B$7,"禁止开仓：风险额度不足",IF(AJ8="周期与交易预期不匹配，请重新确认",IF(账户数据!$B$23="接近锁仓","允许开仓（接近锁仓；周期需复核）","允许开仓（周期需复核）"),IF(账户数据!$B$23="接近锁仓","允许开仓（接近锁仓）","允许开仓")))))))))) | L8: =IF(K8="","",H8) | U8: =IF(OR(AO8="",J8="",AO8<=0),"",(J8-AO8)/AO8) | V8: =IF(OR(AO8="",N8="",AO8<=0),"",(AO8-N8)/AO8) | W8: =IF(OR(U8="",V8="",V8<=0),"",U8/V8) | X8: =IF(OR(K8="",L8="",AP8=""),"",K8*L8-(E8*H8+IF(AND(AK8<>"",AL8<>""),AK8*AL8,0)+IF(AND(AM8<>"",AN8<>""),AM8*AN8,0))-IF(O8="",0,O8)-IF(P8="",0,P8)) | Y8: =IF(OR(X8="",AP8=""),"",IF((E8*H8+IF(AND(AK8<>"",AL8<>""),AK8*AL8,0)+IF(AND(AM8<>"",AN8<>""),AM8*AN8,0))+IF(O8="",0,O8)<=0,"",X8/((E8*H8+IF(AND(AK8<>"",AL8<>""),AK8*AL8,0)+IF(AND(AM8<>"",AN8<>""),AM8*AN8,0))+IF(O8="",0,O8)))) | Z8: =IF(OR(AE8="",多次统计数据!$B$8=""),"",AE8-多次统计数据!$B$8) | AA8: =IF(OR(I8="",M8="",M8<I8),"",M8-I8) | AB8: =IF(OR(A8="",多次统计数据!$B$8="",多次统计数据!$B$6<=0,多次统计数据!$B$6>=1),"",1-POWER(1+多次统计数据!$B$8,-多次统计数据!$B$6/(1-多次统计数据!$B$6))) | AC8: =IF(OR(AB8="",多次统计数据!$B$9=""),"",IF(多次统计数据!$B$9<AB8,"低于上限","达到或超过上限")) | AE8: =IF(OR(X8="",C8="",C8<=0),"",X8/C8) | AJ8: =IF(OR(AG8="",AH8=""),"",IF(OR(AND(AG8="短期博反弹",OR(AH8="1～3个交易日",AH8="4～10个交易日")),AND(AG8="突破冲新高",OR(AH8="4～10个交易日",AH8="11～20个交易日")),AND(AG8="趋势波段",OR(AH8="11～20个交易日",AH8="21～60个交易日",AH8="60个交易日以上"))),"匹配","周期与交易预期不匹配，请重新确认")) | AO8: =IF(OR(A8="",H8="",H8<=0),"",(E8*H8+IF(AND(AK8<>"",AL8<>""),AK8*AL8,0)+IF(AND(AM8<>"",AN8<>""),AM8*AN8,0))/AP8) | AP8: =IF(OR(A8="",H8="",H8<=0),"",H8+IF(AL8="",0,AL8)+IF(AN8="",0,AN8)) | AQ8: =IF(A8="","",IF(M8<>"",0,IF(OR(H8="",N8=""),"",MAX(E8-MAX(N8,IFERROR(SUMPRODUCT(MAX(((持仓跟踪!$A$2:$A$497="每日跟踪")*(持仓跟踪!$B$2:$B$497=A8))*持仓跟踪!$S$2:$S$497)),0)),0)*H8+IF(OR(AK8="",AL8=""),0,MAX(AK8-MAX(N8,IFERROR(SUMPRODUCT(MAX(((持仓跟踪!$A$2:$A$497="每日跟踪")*(持仓跟踪!$B$2:$B$497=A8))*持仓跟踪!$S$2:$S$497)),0)),0)*AL8)+IF(OR(AM8="",AN8=""),0,MAX(AM8-MAX(N8,IFERROR(SUMPRODUCT(MAX(((持仓跟踪!$A$2:$A$497="每日跟踪")*(持仓跟踪!$B$2:$B$497=A8))*持仓跟踪!$S$2:$S$497)),0)),0)*AN8)))) | AR8: =IF(A8="","",IF(OR(E8="",H8=""),"违规：第一批价格或股数缺失",IF(OR(AND(AK8="",AL8<>""),AND(AK8<>"",AL8="")),"违规：第二批价格与股数须成对填写",IF(OR(AND(AM8="",AN8<>""),AND(AM8<>"",AN8="")),"违规：第三批价格与股数须成对填写",IF(AND(OR(AM8<>"",AN8<>""),OR(AK8="",AL8="")),"违规：必须先完成第二批",IF(OR(H8<=0,H8<>INT(H8),MOD(H8,100)<>0,AND(AL8<>"",OR(AL8<=0,AL8<>INT(AL8),MOD(AL8,100)<>0)),AND(AN8<>"",OR(AN8<=0,AN8<>INT(AN8),MOD(AN8,100)<>0))),"违规：股数须为100股整数倍",IF(AND(OR(AL8<>"",AN8<>""),OR(_LockStatus="已锁仓",_LockStatus="解锁信息不完整")),"违规：锁仓期间禁止加仓",IF(AQ8>C8*D8,"违规：超过单笔风险上限",IF(SUM($AQ$2:$AQ$201)>账户数据!$B$7,"违规：超过账户风险上限","通过")))))))))
F9: =IF(OR(C9="",D9="",E9="",N9="",C9<=0,D9<=0,E9<=N9),"",ROUNDDOWN((C9*D9)/(E9-N9)/100,0)*100) | G9: =IF(A9="","",IF(H9<>"","已开仓",IF(账户数据!$B$23="已锁仓","禁止开仓：连续亏损达到上限",IF(账户数据!$B$23="解锁信息不完整","禁止开仓：请完整填写解锁信息",IF(OR(F9="",E9="",N9="",E9<=N9,账户数据!$B$7=""),"",IF(OR(AG9="",AH9="",AI9=""),"禁止开仓：交易预期未填写完整",IF(COUNTIFS(持仓跟踪!$A$2:$A$497,"止损计划",持仓跟踪!$B$2:$B$497,A9,持仓跟踪!$AC$2:$AC$497,"计划有效")=0,"禁止开仓：请先填写止损计划",IF(账户数据!$B$9+F9*(E9-N9)>=账户数据!$B$7,"禁止开仓：风险额度不足",IF(AJ9="周期与交易预期不匹配，请重新确认",IF(账户数据!$B$23="接近锁仓","允许开仓（接近锁仓；周期需复核）","允许开仓（周期需复核）"),IF(账户数据!$B$23="接近锁仓","允许开仓（接近锁仓）","允许开仓")))))))))) | L9: =IF(K9="","",H9) | U9: =IF(OR(AO9="",J9="",AO9<=0),"",(J9-AO9)/AO9) | V9: =IF(OR(AO9="",N9="",AO9<=0),"",(AO9-N9)/AO9) | W9: =IF(OR(U9="",V9="",V9<=0),"",U9/V9) | X9: =IF(OR(K9="",L9="",AP9=""),"",K9*L9-(E9*H9+IF(AND(AK9<>"",AL9<>""),AK9*AL9,0)+IF(AND(AM9<>"",AN9<>""),AM9*AN9,0))-IF(O9="",0,O9)-IF(P9="",0,P9)) | Y9: =IF(OR(X9="",AP9=""),"",IF((E9*H9+IF(AND(AK9<>"",AL9<>""),AK9*AL9,0)+IF(AND(AM9<>"",AN9<>""),AM9*AN9,0))+IF(O9="",0,O9)<=0,"",X9/((E9*H9+IF(AND(AK9<>"",AL9<>""),AK9*AL9,0)+IF(AND(AM9<>"",AN9<>""),AM9*AN9,0))+IF(O9="",0,O9)))) | Z9: =IF(OR(AE9="",多次统计数据!$B$8=""),"",AE9-多次统计数据!$B$8) | AA9: =IF(OR(I9="",M9="",M9<I9),"",M9-I9) | AB9: =IF(OR(A9="",多次统计数据!$B$8="",多次统计数据!$B$6<=0,多次统计数据!$B$6>=1),"",1-POWER(1+多次统计数据!$B$8,-多次统计数据!$B$6/(1-多次统计数据!$B$6))) | AC9: =IF(OR(AB9="",多次统计数据!$B$9=""),"",IF(多次统计数据!$B$9<AB9,"低于上限","达到或超过上限")) | AE9: =IF(OR(X9="",C9="",C9<=0),"",X9/C9) | AJ9: =IF(OR(AG9="",AH9=""),"",IF(OR(AND(AG9="短期博反弹",OR(AH9="1～3个交易日",AH9="4～10个交易日")),AND(AG9="突破冲新高",OR(AH9="4～10个交易日",AH9="11～20个交易日")),AND(AG9="趋势波段",OR(AH9="11～20个交易日",AH9="21～60个交易日",AH9="60个交易日以上"))),"匹配","周期与交易预期不匹配，请重新确认")) | AO9: =IF(OR(A9="",H9="",H9<=0),"",(E9*H9+IF(AND(AK9<>"",AL9<>""),AK9*AL9,0)+IF(AND(AM9<>"",AN9<>""),AM9*AN9,0))/AP9) | AP9: =IF(OR(A9="",H9="",H9<=0),"",H9+IF(AL9="",0,AL9)+IF(AN9="",0,AN9)) | AQ9: =IF(A9="","",IF(M9<>"",0,IF(OR(H9="",N9=""),"",MAX(E9-MAX(N9,IFERROR(SUMPRODUCT(MAX(((持仓跟踪!$A$2:$A$497="每日跟踪")*(持仓跟踪!$B$2:$B$497=A9))*持仓跟踪!$S$2:$S$497)),0)),0)*H9+IF(OR(AK9="",AL9=""),0,MAX(AK9-MAX(N9,IFERROR(SUMPRODUCT(MAX(((持仓跟踪!$A$2:$A$497="每日跟踪")*(持仓跟踪!$B$2:$B$497=A9))*持仓跟踪!$S$2:$S$497)),0)),0)*AL9)+IF(OR(AM9="",AN9=""),0,MAX(AM9-MAX(N9,IFERROR(SUMPRODUCT(MAX(((持仓跟踪!$A$2:$A$497="每日跟踪")*(持仓跟踪!$B$2:$B$497=A9))*持仓跟踪!$S$2:$S$497)),0)),0)*AN9)))) | AR9: =IF(A9="","",IF(OR(E9="",H9=""),"违规：第一批价格或股数缺失",IF(OR(AND(AK9="",AL9<>""),AND(AK9<>"",AL9="")),"违规：第二批价格与股数须成对填写",IF(OR(AND(AM9="",AN9<>""),AND(AM9<>"",AN9="")),"违规：第三批价格与股数须成对填写",IF(AND(OR(AM9<>"",AN9<>""),OR(AK9="",AL9="")),"违规：必须先完成第二批",IF(OR(H9<=0,H9<>INT(H9),MOD(H9,100)<>0,AND(AL9<>"",OR(AL9<=0,AL9<>INT(AL9),MOD(AL9,100)<>0)),AND(AN9<>"",OR(AN9<=0,AN9<>INT(AN9),MOD(AN9,100)<>0))),"违规：股数须为100股整数倍",IF(AND(OR(AL9<>"",AN9<>""),OR(_LockStatus="已锁仓",_LockStatus="解锁信息不完整")),"违规：锁仓期间禁止加仓",IF(AQ9>C9*D9,"违规：超过单笔风险上限",IF(SUM($AQ$2:$AQ$201)>账户数据!$B$7,"违规：超过账户风险上限","通过")))))))))
F10: =IF(OR(C10="",D10="",E10="",N10="",C10<=0,D10<=0,E10<=N10),"",ROUNDDOWN((C10*D10)/(E10-N10)/100,0)*100) | G10: =IF(A10="","",IF(H10<>"","已开仓",IF(账户数据!$B$23="已锁仓","禁止开仓：连续亏损达到上限",IF(账户数据!$B$23="解锁信息不完整","禁止开仓：请完整填写解锁信息",IF(OR(F10="",E10="",N10="",E10<=N10,账户数据!$B$7=""),"",IF(OR(AG10="",AH10="",AI10=""),"禁止开仓：交易预期未填写完整",IF(COUNTIFS(持仓跟踪!$A$2:$A$497,"止损计划",持仓跟踪!$B$2:$B$497,A10,持仓跟踪!$AC$2:$AC$497,"计划有效")=0,"禁止开仓：请先填写止损计划",IF(账户数据!$B$9+F10*(E10-N10)>=账户数据!$B$7,"禁止开仓：风险额度不足",IF(AJ10="周期与交易预期不匹配，请重新确认",IF(账户数据!$B$23="接近锁仓","允许开仓（接近锁仓；周期需复核）","允许开仓（周期需复核）"),IF(账户数据!$B$23="接近锁仓","允许开仓（接近锁仓）","允许开仓")))))))))) | L10: =IF(K10="","",H10) | U10: =IF(OR(AO10="",J10="",AO10<=0),"",(J10-AO10)/AO10) | V10: =IF(OR(AO10="",N10="",AO10<=0),"",(AO10-N10)/AO10) | W10: =IF(OR(U10="",V10="",V10<=0),"",U10/V10) | X10: =IF(OR(K10="",L10="",AP10=""),"",K10*L10-(E10*H10+IF(AND(AK10<>"",AL10<>""),AK10*AL10,0)+IF(AND(AM10<>"",AN10<>""),AM10*AN10,0))-IF(O10="",0,O10)-IF(P10="",0,P10)) | Y10: =IF(OR(X10="",AP10=""),"",IF((E10*H10+IF(AND(AK10<>"",AL10<>""),AK10*AL10,0)+IF(AND(AM10<>"",AN10<>""),AM10*AN10,0))+IF(O10="",0,O10)<=0,"",X10/((E10*H10+IF(AND(AK10<>"",AL10<>""),AK10*AL10,0)+IF(AND(AM10<>"",AN10<>""),AM10*AN10,0))+IF(O10="",0,O10)))) | Z10: =IF(OR(AE10="",多次统计数据!$B$8=""),"",AE10-多次统计数据!$B$8) | AA10: =IF(OR(I10="",M10="",M10<I10),"",M10-I10) | AB10: =IF(OR(A10="",多次统计数据!$B$8="",多次统计数据!$B$6<=0,多次统计数据!$B$6>=1),"",1-POWER(1+多次统计数据!$B$8,-多次统计数据!$B$6/(1-多次统计数据!$B$6))) | AC10: =IF(OR(AB10="",多次统计数据!$B$9=""),"",IF(多次统计数据!$B$9<AB10,"低于上限","达到或超过上限")) | AE10: =IF(OR(X10="",C10="",C10<=0),"",X10/C10) | AJ10: =IF(OR(AG10="",AH10=""),"",IF(OR(AND(AG10="短期博反弹",OR(AH10="1～3个交易日",AH10="4～10个交易日")),AND(AG10="突破冲新高",OR(AH10="4～10个交易日",AH10="11～20个交易日")),AND(AG10="趋势波段",OR(AH10="11～20个交易日",AH10="21～60个交易日",AH10="60个交易日以上"))),"匹配","周期与交易预期不匹配，请重新确认")) | AO10: =IF(OR(A10="",H10="",H10<=0),"",(E10*H10+IF(AND(AK10<>"",AL10<>""),AK10*AL10,0)+IF(AND(AM10<>"",AN10<>""),AM10*AN10,0))/AP10) | AP10: =IF(OR(A10="",H10="",H10<=0),"",H10+IF(AL10="",0,AL10)+IF(AN10="",0,AN10)) | AQ10: =IF(A10="","",IF(M10<>"",0,IF(OR(H10="",N10=""),"",MAX(E10-MAX(N10,IFERROR(SUMPRODUCT(MAX(((持仓跟踪!$A$2:$A$497="每日跟踪")*(持仓跟踪!$B$2:$B$497=A10))*持仓跟踪!$S$2:$S$497)),0)),0)*H10+IF(OR(AK10="",AL10=""),0,MAX(AK10-MAX(N10,IFERROR(SUMPRODUCT(MAX(((持仓跟踪!$A$2:$A$497="每日跟踪")*(持仓跟踪!$B$2:$B$497=A10))*持仓跟踪!$S$2:$S$497)),0)),0)*AL10)+IF(OR(AM10="",AN10=""),0,MAX(AM10-MAX(N10,IFERROR(SUMPRODUCT(MAX(((持仓跟踪!$A$2:$A$497="每日跟踪")*(持仓跟踪!$B$2:$B$497=A10))*持仓跟踪!$S$2:$S$497)),0)),0)*AN10)))) | AR10: =IF(A10="","",IF(OR(E10="",H10=""),"违规：第一批价格或股数缺失",IF(OR(AND(AK10="",AL10<>""),AND(AK10<>"",AL10="")),"违规：第二批价格与股数须成对填写",IF(OR(AND(AM10="",AN10<>""),AND(AM10<>"",AN10="")),"违规：第三批价格与股数须成对填写",IF(AND(OR(AM10<>"",AN10<>""),OR(AK10="",AL10="")),"违规：必须先完成第二批",IF(OR(H10<=0,H10<>INT(H10),MOD(H10,100)<>0,AND(AL10<>"",OR(AL10<=0,AL10<>INT(AL10),MOD(AL10,100)<>0)),AND(AN10<>"",OR(AN10<=0,AN10<>INT(AN10),MOD(AN10,100)<>0))),"违规：股数须为100股整数倍",IF(AND(OR(AL10<>"",AN10<>""),OR(_LockStatus="已锁仓",_LockStatus="解锁信息不完整")),"违规：锁仓期间禁止加仓",IF(AQ10>C10*D10,"违规：超过单笔风险上限",IF(SUM($AQ$2:$AQ$201)>账户数据!$B$7,"违规：超过账户风险上限","通过")))))))))
F11: =IF(OR(C11="",D11="",E11="",N11="",C11<=0,D11<=0,E11<=N11),"",ROUNDDOWN((C11*D11)/(E11-N11)/100,0)*100) | G11: =IF(A11="","",IF(H11<>"","已开仓",IF(账户数据!$B$23="已锁仓","禁止开仓：连续亏损达到上限",IF(账户数据!$B$23="解锁信息不完整","禁止开仓：请完整填写解锁信息",IF(OR(F11="",E11="",N11="",E11<=N11,账户数据!$B$7=""),"",IF(OR(AG11="",AH11="",AI11=""),"禁止开仓：交易预期未填写完整",IF(COUNTIFS(持仓跟踪!$A$2:$A$497,"止损计划",持仓跟踪!$B$2:$B$497,A11,持仓跟踪!$AC$2:$AC$497,"计划有效")=0,"禁止开仓：请先填写止损计划",IF(账户数据!$B$9+F11*(E11-N11)>=账户数据!$B$7,"禁止开仓：风险额度不足",IF(AJ11="周期与交易预期不匹配，请重新确认",IF(账户数据!$B$23="接近锁仓","允许开仓（接近锁仓；周期需复核）","允许开仓（周期需复核）"),IF(账户数据!$B$23="接近锁仓","允许开仓（接近锁仓）","允许开仓")))))))))) | L11: =IF(K11="","",H11) | U11: =IF(OR(AO11="",J11="",AO11<=0),"",(J11-AO11)/AO11) | V11: =IF(OR(AO11="",N11="",AO11<=0),"",(AO11-N11)/AO11) | W11: =IF(OR(U11="",V11="",V11<=0),"",U11/V11) | X11: =IF(OR(K11="",L11="",AP11=""),"",K11*L11-(E11*H11+IF(AND(AK11<>"",AL11<>""),AK11*AL11,0)+IF(AND(AM11<>"",AN11<>""),AM11*AN11,0))-IF(O11="",0,O11)-IF(P11="",0,P11)) | Y11: =IF(OR(X11="",AP11=""),"",IF((E11*H11+IF(AND(AK11<>"",AL11<>""),AK11*AL11,0)+IF(AND(AM11<>"",AN11<>""),AM11*AN11,0))+IF(O11="",0,O11)<=0,"",X11/((E11*H11+IF(AND(AK11<>"",AL11<>""),AK11*AL11,0)+IF(AND(AM11<>"",AN11<>""),AM11*AN11,0))+IF(O11="",0,O11)))) | Z11: =IF(OR(AE11="",多次统计数据!$B$8=""),"",AE11-多次统计数据!$B$8) | AA11: =IF(OR(I11="",M11="",M11<I11),"",M11-I11) | AB11: =IF(OR(A11="",多次统计数据!$B$8="",多次统计数据!$B$6<=0,多次统计数据!$B$6>=1),"",1-POWER(1+多次统计数据!$B$8,-多次统计数据!$B$6/(1-多次统计数据!$B$6))) | AC11: =IF(OR(AB11="",多次统计数据!$B$9=""),"",IF(多次统计数据!$B$9<AB11,"低于上限","达到或超过上限")) | AE11: =IF(OR(X11="",C11="",C11<=0),"",X11/C11) | AJ11: =IF(OR(AG11="",AH11=""),"",IF(OR(AND(AG11="短期博反弹",OR(AH11="1～3个交易日",AH11="4～10个交易日")),AND(AG11="突破冲新高",OR(AH11="4～10个交易日",AH11="11～20个交易日")),AND(AG11="趋势波段",OR(AH11="11～20个交易日",AH11="21～60个交易日",AH11="60个交易日以上"))),"匹配","周期与交易预期不匹配，请重新确认")) | AO11: =IF(OR(A11="",H11="",H11<=0),"",(E11*H11+IF(AND(AK11<>"",AL11<>""),AK11*AL11,0)+IF(AND(AM11<>"",AN11<>""),AM11*AN11,0))/AP11) | AP11: =IF(OR(A11="",H11="",H11<=0),"",H11+IF(AL11="",0,AL11)+IF(AN11="",0,AN11)) | AQ11: =IF(A11="","",IF(M11<>"",0,IF(OR(H11="",N11=""),"",MAX(E11-MAX(N11,IFERROR(SUMPRODUCT(MAX(((持仓跟踪!$A$2:$A$497="每日跟踪")*(持仓跟踪!$B$2:$B$497=A11))*持仓跟踪!$S$2:$S$497)),0)),0)*H11+IF(OR(AK11="",AL11=""),0,MAX(AK11-MAX(N11,IFERROR(SUMPRODUCT(MAX(((持仓跟踪!$A$2:$A$497="每日跟踪")*(持仓跟踪!$B$2:$B$497=A11))*持仓跟踪!$S$2:$S$497)),0)),0)*AL11)+IF(OR(AM11="",AN11=""),0,MAX(AM11-MAX(N11,IFERROR(SUMPRODUCT(MAX(((持仓跟踪!$A$2:$A$497="每日跟踪")*(持仓跟踪!$B$2:$B$497=A11))*持仓跟踪!$S$2:$S$497)),0)),0)*AN11)))) | AR11: =IF(A11="","",IF(OR(E11="",H11=""),"违规：第一批价格或股数缺失",IF(OR(AND(AK11="",AL11<>""),AND(AK11<>"",AL11="")),"违规：第二批价格与股数须成对填写",IF(OR(AND(AM11="",AN11<>""),AND(AM11<>"",AN11="")),"违规：第三批价格与股数须成对填写",IF(AND(OR(AM11<>"",AN11<>""),OR(AK11="",AL11="")),"违规：必须先完成第二批",IF(OR(H11<=0,H11<>INT(H11),MOD(H11,100)<>0,AND(AL11<>"",OR(AL11<=0,AL11<>INT(AL11),MOD(AL11,100)<>0)),AND(AN11<>"",OR(AN11<=0,AN11<>INT(AN11),MOD(AN11,100)<>0))),"违规：股数须为100股整数倍",IF(AND(OR(AL11<>"",AN11<>""),OR(_LockStatus="已锁仓",_LockStatus="解锁信息不完整")),"违规：锁仓期间禁止加仓",IF(AQ11>C11*D11,"违规：超过单笔风险上限",IF(SUM($AQ$2:$AQ$201)>账户数据!$B$7,"违规：超过账户风险上限","通过")))))))))
F12: =IF(OR(C12="",D12="",E12="",N12="",C12<=0,D12<=0,E12<=N12),"",ROUNDDOWN((C12*D12)/(E12-N12)/100,0)*100) | G12: =IF(A12="","",IF(H12<>"","已开仓",IF(账户数据!$B$23="已锁仓","禁止开仓：连续亏损达到上限",IF(账户数据!$B$23="解锁信息不完整","禁止开仓：请完整填写解锁信息",IF(OR(F12="",E12="",N12="",E12<=N12,账户数据!$B$7=""),"",IF(OR(AG12="",AH12="",AI12=""),"禁止开仓：交易预期未填写完整",IF(COUNTIFS(持仓跟踪!$A$2:$A$497,"止损计划",持仓跟踪!$B$2:$B$497,A12,持仓跟踪!$AC$2:$AC$497,"计划有效")=0,"禁止开仓：请先填写止损计划",IF(账户数据!$B$9+F12*(E12-N12)>=账户数据!$B$7,"禁止开仓：风险额度不足",IF(AJ12="周期与交易预期不匹配，请重新确认",IF(账户数据!$B$23="接近锁仓","允许开仓（接近锁仓；周期需复核）","允许开仓（周期需复核）"),IF(账户数据!$B$23="接近锁仓","允许开仓（接近锁仓）","允许开仓")))))))))) | L12: =IF(K12="","",H12) | U12: =IF(OR(AO12="",J12="",AO12<=0),"",(J12-AO12)/AO12) | V12: =IF(OR(AO12="",N12="",AO12<=0),"",(AO12-N12)/AO12) | W12: =IF(OR(U12="",V12="",V12<=0),"",U12/V12) | X12: =IF(OR(K12="",L12="",AP12=""),"",K12*L12-(E12*H12+IF(AND(AK12<>"",AL12<>""),AK12*AL12,0)+IF(AND(AM12<>"",AN12<>""),AM12*AN12,0))-IF(O12="",0,O12)-IF(P12="",0,P12)) | Y12: =IF(OR(X12="",AP12=""),"",IF((E12*H12+IF(AND(AK12<>"",AL12<>""),AK12*AL12,0)+IF(AND(AM12<>"",AN12<>""),AM12*AN12,0))+IF(O12="",0,O12)<=0,"",X12/((E12*H12+IF(AND(AK12<>"",AL12<>""),AK12*AL12,0)+IF(AND(AM12<>"",AN12<>""),AM12*AN12,0))+IF(O12="",0,O12)))) | Z12: =IF(OR(AE12="",多次统计数据!$B$8=""),"",AE12-多次统计数据!$B$8) | AA12: =IF(OR(I12="",M12="",M12<I12),"",M12-I12) | AB12: =IF(OR(A12="",多次统计数据!$B$8="",多次统计数据!$B$6<=0,多次统计数据!$B$6>=1),"",1-POWER(1+多次统计数据!$B$8,-多次统计数据!$B$6/(1-多次统计数据!$B$6))) | AC12: =IF(OR(AB12="",多次统计数据!$B$9=""),"",IF(多次统计数据!$B$9<AB12,"低于上限","达到或超过上限")) | AE12: =IF(OR(X12="",C12="",C12<=0),"",X12/C12) | AJ12: =IF(OR(AG12="",AH12=""),"",IF(OR(AND(AG12="短期博反弹",OR(AH12="1～3个交易日",AH12="4～10个交易日")),AND(AG12="突破冲新高",OR(AH12="4～10个交易日",AH12="11～20个交易日")),AND(AG12="趋势波段",OR(AH12="11～20个交易日",AH12="21～60个交易日",AH12="60个交易日以上"))),"匹配","周期与交易预期不匹配，请重新确认")) | AO12: =IF(OR(A12="",H12="",H12<=0),"",(E12*H12+IF(AND(AK12<>"",AL12<>""),AK12*AL12,0)+IF(AND(AM12<>"",AN12<>""),AM12*AN12,0))/AP12) | AP12: =IF(OR(A12="",H12="",H12<=0),"",H12+IF(AL12="",0,AL12)+IF(AN12="",0,AN12)) | AQ12: =IF(A12="","",IF(M12<>"",0,IF(OR(H12="",N12=""),"",MAX(E12-MAX(N12,IFERROR(SUMPRODUCT(MAX(((持仓跟踪!$A$2:$A$497="每日跟踪")*(持仓跟踪!$B$2:$B$497=A12))*持仓跟踪!$S$2:$S$497)),0)),0)*H12+IF(OR(AK12="",AL12=""),0,MAX(AK12-MAX(N12,IFERROR(SUMPRODUCT(MAX(((持仓跟踪!$A$2:$A$497="每日跟踪")*(持仓跟踪!$B$2:$B$497=A12))*持仓跟踪!$S$2:$S$497)),0)),0)*AL12)+IF(OR(AM12="",AN12=""),0,MAX(AM12-MAX(N12,IFERROR(SUMPRODUCT(MAX(((持仓跟踪!$A$2:$A$497="每日跟踪")*(持仓跟踪!$B$2:$B$497=A12))*持仓跟踪!$S$2:$S$497)),0)),0)*AN12)))) | AR12: =IF(A12="","",IF(OR(E12="",H12=""),"违规：第一批价格或股数缺失",IF(OR(AND(AK12="",AL12<>""),AND(AK12<>"",AL12="")),"违规：第二批价格与股数须成对填写",IF(OR(AND(AM12="",AN12<>""),AND(AM12<>"",AN12="")),"违规：第三批价格与股数须成对填写",IF(AND(OR(AM12<>"",AN12<>""),OR(AK12="",AL12="")),"违规：必须先完成第二批",IF(OR(H12<=0,H12<>INT(H12),MOD(H12,100)<>0,AND(AL12<>"",OR(AL12<=0,AL12<>INT(AL12),MOD(AL12,100)<>0)),AND(AN12<>"",OR(AN12<=0,AN12<>INT(AN12),MOD(AN12,100)<>0))),"违规：股数须为100股整数倍",IF(AND(OR(AL12<>"",AN12<>""),OR(_LockStatus="已锁仓",_LockStatus="解锁信息不完整")),"违规：锁仓期间禁止加仓",IF(AQ12>C12*D12,"违规：超过单笔风险上限",IF(SUM($AQ$2:$AQ$201)>账户数据!$B$7,"违规：超过账户风险上限","通过")))))))))
F13: =IF(OR(C13="",D13="",E13="",N13="",C13<=0,D13<=0,E13<=N13),"",ROUNDDOWN((C13*D13)/(E13-N13)/100,0)*100) | G13: =IF(A13="","",IF(H13<>"","已开仓",IF(账户数据!$B$23="已锁仓","禁止开仓：连续亏损达到上限",IF(账户数据!$B$23="解锁信息不完整","禁止开仓：请完整填写解锁信息",IF(OR(F13="",E13="",N13="",E13<=N13,账户数据!$B$7=""),"",IF(OR(AG13="",AH13="",AI13=""),"禁止开仓：交易预期未填写完整",IF(COUNTIFS(持仓跟踪!$A$2:$A$497,"止损计划",持仓跟踪!$B$2:$B$497,A13,持仓跟踪!$AC$2:$AC$497,"计划有效")=0,"禁止开仓：请先填写止损计划",IF(账户数据!$B$9+F13*(E13-N13)>=账户数据!$B$7,"禁止开仓：风险额度不足",IF(AJ13="周期与交易预期不匹配，请重新确认",IF(账户数据!$B$23="接近锁仓","允许开仓（接近锁仓；周期需复核）","允许开仓（周期需复核）"),IF(账户数据!$B$23="接近锁仓","允许开仓（接近锁仓）","允许开仓")))))))))) | L13: =IF(K13="","",H13) | U13: =IF(OR(AO13="",J13="",AO13<=0),"",(J13-AO13)/AO13) | V13: =IF(OR(AO13="",N13="",AO13<=0),"",(AO13-N13)/AO13) | W13: =IF(OR(U13="",V13="",V13<=0),"",U13/V13) | X13: =IF(OR(K13="",L13="",AP13=""),"",K13*L13-(E13*H13+IF(AND(AK13<>"",AL13<>""),AK13*AL13,0)+IF(AND(AM13<>"",AN13<>""),AM13*AN13,0))-IF(O13="",0,O13)-IF(P13="",0,P13)) | Y13: =IF(OR(X13="",AP13=""),"",IF((E13*H13+IF(AND(AK13<>"",AL13<>""),AK13*AL13,0)+IF(AND(AM13<>"",AN13<>""),AM13*AN13,0))+IF(O13="",0,O13)<=0,"",X13/((E13*H13+IF(AND(AK13<>"",AL13<>""),AK13*AL13,0)+IF(AND(AM13<>"",AN13<>""),AM13*AN13,0))+IF(O13="",0,O13)))) | Z13: =IF(OR(AE13="",多次统计数据!$B$8=""),"",AE13-多次统计数据!$B$8) | AA13: =IF(OR(I13="",M13="",M13<I13),"",M13-I13) | AB13: =IF(OR(A13="",多次统计数据!$B$8="",多次统计数据!$B$6<=0,多次统计数据!$B$6>=1),"",1-POWER(1+多次统计数据!$B$8,-多次统计数据!$B$6/(1-多次统计数据!$B$6))) | AC13: =IF(OR(AB13="",多次统计数据!$B$9=""),"",IF(多次统计数据!$B$9<AB13,"低于上限","达到或超过上限")) | AE13: =IF(OR(X13="",C13="",C13<=0),"",X13/C13) | AJ13: =IF(OR(AG13="",AH13=""),"",IF(OR(AND(AG13="短期博反弹",OR(AH13="1～3个交易日",AH13="4～10个交易日")),AND(AG13="突破冲新高",OR(AH13="4～10个交易日",AH13="11～20个交易日")),AND(AG13="趋势波段",OR(AH13="11～20个交易日",AH13="21～60个交易日",AH13="60个交易日以上"))),"匹配","周期与交易预期不匹配，请重新确认")) | AO13: =IF(OR(A13="",H13="",H13<=0),"",(E13*H13+IF(AND(AK13<>"",AL13<>""),AK13*AL13,0)+IF(AND(AM13<>"",AN13<>""),AM13*AN13,0))/AP13) | AP13: =IF(OR(A13="",H13="",H13<=0),"",H13+IF(AL13="",0,AL13)+IF(AN13="",0,AN13)) | AQ13: =IF(A13="","",IF(M13<>"",0,IF(OR(H13="",N13=""),"",MAX(E13-MAX(N13,IFERROR(SUMPRODUCT(MAX(((持仓跟踪!$A$2:$A$497="每日跟踪")*(持仓跟踪!$B$2:$B$497=A13))*持仓跟踪!$S$2:$S$497)),0)),0)*H13+IF(OR(AK13="",AL13=""),0,MAX(AK13-MAX(N13,IFERROR(SUMPRODUCT(MAX(((持仓跟踪!$A$2:$A$497="每日跟踪")*(持仓跟踪!$B$2:$B$497=A13))*持仓跟踪!$S$2:$S$497)),0)),0)*AL13)+IF(OR(AM13="",AN13=""),0,MAX(AM13-MAX(N13,IFERROR(SUMPRODUCT(MAX(((持仓跟踪!$A$2:$A$497="每日跟踪")*(持仓跟踪!$B$2:$B$497=A13))*持仓跟踪!$S$2:$S$497)),0)),0)*AN13)))) | AR13: =IF(A13="","",IF(OR(E13="",H13=""),"违规：第一批价格或股数缺失",IF(OR(AND(AK13="",AL13<>""),AND(AK13<>"",AL13="")),"违规：第二批价格与股数须成对填写",IF(OR(AND(AM13="",AN13<>""),AND(AM13<>"",AN13="")),"违规：第三批价格与股数须成对填写",IF(AND(OR(AM13<>"",AN13<>""),OR(AK13="",AL13="")),"违规：必须先完成第二批",IF(OR(H13<=0,H13<>INT(H13),MOD(H13,100)<>0,AND(AL13<>"",OR(AL13<=0,AL13<>INT(AL13),MOD(AL13,100)<>0)),AND(AN13<>"",OR(AN13<=0,AN13<>INT(AN13),MOD(AN13,100)<>0))),"违规：股数须为100股整数倍",IF(AND(OR(AL13<>"",AN13<>""),OR(_LockStatus="已锁仓",_LockStatus="解锁信息不完整")),"违规：锁仓期间禁止加仓",IF(AQ13>C13*D13,"违规：超过单笔风险上限",IF(SUM($AQ$2:$AQ$201)>账户数据!$B$7,"违规：超过账户风险上限","通过")))))))))
F14: =IF(OR(C14="",D14="",E14="",N14="",C14<=0,D14<=0,E14<=N14),"",ROUNDDOWN((C14*D14)/(E14-N14)/100,0)*100) | G14: =IF(A14="","",IF(H14<>"","已开仓",IF(账户数据!$B$23="已锁仓","禁止开仓：连续亏损达到上限",IF(账户数据!$B$23="解锁信息不完整","禁止开仓：请完整填写解锁信息",IF(OR(F14="",E14="",N14="",E14<=N14,账户数据!$B$7=""),"",IF(OR(AG14="",AH14="",AI14=""),"禁止开仓：交易预期未填写完整",IF(COUNTIFS(持仓跟踪!$A$2:$A$497,"止损计划",持仓跟踪!$B$2:$B$497,A14,持仓跟踪!$AC$2:$AC$497,"计划有效")=0,"禁止开仓：请先填写止损计划",IF(账户数据!$B$9+F14*(E14-N14)>=账户数据!$B$7,"禁止开仓：风险额度不足",IF(AJ14="周期与交易预期不匹配，请重新确认",IF(账户数据!$B$23="接近锁仓","允许开仓（接近锁仓；周期需复核）","允许开仓（周期需复核）"),IF(账户数据!$B$23="接近锁仓","允许开仓（接近锁仓）","允许开仓")))))))))) | L14: =IF(K14="","",H14) | U14: =IF(OR(AO14="",J14="",AO14<=0),"",(J14-AO14)/AO14) | V14: =IF(OR(AO14="",N14="",AO14<=0),"",(AO14-N14)/AO14) | W14: =IF(OR(U14="",V14="",V14<=0),"",U14/V14) | X14: =IF(OR(K14="",L14="",AP14=""),"",K14*L14-(E14*H14+IF(AND(AK14<>"",AL14<>""),AK14*AL14,0)+IF(AND(AM14<>"",AN14<>""),AM14*AN14,0))-IF(O14="",0,O14)-IF(P14="",0,P14)) | Y14: =IF(OR(X14="",AP14=""),"",IF((E14*H14+IF(AND(AK14<>"",AL14<>""),AK14*AL14,0)+IF(AND(AM14<>"",AN14<>""),AM14*AN14,0))+IF(O14="",0,O14)<=0,"",X14/((E14*H14+IF(AND(AK14<>"",AL14<>""),AK14*AL14,0)+IF(AND(AM14<>"",AN14<>""),AM14*AN14,0))+IF(O14="",0,O14)))) | Z14: =IF(OR(AE14="",多次统计数据!$B$8=""),"",AE14-多次统计数据!$B$8) | AA14: =IF(OR(I14="",M14="",M14<I14),"",M14-I14) | AB14: =IF(OR(A14="",多次统计数据!$B$8="",多次统计数据!$B$6<=0,多次统计数据!$B$6>=1),"",1-POWER(1+多次统计数据!$B$8,-多次统计数据!$B$6/(1-多次统计数据!$B$6))) | AC14: =IF(OR(AB14="",多次统计数据!$B$9=""),"",IF(多次统计数据!$B$9<AB14,"低于上限","达到或超过上限")) | AE14: =IF(OR(X14="",C14="",C14<=0),"",X14/C14) | AJ14: =IF(OR(AG14="",AH14=""),"",IF(OR(AND(AG14="短期博反弹",OR(AH14="1～3个交易日",AH14="4～10个交易日")),AND(AG14="突破冲新高",OR(AH14="4～10个交易日",AH14="11～20个交易日")),AND(AG14="趋势波段",OR(AH14="11～20个交易日",AH14="21～60个交易日",AH14="60个交易日以上"))),"匹配","周期与交易预期不匹配，请重新确认")) | AO14: =IF(OR(A14="",H14="",H14<=0),"",(E14*H14+IF(AND(AK14<>"",AL14<>""),AK14*AL14,0)+IF(AND(AM14<>"",AN14<>""),AM14*AN14,0))/AP14) | AP14: =IF(OR(A14="",H14="",H14<=0),"",H14+IF(AL14="",0,AL14)+IF(AN14="",0,AN14)) | AQ14: =IF(A14="","",IF(M14<>"",0,IF(OR(H14="",N14=""),"",MAX(E14-MAX(N14,IFERROR(SUMPRODUCT(MAX(((持仓跟踪!$A$2:$A$497="每日跟踪")*(持仓跟踪!$B$2:$B$497=A14))*持仓跟踪!$S$2:$S$497)),0)),0)*H14+IF(OR(AK14="",AL14=""),0,MAX(AK14-MAX(N14,IFERROR(SUMPRODUCT(MAX(((持仓跟踪!$A$2:$A$497="每日跟踪")*(持仓跟踪!$B$2:$B$497=A14))*持仓跟踪!$S$2:$S$497)),0)),0)*AL14)+IF(OR(AM14="",AN14=""),0,MAX(AM14-MAX(N14,IFERROR(SUMPRODUCT(MAX(((持仓跟踪!$A$2:$A$497="每日跟踪")*(持仓跟踪!$B$2:$B$497=A14))*持仓跟踪!$S$2:$S$497)),0)),0)*AN14)))) | AR14: =IF(A14="","",IF(OR(E14="",H14=""),"违规：第一批价格或股数缺失",IF(OR(AND(AK14="",AL14<>""),AND(AK14<>"",AL14="")),"违规：第二批价格与股数须成对填写",IF(OR(AND(AM14="",AN14<>""),AND(AM14<>"",AN14="")),"违规：第三批价格与股数须成对填写",IF(AND(OR(AM14<>"",AN14<>""),OR(AK14="",AL14="")),"违规：必须先完成第二批",IF(OR(H14<=0,H14<>INT(H14),MOD(H14,100)<>0,AND(AL14<>"",OR(AL14<=0,AL14<>INT(AL14),MOD(AL14,100)<>0)),AND(AN14<>"",OR(AN14<=0,AN14<>INT(AN14),MOD(AN14,100)<>0))),"违规：股数须为100股整数倍",IF(AND(OR(AL14<>"",AN14<>""),OR(_LockStatus="已锁仓",_LockStatus="解锁信息不完整")),"违规：锁仓期间禁止加仓",IF(AQ14>C14*D14,"违规：超过单笔风险上限",IF(SUM($AQ$2:$AQ$201)>账户数据!$B$7,"违规：超过账户风险上限","通过")))))))))
F15: =IF(OR(C15="",D15="",E15="",N15="",C15<=0,D15<=0,E15<=N15),"",ROUNDDOWN((C15*D15)/(E15-N15)/100,0)*100) | G15: =IF(A15="","",IF(H15<>"","已开仓",IF(账户数据!$B$23="已锁仓","禁止开仓：连续亏损达到上限",IF(账户数据!$B$23="解锁信息不完整","禁止开仓：请完整填写解锁信息",IF(OR(F15="",E15="",N15="",E15<=N15,账户数据!$B$7=""),"",IF(OR(AG15="",AH15="",AI15=""),"禁止开仓：交易预期未填写完整",IF(COUNTIFS(持仓跟踪!$A$2:$A$497,"止损计划",持仓跟踪!$B$2:$B$497,A15,持仓跟踪!$AC$2:$AC$497,"计划有效")=0,"禁止开仓：请先填写止损计划",IF(账户数据!$B$9+F15*(E15-N15)>=账户数据!$B$7,"禁止开仓：风险额度不足",IF(AJ15="周期与交易预期不匹配，请重新确认",IF(账户数据!$B$23="接近锁仓","允许开仓（接近锁仓；周期需复核）","允许开仓（周期需复核）"),IF(账户数据!$B$23="接近锁仓","允许开仓（接近锁仓）","允许开仓")))))))))) | L15: =IF(K15="","",H15) | U15: =IF(OR(AO15="",J15="",AO15<=0),"",(J15-AO15)/AO15) | V15: =IF(OR(AO15="",N15="",AO15<=0),"",(AO15-N15)/AO15) | W15: =IF(OR(U15="",V15="",V15<=0),"",U15/V15) | X15: =IF(OR(K15="",L15="",AP15=""),"",K15*L15-(E15*H15+IF(AND(AK15<>"",AL15<>""),AK15*AL15,0)+IF(AND(AM15<>"",AN15<>""),AM15*AN15,0))-IF(O15="",0,O15)-IF(P15="",0,P15)) | Y15: =IF(OR(X15="",AP15=""),"",IF((E15*H15+IF(AND(AK15<>"",AL15<>""),AK15*AL15,0)+IF(AND(AM15<>"",AN15<>""),AM15*AN15,0))+IF(O15="",0,O15)<=0,"",X15/((E15*H15+IF(AND(AK15<>"",AL15<>""),AK15*AL15,0)+IF(AND(AM15<>"",AN15<>""),AM15*AN15,0))+IF(O15="",0,O15)))) | Z15: =IF(OR(AE15="",多次统计数据!$B$8=""),"",AE15-多次统计数据!$B$8) | AA15: =IF(OR(I15="",M15="",M15<I15),"",M15-I15) | AB15: =IF(OR(A15="",多次统计数据!$B$8="",多次统计数据!$B$6<=0,多次统计数据!$B$6>=1),"",1-POWER(1+多次统计数据!$B$8,-多次统计数据!$B$6/(1-多次统计数据!$B$6))) | AC15: =IF(OR(AB15="",多次统计数据!$B$9=""),"",IF(多次统计数据!$B$9<AB15,"低于上限","达到或超过上限")) | AE15: =IF(OR(X15="",C15="",C15<=0),"",X15/C15) | AJ15: =IF(OR(AG15="",AH15=""),"",IF(OR(AND(AG15="短期博反弹",OR(AH15="1～3个交易日",AH15="4～10个交易日")),AND(AG15="突破冲新高",OR(AH15="4～10个交易日",AH15="11～20个交易日")),AND(AG15="趋势波段",OR(AH15="11～20个交易日",AH15="21～60个交易日",AH15="60个交易日以上"))),"匹配","周期与交易预期不匹配，请重新确认")) | AO15: =IF(OR(A15="",H15="",H15<=0),"",(E15*H15+IF(AND(AK15<>"",AL15<>""),AK15*AL15,0)+IF(AND(AM15<>"",AN15<>""),AM15*AN15,0))/AP15) | AP15: =IF(OR(A15="",H15="",H15<=0),"",H15+IF(AL15="",0,AL15)+IF(AN15="",0,AN15)) | AQ15: =IF(A15="","",IF(M15<>"",0,IF(OR(H15="",N15=""),"",MAX(E15-MAX(N15,IFERROR(SUMPRODUCT(MAX(((持仓跟踪!$A$2:$A$497="每日跟踪")*(持仓跟踪!$B$2:$B$497=A15))*持仓跟踪!$S$2:$S$497)),0)),0)*H15+IF(OR(AK15="",AL15=""),0,MAX(AK15-MAX(N15,IFERROR(SUMPRODUCT(MAX(((持仓跟踪!$A$2:$A$497="每日跟踪")*(持仓跟踪!$B$2:$B$497=A15))*持仓跟踪!$S$2:$S$497)),0)),0)*AL15)+IF(OR(AM15="",AN15=""),0,MAX(AM15-MAX(N15,IFERROR(SUMPRODUCT(MAX(((持仓跟踪!$A$2:$A$497="每日跟踪")*(持仓跟踪!$B$2:$B$497=A15))*持仓跟踪!$S$2:$S$497)),0)),0)*AN15)))) | AR15: =IF(A15="","",IF(OR(E15="",H15=""),"违规：第一批价格或股数缺失",IF(OR(AND(AK15="",AL15<>""),AND(AK15<>"",AL15="")),"违规：第二批价格与股数须成对填写",IF(OR(AND(AM15="",AN15<>""),AND(AM15<>"",AN15="")),"违规：第三批价格与股数须成对填写",IF(AND(OR(AM15<>"",AN15<>""),OR(AK15="",AL15="")),"违规：必须先完成第二批",IF(OR(H15<=0,H15<>INT(H15),MOD(H15,100)<>0,AND(AL15<>"",OR(AL15<=0,AL15<>INT(AL15),MOD(AL15,100)<>0)),AND(AN15<>"",OR(AN15<=0,AN15<>INT(AN15),MOD(AN15,100)<>0))),"违规：股数须为100股整数倍",IF(AND(OR(AL15<>"",AN15<>""),OR(_LockStatus="已锁仓",_LockStatus="解锁信息不完整")),"违规：锁仓期间禁止加仓",IF(AQ15>C15*D15,"违规：超过单笔风险上限",IF(SUM($AQ$2:$AQ$201)>账户数据!$B$7,"违规：超过账户风险上限","通过")))))))))
... F103: =IF(OR(C103="",D103="",E103="",N103="",C103<=0,D103<=0,E103<=N103),"",ROUNDDOWN((C103*D103)/(E103-N103)/100,0)*100) | G103: =IF(A103="","",IF(H103<>"","已开仓",IF(账户数据!$B$23="已锁仓","禁止开仓：连续亏损达到上限",IF(账户数据!$B$23="解锁信息不完整","禁止开仓：请完整填写解锁信息",IF(OR(F103="",E103="",N103="",E103<=N103,账户数据!$B$7=""),"",IF(OR(AG103="",AH103="",AI103=""),"禁止开仓：交易预期未填写完整",IF(COUNTIFS(持仓跟踪!$A$2:$A$497,"止损计划",持仓跟踪!$B$2:$B$497,A103,持仓跟踪!$AC$2:$AC$497,"计划有效")=0,"禁止开仓：请先填写止损计划",IF(账户数据!$B$9+F103*(E103-N103)>=账户数据!$B$7,"禁止开仓：风险额度不足",IF(AJ103="周期与交易预期不匹配，请重新确认",IF(账户数据!$B$23="接近锁仓","允许开仓（接近锁仓；周期需复核）","允许开仓（周期需复核）"),IF(账户数据!$B$23="接近锁仓","允许开仓（接近锁仓）","允许开仓")))))))))) | L103: =IF(K103="","",H103) | U103: =IF(OR(AO103="",J103="",AO103<=0),"",(J103-AO103)/AO103) | V103: =IF(OR(AO103="",N103="",AO103<=0),"",(AO103-N103)/AO103) | W103: =IF(OR(U103="",V103="",V103<=0),"",U103/V103) | X103: =IF(OR(K103="",L103="",AP103=""),"",K103*L103-(E103*H103+IF(AND(AK103<>"",AL103<>""),AK103*AL103,0)+IF(AND(AM103<>"",AN103<>""),AM103*AN103,0))-IF(O103="",0,O103)-IF(P103="",0,P103)) | Y103: =IF(OR(X103="",AP103=""),"",IF((E103*H103+IF(AND(AK103<>"",AL103<>""),AK103*AL103,0)+IF(AND(AM103<>"",AN103<>""),AM103*AN103,0))+IF(O103="",0,O103)<=0,"",X103/((E103*H103+IF(AND(AK103<>"",AL103<>""),AK103*AL103,0)+IF(AND(AM103<>"",AN103<>""),AM103*AN103,0))+IF(O103="",0,O103)))) | Z103: =IF(OR(AE103="",多次统计数据!$B$8=""),"",AE103-多次统计数据!$B$8) | AA103: =IF(OR(I103="",M103="",M103<I103),"",M103-I103) | AB103: =IF(OR(A103="",多次统计数据!$B$8="",多次统计数据!$B$6<=0,多次统计数据!$B$6>=1),"",1-POWER(1+多次统计数据!$B$8,-多次统计数据!$B$6/(1-多次统计数据!$B$6))) | AC103: =IF(OR(AB103="",多次统计数据!$B$9=""),"",IF(多次统计数据!$B$9<AB103,"低于上限","达到或超过上限")) | AE103: =IF(OR(X103="",C103="",C103<=0),"",X103/C103) | AJ103: =IF(OR(AG103="",AH103=""),"",IF(OR(AND(AG103="短期博反弹",OR(AH103="1～3个交易日",AH103="4～10个交易日")),AND(AG103="突破冲新高",OR(AH103="4～10个交易日",AH103="11～20个交易日")),AND(AG103="趋势波段",OR(AH103="11～20个交易日",AH103="21～60个交易日",AH103="60个交易日以上"))),"匹配","周期与交易预期不匹配，请重新确认")) | AO103: =IF(OR(A103="",H103="",H103<=0),"",(E103*H103+IF(AND(AK103<>"",AL103<>""),AK103*AL103,0)+IF(AND(AM103<>"",AN103<>""),AM103*AN103,0))/AP103) | AP103: =IF(OR(A103="",H103="",H103<=0),"",H103+IF(AL103="",0,AL103)+IF(AN103="",0,AN103)) | AQ103: =IF(A103="","",IF(M103<>"",0,IF(OR(H103="",N103=""),"",MAX(E103-MAX(N103,IFERROR(SUMPRODUCT(MAX(((持仓跟踪!$A$2:$A$497="每日跟踪")*(持仓跟踪!$B$2:$B$497=A103))*持仓跟踪!$S$2:$S$497)),0)),0)*H103+IF(OR(AK103="",AL103=""),0,MAX(AK103-MAX(N103,IFERROR(SUMPRODUCT(MAX(((持仓跟踪!$A$2:$A$497="每日跟踪")*(持仓跟踪!$B$2:$B$497=A103))*持仓跟踪!$S$2:$S$497)),0)),0)*AL103)+IF(OR(AM103="",AN103=""),0,MAX(AM103-MAX(N103,IFERROR(SUMPRODUCT(MAX(((持仓跟踪!$A$2:$A$497="每日跟踪")*(持仓跟踪!$B$2:$B$497=A103))*持仓跟踪!$S$2:$S$497)),0)),0)*AN103)))) | AR103: =IF(A103="","",IF(OR(E103="",H103=""),"违规：第一批价格或股数缺失",IF(OR(AND(AK103="",AL103<>""),AND(AK103<>"",AL103="")),"违规：第二批价格与股数须成对填写",IF(OR(AND(AM103="",AN103<>""),AND(AM103<>"",AN103="")),"违规：第三批价格与股数须成对填写",IF(AND(OR(AM103<>"",AN103<>""),OR(AK103="",AL103="")),"违规：必须先完成第二批",IF(OR(H103<=0,H103<>INT(H103),MOD(H103,100)<>0,AND(AL103<>"",OR(AL103<=0,AL103<>INT(AL103),MOD(AL103,100)<>0)),AND(AN103<>"",OR(AN103<=0,AN103<>INT(AN103),MOD(AN103,100)<>0))),"违规：股数须为100股整数倍",IF(AND(OR(AL103<>"",AN103<>""),OR(_LockStatus="已锁仓",_LockStatus="解锁信息不完整")),"违规：锁仓期间禁止加仓",IF(AQ103>C103*D103,"违规：超过单笔风险上限",IF(SUM($AQ$2:$AQ$201)>账户数据!$B$7,"违规：超过账户风险上限","通过")))))))))
F104: =IF(OR(C104="",D104="",E104="",N104="",C104<=0,D104<=0,E104<=N104),"",ROUNDDOWN((C104*D104)/(E104-N104)/100,0)*100) | G104: =IF(A104="","",IF(H104<>"","已开仓",IF(账户数据!$B$23="已锁仓","禁止开仓：连续亏损达到上限",IF(账户数据!$B$23="解锁信息不完整","禁止开仓：请完整填写解锁信息",IF(OR(F104="",E104="",N104="",E104<=N104,账户数据!$B$7=""),"",IF(OR(AG104="",AH104="",AI104=""),"禁止开仓：交易预期未填写完整",IF(COUNTIFS(持仓跟踪!$A$2:$A$497,"止损计划",持仓跟踪!$B$2:$B$497,A104,持仓跟踪!$AC$2:$AC$497,"计划有效")=0,"禁止开仓：请先填写止损计划",IF(账户数据!$B$9+F104*(E104-N104)>=账户数据!$B$7,"禁止开仓：风险额度不足",IF(AJ104="周期与交易预期不匹配，请重新确认",IF(账户数据!$B$23="接近锁仓","允许开仓（接近锁仓；周期需复核）","允许开仓（周期需复核）"),IF(账户数据!$B$23="接近锁仓","允许开仓（接近锁仓）","允许开仓")))))))))) | M104: =IF(A104="","",IFERROR(LOOKUP(2,1/((持仓跟踪!$B$2:$B$497=A104)*(持仓跟踪!$X$2:$X$497="执行卖出")*(持仓跟踪!$H$2:$H$497<>"")),持仓跟踪!$H$2:$H$497),"")) | P104: =IF(A104="","",IFERROR(LOOKUP(2,1/((持仓跟踪!$B$2:$B$497=A104)*(持仓跟踪!$X$2:$X$497="执行卖出")*(持仓跟踪!$AA$2:$AA$497<>"")),持仓跟踪!$AA$2:$AA$497),"")) | U104: =IF(OR(AO104="",J104="",AO104<=0),"",(J104-AO104)/AO104) | V104: =IF(OR(AO104="",N104="",AO104<=0),"",(AO104-N104)/AO104) | W104: =IF(OR(U104="",V104="",V104<=0),"",U104/V104) | X104: =IF(OR(K104="",L104="",AP104=""),"",K104*L104-(E104*H104+IF(AND(AK104<>"",AL104<>""),AK104*AL104,0)+IF(AND(AM104<>"",AN104<>""),AM104*AN104,0))-IF(O104="",0,O104)-IF(P104="",0,P104)) | Y104: =IF(OR(X104="",AP104=""),"",IF((E104*H104+IF(AND(AK104<>"",AL104<>""),AK104*AL104,0)+IF(AND(AM104<>"",AN104<>""),AM104*AN104,0))+IF(O104="",0,O104)<=0,"",X104/((E104*H104+IF(AND(AK104<>"",AL104<>""),AK104*AL104,0)+IF(AND(AM104<>"",AN104<>""),AM104*AN104,0))+IF(O104="",0,O104)))) | Z104: =IF(OR(AE104="",多次统计数据!$B$8=""),"",AE104-多次统计数据!$B$8) | AA104: =IF(OR(I104="",M104="",M104<I104),"",M104-I104) | AB104: =IF(OR(A104="",多次统计数据!$B$8="",多次统计数据!$B$6<=0,多次统计数据!$B$6>=1),"",1-POWER(1+多次统计数据!$B$8,-多次统计数据!$B$6/(1-多次统计数据!$B$6))) | AC104: =IF(OR(AB104="",多次统计数据!$B$9=""),"",IF(多次统计数据!$B$9<AB104,"低于上限","达到或超过上限")) | AE104: =IF(OR(X104="",C104="",C104<=0),"",X104/C104) | AJ104: =IF(OR(AG104="",AH104=""),"",IF(OR(AND(AG104="短期博反弹",OR(AH104="1～3个交易日",AH104="4～10个交易日")),AND(AG104="突破冲新高",OR(AH104="4～10个交易日",AH104="11～20个交易日")),AND(AG104="趋势波段",OR(AH104="11～20个交易日",AH104="21～60个交易日",AH104="60个交易日以上"))),"匹配","周期与交易预期不匹配，请重新确认")) | AO104: =IF(OR(A104="",H104="",H104<=0),"",(E104*H104+IF(AND(AK104<>"",AL104<>""),AK104*AL104,0)+IF(AND(AM104<>"",AN104<>""),AM104*AN104,0))/AP104) | AP104: =IF(OR(A104="",H104="",H104<=0),"",H104+IF(AL104="",0,AL104)+IF(AN104="",0,AN104)) | AQ104: =IF(A104="","",IF(M104<>"",0,IF(OR(H104="",N104=""),"",MAX(E104-MAX(N104,IFERROR(SUMPRODUCT(MAX(((持仓跟踪!$A$2:$A$497="每日跟踪")*(持仓跟踪!$B$2:$B$497=A104))*持仓跟踪!$S$2:$S$497)),0)),0)*H104+IF(OR(AK104="",AL104=""),0,MAX(AK104-MAX(N104,IFERROR(SUMPRODUCT(MAX(((持仓跟踪!$A$2:$A$497="每日跟踪")*(持仓跟踪!$B$2:$B$497=A104))*持仓跟踪!$S$2:$S$497)),0)),0)*AL104)+IF(OR(AM104="",AN104=""),0,MAX(AM104-MAX(N104,IFERROR(SUMPRODUCT(MAX(((持仓跟踪!$A$2:$A$497="每日跟踪")*(持仓跟踪!$B$2:$B$497=A104))*持仓跟踪!$S$2:$S$497)),0)),0)*AN104)))) | AR104: =IF(A104="","",IF(OR(E104="",H104=""),"违规：第一批价格或股数缺失",IF(OR(AND(AK104="",AL104<>""),AND(AK104<>"",AL104="")),"违规：第二批价格与股数须成对填写",IF(OR(AND(AM104="",AN104<>""),AND(AM104<>"",AN104="")),"违规：第三批价格与股数须成对填写",IF(AND(OR(AM104<>"",AN104<>""),OR(AK104="",AL104="")),"违规：必须先完成第二批",IF(OR(H104<=0,H104<>INT(H104),MOD(H104,100)<>0,AND(AL104<>"",OR(AL104<=0,AL104<>INT(AL104),MOD(AL104,100)<>0)),AND(AN104<>"",OR(AN104<=0,AN104<>INT(AN104),MOD(AN104,100)<>0))),"违规：股数须为100股整数倍",IF(AND(OR(AL104<>"",AN104<>""),OR(_LockStatus="已锁仓",_LockStatus="解锁信息不完整")),"违规：锁仓期间禁止加仓",IF(AQ104>C104*D104,"违规：超过单笔风险上限",IF(SUM($AQ$2:$AQ$201)>账户数据!$B$7,"违规：超过账户风险上限","通过")))))))))
F105: =IF(OR(C105="",D105="",E105="",N105="",C105<=0,D105<=0,E105<=N105),"",ROUNDDOWN((C105*D105)/(E105-N105)/100,0)*100) | G105: =IF(A105="","",IF(H105<>"","已开仓",IF(账户数据!$B$23="已锁仓","禁止开仓：连续亏损达到上限",IF(账户数据!$B$23="解锁信息不完整","禁止开仓：请完整填写解锁信息",IF(OR(F105="",E105="",N105="",E105<=N105,账户数据!$B$7=""),"",IF(OR(AG105="",AH105="",AI105=""),"禁止开仓：交易预期未填写完整",IF(COUNTIFS(持仓跟踪!$A$2:$A$497,"止损计划",持仓跟踪!$B$2:$B$497,A105,持仓跟踪!$AC$2:$AC$497,"计划有效")=0,"禁止开仓：请先填写止损计划",IF(账户数据!$B$9+F105*(E105-N105)>=账户数据!$B$7,"禁止开仓：风险额度不足",IF(AJ105="周期与交易预期不匹配，请重新确认",IF(账户数据!$B$23="接近锁仓","允许开仓（接近锁仓；周期需复核）","允许开仓（周期需复核）"),IF(账户数据!$B$23="接近锁仓","允许开仓（接近锁仓）","允许开仓")))))))))) | K105: =IF(A105="","",IFERROR(LOOKUP(2,1/((持仓跟踪!$B$2:$B$497=A105)*(持仓跟踪!$X$2:$X$497="执行卖出")*(持仓跟踪!$Y$2:$Y$497<>"")),持仓跟踪!$Y$2:$Y$497),"")) | L105: =IF(A105="","",IFERROR(LOOKUP(2,1/((持仓跟踪!$B$2:$B$497=A105)*(持仓跟踪!$X$2:$X$497="执行卖出")*(持仓跟踪!$Z$2:$Z$497<>"")),持仓跟踪!$Z$2:$Z$497),"")) | M105: =IF(A105="","",IFERROR(LOOKUP(2,1/((持仓跟踪!$B$2:$B$497=A105)*(持仓跟踪!$X$2:$X$497="执行卖出")*(持仓跟踪!$H$2:$H$497<>"")),持仓跟踪!$H$2:$H$497),"")) | P105: =IF(A105="","",IFERROR(LOOKUP(2,1/((持仓跟踪!$B$2:$B$497=A105)*(持仓跟踪!$X$2:$X$497="执行卖出")*(持仓跟踪!$AA$2:$AA$497<>"")),持仓跟踪!$AA$2:$AA$497),"")) | U105: =IF(OR(AO105="",J105="",AO105<=0),"",(J105-AO105)/AO105) | V105: =IF(OR(AO105="",N105="",AO105<=0),"",(AO105-N105)/AO105) | W105: =IF(OR(U105="",V105="",V105<=0),"",U105/V105) | X105: =IF(OR(K105="",L105="",AP105=""),"",K105*L105-(E105*H105+IF(AND(AK105<>"",AL105<>""),AK105*AL105,0)+IF(AND(AM105<>"",AN105<>""),AM105*AN105,0))-IF(O105="",0,O105)-IF(P105="",0,P105)) | Y105: =IF(OR(X105="",AP105=""),"",IF((E105*H105+IF(AND(AK105<>"",AL105<>""),AK105*AL105,0)+IF(AND(AM105<>"",AN105<>""),AM105*AN105,0))+IF(O105="",0,O105)<=0,"",X105/((E105*H105+IF(AND(AK105<>"",AL105<>""),AK105*AL105,0)+IF(AND(AM105<>"",AN105<>""),AM105*AN105,0))+IF(O105="",0,O105)))) | Z105: =IF(OR(AE105="",多次统计数据!$B$8=""),"",AE105-多次统计数据!$B$8) | AA105: =IF(OR(I105="",M105="",M105<I105),"",M105-I105) | AB105: =IF(OR(A105="",多次统计数据!$B$8="",多次统计数据!$B$6<=0,多次统计数据!$B$6>=1),"",1-POWER(1+多次统计数据!$B$8,-多次统计数据!$B$6/(1-多次统计数据!$B$6))) | AC105: =IF(OR(AB105="",多次统计数据!$B$9=""),"",IF(多次统计数据!$B$9<AB105,"低于上限","达到或超过上限")) | AE105: =IF(OR(X105="",C105="",C105<=0),"",X105/C105) | AJ105: =IF(OR(AG105="",AH105=""),"",IF(OR(AND(AG105="短期博反弹",OR(AH105="1～3个交易日",AH105="4～10个交易日")),AND(AG105="突破冲新高",OR(AH105="4～10个交易日",AH105="11～20个交易日")),AND(AG105="趋势波段",OR(AH105="11～20个交易日",AH105="21～60个交易日",AH105="60个交易日以上"))),"匹配","周期与交易预期不匹配，请重新确认")) | AO105: =IF(OR(A105="",H105="",H105<=0),"",(E105*H105+IF(AND(AK105<>"",AL105<>""),AK105*AL105,0)+IF(AND(AM105<>"",AN105<>""),AM105*AN105,0))/AP105) | AP105: =IF(OR(A105="",H105="",H105<=0),"",H105+IF(AL105="",0,AL105)+IF(AN105="",0,AN105)) | AQ105: =IF(A105="","",IF(M105<>"",0,IF(OR(H105="",N105=""),"",MAX(E105-MAX(N105,IFERROR(SUMPRODUCT(MAX(((持仓跟踪!$A$2:$A$497="每日跟踪")*(持仓跟踪!$B$2:$B$497=A105))*持仓跟踪!$S$2:$S$497)),0)),0)*H105+IF(OR(AK105="",AL105=""),0,MAX(AK105-MAX(N105,IFERROR(SUMPRODUCT(MAX(((持仓跟踪!$A$2:$A$497="每日跟踪")*(持仓跟踪!$B$2:$B$497=A105))*持仓跟踪!$S$2:$S$497)),0)),0)*AL105)+IF(OR(AM105="",AN105=""),0,MAX(AM105-MAX(N105,IFERROR(SUMPRODUCT(MAX(((持仓跟踪!$A$2:$A$497="每日跟踪")*(持仓跟踪!$B$2:$B$497=A105))*持仓跟踪!$S$2:$S$497)),0)),0)*AN105)))) | AR105: =IF(A105="","",IF(OR(E105="",H105=""),"违规：第一批价格或股数缺失",IF(OR(AND(AK105="",AL105<>""),AND(AK105<>"",AL105="")),"违规：第二批价格与股数须成对填写",IF(OR(AND(AM105="",AN105<>""),AND(AM105<>"",AN105="")),"违规：第三批价格与股数须成对填写",IF(AND(OR(AM105<>"",AN105<>""),OR(AK105="",AL105="")),"违规：必须先完成第二批",IF(OR(H105<=0,H105<>INT(H105),MOD(H105,100)<>0,AND(AL105<>"",OR(AL105<=0,AL105<>INT(AL105),MOD(AL105,100)<>0)),AND(AN105<>"",OR(AN105<=0,AN105<>INT(AN105),MOD(AN105,100)<>0))),"违规：股数须为100股整数倍",IF(AND(OR(AL105<>"",AN105<>""),OR(_LockStatus="已锁仓",_LockStatus="解锁信息不完整")),"违规：锁仓期间禁止加仓",IF(AQ105>C105*D105,"违规：超过单笔风险上限",IF(SUM($AQ$2:$AQ$201)>账户数据!$B$7,"违规：超过账户风险上限","通过")))))))))
F106: =IF(OR(C106="",D106="",E106="",N106="",C106<=0,D106<=0,E106<=N106),"",ROUNDDOWN((C106*D106)/(E106-N106)/100,0)*100) | G106: =IF(A106="","",IF(H106<>"","已开仓",IF(账户数据!$B$23="已锁仓","禁止开仓：连续亏损达到上限",IF(账户数据!$B$23="解锁信息不完整","禁止开仓：请完整填写解锁信息",IF(OR(F106="",E106="",N106="",E106<=N106,账户数据!$B$7=""),"",IF(OR(AG106="",AH106="",AI106=""),"禁止开仓：交易预期未填写完整",IF(COUNTIFS(持仓跟踪!$A$2:$A$497,"止损计划",持仓跟踪!$B$2:$B$497,A106,持仓跟踪!$AC$2:$AC$497,"计划有效")=0,"禁止开仓：请先填写止损计划",IF(账户数据!$B$9+F106*(E106-N106)>=账户数据!$B$7,"禁止开仓：风险额度不足",IF(AJ106="周期与交易预期不匹配，请重新确认",IF(账户数据!$B$23="接近锁仓","允许开仓（接近锁仓；周期需复核）","允许开仓（周期需复核）"),IF(账户数据!$B$23="接近锁仓","允许开仓（接近锁仓）","允许开仓")))))))))) | K106: =IF(A106="","",IFERROR(LOOKUP(2,1/((持仓跟踪!$B$2:$B$497=A106)*(持仓跟踪!$X$2:$X$497="执行卖出")*(持仓跟踪!$Y$2:$Y$497<>"")),持仓跟踪!$Y$2:$Y$497),"")) | L106: =IF(A106="","",IFERROR(LOOKUP(2,1/((持仓跟踪!$B$2:$B$497=A106)*(持仓跟踪!$X$2:$X$497="执行卖出")*(持仓跟踪!$Z$2:$Z$497<>"")),持仓跟踪!$Z$2:$Z$497),"")) | M106: =IF(A106="","",IFERROR(LOOKUP(2,1/((持仓跟踪!$B$2:$B$497=A106)*(持仓跟踪!$X$2:$X$497="执行卖出")*(持仓跟踪!$H$2:$H$497<>"")),持仓跟踪!$H$2:$H$497),"")) | P106: =IF(A106="","",IFERROR(LOOKUP(2,1/((持仓跟踪!$B$2:$B$497=A106)*(持仓跟踪!$X$2:$X$497="执行卖出")*(持仓跟踪!$AA$2:$AA$497<>"")),持仓跟踪!$AA$2:$AA$497),"")) | U106: =IF(OR(AO106="",J106="",AO106<=0),"",(J106-AO106)/AO106) | V106: =IF(OR(AO106="",N106="",AO106<=0),"",(AO106-N106)/AO106) | W106: =IF(OR(U106="",V106="",V106<=0),"",U106/V106) | X106: =IF(OR(K106="",L106="",AP106=""),"",K106*L106-(E106*H106+IF(AND(AK106<>"",AL106<>""),AK106*AL106,0)+IF(AND(AM106<>"",AN106<>""),AM106*AN106,0))-IF(O106="",0,O106)-IF(P106="",0,P106)) | Y106: =IF(OR(X106="",AP106=""),"",IF((E106*H106+IF(AND(AK106<>"",AL106<>""),AK106*AL106,0)+IF(AND(AM106<>"",AN106<>""),AM106*AN106,0))+IF(O106="",0,O106)<=0,"",X106/((E106*H106+IF(AND(AK106<>"",AL106<>""),AK106*AL106,0)+IF(AND(AM106<>"",AN106<>""),AM106*AN106,0))+IF(O106="",0,O106)))) | Z106: =IF(OR(AE106="",多次统计数据!$B$8=""),"",AE106-多次统计数据!$B$8) | AA106: =IF(OR(I106="",M106="",M106<I106),"",M106-I106) | AB106: =IF(OR(A106="",多次统计数据!$B$8="",多次统计数据!$B$6<=0,多次统计数据!$B$6>=1),"",1-POWER(1+多次统计数据!$B$8,-多次统计数据!$B$6/(1-多次统计数据!$B$6))) | AC106: =IF(OR(AB106="",多次统计数据!$B$9=""),"",IF(多次统计数据!$B$9<AB106,"低于上限","达到或超过上限")) | AE106: =IF(OR(X106="",C106="",C106<=0),"",X106/C106) | AJ106: =IF(OR(AG106="",AH106=""),"",IF(OR(AND(AG106="短期博反弹",OR(AH106="1～3个交易日",AH106="4～10个交易日")),AND(AG106="突破冲新高",OR(AH106="4～10个交易日",AH106="11～20个交易日")),AND(AG106="趋势波段",OR(AH106="11～20个交易日",AH106="21～60个交易日",AH106="60个交易日以上"))),"匹配","周期与交易预期不匹配，请重新确认")) | AO106: =IF(OR(A106="",H106="",H106<=0),"",(E106*H106+IF(AND(AK106<>"",AL106<>""),AK106*AL106,0)+IF(AND(AM106<>"",AN106<>""),AM106*AN106,0))/AP106) | AP106: =IF(OR(A106="",H106="",H106<=0),"",H106+IF(AL106="",0,AL106)+IF(AN106="",0,AN106)) | AQ106: =IF(A106="","",IF(M106<>"",0,IF(OR(H106="",N106=""),"",MAX(E106-MAX(N106,IFERROR(SUMPRODUCT(MAX(((持仓跟踪!$A$2:$A$497="每日跟踪")*(持仓跟踪!$B$2:$B$497=A106))*持仓跟踪!$S$2:$S$497)),0)),0)*H106+IF(OR(AK106="",AL106=""),0,MAX(AK106-MAX(N106,IFERROR(SUMPRODUCT(MAX(((持仓跟踪!$A$2:$A$497="每日跟踪")*(持仓跟踪!$B$2:$B$497=A106))*持仓跟踪!$S$2:$S$497)),0)),0)*AL106)+IF(OR(AM106="",AN106=""),0,MAX(AM106-MAX(N106,IFERROR(SUMPRODUCT(MAX(((持仓跟踪!$A$2:$A$497="每日跟踪")*(持仓跟踪!$B$2:$B$497=A106))*持仓跟踪!$S$2:$S$497)),0)),0)*AN106)))) | AR106: =IF(A106="","",IF(OR(E106="",H106=""),"违规：第一批价格或股数缺失",IF(OR(AND(AK106="",AL106<>""),AND(AK106<>"",AL106="")),"违规：第二批价格与股数须成对填写",IF(OR(AND(AM106="",AN106<>""),AND(AM106<>"",AN106="")),"违规：第三批价格与股数须成对填写",IF(AND(OR(AM106<>"",AN106<>""),OR(AK106="",AL106="")),"违规：必须先完成第二批",IF(OR(H106<=0,H106<>INT(H106),MOD(H106,100)<>0,AND(AL106<>"",OR(AL106<=0,AL106<>INT(AL106),MOD(AL106,100)<>0)),AND(AN106<>"",OR(AN106<=0,AN106<>INT(AN106),MOD(AN106,100)<>0))),"违规：股数须为100股整数倍",IF(AND(OR(AL106<>"",AN106<>""),OR(_LockStatus="已锁仓",_LockStatus="解锁信息不完整")),"违规：锁仓期间禁止加仓",IF(AQ106>C106*D106,"违规：超过单笔风险上限",IF(SUM($AQ$2:$AQ$201)>账户数据!$B$7,"违规：超过账户风险上限","通过")))))))))
F107: =IF(OR(C107="",D107="",E107="",N107="",C107<=0,D107<=0,E107<=N107),"",ROUNDDOWN((C107*D107)/(E107-N107)/100,0)*100) | G107: =IF(A107="","",IF(H107<>"","已开仓",IF(账户数据!$B$23="已锁仓","禁止开仓：连续亏损达到上限",IF(账户数据!$B$23="解锁信息不完整","禁止开仓：请完整填写解锁信息",IF(OR(F107="",E107="",N107="",E107<=N107,账户数据!$B$7=""),"",IF(OR(AG107="",AH107="",AI107=""),"禁止开仓：交易预期未填写完整",IF(COUNTIFS(持仓跟踪!$A$2:$A$497,"止损计划",持仓跟踪!$B$2:$B$497,A107,持仓跟踪!$AC$2:$AC$497,"计划有效")=0,"禁止开仓：请先填写止损计划",IF(账户数据!$B$9+F107*(E107-N107)>=账户数据!$B$7,"禁止开仓：风险额度不足",IF(AJ107="周期与交易预期不匹配，请重新确认",IF(账户数据!$B$23="接近锁仓","允许开仓（接近锁仓；周期需复核）","允许开仓（周期需复核）"),IF(账户数据!$B$23="接近锁仓","允许开仓（接近锁仓）","允许开仓")))))))))) | K107: =IF(A107="","",IFERROR(LOOKUP(2,1/((持仓跟踪!$B$2:$B$497=A107)*(持仓跟踪!$X$2:$X$497="执行卖出")*(持仓跟踪!$Y$2:$Y$497<>"")),持仓跟踪!$Y$2:$Y$497),"")) | L107: =IF(A107="","",IFERROR(LOOKUP(2,1/((持仓跟踪!$B$2:$B$497=A107)*(持仓跟踪!$X$2:$X$497="执行卖出")*(持仓跟踪!$Z$2:$Z$497<>"")),持仓跟踪!$Z$2:$Z$497),"")) | M107: =IF(A107="","",IFERROR(LOOKUP(2,1/((持仓跟踪!$B$2:$B$497=A107)*(持仓跟踪!$X$2:$X$497="执行卖出")*(持仓跟踪!$H$2:$H$497<>"")),持仓跟踪!$H$2:$H$497),"")) | P107: =IF(A107="","",IFERROR(LOOKUP(2,1/((持仓跟踪!$B$2:$B$497=A107)*(持仓跟踪!$X$2:$X$497="执行卖出")*(持仓跟踪!$AA$2:$AA$497<>"")),持仓跟踪!$AA$2:$AA$497),"")) | U107: =IF(OR(AO107="",J107="",AO107<=0),"",(J107-AO107)/AO107) | V107: =IF(OR(AO107="",N107="",AO107<=0),"",(AO107-N107)/AO107) | W107: =IF(OR(U107="",V107="",V107<=0),"",U107/V107) | X107: =IF(OR(K107="",L107="",AP107=""),"",K107*L107-(E107*H107+IF(AND(AK107<>"",AL107<>""),AK107*AL107,0)+IF(AND(AM107<>"",AN107<>""),AM107*AN107,0))-IF(O107="",0,O107)-IF(P107="",0,P107)) | Y107: =IF(OR(X107="",AP107=""),"",IF((E107*H107+IF(AND(AK107<>"",AL107<>""),AK107*AL107,0)+IF(AND(AM107<>"",AN107<>""),AM107*AN107,0))+IF(O107="",0,O107)<=0,"",X107/((E107*H107+IF(AND(AK107<>"",AL107<>""),AK107*AL107,0)+IF(AND(AM107<>"",AN107<>""),AM107*AN107,0))+IF(O107="",0,O107)))) | Z107: =IF(OR(AE107="",多次统计数据!$B$8=""),"",AE107-多次统计数据!$B$8) | AA107: =IF(OR(I107="",M107="",M107<I107),"",M107-I107) | AB107: =IF(OR(A107="",多次统计数据!$B$8="",多次统计数据!$B$6<=0,多次统计数据!$B$6>=1),"",1-POWER(1+多次统计数据!$B$8,-多次统计数据!$B$6/(1-多次统计数据!$B$6))) | AC107: =IF(OR(AB107="",多次统计数据!$B$9=""),"",IF(多次统计数据!$B$9<AB107,"低于上限","达到或超过上限")) | AE107: =IF(OR(X107="",C107="",C107<=0),"",X107/C107) | AJ107: =IF(OR(AG107="",AH107=""),"",IF(OR(AND(AG107="短期博反弹",OR(AH107="1～3个交易日",AH107="4～10个交易日")),AND(AG107="突破冲新高",OR(AH107="4～10个交易日",AH107="11～20个交易日")),AND(AG107="趋势波段",OR(AH107="11～20个交易日",AH107="21～60个交易日",AH107="60个交易日以上"))),"匹配","周期与交易预期不匹配，请重新确认")) | AO107: =IF(OR(A107="",H107="",H107<=0),"",(E107*H107+IF(AND(AK107<>"",AL107<>""),AK107*AL107,0)+IF(AND(AM107<>"",AN107<>""),AM107*AN107,0))/AP107) | AP107: =IF(OR(A107="",H107="",H107<=0),"",H107+IF(AL107="",0,AL107)+IF(AN107="",0,AN107)) | AQ107: =IF(A107="","",IF(M107<>"",0,IF(OR(H107="",N107=""),"",MAX(E107-MAX(N107,IFERROR(SUMPRODUCT(MAX(((持仓跟踪!$A$2:$A$497="每日跟踪")*(持仓跟踪!$B$2:$B$497=A107))*持仓跟踪!$S$2:$S$497)),0)),0)*H107+IF(OR(AK107="",AL107=""),0,MAX(AK107-MAX(N107,IFERROR(SUMPRODUCT(MAX(((持仓跟踪!$A$2:$A$497="每日跟踪")*(持仓跟踪!$B$2:$B$497=A107))*持仓跟踪!$S$2:$S$497)),0)),0)*AL107)+IF(OR(AM107="",AN107=""),0,MAX(AM107-MAX(N107,IFERROR(SUMPRODUCT(MAX(((持仓跟踪!$A$2:$A$497="每日跟踪")*(持仓跟踪!$B$2:$B$497=A107))*持仓跟踪!$S$2:$S$497)),0)),0)*AN107)))) | AR107: =IF(A107="","",IF(OR(E107="",H107=""),"违规：第一批价格或股数缺失",IF(OR(AND(AK107="",AL107<>""),AND(AK107<>"",AL107="")),"违规：第二批价格与股数须成对填写",IF(OR(AND(AM107="",AN107<>""),AND(AM107<>"",AN107="")),"违规：第三批价格与股数须成对填写",IF(AND(OR(AM107<>"",AN107<>""),OR(AK107="",AL107="")),"违规：必须先完成第二批",IF(OR(H107<=0,H107<>INT(H107),MOD(H107,100)<>0,AND(AL107<>"",OR(AL107<=0,AL107<>INT(AL107),MOD(AL107,100)<>0)),AND(AN107<>"",OR(AN107<=0,AN107<>INT(AN107),MOD(AN107,100)<>0))),"违规：股数须为100股整数倍",IF(AND(OR(AL107<>"",AN107<>""),OR(_LockStatus="已锁仓",_LockStatus="解锁信息不完整")),"违规：锁仓期间禁止加仓",IF(AQ107>C107*D107,"违规：超过单笔风险上限",IF(SUM($AQ$2:$AQ$201)>账户数据!$B$7,"违规：超过账户风险上限","通过")))))))))
F108: =IF(OR(C108="",D108="",E108="",N108="",C108<=0,D108<=0,E108<=N108),"",ROUNDDOWN((C108*D108)/(E108-N108)/100,0)*100) | G108: =IF(A108="","",IF(H108<>"","已开仓",IF(账户数据!$B$23="已锁仓","禁止开仓：连续亏损达到上限",IF(账户数据!$B$23="解锁信息不完整","禁止开仓：请完整填写解锁信息",IF(OR(F108="",E108="",N108="",E108<=N108,账户数据!$B$7=""),"",IF(OR(AG108="",AH108="",AI108=""),"禁止开仓：交易预期未填写完整",IF(COUNTIFS(持仓跟踪!$A$2:$A$497,"止损计划",持仓跟踪!$B$2:$B$497,A108,持仓跟踪!$AC$2:$AC$497,"计划有效")=0,"禁止开仓：请先填写止损计划",IF(账户数据!$B$9+F108*(E108-N108)>=账户数据!$B$7,"禁止开仓：风险额度不足",IF(AJ108="周期与交易预期不匹配，请重新确认",IF(账户数据!$B$23="接近锁仓","允许开仓（接近锁仓；周期需复核）","允许开仓（周期需复核）"),IF(账户数据!$B$23="接近锁仓","允许开仓（接近锁仓）","允许开仓")))))))))) | K108: =IF(A108="","",IFERROR(LOOKUP(2,1/((持仓跟踪!$B$2:$B$497=A108)*(持仓跟踪!$X$2:$X$497="执行卖出")*(持仓跟踪!$Y$2:$Y$497<>"")),持仓跟踪!$Y$2:$Y$497),"")) | L108: =IF(A108="","",IFERROR(LOOKUP(2,1/((持仓跟踪!$B$2:$B$497=A108)*(持仓跟踪!$X$2:$X$497="执行卖出")*(持仓跟踪!$Z$2:$Z$497<>"")),持仓跟踪!$Z$2:$Z$497),"")) | M108: =IF(A108="","",IFERROR(LOOKUP(2,1/((持仓跟踪!$B$2:$B$497=A108)*(持仓跟踪!$X$2:$X$497="执行卖出")*(持仓跟踪!$H$2:$H$497<>"")),持仓跟踪!$H$2:$H$497),"")) | P108: =IF(A108="","",IFERROR(LOOKUP(2,1/((持仓跟踪!$B$2:$B$497=A108)*(持仓跟踪!$X$2:$X$497="执行卖出")*(持仓跟踪!$AA$2:$AA$497<>"")),持仓跟踪!$AA$2:$AA$497),"")) | U108: =IF(OR(AO108="",J108="",AO108<=0),"",(J108-AO108)/AO108) | V108: =IF(OR(AO108="",N108="",AO108<=0),"",(AO108-N108)/AO108) | W108: =IF(OR(U108="",V108="",V108<=0),"",U108/V108) | X108: =IF(OR(K108="",L108="",AP108=""),"",K108*L108-(E108*H108+IF(AND(AK108<>"",AL108<>""),AK108*AL108,0)+IF(AND(AM108<>"",AN108<>""),AM108*AN108,0))-IF(O108="",0,O108)-IF(P108="",0,P108)) | Y108: =IF(OR(X108="",AP108=""),"",IF((E108*H108+IF(AND(AK108<>"",AL108<>""),AK108*AL108,0)+IF(AND(AM108<>"",AN108<>""),AM108*AN108,0))+IF(O108="",0,O108)<=0,"",X108/((E108*H108+IF(AND(AK108<>"",AL108<>""),AK108*AL108,0)+IF(AND(AM108<>"",AN108<>""),AM108*AN108,0))+IF(O108="",0,O108)))) | Z108: =IF(OR(AE108="",多次统计数据!$B$8=""),"",AE108-多次统计数据!$B$8) | AA108: =IF(OR(I108="",M108="",M108<I108),"",M108-I108) | AB108: =IF(OR(A108="",多次统计数据!$B$8="",多次统计数据!$B$6<=0,多次统计数据!$B$6>=1),"",1-POWER(1+多次统计数据!$B$8,-多次统计数据!$B$6/(1-多次统计数据!$B$6))) | AC108: =IF(OR(AB108="",多次统计数据!$B$9=""),"",IF(多次统计数据!$B$9<AB108,"低于上限","达到或超过上限")) | AE108: =IF(OR(X108="",C108="",C108<=0),"",X108/C108) | AJ108: =IF(OR(AG108="",AH108=""),"",IF(OR(AND(AG108="短期博反弹",OR(AH108="1～3个交易日",AH108="4～10个交易日")),AND(AG108="突破冲新高",OR(AH108="4～10个交易日",AH108="11～20个交易日")),AND(AG108="趋势波段",OR(AH108="11～20个交易日",AH108="21～60个交易日",AH108="60个交易日以上"))),"匹配","周期与交易预期不匹配，请重新确认")) | AO108: =IF(OR(A108="",H108="",H108<=0),"",(E108*H108+IF(AND(AK108<>"",AL108<>""),AK108*AL108,0)+IF(AND(AM108<>"",AN108<>""),AM108*AN108,0))/AP108) | AP108: =IF(OR(A108="",H108="",H108<=0),"",H108+IF(AL108="",0,AL108)+IF(AN108="",0,AN108)) | AQ108: =IF(A108="","",IF(M108<>"",0,IF(OR(H108="",N108=""),"",MAX(E108-MAX(N108,IFERROR(SUMPRODUCT(MAX(((持仓跟踪!$A$2:$A$497="每日跟踪")*(持仓跟踪!$B$2:$B$497=A108))*持仓跟踪!$S$2:$S$497)),0)),0)*H108+IF(OR(AK108="",AL108=""),0,MAX(AK108-MAX(N108,IFERROR(SUMPRODUCT(MAX(((持仓跟踪!$A$2:$A$497="每日跟踪")*(持仓跟踪!$B$2:$B$497=A108))*持仓跟踪!$S$2:$S$497)),0)),0)*AL108)+IF(OR(AM108="",AN108=""),0,MAX(AM108-MAX(N108,IFERROR(SUMPRODUCT(MAX(((持仓跟踪!$A$2:$A$497="每日跟踪")*(持仓跟踪!$B$2:$B$497=A108))*持仓跟踪!$S$2:$S$497)),0)),0)*AN108)))) | AR108: =IF(A108="","",IF(OR(E108="",H108=""),"违规：第一批价格或股数缺失",IF(OR(AND(AK108="",AL108<>""),AND(AK108<>"",AL108="")),"违规：第二批价格与股数须成对填写",IF(OR(AND(AM108="",AN108<>""),AND(AM108<>"",AN108="")),"违规：第三批价格与股数须成对填写",IF(AND(OR(AM108<>"",AN108<>""),OR(AK108="",AL108="")),"违规：必须先完成第二批",IF(OR(H108<=0,H108<>INT(H108),MOD(H108,100)<>0,AND(AL108<>"",OR(AL108<=0,AL108<>INT(AL108),MOD(AL108,100)<>0)),AND(AN108<>"",OR(AN108<=0,AN108<>INT(AN108),MOD(AN108,100)<>0))),"违规：股数须为100股整数倍",IF(AND(OR(AL108<>"",AN108<>""),OR(_LockStatus="已锁仓",_LockStatus="解锁信息不完整")),"违规：锁仓期间禁止加仓",IF(AQ108>C108*D108,"违规：超过单笔风险上限",IF(SUM($AQ$2:$AQ$201)>账户数据!$B$7,"违规：超过账户风险上限","通过")))))))))
F109: =IF(OR(C109="",D109="",E109="",N109="",C109<=0,D109<=0,E109<=N109),"",ROUNDDOWN((C109*D109)/(E109-N109)/100,0)*100) | G109: =IF(A109="","",IF(H109<>"","已开仓",IF(账户数据!$B$23="已锁仓","禁止开仓：连续亏损达到上限",IF(账户数据!$B$23="解锁信息不完整","禁止开仓：请完整填写解锁信息",IF(OR(F109="",E109="",N109="",E109<=N109,账户数据!$B$7=""),"",IF(OR(AG109="",AH109="",AI109=""),"禁止开仓：交易预期未填写完整",IF(COUNTIFS(持仓跟踪!$A$2:$A$497,"止损计划",持仓跟踪!$B$2:$B$497,A109,持仓跟踪!$AC$2:$AC$497,"计划有效")=0,"禁止开仓：请先填写止损计划",IF(账户数据!$B$9+F109*(E109-N109)>=账户数据!$B$7,"禁止开仓：风险额度不足",IF(AJ109="周期与交易预期不匹配，请重新确认",IF(账户数据!$B$23="接近锁仓","允许开仓（接近锁仓；周期需复核）","允许开仓（周期需复核）"),IF(账户数据!$B$23="接近锁仓","允许开仓（接近锁仓）","允许开仓")))))))))) | L109: =IF(A109="","",IFERROR(LOOKUP(2,1/((持仓跟踪!$B$2:$B$497=A109)*(持仓跟踪!$X$2:$X$497="执行卖出")*(持仓跟踪!$Z$2:$Z$497<>"")),持仓跟踪!$Z$2:$Z$497),"")) | M109: =IF(A109="","",IFERROR(LOOKUP(2,1/((持仓跟踪!$B$2:$B$497=A109)*(持仓跟踪!$X$2:$X$497="执行卖出")*(持仓跟踪!$H$2:$H$497<>"")),持仓跟踪!$H$2:$H$497),"")) | P109: =IF(A109="","",IFERROR(LOOKUP(2,1/((持仓跟踪!$B$2:$B$497=A109)*(持仓跟踪!$X$2:$X$497="执行卖出")*(持仓跟踪!$AA$2:$AA$497<>"")),持仓跟踪!$AA$2:$AA$497),"")) | U109: =IF(OR(AO109="",J109="",AO109<=0),"",(J109-AO109)/AO109) | V109: =IF(OR(AO109="",N109="",AO109<=0),"",(AO109-N109)/AO109) | W109: =IF(OR(U109="",V109="",V109<=0),"",U109/V109) | X109: =IF(OR(K109="",L109="",AP109=""),"",K109*L109-(E109*H109+IF(AND(AK109<>"",AL109<>""),AK109*AL109,0)+IF(AND(AM109<>"",AN109<>""),AM109*AN109,0))-IF(O109="",0,O109)-IF(P109="",0,P109)) | Y109: =IF(OR(X109="",AP109=""),"",IF((E109*H109+IF(AND(AK109<>"",AL109<>""),AK109*AL109,0)+IF(AND(AM109<>"",AN109<>""),AM109*AN109,0))+IF(O109="",0,O109)<=0,"",X109/((E109*H109+IF(AND(AK109<>"",AL109<>""),AK109*AL109,0)+IF(AND(AM109<>"",AN109<>""),AM109*AN109,0))+IF(O109="",0,O109)))) | Z109: =IF(OR(AE109="",多次统计数据!$B$8=""),"",AE109-多次统计数据!$B$8) | AA109: =IF(OR(I109="",M109="",M109<I109),"",M109-I109) | AB109: =IF(OR(A109="",多次统计数据!$B$8="",多次统计数据!$B$6<=0,多次统计数据!$B$6>=1),"",1-POWER(1+多次统计数据!$B$8,-多次统计数据!$B$6/(1-多次统计数据!$B$6))) | AC109: =IF(OR(AB109="",多次统计数据!$B$9=""),"",IF(多次统计数据!$B$9<AB109,"低于上限","达到或超过上限")) | AE109: =IF(OR(X109="",C109="",C109<=0),"",X109/C109) | AJ109: =IF(OR(AG109="",AH109=""),"",IF(OR(AND(AG109="短期博反弹",OR(AH109="1～3个交易日",AH109="4～10个交易日")),AND(AG109="突破冲新高",OR(AH109="4～10个交易日",AH109="11～20个交易日")),AND(AG109="趋势波段",OR(AH109="11～20个交易日",AH109="21～60个交易日",AH109="60个交易日以上"))),"匹配","周期与交易预期不匹配，请重新确认")) | AO109: =IF(OR(A109="",H109="",H109<=0),"",(E109*H109+IF(AND(AK109<>"",AL109<>""),AK109*AL109,0)+IF(AND(AM109<>"",AN109<>""),AM109*AN109,0))/AP109) | AP109: =IF(OR(A109="",H109="",H109<=0),"",H109+IF(AL109="",0,AL109)+IF(AN109="",0,AN109)) | AQ109: =IF(A109="","",IF(M109<>"",0,IF(OR(H109="",N109=""),"",MAX(E109-MAX(N109,IFERROR(SUMPRODUCT(MAX(((持仓跟踪!$A$2:$A$497="每日跟踪")*(持仓跟踪!$B$2:$B$497=A109))*持仓跟踪!$S$2:$S$497)),0)),0)*H109+IF(OR(AK109="",AL109=""),0,MAX(AK109-MAX(N109,IFERROR(SUMPRODUCT(MAX(((持仓跟踪!$A$2:$A$497="每日跟踪")*(持仓跟踪!$B$2:$B$497=A109))*持仓跟踪!$S$2:$S$497)),0)),0)*AL109)+IF(OR(AM109="",AN109=""),0,MAX(AM109-MAX(N109,IFERROR(SUMPRODUCT(MAX(((持仓跟踪!$A$2:$A$497="每日跟踪")*(持仓跟踪!$B$2:$B$497=A109))*持仓跟踪!$S$2:$S$497)),0)),0)*AN109)))) | AR109: =IF(A109="","",IF(OR(E109="",H109=""),"违规：第一批价格或股数缺失",IF(OR(AND(AK109="",AL109<>""),AND(AK109<>"",AL109="")),"违规：第二批价格与股数须成对填写",IF(OR(AND(AM109="",AN109<>""),AND(AM109<>"",AN109="")),"违规：第三批价格与股数须成对填写",IF(AND(OR(AM109<>"",AN109<>""),OR(AK109="",AL109="")),"违规：必须先完成第二批",IF(OR(H109<=0,H109<>INT(H109),MOD(H109,100)<>0,AND(AL109<>"",OR(AL109<=0,AL109<>INT(AL109),MOD(AL109,100)<>0)),AND(AN109<>"",OR(AN109<=0,AN109<>INT(AN109),MOD(AN109,100)<>0))),"违规：股数须为100股整数倍",IF(AND(OR(AL109<>"",AN109<>""),OR(_LockStatus="已锁仓",_LockStatus="解锁信息不完整")),"违规：锁仓期间禁止加仓",IF(AQ109>C109*D109,"违规：超过单笔风险上限",IF(SUM($AQ$2:$AQ$201)>账户数据!$B$7,"违规：超过账户风险上限","通过")))))))))
F110: =IF(OR(C110="",D110="",E110="",N110="",C110<=0,D110<=0,E110<=N110),"",ROUNDDOWN((C110*D110)/(E110-N110)/100,0)*100) | G110: =IF(A110="","",IF(H110<>"","已开仓",IF(账户数据!$B$23="已锁仓","禁止开仓：连续亏损达到上限",IF(账户数据!$B$23="解锁信息不完整","禁止开仓：请完整填写解锁信息",IF(OR(F110="",E110="",N110="",E110<=N110,账户数据!$B$7=""),"",IF(OR(AG110="",AH110="",AI110=""),"禁止开仓：交易预期未填写完整",IF(COUNTIFS(持仓跟踪!$A$2:$A$497,"止损计划",持仓跟踪!$B$2:$B$497,A110,持仓跟踪!$AC$2:$AC$497,"计划有效")=0,"禁止开仓：请先填写止损计划",IF(账户数据!$B$9+F110*(E110-N110)>=账户数据!$B$7,"禁止开仓：风险额度不足",IF(AJ110="周期与交易预期不匹配，请重新确认",IF(账户数据!$B$23="接近锁仓","允许开仓（接近锁仓；周期需复核）","允许开仓（周期需复核）"),IF(账户数据!$B$23="接近锁仓","允许开仓（接近锁仓）","允许开仓")))))))))) | K110: =IF(A110="","",IFERROR(LOOKUP(2,1/((持仓跟踪!$B$2:$B$497=A110)*(持仓跟踪!$X$2:$X$497="执行卖出")*(持仓跟踪!$Y$2:$Y$497<>"")),持仓跟踪!$Y$2:$Y$497),"")) | L110: =IF(A110="","",IFERROR(LOOKUP(2,1/((持仓跟踪!$B$2:$B$497=A110)*(持仓跟踪!$X$2:$X$497="执行卖出")*(持仓跟踪!$Z$2:$Z$497<>"")),持仓跟踪!$Z$2:$Z$497),"")) | M110: =IF(A110="","",IFERROR(LOOKUP(2,1/((持仓跟踪!$B$2:$B$497=A110)*(持仓跟踪!$X$2:$X$497="执行卖出")*(持仓跟踪!$H$2:$H$497<>"")),持仓跟踪!$H$2:$H$497),"")) | P110: =IF(A110="","",IFERROR(LOOKUP(2,1/((持仓跟踪!$B$2:$B$497=A110)*(持仓跟踪!$X$2:$X$497="执行卖出")*(持仓跟踪!$AA$2:$AA$497<>"")),持仓跟踪!$AA$2:$AA$497),"")) | U110: =IF(OR(AO110="",J110="",AO110<=0),"",(J110-AO110)/AO110) | V110: =IF(OR(AO110="",N110="",AO110<=0),"",(AO110-N110)/AO110) | W110: =IF(OR(U110="",V110="",V110<=0),"",U110/V110) | X110: =IF(OR(K110="",L110="",AP110=""),"",K110*L110-(E110*H110+IF(AND(AK110<>"",AL110<>""),AK110*AL110,0)+IF(AND(AM110<>"",AN110<>""),AM110*AN110,0))-IF(O110="",0,O110)-IF(P110="",0,P110)) | Y110: =IF(OR(X110="",AP110=""),"",IF((E110*H110+IF(AND(AK110<>"",AL110<>""),AK110*AL110,0)+IF(AND(AM110<>"",AN110<>""),AM110*AN110,0))+IF(O110="",0,O110)<=0,"",X110/((E110*H110+IF(AND(AK110<>"",AL110<>""),AK110*AL110,0)+IF(AND(AM110<>"",AN110<>""),AM110*AN110,0))+IF(O110="",0,O110)))) | Z110: =IF(OR(AE110="",多次统计数据!$B$8=""),"",AE110-多次统计数据!$B$8) | AA110: =IF(OR(I110="",M110="",M110<I110),"",M110-I110) | AB110: =IF(OR(A110="",多次统计数据!$B$8="",多次统计数据!$B$6<=0,多次统计数据!$B$6>=1),"",1-POWER(1+多次统计数据!$B$8,-多次统计数据!$B$6/(1-多次统计数据!$B$6))) | AC110: =IF(OR(AB110="",多次统计数据!$B$9=""),"",IF(多次统计数据!$B$9<AB110,"低于上限","达到或超过上限")) | AE110: =IF(OR(X110="",C110="",C110<=0),"",X110/C110) | AJ110: =IF(OR(AG110="",AH110=""),"",IF(OR(AND(AG110="短期博反弹",OR(AH110="1～3个交易日",AH110="4～10个交易日")),AND(AG110="突破冲新高",OR(AH110="4～10个交易日",AH110="11～20个交易日")),AND(AG110="趋势波段",OR(AH110="11～20个交易日",AH110="21～60个交易日",AH110="60个交易日以上"))),"匹配","周期与交易预期不匹配，请重新确认")) | AO110: =IF(OR(A110="",H110="",H110<=0),"",(E110*H110+IF(AND(AK110<>"",AL110<>""),AK110*AL110,0)+IF(AND(AM110<>"",AN110<>""),AM110*AN110,0))/AP110) | AP110: =IF(OR(A110="",H110="",H110<=0),"",H110+IF(AL110="",0,AL110)+IF(AN110="",0,AN110)) | AQ110: =IF(A110="","",IF(M110<>"",0,IF(OR(H110="",N110=""),"",MAX(E110-MAX(N110,IFERROR(SUMPRODUCT(MAX(((持仓跟踪!$A$2:$A$497="每日跟踪")*(持仓跟踪!$B$2:$B$497=A110))*持仓跟踪!$S$2:$S$497)),0)),0)*H110+IF(OR(AK110="",AL110=""),0,MAX(AK110-MAX(N110,IFERROR(SUMPRODUCT(MAX(((持仓跟踪!$A$2:$A$497="每日跟踪")*(持仓跟踪!$B$2:$B$497=A110))*持仓跟踪!$S$2:$S$497)),0)),0)*AL110)+IF(OR(AM110="",AN110=""),0,MAX(AM110-MAX(N110,IFERROR(SUMPRODUCT(MAX(((持仓跟踪!$A$2:$A$497="每日跟踪")*(持仓跟踪!$B$2:$B$497=A110))*持仓跟踪!$S$2:$S$497)),0)),0)*AN110)))) | AR110: =IF(A110="","",IF(OR(E110="",H110=""),"违规：第一批价格或股数缺失",IF(OR(AND(AK110="",AL110<>""),AND(AK110<>"",AL110="")),"违规：第二批价格与股数须成对填写",IF(OR(AND(AM110="",AN110<>""),AND(AM110<>"",AN110="")),"违规：第三批价格与股数须成对填写",IF(AND(OR(AM110<>"",AN110<>""),OR(AK110="",AL110="")),"违规：必须先完成第二批",IF(OR(H110<=0,H110<>INT(H110),MOD(H110,100)<>0,AND(AL110<>"",OR(AL110<=0,AL110<>INT(AL110),MOD(AL110,100)<>0)),AND(AN110<>"",OR(AN110<=0,AN110<>INT(AN110),MOD(AN110,100)<>0))),"违规：股数须为100股整数倍",IF(AND(OR(AL110<>"",AN110<>""),OR(_LockStatus="已锁仓",_LockStatus="解锁信息不完整")),"违规：锁仓期间禁止加仓",IF(AQ110>C110*D110,"违规：超过单笔风险上限",IF(SUM($AQ$2:$AQ$201)>账户数据!$B$7,"违规：超过账户风险上限","通过")))))))))
F111: =IF(OR(C111="",D111="",E111="",N111="",C111<=0,D111<=0,E111<=N111),"",ROUNDDOWN((C111*D111)/(E111-N111)/100,0)*100) | G111: =IF(A111="","",IF(H111<>"","已开仓",IF(账户数据!$B$23="已锁仓","禁止开仓：连续亏损达到上限",IF(账户数据!$B$23="解锁信息不完整","禁止开仓：请完整填写解锁信息",IF(OR(F111="",E111="",N111="",E111<=N111,账户数据!$B$7=""),"",IF(OR(AG111="",AH111="",AI111=""),"禁止开仓：交易预期未填写完整",IF(COUNTIFS(持仓跟踪!$A$2:$A$497,"止损计划",持仓跟踪!$B$2:$B$497,A111,持仓跟踪!$AC$2:$AC$497,"计划有效")=0,"禁止开仓：请先填写止损计划",IF(账户数据!$B$9+F111*(E111-N111)>=账户数据!$B$7,"禁止开仓：风险额度不足",IF(AJ111="周期与交易预期不匹配，请重新确认",IF(账户数据!$B$23="接近锁仓","允许开仓（接近锁仓；周期需复核）","允许开仓（周期需复核）"),IF(账户数据!$B$23="接近锁仓","允许开仓（接近锁仓）","允许开仓")))))))))) | L111: =IF(A111="","",IFERROR(LOOKUP(2,1/((持仓跟踪!$B$2:$B$497=A111)*(持仓跟踪!$X$2:$X$497="执行卖出")*(持仓跟踪!$Z$2:$Z$497<>"")),持仓跟踪!$Z$2:$Z$497),"")) | M111: =IF(A111="","",IFERROR(LOOKUP(2,1/((持仓跟踪!$B$2:$B$497=A111)*(持仓跟踪!$X$2:$X$497="执行卖出")*(持仓跟踪!$H$2:$H$497<>"")),持仓跟踪!$H$2:$H$497),"")) | P111: =IF(A111="","",IFERROR(LOOKUP(2,1/((持仓跟踪!$B$2:$B$497=A111)*(持仓跟踪!$X$2:$X$497="执行卖出")*(持仓跟踪!$AA$2:$AA$497<>"")),持仓跟踪!$AA$2:$AA$497),"")) | U111: =IF(OR(AO111="",J111="",AO111<=0),"",(J111-AO111)/AO111) | V111: =IF(OR(AO111="",N111="",AO111<=0),"",(AO111-N111)/AO111) | W111: =IF(OR(U111="",V111="",V111<=0),"",U111/V111) | X111: =IF(OR(K111="",L111="",AP111=""),"",K111*L111-(E111*H111+IF(AND(AK111<>"",AL111<>""),AK111*AL111,0)+IF(AND(AM111<>"",AN111<>""),AM111*AN111,0))-IF(O111="",0,O111)-IF(P111="",0,P111)) | Y111: =IF(OR(X111="",AP111=""),"",IF((E111*H111+IF(AND(AK111<>"",AL111<>""),AK111*AL111,0)+IF(AND(AM111<>"",AN111<>""),AM111*AN111,0))+IF(O111="",0,O111)<=0,"",X111/((E111*H111+IF(AND(AK111<>"",AL111<>""),AK111*AL111,0)+IF(AND(AM111<>"",AN111<>""),AM111*AN111,0))+IF(O111="",0,O111)))) | Z111: =IF(OR(AE111="",多次统计数据!$B$8=""),"",AE111-多次统计数据!$B$8) | AA111: =IF(OR(I111="",M111="",M111<I111),"",M111-I111) | AB111: =IF(OR(A111="",多次统计数据!$B$8="",多次统计数据!$B$6<=0,多次统计数据!$B$6>=1),"",1-POWER(1+多次统计数据!$B$8,-多次统计数据!$B$6/(1-多次统计数据!$B$6))) | AC111: =IF(OR(AB111="",多次统计数据!$B$9=""),"",IF(多次统计数据!$B$9<AB111,"低于上限","达到或超过上限")) | AE111: =IF(OR(X111="",C111="",C111<=0),"",X111/C111) | AJ111: =IF(OR(AG111="",AH111=""),"",IF(OR(AND(AG111="短期博反弹",OR(AH111="1～3个交易日",AH111="4～10个交易日")),AND(AG111="突破冲新高",OR(AH111="4～10个交易日",AH111="11～20个交易日")),AND(AG111="趋势波段",OR(AH111="11～20个交易日",AH111="21～60个交易日",AH111="60个交易日以上"))),"匹配","周期与交易预期不匹配，请重新确认")) | AO111: =IF(OR(A111="",H111="",H111<=0),"",(E111*H111+IF(AND(AK111<>"",AL111<>""),AK111*AL111,0)+IF(AND(AM111<>"",AN111<>""),AM111*AN111,0))/AP111) | AP111: =IF(OR(A111="",H111="",H111<=0),"",H111+IF(AL111="",0,AL111)+IF(AN111="",0,AN111)) | AQ111: =IF(A111="","",IF(M111<>"",0,IF(OR(H111="",N111=""),"",MAX(E111-MAX(N111,IFERROR(SUMPRODUCT(MAX(((持仓跟踪!$A$2:$A$497="每日跟踪")*(持仓跟踪!$B$2:$B$497=A111))*持仓跟踪!$S$2:$S$497)),0)),0)*H111+IF(OR(AK111="",AL111=""),0,MAX(AK111-MAX(N111,IFERROR(SUMPRODUCT(MAX(((持仓跟踪!$A$2:$A$497="每日跟踪")*(持仓跟踪!$B$2:$B$497=A111))*持仓跟踪!$S$2:$S$497)),0)),0)*AL111)+IF(OR(AM111="",AN111=""),0,MAX(AM111-MAX(N111,IFERROR(SUMPRODUCT(MAX(((持仓跟踪!$A$2:$A$497="每日跟踪")*(持仓跟踪!$B$2:$B$497=A111))*持仓跟踪!$S$2:$S$497)),0)),0)*AN111)))) | AR111: =IF(A111="","",IF(OR(E111="",H111=""),"违规：第一批价格或股数缺失",IF(OR(AND(AK111="",AL111<>""),AND(AK111<>"",AL111="")),"违规：第二批价格与股数须成对填写",IF(OR(AND(AM111="",AN111<>""),AND(AM111<>"",AN111="")),"违规：第三批价格与股数须成对填写",IF(AND(OR(AM111<>"",AN111<>""),OR(AK111="",AL111="")),"违规：必须先完成第二批",IF(OR(H111<=0,H111<>INT(H111),MOD(H111,100)<>0,AND(AL111<>"",OR(AL111<=0,AL111<>INT(AL111),MOD(AL111,100)<>0)),AND(AN111<>"",OR(AN111<=0,AN111<>INT(AN111),MOD(AN111,100)<>0))),"违规：股数须为100股整数倍",IF(AND(OR(AL111<>"",AN111<>""),OR(_LockStatus="已锁仓",_LockStatus="解锁信息不完整")),"违规：锁仓期间禁止加仓",IF(AQ111>C111*D111,"违规：超过单笔风险上限",IF(SUM($AQ$2:$AQ$201)>账户数据!$B$7,"违规：超过账户风险上限","通过")))))))))
F112: =IF(OR(C112="",D112="",E112="",N112="",C112<=0,D112<=0,E112<=N112),"",ROUNDDOWN((C112*D112)/(E112-N112)/100,0)*100) | G112: =IF(A112="","",IF(H112<>"","已开仓",IF(账户数据!$B$23="已锁仓","禁止开仓：连续亏损达到上限",IF(账户数据!$B$23="解锁信息不完整","禁止开仓：请完整填写解锁信息",IF(OR(F112="",E112="",N112="",E112<=N112,账户数据!$B$7=""),"",IF(OR(AG112="",AH112="",AI112=""),"禁止开仓：交易预期未填写完整",IF(COUNTIFS(持仓跟踪!$A$2:$A$497,"止损计划",持仓跟踪!$B$2:$B$497,A112,持仓跟踪!$AC$2:$AC$497,"计划有效")=0,"禁止开仓：请先填写止损计划",IF(账户数据!$B$9+F112*(E112-N112)>=账户数据!$B$7,"禁止开仓：风险额度不足",IF(AJ112="周期与交易预期不匹配，请重新确认",IF(账户数据!$B$23="接近锁仓","允许开仓（接近锁仓；周期需复核）","允许开仓（周期需复核）"),IF(账户数据!$B$23="接近锁仓","允许开仓（接近锁仓）","允许开仓")))))))))) | L112: =IF(A112="","",IFERROR(LOOKUP(2,1/((持仓跟踪!$B$2:$B$497=A112)*(持仓跟踪!$X$2:$X$497="执行卖出")*(持仓跟踪!$Z$2:$Z$497<>"")),持仓跟踪!$Z$2:$Z$497),"")) | M112: =IF(A112="","",IFERROR(LOOKUP(2,1/((持仓跟踪!$B$2:$B$497=A112)*(持仓跟踪!$X$2:$X$497="执行卖出")*(持仓跟踪!$H$2:$H$497<>"")),持仓跟踪!$H$2:$H$497),"")) | P112: =IF(A112="","",IFERROR(LOOKUP(2,1/((持仓跟踪!$B$2:$B$497=A112)*(持仓跟踪!$X$2:$X$497="执行卖出")*(持仓跟踪!$AA$2:$AA$497<>"")),持仓跟踪!$AA$2:$AA$497),"")) | U112: =IF(OR(AO112="",J112="",AO112<=0),"",(J112-AO112)/AO112) | V112: =IF(OR(AO112="",N112="",AO112<=0),"",(AO112-N112)/AO112) | W112: =IF(OR(U112="",V112="",V112<=0),"",U112/V112) | X112: =IF(OR(K112="",L112="",AP112=""),"",K112*L112-(E112*H112+IF(AND(AK112<>"",AL112<>""),AK112*AL112,0)+IF(AND(AM112<>"",AN112<>""),AM112*AN112,0))-IF(O112="",0,O112)-IF(P112="",0,P112)) | Y112: =IF(OR(X112="",AP112=""),"",IF((E112*H112+IF(AND(AK112<>"",AL112<>""),AK112*AL112,0)+IF(AND(AM112<>"",AN112<>""),AM112*AN112,0))+IF(O112="",0,O112)<=0,"",X112/((E112*H112+IF(AND(AK112<>"",AL112<>""),AK112*AL112,0)+IF(AND(AM112<>"",AN112<>""),AM112*AN112,0))+IF(O112="",0,O112)))) | Z112: =IF(OR(AE112="",多次统计数据!$B$8=""),"",AE112-多次统计数据!$B$8) | AA112: =IF(OR(I112="",M112="",M112<I112),"",M112-I112) | AB112: =IF(OR(A112="",多次统计数据!$B$8="",多次统计数据!$B$6<=0,多次统计数据!$B$6>=1),"",1-POWER(1+多次统计数据!$B$8,-多次统计数据!$B$6/(1-多次统计数据!$B$6))) | AC112: =IF(OR(AB112="",多次统计数据!$B$9=""),"",IF(多次统计数据!$B$9<AB112,"低于上限","达到或超过上限")) | AE112: =IF(OR(X112="",C112="",C112<=0),"",X112/C112) | AJ112: =IF(OR(AG112="",AH112=""),"",IF(OR(AND(AG112="短期博反弹",OR(AH112="1～3个交易日",AH112="4～10个交易日")),AND(AG112="突破冲新高",OR(AH112="4～10个交易日",AH112="11～20个交易日")),AND(AG112="趋势波段",OR(AH112="11～20个交易日",AH112="21～60个交易日",AH112="60个交易日以上"))),"匹配","周期与交易预期不匹配，请重新确认")) | AO112: =IF(OR(A112="",H112="",H112<=0),"",(E112*H112+IF(AND(AK112<>"",AL112<>""),AK112*AL112,0)+IF(AND(AM112<>"",AN112<>""),AM112*AN112,0))/AP112) | AP112: =IF(OR(A112="",H112="",H112<=0),"",H112+IF(AL112="",0,AL112)+IF(AN112="",0,AN112)) | AQ112: =IF(A112="","",IF(M112<>"",0,IF(OR(H112="",N112=""),"",MAX(E112-MAX(N112,IFERROR(SUMPRODUCT(MAX(((持仓跟踪!$A$2:$A$497="每日跟踪")*(持仓跟踪!$B$2:$B$497=A112))*持仓跟踪!$S$2:$S$497)),0)),0)*H112+IF(OR(AK112="",AL112=""),0,MAX(AK112-MAX(N112,IFERROR(SUMPRODUCT(MAX(((持仓跟踪!$A$2:$A$497="每日跟踪")*(持仓跟踪!$B$2:$B$497=A112))*持仓跟踪!$S$2:$S$497)),0)),0)*AL112)+IF(OR(AM112="",AN112=""),0,MAX(AM112-MAX(N112,IFERROR(SUMPRODUCT(MAX(((持仓跟踪!$A$2:$A$497="每日跟踪")*(持仓跟踪!$B$2:$B$497=A112))*持仓跟踪!$S$2:$S$497)),0)),0)*AN112)))) | AR112: =IF(A112="","",IF(OR(E112="",H112=""),"违规：第一批价格或股数缺失",IF(OR(AND(AK112="",AL112<>""),AND(AK112<>"",AL112="")),"违规：第二批价格与股数须成对填写",IF(OR(AND(AM112="",AN112<>""),AND(AM112<>"",AN112="")),"违规：第三批价格与股数须成对填写",IF(AND(OR(AM112<>"",AN112<>""),OR(AK112="",AL112="")),"违规：必须先完成第二批",IF(OR(H112<=0,H112<>INT(H112),MOD(H112,100)<>0,AND(AL112<>"",OR(AL112<=0,AL112<>INT(AL112),MOD(AL112,100)<>0)),AND(AN112<>"",OR(AN112<=0,AN112<>INT(AN112),MOD(AN112,100)<>0))),"违规：股数须为100股整数倍",IF(AND(OR(AL112<>"",AN112<>""),OR(_LockStatus="已锁仓",_LockStatus="解锁信息不完整")),"违规：锁仓期间禁止加仓",IF(AQ112>C112*D112,"违规：超过单笔风险上限",IF(SUM($AQ$2:$AQ$201)>账户数据!$B$7,"违规：超过账户风险上限","通过")))))))))
F113: =IF(OR(C113="",D113="",E113="",N113="",C113<=0,D113<=0,E113<=N113),"",ROUNDDOWN((C113*D113)/(E113-N113)/100,0)*100) | G113: =IF(A113="","",IF(H113<>"","已开仓",IF(账户数据!$B$23="已锁仓","禁止开仓：连续亏损达到上限",IF(账户数据!$B$23="解锁信息不完整","禁止开仓：请完整填写解锁信息",IF(OR(F113="",E113="",N113="",E113<=N113,账户数据!$B$7=""),"",IF(OR(AG113="",AH113="",AI113=""),"禁止开仓：交易预期未填写完整",IF(COUNTIFS(持仓跟踪!$A$2:$A$497,"止损计划",持仓跟踪!$B$2:$B$497,A113,持仓跟踪!$AC$2:$AC$497,"计划有效")=0,"禁止开仓：请先填写止损计划",IF(账户数据!$B$9+F113*(E113-N113)>=账户数据!$B$7,"禁止开仓：风险额度不足",IF(AJ113="周期与交易预期不匹配，请重新确认",IF(账户数据!$B$23="接近锁仓","允许开仓（接近锁仓；周期需复核）","允许开仓（周期需复核）"),IF(账户数据!$B$23="接近锁仓","允许开仓（接近锁仓）","允许开仓")))))))))) | K113: =IF(A113="","",IFERROR(LOOKUP(2,1/((持仓跟踪!$B$2:$B$497=A113)*(持仓跟踪!$X$2:$X$497="执行卖出")*(持仓跟踪!$Y$2:$Y$497<>"")),持仓跟踪!$Y$2:$Y$497),"")) | L113: =IF(A113="","",IFERROR(LOOKUP(2,1/((持仓跟踪!$B$2:$B$497=A113)*(持仓跟踪!$X$2:$X$497="执行卖出")*(持仓跟踪!$Z$2:$Z$497<>"")),持仓跟踪!$Z$2:$Z$497),"")) | M113: =IF(A113="","",IFERROR(LOOKUP(2,1/((持仓跟踪!$B$2:$B$497=A113)*(持仓跟踪!$X$2:$X$497="执行卖出")*(持仓跟踪!$H$2:$H$497<>"")),持仓跟踪!$H$2:$H$497),"")) | P113: =IF(A113="","",IFERROR(LOOKUP(2,1/((持仓跟踪!$B$2:$B$497=A113)*(持仓跟踪!$X$2:$X$497="执行卖出")*(持仓跟踪!$AA$2:$AA$497<>"")),持仓跟踪!$AA$2:$AA$497),"")) | U113: =IF(OR(AO113="",J113="",AO113<=0),"",(J113-AO113)/AO113) | V113: =IF(OR(AO113="",N113="",AO113<=0),"",(AO113-N113)/AO113) | W113: =IF(OR(U113="",V113="",V113<=0),"",U113/V113) | X113: =IF(OR(K113="",L113="",AP113=""),"",K113*L113-(E113*H113+IF(AND(AK113<>"",AL113<>""),AK113*AL113,0)+IF(AND(AM113<>"",AN113<>""),AM113*AN113,0))-IF(O113="",0,O113)-IF(P113="",0,P113)) | Y113: =IF(OR(X113="",AP113=""),"",IF((E113*H113+IF(AND(AK113<>"",AL113<>""),AK113*AL113,0)+IF(AND(AM113<>"",AN113<>""),AM113*AN113,0))+IF(O113="",0,O113)<=0,"",X113/((E113*H113+IF(AND(AK113<>"",AL113<>""),AK113*AL113,0)+IF(AND(AM113<>"",AN113<>""),AM113*AN113,0))+IF(O113="",0,O113)))) | Z113: =IF(OR(AE113="",多次统计数据!$B$8=""),"",AE113-多次统计数据!$B$8) | AA113: =IF(OR(I113="",M113="",M113<I113),"",M113-I113) | AB113: =IF(OR(A113="",多次统计数据!$B$8="",多次统计数据!$B$6<=0,多次统计数据!$B$6>=1),"",1-POWER(1+多次统计数据!$B$8,-多次统计数据!$B$6/(1-多次统计数据!$B$6))) | AC113: =IF(OR(AB113="",多次统计数据!$B$9=""),"",IF(多次统计数据!$B$9<AB113,"低于上限","达到或超过上限")) | AE113: =IF(OR(X113="",C113="",C113<=0),"",X113/C113) | AJ113: =IF(OR(AG113="",AH113=""),"",IF(OR(AND(AG113="短期博反弹",OR(AH113="1～3个交易日",AH113="4～10个交易日")),AND(AG113="突破冲新高",OR(AH113="4～10个交易日",AH113="11～20个交易日")),AND(AG113="趋势波段",OR(AH113="11～20个交易日",AH113="21～60个交易日",AH113="60个交易日以上"))),"匹配","周期与交易预期不匹配，请重新确认")) | AO113: =IF(OR(A113="",H113="",H113<=0),"",(E113*H113+IF(AND(AK113<>"",AL113<>""),AK113*AL113,0)+IF(AND(AM113<>"",AN113<>""),AM113*AN113,0))/AP113) | AP113: =IF(OR(A113="",H113="",H113<=0),"",H113+IF(AL113="",0,AL113)+IF(AN113="",0,AN113)) | AQ113: =IF(A113="","",IF(M113<>"",0,IF(OR(H113="",N113=""),"",MAX(E113-MAX(N113,IFERROR(SUMPRODUCT(MAX(((持仓跟踪!$A$2:$A$497="每日跟踪")*(持仓跟踪!$B$2:$B$497=A113))*持仓跟踪!$S$2:$S$497)),0)),0)*H113+IF(OR(AK113="",AL113=""),0,MAX(AK113-MAX(N113,IFERROR(SUMPRODUCT(MAX(((持仓跟踪!$A$2:$A$497="每日跟踪")*(持仓跟踪!$B$2:$B$497=A113))*持仓跟踪!$S$2:$S$497)),0)),0)*AL113)+IF(OR(AM113="",AN113=""),0,MAX(AM113-MAX(N113,IFERROR(SUMPRODUCT(MAX(((持仓跟踪!$A$2:$A$497="每日跟踪")*(持仓跟踪!$B$2:$B$497=A113))*持仓跟踪!$S$2:$S$497)),0)),0)*AN113)))) | AR113: =IF(A113="","",IF(OR(E113="",H113=""),"违规：第一批价格或股数缺失",IF(OR(AND(AK113="",AL113<>""),AND(AK113<>"",AL113="")),"违规：第二批价格与股数须成对填写",IF(OR(AND(AM113="",AN113<>""),AND(AM113<>"",AN113="")),"违规：第三批价格与股数须成对填写",IF(AND(OR(AM113<>"",AN113<>""),OR(AK113="",AL113="")),"违规：必须先完成第二批",IF(OR(H113<=0,H113<>INT(H113),MOD(H113,100)<>0,AND(AL113<>"",OR(AL113<=0,AL113<>INT(AL113),MOD(AL113,100)<>0)),AND(AN113<>"",OR(AN113<=0,AN113<>INT(AN113),MOD(AN113,100)<>0))),"违规：股数须为100股整数倍",IF(AND(OR(AL113<>"",AN113<>""),OR(_LockStatus="已锁仓",_LockStatus="解锁信息不完整")),"违规：锁仓期间禁止加仓",IF(AQ113>C113*D113,"违规：超过单笔风险上限",IF(SUM($AQ$2:$AQ$201)>账户数据!$B$7,"违规：超过账户风险上限","通过")))))))))
F114: =IF(OR(C114="",D114="",E114="",N114="",C114<=0,D114<=0,E114<=N114),"",ROUNDDOWN((C114*D114)/(E114-N114)/100,0)*100) | G114: =IF(A114="","",IF(H114<>"","已开仓",IF(账户数据!$B$23="已锁仓","禁止开仓：连续亏损达到上限",IF(账户数据!$B$23="解锁信息不完整","禁止开仓：请完整填写解锁信息",IF(OR(F114="",E114="",N114="",E114<=N114,账户数据!$B$7=""),"",IF(OR(AG114="",AH114="",AI114=""),"禁止开仓：交易预期未填写完整",IF(COUNTIFS(持仓跟踪!$A$2:$A$497,"止损计划",持仓跟踪!$B$2:$B$497,A114,持仓跟踪!$AC$2:$AC$497,"计划有效")=0,"禁止开仓：请先填写止损计划",IF(账户数据!$B$9+F114*(E114-N114)>=账户数据!$B$7,"禁止开仓：风险额度不足",IF(AJ114="周期与交易预期不匹配，请重新确认",IF(账户数据!$B$23="接近锁仓","允许开仓（接近锁仓；周期需复核）","允许开仓（周期需复核）"),IF(账户数据!$B$23="接近锁仓","允许开仓（接近锁仓）","允许开仓")))))))))) | P114: =IF(A114="","",IFERROR(LOOKUP(2,1/((持仓跟踪!$B$2:$B$497=A114)*(持仓跟踪!$X$2:$X$497="执行卖出")*(持仓跟踪!$AA$2:$AA$497<>"")),持仓跟踪!$AA$2:$AA$497),"")) | U114: =IF(OR(AO114="",J114="",AO114<=0),"",(J114-AO114)/AO114) | V114: =IF(OR(AO114="",N114="",AO114<=0),"",(AO114-N114)/AO114) | W114: =IF(OR(U114="",V114="",V114<=0),"",U114/V114) | X114: =IF(OR(K114="",L114="",AP114=""),"",K114*L114-(E114*H114+IF(AND(AK114<>"",AL114<>""),AK114*AL114,0)+IF(AND(AM114<>"",AN114<>""),AM114*AN114,0))-IF(O114="",0,O114)-IF(P114="",0,P114)) | Y114: =IF(OR(X114="",AP114=""),"",IF((E114*H114+IF(AND(AK114<>"",AL114<>""),AK114*AL114,0)+IF(AND(AM114<>"",AN114<>""),AM114*AN114,0))+IF(O114="",0,O114)<=0,"",X114/((E114*H114+IF(AND(AK114<>"",AL114<>""),AK114*AL114,0)+IF(AND(AM114<>"",AN114<>""),AM114*AN114,0))+IF(O114="",0,O114)))) | Z114: =IF(OR(AE114="",多次统计数据!$B$8=""),"",AE114-多次统计数据!$B$8) | AA114: =IF(OR(I114="",M114="",M114<I114),"",M114-I114) | AB114: =IF(OR(A114="",多次统计数据!$B$8="",多次统计数据!$B$6<=0,多次统计数据!$B$6>=1),"",1-POWER(1+多次统计数据!$B$8,-多次统计数据!$B$6/(1-多次统计数据!$B$6))) | AC114: =IF(OR(AB114="",多次统计数据!$B$9=""),"",IF(多次统计数据!$B$9<AB114,"低于上限","达到或超过上限")) | AE114: =IF(OR(X114="",C114="",C114<=0),"",X114/C114) | AJ114: =IF(OR(AG114="",AH114=""),"",IF(OR(AND(AG114="短期博反弹",OR(AH114="1～3个交易日",AH114="4～10个交易日")),AND(AG114="突破冲新高",OR(AH114="4～10个交易日",AH114="11～20个交易日")),AND(AG114="趋势波段",OR(AH114="11～20个交易日",AH114="21～60个交易日",AH114="60个交易日以上"))),"匹配","周期与交易预期不匹配，请重新确认")) | AO114: =IF(OR(A114="",H114="",H114<=0),"",(E114*H114+IF(AND(AK114<>"",AL114<>""),AK114*AL114,0)+IF(AND(AM114<>"",AN114<>""),AM114*AN114,0))/AP114) | AP114: =IF(OR(A114="",H114="",H114<=0),"",H114+IF(AL114="",0,AL114)+IF(AN114="",0,AN114)) | AQ114: =IF(A114="","",IF(M114<>"",0,IF(OR(H114="",N114=""),"",MAX(E114-MAX(N114,IFERROR(SUMPRODUCT(MAX(((持仓跟踪!$A$2:$A$497="每日跟踪")*(持仓跟踪!$B$2:$B$497=A114))*持仓跟踪!$S$2:$S$497)),0)),0)*H114+IF(OR(AK114="",AL114=""),0,MAX(AK114-MAX(N114,IFERROR(SUMPRODUCT(MAX(((持仓跟踪!$A$2:$A$497="每日跟踪")*(持仓跟踪!$B$2:$B$497=A114))*持仓跟踪!$S$2:$S$497)),0)),0)*AL114)+IF(OR(AM114="",AN114=""),0,MAX(AM114-MAX(N114,IFERROR(SUMPRODUCT(MAX(((持仓跟踪!$A$2:$A$497="每日跟踪")*(持仓跟踪!$B$2:$B$497=A114))*持仓跟踪!$S$2:$S$497)),0)),0)*AN114)))) | AR114: =IF(A114="","",IF(OR(E114="",H114=""),"违规：第一批价格或股数缺失",IF(OR(AND(AK114="",AL114<>""),AND(AK114<>"",AL114="")),"违规：第二批价格与股数须成对填写",IF(OR(AND(AM114="",AN114<>""),AND(AM114<>"",AN114="")),"违规：第三批价格与股数须成对填写",IF(AND(OR(AM114<>"",AN114<>""),OR(AK114="",AL114="")),"违规：必须先完成第二批",IF(OR(H114<=0,H114<>INT(H114),MOD(H114,100)<>0,AND(AL114<>"",OR(AL114<=0,AL114<>INT(AL114),MOD(AL114,100)<>0)),AND(AN114<>"",OR(AN114<=0,AN114<>INT(AN114),MOD(AN114,100)<>0))),"违规：股数须为100股整数倍",IF(AND(OR(AL114<>"",AN114<>""),OR(_LockStatus="已锁仓",_LockStatus="解锁信息不完整")),"违规：锁仓期间禁止加仓",IF(AQ114>C114*D114,"违规：超过单笔风险上限",IF(SUM($AQ$2:$AQ$201)>账户数据!$B$7,"违规：超过账户风险上限","通过")))))))))
F115: =IF(OR(C115="",D115="",E115="",N115="",C115<=0,D115<=0,E115<=N115),"",ROUNDDOWN((C115*D115)/(E115-N115)/100,0)*100) | G115: =IF(A115="","",IF(H115<>"","已开仓",IF(账户数据!$B$23="已锁仓","禁止开仓：连续亏损达到上限",IF(账户数据!$B$23="解锁信息不完整","禁止开仓：请完整填写解锁信息",IF(OR(F115="",E115="",N115="",E115<=N115,账户数据!$B$7=""),"",IF(OR(AG115="",AH115="",AI115=""),"禁止开仓：交易预期未填写完整",IF(COUNTIFS(持仓跟踪!$A$2:$A$497,"止损计划",持仓跟踪!$B$2:$B$497,A115,持仓跟踪!$AC$2:$AC$497,"计划有效")=0,"禁止开仓：请先填写止损计划",IF(账户数据!$B$9+F115*(E115-N115)>=账户数据!$B$7,"禁止开仓：风险额度不足",IF(AJ115="周期与交易预期不匹配，请重新确认",IF(账户数据!$B$23="接近锁仓","允许开仓（接近锁仓；周期需复核）","允许开仓（周期需复核）"),IF(账户数据!$B$23="接近锁仓","允许开仓（接近锁仓）","允许开仓")))))))))) | K115: =IF(A115="","",IFERROR(LOOKUP(2,1/((持仓跟踪!$B$2:$B$497=A115)*(持仓跟踪!$X$2:$X$497="执行卖出")*(持仓跟踪!$Y$2:$Y$497<>"")),持仓跟踪!$Y$2:$Y$497),"")) | L115: =IF(A115="","",IFERROR(LOOKUP(2,1/((持仓跟踪!$B$2:$B$497=A115)*(持仓跟踪!$X$2:$X$497="执行卖出")*(持仓跟踪!$Z$2:$Z$497<>"")),持仓跟踪!$Z$2:$Z$497),"")) | M115: =IF(A115="","",IFERROR(LOOKUP(2,1/((持仓跟踪!$B$2:$B$497=A115)*(持仓跟踪!$X$2:$X$497="执行卖出")*(持仓跟踪!$H$2:$H$497<>"")),持仓跟踪!$H$2:$H$497),"")) | P115: =IF(A115="","",IFERROR(LOOKUP(2,1/((持仓跟踪!$B$2:$B$497=A115)*(持仓跟踪!$X$2:$X$497="执行卖出")*(持仓跟踪!$AA$2:$AA$497<>"")),持仓跟踪!$AA$2:$AA$497),"")) | U115: =IF(OR(AO115="",J115="",AO115<=0),"",(J115-AO115)/AO115) | V115: =IF(OR(AO115="",N115="",AO115<=0),"",(AO115-N115)/AO115) | W115: =IF(OR(U115="",V115="",V115<=0),"",U115/V115) | X115: =IF(OR(K115="",L115="",AP115=""),"",K115*L115-(E115*H115+IF(AND(AK115<>"",AL115<>""),AK115*AL115,0)+IF(AND(AM115<>"",AN115<>""),AM115*AN115,0))-IF(O115="",0,O115)-IF(P115="",0,P115)) | Y115: =IF(OR(X115="",AP115=""),"",IF((E115*H115+IF(AND(AK115<>"",AL115<>""),AK115*AL115,0)+IF(AND(AM115<>"",AN115<>""),AM115*AN115,0))+IF(O115="",0,O115)<=0,"",X115/((E115*H115+IF(AND(AK115<>"",AL115<>""),AK115*AL115,0)+IF(AND(AM115<>"",AN115<>""),AM115*AN115,0))+IF(O115="",0,O115)))) | Z115: =IF(OR(AE115="",多次统计数据!$B$8=""),"",AE115-多次统计数据!$B$8) | AA115: =IF(OR(I115="",M115="",M115<I115),"",M115-I115) | AB115: =IF(OR(A115="",多次统计数据!$B$8="",多次统计数据!$B$6<=0,多次统计数据!$B$6>=1),"",1-POWER(1+多次统计数据!$B$8,-多次统计数据!$B$6/(1-多次统计数据!$B$6))) | AC115: =IF(OR(AB115="",多次统计数据!$B$9=""),"",IF(多次统计数据!$B$9<AB115,"低于上限","达到或超过上限")) | AE115: =IF(OR(X115="",C115="",C115<=0),"",X115/C115) | AJ115: =IF(OR(AG115="",AH115=""),"",IF(OR(AND(AG115="短期博反弹",OR(AH115="1～3个交易日",AH115="4～10个交易日")),AND(AG115="突破冲新高",OR(AH115="4～10个交易日",AH115="11～20个交易日")),AND(AG115="趋势波段",OR(AH115="11～20个交易日",AH115="21～60个交易日",AH115="60个交易日以上"))),"匹配","周期与交易预期不匹配，请重新确认")) | AO115: =IF(OR(A115="",H115="",H115<=0),"",(E115*H115+IF(AND(AK115<>"",AL115<>""),AK115*AL115,0)+IF(AND(AM115<>"",AN115<>""),AM115*AN115,0))/AP115) | AP115: =IF(OR(A115="",H115="",H115<=0),"",H115+IF(AL115="",0,AL115)+IF(AN115="",0,AN115)) | AQ115: =IF(A115="","",IF(M115<>"",0,IF(OR(H115="",N115=""),"",MAX(E115-MAX(N115,IFERROR(SUMPRODUCT(MAX(((持仓跟踪!$A$2:$A$497="每日跟踪")*(持仓跟踪!$B$2:$B$497=A115))*持仓跟踪!$S$2:$S$497)),0)),0)*H115+IF(OR(AK115="",AL115=""),0,MAX(AK115-MAX(N115,IFERROR(SUMPRODUCT(MAX(((持仓跟踪!$A$2:$A$497="每日跟踪")*(持仓跟踪!$B$2:$B$497=A115))*持仓跟踪!$S$2:$S$497)),0)),0)*AL115)+IF(OR(AM115="",AN115=""),0,MAX(AM115-MAX(N115,IFERROR(SUMPRODUCT(MAX(((持仓跟踪!$A$2:$A$497="每日跟踪")*(持仓跟踪!$B$2:$B$497=A115))*持仓跟踪!$S$2:$S$497)),0)),0)*AN115)))) | AR115: =IF(A115="","",IF(OR(E115="",H115=""),"违规：第一批价格或股数缺失",IF(OR(AND(AK115="",AL115<>""),AND(AK115<>"",AL115="")),"违规：第二批价格与股数须成对填写",IF(OR(AND(AM115="",AN115<>""),AND(AM115<>"",AN115="")),"违规：第三批价格与股数须成对填写",IF(AND(OR(AM115<>"",AN115<>""),OR(AK115="",AL115="")),"违规：必须先完成第二批",IF(OR(H115<=0,H115<>INT(H115),MOD(H115,100)<>0,AND(AL115<>"",OR(AL115<=0,AL115<>INT(AL115),MOD(AL115,100)<>0)),AND(AN115<>"",OR(AN115<=0,AN115<>INT(AN115),MOD(AN115,100)<>0))),"违规：股数须为100股整数倍",IF(AND(OR(AL115<>"",AN115<>""),OR(_LockStatus="已锁仓",_LockStatus="解锁信息不完整")),"违规：锁仓期间禁止加仓",IF(AQ115>C115*D115,"违规：超过单笔风险上限",IF(SUM($AQ$2:$AQ$201)>账户数据!$B$7,"违规：超过账户风险上限","通过")))))))))
F116: =IF(OR(C116="",D116="",E116="",N116="",C116<=0,D116<=0,E116<=N116),"",ROUNDDOWN((C116*D116)/(E116-N116)/100,0)*100) | G116: =IF(A116="","",IF(H116<>"","已开仓",IF(账户数据!$B$23="已锁仓","禁止开仓：连续亏损达到上限",IF(账户数据!$B$23="解锁信息不完整","禁止开仓：请完整填写解锁信息",IF(OR(F116="",E116="",N116="",E116<=N116,账户数据!$B$7=""),"",IF(OR(AG116="",AH116="",AI116=""),"禁止开仓：交易预期未填写完整",IF(COUNTIFS(持仓跟踪!$A$2:$A$497,"止损计划",持仓跟踪!$B$2:$B$497,A116,持仓跟踪!$AC$2:$AC$497,"计划有效")=0,"禁止开仓：请先填写止损计划",IF(账户数据!$B$9+F116*(E116-N116)>=账户数据!$B$7,"禁止开仓：风险额度不足",IF(AJ116="周期与交易预期不匹配，请重新确认",IF(账户数据!$B$23="接近锁仓","允许开仓（接近锁仓；周期需复核）","允许开仓（周期需复核）"),IF(账户数据!$B$23="接近锁仓","允许开仓（接近锁仓）","允许开仓")))))))))) | K116: =IF(A116="","",IFERROR(LOOKUP(2,1/((持仓跟踪!$B$2:$B$497=A116)*(持仓跟踪!$X$2:$X$497="执行卖出")*(持仓跟踪!$Y$2:$Y$497<>"")),持仓跟踪!$Y$2:$Y$497),"")) | L116: =IF(A116="","",IFERROR(LOOKUP(2,1/((持仓跟踪!$B$2:$B$497=A116)*(持仓跟踪!$X$2:$X$497="执行卖出")*(持仓跟踪!$Z$2:$Z$497<>"")),持仓跟踪!$Z$2:$Z$497),"")) | M116: =IF(A116="","",IFERROR(LOOKUP(2,1/((持仓跟踪!$B$2:$B$497=A116)*(持仓跟踪!$X$2:$X$497="执行卖出")*(持仓跟踪!$H$2:$H$497<>"")),持仓跟踪!$H$2:$H$497),"")) | P116: =IF(A116="","",IFERROR(LOOKUP(2,1/((持仓跟踪!$B$2:$B$497=A116)*(持仓跟踪!$X$2:$X$497="执行卖出")*(持仓跟踪!$AA$2:$AA$497<>"")),持仓跟踪!$AA$2:$AA$497),"")) | U116: =IF(OR(AO116="",J116="",AO116<=0),"",(J116-AO116)/AO116) | V116: =IF(OR(AO116="",N116="",AO116<=0),"",(AO116-N116)/AO116) | W116: =IF(OR(U116="",V116="",V116<=0),"",U116/V116) | X116: =IF(OR(K116="",L116="",AP116=""),"",K116*L116-(E116*H116+IF(AND(AK116<>"",AL116<>""),AK116*AL116,0)+IF(AND(AM116<>"",AN116<>""),AM116*AN116,0))-IF(O116="",0,O116)-IF(P116="",0,P116)) | Y116: =IF(OR(X116="",AP116=""),"",IF((E116*H116+IF(AND(AK116<>"",AL116<>""),AK116*AL116,0)+IF(AND(AM116<>"",AN116<>""),AM116*AN116,0))+IF(O116="",0,O116)<=0,"",X116/((E116*H116+IF(AND(AK116<>"",AL116<>""),AK116*AL116,0)+IF(AND(AM116<>"",AN116<>""),AM116*AN116,0))+IF(O116="",0,O116)))) | Z116: =IF(OR(AE116="",多次统计数据!$B$8=""),"",AE116-多次统计数据!$B$8) | AA116: =IF(OR(I116="",M116="",M116<I116),"",M116-I116) | AB116: =IF(OR(A116="",多次统计数据!$B$8="",多次统计数据!$B$6<=0,多次统计数据!$B$6>=1),"",1-POWER(1+多次统计数据!$B$8,-多次统计数据!$B$6/(1-多次统计数据!$B$6))) | AC116: =IF(OR(AB116="",多次统计数据!$B$9=""),"",IF(多次统计数据!$B$9<AB116,"低于上限","达到或超过上限")) | AE116: =IF(OR(X116="",C116="",C116<=0),"",X116/C116) | AJ116: =IF(OR(AG116="",AH116=""),"",IF(OR(AND(AG116="短期博反弹",OR(AH116="1～3个交易日",AH116="4～10个交易日")),AND(AG116="突破冲新高",OR(AH116="4～10个交易日",AH116="11～20个交易日")),AND(AG116="趋势波段",OR(AH116="11～20个交易日",AH116="21～60个交易日",AH116="60个交易日以上"))),"匹配","周期与交易预期不匹配，请重新确认")) | AO116: =IF(OR(A116="",H116="",H116<=0),"",(E116*H116+IF(AND(AK116<>"",AL116<>""),AK116*AL116,0)+IF(AND(AM116<>"",AN116<>""),AM116*AN116,0))/AP116) | AP116: =IF(OR(A116="",H116="",H116<=0),"",H116+IF(AL116="",0,AL116)+IF(AN116="",0,AN116)) | AQ116: =IF(A116="","",IF(M116<>"",0,IF(OR(H116="",N116=""),"",MAX(E116-MAX(N116,IFERROR(SUMPRODUCT(MAX(((持仓跟踪!$A$2:$A$497="每日跟踪")*(持仓跟踪!$B$2:$B$497=A116))*持仓跟踪!$S$2:$S$497)),0)),0)*H116+IF(OR(AK116="",AL116=""),0,MAX(AK116-MAX(N116,IFERROR(SUMPRODUCT(MAX(((持仓跟踪!$A$2:$A$497="每日跟踪")*(持仓跟踪!$B$2:$B$497=A116))*持仓跟踪!$S$2:$S$497)),0)),0)*AL116)+IF(OR(AM116="",AN116=""),0,MAX(AM116-MAX(N116,IFERROR(SUMPRODUCT(MAX(((持仓跟踪!$A$2:$A$497="每日跟踪")*(持仓跟踪!$B$2:$B$497=A116))*持仓跟踪!$S$2:$S$497)),0)),0)*AN116)))) | AR116: =IF(A116="","",IF(OR(E116="",H116=""),"违规：第一批价格或股数缺失",IF(OR(AND(AK116="",AL116<>""),AND(AK116<>"",AL116="")),"违规：第二批价格与股数须成对填写",IF(OR(AND(AM116="",AN116<>""),AND(AM116<>"",AN116="")),"违规：第三批价格与股数须成对填写",IF(AND(OR(AM116<>"",AN116<>""),OR(AK116="",AL116="")),"违规：必须先完成第二批",IF(OR(H116<=0,H116<>INT(H116),MOD(H116,100)<>0,AND(AL116<>"",OR(AL116<=0,AL116<>INT(AL116),MOD(AL116,100)<>0)),AND(AN116<>"",OR(AN116<=0,AN116<>INT(AN116),MOD(AN116,100)<>0))),"违规：股数须为100股整数倍",IF(AND(OR(AL116<>"",AN116<>""),OR(_LockStatus="已锁仓",_LockStatus="解锁信息不完整")),"违规：锁仓期间禁止加仓",IF(AQ116>C116*D116,"违规：超过单笔风险上限",IF(SUM($AQ$2:$AQ$201)>账户数据!$B$7,"违规：超过账户风险上限","通过")))))))))
F117: =IF(OR(C117="",D117="",E117="",N117="",C117<=0,D117<=0,E117<=N117),"",ROUNDDOWN((C117*D117)/(E117-N117)/100,0)*100) | G117: =IF(A117="","",IF(H117<>"","已开仓",IF(账户数据!$B$23="已锁仓","禁止开仓：连续亏损达到上限",IF(账户数据!$B$23="解锁信息不完整","禁止开仓：请完整填写解锁信息",IF(OR(F117="",E117="",N117="",E117<=N117,账户数据!$B$7=""),"",IF(OR(AG117="",AH117="",AI117=""),"禁止开仓：交易预期未填写完整",IF(COUNTIFS(持仓跟踪!$A$2:$A$497,"止损计划",持仓跟踪!$B$2:$B$497,A117,持仓跟踪!$AC$2:$AC$497,"计划有效")=0,"禁止开仓：请先填写止损计划",IF(账户数据!$B$9+F117*(E117-N117)>=账户数据!$B$7,"禁止开仓：风险额度不足",IF(AJ117="周期与交易预期不匹配，请重新确认",IF(账户数据!$B$23="接近锁仓","允许开仓（接近锁仓；周期需复核）","允许开仓（周期需复核）"),IF(账户数据!$B$23="接近锁仓","允许开仓（接近锁仓）","允许开仓")))))))))) | K117: =IF(A117="","",IFERROR(LOOKUP(2,1/((持仓跟踪!$B$2:$B$497=A117)*(持仓跟踪!$X$2:$X$497="执行卖出")*(持仓跟踪!$Y$2:$Y$497<>"")),持仓跟踪!$Y$2:$Y$497),"")) | L117: =IF(A117="","",IFERROR(LOOKUP(2,1/((持仓跟踪!$B$2:$B$497=A117)*(持仓跟踪!$X$2:$X$497="执行卖出")*(持仓跟踪!$Z$2:$Z$497<>"")),持仓跟踪!$Z$2:$Z$497),"")) | M117: =IF(A117="","",IFERROR(LOOKUP(2,1/((持仓跟踪!$B$2:$B$497=A117)*(持仓跟踪!$X$2:$X$497="执行卖出")*(持仓跟踪!$H$2:$H$497<>"")),持仓跟踪!$H$2:$H$497),"")) | P117: =IF(A117="","",IFERROR(LOOKUP(2,1/((持仓跟踪!$B$2:$B$497=A117)*(持仓跟踪!$X$2:$X$497="执行卖出")*(持仓跟踪!$AA$2:$AA$497<>"")),持仓跟踪!$AA$2:$AA$497),"")) | U117: =IF(OR(AO117="",J117="",AO117<=0),"",(J117-AO117)/AO117) | V117: =IF(OR(AO117="",N117="",AO117<=0),"",(AO117-N117)/AO117) | W117: =IF(OR(U117="",V117="",V117<=0),"",U117/V117) | X117: =IF(OR(K117="",L117="",AP117=""),"",K117*L117-(E117*H117+IF(AND(AK117<>"",AL117<>""),AK117*AL117,0)+IF(AND(AM117<>"",AN117<>""),AM117*AN117,0))-IF(O117="",0,O117)-IF(P117="",0,P117)) | Y117: =IF(OR(X117="",AP117=""),"",IF((E117*H117+IF(AND(AK117<>"",AL117<>""),AK117*AL117,0)+IF(AND(AM117<>"",AN117<>""),AM117*AN117,0))+IF(O117="",0,O117)<=0,"",X117/((E117*H117+IF(AND(AK117<>"",AL117<>""),AK117*AL117,0)+IF(AND(AM117<>"",AN117<>""),AM117*AN117,0))+IF(O117="",0,O117)))) | Z117: =IF(OR(AE117="",多次统计数据!$B$8=""),"",AE117-多次统计数据!$B$8) | AA117: =IF(OR(I117="",M117="",M117<I117),"",M117-I117) | AB117: =IF(OR(A117="",多次统计数据!$B$8="",多次统计数据!$B$6<=0,多次统计数据!$B$6>=1),"",1-POWER(1+多次统计数据!$B$8,-多次统计数据!$B$6/(1-多次统计数据!$B$6))) | AC117: =IF(OR(AB117="",多次统计数据!$B$9=""),"",IF(多次统计数据!$B$9<AB117,"低于上限","达到或超过上限")) | AE117: =IF(OR(X117="",C117="",C117<=0),"",X117/C117) | AJ117: =IF(OR(AG117="",AH117=""),"",IF(OR(AND(AG117="短期博反弹",OR(AH117="1～3个交易日",AH117="4～10个交易日")),AND(AG117="突破冲新高",OR(AH117="4～10个交易日",AH117="11～20个交易日")),AND(AG117="趋势波段",OR(AH117="11～20个交易日",AH117="21～60个交易日",AH117="60个交易日以上"))),"匹配","周期与交易预期不匹配，请重新确认")) | AO117: =IF(OR(A117="",H117="",H117<=0),"",(E117*H117+IF(AND(AK117<>"",AL117<>""),AK117*AL117,0)+IF(AND(AM117<>"",AN117<>""),AM117*AN117,0))/AP117) | AP117: =IF(OR(A117="",H117="",H117<=0),"",H117+IF(AL117="",0,AL117)+IF(AN117="",0,AN117)) | AQ117: =IF(A117="","",IF(M117<>"",0,IF(OR(H117="",N117=""),"",MAX(E117-MAX(N117,IFERROR(SUMPRODUCT(MAX(((持仓跟踪!$A$2:$A$497="每日跟踪")*(持仓跟踪!$B$2:$B$497=A117))*持仓跟踪!$S$2:$S$497)),0)),0)*H117+IF(OR(AK117="",AL117=""),0,MAX(AK117-MAX(N117,IFERROR(SUMPRODUCT(MAX(((持仓跟踪!$A$2:$A$497="每日跟踪")*(持仓跟踪!$B$2:$B$497=A117))*持仓跟踪!$S$2:$S$497)),0)),0)*AL117)+IF(OR(AM117="",AN117=""),0,MAX(AM117-MAX(N117,IFERROR(SUMPRODUCT(MAX(((持仓跟踪!$A$2:$A$497="每日跟踪")*(持仓跟踪!$B$2:$B$497=A117))*持仓跟踪!$S$2:$S$497)),0)),0)*AN117)))) | AR117: =IF(A117="","",IF(OR(E117="",H117=""),"违规：第一批价格或股数缺失",IF(OR(AND(AK117="",AL117<>""),AND(AK117<>"",AL117="")),"违规：第二批价格与股数须成对填写",IF(OR(AND(AM117="",AN117<>""),AND(AM117<>"",AN117="")),"违规：第三批价格与股数须成对填写",IF(AND(OR(AM117<>"",AN117<>""),OR(AK117="",AL117="")),"违规：必须先完成第二批",IF(OR(H117<=0,H117<>INT(H117),MOD(H117,100)<>0,AND(AL117<>"",OR(AL117<=0,AL117<>INT(AL117),MOD(AL117,100)<>0)),AND(AN117<>"",OR(AN117<=0,AN117<>INT(AN117),MOD(AN117,100)<>0))),"违规：股数须为100股整数倍",IF(AND(OR(AL117<>"",AN117<>""),OR(_LockStatus="已锁仓",_LockStatus="解锁信息不完整")),"违规：锁仓期间禁止加仓",IF(AQ117>C117*D117,"违规：超过单笔风险上限",IF(SUM($AQ$2:$AQ$201)>账户数据!$B$7,"违规：超过账户风险上限","通过")))))))))
F118: =IF(OR(C118="",D118="",E118="",N118="",C118<=0,D118<=0,E118<=N118),"",ROUNDDOWN((C118*D118)/(E118-N118)/100,0)*100) | G118: =IF(A118="","",IF(H118<>"","已开仓",IF(账户数据!$B$23="已锁仓","禁止开仓：连续亏损达到上限",IF(账户数据!$B$23="解锁信息不完整","禁止开仓：请完整填写解锁信息",IF(OR(F118="",E118="",N118="",E118<=N118,账户数据!$B$7=""),"",IF(OR(AG118="",AH118="",AI118=""),"禁止开仓：交易预期未填写完整",IF(COUNTIFS(持仓跟踪!$A$2:$A$497,"止损计划",持仓跟踪!$B$2:$B$497,A118,持仓跟踪!$AC$2:$AC$497,"计划有效")=0,"禁止开仓：请先填写止损计划",IF(账户数据!$B$9+F118*(E118-N118)>=账户数据!$B$7,"禁止开仓：风险额度不足",IF(AJ118="周期与交易预期不匹配，请重新确认",IF(账户数据!$B$23="接近锁仓","允许开仓（接近锁仓；周期需复核）","允许开仓（周期需复核）"),IF(账户数据!$B$23="接近锁仓","允许开仓（接近锁仓）","允许开仓")))))))))) | K118: =IF(A118="","",IFERROR(LOOKUP(2,1/((持仓跟踪!$B$2:$B$497=A118)*(持仓跟踪!$X$2:$X$497="执行卖出")*(持仓跟踪!$Y$2:$Y$497<>"")),持仓跟踪!$Y$2:$Y$497),"")) | L118: =IF(A118="","",IFERROR(LOOKUP(2,1/((持仓跟踪!$B$2:$B$497=A118)*(持仓跟踪!$X$2:$X$497="执行卖出")*(持仓跟踪!$Z$2:$Z$497<>"")),持仓跟踪!$Z$2:$Z$497),"")) | M118: =IF(A118="","",IFERROR(LOOKUP(2,1/((持仓跟踪!$B$2:$B$497=A118)*(持仓跟踪!$X$2:$X$497="执行卖出")*(持仓跟踪!$H$2:$H$497<>"")),持仓跟踪!$H$2:$H$497),"")) | P118: =IF(A118="","",IFERROR(LOOKUP(2,1/((持仓跟踪!$B$2:$B$497=A118)*(持仓跟踪!$X$2:$X$497="执行卖出")*(持仓跟踪!$AA$2:$AA$497<>"")),持仓跟踪!$AA$2:$AA$497),"")) | U118: =IF(OR(AO118="",J118="",AO118<=0),"",(J118-AO118)/AO118) | V118: =IF(OR(AO118="",N118="",AO118<=0),"",(AO118-N118)/AO118) | W118: =IF(OR(U118="",V118="",V118<=0),"",U118/V118) | X118: =IF(OR(K118="",L118="",AP118=""),"",K118*L118-(E118*H118+IF(AND(AK118<>"",AL118<>""),AK118*AL118,0)+IF(AND(AM118<>"",AN118<>""),AM118*AN118,0))-IF(O118="",0,O118)-IF(P118="",0,P118)) | Y118: =IF(OR(X118="",AP118=""),"",IF((E118*H118+IF(AND(AK118<>"",AL118<>""),AK118*AL118,0)+IF(AND(AM118<>"",AN118<>""),AM118*AN118,0))+IF(O118="",0,O118)<=0,"",X118/((E118*H118+IF(AND(AK118<>"",AL118<>""),AK118*AL118,0)+IF(AND(AM118<>"",AN118<>""),AM118*AN118,0))+IF(O118="",0,O118)))) | Z118: =IF(OR(AE118="",多次统计数据!$B$8=""),"",AE118-多次统计数据!$B$8) | AA118: =IF(OR(I118="",M118="",M118<I118),"",M118-I118) | AB118: =IF(OR(A118="",多次统计数据!$B$8="",多次统计数据!$B$6<=0,多次统计数据!$B$6>=1),"",1-POWER(1+多次统计数据!$B$8,-多次统计数据!$B$6/(1-多次统计数据!$B$6))) | AC118: =IF(OR(AB118="",多次统计数据!$B$9=""),"",IF(多次统计数据!$B$9<AB118,"低于上限","达到或超过上限")) | AE118: =IF(OR(X118="",C118="",C118<=0),"",X118/C118) | AJ118: =IF(OR(AG118="",AH118=""),"",IF(OR(AND(AG118="短期博反弹",OR(AH118="1～3个交易日",AH118="4～10个交易日")),AND(AG118="突破冲新高",OR(AH118="4～10个交易日",AH118="11～20个交易日")),AND(AG118="趋势波段",OR(AH118="11～20个交易日",AH118="21～60个交易日",AH118="60个交易日以上"))),"匹配","周期与交易预期不匹配，请重新确认")) | AO118: =IF(OR(A118="",H118="",H118<=0),"",(E118*H118+IF(AND(AK118<>"",AL118<>""),AK118*AL118,0)+IF(AND(AM118<>"",AN118<>""),AM118*AN118,0))/AP118) | AP118: =IF(OR(A118="",H118="",H118<=0),"",H118+IF(AL118="",0,AL118)+IF(AN118="",0,AN118)) | AQ118: =IF(A118="","",IF(M118<>"",0,IF(OR(H118="",N118=""),"",MAX(E118-MAX(N118,IFERROR(SUMPRODUCT(MAX(((持仓跟踪!$A$2:$A$497="每日跟踪")*(持仓跟踪!$B$2:$B$497=A118))*持仓跟踪!$S$2:$S$497)),0)),0)*H118+IF(OR(AK118="",AL118=""),0,MAX(AK118-MAX(N118,IFERROR(SUMPRODUCT(MAX(((持仓跟踪!$A$2:$A$497="每日跟踪")*(持仓跟踪!$B$2:$B$497=A118))*持仓跟踪!$S$2:$S$497)),0)),0)*AL118)+IF(OR(AM118="",AN118=""),0,MAX(AM118-MAX(N118,IFERROR(SUMPRODUCT(MAX(((持仓跟踪!$A$2:$A$497="每日跟踪")*(持仓跟踪!$B$2:$B$497=A118))*持仓跟踪!$S$2:$S$497)),0)),0)*AN118)))) | AR118: =IF(A118="","",IF(OR(E118="",H118=""),"违规：第一批价格或股数缺失",IF(OR(AND(AK118="",AL118<>""),AND(AK118<>"",AL118="")),"违规：第二批价格与股数须成对填写",IF(OR(AND(AM118="",AN118<>""),AND(AM118<>"",AN118="")),"违规：第三批价格与股数须成对填写",IF(AND(OR(AM118<>"",AN118<>""),OR(AK118="",AL118="")),"违规：必须先完成第二批",IF(OR(H118<=0,H118<>INT(H118),MOD(H118,100)<>0,AND(AL118<>"",OR(AL118<=0,AL118<>INT(AL118),MOD(AL118,100)<>0)),AND(AN118<>"",OR(AN118<=0,AN118<>INT(AN118),MOD(AN118,100)<>0))),"违规：股数须为100股整数倍",IF(AND(OR(AL118<>"",AN118<>""),OR(_LockStatus="已锁仓",_LockStatus="解锁信息不完整")),"违规：锁仓期间禁止加仓",IF(AQ118>C118*D118,"违规：超过单笔风险上限",IF(SUM($AQ$2:$AQ$201)>账户数据!$B$7,"违规：超过账户风险上限","通过")))))))))
F119: =IF(OR(C119="",D119="",E119="",N119="",C119<=0,D119<=0,E119<=N119),"",ROUNDDOWN((C119*D119)/(E119-N119)/100,0)*100) | G119: =IF(A119="","",IF(H119<>"","已开仓",IF(账户数据!$B$23="已锁仓","禁止开仓：连续亏损达到上限",IF(账户数据!$B$23="解锁信息不完整","禁止开仓：请完整填写解锁信息",IF(OR(F119="",E119="",N119="",E119<=N119,账户数据!$B$7=""),"",IF(OR(AG119="",AH119="",AI119=""),"禁止开仓：交易预期未填写完整",IF(COUNTIFS(持仓跟踪!$A$2:$A$497,"止损计划",持仓跟踪!$B$2:$B$497,A119,持仓跟踪!$AC$2:$AC$497,"计划有效")=0,"禁止开仓：请先填写止损计划",IF(账户数据!$B$9+F119*(E119-N119)>=账户数据!$B$7,"禁止开仓：风险额度不足",IF(AJ119="周期与交易预期不匹配，请重新确认",IF(账户数据!$B$23="接近锁仓","允许开仓（接近锁仓；周期需复核）","允许开仓（周期需复核）"),IF(账户数据!$B$23="接近锁仓","允许开仓（接近锁仓）","允许开仓")))))))))) | K119: =IF(A119="","",IFERROR(LOOKUP(2,1/((持仓跟踪!$B$2:$B$497=A119)*(持仓跟踪!$X$2:$X$497="执行卖出")*(持仓跟踪!$Y$2:$Y$497<>"")),持仓跟踪!$Y$2:$Y$497),"")) | L119: =IF(A119="","",IFERROR(LOOKUP(2,1/((持仓跟踪!$B$2:$B$497=A119)*(持仓跟踪!$X$2:$X$497="执行卖出")*(持仓跟踪!$Z$2:$Z$497<>"")),持仓跟踪!$Z$2:$Z$497),"")) | M119: =IF(A119="","",IFERROR(LOOKUP(2,1/((持仓跟踪!$B$2:$B$497=A119)*(持仓跟踪!$X$2:$X$497="执行卖出")*(持仓跟踪!$H$2:$H$497<>"")),持仓跟踪!$H$2:$H$497),"")) | P119: =IF(A119="","",IFERROR(LOOKUP(2,1/((持仓跟踪!$B$2:$B$497=A119)*(持仓跟踪!$X$2:$X$497="执行卖出")*(持仓跟踪!$AA$2:$AA$497<>"")),持仓跟踪!$AA$2:$AA$497),"")) | U119: =IF(OR(AO119="",J119="",AO119<=0),"",(J119-AO119)/AO119) | V119: =IF(OR(AO119="",N119="",AO119<=0),"",(AO119-N119)/AO119) | W119: =IF(OR(U119="",V119="",V119<=0),"",U119/V119) | X119: =IF(OR(K119="",L119="",AP119=""),"",K119*L119-(E119*H119+IF(AND(AK119<>"",AL119<>""),AK119*AL119,0)+IF(AND(AM119<>"",AN119<>""),AM119*AN119,0))-IF(O119="",0,O119)-IF(P119="",0,P119)) | Y119: =IF(OR(X119="",AP119=""),"",IF((E119*H119+IF(AND(AK119<>"",AL119<>""),AK119*AL119,0)+IF(AND(AM119<>"",AN119<>""),AM119*AN119,0))+IF(O119="",0,O119)<=0,"",X119/((E119*H119+IF(AND(AK119<>"",AL119<>""),AK119*AL119,0)+IF(AND(AM119<>"",AN119<>""),AM119*AN119,0))+IF(O119="",0,O119)))) | Z119: =IF(OR(AE119="",多次统计数据!$B$8=""),"",AE119-多次统计数据!$B$8) | AA119: =IF(OR(I119="",M119="",M119<I119),"",M119-I119) | AB119: =IF(OR(A119="",多次统计数据!$B$8="",多次统计数据!$B$6<=0,多次统计数据!$B$6>=1),"",1-POWER(1+多次统计数据!$B$8,-多次统计数据!$B$6/(1-多次统计数据!$B$6))) | AC119: =IF(OR(AB119="",多次统计数据!$B$9=""),"",IF(多次统计数据!$B$9<AB119,"低于上限","达到或超过上限")) | AE119: =IF(OR(X119="",C119="",C119<=0),"",X119/C119) | AJ119: =IF(OR(AG119="",AH119=""),"",IF(OR(AND(AG119="短期博反弹",OR(AH119="1～3个交易日",AH119="4～10个交易日")),AND(AG119="突破冲新高",OR(AH119="4～10个交易日",AH119="11～20个交易日")),AND(AG119="趋势波段",OR(AH119="11～20个交易日",AH119="21～60个交易日",AH119="60个交易日以上"))),"匹配","周期与交易预期不匹配，请重新确认")) | AO119: =IF(OR(A119="",H119="",H119<=0),"",(E119*H119+IF(AND(AK119<>"",AL119<>""),AK119*AL119,0)+IF(AND(AM119<>"",AN119<>""),AM119*AN119,0))/AP119) | AP119: =IF(OR(A119="",H119="",H119<=0),"",H119+IF(AL119="",0,AL119)+IF(AN119="",0,AN119)) | AQ119: =IF(A119="","",IF(M119<>"",0,IF(OR(H119="",N119=""),"",MAX(E119-MAX(N119,IFERROR(SUMPRODUCT(MAX(((持仓跟踪!$A$2:$A$497="每日跟踪")*(持仓跟踪!$B$2:$B$497=A119))*持仓跟踪!$S$2:$S$497)),0)),0)*H119+IF(OR(AK119="",AL119=""),0,MAX(AK119-MAX(N119,IFERROR(SUMPRODUCT(MAX(((持仓跟踪!$A$2:$A$497="每日跟踪")*(持仓跟踪!$B$2:$B$497=A119))*持仓跟踪!$S$2:$S$497)),0)),0)*AL119)+IF(OR(AM119="",AN119=""),0,MAX(AM119-MAX(N119,IFERROR(SUMPRODUCT(MAX(((持仓跟踪!$A$2:$A$497="每日跟踪")*(持仓跟踪!$B$2:$B$497=A119))*持仓跟踪!$S$2:$S$497)),0)),0)*AN119)))) | AR119: =IF(A119="","",IF(OR(E119="",H119=""),"违规：第一批价格或股数缺失",IF(OR(AND(AK119="",AL119<>""),AND(AK119<>"",AL119="")),"违规：第二批价格与股数须成对填写",IF(OR(AND(AM119="",AN119<>""),AND(AM119<>"",AN119="")),"违规：第三批价格与股数须成对填写",IF(AND(OR(AM119<>"",AN119<>""),OR(AK119="",AL119="")),"违规：必须先完成第二批",IF(OR(H119<=0,H119<>INT(H119),MOD(H119,100)<>0,AND(AL119<>"",OR(AL119<=0,AL119<>INT(AL119),MOD(AL119,100)<>0)),AND(AN119<>"",OR(AN119<=0,AN119<>INT(AN119),MOD(AN119,100)<>0))),"违规：股数须为100股整数倍",IF(AND(OR(AL119<>"",AN119<>""),OR(_LockStatus="已锁仓",_LockStatus="解锁信息不完整")),"违规：锁仓期间禁止加仓",IF(AQ119>C119*D119,"违规：超过单笔风险上限",IF(SUM($AQ$2:$AQ$201)>账户数据!$B$7,"违规：超过账户风险上限","通过")))))))))
F120: =IF(OR(C120="",D120="",E120="",N120="",C120<=0,D120<=0,E120<=N120),"",ROUNDDOWN((C120*D120)/(E120-N120)/100,0)*100) | G120: =IF(A120="","",IF(H120<>"","已开仓",IF(账户数据!$B$23="已锁仓","禁止开仓：连续亏损达到上限",IF(账户数据!$B$23="解锁信息不完整","禁止开仓：请完整填写解锁信息",IF(OR(F120="",E120="",N120="",E120<=N120,账户数据!$B$7=""),"",IF(OR(AG120="",AH120="",AI120=""),"禁止开仓：交易预期未填写完整",IF(COUNTIFS(持仓跟踪!$A$2:$A$497,"止损计划",持仓跟踪!$B$2:$B$497,A120,持仓跟踪!$AC$2:$AC$497,"计划有效")=0,"禁止开仓：请先填写止损计划",IF(账户数据!$B$9+F120*(E120-N120)>=账户数据!$B$7,"禁止开仓：风险额度不足",IF(AJ120="周期与交易预期不匹配，请重新确认",IF(账户数据!$B$23="接近锁仓","允许开仓（接近锁仓；周期需复核）","允许开仓（周期需复核）"),IF(账户数据!$B$23="接近锁仓","允许开仓（接近锁仓）","允许开仓")))))))))) | K120: =IF(A120="","",IFERROR(LOOKUP(2,1/((持仓跟踪!$B$2:$B$497=A120)*(持仓跟踪!$X$2:$X$497="执行卖出")*(持仓跟踪!$Y$2:$Y$497<>"")),持仓跟踪!$Y$2:$Y$497),"")) | L120: =IF(A120="","",IFERROR(LOOKUP(2,1/((持仓跟踪!$B$2:$B$497=A120)*(持仓跟踪!$X$2:$X$497="执行卖出")*(持仓跟踪!$Z$2:$Z$497<>"")),持仓跟踪!$Z$2:$Z$497),"")) | M120: =IF(A120="","",IFERROR(LOOKUP(2,1/((持仓跟踪!$B$2:$B$497=A120)*(持仓跟踪!$X$2:$X$497="执行卖出")*(持仓跟踪!$H$2:$H$497<>"")),持仓跟踪!$H$2:$H$497),"")) | P120: =IF(A120="","",IFERROR(LOOKUP(2,1/((持仓跟踪!$B$2:$B$497=A120)*(持仓跟踪!$X$2:$X$497="执行卖出")*(持仓跟踪!$AA$2:$AA$497<>"")),持仓跟踪!$AA$2:$AA$497),"")) | U120: =IF(OR(AO120="",J120="",AO120<=0),"",(J120-AO120)/AO120) | V120: =IF(OR(AO120="",N120="",AO120<=0),"",(AO120-N120)/AO120) | W120: =IF(OR(U120="",V120="",V120<=0),"",U120/V120) | X120: =IF(OR(K120="",L120="",AP120=""),"",K120*L120-(E120*H120+IF(AND(AK120<>"",AL120<>""),AK120*AL120,0)+IF(AND(AM120<>"",AN120<>""),AM120*AN120,0))-IF(O120="",0,O120)-IF(P120="",0,P120)) | Y120: =IF(OR(X120="",AP120=""),"",IF((E120*H120+IF(AND(AK120<>"",AL120<>""),AK120*AL120,0)+IF(AND(AM120<>"",AN120<>""),AM120*AN120,0))+IF(O120="",0,O120)<=0,"",X120/((E120*H120+IF(AND(AK120<>"",AL120<>""),AK120*AL120,0)+IF(AND(AM120<>"",AN120<>""),AM120*AN120,0))+IF(O120="",0,O120)))) | Z120: =IF(OR(AE120="",多次统计数据!$B$8=""),"",AE120-多次统计数据!$B$8) | AA120: =IF(OR(I120="",M120="",M120<I120),"",M120-I120) | AB120: =IF(OR(A120="",多次统计数据!$B$8="",多次统计数据!$B$6<=0,多次统计数据!$B$6>=1),"",1-POWER(1+多次统计数据!$B$8,-多次统计数据!$B$6/(1-多次统计数据!$B$6))) | AC120: =IF(OR(AB120="",多次统计数据!$B$9=""),"",IF(多次统计数据!$B$9<AB120,"低于上限","达到或超过上限")) | AE120: =IF(OR(X120="",C120="",C120<=0),"",X120/C120) | AJ120: =IF(OR(AG120="",AH120=""),"",IF(OR(AND(AG120="短期博反弹",OR(AH120="1～3个交易日",AH120="4～10个交易日")),AND(AG120="突破冲新高",OR(AH120="4～10个交易日",AH120="11～20个交易日")),AND(AG120="趋势波段",OR(AH120="11～20个交易日",AH120="21～60个交易日",AH120="60个交易日以上"))),"匹配","周期与交易预期不匹配，请重新确认")) | AO120: =IF(OR(A120="",H120="",H120<=0),"",(E120*H120+IF(AND(AK120<>"",AL120<>""),AK120*AL120,0)+IF(AND(AM120<>"",AN120<>""),AM120*AN120,0))/AP120) | AP120: =IF(OR(A120="",H120="",H120<=0),"",H120+IF(AL120="",0,AL120)+IF(AN120="",0,AN120)) | AQ120: =IF(A120="","",IF(M120<>"",0,IF(OR(H120="",N120=""),"",MAX(E120-MAX(N120,IFERROR(SUMPRODUCT(MAX(((持仓跟踪!$A$2:$A$497="每日跟踪")*(持仓跟踪!$B$2:$B$497=A120))*持仓跟踪!$S$2:$S$497)),0)),0)*H120+IF(OR(AK120="",AL120=""),0,MAX(AK120-MAX(N120,IFERROR(SUMPRODUCT(MAX(((持仓跟踪!$A$2:$A$497="每日跟踪")*(持仓跟踪!$B$2:$B$497=A120))*持仓跟踪!$S$2:$S$497)),0)),0)*AL120)+IF(OR(AM120="",AN120=""),0,MAX(AM120-MAX(N120,IFERROR(SUMPRODUCT(MAX(((持仓跟踪!$A$2:$A$497="每日跟踪")*(持仓跟踪!$B$2:$B$497=A120))*持仓跟踪!$S$2:$S$497)),0)),0)*AN120)))) | AR120: =IF(A120="","",IF(OR(E120="",H120=""),"违规：第一批价格或股数缺失",IF(OR(AND(AK120="",AL120<>""),AND(AK120<>"",AL120="")),"违规：第二批价格与股数须成对填写",IF(OR(AND(AM120="",AN120<>""),AND(AM120<>"",AN120="")),"违规：第三批价格与股数须成对填写",IF(AND(OR(AM120<>"",AN120<>""),OR(AK120="",AL120="")),"违规：必须先完成第二批",IF(OR(H120<=0,H120<>INT(H120),MOD(H120,100)<>0,AND(AL120<>"",OR(AL120<=0,AL120<>INT(AL120),MOD(AL120,100)<>0)),AND(AN120<>"",OR(AN120<=0,AN120<>INT(AN120),MOD(AN120,100)<>0))),"违规：股数须为100股整数倍",IF(AND(OR(AL120<>"",AN120<>""),OR(_LockStatus="已锁仓",_LockStatus="解锁信息不完整")),"违规：锁仓期间禁止加仓",IF(AQ120>C120*D120,"违规：超过单笔风险上限",IF(SUM($AQ$2:$AQ$201)>账户数据!$B$7,"违规：超过账户风险上限","通过")))))))))
F121: =IF(OR(C121="",D121="",E121="",N121="",C121<=0,D121<=0,E121<=N121),"",ROUNDDOWN((C121*D121)/(E121-N121)/100,0)*100) | G121: =IF(A121="","",IF(H121<>"","已开仓",IF(账户数据!$B$23="已锁仓","禁止开仓：连续亏损达到上限",IF(账户数据!$B$23="解锁信息不完整","禁止开仓：请完整填写解锁信息",IF(OR(F121="",E121="",N121="",E121<=N121,账户数据!$B$7=""),"",IF(OR(AG121="",AH121="",AI121=""),"禁止开仓：交易预期未填写完整",IF(COUNTIFS(持仓跟踪!$A$2:$A$497,"止损计划",持仓跟踪!$B$2:$B$497,A121,持仓跟踪!$AC$2:$AC$497,"计划有效")=0,"禁止开仓：请先填写止损计划",IF(账户数据!$B$9+F121*(E121-N121)>=账户数据!$B$7,"禁止开仓：风险额度不足",IF(AJ121="周期与交易预期不匹配，请重新确认",IF(账户数据!$B$23="接近锁仓","允许开仓（接近锁仓；周期需复核）","允许开仓（周期需复核）"),IF(账户数据!$B$23="接近锁仓","允许开仓（接近锁仓）","允许开仓")))))))))) | K121: =IF(A121="","",IFERROR(LOOKUP(2,1/((持仓跟踪!$B$2:$B$497=A121)*(持仓跟踪!$X$2:$X$497="执行卖出")*(持仓跟踪!$Y$2:$Y$497<>"")),持仓跟踪!$Y$2:$Y$497),"")) | L121: =IF(A121="","",IFERROR(LOOKUP(2,1/((持仓跟踪!$B$2:$B$497=A121)*(持仓跟踪!$X$2:$X$497="执行卖出")*(持仓跟踪!$Z$2:$Z$497<>"")),持仓跟踪!$Z$2:$Z$497),"")) | M121: =IF(A121="","",IFERROR(LOOKUP(2,1/((持仓跟踪!$B$2:$B$497=A121)*(持仓跟踪!$X$2:$X$497="执行卖出")*(持仓跟踪!$H$2:$H$497<>"")),持仓跟踪!$H$2:$H$497),"")) | P121: =IF(A121="","",IFERROR(LOOKUP(2,1/((持仓跟踪!$B$2:$B$497=A121)*(持仓跟踪!$X$2:$X$497="执行卖出")*(持仓跟踪!$AA$2:$AA$497<>"")),持仓跟踪!$AA$2:$AA$497),"")) | U121: =IF(OR(AO121="",J121="",AO121<=0),"",(J121-AO121)/AO121) | V121: =IF(OR(AO121="",N121="",AO121<=0),"",(AO121-N121)/AO121) | W121: =IF(OR(U121="",V121="",V121<=0),"",U121/V121) | X121: =IF(OR(K121="",L121="",AP121=""),"",K121*L121-(E121*H121+IF(AND(AK121<>"",AL121<>""),AK121*AL121,0)+IF(AND(AM121<>"",AN121<>""),AM121*AN121,0))-IF(O121="",0,O121)-IF(P121="",0,P121)) | Y121: =IF(OR(X121="",AP121=""),"",IF((E121*H121+IF(AND(AK121<>"",AL121<>""),AK121*AL121,0)+IF(AND(AM121<>"",AN121<>""),AM121*AN121,0))+IF(O121="",0,O121)<=0,"",X121/((E121*H121+IF(AND(AK121<>"",AL121<>""),AK121*AL121,0)+IF(AND(AM121<>"",AN121<>""),AM121*AN121,0))+IF(O121="",0,O121)))) | Z121: =IF(OR(AE121="",多次统计数据!$B$8=""),"",AE121-多次统计数据!$B$8) | AA121: =IF(OR(I121="",M121="",M121<I121),"",M121-I121) | AB121: =IF(OR(A121="",多次统计数据!$B$8="",多次统计数据!$B$6<=0,多次统计数据!$B$6>=1),"",1-POWER(1+多次统计数据!$B$8,-多次统计数据!$B$6/(1-多次统计数据!$B$6))) | AC121: =IF(OR(AB121="",多次统计数据!$B$9=""),"",IF(多次统计数据!$B$9<AB121,"低于上限","达到或超过上限")) | AE121: =IF(OR(X121="",C121="",C121<=0),"",X121/C121) | AJ121: =IF(OR(AG121="",AH121=""),"",IF(OR(AND(AG121="短期博反弹",OR(AH121="1～3个交易日",AH121="4～10个交易日")),AND(AG121="突破冲新高",OR(AH121="4～10个交易日",AH121="11～20个交易日")),AND(AG121="趋势波段",OR(AH121="11～20个交易日",AH121="21～60个交易日",AH121="60个交易日以上"))),"匹配","周期与交易预期不匹配，请重新确认")) | AO121: =IF(OR(A121="",H121="",H121<=0),"",(E121*H121+IF(AND(AK121<>"",AL121<>""),AK121*AL121,0)+IF(AND(AM121<>"",AN121<>""),AM121*AN121,0))/AP121) | AP121: =IF(OR(A121="",H121="",H121<=0),"",H121+IF(AL121="",0,AL121)+IF(AN121="",0,AN121)) | AQ121: =IF(A121="","",IF(M121<>"",0,IF(OR(H121="",N121=""),"",MAX(E121-MAX(N121,IFERROR(SUMPRODUCT(MAX(((持仓跟踪!$A$2:$A$497="每日跟踪")*(持仓跟踪!$B$2:$B$497=A121))*持仓跟踪!$S$2:$S$497)),0)),0)*H121+IF(OR(AK121="",AL121=""),0,MAX(AK121-MAX(N121,IFERROR(SUMPRODUCT(MAX(((持仓跟踪!$A$2:$A$497="每日跟踪")*(持仓跟踪!$B$2:$B$497=A121))*持仓跟踪!$S$2:$S$497)),0)),0)*AL121)+IF(OR(AM121="",AN121=""),0,MAX(AM121-MAX(N121,IFERROR(SUMPRODUCT(MAX(((持仓跟踪!$A$2:$A$497="每日跟踪")*(持仓跟踪!$B$2:$B$497=A121))*持仓跟踪!$S$2:$S$497)),0)),0)*AN121)))) | AR121: =IF(A121="","",IF(OR(E121="",H121=""),"违规：第一批价格或股数缺失",IF(OR(AND(AK121="",AL121<>""),AND(AK121<>"",AL121="")),"违规：第二批价格与股数须成对填写",IF(OR(AND(AM121="",AN121<>""),AND(AM121<>"",AN121="")),"违规：第三批价格与股数须成对填写",IF(AND(OR(AM121<>"",AN121<>""),OR(AK121="",AL121="")),"违规：必须先完成第二批",IF(OR(H121<=0,H121<>INT(H121),MOD(H121,100)<>0,AND(AL121<>"",OR(AL121<=0,AL121<>INT(AL121),MOD(AL121,100)<>0)),AND(AN121<>"",OR(AN121<=0,AN121<>INT(AN121),MOD(AN121,100)<>0))),"违规：股数须为100股整数倍",IF(AND(OR(AL121<>"",AN121<>""),OR(_LockStatus="已锁仓",_LockStatus="解锁信息不完整")),"违规：锁仓期间禁止加仓",IF(AQ121>C121*D121,"违规：超过单笔风险上限",IF(SUM($AQ$2:$AQ$201)>账户数据!$B$7,"违规：超过账户风险上限","通过")))))))))
F122: =IF(OR(C122="",D122="",E122="",N122="",C122<=0,D122<=0,E122<=N122),"",ROUNDDOWN((C122*D122)/(E122-N122)/100,0)*100) | G122: =IF(A122="","",IF(H122<>"","已开仓",IF(账户数据!$B$23="已锁仓","禁止开仓：连续亏损达到上限",IF(账户数据!$B$23="解锁信息不完整","禁止开仓：请完整填写解锁信息",IF(OR(F122="",E122="",N122="",E122<=N122,账户数据!$B$7=""),"",IF(OR(AG122="",AH122="",AI122=""),"禁止开仓：交易预期未填写完整",IF(COUNTIFS(持仓跟踪!$A$2:$A$497,"止损计划",持仓跟踪!$B$2:$B$497,A122,持仓跟踪!$AC$2:$AC$497,"计划有效")=0,"禁止开仓：请先填写止损计划",IF(账户数据!$B$9+F122*(E122-N122)>=账户数据!$B$7,"禁止开仓：风险额度不足",IF(AJ122="周期与交易预期不匹配，请重新确认",IF(账户数据!$B$23="接近锁仓","允许开仓（接近锁仓；周期需复核）","允许开仓（周期需复核）"),IF(账户数据!$B$23="接近锁仓","允许开仓（接近锁仓）","允许开仓")))))))))) | K122: =IF(A122="","",IFERROR(LOOKUP(2,1/((持仓跟踪!$B$2:$B$497=A122)*(持仓跟踪!$X$2:$X$497="执行卖出")*(持仓跟踪!$Y$2:$Y$497<>"")),持仓跟踪!$Y$2:$Y$497),"")) | L122: =IF(A122="","",IFERROR(LOOKUP(2,1/((持仓跟踪!$B$2:$B$497=A122)*(持仓跟踪!$X$2:$X$497="执行卖出")*(持仓跟踪!$Z$2:$Z$497<>"")),持仓跟踪!$Z$2:$Z$497),"")) | M122: =IF(A122="","",IFERROR(LOOKUP(2,1/((持仓跟踪!$B$2:$B$497=A122)*(持仓跟踪!$X$2:$X$497="执行卖出")*(持仓跟踪!$H$2:$H$497<>"")),持仓跟踪!$H$2:$H$497),"")) | P122: =IF(A122="","",IFERROR(LOOKUP(2,1/((持仓跟踪!$B$2:$B$497=A122)*(持仓跟踪!$X$2:$X$497="执行卖出")*(持仓跟踪!$AA$2:$AA$497<>"")),持仓跟踪!$AA$2:$AA$497),"")) | U122: =IF(OR(AO122="",J122="",AO122<=0),"",(J122-AO122)/AO122) | V122: =IF(OR(AO122="",N122="",AO122<=0),"",(AO122-N122)/AO122) | W122: =IF(OR(U122="",V122="",V122<=0),"",U122/V122) | X122: =IF(OR(K122="",L122="",AP122=""),"",K122*L122-(E122*H122+IF(AND(AK122<>"",AL122<>""),AK122*AL122,0)+IF(AND(AM122<>"",AN122<>""),AM122*AN122,0))-IF(O122="",0,O122)-IF(P122="",0,P122)) | Y122: =IF(OR(X122="",AP122=""),"",IF((E122*H122+IF(AND(AK122<>"",AL122<>""),AK122*AL122,0)+IF(AND(AM122<>"",AN122<>""),AM122*AN122,0))+IF(O122="",0,O122)<=0,"",X122/((E122*H122+IF(AND(AK122<>"",AL122<>""),AK122*AL122,0)+IF(AND(AM122<>"",AN122<>""),AM122*AN122,0))+IF(O122="",0,O122)))) | Z122: =IF(OR(AE122="",多次统计数据!$B$8=""),"",AE122-多次统计数据!$B$8) | AA122: =IF(OR(I122="",M122="",M122<I122),"",M122-I122) | AB122: =IF(OR(A122="",多次统计数据!$B$8="",多次统计数据!$B$6<=0,多次统计数据!$B$6>=1),"",1-POWER(1+多次统计数据!$B$8,-多次统计数据!$B$6/(1-多次统计数据!$B$6))) | AC122: =IF(OR(AB122="",多次统计数据!$B$9=""),"",IF(多次统计数据!$B$9<AB122,"低于上限","达到或超过上限")) | AE122: =IF(OR(X122="",C122="",C122<=0),"",X122/C122) | AJ122: =IF(OR(AG122="",AH122=""),"",IF(OR(AND(AG122="短期博反弹",OR(AH122="1～3个交易日",AH122="4～10个交易日")),AND(AG122="突破冲新高",OR(AH122="4～10个交易日",AH122="11～20个交易日")),AND(AG122="趋势波段",OR(AH122="11～20个交易日",AH122="21～60个交易日",AH122="60个交易日以上"))),"匹配","周期与交易预期不匹配，请重新确认")) | AO122: =IF(OR(A122="",H122="",H122<=0),"",(E122*H122+IF(AND(AK122<>"",AL122<>""),AK122*AL122,0)+IF(AND(AM122<>"",AN122<>""),AM122*AN122,0))/AP122) | AP122: =IF(OR(A122="",H122="",H122<=0),"",H122+IF(AL122="",0,AL122)+IF(AN122="",0,AN122)) | AQ122: =IF(A122="","",IF(M122<>"",0,IF(OR(H122="",N122=""),"",MAX(E122-MAX(N122,IFERROR(SUMPRODUCT(MAX(((持仓跟踪!$A$2:$A$497="每日跟踪")*(持仓跟踪!$B$2:$B$497=A122))*持仓跟踪!$S$2:$S$497)),0)),0)*H122+IF(OR(AK122="",AL122=""),0,MAX(AK122-MAX(N122,IFERROR(SUMPRODUCT(MAX(((持仓跟踪!$A$2:$A$497="每日跟踪")*(持仓跟踪!$B$2:$B$497=A122))*持仓跟踪!$S$2:$S$497)),0)),0)*AL122)+IF(OR(AM122="",AN122=""),0,MAX(AM122-MAX(N122,IFERROR(SUMPRODUCT(MAX(((持仓跟踪!$A$2:$A$497="每日跟踪")*(持仓跟踪!$B$2:$B$497=A122))*持仓跟踪!$S$2:$S$497)),0)),0)*AN122)))) | AR122: =IF(A122="","",IF(OR(E122="",H122=""),"违规：第一批价格或股数缺失",IF(OR(AND(AK122="",AL122<>""),AND(AK122<>"",AL122="")),"违规：第二批价格与股数须成对填写",IF(OR(AND(AM122="",AN122<>""),AND(AM122<>"",AN122="")),"违规：第三批价格与股数须成对填写",IF(AND(OR(AM122<>"",AN122<>""),OR(AK122="",AL122="")),"违规：必须先完成第二批",IF(OR(H122<=0,H122<>INT(H122),MOD(H122,100)<>0,AND(AL122<>"",OR(AL122<=0,AL122<>INT(AL122),MOD(AL122,100)<>0)),AND(AN122<>"",OR(AN122<=0,AN122<>INT(AN122),MOD(AN122,100)<>0))),"违规：股数须为100股整数倍",IF(AND(OR(AL122<>"",AN122<>""),OR(_LockStatus="已锁仓",_LockStatus="解锁信息不完整")),"违规：锁仓期间禁止加仓",IF(AQ122>C122*D122,"违规：超过单笔风险上限",IF(SUM($AQ$2:$AQ$201)>账户数据!$B$7,"违规：超过账户风险上限","通过")))))))))
F123: =IF(OR(C123="",D123="",E123="",N123="",C123<=0,D123<=0,E123<=N123),"",ROUNDDOWN((C123*D123)/(E123-N123)/100,0)*100) | G123: =IF(A123="","",IF(H123<>"","已开仓",IF(账户数据!$B$23="已锁仓","禁止开仓：连续亏损达到上限",IF(账户数据!$B$23="解锁信息不完整","禁止开仓：请完整填写解锁信息",IF(OR(F123="",E123="",N123="",E123<=N123,账户数据!$B$7=""),"",IF(OR(AG123="",AH123="",AI123=""),"禁止开仓：交易预期未填写完整",IF(COUNTIFS(持仓跟踪!$A$2:$A$497,"止损计划",持仓跟踪!$B$2:$B$497,A123,持仓跟踪!$AC$2:$AC$497,"计划有效")=0,"禁止开仓：请先填写止损计划",IF(账户数据!$B$9+F123*(E123-N123)>=账户数据!$B$7,"禁止开仓：风险额度不足",IF(AJ123="周期与交易预期不匹配，请重新确认",IF(账户数据!$B$23="接近锁仓","允许开仓（接近锁仓；周期需复核）","允许开仓（周期需复核）"),IF(账户数据!$B$23="接近锁仓","允许开仓（接近锁仓）","允许开仓")))))))))) | K123: =IF(A123="","",IFERROR(LOOKUP(2,1/((持仓跟踪!$B$2:$B$497=A123)*(持仓跟踪!$X$2:$X$497="执行卖出")*(持仓跟踪!$Y$2:$Y$497<>"")),持仓跟踪!$Y$2:$Y$497),"")) | L123: =IF(A123="","",IFERROR(LOOKUP(2,1/((持仓跟踪!$B$2:$B$497=A123)*(持仓跟踪!$X$2:$X$497="执行卖出")*(持仓跟踪!$Z$2:$Z$497<>"")),持仓跟踪!$Z$2:$Z$497),"")) | M123: =IF(A123="","",IFERROR(LOOKUP(2,1/((持仓跟踪!$B$2:$B$497=A123)*(持仓跟踪!$X$2:$X$497="执行卖出")*(持仓跟踪!$H$2:$H$497<>"")),持仓跟踪!$H$2:$H$497),"")) | P123: =IF(A123="","",IFERROR(LOOKUP(2,1/((持仓跟踪!$B$2:$B$497=A123)*(持仓跟踪!$X$2:$X$497="执行卖出")*(持仓跟踪!$AA$2:$AA$497<>"")),持仓跟踪!$AA$2:$AA$497),"")) | U123: =IF(OR(AO123="",J123="",AO123<=0),"",(J123-AO123)/AO123) | V123: =IF(OR(AO123="",N123="",AO123<=0),"",(AO123-N123)/AO123) | W123: =IF(OR(U123="",V123="",V123<=0),"",U123/V123) | X123: =IF(OR(K123="",L123="",AP123=""),"",K123*L123-(E123*H123+IF(AND(AK123<>"",AL123<>""),AK123*AL123,0)+IF(AND(AM123<>"",AN123<>""),AM123*AN123,0))-IF(O123="",0,O123)-IF(P123="",0,P123)) | Y123: =IF(OR(X123="",AP123=""),"",IF((E123*H123+IF(AND(AK123<>"",AL123<>""),AK123*AL123,0)+IF(AND(AM123<>"",AN123<>""),AM123*AN123,0))+IF(O123="",0,O123)<=0,"",X123/((E123*H123+IF(AND(AK123<>"",AL123<>""),AK123*AL123,0)+IF(AND(AM123<>"",AN123<>""),AM123*AN123,0))+IF(O123="",0,O123)))) | Z123: =IF(OR(AE123="",多次统计数据!$B$8=""),"",AE123-多次统计数据!$B$8) | AA123: =IF(OR(I123="",M123="",M123<I123),"",M123-I123) | AB123: =IF(OR(A123="",多次统计数据!$B$8="",多次统计数据!$B$6<=0,多次统计数据!$B$6>=1),"",1-POWER(1+多次统计数据!$B$8,-多次统计数据!$B$6/(1-多次统计数据!$B$6))) | AC123: =IF(OR(AB123="",多次统计数据!$B$9=""),"",IF(多次统计数据!$B$9<AB123,"低于上限","达到或超过上限")) | AE123: =IF(OR(X123="",C123="",C123<=0),"",X123/C123) | AJ123: =IF(OR(AG123="",AH123=""),"",IF(OR(AND(AG123="短期博反弹",OR(AH123="1～3个交易日",AH123="4～10个交易日")),AND(AG123="突破冲新高",OR(AH123="4～10个交易日",AH123="11～20个交易日")),AND(AG123="趋势波段",OR(AH123="11～20个交易日",AH123="21～60个交易日",AH123="60个交易日以上"))),"匹配","周期与交易预期不匹配，请重新确认")) | AO123: =IF(OR(A123="",H123="",H123<=0),"",(E123*H123+IF(AND(AK123<>"",AL123<>""),AK123*AL123,0)+IF(AND(AM123<>"",AN123<>""),AM123*AN123,0))/AP123) | AP123: =IF(OR(A123="",H123="",H123<=0),"",H123+IF(AL123="",0,AL123)+IF(AN123="",0,AN123)) | AQ123: =IF(A123="","",IF(M123<>"",0,IF(OR(H123="",N123=""),"",MAX(E123-MAX(N123,IFERROR(SUMPRODUCT(MAX(((持仓跟踪!$A$2:$A$497="每日跟踪")*(持仓跟踪!$B$2:$B$497=A123))*持仓跟踪!$S$2:$S$497)),0)),0)*H123+IF(OR(AK123="",AL123=""),0,MAX(AK123-MAX(N123,IFERROR(SUMPRODUCT(MAX(((持仓跟踪!$A$2:$A$497="每日跟踪")*(持仓跟踪!$B$2:$B$497=A123))*持仓跟踪!$S$2:$S$497)),0)),0)*AL123)+IF(OR(AM123="",AN123=""),0,MAX(AM123-MAX(N123,IFERROR(SUMPRODUCT(MAX(((持仓跟踪!$A$2:$A$497="每日跟踪")*(持仓跟踪!$B$2:$B$497=A123))*持仓跟踪!$S$2:$S$497)),0)),0)*AN123)))) | AR123: =IF(A123="","",IF(OR(E123="",H123=""),"违规：第一批价格或股数缺失",IF(OR(AND(AK123="",AL123<>""),AND(AK123<>"",AL123="")),"违规：第二批价格与股数须成对填写",IF(OR(AND(AM123="",AN123<>""),AND(AM123<>"",AN123="")),"违规：第三批价格与股数须成对填写",IF(AND(OR(AM123<>"",AN123<>""),OR(AK123="",AL123="")),"违规：必须先完成第二批",IF(OR(H123<=0,H123<>INT(H123),MOD(H123,100)<>0,AND(AL123<>"",OR(AL123<=0,AL123<>INT(AL123),MOD(AL123,100)<>0)),AND(AN123<>"",OR(AN123<=0,AN123<>INT(AN123),MOD(AN123,100)<>0))),"违规：股数须为100股整数倍",IF(AND(OR(AL123<>"",AN123<>""),OR(_LockStatus="已锁仓",_LockStatus="解锁信息不完整")),"违规：锁仓期间禁止加仓",IF(AQ123>C123*D123,"违规：超过单笔风险上限",IF(SUM($AQ$2:$AQ$201)>账户数据!$B$7,"违规：超过账户风险上限","通过")))))))))
F124: =IF(OR(C124="",D124="",E124="",N124="",C124<=0,D124<=0,E124<=N124),"",ROUNDDOWN((C124*D124)/(E124-N124)/100,0)*100) | G124: =IF(A124="","",IF(H124<>"","已开仓",IF(账户数据!$B$23="已锁仓","禁止开仓：连续亏损达到上限",IF(账户数据!$B$23="解锁信息不完整","禁止开仓：请完整填写解锁信息",IF(OR(F124="",E124="",N124="",E124<=N124,账户数据!$B$7=""),"",IF(OR(AG124="",AH124="",AI124=""),"禁止开仓：交易预期未填写完整",IF(COUNTIFS(持仓跟踪!$A$2:$A$497,"止损计划",持仓跟踪!$B$2:$B$497,A124,持仓跟踪!$AC$2:$AC$497,"计划有效")=0,"禁止开仓：请先填写止损计划",IF(账户数据!$B$9+F124*(E124-N124)>=账户数据!$B$7,"禁止开仓：风险额度不足",IF(AJ124="周期与交易预期不匹配，请重新确认",IF(账户数据!$B$23="接近锁仓","允许开仓（接近锁仓；周期需复核）","允许开仓（周期需复核）"),IF(账户数据!$B$23="接近锁仓","允许开仓（接近锁仓）","允许开仓")))))))))) | K124: =IF(A124="","",IFERROR(LOOKUP(2,1/((持仓跟踪!$B$2:$B$497=A124)*(持仓跟踪!$X$2:$X$497="执行卖出")*(持仓跟踪!$Y$2:$Y$497<>"")),持仓跟踪!$Y$2:$Y$497),"")) | L124: =IF(A124="","",IFERROR(LOOKUP(2,1/((持仓跟踪!$B$2:$B$497=A124)*(持仓跟踪!$X$2:$X$497="执行卖出")*(持仓跟踪!$Z$2:$Z$497<>"")),持仓跟踪!$Z$2:$Z$497),"")) | M124: =IF(A124="","",IFERROR(LOOKUP(2,1/((持仓跟踪!$B$2:$B$497=A124)*(持仓跟踪!$X$2:$X$497="执行卖出")*(持仓跟踪!$H$2:$H$497<>"")),持仓跟踪!$H$2:$H$497),"")) | P124: =IF(A124="","",IFERROR(LOOKUP(2,1/((持仓跟踪!$B$2:$B$497=A124)*(持仓跟踪!$X$2:$X$497="执行卖出")*(持仓跟踪!$AA$2:$AA$497<>"")),持仓跟踪!$AA$2:$AA$497),"")) | U124: =IF(OR(AO124="",J124="",AO124<=0),"",(J124-AO124)/AO124) | V124: =IF(OR(AO124="",N124="",AO124<=0),"",(AO124-N124)/AO124) | W124: =IF(OR(U124="",V124="",V124<=0),"",U124/V124) | X124: =IF(OR(K124="",L124="",AP124=""),"",K124*L124-(E124*H124+IF(AND(AK124<>"",AL124<>""),AK124*AL124,0)+IF(AND(AM124<>"",AN124<>""),AM124*AN124,0))-IF(O124="",0,O124)-IF(P124="",0,P124)) | Y124: =IF(OR(X124="",AP124=""),"",IF((E124*H124+IF(AND(AK124<>"",AL124<>""),AK124*AL124,0)+IF(AND(AM124<>"",AN124<>""),AM124*AN124,0))+IF(O124="",0,O124)<=0,"",X124/((E124*H124+IF(AND(AK124<>"",AL124<>""),AK124*AL124,0)+IF(AND(AM124<>"",AN124<>""),AM124*AN124,0))+IF(O124="",0,O124)))) | Z124: =IF(OR(AE124="",多次统计数据!$B$8=""),"",AE124-多次统计数据!$B$8) | AA124: =IF(OR(I124="",M124="",M124<I124),"",M124-I124) | AB124: =IF(OR(A124="",多次统计数据!$B$8="",多次统计数据!$B$6<=0,多次统计数据!$B$6>=1),"",1-POWER(1+多次统计数据!$B$8,-多次统计数据!$B$6/(1-多次统计数据!$B$6))) | AC124: =IF(OR(AB124="",多次统计数据!$B$9=""),"",IF(多次统计数据!$B$9<AB124,"低于上限","达到或超过上限")) | AE124: =IF(OR(X124="",C124="",C124<=0),"",X124/C124) | AJ124: =IF(OR(AG124="",AH124=""),"",IF(OR(AND(AG124="短期博反弹",OR(AH124="1～3个交易日",AH124="4～10个交易日")),AND(AG124="突破冲新高",OR(AH124="4～10个交易日",AH124="11～20个交易日")),AND(AG124="趋势波段",OR(AH124="11～20个交易日",AH124="21～60个交易日",AH124="60个交易日以上"))),"匹配","周期与交易预期不匹配，请重新确认")) | AO124: =IF(OR(A124="",H124="",H124<=0),"",(E124*H124+IF(AND(AK124<>"",AL124<>""),AK124*AL124,0)+IF(AND(AM124<>"",AN124<>""),AM124*AN124,0))/AP124) | AP124: =IF(OR(A124="",H124="",H124<=0),"",H124+IF(AL124="",0,AL124)+IF(AN124="",0,AN124)) | AQ124: =IF(A124="","",IF(M124<>"",0,IF(OR(H124="",N124=""),"",MAX(E124-MAX(N124,IFERROR(SUMPRODUCT(MAX(((持仓跟踪!$A$2:$A$497="每日跟踪")*(持仓跟踪!$B$2:$B$497=A124))*持仓跟踪!$S$2:$S$497)),0)),0)*H124+IF(OR(AK124="",AL124=""),0,MAX(AK124-MAX(N124,IFERROR(SUMPRODUCT(MAX(((持仓跟踪!$A$2:$A$497="每日跟踪")*(持仓跟踪!$B$2:$B$497=A124))*持仓跟踪!$S$2:$S$497)),0)),0)*AL124)+IF(OR(AM124="",AN124=""),0,MAX(AM124-MAX(N124,IFERROR(SUMPRODUCT(MAX(((持仓跟踪!$A$2:$A$497="每日跟踪")*(持仓跟踪!$B$2:$B$497=A124))*持仓跟踪!$S$2:$S$497)),0)),0)*AN124)))) | AR124: =IF(A124="","",IF(OR(E124="",H124=""),"违规：第一批价格或股数缺失",IF(OR(AND(AK124="",AL124<>""),AND(AK124<>"",AL124="")),"违规：第二批价格与股数须成对填写",IF(OR(AND(AM124="",AN124<>""),AND(AM124<>"",AN124="")),"违规：第三批价格与股数须成对填写",IF(AND(OR(AM124<>"",AN124<>""),OR(AK124="",AL124="")),"违规：必须先完成第二批",IF(OR(H124<=0,H124<>INT(H124),MOD(H124,100)<>0,AND(AL124<>"",OR(AL124<=0,AL124<>INT(AL124),MOD(AL124,100)<>0)),AND(AN124<>"",OR(AN124<=0,AN124<>INT(AN124),MOD(AN124,100)<>0))),"违规：股数须为100股整数倍",IF(AND(OR(AL124<>"",AN124<>""),OR(_LockStatus="已锁仓",_LockStatus="解锁信息不完整")),"违规：锁仓期间禁止加仓",IF(AQ124>C124*D124,"违规：超过单笔风险上限",IF(SUM($AQ$2:$AQ$201)>账户数据!$B$7,"违规：超过账户风险上限","通过")))))))))
F125: =IF(OR(C125="",D125="",E125="",N125="",C125<=0,D125<=0,E125<=N125),"",ROUNDDOWN((C125*D125)/(E125-N125)/100,0)*100) | G125: =IF(A125="","",IF(H125<>"","已开仓",IF(账户数据!$B$23="已锁仓","禁止开仓：连续亏损达到上限",IF(账户数据!$B$23="解锁信息不完整","禁止开仓：请完整填写解锁信息",IF(OR(F125="",E125="",N125="",E125<=N125,账户数据!$B$7=""),"",IF(OR(AG125="",AH125="",AI125=""),"禁止开仓：交易预期未填写完整",IF(COUNTIFS(持仓跟踪!$A$2:$A$497,"止损计划",持仓跟踪!$B$2:$B$497,A125,持仓跟踪!$AC$2:$AC$497,"计划有效")=0,"禁止开仓：请先填写止损计划",IF(账户数据!$B$9+F125*(E125-N125)>=账户数据!$B$7,"禁止开仓：风险额度不足",IF(AJ125="周期与交易预期不匹配，请重新确认",IF(账户数据!$B$23="接近锁仓","允许开仓（接近锁仓；周期需复核）","允许开仓（周期需复核）"),IF(账户数据!$B$23="接近锁仓","允许开仓（接近锁仓）","允许开仓")))))))))) | K125: =IF(A125="","",IFERROR(LOOKUP(2,1/((持仓跟踪!$B$2:$B$497=A125)*(持仓跟踪!$X$2:$X$497="执行卖出")*(持仓跟踪!$Y$2:$Y$497<>"")),持仓跟踪!$Y$2:$Y$497),"")) | L125: =IF(A125="","",IFERROR(LOOKUP(2,1/((持仓跟踪!$B$2:$B$497=A125)*(持仓跟踪!$X$2:$X$497="执行卖出")*(持仓跟踪!$Z$2:$Z$497<>"")),持仓跟踪!$Z$2:$Z$497),"")) | M125: =IF(A125="","",IFERROR(LOOKUP(2,1/((持仓跟踪!$B$2:$B$497=A125)*(持仓跟踪!$X$2:$X$497="执行卖出")*(持仓跟踪!$H$2:$H$497<>"")),持仓跟踪!$H$2:$H$497),"")) | P125: =IF(A125="","",IFERROR(LOOKUP(2,1/((持仓跟踪!$B$2:$B$497=A125)*(持仓跟踪!$X$2:$X$497="执行卖出")*(持仓跟踪!$AA$2:$AA$497<>"")),持仓跟踪!$AA$2:$AA$497),"")) | U125: =IF(OR(AO125="",J125="",AO125<=0),"",(J125-AO125)/AO125) | V125: =IF(OR(AO125="",N125="",AO125<=0),"",(AO125-N125)/AO125) | W125: =IF(OR(U125="",V125="",V125<=0),"",U125/V125) | X125: =IF(OR(K125="",L125="",AP125=""),"",K125*L125-(E125*H125+IF(AND(AK125<>"",AL125<>""),AK125*AL125,0)+IF(AND(AM125<>"",AN125<>""),AM125*AN125,0))-IF(O125="",0,O125)-IF(P125="",0,P125)) | Y125: =IF(OR(X125="",AP125=""),"",IF((E125*H125+IF(AND(AK125<>"",AL125<>""),AK125*AL125,0)+IF(AND(AM125<>"",AN125<>""),AM125*AN125,0))+IF(O125="",0,O125)<=0,"",X125/((E125*H125+IF(AND(AK125<>"",AL125<>""),AK125*AL125,0)+IF(AND(AM125<>"",AN125<>""),AM125*AN125,0))+IF(O125="",0,O125)))) | Z125: =IF(OR(AE125="",多次统计数据!$B$8=""),"",AE125-多次统计数据!$B$8) | AA125: =IF(OR(I125="",M125="",M125<I125),"",M125-I125) | AB125: =IF(OR(A125="",多次统计数据!$B$8="",多次统计数据!$B$6<=0,多次统计数据!$B$6>=1),"",1-POWER(1+多次统计数据!$B$8,-多次统计数据!$B$6/(1-多次统计数据!$B$6))) | AC125: =IF(OR(AB125="",多次统计数据!$B$9=""),"",IF(多次统计数据!$B$9<AB125,"低于上限","达到或超过上限")) | AE125: =IF(OR(X125="",C125="",C125<=0),"",X125/C125) | AJ125: =IF(OR(AG125="",AH125=""),"",IF(OR(AND(AG125="短期博反弹",OR(AH125="1～3个交易日",AH125="4～10个交易日")),AND(AG125="突破冲新高",OR(AH125="4～10个交易日",AH125="11～20个交易日")),AND(AG125="趋势波段",OR(AH125="11～20个交易日",AH125="21～60个交易日",AH125="60个交易日以上"))),"匹配","周期与交易预期不匹配，请重新确认")) | AO125: =IF(OR(A125="",H125="",H125<=0),"",(E125*H125+IF(AND(AK125<>"",AL125<>""),AK125*AL125,0)+IF(AND(AM125<>"",AN125<>""),AM125*AN125,0))/AP125) | AP125: =IF(OR(A125="",H125="",H125<=0),"",H125+IF(AL125="",0,AL125)+IF(AN125="",0,AN125)) | AQ125: =IF(A125="","",IF(M125<>"",0,IF(OR(H125="",N125=""),"",MAX(E125-MAX(N125,IFERROR(SUMPRODUCT(MAX(((持仓跟踪!$A$2:$A$497="每日跟踪")*(持仓跟踪!$B$2:$B$497=A125))*持仓跟踪!$S$2:$S$497)),0)),0)*H125+IF(OR(AK125="",AL125=""),0,MAX(AK125-MAX(N125,IFERROR(SUMPRODUCT(MAX(((持仓跟踪!$A$2:$A$497="每日跟踪")*(持仓跟踪!$B$2:$B$497=A125))*持仓跟踪!$S$2:$S$497)),0)),0)*AL125)+IF(OR(AM125="",AN125=""),0,MAX(AM125-MAX(N125,IFERROR(SUMPRODUCT(MAX(((持仓跟踪!$A$2:$A$497="每日跟踪")*(持仓跟踪!$B$2:$B$497=A125))*持仓跟踪!$S$2:$S$497)),0)),0)*AN125)))) | AR125: =IF(A125="","",IF(OR(E125="",H125=""),"违规：第一批价格或股数缺失",IF(OR(AND(AK125="",AL125<>""),AND(AK125<>"",AL125="")),"违规：第二批价格与股数须成对填写",IF(OR(AND(AM125="",AN125<>""),AND(AM125<>"",AN125="")),"违规：第三批价格与股数须成对填写",IF(AND(OR(AM125<>"",AN125<>""),OR(AK125="",AL125="")),"违规：必须先完成第二批",IF(OR(H125<=0,H125<>INT(H125),MOD(H125,100)<>0,AND(AL125<>"",OR(AL125<=0,AL125<>INT(AL125),MOD(AL125,100)<>0)),AND(AN125<>"",OR(AN125<=0,AN125<>INT(AN125),MOD(AN125,100)<>0))),"违规：股数须为100股整数倍",IF(AND(OR(AL125<>"",AN125<>""),OR(_LockStatus="已锁仓",_LockStatus="解锁信息不完整")),"违规：锁仓期间禁止加仓",IF(AQ125>C125*D125,"违规：超过单笔风险上限",IF(SUM($AQ$2:$AQ$201)>账户数据!$B$7,"违规：超过账户风险上限","通过")))))))))
F126: =IF(OR(C126="",D126="",E126="",N126="",C126<=0,D126<=0,E126<=N126),"",ROUNDDOWN((C126*D126)/(E126-N126)/100,0)*100) | G126: =IF(A126="","",IF(H126<>"","已开仓",IF(账户数据!$B$23="已锁仓","禁止开仓：连续亏损达到上限",IF(账户数据!$B$23="解锁信息不完整","禁止开仓：请完整填写解锁信息",IF(OR(F126="",E126="",N126="",E126<=N126,账户数据!$B$7=""),"",IF(OR(AG126="",AH126="",AI126=""),"禁止开仓：交易预期未填写完整",IF(COUNTIFS(持仓跟踪!$A$2:$A$497,"止损计划",持仓跟踪!$B$2:$B$497,A126,持仓跟踪!$AC$2:$AC$497,"计划有效")=0,"禁止开仓：请先填写止损计划",IF(账户数据!$B$9+F126*(E126-N126)>=账户数据!$B$7,"禁止开仓：风险额度不足",IF(AJ126="周期与交易预期不匹配，请重新确认",IF(账户数据!$B$23="接近锁仓","允许开仓（接近锁仓；周期需复核）","允许开仓（周期需复核）"),IF(账户数据!$B$23="接近锁仓","允许开仓（接近锁仓）","允许开仓")))))))))) | K126: =IF(A126="","",IFERROR(LOOKUP(2,1/((持仓跟踪!$B$2:$B$497=A126)*(持仓跟踪!$X$2:$X$497="执行卖出")*(持仓跟踪!$Y$2:$Y$497<>"")),持仓跟踪!$Y$2:$Y$497),"")) | L126: =IF(A126="","",IFERROR(LOOKUP(2,1/((持仓跟踪!$B$2:$B$497=A126)*(持仓跟踪!$X$2:$X$497="执行卖出")*(持仓跟踪!$Z$2:$Z$497<>"")),持仓跟踪!$Z$2:$Z$497),"")) | M126: =IF(A126="","",IFERROR(LOOKUP(2,1/((持仓跟踪!$B$2:$B$497=A126)*(持仓跟踪!$X$2:$X$497="执行卖出")*(持仓跟踪!$H$2:$H$497<>"")),持仓跟踪!$H$2:$H$497),"")) | P126: =IF(A126="","",IFERROR(LOOKUP(2,1/((持仓跟踪!$B$2:$B$497=A126)*(持仓跟踪!$X$2:$X$497="执行卖出")*(持仓跟踪!$AA$2:$AA$497<>"")),持仓跟踪!$AA$2:$AA$497),"")) | U126: =IF(OR(AO126="",J126="",AO126<=0),"",(J126-AO126)/AO126) | V126: =IF(OR(AO126="",N126="",AO126<=0),"",(AO126-N126)/AO126) | W126: =IF(OR(U126="",V126="",V126<=0),"",U126/V126) | X126: =IF(OR(K126="",L126="",AP126=""),"",K126*L126-(E126*H126+IF(AND(AK126<>"",AL126<>""),AK126*AL126,0)+IF(AND(AM126<>"",AN126<>""),AM126*AN126,0))-IF(O126="",0,O126)-IF(P126="",0,P126)) | Y126: =IF(OR(X126="",AP126=""),"",IF((E126*H126+IF(AND(AK126<>"",AL126<>""),AK126*AL126,0)+IF(AND(AM126<>"",AN126<>""),AM126*AN126,0))+IF(O126="",0,O126)<=0,"",X126/((E126*H126+IF(AND(AK126<>"",AL126<>""),AK126*AL126,0)+IF(AND(AM126<>"",AN126<>""),AM126*AN126,0))+IF(O126="",0,O126)))) | Z126: =IF(OR(AE126="",多次统计数据!$B$8=""),"",AE126-多次统计数据!$B$8) | AA126: =IF(OR(I126="",M126="",M126<I126),"",M126-I126) | AB126: =IF(OR(A126="",多次统计数据!$B$8="",多次统计数据!$B$6<=0,多次统计数据!$B$6>=1),"",1-POWER(1+多次统计数据!$B$8,-多次统计数据!$B$6/(1-多次统计数据!$B$6))) | AC126: =IF(OR(AB126="",多次统计数据!$B$9=""),"",IF(多次统计数据!$B$9<AB126,"低于上限","达到或超过上限")) | AE126: =IF(OR(X126="",C126="",C126<=0),"",X126/C126) | AJ126: =IF(OR(AG126="",AH126=""),"",IF(OR(AND(AG126="短期博反弹",OR(AH126="1～3个交易日",AH126="4～10个交易日")),AND(AG126="突破冲新高",OR(AH126="4～10个交易日",AH126="11～20个交易日")),AND(AG126="趋势波段",OR(AH126="11～20个交易日",AH126="21～60个交易日",AH126="60个交易日以上"))),"匹配","周期与交易预期不匹配，请重新确认")) | AO126: =IF(OR(A126="",H126="",H126<=0),"",(E126*H126+IF(AND(AK126<>"",AL126<>""),AK126*AL126,0)+IF(AND(AM126<>"",AN126<>""),AM126*AN126,0))/AP126) | AP126: =IF(OR(A126="",H126="",H126<=0),"",H126+IF(AL126="",0,AL126)+IF(AN126="",0,AN126)) | AQ126: =IF(A126="","",IF(M126<>"",0,IF(OR(H126="",N126=""),"",MAX(E126-MAX(N126,IFERROR(SUMPRODUCT(MAX(((持仓跟踪!$A$2:$A$497="每日跟踪")*(持仓跟踪!$B$2:$B$497=A126))*持仓跟踪!$S$2:$S$497)),0)),0)*H126+IF(OR(AK126="",AL126=""),0,MAX(AK126-MAX(N126,IFERROR(SUMPRODUCT(MAX(((持仓跟踪!$A$2:$A$497="每日跟踪")*(持仓跟踪!$B$2:$B$497=A126))*持仓跟踪!$S$2:$S$497)),0)),0)*AL126)+IF(OR(AM126="",AN126=""),0,MAX(AM126-MAX(N126,IFERROR(SUMPRODUCT(MAX(((持仓跟踪!$A$2:$A$497="每日跟踪")*(持仓跟踪!$B$2:$B$497=A126))*持仓跟踪!$S$2:$S$497)),0)),0)*AN126)))) | AR126: =IF(A126="","",IF(OR(E126="",H126=""),"违规：第一批价格或股数缺失",IF(OR(AND(AK126="",AL126<>""),AND(AK126<>"",AL126="")),"违规：第二批价格与股数须成对填写",IF(OR(AND(AM126="",AN126<>""),AND(AM126<>"",AN126="")),"违规：第三批价格与股数须成对填写",IF(AND(OR(AM126<>"",AN126<>""),OR(AK126="",AL126="")),"违规：必须先完成第二批",IF(OR(H126<=0,H126<>INT(H126),MOD(H126,100)<>0,AND(AL126<>"",OR(AL126<=0,AL126<>INT(AL126),MOD(AL126,100)<>0)),AND(AN126<>"",OR(AN126<=0,AN126<>INT(AN126),MOD(AN126,100)<>0))),"违规：股数须为100股整数倍",IF(AND(OR(AL126<>"",AN126<>""),OR(_LockStatus="已锁仓",_LockStatus="解锁信息不完整")),"违规：锁仓期间禁止加仓",IF(AQ126>C126*D126,"违规：超过单笔风险上限",IF(SUM($AQ$2:$AQ$201)>账户数据!$B$7,"违规：超过账户风险上限","通过")))))))))
... F165: =IF(OR(C165="",D165="",E165="",N165="",C165<=0,D165<=0,E165<=N165),"",ROUNDDOWN((C165*D165)/(E165-N165)/100,0)*100) | G165: =IF(A165="","",IF(H165<>"","已开仓",IF(账户数据!$B$23="已锁仓","禁止开仓：连续亏损达到上限",IF(账户数据!$B$23="解锁信息不完整","禁止开仓：请完整填写解锁信息",IF(OR(F165="",E165="",N165="",E165<=N165,账户数据!$B$7=""),"",IF(OR(AG165="",AH165="",AI165=""),"禁止开仓：交易预期未填写完整",IF(COUNTIFS(持仓跟踪!$A$2:$A$497,"止损计划",持仓跟踪!$B$2:$B$497,A165,持仓跟踪!$AC$2:$AC$497,"计划有效")=0,"禁止开仓：请先填写止损计划",IF(账户数据!$B$9+F165*(E165-N165)>=账户数据!$B$7,"禁止开仓：风险额度不足",IF(AJ165="周期与交易预期不匹配，请重新确认",IF(账户数据!$B$23="接近锁仓","允许开仓（接近锁仓；周期需复核）","允许开仓（周期需复核）"),IF(账户数据!$B$23="接近锁仓","允许开仓（接近锁仓）","允许开仓")))))))))) | K165: =IF(A165="","",IFERROR(LOOKUP(2,1/((持仓跟踪!$B$2:$B$497=A165)*(持仓跟踪!$X$2:$X$497="执行卖出")*(持仓跟踪!$Y$2:$Y$497<>"")),持仓跟踪!$Y$2:$Y$497),"")) | L165: =IF(A165="","",IFERROR(LOOKUP(2,1/((持仓跟踪!$B$2:$B$497=A165)*(持仓跟踪!$X$2:$X$497="执行卖出")*(持仓跟踪!$Z$2:$Z$497<>"")),持仓跟踪!$Z$2:$Z$497),"")) | M165: =IF(A165="","",IFERROR(LOOKUP(2,1/((持仓跟踪!$B$2:$B$497=A165)*(持仓跟踪!$X$2:$X$497="执行卖出")*(持仓跟踪!$H$2:$H$497<>"")),持仓跟踪!$H$2:$H$497),"")) | P165: =IF(A165="","",IFERROR(LOOKUP(2,1/((持仓跟踪!$B$2:$B$497=A165)*(持仓跟踪!$X$2:$X$497="执行卖出")*(持仓跟踪!$AA$2:$AA$497<>"")),持仓跟踪!$AA$2:$AA$497),"")) | U165: =IF(OR(AO165="",J165="",AO165<=0),"",(J165-AO165)/AO165) | V165: =IF(OR(AO165="",N165="",AO165<=0),"",(AO165-N165)/AO165) | W165: =IF(OR(U165="",V165="",V165<=0),"",U165/V165) | X165: =IF(OR(K165="",L165="",AP165=""),"",K165*L165-(E165*H165+IF(AND(AK165<>"",AL165<>""),AK165*AL165,0)+IF(AND(AM165<>"",AN165<>""),AM165*AN165,0))-IF(O165="",0,O165)-IF(P165="",0,P165)) | Y165: =IF(OR(X165="",AP165=""),"",IF((E165*H165+IF(AND(AK165<>"",AL165<>""),AK165*AL165,0)+IF(AND(AM165<>"",AN165<>""),AM165*AN165,0))+IF(O165="",0,O165)<=0,"",X165/((E165*H165+IF(AND(AK165<>"",AL165<>""),AK165*AL165,0)+IF(AND(AM165<>"",AN165<>""),AM165*AN165,0))+IF(O165="",0,O165)))) | Z165: =IF(OR(AE165="",多次统计数据!$B$8=""),"",AE165-多次统计数据!$B$8) | AA165: =IF(OR(I165="",M165="",M165<I165),"",M165-I165) | AB165: =IF(OR(A165="",多次统计数据!$B$8="",多次统计数据!$B$6<=0,多次统计数据!$B$6>=1),"",1-POWER(1+多次统计数据!$B$8,-多次统计数据!$B$6/(1-多次统计数据!$B$6))) | AC165: =IF(OR(AB165="",多次统计数据!$B$9=""),"",IF(多次统计数据!$B$9<AB165,"低于上限","达到或超过上限")) | AE165: =IF(OR(X165="",C165="",C165<=0),"",X165/C165) | AJ165: =IF(OR(AG165="",AH165=""),"",IF(OR(AND(AG165="短期博反弹",OR(AH165="1～3个交易日",AH165="4～10个交易日")),AND(AG165="突破冲新高",OR(AH165="4～10个交易日",AH165="11～20个交易日")),AND(AG165="趋势波段",OR(AH165="11～20个交易日",AH165="21～60个交易日",AH165="60个交易日以上"))),"匹配","周期与交易预期不匹配，请重新确认")) | AO165: =IF(OR(A165="",H165="",H165<=0),"",(E165*H165+IF(AND(AK165<>"",AL165<>""),AK165*AL165,0)+IF(AND(AM165<>"",AN165<>""),AM165*AN165,0))/AP165) | AP165: =IF(OR(A165="",H165="",H165<=0),"",H165+IF(AL165="",0,AL165)+IF(AN165="",0,AN165)) | AQ165: =IF(A165="","",IF(M165<>"",0,IF(OR(H165="",N165=""),"",MAX(E165-MAX(N165,IFERROR(SUMPRODUCT(MAX(((持仓跟踪!$A$2:$A$497="每日跟踪")*(持仓跟踪!$B$2:$B$497=A165))*持仓跟踪!$S$2:$S$497)),0)),0)*H165+IF(OR(AK165="",AL165=""),0,MAX(AK165-MAX(N165,IFERROR(SUMPRODUCT(MAX(((持仓跟踪!$A$2:$A$497="每日跟踪")*(持仓跟踪!$B$2:$B$497=A165))*持仓跟踪!$S$2:$S$497)),0)),0)*AL165)+IF(OR(AM165="",AN165=""),0,MAX(AM165-MAX(N165,IFERROR(SUMPRODUCT(MAX(((持仓跟踪!$A$2:$A$497="每日跟踪")*(持仓跟踪!$B$2:$B$497=A165))*持仓跟踪!$S$2:$S$497)),0)),0)*AN165)))) | AR165: =IF(A165="","",IF(OR(E165="",H165=""),"违规：第一批价格或股数缺失",IF(OR(AND(AK165="",AL165<>""),AND(AK165<>"",AL165="")),"违规：第二批价格与股数须成对填写",IF(OR(AND(AM165="",AN165<>""),AND(AM165<>"",AN165="")),"违规：第三批价格与股数须成对填写",IF(AND(OR(AM165<>"",AN165<>""),OR(AK165="",AL165="")),"违规：必须先完成第二批",IF(OR(H165<=0,H165<>INT(H165),MOD(H165,100)<>0,AND(AL165<>"",OR(AL165<=0,AL165<>INT(AL165),MOD(AL165,100)<>0)),AND(AN165<>"",OR(AN165<=0,AN165<>INT(AN165),MOD(AN165,100)<>0))),"违规：股数须为100股整数倍",IF(AND(OR(AL165<>"",AN165<>""),OR(_LockStatus="已锁仓",_LockStatus="解锁信息不完整")),"违规：锁仓期间禁止加仓",IF(AQ165>C165*D165,"违规：超过单笔风险上限",IF(SUM($AQ$2:$AQ$201)>账户数据!$B$7,"违规：超过账户风险上限","通过")))))))))
A166: 1 | B166: 沪电股份 | C166: 100000 | D166: 0.02 | E166: 5.11 | F166: =IF(OR(C166="",D166="",E166="",N166="",C166<=0,D166<=0,E166<=N166),"",ROUNDDOWN((C166*D166)/(E166-N166)/100,0)*100) -> 3200 | G166: =IF(A166="","",IF(H166<>"","已开仓",IF(账户数据!$B$23="已锁仓","禁止开仓：连续亏损达到上限",IF(账户数据!$B$23="解锁信息不完整","禁止开仓：请完整填写解锁信息",IF(OR(F166="",E166="",N166="",E166<=N166,账户数据!$B$7=""),"",IF(OR(AG166="",AH166="",AI166=""),"禁止开仓：交易预期未填写完整",IF(COUNTIFS(持仓跟踪!$A$2:$A$497,"止损计划",持仓跟踪!$B$2:$B$497,A166,持仓跟踪!$AC$2:$AC$497,"计划有效")=0,"禁止开仓：请先填写止损计划",IF(账户数据!$B$9+F166*(E166-N166)>=账户数据!$B$7,"禁止开仓：风险额度不足",IF(AJ166="周期与交易预期不匹配，请重新确认",IF(账户数据!$B$23="接近锁仓","允许开仓（接近锁仓；周期需复核）","允许开仓（周期需复核）"),IF(账户数据!$B$23="接近锁仓","允许开仓（接近锁仓）","允许开仓")))))))))) -> 已开仓 | H166: 3200 | I166: 43420 | J166: 6 | K166: 4.41 | L166: 3200 | M166: 43424 | N166: 4.5 | P166: =IF(A166="","",IFERROR(LOOKUP(2,1/((持仓跟踪!$B$2:$B$497=A166)*(持仓跟踪!$X$2:$X$497="执行卖出")*(持仓跟踪!$AA$2:$AA$497<>"")),持仓跟踪!$AA$2:$AA$497),"")) | U166: =IF(OR(AO166="",J166="",AO166<=0),"",(J166-AO166)/AO166) -> 0.1741683 | V166: =IF(OR(AO166="",N166="",AO166<=0),"",(AO166-N166)/AO166) -> 0.11937378 | W166: =IF(OR(U166="",V166="",V166<=0),"",U166/V166) -> 1.4590164 | X166: =IF(OR(K166="",L166="",AP166=""),"",K166*L166-(E166*H166+IF(AND(AK166<>"",AL166<>""),AK166*AL166,0)+IF(AND(AM166<>"",AN166<>""),AM166*AN166,0))-IF(O166="",0,O166)-IF(P166="",0,P166)) -> -2240 | Y166: =IF(OR(X166="",AP166=""),"",IF((E166*H166+IF(AND(AK166<>"",AL166<>""),AK166*AL166,0)+IF(AND(AM166<>"",AN166<>""),AM166*AN166,0))+IF(O166="",0,O166)<=0,"",X166/((E166*H166+IF(AND(AK166<>"",AL166<>""),AK166*AL166,0)+IF(AND(AM166<>"",AN166<>""),AM166*AN166,0))+IF(O166="",0,O166)))) -> -0.1369863 | Z166: =IF(OR(AE166="",多次统计数据!$B$8=""),"",AE166-多次统计数据!$B$8) -> -0.079520605 | AA166: =IF(OR(I166="",M166="",M166<I166),"",M166-I166) -> 4 | AB166: =IF(OR(A166="",多次统计数据!$B$8="",多次统计数据!$B$6<=0,多次统计数据!$B$6>=1),"",1-POWER(1+多次统计数据!$B$8,-多次统计数据!$B$6/(1-多次统计数据!$B$6))) -> 0.043466093 | AC166: =IF(OR(AB166="",多次统计数据!$B$9=""),"",IF(多次统计数据!$B$9<AB166,"低于上限","达到或超过上限")) -> 低于上限 | AE166: =IF(OR(X166="",C166="",C166<=0),"",X166/C166) -> -0.0224 | AJ166: =IF(OR(AG166="",AH166=""),"",IF(OR(AND(AG166="短期博反弹",OR(AH166="1～3个交易日",AH166="4～10个交易日")),AND(AG166="突破冲新高",OR(AH166="4～10个交易日",AH166="11～20个交易日")),AND(AG166="趋势波段",OR(AH166="11～20个交易日",AH166="21～60个交易日",AH166="60个交易日以上"))),"匹配","周期与交易预期不匹配，请重新确认")) | AO166: =IF(OR(A166="",H166="",H166<=0),"",(E166*H166+IF(AND(AK166<>"",AL166<>""),AK166*AL166,0)+IF(AND(AM166<>"",AN166<>""),AM166*AN166,0))/AP166) -> 5.11 | AP166: =IF(OR(A166="",H166="",H166<=0),"",H166+IF(AL166="",0,AL166)+IF(AN166="",0,AN166)) -> 3200 | AQ166: =IF(A166="","",IF(M166<>"",0,IF(OR(H166="",N166=""),"",MAX(E166-MAX(N166,IFERROR(SUMPRODUCT(MAX(((持仓跟踪!$A$2:$A$497="每日跟踪")*(持仓跟踪!$B$2:$B$497=A166))*持仓跟踪!$S$2:$S$497)),0)),0)*H166+IF(OR(AK166="",AL166=""),0,MAX(AK166-MAX(N166,IFERROR(SUMPRODUCT(MAX(((持仓跟踪!$A$2:$A$497="每日跟踪")*(持仓跟踪!$B$2:$B$497=A166))*持仓跟踪!$S$2:$S$497)),0)),0)*AL166)+IF(OR(AM166="",AN166=""),0,MAX(AM166-MAX(N166,IFERROR(SUMPRODUCT(MAX(((持仓跟踪!$A$2:$A$497="每日跟踪")*(持仓跟踪!$B$2:$B$497=A166))*持仓跟踪!$S$2:$S$497)),0)),0)*AN166)))) -> 0 | AR166: =IF(A166="","",IF(OR(E166="",H166=""),"违规：第一批价格或股数缺失",IF(OR(AND(AK166="",AL166<>""),AND(AK166<>"",AL166="")),"违规：第二批价格与股数须成对填写",IF(OR(AND(AM166="",AN166<>""),AND(AM166<>"",AN166="")),"违规：第三批价格与股数须成对填写",IF(AND(OR(AM166<>"",AN166<>""),OR(AK166="",AL166="")),"违规：必须先完成第二批",IF(OR(H166<=0,H166<>INT(H166),MOD(H166,100)<>0,AND(AL166<>"",OR(AL166<=0,AL166<>INT(AL166),MOD(AL166,100)<>0)),AND(AN166<>"",OR(AN166<=0,AN166<>INT(AN166),MOD(AN166,100)<>0))),"违规：股数须为100股整数倍",IF(AND(OR(AL166<>"",AN166<>""),OR(_LockStatus="已锁仓",_LockStatus="解锁信息不完整")),"违规：锁仓期间禁止加仓",IF(AQ166>C166*D166,"违规：超过单笔风险上限",IF(SUM($AQ$2:$AQ$201)>账户数据!$B$7,"违规：超过账户风险上限","通过"))))))))) -> 通过
A167: 2 | B167: 沪电股份 | C167: 97760 | D167: 0.02 | E167: 4.87 | F167: =IF(OR(C167="",D167="",E167="",N167="",C167<=0,D167<=0,E167<=N167),"",ROUNDDOWN((C167*D167)/(E167-N167)/100,0)*100) -> 5200 | G167: =IF(A167="","",IF(H167<>"","已开仓",IF(账户数据!$B$23="已锁仓","禁止开仓：连续亏损达到上限",IF(账户数据!$B$23="解锁信息不完整","禁止开仓：请完整填写解锁信息",IF(OR(F167="",E167="",N167="",E167<=N167,账户数据!$B$7=""),"",IF(OR(AG167="",AH167="",AI167=""),"禁止开仓：交易预期未填写完整",IF(COUNTIFS(持仓跟踪!$A$2:$A$497,"止损计划",持仓跟踪!$B$2:$B$497,A167,持仓跟踪!$AC$2:$AC$497,"计划有效")=0,"禁止开仓：请先填写止损计划",IF(账户数据!$B$9+F167*(E167-N167)>=账户数据!$B$7,"禁止开仓：风险额度不足",IF(AJ167="周期与交易预期不匹配，请重新确认",IF(账户数据!$B$23="接近锁仓","允许开仓（接近锁仓；周期需复核）","允许开仓（周期需复核）"),IF(账户数据!$B$23="接近锁仓","允许开仓（接近锁仓）","允许开仓")))))))))) -> 已开仓 | H167: 5200 | I167: 43479 | J167: 5.5 | K167: 7.84 | L167: 5200 | M167: 43521 | N167: 4.5 | P167: =IF(A167="","",IFERROR(LOOKUP(2,1/((持仓跟踪!$B$2:$B$497=A167)*(持仓跟踪!$X$2:$X$497="执行卖出")*(持仓跟踪!$AA$2:$AA$497<>"")),持仓跟踪!$AA$2:$AA$497),"")) | U167: =IF(OR(AO167="",J167="",AO167<=0),"",(J167-AO167)/AO167) -> 0.12936345 | V167: =IF(OR(AO167="",N167="",AO167<=0),"",(AO167-N167)/AO167) -> 0.075975359 | W167: =IF(OR(U167="",V167="",V167<=0),"",U167/V167) -> 1.7027027 | X167: =IF(OR(K167="",L167="",AP167=""),"",K167*L167-(E167*H167+IF(AND(AK167<>"",AL167<>""),AK167*AL167,0)+IF(AND(AM167<>"",AN167<>""),AM167*AN167,0))-IF(O167="",0,O167)-IF(P167="",0,P167)) -> 15444 | Y167: =IF(OR(X167="",AP167=""),"",IF((E167*H167+IF(AND(AK167<>"",AL167<>""),AK167*AL167,0)+IF(AND(AM167<>"",AN167<>""),AM167*AN167,0))+IF(O167="",0,O167)<=0,"",X167/((E167*H167+IF(AND(AK167<>"",AL167<>""),AK167*AL167,0)+IF(AND(AM167<>"",AN167<>""),AM167*AN167,0))+IF(O167="",0,O167)))) -> 0.60985626 | Z167: =IF(OR(AE167="",多次统计数据!$B$8=""),"",AE167-多次统计数据!$B$8) -> 0.10085812 | AA167: =IF(OR(I167="",M167="",M167<I167),"",M167-I167) -> 42 | AB167: =IF(OR(A167="",多次统计数据!$B$8="",多次统计数据!$B$6<=0,多次统计数据!$B$6>=1),"",1-POWER(1+多次统计数据!$B$8,-多次统计数据!$B$6/(1-多次统计数据!$B$6))) -> 0.043466093 | AC167: =IF(OR(AB167="",多次统计数据!$B$9=""),"",IF(多次统计数据!$B$9<AB167,"低于上限","达到或超过上限")) -> 低于上限 | AE167: =IF(OR(X167="",C167="",C167<=0),"",X167/C167) -> 0.15797872 | AJ167: =IF(OR(AG167="",AH167=""),"",IF(OR(AND(AG167="短期博反弹",OR(AH167="1～3个交易日",AH167="4～10个交易日")),AND(AG167="突破冲新高",OR(AH167="4～10个交易日",AH167="11～20个交易日")),AND(AG167="趋势波段",OR(AH167="11～20个交易日",AH167="21～60个交易日",AH167="60个交易日以上"))),"匹配","周期与交易预期不匹配，请重新确认")) | AO167: =IF(OR(A167="",H167="",H167<=0),"",(E167*H167+IF(AND(AK167<>"",AL167<>""),AK167*AL167,0)+IF(AND(AM167<>"",AN167<>""),AM167*AN167,0))/AP167) -> 4.87 | AP167: =IF(OR(A167="",H167="",H167<=0),"",H167+IF(AL167="",0,AL167)+IF(AN167="",0,AN167)) -> 5200 | AQ167: =IF(A167="","",IF(M167<>"",0,IF(OR(H167="",N167=""),"",MAX(E167-MAX(N167,IFERROR(SUMPRODUCT(MAX(((持仓跟踪!$A$2:$A$497="每日跟踪")*(持仓跟踪!$B$2:$B$497=A167))*持仓跟踪!$S$2:$S$497)),0)),0)*H167+IF(OR(AK167="",AL167=""),0,MAX(AK167-MAX(N167,IFERROR(SUMPRODUCT(MAX(((持仓跟踪!$A$2:$A$497="每日跟踪")*(持仓跟踪!$B$2:$B$497=A167))*持仓跟踪!$S$2:$S$497)),0)),0)*AL167)+IF(OR(AM167="",AN167=""),0,MAX(AM167-MAX(N167,IFERROR(SUMPRODUCT(MAX(((持仓跟踪!$A$2:$A$497="每日跟踪")*(持仓跟踪!$B$2:$B$497=A167))*持仓跟踪!$S$2:$S$497)),0)),0)*AN167)))) -> 0 | AR167: =IF(A167="","",IF(OR(E167="",H167=""),"违规：第一批价格或股数缺失",IF(OR(AND(AK167="",AL167<>""),AND(AK167<>"",AL167="")),"违规：第二批价格与股数须成对填写",IF(OR(AND(AM167="",AN167<>""),AND(AM167<>"",AN167="")),"违规：第三批价格与股数须成对填写",IF(AND(OR(AM167<>"",AN167<>""),OR(AK167="",AL167="")),"违规：必须先完成第二批",IF(OR(H167<=0,H167<>INT(H167),MOD(H167,100)<>0,AND(AL167<>"",OR(AL167<=0,AL167<>INT(AL167),MOD(AL167,100)<>0)),AND(AN167<>"",OR(AN167<=0,AN167<>INT(AN167),MOD(AN167,100)<>0))),"违规：股数须为100股整数倍",IF(AND(OR(AL167<>"",AN167<>""),OR(_LockStatus="已锁仓",_LockStatus="解锁信息不完整")),"违规：锁仓期间禁止加仓",IF(AQ167>C167*D167,"违规：超过单笔风险上限",IF(SUM($AQ$2:$AQ$201)>账户数据!$B$7,"违规：超过账户风险上限","通过"))))))))) -> 通过
A168: 3 | B168: 沪电股份 | C168: 113204 | D168: 0.02 | E168: 20.45 | F168: =IF(OR(C168="",D168="",E168="",N168="",C168<=0,D168<=0,E168<=N168),"",ROUNDDOWN((C168*D168)/(E168-N168)/100,0)*100) -> 1800 | G168: =IF(A168="","",IF(H168<>"","已开仓",IF(账户数据!$B$23="已锁仓","禁止开仓：连续亏损达到上限",IF(账户数据!$B$23="解锁信息不完整","禁止开仓：请完整填写解锁信息",IF(OR(F168="",E168="",N168="",E168<=N168,账户数据!$B$7=""),"",IF(OR(AG168="",AH168="",AI168=""),"禁止开仓：交易预期未填写完整",IF(COUNTIFS(持仓跟踪!$A$2:$A$497,"止损计划",持仓跟踪!$B$2:$B$497,A168,持仓跟踪!$AC$2:$AC$497,"计划有效")=0,"禁止开仓：请先填写止损计划",IF(账户数据!$B$9+F168*(E168-N168)>=账户数据!$B$7,"禁止开仓：风险额度不足",IF(AJ168="周期与交易预期不匹配，请重新确认",IF(账户数据!$B$23="接近锁仓","允许开仓（接近锁仓；周期需复核）","允许开仓（周期需复核）"),IF(账户数据!$B$23="接近锁仓","允许开仓（接近锁仓）","允许开仓")))))))))) -> 已开仓 | H168: 1800 | I168: 43487 | J168: 22 | K168: 17.45 | L168: 1800 | M168: 43864 | N168: 19.2 | P168: =IF(A168="","",IFERROR(LOOKUP(2,1/((持仓跟踪!$B$2:$B$497=A168)*(持仓跟踪!$X$2:$X$497="执行卖出")*(持仓跟踪!$AA$2:$AA$497<>"")),持仓跟踪!$AA$2:$AA$497),"")) | U168: =IF(OR(AO168="",J168="",AO168<=0),"",(J168-AO168)/AO168) -> 0.075794621 | V168: =IF(OR(AO168="",N168="",AO168<=0),"",(AO168-N168)/AO168) -> 0.061124694 | W168: =IF(OR(U168="",V168="",V168<=0),"",U168/V168) -> 1.24 | X168: =IF(OR(K168="",L168="",AP168=""),"",K168*L168-(E168*H168+IF(AND(AK168<>"",AL168<>""),AK168*AL168,0)+IF(AND(AM168<>"",AN168<>""),AM168*AN168,0))-IF(O168="",0,O168)-IF(P168="",0,P168)) -> -5400 | Y168: =IF(OR(X168="",AP168=""),"",IF((E168*H168+IF(AND(AK168<>"",AL168<>""),AK168*AL168,0)+IF(AND(AM168<>"",AN168<>""),AM168*AN168,0))+IF(O168="",0,O168)<=0,"",X168/((E168*H168+IF(AND(AK168<>"",AL168<>""),AK168*AL168,0)+IF(AND(AM168<>"",AN168<>""),AM168*AN168,0))+IF(O168="",0,O168)))) -> -0.14669927 | Z168: =IF(OR(AE168="",多次统计数据!$B$8=""),"",AE168-多次统计数据!$B$8) -> -0.1048221 | AA168: =IF(OR(I168="",M168="",M168<I168),"",M168-I168) -> 377 | AB168: =IF(OR(A168="",多次统计数据!$B$8="",多次统计数据!$B$6<=0,多次统计数据!$B$6>=1),"",1-POWER(1+多次统计数据!$B$8,-多次统计数据!$B$6/(1-多次统计数据!$B$6))) -> 0.043466093 | AC168: =IF(OR(AB168="",多次统计数据!$B$9=""),"",IF(多次统计数据!$B$9<AB168,"低于上限","达到或超过上限")) -> 低于上限 | AE168: =IF(OR(X168="",C168="",C168<=0),"",X168/C168) -> -0.047701495 | AJ168: =IF(OR(AG168="",AH168=""),"",IF(OR(AND(AG168="短期博反弹",OR(AH168="1～3个交易日",AH168="4～10个交易日")),AND(AG168="突破冲新高",OR(AH168="4～10个交易日",AH168="11～20个交易日")),AND(AG168="趋势波段",OR(AH168="11～20个交易日",AH168="21～60个交易日",AH168="60个交易日以上"))),"匹配","周期与交易预期不匹配，请重新确认")) | AO168: =IF(OR(A168="",H168="",H168<=0),"",(E168*H168+IF(AND(AK168<>"",AL168<>""),AK168*AL168,0)+IF(AND(AM168<>"",AN168<>""),AM168*AN168,0))/AP168) -> 20.45 | AP168: =IF(OR(A168="",H168="",H168<=0),"",H168+IF(AL168="",0,AL168)+IF(AN168="",0,AN168)) -> 1800 | AQ168: =IF(A168="","",IF(M168<>"",0,IF(OR(H168="",N168=""),"",MAX(E168-MAX(N168,IFERROR(SUMPRODUCT(MAX(((持仓跟踪!$A$2:$A$497="每日跟踪")*(持仓跟踪!$B$2:$B$497=A168))*持仓跟踪!$S$2:$S$497)),0)),0)*H168+IF(OR(AK168="",AL168=""),0,MAX(AK168-MAX(N168,IFERROR(SUMPRODUCT(MAX(((持仓跟踪!$A$2:$A$497="每日跟踪")*(持仓跟踪!$B$2:$B$497=A168))*持仓跟踪!$S$2:$S$497)),0)),0)*AL168)+IF(OR(AM168="",AN168=""),0,MAX(AM168-MAX(N168,IFERROR(SUMPRODUCT(MAX(((持仓跟踪!$A$2:$A$497="每日跟踪")*(持仓跟踪!$B$2:$B$497=A168))*持仓跟踪!$S$2:$S$497)),0)),0)*AN168)))) -> 0 | AR168: =IF(A168="","",IF(OR(E168="",H168=""),"违规：第一批价格或股数缺失",IF(OR(AND(AK168="",AL168<>""),AND(AK168<>"",AL168="")),"违规：第二批价格与股数须成对填写",IF(OR(AND(AM168="",AN168<>""),AND(AM168<>"",AN168="")),"违规：第三批价格与股数须成对填写",IF(AND(OR(AM168<>"",AN168<>""),OR(AK168="",AL168="")),"违规：必须先完成第二批",IF(OR(H168<=0,H168<>INT(H168),MOD(H168,100)<>0,AND(AL168<>"",OR(AL168<=0,AL168<>INT(AL168),MOD(AL168,100)<>0)),AND(AN168<>"",OR(AN168<=0,AN168<>INT(AN168),MOD(AN168,100)<>0))),"违规：股数须为100股整数倍",IF(AND(OR(AL168<>"",AN168<>""),OR(_LockStatus="已锁仓",_LockStatus="解锁信息不完整")),"违规：锁仓期间禁止加仓",IF(AQ168>C168*D168,"违规：超过单笔风险上限",IF(SUM($AQ$2:$AQ$201)>账户数据!$B$7,"违规：超过账户风险上限","通过"))))))))) -> 通过
A169: 4 | B169: 沪电股份 | C169: 107804 | D169: 0.02 | E169: 20.97 | F169: =IF(OR(C169="",D169="",E169="",N169="",C169<=0,D169<=0,E169<=N169),"",ROUNDDOWN((C169*D169)/(E169-N169)/100,0)*100) -> 2200 | G169: =IF(A169="","",IF(H169<>"","已开仓",IF(账户数据!$B$23="已锁仓","禁止开仓：连续亏损达到上限",IF(账户数据!$B$23="解锁信息不完整","禁止开仓：请完整填写解锁信息",IF(OR(F169="",E169="",N169="",E169<=N169,账户数据!$B$7=""),"",IF(OR(AG169="",AH169="",AI169=""),"禁止开仓：交易预期未填写完整",IF(COUNTIFS(持仓跟踪!$A$2:$A$497,"止损计划",持仓跟踪!$B$2:$B$497,A169,持仓跟踪!$AC$2:$AC$497,"计划有效")=0,"禁止开仓：请先填写止损计划",IF(账户数据!$B$9+F169*(E169-N169)>=账户数据!$B$7,"禁止开仓：风险额度不足",IF(AJ169="周期与交易预期不匹配，请重新确认",IF(账户数据!$B$23="接近锁仓","允许开仓（接近锁仓；周期需复核）","允许开仓（周期需复核）"),IF(账户数据!$B$23="接近锁仓","允许开仓（接近锁仓）","允许开仓")))))))))) -> 已开仓 | H169: 2200 | I169: 43882 | J169: 23 | K169: 23.65 | L169: 2200 | M169: 43893 | N169: 20 | P169: =IF(A169="","",IFERROR(LOOKUP(2,1/((持仓跟踪!$B$2:$B$497=A169)*(持仓跟踪!$X$2:$X$497="执行卖出")*(持仓跟踪!$AA$2:$AA$497<>"")),持仓跟踪!$AA$2:$AA$497),"")) | U169: =IF(OR(AO169="",J169="",AO169<=0),"",(J169-AO169)/AO169) -> 0.096804959 | V169: =IF(OR(AO169="",N169="",AO169<=0),"",(AO169-N169)/AO169) -> 0.046256557 | W169: =IF(OR(U169="",V169="",V169<=0),"",U169/V169) -> 2.0927835 | X169: =IF(OR(K169="",L169="",AP169=""),"",K169*L169-(E169*H169+IF(AND(AK169<>"",AL169<>""),AK169*AL169,0)+IF(AND(AM169<>"",AN169<>""),AM169*AN169,0))-IF(O169="",0,O169)-IF(P169="",0,P169)) -> 5896 | Y169: =IF(OR(X169="",AP169=""),"",IF((E169*H169+IF(AND(AK169<>"",AL169<>""),AK169*AL169,0)+IF(AND(AM169<>"",AN169<>""),AM169*AN169,0))+IF(O169="",0,O169)<=0,"",X169/((E169*H169+IF(AND(AK169<>"",AL169<>""),AK169*AL169,0)+IF(AND(AM169<>"",AN169<>""),AM169*AN169,0))+IF(O169="",0,O169)))) -> 0.12780162 | Z169: =IF(OR(AE169="",多次统计数据!$B$8=""),"",AE169-多次统计数据!$B$8) -> -0.0024287572 | AA169: =IF(OR(I169="",M169="",M169<I169),"",M169-I169) -> 11 | AB169: =IF(OR(A169="",多次统计数据!$B$8="",多次统计数据!$B$6<=0,多次统计数据!$B$6>=1),"",1-POWER(1+多次统计数据!$B$8,-多次统计数据!$B$6/(1-多次统计数据!$B$6))) -> 0.043466093 | AC169: =IF(OR(AB169="",多次统计数据!$B$9=""),"",IF(多次统计数据!$B$9<AB169,"低于上限","达到或超过上限")) -> 低于上限 | AE169: =IF(OR(X169="",C169="",C169<=0),"",X169/C169) -> 0.054691848 | AJ169: =IF(OR(AG169="",AH169=""),"",IF(OR(AND(AG169="短期博反弹",OR(AH169="1～3个交易日",AH169="4～10个交易日")),AND(AG169="突破冲新高",OR(AH169="4～10个交易日",AH169="11～20个交易日")),AND(AG169="趋势波段",OR(AH169="11～20个交易日",AH169="21～60个交易日",AH169="60个交易日以上"))),"匹配","周期与交易预期不匹配，请重新确认")) | AO169: =IF(OR(A169="",H169="",H169<=0),"",(E169*H169+IF(AND(AK169<>"",AL169<>""),AK169*AL169,0)+IF(AND(AM169<>"",AN169<>""),AM169*AN169,0))/AP169) -> 20.97 | AP169: =IF(OR(A169="",H169="",H169<=0),"",H169+IF(AL169="",0,AL169)+IF(AN169="",0,AN169)) -> 2200 | AQ169: =IF(A169="","",IF(M169<>"",0,IF(OR(H169="",N169=""),"",MAX(E169-MAX(N169,IFERROR(SUMPRODUCT(MAX(((持仓跟踪!$A$2:$A$497="每日跟踪")*(持仓跟踪!$B$2:$B$497=A169))*持仓跟踪!$S$2:$S$497)),0)),0)*H169+IF(OR(AK169="",AL169=""),0,MAX(AK169-MAX(N169,IFERROR(SUMPRODUCT(MAX(((持仓跟踪!$A$2:$A$497="每日跟踪")*(持仓跟踪!$B$2:$B$497=A169))*持仓跟踪!$S$2:$S$497)),0)),0)*AL169)+IF(OR(AM169="",AN169=""),0,MAX(AM169-MAX(N169,IFERROR(SUMPRODUCT(MAX(((持仓跟踪!$A$2:$A$497="每日跟踪")*(持仓跟踪!$B$2:$B$497=A169))*持仓跟踪!$S$2:$S$497)),0)),0)*AN169)))) -> 0 | AR169: =IF(A169="","",IF(OR(E169="",H169=""),"违规：第一批价格或股数缺失",IF(OR(AND(AK169="",AL169<>""),AND(AK169<>"",AL169="")),"违规：第二批价格与股数须成对填写",IF(OR(AND(AM169="",AN169<>""),AND(AM169<>"",AN169="")),"违规：第三批价格与股数须成对填写",IF(AND(OR(AM169<>"",AN169<>""),OR(AK169="",AL169="")),"违规：必须先完成第二批",IF(OR(H169<=0,H169<>INT(H169),MOD(H169,100)<>0,AND(AL169<>"",OR(AL169<=0,AL169<>INT(AL169),MOD(AL169,100)<>0)),AND(AN169<>"",OR(AN169<=0,AN169<>INT(AN169),MOD(AN169,100)<>0))),"违规：股数须为100股整数倍",IF(AND(OR(AL169<>"",AN169<>""),OR(_LockStatus="已锁仓",_LockStatus="解锁信息不完整")),"违规：锁仓期间禁止加仓",IF(AQ169>C169*D169,"违规：超过单笔风险上限",IF(SUM($AQ$2:$AQ$201)>账户数据!$B$7,"违规：超过账户风险上限","通过"))))))))) -> 通过
A170: 5 | B170: 沪电股份 | C170: 113700 | D170: 0.02 | E170: 22.61 | F170: =IF(OR(C170="",D170="",E170="",N170="",C170<=0,D170<=0,E170<=N170),"",ROUNDDOWN((C170*D170)/(E170-N170)/100,0)*100) -> 1400 | G170: =IF(A170="","",IF(H170<>"","已开仓",IF(账户数据!$B$23="已锁仓","禁止开仓：连续亏损达到上限",IF(账户数据!$B$23="解锁信息不完整","禁止开仓：请完整填写解锁信息",IF(OR(F170="",E170="",N170="",E170<=N170,账户数据!$B$7=""),"",IF(OR(AG170="",AH170="",AI170=""),"禁止开仓：交易预期未填写完整",IF(COUNTIFS(持仓跟踪!$A$2:$A$497,"止损计划",持仓跟踪!$B$2:$B$497,A170,持仓跟踪!$AC$2:$AC$497,"计划有效")=0,"禁止开仓：请先填写止损计划",IF(账户数据!$B$9+F170*(E170-N170)>=账户数据!$B$7,"禁止开仓：风险额度不足",IF(AJ170="周期与交易预期不匹配，请重新确认",IF(账户数据!$B$23="接近锁仓","允许开仓（接近锁仓；周期需复核）","允许开仓（周期需复核）"),IF(账户数据!$B$23="接近锁仓","允许开仓（接近锁仓）","允许开仓")))))))))) -> 已开仓 | H170: 1400 | I170: 43896 | J170: 25 | K170: 19.42 | L170: 1400 | M170: 43920 | N170: 21 | P170: =IF(A170="","",IFERROR(LOOKUP(2,1/((持仓跟踪!$B$2:$B$497=A170)*(持仓跟踪!$X$2:$X$497="执行卖出")*(持仓跟踪!$AA$2:$AA$497<>"")),持仓跟踪!$AA$2:$AA$497),"")) | U170: =IF(OR(AO170="",J170="",AO170<=0),"",(J170-AO170)/AO170) -> 0.10570544 | V170: =IF(OR(AO170="",N170="",AO170<=0),"",(AO170-N170)/AO170) -> 0.07120743 | W170: =IF(OR(U170="",V170="",V170<=0),"",U170/V170) -> 1.484472 | X170: =IF(OR(K170="",L170="",AP170=""),"",K170*L170-(E170*H170+IF(AND(AK170<>"",AL170<>""),AK170*AL170,0)+IF(AND(AM170<>"",AN170<>""),AM170*AN170,0))-IF(O170="",0,O170)-IF(P170="",0,P170)) -> -4466 | Y170: =IF(OR(X170="",AP170=""),"",IF((E170*H170+IF(AND(AK170<>"",AL170<>""),AK170*AL170,0)+IF(AND(AM170<>"",AN170<>""),AM170*AN170,0))+IF(O170="",0,O170)<=0,"",X170/((E170*H170+IF(AND(AK170<>"",AL170<>""),AK170*AL170,0)+IF(AND(AM170<>"",AN170<>""),AM170*AN170,0))+IF(O170="",0,O170)))) -> -0.14108801 | Z170: =IF(OR(AE170="",多次统计数据!$B$8=""),"",AE170-多次统计数据!$B$8) -> -0.096399409 | AA170: =IF(OR(I170="",M170="",M170<I170),"",M170-I170) -> 24 | AB170: =IF(OR(A170="",多次统计数据!$B$8="",多次统计数据!$B$6<=0,多次统计数据!$B$6>=1),"",1-POWER(1+多次统计数据!$B$8,-多次统计数据!$B$6/(1-多次统计数据!$B$6))) -> 0.043466093 | AC170: =IF(OR(AB170="",多次统计数据!$B$9=""),"",IF(多次统计数据!$B$9<AB170,"低于上限","达到或超过上限")) -> 低于上限 | AE170: =IF(OR(X170="",C170="",C170<=0),"",X170/C170) -> -0.039278804 | AJ170: =IF(OR(AG170="",AH170=""),"",IF(OR(AND(AG170="短期博反弹",OR(AH170="1～3个交易日",AH170="4～10个交易日")),AND(AG170="突破冲新高",OR(AH170="4～10个交易日",AH170="11～20个交易日")),AND(AG170="趋势波段",OR(AH170="11～20个交易日",AH170="21～60个交易日",AH170="60个交易日以上"))),"匹配","周期与交易预期不匹配，请重新确认")) | AO170: =IF(OR(A170="",H170="",H170<=0),"",(E170*H170+IF(AND(AK170<>"",AL170<>""),AK170*AL170,0)+IF(AND(AM170<>"",AN170<>""),AM170*AN170,0))/AP170) -> 22.61 | AP170: =IF(OR(A170="",H170="",H170<=0),"",H170+IF(AL170="",0,AL170)+IF(AN170="",0,AN170)) -> 1400 | AQ170: =IF(A170="","",IF(M170<>"",0,IF(OR(H170="",N170=""),"",MAX(E170-MAX(N170,IFERROR(SUMPRODUCT(MAX(((持仓跟踪!$A$2:$A$497="每日跟踪")*(持仓跟踪!$B$2:$B$497=A170))*持仓跟踪!$S$2:$S$497)),0)),0)*H170+IF(OR(AK170="",AL170=""),0,MAX(AK170-MAX(N170,IFERROR(SUMPRODUCT(MAX(((持仓跟踪!$A$2:$A$497="每日跟踪")*(持仓跟踪!$B$2:$B$497=A170))*持仓跟踪!$S$2:$S$497)),0)),0)*AL170)+IF(OR(AM170="",AN170=""),0,MAX(AM170-MAX(N170,IFERROR(SUMPRODUCT(MAX(((持仓跟踪!$A$2:$A$497="每日跟踪")*(持仓跟踪!$B$2:$B$497=A170))*持仓跟踪!$S$2:$S$497)),0)),0)*AN170)))) -> 0 | AR170: =IF(A170="","",IF(OR(E170="",H170=""),"违规：第一批价格或股数缺失",IF(OR(AND(AK170="",AL170<>""),AND(AK170<>"",AL170="")),"违规：第二批价格与股数须成对填写",IF(OR(AND(AM170="",AN170<>""),AND(AM170<>"",AN170="")),"违规：第三批价格与股数须成对填写",IF(AND(OR(AM170<>"",AN170<>""),OR(AK170="",AL170="")),"违规：必须先完成第二批",IF(OR(H170<=0,H170<>INT(H170),MOD(H170,100)<>0,AND(AL170<>"",OR(AL170<=0,AL170<>INT(AL170),MOD(AL170,100)<>0)),AND(AN170<>"",OR(AN170<=0,AN170<>INT(AN170),MOD(AN170,100)<>0))),"违规：股数须为100股整数倍",IF(AND(OR(AL170<>"",AN170<>""),OR(_LockStatus="已锁仓",_LockStatus="解锁信息不完整")),"违规：锁仓期间禁止加仓",IF(AQ170>C170*D170,"违规：超过单笔风险上限",IF(SUM($AQ$2:$AQ$201)>账户数据!$B$7,"违规：超过账户风险上限","通过"))))))))) -> 通过
A171: 6 | B171: 沪电股份 | C171: 109234 | D171: 0.02 | E171: 23.1 | F171: =IF(OR(C171="",D171="",E171="",N171="",C171<=0,D171<=0,E171<=N171),"",ROUNDDOWN((C171*D171)/(E171-N171)/100,0)*100) -> 1900 | G171: =IF(A171="","",IF(H171<>"","已开仓",IF(账户数据!$B$23="已锁仓","禁止开仓：连续亏损达到上限",IF(账户数据!$B$23="解锁信息不完整","禁止开仓：请完整填写解锁信息",IF(OR(F171="",E171="",N171="",E171<=N171,账户数据!$B$7=""),"",IF(OR(AG171="",AH171="",AI171=""),"禁止开仓：交易预期未填写完整",IF(COUNTIFS(持仓跟踪!$A$2:$A$497,"止损计划",持仓跟踪!$B$2:$B$497,A171,持仓跟踪!$AC$2:$AC$497,"计划有效")=0,"禁止开仓：请先填写止损计划",IF(账户数据!$B$9+F171*(E171-N171)>=账户数据!$B$7,"禁止开仓：风险额度不足",IF(AJ171="周期与交易预期不匹配，请重新确认",IF(账户数据!$B$23="接近锁仓","允许开仓（接近锁仓；周期需复核）","允许开仓（周期需复核）"),IF(账户数据!$B$23="接近锁仓","允许开仓（接近锁仓）","允许开仓")))))))))) -> 已开仓 | H171: 1900 | I171: 43957 | J171: 25 | K171: 20.75 | L171: 1900 | M171: 43969 | N171: 22 | P171: =IF(A171="","",IFERROR(LOOKUP(2,1/((持仓跟踪!$B$2:$B$497=A171)*(持仓跟踪!$X$2:$X$497="执行卖出")*(持仓跟踪!$AA$2:$AA$497<>"")),持仓跟踪!$AA$2:$AA$497),"")) | U171: =IF(OR(AO171="",J171="",AO171<=0),"",(J171-AO171)/AO171) -> 0.082251082 | V171: =IF(OR(AO171="",N171="",AO171<=0),"",(AO171-N171)/AO171) -> 0.047619048 | W171: =IF(OR(U171="",V171="",V171<=0),"",U171/V171) -> 1.7272727 | X171: =IF(OR(K171="",L171="",AP171=""),"",K171*L171-(E171*H171+IF(AND(AK171<>"",AL171<>""),AK171*AL171,0)+IF(AND(AM171<>"",AN171<>""),AM171*AN171,0))-IF(O171="",0,O171)-IF(P171="",0,P171)) -> -4465 | Y171: =IF(OR(X171="",AP171=""),"",IF((E171*H171+IF(AND(AK171<>"",AL171<>""),AK171*AL171,0)+IF(AND(AM171<>"",AN171<>""),AM171*AN171,0))+IF(O171="",0,O171)<=0,"",X171/((E171*H171+IF(AND(AK171<>"",AL171<>""),AK171*AL171,0)+IF(AND(AM171<>"",AN171<>""),AM171*AN171,0))+IF(O171="",0,O171)))) -> -0.1017316 | Z171: =IF(OR(AE171="",多次统计数据!$B$8=""),"",AE171-多次统计数据!$B$8) -> -0.097996157 | AA171: =IF(OR(I171="",M171="",M171<I171),"",M171-I171) -> 12 | AB171: =IF(OR(A171="",多次统计数据!$B$8="",多次统计数据!$B$6<=0,多次统计数据!$B$6>=1),"",1-POWER(1+多次统计数据!$B$8,-多次统计数据!$B$6/(1-多次统计数据!$B$6))) -> 0.043466093 | AC171: =IF(OR(AB171="",多次统计数据!$B$9=""),"",IF(多次统计数据!$B$9<AB171,"低于上限","达到或超过上限")) -> 低于上限 | AE171: =IF(OR(X171="",C171="",C171<=0),"",X171/C171) -> -0.040875552 | AJ171: =IF(OR(AG171="",AH171=""),"",IF(OR(AND(AG171="短期博反弹",OR(AH171="1～3个交易日",AH171="4～10个交易日")),AND(AG171="突破冲新高",OR(AH171="4～10个交易日",AH171="11～20个交易日")),AND(AG171="趋势波段",OR(AH171="11～20个交易日",AH171="21～60个交易日",AH171="60个交易日以上"))),"匹配","周期与交易预期不匹配，请重新确认")) | AO171: =IF(OR(A171="",H171="",H171<=0),"",(E171*H171+IF(AND(AK171<>"",AL171<>""),AK171*AL171,0)+IF(AND(AM171<>"",AN171<>""),AM171*AN171,0))/AP171) -> 23.1 | AP171: =IF(OR(A171="",H171="",H171<=0),"",H171+IF(AL171="",0,AL171)+IF(AN171="",0,AN171)) -> 1900 | AQ171: =IF(A171="","",IF(M171<>"",0,IF(OR(H171="",N171=""),"",MAX(E171-MAX(N171,IFERROR(SUMPRODUCT(MAX(((持仓跟踪!$A$2:$A$497="每日跟踪")*(持仓跟踪!$B$2:$B$497=A171))*持仓跟踪!$S$2:$S$497)),0)),0)*H171+IF(OR(AK171="",AL171=""),0,MAX(AK171-MAX(N171,IFERROR(SUMPRODUCT(MAX(((持仓跟踪!$A$2:$A$497="每日跟踪")*(持仓跟踪!$B$2:$B$497=A171))*持仓跟踪!$S$2:$S$497)),0)),0)*AL171)+IF(OR(AM171="",AN171=""),0,MAX(AM171-MAX(N171,IFERROR(SUMPRODUCT(MAX(((持仓跟踪!$A$2:$A$497="每日跟踪")*(持仓跟踪!$B$2:$B$497=A171))*持仓跟踪!$S$2:$S$497)),0)),0)*AN171)))) -> 0 | AR171: =IF(A171="","",IF(OR(E171="",H171=""),"违规：第一批价格或股数缺失",IF(OR(AND(AK171="",AL171<>""),AND(AK171<>"",AL171="")),"违规：第二批价格与股数须成对填写",IF(OR(AND(AM171="",AN171<>""),AND(AM171<>"",AN171="")),"违规：第三批价格与股数须成对填写",IF(AND(OR(AM171<>"",AN171<>""),OR(AK171="",AL171="")),"违规：必须先完成第二批",IF(OR(H171<=0,H171<>INT(H171),MOD(H171,100)<>0,AND(AL171<>"",OR(AL171<=0,AL171<>INT(AL171),MOD(AL171,100)<>0)),AND(AN171<>"",OR(AN171<=0,AN171<>INT(AN171),MOD(AN171,100)<>0))),"违规：股数须为100股整数倍",IF(AND(OR(AL171<>"",AN171<>""),OR(_LockStatus="已锁仓",_LockStatus="解锁信息不完整")),"违规：锁仓期间禁止加仓",IF(AQ171>C171*D171,"违规：超过单笔风险上限",IF(SUM($AQ$2:$AQ$201)>账户数据!$B$7,"违规：超过账户风险上限","通过"))))))))) -> 通过
A172: 7 | B172: 沪电股份 | C172: 104769 | D172: 0.02 | E172: 22.2 | F172: =IF(OR(C172="",D172="",E172="",N172="",C172<=0,D172<=0,E172<=N172),"",ROUNDDOWN((C172*D172)/(E172-N172)/100,0)*100) -> 1700 | G172: =IF(A172="","",IF(H172<>"","已开仓",IF(账户数据!$B$23="已锁仓","禁止开仓：连续亏损达到上限",IF(账户数据!$B$23="解锁信息不完整","禁止开仓：请完整填写解锁信息",IF(OR(F172="",E172="",N172="",E172<=N172,账户数据!$B$7=""),"",IF(OR(AG172="",AH172="",AI172=""),"禁止开仓：交易预期未填写完整",IF(COUNTIFS(持仓跟踪!$A$2:$A$497,"止损计划",持仓跟踪!$B$2:$B$497,A172,持仓跟踪!$AC$2:$AC$497,"计划有效")=0,"禁止开仓：请先填写止损计划",IF(账户数据!$B$9+F172*(E172-N172)>=账户数据!$B$7,"禁止开仓：风险额度不足",IF(AJ172="周期与交易预期不匹配，请重新确认",IF(账户数据!$B$23="接近锁仓","允许开仓（接近锁仓；周期需复核）","允许开仓（周期需复核）"),IF(账户数据!$B$23="接近锁仓","允许开仓（接近锁仓）","允许开仓")))))))))) -> 已开仓 | H172: 1700 | I172: 44018 | J172: 25 | K172: 19.94 | L172: 1700 | M172: 44028 | N172: 21 | P172: =IF(A172="","",IFERROR(LOOKUP(2,1/((持仓跟踪!$B$2:$B$497=A172)*(持仓跟踪!$X$2:$X$497="执行卖出")*(持仓跟踪!$AA$2:$AA$497<>"")),持仓跟踪!$AA$2:$AA$497),"")) | U172: =IF(OR(AO172="",J172="",AO172<=0),"",(J172-AO172)/AO172) -> 0.12612613 | V172: =IF(OR(AO172="",N172="",AO172<=0),"",(AO172-N172)/AO172) -> 0.054054054 | W172: =IF(OR(U172="",V172="",V172<=0),"",U172/V172) -> 2.3333333 | X172: =IF(OR(K172="",L172="",AP172=""),"",K172*L172-(E172*H172+IF(AND(AK172<>"",AL172<>""),AK172*AL172,0)+IF(AND(AM172<>"",AN172<>""),AM172*AN172,0))-IF(O172="",0,O172)-IF(P172="",0,P172)) -> -3842 | Y172: =IF(OR(X172="",AP172=""),"",IF((E172*H172+IF(AND(AK172<>"",AL172<>""),AK172*AL172,0)+IF(AND(AM172<>"",AN172<>""),AM172*AN172,0))+IF(O172="",0,O172)<=0,"",X172/((E172*H172+IF(AND(AK172<>"",AL172<>""),AK172*AL172,0)+IF(AND(AM172<>"",AN172<>""),AM172*AN172,0))+IF(O172="",0,O172)))) -> -0.1018018 | Z172: =IF(OR(AE172="",多次统计数据!$B$8=""),"",AE172-多次统计数据!$B$8) -> -0.093791758 | AA172: =IF(OR(I172="",M172="",M172<I172),"",M172-I172) -> 10 | AB172: =IF(OR(A172="",多次统计数据!$B$8="",多次统计数据!$B$6<=0,多次统计数据!$B$6>=1),"",1-POWER(1+多次统计数据!$B$8,-多次统计数据!$B$6/(1-多次统计数据!$B$6))) -> 0.043466093 | AC172: =IF(OR(AB172="",多次统计数据!$B$9=""),"",IF(多次统计数据!$B$9<AB172,"低于上限","达到或超过上限")) -> 低于上限 | AE172: =IF(OR(X172="",C172="",C172<=0),"",X172/C172) -> -0.036671153 | AJ172: =IF(OR(AG172="",AH172=""),"",IF(OR(AND(AG172="短期博反弹",OR(AH172="1～3个交易日",AH172="4～10个交易日")),AND(AG172="突破冲新高",OR(AH172="4～10个交易日",AH172="11～20个交易日")),AND(AG172="趋势波段",OR(AH172="11～20个交易日",AH172="21～60个交易日",AH172="60个交易日以上"))),"匹配","周期与交易预期不匹配，请重新确认")) | AO172: =IF(OR(A172="",H172="",H172<=0),"",(E172*H172+IF(AND(AK172<>"",AL172<>""),AK172*AL172,0)+IF(AND(AM172<>"",AN172<>""),AM172*AN172,0))/AP172) -> 22.2 | AP172: =IF(OR(A172="",H172="",H172<=0),"",H172+IF(AL172="",0,AL172)+IF(AN172="",0,AN172)) -> 1700 | AQ172: =IF(A172="","",IF(M172<>"",0,IF(OR(H172="",N172=""),"",MAX(E172-MAX(N172,IFERROR(SUMPRODUCT(MAX(((持仓跟踪!$A$2:$A$497="每日跟踪")*(持仓跟踪!$B$2:$B$497=A172))*持仓跟踪!$S$2:$S$497)),0)),0)*H172+IF(OR(AK172="",AL172=""),0,MAX(AK172-MAX(N172,IFERROR(SUMPRODUCT(MAX(((持仓跟踪!$A$2:$A$497="每日跟踪")*(持仓跟踪!$B$2:$B$497=A172))*持仓跟踪!$S$2:$S$497)),0)),0)*AL172)+IF(OR(AM172="",AN172=""),0,MAX(AM172-MAX(N172,IFERROR(SUMPRODUCT(MAX(((持仓跟踪!$A$2:$A$497="每日跟踪")*(持仓跟踪!$B$2:$B$497=A172))*持仓跟踪!$S$2:$S$497)),0)),0)*AN172)))) -> 0 | AR172: =IF(A172="","",IF(OR(E172="",H172=""),"违规：第一批价格或股数缺失",IF(OR(AND(AK172="",AL172<>""),AND(AK172<>"",AL172="")),"违规：第二批价格与股数须成对填写",IF(OR(AND(AM172="",AN172<>""),AND(AM172<>"",AN172="")),"违规：第三批价格与股数须成对填写",IF(AND(OR(AM172<>"",AN172<>""),OR(AK172="",AL172="")),"违规：必须先完成第二批",IF(OR(H172<=0,H172<>INT(H172),MOD(H172,100)<>0,AND(AL172<>"",OR(AL172<=0,AL172<>INT(AL172),MOD(AL172,100)<>0)),AND(AN172<>"",OR(AN172<=0,AN172<>INT(AN172),MOD(AN172,100)<>0))),"违规：股数须为100股整数倍",IF(AND(OR(AL172<>"",AN172<>""),OR(_LockStatus="已锁仓",_LockStatus="解锁信息不完整")),"违规：锁仓期间禁止加仓",IF(AQ172>C172*D172,"违规：超过单笔风险上限",IF(SUM($AQ$2:$AQ$201)>账户数据!$B$7,"违规：超过账户风险上限","通过"))))))))) -> 通过
A173: 8 | B173: 沪电股份 | C173: 100927 | D173: 0.02 | E173: 16.51 | F173: =IF(OR(C173="",D173="",E173="",N173="",C173<=0,D173<=0,E173<=N173),"",ROUNDDOWN((C173*D173)/(E173-N173)/100,0)*100) -> 3900 | G173: =IF(A173="","",IF(H173<>"","已开仓",IF(账户数据!$B$23="已锁仓","禁止开仓：连续亏损达到上限",IF(账户数据!$B$23="解锁信息不完整","禁止开仓：请完整填写解锁信息",IF(OR(F173="",E173="",N173="",E173<=N173,账户数据!$B$7=""),"",IF(OR(AG173="",AH173="",AI173=""),"禁止开仓：交易预期未填写完整",IF(COUNTIFS(持仓跟踪!$A$2:$A$497,"止损计划",持仓跟踪!$B$2:$B$497,A173,持仓跟踪!$AC$2:$AC$497,"计划有效")=0,"禁止开仓：请先填写止损计划",IF(账户数据!$B$9+F173*(E173-N173)>=账户数据!$B$7,"禁止开仓：风险额度不足",IF(AJ173="周期与交易预期不匹配，请重新确认",IF(账户数据!$B$23="接近锁仓","允许开仓（接近锁仓；周期需复核）","允许开仓（周期需复核）"),IF(账户数据!$B$23="接近锁仓","允许开仓（接近锁仓）","允许开仓")))))))))) -> 已开仓 | H173: 3900 | I173: 44076 | J173: 17.5 | K173: 16.57 | L173: 3900 | M173: 44168 | N173: 16 | P173: =IF(A173="","",IFERROR(LOOKUP(2,1/((持仓跟踪!$B$2:$B$497=A173)*(持仓跟踪!$X$2:$X$497="执行卖出")*(持仓跟踪!$AA$2:$AA$497<>"")),持仓跟踪!$AA$2:$AA$497),"")) | U173: =IF(OR(AO173="",J173="",AO173<=0),"",(J173-AO173)/AO173) -> 0.059963658 | V173: =IF(OR(AO173="",N173="",AO173<=0),"",(AO173-N173)/AO173) -> 0.030890369 | W173: =IF(OR(U173="",V173="",V173<=0),"",U173/V173) -> 1.9411765 | X173: =IF(OR(K173="",L173="",AP173=""),"",K173*L173-(E173*H173+IF(AND(AK173<>"",AL173<>""),AK173*AL173,0)+IF(AND(AM173<>"",AN173<>""),AM173*AN173,0))-IF(O173="",0,O173)-IF(P173="",0,P173)) -> 234 | Y173: =IF(OR(X173="",AP173=""),"",IF((E173*H173+IF(AND(AK173<>"",AL173<>""),AK173*AL173,0)+IF(AND(AM173<>"",AN173<>""),AM173*AN173,0))+IF(O173="",0,O173)<=0,"",X173/((E173*H173+IF(AND(AK173<>"",AL173<>""),AK173*AL173,0)+IF(AND(AM173<>"",AN173<>""),AM173*AN173,0))+IF(O173="",0,O173)))) -> 0.0036341611 | Z173: =IF(OR(AE173="",多次统计数据!$B$8=""),"",AE173-多次统计数据!$B$8) -> -0.054802098 | AA173: =IF(OR(I173="",M173="",M173<I173),"",M173-I173) -> 92 | AB173: =IF(OR(A173="",多次统计数据!$B$8="",多次统计数据!$B$6<=0,多次统计数据!$B$6>=1),"",1-POWER(1+多次统计数据!$B$8,-多次统计数据!$B$6/(1-多次统计数据!$B$6))) -> 0.043466093 | AC173: =IF(OR(AB173="",多次统计数据!$B$9=""),"",IF(多次统计数据!$B$9<AB173,"低于上限","达到或超过上限")) -> 低于上限 | AE173: =IF(OR(X173="",C173="",C173<=0),"",X173/C173) -> 0.0023185074 | AJ173: =IF(OR(AG173="",AH173=""),"",IF(OR(AND(AG173="短期博反弹",OR(AH173="1～3个交易日",AH173="4～10个交易日")),AND(AG173="突破冲新高",OR(AH173="4～10个交易日",AH173="11～20个交易日")),AND(AG173="趋势波段",OR(AH173="11～20个交易日",AH173="21～60个交易日",AH173="60个交易日以上"))),"匹配","周期与交易预期不匹配，请重新确认")) | AO173: =IF(OR(A173="",H173="",H173<=0),"",(E173*H173+IF(AND(AK173<>"",AL173<>""),AK173*AL173,0)+IF(AND(AM173<>"",AN173<>""),AM173*AN173,0))/AP173) -> 16.51 | AP173: =IF(OR(A173="",H173="",H173<=0),"",H173+IF(AL173="",0,AL173)+IF(AN173="",0,AN173)) -> 3900 | AQ173: =IF(A173="","",IF(M173<>"",0,IF(OR(H173="",N173=""),"",MAX(E173-MAX(N173,IFERROR(SUMPRODUCT(MAX(((持仓跟踪!$A$2:$A$497="每日跟踪")*(持仓跟踪!$B$2:$B$497=A173))*持仓跟踪!$S$2:$S$497)),0)),0)*H173+IF(OR(AK173="",AL173=""),0,MAX(AK173-MAX(N173,IFERROR(SUMPRODUCT(MAX(((持仓跟踪!$A$2:$A$497="每日跟踪")*(持仓跟踪!$B$2:$B$497=A173))*持仓跟踪!$S$2:$S$497)),0)),0)*AL173)+IF(OR(AM173="",AN173=""),0,MAX(AM173-MAX(N173,IFERROR(SUMPRODUCT(MAX(((持仓跟踪!$A$2:$A$497="每日跟踪")*(持仓跟踪!$B$2:$B$497=A173))*持仓跟踪!$S$2:$S$497)),0)),0)*AN173)))) -> 0 | AR173: =IF(A173="","",IF(OR(E173="",H173=""),"违规：第一批价格或股数缺失",IF(OR(AND(AK173="",AL173<>""),AND(AK173<>"",AL173="")),"违规：第二批价格与股数须成对填写",IF(OR(AND(AM173="",AN173<>""),AND(AM173<>"",AN173="")),"违规：第三批价格与股数须成对填写",IF(AND(OR(AM173<>"",AN173<>""),OR(AK173="",AL173="")),"违规：必须先完成第二批",IF(OR(H173<=0,H173<>INT(H173),MOD(H173,100)<>0,AND(AL173<>"",OR(AL173<=0,AL173<>INT(AL173),MOD(AL173,100)<>0)),AND(AN173<>"",OR(AN173<=0,AN173<>INT(AN173),MOD(AN173,100)<>0))),"违规：股数须为100股整数倍",IF(AND(OR(AL173<>"",AN173<>""),OR(_LockStatus="已锁仓",_LockStatus="解锁信息不完整")),"违规：锁仓期间禁止加仓",IF(AQ173>C173*D173,"违规：超过单笔风险上限",IF(SUM($AQ$2:$AQ$201)>账户数据!$B$7,"违规：超过账户风险上限","通过"))))))))) -> 通过
A174: 9 | B174: 沪电股份 | C174: 101161 | D174: 0.02 | E174: 15.57 | F174: =IF(OR(C174="",D174="",E174="",N174="",C174<=0,D174<=0,E174<=N174),"",ROUNDDOWN((C174*D174)/(E174-N174)/100,0)*100) -> 3500 | G174: =IF(A174="","",IF(H174<>"","已开仓",IF(账户数据!$B$23="已锁仓","禁止开仓：连续亏损达到上限",IF(账户数据!$B$23="解锁信息不完整","禁止开仓：请完整填写解锁信息",IF(OR(F174="",E174="",N174="",E174<=N174,账户数据!$B$7=""),"",IF(OR(AG174="",AH174="",AI174=""),"禁止开仓：交易预期未填写完整",IF(COUNTIFS(持仓跟踪!$A$2:$A$497,"止损计划",持仓跟踪!$B$2:$B$497,A174,持仓跟踪!$AC$2:$AC$497,"计划有效")=0,"禁止开仓：请先填写止损计划",IF(账户数据!$B$9+F174*(E174-N174)>=账户数据!$B$7,"禁止开仓：风险额度不足",IF(AJ174="周期与交易预期不匹配，请重新确认",IF(账户数据!$B$23="接近锁仓","允许开仓（接近锁仓；周期需复核）","允许开仓（周期需复核）"),IF(账户数据!$B$23="接近锁仓","允许开仓（接近锁仓）","允许开仓")))))))))) -> 已开仓 | H174: 3500 | I174: 44204 | J174: 16.5 | K174: 15.96 | L174: 3500 | M174: 44214 | N174: 15 | P174: =IF(A174="","",IFERROR(LOOKUP(2,1/((持仓跟踪!$B$2:$B$497=A174)*(持仓跟踪!$X$2:$X$497="执行卖出")*(持仓跟踪!$AA$2:$AA$497<>"")),持仓跟踪!$AA$2:$AA$497),"")) | U174: =IF(OR(AO174="",J174="",AO174<=0),"",(J174-AO174)/AO174) -> 0.05973025 | V174: =IF(OR(AO174="",N174="",AO174<=0),"",(AO174-N174)/AO174) -> 0.036608863 | W174: =IF(OR(U174="",V174="",V174<=0),"",U174/V174) -> 1.6315789 | X174: =IF(OR(K174="",L174="",AP174=""),"",K174*L174-(E174*H174+IF(AND(AK174<>"",AL174<>""),AK174*AL174,0)+IF(AND(AM174<>"",AN174<>""),AM174*AN174,0))-IF(O174="",0,O174)-IF(P174="",0,P174)) -> 1365 | Y174: =IF(OR(X174="",AP174=""),"",IF((E174*H174+IF(AND(AK174<>"",AL174<>""),AK174*AL174,0)+IF(AND(AM174<>"",AN174<>""),AM174*AN174,0))+IF(O174="",0,O174)<=0,"",X174/((E174*H174+IF(AND(AK174<>"",AL174<>""),AK174*AL174,0)+IF(AND(AM174<>"",AN174<>""),AM174*AN174,0))+IF(O174="",0,O174)))) -> 0.02504817 | Z174: =IF(OR(AE174="",多次统计数据!$B$8=""),"",AE174-多次统计数据!$B$8) -> -0.043627263 | AA174: =IF(OR(I174="",M174="",M174<I174),"",M174-I174) -> 10 | AB174: =IF(OR(A174="",多次统计数据!$B$8="",多次统计数据!$B$6<=0,多次统计数据!$B$6>=1),"",1-POWER(1+多次统计数据!$B$8,-多次统计数据!$B$6/(1-多次统计数据!$B$6))) -> 0.043466093 | AC174: =IF(OR(AB174="",多次统计数据!$B$9=""),"",IF(多次统计数据!$B$9<AB174,"低于上限","达到或超过上限")) -> 低于上限 | AE174: =IF(OR(X174="",C174="",C174<=0),"",X174/C174) -> 0.013493342 | AJ174: =IF(OR(AG174="",AH174=""),"",IF(OR(AND(AG174="短期博反弹",OR(AH174="1～3个交易日",AH174="4～10个交易日")),AND(AG174="突破冲新高",OR(AH174="4～10个交易日",AH174="11～20个交易日")),AND(AG174="趋势波段",OR(AH174="11～20个交易日",AH174="21～60个交易日",AH174="60个交易日以上"))),"匹配","周期与交易预期不匹配，请重新确认")) | AO174: =IF(OR(A174="",H174="",H174<=0),"",(E174*H174+IF(AND(AK174<>"",AL174<>""),AK174*AL174,0)+IF(AND(AM174<>"",AN174<>""),AM174*AN174,0))/AP174) -> 15.57 | AP174: =IF(OR(A174="",H174="",H174<=0),"",H174+IF(AL174="",0,AL174)+IF(AN174="",0,AN174)) -> 3500 | AQ174: =IF(A174="","",IF(M174<>"",0,IF(OR(H174="",N174=""),"",MAX(E174-MAX(N174,IFERROR(SUMPRODUCT(MAX(((持仓跟踪!$A$2:$A$497="每日跟踪")*(持仓跟踪!$B$2:$B$497=A174))*持仓跟踪!$S$2:$S$497)),0)),0)*H174+IF(OR(AK174="",AL174=""),0,MAX(AK174-MAX(N174,IFERROR(SUMPRODUCT(MAX(((持仓跟踪!$A$2:$A$497="每日跟踪")*(持仓跟踪!$B$2:$B$497=A174))*持仓跟踪!$S$2:$S$497)),0)),0)*AL174)+IF(OR(AM174="",AN174=""),0,MAX(AM174-MAX(N174,IFERROR(SUMPRODUCT(MAX(((持仓跟踪!$A$2:$A$497="每日跟踪")*(持仓跟踪!$B$2:$B$497=A174))*持仓跟踪!$S$2:$S$497)),0)),0)*AN174)))) -> 0 | AR174: =IF(A174="","",IF(OR(E174="",H174=""),"违规：第一批价格或股数缺失",IF(OR(AND(AK174="",AL174<>""),AND(AK174<>"",AL174="")),"违规：第二批价格与股数须成对填写",IF(OR(AND(AM174="",AN174<>""),AND(AM174<>"",AN174="")),"违规：第三批价格与股数须成对填写",IF(AND(OR(AM174<>"",AN174<>""),OR(AK174="",AL174="")),"违规：必须先完成第二批",IF(OR(H174<=0,H174<>INT(H174),MOD(H174,100)<>0,AND(AL174<>"",OR(AL174<=0,AL174<>INT(AL174),MOD(AL174,100)<>0)),AND(AN174<>"",OR(AN174<=0,AN174<>INT(AN174),MOD(AN174,100)<>0))),"违规：股数须为100股整数倍",IF(AND(OR(AL174<>"",AN174<>""),OR(_LockStatus="已锁仓",_LockStatus="解锁信息不完整")),"违规：锁仓期间禁止加仓",IF(AQ174>C174*D174,"违规：超过单笔风险上限",IF(SUM($AQ$2:$AQ$201)>账户数据!$B$7,"违规：超过账户风险上限","通过"))))))))) -> 通过
A175: 10 | B175: 沪电股份 | C175: 102526 | D175: 0.02 | E175: 14.96 | F175: =IF(OR(C175="",D175="",E175="",N175="",C175<=0,D175<=0,E175<=N175),"",ROUNDDOWN((C175*D175)/(E175-N175)/100,0)*100) -> 2600 | G175: =IF(A175="","",IF(H175<>"","已开仓",IF(账户数据!$B$23="已锁仓","禁止开仓：连续亏损达到上限",IF(账户数据!$B$23="解锁信息不完整","禁止开仓：请完整填写解锁信息",IF(OR(F175="",E175="",N175="",E175<=N175,账户数据!$B$7=""),"",IF(OR(AG175="",AH175="",AI175=""),"禁止开仓：交易预期未填写完整",IF(COUNTIFS(持仓跟踪!$A$2:$A$497,"止损计划",持仓跟踪!$B$2:$B$497,A175,持仓跟踪!$AC$2:$AC$497,"计划有效")=0,"禁止开仓：请先填写止损计划",IF(账户数据!$B$9+F175*(E175-N175)>=账户数据!$B$7,"禁止开仓：风险额度不足",IF(AJ175="周期与交易预期不匹配，请重新确认",IF(账户数据!$B$23="接近锁仓","允许开仓（接近锁仓；周期需复核）","允许开仓（周期需复核）"),IF(账户数据!$B$23="接近锁仓","允许开仓（接近锁仓）","允许开仓")))))))))) -> 已开仓 | H175: 2600 | I175: 44217 | K175: =IF(A175="","",IFERROR(LOOKUP(2,1/((持仓跟踪!$B$2:$B$497=A175)*(持仓跟踪!$X$2:$X$497="执行卖出")*(持仓跟踪!$Y$2:$Y$497<>"")),持仓跟踪!$Y$2:$Y$497),"")) | L175: =IF(A175="","",IFERROR(LOOKUP(2,1/((持仓跟踪!$B$2:$B$497=A175)*(持仓跟踪!$X$2:$X$497="执行卖出")*(持仓跟踪!$Z$2:$Z$497<>"")),持仓跟踪!$Z$2:$Z$497),"")) | M175: =IF(A175="","",IFERROR(LOOKUP(2,1/((持仓跟踪!$B$2:$B$497=A175)*(持仓跟踪!$X$2:$X$497="执行卖出")*(持仓跟踪!$H$2:$H$497<>"")),持仓跟踪!$H$2:$H$497),"")) | N175: 14.2 | P175: =IF(A175="","",IFERROR(LOOKUP(2,1/((持仓跟踪!$B$2:$B$497=A175)*(持仓跟踪!$X$2:$X$497="执行卖出")*(持仓跟踪!$AA$2:$AA$497<>"")),持仓跟踪!$AA$2:$AA$497),"")) | U175: =IF(OR(AO175="",J175="",AO175<=0),"",(J175-AO175)/AO175) | V175: =IF(OR(AO175="",N175="",AO175<=0),"",(AO175-N175)/AO175) -> 0.050802139 | W175: =IF(OR(U175="",V175="",V175<=0),"",U175/V175) | X175: =IF(OR(K175="",L175="",AP175=""),"",K175*L175-(E175*H175+IF(AND(AK175<>"",AL175<>""),AK175*AL175,0)+IF(AND(AM175<>"",AN175<>""),AM175*AN175,0))-IF(O175="",0,O175)-IF(P175="",0,P175)) | Y175: =IF(OR(X175="",AP175=""),"",IF((E175*H175+IF(AND(AK175<>"",AL175<>""),AK175*AL175,0)+IF(AND(AM175<>"",AN175<>""),AM175*AN175,0))+IF(O175="",0,O175)<=0,"",X175/((E175*H175+IF(AND(AK175<>"",AL175<>""),AK175*AL175,0)+IF(AND(AM175<>"",AN175<>""),AM175*AN175,0))+IF(O175="",0,O175)))) | Z175: =IF(OR(AE175="",多次统计数据!$B$8=""),"",AE175-多次统计数据!$B$8) | AA175: =IF(OR(I175="",M175="",M175<I175),"",M175-I175) | AB175: =IF(OR(A175="",多次统计数据!$B$8="",多次统计数据!$B$6<=0,多次统计数据!$B$6>=1),"",1-POWER(1+多次统计数据!$B$8,-多次统计数据!$B$6/(1-多次统计数据!$B$6))) -> 0.043466093 | AC175: =IF(OR(AB175="",多次统计数据!$B$9=""),"",IF(多次统计数据!$B$9<AB175,"低于上限","达到或超过上限")) -> 低于上限 | AE175: =IF(OR(X175="",C175="",C175<=0),"",X175/C175) | AJ175: =IF(OR(AG175="",AH175=""),"",IF(OR(AND(AG175="短期博反弹",OR(AH175="1～3个交易日",AH175="4～10个交易日")),AND(AG175="突破冲新高",OR(AH175="4～10个交易日",AH175="11～20个交易日")),AND(AG175="趋势波段",OR(AH175="11～20个交易日",AH175="21～60个交易日",AH175="60个交易日以上"))),"匹配","周期与交易预期不匹配，请重新确认")) | AO175: =IF(OR(A175="",H175="",H175<=0),"",(E175*H175+IF(AND(AK175<>"",AL175<>""),AK175*AL175,0)+IF(AND(AM175<>"",AN175<>""),AM175*AN175,0))/AP175) -> 14.96 | AP175: =IF(OR(A175="",H175="",H175<=0),"",H175+IF(AL175="",0,AL175)+IF(AN175="",0,AN175)) -> 2600 | AQ175: =IF(A175="","",IF(M175<>"",0,IF(OR(H175="",N175=""),"",MAX(E175-MAX(N175,IFERROR(SUMPRODUCT(MAX(((持仓跟踪!$A$2:$A$497="每日跟踪")*(持仓跟踪!$B$2:$B$497=A175))*持仓跟踪!$S$2:$S$497)),0)),0)*H175+IF(OR(AK175="",AL175=""),0,MAX(AK175-MAX(N175,IFERROR(SUMPRODUCT(MAX(((持仓跟踪!$A$2:$A$497="每日跟踪")*(持仓跟踪!$B$2:$B$497=A175))*持仓跟踪!$S$2:$S$497)),0)),0)*AL175)+IF(OR(AM175="",AN175=""),0,MAX(AM175-MAX(N175,IFERROR(SUMPRODUCT(MAX(((持仓跟踪!$A$2:$A$497="每日跟踪")*(持仓跟踪!$B$2:$B$497=A175))*持仓跟踪!$S$2:$S$497)),0)),0)*AN175)))) -> 1976 | AR175: =IF(A175="","",IF(OR(E175="",H175=""),"违规：第一批价格或股数缺失",IF(OR(AND(AK175="",AL175<>""),AND(AK175<>"",AL175="")),"违规：第二批价格与股数须成对填写",IF(OR(AND(AM175="",AN175<>""),AND(AM175<>"",AN175="")),"违规：第三批价格与股数须成对填写",IF(AND(OR(AM175<>"",AN175<>""),OR(AK175="",AL175="")),"违规：必须先完成第二批",IF(OR(H175<=0,H175<>INT(H175),MOD(H175,100)<>0,AND(AL175<>"",OR(AL175<=0,AL175<>INT(AL175),MOD(AL175,100)<>0)),AND(AN175<>"",OR(AN175<=0,AN175<>INT(AN175),MOD(AN175,100)<>0))),"违规：股数须为100股整数倍",IF(AND(OR(AL175<>"",AN175<>""),OR(_LockStatus="已锁仓",_LockStatus="解锁信息不完整")),"违规：锁仓期间禁止加仓",IF(AQ175>C175*D175,"违规：超过单笔风险上限",IF(SUM($AQ$2:$AQ$201)>账户数据!$B$7,"违规：超过账户风险上限","通过"))))))))) -> 通过
F176: =IF(OR(C176="",D176="",E176="",N176="",C176<=0,D176<=0,E176<=N176),"",ROUNDDOWN((C176*D176)/(E176-N176)/100,0)*100) | G176: =IF(A176="","",IF(H176<>"","已开仓",IF(账户数据!$B$23="已锁仓","禁止开仓：连续亏损达到上限",IF(账户数据!$B$23="解锁信息不完整","禁止开仓：请完整填写解锁信息",IF(OR(F176="",E176="",N176="",E176<=N176,账户数据!$B$7=""),"",IF(OR(AG176="",AH176="",AI176=""),"禁止开仓：交易预期未填写完整",IF(COUNTIFS(持仓跟踪!$A$2:$A$497,"止损计划",持仓跟踪!$B$2:$B$497,A176,持仓跟踪!$AC$2:$AC$497,"计划有效")=0,"禁止开仓：请先填写止损计划",IF(账户数据!$B$9+F176*(E176-N176)>=账户数据!$B$7,"禁止开仓：风险额度不足",IF(AJ176="周期与交易预期不匹配，请重新确认",IF(账户数据!$B$23="接近锁仓","允许开仓（接近锁仓；周期需复核）","允许开仓（周期需复核）"),IF(账户数据!$B$23="接近锁仓","允许开仓（接近锁仓）","允许开仓")))))))))) | K176: =IF(A176="","",IFERROR(LOOKUP(2,1/((持仓跟踪!$B$2:$B$497=A176)*(持仓跟踪!$X$2:$X$497="执行卖出")*(持仓跟踪!$Y$2:$Y$497<>"")),持仓跟踪!$Y$2:$Y$497),"")) | L176: =IF(A176="","",IFERROR(LOOKUP(2,1/((持仓跟踪!$B$2:$B$497=A176)*(持仓跟踪!$X$2:$X$497="执行卖出")*(持仓跟踪!$Z$2:$Z$497<>"")),持仓跟踪!$Z$2:$Z$497),"")) | M176: =IF(A176="","",IFERROR(LOOKUP(2,1/((持仓跟踪!$B$2:$B$497=A176)*(持仓跟踪!$X$2:$X$497="执行卖出")*(持仓跟踪!$H$2:$H$497<>"")),持仓跟踪!$H$2:$H$497),"")) | P176: =IF(A176="","",IFERROR(LOOKUP(2,1/((持仓跟踪!$B$2:$B$497=A176)*(持仓跟踪!$X$2:$X$497="执行卖出")*(持仓跟踪!$AA$2:$AA$497<>"")),持仓跟踪!$AA$2:$AA$497),"")) | U176: =IF(OR(AO176="",J176="",AO176<=0),"",(J176-AO176)/AO176) | V176: =IF(OR(AO176="",N176="",AO176<=0),"",(AO176-N176)/AO176) | W176: =IF(OR(U176="",V176="",V176<=0),"",U176/V176) | X176: =IF(OR(K176="",L176="",AP176=""),"",K176*L176-(E176*H176+IF(AND(AK176<>"",AL176<>""),AK176*AL176,0)+IF(AND(AM176<>"",AN176<>""),AM176*AN176,0))-IF(O176="",0,O176)-IF(P176="",0,P176)) | Y176: =IF(OR(X176="",AP176=""),"",IF((E176*H176+IF(AND(AK176<>"",AL176<>""),AK176*AL176,0)+IF(AND(AM176<>"",AN176<>""),AM176*AN176,0))+IF(O176="",0,O176)<=0,"",X176/((E176*H176+IF(AND(AK176<>"",AL176<>""),AK176*AL176,0)+IF(AND(AM176<>"",AN176<>""),AM176*AN176,0))+IF(O176="",0,O176)))) | Z176: =IF(OR(AE176="",多次统计数据!$B$8=""),"",AE176-多次统计数据!$B$8) | AA176: =IF(OR(I176="",M176="",M176<I176),"",M176-I176) | AB176: =IF(OR(A176="",多次统计数据!$B$8="",多次统计数据!$B$6<=0,多次统计数据!$B$6>=1),"",1-POWER(1+多次统计数据!$B$8,-多次统计数据!$B$6/(1-多次统计数据!$B$6))) | AC176: =IF(OR(AB176="",多次统计数据!$B$9=""),"",IF(多次统计数据!$B$9<AB176,"低于上限","达到或超过上限")) | AE176: =IF(OR(X176="",C176="",C176<=0),"",X176/C176) | AJ176: =IF(OR(AG176="",AH176=""),"",IF(OR(AND(AG176="短期博反弹",OR(AH176="1～3个交易日",AH176="4～10个交易日")),AND(AG176="突破冲新高",OR(AH176="4～10个交易日",AH176="11～20个交易日")),AND(AG176="趋势波段",OR(AH176="11～20个交易日",AH176="21～60个交易日",AH176="60个交易日以上"))),"匹配","周期与交易预期不匹配，请重新确认")) | AO176: =IF(OR(A176="",H176="",H176<=0),"",(E176*H176+IF(AND(AK176<>"",AL176<>""),AK176*AL176,0)+IF(AND(AM176<>"",AN176<>""),AM176*AN176,0))/AP176) | AP176: =IF(OR(A176="",H176="",H176<=0),"",H176+IF(AL176="",0,AL176)+IF(AN176="",0,AN176)) | AQ176: =IF(A176="","",IF(M176<>"",0,IF(OR(H176="",N176=""),"",MAX(E176-MAX(N176,IFERROR(SUMPRODUCT(MAX(((持仓跟踪!$A$2:$A$497="每日跟踪")*(持仓跟踪!$B$2:$B$497=A176))*持仓跟踪!$S$2:$S$497)),0)),0)*H176+IF(OR(AK176="",AL176=""),0,MAX(AK176-MAX(N176,IFERROR(SUMPRODUCT(MAX(((持仓跟踪!$A$2:$A$497="每日跟踪")*(持仓跟踪!$B$2:$B$497=A176))*持仓跟踪!$S$2:$S$497)),0)),0)*AL176)+IF(OR(AM176="",AN176=""),0,MAX(AM176-MAX(N176,IFERROR(SUMPRODUCT(MAX(((持仓跟踪!$A$2:$A$497="每日跟踪")*(持仓跟踪!$B$2:$B$497=A176))*持仓跟踪!$S$2:$S$497)),0)),0)*AN176)))) | AR176: =IF(A176="","",IF(OR(E176="",H176=""),"违规：第一批价格或股数缺失",IF(OR(AND(AK176="",AL176<>""),AND(AK176<>"",AL176="")),"违规：第二批价格与股数须成对填写",IF(OR(AND(AM176="",AN176<>""),AND(AM176<>"",AN176="")),"违规：第三批价格与股数须成对填写",IF(AND(OR(AM176<>"",AN176<>""),OR(AK176="",AL176="")),"违规：必须先完成第二批",IF(OR(H176<=0,H176<>INT(H176),MOD(H176,100)<>0,AND(AL176<>"",OR(AL176<=0,AL176<>INT(AL176),MOD(AL176,100)<>0)),AND(AN176<>"",OR(AN176<=0,AN176<>INT(AN176),MOD(AN176,100)<>0))),"违规：股数须为100股整数倍",IF(AND(OR(AL176<>"",AN176<>""),OR(_LockStatus="已锁仓",_LockStatus="解锁信息不完整")),"违规：锁仓期间禁止加仓",IF(AQ176>C176*D176,"违规：超过单笔风险上限",IF(SUM($AQ$2:$AQ$201)>账户数据!$B$7,"违规：超过账户风险上限","通过")))))))))
F177: =IF(OR(C177="",D177="",E177="",N177="",C177<=0,D177<=0,E177<=N177),"",ROUNDDOWN((C177*D177)/(E177-N177)/100,0)*100) | G177: =IF(A177="","",IF(H177<>"","已开仓",IF(账户数据!$B$23="已锁仓","禁止开仓：连续亏损达到上限",IF(账户数据!$B$23="解锁信息不完整","禁止开仓：请完整填写解锁信息",IF(OR(F177="",E177="",N177="",E177<=N177,账户数据!$B$7=""),"",IF(OR(AG177="",AH177="",AI177=""),"禁止开仓：交易预期未填写完整",IF(COUNTIFS(持仓跟踪!$A$2:$A$497,"止损计划",持仓跟踪!$B$2:$B$497,A177,持仓跟踪!$AC$2:$AC$497,"计划有效")=0,"禁止开仓：请先填写止损计划",IF(账户数据!$B$9+F177*(E177-N177)>=账户数据!$B$7,"禁止开仓：风险额度不足",IF(AJ177="周期与交易预期不匹配，请重新确认",IF(账户数据!$B$23="接近锁仓","允许开仓（接近锁仓；周期需复核）","允许开仓（周期需复核）"),IF(账户数据!$B$23="接近锁仓","允许开仓（接近锁仓）","允许开仓")))))))))) | K177: =IF(A177="","",IFERROR(LOOKUP(2,1/((持仓跟踪!$B$2:$B$497=A177)*(持仓跟踪!$X$2:$X$497="执行卖出")*(持仓跟踪!$Y$2:$Y$497<>"")),持仓跟踪!$Y$2:$Y$497),"")) | L177: =IF(A177="","",IFERROR(LOOKUP(2,1/((持仓跟踪!$B$2:$B$497=A177)*(持仓跟踪!$X$2:$X$497="执行卖出")*(持仓跟踪!$Z$2:$Z$497<>"")),持仓跟踪!$Z$2:$Z$497),"")) | M177: =IF(A177="","",IFERROR(LOOKUP(2,1/((持仓跟踪!$B$2:$B$497=A177)*(持仓跟踪!$X$2:$X$497="执行卖出")*(持仓跟踪!$H$2:$H$497<>"")),持仓跟踪!$H$2:$H$497),"")) | P177: =IF(A177="","",IFERROR(LOOKUP(2,1/((持仓跟踪!$B$2:$B$497=A177)*(持仓跟踪!$X$2:$X$497="执行卖出")*(持仓跟踪!$AA$2:$AA$497<>"")),持仓跟踪!$AA$2:$AA$497),"")) | U177: =IF(OR(AO177="",J177="",AO177<=0),"",(J177-AO177)/AO177) | V177: =IF(OR(AO177="",N177="",AO177<=0),"",(AO177-N177)/AO177) | W177: =IF(OR(U177="",V177="",V177<=0),"",U177/V177) | X177: =IF(OR(K177="",L177="",AP177=""),"",K177*L177-(E177*H177+IF(AND(AK177<>"",AL177<>""),AK177*AL177,0)+IF(AND(AM177<>"",AN177<>""),AM177*AN177,0))-IF(O177="",0,O177)-IF(P177="",0,P177)) | Y177: =IF(OR(X177="",AP177=""),"",IF((E177*H177+IF(AND(AK177<>"",AL177<>""),AK177*AL177,0)+IF(AND(AM177<>"",AN177<>""),AM177*AN177,0))+IF(O177="",0,O177)<=0,"",X177/((E177*H177+IF(AND(AK177<>"",AL177<>""),AK177*AL177,0)+IF(AND(AM177<>"",AN177<>""),AM177*AN177,0))+IF(O177="",0,O177)))) | Z177: =IF(OR(AE177="",多次统计数据!$B$8=""),"",AE177-多次统计数据!$B$8) | AA177: =IF(OR(I177="",M177="",M177<I177),"",M177-I177) | AB177: =IF(OR(A177="",多次统计数据!$B$8="",多次统计数据!$B$6<=0,多次统计数据!$B$6>=1),"",1-POWER(1+多次统计数据!$B$8,-多次统计数据!$B$6/(1-多次统计数据!$B$6))) | AC177: =IF(OR(AB177="",多次统计数据!$B$9=""),"",IF(多次统计数据!$B$9<AB177,"低于上限","达到或超过上限")) | AE177: =IF(OR(X177="",C177="",C177<=0),"",X177/C177) | AJ177: =IF(OR(AG177="",AH177=""),"",IF(OR(AND(AG177="短期博反弹",OR(AH177="1～3个交易日",AH177="4～10个交易日")),AND(AG177="突破冲新高",OR(AH177="4～10个交易日",AH177="11～20个交易日")),AND(AG177="趋势波段",OR(AH177="11～20个交易日",AH177="21～60个交易日",AH177="60个交易日以上"))),"匹配","周期与交易预期不匹配，请重新确认")) | AO177: =IF(OR(A177="",H177="",H177<=0),"",(E177*H177+IF(AND(AK177<>"",AL177<>""),AK177*AL177,0)+IF(AND(AM177<>"",AN177<>""),AM177*AN177,0))/AP177) | AP177: =IF(OR(A177="",H177="",H177<=0),"",H177+IF(AL177="",0,AL177)+IF(AN177="",0,AN177)) | AQ177: =IF(A177="","",IF(M177<>"",0,IF(OR(H177="",N177=""),"",MAX(E177-MAX(N177,IFERROR(SUMPRODUCT(MAX(((持仓跟踪!$A$2:$A$497="每日跟踪")*(持仓跟踪!$B$2:$B$497=A177))*持仓跟踪!$S$2:$S$497)),0)),0)*H177+IF(OR(AK177="",AL177=""),0,MAX(AK177-MAX(N177,IFERROR(SUMPRODUCT(MAX(((持仓跟踪!$A$2:$A$497="每日跟踪")*(持仓跟踪!$B$2:$B$497=A177))*持仓跟踪!$S$2:$S$497)),0)),0)*AL177)+IF(OR(AM177="",AN177=""),0,MAX(AM177-MAX(N177,IFERROR(SUMPRODUCT(MAX(((持仓跟踪!$A$2:$A$497="每日跟踪")*(持仓跟踪!$B$2:$B$497=A177))*持仓跟踪!$S$2:$S$497)),0)),0)*AN177)))) | AR177: =IF(A177="","",IF(OR(E177="",H177=""),"违规：第一批价格或股数缺失",IF(OR(AND(AK177="",AL177<>""),AND(AK177<>"",AL177="")),"违规：第二批价格与股数须成对填写",IF(OR(AND(AM177="",AN177<>""),AND(AM177<>"",AN177="")),"违规：第三批价格与股数须成对填写",IF(AND(OR(AM177<>"",AN177<>""),OR(AK177="",AL177="")),"违规：必须先完成第二批",IF(OR(H177<=0,H177<>INT(H177),MOD(H177,100)<>0,AND(AL177<>"",OR(AL177<=0,AL177<>INT(AL177),MOD(AL177,100)<>0)),AND(AN177<>"",OR(AN177<=0,AN177<>INT(AN177),MOD(AN177,100)<>0))),"违规：股数须为100股整数倍",IF(AND(OR(AL177<>"",AN177<>""),OR(_LockStatus="已锁仓",_LockStatus="解锁信息不完整")),"违规：锁仓期间禁止加仓",IF(AQ177>C177*D177,"违规：超过单笔风险上限",IF(SUM($AQ$2:$AQ$201)>账户数据!$B$7,"违规：超过账户风险上限","通过")))))))))
F178: =IF(OR(C178="",D178="",E178="",N178="",C178<=0,D178<=0,E178<=N178),"",ROUNDDOWN((C178*D178)/(E178-N178)/100,0)*100) | G178: =IF(A178="","",IF(H178<>"","已开仓",IF(账户数据!$B$23="已锁仓","禁止开仓：连续亏损达到上限",IF(账户数据!$B$23="解锁信息不完整","禁止开仓：请完整填写解锁信息",IF(OR(F178="",E178="",N178="",E178<=N178,账户数据!$B$7=""),"",IF(OR(AG178="",AH178="",AI178=""),"禁止开仓：交易预期未填写完整",IF(COUNTIFS(持仓跟踪!$A$2:$A$497,"止损计划",持仓跟踪!$B$2:$B$497,A178,持仓跟踪!$AC$2:$AC$497,"计划有效")=0,"禁止开仓：请先填写止损计划",IF(账户数据!$B$9+F178*(E178-N178)>=账户数据!$B$7,"禁止开仓：风险额度不足",IF(AJ178="周期与交易预期不匹配，请重新确认",IF(账户数据!$B$23="接近锁仓","允许开仓（接近锁仓；周期需复核）","允许开仓（周期需复核）"),IF(账户数据!$B$23="接近锁仓","允许开仓（接近锁仓）","允许开仓")))))))))) | K178: =IF(A178="","",IFERROR(LOOKUP(2,1/((持仓跟踪!$B$2:$B$497=A178)*(持仓跟踪!$X$2:$X$497="执行卖出")*(持仓跟踪!$Y$2:$Y$497<>"")),持仓跟踪!$Y$2:$Y$497),"")) | L178: =IF(A178="","",IFERROR(LOOKUP(2,1/((持仓跟踪!$B$2:$B$497=A178)*(持仓跟踪!$X$2:$X$497="执行卖出")*(持仓跟踪!$Z$2:$Z$497<>"")),持仓跟踪!$Z$2:$Z$497),"")) | M178: =IF(A178="","",IFERROR(LOOKUP(2,1/((持仓跟踪!$B$2:$B$497=A178)*(持仓跟踪!$X$2:$X$497="执行卖出")*(持仓跟踪!$H$2:$H$497<>"")),持仓跟踪!$H$2:$H$497),"")) | P178: =IF(A178="","",IFERROR(LOOKUP(2,1/((持仓跟踪!$B$2:$B$497=A178)*(持仓跟踪!$X$2:$X$497="执行卖出")*(持仓跟踪!$AA$2:$AA$497<>"")),持仓跟踪!$AA$2:$AA$497),"")) | U178: =IF(OR(AO178="",J178="",AO178<=0),"",(J178-AO178)/AO178) | V178: =IF(OR(AO178="",N178="",AO178<=0),"",(AO178-N178)/AO178) | W178: =IF(OR(U178="",V178="",V178<=0),"",U178/V178) | X178: =IF(OR(K178="",L178="",AP178=""),"",K178*L178-(E178*H178+IF(AND(AK178<>"",AL178<>""),AK178*AL178,0)+IF(AND(AM178<>"",AN178<>""),AM178*AN178,0))-IF(O178="",0,O178)-IF(P178="",0,P178)) | Y178: =IF(OR(X178="",AP178=""),"",IF((E178*H178+IF(AND(AK178<>"",AL178<>""),AK178*AL178,0)+IF(AND(AM178<>"",AN178<>""),AM178*AN178,0))+IF(O178="",0,O178)<=0,"",X178/((E178*H178+IF(AND(AK178<>"",AL178<>""),AK178*AL178,0)+IF(AND(AM178<>"",AN178<>""),AM178*AN178,0))+IF(O178="",0,O178)))) | Z178: =IF(OR(AE178="",多次统计数据!$B$8=""),"",AE178-多次统计数据!$B$8) | AA178: =IF(OR(I178="",M178="",M178<I178),"",M178-I178) | AB178: =IF(OR(A178="",多次统计数据!$B$8="",多次统计数据!$B$6<=0,多次统计数据!$B$6>=1),"",1-POWER(1+多次统计数据!$B$8,-多次统计数据!$B$6/(1-多次统计数据!$B$6))) | AC178: =IF(OR(AB178="",多次统计数据!$B$9=""),"",IF(多次统计数据!$B$9<AB178,"低于上限","达到或超过上限")) | AE178: =IF(OR(X178="",C178="",C178<=0),"",X178/C178) | AJ178: =IF(OR(AG178="",AH178=""),"",IF(OR(AND(AG178="短期博反弹",OR(AH178="1～3个交易日",AH178="4～10个交易日")),AND(AG178="突破冲新高",OR(AH178="4～10个交易日",AH178="11～20个交易日")),AND(AG178="趋势波段",OR(AH178="11～20个交易日",AH178="21～60个交易日",AH178="60个交易日以上"))),"匹配","周期与交易预期不匹配，请重新确认")) | AO178: =IF(OR(A178="",H178="",H178<=0),"",(E178*H178+IF(AND(AK178<>"",AL178<>""),AK178*AL178,0)+IF(AND(AM178<>"",AN178<>""),AM178*AN178,0))/AP178) | AP178: =IF(OR(A178="",H178="",H178<=0),"",H178+IF(AL178="",0,AL178)+IF(AN178="",0,AN178)) | AQ178: =IF(A178="","",IF(M178<>"",0,IF(OR(H178="",N178=""),"",MAX(E178-MAX(N178,IFERROR(SUMPRODUCT(MAX(((持仓跟踪!$A$2:$A$497="每日跟踪")*(持仓跟踪!$B$2:$B$497=A178))*持仓跟踪!$S$2:$S$497)),0)),0)*H178+IF(OR(AK178="",AL178=""),0,MAX(AK178-MAX(N178,IFERROR(SUMPRODUCT(MAX(((持仓跟踪!$A$2:$A$497="每日跟踪")*(持仓跟踪!$B$2:$B$497=A178))*持仓跟踪!$S$2:$S$497)),0)),0)*AL178)+IF(OR(AM178="",AN178=""),0,MAX(AM178-MAX(N178,IFERROR(SUMPRODUCT(MAX(((持仓跟踪!$A$2:$A$497="每日跟踪")*(持仓跟踪!$B$2:$B$497=A178))*持仓跟踪!$S$2:$S$497)),0)),0)*AN178)))) | AR178: =IF(A178="","",IF(OR(E178="",H178=""),"违规：第一批价格或股数缺失",IF(OR(AND(AK178="",AL178<>""),AND(AK178<>"",AL178="")),"违规：第二批价格与股数须成对填写",IF(OR(AND(AM178="",AN178<>""),AND(AM178<>"",AN178="")),"违规：第三批价格与股数须成对填写",IF(AND(OR(AM178<>"",AN178<>""),OR(AK178="",AL178="")),"违规：必须先完成第二批",IF(OR(H178<=0,H178<>INT(H178),MOD(H178,100)<>0,AND(AL178<>"",OR(AL178<=0,AL178<>INT(AL178),MOD(AL178,100)<>0)),AND(AN178<>"",OR(AN178<=0,AN178<>INT(AN178),MOD(AN178,100)<>0))),"违规：股数须为100股整数倍",IF(AND(OR(AL178<>"",AN178<>""),OR(_LockStatus="已锁仓",_LockStatus="解锁信息不完整")),"违规：锁仓期间禁止加仓",IF(AQ178>C178*D178,"违规：超过单笔风险上限",IF(SUM($AQ$2:$AQ$201)>账户数据!$B$7,"违规：超过账户风险上限","通过")))))))))
F179: =IF(OR(C179="",D179="",E179="",N179="",C179<=0,D179<=0,E179<=N179),"",ROUNDDOWN((C179*D179)/(E179-N179)/100,0)*100) | G179: =IF(A179="","",IF(H179<>"","已开仓",IF(账户数据!$B$23="已锁仓","禁止开仓：连续亏损达到上限",IF(账户数据!$B$23="解锁信息不完整","禁止开仓：请完整填写解锁信息",IF(OR(F179="",E179="",N179="",E179<=N179,账户数据!$B$7=""),"",IF(OR(AG179="",AH179="",AI179=""),"禁止开仓：交易预期未填写完整",IF(COUNTIFS(持仓跟踪!$A$2:$A$497,"止损计划",持仓跟踪!$B$2:$B$497,A179,持仓跟踪!$AC$2:$AC$497,"计划有效")=0,"禁止开仓：请先填写止损计划",IF(账户数据!$B$9+F179*(E179-N179)>=账户数据!$B$7,"禁止开仓：风险额度不足",IF(AJ179="周期与交易预期不匹配，请重新确认",IF(账户数据!$B$23="接近锁仓","允许开仓（接近锁仓；周期需复核）","允许开仓（周期需复核）"),IF(账户数据!$B$23="接近锁仓","允许开仓（接近锁仓）","允许开仓")))))))))) | K179: =IF(A179="","",IFERROR(LOOKUP(2,1/((持仓跟踪!$B$2:$B$497=A179)*(持仓跟踪!$X$2:$X$497="执行卖出")*(持仓跟踪!$Y$2:$Y$497<>"")),持仓跟踪!$Y$2:$Y$497),"")) | L179: =IF(A179="","",IFERROR(LOOKUP(2,1/((持仓跟踪!$B$2:$B$497=A179)*(持仓跟踪!$X$2:$X$497="执行卖出")*(持仓跟踪!$Z$2:$Z$497<>"")),持仓跟踪!$Z$2:$Z$497),"")) | M179: =IF(A179="","",IFERROR(LOOKUP(2,1/((持仓跟踪!$B$2:$B$497=A179)*(持仓跟踪!$X$2:$X$497="执行卖出")*(持仓跟踪!$H$2:$H$497<>"")),持仓跟踪!$H$2:$H$497),"")) | P179: =IF(A179="","",IFERROR(LOOKUP(2,1/((持仓跟踪!$B$2:$B$497=A179)*(持仓跟踪!$X$2:$X$497="执行卖出")*(持仓跟踪!$AA$2:$AA$497<>"")),持仓跟踪!$AA$2:$AA$497),"")) | U179: =IF(OR(AO179="",J179="",AO179<=0),"",(J179-AO179)/AO179) | V179: =IF(OR(AO179="",N179="",AO179<=0),"",(AO179-N179)/AO179) | W179: =IF(OR(U179="",V179="",V179<=0),"",U179/V179) | X179: =IF(OR(K179="",L179="",AP179=""),"",K179*L179-(E179*H179+IF(AND(AK179<>"",AL179<>""),AK179*AL179,0)+IF(AND(AM179<>"",AN179<>""),AM179*AN179,0))-IF(O179="",0,O179)-IF(P179="",0,P179)) | Y179: =IF(OR(X179="",AP179=""),"",IF((E179*H179+IF(AND(AK179<>"",AL179<>""),AK179*AL179,0)+IF(AND(AM179<>"",AN179<>""),AM179*AN179,0))+IF(O179="",0,O179)<=0,"",X179/((E179*H179+IF(AND(AK179<>"",AL179<>""),AK179*AL179,0)+IF(AND(AM179<>"",AN179<>""),AM179*AN179,0))+IF(O179="",0,O179)))) | Z179: =IF(OR(AE179="",多次统计数据!$B$8=""),"",AE179-多次统计数据!$B$8) | AA179: =IF(OR(I179="",M179="",M179<I179),"",M179-I179) | AB179: =IF(OR(A179="",多次统计数据!$B$8="",多次统计数据!$B$6<=0,多次统计数据!$B$6>=1),"",1-POWER(1+多次统计数据!$B$8,-多次统计数据!$B$6/(1-多次统计数据!$B$6))) | AC179: =IF(OR(AB179="",多次统计数据!$B$9=""),"",IF(多次统计数据!$B$9<AB179,"低于上限","达到或超过上限")) | AE179: =IF(OR(X179="",C179="",C179<=0),"",X179/C179) | AJ179: =IF(OR(AG179="",AH179=""),"",IF(OR(AND(AG179="短期博反弹",OR(AH179="1～3个交易日",AH179="4～10个交易日")),AND(AG179="突破冲新高",OR(AH179="4～10个交易日",AH179="11～20个交易日")),AND(AG179="趋势波段",OR(AH179="11～20个交易日",AH179="21～60个交易日",AH179="60个交易日以上"))),"匹配","周期与交易预期不匹配，请重新确认")) | AO179: =IF(OR(A179="",H179="",H179<=0),"",(E179*H179+IF(AND(AK179<>"",AL179<>""),AK179*AL179,0)+IF(AND(AM179<>"",AN179<>""),AM179*AN179,0))/AP179) | AP179: =IF(OR(A179="",H179="",H179<=0),"",H179+IF(AL179="",0,AL179)+IF(AN179="",0,AN179)) | AQ179: =IF(A179="","",IF(M179<>"",0,IF(OR(H179="",N179=""),"",MAX(E179-MAX(N179,IFERROR(SUMPRODUCT(MAX(((持仓跟踪!$A$2:$A$497="每日跟踪")*(持仓跟踪!$B$2:$B$497=A179))*持仓跟踪!$S$2:$S$497)),0)),0)*H179+IF(OR(AK179="",AL179=""),0,MAX(AK179-MAX(N179,IFERROR(SUMPRODUCT(MAX(((持仓跟踪!$A$2:$A$497="每日跟踪")*(持仓跟踪!$B$2:$B$497=A179))*持仓跟踪!$S$2:$S$497)),0)),0)*AL179)+IF(OR(AM179="",AN179=""),0,MAX(AM179-MAX(N179,IFERROR(SUMPRODUCT(MAX(((持仓跟踪!$A$2:$A$497="每日跟踪")*(持仓跟踪!$B$2:$B$497=A179))*持仓跟踪!$S$2:$S$497)),0)),0)*AN179)))) | AR179: =IF(A179="","",IF(OR(E179="",H179=""),"违规：第一批价格或股数缺失",IF(OR(AND(AK179="",AL179<>""),AND(AK179<>"",AL179="")),"违规：第二批价格与股数须成对填写",IF(OR(AND(AM179="",AN179<>""),AND(AM179<>"",AN179="")),"违规：第三批价格与股数须成对填写",IF(AND(OR(AM179<>"",AN179<>""),OR(AK179="",AL179="")),"违规：必须先完成第二批",IF(OR(H179<=0,H179<>INT(H179),MOD(H179,100)<>0,AND(AL179<>"",OR(AL179<=0,AL179<>INT(AL179),MOD(AL179,100)<>0)),AND(AN179<>"",OR(AN179<=0,AN179<>INT(AN179),MOD(AN179,100)<>0))),"违规：股数须为100股整数倍",IF(AND(OR(AL179<>"",AN179<>""),OR(_LockStatus="已锁仓",_LockStatus="解锁信息不完整")),"违规：锁仓期间禁止加仓",IF(AQ179>C179*D179,"违规：超过单笔风险上限",IF(SUM($AQ$2:$AQ$201)>账户数据!$B$7,"违规：超过账户风险上限","通过")))))))))
F180: =IF(OR(C180="",D180="",E180="",N180="",C180<=0,D180<=0,E180<=N180),"",ROUNDDOWN((C180*D180)/(E180-N180)/100,0)*100) | G180: =IF(A180="","",IF(H180<>"","已开仓",IF(账户数据!$B$23="已锁仓","禁止开仓：连续亏损达到上限",IF(账户数据!$B$23="解锁信息不完整","禁止开仓：请完整填写解锁信息",IF(OR(F180="",E180="",N180="",E180<=N180,账户数据!$B$7=""),"",IF(OR(AG180="",AH180="",AI180=""),"禁止开仓：交易预期未填写完整",IF(COUNTIFS(持仓跟踪!$A$2:$A$497,"止损计划",持仓跟踪!$B$2:$B$497,A180,持仓跟踪!$AC$2:$AC$497,"计划有效")=0,"禁止开仓：请先填写止损计划",IF(账户数据!$B$9+F180*(E180-N180)>=账户数据!$B$7,"禁止开仓：风险额度不足",IF(AJ180="周期与交易预期不匹配，请重新确认",IF(账户数据!$B$23="接近锁仓","允许开仓（接近锁仓；周期需复核）","允许开仓（周期需复核）"),IF(账户数据!$B$23="接近锁仓","允许开仓（接近锁仓）","允许开仓")))))))))) | K180: =IF(A180="","",IFERROR(LOOKUP(2,1/((持仓跟踪!$B$2:$B$497=A180)*(持仓跟踪!$X$2:$X$497="执行卖出")*(持仓跟踪!$Y$2:$Y$497<>"")),持仓跟踪!$Y$2:$Y$497),"")) | L180: =IF(A180="","",IFERROR(LOOKUP(2,1/((持仓跟踪!$B$2:$B$497=A180)*(持仓跟踪!$X$2:$X$497="执行卖出")*(持仓跟踪!$Z$2:$Z$497<>"")),持仓跟踪!$Z$2:$Z$497),"")) | M180: =IF(A180="","",IFERROR(LOOKUP(2,1/((持仓跟踪!$B$2:$B$497=A180)*(持仓跟踪!$X$2:$X$497="执行卖出")*(持仓跟踪!$H$2:$H$497<>"")),持仓跟踪!$H$2:$H$497),"")) | P180: =IF(A180="","",IFERROR(LOOKUP(2,1/((持仓跟踪!$B$2:$B$497=A180)*(持仓跟踪!$X$2:$X$497="执行卖出")*(持仓跟踪!$AA$2:$AA$497<>"")),持仓跟踪!$AA$2:$AA$497),"")) | U180: =IF(OR(AO180="",J180="",AO180<=0),"",(J180-AO180)/AO180) | V180: =IF(OR(AO180="",N180="",AO180<=0),"",(AO180-N180)/AO180) | W180: =IF(OR(U180="",V180="",V180<=0),"",U180/V180) | X180: =IF(OR(K180="",L180="",AP180=""),"",K180*L180-(E180*H180+IF(AND(AK180<>"",AL180<>""),AK180*AL180,0)+IF(AND(AM180<>"",AN180<>""),AM180*AN180,0))-IF(O180="",0,O180)-IF(P180="",0,P180)) | Y180: =IF(OR(X180="",AP180=""),"",IF((E180*H180+IF(AND(AK180<>"",AL180<>""),AK180*AL180,0)+IF(AND(AM180<>"",AN180<>""),AM180*AN180,0))+IF(O180="",0,O180)<=0,"",X180/((E180*H180+IF(AND(AK180<>"",AL180<>""),AK180*AL180,0)+IF(AND(AM180<>"",AN180<>""),AM180*AN180,0))+IF(O180="",0,O180)))) | Z180: =IF(OR(AE180="",多次统计数据!$B$8=""),"",AE180-多次统计数据!$B$8) | AA180: =IF(OR(I180="",M180="",M180<I180),"",M180-I180) | AB180: =IF(OR(A180="",多次统计数据!$B$8="",多次统计数据!$B$6<=0,多次统计数据!$B$6>=1),"",1-POWER(1+多次统计数据!$B$8,-多次统计数据!$B$6/(1-多次统计数据!$B$6))) | AC180: =IF(OR(AB180="",多次统计数据!$B$9=""),"",IF(多次统计数据!$B$9<AB180,"低于上限","达到或超过上限")) | AE180: =IF(OR(X180="",C180="",C180<=0),"",X180/C180) | AJ180: =IF(OR(AG180="",AH180=""),"",IF(OR(AND(AG180="短期博反弹",OR(AH180="1～3个交易日",AH180="4～10个交易日")),AND(AG180="突破冲新高",OR(AH180="4～10个交易日",AH180="11～20个交易日")),AND(AG180="趋势波段",OR(AH180="11～20个交易日",AH180="21～60个交易日",AH180="60个交易日以上"))),"匹配","周期与交易预期不匹配，请重新确认")) | AO180: =IF(OR(A180="",H180="",H180<=0),"",(E180*H180+IF(AND(AK180<>"",AL180<>""),AK180*AL180,0)+IF(AND(AM180<>"",AN180<>""),AM180*AN180,0))/AP180) | AP180: =IF(OR(A180="",H180="",H180<=0),"",H180+IF(AL180="",0,AL180)+IF(AN180="",0,AN180)) | AQ180: =IF(A180="","",IF(M180<>"",0,IF(OR(H180="",N180=""),"",MAX(E180-MAX(N180,IFERROR(SUMPRODUCT(MAX(((持仓跟踪!$A$2:$A$497="每日跟踪")*(持仓跟踪!$B$2:$B$497=A180))*持仓跟踪!$S$2:$S$497)),0)),0)*H180+IF(OR(AK180="",AL180=""),0,MAX(AK180-MAX(N180,IFERROR(SUMPRODUCT(MAX(((持仓跟踪!$A$2:$A$497="每日跟踪")*(持仓跟踪!$B$2:$B$497=A180))*持仓跟踪!$S$2:$S$497)),0)),0)*AL180)+IF(OR(AM180="",AN180=""),0,MAX(AM180-MAX(N180,IFERROR(SUMPRODUCT(MAX(((持仓跟踪!$A$2:$A$497="每日跟踪")*(持仓跟踪!$B$2:$B$497=A180))*持仓跟踪!$S$2:$S$497)),0)),0)*AN180)))) | AR180: =IF(A180="","",IF(OR(E180="",H180=""),"违规：第一批价格或股数缺失",IF(OR(AND(AK180="",AL180<>""),AND(AK180<>"",AL180="")),"违规：第二批价格与股数须成对填写",IF(OR(AND(AM180="",AN180<>""),AND(AM180<>"",AN180="")),"违规：第三批价格与股数须成对填写",IF(AND(OR(AM180<>"",AN180<>""),OR(AK180="",AL180="")),"违规：必须先完成第二批",IF(OR(H180<=0,H180<>INT(H180),MOD(H180,100)<>0,AND(AL180<>"",OR(AL180<=0,AL180<>INT(AL180),MOD(AL180,100)<>0)),AND(AN180<>"",OR(AN180<=0,AN180<>INT(AN180),MOD(AN180,100)<>0))),"违规：股数须为100股整数倍",IF(AND(OR(AL180<>"",AN180<>""),OR(_LockStatus="已锁仓",_LockStatus="解锁信息不完整")),"违规：锁仓期间禁止加仓",IF(AQ180>C180*D180,"违规：超过单笔风险上限",IF(SUM($AQ$2:$AQ$201)>账户数据!$B$7,"违规：超过账户风险上限","通过")))))))))
