Workbook
Name _AccountRiskLimit: 账户数据!$B$7
Name _LockStatus: 账户数据!$B$23
Name _TrackRule: 持仓跟踪!$AC$2:$AC$501
Name _TrackTradeId: 持仓跟踪!$B$2:$B$501
Name _TrackType: 持仓跟踪!$A$2:$A$501
Name _TradeIds: 单次交易!$A$2:$A$201
Name 技术指标列表: 技术指标!$A$2:$A$201

Sheet 单次交易
A1: 交易编号 | B1: 股票代码 | C1: 买入时账户金额 | D1: 本次允许亏损比例 | E1: 第一批买入价 | F1: 买入建议股数 | G1: 开仓风险告警 | H1: 第一批买入股数 | I1: 首次买入日期 | J1: 期望卖出价 | K1: 实际卖出价 | L1: 卖出股数 | M1: 卖出日期 | N1: 止损价 | O1: 买入总费用 | P1: 卖出费用 | Q1: 买入价的由来 | R1: 止损价的由来 | S1: 期望卖出价的由来 | T1: 实际卖出价的由来 | U1: 期望盈利比例 | V1: 期望止损比例 | W1: 盈亏比 | X1: 实际盈亏金额 | Y1: 单笔仓位收益率 | Z1: 账户收益率与平均盈利率差值 | AA1: 持有天数 | AB1: 复利容许平均亏损上限 | AC1: 复利风险判断 | AD1: 交易打分评价 | AE1: 实际账户收益率 | AF1: 列1 | AG1: 交易预期类型 | AH1: 预期持有周期 | AI1: 预期选择理由 | AJ1: 周期匹配检查 | AK1: 第二批买入价 | AL1: 第二批买入股数 | AM1: 第三批买入价 | AN1: 第三批买入股数 | AO1: 实际加权买入价 | AP1: 累计买入股数 | AQ1: 当前持仓风险 | AR1: 分仓规则检查
A2: 1 | B2: 长电科技 | C2: 100000 | D2: 0.02 | E2: 24 | F2: =IF(OR(C2="",D2="",E2="",N2="",C2<=0,D2<=0,E2<=N2),"",ROUNDDOWN((C2*D2)/(E2-N2)/100,0)*100) | G2: =IF(A2="","",IF(H2<>"","已开仓",IF(账户数据!$B$23="已锁仓","禁止开仓：连续亏损达到上限",IF(账户数据!$B$23="解锁信息不完整","禁止开仓：请完整填写解锁信息",IF(OR(F2="",E2="",N2="",E2<=N2,账户数据!$B$7=""),"",IF(OR(AG2="",AH2="",AI2=""),"禁止开仓：交易预期未填写完整",IF(COUNTIFS(持仓跟踪!$A$2:$A$501,"止损计划",持仓跟踪!$B$2:$B$501,A2,持仓跟踪!$AC$2:$AC$501,"计划有效")=0,"禁止开仓：请先填写止损计划",IF(账户数据!$B$9+F2*(E2-N2)>=账户数据!$B$7,"禁止开仓：风险额度不足",IF(AJ2="周期与交易预期不匹配，请重新确认",IF(账户数据!$B$23="接近锁仓","允许开仓（接近锁仓；周期需复核）","允许开仓（周期需复核）"),IF(账户数据!$B$23="接近锁仓","允许开仓（接近锁仓）","允许开仓")))))))))) | H2: 4000 | I2: 44701 | J2: 25 | K2: 22.97 | L2: =IF(K2="","",H2) | M2: 44705 | N2: 23.5 | R2: 之前的支撑位 | S2: 之前的压力位 | U2: =IF(OR(AO2="",J2="",AO2<=0),"",(J2-AO2)/AO2) | V2: =IF(OR(AO2="",N2="",AO2<=0),"",(AO2-N2)/AO2) | W2: =IF(OR(U2="",V2="",V2<=0),"",U2/V2) | X2: =IF(OR(K2="",L2="",AP2=""),"",K2*L2-(E2*H2+IF(AND(AK2<>"",AL2<>""),AK2*AL2,0)+IF(AND(AM2<>"",AN2<>""),AM2*AN2,0))-IF(O2="",0,O2)-IF(P2="",0,P2)) | Y2: =IF(OR(X2="",AP2=""),"",IF((E2*H2+IF(AND(AK2<>"",AL2<>""),AK2*AL2,0)+IF(AND(AM2<>"",AN2<>""),AM2*AN2,0))+IF(O2="",0,O2)<=0,"",X2/((E2*H2+IF(AND(AK2<>"",AL2<>""),AK2*AL2,0)+IF(AND(AM2<>"",AN2<>""),AM2*AN2,0))+IF(O2="",0,O2)))) | Z2: =IF(OR(AE2="",多次统计数据!$B$8=""),"",AE2-多次统计数据!$B$8) | AA2: =IF(OR(I2="",M2="",M2<I2),"",M2-I2) | AB2: =IF(OR(A2="",多次统计数据!$B$8="",多次统计数据!$B$6<=0,多次统计数据!$B$6>=1),"",1-POWER(1+多次统计数据!$B$8,-多次统计数据!$B$6/(1-多次统计数据!$B$6))) | AC2: =IF(OR(AB2="",多次统计数据!$B$9=""),"",IF(多次统计数据!$B$9<AB2,"低于上限","达到或超过上限")) | AE2: =IF(OR(X2="",C2="",C2<=0),"",X2/C2) | AJ2: =IF(OR(AG2="",AH2=""),"",IF(OR(AND(AG2="短期博反弹",OR(AH2="1～3个交易日",AH2="4～10个交易日")),AND(AG2="突破冲新高",OR(AH2="4～10个交易日",AH2="11～20个交易日")),AND(AG2="趋势波段",OR(AH2="11～20个交易日",AH2="21～60个交易日",AH2="60个交易日以上"))),"匹配","周期与交易预期不匹配，请重新确认")) | AO2: =IF(OR(A2="",H2="",H2<=0),"",(E2*H2+IF(AND(AK2<>"",AL2<>""),AK2*AL2,0)+IF(AND(AM2<>"",AN2<>""),AM2*AN2,0))/AP2) | AP2: =IF(OR(A2="",H2="",H2<=0),"",H2+IF(AL2="",0,AL2)+IF(AN2="",0,AN2)) | AQ2: =IF(A2="","",IF(M2<>"",0,IF(OR(H2="",N2=""),"",MAX(E2-MAX(N2,IFERROR(AGGREGATE(14,6,'持仓跟踪'!$S$2:$S$501/(('持仓跟踪'!$A$2:$A$501="每日跟踪")*('持仓跟踪'!$B$2:$B$501=A2)),1),0)),0)*H2+IF(OR(AK2="",AL2=""),0,MAX(AK2-MAX(N2,IFERROR(AGGREGATE(14,6,'持仓跟踪'!$S$2:$S$501/(('持仓跟踪'!$A$2:$A$501="每日跟踪")*('持仓跟踪'!$B$2:$B$501=A2)),1),0)),0)*AL2)+IF(OR(AM2="",AN2=""),0,MAX(AM2-MAX(N2,IFERROR(AGGREGATE(14,6,'持仓跟踪'!$S$2:$S$501/(('持仓跟踪'!$A$2:$A$501="每日跟踪")*('持仓跟踪'!$B$2:$B$501=A2)),1),0)),0)*AN2)))) | AR2: =IF(A2="","",IF(OR(E2="",H2=""),"违规：第一批价格或股数缺失",IF(OR(AND(AK2="",AL2<>""),AND(AK2<>"",AL2="")),"违规：第二批价格与股数须成对填写",IF(OR(AND(AM2="",AN2<>""),AND(AM2<>"",AN2="")),"违规：第三批价格与股数须成对填写",IF(AND(OR(AM2<>"",AN2<>""),OR(AK2="",AL2="")),"违规：必须先完成第二批",IF(OR(H2<=0,H2<>INT(H2),MOD(H2,100)<>0,AND(AL2<>"",OR(AL2<=0,AL2<>INT(AL2),MOD(AL2,100)<>0)),AND(AN2<>"",OR(AN2<=0,AN2<>INT(AN2),MOD(AN2,100)<>0))),"违规：股数须为100股整数倍",IF(AND(OR(AL2<>"",AN2<>""),OR(_LockStatus="已锁仓",_LockStatus="解锁信息不完整")),"违规：锁仓期间禁止加仓",IF(AQ2>C2*D2,"违规：超过单笔风险上限",IF(SUM($AQ$2:$AQ$201)>账户数据!$B$7,"违规：超过账户风险上限","通过")))))))))
A3: 2 | B3: 长电科技 | C3: =IF(C2="","",C2+SUM(单次交易!Y2:Y201)) | D3: 0.02 | E3: 33.13 | F3: =IF(OR(C3="",D3="",E3="",N3="",C3<=0,D3<=0,E3<=N3),"",ROUNDDOWN((C3*D3)/(E3-N3)/100,0)*100) | G3: =IF(A3="","",IF(H3<>"","已开仓",IF(账户数据!$B$23="已锁仓","禁止开仓：连续亏损达到上限",IF(账户数据!$B$23="解锁信息不完整","禁止开仓：请完整填写解锁信息",IF(OR(F3="",E3="",N3="",E3<=N3,账户数据!$B$7=""),"",IF(OR(AG3="",AH3="",AI3=""),"禁止开仓：交易预期未填写完整",IF(COUNTIFS(持仓跟踪!$A$2:$A$501,"止损计划",持仓跟踪!$B$2:$B$501,A3,持仓跟踪!$AC$2:$AC$501,"计划有效")=0,"禁止开仓：请先填写止损计划",IF(账户数据!$B$9+F3*(E3-N3)>=账户数据!$B$7,"禁止开仓：风险额度不足",IF(AJ3="周期与交易预期不匹配，请重新确认",IF(账户数据!$B$23="接近锁仓","允许开仓（接近锁仓；周期需复核）","允许开仓（周期需复核）"),IF(账户数据!$B$23="接近锁仓","允许开仓（接近锁仓）","允许开仓")))))))))) | H3: 3100 | I3: 45135 | J3: 36 | K3: 32.1 | L3: =IF(K3="","",H3) | M3: 45147 | N3: 32.5 | U3: =IF(OR(AO3="",J3="",AO3<=0),"",(J3-AO3)/AO3) | V3: =IF(OR(AO3="",N3="",AO3<=0),"",(AO3-N3)/AO3) | W3: =IF(OR(U3="",V3="",V3<=0),"",U3/V3) | X3: =IF(OR(K3="",L3="",AP3=""),"",K3*L3-(E3*H3+IF(AND(AK3<>"",AL3<>""),AK3*AL3,0)+IF(AND(AM3<>"",AN3<>""),AM3*AN3,0))-IF(O3="",0,O3)-IF(P3="",0,P3)) | Y3: =IF(OR(X3="",AP3=""),"",IF((E3*H3+IF(AND(AK3<>"",AL3<>""),AK3*AL3,0)+IF(AND(AM3<>"",AN3<>""),AM3*AN3,0))+IF(O3="",0,O3)<=0,"",X3/((E3*H3+IF(AND(AK3<>"",AL3<>""),AK3*AL3,0)+IF(AND(AM3<>"",AN3<>""),AM3*AN3,0))+IF(O3="",0,O3)))) | Z3: =IF(OR(AE3="",多次统计数据!$B$8=""),"",AE3-多次统计数据!$B$8) | AA3: =IF(OR(I3="",M3="",M3<I3),"",M3-I3) | AB3: =IF(OR(A3="",多次统计数据!$B$8="",多次统计数据!$B$6<=0,多次统计数据!$B$6>=1),"",1-POWER(1+多次统计数据!$B$8,-多次统计数据!$B$6/(1-多次统计数据!$B$6))) | AC3: =IF(OR(AB3="",多次统计数据!$B$9=""),"",IF(多次统计数据!$B$9<AB3,"低于上限","达到或超过上限")) | AE3: =IF(OR(X3="",C3="",C3<=0),"",X3/C3) | AJ3: =IF(OR(AG3="",AH3=""),"",IF(OR(AND(AG3="短期博反弹",OR(AH3="1～3个交易日",AH3="4～10个交易日")),AND(AG3="突破冲新高",OR(AH3="4～10个交易日",AH3="11～20个交易日")),AND(AG3="趋势波段",OR(AH3="11～20个交易日",AH3="21～60个交易日",AH3="60个交易日以上"))),"匹配","周期与交易预期不匹配，请重新确认")) | AO3: =IF(OR(A3="",H3="",H3<=0),"",(E3*H3+IF(AND(AK3<>"",AL3<>""),AK3*AL3,0)+IF(AND(AM3<>"",AN3<>""),AM3*AN3,0))/AP3) | AP3: =IF(OR(A3="",H3="",H3<=0),"",H3+IF(AL3="",0,AL3)+IF(AN3="",0,AN3)) | AQ3: =IF(A3="","",IF(M3<>"",0,IF(OR(H3="",N3=""),"",MAX(E3-MAX(N3,IFERROR(AGGREGATE(14,6,'持仓跟踪'!$S$2:$S$501/(('持仓跟踪'!$A$2:$A$501="每日跟踪")*('持仓跟踪'!$B$2:$B$501=A3)),1),0)),0)*H3+IF(OR(AK3="",AL3=""),0,MAX(AK3-MAX(N3,IFERROR(AGGREGATE(14,6,'持仓跟踪'!$S$2:$S$501/(('持仓跟踪'!$A$2:$A$501="每日跟踪")*('持仓跟踪'!$B$2:$B$501=A3)),1),0)),0)*AL3)+IF(OR(AM3="",AN3=""),0,MAX(AM3-MAX(N3,IFERROR(AGGREGATE(14,6,'持仓跟踪'!$S$2:$S$501/(('持仓跟踪'!$A$2:$A$501="每日跟踪")*('持仓跟踪'!$B$2:$B$501=A3)),1),0)),0)*AN3)))) | AR3: =IF(A3="","",IF(OR(E3="",H3=""),"违规：第一批价格或股数缺失",IF(OR(AND(AK3="",AL3<>""),AND(AK3<>"",AL3="")),"违规：第二批价格与股数须成对填写",IF(OR(AND(AM3="",AN3<>""),AND(AM3<>"",AN3="")),"违规：第三批价格与股数须成对填写",IF(AND(OR(AM3<>"",AN3<>""),OR(AK3="",AL3="")),"违规：必须先完成第二批",IF(OR(H3<=0,H3<>INT(H3),MOD(H3,100)<>0,AND(AL3<>"",OR(AL3<=0,AL3<>INT(AL3),MOD(AL3,100)<>0)),AND(AN3<>"",OR(AN3<=0,AN3<>INT(AN3),MOD(AN3,100)<>0))),"违规：股数须为100股整数倍",IF(AND(OR(AL3<>"",AN3<>""),OR(_LockStatus="已锁仓",_LockStatus="解锁信息不完整")),"违规：锁仓期间禁止加仓",IF(AQ3>C3*D3,"违规：超过单笔风险上限",IF(SUM($AQ$2:$AQ$201)>账户数据!$B$7,"违规：超过账户风险上限","通过")))))))))
A4: 3 | B4: 长电科技 | C4: 92687 | D4: 0.02 | E4: 28.16 | F4: =IF(OR(C4="",D4="",E4="",N4="",C4<=0,D4<=0,E4<=N4),"",ROUNDDOWN((C4*D4)/(E4-N4)/100,0)*100) | G4: =IF(A4="","",IF(H4<>"","已开仓",IF(账户数据!$B$23="已锁仓","禁止开仓：连续亏损达到上限",IF(账户数据!$B$23="解锁信息不完整","禁止开仓：请完整填写解锁信息",IF(OR(F4="",E4="",N4="",E4<=N4,账户数据!$B$7=""),"",IF(OR(AG4="",AH4="",AI4=""),"禁止开仓：交易预期未填写完整",IF(COUNTIFS(持仓跟踪!$A$2:$A$501,"止损计划",持仓跟踪!$B$2:$B$501,A4,持仓跟踪!$AC$2:$AC$501,"计划有效")=0,"禁止开仓：请先填写止损计划",IF(账户数据!$B$9+F4*(E4-N4)>=账户数据!$B$7,"禁止开仓：风险额度不足",IF(AJ4="周期与交易预期不匹配，请重新确认",IF(账户数据!$B$23="接近锁仓","允许开仓（接近锁仓；周期需复核）","允许开仓（周期需复核）"),IF(账户数据!$B$23="接近锁仓","允许开仓（接近锁仓）","允许开仓")))))))))) | H4: 2800 | I4: 45226 | J4: 30 | K4: 30.2 | L4: =IF(K4="","",H4) | M4: 45231 | N4: 27.5 | R4: 下方支撑位 | S4: 前高 | U4: =IF(OR(AO4="",J4="",AO4<=0),"",(J4-AO4)/AO4) | V4: =IF(OR(AO4="",N4="",AO4<=0),"",(AO4-N4)/AO4) | W4: =IF(OR(U4="",V4="",V4<=0),"",U4/V4) | X4: =IF(OR(K4="",L4="",AP4=""),"",K4*L4-(E4*H4+IF(AND(AK4<>"",AL4<>""),AK4*AL4,0)+IF(AND(AM4<>"",AN4<>""),AM4*AN4,0))-IF(O4="",0,O4)-IF(P4="",0,P4)) | Y4: =IF(OR(X4="",AP4=""),"",IF((E4*H4+IF(AND(AK4<>"",AL4<>""),AK4*AL4,0)+IF(AND(AM4<>"",AN4<>""),AM4*AN4,0))+IF(O4="",0,O4)<=0,"",X4/((E4*H4+IF(AND(AK4<>"",AL4<>""),AK4*AL4,0)+IF(AND(AM4<>"",AN4<>""),AM4*AN4,0))+IF(O4="",0,O4)))) | Z4: =IF(OR(AE4="",多次统计数据!$B$8=""),"",AE4-多次统计数据!$B$8) | AA4: =IF(OR(I4="",M4="",M4<I4),"",M4-I4) | AB4: =IF(OR(A4="",多次统计数据!$B$8="",多次统计数据!$B$6<=0,多次统计数据!$B$6>=1),"",1-POWER(1+多次统计数据!$B$8,-多次统计数据!$B$6/(1-多次统计数据!$B$6))) | AC4: =IF(OR(AB4="",多次统计数据!$B$9=""),"",IF(多次统计数据!$B$9<AB4,"低于上限","达到或超过上限")) | AE4: =IF(OR(X4="",C4="",C4<=0),"",X4/C4) | AJ4: =IF(OR(AG4="",AH4=""),"",IF(OR(AND(AG4="短期博反弹",OR(AH4="1～3个交易日",AH4="4～10个交易日")),AND(AG4="突破冲新高",OR(AH4="4～10个交易日",AH4="11～20个交易日")),AND(AG4="趋势波段",OR(AH4="11～20个交易日",AH4="21～60个交易日",AH4="60个交易日以上"))),"匹配","周期与交易预期不匹配，请重新确认")) | AO4: =IF(OR(A4="",H4="",H4<=0),"",(E4*H4+IF(AND(AK4<>"",AL4<>""),AK4*AL4,0)+IF(AND(AM4<>"",AN4<>""),AM4*AN4,0))/AP4) | AP4: =IF(OR(A4="",H4="",H4<=0),"",H4+IF(AL4="",0,AL4)+IF(AN4="",0,AN4)) | AQ4: =IF(A4="","",IF(M4<>"",0,IF(OR(H4="",N4=""),"",MAX(E4-MAX(N4,IFERROR(AGGREGATE(14,6,'持仓跟踪'!$S$2:$S$501/(('持仓跟踪'!$A$2:$A$501="每日跟踪")*('持仓跟踪'!$B$2:$B$501=A4)),1),0)),0)*H4+IF(OR(AK4="",AL4=""),0,MAX(AK4-MAX(N4,IFERROR(AGGREGATE(14,6,'持仓跟踪'!$S$2:$S$501/(('持仓跟踪'!$A$2:$A$501="每日跟踪")*('持仓跟踪'!$B$2:$B$501=A4)),1),0)),0)*AL4)+IF(OR(AM4="",AN4=""),0,MAX(AM4-MAX(N4,IFERROR(AGGREGATE(14,6,'持仓跟踪'!$S$2:$S$501/(('持仓跟踪'!$A$2:$A$501="每日跟踪")*('持仓跟踪'!$B$2:$B$501=A4)),1),0)),0)*AN4)))) | AR4: =IF(A4="","",IF(OR(E4="",H4=""),"违规：第一批价格或股数缺失",IF(OR(AND(AK4="",AL4<>""),AND(AK4<>"",AL4="")),"违规：第二批价格与股数须成对填写",IF(OR(AND(AM4="",AN4<>""),AND(AM4<>"",AN4="")),"违规：第三批价格与股数须成对填写",IF(AND(OR(AM4<>"",AN4<>""),OR(AK4="",AL4="")),"违规：必须先完成第二批",IF(OR(H4<=0,H4<>INT(H4),MOD(H4,100)<>0,AND(AL4<>"",OR(AL4<=0,AL4<>INT(AL4),MOD(AL4,100)<>0)),AND(AN4<>"",OR(AN4<=0,AN4<>INT(AN4),MOD(AN4,100)<>0))),"违规：股数须为100股整数倍",IF(AND(OR(AL4<>"",AN4<>""),OR(_LockStatus="已锁仓",_LockStatus="解锁信息不完整")),"违规：锁仓期间禁止加仓",IF(AQ4>C4*D4,"违规：超过单笔风险上限",IF(SUM($AQ$2:$AQ$201)>账户数据!$B$7,"违规：超过账户风险上限","通过")))))))))
A5: 4 | B5: 长电科技 | C5: 98399 | D5: 0.02 | E5: 25.78 | F5: =IF(OR(C5="",D5="",E5="",N5="",C5<=0,D5<=0,E5<=N5),"",ROUNDDOWN((C5*D5)/(E5-N5)/100,0)*100) | G5: =IF(A5="","",IF(H5<>"","已开仓",IF(账户数据!$B$23="已锁仓","禁止开仓：连续亏损达到上限",IF(账户数据!$B$23="解锁信息不完整","禁止开仓：请完整填写解锁信息",IF(OR(F5="",E5="",N5="",E5<=N5,账户数据!$B$7=""),"",IF(OR(AG5="",AH5="",AI5=""),"禁止开仓：交易预期未填写完整",IF(COUNTIFS(持仓跟踪!$A$2:$A$501,"止损计划",持仓跟踪!$B$2:$B$501,A5,持仓跟踪!$AC$2:$AC$501,"计划有效")=0,"禁止开仓：请先填写止损计划",IF(账户数据!$B$9+F5*(E5-N5)>=账户数据!$B$7,"禁止开仓：风险额度不足",IF(AJ5="周期与交易预期不匹配，请重新确认",IF(账户数据!$B$23="接近锁仓","允许开仓（接近锁仓；周期需复核）","允许开仓（周期需复核）"),IF(账户数据!$B$23="接近锁仓","允许开仓（接近锁仓）","允许开仓")))))))))) | H5: 2500 | I5: 45306 | J5: 30 | K5: 24.68 | L5: =IF(K5="","",H5) | M5: 45308 | N5: 25 | R5: 下方支撑位 | S5: 前高 | U5: =IF(OR(AO5="",J5="",AO5<=0),"",(J5-AO5)/AO5) | V5: =IF(OR(AO5="",N5="",AO5<=0),"",(AO5-N5)/AO5) | W5: =IF(OR(U5="",V5="",V5<=0),"",U5/V5) | X5: =IF(OR(K5="",L5="",AP5=""),"",K5*L5-(E5*H5+IF(AND(AK5<>"",AL5<>""),AK5*AL5,0)+IF(AND(AM5<>"",AN5<>""),AM5*AN5,0))-IF(O5="",0,O5)-IF(P5="",0,P5)) | Y5: =IF(OR(X5="",AP5=""),"",IF((E5*H5+IF(AND(AK5<>"",AL5<>""),AK5*AL5,0)+IF(AND(AM5<>"",AN5<>""),AM5*AN5,0))+IF(O5="",0,O5)<=0,"",X5/((E5*H5+IF(AND(AK5<>"",AL5<>""),AK5*AL5,0)+IF(AND(AM5<>"",AN5<>""),AM5*AN5,0))+IF(O5="",0,O5)))) | Z5: =IF(OR(AE5="",多次统计数据!$B$8=""),"",AE5-多次统计数据!$B$8) | AA5: =IF(OR(I5="",M5="",M5<I5),"",M5-I5) | AB5: =IF(OR(A5="",多次统计数据!$B$8="",多次统计数据!$B$6<=0,多次统计数据!$B$6>=1),"",1-POWER(1+多次统计数据!$B$8,-多次统计数据!$B$6/(1-多次统计数据!$B$6))) | AC5: =IF(OR(AB5="",多次统计数据!$B$9=""),"",IF(多次统计数据!$B$9<AB5,"低于上限","达到或超过上限")) | AE5: =IF(OR(X5="",C5="",C5<=0),"",X5/C5) | AJ5: =IF(OR(AG5="",AH5=""),"",IF(OR(AND(AG5="短期博反弹",OR(AH5="1～3个交易日",AH5="4～10个交易日")),AND(AG5="突破冲新高",OR(AH5="4～10个交易日",AH5="11～20个交易日")),AND(AG5="趋势波段",OR(AH5="11～20个交易日",AH5="21～60个交易日",AH5="60个交易日以上"))),"匹配","周期与交易预期不匹配，请重新确认")) | AO5: =IF(OR(A5="",H5="",H5<=0),"",(E5*H5+IF(AND(AK5<>"",AL5<>""),AK5*AL5,0)+IF(AND(AM5<>"",AN5<>""),AM5*AN5,0))/AP5) | AP5: =IF(OR(A5="",H5="",H5<=0),"",H5+IF(AL5="",0,AL5)+IF(AN5="",0,AN5)) | AQ5: =IF(A5="","",IF(M5<>"",0,IF(OR(H5="",N5=""),"",MAX(E5-MAX(N5,IFERROR(AGGREGATE(14,6,'持仓跟踪'!$S$2:$S$501/(('持仓跟踪'!$A$2:$A$501="每日跟踪")*('持仓跟踪'!$B$2:$B$501=A5)),1),0)),0)*H5+IF(OR(AK5="",AL5=""),0,MAX(AK5-MAX(N5,IFERROR(AGGREGATE(14,6,'持仓跟踪'!$S$2:$S$501/(('持仓跟踪'!$A$2:$A$501="每日跟踪")*('持仓跟踪'!$B$2:$B$501=A5)),1),0)),0)*AL5)+IF(OR(AM5="",AN5=""),0,MAX(AM5-MAX(N5,IFERROR(AGGREGATE(14,6,'持仓跟踪'!$S$2:$S$501/(('持仓跟踪'!$A$2:$A$501="每日跟踪")*('持仓跟踪'!$B$2:$B$501=A5)),1),0)),0)*AN5)))) | AR5: =IF(A5="","",IF(OR(E5="",H5=""),"违规：第一批价格或股数缺失",IF(OR(AND(AK5="",AL5<>""),AND(AK5<>"",AL5="")),"违规：第二批价格与股数须成对填写",IF(OR(AND(AM5="",AN5<>""),AND(AM5<>"",AN5="")),"违规：第三批价格与股数须成对填写",IF(AND(OR(AM5<>"",AN5<>""),OR(AK5="",AL5="")),"违规：必须先完成第二批",IF(OR(H5<=0,H5<>INT(H5),MOD(H5,100)<>0,AND(AL5<>"",OR(AL5<=0,AL5<>INT(AL5),MOD(AL5,100)<>0)),AND(AN5<>"",OR(AN5<=0,AN5<>INT(AN5),MOD(AN5,100)<>0))),"违规：股数须为100股整数倍",IF(AND(OR(AL5<>"",AN5<>""),OR(_LockStatus="已锁仓",_LockStatus="解锁信息不完整")),"违规：锁仓期间禁止加仓",IF(AQ5>C5*D5,"违规：超过单笔风险上限",IF(SUM($AQ$2:$AQ$201)>账户数据!$B$7,"违规：超过账户风险上限","通过")))))))))
A6: 5 | B6: 长电科技 | C6: 95649 | D6: 0.02 | E6: 35 | F6: =IF(OR(C6="",D6="",E6="",N6="",C6<=0,D6<=0,E6<=N6),"",ROUNDDOWN((C6*D6)/(E6-N6)/100,0)*100) | G6: =IF(A6="","",IF(H6<>"","已开仓",IF(账户数据!$B$23="已锁仓","禁止开仓：连续亏损达到上限",IF(账户数据!$B$23="解锁信息不完整","禁止开仓：请完整填写解锁信息",IF(OR(F6="",E6="",N6="",E6<=N6,账户数据!$B$7=""),"",IF(OR(AG6="",AH6="",AI6=""),"禁止开仓：交易预期未填写完整",IF(COUNTIFS(持仓跟踪!$A$2:$A$501,"止损计划",持仓跟踪!$B$2:$B$501,A6,持仓跟踪!$AC$2:$AC$501,"计划有效")=0,"禁止开仓：请先填写止损计划",IF(账户数据!$B$9+F6*(E6-N6)>=账户数据!$B$7,"禁止开仓：风险额度不足",IF(AJ6="周期与交易预期不匹配，请重新确认",IF(账户数据!$B$23="接近锁仓","允许开仓（接近锁仓；周期需复核）","允许开仓（周期需复核）"),IF(账户数据!$B$23="接近锁仓","允许开仓（接近锁仓）","允许开仓")))))))))) | H6: 900 | I6: 45491 | J6: 40 | K6: 31.84 | L6: =IF(K6="","",H6) | M6: 45498 | N6: 33 | R6: 下发支撑位 | S6: 从收益率的角度推断 | U6: =IF(OR(AO6="",J6="",AO6<=0),"",(J6-AO6)/AO6) | V6: =IF(OR(AO6="",N6="",AO6<=0),"",(AO6-N6)/AO6) | W6: =IF(OR(U6="",V6="",V6<=0),"",U6/V6) | X6: =IF(OR(K6="",L6="",AP6=""),"",K6*L6-(E6*H6+IF(AND(AK6<>"",AL6<>""),AK6*AL6,0)+IF(AND(AM6<>"",AN6<>""),AM6*AN6,0))-IF(O6="",0,O6)-IF(P6="",0,P6)) | Y6: =IF(OR(X6="",AP6=""),"",IF((E6*H6+IF(AND(AK6<>"",AL6<>""),AK6*AL6,0)+IF(AND(AM6<>"",AN6<>""),AM6*AN6,0))+IF(O6="",0,O6)<=0,"",X6/((E6*H6+IF(AND(AK6<>"",AL6<>""),AK6*AL6,0)+IF(AND(AM6<>"",AN6<>""),AM6*AN6,0))+IF(O6="",0,O6)))) | Z6: =IF(OR(AE6="",多次统计数据!$B$8=""),"",AE6-多次统计数据!$B$8) | AA6: =IF(OR(I6="",M6="",M6<I6),"",M6-I6) | AB6: =IF(OR(A6="",多次统计数据!$B$8="",多次统计数据!$B$6<=0,多次统计数据!$B$6>=1),"",1-POWER(1+多次统计数据!$B$8,-多次统计数据!$B$6/(1-多次统计数据!$B$6))) | AC6: =IF(OR(AB6="",多次统计数据!$B$9=""),"",IF(多次统计数据!$B$9<AB6,"低于上限","达到或超过上限")) | AE6: =IF(OR(X6="",C6="",C6<=0),"",X6/C6) | AJ6: =IF(OR(AG6="",AH6=""),"",IF(OR(AND(AG6="短期博反弹",OR(AH6="1～3个交易日",AH6="4～10个交易日")),AND(AG6="突破冲新高",OR(AH6="4～10个交易日",AH6="11～20个交易日")),AND(AG6="趋势波段",OR(AH6="11～20个交易日",AH6="21～60个交易日",AH6="60个交易日以上"))),"匹配","周期与交易预期不匹配，请重新确认")) | AO6: =IF(OR(A6="",H6="",H6<=0),"",(E6*H6+IF(AND(AK6<>"",AL6<>""),AK6*AL6,0)+IF(AND(AM6<>"",AN6<>""),AM6*AN6,0))/AP6) | AP6: =IF(OR(A6="",H6="",H6<=0),"",H6+IF(AL6="",0,AL6)+IF(AN6="",0,AN6)) | AQ6: =IF(A6="","",IF(M6<>"",0,IF(OR(H6="",N6=""),"",MAX(E6-MAX(N6,IFERROR(AGGREGATE(14,6,'持仓跟踪'!$S$2:$S$501/(('持仓跟踪'!$A$2:$A$501="每日跟踪")*('持仓跟踪'!$B$2:$B$501=A6)),1),0)),0)*H6+IF(OR(AK6="",AL6=""),0,MAX(AK6-MAX(N6,IFERROR(AGGREGATE(14,6,'持仓跟踪'!$S$2:$S$501/(('持仓跟踪'!$A$2:$A$501="每日跟踪")*('持仓跟踪'!$B$2:$B$501=A6)),1),0)),0)*AL6)+IF(OR(AM6="",AN6=""),0,MAX(AM6-MAX(N6,IFERROR(AGGREGATE(14,6,'持仓跟踪'!$S$2:$S$501/(('持仓跟踪'!$A$2:$A$501="每日跟踪")*('持仓跟踪'!$B$2:$B$501=A6)),1),0)),0)*AN6)))) | AR6: =IF(A6="","",IF(OR(E6="",H6=""),"违规：第一批价格或股数缺失",IF(OR(AND(AK6="",AL6<>""),AND(AK6<>"",AL6="")),"违规：第二批价格与股数须成对填写",IF(OR(AND(AM6="",AN6<>""),AND(AM6<>"",AN6="")),"违规：第三批价格与股数须成对填写",IF(AND(OR(AM6<>"",AN6<>""),OR(AK6="",AL6="")),"违规：必须先完成第二批",IF(OR(H6<=0,H6<>INT(H6),MOD(H6,100)<>0,AND(AL6<>"",OR(AL6<=0,AL6<>INT(AL6),MOD(AL6,100)<>0)),AND(AN6<>"",OR(AN6<=0,AN6<>INT(AN6),MOD(AN6,100)<>0))),"违规：股数须为100股整数倍",IF(AND(OR(AL6<>"",AN6<>""),OR(_LockStatus="已锁仓",_LockStatus="解锁信息不完整")),"违规：锁仓期间禁止加仓",IF(AQ6>C6*D6,"违规：超过单笔风险上限",IF(SUM($AQ$2:$AQ$201)>账户数据!$B$7,"违规：超过账户风险上限","通过")))))))))
A7: 6 | B7: 长电科技 | C7: 92805 | D7: 0.02 | E7: 30.78 | F7: =IF(OR(C7="",D7="",E7="",N7="",C7<=0,D7<=0,E7<=N7),"",ROUNDDOWN((C7*D7)/(E7-N7)/100,0)*100) | G7: =IF(A7="","",IF(H7<>"","已开仓",IF(账户数据!$B$23="已锁仓","禁止开仓：连续亏损达到上限",IF(账户数据!$B$23="解锁信息不完整","禁止开仓：请完整填写解锁信息",IF(OR(F7="",E7="",N7="",E7<=N7,账户数据!$B$7=""),"",IF(OR(AG7="",AH7="",AI7=""),"禁止开仓：交易预期未填写完整",IF(COUNTIFS(持仓跟踪!$A$2:$A$501,"止损计划",持仓跟踪!$B$2:$B$501,A7,持仓跟踪!$AC$2:$AC$501,"计划有效")=0,"禁止开仓：请先填写止损计划",IF(账户数据!$B$9+F7*(E7-N7)>=账户数据!$B$7,"禁止开仓：风险额度不足",IF(AJ7="周期与交易预期不匹配，请重新确认",IF(账户数据!$B$23="接近锁仓","允许开仓（接近锁仓；周期需复核）","允许开仓（周期需复核）"),IF(账户数据!$B$23="接近锁仓","允许开仓（接近锁仓）","允许开仓")))))))))) | H7: 6600 | I7: 45537 | J7: 34 | K7: 30.23 | L7: =IF(K7="","",H7) | M7: 45559 | N7: 30.5 | U7: =IF(OR(AO7="",J7="",AO7<=0),"",(J7-AO7)/AO7) | V7: =IF(OR(AO7="",N7="",AO7<=0),"",(AO7-N7)/AO7) | W7: =IF(OR(U7="",V7="",V7<=0),"",U7/V7) | X7: =IF(OR(K7="",L7="",AP7=""),"",K7*L7-(E7*H7+IF(AND(AK7<>"",AL7<>""),AK7*AL7,0)+IF(AND(AM7<>"",AN7<>""),AM7*AN7,0))-IF(O7="",0,O7)-IF(P7="",0,P7)) | Y7: =IF(OR(X7="",AP7=""),"",IF((E7*H7+IF(AND(AK7<>"",AL7<>""),AK7*AL7,0)+IF(AND(AM7<>"",AN7<>""),AM7*AN7,0))+IF(O7="",0,O7)<=0,"",X7/((E7*H7+IF(AND(AK7<>"",AL7<>""),AK7*AL7,0)+IF(AND(AM7<>"",AN7<>""),AM7*AN7,0))+IF(O7="",0,O7)))) | Z7: =IF(OR(AE7="",多次统计数据!$B$8=""),"",AE7-多次统计数据!$B$8) | AA7: =IF(OR(I7="",M7="",M7<I7),"",M7-I7) | AB7: =IF(OR(A7="",多次统计数据!$B$8="",多次统计数据!$B$6<=0,多次统计数据!$B$6>=1),"",1-POWER(1+多次统计数据!$B$8,-多次统计数据!$B$6/(1-多次统计数据!$B$6))) | AC7: =IF(OR(AB7="",多次统计数据!$B$9=""),"",IF(多次统计数据!$B$9<AB7,"低于上限","达到或超过上限")) | AE7: =IF(OR(X7="",C7="",C7<=0),"",X7/C7) | AJ7: =IF(OR(AG7="",AH7=""),"",IF(OR(AND(AG7="短期博反弹",OR(AH7="1～3个交易日",AH7="4～10个交易日")),AND(AG7="突破冲新高",OR(AH7="4～10个交易日",AH7="11～20个交易日")),AND(AG7="趋势波段",OR(AH7="11～20个交易日",AH7="21～60个交易日",AH7="60个交易日以上"))),"匹配","周期与交易预期不匹配，请重新确认")) | AO7: =IF(OR(A7="",H7="",H7<=0),"",(E7*H7+IF(AND(AK7<>"",AL7<>""),AK7*AL7,0)+IF(AND(AM7<>"",AN7<>""),AM7*AN7,0))/AP7) | AP7: =IF(OR(A7="",H7="",H7<=0),"",H7+IF(AL7="",0,AL7)+IF(AN7="",0,AN7)) | AQ7: =IF(A7="","",IF(M7<>"",0,IF(OR(H7="",N7=""),"",MAX(E7-MAX(N7,IFERROR(AGGREGATE(14,6,'持仓跟踪'!$S$2:$S$501/(('持仓跟踪'!$A$2:$A$501="每日跟踪")*('持仓跟踪'!$B$2:$B$501=A7)),1),0)),0)*H7+IF(OR(AK7="",AL7=""),0,MAX(AK7-MAX(N7,IFERROR(AGGREGATE(14,6,'持仓跟踪'!$S$2:$S$501/(('持仓跟踪'!$A$2:$A$501="每日跟踪")*('持仓跟踪'!$B$2:$B$501=A7)),1),0)),0)*AL7)+IF(OR(AM7="",AN7=""),0,MAX(AM7-MAX(N7,IFERROR(AGGREGATE(14,6,'持仓跟踪'!$S$2:$S$501/(('持仓跟踪'!$A$2:$A$501="每日跟踪")*('持仓跟踪'!$B$2:$B$501=A7)),1),0)),0)*AN7)))) | AR7: =IF(A7="","",IF(OR(E7="",H7=""),"违规：第一批价格或股数缺失",IF(OR(AND(AK7="",AL7<>""),AND(AK7<>"",AL7="")),"违规：第二批价格与股数须成对填写",IF(OR(AND(AM7="",AN7<>""),AND(AM7<>"",AN7="")),"违规：第三批价格与股数须成对填写",IF(AND(OR(AM7<>"",AN7<>""),OR(AK7="",AL7="")),"违规：必须先完成第二批",IF(OR(H7<=0,H7<>INT(H7),MOD(H7,100)<>0,AND(AL7<>"",OR(AL7<=0,AL7<>INT(AL7),MOD(AL7,100)<>0)),AND(AN7<>"",OR(AN7<=0,AN7<>INT(AN7),MOD(AN7,100)<>0))),"违规：股数须为100股整数倍",IF(AND(OR(AL7<>"",AN7<>""),OR(_LockStatus="已锁仓",_LockStatus="解锁信息不完整")),"违规：锁仓期间禁止加仓",IF(AQ7>C7*D7,"违规：超过单笔风险上限",IF(SUM($AQ$2:$AQ$201)>账户数据!$B$7,"违规：超过账户风险上限","通过")))))))))
F8: =IF(OR(C8="",D8="",E8="",N8="",C8<=0,D8<=0,E8<=N8),"",ROUNDDOWN((C8*D8)/(E8-N8)/100,0)*100) | G8: =IF(A8="","",IF(H8<>"","已开仓",IF(账户数据!$B$23="已锁仓","禁止开仓：连续亏损达到上限",IF(账户数据!$B$23="解锁信息不完整","禁止开仓：请完整填写解锁信息",IF(OR(F8="",E8="",N8="",E8<=N8,账户数据!$B$7=""),"",IF(OR(AG8="",AH8="",AI8=""),"禁止开仓：交易预期未填写完整",IF(COUNTIFS(持仓跟踪!$A$2:$A$501,"止损计划",持仓跟踪!$B$2:$B$501,A8,持仓跟踪!$AC$2:$AC$501,"计划有效")=0,"禁止开仓：请先填写止损计划",IF(账户数据!$B$9+F8*(E8-N8)>=账户数据!$B$7,"禁止开仓：风险额度不足",IF(AJ8="周期与交易预期不匹配，请重新确认",IF(账户数据!$B$23="接近锁仓","允许开仓（接近锁仓；周期需复核）","允许开仓（周期需复核）"),IF(账户数据!$B$23="接近锁仓","允许开仓（接近锁仓）","允许开仓")))))))))) | L8: =IF(K8="","",H8) | U8: =IF(OR(AO8="",J8="",AO8<=0),"",(J8-AO8)/AO8) | V8: =IF(OR(AO8="",N8="",AO8<=0),"",(AO8-N8)/AO8) | W8: =IF(OR(U8="",V8="",V8<=0),"",U8/V8) | X8: =IF(OR(K8="",L8="",AP8=""),"",K8*L8-(E8*H8+IF(AND(AK8<>"",AL8<>""),AK8*AL8,0)+IF(AND(AM8<>"",AN8<>""),AM8*AN8,0))-IF(O8="",0,O8)-IF(P8="",0,P8)) | Y8: =IF(OR(X8="",AP8=""),"",IF((E8*H8+IF(AND(AK8<>"",AL8<>""),AK8*AL8,0)+IF(AND(AM8<>"",AN8<>""),AM8*AN8,0))+IF(O8="",0,O8)<=0,"",X8/((E8*H8+IF(AND(AK8<>"",AL8<>""),AK8*AL8,0)+IF(AND(AM8<>"",AN8<>""),AM8*AN8,0))+IF(O8="",0,O8)))) | Z8: =IF(OR(AE8="",多次统计数据!$B$8=""),"",AE8-多次统计数据!$B$8) | AA8: =IF(OR(I8="",M8="",M8<I8),"",M8-I8) | AB8: =IF(OR(A8="",多次统计数据!$B$8="",多次统计数据!$B$6<=0,多次统计数据!$B$6>=1),"",1-POWER(1+多次统计数据!$B$8,-多次统计数据!$B$6/(1-多次统计数据!$B$6))) | AC8: =IF(OR(AB8="",多次统计数据!$B$9=""),"",IF(多次统计数据!$B$9<AB8,"低于上限","达到或超过上限")) | AE8: =IF(OR(X8="",C8="",C8<=0),"",X8/C8) | AJ8: =IF(OR(AG8="",AH8=""),"",IF(OR(AND(AG8="短期博反弹",OR(AH8="1～3个交易日",AH8="4～10个交易日")),AND(AG8="突破冲新高",OR(AH8="4～10个交易日",AH8="11～20个交易日")),AND(AG8="趋势波段",OR(AH8="11～20个交易日",AH8="21～60个交易日",AH8="60个交易日以上"))),"匹配","周期与交易预期不匹配，请重新确认")) | AO8: =IF(OR(A8="",H8="",H8<=0),"",(E8*H8+IF(AND(AK8<>"",AL8<>""),AK8*AL8,0)+IF(AND(AM8<>"",AN8<>""),AM8*AN8,0))/AP8) | AP8: =IF(OR(A8="",H8="",H8<=0),"",H8+IF(AL8="",0,AL8)+IF(AN8="",0,AN8)) | AQ8: =IF(A8="","",IF(M8<>"",0,IF(OR(H8="",N8=""),"",MAX(E8-MAX(N8,IFERROR(AGGREGATE(14,6,'持仓跟踪'!$S$2:$S$501/(('持仓跟踪'!$A$2:$A$501="每日跟踪")*('持仓跟踪'!$B$2:$B$501=A8)),1),0)),0)*H8+IF(OR(AK8="",AL8=""),0,MAX(AK8-MAX(N8,IFERROR(AGGREGATE(14,6,'持仓跟踪'!$S$2:$S$501/(('持仓跟踪'!$A$2:$A$501="每日跟踪")*('持仓跟踪'!$B$2:$B$501=A8)),1),0)),0)*AL8)+IF(OR(AM8="",AN8=""),0,MAX(AM8-MAX(N8,IFERROR(AGGREGATE(14,6,'持仓跟踪'!$S$2:$S$501/(('持仓跟踪'!$A$2:$A$501="每日跟踪")*('持仓跟踪'!$B$2:$B$501=A8)),1),0)),0)*AN8)))) | AR8: =IF(A8="","",IF(OR(E8="",H8=""),"违规：第一批价格或股数缺失",IF(OR(AND(AK8="",AL8<>""),AND(AK8<>"",AL8="")),"违规：第二批价格与股数须成对填写",IF(OR(AND(AM8="",AN8<>""),AND(AM8<>"",AN8="")),"违规：第三批价格与股数须成对填写",IF(AND(OR(AM8<>"",AN8<>""),OR(AK8="",AL8="")),"违规：必须先完成第二批",IF(OR(H8<=0,H8<>INT(H8),MOD(H8,100)<>0,AND(AL8<>"",OR(AL8<=0,AL8<>INT(AL8),MOD(AL8,100)<>0)),AND(AN8<>"",OR(AN8<=0,AN8<>INT(AN8),MOD(AN8,100)<>0))),"违规：股数须为100股整数倍",IF(AND(OR(AL8<>"",AN8<>""),OR(_LockStatus="已锁仓",_LockStatus="解锁信息不完整")),"违规：锁仓期间禁止加仓",IF(AQ8>C8*D8,"违规：超过单笔风险上限",IF(SUM($AQ$2:$AQ$201)>账户数据!$B$7,"违规：超过账户风险上限","通过")))))))))
F9: =IF(OR(C9="",D9="",E9="",N9="",C9<=0,D9<=0,E9<=N9),"",ROUNDDOWN((C9*D9)/(E9-N9)/100,0)*100) | G9: =IF(A9="","",IF(H9<>"","已开仓",IF(账户数据!$B$23="已锁仓","禁止开仓：连续亏损达到上限",IF(账户数据!$B$23="解锁信息不完整","禁止开仓：请完整填写解锁信息",IF(OR(F9="",E9="",N9="",E9<=N9,账户数据!$B$7=""),"",IF(OR(AG9="",AH9="",AI9=""),"禁止开仓：交易预期未填写完整",IF(COUNTIFS(持仓跟踪!$A$2:$A$501,"止损计划",持仓跟踪!$B$2:$B$501,A9,持仓跟踪!$AC$2:$AC$501,"计划有效")=0,"禁止开仓：请先填写止损计划",IF(账户数据!$B$9+F9*(E9-N9)>=账户数据!$B$7,"禁止开仓：风险额度不足",IF(AJ9="周期与交易预期不匹配，请重新确认",IF(账户数据!$B$23="接近锁仓","允许开仓（接近锁仓；周期需复核）","允许开仓（周期需复核）"),IF(账户数据!$B$23="接近锁仓","允许开仓（接近锁仓）","允许开仓")))))))))) | L9: =IF(K9="","",H9) | U9: =IF(OR(AO9="",J9="",AO9<=0),"",(J9-AO9)/AO9) | V9: =IF(OR(AO9="",N9="",AO9<=0),"",(AO9-N9)/AO9) | W9: =IF(OR(U9="",V9="",V9<=0),"",U9/V9) | X9: =IF(OR(K9="",L9="",AP9=""),"",K9*L9-(E9*H9+IF(AND(AK9<>"",AL9<>""),AK9*AL9,0)+IF(AND(AM9<>"",AN9<>""),AM9*AN9,0))-IF(O9="",0,O9)-IF(P9="",0,P9)) | Y9: =IF(OR(X9="",AP9=""),"",IF((E9*H9+IF(AND(AK9<>"",AL9<>""),AK9*AL9,0)+IF(AND(AM9<>"",AN9<>""),AM9*AN9,0))+IF(O9="",0,O9)<=0,"",X9/((E9*H9+IF(AND(AK9<>"",AL9<>""),AK9*AL9,0)+IF(AND(AM9<>"",AN9<>""),AM9*AN9,0))+IF(O9="",0,O9)))) | Z9: =IF(OR(AE9="",多次统计数据!$B$8=""),"",AE9-多次统计数据!$B$8) | AA9: =IF(OR(I9="",M9="",M9<I9),"",M9-I9) | AB9: =IF(OR(A9="",多次统计数据!$B$8="",多次统计数据!$B$6<=0,多次统计数据!$B$6>=1),"",1-POWER(1+多次统计数据!$B$8,-多次统计数据!$B$6/(1-多次统计数据!$B$6))) | AC9: =IF(OR(AB9="",多次统计数据!$B$9=""),"",IF(多次统计数据!$B$9<AB9,"低于上限","达到或超过上限")) | AE9: =IF(OR(X9="",C9="",C9<=0),"",X9/C9) | AJ9: =IF(OR(AG9="",AH9=""),"",IF(OR(AND(AG9="短期博反弹",OR(AH9="1～3个交易日",AH9="4～10个交易日")),AND(AG9="突破冲新高",OR(AH9="4～10个交易日",AH9="11～20个交易日")),AND(AG9="趋势波段",OR(AH9="11～20个交易日",AH9="21～60个交易日",AH9="60个交易日以上"))),"匹配","周期与交易预期不匹配，请重新确认")) | AO9: =IF(OR(A9="",H9="",H9<=0),"",(E9*H9+IF(AND(AK9<>"",AL9<>""),AK9*AL9,0)+IF(AND(AM9<>"",AN9<>""),AM9*AN9,0))/AP9) | AP9: =IF(OR(A9="",H9="",H9<=0),"",H9+IF(AL9="",0,AL9)+IF(AN9="",0,AN9)) | AQ9: =IF(A9="","",IF(M9<>"",0,IF(OR(H9="",N9=""),"",MAX(E9-MAX(N9,IFERROR(AGGREGATE(14,6,'持仓跟踪'!$S$2:$S$501/(('持仓跟踪'!$A$2:$A$501="每日跟踪")*('持仓跟踪'!$B$2:$B$501=A9)),1),0)),0)*H9+IF(OR(AK9="",AL9=""),0,MAX(AK9-MAX(N9,IFERROR(AGGREGATE(14,6,'持仓跟踪'!$S$2:$S$501/(('持仓跟踪'!$A$2:$A$501="每日跟踪")*('持仓跟踪'!$B$2:$B$501=A9)),1),0)),0)*AL9)+IF(OR(AM9="",AN9=""),0,MAX(AM9-MAX(N9,IFERROR(AGGREGATE(14,6,'持仓跟踪'!$S$2:$S$501/(('持仓跟踪'!$A$2:$A$501="每日跟踪")*('持仓跟踪'!$B$2:$B$501=A9)),1),0)),0)*AN9)))) | AR9: =IF(A9="","",IF(OR(E9="",H9=""),"违规：第一批价格或股数缺失",IF(OR(AND(AK9="",AL9<>""),AND(AK9<>"",AL9="")),"违规：第二批价格与股数须成对填写",IF(OR(AND(AM9="",AN9<>""),AND(AM9<>"",AN9="")),"违规：第三批价格与股数须成对填写",IF(AND(OR(AM9<>"",AN9<>""),OR(AK9="",AL9="")),"违规：必须先完成第二批",IF(OR(H9<=0,H9<>INT(H9),MOD(H9,100)<>0,AND(AL9<>"",OR(AL9<=0,AL9<>INT(AL9),MOD(AL9,100)<>0)),AND(AN9<>"",OR(AN9<=0,AN9<>INT(AN9),MOD(AN9,100)<>0))),"违规：股数须为100股整数倍",IF(AND(OR(AL9<>"",AN9<>""),OR(_LockStatus="已锁仓",_LockStatus="解锁信息不完整")),"违规：锁仓期间禁止加仓",IF(AQ9>C9*D9,"违规：超过单笔风险上限",IF(SUM($AQ$2:$AQ$201)>账户数据!$B$7,"违规：超过账户风险上限","通过")))))))))
A10: 9 | B10: 北方稀土 | C10: 89175 | D10: 0.02 | E10: 16.87 | F10: =IF(OR(C10="",D10="",E10="",N10="",C10<=0,D10<=0,E10<=N10),"",ROUNDDOWN((C10*D10)/(E10-N10)/100,0)*100) | G10: =IF(A10="","",IF(H10<>"","已开仓",IF(账户数据!$B$23="已锁仓","禁止开仓：连续亏损达到上限",IF(账户数据!$B$23="解锁信息不完整","禁止开仓：请完整填写解锁信息",IF(OR(F10="",E10="",N10="",E10<=N10,账户数据!$B$7=""),"",IF(OR(AG10="",AH10="",AI10=""),"禁止开仓：交易预期未填写完整",IF(COUNTIFS(持仓跟踪!$A$2:$A$501,"止损计划",持仓跟踪!$B$2:$B$501,A10,持仓跟踪!$AC$2:$AC$501,"计划有效")=0,"禁止开仓：请先填写止损计划",IF(账户数据!$B$9+F10*(E10-N10)>=账户数据!$B$7,"禁止开仓：风险额度不足",IF(AJ10="周期与交易预期不匹配，请重新确认",IF(账户数据!$B$23="接近锁仓","允许开仓（接近锁仓；周期需复核）","允许开仓（周期需复核）"),IF(账户数据!$B$23="接近锁仓","允许开仓（接近锁仓）","允许开仓")))))))))) | H10: 4200 | I10: 45559 | J10: 18 | K10: 19.73 | L10: =IF(K10="","",H10) | M10: 45576 | N10: 16.45 | R10: 下方支撑位 | S10: 前方高点，整数位，凑一下啊盈亏比 | U10: =IF(OR(AO10="",J10="",AO10<=0),"",(J10-AO10)/AO10) | V10: =IF(OR(AO10="",N10="",AO10<=0),"",(AO10-N10)/AO10) | W10: =IF(OR(U10="",V10="",V10<=0),"",U10/V10) | X10: =IF(OR(K10="",L10="",AP10=""),"",K10*L10-(E10*H10+IF(AND(AK10<>"",AL10<>""),AK10*AL10,0)+IF(AND(AM10<>"",AN10<>""),AM10*AN10,0))-IF(O10="",0,O10)-IF(P10="",0,P10)) | Y10: =IF(OR(X10="",AP10=""),"",IF((E10*H10+IF(AND(AK10<>"",AL10<>""),AK10*AL10,0)+IF(AND(AM10<>"",AN10<>""),AM10*AN10,0))+IF(O10="",0,O10)<=0,"",X10/((E10*H10+IF(AND(AK10<>"",AL10<>""),AK10*AL10,0)+IF(AND(AM10<>"",AN10<>""),AM10*AN10,0))+IF(O10="",0,O10)))) | Z10: =IF(OR(AE10="",多次统计数据!$B$8=""),"",AE10-多次统计数据!$B$8) | AA10: =IF(OR(I10="",M10="",M10<I10),"",M10-I10) | AB10: =IF(OR(A10="",多次统计数据!$B$8="",多次统计数据!$B$6<=0,多次统计数据!$B$6>=1),"",1-POWER(1+多次统计数据!$B$8,-多次统计数据!$B$6/(1-多次统计数据!$B$6))) | AC10: =IF(OR(AB10="",多次统计数据!$B$9=""),"",IF(多次统计数据!$B$9<AB10,"低于上限","达到或超过上限")) | AE10: =IF(OR(X10="",C10="",C10<=0),"",X10/C10) | AJ10: =IF(OR(AG10="",AH10=""),"",IF(OR(AND(AG10="短期博反弹",OR(AH10="1～3个交易日",AH10="4～10个交易日")),AND(AG10="突破冲新高",OR(AH10="4～10个交易日",AH10="11～20个交易日")),AND(AG10="趋势波段",OR(AH10="11～20个交易日",AH10="21～60个交易日",AH10="60个交易日以上"))),"匹配","周期与交易预期不匹配，请重新确认")) | AO10: =IF(OR(A10="",H10="",H10<=0),"",(E10*H10+IF(AND(AK10<>"",AL10<>""),AK10*AL10,0)+IF(AND(AM10<>"",AN10<>""),AM10*AN10,0))/AP10) | AP10: =IF(OR(A10="",H10="",H10<=0),"",H10+IF(AL10="",0,AL10)+IF(AN10="",0,AN10)) | AQ10: =IF(A10="","",IF(M10<>"",0,IF(OR(H10="",N10=""),"",MAX(E10-MAX(N10,IFERROR(AGGREGATE(14,6,'持仓跟踪'!$S$2:$S$501/(('持仓跟踪'!$A$2:$A$501="每日跟踪")*('持仓跟踪'!$B$2:$B$501=A10)),1),0)),0)*H10+IF(OR(AK10="",AL10=""),0,MAX(AK10-MAX(N10,IFERROR(AGGREGATE(14,6,'持仓跟踪'!$S$2:$S$501/(('持仓跟踪'!$A$2:$A$501="每日跟踪")*('持仓跟踪'!$B$2:$B$501=A10)),1),0)),0)*AL10)+IF(OR(AM10="",AN10=""),0,MAX(AM10-MAX(N10,IFERROR(AGGREGATE(14,6,'持仓跟踪'!$S$2:$S$501/(('持仓跟踪'!$A$2:$A$501="每日跟踪")*('持仓跟踪'!$B$2:$B$501=A10)),1),0)),0)*AN10)))) | AR10: =IF(A10="","",IF(OR(E10="",H10=""),"违规：第一批价格或股数缺失",IF(OR(AND(AK10="",AL10<>""),AND(AK10<>"",AL10="")),"违规：第二批价格与股数须成对填写",IF(OR(AND(AM10="",AN10<>""),AND(AM10<>"",AN10="")),"违规：第三批价格与股数须成对填写",IF(AND(OR(AM10<>"",AN10<>""),OR(AK10="",AL10="")),"违规：必须先完成第二批",IF(OR(H10<=0,H10<>INT(H10),MOD(H10,100)<>0,AND(AL10<>"",OR(AL10<=0,AL10<>INT(AL10),MOD(AL10,100)<>0)),AND(AN10<>"",OR(AN10<=0,AN10<>INT(AN10),MOD(AN10,100)<>0))),"违规：股数须为100股整数倍",IF(AND(OR(AL10<>"",AN10<>""),OR(_LockStatus="已锁仓",_LockStatus="解锁信息不完整")),"违规：锁仓期间禁止加仓",IF(AQ10>C10*D10,"违规：超过单笔风险上限",IF(SUM($AQ$2:$AQ$201)>账户数据!$B$7,"违规：超过账户风险上限","通过")))))))))
A11: 10 | B11: 北方稀土 | C11: 101187 | D11: 0.02 | E11: 24.41 | F11: =IF(OR(C11="",D11="",E11="",N11="",C11<=0,D11<=0,E11<=N11),"",ROUNDDOWN((C11*D11)/(E11-N11)/100,0)*100) | G11: =IF(A11="","",IF(H11<>"","已开仓",IF(账户数据!$B$23="已锁仓","禁止开仓：连续亏损达到上限",IF(账户数据!$B$23="解锁信息不完整","禁止开仓：请完整填写解锁信息",IF(OR(F11="",E11="",N11="",E11<=N11,账户数据!$B$7=""),"",IF(OR(AG11="",AH11="",AI11=""),"禁止开仓：交易预期未填写完整",IF(COUNTIFS(持仓跟踪!$A$2:$A$501,"止损计划",持仓跟踪!$B$2:$B$501,A11,持仓跟踪!$AC$2:$AC$501,"计划有效")=0,"禁止开仓：请先填写止损计划",IF(账户数据!$B$9+F11*(E11-N11)>=账户数据!$B$7,"禁止开仓：风险额度不足",IF(AJ11="周期与交易预期不匹配，请重新确认",IF(账户数据!$B$23="接近锁仓","允许开仓（接近锁仓；周期需复核）","允许开仓（周期需复核）"),IF(账户数据!$B$23="接近锁仓","允许开仓（接近锁仓）","允许开仓")))))))))) | H11: 1800 | I11: 45783 | J11: 26.8 | K11: 23.19 | L11: =IF(K11="","",H11) | M11: 45799 | N11: 23.3 | U11: =IF(OR(AO11="",J11="",AO11<=0),"",(J11-AO11)/AO11) | V11: =IF(OR(AO11="",N11="",AO11<=0),"",(AO11-N11)/AO11) | W11: =IF(OR(U11="",V11="",V11<=0),"",U11/V11) | X11: =IF(OR(K11="",L11="",AP11=""),"",K11*L11-(E11*H11+IF(AND(AK11<>"",AL11<>""),AK11*AL11,0)+IF(AND(AM11<>"",AN11<>""),AM11*AN11,0))-IF(O11="",0,O11)-IF(P11="",0,P11)) | Y11: =IF(OR(X11="",AP11=""),"",IF((E11*H11+IF(AND(AK11<>"",AL11<>""),AK11*AL11,0)+IF(AND(AM11<>"",AN11<>""),AM11*AN11,0))+IF(O11="",0,O11)<=0,"",X11/((E11*H11+IF(AND(AK11<>"",AL11<>""),AK11*AL11,0)+IF(AND(AM11<>"",AN11<>""),AM11*AN11,0))+IF(O11="",0,O11)))) | Z11: =IF(OR(AE11="",多次统计数据!$B$8=""),"",AE11-多次统计数据!$B$8) | AA11: =IF(OR(I11="",M11="",M11<I11),"",M11-I11) | AB11: =IF(OR(A11="",多次统计数据!$B$8="",多次统计数据!$B$6<=0,多次统计数据!$B$6>=1),"",1-POWER(1+多次统计数据!$B$8,-多次统计数据!$B$6/(1-多次统计数据!$B$6))) | AC11: =IF(OR(AB11="",多次统计数据!$B$9=""),"",IF(多次统计数据!$B$9<AB11,"低于上限","达到或超过上限")) | AE11: =IF(OR(X11="",C11="",C11<=0),"",X11/C11) | AJ11: =IF(OR(AG11="",AH11=""),"",IF(OR(AND(AG11="短期博反弹",OR(AH11="1～3个交易日",AH11="4～10个交易日")),AND(AG11="突破冲新高",OR(AH11="4～10个交易日",AH11="11～20个交易日")),AND(AG11="趋势波段",OR(AH11="11～20个交易日",AH11="21～60个交易日",AH11="60个交易日以上"))),"匹配","周期与交易预期不匹配，请重新确认")) | AO11: =IF(OR(A11="",H11="",H11<=0),"",(E11*H11+IF(AND(AK11<>"",AL11<>""),AK11*AL11,0)+IF(AND(AM11<>"",AN11<>""),AM11*AN11,0))/AP11) | AP11: =IF(OR(A11="",H11="",H11<=0),"",H11+IF(AL11="",0,AL11)+IF(AN11="",0,AN11)) | AQ11: =IF(A11="","",IF(M11<>"",0,IF(OR(H11="",N11=""),"",MAX(E11-MAX(N11,IFERROR(AGGREGATE(14,6,'持仓跟踪'!$S$2:$S$501/(('持仓跟踪'!$A$2:$A$501="每日跟踪")*('持仓跟踪'!$B$2:$B$501=A11)),1),0)),0)*H11+IF(OR(AK11="",AL11=""),0,MAX(AK11-MAX(N11,IFERROR(AGGREGATE(14,6,'持仓跟踪'!$S$2:$S$501/(('持仓跟踪'!$A$2:$A$501="每日跟踪")*('持仓跟踪'!$B$2:$B$501=A11)),1),0)),0)*AL11)+IF(OR(AM11="",AN11=""),0,MAX(AM11-MAX(N11,IFERROR(AGGREGATE(14,6,'持仓跟踪'!$S$2:$S$501/(('持仓跟踪'!$A$2:$A$501="每日跟踪")*('持仓跟踪'!$B$2:$B$501=A11)),1),0)),0)*AN11)))) | AR11: =IF(A11="","",IF(OR(E11="",H11=""),"违规：第一批价格或股数缺失",IF(OR(AND(AK11="",AL11<>""),AND(AK11<>"",AL11="")),"违规：第二批价格与股数须成对填写",IF(OR(AND(AM11="",AN11<>""),AND(AM11<>"",AN11="")),"违规：第三批价格与股数须成对填写",IF(AND(OR(AM11<>"",AN11<>""),OR(AK11="",AL11="")),"违规：必须先完成第二批",IF(OR(H11<=0,H11<>INT(H11),MOD(H11,100)<>0,AND(AL11<>"",OR(AL11<=0,AL11<>INT(AL11),MOD(AL11,100)<>0)),AND(AN11<>"",OR(AN11<=0,AN11<>INT(AN11),MOD(AN11,100)<>0))),"违规：股数须为100股整数倍",IF(AND(OR(AL11<>"",AN11<>""),OR(_LockStatus="已锁仓",_LockStatus="解锁信息不完整")),"违规：锁仓期间禁止加仓",IF(AQ11>C11*D11,"违规：超过单笔风险上限",IF(SUM($AQ$2:$AQ$201)>账户数据!$B$7,"违规：超过账户风险上限","通过")))))))))
A12: 11 | B12: 赛轮轮胎 | C12: 98991 | D12: 0.02 | E12: 8.22 | F12: =IF(OR(C12="",D12="",E12="",N12="",C12<=0,D12<=0,E12<=N12),"",ROUNDDOWN((C12*D12)/(E12-N12)/100,0)*100) | G12: =IF(A12="","",IF(H12<>"","已开仓",IF(账户数据!$B$23="已锁仓","禁止开仓：连续亏损达到上限",IF(账户数据!$B$23="解锁信息不完整","禁止开仓：请完整填写解锁信息",IF(OR(F12="",E12="",N12="",E12<=N12,账户数据!$B$7=""),"",IF(OR(AG12="",AH12="",AI12=""),"禁止开仓：交易预期未填写完整",IF(COUNTIFS(持仓跟踪!$A$2:$A$501,"止损计划",持仓跟踪!$B$2:$B$501,A12,持仓跟踪!$AC$2:$AC$501,"计划有效")=0,"禁止开仓：请先填写止损计划",IF(账户数据!$B$9+F12*(E12-N12)>=账户数据!$B$7,"禁止开仓：风险额度不足",IF(AJ12="周期与交易预期不匹配，请重新确认",IF(账户数据!$B$23="接近锁仓","允许开仓（接近锁仓；周期需复核）","允许开仓（周期需复核）"),IF(账户数据!$B$23="接近锁仓","允许开仓（接近锁仓）","允许开仓")))))))))) | H12: 3100 | I12: 44867 | J12: 9.5 | K12: 8.44 | L12: =IF(K12="","",H12) | M12: 44923 | N12: 7.6 | R12: 前方支撑位 | S12: 前方高点 | U12: =IF(OR(AO12="",J12="",AO12<=0),"",(J12-AO12)/AO12) | V12: =IF(OR(AO12="",N12="",AO12<=0),"",(AO12-N12)/AO12) | W12: =IF(OR(U12="",V12="",V12<=0),"",U12/V12) | X12: =IF(OR(K12="",L12="",AP12=""),"",K12*L12-(E12*H12+IF(AND(AK12<>"",AL12<>""),AK12*AL12,0)+IF(AND(AM12<>"",AN12<>""),AM12*AN12,0))-IF(O12="",0,O12)-IF(P12="",0,P12)) | Y12: =IF(OR(X12="",AP12=""),"",IF((E12*H12+IF(AND(AK12<>"",AL12<>""),AK12*AL12,0)+IF(AND(AM12<>"",AN12<>""),AM12*AN12,0))+IF(O12="",0,O12)<=0,"",X12/((E12*H12+IF(AND(AK12<>"",AL12<>""),AK12*AL12,0)+IF(AND(AM12<>"",AN12<>""),AM12*AN12,0))+IF(O12="",0,O12)))) | Z12: =IF(OR(AE12="",多次统计数据!$B$8=""),"",AE12-多次统计数据!$B$8) | AA12: =IF(OR(I12="",M12="",M12<I12),"",M12-I12) | AB12: =IF(OR(A12="",多次统计数据!$B$8="",多次统计数据!$B$6<=0,多次统计数据!$B$6>=1),"",1-POWER(1+多次统计数据!$B$8,-多次统计数据!$B$6/(1-多次统计数据!$B$6))) | AC12: =IF(OR(AB12="",多次统计数据!$B$9=""),"",IF(多次统计数据!$B$9<AB12,"低于上限","达到或超过上限")) | AE12: =IF(OR(X12="",C12="",C12<=0),"",X12/C12) | AJ12: =IF(OR(AG12="",AH12=""),"",IF(OR(AND(AG12="短期博反弹",OR(AH12="1～3个交易日",AH12="4～10个交易日")),AND(AG12="突破冲新高",OR(AH12="4～10个交易日",AH12="11～20个交易日")),AND(AG12="趋势波段",OR(AH12="11～20个交易日",AH12="21～60个交易日",AH12="60个交易日以上"))),"匹配","周期与交易预期不匹配，请重新确认")) | AO12: =IF(OR(A12="",H12="",H12<=0),"",(E12*H12+IF(AND(AK12<>"",AL12<>""),AK12*AL12,0)+IF(AND(AM12<>"",AN12<>""),AM12*AN12,0))/AP12) | AP12: =IF(OR(A12="",H12="",H12<=0),"",H12+IF(AL12="",0,AL12)+IF(AN12="",0,AN12)) | AQ12: =IF(A12="","",IF(M12<>"",0,IF(OR(H12="",N12=""),"",MAX(E12-MAX(N12,IFERROR(AGGREGATE(14,6,'持仓跟踪'!$S$2:$S$501/(('持仓跟踪'!$A$2:$A$501="每日跟踪")*('持仓跟踪'!$B$2:$B$501=A12)),1),0)),0)*H12+IF(OR(AK12="",AL12=""),0,MAX(AK12-MAX(N12,IFERROR(AGGREGATE(14,6,'持仓跟踪'!$S$2:$S$501/(('持仓跟踪'!$A$2:$A$501="每日跟踪")*('持仓跟踪'!$B$2:$B$501=A12)),1),0)),0)*AL12)+IF(OR(AM12="",AN12=""),0,MAX(AM12-MAX(N12,IFERROR(AGGREGATE(14,6,'持仓跟踪'!$S$2:$S$501/(('持仓跟踪'!$A$2:$A$501="每日跟踪")*('持仓跟踪'!$B$2:$B$501=A12)),1),0)),0)*AN12)))) | AR12: =IF(A12="","",IF(OR(E12="",H12=""),"违规：第一批价格或股数缺失",IF(OR(AND(AK12="",AL12<>""),AND(AK12<>"",AL12="")),"违规：第二批价格与股数须成对填写",IF(OR(AND(AM12="",AN12<>""),AND(AM12<>"",AN12="")),"违规：第三批价格与股数须成对填写",IF(AND(OR(AM12<>"",AN12<>""),OR(AK12="",AL12="")),"违规：必须先完成第二批",IF(OR(H12<=0,H12<>INT(H12),MOD(H12,100)<>0,AND(AL12<>"",OR(AL12<=0,AL12<>INT(AL12),MOD(AL12,100)<>0)),AND(AN12<>"",OR(AN12<=0,AN12<>INT(AN12),MOD(AN12,100)<>0))),"违规：股数须为100股整数倍",IF(AND(OR(AL12<>"",AN12<>""),OR(_LockStatus="已锁仓",_LockStatus="解锁信息不完整")),"违规：锁仓期间禁止加仓",IF(AQ12>C12*D12,"违规：超过单笔风险上限",IF(SUM($AQ$2:$AQ$201)>账户数据!$B$7,"违规：超过账户风险上限","通过")))))))))
A13: 12 | B13: 赛轮轮胎 | C13: 99673 | D13: 0.02 | E13: 10.38 | F13: =IF(OR(C13="",D13="",E13="",N13="",C13<=0,D13<=0,E13<=N13),"",ROUNDDOWN((C13*D13)/(E13-N13)/100,0)*100) | G13: =IF(A13="","",IF(H13<>"","已开仓",IF(账户数据!$B$23="已锁仓","禁止开仓：连续亏损达到上限",IF(账户数据!$B$23="解锁信息不完整","禁止开仓：请完整填写解锁信息",IF(OR(F13="",E13="",N13="",E13<=N13,账户数据!$B$7=""),"",IF(OR(AG13="",AH13="",AI13=""),"禁止开仓：交易预期未填写完整",IF(COUNTIFS(持仓跟踪!$A$2:$A$501,"止损计划",持仓跟踪!$B$2:$B$501,A13,持仓跟踪!$AC$2:$AC$501,"计划有效")=0,"禁止开仓：请先填写止损计划",IF(账户数据!$B$9+F13*(E13-N13)>=账户数据!$B$7,"禁止开仓：风险额度不足",IF(AJ13="周期与交易预期不匹配，请重新确认",IF(账户数据!$B$23="接近锁仓","允许开仓（接近锁仓；周期需复核）","允许开仓（周期需复核）"),IF(账户数据!$B$23="接近锁仓","允许开仓（接近锁仓）","允许开仓")))))))))) | H13: 2200 | I13: 44979 | J13: 12.17 | K13: 9.55 | L13: =IF(K13="","",H13) | M13: 44995 | N13: 9.5 | R13: 前方支撑区域 | S13: 前方高点 | U13: =IF(OR(AO13="",J13="",AO13<=0),"",(J13-AO13)/AO13) | V13: =IF(OR(AO13="",N13="",AO13<=0),"",(AO13-N13)/AO13) | W13: =IF(OR(U13="",V13="",V13<=0),"",U13/V13) | X13: =IF(OR(K13="",L13="",AP13=""),"",K13*L13-(E13*H13+IF(AND(AK13<>"",AL13<>""),AK13*AL13,0)+IF(AND(AM13<>"",AN13<>""),AM13*AN13,0))-IF(O13="",0,O13)-IF(P13="",0,P13)) | Y13: =IF(OR(X13="",AP13=""),"",IF((E13*H13+IF(AND(AK13<>"",AL13<>""),AK13*AL13,0)+IF(AND(AM13<>"",AN13<>""),AM13*AN13,0))+IF(O13="",0,O13)<=0,"",X13/((E13*H13+IF(AND(AK13<>"",AL13<>""),AK13*AL13,0)+IF(AND(AM13<>"",AN13<>""),AM13*AN13,0))+IF(O13="",0,O13)))) | Z13: =IF(OR(AE13="",多次统计数据!$B$8=""),"",AE13-多次统计数据!$B$8) | AA13: =IF(OR(I13="",M13="",M13<I13),"",M13-I13) | AB13: =IF(OR(A13="",多次统计数据!$B$8="",多次统计数据!$B$6<=0,多次统计数据!$B$6>=1),"",1-POWER(1+多次统计数据!$B$8,-多次统计数据!$B$6/(1-多次统计数据!$B$6))) | AC13: =IF(OR(AB13="",多次统计数据!$B$9=""),"",IF(多次统计数据!$B$9<AB13,"低于上限","达到或超过上限")) | AE13: =IF(OR(X13="",C13="",C13<=0),"",X13/C13) | AJ13: =IF(OR(AG13="",AH13=""),"",IF(OR(AND(AG13="短期博反弹",OR(AH13="1～3个交易日",AH13="4～10个交易日")),AND(AG13="突破冲新高",OR(AH13="4～10个交易日",AH13="11～20个交易日")),AND(AG13="趋势波段",OR(AH13="11～20个交易日",AH13="21～60个交易日",AH13="60个交易日以上"))),"匹配","周期与交易预期不匹配，请重新确认")) | AO13: =IF(OR(A13="",H13="",H13<=0),"",(E13*H13+IF(AND(AK13<>"",AL13<>""),AK13*AL13,0)+IF(AND(AM13<>"",AN13<>""),AM13*AN13,0))/AP13) | AP13: =IF(OR(A13="",H13="",H13<=0),"",H13+IF(AL13="",0,AL13)+IF(AN13="",0,AN13)) | AQ13: =IF(A13="","",IF(M13<>"",0,IF(OR(H13="",N13=""),"",MAX(E13-MAX(N13,IFERROR(AGGREGATE(14,6,'持仓跟踪'!$S$2:$S$501/(('持仓跟踪'!$A$2:$A$501="每日跟踪")*('持仓跟踪'!$B$2:$B$501=A13)),1),0)),0)*H13+IF(OR(AK13="",AL13=""),0,MAX(AK13-MAX(N13,IFERROR(AGGREGATE(14,6,'持仓跟踪'!$S$2:$S$501/(('持仓跟踪'!$A$2:$A$501="每日跟踪")*('持仓跟踪'!$B$2:$B$501=A13)),1),0)),0)*AL13)+IF(OR(AM13="",AN13=""),0,MAX(AM13-MAX(N13,IFERROR(AGGREGATE(14,6,'持仓跟踪'!$S$2:$S$501/(('持仓跟踪'!$A$2:$A$501="每日跟踪")*('持仓跟踪'!$B$2:$B$501=A13)),1),0)),0)*AN13)))) | AR13: =IF(A13="","",IF(OR(E13="",H13=""),"违规：第一批价格或股数缺失",IF(OR(AND(AK13="",AL13<>""),AND(AK13<>"",AL13="")),"违规：第二批价格与股数须成对填写",IF(OR(AND(AM13="",AN13<>""),AND(AM13<>"",AN13="")),"违规：第三批价格与股数须成对填写",IF(AND(OR(AM13<>"",AN13<>""),OR(AK13="",AL13="")),"违规：必须先完成第二批",IF(OR(H13<=0,H13<>INT(H13),MOD(H13,100)<>0,AND(AL13<>"",OR(AL13<=0,AL13<>INT(AL13),MOD(AL13,100)<>0)),AND(AN13<>"",OR(AN13<=0,AN13<>INT(AN13),MOD(AN13,100)<>0))),"违规：股数须为100股整数倍",IF(AND(OR(AL13<>"",AN13<>""),OR(_LockStatus="已锁仓",_LockStatus="解锁信息不完整")),"违规：锁仓期间禁止加仓",IF(AQ13>C13*D13,"违规：超过单笔风险上限",IF(SUM($AQ$2:$AQ$201)>账户数据!$B$7,"违规：超过账户风险上限","通过")))))))))
A14: 13 | B14: 赛轮轮胎 | C14: 97847 | D14: 0.02 | E14: 10.49 | F14: =IF(OR(C14="",D14="",E14="",N14="",C14<=0,D14<=0,E14<=N14),"",ROUNDDOWN((C14*D14)/(E14-N14)/100,0)*100) | G14: =IF(A14="","",IF(H14<>"","已开仓",IF(账户数据!$B$23="已锁仓","禁止开仓：连续亏损达到上限",IF(账户数据!$B$23="解锁信息不完整","禁止开仓：请完整填写解锁信息",IF(OR(F14="",E14="",N14="",E14<=N14,账户数据!$B$7=""),"",IF(OR(AG14="",AH14="",AI14=""),"禁止开仓：交易预期未填写完整",IF(COUNTIFS(持仓跟踪!$A$2:$A$501,"止损计划",持仓跟踪!$B$2:$B$501,A14,持仓跟踪!$AC$2:$AC$501,"计划有效")=0,"禁止开仓：请先填写止损计划",IF(账户数据!$B$9+F14*(E14-N14)>=账户数据!$B$7,"禁止开仓：风险额度不足",IF(AJ14="周期与交易预期不匹配，请重新确认",IF(账户数据!$B$23="接近锁仓","允许开仓（接近锁仓；周期需复核）","允许开仓（周期需复核）"),IF(账户数据!$B$23="接近锁仓","允许开仓（接近锁仓）","允许开仓")))))))))) | H14: 3900 | I14: 45106 | J14: 12 | K14: 10.73 | L14: =IF(K14="","",H14) | M14: 45119 | N14: 10 | R14: 前方支撑区域 | S14: 新高 | U14: =IF(OR(AO14="",J14="",AO14<=0),"",(J14-AO14)/AO14) | V14: =IF(OR(AO14="",N14="",AO14<=0),"",(AO14-N14)/AO14) | W14: =IF(OR(U14="",V14="",V14<=0),"",U14/V14) | X14: =IF(OR(K14="",L14="",AP14=""),"",K14*L14-(E14*H14+IF(AND(AK14<>"",AL14<>""),AK14*AL14,0)+IF(AND(AM14<>"",AN14<>""),AM14*AN14,0))-IF(O14="",0,O14)-IF(P14="",0,P14)) | Y14: =IF(OR(X14="",AP14=""),"",IF((E14*H14+IF(AND(AK14<>"",AL14<>""),AK14*AL14,0)+IF(AND(AM14<>"",AN14<>""),AM14*AN14,0))+IF(O14="",0,O14)<=0,"",X14/((E14*H14+IF(AND(AK14<>"",AL14<>""),AK14*AL14,0)+IF(AND(AM14<>"",AN14<>""),AM14*AN14,0))+IF(O14="",0,O14)))) | Z14: =IF(OR(AE14="",多次统计数据!$B$8=""),"",AE14-多次统计数据!$B$8) | AA14: =IF(OR(I14="",M14="",M14<I14),"",M14-I14) | AB14: =IF(OR(A14="",多次统计数据!$B$8="",多次统计数据!$B$6<=0,多次统计数据!$B$6>=1),"",1-POWER(1+多次统计数据!$B$8,-多次统计数据!$B$6/(1-多次统计数据!$B$6))) | AC14: =IF(OR(AB14="",多次统计数据!$B$9=""),"",IF(多次统计数据!$B$9<AB14,"低于上限","达到或超过上限")) | AE14: =IF(OR(X14="",C14="",C14<=0),"",X14/C14) | AJ14: =IF(OR(AG14="",AH14=""),"",IF(OR(AND(AG14="短期博反弹",OR(AH14="1～3个交易日",AH14="4～10个交易日")),AND(AG14="突破冲新高",OR(AH14="4～10个交易日",AH14="11～20个交易日")),AND(AG14="趋势波段",OR(AH14="11～20个交易日",AH14="21～60个交易日",AH14="60个交易日以上"))),"匹配","周期与交易预期不匹配，请重新确认")) | AO14: =IF(OR(A14="",H14="",H14<=0),"",(E14*H14+IF(AND(AK14<>"",AL14<>""),AK14*AL14,0)+IF(AND(AM14<>"",AN14<>""),AM14*AN14,0))/AP14) | AP14: =IF(OR(A14="",H14="",H14<=0),"",H14+IF(AL14="",0,AL14)+IF(AN14="",0,AN14)) | AQ14: =IF(A14="","",IF(M14<>"",0,IF(OR(H14="",N14=""),"",MAX(E14-MAX(N14,IFERROR(AGGREGATE(14,6,'持仓跟踪'!$S$2:$S$501/(('持仓跟踪'!$A$2:$A$501="每日跟踪")*('持仓跟踪'!$B$2:$B$501=A14)),1),0)),0)*H14+IF(OR(AK14="",AL14=""),0,MAX(AK14-MAX(N14,IFERROR(AGGREGATE(14,6,'持仓跟踪'!$S$2:$S$501/(('持仓跟踪'!$A$2:$A$501="每日跟踪")*('持仓跟踪'!$B$2:$B$501=A14)),1),0)),0)*AL14)+IF(OR(AM14="",AN14=""),0,MAX(AM14-MAX(N14,IFERROR(AGGREGATE(14,6,'持仓跟踪'!$S$2:$S$501/(('持仓跟踪'!$A$2:$A$501="每日跟踪")*('持仓跟踪'!$B$2:$B$501=A14)),1),0)),0)*AN14)))) | AR14: =IF(A14="","",IF(OR(E14="",H14=""),"违规：第一批价格或股数缺失",IF(OR(AND(AK14="",AL14<>""),AND(AK14<>"",AL14="")),"违规：第二批价格与股数须成对填写",IF(OR(AND(AM14="",AN14<>""),AND(AM14<>"",AN14="")),"违规：第三批价格与股数须成对填写",IF(AND(OR(AM14<>"",AN14<>""),OR(AK14="",AL14="")),"违规：必须先完成第二批",IF(OR(H14<=0,H14<>INT(H14),MOD(H14,100)<>0,AND(AL14<>"",OR(AL14<=0,AL14<>INT(AL14),MOD(AL14,100)<>0)),AND(AN14<>"",OR(AN14<=0,AN14<>INT(AN14),MOD(AN14,100)<>0))),"违规：股数须为100股整数倍",IF(AND(OR(AL14<>"",AN14<>""),OR(_LockStatus="已锁仓",_LockStatus="解锁信息不完整")),"违规：锁仓期间禁止加仓",IF(AQ14>C14*D14,"违规：超过单笔风险上限",IF(SUM($AQ$2:$AQ$201)>账户数据!$B$7,"违规：超过账户风险上限","通过")))))))))
A15: 14 | B15: 赛轮轮胎 | C15: 98783 | D15: 0.02 | E15: 10.44 | F15: =IF(OR(C15="",D15="",E15="",N15="",C15<=0,D15<=0,E15<=N15),"",ROUNDDOWN((C15*D15)/(E15-N15)/100,0)*100) | G15: =IF(A15="","",IF(H15<>"","已开仓",IF(账户数据!$B$23="已锁仓","禁止开仓：连续亏损达到上限",IF(账户数据!$B$23="解锁信息不完整","禁止开仓：请完整填写解锁信息",IF(OR(F15="",E15="",N15="",E15<=N15,账户数据!$B$7=""),"",IF(OR(AG15="",AH15="",AI15=""),"禁止开仓：交易预期未填写完整",IF(COUNTIFS(持仓跟踪!$A$2:$A$501,"止损计划",持仓跟踪!$B$2:$B$501,A15,持仓跟踪!$AC$2:$AC$501,"计划有效")=0,"禁止开仓：请先填写止损计划",IF(账户数据!$B$9+F15*(E15-N15)>=账户数据!$B$7,"禁止开仓：风险额度不足",IF(AJ15="周期与交易预期不匹配，请重新确认",IF(账户数据!$B$23="接近锁仓","允许开仓（接近锁仓；周期需复核）","允许开仓（周期需复核）"),IF(账户数据!$B$23="接近锁仓","允许开仓（接近锁仓）","允许开仓")))))))))) | H15: 7500 | I15: 45320 | J15: 11 | K15: 11.3 | L15: =IF(K15="","",H15) | M15: 45323 | N15: 10.18 | U15: =IF(OR(AO15="",J15="",AO15<=0),"",(J15-AO15)/AO15) | V15: =IF(OR(AO15="",N15="",AO15<=0),"",(AO15-N15)/AO15) | W15: =IF(OR(U15="",V15="",V15<=0),"",U15/V15) | X15: =IF(OR(K15="",L15="",AP15=""),"",K15*L15-(E15*H15+IF(AND(AK15<>"",AL15<>""),AK15*AL15,0)+IF(AND(AM15<>"",AN15<>""),AM15*AN15,0))-IF(O15="",0,O15)-IF(P15="",0,P15)) | Y15: =IF(OR(X15="",AP15=""),"",IF((E15*H15+IF(AND(AK15<>"",AL15<>""),AK15*AL15,0)+IF(AND(AM15<>"",AN15<>""),AM15*AN15,0))+IF(O15="",0,O15)<=0,"",X15/((E15*H15+IF(AND(AK15<>"",AL15<>""),AK15*AL15,0)+IF(AND(AM15<>"",AN15<>""),AM15*AN15,0))+IF(O15="",0,O15)))) | Z15: =IF(OR(AE15="",多次统计数据!$B$8=""),"",AE15-多次统计数据!$B$8) | AA15: =IF(OR(I15="",M15="",M15<I15),"",M15-I15) | AB15: =IF(OR(A15="",多次统计数据!$B$8="",多次统计数据!$B$6<=0,多次统计数据!$B$6>=1),"",1-POWER(1+多次统计数据!$B$8,-多次统计数据!$B$6/(1-多次统计数据!$B$6))) | AC15: =IF(OR(AB15="",多次统计数据!$B$9=""),"",IF(多次统计数据!$B$9<AB15,"低于上限","达到或超过上限")) | AE15: =IF(OR(X15="",C15="",C15<=0),"",X15/C15) | AJ15: =IF(OR(AG15="",AH15=""),"",IF(OR(AND(AG15="短期博反弹",OR(AH15="1～3个交易日",AH15="4～10个交易日")),AND(AG15="突破冲新高",OR(AH15="4～10个交易日",AH15="11～20个交易日")),AND(AG15="趋势波段",OR(AH15="11～20个交易日",AH15="21～60个交易日",AH15="60个交易日以上"))),"匹配","周期与交易预期不匹配，请重新确认")) | AO15: =IF(OR(A15="",H15="",H15<=0),"",(E15*H15+IF(AND(AK15<>"",AL15<>""),AK15*AL15,0)+IF(AND(AM15<>"",AN15<>""),AM15*AN15,0))/AP15) | AP15: =IF(OR(A15="",H15="",H15<=0),"",H15+IF(AL15="",0,AL15)+IF(AN15="",0,AN15)) | AQ15: =IF(A15="","",IF(M15<>"",0,IF(OR(H15="",N15=""),"",MAX(E15-MAX(N15,IFERROR(AGGREGATE(14,6,'持仓跟踪'!$S$2:$S$501/(('持仓跟踪'!$A$2:$A$501="每日跟踪")*('持仓跟踪'!$B$2:$B$501=A15)),1),0)),0)*H15+IF(OR(AK15="",AL15=""),0,MAX(AK15-MAX(N15,IFERROR(AGGREGATE(14,6,'持仓跟踪'!$S$2:$S$501/(('持仓跟踪'!$A$2:$A$501="每日跟踪")*('持仓跟踪'!$B$2:$B$501=A15)),1),0)),0)*AL15)+IF(OR(AM15="",AN15=""),0,MAX(AM15-MAX(N15,IFERROR(AGGREGATE(14,6,'持仓跟踪'!$S$2:$S$501/(('持仓跟踪'!$A$2:$A$501="每日跟踪")*('持仓跟踪'!$B$2:$B$501=A15)),1),0)),0)*AN15)))) | AR15: =IF(A15="","",IF(OR(E15="",H15=""),"违规：第一批价格或股数缺失",IF(OR(AND(AK15="",AL15<>""),AND(AK15<>"",AL15="")),"违规：第二批价格与股数须成对填写",IF(OR(AND(AM15="",AN15<>""),AND(AM15<>"",AN15="")),"违规：第三批价格与股数须成对填写",IF(AND(OR(AM15<>"",AN15<>""),OR(AK15="",AL15="")),"违规：必须先完成第二批",IF(OR(H15<=0,H15<>INT(H15),MOD(H15,100)<>0,AND(AL15<>"",OR(AL15<=0,AL15<>INT(AL15),MOD(AL15,100)<>0)),AND(AN15<>"",OR(AN15<=0,AN15<>INT(AN15),MOD(AN15,100)<>0))),"违规：股数须为100股整数倍",IF(AND(OR(AL15<>"",AN15<>""),OR(_LockStatus="已锁仓",_LockStatus="解锁信息不完整")),"违规：锁仓期间禁止加仓",IF(AQ15>C15*D15,"违规：超过单笔风险上限",IF(SUM($AQ$2:$AQ$201)>账户数据!$B$7,"违规：超过账户风险上限","通过")))))))))
A16: 15 | B16: 赛轮轮胎 | C16: 105233 | D16: 0.02 | E16: 14.37 | F16: =IF(OR(C16="",D16="",E16="",N16="",C16<=0,D16<=0,E16<=N16),"",ROUNDDOWN((C16*D16)/(E16-N16)/100,0)*100) | G16: =IF(A16="","",IF(H16<>"","已开仓",IF(账户数据!$B$23="已锁仓","禁止开仓：连续亏损达到上限",IF(账户数据!$B$23="解锁信息不完整","禁止开仓：请完整填写解锁信息",IF(OR(F16="",E16="",N16="",E16<=N16,账户数据!$B$7=""),"",IF(OR(AG16="",AH16="",AI16=""),"禁止开仓：交易预期未填写完整",IF(COUNTIFS(持仓跟踪!$A$2:$A$501,"止损计划",持仓跟踪!$B$2:$B$501,A16,持仓跟踪!$AC$2:$AC$501,"计划有效")=0,"禁止开仓：请先填写止损计划",IF(账户数据!$B$9+F16*(E16-N16)>=账户数据!$B$7,"禁止开仓：风险额度不足",IF(AJ16="周期与交易预期不匹配，请重新确认",IF(账户数据!$B$23="接近锁仓","允许开仓（接近锁仓；周期需复核）","允许开仓（周期需复核）"),IF(账户数据!$B$23="接近锁仓","允许开仓（接近锁仓）","允许开仓")))))))))) | H16: 5000 | I16: 45562 | J16: 16 | K16: 14.01 | L16: =IF(K16="","",H16) | M16: 45574 | N16: 14 | U16: =IF(OR(AO16="",J16="",AO16<=0),"",(J16-AO16)/AO16) | V16: =IF(OR(AO16="",N16="",AO16<=0),"",(AO16-N16)/AO16) | W16: =IF(OR(U16="",V16="",V16<=0),"",U16/V16) | X16: =IF(OR(K16="",L16="",AP16=""),"",K16*L16-(E16*H16+IF(AND(AK16<>"",AL16<>""),AK16*AL16,0)+IF(AND(AM16<>"",AN16<>""),AM16*AN16,0))-IF(O16="",0,O16)-IF(P16="",0,P16)) | Y16: =IF(OR(X16="",AP16=""),"",IF((E16*H16+IF(AND(AK16<>"",AL16<>""),AK16*AL16,0)+IF(AND(AM16<>"",AN16<>""),AM16*AN16,0))+IF(O16="",0,O16)<=0,"",X16/((E16*H16+IF(AND(AK16<>"",AL16<>""),AK16*AL16,0)+IF(AND(AM16<>"",AN16<>""),AM16*AN16,0))+IF(O16="",0,O16)))) | Z16: =IF(OR(AE16="",多次统计数据!$B$8=""),"",AE16-多次统计数据!$B$8) | AA16: =IF(OR(I16="",M16="",M16<I16),"",M16-I16) | AB16: =IF(OR(A16="",多次统计数据!$B$8="",多次统计数据!$B$6<=0,多次统计数据!$B$6>=1),"",1-POWER(1+多次统计数据!$B$8,-多次统计数据!$B$6/(1-多次统计数据!$B$6))) | AC16: =IF(OR(AB16="",多次统计数据!$B$9=""),"",IF(多次统计数据!$B$9<AB16,"低于上限","达到或超过上限")) | AE16: =IF(OR(X16="",C16="",C16<=0),"",X16/C16) | AJ16: =IF(OR(AG16="",AH16=""),"",IF(OR(AND(AG16="短期博反弹",OR(AH16="1～3个交易日",AH16="4～10个交易日")),AND(AG16="突破冲新高",OR(AH16="4～10个交易日",AH16="11～20个交易日")),AND(AG16="趋势波段",OR(AH16="11～20个交易日",AH16="21～60个交易日",AH16="60个交易日以上"))),"匹配","周期与交易预期不匹配，请重新确认")) | AO16: =IF(OR(A16="",H16="",H16<=0),"",(E16*H16+IF(AND(AK16<>"",AL16<>""),AK16*AL16,0)+IF(AND(AM16<>"",AN16<>""),AM16*AN16,0))/AP16) | AP16: =IF(OR(A16="",H16="",H16<=0),"",H16+IF(AL16="",0,AL16)+IF(AN16="",0,AN16)) | AQ16: =IF(A16="","",IF(M16<>"",0,IF(OR(H16="",N16=""),"",MAX(E16-MAX(N16,IFERROR(AGGREGATE(14,6,'持仓跟踪'!$S$2:$S$501/(('持仓跟踪'!$A$2:$A$501="每日跟踪")*('持仓跟踪'!$B$2:$B$501=A16)),1),0)),0)*H16+IF(OR(AK16="",AL16=""),0,MAX(AK16-MAX(N16,IFERROR(AGGREGATE(14,6,'持仓跟踪'!$S$2:$S$501/(('持仓跟踪'!$A$2:$A$501="每日跟踪")*('持仓跟踪'!$B$2:$B$501=A16)),1),0)),0)*AL16)+IF(OR(AM16="",AN16=""),0,MAX(AM16-MAX(N16,IFERROR(AGGREGATE(14,6,'持仓跟踪'!$S$2:$S$501/(('持仓跟踪'!$A$2:$A$501="每日跟踪")*('持仓跟踪'!$B$2:$B$501=A16)),1),0)),0)*AN16)))) | AR16: =IF(A16="","",IF(OR(E16="",H16=""),"违规：第一批价格或股数缺失",IF(OR(AND(AK16="",AL16<>""),AND(AK16<>"",AL16="")),"违规：第二批价格与股数须成对填写",IF(OR(AND(AM16="",AN16<>""),AND(AM16<>"",AN16="")),"违规：第三批价格与股数须成对填写",IF(AND(OR(AM16<>"",AN16<>""),OR(AK16="",AL16="")),"违规：必须先完成第二批",IF(OR(H16<=0,H16<>INT(H16),MOD(H16,100)<>0,AND(AL16<>"",OR(AL16<=0,AL16<>INT(AL16),MOD(AL16,100)<>0)),AND(AN16<>"",OR(AN16<=0,AN16<>INT(AN16),MOD(AN16,100)<>0))),"违规：股数须为100股整数倍",IF(AND(OR(AL16<>"",AN16<>""),OR(_LockStatus="已锁仓",_LockStatus="解锁信息不完整")),"违规：锁仓期间禁止加仓",IF(AQ16>C16*D16,"违规：超过单笔风险上限",IF(SUM($AQ$2:$AQ$201)>账户数据!$B$7,"违规：超过账户风险上限","通过")))))))))
A17: 16 | B17: 赛轮轮胎 | C17: 103433 | D17: 0.02 | E17: 14.86 | F17: =IF(OR(C17="",D17="",E17="",N17="",C17<=0,D17<=0,E17<=N17),"",ROUNDDOWN((C17*D17)/(E17-N17)/100,0)*100) | G17: =IF(A17="","",IF(H17<>"","已开仓",IF(账户数据!$B$23="已锁仓","禁止开仓：连续亏损达到上限",IF(账户数据!$B$23="解锁信息不完整","禁止开仓：请完整填写解锁信息",IF(OR(F17="",E17="",N17="",E17<=N17,账户数据!$B$7=""),"",IF(OR(AG17="",AH17="",AI17=""),"禁止开仓：交易预期未填写完整",IF(COUNTIFS(持仓跟踪!$A$2:$A$501,"止损计划",持仓跟踪!$B$2:$B$501,A17,持仓跟踪!$AC$2:$AC$501,"计划有效")=0,"禁止开仓：请先填写止损计划",IF(账户数据!$B$9+F17*(E17-N17)>=账户数据!$B$7,"禁止开仓：风险额度不足",IF(AJ17="周期与交易预期不匹配，请重新确认",IF(账户数据!$B$23="接近锁仓","允许开仓（接近锁仓；周期需复核）","允许开仓（周期需复核）"),IF(账户数据!$B$23="接近锁仓","允许开仓（接近锁仓）","允许开仓")))))))))) | H17: 3000 | I17: 45674 | J17: 16 | K17: 15.17 | L17: =IF(K17="","",H17) | M17: 45716 | N17: 14 | U17: =IF(OR(AO17="",J17="",AO17<=0),"",(J17-AO17)/AO17) | V17: =IF(OR(AO17="",N17="",AO17<=0),"",(AO17-N17)/AO17) | W17: =IF(OR(U17="",V17="",V17<=0),"",U17/V17) | X17: =IF(OR(K17="",L17="",AP17=""),"",K17*L17-(E17*H17+IF(AND(AK17<>"",AL17<>""),AK17*AL17,0)+IF(AND(AM17<>"",AN17<>""),AM17*AN17,0))-IF(O17="",0,O17)-IF(P17="",0,P17)) | Y17: =IF(OR(X17="",AP17=""),"",IF((E17*H17+IF(AND(AK17<>"",AL17<>""),AK17*AL17,0)+IF(AND(AM17<>"",AN17<>""),AM17*AN17,0))+IF(O17="",0,O17)<=0,"",X17/((E17*H17+IF(AND(AK17<>"",AL17<>""),AK17*AL17,0)+IF(AND(AM17<>"",AN17<>""),AM17*AN17,0))+IF(O17="",0,O17)))) | Z17: =IF(OR(AE17="",多次统计数据!$B$8=""),"",AE17-多次统计数据!$B$8) | AA17: =IF(OR(I17="",M17="",M17<I17),"",M17-I17) | AB17: =IF(OR(A17="",多次统计数据!$B$8="",多次统计数据!$B$6<=0,多次统计数据!$B$6>=1),"",1-POWER(1+多次统计数据!$B$8,-多次统计数据!$B$6/(1-多次统计数据!$B$6))) | AC17: =IF(OR(AB17="",多次统计数据!$B$9=""),"",IF(多次统计数据!$B$9<AB17,"低于上限","达到或超过上限")) | AE17: =IF(OR(X17="",C17="",C17<=0),"",X17/C17) | AJ17: =IF(OR(AG17="",AH17=""),"",IF(OR(AND(AG17="短期博反弹",OR(AH17="1～3个交易日",AH17="4～10个交易日")),AND(AG17="突破冲新高",OR(AH17="4～10个交易日",AH17="11～20个交易日")),AND(AG17="趋势波段",OR(AH17="11～20个交易日",AH17="21～60个交易日",AH17="60个交易日以上"))),"匹配","周期与交易预期不匹配，请重新确认")) | AO17: =IF(OR(A17="",H17="",H17<=0),"",(E17*H17+IF(AND(AK17<>"",AL17<>""),AK17*AL17,0)+IF(AND(AM17<>"",AN17<>""),AM17*AN17,0))/AP17) | AP17: =IF(OR(A17="",H17="",H17<=0),"",H17+IF(AL17="",0,AL17)+IF(AN17="",0,AN17)) | AQ17: =IF(A17="","",IF(M17<>"",0,IF(OR(H17="",N17=""),"",MAX(E17-MAX(N17,IFERROR(AGGREGATE(14,6,'持仓跟踪'!$S$2:$S$501/(('持仓跟踪'!$A$2:$A$501="每日跟踪")*('持仓跟踪'!$B$2:$B$501=A17)),1),0)),0)*H17+IF(OR(AK17="",AL17=""),0,MAX(AK17-MAX(N17,IFERROR(AGGREGATE(14,6,'持仓跟踪'!$S$2:$S$501/(('持仓跟踪'!$A$2:$A$501="每日跟踪")*('持仓跟踪'!$B$2:$B$501=A17)),1),0)),0)*AL17)+IF(OR(AM17="",AN17=""),0,MAX(AM17-MAX(N17,IFERROR(AGGREGATE(14,6,'持仓跟踪'!$S$2:$S$501/(('持仓跟踪'!$A$2:$A$501="每日跟踪")*('持仓跟踪'!$B$2:$B$501=A17)),1),0)),0)*AN17)))) | AR17: =IF(A17="","",IF(OR(E17="",H17=""),"违规：第一批价格或股数缺失",IF(OR(AND(AK17="",AL17<>""),AND(AK17<>"",AL17="")),"违规：第二批价格与股数须成对填写",IF(OR(AND(AM17="",AN17<>""),AND(AM17<>"",AN17="")),"违规：第三批价格与股数须成对填写",IF(AND(OR(AM17<>"",AN17<>""),OR(AK17="",AL17="")),"违规：必须先完成第二批",IF(OR(H17<=0,H17<>INT(H17),MOD(H17,100)<>0,AND(AL17<>"",OR(AL17<=0,AL17<>INT(AL17),MOD(AL17,100)<>0)),AND(AN17<>"",OR(AN17<=0,AN17<>INT(AN17),MOD(AN17,100)<>0))),"违规：股数须为100股整数倍",IF(AND(OR(AL17<>"",AN17<>""),OR(_LockStatus="已锁仓",_LockStatus="解锁信息不完整")),"违规：锁仓期间禁止加仓",IF(AQ17>C17*D17,"违规：超过单笔风险上限",IF(SUM($AQ$2:$AQ$201)>账户数据!$B$7,"违规：超过账户风险上限","通过")))))))))
A18: 17 | B18: 赛轮轮胎 | C18: 104364 | D18: 0.02 | E18: 12.91 | F18: =IF(OR(C18="",D18="",E18="",N18="",C18<=0,D18<=0,E18<=N18),"",ROUNDDOWN((C18*D18)/(E18-N18)/100,0)*100) | G18: =IF(A18="","",IF(H18<>"","已开仓",IF(账户数据!$B$23="已锁仓","禁止开仓：连续亏损达到上限",IF(账户数据!$B$23="解锁信息不完整","禁止开仓：请完整填写解锁信息",IF(OR(F18="",E18="",N18="",E18<=N18,账户数据!$B$7=""),"",IF(OR(AG18="",AH18="",AI18=""),"禁止开仓：交易预期未填写完整",IF(COUNTIFS(持仓跟踪!$A$2:$A$501,"止损计划",持仓跟踪!$B$2:$B$501,A18,持仓跟踪!$AC$2:$AC$501,"计划有效")=0,"禁止开仓：请先填写止损计划",IF(账户数据!$B$9+F18*(E18-N18)>=账户数据!$B$7,"禁止开仓：风险额度不足",IF(AJ18="周期与交易预期不匹配，请重新确认",IF(账户数据!$B$23="接近锁仓","允许开仓（接近锁仓；周期需复核）","允许开仓（周期需复核）"),IF(账户数据!$B$23="接近锁仓","允许开仓（接近锁仓）","允许开仓")))))))))) | H18: 5000 | I18: 45888 | J18: 14 | K18: 14.62 | L18: =IF(K18="","",H18) | M18: 45917 | N18: 12.5 | U18: =IF(OR(AO18="",J18="",AO18<=0),"",(J18-AO18)/AO18) | V18: =IF(OR(AO18="",N18="",AO18<=0),"",(AO18-N18)/AO18) | W18: =IF(OR(U18="",V18="",V18<=0),"",U18/V18) | X18: =IF(OR(K18="",L18="",AP18=""),"",K18*L18-(E18*H18+IF(AND(AK18<>"",AL18<>""),AK18*AL18,0)+IF(AND(AM18<>"",AN18<>""),AM18*AN18,0))-IF(O18="",0,O18)-IF(P18="",0,P18)) | Y18: =IF(OR(X18="",AP18=""),"",IF((E18*H18+IF(AND(AK18<>"",AL18<>""),AK18*AL18,0)+IF(AND(AM18<>"",AN18<>""),AM18*AN18,0))+IF(O18="",0,O18)<=0,"",X18/((E18*H18+IF(AND(AK18<>"",AL18<>""),AK18*AL18,0)+IF(AND(AM18<>"",AN18<>""),AM18*AN18,0))+IF(O18="",0,O18)))) | Z18: =IF(OR(AE18="",多次统计数据!$B$8=""),"",AE18-多次统计数据!$B$8) | AA18: =IF(OR(I18="",M18="",M18<I18),"",M18-I18) | AB18: =IF(OR(A18="",多次统计数据!$B$8="",多次统计数据!$B$6<=0,多次统计数据!$B$6>=1),"",1-POWER(1+多次统计数据!$B$8,-多次统计数据!$B$6/(1-多次统计数据!$B$6))) | AC18: =IF(OR(AB18="",多次统计数据!$B$9=""),"",IF(多次统计数据!$B$9<AB18,"低于上限","达到或超过上限")) | AE18: =IF(OR(X18="",C18="",C18<=0),"",X18/C18) | AJ18: =IF(OR(AG18="",AH18=""),"",IF(OR(AND(AG18="短期博反弹",OR(AH18="1～3个交易日",AH18="4～10个交易日")),AND(AG18="突破冲新高",OR(AH18="4～10个交易日",AH18="11～20个交易日")),AND(AG18="趋势波段",OR(AH18="11～20个交易日",AH18="21～60个交易日",AH18="60个交易日以上"))),"匹配","周期与交易预期不匹配，请重新确认")) | AO18: =IF(OR(A18="",H18="",H18<=0),"",(E18*H18+IF(AND(AK18<>"",AL18<>""),AK18*AL18,0)+IF(AND(AM18<>"",AN18<>""),AM18*AN18,0))/AP18) | AP18: =IF(OR(A18="",H18="",H18<=0),"",H18+IF(AL18="",0,AL18)+IF(AN18="",0,AN18)) | AQ18: =IF(A18="","",IF(M18<>"",0,IF(OR(H18="",N18=""),"",MAX(E18-MAX(N18,IFERROR(AGGREGATE(14,6,'持仓跟踪'!$S$2:$S$501/(('持仓跟踪'!$A$2:$A$501="每日跟踪")*('持仓跟踪'!$B$2:$B$501=A18)),1),0)),0)*H18+IF(OR(AK18="",AL18=""),0,MAX(AK18-MAX(N18,IFERROR(AGGREGATE(14,6,'持仓跟踪'!$S$2:$S$501/(('持仓跟踪'!$A$2:$A$501="每日跟踪")*('持仓跟踪'!$B$2:$B$501=A18)),1),0)),0)*AL18)+IF(OR(AM18="",AN18=""),0,MAX(AM18-MAX(N18,IFERROR(AGGREGATE(14,6,'持仓跟踪'!$S$2:$S$501/(('持仓跟踪'!$A$2:$A$501="每日跟踪")*('持仓跟踪'!$B$2:$B$501=A18)),1),0)),0)*AN18)))) | AR18: =IF(A18="","",IF(OR(E18="",H18=""),"违规：第一批价格或股数缺失",IF(OR(AND(AK18="",AL18<>""),AND(AK18<>"",AL18="")),"违规：第二批价格与股数须成对填写",IF(OR(AND(AM18="",AN18<>""),AND(AM18<>"",AN18="")),"违规：第三批价格与股数须成对填写",IF(AND(OR(AM18<>"",AN18<>""),OR(AK18="",AL18="")),"违规：必须先完成第二批",IF(OR(H18<=0,H18<>INT(H18),MOD(H18,100)<>0,AND(AL18<>"",OR(AL18<=0,AL18<>INT(AL18),MOD(AL18,100)<>0)),AND(AN18<>"",OR(AN18<=0,AN18<>INT(AN18),MOD(AN18,100)<>0))),"违规：股数须为100股整数倍",IF(AND(OR(AL18<>"",AN18<>""),OR(_LockStatus="已锁仓",_LockStatus="解锁信息不完整")),"违规：锁仓期间禁止加仓",IF(AQ18>C18*D18,"违规：超过单笔风险上限",IF(SUM($AQ$2:$AQ$201)>账户数据!$B$7,"违规：超过账户风险上限","通过")))))))))
A19: 18 | B19: 通富微电 | C19: 112913 | D19: 0.02 | E19: 20.1 | F19: =IF(OR(C19="",D19="",E19="",N19="",C19<=0,D19<=0,E19<=N19),"",ROUNDDOWN((C19*D19)/(E19-N19)/100,0)*100) | G19: =IF(A19="","",IF(H19<>"","已开仓",IF(账户数据!$B$23="已锁仓","禁止开仓：连续亏损达到上限",IF(账户数据!$B$23="解锁信息不完整","禁止开仓：请完整填写解锁信息",IF(OR(F19="",E19="",N19="",E19<=N19,账户数据!$B$7=""),"",IF(OR(AG19="",AH19="",AI19=""),"禁止开仓：交易预期未填写完整",IF(COUNTIFS(持仓跟踪!$A$2:$A$501,"止损计划",持仓跟踪!$B$2:$B$501,A19,持仓跟踪!$AC$2:$AC$501,"计划有效")=0,"禁止开仓：请先填写止损计划",IF(账户数据!$B$9+F19*(E19-N19)>=账户数据!$B$7,"禁止开仓：风险额度不足",IF(AJ19="周期与交易预期不匹配，请重新确认",IF(账户数据!$B$23="接近锁仓","允许开仓（接近锁仓；周期需复核）","允许开仓（周期需复核）"),IF(账户数据!$B$23="接近锁仓","允许开仓（接近锁仓）","允许开仓")))))))))) | H19: 2000 | I19: 44540 | J19: 23 | K19: 18.9 | L19: =IF(K19="","",H19) | M19: 44550 | N19: 19 | U19: =IF(OR(AO19="",J19="",AO19<=0),"",(J19-AO19)/AO19) | V19: =IF(OR(AO19="",N19="",AO19<=0),"",(AO19-N19)/AO19) | W19: =IF(OR(U19="",V19="",V19<=0),"",U19/V19) | X19: =IF(OR(K19="",L19="",AP19=""),"",K19*L19-(E19*H19+IF(AND(AK19<>"",AL19<>""),AK19*AL19,0)+IF(AND(AM19<>"",AN19<>""),AM19*AN19,0))-IF(O19="",0,O19)-IF(P19="",0,P19)) | Y19: =IF(OR(X19="",AP19=""),"",IF((E19*H19+IF(AND(AK19<>"",AL19<>""),AK19*AL19,0)+IF(AND(AM19<>"",AN19<>""),AM19*AN19,0))+IF(O19="",0,O19)<=0,"",X19/((E19*H19+IF(AND(AK19<>"",AL19<>""),AK19*AL19,0)+IF(AND(AM19<>"",AN19<>""),AM19*AN19,0))+IF(O19="",0,O19)))) | Z19: =IF(OR(AE19="",多次统计数据!$B$8=""),"",AE19-多次统计数据!$B$8) | AA19: =IF(OR(I19="",M19="",M19<I19),"",M19-I19) | AB19: =IF(OR(A19="",多次统计数据!$B$8="",多次统计数据!$B$6<=0,多次统计数据!$B$6>=1),"",1-POWER(1+多次统计数据!$B$8,-多次统计数据!$B$6/(1-多次统计数据!$B$6))) | AC19: =IF(OR(AB19="",多次统计数据!$B$9=""),"",IF(多次统计数据!$B$9<AB19,"低于上限","达到或超过上限")) | AE19: =IF(OR(X19="",C19="",C19<=0),"",X19/C19) | AJ19: =IF(OR(AG19="",AH19=""),"",IF(OR(AND(AG19="短期博反弹",OR(AH19="1～3个交易日",AH19="4～10个交易日")),AND(AG19="突破冲新高",OR(AH19="4～10个交易日",AH19="11～20个交易日")),AND(AG19="趋势波段",OR(AH19="11～20个交易日",AH19="21～60个交易日",AH19="60个交易日以上"))),"匹配","周期与交易预期不匹配，请重新确认")) | AO19: =IF(OR(A19="",H19="",H19<=0),"",(E19*H19+IF(AND(AK19<>"",AL19<>""),AK19*AL19,0)+IF(AND(AM19<>"",AN19<>""),AM19*AN19,0))/AP19) | AP19: =IF(OR(A19="",H19="",H19<=0),"",H19+IF(AL19="",0,AL19)+IF(AN19="",0,AN19)) | AQ19: =IF(A19="","",IF(M19<>"",0,IF(OR(H19="",N19=""),"",MAX(E19-MAX(N19,IFERROR(AGGREGATE(14,6,'持仓跟踪'!$S$2:$S$501/(('持仓跟踪'!$A$2:$A$501="每日跟踪")*('持仓跟踪'!$B$2:$B$501=A19)),1),0)),0)*H19+IF(OR(AK19="",AL19=""),0,MAX(AK19-MAX(N19,IFERROR(AGGREGATE(14,6,'持仓跟踪'!$S$2:$S$501/(('持仓跟踪'!$A$2:$A$501="每日跟踪")*('持仓跟踪'!$B$2:$B$501=A19)),1),0)),0)*AL19)+IF(OR(AM19="",AN19=""),0,MAX(AM19-MAX(N19,IFERROR(AGGREGATE(14,6,'持仓跟踪'!$S$2:$S$501/(('持仓跟踪'!$A$2:$A$501="每日跟踪")*('持仓跟踪'!$B$2:$B$501=A19)),1),0)),0)*AN19)))) | AR19: =IF(A19="","",IF(OR(E19="",H19=""),"违规：第一批价格或股数缺失",IF(OR(AND(AK19="",AL19<>""),AND(AK19<>"",AL19="")),"违规：第二批价格与股数须成对填写",IF(OR(AND(AM19="",AN19<>""),AND(AM19<>"",AN19="")),"违规：第三批价格与股数须成对填写",IF(AND(OR(AM19<>"",AN19<>""),OR(AK19="",AL19="")),"违规：必须先完成第二批",IF(OR(H19<=0,H19<>INT(H19),MOD(H19,100)<>0,AND(AL19<>"",OR(AL19<=0,AL19<>INT(AL19),MOD(AL19,100)<>0)),AND(AN19<>"",OR(AN19<=0,AN19<>INT(AN19),MOD(AN19,100)<>0))),"违规：股数须为100股整数倍",IF(AND(OR(AL19<>"",AN19<>""),OR(_LockStatus="已锁仓",_LockStatus="解锁信息不完整")),"违规：锁仓期间禁止加仓",IF(AQ19>C19*D19,"违规：超过单笔风险上限",IF(SUM($AQ$2:$AQ$201)>账户数据!$B$7,"违规：超过账户风险上限","通过")))))))))
A20: 19 | B20: 通富微电 | C20: 110513 | D20: 0.02 | E20: 14.23 | F20: =IF(OR(C20="",D20="",E20="",N20="",C20<=0,D20<=0,E20<=N20),"",ROUNDDOWN((C20*D20)/(E20-N20)/100,0)*100) | G20: =IF(A20="","",IF(H20<>"","已开仓",IF(账户数据!$B$23="已锁仓","禁止开仓：连续亏损达到上限",IF(账户数据!$B$23="解锁信息不完整","禁止开仓：请完整填写解锁信息",IF(OR(F20="",E20="",N20="",E20<=N20,账户数据!$B$7=""),"",IF(OR(AG20="",AH20="",AI20=""),"禁止开仓：交易预期未填写完整",IF(COUNTIFS(持仓跟踪!$A$2:$A$501,"止损计划",持仓跟踪!$B$2:$B$501,A20,持仓跟踪!$AC$2:$AC$501,"计划有效")=0,"禁止开仓：请先填写止损计划",IF(账户数据!$B$9+F20*(E20-N20)>=账户数据!$B$7,"禁止开仓：风险额度不足",IF(AJ20="周期与交易预期不匹配，请重新确认",IF(账户数据!$B$23="接近锁仓","允许开仓（接近锁仓；周期需复核）","允许开仓（周期需复核）"),IF(账户数据!$B$23="接近锁仓","允许开仓（接近锁仓）","允许开仓")))))))))) | H20: 3000 | I20: 44727 | J20: 16 | K20: 14.86 | L20: =IF(K20="","",H20) | M20: 44741 | N20: 13.5 | U20: =IF(OR(AO20="",J20="",AO20<=0),"",(J20-AO20)/AO20) | V20: =IF(OR(AO20="",N20="",AO20<=0),"",(AO20-N20)/AO20) | W20: =IF(OR(U20="",V20="",V20<=0),"",U20/V20) | X20: =IF(OR(K20="",L20="",AP20=""),"",K20*L20-(E20*H20+IF(AND(AK20<>"",AL20<>""),AK20*AL20,0)+IF(AND(AM20<>"",AN20<>""),AM20*AN20,0))-IF(O20="",0,O20)-IF(P20="",0,P20)) | Y20: =IF(OR(X20="",AP20=""),"",IF((E20*H20+IF(AND(AK20<>"",AL20<>""),AK20*AL20,0)+IF(AND(AM20<>"",AN20<>""),AM20*AN20,0))+IF(O20="",0,O20)<=0,"",X20/((E20*H20+IF(AND(AK20<>"",AL20<>""),AK20*AL20,0)+IF(AND(AM20<>"",AN20<>""),AM20*AN20,0))+IF(O20="",0,O20)))) | Z20: =IF(OR(AE20="",多次统计数据!$B$8=""),"",AE20-多次统计数据!$B$8) | AA20: =IF(OR(I20="",M20="",M20<I20),"",M20-I20) | AB20: =IF(OR(A20="",多次统计数据!$B$8="",多次统计数据!$B$6<=0,多次统计数据!$B$6>=1),"",1-POWER(1+多次统计数据!$B$8,-多次统计数据!$B$6/(1-多次统计数据!$B$6))) | AC20: =IF(OR(AB20="",多次统计数据!$B$9=""),"",IF(多次统计数据!$B$9<AB20,"低于上限","达到或超过上限")) | AE20: =IF(OR(X20="",C20="",C20<=0),"",X20/C20) | AJ20: =IF(OR(AG20="",AH20=""),"",IF(OR(AND(AG20="短期博反弹",OR(AH20="1～3个交易日",AH20="4～10个交易日")),AND(AG20="突破冲新高",OR(AH20="4～10个交易日",AH20="11～20个交易日")),AND(AG20="趋势波段",OR(AH20="11～20个交易日",AH20="21～60个交易日",AH20="60个交易日以上"))),"匹配","周期与交易预期不匹配，请重新确认")) | AO20: =IF(OR(A20="",H20="",H20<=0),"",(E20*H20+IF(AND(AK20<>"",AL20<>""),AK20*AL20,0)+IF(AND(AM20<>"",AN20<>""),AM20*AN20,0))/AP20) | AP20: =IF(OR(A20="",H20="",H20<=0),"",H20+IF(AL20="",0,AL20)+IF(AN20="",0,AN20)) | AQ20: =IF(A20="","",IF(M20<>"",0,IF(OR(H20="",N20=""),"",MAX(E20-MAX(N20,IFERROR(AGGREGATE(14,6,'持仓跟踪'!$S$2:$S$501/(('持仓跟踪'!$A$2:$A$501="每日跟踪")*('持仓跟踪'!$B$2:$B$501=A20)),1),0)),0)*H20+IF(OR(AK20="",AL20=""),0,MAX(AK20-MAX(N20,IFERROR(AGGREGATE(14,6,'持仓跟踪'!$S$2:$S$501/(('持仓跟踪'!$A$2:$A$501="每日跟踪")*('持仓跟踪'!$B$2:$B$501=A20)),1),0)),0)*AL20)+IF(OR(AM20="",AN20=""),0,MAX(AM20-MAX(N20,IFERROR(AGGREGATE(14,6,'持仓跟踪'!$S$2:$S$501/(('持仓跟踪'!$A$2:$A$501="每日跟踪")*('持仓跟踪'!$B$2:$B$501=A20)),1),0)),0)*AN20)))) | AR20: =IF(A20="","",IF(OR(E20="",H20=""),"违规：第一批价格或股数缺失",IF(OR(AND(AK20="",AL20<>""),AND(AK20<>"",AL20="")),"违规：第二批价格与股数须成对填写",IF(OR(AND(AM20="",AN20<>""),AND(AM20<>"",AN20="")),"违规：第三批价格与股数须成对填写",IF(AND(OR(AM20<>"",AN20<>""),OR(AK20="",AL20="")),"违规：必须先完成第二批",IF(OR(H20<=0,H20<>INT(H20),MOD(H20,100)<>0,AND(AL20<>"",OR(AL20<=0,AL20<>INT(AL20),MOD(AL20,100)<>0)),AND(AN20<>"",OR(AN20<=0,AN20<>INT(AN20),MOD(AN20,100)<>0))),"违规：股数须为100股整数倍",IF(AND(OR(AL20<>"",AN20<>""),OR(_LockStatus="已锁仓",_LockStatus="解锁信息不完整")),"违规：锁仓期间禁止加仓",IF(AQ20>C20*D20,"违规：超过单笔风险上限",IF(SUM($AQ$2:$AQ$201)>账户数据!$B$7,"违规：超过账户风险上限","通过")))))))))
A21: 20 | B21: 通富微电 | C21: 112403 | D21: 0.02 | E21: 20.05 | F21: =IF(OR(C21="",D21="",E21="",N21="",C21<=0,D21<=0,E21<=N21),"",ROUNDDOWN((C21*D21)/(E21-N21)/100,0)*100) | G21: =IF(A21="","",IF(H21<>"","已开仓",IF(账户数据!$B$23="已锁仓","禁止开仓：连续亏损达到上限",IF(账户数据!$B$23="解锁信息不完整","禁止开仓：请完整填写解锁信息",IF(OR(F21="",E21="",N21="",E21<=N21,账户数据!$B$7=""),"",IF(OR(AG21="",AH21="",AI21=""),"禁止开仓：交易预期未填写完整",IF(COUNTIFS(持仓跟踪!$A$2:$A$501,"止损计划",持仓跟踪!$B$2:$B$501,A21,持仓跟踪!$AC$2:$AC$501,"计划有效")=0,"禁止开仓：请先填写止损计划",IF(账户数据!$B$9+F21*(E21-N21)>=账户数据!$B$7,"禁止开仓：风险额度不足",IF(AJ21="周期与交易预期不匹配，请重新确认",IF(账户数据!$B$23="接近锁仓","允许开仓（接近锁仓；周期需复核）","允许开仓（周期需复核）"),IF(账户数据!$B$23="接近锁仓","允许开仓（接近锁仓）","允许开仓")))))))))) | H21: 4000 | I21: 45068 | J21: 22.5 | K21: 25.16 | L21: =IF(K21="","",H21) | M21: 45091 | N21: 19.5 | U21: =IF(OR(AO21="",J21="",AO21<=0),"",(J21-AO21)/AO21) | V21: =IF(OR(AO21="",N21="",AO21<=0),"",(AO21-N21)/AO21) | W21: =IF(OR(U21="",V21="",V21<=0),"",U21/V21) | X21: =IF(OR(K21="",L21="",AP21=""),"",K21*L21-(E21*H21+IF(AND(AK21<>"",AL21<>""),AK21*AL21,0)+IF(AND(AM21<>"",AN21<>""),AM21*AN21,0))-IF(O21="",0,O21)-IF(P21="",0,P21)) | Y21: =IF(OR(X21="",AP21=""),"",IF((E21*H21+IF(AND(AK21<>"",AL21<>""),AK21*AL21,0)+IF(AND(AM21<>"",AN21<>""),AM21*AN21,0))+IF(O21="",0,O21)<=0,"",X21/((E21*H21+IF(AND(AK21<>"",AL21<>""),AK21*AL21,0)+IF(AND(AM21<>"",AN21<>""),AM21*AN21,0))+IF(O21="",0,O21)))) | Z21: =IF(OR(AE21="",多次统计数据!$B$8=""),"",AE21-多次统计数据!$B$8) | AA21: =IF(OR(I21="",M21="",M21<I21),"",M21-I21) | AB21: =IF(OR(A21="",多次统计数据!$B$8="",多次统计数据!$B$6<=0,多次统计数据!$B$6>=1),"",1-POWER(1+多次统计数据!$B$8,-多次统计数据!$B$6/(1-多次统计数据!$B$6))) | AC21: =IF(OR(AB21="",多次统计数据!$B$9=""),"",IF(多次统计数据!$B$9<AB21,"低于上限","达到或超过上限")) | AE21: =IF(OR(X21="",C21="",C21<=0),"",X21/C21) | AJ21: =IF(OR(AG21="",AH21=""),"",IF(OR(AND(AG21="短期博反弹",OR(AH21="1～3个交易日",AH21="4～10个交易日")),AND(AG21="突破冲新高",OR(AH21="4～10个交易日",AH21="11～20个交易日")),AND(AG21="趋势波段",OR(AH21="11～20个交易日",AH21="21～60个交易日",AH21="60个交易日以上"))),"匹配","周期与交易预期不匹配，请重新确认")) | AO21: =IF(OR(A21="",H21="",H21<=0),"",(E21*H21+IF(AND(AK21<>"",AL21<>""),AK21*AL21,0)+IF(AND(AM21<>"",AN21<>""),AM21*AN21,0))/AP21) | AP21: =IF(OR(A21="",H21="",H21<=0),"",H21+IF(AL21="",0,AL21)+IF(AN21="",0,AN21)) | AQ21: =IF(A21="","",IF(M21<>"",0,IF(OR(H21="",N21=""),"",MAX(E21-MAX(N21,IFERROR(AGGREGATE(14,6,'持仓跟踪'!$S$2:$S$501/(('持仓跟踪'!$A$2:$A$501="每日跟踪")*('持仓跟踪'!$B$2:$B$501=A21)),1),0)),0)*H21+IF(OR(AK21="",AL21=""),0,MAX(AK21-MAX(N21,IFERROR(AGGREGATE(14,6,'持仓跟踪'!$S$2:$S$501/(('持仓跟踪'!$A$2:$A$501="每日跟踪")*('持仓跟踪'!$B$2:$B$501=A21)),1),0)),0)*AL21)+IF(OR(AM21="",AN21=""),0,MAX(AM21-MAX(N21,IFERROR(AGGREGATE(14,6,'持仓跟踪'!$S$2:$S$501/(('持仓跟踪'!$A$2:$A$501="每日跟踪")*('持仓跟踪'!$B$2:$B$501=A21)),1),0)),0)*AN21)))) | AR21: =IF(A21="","",IF(OR(E21="",H21=""),"违规：第一批价格或股数缺失",IF(OR(AND(AK21="",AL21<>""),AND(AK21<>"",AL21="")),"违规：第二批价格与股数须成对填写",IF(OR(AND(AM21="",AN21<>""),AND(AM21<>"",AN21="")),"违规：第三批价格与股数须成对填写",IF(AND(OR(AM21<>"",AN21<>""),OR(AK21="",AL21="")),"违规：必须先完成第二批",IF(OR(H21<=0,H21<>INT(H21),MOD(H21,100)<>0,AND(AL21<>"",OR(AL21<=0,AL21<>INT(AL21),MOD(AL21,100)<>0)),AND(AN21<>"",OR(AN21<=0,AN21<>INT(AN21),MOD(AN21,100)<>0))),"违规：股数须为100股整数倍",IF(AND(OR(AL21<>"",AN21<>""),OR(_LockStatus="已锁仓",_LockStatus="解锁信息不完整")),"违规：锁仓期间禁止加仓",IF(AQ21>C21*D21,"违规：超过单笔风险上限",IF(SUM($AQ$2:$AQ$201)>账户数据!$B$7,"违规：超过账户风险上限","通过")))))))))
A22: 21 | B22: 通富微电 | C22: 132843 | D22: 0.02 | E22: 24.36 | F22: =IF(OR(C22="",D22="",E22="",N22="",C22<=0,D22<=0,E22<=N22),"",ROUNDDOWN((C22*D22)/(E22-N22)/100,0)*100) | G22: =IF(A22="","",IF(H22<>"","已开仓",IF(账户数据!$B$23="已锁仓","禁止开仓：连续亏损达到上限",IF(账户数据!$B$23="解锁信息不完整","禁止开仓：请完整填写解锁信息",IF(OR(F22="",E22="",N22="",E22<=N22,账户数据!$B$7=""),"",IF(OR(AG22="",AH22="",AI22=""),"禁止开仓：交易预期未填写完整",IF(COUNTIFS(持仓跟踪!$A$2:$A$501,"止损计划",持仓跟踪!$B$2:$B$501,A22,持仓跟踪!$AC$2:$AC$501,"计划有效")=0,"禁止开仓：请先填写止损计划",IF(账户数据!$B$9+F22*(E22-N22)>=账户数据!$B$7,"禁止开仓：风险额度不足",IF(AJ22="周期与交易预期不匹配，请重新确认",IF(账户数据!$B$23="接近锁仓","允许开仓（接近锁仓；周期需复核）","允许开仓（周期需复核）"),IF(账户数据!$B$23="接近锁仓","允许开仓（接近锁仓）","允许开仓")))))))))) | H22: 1900 | I22: 45128 | J22: 28 | K22: 22.11 | L22: =IF(K22="","",H22) | M22: 45134 | N22: 23 | U22: =IF(OR(AO22="",J22="",AO22<=0),"",(J22-AO22)/AO22) | V22: =IF(OR(AO22="",N22="",AO22<=0),"",(AO22-N22)/AO22) | W22: =IF(OR(U22="",V22="",V22<=0),"",U22/V22) | X22: =IF(OR(K22="",L22="",AP22=""),"",K22*L22-(E22*H22+IF(AND(AK22<>"",AL22<>""),AK22*AL22,0)+IF(AND(AM22<>"",AN22<>""),AM22*AN22,0))-IF(O22="",0,O22)-IF(P22="",0,P22)) | Y22: =IF(OR(X22="",AP22=""),"",IF((E22*H22+IF(AND(AK22<>"",AL22<>""),AK22*AL22,0)+IF(AND(AM22<>"",AN22<>""),AM22*AN22,0))+IF(O22="",0,O22)<=0,"",X22/((E22*H22+IF(AND(AK22<>"",AL22<>""),AK22*AL22,0)+IF(AND(AM22<>"",AN22<>""),AM22*AN22,0))+IF(O22="",0,O22)))) | Z22: =IF(OR(AE22="",多次统计数据!$B$8=""),"",AE22-多次统计数据!$B$8) | AA22: =IF(OR(I22="",M22="",M22<I22),"",M22-I22) | AB22: =IF(OR(A22="",多次统计数据!$B$8="",多次统计数据!$B$6<=0,多次统计数据!$B$6>=1),"",1-POWER(1+多次统计数据!$B$8,-多次统计数据!$B$6/(1-多次统计数据!$B$6))) | AC22: =IF(OR(AB22="",多次统计数据!$B$9=""),"",IF(多次统计数据!$B$9<AB22,"低于上限","达到或超过上限")) | AE22: =IF(OR(X22="",C22="",C22<=0),"",X22/C22) | AJ22: =IF(OR(AG22="",AH22=""),"",IF(OR(AND(AG22="短期博反弹",OR(AH22="1～3个交易日",AH22="4～10个交易日")),AND(AG22="突破冲新高",OR(AH22="4～10个交易日",AH22="11～20个交易日")),AND(AG22="趋势波段",OR(AH22="11～20个交易日",AH22="21～60个交易日",AH22="60个交易日以上"))),"匹配","周期与交易预期不匹配，请重新确认")) | AO22: =IF(OR(A22="",H22="",H22<=0),"",(E22*H22+IF(AND(AK22<>"",AL22<>""),AK22*AL22,0)+IF(AND(AM22<>"",AN22<>""),AM22*AN22,0))/AP22) | AP22: =IF(OR(A22="",H22="",H22<=0),"",H22+IF(AL22="",0,AL22)+IF(AN22="",0,AN22)) | AQ22: =IF(A22="","",IF(M22<>"",0,IF(OR(H22="",N22=""),"",MAX(E22-MAX(N22,IFERROR(AGGREGATE(14,6,'持仓跟踪'!$S$2:$S$501/(('持仓跟踪'!$A$2:$A$501="每日跟踪")*('持仓跟踪'!$B$2:$B$501=A22)),1),0)),0)*H22+IF(OR(AK22="",AL22=""),0,MAX(AK22-MAX(N22,IFERROR(AGGREGATE(14,6,'持仓跟踪'!$S$2:$S$501/(('持仓跟踪'!$A$2:$A$501="每日跟踪")*('持仓跟踪'!$B$2:$B$501=A22)),1),0)),0)*AL22)+IF(OR(AM22="",AN22=""),0,MAX(AM22-MAX(N22,IFERROR(AGGREGATE(14,6,'持仓跟踪'!$S$2:$S$501/(('持仓跟踪'!$A$2:$A$501="每日跟踪")*('持仓跟踪'!$B$2:$B$501=A22)),1),0)),0)*AN22)))) | AR22: =IF(A22="","",IF(OR(E22="",H22=""),"违规：第一批价格或股数缺失",IF(OR(AND(AK22="",AL22<>""),AND(AK22<>"",AL22="")),"违规：第二批价格与股数须成对填写",IF(OR(AND(AM22="",AN22<>""),AND(AM22<>"",AN22="")),"违规：第三批价格与股数须成对填写",IF(AND(OR(AM22<>"",AN22<>""),OR(AK22="",AL22="")),"违规：必须先完成第二批",IF(OR(H22<=0,H22<>INT(H22),MOD(H22,100)<>0,AND(AL22<>"",OR(AL22<=0,AL22<>INT(AL22),MOD(AL22,100)<>0)),AND(AN22<>"",OR(AN22<=0,AN22<>INT(AN22),MOD(AN22,100)<>0))),"违规：股数须为100股整数倍",IF(AND(OR(AL22<>"",AN22<>""),OR(_LockStatus="已锁仓",_LockStatus="解锁信息不完整")),"违规：锁仓期间禁止加仓",IF(AQ22>C22*D22,"违规：超过单笔风险上限",IF(SUM($AQ$2:$AQ$201)>账户数据!$B$7,"违规：超过账户风险上限","通过")))))))))
A23: 22 | B23: 通富微电 | C23: 128568 | D23: 0.02 | E23: 19.84 | F23: =IF(OR(C23="",D23="",E23="",N23="",C23<=0,D23<=0,E23<=N23),"",ROUNDDOWN((C23*D23)/(E23-N23)/100,0)*100) | G23: =IF(A23="","",IF(H23<>"","已开仓",IF(账户数据!$B$23="已锁仓","禁止开仓：连续亏损达到上限",IF(账户数据!$B$23="解锁信息不完整","禁止开仓：请完整填写解锁信息",IF(OR(F23="",E23="",N23="",E23<=N23,账户数据!$B$7=""),"",IF(OR(AG23="",AH23="",AI23=""),"禁止开仓：交易预期未填写完整",IF(COUNTIFS(持仓跟踪!$A$2:$A$501,"止损计划",持仓跟踪!$B$2:$B$501,A23,持仓跟踪!$AC$2:$AC$501,"计划有效")=0,"禁止开仓：请先填写止损计划",IF(账户数据!$B$9+F23*(E23-N23)>=账户数据!$B$7,"禁止开仓：风险额度不足",IF(AJ23="周期与交易预期不匹配，请重新确认",IF(账户数据!$B$23="接近锁仓","允许开仓（接近锁仓；周期需复核）","允许开仓（周期需复核）"),IF(账户数据!$B$23="接近锁仓","允许开仓（接近锁仓）","允许开仓")))))))))) | H23: 1300 | I23: 45218 | J23: 24 | K23: 17.84 | L23: =IF(K23="","",H23) | M23: 45222 | N23: 18 | U23: =IF(OR(AO23="",J23="",AO23<=0),"",(J23-AO23)/AO23) | V23: =IF(OR(AO23="",N23="",AO23<=0),"",(AO23-N23)/AO23) | W23: =IF(OR(U23="",V23="",V23<=0),"",U23/V23) | X23: =IF(OR(K23="",L23="",AP23=""),"",K23*L23-(E23*H23+IF(AND(AK23<>"",AL23<>""),AK23*AL23,0)+IF(AND(AM23<>"",AN23<>""),AM23*AN23,0))-IF(O23="",0,O23)-IF(P23="",0,P23)) | Y23: =IF(OR(X23="",AP23=""),"",IF((E23*H23+IF(AND(AK23<>"",AL23<>""),AK23*AL23,0)+IF(AND(AM23<>"",AN23<>""),AM23*AN23,0))+IF(O23="",0,O23)<=0,"",X23/((E23*H23+IF(AND(AK23<>"",AL23<>""),AK23*AL23,0)+IF(AND(AM23<>"",AN23<>""),AM23*AN23,0))+IF(O23="",0,O23)))) | Z23: =IF(OR(AE23="",多次统计数据!$B$8=""),"",AE23-多次统计数据!$B$8) | AA23: =IF(OR(I23="",M23="",M23<I23),"",M23-I23) | AB23: =IF(OR(A23="",多次统计数据!$B$8="",多次统计数据!$B$6<=0,多次统计数据!$B$6>=1),"",1-POWER(1+多次统计数据!$B$8,-多次统计数据!$B$6/(1-多次统计数据!$B$6))) | AC23: =IF(OR(AB23="",多次统计数据!$B$9=""),"",IF(多次统计数据!$B$9<AB23,"低于上限","达到或超过上限")) | AE23: =IF(OR(X23="",C23="",C23<=0),"",X23/C23) | AJ23: =IF(OR(AG23="",AH23=""),"",IF(OR(AND(AG23="短期博反弹",OR(AH23="1～3个交易日",AH23="4～10个交易日")),AND(AG23="突破冲新高",OR(AH23="4～10个交易日",AH23="11～20个交易日")),AND(AG23="趋势波段",OR(AH23="11～20个交易日",AH23="21～60个交易日",AH23="60个交易日以上"))),"匹配","周期与交易预期不匹配，请重新确认")) | AO23: =IF(OR(A23="",H23="",H23<=0),"",(E23*H23+IF(AND(AK23<>"",AL23<>""),AK23*AL23,0)+IF(AND(AM23<>"",AN23<>""),AM23*AN23,0))/AP23) | AP23: =IF(OR(A23="",H23="",H23<=0),"",H23+IF(AL23="",0,AL23)+IF(AN23="",0,AN23)) | AQ23: =IF(A23="","",IF(M23<>"",0,IF(OR(H23="",N23=""),"",MAX(E23-MAX(N23,IFERROR(AGGREGATE(14,6,'持仓跟踪'!$S$2:$S$501/(('持仓跟踪'!$A$2:$A$501="每日跟踪")*('持仓跟踪'!$B$2:$B$501=A23)),1),0)),0)*H23+IF(OR(AK23="",AL23=""),0,MAX(AK23-MAX(N23,IFERROR(AGGREGATE(14,6,'持仓跟踪'!$S$2:$S$501/(('持仓跟踪'!$A$2:$A$501="每日跟踪")*('持仓跟踪'!$B$2:$B$501=A23)),1),0)),0)*AL23)+IF(OR(AM23="",AN23=""),0,MAX(AM23-MAX(N23,IFERROR(AGGREGATE(14,6,'持仓跟踪'!$S$2:$S$501/(('持仓跟踪'!$A$2:$A$501="每日跟踪")*('持仓跟踪'!$B$2:$B$501=A23)),1),0)),0)*AN23)))) | AR23: =IF(A23="","",IF(OR(E23="",H23=""),"违规：第一批价格或股数缺失",IF(OR(AND(AK23="",AL23<>""),AND(AK23<>"",AL23="")),"违规：第二批价格与股数须成对填写",IF(OR(AND(AM23="",AN23<>""),AND(AM23<>"",AN23="")),"违规：第三批价格与股数须成对填写",IF(AND(OR(AM23<>"",AN23<>""),OR(AK23="",AL23="")),"违规：必须先完成第二批",IF(OR(H23<=0,H23<>INT(H23),MOD(H23,100)<>0,AND(AL23<>"",OR(AL23<=0,AL23<>INT(AL23),MOD(AL23,100)<>0)),AND(AN23<>"",OR(AN23<=0,AN23<>INT(AN23),MOD(AN23,100)<>0))),"违规：股数须为100股整数倍",IF(AND(OR(AL23<>"",AN23<>""),OR(_LockStatus="已锁仓",_LockStatus="解锁信息不完整")),"违规：锁仓期间禁止加仓",IF(AQ23>C23*D23,"违规：超过单笔风险上限",IF(SUM($AQ$2:$AQ$201)>账户数据!$B$7,"违规：超过账户风险上限","通过")))))))))
A24: 23 | B24: 通富微电 | C24: 125968 | D24: 0.02 | E24: 21.54 | F24: =IF(OR(C24="",D24="",E24="",N24="",C24<=0,D24<=0,E24<=N24),"",ROUNDDOWN((C24*D24)/(E24-N24)/100,0)*100) | G24: =IF(A24="","",IF(H24<>"","已开仓",IF(账户数据!$B$23="已锁仓","禁止开仓：连续亏损达到上限",IF(账户数据!$B$23="解锁信息不完整","禁止开仓：请完整填写解锁信息",IF(OR(F24="",E24="",N24="",E24<=N24,账户数据!$B$7=""),"",IF(OR(AG24="",AH24="",AI24=""),"禁止开仓：交易预期未填写完整",IF(COUNTIFS(持仓跟踪!$A$2:$A$501,"止损计划",持仓跟踪!$B$2:$B$501,A24,持仓跟踪!$AC$2:$AC$501,"计划有效")=0,"禁止开仓：请先填写止损计划",IF(账户数据!$B$9+F24*(E24-N24)>=账户数据!$B$7,"禁止开仓：风险额度不足",IF(AJ24="周期与交易预期不匹配，请重新确认",IF(账户数据!$B$23="接近锁仓","允许开仓（接近锁仓；周期需复核）","允许开仓（周期需复核）"),IF(账户数据!$B$23="接近锁仓","允许开仓（接近锁仓）","允许开仓")))))))))) | H24: 3400 | I24: 45439 | J24: 27 | K24: 23.44 | L24: =IF(K24="","",H24) | M24: 45449 | N24: 20.8 | U24: =IF(OR(AO24="",J24="",AO24<=0),"",(J24-AO24)/AO24) | V24: =IF(OR(AO24="",N24="",AO24<=0),"",(AO24-N24)/AO24) | W24: =IF(OR(U24="",V24="",V24<=0),"",U24/V24) | X24: =IF(OR(K24="",L24="",AP24=""),"",K24*L24-(E24*H24+IF(AND(AK24<>"",AL24<>""),AK24*AL24,0)+IF(AND(AM24<>"",AN24<>""),AM24*AN24,0))-IF(O24="",0,O24)-IF(P24="",0,P24)) | Y24: =IF(OR(X24="",AP24=""),"",IF((E24*H24+IF(AND(AK24<>"",AL24<>""),AK24*AL24,0)+IF(AND(AM24<>"",AN24<>""),AM24*AN24,0))+IF(O24="",0,O24)<=0,"",X24/((E24*H24+IF(AND(AK24<>"",AL24<>""),AK24*AL24,0)+IF(AND(AM24<>"",AN24<>""),AM24*AN24,0))+IF(O24="",0,O24)))) | Z24: =IF(OR(AE24="",多次统计数据!$B$8=""),"",AE24-多次统计数据!$B$8) | AA24: =IF(OR(I24="",M24="",M24<I24),"",M24-I24) | AB24: =IF(OR(A24="",多次统计数据!$B$8="",多次统计数据!$B$6<=0,多次统计数据!$B$6>=1),"",1-POWER(1+多次统计数据!$B$8,-多次统计数据!$B$6/(1-多次统计数据!$B$6))) | AC24: =IF(OR(AB24="",多次统计数据!$B$9=""),"",IF(多次统计数据!$B$9<AB24,"低于上限","达到或超过上限")) | AE24: =IF(OR(X24="",C24="",C24<=0),"",X24/C24) | AJ24: =IF(OR(AG24="",AH24=""),"",IF(OR(AND(AG24="短期博反弹",OR(AH24="1～3个交易日",AH24="4～10个交易日")),AND(AG24="突破冲新高",OR(AH24="4～10个交易日",AH24="11～20个交易日")),AND(AG24="趋势波段",OR(AH24="11～20个交易日",AH24="21～60个交易日",AH24="60个交易日以上"))),"匹配","周期与交易预期不匹配，请重新确认")) | AO24: =IF(OR(A24="",H24="",H24<=0),"",(E24*H24+IF(AND(AK24<>"",AL24<>""),AK24*AL24,0)+IF(AND(AM24<>"",AN24<>""),AM24*AN24,0))/AP24) | AP24: =IF(OR(A24="",H24="",H24<=0),"",H24+IF(AL24="",0,AL24)+IF(AN24="",0,AN24)) | AQ24: =IF(A24="","",IF(M24<>"",0,IF(OR(H24="",N24=""),"",MAX(E24-MAX(N24,IFERROR(AGGREGATE(14,6,'持仓跟踪'!$S$2:$S$501/(('持仓跟踪'!$A$2:$A$501="每日跟踪")*('持仓跟踪'!$B$2:$B$501=A24)),1),0)),0)*H24+IF(OR(AK24="",AL24=""),0,MAX(AK24-MAX(N24,IFERROR(AGGREGATE(14,6,'持仓跟踪'!$S$2:$S$501/(('持仓跟踪'!$A$2:$A$501="每日跟踪")*('持仓跟踪'!$B$2:$B$501=A24)),1),0)),0)*AL24)+IF(OR(AM24="",AN24=""),0,MAX(AM24-MAX(N24,IFERROR(AGGREGATE(14,6,'持仓跟踪'!$S$2:$S$501/(('持仓跟踪'!$A$2:$A$501="每日跟踪")*('持仓跟踪'!$B$2:$B$501=A24)),1),0)),0)*AN24)))) | AR24: =IF(A24="","",IF(OR(E24="",H24=""),"违规：第一批价格或股数缺失",IF(OR(AND(AK24="",AL24<>""),AND(AK24<>"",AL24="")),"违规：第二批价格与股数须成对填写",IF(OR(AND(AM24="",AN24<>""),AND(AM24<>"",AN24="")),"违规：第三批价格与股数须成对填写",IF(AND(OR(AM24<>"",AN24<>""),OR(AK24="",AL24="")),"违规：必须先完成第二批",IF(OR(H24<=0,H24<>INT(H24),MOD(H24,100)<>0,AND(AL24<>"",OR(AL24<=0,AL24<>INT(AL24),MOD(AL24,100)<>0)),AND(AN24<>"",OR(AN24<=0,AN24<>INT(AN24),MOD(AN24,100)<>0))),"违规：股数须为100股整数倍",IF(AND(OR(AL24<>"",AN24<>""),OR(_LockStatus="已锁仓",_LockStatus="解锁信息不完整")),"违规：锁仓期间禁止加仓",IF(AQ24>C24*D24,"违规：超过单笔风险上限",IF(SUM($AQ$2:$AQ$201)>账户数据!$B$7,"违规：超过账户风险上限","通过")))))))))
A25: 24 | B25: 通富微电 | C25: 132428 | D25: 0.02 | E25: 22.04 | F25: =IF(OR(C25="",D25="",E25="",N25="",C25<=0,D25<=0,E25<=N25),"",ROUNDDOWN((C25*D25)/(E25-N25)/100,0)*100) | G25: =IF(A25="","",IF(H25<>"","已开仓",IF(账户数据!$B$23="已锁仓","禁止开仓：连续亏损达到上限",IF(账户数据!$B$23="解锁信息不完整","禁止开仓：请完整填写解锁信息",IF(OR(F25="",E25="",N25="",E25<=N25,账户数据!$B$7=""),"",IF(OR(AG25="",AH25="",AI25=""),"禁止开仓：交易预期未填写完整",IF(COUNTIFS(持仓跟踪!$A$2:$A$501,"止损计划",持仓跟踪!$B$2:$B$501,A25,持仓跟踪!$AC$2:$AC$501,"计划有效")=0,"禁止开仓：请先填写止损计划",IF(账户数据!$B$9+F25*(E25-N25)>=账户数据!$B$7,"禁止开仓：风险额度不足",IF(AJ25="周期与交易预期不匹配，请重新确认",IF(账户数据!$B$23="接近锁仓","允许开仓（接近锁仓；周期需复核）","允许开仓（周期需复核）"),IF(账户数据!$B$23="接近锁仓","允许开仓（接近锁仓）","允许开仓")))))))))) | H25: 2100 | I25: 45503 | J25: 24.5 | K25: 20.51 | L25: =IF(K25="","",H25) | M25: 45509 | N25: 20.8 | U25: =IF(OR(AO25="",J25="",AO25<=0),"",(J25-AO25)/AO25) | V25: =IF(OR(AO25="",N25="",AO25<=0),"",(AO25-N25)/AO25) | W25: =IF(OR(U25="",V25="",V25<=0),"",U25/V25) | X25: =IF(OR(K25="",L25="",AP25=""),"",K25*L25-(E25*H25+IF(AND(AK25<>"",AL25<>""),AK25*AL25,0)+IF(AND(AM25<>"",AN25<>""),AM25*AN25,0))-IF(O25="",0,O25)-IF(P25="",0,P25)) | Y25: =IF(OR(X25="",AP25=""),"",IF((E25*H25+IF(AND(AK25<>"",AL25<>""),AK25*AL25,0)+IF(AND(AM25<>"",AN25<>""),AM25*AN25,0))+IF(O25="",0,O25)<=0,"",X25/((E25*H25+IF(AND(AK25<>"",AL25<>""),AK25*AL25,0)+IF(AND(AM25<>"",AN25<>""),AM25*AN25,0))+IF(O25="",0,O25)))) | Z25: =IF(OR(AE25="",多次统计数据!$B$8=""),"",AE25-多次统计数据!$B$8) | AA25: =IF(OR(I25="",M25="",M25<I25),"",M25-I25) | AB25: =IF(OR(A25="",多次统计数据!$B$8="",多次统计数据!$B$6<=0,多次统计数据!$B$6>=1),"",1-POWER(1+多次统计数据!$B$8,-多次统计数据!$B$6/(1-多次统计数据!$B$6))) | AC25: =IF(OR(AB25="",多次统计数据!$B$9=""),"",IF(多次统计数据!$B$9<AB25,"低于上限","达到或超过上限")) | AE25: =IF(OR(X25="",C25="",C25<=0),"",X25/C25) | AJ25: =IF(OR(AG25="",AH25=""),"",IF(OR(AND(AG25="短期博反弹",OR(AH25="1～3个交易日",AH25="4～10个交易日")),AND(AG25="突破冲新高",OR(AH25="4～10个交易日",AH25="11～20个交易日")),AND(AG25="趋势波段",OR(AH25="11～20个交易日",AH25="21～60个交易日",AH25="60个交易日以上"))),"匹配","周期与交易预期不匹配，请重新确认")) | AO25: =IF(OR(A25="",H25="",H25<=0),"",(E25*H25+IF(AND(AK25<>"",AL25<>""),AK25*AL25,0)+IF(AND(AM25<>"",AN25<>""),AM25*AN25,0))/AP25) | AP25: =IF(OR(A25="",H25="",H25<=0),"",H25+IF(AL25="",0,AL25)+IF(AN25="",0,AN25)) | AQ25: =IF(A25="","",IF(M25<>"",0,IF(OR(H25="",N25=""),"",MAX(E25-MAX(N25,IFERROR(AGGREGATE(14,6,'持仓跟踪'!$S$2:$S$501/(('持仓跟踪'!$A$2:$A$501="每日跟踪")*('持仓跟踪'!$B$2:$B$501=A25)),1),0)),0)*H25+IF(OR(AK25="",AL25=""),0,MAX(AK25-MAX(N25,IFERROR(AGGREGATE(14,6,'持仓跟踪'!$S$2:$S$501/(('持仓跟踪'!$A$2:$A$501="每日跟踪")*('持仓跟踪'!$B$2:$B$501=A25)),1),0)),0)*AL25)+IF(OR(AM25="",AN25=""),0,MAX(AM25-MAX(N25,IFERROR(AGGREGATE(14,6,'持仓跟踪'!$S$2:$S$501/(('持仓跟踪'!$A$2:$A$501="每日跟踪")*('持仓跟踪'!$B$2:$B$501=A25)),1),0)),0)*AN25)))) | AR25: =IF(A25="","",IF(OR(E25="",H25=""),"违规：第一批价格或股数缺失",IF(OR(AND(AK25="",AL25<>""),AND(AK25<>"",AL25="")),"违规：第二批价格与股数须成对填写",IF(OR(AND(AM25="",AN25<>""),AND(AM25<>"",AN25="")),"违规：第三批价格与股数须成对填写",IF(AND(OR(AM25<>"",AN25<>""),OR(AK25="",AL25="")),"违规：必须先完成第二批",IF(OR(H25<=0,H25<>INT(H25),MOD(H25,100)<>0,AND(AL25<>"",OR(AL25<=0,AL25<>INT(AL25),MOD(AL25,100)<>0)),AND(AN25<>"",OR(AN25<=0,AN25<>INT(AN25),MOD(AN25,100)<>0))),"违规：股数须为100股整数倍",IF(AND(OR(AL25<>"",AN25<>""),OR(_LockStatus="已锁仓",_LockStatus="解锁信息不完整")),"违规：锁仓期间禁止加仓",IF(AQ25>C25*D25,"违规：超过单笔风险上限",IF(SUM($AQ$2:$AQ$201)>账户数据!$B$7,"违规：超过账户风险上限","通过")))))))))
A26: 25 | B26: 通富微电 | C26: 129215 | D26: 0.02 | E26: 18.92 | F26: =IF(OR(C26="",D26="",E26="",N26="",C26<=0,D26<=0,E26<=N26),"",ROUNDDOWN((C26*D26)/(E26-N26)/100,0)*100) | G26: =IF(A26="","",IF(H26<>"","已开仓",IF(账户数据!$B$23="已锁仓","禁止开仓：连续亏损达到上限",IF(账户数据!$B$23="解锁信息不完整","禁止开仓：请完整填写解锁信息",IF(OR(F26="",E26="",N26="",E26<=N26,账户数据!$B$7=""),"",IF(OR(AG26="",AH26="",AI26=""),"禁止开仓：交易预期未填写完整",IF(COUNTIFS(持仓跟踪!$A$2:$A$501,"止损计划",持仓跟踪!$B$2:$B$501,A26,持仓跟踪!$AC$2:$AC$501,"计划有效")=0,"禁止开仓：请先填写止损计划",IF(账户数据!$B$9+F26*(E26-N26)>=账户数据!$B$7,"禁止开仓：风险额度不足",IF(AJ26="周期与交易预期不匹配，请重新确认",IF(账户数据!$B$23="接近锁仓","允许开仓（接近锁仓；周期需复核）","允许开仓（周期需复核）"),IF(账户数据!$B$23="接近锁仓","允许开仓（接近锁仓）","允许开仓")))))))))) | H26: 2800 | I26: 45559 | J26: 21 | K26: 24.77 | L26: =IF(K26="","",H26) | M26: 45574 | N26: 18 | U26: =IF(OR(AO26="",J26="",AO26<=0),"",(J26-AO26)/AO26) | V26: =IF(OR(AO26="",N26="",AO26<=0),"",(AO26-N26)/AO26) | W26: =IF(OR(U26="",V26="",V26<=0),"",U26/V26) | X26: =IF(OR(K26="",L26="",AP26=""),"",K26*L26-(E26*H26+IF(AND(AK26<>"",AL26<>""),AK26*AL26,0)+IF(AND(AM26<>"",AN26<>""),AM26*AN26,0))-IF(O26="",0,O26)-IF(P26="",0,P26)) | Y26: =IF(OR(X26="",AP26=""),"",IF((E26*H26+IF(AND(AK26<>"",AL26<>""),AK26*AL26,0)+IF(AND(AM26<>"",AN26<>""),AM26*AN26,0))+IF(O26="",0,O26)<=0,"",X26/((E26*H26+IF(AND(AK26<>"",AL26<>""),AK26*AL26,0)+IF(AND(AM26<>"",AN26<>""),AM26*AN26,0))+IF(O26="",0,O26)))) | Z26: =IF(OR(AE26="",多次统计数据!$B$8=""),"",AE26-多次统计数据!$B$8) | AA26: =IF(OR(I26="",M26="",M26<I26),"",M26-I26) | AB26: =IF(OR(A26="",多次统计数据!$B$8="",多次统计数据!$B$6<=0,多次统计数据!$B$6>=1),"",1-POWER(1+多次统计数据!$B$8,-多次统计数据!$B$6/(1-多次统计数据!$B$6))) | AC26: =IF(OR(AB26="",多次统计数据!$B$9=""),"",IF(多次统计数据!$B$9<AB26,"低于上限","达到或超过上限")) | AE26: =IF(OR(X26="",C26="",C26<=0),"",X26/C26) | AJ26: =IF(OR(AG26="",AH26=""),"",IF(OR(AND(AG26="短期博反弹",OR(AH26="1～3个交易日",AH26="4～10个交易日")),AND(AG26="突破冲新高",OR(AH26="4～10个交易日",AH26="11～20个交易日")),AND(AG26="趋势波段",OR(AH26="11～20个交易日",AH26="21～60个交易日",AH26="60个交易日以上"))),"匹配","周期与交易预期不匹配，请重新确认")) | AO26: =IF(OR(A26="",H26="",H26<=0),"",(E26*H26+IF(AND(AK26<>"",AL26<>""),AK26*AL26,0)+IF(AND(AM26<>"",AN26<>""),AM26*AN26,0))/AP26) | AP26: =IF(OR(A26="",H26="",H26<=0),"",H26+IF(AL26="",0,AL26)+IF(AN26="",0,AN26)) | AQ26: =IF(A26="","",IF(M26<>"",0,IF(OR(H26="",N26=""),"",MAX(E26-MAX(N26,IFERROR(AGGREGATE(14,6,'持仓跟踪'!$S$2:$S$501/(('持仓跟踪'!$A$2:$A$501="每日跟踪")*('持仓跟踪'!$B$2:$B$501=A26)),1),0)),0)*H26+IF(OR(AK26="",AL26=""),0,MAX(AK26-MAX(N26,IFERROR(AGGREGATE(14,6,'持仓跟踪'!$S$2:$S$501/(('持仓跟踪'!$A$2:$A$501="每日跟踪")*('持仓跟踪'!$B$2:$B$501=A26)),1),0)),0)*AL26)+IF(OR(AM26="",AN26=""),0,MAX(AM26-MAX(N26,IFERROR(AGGREGATE(14,6,'持仓跟踪'!$S$2:$S$501/(('持仓跟踪'!$A$2:$A$501="每日跟踪")*('持仓跟踪'!$B$2:$B$501=A26)),1),0)),0)*AN26)))) | AR26: =IF(A26="","",IF(OR(E26="",H26=""),"违规：第一批价格或股数缺失",IF(OR(AND(AK26="",AL26<>""),AND(AK26<>"",AL26="")),"违规：第二批价格与股数须成对填写",IF(OR(AND(AM26="",AN26<>""),AND(AM26<>"",AN26="")),"违规：第三批价格与股数须成对填写",IF(AND(OR(AM26<>"",AN26<>""),OR(AK26="",AL26="")),"违规：必须先完成第二批",IF(OR(H26<=0,H26<>INT(H26),MOD(H26,100)<>0,AND(AL26<>"",OR(AL26<=0,AL26<>INT(AL26),MOD(AL26,100)<>0)),AND(AN26<>"",OR(AN26<=0,AN26<>INT(AN26),MOD(AN26,100)<>0))),"违规：股数须为100股整数倍",IF(AND(OR(AL26<>"",AN26<>""),OR(_LockStatus="已锁仓",_LockStatus="解锁信息不完整")),"违规：锁仓期间禁止加仓",IF(AQ26>C26*D26,"违规：超过单笔风险上限",IF(SUM($AQ$2:$AQ$201)>账户数据!$B$7,"违规：超过账户风险上限","通过")))))))))
... A30: 29 | B30: 比亚迪 | C30: 151651 | D30: 0.02 | E30: 83.5 | F30: =IF(OR(C30="",D30="",E30="",N30="",C30<=0,D30<=0,E30<=N30),"",ROUNDDOWN((C30*D30)/(E30-N30)/100,0)*100) | G30: =IF(A30="","",IF(H30<>"","已开仓",IF(账户数据!$B$23="已锁仓","禁止开仓：连续亏损达到上限",IF(账户数据!$B$23="解锁信息不完整","禁止开仓：请完整填写解锁信息",IF(OR(F30="",E30="",N30="",E30<=N30,账户数据!$B$7=""),"",IF(OR(AG30="",AH30="",AI30=""),"禁止开仓：交易预期未填写完整",IF(COUNTIFS(持仓跟踪!$A$2:$A$501,"止损计划",持仓跟踪!$B$2:$B$501,A30,持仓跟踪!$AC$2:$AC$501,"计划有效")=0,"禁止开仓：请先填写止损计划",IF(账户数据!$B$9+F30*(E30-N30)>=账户数据!$B$7,"禁止开仓：风险额度不足",IF(AJ30="周期与交易预期不匹配，请重新确认",IF(账户数据!$B$23="接近锁仓","允许开仓（接近锁仓；周期需复核）","允许开仓（周期需复核）"),IF(账户数据!$B$23="接近锁仓","允许开仓（接近锁仓）","允许开仓")))))))))) | H30: 800 | I30: 45056 | J30: 90 | K30: 79.23 | L30: =IF(K30="","",H30) | M30: 45072 | N30: 80 | U30: =IF(OR(AO30="",J30="",AO30<=0),"",(J30-AO30)/AO30) | V30: =IF(OR(AO30="",N30="",AO30<=0),"",(AO30-N30)/AO30) | W30: =IF(OR(U30="",V30="",V30<=0),"",U30/V30) | X30: =IF(OR(K30="",L30="",AP30=""),"",K30*L30-(E30*H30+IF(AND(AK30<>"",AL30<>""),AK30*AL30,0)+IF(AND(AM30<>"",AN30<>""),AM30*AN30,0))-IF(O30="",0,O30)-IF(P30="",0,P30)) | Y30: =IF(OR(X30="",AP30=""),"",IF((E30*H30+IF(AND(AK30<>"",AL30<>""),AK30*AL30,0)+IF(AND(AM30<>"",AN30<>""),AM30*AN30,0))+IF(O30="",0,O30)<=0,"",X30/((E30*H30+IF(AND(AK30<>"",AL30<>""),AK30*AL30,0)+IF(AND(AM30<>"",AN30<>""),AM30*AN30,0))+IF(O30="",0,O30)))) | Z30: =IF(OR(AE30="",多次统计数据!$B$8=""),"",AE30-多次统计数据!$B$8) | AA30: =IF(OR(I30="",M30="",M30<I30),"",M30-I30) | AB30: =IF(OR(A30="",多次统计数据!$B$8="",多次统计数据!$B$6<=0,多次统计数据!$B$6>=1),"",1-POWER(1+多次统计数据!$B$8,-多次统计数据!$B$6/(1-多次统计数据!$B$6))) | AC30: =IF(OR(AB30="",多次统计数据!$B$9=""),"",IF(多次统计数据!$B$9<AB30,"低于上限","达到或超过上限")) | AE30: =IF(OR(X30="",C30="",C30<=0),"",X30/C30) | AJ30: =IF(OR(AG30="",AH30=""),"",IF(OR(AND(AG30="短期博反弹",OR(AH30="1～3个交易日",AH30="4～10个交易日")),AND(AG30="突破冲新高",OR(AH30="4～10个交易日",AH30="11～20个交易日")),AND(AG30="趋势波段",OR(AH30="11～20个交易日",AH30="21～60个交易日",AH30="60个交易日以上"))),"匹配","周期与交易预期不匹配，请重新确认")) | AO30: =IF(OR(A30="",H30="",H30<=0),"",(E30*H30+IF(AND(AK30<>"",AL30<>""),AK30*AL30,0)+IF(AND(AM30<>"",AN30<>""),AM30*AN30,0))/AP30) | AP30: =IF(OR(A30="",H30="",H30<=0),"",H30+IF(AL30="",0,AL30)+IF(AN30="",0,AN30)) | AQ30: =IF(A30="","",IF(M30<>"",0,IF(OR(H30="",N30=""),"",MAX(E30-MAX(N30,IFERROR(AGGREGATE(14,6,'持仓跟踪'!$S$2:$S$501/(('持仓跟踪'!$A$2:$A$501="每日跟踪")*('持仓跟踪'!$B$2:$B$501=A30)),1),0)),0)*H30+IF(OR(AK30="",AL30=""),0,MAX(AK30-MAX(N30,IFERROR(AGGREGATE(14,6,'持仓跟踪'!$S$2:$S$501/(('持仓跟踪'!$A$2:$A$501="每日跟踪")*('持仓跟踪'!$B$2:$B$501=A30)),1),0)),0)*AL30)+IF(OR(AM30="",AN30=""),0,MAX(AM30-MAX(N30,IFERROR(AGGREGATE(14,6,'持仓跟踪'!$S$2:$S$501/(('持仓跟踪'!$A$2:$A$501="每日跟踪")*('持仓跟踪'!$B$2:$B$501=A30)),1),0)),0)*AN30)))) | AR30: =IF(A30="","",IF(OR(E30="",H30=""),"违规：第一批价格或股数缺失",IF(OR(AND(AK30="",AL30<>""),AND(AK30<>"",AL30="")),"违规：第二批价格与股数须成对填写",IF(OR(AND(AM30="",AN30<>""),AND(AM30<>"",AN30="")),"违规：第三批价格与股数须成对填写",IF(AND(OR(AM30<>"",AN30<>""),OR(AK30="",AL30="")),"违规：必须先完成第二批",IF(OR(H30<=0,H30<>INT(H30),MOD(H30,100)<>0,AND(AL30<>"",OR(AL30<=0,AL30<>INT(AL30),MOD(AL30,100)<>0)),AND(AN30<>"",OR(AN30<=0,AN30<>INT(AN30),MOD(AN30,100)<>0))),"违规：股数须为100股整数倍",IF(AND(OR(AL30<>"",AN30<>""),OR(_LockStatus="已锁仓",_LockStatus="解锁信息不完整")),"违规：锁仓期间禁止加仓",IF(AQ30>C30*D30,"违规：超过单笔风险上限",IF(SUM($AQ$2:$AQ$201)>账户数据!$B$7,"违规：超过账户风险上限","通过")))))))))
A31: 30 | B31: 比亚迪 | C31: 148235 | D31: 0.02 | E31: 86.28 | F31: =IF(OR(C31="",D31="",E31="",N31="",C31<=0,D31<=0,E31<=N31),"",ROUNDDOWN((C31*D31)/(E31-N31)/100,0)*100) | G31: =IF(A31="","",IF(H31<>"","已开仓",IF(账户数据!$B$23="已锁仓","禁止开仓：连续亏损达到上限",IF(账户数据!$B$23="解锁信息不完整","禁止开仓：请完整填写解锁信息",IF(OR(F31="",E31="",N31="",E31<=N31,账户数据!$B$7=""),"",IF(OR(AG31="",AH31="",AI31=""),"禁止开仓：交易预期未填写完整",IF(COUNTIFS(持仓跟踪!$A$2:$A$501,"止损计划",持仓跟踪!$B$2:$B$501,A31,持仓跟踪!$AC$2:$AC$501,"计划有效")=0,"禁止开仓：请先填写止损计划",IF(账户数据!$B$9+F31*(E31-N31)>=账户数据!$B$7,"禁止开仓：风险额度不足",IF(AJ31="周期与交易预期不匹配，请重新确认",IF(账户数据!$B$23="接近锁仓","允许开仓（接近锁仓；周期需复核）","允许开仓（周期需复核）"),IF(账户数据!$B$23="接近锁仓","允许开仓（接近锁仓）","允许开仓")))))))))) | H31: 1300 | I31: 45135 | J31: 95 | K31: 79.22 | L31: =IF(K31="","",H31) | M31: 45152 | N31: 84 | U31: =IF(OR(AO31="",J31="",AO31<=0),"",(J31-AO31)/AO31) | V31: =IF(OR(AO31="",N31="",AO31<=0),"",(AO31-N31)/AO31) | W31: =IF(OR(U31="",V31="",V31<=0),"",U31/V31) | X31: =IF(OR(K31="",L31="",AP31=""),"",K31*L31-(E31*H31+IF(AND(AK31<>"",AL31<>""),AK31*AL31,0)+IF(AND(AM31<>"",AN31<>""),AM31*AN31,0))-IF(O31="",0,O31)-IF(P31="",0,P31)) | Y31: =IF(OR(X31="",AP31=""),"",IF((E31*H31+IF(AND(AK31<>"",AL31<>""),AK31*AL31,0)+IF(AND(AM31<>"",AN31<>""),AM31*AN31,0))+IF(O31="",0,O31)<=0,"",X31/((E31*H31+IF(AND(AK31<>"",AL31<>""),AK31*AL31,0)+IF(AND(AM31<>"",AN31<>""),AM31*AN31,0))+IF(O31="",0,O31)))) | Z31: =IF(OR(AE31="",多次统计数据!$B$8=""),"",AE31-多次统计数据!$B$8) | AA31: =IF(OR(I31="",M31="",M31<I31),"",M31-I31) | AB31: =IF(OR(A31="",多次统计数据!$B$8="",多次统计数据!$B$6<=0,多次统计数据!$B$6>=1),"",1-POWER(1+多次统计数据!$B$8,-多次统计数据!$B$6/(1-多次统计数据!$B$6))) | AC31: =IF(OR(AB31="",多次统计数据!$B$9=""),"",IF(多次统计数据!$B$9<AB31,"低于上限","达到或超过上限")) | AE31: =IF(OR(X31="",C31="",C31<=0),"",X31/C31) | AF31: 特别注意，放大了风险 | AJ31: =IF(OR(AG31="",AH31=""),"",IF(OR(AND(AG31="短期博反弹",OR(AH31="1～3个交易日",AH31="4～10个交易日")),AND(AG31="突破冲新高",OR(AH31="4～10个交易日",AH31="11～20个交易日")),AND(AG31="趋势波段",OR(AH31="11～20个交易日",AH31="21～60个交易日",AH31="60个交易日以上"))),"匹配","周期与交易预期不匹配，请重新确认")) | AO31: =IF(OR(A31="",H31="",H31<=0),"",(E31*H31+IF(AND(AK31<>"",AL31<>""),AK31*AL31,0)+IF(AND(AM31<>"",AN31<>""),AM31*AN31,0))/AP31) | AP31: =IF(OR(A31="",H31="",H31<=0),"",H31+IF(AL31="",0,AL31)+IF(AN31="",0,AN31)) | AQ31: =IF(A31="","",IF(M31<>"",0,IF(OR(H31="",N31=""),"",MAX(E31-MAX(N31,IFERROR(AGGREGATE(14,6,'持仓跟踪'!$S$2:$S$501/(('持仓跟踪'!$A$2:$A$501="每日跟踪")*('持仓跟踪'!$B$2:$B$501=A31)),1),0)),0)*H31+IF(OR(AK31="",AL31=""),0,MAX(AK31-MAX(N31,IFERROR(AGGREGATE(14,6,'持仓跟踪'!$S$2:$S$501/(('持仓跟踪'!$A$2:$A$501="每日跟踪")*('持仓跟踪'!$B$2:$B$501=A31)),1),0)),0)*AL31)+IF(OR(AM31="",AN31=""),0,MAX(AM31-MAX(N31,IFERROR(AGGREGATE(14,6,'持仓跟踪'!$S$2:$S$501/(('持仓跟踪'!$A$2:$A$501="每日跟踪")*('持仓跟踪'!$B$2:$B$501=A31)),1),0)),0)*AN31)))) | AR31: =IF(A31="","",IF(OR(E31="",H31=""),"违规：第一批价格或股数缺失",IF(OR(AND(AK31="",AL31<>""),AND(AK31<>"",AL31="")),"违规：第二批价格与股数须成对填写",IF(OR(AND(AM31="",AN31<>""),AND(AM31<>"",AN31="")),"违规：第三批价格与股数须成对填写",IF(AND(OR(AM31<>"",AN31<>""),OR(AK31="",AL31="")),"违规：必须先完成第二批",IF(OR(H31<=0,H31<>INT(H31),MOD(H31,100)<>0,AND(AL31<>"",OR(AL31<=0,AL31<>INT(AL31),MOD(AL31,100)<>0)),AND(AN31<>"",OR(AN31<=0,AN31<>INT(AN31),MOD(AN31,100)<>0))),"违规：股数须为100股整数倍",IF(AND(OR(AL31<>"",AN31<>""),OR(_LockStatus="已锁仓",_LockStatus="解锁信息不完整")),"违规：锁仓期间禁止加仓",IF(AQ31>C31*D31,"违规：超过单笔风险上限",IF(SUM($AQ$2:$AQ$201)>账户数据!$B$7,"违规：超过账户风险上限","通过")))))))))
A32: 31 | B32: 比亚迪 | C32: 139057 | D32: 0.02 | E32: 73.91 | F32: =IF(OR(C32="",D32="",E32="",N32="",C32<=0,D32<=0,E32<=N32),"",ROUNDDOWN((C32*D32)/(E32-N32)/100,0)*100) | G32: =IF(A32="","",IF(H32<>"","已开仓",IF(账户数据!$B$23="已锁仓","禁止开仓：连续亏损达到上限",IF(账户数据!$B$23="解锁信息不完整","禁止开仓：请完整填写解锁信息",IF(OR(F32="",E32="",N32="",E32<=N32,账户数据!$B$7=""),"",IF(OR(AG32="",AH32="",AI32=""),"禁止开仓：交易预期未填写完整",IF(COUNTIFS(持仓跟踪!$A$2:$A$501,"止损计划",持仓跟踪!$B$2:$B$501,A32,持仓跟踪!$AC$2:$AC$501,"计划有效")=0,"禁止开仓：请先填写止损计划",IF(账户数据!$B$9+F32*(E32-N32)>=账户数据!$B$7,"禁止开仓：风险额度不足",IF(AJ32="周期与交易预期不匹配，请重新确认",IF(账户数据!$B$23="接近锁仓","允许开仓（接近锁仓；周期需复核）","允许开仓（周期需复核）"),IF(账户数据!$B$23="接近锁仓","允许开仓（接近锁仓）","允许开仓")))))))))) | H32: 700 | I32: 45419 | J32: 75 | K32: 69.59 | L32: =IF(K32="","",H32) | M32: 45434 | N32: 70 | U32: =IF(OR(AO32="",J32="",AO32<=0),"",(J32-AO32)/AO32) | V32: =IF(OR(AO32="",N32="",AO32<=0),"",(AO32-N32)/AO32) | W32: =IF(OR(U32="",V32="",V32<=0),"",U32/V32) | X32: =IF(OR(K32="",L32="",AP32=""),"",K32*L32-(E32*H32+IF(AND(AK32<>"",AL32<>""),AK32*AL32,0)+IF(AND(AM32<>"",AN32<>""),AM32*AN32,0))-IF(O32="",0,O32)-IF(P32="",0,P32)) | Y32: =IF(OR(X32="",AP32=""),"",IF((E32*H32+IF(AND(AK32<>"",AL32<>""),AK32*AL32,0)+IF(AND(AM32<>"",AN32<>""),AM32*AN32,0))+IF(O32="",0,O32)<=0,"",X32/((E32*H32+IF(AND(AK32<>"",AL32<>""),AK32*AL32,0)+IF(AND(AM32<>"",AN32<>""),AM32*AN32,0))+IF(O32="",0,O32)))) | Z32: =IF(OR(AE32="",多次统计数据!$B$8=""),"",AE32-多次统计数据!$B$8) | AA32: =IF(OR(I32="",M32="",M32<I32),"",M32-I32) | AB32: =IF(OR(A32="",多次统计数据!$B$8="",多次统计数据!$B$6<=0,多次统计数据!$B$6>=1),"",1-POWER(1+多次统计数据!$B$8,-多次统计数据!$B$6/(1-多次统计数据!$B$6))) | AC32: =IF(OR(AB32="",多次统计数据!$B$9=""),"",IF(多次统计数据!$B$9<AB32,"低于上限","达到或超过上限")) | AE32: =IF(OR(X32="",C32="",C32<=0),"",X32/C32) | AJ32: =IF(OR(AG32="",AH32=""),"",IF(OR(AND(AG32="短期博反弹",OR(AH32="1～3个交易日",AH32="4～10个交易日")),AND(AG32="突破冲新高",OR(AH32="4～10个交易日",AH32="11～20个交易日")),AND(AG32="趋势波段",OR(AH32="11～20个交易日",AH32="21～60个交易日",AH32="60个交易日以上"))),"匹配","周期与交易预期不匹配，请重新确认")) | AO32: =IF(OR(A32="",H32="",H32<=0),"",(E32*H32+IF(AND(AK32<>"",AL32<>""),AK32*AL32,0)+IF(AND(AM32<>"",AN32<>""),AM32*AN32,0))/AP32) | AP32: =IF(OR(A32="",H32="",H32<=0),"",H32+IF(AL32="",0,AL32)+IF(AN32="",0,AN32)) | AQ32: =IF(A32="","",IF(M32<>"",0,IF(OR(H32="",N32=""),"",MAX(E32-MAX(N32,IFERROR(AGGREGATE(14,6,'持仓跟踪'!$S$2:$S$501/(('持仓跟踪'!$A$2:$A$501="每日跟踪")*('持仓跟踪'!$B$2:$B$501=A32)),1),0)),0)*H32+IF(OR(AK32="",AL32=""),0,MAX(AK32-MAX(N32,IFERROR(AGGREGATE(14,6,'持仓跟踪'!$S$2:$S$501/(('持仓跟踪'!$A$2:$A$501="每日跟踪")*('持仓跟踪'!$B$2:$B$501=A32)),1),0)),0)*AL32)+IF(OR(AM32="",AN32=""),0,MAX(AM32-MAX(N32,IFERROR(AGGREGATE(14,6,'持仓跟踪'!$S$2:$S$501/(('持仓跟踪'!$A$2:$A$501="每日跟踪")*('持仓跟踪'!$B$2:$B$501=A32)),1),0)),0)*AN32)))) | AR32: =IF(A32="","",IF(OR(E32="",H32=""),"违规：第一批价格或股数缺失",IF(OR(AND(AK32="",AL32<>""),AND(AK32<>"",AL32="")),"违规：第二批价格与股数须成对填写",IF(OR(AND(AM32="",AN32<>""),AND(AM32<>"",AN32="")),"违规：第三批价格与股数须成对填写",IF(AND(OR(AM32<>"",AN32<>""),OR(AK32="",AL32="")),"违规：必须先完成第二批",IF(OR(H32<=0,H32<>INT(H32),MOD(H32,100)<>0,AND(AL32<>"",OR(AL32<=0,AL32<>INT(AL32),MOD(AL32,100)<>0)),AND(AN32<>"",OR(AN32<=0,AN32<>INT(AN32),MOD(AN32,100)<>0))),"违规：股数须为100股整数倍",IF(AND(OR(AL32<>"",AN32<>""),OR(_LockStatus="已锁仓",_LockStatus="解锁信息不完整")),"违规：锁仓期间禁止加仓",IF(AQ32>C32*D32,"违规：超过单笔风险上限",IF(SUM($AQ$2:$AQ$201)>账户数据!$B$7,"违规：超过账户风险上限","通过")))))))))
A33: 32 | B33: 沪电股份 | C33: 136033 | D33: 0.02 | E33: 11.92 | F33: =IF(OR(C33="",D33="",E33="",N33="",C33<=0,D33<=0,E33<=N33),"",ROUNDDOWN((C33*D33)/(E33-N33)/100,0)*100) | G33: =IF(A33="","",IF(H33<>"","已开仓",IF(账户数据!$B$23="已锁仓","禁止开仓：连续亏损达到上限",IF(账户数据!$B$23="解锁信息不完整","禁止开仓：请完整填写解锁信息",IF(OR(F33="",E33="",N33="",E33<=N33,账户数据!$B$7=""),"",IF(OR(AG33="",AH33="",AI33=""),"禁止开仓：交易预期未填写完整",IF(COUNTIFS(持仓跟踪!$A$2:$A$501,"止损计划",持仓跟踪!$B$2:$B$501,A33,持仓跟踪!$AC$2:$AC$501,"计划有效")=0,"禁止开仓：请先填写止损计划",IF(账户数据!$B$9+F33*(E33-N33)>=账户数据!$B$7,"禁止开仓：风险额度不足",IF(AJ33="周期与交易预期不匹配，请重新确认",IF(账户数据!$B$23="接近锁仓","允许开仓（接近锁仓；周期需复核）","允许开仓（周期需复核）"),IF(账户数据!$B$23="接近锁仓","允许开仓（接近锁仓）","允许开仓")))))))))) | H33: 6400 | I33: 44344 | J33: 12.75 | K33: 11.24 | L33: =IF(K33="","",H33) | M33: 44362 | N33: 11.5 | U33: =IF(OR(AO33="",J33="",AO33<=0),"",(J33-AO33)/AO33) | V33: =IF(OR(AO33="",N33="",AO33<=0),"",(AO33-N33)/AO33) | W33: =IF(OR(U33="",V33="",V33<=0),"",U33/V33) | X33: =IF(OR(K33="",L33="",AP33=""),"",K33*L33-(E33*H33+IF(AND(AK33<>"",AL33<>""),AK33*AL33,0)+IF(AND(AM33<>"",AN33<>""),AM33*AN33,0))-IF(O33="",0,O33)-IF(P33="",0,P33)) | Y33: =IF(OR(X33="",AP33=""),"",IF((E33*H33+IF(AND(AK33<>"",AL33<>""),AK33*AL33,0)+IF(AND(AM33<>"",AN33<>""),AM33*AN33,0))+IF(O33="",0,O33)<=0,"",X33/((E33*H33+IF(AND(AK33<>"",AL33<>""),AK33*AL33,0)+IF(AND(AM33<>"",AN33<>""),AM33*AN33,0))+IF(O33="",0,O33)))) | Z33: =IF(OR(AE33="",多次统计数据!$B$8=""),"",AE33-多次统计数据!$B$8) | AA33: =IF(OR(I33="",M33="",M33<I33),"",M33-I33) | AB33: =IF(OR(A33="",多次统计数据!$B$8="",多次统计数据!$B$6<=0,多次统计数据!$B$6>=1),"",1-POWER(1+多次统计数据!$B$8,-多次统计数据!$B$6/(1-多次统计数据!$B$6))) | AC33: =IF(OR(AB33="",多次统计数据!$B$9=""),"",IF(多次统计数据!$B$9<AB33,"低于上限","达到或超过上限")) | AE33: =IF(OR(X33="",C33="",C33<=0),"",X33/C33) | AJ33: =IF(OR(AG33="",AH33=""),"",IF(OR(AND(AG33="短期博反弹",OR(AH33="1～3个交易日",AH33="4～10个交易日")),AND(AG33="突破冲新高",OR(AH33="4～10个交易日",AH33="11～20个交易日")),AND(AG33="趋势波段",OR(AH33="11～20个交易日",AH33="21～60个交易日",AH33="60个交易日以上"))),"匹配","周期与交易预期不匹配，请重新确认")) | AO33: =IF(OR(A33="",H33="",H33<=0),"",(E33*H33+IF(AND(AK33<>"",AL33<>""),AK33*AL33,0)+IF(AND(AM33<>"",AN33<>""),AM33*AN33,0))/AP33) | AP33: =IF(OR(A33="",H33="",H33<=0),"",H33+IF(AL33="",0,AL33)+IF(AN33="",0,AN33)) | AQ33: =IF(A33="","",IF(M33<>"",0,IF(OR(H33="",N33=""),"",MAX(E33-MAX(N33,IFERROR(AGGREGATE(14,6,'持仓跟踪'!$S$2:$S$501/(('持仓跟踪'!$A$2:$A$501="每日跟踪")*('持仓跟踪'!$B$2:$B$501=A33)),1),0)),0)*H33+IF(OR(AK33="",AL33=""),0,MAX(AK33-MAX(N33,IFERROR(AGGREGATE(14,6,'持仓跟踪'!$S$2:$S$501/(('持仓跟踪'!$A$2:$A$501="每日跟踪")*('持仓跟踪'!$B$2:$B$501=A33)),1),0)),0)*AL33)+IF(OR(AM33="",AN33=""),0,MAX(AM33-MAX(N33,IFERROR(AGGREGATE(14,6,'持仓跟踪'!$S$2:$S$501/(('持仓跟踪'!$A$2:$A$501="每日跟踪")*('持仓跟踪'!$B$2:$B$501=A33)),1),0)),0)*AN33)))) | AR33: =IF(A33="","",IF(OR(E33="",H33=""),"违规：第一批价格或股数缺失",IF(OR(AND(AK33="",AL33<>""),AND(AK33<>"",AL33="")),"违规：第二批价格与股数须成对填写",IF(OR(AND(AM33="",AN33<>""),AND(AM33<>"",AN33="")),"违规：第三批价格与股数须成对填写",IF(AND(OR(AM33<>"",AN33<>""),OR(AK33="",AL33="")),"违规：必须先完成第二批",IF(OR(H33<=0,H33<>INT(H33),MOD(H33,100)<>0,AND(AL33<>"",OR(AL33<=0,AL33<>INT(AL33),MOD(AL33,100)<>0)),AND(AN33<>"",OR(AN33<=0,AN33<>INT(AN33),MOD(AN33,100)<>0))),"违规：股数须为100股整数倍",IF(AND(OR(AL33<>"",AN33<>""),OR(_LockStatus="已锁仓",_LockStatus="解锁信息不完整")),"违规：锁仓期间禁止加仓",IF(AQ33>C33*D33,"违规：超过单笔风险上限",IF(SUM($AQ$2:$AQ$201)>账户数据!$B$7,"违规：超过账户风险上限","通过")))))))))
A34: 33 | B34: 沪电股份 | C34: 131681 | D34: 0.02 | E34: 12.13 | F34: =IF(OR(C34="",D34="",E34="",N34="",C34<=0,D34<=0,E34<=N34),"",ROUNDDOWN((C34*D34)/(E34-N34)/100,0)*100) | G34: =IF(A34="","",IF(H34<>"","已开仓",IF(账户数据!$B$23="已锁仓","禁止开仓：连续亏损达到上限",IF(账户数据!$B$23="解锁信息不完整","禁止开仓：请完整填写解锁信息",IF(OR(F34="",E34="",N34="",E34<=N34,账户数据!$B$7=""),"",IF(OR(AG34="",AH34="",AI34=""),"禁止开仓：交易预期未填写完整",IF(COUNTIFS(持仓跟踪!$A$2:$A$501,"止损计划",持仓跟踪!$B$2:$B$501,A34,持仓跟踪!$AC$2:$AC$501,"计划有效")=0,"禁止开仓：请先填写止损计划",IF(账户数据!$B$9+F34*(E34-N34)>=账户数据!$B$7,"禁止开仓：风险额度不足",IF(AJ34="周期与交易预期不匹配，请重新确认",IF(账户数据!$B$23="接近锁仓","允许开仓（接近锁仓；周期需复核）","允许开仓（周期需复核）"),IF(账户数据!$B$23="接近锁仓","允许开仓（接近锁仓）","允许开仓")))))))))) | H34: 2800 | I34: 44385 | J34: 13 | K34: 11.09 | L34: =IF(K34="","",H34) | M34: 44396 | N34: 11.2 | U34: =IF(OR(AO34="",J34="",AO34<=0),"",(J34-AO34)/AO34) | V34: =IF(OR(AO34="",N34="",AO34<=0),"",(AO34-N34)/AO34) | W34: =IF(OR(U34="",V34="",V34<=0),"",U34/V34) | X34: =IF(OR(K34="",L34="",AP34=""),"",K34*L34-(E34*H34+IF(AND(AK34<>"",AL34<>""),AK34*AL34,0)+IF(AND(AM34<>"",AN34<>""),AM34*AN34,0))-IF(O34="",0,O34)-IF(P34="",0,P34)) | Y34: =IF(OR(X34="",AP34=""),"",IF((E34*H34+IF(AND(AK34<>"",AL34<>""),AK34*AL34,0)+IF(AND(AM34<>"",AN34<>""),AM34*AN34,0))+IF(O34="",0,O34)<=0,"",X34/((E34*H34+IF(AND(AK34<>"",AL34<>""),AK34*AL34,0)+IF(AND(AM34<>"",AN34<>""),AM34*AN34,0))+IF(O34="",0,O34)))) | Z34: =IF(OR(AE34="",多次统计数据!$B$8=""),"",AE34-多次统计数据!$B$8) | AA34: =IF(OR(I34="",M34="",M34<I34),"",M34-I34) | AB34: =IF(OR(A34="",多次统计数据!$B$8="",多次统计数据!$B$6<=0,多次统计数据!$B$6>=1),"",1-POWER(1+多次统计数据!$B$8,-多次统计数据!$B$6/(1-多次统计数据!$B$6))) | AC34: =IF(OR(AB34="",多次统计数据!$B$9=""),"",IF(多次统计数据!$B$9<AB34,"低于上限","达到或超过上限")) | AE34: =IF(OR(X34="",C34="",C34<=0),"",X34/C34) | AJ34: =IF(OR(AG34="",AH34=""),"",IF(OR(AND(AG34="短期博反弹",OR(AH34="1～3个交易日",AH34="4～10个交易日")),AND(AG34="突破冲新高",OR(AH34="4～10个交易日",AH34="11～20个交易日")),AND(AG34="趋势波段",OR(AH34="11～20个交易日",AH34="21～60个交易日",AH34="60个交易日以上"))),"匹配","周期与交易预期不匹配，请重新确认")) | AO34: =IF(OR(A34="",H34="",H34<=0),"",(E34*H34+IF(AND(AK34<>"",AL34<>""),AK34*AL34,0)+IF(AND(AM34<>"",AN34<>""),AM34*AN34,0))/AP34) | AP34: =IF(OR(A34="",H34="",H34<=0),"",H34+IF(AL34="",0,AL34)+IF(AN34="",0,AN34)) | AQ34: =IF(A34="","",IF(M34<>"",0,IF(OR(H34="",N34=""),"",MAX(E34-MAX(N34,IFERROR(AGGREGATE(14,6,'持仓跟踪'!$S$2:$S$501/(('持仓跟踪'!$A$2:$A$501="每日跟踪")*('持仓跟踪'!$B$2:$B$501=A34)),1),0)),0)*H34+IF(OR(AK34="",AL34=""),0,MAX(AK34-MAX(N34,IFERROR(AGGREGATE(14,6,'持仓跟踪'!$S$2:$S$501/(('持仓跟踪'!$A$2:$A$501="每日跟踪")*('持仓跟踪'!$B$2:$B$501=A34)),1),0)),0)*AL34)+IF(OR(AM34="",AN34=""),0,MAX(AM34-MAX(N34,IFERROR(AGGREGATE(14,6,'持仓跟踪'!$S$2:$S$501/(('持仓跟踪'!$A$2:$A$501="每日跟踪")*('持仓跟踪'!$B$2:$B$501=A34)),1),0)),0)*AN34)))) | AR34: =IF(A34="","",IF(OR(E34="",H34=""),"违规：第一批价格或股数缺失",IF(OR(AND(AK34="",AL34<>""),AND(AK34<>"",AL34="")),"违规：第二批价格与股数须成对填写",IF(OR(AND(AM34="",AN34<>""),AND(AM34<>"",AN34="")),"违规：第三批价格与股数须成对填写",IF(AND(OR(AM34<>"",AN34<>""),OR(AK34="",AL34="")),"违规：必须先完成第二批",IF(OR(H34<=0,H34<>INT(H34),MOD(H34,100)<>0,AND(AL34<>"",OR(AL34<=0,AL34<>INT(AL34),MOD(AL34,100)<>0)),AND(AN34<>"",OR(AN34<=0,AN34<>INT(AN34),MOD(AN34,100)<>0))),"违规：股数须为100股整数倍",IF(AND(OR(AL34<>"",AN34<>""),OR(_LockStatus="已锁仓",_LockStatus="解锁信息不完整")),"违规：锁仓期间禁止加仓",IF(AQ34>C34*D34,"违规：超过单笔风险上限",IF(SUM($AQ$2:$AQ$201)>账户数据!$B$7,"违规：超过账户风险上限","通过")))))))))
A35: 34 | B35: 沪电股份 | C35: 128769 | D35: 0.02 | E35: 11.08 | F35: =IF(OR(C35="",D35="",E35="",N35="",C35<=0,D35<=0,E35<=N35),"",ROUNDDOWN((C35*D35)/(E35-N35)/100,0)*100) | G35: =IF(A35="","",IF(H35<>"","已开仓",IF(账户数据!$B$23="已锁仓","禁止开仓：连续亏损达到上限",IF(账户数据!$B$23="解锁信息不完整","禁止开仓：请完整填写解锁信息",IF(OR(F35="",E35="",N35="",E35<=N35,账户数据!$B$7=""),"",IF(OR(AG35="",AH35="",AI35=""),"禁止开仓：交易预期未填写完整",IF(COUNTIFS(持仓跟踪!$A$2:$A$501,"止损计划",持仓跟踪!$B$2:$B$501,A35,持仓跟踪!$AC$2:$AC$501,"计划有效")=0,"禁止开仓：请先填写止损计划",IF(账户数据!$B$9+F35*(E35-N35)>=账户数据!$B$7,"禁止开仓：风险额度不足",IF(AJ35="周期与交易预期不匹配，请重新确认",IF(账户数据!$B$23="接近锁仓","允许开仓（接近锁仓；周期需复核）","允许开仓（周期需复核）"),IF(账户数据!$B$23="接近锁仓","允许开仓（接近锁仓）","允许开仓")))))))))) | H35: 4400 | I35: 44405 | J35: 12.36 | K35: 11.36 | L35: =IF(K35="","",H35) | M35: 44406 | N35: 10.5 | U35: =IF(OR(AO35="",J35="",AO35<=0),"",(J35-AO35)/AO35) | V35: =IF(OR(AO35="",N35="",AO35<=0),"",(AO35-N35)/AO35) | W35: =IF(OR(U35="",V35="",V35<=0),"",U35/V35) | X35: =IF(OR(K35="",L35="",AP35=""),"",K35*L35-(E35*H35+IF(AND(AK35<>"",AL35<>""),AK35*AL35,0)+IF(AND(AM35<>"",AN35<>""),AM35*AN35,0))-IF(O35="",0,O35)-IF(P35="",0,P35)) | Y35: =IF(OR(X35="",AP35=""),"",IF((E35*H35+IF(AND(AK35<>"",AL35<>""),AK35*AL35,0)+IF(AND(AM35<>"",AN35<>""),AM35*AN35,0))+IF(O35="",0,O35)<=0,"",X35/((E35*H35+IF(AND(AK35<>"",AL35<>""),AK35*AL35,0)+IF(AND(AM35<>"",AN35<>""),AM35*AN35,0))+IF(O35="",0,O35)))) | Z35: =IF(OR(AE35="",多次统计数据!$B$8=""),"",AE35-多次统计数据!$B$8) | AA35: =IF(OR(I35="",M35="",M35<I35),"",M35-I35) | AB35: =IF(OR(A35="",多次统计数据!$B$8="",多次统计数据!$B$6<=0,多次统计数据!$B$6>=1),"",1-POWER(1+多次统计数据!$B$8,-多次统计数据!$B$6/(1-多次统计数据!$B$6))) | AC35: =IF(OR(AB35="",多次统计数据!$B$9=""),"",IF(多次统计数据!$B$9<AB35,"低于上限","达到或超过上限")) | AE35: =IF(OR(X35="",C35="",C35<=0),"",X35/C35) | AJ35: =IF(OR(AG35="",AH35=""),"",IF(OR(AND(AG35="短期博反弹",OR(AH35="1～3个交易日",AH35="4～10个交易日")),AND(AG35="突破冲新高",OR(AH35="4～10个交易日",AH35="11～20个交易日")),AND(AG35="趋势波段",OR(AH35="11～20个交易日",AH35="21～60个交易日",AH35="60个交易日以上"))),"匹配","周期与交易预期不匹配，请重新确认")) | AO35: =IF(OR(A35="",H35="",H35<=0),"",(E35*H35+IF(AND(AK35<>"",AL35<>""),AK35*AL35,0)+IF(AND(AM35<>"",AN35<>""),AM35*AN35,0))/AP35) | AP35: =IF(OR(A35="",H35="",H35<=0),"",H35+IF(AL35="",0,AL35)+IF(AN35="",0,AN35)) | AQ35: =IF(A35="","",IF(M35<>"",0,IF(OR(H35="",N35=""),"",MAX(E35-MAX(N35,IFERROR(AGGREGATE(14,6,'持仓跟踪'!$S$2:$S$501/(('持仓跟踪'!$A$2:$A$501="每日跟踪")*('持仓跟踪'!$B$2:$B$501=A35)),1),0)),0)*H35+IF(OR(AK35="",AL35=""),0,MAX(AK35-MAX(N35,IFERROR(AGGREGATE(14,6,'持仓跟踪'!$S$2:$S$501/(('持仓跟踪'!$A$2:$A$501="每日跟踪")*('持仓跟踪'!$B$2:$B$501=A35)),1),0)),0)*AL35)+IF(OR(AM35="",AN35=""),0,MAX(AM35-MAX(N35,IFERROR(AGGREGATE(14,6,'持仓跟踪'!$S$2:$S$501/(('持仓跟踪'!$A$2:$A$501="每日跟踪")*('持仓跟踪'!$B$2:$B$501=A35)),1),0)),0)*AN35)))) | AR35: =IF(A35="","",IF(OR(E35="",H35=""),"违规：第一批价格或股数缺失",IF(OR(AND(AK35="",AL35<>""),AND(AK35<>"",AL35="")),"违规：第二批价格与股数须成对填写",IF(OR(AND(AM35="",AN35<>""),AND(AM35<>"",AN35="")),"违规：第三批价格与股数须成对填写",IF(AND(OR(AM35<>"",AN35<>""),OR(AK35="",AL35="")),"违规：必须先完成第二批",IF(OR(H35<=0,H35<>INT(H35),MOD(H35,100)<>0,AND(AL35<>"",OR(AL35<=0,AL35<>INT(AL35),MOD(AL35,100)<>0)),AND(AN35<>"",OR(AN35<=0,AN35<>INT(AN35),MOD(AN35,100)<>0))),"违规：股数须为100股整数倍",IF(AND(OR(AL35<>"",AN35<>""),OR(_LockStatus="已锁仓",_LockStatus="解锁信息不完整")),"违规：锁仓期间禁止加仓",IF(AQ35>C35*D35,"违规：超过单笔风险上限",IF(SUM($AQ$2:$AQ$201)>账户数据!$B$7,"违规：超过账户风险上限","通过")))))))))
A36: 35 | B36: 沪电股份 | C36: 130001 | D36: 0.02 | E36: 8.38 | F36: =IF(OR(C36="",D36="",E36="",N36="",C36<=0,D36<=0,E36<=N36),"",ROUNDDOWN((C36*D36)/(E36-N36)/100,0)*100) | G36: =IF(A36="","",IF(H36<>"","已开仓",IF(账户数据!$B$23="已锁仓","禁止开仓：连续亏损达到上限",IF(账户数据!$B$23="解锁信息不完整","禁止开仓：请完整填写解锁信息",IF(OR(F36="",E36="",N36="",E36<=N36,账户数据!$B$7=""),"",IF(OR(AG36="",AH36="",AI36=""),"禁止开仓：交易预期未填写完整",IF(COUNTIFS(持仓跟踪!$A$2:$A$501,"止损计划",持仓跟踪!$B$2:$B$501,A36,持仓跟踪!$AC$2:$AC$501,"计划有效")=0,"禁止开仓：请先填写止损计划",IF(账户数据!$B$9+F36*(E36-N36)>=账户数据!$B$7,"禁止开仓：风险额度不足",IF(AJ36="周期与交易预期不匹配，请重新确认",IF(账户数据!$B$23="接近锁仓","允许开仓（接近锁仓；周期需复核）","允许开仓（周期需复核）"),IF(账户数据!$B$23="接近锁仓","允许开仓（接近锁仓）","允许开仓")))))))))) | H36: 6800 | I36: 44496 | J36: 9.45 | K36: 9.8 | L36: =IF(K36="","",H36) | M36: 44508 | N36: 8 | U36: =IF(OR(AO36="",J36="",AO36<=0),"",(J36-AO36)/AO36) | V36: =IF(OR(AO36="",N36="",AO36<=0),"",(AO36-N36)/AO36) | W36: =IF(OR(U36="",V36="",V36<=0),"",U36/V36) | X36: =IF(OR(K36="",L36="",AP36=""),"",K36*L36-(E36*H36+IF(AND(AK36<>"",AL36<>""),AK36*AL36,0)+IF(AND(AM36<>"",AN36<>""),AM36*AN36,0))-IF(O36="",0,O36)-IF(P36="",0,P36)) | Y36: =IF(OR(X36="",AP36=""),"",IF((E36*H36+IF(AND(AK36<>"",AL36<>""),AK36*AL36,0)+IF(AND(AM36<>"",AN36<>""),AM36*AN36,0))+IF(O36="",0,O36)<=0,"",X36/((E36*H36+IF(AND(AK36<>"",AL36<>""),AK36*AL36,0)+IF(AND(AM36<>"",AN36<>""),AM36*AN36,0))+IF(O36="",0,O36)))) | Z36: =IF(OR(AE36="",多次统计数据!$B$8=""),"",AE36-多次统计数据!$B$8) | AA36: =IF(OR(I36="",M36="",M36<I36),"",M36-I36) | AB36: =IF(OR(A36="",多次统计数据!$B$8="",多次统计数据!$B$6<=0,多次统计数据!$B$6>=1),"",1-POWER(1+多次统计数据!$B$8,-多次统计数据!$B$6/(1-多次统计数据!$B$6))) | AC36: =IF(OR(AB36="",多次统计数据!$B$9=""),"",IF(多次统计数据!$B$9<AB36,"低于上限","达到或超过上限")) | AE36: =IF(OR(X36="",C36="",C36<=0),"",X36/C36) | AJ36: =IF(OR(AG36="",AH36=""),"",IF(OR(AND(AG36="短期博反弹",OR(AH36="1～3个交易日",AH36="4～10个交易日")),AND(AG36="突破冲新高",OR(AH36="4～10个交易日",AH36="11～20个交易日")),AND(AG36="趋势波段",OR(AH36="11～20个交易日",AH36="21～60个交易日",AH36="60个交易日以上"))),"匹配","周期与交易预期不匹配，请重新确认")) | AO36: =IF(OR(A36="",H36="",H36<=0),"",(E36*H36+IF(AND(AK36<>"",AL36<>""),AK36*AL36,0)+IF(AND(AM36<>"",AN36<>""),AM36*AN36,0))/AP36) | AP36: =IF(OR(A36="",H36="",H36<=0),"",H36+IF(AL36="",0,AL36)+IF(AN36="",0,AN36)) | AQ36: =IF(A36="","",IF(M36<>"",0,IF(OR(H36="",N36=""),"",MAX(E36-MAX(N36,IFERROR(AGGREGATE(14,6,'持仓跟踪'!$S$2:$S$501/(('持仓跟踪'!$A$2:$A$501="每日跟踪")*('持仓跟踪'!$B$2:$B$501=A36)),1),0)),0)*H36+IF(OR(AK36="",AL36=""),0,MAX(AK36-MAX(N36,IFERROR(AGGREGATE(14,6,'持仓跟踪'!$S$2:$S$501/(('持仓跟踪'!$A$2:$A$501="每日跟踪")*('持仓跟踪'!$B$2:$B$501=A36)),1),0)),0)*AL36)+IF(OR(AM36="",AN36=""),0,MAX(AM36-MAX(N36,IFERROR(AGGREGATE(14,6,'持仓跟踪'!$S$2:$S$501/(('持仓跟踪'!$A$2:$A$501="每日跟踪")*('持仓跟踪'!$B$2:$B$501=A36)),1),0)),0)*AN36)))) | AR36: =IF(A36="","",IF(OR(E36="",H36=""),"违规：第一批价格或股数缺失",IF(OR(AND(AK36="",AL36<>""),AND(AK36<>"",AL36="")),"违规：第二批价格与股数须成对填写",IF(OR(AND(AM36="",AN36<>""),AND(AM36<>"",AN36="")),"违规：第三批价格与股数须成对填写",IF(AND(OR(AM36<>"",AN36<>""),OR(AK36="",AL36="")),"违规：必须先完成第二批",IF(OR(H36<=0,H36<>INT(H36),MOD(H36,100)<>0,AND(AL36<>"",OR(AL36<=0,AL36<>INT(AL36),MOD(AL36,100)<>0)),AND(AN36<>"",OR(AN36<=0,AN36<>INT(AN36),MOD(AN36,100)<>0))),"违规：股数须为100股整数倍",IF(AND(OR(AL36<>"",AN36<>""),OR(_LockStatus="已锁仓",_LockStatus="解锁信息不完整")),"违规：锁仓期间禁止加仓",IF(AQ36>C36*D36,"违规：超过单笔风险上限",IF(SUM($AQ$2:$AQ$201)>账户数据!$B$7,"违规：超过账户风险上限","通过")))))))))
A37: 36 | B37: 沪电股份 | C37: 139657 | D37: 0.02 | E37: 15.16 | F37: =IF(OR(C37="",D37="",E37="",N37="",C37<=0,D37<=0,E37<=N37),"",ROUNDDOWN((C37*D37)/(E37-N37)/100,0)*100) | G37: =IF(A37="","",IF(H37<>"","已开仓",IF(账户数据!$B$23="已锁仓","禁止开仓：连续亏损达到上限",IF(账户数据!$B$23="解锁信息不完整","禁止开仓：请完整填写解锁信息",IF(OR(F37="",E37="",N37="",E37<=N37,账户数据!$B$7=""),"",IF(OR(AG37="",AH37="",AI37=""),"禁止开仓：交易预期未填写完整",IF(COUNTIFS(持仓跟踪!$A$2:$A$501,"止损计划",持仓跟踪!$B$2:$B$501,A37,持仓跟踪!$AC$2:$AC$501,"计划有效")=0,"禁止开仓：请先填写止损计划",IF(账户数据!$B$9+F37*(E37-N37)>=账户数据!$B$7,"禁止开仓：风险额度不足",IF(AJ37="周期与交易预期不匹配，请重新确认",IF(账户数据!$B$23="接近锁仓","允许开仓（接近锁仓；周期需复核）","允许开仓（周期需复核）"),IF(账户数据!$B$23="接近锁仓","允许开仓（接近锁仓）","允许开仓")))))))))) | H37: 2400 | I37: 44553 | J37: 18 | K37: 13.4 | L37: =IF(K37="","",H37) | M37: 44568 | N37: 14 | U37: =IF(OR(AO37="",J37="",AO37<=0),"",(J37-AO37)/AO37) | V37: =IF(OR(AO37="",N37="",AO37<=0),"",(AO37-N37)/AO37) | W37: =IF(OR(U37="",V37="",V37<=0),"",U37/V37) | X37: =IF(OR(K37="",L37="",AP37=""),"",K37*L37-(E37*H37+IF(AND(AK37<>"",AL37<>""),AK37*AL37,0)+IF(AND(AM37<>"",AN37<>""),AM37*AN37,0))-IF(O37="",0,O37)-IF(P37="",0,P37)) | Y37: =IF(OR(X37="",AP37=""),"",IF((E37*H37+IF(AND(AK37<>"",AL37<>""),AK37*AL37,0)+IF(AND(AM37<>"",AN37<>""),AM37*AN37,0))+IF(O37="",0,O37)<=0,"",X37/((E37*H37+IF(AND(AK37<>"",AL37<>""),AK37*AL37,0)+IF(AND(AM37<>"",AN37<>""),AM37*AN37,0))+IF(O37="",0,O37)))) | Z37: =IF(OR(AE37="",多次统计数据!$B$8=""),"",AE37-多次统计数据!$B$8) | AA37: =IF(OR(I37="",M37="",M37<I37),"",M37-I37) | AB37: =IF(OR(A37="",多次统计数据!$B$8="",多次统计数据!$B$6<=0,多次统计数据!$B$6>=1),"",1-POWER(1+多次统计数据!$B$8,-多次统计数据!$B$6/(1-多次统计数据!$B$6))) | AC37: =IF(OR(AB37="",多次统计数据!$B$9=""),"",IF(多次统计数据!$B$9<AB37,"低于上限","达到或超过上限")) | AE37: =IF(OR(X37="",C37="",C37<=0),"",X37/C37) | AJ37: =IF(OR(AG37="",AH37=""),"",IF(OR(AND(AG37="短期博反弹",OR(AH37="1～3个交易日",AH37="4～10个交易日")),AND(AG37="突破冲新高",OR(AH37="4～10个交易日",AH37="11～20个交易日")),AND(AG37="趋势波段",OR(AH37="11～20个交易日",AH37="21～60个交易日",AH37="60个交易日以上"))),"匹配","周期与交易预期不匹配，请重新确认")) | AO37: =IF(OR(A37="",H37="",H37<=0),"",(E37*H37+IF(AND(AK37<>"",AL37<>""),AK37*AL37,0)+IF(AND(AM37<>"",AN37<>""),AM37*AN37,0))/AP37) | AP37: =IF(OR(A37="",H37="",H37<=0),"",H37+IF(AL37="",0,AL37)+IF(AN37="",0,AN37)) | AQ37: =IF(A37="","",IF(M37<>"",0,IF(OR(H37="",N37=""),"",MAX(E37-MAX(N37,IFERROR(AGGREGATE(14,6,'持仓跟踪'!$S$2:$S$501/(('持仓跟踪'!$A$2:$A$501="每日跟踪")*('持仓跟踪'!$B$2:$B$501=A37)),1),0)),0)*H37+IF(OR(AK37="",AL37=""),0,MAX(AK37-MAX(N37,IFERROR(AGGREGATE(14,6,'持仓跟踪'!$S$2:$S$501/(('持仓跟踪'!$A$2:$A$501="每日跟踪")*('持仓跟踪'!$B$2:$B$501=A37)),1),0)),0)*AL37)+IF(OR(AM37="",AN37=""),0,MAX(AM37-MAX(N37,IFERROR(AGGREGATE(14,6,'持仓跟踪'!$S$2:$S$501/(('持仓跟踪'!$A$2:$A$501="每日跟踪")*('持仓跟踪'!$B$2:$B$501=A37)),1),0)),0)*AN37)))) | AR37: =IF(A37="","",IF(OR(E37="",H37=""),"违规：第一批价格或股数缺失",IF(OR(AND(AK37="",AL37<>""),AND(AK37<>"",AL37="")),"违规：第二批价格与股数须成对填写",IF(OR(AND(AM37="",AN37<>""),AND(AM37<>"",AN37="")),"违规：第三批价格与股数须成对填写",IF(AND(OR(AM37<>"",AN37<>""),OR(AK37="",AL37="")),"违规：必须先完成第二批",IF(OR(H37<=0,H37<>INT(H37),MOD(H37,100)<>0,AND(AL37<>"",OR(AL37<=0,AL37<>INT(AL37),MOD(AL37,100)<>0)),AND(AN37<>"",OR(AN37<=0,AN37<>INT(AN37),MOD(AN37,100)<>0))),"违规：股数须为100股整数倍",IF(AND(OR(AL37<>"",AN37<>""),OR(_LockStatus="已锁仓",_LockStatus="解锁信息不完整")),"违规：锁仓期间禁止加仓",IF(AQ37>C37*D37,"违规：超过单笔风险上限",IF(SUM($AQ$2:$AQ$201)>账户数据!$B$7,"违规：超过账户风险上限","通过")))))))))
A38: 37 | B38: 沪电股份 | C38: 135433 | D38: 0.02 | E38: 12.17 | F38: =IF(OR(C38="",D38="",E38="",N38="",C38<=0,D38<=0,E38<=N38),"",ROUNDDOWN((C38*D38)/(E38-N38)/100,0)*100) | G38: =IF(A38="","",IF(H38<>"","已开仓",IF(账户数据!$B$23="已锁仓","禁止开仓：连续亏损达到上限",IF(账户数据!$B$23="解锁信息不完整","禁止开仓：请完整填写解锁信息",IF(OR(F38="",E38="",N38="",E38<=N38,账户数据!$B$7=""),"",IF(OR(AG38="",AH38="",AI38=""),"禁止开仓：交易预期未填写完整",IF(COUNTIFS(持仓跟踪!$A$2:$A$501,"止损计划",持仓跟踪!$B$2:$B$501,A38,持仓跟踪!$AC$2:$AC$501,"计划有效")=0,"禁止开仓：请先填写止损计划",IF(账户数据!$B$9+F38*(E38-N38)>=账户数据!$B$7,"禁止开仓：风险额度不足",IF(AJ38="周期与交易预期不匹配，请重新确认",IF(账户数据!$B$23="接近锁仓","允许开仓（接近锁仓；周期需复核）","允许开仓（周期需复核）"),IF(账户数据!$B$23="接近锁仓","允许开仓（接近锁仓）","允许开仓")))))))))) | H38: 2700 | I38: 44641 | J38: 14 | K38: 9.49 | L38: =IF(K38="","",H38) | M38: 44662 | N38: 11.2 | U38: =IF(OR(AO38="",J38="",AO38<=0),"",(J38-AO38)/AO38) | V38: =IF(OR(AO38="",N38="",AO38<=0),"",(AO38-N38)/AO38) | W38: =IF(OR(U38="",V38="",V38<=0),"",U38/V38) | X38: =IF(OR(K38="",L38="",AP38=""),"",K38*L38-(E38*H38+IF(AND(AK38<>"",AL38<>""),AK38*AL38,0)+IF(AND(AM38<>"",AN38<>""),AM38*AN38,0))-IF(O38="",0,O38)-IF(P38="",0,P38)) | Y38: =IF(OR(X38="",AP38=""),"",IF((E38*H38+IF(AND(AK38<>"",AL38<>""),AK38*AL38,0)+IF(AND(AM38<>"",AN38<>""),AM38*AN38,0))+IF(O38="",0,O38)<=0,"",X38/((E38*H38+IF(AND(AK38<>"",AL38<>""),AK38*AL38,0)+IF(AND(AM38<>"",AN38<>""),AM38*AN38,0))+IF(O38="",0,O38)))) | Z38: =IF(OR(AE38="",多次统计数据!$B$8=""),"",AE38-多次统计数据!$B$8) | AA38: =IF(OR(I38="",M38="",M38<I38),"",M38-I38) | AB38: =IF(OR(A38="",多次统计数据!$B$8="",多次统计数据!$B$6<=0,多次统计数据!$B$6>=1),"",1-POWER(1+多次统计数据!$B$8,-多次统计数据!$B$6/(1-多次统计数据!$B$6))) | AC38: =IF(OR(AB38="",多次统计数据!$B$9=""),"",IF(多次统计数据!$B$9<AB38,"低于上限","达到或超过上限")) | AE38: =IF(OR(X38="",C38="",C38<=0),"",X38/C38) | AF38: 不遵守纪律 | AJ38: =IF(OR(AG38="",AH38=""),"",IF(OR(AND(AG38="短期博反弹",OR(AH38="1～3个交易日",AH38="4～10个交易日")),AND(AG38="突破冲新高",OR(AH38="4～10个交易日",AH38="11～20个交易日")),AND(AG38="趋势波段",OR(AH38="11～20个交易日",AH38="21～60个交易日",AH38="60个交易日以上"))),"匹配","周期与交易预期不匹配，请重新确认")) | AO38: =IF(OR(A38="",H38="",H38<=0),"",(E38*H38+IF(AND(AK38<>"",AL38<>""),AK38*AL38,0)+IF(AND(AM38<>"",AN38<>""),AM38*AN38,0))/AP38) | AP38: =IF(OR(A38="",H38="",H38<=0),"",H38+IF(AL38="",0,AL38)+IF(AN38="",0,AN38)) | AQ38: =IF(A38="","",IF(M38<>"",0,IF(OR(H38="",N38=""),"",MAX(E38-MAX(N38,IFERROR(AGGREGATE(14,6,'持仓跟踪'!$S$2:$S$501/(('持仓跟踪'!$A$2:$A$501="每日跟踪")*('持仓跟踪'!$B$2:$B$501=A38)),1),0)),0)*H38+IF(OR(AK38="",AL38=""),0,MAX(AK38-MAX(N38,IFERROR(AGGREGATE(14,6,'持仓跟踪'!$S$2:$S$501/(('持仓跟踪'!$A$2:$A$501="每日跟踪")*('持仓跟踪'!$B$2:$B$501=A38)),1),0)),0)*AL38)+IF(OR(AM38="",AN38=""),0,MAX(AM38-MAX(N38,IFERROR(AGGREGATE(14,6,'持仓跟踪'!$S$2:$S$501/(('持仓跟踪'!$A$2:$A$501="每日跟踪")*('持仓跟踪'!$B$2:$B$501=A38)),1),0)),0)*AN38)))) | AR38: =IF(A38="","",IF(OR(E38="",H38=""),"违规：第一批价格或股数缺失",IF(OR(AND(AK38="",AL38<>""),AND(AK38<>"",AL38="")),"违规：第二批价格与股数须成对填写",IF(OR(AND(AM38="",AN38<>""),AND(AM38<>"",AN38="")),"违规：第三批价格与股数须成对填写",IF(AND(OR(AM38<>"",AN38<>""),OR(AK38="",AL38="")),"违规：必须先完成第二批",IF(OR(H38<=0,H38<>INT(H38),MOD(H38,100)<>0,AND(AL38<>"",OR(AL38<=0,AL38<>INT(AL38),MOD(AL38,100)<>0)),AND(AN38<>"",OR(AN38<=0,AN38<>INT(AN38),MOD(AN38,100)<>0))),"违规：股数须为100股整数倍",IF(AND(OR(AL38<>"",AN38<>""),OR(_LockStatus="已锁仓",_LockStatus="解锁信息不完整")),"违规：锁仓期间禁止加仓",IF(AQ38>C38*D38,"违规：超过单笔风险上限",IF(SUM($AQ$2:$AQ$201)>账户数据!$B$7,"违规：超过账户风险上限","通过")))))))))
A39: 38 | B39: 沪电股份 | C39: 128197 | D39: 0.02 | E39: 10.45 | F39: =IF(OR(C39="",D39="",E39="",N39="",C39<=0,D39<=0,E39<=N39),"",ROUNDDOWN((C39*D39)/(E39-N39)/100,0)*100) | G39: =IF(A39="","",IF(H39<>"","已开仓",IF(账户数据!$B$23="已锁仓","禁止开仓：连续亏损达到上限",IF(账户数据!$B$23="解锁信息不完整","禁止开仓：请完整填写解锁信息",IF(OR(F39="",E39="",N39="",E39<=N39,账户数据!$B$7=""),"",IF(OR(AG39="",AH39="",AI39=""),"禁止开仓：交易预期未填写完整",IF(COUNTIFS(持仓跟踪!$A$2:$A$501,"止损计划",持仓跟踪!$B$2:$B$501,A39,持仓跟踪!$AC$2:$AC$501,"计划有效")=0,"禁止开仓：请先填写止损计划",IF(账户数据!$B$9+F39*(E39-N39)>=账户数据!$B$7,"禁止开仓：风险额度不足",IF(AJ39="周期与交易预期不匹配，请重新确认",IF(账户数据!$B$23="接近锁仓","允许开仓（接近锁仓；周期需复核）","允许开仓（周期需复核）"),IF(账户数据!$B$23="接近锁仓","允许开仓（接近锁仓）","允许开仓")))))))))) | H39: 5600 | I39: 44670 | J39: 12 | K39: 9.28 | L39: =IF(K39="","",H39) | M39: 44676 | N39: 10 | U39: =IF(OR(AO39="",J39="",AO39<=0),"",(J39-AO39)/AO39) | V39: =IF(OR(AO39="",N39="",AO39<=0),"",(AO39-N39)/AO39) | W39: =IF(OR(U39="",V39="",V39<=0),"",U39/V39) | X39: =IF(OR(K39="",L39="",AP39=""),"",K39*L39-(E39*H39+IF(AND(AK39<>"",AL39<>""),AK39*AL39,0)+IF(AND(AM39<>"",AN39<>""),AM39*AN39,0))-IF(O39="",0,O39)-IF(P39="",0,P39)) | Y39: =IF(OR(X39="",AP39=""),"",IF((E39*H39+IF(AND(AK39<>"",AL39<>""),AK39*AL39,0)+IF(AND(AM39<>"",AN39<>""),AM39*AN39,0))+IF(O39="",0,O39)<=0,"",X39/((E39*H39+IF(AND(AK39<>"",AL39<>""),AK39*AL39,0)+IF(AND(AM39<>"",AN39<>""),AM39*AN39,0))+IF(O39="",0,O39)))) | Z39: =IF(OR(AE39="",多次统计数据!$B$8=""),"",AE39-多次统计数据!$B$8) | AA39: =IF(OR(I39="",M39="",M39<I39),"",M39-I39) | AB39: =IF(OR(A39="",多次统计数据!$B$8="",多次统计数据!$B$6<=0,多次统计数据!$B$6>=1),"",1-POWER(1+多次统计数据!$B$8,-多次统计数据!$B$6/(1-多次统计数据!$B$6))) | AC39: =IF(OR(AB39="",多次统计数据!$B$9=""),"",IF(多次统计数据!$B$9<AB39,"低于上限","达到或超过上限")) | AE39: =IF(OR(X39="",C39="",C39<=0),"",X39/C39) | AJ39: =IF(OR(AG39="",AH39=""),"",IF(OR(AND(AG39="短期博反弹",OR(AH39="1～3个交易日",AH39="4～10个交易日")),AND(AG39="突破冲新高",OR(AH39="4～10个交易日",AH39="11～20个交易日")),AND(AG39="趋势波段",OR(AH39="11～20个交易日",AH39="21～60个交易日",AH39="60个交易日以上"))),"匹配","周期与交易预期不匹配，请重新确认")) | AO39: =IF(OR(A39="",H39="",H39<=0),"",(E39*H39+IF(AND(AK39<>"",AL39<>""),AK39*AL39,0)+IF(AND(AM39<>"",AN39<>""),AM39*AN39,0))/AP39) | AP39: =IF(OR(A39="",H39="",H39<=0),"",H39+IF(AL39="",0,AL39)+IF(AN39="",0,AN39)) | AQ39: =IF(A39="","",IF(M39<>"",0,IF(OR(H39="",N39=""),"",MAX(E39-MAX(N39,IFERROR(AGGREGATE(14,6,'持仓跟踪'!$S$2:$S$501/(('持仓跟踪'!$A$2:$A$501="每日跟踪")*('持仓跟踪'!$B$2:$B$501=A39)),1),0)),0)*H39+IF(OR(AK39="",AL39=""),0,MAX(AK39-MAX(N39,IFERROR(AGGREGATE(14,6,'持仓跟踪'!$S$2:$S$501/(('持仓跟踪'!$A$2:$A$501="每日跟踪")*('持仓跟踪'!$B$2:$B$501=A39)),1),0)),0)*AL39)+IF(OR(AM39="",AN39=""),0,MAX(AM39-MAX(N39,IFERROR(AGGREGATE(14,6,'持仓跟踪'!$S$2:$S$501/(('持仓跟踪'!$A$2:$A$501="每日跟踪")*('持仓跟踪'!$B$2:$B$501=A39)),1),0)),0)*AN39)))) | AR39: =IF(A39="","",IF(OR(E39="",H39=""),"违规：第一批价格或股数缺失",IF(OR(AND(AK39="",AL39<>""),AND(AK39<>"",AL39="")),"违规：第二批价格与股数须成对填写",IF(OR(AND(AM39="",AN39<>""),AND(AM39<>"",AN39="")),"违规：第三批价格与股数须成对填写",IF(AND(OR(AM39<>"",AN39<>""),OR(AK39="",AL39="")),"违规：必须先完成第二批",IF(OR(H39<=0,H39<>INT(H39),MOD(H39,100)<>0,AND(AL39<>"",OR(AL39<=0,AL39<>INT(AL39),MOD(AL39,100)<>0)),AND(AN39<>"",OR(AN39<=0,AN39<>INT(AN39),MOD(AN39,100)<>0))),"违规：股数须为100股整数倍",IF(AND(OR(AL39<>"",AN39<>""),OR(_LockStatus="已锁仓",_LockStatus="解锁信息不完整")),"违规：锁仓期间禁止加仓",IF(AQ39>C39*D39,"违规：超过单笔风险上限",IF(SUM($AQ$2:$AQ$201)>账户数据!$B$7,"违规：超过账户风险上限","通过")))))))))
A40: 39 | B40: 沪电股份 | C40: 121645 | D40: 0.02 | E40: 13.54 | F40: =IF(OR(C40="",D40="",E40="",N40="",C40<=0,D40<=0,E40<=N40),"",ROUNDDOWN((C40*D40)/(E40-N40)/100,0)*100) | G40: =IF(A40="","",IF(H40<>"","已开仓",IF(账户数据!$B$23="已锁仓","禁止开仓：连续亏损达到上限",IF(账户数据!$B$23="解锁信息不完整","禁止开仓：请完整填写解锁信息",IF(OR(F40="",E40="",N40="",E40<=N40,账户数据!$B$7=""),"",IF(OR(AG40="",AH40="",AI40=""),"禁止开仓：交易预期未填写完整",IF(COUNTIFS(持仓跟踪!$A$2:$A$501,"止损计划",持仓跟踪!$B$2:$B$501,A40,持仓跟踪!$AC$2:$AC$501,"计划有效")=0,"禁止开仓：请先填写止损计划",IF(账户数据!$B$9+F40*(E40-N40)>=账户数据!$B$7,"禁止开仓：风险额度不足",IF(AJ40="周期与交易预期不匹配，请重新确认",IF(账户数据!$B$23="接近锁仓","允许开仓（接近锁仓；周期需复核）","允许开仓（周期需复核）"),IF(账户数据!$B$23="接近锁仓","允许开仓（接近锁仓）","允许开仓")))))))))) | H40: 4500 | I40: 44740 | J40: 15 | K40: 12.66 | L40: =IF(K40="","",H40) | M40: 44743 | N40: 13 | U40: =IF(OR(AO40="",J40="",AO40<=0),"",(J40-AO40)/AO40) | V40: =IF(OR(AO40="",N40="",AO40<=0),"",(AO40-N40)/AO40) | W40: =IF(OR(U40="",V40="",V40<=0),"",U40/V40) | X40: =IF(OR(K40="",L40="",AP40=""),"",K40*L40-(E40*H40+IF(AND(AK40<>"",AL40<>""),AK40*AL40,0)+IF(AND(AM40<>"",AN40<>""),AM40*AN40,0))-IF(O40="",0,O40)-IF(P40="",0,P40)) | Y40: =IF(OR(X40="",AP40=""),"",IF((E40*H40+IF(AND(AK40<>"",AL40<>""),AK40*AL40,0)+IF(AND(AM40<>"",AN40<>""),AM40*AN40,0))+IF(O40="",0,O40)<=0,"",X40/((E40*H40+IF(AND(AK40<>"",AL40<>""),AK40*AL40,0)+IF(AND(AM40<>"",AN40<>""),AM40*AN40,0))+IF(O40="",0,O40)))) | Z40: =IF(OR(AE40="",多次统计数据!$B$8=""),"",AE40-多次统计数据!$B$8) | AA40: =IF(OR(I40="",M40="",M40<I40),"",M40-I40) | AB40: =IF(OR(A40="",多次统计数据!$B$8="",多次统计数据!$B$6<=0,多次统计数据!$B$6>=1),"",1-POWER(1+多次统计数据!$B$8,-多次统计数据!$B$6/(1-多次统计数据!$B$6))) | AC40: =IF(OR(AB40="",多次统计数据!$B$9=""),"",IF(多次统计数据!$B$9<AB40,"低于上限","达到或超过上限")) | AE40: =IF(OR(X40="",C40="",C40<=0),"",X40/C40) | AJ40: =IF(OR(AG40="",AH40=""),"",IF(OR(AND(AG40="短期博反弹",OR(AH40="1～3个交易日",AH40="4～10个交易日")),AND(AG40="突破冲新高",OR(AH40="4～10个交易日",AH40="11～20个交易日")),AND(AG40="趋势波段",OR(AH40="11～20个交易日",AH40="21～60个交易日",AH40="60个交易日以上"))),"匹配","周期与交易预期不匹配，请重新确认")) | AO40: =IF(OR(A40="",H40="",H40<=0),"",(E40*H40+IF(AND(AK40<>"",AL40<>""),AK40*AL40,0)+IF(AND(AM40<>"",AN40<>""),AM40*AN40,0))/AP40) | AP40: =IF(OR(A40="",H40="",H40<=0),"",H40+IF(AL40="",0,AL40)+IF(AN40="",0,AN40)) | AQ40: =IF(A40="","",IF(M40<>"",0,IF(OR(H40="",N40=""),"",MAX(E40-MAX(N40,IFERROR(AGGREGATE(14,6,'持仓跟踪'!$S$2:$S$501/(('持仓跟踪'!$A$2:$A$501="每日跟踪")*('持仓跟踪'!$B$2:$B$501=A40)),1),0)),0)*H40+IF(OR(AK40="",AL40=""),0,MAX(AK40-MAX(N40,IFERROR(AGGREGATE(14,6,'持仓跟踪'!$S$2:$S$501/(('持仓跟踪'!$A$2:$A$501="每日跟踪")*('持仓跟踪'!$B$2:$B$501=A40)),1),0)),0)*AL40)+IF(OR(AM40="",AN40=""),0,MAX(AM40-MAX(N40,IFERROR(AGGREGATE(14,6,'持仓跟踪'!$S$2:$S$501/(('持仓跟踪'!$A$2:$A$501="每日跟踪")*('持仓跟踪'!$B$2:$B$501=A40)),1),0)),0)*AN40)))) | AR40: =IF(A40="","",IF(OR(E40="",H40=""),"违规：第一批价格或股数缺失",IF(OR(AND(AK40="",AL40<>""),AND(AK40<>"",AL40="")),"违规：第二批价格与股数须成对填写",IF(OR(AND(AM40="",AN40<>""),AND(AM40<>"",AN40="")),"违规：第三批价格与股数须成对填写",IF(AND(OR(AM40<>"",AN40<>""),OR(AK40="",AL40="")),"违规：必须先完成第二批",IF(OR(H40<=0,H40<>INT(H40),MOD(H40,100)<>0,AND(AL40<>"",OR(AL40<=0,AL40<>INT(AL40),MOD(AL40,100)<>0)),AND(AN40<>"",OR(AN40<=0,AN40<>INT(AN40),MOD(AN40,100)<>0))),"违规：股数须为100股整数倍",IF(AND(OR(AL40<>"",AN40<>""),OR(_LockStatus="已锁仓",_LockStatus="解锁信息不完整")),"违规：锁仓期间禁止加仓",IF(AQ40>C40*D40,"违规：超过单笔风险上限",IF(SUM($AQ$2:$AQ$201)>账户数据!$B$7,"违规：超过账户风险上限","通过")))))))))
A41: 40 | B41: 沪电股份 | C41: 117685 | D41: 0.02 | E41: 11.67 | F41: =IF(OR(C41="",D41="",E41="",N41="",C41<=0,D41<=0,E41<=N41),"",ROUNDDOWN((C41*D41)/(E41-N41)/100,0)*100) | G41: =IF(A41="","",IF(H41<>"","已开仓",IF(账户数据!$B$23="已锁仓","禁止开仓：连续亏损达到上限",IF(账户数据!$B$23="解锁信息不完整","禁止开仓：请完整填写解锁信息",IF(OR(F41="",E41="",N41="",E41<=N41,账户数据!$B$7=""),"",IF(OR(AG41="",AH41="",AI41=""),"禁止开仓：交易预期未填写完整",IF(COUNTIFS(持仓跟踪!$A$2:$A$501,"止损计划",持仓跟踪!$B$2:$B$501,A41,持仓跟踪!$AC$2:$AC$501,"计划有效")=0,"禁止开仓：请先填写止损计划",IF(账户数据!$B$9+F41*(E41-N41)>=账户数据!$B$7,"禁止开仓：风险额度不足",IF(AJ41="周期与交易预期不匹配，请重新确认",IF(账户数据!$B$23="接近锁仓","允许开仓（接近锁仓；周期需复核）","允许开仓（周期需复核）"),IF(账户数据!$B$23="接近锁仓","允许开仓（接近锁仓）","允许开仓")))))))))) | H41: 2000 | I41: 44883 | J41: 15 | K41: 10.23 | L41: =IF(K41="","",H41) | M41: 44914 | N41: 10.52 | U41: =IF(OR(AO41="",J41="",AO41<=0),"",(J41-AO41)/AO41) | V41: =IF(OR(AO41="",N41="",AO41<=0),"",(AO41-N41)/AO41) | W41: =IF(OR(U41="",V41="",V41<=0),"",U41/V41) | X41: =IF(OR(K41="",L41="",AP41=""),"",K41*L41-(E41*H41+IF(AND(AK41<>"",AL41<>""),AK41*AL41,0)+IF(AND(AM41<>"",AN41<>""),AM41*AN41,0))-IF(O41="",0,O41)-IF(P41="",0,P41)) | Y41: =IF(OR(X41="",AP41=""),"",IF((E41*H41+IF(AND(AK41<>"",AL41<>""),AK41*AL41,0)+IF(AND(AM41<>"",AN41<>""),AM41*AN41,0))+IF(O41="",0,O41)<=0,"",X41/((E41*H41+IF(AND(AK41<>"",AL41<>""),AK41*AL41,0)+IF(AND(AM41<>"",AN41<>""),AM41*AN41,0))+IF(O41="",0,O41)))) | Z41: =IF(OR(AE41="",多次统计数据!$B$8=""),"",AE41-多次统计数据!$B$8) | AA41: =IF(OR(I41="",M41="",M41<I41),"",M41-I41) | AB41: =IF(OR(A41="",多次统计数据!$B$8="",多次统计数据!$B$6<=0,多次统计数据!$B$6>=1),"",1-POWER(1+多次统计数据!$B$8,-多次统计数据!$B$6/(1-多次统计数据!$B$6))) | AC41: =IF(OR(AB41="",多次统计数据!$B$9=""),"",IF(多次统计数据!$B$9<AB41,"低于上限","达到或超过上限")) | AE41: =IF(OR(X41="",C41="",C41<=0),"",X41/C41) | AJ41: =IF(OR(AG41="",AH41=""),"",IF(OR(AND(AG41="短期博反弹",OR(AH41="1～3个交易日",AH41="4～10个交易日")),AND(AG41="突破冲新高",OR(AH41="4～10个交易日",AH41="11～20个交易日")),AND(AG41="趋势波段",OR(AH41="11～20个交易日",AH41="21～60个交易日",AH41="60个交易日以上"))),"匹配","周期与交易预期不匹配，请重新确认")) | AO41: =IF(OR(A41="",H41="",H41<=0),"",(E41*H41+IF(AND(AK41<>"",AL41<>""),AK41*AL41,0)+IF(AND(AM41<>"",AN41<>""),AM41*AN41,0))/AP41) | AP41: =IF(OR(A41="",H41="",H41<=0),"",H41+IF(AL41="",0,AL41)+IF(AN41="",0,AN41)) | AQ41: =IF(A41="","",IF(M41<>"",0,IF(OR(H41="",N41=""),"",MAX(E41-MAX(N41,IFERROR(AGGREGATE(14,6,'持仓跟踪'!$S$2:$S$501/(('持仓跟踪'!$A$2:$A$501="每日跟踪")*('持仓跟踪'!$B$2:$B$501=A41)),1),0)),0)*H41+IF(OR(AK41="",AL41=""),0,MAX(AK41-MAX(N41,IFERROR(AGGREGATE(14,6,'持仓跟踪'!$S$2:$S$501/(('持仓跟踪'!$A$2:$A$501="每日跟踪")*('持仓跟踪'!$B$2:$B$501=A41)),1),0)),0)*AL41)+IF(OR(AM41="",AN41=""),0,MAX(AM41-MAX(N41,IFERROR(AGGREGATE(14,6,'持仓跟踪'!$S$2:$S$501/(('持仓跟踪'!$A$2:$A$501="每日跟踪")*('持仓跟踪'!$B$2:$B$501=A41)),1),0)),0)*AN41)))) | AR41: =IF(A41="","",IF(OR(E41="",H41=""),"违规：第一批价格或股数缺失",IF(OR(AND(AK41="",AL41<>""),AND(AK41<>"",AL41="")),"违规：第二批价格与股数须成对填写",IF(OR(AND(AM41="",AN41<>""),AND(AM41<>"",AN41="")),"违规：第三批价格与股数须成对填写",IF(AND(OR(AM41<>"",AN41<>""),OR(AK41="",AL41="")),"违规：必须先完成第二批",IF(OR(H41<=0,H41<>INT(H41),MOD(H41,100)<>0,AND(AL41<>"",OR(AL41<=0,AL41<>INT(AL41),MOD(AL41,100)<>0)),AND(AN41<>"",OR(AN41<=0,AN41<>INT(AN41),MOD(AN41,100)<>0))),"违规：股数须为100股整数倍",IF(AND(OR(AL41<>"",AN41<>""),OR(_LockStatus="已锁仓",_LockStatus="解锁信息不完整")),"违规：锁仓期间禁止加仓",IF(AQ41>C41*D41,"违规：超过单笔风险上限",IF(SUM($AQ$2:$AQ$201)>账户数据!$B$7,"违规：超过账户风险上限","通过")))))))))
A42: 41 | B42: 沪电股份 | C42: 114805 | D42: 0.02 | E42: 18.24 | F42: =IF(OR(C42="",D42="",E42="",N42="",C42<=0,D42<=0,E42<=N42),"",ROUNDDOWN((C42*D42)/(E42-N42)/100,0)*100) | G42: =IF(A42="","",IF(H42<>"","已开仓",IF(账户数据!$B$23="已锁仓","禁止开仓：连续亏损达到上限",IF(账户数据!$B$23="解锁信息不完整","禁止开仓：请完整填写解锁信息",IF(OR(F42="",E42="",N42="",E42<=N42,账户数据!$B$7=""),"",IF(OR(AG42="",AH42="",AI42=""),"禁止开仓：交易预期未填写完整",IF(COUNTIFS(持仓跟踪!$A$2:$A$501,"止损计划",持仓跟踪!$B$2:$B$501,A42,持仓跟踪!$AC$2:$AC$501,"计划有效")=0,"禁止开仓：请先填写止损计划",IF(账户数据!$B$9+F42*(E42-N42)>=账户数据!$B$7,"禁止开仓：风险额度不足",IF(AJ42="周期与交易预期不匹配，请重新确认",IF(账户数据!$B$23="接近锁仓","允许开仓（接近锁仓；周期需复核）","允许开仓（周期需复核）"),IF(账户数据!$B$23="接近锁仓","允许开仓（接近锁仓）","允许开仓")))))))))) | H42: 1800 | I42: 45064 | J42: 20 | K42: 16.44 | L42: =IF(K42="","",H42) | M42: 45069 | N42: 17 | U42: =IF(OR(AO42="",J42="",AO42<=0),"",(J42-AO42)/AO42) | V42: =IF(OR(AO42="",N42="",AO42<=0),"",(AO42-N42)/AO42) | W42: =IF(OR(U42="",V42="",V42<=0),"",U42/V42) | X42: =IF(OR(K42="",L42="",AP42=""),"",K42*L42-(E42*H42+IF(AND(AK42<>"",AL42<>""),AK42*AL42,0)+IF(AND(AM42<>"",AN42<>""),AM42*AN42,0))-IF(O42="",0,O42)-IF(P42="",0,P42)) | Y42: =IF(OR(X42="",AP42=""),"",IF((E42*H42+IF(AND(AK42<>"",AL42<>""),AK42*AL42,0)+IF(AND(AM42<>"",AN42<>""),AM42*AN42,0))+IF(O42="",0,O42)<=0,"",X42/((E42*H42+IF(AND(AK42<>"",AL42<>""),AK42*AL42,0)+IF(AND(AM42<>"",AN42<>""),AM42*AN42,0))+IF(O42="",0,O42)))) | Z42: =IF(OR(AE42="",多次统计数据!$B$8=""),"",AE42-多次统计数据!$B$8) | AA42: =IF(OR(I42="",M42="",M42<I42),"",M42-I42) | AB42: =IF(OR(A42="",多次统计数据!$B$8="",多次统计数据!$B$6<=0,多次统计数据!$B$6>=1),"",1-POWER(1+多次统计数据!$B$8,-多次统计数据!$B$6/(1-多次统计数据!$B$6))) | AC42: =IF(OR(AB42="",多次统计数据!$B$9=""),"",IF(多次统计数据!$B$9<AB42,"低于上限","达到或超过上限")) | AE42: =IF(OR(X42="",C42="",C42<=0),"",X42/C42) | AJ42: =IF(OR(AG42="",AH42=""),"",IF(OR(AND(AG42="短期博反弹",OR(AH42="1～3个交易日",AH42="4～10个交易日")),AND(AG42="突破冲新高",OR(AH42="4～10个交易日",AH42="11～20个交易日")),AND(AG42="趋势波段",OR(AH42="11～20个交易日",AH42="21～60个交易日",AH42="60个交易日以上"))),"匹配","周期与交易预期不匹配，请重新确认")) | AO42: =IF(OR(A42="",H42="",H42<=0),"",(E42*H42+IF(AND(AK42<>"",AL42<>""),AK42*AL42,0)+IF(AND(AM42<>"",AN42<>""),AM42*AN42,0))/AP42) | AP42: =IF(OR(A42="",H42="",H42<=0),"",H42+IF(AL42="",0,AL42)+IF(AN42="",0,AN42)) | AQ42: =IF(A42="","",IF(M42<>"",0,IF(OR(H42="",N42=""),"",MAX(E42-MAX(N42,IFERROR(AGGREGATE(14,6,'持仓跟踪'!$S$2:$S$501/(('持仓跟踪'!$A$2:$A$501="每日跟踪")*('持仓跟踪'!$B$2:$B$501=A42)),1),0)),0)*H42+IF(OR(AK42="",AL42=""),0,MAX(AK42-MAX(N42,IFERROR(AGGREGATE(14,6,'持仓跟踪'!$S$2:$S$501/(('持仓跟踪'!$A$2:$A$501="每日跟踪")*('持仓跟踪'!$B$2:$B$501=A42)),1),0)),0)*AL42)+IF(OR(AM42="",AN42=""),0,MAX(AM42-MAX(N42,IFERROR(AGGREGATE(14,6,'持仓跟踪'!$S$2:$S$501/(('持仓跟踪'!$A$2:$A$501="每日跟踪")*('持仓跟踪'!$B$2:$B$501=A42)),1),0)),0)*AN42)))) | AR42: =IF(A42="","",IF(OR(E42="",H42=""),"违规：第一批价格或股数缺失",IF(OR(AND(AK42="",AL42<>""),AND(AK42<>"",AL42="")),"违规：第二批价格与股数须成对填写",IF(OR(AND(AM42="",AN42<>""),AND(AM42<>"",AN42="")),"违规：第三批价格与股数须成对填写",IF(AND(OR(AM42<>"",AN42<>""),OR(AK42="",AL42="")),"违规：必须先完成第二批",IF(OR(H42<=0,H42<>INT(H42),MOD(H42,100)<>0,AND(AL42<>"",OR(AL42<=0,AL42<>INT(AL42),MOD(AL42,100)<>0)),AND(AN42<>"",OR(AN42<=0,AN42<>INT(AN42),MOD(AN42,100)<>0))),"违规：股数须为100股整数倍",IF(AND(OR(AL42<>"",AN42<>""),OR(_LockStatus="已锁仓",_LockStatus="解锁信息不完整")),"违规：锁仓期间禁止加仓",IF(AQ42>C42*D42,"违规：超过单笔风险上限",IF(SUM($AQ$2:$AQ$201)>账户数据!$B$7,"违规：超过账户风险上限","通过")))))))))
A43: 42 | B43: 沪电股份 | C43: 111565 | D43: 0.02 | E43: 20.31 | F43: =IF(OR(C43="",D43="",E43="",N43="",C43<=0,D43<=0,E43<=N43),"",ROUNDDOWN((C43*D43)/(E43-N43)/100,0)*100) | G43: =IF(A43="","",IF(H43<>"","已开仓",IF(账户数据!$B$23="已锁仓","禁止开仓：连续亏损达到上限",IF(账户数据!$B$23="解锁信息不完整","禁止开仓：请完整填写解锁信息",IF(OR(F43="",E43="",N43="",E43<=N43,账户数据!$B$7=""),"",IF(OR(AG43="",AH43="",AI43=""),"禁止开仓：交易预期未填写完整",IF(COUNTIFS(持仓跟踪!$A$2:$A$501,"止损计划",持仓跟踪!$B$2:$B$501,A43,持仓跟踪!$AC$2:$AC$501,"计划有效")=0,"禁止开仓：请先填写止损计划",IF(账户数据!$B$9+F43*(E43-N43)>=账户数据!$B$7,"禁止开仓：风险额度不足",IF(AJ43="周期与交易预期不匹配，请重新确认",IF(账户数据!$B$23="接近锁仓","允许开仓（接近锁仓；周期需复核）","允许开仓（周期需复核）"),IF(账户数据!$B$23="接近锁仓","允许开仓（接近锁仓）","允许开仓")))))))))) | H43: 1700 | I43: 45086 | J43: 24 | K43: 18 | L43: =IF(K43="","",H43) | M43: 45103 | N43: 19 | U43: =IF(OR(AO43="",J43="",AO43<=0),"",(J43-AO43)/AO43) | V43: =IF(OR(AO43="",N43="",AO43<=0),"",(AO43-N43)/AO43) | W43: =IF(OR(U43="",V43="",V43<=0),"",U43/V43) | X43: =IF(OR(K43="",L43="",AP43=""),"",K43*L43-(E43*H43+IF(AND(AK43<>"",AL43<>""),AK43*AL43,0)+IF(AND(AM43<>"",AN43<>""),AM43*AN43,0))-IF(O43="",0,O43)-IF(P43="",0,P43)) | Y43: =IF(OR(X43="",AP43=""),"",IF((E43*H43+IF(AND(AK43<>"",AL43<>""),AK43*AL43,0)+IF(AND(AM43<>"",AN43<>""),AM43*AN43,0))+IF(O43="",0,O43)<=0,"",X43/((E43*H43+IF(AND(AK43<>"",AL43<>""),AK43*AL43,0)+IF(AND(AM43<>"",AN43<>""),AM43*AN43,0))+IF(O43="",0,O43)))) | Z43: =IF(OR(AE43="",多次统计数据!$B$8=""),"",AE43-多次统计数据!$B$8) | AA43: =IF(OR(I43="",M43="",M43<I43),"",M43-I43) | AB43: =IF(OR(A43="",多次统计数据!$B$8="",多次统计数据!$B$6<=0,多次统计数据!$B$6>=1),"",1-POWER(1+多次统计数据!$B$8,-多次统计数据!$B$6/(1-多次统计数据!$B$6))) | AC43: =IF(OR(AB43="",多次统计数据!$B$9=""),"",IF(多次统计数据!$B$9<AB43,"低于上限","达到或超过上限")) | AE43: =IF(OR(X43="",C43="",C43<=0),"",X43/C43) | AJ43: =IF(OR(AG43="",AH43=""),"",IF(OR(AND(AG43="短期博反弹",OR(AH43="1～3个交易日",AH43="4～10个交易日")),AND(AG43="突破冲新高",OR(AH43="4～10个交易日",AH43="11～20个交易日")),AND(AG43="趋势波段",OR(AH43="11～20个交易日",AH43="21～60个交易日",AH43="60个交易日以上"))),"匹配","周期与交易预期不匹配，请重新确认")) | AO43: =IF(OR(A43="",H43="",H43<=0),"",(E43*H43+IF(AND(AK43<>"",AL43<>""),AK43*AL43,0)+IF(AND(AM43<>"",AN43<>""),AM43*AN43,0))/AP43) | AP43: =IF(OR(A43="",H43="",H43<=0),"",H43+IF(AL43="",0,AL43)+IF(AN43="",0,AN43)) | AQ43: =IF(A43="","",IF(M43<>"",0,IF(OR(H43="",N43=""),"",MAX(E43-MAX(N43,IFERROR(AGGREGATE(14,6,'持仓跟踪'!$S$2:$S$501/(('持仓跟踪'!$A$2:$A$501="每日跟踪")*('持仓跟踪'!$B$2:$B$501=A43)),1),0)),0)*H43+IF(OR(AK43="",AL43=""),0,MAX(AK43-MAX(N43,IFERROR(AGGREGATE(14,6,'持仓跟踪'!$S$2:$S$501/(('持仓跟踪'!$A$2:$A$501="每日跟踪")*('持仓跟踪'!$B$2:$B$501=A43)),1),0)),0)*AL43)+IF(OR(AM43="",AN43=""),0,MAX(AM43-MAX(N43,IFERROR(AGGREGATE(14,6,'持仓跟踪'!$S$2:$S$501/(('持仓跟踪'!$A$2:$A$501="每日跟踪")*('持仓跟踪'!$B$2:$B$501=A43)),1),0)),0)*AN43)))) | AR43: =IF(A43="","",IF(OR(E43="",H43=""),"违规：第一批价格或股数缺失",IF(OR(AND(AK43="",AL43<>""),AND(AK43<>"",AL43="")),"违规：第二批价格与股数须成对填写",IF(OR(AND(AM43="",AN43<>""),AND(AM43<>"",AN43="")),"违规：第三批价格与股数须成对填写",IF(AND(OR(AM43<>"",AN43<>""),OR(AK43="",AL43="")),"违规：必须先完成第二批",IF(OR(H43<=0,H43<>INT(H43),MOD(H43,100)<>0,AND(AL43<>"",OR(AL43<=0,AL43<>INT(AL43),MOD(AL43,100)<>0)),AND(AN43<>"",OR(AN43<=0,AN43<>INT(AN43),MOD(AN43,100)<>0))),"违规：股数须为100股整数倍",IF(AND(OR(AL43<>"",AN43<>""),OR(_LockStatus="已锁仓",_LockStatus="解锁信息不完整")),"违规：锁仓期间禁止加仓",IF(AQ43>C43*D43,"违规：超过单笔风险上限",IF(SUM($AQ$2:$AQ$201)>账户数据!$B$7,"违规：超过账户风险上限","通过")))))))))
A44: 43 | B44: 沪电股份 | C44: 107638 | D44: 0.02 | E44: 20.43 | F44: =IF(OR(C44="",D44="",E44="",N44="",C44<=0,D44<=0,E44<=N44),"",ROUNDDOWN((C44*D44)/(E44-N44)/100,0)*100) | G44: =IF(A44="","",IF(H44<>"","已开仓",IF(账户数据!$B$23="已锁仓","禁止开仓：连续亏损达到上限",IF(账户数据!$B$23="解锁信息不完整","禁止开仓：请完整填写解锁信息",IF(OR(F44="",E44="",N44="",E44<=N44,账户数据!$B$7=""),"",IF(OR(AG44="",AH44="",AI44=""),"禁止开仓：交易预期未填写完整",IF(COUNTIFS(持仓跟踪!$A$2:$A$501,"止损计划",持仓跟踪!$B$2:$B$501,A44,持仓跟踪!$AC$2:$AC$501,"计划有效")=0,"禁止开仓：请先填写止损计划",IF(账户数据!$B$9+F44*(E44-N44)>=账户数据!$B$7,"禁止开仓：风险额度不足",IF(AJ44="周期与交易预期不匹配，请重新确认",IF(账户数据!$B$23="接近锁仓","允许开仓（接近锁仓；周期需复核）","允许开仓（周期需复核）"),IF(账户数据!$B$23="接近锁仓","允许开仓（接近锁仓）","允许开仓")))))))))) | H44: 600 | I44: 45138 | J44: 24 | K44: 30.34 | L44: =IF(K44="","",H44) | M44: 45366 | N44: 17 | U44: =IF(OR(AO44="",J44="",AO44<=0),"",(J44-AO44)/AO44) | V44: =IF(OR(AO44="",N44="",AO44<=0),"",(AO44-N44)/AO44) | W44: =IF(OR(U44="",V44="",V44<=0),"",U44/V44) | X44: =IF(OR(K44="",L44="",AP44=""),"",K44*L44-(E44*H44+IF(AND(AK44<>"",AL44<>""),AK44*AL44,0)+IF(AND(AM44<>"",AN44<>""),AM44*AN44,0))-IF(O44="",0,O44)-IF(P44="",0,P44)) | Y44: =IF(OR(X44="",AP44=""),"",IF((E44*H44+IF(AND(AK44<>"",AL44<>""),AK44*AL44,0)+IF(AND(AM44<>"",AN44<>""),AM44*AN44,0))+IF(O44="",0,O44)<=0,"",X44/((E44*H44+IF(AND(AK44<>"",AL44<>""),AK44*AL44,0)+IF(AND(AM44<>"",AN44<>""),AM44*AN44,0))+IF(O44="",0,O44)))) | Z44: =IF(OR(AE44="",多次统计数据!$B$8=""),"",AE44-多次统计数据!$B$8) | AA44: =IF(OR(I44="",M44="",M44<I44),"",M44-I44) | AB44: =IF(OR(A44="",多次统计数据!$B$8="",多次统计数据!$B$6<=0,多次统计数据!$B$6>=1),"",1-POWER(1+多次统计数据!$B$8,-多次统计数据!$B$6/(1-多次统计数据!$B$6))) | AC44: =IF(OR(AB44="",多次统计数据!$B$9=""),"",IF(多次统计数据!$B$9<AB44,"低于上限","达到或超过上限")) | AE44: =IF(OR(X44="",C44="",C44<=0),"",X44/C44) | AJ44: =IF(OR(AG44="",AH44=""),"",IF(OR(AND(AG44="短期博反弹",OR(AH44="1～3个交易日",AH44="4～10个交易日")),AND(AG44="突破冲新高",OR(AH44="4～10个交易日",AH44="11～20个交易日")),AND(AG44="趋势波段",OR(AH44="11～20个交易日",AH44="21～60个交易日",AH44="60个交易日以上"))),"匹配","周期与交易预期不匹配，请重新确认")) | AO44: =IF(OR(A44="",H44="",H44<=0),"",(E44*H44+IF(AND(AK44<>"",AL44<>""),AK44*AL44,0)+IF(AND(AM44<>"",AN44<>""),AM44*AN44,0))/AP44) | AP44: =IF(OR(A44="",H44="",H44<=0),"",H44+IF(AL44="",0,AL44)+IF(AN44="",0,AN44)) | AQ44: =IF(A44="","",IF(M44<>"",0,IF(OR(H44="",N44=""),"",MAX(E44-MAX(N44,IFERROR(AGGREGATE(14,6,'持仓跟踪'!$S$2:$S$501/(('持仓跟踪'!$A$2:$A$501="每日跟踪")*('持仓跟踪'!$B$2:$B$501=A44)),1),0)),0)*H44+IF(OR(AK44="",AL44=""),0,MAX(AK44-MAX(N44,IFERROR(AGGREGATE(14,6,'持仓跟踪'!$S$2:$S$501/(('持仓跟踪'!$A$2:$A$501="每日跟踪")*('持仓跟踪'!$B$2:$B$501=A44)),1),0)),0)*AL44)+IF(OR(AM44="",AN44=""),0,MAX(AM44-MAX(N44,IFERROR(AGGREGATE(14,6,'持仓跟踪'!$S$2:$S$501/(('持仓跟踪'!$A$2:$A$501="每日跟踪")*('持仓跟踪'!$B$2:$B$501=A44)),1),0)),0)*AN44)))) | AR44: =IF(A44="","",IF(OR(E44="",H44=""),"违规：第一批价格或股数缺失",IF(OR(AND(AK44="",AL44<>""),AND(AK44<>"",AL44="")),"违规：第二批价格与股数须成对填写",IF(OR(AND(AM44="",AN44<>""),AND(AM44<>"",AN44="")),"违规：第三批价格与股数须成对填写",IF(AND(OR(AM44<>"",AN44<>""),OR(AK44="",AL44="")),"违规：必须先完成第二批",IF(OR(H44<=0,H44<>INT(H44),MOD(H44,100)<>0,AND(AL44<>"",OR(AL44<=0,AL44<>INT(AL44),MOD(AL44,100)<>0)),AND(AN44<>"",OR(AN44<=0,AN44<>INT(AN44),MOD(AN44,100)<>0))),"违规：股数须为100股整数倍",IF(AND(OR(AL44<>"",AN44<>""),OR(_LockStatus="已锁仓",_LockStatus="解锁信息不完整")),"违规：锁仓期间禁止加仓",IF(AQ44>C44*D44,"违规：超过单笔风险上限",IF(SUM($AQ$2:$AQ$201)>账户数据!$B$7,"违规：超过账户风险上限","通过")))))))))
A45: 44 | B45: 深南电路 | C45: 113584 | D45: 0.02 | E45: 64.98 | F45: =IF(OR(C45="",D45="",E45="",N45="",C45<=0,D45<=0,E45<=N45),"",ROUNDDOWN((C45*D45)/(E45-N45)/100,0)*100) | G45: =IF(A45="","",IF(H45<>"","已开仓",IF(账户数据!$B$23="已锁仓","禁止开仓：连续亏损达到上限",IF(账户数据!$B$23="解锁信息不完整","禁止开仓：请完整填写解锁信息",IF(OR(F45="",E45="",N45="",E45<=N45,账户数据!$B$7=""),"",IF(OR(AG45="",AH45="",AI45=""),"禁止开仓：交易预期未填写完整",IF(COUNTIFS(持仓跟踪!$A$2:$A$501,"止损计划",持仓跟踪!$B$2:$B$501,A45,持仓跟踪!$AC$2:$AC$501,"计划有效")=0,"禁止开仓：请先填写止损计划",IF(账户数据!$B$9+F45*(E45-N45)>=账户数据!$B$7,"禁止开仓：风险额度不足",IF(AJ45="周期与交易预期不匹配，请重新确认",IF(账户数据!$B$23="接近锁仓","允许开仓（接近锁仓；周期需复核）","允许开仓（周期需复核）"),IF(账户数据!$B$23="接近锁仓","允许开仓（接近锁仓）","允许开仓")))))))))) | H45: 1100 | I45: 44613 | J45: 69 | K45: 69.19 | L45: =IF(K45="","",H45) | M45: 44719 | N45: 63 | U45: =IF(OR(AO45="",J45="",AO45<=0),"",(J45-AO45)/AO45) | V45: =IF(OR(AO45="",N45="",AO45<=0),"",(AO45-N45)/AO45) | W45: =IF(OR(U45="",V45="",V45<=0),"",U45/V45) | X45: =IF(OR(K45="",L45="",AP45=""),"",K45*L45-(E45*H45+IF(AND(AK45<>"",AL45<>""),AK45*AL45,0)+IF(AND(AM45<>"",AN45<>""),AM45*AN45,0))-IF(O45="",0,O45)-IF(P45="",0,P45)) | Y45: =IF(OR(X45="",AP45=""),"",IF((E45*H45+IF(AND(AK45<>"",AL45<>""),AK45*AL45,0)+IF(AND(AM45<>"",AN45<>""),AM45*AN45,0))+IF(O45="",0,O45)<=0,"",X45/((E45*H45+IF(AND(AK45<>"",AL45<>""),AK45*AL45,0)+IF(AND(AM45<>"",AN45<>""),AM45*AN45,0))+IF(O45="",0,O45)))) | Z45: =IF(OR(AE45="",多次统计数据!$B$8=""),"",AE45-多次统计数据!$B$8) | AA45: =IF(OR(I45="",M45="",M45<I45),"",M45-I45) | AB45: =IF(OR(A45="",多次统计数据!$B$8="",多次统计数据!$B$6<=0,多次统计数据!$B$6>=1),"",1-POWER(1+多次统计数据!$B$8,-多次统计数据!$B$6/(1-多次统计数据!$B$6))) | AC45: =IF(OR(AB45="",多次统计数据!$B$9=""),"",IF(多次统计数据!$B$9<AB45,"低于上限","达到或超过上限")) | AE45: =IF(OR(X45="",C45="",C45<=0),"",X45/C45) | AJ45: =IF(OR(AG45="",AH45=""),"",IF(OR(AND(AG45="短期博反弹",OR(AH45="1～3个交易日",AH45="4～10个交易日")),AND(AG45="突破冲新高",OR(AH45="4～10个交易日",AH45="11～20个交易日")),AND(AG45="趋势波段",OR(AH45="11～20个交易日",AH45="21～60个交易日",AH45="60个交易日以上"))),"匹配","周期与交易预期不匹配，请重新确认")) | AO45: =IF(OR(A45="",H45="",H45<=0),"",(E45*H45+IF(AND(AK45<>"",AL45<>""),AK45*AL45,0)+IF(AND(AM45<>"",AN45<>""),AM45*AN45,0))/AP45) | AP45: =IF(OR(A45="",H45="",H45<=0),"",H45+IF(AL45="",0,AL45)+IF(AN45="",0,AN45)) | AQ45: =IF(A45="","",IF(M45<>"",0,IF(OR(H45="",N45=""),"",MAX(E45-MAX(N45,IFERROR(AGGREGATE(14,6,'持仓跟踪'!$S$2:$S$501/(('持仓跟踪'!$A$2:$A$501="每日跟踪")*('持仓跟踪'!$B$2:$B$501=A45)),1),0)),0)*H45+IF(OR(AK45="",AL45=""),0,MAX(AK45-MAX(N45,IFERROR(AGGREGATE(14,6,'持仓跟踪'!$S$2:$S$501/(('持仓跟踪'!$A$2:$A$501="每日跟踪")*('持仓跟踪'!$B$2:$B$501=A45)),1),0)),0)*AL45)+IF(OR(AM45="",AN45=""),0,MAX(AM45-MAX(N45,IFERROR(AGGREGATE(14,6,'持仓跟踪'!$S$2:$S$501/(('持仓跟踪'!$A$2:$A$501="每日跟踪")*('持仓跟踪'!$B$2:$B$501=A45)),1),0)),0)*AN45)))) | AR45: =IF(A45="","",IF(OR(E45="",H45=""),"违规：第一批价格或股数缺失",IF(OR(AND(AK45="",AL45<>""),AND(AK45<>"",AL45="")),"违规：第二批价格与股数须成对填写",IF(OR(AND(AM45="",AN45<>""),AND(AM45<>"",AN45="")),"违规：第三批价格与股数须成对填写",IF(AND(OR(AM45<>"",AN45<>""),OR(AK45="",AL45="")),"违规：必须先完成第二批",IF(OR(H45<=0,H45<>INT(H45),MOD(H45,100)<>0,AND(AL45<>"",OR(AL45<=0,AL45<>INT(AL45),MOD(AL45,100)<>0)),AND(AN45<>"",OR(AN45<=0,AN45<>INT(AN45),MOD(AN45,100)<>0))),"违规：股数须为100股整数倍",IF(AND(OR(AL45<>"",AN45<>""),OR(_LockStatus="已锁仓",_LockStatus="解锁信息不完整")),"违规：锁仓期间禁止加仓",IF(AQ45>C45*D45,"违规：超过单笔风险上限",IF(SUM($AQ$2:$AQ$201)>账户数据!$B$7,"违规：超过账户风险上限","通过")))))))))
A46: 45 | B46: 深南电路 | C46: 118215 | D46: 0.02 | E46: 66.85 | F46: =IF(OR(C46="",D46="",E46="",N46="",C46<=0,D46<=0,E46<=N46),"",ROUNDDOWN((C46*D46)/(E46-N46)/100,0)*100) | G46: =IF(A46="","",IF(H46<>"","已开仓",IF(账户数据!$B$23="已锁仓","禁止开仓：连续亏损达到上限",IF(账户数据!$B$23="解锁信息不完整","禁止开仓：请完整填写解锁信息",IF(OR(F46="",E46="",N46="",E46<=N46,账户数据!$B$7=""),"",IF(OR(AG46="",AH46="",AI46=""),"禁止开仓：交易预期未填写完整",IF(COUNTIFS(持仓跟踪!$A$2:$A$501,"止损计划",持仓跟踪!$B$2:$B$501,A46,持仓跟踪!$AC$2:$AC$501,"计划有效")=0,"禁止开仓：请先填写止损计划",IF(账户数据!$B$9+F46*(E46-N46)>=账户数据!$B$7,"禁止开仓：风险额度不足",IF(AJ46="周期与交易预期不匹配，请重新确认",IF(账户数据!$B$23="接近锁仓","允许开仓（接近锁仓；周期需复核）","允许开仓（周期需复核）"),IF(账户数据!$B$23="接近锁仓","允许开仓（接近锁仓）","允许开仓")))))))))) | H46: 6700 | I46: 44722 | J46: 69 | K46: 66.07 | L46: =IF(K46="","",H46) | M46: 44725 | N46: 66.5 | U46: =IF(OR(AO46="",J46="",AO46<=0),"",(J46-AO46)/AO46) | V46: =IF(OR(AO46="",N46="",AO46<=0),"",(AO46-N46)/AO46) | W46: =IF(OR(U46="",V46="",V46<=0),"",U46/V46) | X46: =IF(OR(K46="",L46="",AP46=""),"",K46*L46-(E46*H46+IF(AND(AK46<>"",AL46<>""),AK46*AL46,0)+IF(AND(AM46<>"",AN46<>""),AM46*AN46,0))-IF(O46="",0,O46)-IF(P46="",0,P46)) | Y46: =IF(OR(X46="",AP46=""),"",IF((E46*H46+IF(AND(AK46<>"",AL46<>""),AK46*AL46,0)+IF(AND(AM46<>"",AN46<>""),AM46*AN46,0))+IF(O46="",0,O46)<=0,"",X46/((E46*H46+IF(AND(AK46<>"",AL46<>""),AK46*AL46,0)+IF(AND(AM46<>"",AN46<>""),AM46*AN46,0))+IF(O46="",0,O46)))) | Z46: =IF(OR(AE46="",多次统计数据!$B$8=""),"",AE46-多次统计数据!$B$8) | AA46: =IF(OR(I46="",M46="",M46<I46),"",M46-I46) | AB46: =IF(OR(A46="",多次统计数据!$B$8="",多次统计数据!$B$6<=0,多次统计数据!$B$6>=1),"",1-POWER(1+多次统计数据!$B$8,-多次统计数据!$B$6/(1-多次统计数据!$B$6))) | AC46: =IF(OR(AB46="",多次统计数据!$B$9=""),"",IF(多次统计数据!$B$9<AB46,"低于上限","达到或超过上限")) | AE46: =IF(OR(X46="",C46="",C46<=0),"",X46/C46) | AJ46: =IF(OR(AG46="",AH46=""),"",IF(OR(AND(AG46="短期博反弹",OR(AH46="1～3个交易日",AH46="4～10个交易日")),AND(AG46="突破冲新高",OR(AH46="4～10个交易日",AH46="11～20个交易日")),AND(AG46="趋势波段",OR(AH46="11～20个交易日",AH46="21～60个交易日",AH46="60个交易日以上"))),"匹配","周期与交易预期不匹配，请重新确认")) | AO46: =IF(OR(A46="",H46="",H46<=0),"",(E46*H46+IF(AND(AK46<>"",AL46<>""),AK46*AL46,0)+IF(AND(AM46<>"",AN46<>""),AM46*AN46,0))/AP46) | AP46: =IF(OR(A46="",H46="",H46<=0),"",H46+IF(AL46="",0,AL46)+IF(AN46="",0,AN46)) | AQ46: =IF(A46="","",IF(M46<>"",0,IF(OR(H46="",N46=""),"",MAX(E46-MAX(N46,IFERROR(AGGREGATE(14,6,'持仓跟踪'!$S$2:$S$501/(('持仓跟踪'!$A$2:$A$501="每日跟踪")*('持仓跟踪'!$B$2:$B$501=A46)),1),0)),0)*H46+IF(OR(AK46="",AL46=""),0,MAX(AK46-MAX(N46,IFERROR(AGGREGATE(14,6,'持仓跟踪'!$S$2:$S$501/(('持仓跟踪'!$A$2:$A$501="每日跟踪")*('持仓跟踪'!$B$2:$B$501=A46)),1),0)),0)*AL46)+IF(OR(AM46="",AN46=""),0,MAX(AM46-MAX(N46,IFERROR(AGGREGATE(14,6,'持仓跟踪'!$S$2:$S$501/(('持仓跟踪'!$A$2:$A$501="每日跟踪")*('持仓跟踪'!$B$2:$B$501=A46)),1),0)),0)*AN46)))) | AR46: =IF(A46="","",IF(OR(E46="",H46=""),"违规：第一批价格或股数缺失",IF(OR(AND(AK46="",AL46<>""),AND(AK46<>"",AL46="")),"违规：第二批价格与股数须成对填写",IF(OR(AND(AM46="",AN46<>""),AND(AM46<>"",AN46="")),"违规：第三批价格与股数须成对填写",IF(AND(OR(AM46<>"",AN46<>""),OR(AK46="",AL46="")),"违规：必须先完成第二批",IF(OR(H46<=0,H46<>INT(H46),MOD(H46,100)<>0,AND(AL46<>"",OR(AL46<=0,AL46<>INT(AL46),MOD(AL46,100)<>0)),AND(AN46<>"",OR(AN46<=0,AN46<>INT(AN46),MOD(AN46,100)<>0))),"违规：股数须为100股整数倍",IF(AND(OR(AL46<>"",AN46<>""),OR(_LockStatus="已锁仓",_LockStatus="解锁信息不完整")),"违规：锁仓期间禁止加仓",IF(AQ46>C46*D46,"违规：超过单笔风险上限",IF(SUM($AQ$2:$AQ$201)>账户数据!$B$7,"违规：超过账户风险上限","通过")))))))))
A47: 46 | B47: 深南电路 | C47: 112989 | D47: 0.02 | E47: 66.45 | F47: =IF(OR(C47="",D47="",E47="",N47="",C47<=0,D47<=0,E47<=N47),"",ROUNDDOWN((C47*D47)/(E47-N47)/100,0)*100) | G47: =IF(A47="","",IF(H47<>"","已开仓",IF(账户数据!$B$23="已锁仓","禁止开仓：连续亏损达到上限",IF(账户数据!$B$23="解锁信息不完整","禁止开仓：请完整填写解锁信息",IF(OR(F47="",E47="",N47="",E47<=N47,账户数据!$B$7=""),"",IF(OR(AG47="",AH47="",AI47=""),"禁止开仓：交易预期未填写完整",IF(COUNTIFS(持仓跟踪!$A$2:$A$501,"止损计划",持仓跟踪!$B$2:$B$501,A47,持仓跟踪!$AC$2:$AC$501,"计划有效")=0,"禁止开仓：请先填写止损计划",IF(账户数据!$B$9+F47*(E47-N47)>=账户数据!$B$7,"禁止开仓：风险额度不足",IF(AJ47="周期与交易预期不匹配，请重新确认",IF(账户数据!$B$23="接近锁仓","允许开仓（接近锁仓；周期需复核）","允许开仓（周期需复核）"),IF(账户数据!$B$23="接近锁仓","允许开仓（接近锁仓）","允许开仓")))))))))) | H47: 1500 | I47: 44732 | J47: 69 | K47: 63.21 | L47: =IF(K47="","",H47) | M47: 44764 | N47: 65 | U47: =IF(OR(AO47="",J47="",AO47<=0),"",(J47-AO47)/AO47) | V47: =IF(OR(AO47="",N47="",AO47<=0),"",(AO47-N47)/AO47) | W47: =IF(OR(U47="",V47="",V47<=0),"",U47/V47) | X47: =IF(OR(K47="",L47="",AP47=""),"",K47*L47-(E47*H47+IF(AND(AK47<>"",AL47<>""),AK47*AL47,0)+IF(AND(AM47<>"",AN47<>""),AM47*AN47,0))-IF(O47="",0,O47)-IF(P47="",0,P47)) | Y47: =IF(OR(X47="",AP47=""),"",IF((E47*H47+IF(AND(AK47<>"",AL47<>""),AK47*AL47,0)+IF(AND(AM47<>"",AN47<>""),AM47*AN47,0))+IF(O47="",0,O47)<=0,"",X47/((E47*H47+IF(AND(AK47<>"",AL47<>""),AK47*AL47,0)+IF(AND(AM47<>"",AN47<>""),AM47*AN47,0))+IF(O47="",0,O47)))) | Z47: =IF(OR(AE47="",多次统计数据!$B$8=""),"",AE47-多次统计数据!$B$8) | AA47: =IF(OR(I47="",M47="",M47<I47),"",M47-I47) | AB47: =IF(OR(A47="",多次统计数据!$B$8="",多次统计数据!$B$6<=0,多次统计数据!$B$6>=1),"",1-POWER(1+多次统计数据!$B$8,-多次统计数据!$B$6/(1-多次统计数据!$B$6))) | AC47: =IF(OR(AB47="",多次统计数据!$B$9=""),"",IF(多次统计数据!$B$9<AB47,"低于上限","达到或超过上限")) | AE47: =IF(OR(X47="",C47="",C47<=0),"",X47/C47) | AF47: 不准守纪律，想上涨 | AJ47: =IF(OR(AG47="",AH47=""),"",IF(OR(AND(AG47="短期博反弹",OR(AH47="1～3个交易日",AH47="4～10个交易日")),AND(AG47="突破冲新高",OR(AH47="4～10个交易日",AH47="11～20个交易日")),AND(AG47="趋势波段",OR(AH47="11～20个交易日",AH47="21～60个交易日",AH47="60个交易日以上"))),"匹配","周期与交易预期不匹配，请重新确认")) | AO47: =IF(OR(A47="",H47="",H47<=0),"",(E47*H47+IF(AND(AK47<>"",AL47<>""),AK47*AL47,0)+IF(AND(AM47<>"",AN47<>""),AM47*AN47,0))/AP47) | AP47: =IF(OR(A47="",H47="",H47<=0),"",H47+IF(AL47="",0,AL47)+IF(AN47="",0,AN47)) | AQ47: =IF(A47="","",IF(M47<>"",0,IF(OR(H47="",N47=""),"",MAX(E47-MAX(N47,IFERROR(AGGREGATE(14,6,'持仓跟踪'!$S$2:$S$501/(('持仓跟踪'!$A$2:$A$501="每日跟踪")*('持仓跟踪'!$B$2:$B$501=A47)),1),0)),0)*H47+IF(OR(AK47="",AL47=""),0,MAX(AK47-MAX(N47,IFERROR(AGGREGATE(14,6,'持仓跟踪'!$S$2:$S$501/(('持仓跟踪'!$A$2:$A$501="每日跟踪")*('持仓跟踪'!$B$2:$B$501=A47)),1),0)),0)*AL47)+IF(OR(AM47="",AN47=""),0,MAX(AM47-MAX(N47,IFERROR(AGGREGATE(14,6,'持仓跟踪'!$S$2:$S$501/(('持仓跟踪'!$A$2:$A$501="每日跟踪")*('持仓跟踪'!$B$2:$B$501=A47)),1),0)),0)*AN47)))) | AR47: =IF(A47="","",IF(OR(E47="",H47=""),"违规：第一批价格或股数缺失",IF(OR(AND(AK47="",AL47<>""),AND(AK47<>"",AL47="")),"违规：第二批价格与股数须成对填写",IF(OR(AND(AM47="",AN47<>""),AND(AM47<>"",AN47="")),"违规：第三批价格与股数须成对填写",IF(AND(OR(AM47<>"",AN47<>""),OR(AK47="",AL47="")),"违规：必须先完成第二批",IF(OR(H47<=0,H47<>INT(H47),MOD(H47,100)<>0,AND(AL47<>"",OR(AL47<=0,AL47<>INT(AL47),MOD(AL47,100)<>0)),AND(AN47<>"",OR(AN47<=0,AN47<>INT(AN47),MOD(AN47,100)<>0))),"违规：股数须为100股整数倍",IF(AND(OR(AL47<>"",AN47<>""),OR(_LockStatus="已锁仓",_LockStatus="解锁信息不完整")),"违规：锁仓期间禁止加仓",IF(AQ47>C47*D47,"违规：超过单笔风险上限",IF(SUM($AQ$2:$AQ$201)>账户数据!$B$7,"违规：超过账户风险上限","通过")))))))))
A48: 47 | B48: 深南电路 | C48: 108129 | D48: 0.02 | E48: 51.49 | F48: =IF(OR(C48="",D48="",E48="",N48="",C48<=0,D48<=0,E48<=N48),"",ROUNDDOWN((C48*D48)/(E48-N48)/100,0)*100) | G48: =IF(A48="","",IF(H48<>"","已开仓",IF(账户数据!$B$23="已锁仓","禁止开仓：连续亏损达到上限",IF(账户数据!$B$23="解锁信息不完整","禁止开仓：请完整填写解锁信息",IF(OR(F48="",E48="",N48="",E48<=N48,账户数据!$B$7=""),"",IF(OR(AG48="",AH48="",AI48=""),"禁止开仓：交易预期未填写完整",IF(COUNTIFS(持仓跟踪!$A$2:$A$501,"止损计划",持仓跟踪!$B$2:$B$501,A48,持仓跟踪!$AC$2:$AC$501,"计划有效")=0,"禁止开仓：请先填写止损计划",IF(账户数据!$B$9+F48*(E48-N48)>=账户数据!$B$7,"禁止开仓：风险额度不足",IF(AJ48="周期与交易预期不匹配，请重新确认",IF(账户数据!$B$23="接近锁仓","允许开仓（接近锁仓；周期需复核）","允许开仓（周期需复核）"),IF(账户数据!$B$23="接近锁仓","允许开仓（接近锁仓）","允许开仓")))))))))) | H48: 1400 | I48: 45070 | J48: 55 | K48: 56 | L48: =IF(K48="","",H48) | M48: 45077 | N48: 50 | U48: =IF(OR(AO48="",J48="",AO48<=0),"",(J48-AO48)/AO48) | V48: =IF(OR(AO48="",N48="",AO48<=0),"",(AO48-N48)/AO48) | W48: =IF(OR(U48="",V48="",V48<=0),"",U48/V48) | X48: =IF(OR(K48="",L48="",AP48=""),"",K48*L48-(E48*H48+IF(AND(AK48<>"",AL48<>""),AK48*AL48,0)+IF(AND(AM48<>"",AN48<>""),AM48*AN48,0))-IF(O48="",0,O48)-IF(P48="",0,P48)) | Y48: =IF(OR(X48="",AP48=""),"",IF((E48*H48+IF(AND(AK48<>"",AL48<>""),AK48*AL48,0)+IF(AND(AM48<>"",AN48<>""),AM48*AN48,0))+IF(O48="",0,O48)<=0,"",X48/((E48*H48+IF(AND(AK48<>"",AL48<>""),AK48*AL48,0)+IF(AND(AM48<>"",AN48<>""),AM48*AN48,0))+IF(O48="",0,O48)))) | Z48: =IF(OR(AE48="",多次统计数据!$B$8=""),"",AE48-多次统计数据!$B$8) | AA48: =IF(OR(I48="",M48="",M48<I48),"",M48-I48) | AB48: =IF(OR(A48="",多次统计数据!$B$8="",多次统计数据!$B$6<=0,多次统计数据!$B$6>=1),"",1-POWER(1+多次统计数据!$B$8,-多次统计数据!$B$6/(1-多次统计数据!$B$6))) | AC48: =IF(OR(AB48="",多次统计数据!$B$9=""),"",IF(多次统计数据!$B$9<AB48,"低于上限","达到或超过上限")) | AE48: =IF(OR(X48="",C48="",C48<=0),"",X48/C48) | AJ48: =IF(OR(AG48="",AH48=""),"",IF(OR(AND(AG48="短期博反弹",OR(AH48="1～3个交易日",AH48="4～10个交易日")),AND(AG48="突破冲新高",OR(AH48="4～10个交易日",AH48="11～20个交易日")),AND(AG48="趋势波段",OR(AH48="11～20个交易日",AH48="21～60个交易日",AH48="60个交易日以上"))),"匹配","周期与交易预期不匹配，请重新确认")) | AO48: =IF(OR(A48="",H48="",H48<=0),"",(E48*H48+IF(AND(AK48<>"",AL48<>""),AK48*AL48,0)+IF(AND(AM48<>"",AN48<>""),AM48*AN48,0))/AP48) | AP48: =IF(OR(A48="",H48="",H48<=0),"",H48+IF(AL48="",0,AL48)+IF(AN48="",0,AN48)) | AQ48: =IF(A48="","",IF(M48<>"",0,IF(OR(H48="",N48=""),"",MAX(E48-MAX(N48,IFERROR(AGGREGATE(14,6,'持仓跟踪'!$S$2:$S$501/(('持仓跟踪'!$A$2:$A$501="每日跟踪")*('持仓跟踪'!$B$2:$B$501=A48)),1),0)),0)*H48+IF(OR(AK48="",AL48=""),0,MAX(AK48-MAX(N48,IFERROR(AGGREGATE(14,6,'持仓跟踪'!$S$2:$S$501/(('持仓跟踪'!$A$2:$A$501="每日跟踪")*('持仓跟踪'!$B$2:$B$501=A48)),1),0)),0)*AL48)+IF(OR(AM48="",AN48=""),0,MAX(AM48-MAX(N48,IFERROR(AGGREGATE(14,6,'持仓跟踪'!$S$2:$S$501/(('持仓跟踪'!$A$2:$A$501="每日跟踪")*('持仓跟踪'!$B$2:$B$501=A48)),1),0)),0)*AN48)))) | AR48: =IF(A48="","",IF(OR(E48="",H48=""),"违规：第一批价格或股数缺失",IF(OR(AND(AK48="",AL48<>""),AND(AK48<>"",AL48="")),"违规：第二批价格与股数须成对填写",IF(OR(AND(AM48="",AN48<>""),AND(AM48<>"",AN48="")),"违规：第三批价格与股数须成对填写",IF(AND(OR(AM48<>"",AN48<>""),OR(AK48="",AL48="")),"违规：必须先完成第二批",IF(OR(H48<=0,H48<>INT(H48),MOD(H48,100)<>0,AND(AL48<>"",OR(AL48<=0,AL48<>INT(AL48),MOD(AL48,100)<>0)),AND(AN48<>"",OR(AN48<=0,AN48<>INT(AN48),MOD(AN48,100)<>0))),"违规：股数须为100股整数倍",IF(AND(OR(AL48<>"",AN48<>""),OR(_LockStatus="已锁仓",_LockStatus="解锁信息不完整")),"违规：锁仓期间禁止加仓",IF(AQ48>C48*D48,"违规：超过单笔风险上限",IF(SUM($AQ$2:$AQ$201)>账户数据!$B$7,"违规：超过账户风险上限","通过")))))))))
A49: 48 | B49: 深南电路 | C49: 111443 | D49: 0.02 | E49: 52.19 | F49: =IF(OR(C49="",D49="",E49="",N49="",C49<=0,D49<=0,E49<=N49),"",ROUNDDOWN((C49*D49)/(E49-N49)/100,0)*100) | G49: =IF(A49="","",IF(H49<>"","已开仓",IF(账户数据!$B$23="已锁仓","禁止开仓：连续亏损达到上限",IF(账户数据!$B$23="解锁信息不完整","禁止开仓：请完整填写解锁信息",IF(OR(F49="",E49="",N49="",E49<=N49,账户数据!$B$7=""),"",IF(OR(AG49="",AH49="",AI49=""),"禁止开仓：交易预期未填写完整",IF(COUNTIFS(持仓跟踪!$A$2:$A$501,"止损计划",持仓跟踪!$B$2:$B$501,A49,持仓跟踪!$AC$2:$AC$501,"计划有效")=0,"禁止开仓：请先填写止损计划",IF(账户数据!$B$9+F49*(E49-N49)>=账户数据!$B$7,"禁止开仓：风险额度不足",IF(AJ49="周期与交易预期不匹配，请重新确认",IF(账户数据!$B$23="接近锁仓","允许开仓（接近锁仓；周期需复核）","允许开仓（周期需复核）"),IF(账户数据!$B$23="接近锁仓","允许开仓（接近锁仓）","允许开仓")))))))))) | H49: 1000 | I49: 45153 | J49: 55 | K49: 46.45 | L49: =IF(K49="","",H49) | M49: 45159 | N49: 50 | U49: =IF(OR(AO49="",J49="",AO49<=0),"",(J49-AO49)/AO49) | V49: =IF(OR(AO49="",N49="",AO49<=0),"",(AO49-N49)/AO49) | W49: =IF(OR(U49="",V49="",V49<=0),"",U49/V49) | X49: =IF(OR(K49="",L49="",AP49=""),"",K49*L49-(E49*H49+IF(AND(AK49<>"",AL49<>""),AK49*AL49,0)+IF(AND(AM49<>"",AN49<>""),AM49*AN49,0))-IF(O49="",0,O49)-IF(P49="",0,P49)) | Y49: =IF(OR(X49="",AP49=""),"",IF((E49*H49+IF(AND(AK49<>"",AL49<>""),AK49*AL49,0)+IF(AND(AM49<>"",AN49<>""),AM49*AN49,0))+IF(O49="",0,O49)<=0,"",X49/((E49*H49+IF(AND(AK49<>"",AL49<>""),AK49*AL49,0)+IF(AND(AM49<>"",AN49<>""),AM49*AN49,0))+IF(O49="",0,O49)))) | Z49: =IF(OR(AE49="",多次统计数据!$B$8=""),"",AE49-多次统计数据!$B$8) | AA49: =IF(OR(I49="",M49="",M49<I49),"",M49-I49) | AB49: =IF(OR(A49="",多次统计数据!$B$8="",多次统计数据!$B$6<=0,多次统计数据!$B$6>=1),"",1-POWER(1+多次统计数据!$B$8,-多次统计数据!$B$6/(1-多次统计数据!$B$6))) | AC49: =IF(OR(AB49="",多次统计数据!$B$9=""),"",IF(多次统计数据!$B$9<AB49,"低于上限","达到或超过上限")) | AE49: =IF(OR(X49="",C49="",C49<=0),"",X49/C49) | AF49: 盈利比不好，强行买入了 | AJ49: =IF(OR(AG49="",AH49=""),"",IF(OR(AND(AG49="短期博反弹",OR(AH49="1～3个交易日",AH49="4～10个交易日")),AND(AG49="突破冲新高",OR(AH49="4～10个交易日",AH49="11～20个交易日")),AND(AG49="趋势波段",OR(AH49="11～20个交易日",AH49="21～60个交易日",AH49="60个交易日以上"))),"匹配","周期与交易预期不匹配，请重新确认")) | AO49: =IF(OR(A49="",H49="",H49<=0),"",(E49*H49+IF(AND(AK49<>"",AL49<>""),AK49*AL49,0)+IF(AND(AM49<>"",AN49<>""),AM49*AN49,0))/AP49) | AP49: =IF(OR(A49="",H49="",H49<=0),"",H49+IF(AL49="",0,AL49)+IF(AN49="",0,AN49)) | AQ49: =IF(A49="","",IF(M49<>"",0,IF(OR(H49="",N49=""),"",MAX(E49-MAX(N49,IFERROR(AGGREGATE(14,6,'持仓跟踪'!$S$2:$S$501/(('持仓跟踪'!$A$2:$A$501="每日跟踪")*('持仓跟踪'!$B$2:$B$501=A49)),1),0)),0)*H49+IF(OR(AK49="",AL49=""),0,MAX(AK49-MAX(N49,IFERROR(AGGREGATE(14,6,'持仓跟踪'!$S$2:$S$501/(('持仓跟踪'!$A$2:$A$501="每日跟踪")*('持仓跟踪'!$B$2:$B$501=A49)),1),0)),0)*AL49)+IF(OR(AM49="",AN49=""),0,MAX(AM49-MAX(N49,IFERROR(AGGREGATE(14,6,'持仓跟踪'!$S$2:$S$501/(('持仓跟踪'!$A$2:$A$501="每日跟踪")*('持仓跟踪'!$B$2:$B$501=A49)),1),0)),0)*AN49)))) | AR49: =IF(A49="","",IF(OR(E49="",H49=""),"违规：第一批价格或股数缺失",IF(OR(AND(AK49="",AL49<>""),AND(AK49<>"",AL49="")),"违规：第二批价格与股数须成对填写",IF(OR(AND(AM49="",AN49<>""),AND(AM49<>"",AN49="")),"违规：第三批价格与股数须成对填写",IF(AND(OR(AM49<>"",AN49<>""),OR(AK49="",AL49="")),"违规：必须先完成第二批",IF(OR(H49<=0,H49<>INT(H49),MOD(H49,100)<>0,AND(AL49<>"",OR(AL49<=0,AL49<>INT(AL49),MOD(AL49,100)<>0)),AND(AN49<>"",OR(AN49<=0,AN49<>INT(AN49),MOD(AN49,100)<>0))),"违规：股数须为100股整数倍",IF(AND(OR(AL49<>"",AN49<>""),OR(_LockStatus="已锁仓",_LockStatus="解锁信息不完整")),"违规：锁仓期间禁止加仓",IF(AQ49>C49*D49,"违规：超过单笔风险上限",IF(SUM($AQ$2:$AQ$201)>账户数据!$B$7,"违规：超过账户风险上限","通过")))))))))
A50: 49 | B50: 深南电路 | C50: 108793 | D50: 0.02 | E50: 41.88 | F50: =IF(OR(C50="",D50="",E50="",N50="",C50<=0,D50<=0,E50<=N50),"",ROUNDDOWN((C50*D50)/(E50-N50)/100,0)*100) | G50: =IF(A50="","",IF(H50<>"","已开仓",IF(账户数据!$B$23="已锁仓","禁止开仓：连续亏损达到上限",IF(账户数据!$B$23="解锁信息不完整","禁止开仓：请完整填写解锁信息",IF(OR(F50="",E50="",N50="",E50<=N50,账户数据!$B$7=""),"",IF(OR(AG50="",AH50="",AI50=""),"禁止开仓：交易预期未填写完整",IF(COUNTIFS(持仓跟踪!$A$2:$A$501,"止损计划",持仓跟踪!$B$2:$B$501,A50,持仓跟踪!$AC$2:$AC$501,"计划有效")=0,"禁止开仓：请先填写止损计划",IF(账户数据!$B$9+F50*(E50-N50)>=账户数据!$B$7,"禁止开仓：风险额度不足",IF(AJ50="周期与交易预期不匹配，请重新确认",IF(账户数据!$B$23="接近锁仓","允许开仓（接近锁仓；周期需复核）","允许开仓（周期需复核）"),IF(账户数据!$B$23="接近锁仓","允许开仓（接近锁仓）","允许开仓")))))))))) | H50: 1100 | I50: 45309 | J50: 45.5 | K50: 38.83 | L50: =IF(K50="","",H50) | M50: 45313 | N50: 40 | U50: =IF(OR(AO50="",J50="",AO50<=0),"",(J50-AO50)/AO50) | V50: =IF(OR(AO50="",N50="",AO50<=0),"",(AO50-N50)/AO50) | W50: =IF(OR(U50="",V50="",V50<=0),"",U50/V50) | X50: =IF(OR(K50="",L50="",AP50=""),"",K50*L50-(E50*H50+IF(AND(AK50<>"",AL50<>""),AK50*AL50,0)+IF(AND(AM50<>"",AN50<>""),AM50*AN50,0))-IF(O50="",0,O50)-IF(P50="",0,P50)) | Y50: =IF(OR(X50="",AP50=""),"",IF((E50*H50+IF(AND(AK50<>"",AL50<>""),AK50*AL50,0)+IF(AND(AM50<>"",AN50<>""),AM50*AN50,0))+IF(O50="",0,O50)<=0,"",X50/((E50*H50+IF(AND(AK50<>"",AL50<>""),AK50*AL50,0)+IF(AND(AM50<>"",AN50<>""),AM50*AN50,0))+IF(O50="",0,O50)))) | Z50: =IF(OR(AE50="",多次统计数据!$B$8=""),"",AE50-多次统计数据!$B$8) | AA50: =IF(OR(I50="",M50="",M50<I50),"",M50-I50) | AB50: =IF(OR(A50="",多次统计数据!$B$8="",多次统计数据!$B$6<=0,多次统计数据!$B$6>=1),"",1-POWER(1+多次统计数据!$B$8,-多次统计数据!$B$6/(1-多次统计数据!$B$6))) | AC50: =IF(OR(AB50="",多次统计数据!$B$9=""),"",IF(多次统计数据!$B$9<AB50,"低于上限","达到或超过上限")) | AE50: =IF(OR(X50="",C50="",C50<=0),"",X50/C50) | AF50: 不要强跑等确认上升 | AJ50: =IF(OR(AG50="",AH50=""),"",IF(OR(AND(AG50="短期博反弹",OR(AH50="1～3个交易日",AH50="4～10个交易日")),AND(AG50="突破冲新高",OR(AH50="4～10个交易日",AH50="11～20个交易日")),AND(AG50="趋势波段",OR(AH50="11～20个交易日",AH50="21～60个交易日",AH50="60个交易日以上"))),"匹配","周期与交易预期不匹配，请重新确认")) | AO50: =IF(OR(A50="",H50="",H50<=0),"",(E50*H50+IF(AND(AK50<>"",AL50<>""),AK50*AL50,0)+IF(AND(AM50<>"",AN50<>""),AM50*AN50,0))/AP50) | AP50: =IF(OR(A50="",H50="",H50<=0),"",H50+IF(AL50="",0,AL50)+IF(AN50="",0,AN50)) | AQ50: =IF(A50="","",IF(M50<>"",0,IF(OR(H50="",N50=""),"",MAX(E50-MAX(N50,IFERROR(AGGREGATE(14,6,'持仓跟踪'!$S$2:$S$501/(('持仓跟踪'!$A$2:$A$501="每日跟踪")*('持仓跟踪'!$B$2:$B$501=A50)),1),0)),0)*H50+IF(OR(AK50="",AL50=""),0,MAX(AK50-MAX(N50,IFERROR(AGGREGATE(14,6,'持仓跟踪'!$S$2:$S$501/(('持仓跟踪'!$A$2:$A$501="每日跟踪")*('持仓跟踪'!$B$2:$B$501=A50)),1),0)),0)*AL50)+IF(OR(AM50="",AN50=""),0,MAX(AM50-MAX(N50,IFERROR(AGGREGATE(14,6,'持仓跟踪'!$S$2:$S$501/(('持仓跟踪'!$A$2:$A$501="每日跟踪")*('持仓跟踪'!$B$2:$B$501=A50)),1),0)),0)*AN50)))) | AR50: =IF(A50="","",IF(OR(E50="",H50=""),"违规：第一批价格或股数缺失",IF(OR(AND(AK50="",AL50<>""),AND(AK50<>"",AL50="")),"违规：第二批价格与股数须成对填写",IF(OR(AND(AM50="",AN50<>""),AND(AM50<>"",AN50="")),"违规：第三批价格与股数须成对填写",IF(AND(OR(AM50<>"",AN50<>""),OR(AK50="",AL50="")),"违规：必须先完成第二批",IF(OR(H50<=0,H50<>INT(H50),MOD(H50,100)<>0,AND(AL50<>"",OR(AL50<=0,AL50<>INT(AL50),MOD(AL50,100)<>0)),AND(AN50<>"",OR(AN50<=0,AN50<>INT(AN50),MOD(AN50,100)<>0))),"违规：股数须为100股整数倍",IF(AND(OR(AL50<>"",AN50<>""),OR(_LockStatus="已锁仓",_LockStatus="解锁信息不完整")),"违规：锁仓期间禁止加仓",IF(AQ50>C50*D50,"违规：超过单笔风险上限",IF(SUM($AQ$2:$AQ$201)>账户数据!$B$7,"违规：超过账户风险上限","通过")))))))))
A51: 50 | B51: 深南电路 | C51: 105348 | D51: 0.02 | E51: 97.5 | F51: =IF(OR(C51="",D51="",E51="",N51="",C51<=0,D51<=0,E51<=N51),"",ROUNDDOWN((C51*D51)/(E51-N51)/100,0)*100) | G51: =IF(A51="","",IF(H51<>"","已开仓",IF(账户数据!$B$23="已锁仓","禁止开仓：连续亏损达到上限",IF(账户数据!$B$23="解锁信息不完整","禁止开仓：请完整填写解锁信息",IF(OR(F51="",E51="",N51="",E51<=N51,账户数据!$B$7=""),"",IF(OR(AG51="",AH51="",AI51=""),"禁止开仓：交易预期未填写完整",IF(COUNTIFS(持仓跟踪!$A$2:$A$501,"止损计划",持仓跟踪!$B$2:$B$501,A51,持仓跟踪!$AC$2:$AC$501,"计划有效")=0,"禁止开仓：请先填写止损计划",IF(账户数据!$B$9+F51*(E51-N51)>=账户数据!$B$7,"禁止开仓：风险额度不足",IF(AJ51="周期与交易预期不匹配，请重新确认",IF(账户数据!$B$23="接近锁仓","允许开仓（接近锁仓；周期需复核）","允许开仓（周期需复核）"),IF(账户数据!$B$23="接近锁仓","允许开仓（接近锁仓）","允许开仓")))))))))) | H51: 800 | I51: 45833 | J51: 100 | K51: 129.8 | L51: =IF(K51="","",H51) | M51: 45861 | N51: 95 | U51: =IF(OR(AO51="",J51="",AO51<=0),"",(J51-AO51)/AO51) | V51: =IF(OR(AO51="",N51="",AO51<=0),"",(AO51-N51)/AO51) | W51: =IF(OR(U51="",V51="",V51<=0),"",U51/V51) | X51: =IF(OR(K51="",L51="",AP51=""),"",K51*L51-(E51*H51+IF(AND(AK51<>"",AL51<>""),AK51*AL51,0)+IF(AND(AM51<>"",AN51<>""),AM51*AN51,0))-IF(O51="",0,O51)-IF(P51="",0,P51)) | Y51: =IF(OR(X51="",AP51=""),"",IF((E51*H51+IF(AND(AK51<>"",AL51<>""),AK51*AL51,0)+IF(AND(AM51<>"",AN51<>""),AM51*AN51,0))+IF(O51="",0,O51)<=0,"",X51/((E51*H51+IF(AND(AK51<>"",AL51<>""),AK51*AL51,0)+IF(AND(AM51<>"",AN51<>""),AM51*AN51,0))+IF(O51="",0,O51)))) | Z51: =IF(OR(AE51="",多次统计数据!$B$8=""),"",AE51-多次统计数据!$B$8) | AA51: =IF(OR(I51="",M51="",M51<I51),"",M51-I51) | AB51: =IF(OR(A51="",多次统计数据!$B$8="",多次统计数据!$B$6<=0,多次统计数据!$B$6>=1),"",1-POWER(1+多次统计数据!$B$8,-多次统计数据!$B$6/(1-多次统计数据!$B$6))) | AC51: =IF(OR(AB51="",多次统计数据!$B$9=""),"",IF(多次统计数据!$B$9<AB51,"低于上限","达到或超过上限")) | AE51: =IF(OR(X51="",C51="",C51<=0),"",X51/C51) | AJ51: =IF(OR(AG51="",AH51=""),"",IF(OR(AND(AG51="短期博反弹",OR(AH51="1～3个交易日",AH51="4～10个交易日")),AND(AG51="突破冲新高",OR(AH51="4～10个交易日",AH51="11～20个交易日")),AND(AG51="趋势波段",OR(AH51="11～20个交易日",AH51="21～60个交易日",AH51="60个交易日以上"))),"匹配","周期与交易预期不匹配，请重新确认")) | AO51: =IF(OR(A51="",H51="",H51<=0),"",(E51*H51+IF(AND(AK51<>"",AL51<>""),AK51*AL51,0)+IF(AND(AM51<>"",AN51<>""),AM51*AN51,0))/AP51) | AP51: =IF(OR(A51="",H51="",H51<=0),"",H51+IF(AL51="",0,AL51)+IF(AN51="",0,AN51)) | AQ51: =IF(A51="","",IF(M51<>"",0,IF(OR(H51="",N51=""),"",MAX(E51-MAX(N51,IFERROR(AGGREGATE(14,6,'持仓跟踪'!$S$2:$S$501/(('持仓跟踪'!$A$2:$A$501="每日跟踪")*('持仓跟踪'!$B$2:$B$501=A51)),1),0)),0)*H51+IF(OR(AK51="",AL51=""),0,MAX(AK51-MAX(N51,IFERROR(AGGREGATE(14,6,'持仓跟踪'!$S$2:$S$501/(('持仓跟踪'!$A$2:$A$501="每日跟踪")*('持仓跟踪'!$B$2:$B$501=A51)),1),0)),0)*AL51)+IF(OR(AM51="",AN51=""),0,MAX(AM51-MAX(N51,IFERROR(AGGREGATE(14,6,'持仓跟踪'!$S$2:$S$501/(('持仓跟踪'!$A$2:$A$501="每日跟踪")*('持仓跟踪'!$B$2:$B$501=A51)),1),0)),0)*AN51)))) | AR51: =IF(A51="","",IF(OR(E51="",H51=""),"违规：第一批价格或股数缺失",IF(OR(AND(AK51="",AL51<>""),AND(AK51<>"",AL51="")),"违规：第二批价格与股数须成对填写",IF(OR(AND(AM51="",AN51<>""),AND(AM51<>"",AN51="")),"违规：第三批价格与股数须成对填写",IF(AND(OR(AM51<>"",AN51<>""),OR(AK51="",AL51="")),"违规：必须先完成第二批",IF(OR(H51<=0,H51<>INT(H51),MOD(H51,100)<>0,AND(AL51<>"",OR(AL51<=0,AL51<>INT(AL51),MOD(AL51,100)<>0)),AND(AN51<>"",OR(AN51<=0,AN51<>INT(AN51),MOD(AN51,100)<>0))),"违规：股数须为100股整数倍",IF(AND(OR(AL51<>"",AN51<>""),OR(_LockStatus="已锁仓",_LockStatus="解锁信息不完整")),"违规：锁仓期间禁止加仓",IF(AQ51>C51*D51,"违规：超过单笔风险上限",IF(SUM($AQ$2:$AQ$201)>账户数据!$B$7,"违规：超过账户风险上限","通过")))))))))
A52: 51 | B52: 深南电路 | C52: 131188 | D52: 0.02 | E52: 139.18 | F52: =IF(OR(C52="",D52="",E52="",N52="",C52<=0,D52<=0,E52<=N52),"",ROUNDDOWN((C52*D52)/(E52-N52)/100,0)*100) | G52: =IF(A52="","",IF(H52<>"","已开仓",IF(账户数据!$B$23="已锁仓","禁止开仓：连续亏损达到上限",IF(账户数据!$B$23="解锁信息不完整","禁止开仓：请完整填写解锁信息",IF(OR(F52="",E52="",N52="",E52<=N52,账户数据!$B$7=""),"",IF(OR(AG52="",AH52="",AI52=""),"禁止开仓：交易预期未填写完整",IF(COUNTIFS(持仓跟踪!$A$2:$A$501,"止损计划",持仓跟踪!$B$2:$B$501,A52,持仓跟踪!$AC$2:$AC$501,"计划有效")=0,"禁止开仓：请先填写止损计划",IF(账户数据!$B$9+F52*(E52-N52)>=账户数据!$B$7,"禁止开仓：风险额度不足",IF(AJ52="周期与交易预期不匹配，请重新确认",IF(账户数据!$B$23="接近锁仓","允许开仓（接近锁仓；周期需复核）","允许开仓（周期需复核）"),IF(账户数据!$B$23="接近锁仓","允许开仓（接近锁仓）","允许开仓")))))))))) | H52: 600 | I52: 45890 | J52: 150 | K52: 177.39 | L52: =IF(K52="","",H52) | M52: 45902 | N52: 135 | U52: =IF(OR(AO52="",J52="",AO52<=0),"",(J52-AO52)/AO52) | V52: =IF(OR(AO52="",N52="",AO52<=0),"",(AO52-N52)/AO52) | W52: =IF(OR(U52="",V52="",V52<=0),"",U52/V52) | X52: =IF(OR(K52="",L52="",AP52=""),"",K52*L52-(E52*H52+IF(AND(AK52<>"",AL52<>""),AK52*AL52,0)+IF(AND(AM52<>"",AN52<>""),AM52*AN52,0))-IF(O52="",0,O52)-IF(P52="",0,P52)) | Y52: =IF(OR(X52="",AP52=""),"",IF((E52*H52+IF(AND(AK52<>"",AL52<>""),AK52*AL52,0)+IF(AND(AM52<>"",AN52<>""),AM52*AN52,0))+IF(O52="",0,O52)<=0,"",X52/((E52*H52+IF(AND(AK52<>"",AL52<>""),AK52*AL52,0)+IF(AND(AM52<>"",AN52<>""),AM52*AN52,0))+IF(O52="",0,O52)))) | Z52: =IF(OR(AE52="",多次统计数据!$B$8=""),"",AE52-多次统计数据!$B$8) | AA52: =IF(OR(I52="",M52="",M52<I52),"",M52-I52) | AB52: =IF(OR(A52="",多次统计数据!$B$8="",多次统计数据!$B$6<=0,多次统计数据!$B$6>=1),"",1-POWER(1+多次统计数据!$B$8,-多次统计数据!$B$6/(1-多次统计数据!$B$6))) | AC52: =IF(OR(AB52="",多次统计数据!$B$9=""),"",IF(多次统计数据!$B$9<AB52,"低于上限","达到或超过上限")) | AE52: =IF(OR(X52="",C52="",C52<=0),"",X52/C52) | AJ52: =IF(OR(AG52="",AH52=""),"",IF(OR(AND(AG52="短期博反弹",OR(AH52="1～3个交易日",AH52="4～10个交易日")),AND(AG52="突破冲新高",OR(AH52="4～10个交易日",AH52="11～20个交易日")),AND(AG52="趋势波段",OR(AH52="11～20个交易日",AH52="21～60个交易日",AH52="60个交易日以上"))),"匹配","周期与交易预期不匹配，请重新确认")) | AO52: =IF(OR(A52="",H52="",H52<=0),"",(E52*H52+IF(AND(AK52<>"",AL52<>""),AK52*AL52,0)+IF(AND(AM52<>"",AN52<>""),AM52*AN52,0))/AP52) | AP52: =IF(OR(A52="",H52="",H52<=0),"",H52+IF(AL52="",0,AL52)+IF(AN52="",0,AN52)) | AQ52: =IF(A52="","",IF(M52<>"",0,IF(OR(H52="",N52=""),"",MAX(E52-MAX(N52,IFERROR(AGGREGATE(14,6,'持仓跟踪'!$S$2:$S$501/(('持仓跟踪'!$A$2:$A$501="每日跟踪")*('持仓跟踪'!$B$2:$B$501=A52)),1),0)),0)*H52+IF(OR(AK52="",AL52=""),0,MAX(AK52-MAX(N52,IFERROR(AGGREGATE(14,6,'持仓跟踪'!$S$2:$S$501/(('持仓跟踪'!$A$2:$A$501="每日跟踪")*('持仓跟踪'!$B$2:$B$501=A52)),1),0)),0)*AL52)+IF(OR(AM52="",AN52=""),0,MAX(AM52-MAX(N52,IFERROR(AGGREGATE(14,6,'持仓跟踪'!$S$2:$S$501/(('持仓跟踪'!$A$2:$A$501="每日跟踪")*('持仓跟踪'!$B$2:$B$501=A52)),1),0)),0)*AN52)))) | AR52: =IF(A52="","",IF(OR(E52="",H52=""),"违规：第一批价格或股数缺失",IF(OR(AND(AK52="",AL52<>""),AND(AK52<>"",AL52="")),"违规：第二批价格与股数须成对填写",IF(OR(AND(AM52="",AN52<>""),AND(AM52<>"",AN52="")),"违规：第三批价格与股数须成对填写",IF(AND(OR(AM52<>"",AN52<>""),OR(AK52="",AL52="")),"违规：必须先完成第二批",IF(OR(H52<=0,H52<>INT(H52),MOD(H52,100)<>0,AND(AL52<>"",OR(AL52<=0,AL52<>INT(AL52),MOD(AL52,100)<>0)),AND(AN52<>"",OR(AN52<=0,AN52<>INT(AN52),MOD(AN52,100)<>0))),"违规：股数须为100股整数倍",IF(AND(OR(AL52<>"",AN52<>""),OR(_LockStatus="已锁仓",_LockStatus="解锁信息不完整")),"违规：锁仓期间禁止加仓",IF(AQ52>C52*D52,"违规：超过单笔风险上限",IF(SUM($AQ$2:$AQ$201)>账户数据!$B$7,"违规：超过账户风险上限","通过")))))))))
A53: 52 | B53: 双汇发展 | C53: 154114 | D53: 0.02 | E53: 41.46 | F53: =IF(OR(C53="",D53="",E53="",N53="",C53<=0,D53<=0,E53<=N53),"",ROUNDDOWN((C53*D53)/(E53-N53)/100,0)*100) | G53: =IF(A53="","",IF(H53<>"","已开仓",IF(账户数据!$B$23="已锁仓","禁止开仓：连续亏损达到上限",IF(账户数据!$B$23="解锁信息不完整","禁止开仓：请完整填写解锁信息",IF(OR(F53="",E53="",N53="",E53<=N53,账户数据!$B$7=""),"",IF(OR(AG53="",AH53="",AI53=""),"禁止开仓：交易预期未填写完整",IF(COUNTIFS(持仓跟踪!$A$2:$A$501,"止损计划",持仓跟踪!$B$2:$B$501,A53,持仓跟踪!$AC$2:$AC$501,"计划有效")=0,"禁止开仓：请先填写止损计划",IF(账户数据!$B$9+F53*(E53-N53)>=账户数据!$B$7,"禁止开仓：风险额度不足",IF(AJ53="周期与交易预期不匹配，请重新确认",IF(账户数据!$B$23="接近锁仓","允许开仓（接近锁仓；周期需复核）","允许开仓（周期需复核）"),IF(账户数据!$B$23="接近锁仓","允许开仓（接近锁仓）","允许开仓")))))))))) | H53: 1200 | I53: 44221 | J53: 45 | K53: 38.76 | L53: =IF(K53="","",H53) | M53: 44223 | N53: 39 | U53: =IF(OR(AO53="",J53="",AO53<=0),"",(J53-AO53)/AO53) | V53: =IF(OR(AO53="",N53="",AO53<=0),"",(AO53-N53)/AO53) | W53: =IF(OR(U53="",V53="",V53<=0),"",U53/V53) | X53: =IF(OR(K53="",L53="",AP53=""),"",K53*L53-(E53*H53+IF(AND(AK53<>"",AL53<>""),AK53*AL53,0)+IF(AND(AM53<>"",AN53<>""),AM53*AN53,0))-IF(O53="",0,O53)-IF(P53="",0,P53)) | Y53: =IF(OR(X53="",AP53=""),"",IF((E53*H53+IF(AND(AK53<>"",AL53<>""),AK53*AL53,0)+IF(AND(AM53<>"",AN53<>""),AM53*AN53,0))+IF(O53="",0,O53)<=0,"",X53/((E53*H53+IF(AND(AK53<>"",AL53<>""),AK53*AL53,0)+IF(AND(AM53<>"",AN53<>""),AM53*AN53,0))+IF(O53="",0,O53)))) | Z53: =IF(OR(AE53="",多次统计数据!$B$8=""),"",AE53-多次统计数据!$B$8) | AA53: =IF(OR(I53="",M53="",M53<I53),"",M53-I53) | AB53: =IF(OR(A53="",多次统计数据!$B$8="",多次统计数据!$B$6<=0,多次统计数据!$B$6>=1),"",1-POWER(1+多次统计数据!$B$8,-多次统计数据!$B$6/(1-多次统计数据!$B$6))) | AC53: =IF(OR(AB53="",多次统计数据!$B$9=""),"",IF(多次统计数据!$B$9<AB53,"低于上限","达到或超过上限")) | AE53: =IF(OR(X53="",C53="",C53<=0),"",X53/C53) | AJ53: =IF(OR(AG53="",AH53=""),"",IF(OR(AND(AG53="短期博反弹",OR(AH53="1～3个交易日",AH53="4～10个交易日")),AND(AG53="突破冲新高",OR(AH53="4～10个交易日",AH53="11～20个交易日")),AND(AG53="趋势波段",OR(AH53="11～20个交易日",AH53="21～60个交易日",AH53="60个交易日以上"))),"匹配","周期与交易预期不匹配，请重新确认")) | AO53: =IF(OR(A53="",H53="",H53<=0),"",(E53*H53+IF(AND(AK53<>"",AL53<>""),AK53*AL53,0)+IF(AND(AM53<>"",AN53<>""),AM53*AN53,0))/AP53) | AP53: =IF(OR(A53="",H53="",H53<=0),"",H53+IF(AL53="",0,AL53)+IF(AN53="",0,AN53)) | AQ53: =IF(A53="","",IF(M53<>"",0,IF(OR(H53="",N53=""),"",MAX(E53-MAX(N53,IFERROR(AGGREGATE(14,6,'持仓跟踪'!$S$2:$S$501/(('持仓跟踪'!$A$2:$A$501="每日跟踪")*('持仓跟踪'!$B$2:$B$501=A53)),1),0)),0)*H53+IF(OR(AK53="",AL53=""),0,MAX(AK53-MAX(N53,IFERROR(AGGREGATE(14,6,'持仓跟踪'!$S$2:$S$501/(('持仓跟踪'!$A$2:$A$501="每日跟踪")*('持仓跟踪'!$B$2:$B$501=A53)),1),0)),0)*AL53)+IF(OR(AM53="",AN53=""),0,MAX(AM53-MAX(N53,IFERROR(AGGREGATE(14,6,'持仓跟踪'!$S$2:$S$501/(('持仓跟踪'!$A$2:$A$501="每日跟踪")*('持仓跟踪'!$B$2:$B$501=A53)),1),0)),0)*AN53)))) | AR53: =IF(A53="","",IF(OR(E53="",H53=""),"违规：第一批价格或股数缺失",IF(OR(AND(AK53="",AL53<>""),AND(AK53<>"",AL53="")),"违规：第二批价格与股数须成对填写",IF(OR(AND(AM53="",AN53<>""),AND(AM53<>"",AN53="")),"违规：第三批价格与股数须成对填写",IF(AND(OR(AM53<>"",AN53<>""),OR(AK53="",AL53="")),"违规：必须先完成第二批",IF(OR(H53<=0,H53<>INT(H53),MOD(H53,100)<>0,AND(AL53<>"",OR(AL53<=0,AL53<>INT(AL53),MOD(AL53,100)<>0)),AND(AN53<>"",OR(AN53<=0,AN53<>INT(AN53),MOD(AN53,100)<>0))),"违规：股数须为100股整数倍",IF(AND(OR(AL53<>"",AN53<>""),OR(_LockStatus="已锁仓",_LockStatus="解锁信息不完整")),"违规：锁仓期间禁止加仓",IF(AQ53>C53*D53,"违规：超过单笔风险上限",IF(SUM($AQ$2:$AQ$201)>账户数据!$B$7,"违规：超过账户风险上限","通过")))))))))
A54: 53 | B54: 双汇发展 | C54: 150874 | D54: 0.02 | E54: 20.64 | F54: =IF(OR(C54="",D54="",E54="",N54="",C54<=0,D54<=0,E54<=N54),"",ROUNDDOWN((C54*D54)/(E54-N54)/100,0)*100) | G54: =IF(A54="","",IF(H54<>"","已开仓",IF(账户数据!$B$23="已锁仓","禁止开仓：连续亏损达到上限",IF(账户数据!$B$23="解锁信息不完整","禁止开仓：请完整填写解锁信息",IF(OR(F54="",E54="",N54="",E54<=N54,账户数据!$B$7=""),"",IF(OR(AG54="",AH54="",AI54=""),"禁止开仓：交易预期未填写完整",IF(COUNTIFS(持仓跟踪!$A$2:$A$501,"止损计划",持仓跟踪!$B$2:$B$501,A54,持仓跟踪!$AC$2:$AC$501,"计划有效")=0,"禁止开仓：请先填写止损计划",IF(账户数据!$B$9+F54*(E54-N54)>=账户数据!$B$7,"禁止开仓：风险额度不足",IF(AJ54="周期与交易预期不匹配，请重新确认",IF(账户数据!$B$23="接近锁仓","允许开仓（接近锁仓；周期需复核）","允许开仓（周期需复核）"),IF(账户数据!$B$23="接近锁仓","允许开仓（接近锁仓）","允许开仓")))))))))) | H54: 1600 | I54: 44496 | J54: 24 | K54: 22.77 | L54: =IF(K54="","",H54) | M54: 44501 | N54: 18.8 | U54: =IF(OR(AO54="",J54="",AO54<=0),"",(J54-AO54)/AO54) | V54: =IF(OR(AO54="",N54="",AO54<=0),"",(AO54-N54)/AO54) | W54: =IF(OR(U54="",V54="",V54<=0),"",U54/V54) | X54: =IF(OR(K54="",L54="",AP54=""),"",K54*L54-(E54*H54+IF(AND(AK54<>"",AL54<>""),AK54*AL54,0)+IF(AND(AM54<>"",AN54<>""),AM54*AN54,0))-IF(O54="",0,O54)-IF(P54="",0,P54)) | Y54: =IF(OR(X54="",AP54=""),"",IF((E54*H54+IF(AND(AK54<>"",AL54<>""),AK54*AL54,0)+IF(AND(AM54<>"",AN54<>""),AM54*AN54,0))+IF(O54="",0,O54)<=0,"",X54/((E54*H54+IF(AND(AK54<>"",AL54<>""),AK54*AL54,0)+IF(AND(AM54<>"",AN54<>""),AM54*AN54,0))+IF(O54="",0,O54)))) | Z54: =IF(OR(AE54="",多次统计数据!$B$8=""),"",AE54-多次统计数据!$B$8) | AA54: =IF(OR(I54="",M54="",M54<I54),"",M54-I54) | AB54: =IF(OR(A54="",多次统计数据!$B$8="",多次统计数据!$B$6<=0,多次统计数据!$B$6>=1),"",1-POWER(1+多次统计数据!$B$8,-多次统计数据!$B$6/(1-多次统计数据!$B$6))) | AC54: =IF(OR(AB54="",多次统计数据!$B$9=""),"",IF(多次统计数据!$B$9<AB54,"低于上限","达到或超过上限")) | AE54: =IF(OR(X54="",C54="",C54<=0),"",X54/C54) | AJ54: =IF(OR(AG54="",AH54=""),"",IF(OR(AND(AG54="短期博反弹",OR(AH54="1～3个交易日",AH54="4～10个交易日")),AND(AG54="突破冲新高",OR(AH54="4～10个交易日",AH54="11～20个交易日")),AND(AG54="趋势波段",OR(AH54="11～20个交易日",AH54="21～60个交易日",AH54="60个交易日以上"))),"匹配","周期与交易预期不匹配，请重新确认")) | AO54: =IF(OR(A54="",H54="",H54<=0),"",(E54*H54+IF(AND(AK54<>"",AL54<>""),AK54*AL54,0)+IF(AND(AM54<>"",AN54<>""),AM54*AN54,0))/AP54) | AP54: =IF(OR(A54="",H54="",H54<=0),"",H54+IF(AL54="",0,AL54)+IF(AN54="",0,AN54)) | AQ54: =IF(A54="","",IF(M54<>"",0,IF(OR(H54="",N54=""),"",MAX(E54-MAX(N54,IFERROR(AGGREGATE(14,6,'持仓跟踪'!$S$2:$S$501/(('持仓跟踪'!$A$2:$A$501="每日跟踪")*('持仓跟踪'!$B$2:$B$501=A54)),1),0)),0)*H54+IF(OR(AK54="",AL54=""),0,MAX(AK54-MAX(N54,IFERROR(AGGREGATE(14,6,'持仓跟踪'!$S$2:$S$501/(('持仓跟踪'!$A$2:$A$501="每日跟踪")*('持仓跟踪'!$B$2:$B$501=A54)),1),0)),0)*AL54)+IF(OR(AM54="",AN54=""),0,MAX(AM54-MAX(N54,IFERROR(AGGREGATE(14,6,'持仓跟踪'!$S$2:$S$501/(('持仓跟踪'!$A$2:$A$501="每日跟踪")*('持仓跟踪'!$B$2:$B$501=A54)),1),0)),0)*AN54)))) | AR54: =IF(A54="","",IF(OR(E54="",H54=""),"违规：第一批价格或股数缺失",IF(OR(AND(AK54="",AL54<>""),AND(AK54<>"",AL54="")),"违规：第二批价格与股数须成对填写",IF(OR(AND(AM54="",AN54<>""),AND(AM54<>"",AN54="")),"违规：第三批价格与股数须成对填写",IF(AND(OR(AM54<>"",AN54<>""),OR(AK54="",AL54="")),"违规：必须先完成第二批",IF(OR(H54<=0,H54<>INT(H54),MOD(H54,100)<>0,AND(AL54<>"",OR(AL54<=0,AL54<>INT(AL54),MOD(AL54,100)<>0)),AND(AN54<>"",OR(AN54<=0,AN54<>INT(AN54),MOD(AN54,100)<>0))),"违规：股数须为100股整数倍",IF(AND(OR(AL54<>"",AN54<>""),OR(_LockStatus="已锁仓",_LockStatus="解锁信息不完整")),"违规：锁仓期间禁止加仓",IF(AQ54>C54*D54,"违规：超过单笔风险上限",IF(SUM($AQ$2:$AQ$201)>账户数据!$B$7,"违规：超过账户风险上限","通过")))))))))
A55: 54 | B55: 双汇发展 | C55: 154282 | D55: 0.02 | E55: 21.57 | F55: =IF(OR(C55="",D55="",E55="",N55="",C55<=0,D55<=0,E55<=N55),"",ROUNDDOWN((C55*D55)/(E55-N55)/100,0)*100) | G55: =IF(A55="","",IF(H55<>"","已开仓",IF(账户数据!$B$23="已锁仓","禁止开仓：连续亏损达到上限",IF(账户数据!$B$23="解锁信息不完整","禁止开仓：请完整填写解锁信息",IF(OR(F55="",E55="",N55="",E55<=N55,账户数据!$B$7=""),"",IF(OR(AG55="",AH55="",AI55=""),"禁止开仓：交易预期未填写完整",IF(COUNTIFS(持仓跟踪!$A$2:$A$501,"止损计划",持仓跟踪!$B$2:$B$501,A55,持仓跟踪!$AC$2:$AC$501,"计划有效")=0,"禁止开仓：请先填写止损计划",IF(账户数据!$B$9+F55*(E55-N55)>=账户数据!$B$7,"禁止开仓：风险额度不足",IF(AJ55="周期与交易预期不匹配，请重新确认",IF(账户数据!$B$23="接近锁仓","允许开仓（接近锁仓；周期需复核）","允许开仓（周期需复核）"),IF(账户数据!$B$23="接近锁仓","允许开仓（接近锁仓）","允许开仓")))))))))) | H55: 1900 | I55: 44662 | J55: 24 | K55: 24.04 | L55: =IF(K55="","",H55) | M55: 44670 | N55: 20 | U55: =IF(OR(AO55="",J55="",AO55<=0),"",(J55-AO55)/AO55) | V55: =IF(OR(AO55="",N55="",AO55<=0),"",(AO55-N55)/AO55) | W55: =IF(OR(U55="",V55="",V55<=0),"",U55/V55) | X55: =IF(OR(K55="",L55="",AP55=""),"",K55*L55-(E55*H55+IF(AND(AK55<>"",AL55<>""),AK55*AL55,0)+IF(AND(AM55<>"",AN55<>""),AM55*AN55,0))-IF(O55="",0,O55)-IF(P55="",0,P55)) | Y55: =IF(OR(X55="",AP55=""),"",IF((E55*H55+IF(AND(AK55<>"",AL55<>""),AK55*AL55,0)+IF(AND(AM55<>"",AN55<>""),AM55*AN55,0))+IF(O55="",0,O55)<=0,"",X55/((E55*H55+IF(AND(AK55<>"",AL55<>""),AK55*AL55,0)+IF(AND(AM55<>"",AN55<>""),AM55*AN55,0))+IF(O55="",0,O55)))) | Z55: =IF(OR(AE55="",多次统计数据!$B$8=""),"",AE55-多次统计数据!$B$8) | AA55: =IF(OR(I55="",M55="",M55<I55),"",M55-I55) | AB55: =IF(OR(A55="",多次统计数据!$B$8="",多次统计数据!$B$6<=0,多次统计数据!$B$6>=1),"",1-POWER(1+多次统计数据!$B$8,-多次统计数据!$B$6/(1-多次统计数据!$B$6))) | AC55: =IF(OR(AB55="",多次统计数据!$B$9=""),"",IF(多次统计数据!$B$9<AB55,"低于上限","达到或超过上限")) | AE55: =IF(OR(X55="",C55="",C55<=0),"",X55/C55) | AJ55: =IF(OR(AG55="",AH55=""),"",IF(OR(AND(AG55="短期博反弹",OR(AH55="1～3个交易日",AH55="4～10个交易日")),AND(AG55="突破冲新高",OR(AH55="4～10个交易日",AH55="11～20个交易日")),AND(AG55="趋势波段",OR(AH55="11～20个交易日",AH55="21～60个交易日",AH55="60个交易日以上"))),"匹配","周期与交易预期不匹配，请重新确认")) | AO55: =IF(OR(A55="",H55="",H55<=0),"",(E55*H55+IF(AND(AK55<>"",AL55<>""),AK55*AL55,0)+IF(AND(AM55<>"",AN55<>""),AM55*AN55,0))/AP55) | AP55: =IF(OR(A55="",H55="",H55<=0),"",H55+IF(AL55="",0,AL55)+IF(AN55="",0,AN55)) | AQ55: =IF(A55="","",IF(M55<>"",0,IF(OR(H55="",N55=""),"",MAX(E55-MAX(N55,IFERROR(AGGREGATE(14,6,'持仓跟踪'!$S$2:$S$501/(('持仓跟踪'!$A$2:$A$501="每日跟踪")*('持仓跟踪'!$B$2:$B$501=A55)),1),0)),0)*H55+IF(OR(AK55="",AL55=""),0,MAX(AK55-MAX(N55,IFERROR(AGGREGATE(14,6,'持仓跟踪'!$S$2:$S$501/(('持仓跟踪'!$A$2:$A$501="每日跟踪")*('持仓跟踪'!$B$2:$B$501=A55)),1),0)),0)*AL55)+IF(OR(AM55="",AN55=""),0,MAX(AM55-MAX(N55,IFERROR(AGGREGATE(14,6,'持仓跟踪'!$S$2:$S$501/(('持仓跟踪'!$A$2:$A$501="每日跟踪")*('持仓跟踪'!$B$2:$B$501=A55)),1),0)),0)*AN55)))) | AR55: =IF(A55="","",IF(OR(E55="",H55=""),"违规：第一批价格或股数缺失",IF(OR(AND(AK55="",AL55<>""),AND(AK55<>"",AL55="")),"违规：第二批价格与股数须成对填写",IF(OR(AND(AM55="",AN55<>""),AND(AM55<>"",AN55="")),"违规：第三批价格与股数须成对填写",IF(AND(OR(AM55<>"",AN55<>""),OR(AK55="",AL55="")),"违规：必须先完成第二批",IF(OR(H55<=0,H55<>INT(H55),MOD(H55,100)<>0,AND(AL55<>"",OR(AL55<=0,AL55<>INT(AL55),MOD(AL55,100)<>0)),AND(AN55<>"",OR(AN55<=0,AN55<>INT(AN55),MOD(AN55,100)<>0))),"违规：股数须为100股整数倍",IF(AND(OR(AL55<>"",AN55<>""),OR(_LockStatus="已锁仓",_LockStatus="解锁信息不完整")),"违规：锁仓期间禁止加仓",IF(AQ55>C55*D55,"违规：超过单笔风险上限",IF(SUM($AQ$2:$AQ$201)>账户数据!$B$7,"违规：超过账户风险上限","通过")))))))))
A56: 55 | B56: 双汇发展 | C56: 158975 | D56: 0.02 | E56: 21.3 | F56: =IF(OR(C56="",D56="",E56="",N56="",C56<=0,D56<=0,E56<=N56),"",ROUNDDOWN((C56*D56)/(E56-N56)/100,0)*100) | G56: =IF(A56="","",IF(H56<>"","已开仓",IF(账户数据!$B$23="已锁仓","禁止开仓：连续亏损达到上限",IF(账户数据!$B$23="解锁信息不完整","禁止开仓：请完整填写解锁信息",IF(OR(F56="",E56="",N56="",E56<=N56,账户数据!$B$7=""),"",IF(OR(AG56="",AH56="",AI56=""),"禁止开仓：交易预期未填写完整",IF(COUNTIFS(持仓跟踪!$A$2:$A$501,"止损计划",持仓跟踪!$B$2:$B$501,A56,持仓跟踪!$AC$2:$AC$501,"计划有效")=0,"禁止开仓：请先填写止损计划",IF(账户数据!$B$9+F56*(E56-N56)>=账户数据!$B$7,"禁止开仓：风险额度不足",IF(AJ56="周期与交易预期不匹配，请重新确认",IF(账户数据!$B$23="接近锁仓","允许开仓（接近锁仓；周期需复核）","允许开仓（周期需复核）"),IF(账户数据!$B$23="接近锁仓","允许开仓（接近锁仓）","允许开仓")))))))))) | H56: 2000 | I56: 44719 | J56: 24 | K56: 20.41 | L56: =IF(K56="","",H56) | M56: 44769 | N56: 20 | U56: =IF(OR(AO56="",J56="",AO56<=0),"",(J56-AO56)/AO56) | V56: =IF(OR(AO56="",N56="",AO56<=0),"",(AO56-N56)/AO56) | W56: =IF(OR(U56="",V56="",V56<=0),"",U56/V56) | X56: =IF(OR(K56="",L56="",AP56=""),"",K56*L56-(E56*H56+IF(AND(AK56<>"",AL56<>""),AK56*AL56,0)+IF(AND(AM56<>"",AN56<>""),AM56*AN56,0))-IF(O56="",0,O56)-IF(P56="",0,P56)) | Y56: =IF(OR(X56="",AP56=""),"",IF((E56*H56+IF(AND(AK56<>"",AL56<>""),AK56*AL56,0)+IF(AND(AM56<>"",AN56<>""),AM56*AN56,0))+IF(O56="",0,O56)<=0,"",X56/((E56*H56+IF(AND(AK56<>"",AL56<>""),AK56*AL56,0)+IF(AND(AM56<>"",AN56<>""),AM56*AN56,0))+IF(O56="",0,O56)))) | Z56: =IF(OR(AE56="",多次统计数据!$B$8=""),"",AE56-多次统计数据!$B$8) | AA56: =IF(OR(I56="",M56="",M56<I56),"",M56-I56) | AB56: =IF(OR(A56="",多次统计数据!$B$8="",多次统计数据!$B$6<=0,多次统计数据!$B$6>=1),"",1-POWER(1+多次统计数据!$B$8,-多次统计数据!$B$6/(1-多次统计数据!$B$6))) | AC56: =IF(OR(AB56="",多次统计数据!$B$9=""),"",IF(多次统计数据!$B$9<AB56,"低于上限","达到或超过上限")) | AE56: =IF(OR(X56="",C56="",C56<=0),"",X56/C56) | AJ56: =IF(OR(AG56="",AH56=""),"",IF(OR(AND(AG56="短期博反弹",OR(AH56="1～3个交易日",AH56="4～10个交易日")),AND(AG56="突破冲新高",OR(AH56="4～10个交易日",AH56="11～20个交易日")),AND(AG56="趋势波段",OR(AH56="11～20个交易日",AH56="21～60个交易日",AH56="60个交易日以上"))),"匹配","周期与交易预期不匹配，请重新确认")) | AO56: =IF(OR(A56="",H56="",H56<=0),"",(E56*H56+IF(AND(AK56<>"",AL56<>""),AK56*AL56,0)+IF(AND(AM56<>"",AN56<>""),AM56*AN56,0))/AP56) | AP56: =IF(OR(A56="",H56="",H56<=0),"",H56+IF(AL56="",0,AL56)+IF(AN56="",0,AN56)) | AQ56: =IF(A56="","",IF(M56<>"",0,IF(OR(H56="",N56=""),"",MAX(E56-MAX(N56,IFERROR(AGGREGATE(14,6,'持仓跟踪'!$S$2:$S$501/(('持仓跟踪'!$A$2:$A$501="每日跟踪")*('持仓跟踪'!$B$2:$B$501=A56)),1),0)),0)*H56+IF(OR(AK56="",AL56=""),0,MAX(AK56-MAX(N56,IFERROR(AGGREGATE(14,6,'持仓跟踪'!$S$2:$S$501/(('持仓跟踪'!$A$2:$A$501="每日跟踪")*('持仓跟踪'!$B$2:$B$501=A56)),1),0)),0)*AL56)+IF(OR(AM56="",AN56=""),0,MAX(AM56-MAX(N56,IFERROR(AGGREGATE(14,6,'持仓跟踪'!$S$2:$S$501/(('持仓跟踪'!$A$2:$A$501="每日跟踪")*('持仓跟踪'!$B$2:$B$501=A56)),1),0)),0)*AN56)))) | AR56: =IF(A56="","",IF(OR(E56="",H56=""),"违规：第一批价格或股数缺失",IF(OR(AND(AK56="",AL56<>""),AND(AK56<>"",AL56="")),"违规：第二批价格与股数须成对填写",IF(OR(AND(AM56="",AN56<>""),AND(AM56<>"",AN56="")),"违规：第三批价格与股数须成对填写",IF(AND(OR(AM56<>"",AN56<>""),OR(AK56="",AL56="")),"违规：必须先完成第二批",IF(OR(H56<=0,H56<>INT(H56),MOD(H56,100)<>0,AND(AL56<>"",OR(AL56<=0,AL56<>INT(AL56),MOD(AL56,100)<>0)),AND(AN56<>"",OR(AN56<=0,AN56<>INT(AN56),MOD(AN56,100)<>0))),"违规：股数须为100股整数倍",IF(AND(OR(AL56<>"",AN56<>""),OR(_LockStatus="已锁仓",_LockStatus="解锁信息不完整")),"违规：锁仓期间禁止加仓",IF(AQ56>C56*D56,"违规：超过单笔风险上限",IF(SUM($AQ$2:$AQ$201)>账户数据!$B$7,"违规：超过账户风险上限","通过")))))))))
A57: 56 | B57: 航发动力 | C57: 157195 | D57: 0.02 | E57: 50.39 | F57: =IF(OR(C57="",D57="",E57="",N57="",C57<=0,D57<=0,E57<=N57),"",ROUNDDOWN((C57*D57)/(E57-N57)/100,0)*100) | G57: =IF(A57="","",IF(H57<>"","已开仓",IF(账户数据!$B$23="已锁仓","禁止开仓：连续亏损达到上限",IF(账户数据!$B$23="解锁信息不完整","禁止开仓：请完整填写解锁信息",IF(OR(F57="",E57="",N57="",E57<=N57,账户数据!$B$7=""),"",IF(OR(AG57="",AH57="",AI57=""),"禁止开仓：交易预期未填写完整",IF(COUNTIFS(持仓跟踪!$A$2:$A$501,"止损计划",持仓跟踪!$B$2:$B$501,A57,持仓跟踪!$AC$2:$AC$501,"计划有效")=0,"禁止开仓：请先填写止损计划",IF(账户数据!$B$9+F57*(E57-N57)>=账户数据!$B$7,"禁止开仓：风险额度不足",IF(AJ57="周期与交易预期不匹配，请重新确认",IF(账户数据!$B$23="接近锁仓","允许开仓（接近锁仓；周期需复核）","允许开仓（周期需复核）"),IF(账户数据!$B$23="接近锁仓","允许开仓（接近锁仓）","允许开仓")))))))))) | H57: 1000 | I57: 44351 | J57: 60 | K57: 55 | L57: =IF(K57="","",H57) | M57: 44356 | N57: 47.5 | U57: =IF(OR(AO57="",J57="",AO57<=0),"",(J57-AO57)/AO57) | V57: =IF(OR(AO57="",N57="",AO57<=0),"",(AO57-N57)/AO57) | W57: =IF(OR(U57="",V57="",V57<=0),"",U57/V57) | X57: =IF(OR(K57="",L57="",AP57=""),"",K57*L57-(E57*H57+IF(AND(AK57<>"",AL57<>""),AK57*AL57,0)+IF(AND(AM57<>"",AN57<>""),AM57*AN57,0))-IF(O57="",0,O57)-IF(P57="",0,P57)) | Y57: =IF(OR(X57="",AP57=""),"",IF((E57*H57+IF(AND(AK57<>"",AL57<>""),AK57*AL57,0)+IF(AND(AM57<>"",AN57<>""),AM57*AN57,0))+IF(O57="",0,O57)<=0,"",X57/((E57*H57+IF(AND(AK57<>"",AL57<>""),AK57*AL57,0)+IF(AND(AM57<>"",AN57<>""),AM57*AN57,0))+IF(O57="",0,O57)))) | Z57: =IF(OR(AE57="",多次统计数据!$B$8=""),"",AE57-多次统计数据!$B$8) | AA57: =IF(OR(I57="",M57="",M57<I57),"",M57-I57) | AB57: =IF(OR(A57="",多次统计数据!$B$8="",多次统计数据!$B$6<=0,多次统计数据!$B$6>=1),"",1-POWER(1+多次统计数据!$B$8,-多次统计数据!$B$6/(1-多次统计数据!$B$6))) | AC57: =IF(OR(AB57="",多次统计数据!$B$9=""),"",IF(多次统计数据!$B$9<AB57,"低于上限","达到或超过上限")) | AE57: =IF(OR(X57="",C57="",C57<=0),"",X57/C57) | AJ57: =IF(OR(AG57="",AH57=""),"",IF(OR(AND(AG57="短期博反弹",OR(AH57="1～3个交易日",AH57="4～10个交易日")),AND(AG57="突破冲新高",OR(AH57="4～10个交易日",AH57="11～20个交易日")),AND(AG57="趋势波段",OR(AH57="11～20个交易日",AH57="21～60个交易日",AH57="60个交易日以上"))),"匹配","周期与交易预期不匹配，请重新确认")) | AO57: =IF(OR(A57="",H57="",H57<=0),"",(E57*H57+IF(AND(AK57<>"",AL57<>""),AK57*AL57,0)+IF(AND(AM57<>"",AN57<>""),AM57*AN57,0))/AP57) | AP57: =IF(OR(A57="",H57="",H57<=0),"",H57+IF(AL57="",0,AL57)+IF(AN57="",0,AN57)) | AQ57: =IF(A57="","",IF(M57<>"",0,IF(OR(H57="",N57=""),"",MAX(E57-MAX(N57,IFERROR(AGGREGATE(14,6,'持仓跟踪'!$S$2:$S$501/(('持仓跟踪'!$A$2:$A$501="每日跟踪")*('持仓跟踪'!$B$2:$B$501=A57)),1),0)),0)*H57+IF(OR(AK57="",AL57=""),0,MAX(AK57-MAX(N57,IFERROR(AGGREGATE(14,6,'持仓跟踪'!$S$2:$S$501/(('持仓跟踪'!$A$2:$A$501="每日跟踪")*('持仓跟踪'!$B$2:$B$501=A57)),1),0)),0)*AL57)+IF(OR(AM57="",AN57=""),0,MAX(AM57-MAX(N57,IFERROR(AGGREGATE(14,6,'持仓跟踪'!$S$2:$S$501/(('持仓跟踪'!$A$2:$A$501="每日跟踪")*('持仓跟踪'!$B$2:$B$501=A57)),1),0)),0)*AN57)))) | AR57: =IF(A57="","",IF(OR(E57="",H57=""),"违规：第一批价格或股数缺失",IF(OR(AND(AK57="",AL57<>""),AND(AK57<>"",AL57="")),"违规：第二批价格与股数须成对填写",IF(OR(AND(AM57="",AN57<>""),AND(AM57<>"",AN57="")),"违规：第三批价格与股数须成对填写",IF(AND(OR(AM57<>"",AN57<>""),OR(AK57="",AL57="")),"违规：必须先完成第二批",IF(OR(H57<=0,H57<>INT(H57),MOD(H57,100)<>0,AND(AL57<>"",OR(AL57<=0,AL57<>INT(AL57),MOD(AL57,100)<>0)),AND(AN57<>"",OR(AN57<=0,AN57<>INT(AN57),MOD(AN57,100)<>0))),"违规：股数须为100股整数倍",IF(AND(OR(AL57<>"",AN57<>""),OR(_LockStatus="已锁仓",_LockStatus="解锁信息不完整")),"违规：锁仓期间禁止加仓",IF(AQ57>C57*D57,"违规：超过单笔风险上限",IF(SUM($AQ$2:$AQ$201)>账户数据!$B$7,"违规：超过账户风险上限","通过")))))))))
A58: 57 | B58: 航发动力 | C58: 161805 | D58: 0.02 | E58: 45.04 | F58: =IF(OR(C58="",D58="",E58="",N58="",C58<=0,D58<=0,E58<=N58),"",ROUNDDOWN((C58*D58)/(E58-N58)/100,0)*100) | G58: =IF(A58="","",IF(H58<>"","已开仓",IF(账户数据!$B$23="已锁仓","禁止开仓：连续亏损达到上限",IF(账户数据!$B$23="解锁信息不完整","禁止开仓：请完整填写解锁信息",IF(OR(F58="",E58="",N58="",E58<=N58,账户数据!$B$7=""),"",IF(OR(AG58="",AH58="",AI58=""),"禁止开仓：交易预期未填写完整",IF(COUNTIFS(持仓跟踪!$A$2:$A$501,"止损计划",持仓跟踪!$B$2:$B$501,A58,持仓跟踪!$AC$2:$AC$501,"计划有效")=0,"禁止开仓：请先填写止损计划",IF(账户数据!$B$9+F58*(E58-N58)>=账户数据!$B$7,"禁止开仓：风险额度不足",IF(AJ58="周期与交易预期不匹配，请重新确认",IF(账户数据!$B$23="接近锁仓","允许开仓（接近锁仓；周期需复核）","允许开仓（周期需复核）"),IF(账户数据!$B$23="接近锁仓","允许开仓（接近锁仓）","允许开仓")))))))))) | H58: 1200 | I58: 44742 | J58: 50 | K58: 49.64 | L58: =IF(K58="","",H58) | M58: 44755 | N58: 42.5 | U58: =IF(OR(AO58="",J58="",AO58<=0),"",(J58-AO58)/AO58) | V58: =IF(OR(AO58="",N58="",AO58<=0),"",(AO58-N58)/AO58) | W58: =IF(OR(U58="",V58="",V58<=0),"",U58/V58) | X58: =IF(OR(K58="",L58="",AP58=""),"",K58*L58-(E58*H58+IF(AND(AK58<>"",AL58<>""),AK58*AL58,0)+IF(AND(AM58<>"",AN58<>""),AM58*AN58,0))-IF(O58="",0,O58)-IF(P58="",0,P58)) | Y58: =IF(OR(X58="",AP58=""),"",IF((E58*H58+IF(AND(AK58<>"",AL58<>""),AK58*AL58,0)+IF(AND(AM58<>"",AN58<>""),AM58*AN58,0))+IF(O58="",0,O58)<=0,"",X58/((E58*H58+IF(AND(AK58<>"",AL58<>""),AK58*AL58,0)+IF(AND(AM58<>"",AN58<>""),AM58*AN58,0))+IF(O58="",0,O58)))) | Z58: =IF(OR(AE58="",多次统计数据!$B$8=""),"",AE58-多次统计数据!$B$8) | AA58: =IF(OR(I58="",M58="",M58<I58),"",M58-I58) | AB58: =IF(OR(A58="",多次统计数据!$B$8="",多次统计数据!$B$6<=0,多次统计数据!$B$6>=1),"",1-POWER(1+多次统计数据!$B$8,-多次统计数据!$B$6/(1-多次统计数据!$B$6))) | AC58: =IF(OR(AB58="",多次统计数据!$B$9=""),"",IF(多次统计数据!$B$9<AB58,"低于上限","达到或超过上限")) | AE58: =IF(OR(X58="",C58="",C58<=0),"",X58/C58) | AJ58: =IF(OR(AG58="",AH58=""),"",IF(OR(AND(AG58="短期博反弹",OR(AH58="1～3个交易日",AH58="4～10个交易日")),AND(AG58="突破冲新高",OR(AH58="4～10个交易日",AH58="11～20个交易日")),AND(AG58="趋势波段",OR(AH58="11～20个交易日",AH58="21～60个交易日",AH58="60个交易日以上"))),"匹配","周期与交易预期不匹配，请重新确认")) | AO58: =IF(OR(A58="",H58="",H58<=0),"",(E58*H58+IF(AND(AK58<>"",AL58<>""),AK58*AL58,0)+IF(AND(AM58<>"",AN58<>""),AM58*AN58,0))/AP58) | AP58: =IF(OR(A58="",H58="",H58<=0),"",H58+IF(AL58="",0,AL58)+IF(AN58="",0,AN58)) | AQ58: =IF(A58="","",IF(M58<>"",0,IF(OR(H58="",N58=""),"",MAX(E58-MAX(N58,IFERROR(AGGREGATE(14,6,'持仓跟踪'!$S$2:$S$501/(('持仓跟踪'!$A$2:$A$501="每日跟踪")*('持仓跟踪'!$B$2:$B$501=A58)),1),0)),0)*H58+IF(OR(AK58="",AL58=""),0,MAX(AK58-MAX(N58,IFERROR(AGGREGATE(14,6,'持仓跟踪'!$S$2:$S$501/(('持仓跟踪'!$A$2:$A$501="每日跟踪")*('持仓跟踪'!$B$2:$B$501=A58)),1),0)),0)*AL58)+IF(OR(AM58="",AN58=""),0,MAX(AM58-MAX(N58,IFERROR(AGGREGATE(14,6,'持仓跟踪'!$S$2:$S$501/(('持仓跟踪'!$A$2:$A$501="每日跟踪")*('持仓跟踪'!$B$2:$B$501=A58)),1),0)),0)*AN58)))) | AR58: =IF(A58="","",IF(OR(E58="",H58=""),"违规：第一批价格或股数缺失",IF(OR(AND(AK58="",AL58<>""),AND(AK58<>"",AL58="")),"违规：第二批价格与股数须成对填写",IF(OR(AND(AM58="",AN58<>""),AND(AM58<>"",AN58="")),"违规：第三批价格与股数须成对填写",IF(AND(OR(AM58<>"",AN58<>""),OR(AK58="",AL58="")),"违规：必须先完成第二批",IF(OR(H58<=0,H58<>INT(H58),MOD(H58,100)<>0,AND(AL58<>"",OR(AL58<=0,AL58<>INT(AL58),MOD(AL58,100)<>0)),AND(AN58<>"",OR(AN58<=0,AN58<>INT(AN58),MOD(AN58,100)<>0))),"违规：股数须为100股整数倍",IF(AND(OR(AL58<>"",AN58<>""),OR(_LockStatus="已锁仓",_LockStatus="解锁信息不完整")),"违规：锁仓期间禁止加仓",IF(AQ58>C58*D58,"违规：超过单笔风险上限",IF(SUM($AQ$2:$AQ$201)>账户数据!$B$7,"违规：超过账户风险上限","通过")))))))))
A59: 58 | B59: 航发动力 | C59: 167325 | D59: 0.02 | E59: 44.84 | F59: =IF(OR(C59="",D59="",E59="",N59="",C59<=0,D59<=0,E59<=N59),"",ROUNDDOWN((C59*D59)/(E59-N59)/100,0)*100) | G59: =IF(A59="","",IF(H59<>"","已开仓",IF(账户数据!$B$23="已锁仓","禁止开仓：连续亏损达到上限",IF(账户数据!$B$23="解锁信息不完整","禁止开仓：请完整填写解锁信息",IF(OR(F59="",E59="",N59="",E59<=N59,账户数据!$B$7=""),"",IF(OR(AG59="",AH59="",AI59=""),"禁止开仓：交易预期未填写完整",IF(COUNTIFS(持仓跟踪!$A$2:$A$501,"止损计划",持仓跟踪!$B$2:$B$501,A59,持仓跟踪!$AC$2:$AC$501,"计划有效")=0,"禁止开仓：请先填写止损计划",IF(账户数据!$B$9+F59*(E59-N59)>=账户数据!$B$7,"禁止开仓：风险额度不足",IF(AJ59="周期与交易预期不匹配，请重新确认",IF(账户数据!$B$23="接近锁仓","允许开仓（接近锁仓；周期需复核）","允许开仓（周期需复核）"),IF(账户数据!$B$23="接近锁仓","允许开仓（接近锁仓）","允许开仓")))))))))) | H59: 2400 | I59: 44966 | J59: 48.5 | K59: 45.09 | L59: =IF(K59="","",H59) | M59: 44980 | N59: 43.5 | U59: =IF(OR(AO59="",J59="",AO59<=0),"",(J59-AO59)/AO59) | V59: =IF(OR(AO59="",N59="",AO59<=0),"",(AO59-N59)/AO59) | W59: =IF(OR(U59="",V59="",V59<=0),"",U59/V59) | X59: =IF(OR(K59="",L59="",AP59=""),"",K59*L59-(E59*H59+IF(AND(AK59<>"",AL59<>""),AK59*AL59,0)+IF(AND(AM59<>"",AN59<>""),AM59*AN59,0))-IF(O59="",0,O59)-IF(P59="",0,P59)) | Y59: =IF(OR(X59="",AP59=""),"",IF((E59*H59+IF(AND(AK59<>"",AL59<>""),AK59*AL59,0)+IF(AND(AM59<>"",AN59<>""),AM59*AN59,0))+IF(O59="",0,O59)<=0,"",X59/((E59*H59+IF(AND(AK59<>"",AL59<>""),AK59*AL59,0)+IF(AND(AM59<>"",AN59<>""),AM59*AN59,0))+IF(O59="",0,O59)))) | Z59: =IF(OR(AE59="",多次统计数据!$B$8=""),"",AE59-多次统计数据!$B$8) | AA59: =IF(OR(I59="",M59="",M59<I59),"",M59-I59) | AB59: =IF(OR(A59="",多次统计数据!$B$8="",多次统计数据!$B$6<=0,多次统计数据!$B$6>=1),"",1-POWER(1+多次统计数据!$B$8,-多次统计数据!$B$6/(1-多次统计数据!$B$6))) | AC59: =IF(OR(AB59="",多次统计数据!$B$9=""),"",IF(多次统计数据!$B$9<AB59,"低于上限","达到或超过上限")) | AE59: =IF(OR(X59="",C59="",C59<=0),"",X59/C59) | AJ59: =IF(OR(AG59="",AH59=""),"",IF(OR(AND(AG59="短期博反弹",OR(AH59="1～3个交易日",AH59="4～10个交易日")),AND(AG59="突破冲新高",OR(AH59="4～10个交易日",AH59="11～20个交易日")),AND(AG59="趋势波段",OR(AH59="11～20个交易日",AH59="21～60个交易日",AH59="60个交易日以上"))),"匹配","周期与交易预期不匹配，请重新确认")) | AO59: =IF(OR(A59="",H59="",H59<=0),"",(E59*H59+IF(AND(AK59<>"",AL59<>""),AK59*AL59,0)+IF(AND(AM59<>"",AN59<>""),AM59*AN59,0))/AP59) | AP59: =IF(OR(A59="",H59="",H59<=0),"",H59+IF(AL59="",0,AL59)+IF(AN59="",0,AN59)) | AQ59: =IF(A59="","",IF(M59<>"",0,IF(OR(H59="",N59=""),"",MAX(E59-MAX(N59,IFERROR(AGGREGATE(14,6,'持仓跟踪'!$S$2:$S$501/(('持仓跟踪'!$A$2:$A$501="每日跟踪")*('持仓跟踪'!$B$2:$B$501=A59)),1),0)),0)*H59+IF(OR(AK59="",AL59=""),0,MAX(AK59-MAX(N59,IFERROR(AGGREGATE(14,6,'持仓跟踪'!$S$2:$S$501/(('持仓跟踪'!$A$2:$A$501="每日跟踪")*('持仓跟踪'!$B$2:$B$501=A59)),1),0)),0)*AL59)+IF(OR(AM59="",AN59=""),0,MAX(AM59-MAX(N59,IFERROR(AGGREGATE(14,6,'持仓跟踪'!$S$2:$S$501/(('持仓跟踪'!$A$2:$A$501="每日跟踪")*('持仓跟踪'!$B$2:$B$501=A59)),1),0)),0)*AN59)))) | AR59: =IF(A59="","",IF(OR(E59="",H59=""),"违规：第一批价格或股数缺失",IF(OR(AND(AK59="",AL59<>""),AND(AK59<>"",AL59="")),"违规：第二批价格与股数须成对填写",IF(OR(AND(AM59="",AN59<>""),AND(AM59<>"",AN59="")),"违规：第三批价格与股数须成对填写",IF(AND(OR(AM59<>"",AN59<>""),OR(AK59="",AL59="")),"违规：必须先完成第二批",IF(OR(H59<=0,H59<>INT(H59),MOD(H59,100)<>0,AND(AL59<>"",OR(AL59<=0,AL59<>INT(AL59),MOD(AL59,100)<>0)),AND(AN59<>"",OR(AN59<=0,AN59<>INT(AN59),MOD(AN59,100)<>0))),"违规：股数须为100股整数倍",IF(AND(OR(AL59<>"",AN59<>""),OR(_LockStatus="已锁仓",_LockStatus="解锁信息不完整")),"违规：锁仓期间禁止加仓",IF(AQ59>C59*D59,"违规：超过单笔风险上限",IF(SUM($AQ$2:$AQ$201)>账户数据!$B$7,"违规：超过账户风险上限","通过")))))))))
A60: 59 | B60: 航发动力 | C60: 167925 | D60: 0.02 | E60: 40.5 | F60: =IF(OR(C60="",D60="",E60="",N60="",C60<=0,D60<=0,E60<=N60),"",ROUNDDOWN((C60*D60)/(E60-N60)/100,0)*100) | G60: =IF(A60="","",IF(H60<>"","已开仓",IF(账户数据!$B$23="已锁仓","禁止开仓：连续亏损达到上限",IF(账户数据!$B$23="解锁信息不完整","禁止开仓：请完整填写解锁信息",IF(OR(F60="",E60="",N60="",E60<=N60,账户数据!$B$7=""),"",IF(OR(AG60="",AH60="",AI60=""),"禁止开仓：交易预期未填写完整",IF(COUNTIFS(持仓跟踪!$A$2:$A$501,"止损计划",持仓跟踪!$B$2:$B$501,A60,持仓跟踪!$AC$2:$AC$501,"计划有效")=0,"禁止开仓：请先填写止损计划",IF(账户数据!$B$9+F60*(E60-N60)>=账户数据!$B$7,"禁止开仓：风险额度不足",IF(AJ60="周期与交易预期不匹配，请重新确认",IF(账户数据!$B$23="接近锁仓","允许开仓（接近锁仓；周期需复核）","允许开仓（周期需复核）"),IF(账户数据!$B$23="接近锁仓","允许开仓（接近锁仓）","允许开仓")))))))))) | H60: 1600 | I60: 45104 | J60: 42.5 | K60: 42.23 | L60: =IF(K60="","",H60) | M60: 45112 | N60: 38.5 | U60: =IF(OR(AO60="",J60="",AO60<=0),"",(J60-AO60)/AO60) | V60: =IF(OR(AO60="",N60="",AO60<=0),"",(AO60-N60)/AO60) | W60: =IF(OR(U60="",V60="",V60<=0),"",U60/V60) | X60: =IF(OR(K60="",L60="",AP60=""),"",K60*L60-(E60*H60+IF(AND(AK60<>"",AL60<>""),AK60*AL60,0)+IF(AND(AM60<>"",AN60<>""),AM60*AN60,0))-IF(O60="",0,O60)-IF(P60="",0,P60)) | Y60: =IF(OR(X60="",AP60=""),"",IF((E60*H60+IF(AND(AK60<>"",AL60<>""),AK60*AL60,0)+IF(AND(AM60<>"",AN60<>""),AM60*AN60,0))+IF(O60="",0,O60)<=0,"",X60/((E60*H60+IF(AND(AK60<>"",AL60<>""),AK60*AL60,0)+IF(AND(AM60<>"",AN60<>""),AM60*AN60,0))+IF(O60="",0,O60)))) | Z60: =IF(OR(AE60="",多次统计数据!$B$8=""),"",AE60-多次统计数据!$B$8) | AA60: =IF(OR(I60="",M60="",M60<I60),"",M60-I60) | AB60: =IF(OR(A60="",多次统计数据!$B$8="",多次统计数据!$B$6<=0,多次统计数据!$B$6>=1),"",1-POWER(1+多次统计数据!$B$8,-多次统计数据!$B$6/(1-多次统计数据!$B$6))) | AC60: =IF(OR(AB60="",多次统计数据!$B$9=""),"",IF(多次统计数据!$B$9<AB60,"低于上限","达到或超过上限")) | AE60: =IF(OR(X60="",C60="",C60<=0),"",X60/C60) | AJ60: =IF(OR(AG60="",AH60=""),"",IF(OR(AND(AG60="短期博反弹",OR(AH60="1～3个交易日",AH60="4～10个交易日")),AND(AG60="突破冲新高",OR(AH60="4～10个交易日",AH60="11～20个交易日")),AND(AG60="趋势波段",OR(AH60="11～20个交易日",AH60="21～60个交易日",AH60="60个交易日以上"))),"匹配","周期与交易预期不匹配，请重新确认")) | AO60: =IF(OR(A60="",H60="",H60<=0),"",(E60*H60+IF(AND(AK60<>"",AL60<>""),AK60*AL60,0)+IF(AND(AM60<>"",AN60<>""),AM60*AN60,0))/AP60) | AP60: =IF(OR(A60="",H60="",H60<=0),"",H60+IF(AL60="",0,AL60)+IF(AN60="",0,AN60)) | AQ60: =IF(A60="","",IF(M60<>"",0,IF(OR(H60="",N60=""),"",MAX(E60-MAX(N60,IFERROR(AGGREGATE(14,6,'持仓跟踪'!$S$2:$S$501/(('持仓跟踪'!$A$2:$A$501="每日跟踪")*('持仓跟踪'!$B$2:$B$501=A60)),1),0)),0)*H60+IF(OR(AK60="",AL60=""),0,MAX(AK60-MAX(N60,IFERROR(AGGREGATE(14,6,'持仓跟踪'!$S$2:$S$501/(('持仓跟踪'!$A$2:$A$501="每日跟踪")*('持仓跟踪'!$B$2:$B$501=A60)),1),0)),0)*AL60)+IF(OR(AM60="",AN60=""),0,MAX(AM60-MAX(N60,IFERROR(AGGREGATE(14,6,'持仓跟踪'!$S$2:$S$501/(('持仓跟踪'!$A$2:$A$501="每日跟踪")*('持仓跟踪'!$B$2:$B$501=A60)),1),0)),0)*AN60)))) | AR60: =IF(A60="","",IF(OR(E60="",H60=""),"违规：第一批价格或股数缺失",IF(OR(AND(AK60="",AL60<>""),AND(AK60<>"",AL60="")),"违规：第二批价格与股数须成对填写",IF(OR(AND(AM60="",AN60<>""),AND(AM60<>"",AN60="")),"违规：第三批价格与股数须成对填写",IF(AND(OR(AM60<>"",AN60<>""),OR(AK60="",AL60="")),"违规：必须先完成第二批",IF(OR(H60<=0,H60<>INT(H60),MOD(H60,100)<>0,AND(AL60<>"",OR(AL60<=0,AL60<>INT(AL60),MOD(AL60,100)<>0)),AND(AN60<>"",OR(AN60<=0,AN60<>INT(AN60),MOD(AN60,100)<>0))),"违规：股数须为100股整数倍",IF(AND(OR(AL60<>"",AN60<>""),OR(_LockStatus="已锁仓",_LockStatus="解锁信息不完整")),"违规：锁仓期间禁止加仓",IF(AQ60>C60*D60,"违规：超过单笔风险上限",IF(SUM($AQ$2:$AQ$201)>账户数据!$B$7,"违规：超过账户风险上限","通过")))))))))
A61: 60 | B61: 航发动力 | C61: 170693 | D61: 0.02 | E61: 38.09 | F61: =IF(OR(C61="",D61="",E61="",N61="",C61<=0,D61<=0,E61<=N61),"",ROUNDDOWN((C61*D61)/(E61-N61)/100,0)*100) | G61: =IF(A61="","",IF(H61<>"","已开仓",IF(账户数据!$B$23="已锁仓","禁止开仓：连续亏损达到上限",IF(账户数据!$B$23="解锁信息不完整","禁止开仓：请完整填写解锁信息",IF(OR(F61="",E61="",N61="",E61<=N61,账户数据!$B$7=""),"",IF(OR(AG61="",AH61="",AI61=""),"禁止开仓：交易预期未填写完整",IF(COUNTIFS(持仓跟踪!$A$2:$A$501,"止损计划",持仓跟踪!$B$2:$B$501,A61,持仓跟踪!$AC$2:$AC$501,"计划有效")=0,"禁止开仓：请先填写止损计划",IF(账户数据!$B$9+F61*(E61-N61)>=账户数据!$B$7,"禁止开仓：风险额度不足",IF(AJ61="周期与交易预期不匹配，请重新确认",IF(账户数据!$B$23="接近锁仓","允许开仓（接近锁仓；周期需复核）","允许开仓（周期需复核）"),IF(账户数据!$B$23="接近锁仓","允许开仓（接近锁仓）","允许开仓")))))))))) | H61: 1500 | I61: 45162 | J61: 40 | K61: 37.47 | L61: =IF(K61="","",H61) | M61: 45166 | N61: 37 | U61: =IF(OR(AO61="",J61="",AO61<=0),"",(J61-AO61)/AO61) | V61: =IF(OR(AO61="",N61="",AO61<=0),"",(AO61-N61)/AO61) | W61: =IF(OR(U61="",V61="",V61<=0),"",U61/V61) | X61: =IF(OR(K61="",L61="",AP61=""),"",K61*L61-(E61*H61+IF(AND(AK61<>"",AL61<>""),AK61*AL61,0)+IF(AND(AM61<>"",AN61<>""),AM61*AN61,0))-IF(O61="",0,O61)-IF(P61="",0,P61)) | Y61: =IF(OR(X61="",AP61=""),"",IF((E61*H61+IF(AND(AK61<>"",AL61<>""),AK61*AL61,0)+IF(AND(AM61<>"",AN61<>""),AM61*AN61,0))+IF(O61="",0,O61)<=0,"",X61/((E61*H61+IF(AND(AK61<>"",AL61<>""),AK61*AL61,0)+IF(AND(AM61<>"",AN61<>""),AM61*AN61,0))+IF(O61="",0,O61)))) | Z61: =IF(OR(AE61="",多次统计数据!$B$8=""),"",AE61-多次统计数据!$B$8) | AA61: =IF(OR(I61="",M61="",M61<I61),"",M61-I61) | AB61: =IF(OR(A61="",多次统计数据!$B$8="",多次统计数据!$B$6<=0,多次统计数据!$B$6>=1),"",1-POWER(1+多次统计数据!$B$8,-多次统计数据!$B$6/(1-多次统计数据!$B$6))) | AC61: =IF(OR(AB61="",多次统计数据!$B$9=""),"",IF(多次统计数据!$B$9<AB61,"低于上限","达到或超过上限")) | AE61: =IF(OR(X61="",C61="",C61<=0),"",X61/C61) | AJ61: =IF(OR(AG61="",AH61=""),"",IF(OR(AND(AG61="短期博反弹",OR(AH61="1～3个交易日",AH61="4～10个交易日")),AND(AG61="突破冲新高",OR(AH61="4～10个交易日",AH61="11～20个交易日")),AND(AG61="趋势波段",OR(AH61="11～20个交易日",AH61="21～60个交易日",AH61="60个交易日以上"))),"匹配","周期与交易预期不匹配，请重新确认")) | AO61: =IF(OR(A61="",H61="",H61<=0),"",(E61*H61+IF(AND(AK61<>"",AL61<>""),AK61*AL61,0)+IF(AND(AM61<>"",AN61<>""),AM61*AN61,0))/AP61) | AP61: =IF(OR(A61="",H61="",H61<=0),"",H61+IF(AL61="",0,AL61)+IF(AN61="",0,AN61)) | AQ61: =IF(A61="","",IF(M61<>"",0,IF(OR(H61="",N61=""),"",MAX(E61-MAX(N61,IFERROR(AGGREGATE(14,6,'持仓跟踪'!$S$2:$S$501/(('持仓跟踪'!$A$2:$A$501="每日跟踪")*('持仓跟踪'!$B$2:$B$501=A61)),1),0)),0)*H61+IF(OR(AK61="",AL61=""),0,MAX(AK61-MAX(N61,IFERROR(AGGREGATE(14,6,'持仓跟踪'!$S$2:$S$501/(('持仓跟踪'!$A$2:$A$501="每日跟踪")*('持仓跟踪'!$B$2:$B$501=A61)),1),0)),0)*AL61)+IF(OR(AM61="",AN61=""),0,MAX(AM61-MAX(N61,IFERROR(AGGREGATE(14,6,'持仓跟踪'!$S$2:$S$501/(('持仓跟踪'!$A$2:$A$501="每日跟踪")*('持仓跟踪'!$B$2:$B$501=A61)),1),0)),0)*AN61)))) | AR61: =IF(A61="","",IF(OR(E61="",H61=""),"违规：第一批价格或股数缺失",IF(OR(AND(AK61="",AL61<>""),AND(AK61<>"",AL61="")),"违规：第二批价格与股数须成对填写",IF(OR(AND(AM61="",AN61<>""),AND(AM61<>"",AN61="")),"违规：第三批价格与股数须成对填写",IF(AND(OR(AM61<>"",AN61<>""),OR(AK61="",AL61="")),"违规：必须先完成第二批",IF(OR(H61<=0,H61<>INT(H61),MOD(H61,100)<>0,AND(AL61<>"",OR(AL61<=0,AL61<>INT(AL61),MOD(AL61,100)<>0)),AND(AN61<>"",OR(AN61<=0,AN61<>INT(AN61),MOD(AN61,100)<>0))),"违规：股数须为100股整数倍",IF(AND(OR(AL61<>"",AN61<>""),OR(_LockStatus="已锁仓",_LockStatus="解锁信息不完整")),"违规：锁仓期间禁止加仓",IF(AQ61>C61*D61,"违规：超过单笔风险上限",IF(SUM($AQ$2:$AQ$201)>账户数据!$B$7,"违规：超过账户风险上限","通过")))))))))
A62: 61 | B62: 航发动力 | C62: 169763 | D62: 0.02 | E62: 31.73 | F62: =IF(OR(C62="",D62="",E62="",N62="",C62<=0,D62<=0,E62<=N62),"",ROUNDDOWN((C62*D62)/(E62-N62)/100,0)*100) | G62: =IF(A62="","",IF(H62<>"","已开仓",IF(账户数据!$B$23="已锁仓","禁止开仓：连续亏损达到上限",IF(账户数据!$B$23="解锁信息不完整","禁止开仓：请完整填写解锁信息",IF(OR(F62="",E62="",N62="",E62<=N62,账户数据!$B$7=""),"",IF(OR(AG62="",AH62="",AI62=""),"禁止开仓：交易预期未填写完整",IF(COUNTIFS(持仓跟踪!$A$2:$A$501,"止损计划",持仓跟踪!$B$2:$B$501,A62,持仓跟踪!$AC$2:$AC$501,"计划有效")=0,"禁止开仓：请先填写止损计划",IF(账户数据!$B$9+F62*(E62-N62)>=账户数据!$B$7,"禁止开仓：风险额度不足",IF(AJ62="周期与交易预期不匹配，请重新确认",IF(账户数据!$B$23="接近锁仓","允许开仓（接近锁仓；周期需复核）","允许开仓（周期需复核）"),IF(账户数据!$B$23="接近锁仓","允许开仓（接近锁仓）","允许开仓")))))))))) | H62: 1900 | I62: 45313 | J62: 35 | K62: 29.67 | L62: =IF(K62="","",H62) | M62: 45324 | N62: 30 | U62: =IF(OR(AO62="",J62="",AO62<=0),"",(J62-AO62)/AO62) | V62: =IF(OR(AO62="",N62="",AO62<=0),"",(AO62-N62)/AO62) | W62: =IF(OR(U62="",V62="",V62<=0),"",U62/V62) | X62: =IF(OR(K62="",L62="",AP62=""),"",K62*L62-(E62*H62+IF(AND(AK62<>"",AL62<>""),AK62*AL62,0)+IF(AND(AM62<>"",AN62<>""),AM62*AN62,0))-IF(O62="",0,O62)-IF(P62="",0,P62)) | Y62: =IF(OR(X62="",AP62=""),"",IF((E62*H62+IF(AND(AK62<>"",AL62<>""),AK62*AL62,0)+IF(AND(AM62<>"",AN62<>""),AM62*AN62,0))+IF(O62="",0,O62)<=0,"",X62/((E62*H62+IF(AND(AK62<>"",AL62<>""),AK62*AL62,0)+IF(AND(AM62<>"",AN62<>""),AM62*AN62,0))+IF(O62="",0,O62)))) | Z62: =IF(OR(AE62="",多次统计数据!$B$8=""),"",AE62-多次统计数据!$B$8) | AA62: =IF(OR(I62="",M62="",M62<I62),"",M62-I62) | AB62: =IF(OR(A62="",多次统计数据!$B$8="",多次统计数据!$B$6<=0,多次统计数据!$B$6>=1),"",1-POWER(1+多次统计数据!$B$8,-多次统计数据!$B$6/(1-多次统计数据!$B$6))) | AC62: =IF(OR(AB62="",多次统计数据!$B$9=""),"",IF(多次统计数据!$B$9<AB62,"低于上限","达到或超过上限")) | AE62: =IF(OR(X62="",C62="",C62<=0),"",X62/C62) | AF62: 别贪，这是低点反弹 | AJ62: =IF(OR(AG62="",AH62=""),"",IF(OR(AND(AG62="短期博反弹",OR(AH62="1～3个交易日",AH62="4～10个交易日")),AND(AG62="突破冲新高",OR(AH62="4～10个交易日",AH62="11～20个交易日")),AND(AG62="趋势波段",OR(AH62="11～20个交易日",AH62="21～60个交易日",AH62="60个交易日以上"))),"匹配","周期与交易预期不匹配，请重新确认")) | AO62: =IF(OR(A62="",H62="",H62<=0),"",(E62*H62+IF(AND(AK62<>"",AL62<>""),AK62*AL62,0)+IF(AND(AM62<>"",AN62<>""),AM62*AN62,0))/AP62) | AP62: =IF(OR(A62="",H62="",H62<=0),"",H62+IF(AL62="",0,AL62)+IF(AN62="",0,AN62)) | AQ62: =IF(A62="","",IF(M62<>"",0,IF(OR(H62="",N62=""),"",MAX(E62-MAX(N62,IFERROR(AGGREGATE(14,6,'持仓跟踪'!$S$2:$S$501/(('持仓跟踪'!$A$2:$A$501="每日跟踪")*('持仓跟踪'!$B$2:$B$501=A62)),1),0)),0)*H62+IF(OR(AK62="",AL62=""),0,MAX(AK62-MAX(N62,IFERROR(AGGREGATE(14,6,'持仓跟踪'!$S$2:$S$501/(('持仓跟踪'!$A$2:$A$501="每日跟踪")*('持仓跟踪'!$B$2:$B$501=A62)),1),0)),0)*AL62)+IF(OR(AM62="",AN62=""),0,MAX(AM62-MAX(N62,IFERROR(AGGREGATE(14,6,'持仓跟踪'!$S$2:$S$501/(('持仓跟踪'!$A$2:$A$501="每日跟踪")*('持仓跟踪'!$B$2:$B$501=A62)),1),0)),0)*AN62)))) | AR62: =IF(A62="","",IF(OR(E62="",H62=""),"违规：第一批价格或股数缺失",IF(OR(AND(AK62="",AL62<>""),AND(AK62<>"",AL62="")),"违规：第二批价格与股数须成对填写",IF(OR(AND(AM62="",AN62<>""),AND(AM62<>"",AN62="")),"违规：第三批价格与股数须成对填写",IF(AND(OR(AM62<>"",AN62<>""),OR(AK62="",AL62="")),"违规：必须先完成第二批",IF(OR(H62<=0,H62<>INT(H62),MOD(H62,100)<>0,AND(AL62<>"",OR(AL62<=0,AL62<>INT(AL62),MOD(AL62,100)<>0)),AND(AN62<>"",OR(AN62<=0,AN62<>INT(AN62),MOD(AN62,100)<>0))),"违规：股数须为100股整数倍",IF(AND(OR(AL62<>"",AN62<>""),OR(_LockStatus="已锁仓",_LockStatus="解锁信息不完整")),"违规：锁仓期间禁止加仓",IF(AQ62>C62*D62,"违规：超过单笔风险上限",IF(SUM($AQ$2:$AQ$201)>账户数据!$B$7,"违规：超过账户风险上限","通过")))))))))
A63: 62 | B63: 航发动力 | C63: 165849 | D63: 0.02 | E63: 36.33 | F63: =IF(OR(C63="",D63="",E63="",N63="",C63<=0,D63<=0,E63<=N63),"",ROUNDDOWN((C63*D63)/(E63-N63)/100,0)*100) | G63: =IF(A63="","",IF(H63<>"","已开仓",IF(账户数据!$B$23="已锁仓","禁止开仓：连续亏损达到上限",IF(账户数据!$B$23="解锁信息不完整","禁止开仓：请完整填写解锁信息",IF(OR(F63="",E63="",N63="",E63<=N63,账户数据!$B$7=""),"",IF(OR(AG63="",AH63="",AI63=""),"禁止开仓：交易预期未填写完整",IF(COUNTIFS(持仓跟踪!$A$2:$A$501,"止损计划",持仓跟踪!$B$2:$B$501,A63,持仓跟踪!$AC$2:$AC$501,"计划有效")=0,"禁止开仓：请先填写止损计划",IF(账户数据!$B$9+F63*(E63-N63)>=账户数据!$B$7,"禁止开仓：风险额度不足",IF(AJ63="周期与交易预期不匹配，请重新确认",IF(账户数据!$B$23="接近锁仓","允许开仓（接近锁仓；周期需复核）","允许开仓（周期需复核）"),IF(账户数据!$B$23="接近锁仓","允许开仓（接近锁仓）","允许开仓")))))))))) | H63: 1900 | I63: 45429 | J63: 38 | K63: 35.05 | L63: =IF(K63="","",H63) | M63: 45435 | N63: 35.5 | U63: =IF(OR(AO63="",J63="",AO63<=0),"",(J63-AO63)/AO63) | V63: =IF(OR(AO63="",N63="",AO63<=0),"",(AO63-N63)/AO63) | W63: =IF(OR(U63="",V63="",V63<=0),"",U63/V63) | X63: =IF(OR(K63="",L63="",AP63=""),"",K63*L63-(E63*H63+IF(AND(AK63<>"",AL63<>""),AK63*AL63,0)+IF(AND(AM63<>"",AN63<>""),AM63*AN63,0))-IF(O63="",0,O63)-IF(P63="",0,P63)) | Y63: =IF(OR(X63="",AP63=""),"",IF((E63*H63+IF(AND(AK63<>"",AL63<>""),AK63*AL63,0)+IF(AND(AM63<>"",AN63<>""),AM63*AN63,0))+IF(O63="",0,O63)<=0,"",X63/((E63*H63+IF(AND(AK63<>"",AL63<>""),AK63*AL63,0)+IF(AND(AM63<>"",AN63<>""),AM63*AN63,0))+IF(O63="",0,O63)))) | Z63: =IF(OR(AE63="",多次统计数据!$B$8=""),"",AE63-多次统计数据!$B$8) | AA63: =IF(OR(I63="",M63="",M63<I63),"",M63-I63) | AB63: =IF(OR(A63="",多次统计数据!$B$8="",多次统计数据!$B$6<=0,多次统计数据!$B$6>=1),"",1-POWER(1+多次统计数据!$B$8,-多次统计数据!$B$6/(1-多次统计数据!$B$6))) | AC63: =IF(OR(AB63="",多次统计数据!$B$9=""),"",IF(多次统计数据!$B$9<AB63,"低于上限","达到或超过上限")) | AE63: =IF(OR(X63="",C63="",C63<=0),"",X63/C63) | AJ63: =IF(OR(AG63="",AH63=""),"",IF(OR(AND(AG63="短期博反弹",OR(AH63="1～3个交易日",AH63="4～10个交易日")),AND(AG63="突破冲新高",OR(AH63="4～10个交易日",AH63="11～20个交易日")),AND(AG63="趋势波段",OR(AH63="11～20个交易日",AH63="21～60个交易日",AH63="60个交易日以上"))),"匹配","周期与交易预期不匹配，请重新确认")) | AO63: =IF(OR(A63="",H63="",H63<=0),"",(E63*H63+IF(AND(AK63<>"",AL63<>""),AK63*AL63,0)+IF(AND(AM63<>"",AN63<>""),AM63*AN63,0))/AP63) | AP63: =IF(OR(A63="",H63="",H63<=0),"",H63+IF(AL63="",0,AL63)+IF(AN63="",0,AN63)) | AQ63: =IF(A63="","",IF(M63<>"",0,IF(OR(H63="",N63=""),"",MAX(E63-MAX(N63,IFERROR(AGGREGATE(14,6,'持仓跟踪'!$S$2:$S$501/(('持仓跟踪'!$A$2:$A$501="每日跟踪")*('持仓跟踪'!$B$2:$B$501=A63)),1),0)),0)*H63+IF(OR(AK63="",AL63=""),0,MAX(AK63-MAX(N63,IFERROR(AGGREGATE(14,6,'持仓跟踪'!$S$2:$S$501/(('持仓跟踪'!$A$2:$A$501="每日跟踪")*('持仓跟踪'!$B$2:$B$501=A63)),1),0)),0)*AL63)+IF(OR(AM63="",AN63=""),0,MAX(AM63-MAX(N63,IFERROR(AGGREGATE(14,6,'持仓跟踪'!$S$2:$S$501/(('持仓跟踪'!$A$2:$A$501="每日跟踪")*('持仓跟踪'!$B$2:$B$501=A63)),1),0)),0)*AN63)))) | AR63: =IF(A63="","",IF(OR(E63="",H63=""),"违规：第一批价格或股数缺失",IF(OR(AND(AK63="",AL63<>""),AND(AK63<>"",AL63="")),"违规：第二批价格与股数须成对填写",IF(OR(AND(AM63="",AN63<>""),AND(AM63<>"",AN63="")),"违规：第三批价格与股数须成对填写",IF(AND(OR(AM63<>"",AN63<>""),OR(AK63="",AL63="")),"违规：必须先完成第二批",IF(OR(H63<=0,H63<>INT(H63),MOD(H63,100)<>0,AND(AL63<>"",OR(AL63<=0,AL63<>INT(AL63),MOD(AL63,100)<>0)),AND(AN63<>"",OR(AN63<=0,AN63<>INT(AN63),MOD(AN63,100)<>0))),"违规：股数须为100股整数倍",IF(AND(OR(AL63<>"",AN63<>""),OR(_LockStatus="已锁仓",_LockStatus="解锁信息不完整")),"违规：锁仓期间禁止加仓",IF(AQ63>C63*D63,"违规：超过单笔风险上限",IF(SUM($AQ$2:$AQ$201)>账户数据!$B$7,"违规：超过账户风险上限","通过")))))))))
A64: 63 | B64: 航发动力 | C64: 163417 | D64: 0.02 | E64: 35 | F64: =IF(OR(C64="",D64="",E64="",N64="",C64<=0,D64<=0,E64<=N64),"",ROUNDDOWN((C64*D64)/(E64-N64)/100,0)*100) | G64: =IF(A64="","",IF(H64<>"","已开仓",IF(账户数据!$B$23="已锁仓","禁止开仓：连续亏损达到上限",IF(账户数据!$B$23="解锁信息不完整","禁止开仓：请完整填写解锁信息",IF(OR(F64="",E64="",N64="",E64<=N64,账户数据!$B$7=""),"",IF(OR(AG64="",AH64="",AI64=""),"禁止开仓：交易预期未填写完整",IF(COUNTIFS(持仓跟踪!$A$2:$A$501,"止损计划",持仓跟踪!$B$2:$B$501,A64,持仓跟踪!$AC$2:$AC$501,"计划有效")=0,"禁止开仓：请先填写止损计划",IF(账户数据!$B$9+F64*(E64-N64)>=账户数据!$B$7,"禁止开仓：风险额度不足",IF(AJ64="周期与交易预期不匹配，请重新确认",IF(账户数据!$B$23="接近锁仓","允许开仓（接近锁仓；周期需复核）","允许开仓（周期需复核）"),IF(账户数据!$B$23="接近锁仓","允许开仓（接近锁仓）","允许开仓")))))))))) | H64: 1600 | I64: 45785 | J64: 37 | K64: 41.19 | L64: =IF(K64="","",H64) | M64: 45870 | N64: 33 | U64: =IF(OR(AO64="",J64="",AO64<=0),"",(J64-AO64)/AO64) | V64: =IF(OR(AO64="",N64="",AO64<=0),"",(AO64-N64)/AO64) | W64: =IF(OR(U64="",V64="",V64<=0),"",U64/V64) | X64: =IF(OR(K64="",L64="",AP64=""),"",K64*L64-(E64*H64+IF(AND(AK64<>"",AL64<>""),AK64*AL64,0)+IF(AND(AM64<>"",AN64<>""),AM64*AN64,0))-IF(O64="",0,O64)-IF(P64="",0,P64)) | Y64: =IF(OR(X64="",AP64=""),"",IF((E64*H64+IF(AND(AK64<>"",AL64<>""),AK64*AL64,0)+IF(AND(AM64<>"",AN64<>""),AM64*AN64,0))+IF(O64="",0,O64)<=0,"",X64/((E64*H64+IF(AND(AK64<>"",AL64<>""),AK64*AL64,0)+IF(AND(AM64<>"",AN64<>""),AM64*AN64,0))+IF(O64="",0,O64)))) | Z64: =IF(OR(AE64="",多次统计数据!$B$8=""),"",AE64-多次统计数据!$B$8) | AA64: =IF(OR(I64="",M64="",M64<I64),"",M64-I64) | AB64: =IF(OR(A64="",多次统计数据!$B$8="",多次统计数据!$B$6<=0,多次统计数据!$B$6>=1),"",1-POWER(1+多次统计数据!$B$8,-多次统计数据!$B$6/(1-多次统计数据!$B$6))) | AC64: =IF(OR(AB64="",多次统计数据!$B$9=""),"",IF(多次统计数据!$B$9<AB64,"低于上限","达到或超过上限")) | AE64: =IF(OR(X64="",C64="",C64<=0),"",X64/C64) | AJ64: =IF(OR(AG64="",AH64=""),"",IF(OR(AND(AG64="短期博反弹",OR(AH64="1～3个交易日",AH64="4～10个交易日")),AND(AG64="突破冲新高",OR(AH64="4～10个交易日",AH64="11～20个交易日")),AND(AG64="趋势波段",OR(AH64="11～20个交易日",AH64="21～60个交易日",AH64="60个交易日以上"))),"匹配","周期与交易预期不匹配，请重新确认")) | AO64: =IF(OR(A64="",H64="",H64<=0),"",(E64*H64+IF(AND(AK64<>"",AL64<>""),AK64*AL64,0)+IF(AND(AM64<>"",AN64<>""),AM64*AN64,0))/AP64) | AP64: =IF(OR(A64="",H64="",H64<=0),"",H64+IF(AL64="",0,AL64)+IF(AN64="",0,AN64)) | AQ64: =IF(A64="","",IF(M64<>"",0,IF(OR(H64="",N64=""),"",MAX(E64-MAX(N64,IFERROR(AGGREGATE(14,6,'持仓跟踪'!$S$2:$S$501/(('持仓跟踪'!$A$2:$A$501="每日跟踪")*('持仓跟踪'!$B$2:$B$501=A64)),1),0)),0)*H64+IF(OR(AK64="",AL64=""),0,MAX(AK64-MAX(N64,IFERROR(AGGREGATE(14,6,'持仓跟踪'!$S$2:$S$501/(('持仓跟踪'!$A$2:$A$501="每日跟踪")*('持仓跟踪'!$B$2:$B$501=A64)),1),0)),0)*AL64)+IF(OR(AM64="",AN64=""),0,MAX(AM64-MAX(N64,IFERROR(AGGREGATE(14,6,'持仓跟踪'!$S$2:$S$501/(('持仓跟踪'!$A$2:$A$501="每日跟踪")*('持仓跟踪'!$B$2:$B$501=A64)),1),0)),0)*AN64)))) | AR64: =IF(A64="","",IF(OR(E64="",H64=""),"违规：第一批价格或股数缺失",IF(OR(AND(AK64="",AL64<>""),AND(AK64<>"",AL64="")),"违规：第二批价格与股数须成对填写",IF(OR(AND(AM64="",AN64<>""),AND(AM64<>"",AN64="")),"违规：第三批价格与股数须成对填写",IF(AND(OR(AM64<>"",AN64<>""),OR(AK64="",AL64="")),"违规：必须先完成第二批",IF(OR(H64<=0,H64<>INT(H64),MOD(H64,100)<>0,AND(AL64<>"",OR(AL64<=0,AL64<>INT(AL64),MOD(AL64,100)<>0)),AND(AN64<>"",OR(AN64<=0,AN64<>INT(AN64),MOD(AN64,100)<>0))),"违规：股数须为100股整数倍",IF(AND(OR(AL64<>"",AN64<>""),OR(_LockStatus="已锁仓",_LockStatus="解锁信息不完整")),"违规：锁仓期间禁止加仓",IF(AQ64>C64*D64,"违规：超过单笔风险上限",IF(SUM($AQ$2:$AQ$201)>账户数据!$B$7,"违规：超过账户风险上限","通过")))))))))
