Workbook

Sheet 单次交易
A1: 交易编号 | B1: 股票代码 | C1: 买入时账户金额 | D1: 本次允许亏损比例 | E1: 买入价 | F1: 买入建议股数 | G1: 开仓风险告警 | H1: 实际买入股数 | I1: 买入日期 | J1: 期望卖出价 | K1: 实际卖出价 | L1: 卖出股数 | M1: 卖出日期 | N1: 止损价 | O1: 买入费用 | P1: 卖出费用 | Q1: 买入价的由来 | R1: 止损价的由来 | S1: 期望卖出价的由来 | T1: 实际卖出价的由来 | U1: 期望盈利比例 | V1: 期望止损比例 | W1: 盈亏比 | X1: 实际盈亏金额 | Y1: 实际收益率 | Z1: 与平均盈利比例差值 | AA1: 持有天数 | AB1: 复利容许平均亏损上限 | AC1: 复利风险判断 | AD1: 交易打分评价
A2: T2026001 | B2: 600519 | C2: 100000 | D2: 0.01 | E2: 11.25 | F2: =IF(OR(C2="",D2="",E2="",N2="",C2<=0,D2<=0,E2<=N2),"",ROUNDDOWN((C2*D2)/(E2-N2)/100,0)*100) -> 1000 | G2: =IF(OR(A2="",F2="",E2="",N2="",E2<=N2,账户数据!$B$7=""),"",IF(账户数据!$B$9+IF(H2="",F2*(E2-N2),0)>=账户数据!$B$7,"禁止开仓","允许开仓")) -> 禁止开仓 | H2: 200 | I2: 46128 | J2: 12.38 | K2: 12.71 | L2: =IF(K2="","",H2) -> 200 | M2: 46130 | N2: 10.25 | O2: 5 | P2: 5 | Q2: 蜡烛图与RSI共同确认 | R2: 止损设在10.25 | S2: 目标参考缺口 | T2: 按计划成交 | U2: =IF(OR(E2="",J2="",E2<=0),"",(J2-E2)/E2) -> 0.10044444 | V2: =IF(OR(E2="",N2="",E2<=0),"",(E2-N2)/E2) -> 0.088888889 | W2: =IF(OR(U2="",V2="",V2<=0),"",U2/V2) -> 1.13 | X2: =IF(OR(K2="",L2="",E2="",H2=""),"",K2*L2-E2*H2-IF(O2="",0,O2)-IF(P2="",0,P2)) -> 282 | Y2: =IF(OR(X2="",E2="",H2=""),"",IF(E2*H2+IF(O2="",0,O2)<=0,"",X2/(E2*H2+IF(O2="",0,O2)))) -> 0.12505543 | Z2: =IF(OR(Y2="",多次统计数据!$B$8=""),"",Y2-多次统计数据!$B$8) -> -0.0030756577 | AA2: =IF(OR(I2="",M2="",M2<I2),"",M2-I2) -> 2 | AB2: =IF(OR(A2="",多次统计数据!$B$8="",多次统计数据!$B$6<=0,多次统计数据!$B$6>=1),"",1-POWER(1+多次统计数据!$B$8,-多次统计数据!$B$6/(1-多次统计数据!$B$6))) -> 0.11918507 | AC2: =IF(OR(AB2="",多次统计数据!$B$9=""),"",IF(多次统计数据!$B$9<AB2,"低于上限","达到或超过上限")) -> 低于上限 | AD2: 4-良好
A3: T2026002 | B3: 000001 | C3: 100282 | D3: 0.01 | E3: 12.5 | F3: =IF(OR(C3="",D3="",E3="",N3="",C3<=0,D3<=0,E3<=N3),"",ROUNDDOWN((C3*D3)/(E3-N3)/100,0)*100) -> 800 | G3: =IF(OR(A3="",F3="",E3="",N3="",E3<=N3,账户数据!$B$7=""),"",IF(账户数据!$B$9+IF(H3="",F3*(E3-N3),0)>=账户数据!$B$7,"禁止开仓","允许开仓")) -> 禁止开仓 | H3: 300 | I3: 46129 | J3: 13.75 | K3: 14.25 | L3: =IF(K3="","",H3) -> 300 | M3: 46132 | N3: 11.25 | O3: 5 | P3: 5 | Q3: 趋势线与KDJ共同确认 | R3: 止损设在11.25 | S3: 目标参考形态突破 | T3: 按计划成交 | U3: =IF(OR(E3="",J3="",E3<=0),"",(J3-E3)/E3) -> 0.1 | V3: =IF(OR(E3="",N3="",E3<=0),"",(E3-N3)/E3) -> 0.1 | W3: =IF(OR(U3="",V3="",V3<=0),"",U3/V3) -> 1 | X3: =IF(OR(K3="",L3="",E3="",H3=""),"",K3*L3-E3*H3-IF(O3="",0,O3)-IF(P3="",0,P3)) -> 515 | Y3: =IF(OR(X3="",E3="",H3=""),"",IF(E3*H3+IF(O3="",0,O3)<=0,"",X3/(E3*H3+IF(O3="",0,O3)))) -> 0.13715047 | Z3: =IF(OR(Y3="",多次统计数据!$B$8=""),"",Y3-多次统计数据!$B$8) -> 0.009019376 | AA3: =IF(OR(I3="",M3="",M3<I3),"",M3-I3) -> 3 | AB3: =IF(OR(A3="",多次统计数据!$B$8="",多次统计数据!$B$6<=0,多次统计数据!$B$6>=1),"",1-POWER(1+多次统计数据!$B$8,-多次统计数据!$B$6/(1-多次统计数据!$B$6))) -> 0.11918507 | AC3: =IF(OR(AB3="",多次统计数据!$B$9=""),"",IF(多次统计数据!$B$9<AB3,"低于上限","达到或超过上限")) -> 低于上限 | AD3: 4-良好
A4: T2026003 | B4: 300750 | C4: 100797 | D4: 0.01 | E4: 13.75 | F4: =IF(OR(C4="",D4="",E4="",N4="",C4<=0,D4<=0,E4<=N4),"",ROUNDDOWN((C4*D4)/(E4-N4)/100,0)*100) -> 600 | G4: =IF(OR(A4="",F4="",E4="",N4="",E4<=N4,账户数据!$B$7=""),"",IF(账户数据!$B$9+IF(H4="",F4*(E4-N4),0)>=账户数据!$B$7,"禁止开仓","允许开仓")) -> 禁止开仓 | H4: 300 | I4: 46130 | J4: 15.13 | K4: 15.4 | L4: =IF(K4="","",H4) -> 300 | M4: 46134 | N4: 12.25 | O4: 0 | P4: 5 | Q4: MACD与布林带共同确认 | R4: 止损设在12.25 | S4: 目标参考均线金叉 | T4: 按计划成交 | U4: =IF(OR(E4="",J4="",E4<=0),"",(J4-E4)/E4) -> 0.10036364 | V4: =IF(OR(E4="",N4="",E4<=0),"",(E4-N4)/E4) -> 0.10909091 | W4: =IF(OR(U4="",V4="",V4<=0),"",U4/V4) -> 0.92 | X4: =IF(OR(K4="",L4="",E4="",H4=""),"",K4*L4-E4*H4-IF(O4="",0,O4)-IF(P4="",0,P4)) -> 490 | Y4: =IF(OR(X4="",E4="",H4=""),"",IF(E4*H4+IF(O4="",0,O4)<=0,"",X4/(E4*H4+IF(O4="",0,O4)))) -> 0.11878788 | Z4: =IF(OR(Y4="",多次统计数据!$B$8=""),"",Y4-多次统计数据!$B$8) -> -0.0093432113 | AA4: =IF(OR(I4="",M4="",M4<I4),"",M4-I4) -> 4 | AB4: =IF(OR(A4="",多次统计数据!$B$8="",多次统计数据!$B$6<=0,多次统计数据!$B$6>=1),"",1-POWER(1+多次统计数据!$B$8,-多次统计数据!$B$6/(1-多次统计数据!$B$6))) -> 0.11918507 | AC4: =IF(OR(AB4="",多次统计数据!$B$9=""),"",IF(多次统计数据!$B$9<AB4,"低于上限","达到或超过上限")) -> 低于上限 | AD4: 4-良好
A5: T2026004 | B5: 002594 | C5: 101287 | D5: 0.01 | E5: 15 | F5: =IF(OR(C5="",D5="",E5="",N5="",C5<=0,D5<=0,E5<=N5),"",ROUNDDOWN((C5*D5)/(E5-N5)/100,0)*100) -> 1300 | G5: =IF(OR(A5="",F5="",E5="",N5="",E5<=N5,账户数据!$B$7=""),"",IF(账户数据!$B$9+IF(H5="",F5*(E5-N5),0)>=账户数据!$B$7,"禁止开仓","允许开仓")) -> 禁止开仓 | H5: 1000 | I5: 46131 | J5: 16.5 | K5: 16.95 | L5: =IF(K5="","",H5) -> 1000 | M5: 46136 | N5: 14.25 | O5: 5 | P5: 0 | Q5: 移动平均线与支撑位共同确认 | R5: 止损设在14.25 | S5: 目标参考均线死叉 | T5: 按计划成交 | U5: =IF(OR(E5="",J5="",E5<=0),"",(J5-E5)/E5) -> 0.1 | V5: =IF(OR(E5="",N5="",E5<=0),"",(E5-N5)/E5) -> 0.05 | W5: =IF(OR(U5="",V5="",V5<=0),"",U5/V5) -> 2 | X5: =IF(OR(K5="",L5="",E5="",H5=""),"",K5*L5-E5*H5-IF(O5="",0,O5)-IF(P5="",0,P5)) -> 1945 | Y5: =IF(OR(X5="",E5="",H5=""),"",IF(E5*H5+IF(O5="",0,O5)<=0,"",X5/(E5*H5+IF(O5="",0,O5)))) -> 0.12962346 | Z5: =IF(OR(Y5="",多次统计数据!$B$8=""),"",Y5-多次统计数据!$B$8) -> 0.0014923688 | AA5: =IF(OR(I5="",M5="",M5<I5),"",M5-I5) -> 5 | AB5: =IF(OR(A5="",多次统计数据!$B$8="",多次统计数据!$B$6<=0,多次统计数据!$B$6>=1),"",1-POWER(1+多次统计数据!$B$8,-多次统计数据!$B$6/(1-多次统计数据!$B$6))) -> 0.11918507 | AC5: =IF(OR(AB5="",多次统计数据!$B$9=""),"",IF(多次统计数据!$B$9<AB5,"低于上限","达到或超过上限")) -> 低于上限 | AD5: 4-良好
A6: T2026005 | B6: 601318 | C6: 103232 | D6: 0.01 | E6: 16.25 | F6: =IF(OR(C6="",D6="",E6="",N6="",C6<=0,D6<=0,E6<=N6),"",ROUNDDOWN((C6*D6)/(E6-N6)/100,0)*100) -> 1000 | G6: =IF(OR(A6="",F6="",E6="",N6="",E6<=N6,账户数据!$B$7=""),"",IF(账户数据!$B$9+IF(H6="",F6*(E6-N6),0)>=账户数据!$B$7,"禁止开仓","允许开仓")) -> 禁止开仓 | H6: 1000 | I6: 46132 | J6: 17.88 | K6: 15.25 | L6: =IF(K6="","",H6) -> 1000 | M6: 46138 | N6: 15.25 | O6: 5 | P6: 5 | Q6: 成交量与压力位共同确认 | R6: 止损设在15.25 | S6: 目标参考量价背离 | T6: 按计划成交 | U6: =IF(OR(E6="",J6="",E6<=0),"",(J6-E6)/E6) -> 0.10030769 | V6: =IF(OR(E6="",N6="",E6<=0),"",(E6-N6)/E6) -> 0.061538462 | W6: =IF(OR(U6="",V6="",V6<=0),"",U6/V6) -> 1.63 | X6: =IF(OR(K6="",L6="",E6="",H6=""),"",K6*L6-E6*H6-IF(O6="",0,O6)-IF(P6="",0,P6)) -> -1010 | Y6: =IF(OR(X6="",E6="",H6=""),"",IF(E6*H6+IF(O6="",0,O6)<=0,"",X6/(E6*H6+IF(O6="",0,O6)))) -> -0.062134728 | Z6: =IF(OR(Y6="",多次统计数据!$B$8=""),"",Y6-多次统计数据!$B$8) -> -0.19026582 | AA6: =IF(OR(I6="",M6="",M6<I6),"",M6-I6) -> 6 | AB6: =IF(OR(A6="",多次统计数据!$B$8="",多次统计数据!$B$6<=0,多次统计数据!$B$6>=1),"",1-POWER(1+多次统计数据!$B$8,-多次统计数据!$B$6/(1-多次统计数据!$B$6))) -> 0.11918507 | AC6: =IF(OR(AB6="",多次统计数据!$B$9=""),"",IF(多次统计数据!$B$9<AB6,"低于上限","达到或超过上限")) -> 低于上限 | AD6: 2-较差
A7: T2026006 | B7: 688981 | C7: 102222 | D7: 0.01 | E7: 17.5 | F7: =IF(OR(C7="",D7="",E7="",N7="",C7<=0,D7<=0,E7<=N7),"",ROUNDDOWN((C7*D7)/(E7-N7)/100,0)*100) -> 800 | G7: =IF(OR(A7="",F7="",E7="",N7="",E7<=N7,账户数据!$B$7=""),"",IF(账户数据!$B$9+IF(H7="",F7*(E7-N7),0)>=账户数据!$B$7,"禁止开仓","允许开仓")) -> 禁止开仓 | H7: 100 | I7: 46133 | J7: 19.25 | K7: 16.25 | L7: =IF(K7="","",H7) -> 100 | M7: 46140 | N7: 16.25 | O7: 0 | P7: 5 | Q7: RSI与缺口共同确认 | R7: 止损设在16.25 | S7: 目标参考趋势背离 | T7: 按计划成交 | U7: =IF(OR(E7="",J7="",E7<=0),"",(J7-E7)/E7) -> 0.1 | V7: =IF(OR(E7="",N7="",E7<=0),"",(E7-N7)/E7) -> 0.071428571 | W7: =IF(OR(U7="",V7="",V7<=0),"",U7/V7) -> 1.4 | X7: =IF(OR(K7="",L7="",E7="",H7=""),"",K7*L7-E7*H7-IF(O7="",0,O7)-IF(P7="",0,P7)) -> -130 | Y7: =IF(OR(X7="",E7="",H7=""),"",IF(E7*H7+IF(O7="",0,O7)<=0,"",X7/(E7*H7+IF(O7="",0,O7)))) -> -0.074285714 | Z7: =IF(OR(Y7="",多次统计数据!$B$8=""),"",Y7-多次统计数据!$B$8) -> -0.2024168 | AA7: =IF(OR(I7="",M7="",M7<I7),"",M7-I7) -> 7 | AB7: =IF(OR(A7="",多次统计数据!$B$8="",多次统计数据!$B$6<=0,多次统计数据!$B$6>=1),"",1-POWER(1+多次统计数据!$B$8,-多次统计数据!$B$6/(1-多次统计数据!$B$6))) -> 0.11918507 | AC7: =IF(OR(AB7="",多次统计数据!$B$9=""),"",IF(多次统计数据!$B$9<AB7,"低于上限","达到或超过上限")) -> 低于上限 | AD7: 2-较差
A8: T2026007 | B8: 000858 | C8: 102092 | D8: 0.01 | E8: 18.75 | F8: =IF(OR(C8="",D8="",E8="",N8="",C8<=0,D8<=0,E8<=N8),"",ROUNDDOWN((C8*D8)/(E8-N8)/100,0)*100) -> 600 | G8: =IF(OR(A8="",F8="",E8="",N8="",E8<=N8,账户数据!$B$7=""),"",IF(账户数据!$B$9+IF(H8="",F8*(E8-N8),0)>=账户数据!$B$7,"禁止开仓","允许开仓")) -> 禁止开仓 | H8: 200 | I8: 46134 | J8: 20.62 | K8: 17.25 | L8: =IF(K8="","",H8) -> 200 | M8: 46135 | N8: 17.25 | O8: 5 | P8: 5 | Q8: KDJ与形态突破共同确认 | R8: 止损设在17.25 | S8: 目标参考ATR | T8: 按计划成交 | U8: =IF(OR(E8="",J8="",E8<=0),"",(J8-E8)/E8) -> 0.099733333 | V8: =IF(OR(E8="",N8="",E8<=0),"",(E8-N8)/E8) -> 0.08 | W8: =IF(OR(U8="",V8="",V8<=0),"",U8/V8) -> 1.2466667 | X8: =IF(OR(K8="",L8="",E8="",H8=""),"",K8*L8-E8*H8-IF(O8="",0,O8)-IF(P8="",0,P8)) -> -310 | Y8: =IF(OR(X8="",E8="",H8=""),"",IF(E8*H8+IF(O8="",0,O8)<=0,"",X8/(E8*H8+IF(O8="",0,O8)))) -> -0.082556591 | Z8: =IF(OR(Y8="",多次统计数据!$B$8=""),"",Y8-多次统计数据!$B$8) -> -0.21068768 | AA8: =IF(OR(I8="",M8="",M8<I8),"",M8-I8) -> 1 | AB8: =IF(OR(A8="",多次统计数据!$B$8="",多次统计数据!$B$6<=0,多次统计数据!$B$6>=1),"",1-POWER(1+多次统计数据!$B$8,-多次统计数据!$B$6/(1-多次统计数据!$B$6))) -> 0.11918507 | AC8: =IF(OR(AB8="",多次统计数据!$B$9=""),"",IF(多次统计数据!$B$9<AB8,"低于上限","达到或超过上限")) -> 低于上限 | AD8: 2-较差
A9: T2026008 | B9: 600036 | C9: 101782 | D9: 0.01 | E9: 20 | F9: =IF(OR(C9="",D9="",E9="",N9="",C9<=0,D9<=0,E9<=N9),"",ROUNDDOWN((C9*D9)/(E9-N9)/100,0)*100) -> 1300 | G9: =IF(OR(A9="",F9="",E9="",N9="",E9<=N9,账户数据!$B$7=""),"",IF(账户数据!$B$9+IF(H9="",F9*(E9-N9),0)>=账户数据!$B$7,"禁止开仓","允许开仓")) -> 禁止开仓 | H9: 700 | I9: 46135 | J9: 22 | K9: 19 | L9: =IF(K9="","",H9) -> 700 | M9: 46137 | N9: 19.25 | O9: 5 | P9: 0 | Q9: 布林带与均线金叉共同确认 | R9: 止损设在19.25 | S9: 目标参考换手率 | T9: 按计划成交 | U9: =IF(OR(E9="",J9="",E9<=0),"",(J9-E9)/E9) -> 0.1 | V9: =IF(OR(E9="",N9="",E9<=0),"",(E9-N9)/E9) -> 0.0375 | W9: =IF(OR(U9="",V9="",V9<=0),"",U9/V9) -> 2.6666667 | X9: =IF(OR(K9="",L9="",E9="",H9=""),"",K9*L9-E9*H9-IF(O9="",0,O9)-IF(P9="",0,P9)) -> -705 | Y9: =IF(OR(X9="",E9="",H9=""),"",IF(E9*H9+IF(O9="",0,O9)<=0,"",X9/(E9*H9+IF(O9="",0,O9)))) -> -0.050339165 | Z9: =IF(OR(Y9="",多次统计数据!$B$8=""),"",Y9-多次统计数据!$B$8) -> -0.17847025 | AA9: =IF(OR(I9="",M9="",M9<I9),"",M9-I9) -> 2 | AB9: =IF(OR(A9="",多次统计数据!$B$8="",多次统计数据!$B$6<=0,多次统计数据!$B$6>=1),"",1-POWER(1+多次统计数据!$B$8,-多次统计数据!$B$6/(1-多次统计数据!$B$6))) -> 0.11918507 | AC9: =IF(OR(AB9="",多次统计数据!$B$9=""),"",IF(多次统计数据!$B$9<AB9,"低于上限","达到或超过上限")) -> 低于上限 | AD9: 2-较差
A10: T2026009 | B10: 002415 | C10: 101077 | D10: 0.01 | E10: 21.25 | F10: =IF(OR(C10="",D10="",E10="",N10="",C10<=0,D10<=0,E10<=N10),"",ROUNDDOWN((C10*D10)/(E10-N10)/100,0)*100) -> 1000 | G10: =IF(OR(A10="",F10="",E10="",N10="",E10<=N10,账户数据!$B$7=""),"",IF(账户数据!$B$9+IF(H10="",F10*(E10-N10),0)>=账户数据!$B$7,"禁止开仓","允许开仓")) -> 禁止开仓 | H10: 800 | I10: 46136 | J10: 23.38 | K10: 21.25 | L10: =IF(K10="","",H10) -> 800 | M10: 46139 | N10: 20.25 | O10: 0 | P10: 0 | Q10: 支撑位与均线死叉共同确认 | R10: 止损设在20.25 | S10: 目标参考相对强弱 | T10: 按计划成交 | U10: =IF(OR(E10="",J10="",E10<=0),"",(J10-E10)/E10) -> 0.10023529 | V10: =IF(OR(E10="",N10="",E10<=0),"",(E10-N10)/E10) -> 0.047058824 | W10: =IF(OR(U10="",V10="",V10<=0),"",U10/V10) -> 2.13 | X10: =IF(OR(K10="",L10="",E10="",H10=""),"",K10*L10-E10*H10-IF(O10="",0,O10)-IF(P10="",0,P10)) -> 0 | Y10: =IF(OR(X10="",E10="",H10=""),"",IF(E10*H10+IF(O10="",0,O10)<=0,"",X10/(E10*H10+IF(O10="",0,O10)))) -> 0 | Z10: =IF(OR(Y10="",多次统计数据!$B$8=""),"",Y10-多次统计数据!$B$8) -> -0.12813109 | AA10: =IF(OR(I10="",M10="",M10<I10),"",M10-I10) -> 3 | AB10: =IF(OR(A10="",多次统计数据!$B$8="",多次统计数据!$B$6<=0,多次统计数据!$B$6>=1),"",1-POWER(1+多次统计数据!$B$8,-多次统计数据!$B$6/(1-多次统计数据!$B$6))) -> 0.11918507 | AC10: =IF(OR(AB10="",多次统计数据!$B$9=""),"",IF(多次统计数据!$B$9<AB10,"低于上限","达到或超过上限")) -> 低于上限 | AD10: 3-一般
A11: T2026010 | B11: 601899 | C11: 101077 | D11: 0.01 | E11: 22.5 | F11: =IF(OR(C11="",D11="",E11="",N11="",C11<=0,D11<=0,E11<=N11),"",ROUNDDOWN((C11*D11)/(E11-N11)/100,0)*100) -> 800 | G11: =IF(OR(A11="",F11="",E11="",N11="",E11<=N11,账户数据!$B$7=""),"",IF(账户数据!$B$9+IF(H11="",F11*(E11-N11),0)>=账户数据!$B$7,"禁止开仓","允许开仓")) -> 禁止开仓 | H11: 800 | I11: 46137 | J11: 24.75 | L11: =IF(K11="","",H11) | N11: 21.25 | O11: 5 | P11: 5 | Q11: 压力位与量价背离共同确认 | R11: 止损设在21.25 | S11: 目标参考板块共振 | U11: =IF(OR(E11="",J11="",E11<=0),"",(J11-E11)/E11) -> 0.1 | V11: =IF(OR(E11="",N11="",E11<=0),"",(E11-N11)/E11) -> 0.055555556 | W11: =IF(OR(U11="",V11="",V11<=0),"",U11/V11) -> 1.8 | X11: =IF(OR(K11="",L11="",E11="",H11=""),"",K11*L11-E11*H11-IF(O11="",0,O11)-IF(P11="",0,P11)) | Y11: =IF(OR(X11="",E11="",H11=""),"",IF(E11*H11+IF(O11="",0,O11)<=0,"",X11/(E11*H11+IF(O11="",0,O11)))) | Z11: =IF(OR(Y11="",多次统计数据!$B$8=""),"",Y11-多次统计数据!$B$8) | AA11: =IF(OR(I11="",M11="",M11<I11),"",M11-I11) | AB11: =IF(OR(A11="",多次统计数据!$B$8="",多次统计数据!$B$6<=0,多次统计数据!$B$6>=1),"",1-POWER(1+多次统计数据!$B$8,-多次统计数据!$B$6/(1-多次统计数据!$B$6))) -> 0.11918507 | AC11: =IF(OR(AB11="",多次统计数据!$B$9=""),"",IF(多次统计数据!$B$9<AB11,"低于上限","达到或超过上限")) -> 低于上限
A12: T2026011 | B12: 600519 | C12: 101077 | D12: 0.01 | E12: 10 | F12: =IF(OR(C12="",D12="",E12="",N12="",C12<=0,D12<=0,E12<=N12),"",ROUNDDOWN((C12*D12)/(E12-N12)/100,0)*100) -> 600 | G12: =IF(OR(A12="",F12="",E12="",N12="",E12<=N12,账户数据!$B$7=""),"",IF(账户数据!$B$9+IF(H12="",F12*(E12-N12),0)>=账户数据!$B$7,"禁止开仓","允许开仓")) -> 禁止开仓 | H12: 100 | I12: 46138 | J12: 11 | K12: 11.4 | L12: =IF(K12="","",H12) -> 100 | M12: 46143 | N12: 8.5 | O12: 5 | P12: 5 | Q12: 缺口与趋势背离共同确认 | R12: 止损设在8.50 | S12: 目标参考蜡烛图 | T12: 按计划成交 | U12: =IF(OR(E12="",J12="",E12<=0),"",(J12-E12)/E12) -> 0.1 | V12: =IF(OR(E12="",N12="",E12<=0),"",(E12-N12)/E12) -> 0.15 | W12: =IF(OR(U12="",V12="",V12<=0),"",U12/V12) -> 0.66666667 | X12: =IF(OR(K12="",L12="",E12="",H12=""),"",K12*L12-E12*H12-IF(O12="",0,O12)-IF(P12="",0,P12)) -> 130 | Y12: =IF(OR(X12="",E12="",H12=""),"",IF(E12*H12+IF(O12="",0,O12)<=0,"",X12/(E12*H12+IF(O12="",0,O12)))) -> 0.12935323 | Z12: =IF(OR(Y12="",多次统计数据!$B$8=""),"",Y12-多次统计数据!$B$8) -> 0.0012221438 | AA12: =IF(OR(I12="",M12="",M12<I12),"",M12-I12) -> 5 | AB12: =IF(OR(A12="",多次统计数据!$B$8="",多次统计数据!$B$6<=0,多次统计数据!$B$6>=1),"",1-POWER(1+多次统计数据!$B$8,-多次统计数据!$B$6/(1-多次统计数据!$B$6))) -> 0.11918507 | AC12: =IF(OR(AB12="",多次统计数据!$B$9=""),"",IF(多次统计数据!$B$9<AB12,"低于上限","达到或超过上限")) -> 低于上限 | AD12: 4-良好
A13: T2026012 | B13: 000001 | C13: 101207 | D13: 0.01 | E13: 11.25 | F13: =IF(OR(C13="",D13="",E13="",N13="",C13<=0,D13<=0,E13<=N13),"",ROUNDDOWN((C13*D13)/(E13-N13)/100,0)*100) -> 1300 | G13: =IF(OR(A13="",F13="",E13="",N13="",E13<=N13,账户数据!$B$7=""),"",IF(账户数据!$B$9+IF(H13="",F13*(E13-N13),0)>=账户数据!$B$7,"禁止开仓","允许开仓")) -> 禁止开仓 | H13: 500 | I13: 46139 | J13: 12.38 | K13: 12.6 | L13: =IF(K13="","",H13) -> 500 | M13: 46145 | N13: 10.5 | O13: 0 | P13: 0 | Q13: 形态突破与ATR共同确认 | R13: 止损设在10.50 | S13: 目标参考趋势线 | T13: 按计划成交 | U13: =IF(OR(E13="",J13="",E13<=0),"",(J13-E13)/E13) -> 0.10044444 | V13: =IF(OR(E13="",N13="",E13<=0),"",(E13-N13)/E13) -> 0.066666667 | W13: =IF(OR(U13="",V13="",V13<=0),"",U13/V13) -> 1.5066667 | X13: =IF(OR(K13="",L13="",E13="",H13=""),"",K13*L13-E13*H13-IF(O13="",0,O13)-IF(P13="",0,P13)) -> 675 | Y13: =IF(OR(X13="",E13="",H13=""),"",IF(E13*H13+IF(O13="",0,O13)<=0,"",X13/(E13*H13+IF(O13="",0,O13)))) -> 0.12 | Z13: =IF(OR(Y13="",多次统计数据!$B$8=""),"",Y13-多次统计数据!$B$8) -> -0.0081310901 | AA13: =IF(OR(I13="",M13="",M13<I13),"",M13-I13) -> 6 | AB13: =IF(OR(A13="",多次统计数据!$B$8="",多次统计数据!$B$6<=0,多次统计数据!$B$6>=1),"",1-POWER(1+多次统计数据!$B$8,-多次统计数据!$B$6/(1-多次统计数据!$B$6))) -> 0.11918507 | AC13: =IF(OR(AB13="",多次统计数据!$B$9=""),"",IF(多次统计数据!$B$9<AB13,"低于上限","达到或超过上限")) -> 低于上限 | AD13: 4-良好
A14: T2026013 | B14: 300750 | C14: 101882 | D14: 0.01 | E14: 12.5 | F14: =IF(OR(C14="",D14="",E14="",N14="",C14<=0,D14<=0,E14<=N14),"",ROUNDDOWN((C14*D14)/(E14-N14)/100,0)*100) -> 1000 | G14: =IF(OR(A14="",F14="",E14="",N14="",E14<=N14,账户数据!$B$7=""),"",IF(账户数据!$B$9+IF(H14="",F14*(E14-N14),0)>=账户数据!$B$7,"禁止开仓","允许开仓")) -> 禁止开仓 | H14: 600 | I14: 46140 | J14: 13.75 | K14: 14.13 | L14: =IF(K14="","",H14) -> 600 | M14: 46147 | N14: 11.5 | O14: 5 | P14: 5 | Q14: 均线金叉与换手率共同确认 | R14: 止损设在11.50 | S14: 目标参考MACD | T14: 按计划成交 | U14: =IF(OR(E14="",J14="",E14<=0),"",(J14-E14)/E14) -> 0.1 | V14: =IF(OR(E14="",N14="",E14<=0),"",(E14-N14)/E14) -> 0.08 | W14: =IF(OR(U14="",V14="",V14<=0),"",U14/V14) -> 1.25 | X14: =IF(OR(K14="",L14="",E14="",H14=""),"",K14*L14-E14*H14-IF(O14="",0,O14)-IF(P14="",0,P14)) -> 968 | Y14: =IF(OR(X14="",E14="",H14=""),"",IF(E14*H14+IF(O14="",0,O14)<=0,"",X14/(E14*H14+IF(O14="",0,O14)))) -> 0.12898068 | Z14: =IF(OR(Y14="",多次统计数据!$B$8=""),"",Y14-多次统计数据!$B$8) -> 0.00084958947 | AA14: =IF(OR(I14="",M14="",M14<I14),"",M14-I14) -> 7 | AB14: =IF(OR(A14="",多次统计数据!$B$8="",多次统计数据!$B$6<=0,多次统计数据!$B$6>=1),"",1-POWER(1+多次统计数据!$B$8,-多次统计数据!$B$6/(1-多次统计数据!$B$6))) -> 0.11918507 | AC14: =IF(OR(AB14="",多次统计数据!$B$9=""),"",IF(多次统计数据!$B$9<AB14,"低于上限","达到或超过上限")) -> 低于上限 | AD14: 4-良好
A15: T2026014 | B15: 002594 | C15: 102850 | D15: 0.01 | E15: 13.75 | F15: =IF(OR(C15="",D15="",E15="",N15="",C15<=0,D15<=0,E15<=N15),"",ROUNDDOWN((C15*D15)/(E15-N15)/100,0)*100) -> 800 | G15: =IF(OR(A15="",F15="",E15="",N15="",E15<=N15,账户数据!$B$7=""),"",IF(账户数据!$B$9+IF(H15="",F15*(E15-N15),0)>=账户数据!$B$7,"禁止开仓","允许开仓")) -> 禁止开仓 | H15: 600 | I15: 46141 | J15: 15.13 | K15: 15.68 | L15: =IF(K15="","",H15) -> 600 | M15: 46142 | N15: 12.5 | O15: 5 | P15: 5 | Q15: 均线死叉与相对强弱共同确认 | R15: 止损设在12.50 | S15: 目标参考移动平均线 | T15: 按计划成交 | U15: =IF(OR(E15="",J15="",E15<=0),"",(J15-E15)/E15) -> 0.10036364 | V15: =IF(OR(E15="",N15="",E15<=0),"",(E15-N15)/E15) -> 0.090909091 | W15: =IF(OR(U15="",V15="",V15<=0),"",U15/V15) -> 1.104 | X15: =IF(OR(K15="",L15="",E15="",H15=""),"",K15*L15-E15*H15-IF(O15="",0,O15)-IF(P15="",0,P15)) -> 1148 | Y15: =IF(OR(X15="",E15="",H15=""),"",IF(E15*H15+IF(O15="",0,O15)<=0,"",X15/(E15*H15+IF(O15="",0,O15)))) -> 0.13906723 | Z15: =IF(OR(Y15="",多次统计数据!$B$8=""),"",Y15-多次统计数据!$B$8) -> 0.010936142 | AA15: =IF(OR(I15="",M15="",M15<I15),"",M15-I15) -> 1 | AB15: =IF(OR(A15="",多次统计数据!$B$8="",多次统计数据!$B$6<=0,多次统计数据!$B$6>=1),"",1-POWER(1+多次统计数据!$B$8,-多次统计数据!$B$6/(1-多次统计数据!$B$6))) -> 0.11918507 | AC15: =IF(OR(AB15="",多次统计数据!$B$9=""),"",IF(多次统计数据!$B$9<AB15,"低于上限","达到或超过上限")) -> 低于上限 | AD15: 4-良好
A16: T2026015 | B16: 601318 | C16: 103998 | D16: 0.01 | E16: 15 | F16: =IF(OR(C16="",D16="",E16="",N16="",C16<=0,D16<=0,E16<=N16),"",ROUNDDOWN((C16*D16)/(E16-N16)/100,0)*100) -> 600 | G16: =IF(OR(A16="",F16="",E16="",N16="",E16<=N16,账户数据!$B$7=""),"",IF(账户数据!$B$9+IF(H16="",F16*(E16-N16),0)>=账户数据!$B$7,"禁止开仓","允许开仓")) -> 禁止开仓 | H16: 600 | I16: 46142 | J16: 16.5 | K16: 13.5 | L16: =IF(K16="","",H16) -> 600 | M16: 46144 | N16: 13.5 | O16: 0 | P16: 5 | Q16: 量价背离与板块共振共同确认 | R16: 止损设在13.50 | S16: 目标参考成交量 | T16: 按计划成交 | U16: =IF(OR(E16="",J16="",E16<=0),"",(J16-E16)/E16) -> 0.1 | V16: =IF(OR(E16="",N16="",E16<=0),"",(E16-N16)/E16) -> 0.1 | W16: =IF(OR(U16="",V16="",V16<=0),"",U16/V16) -> 1 | X16: =IF(OR(K16="",L16="",E16="",H16=""),"",K16*L16-E16*H16-IF(O16="",0,O16)-IF(P16="",0,P16)) -> -905 | Y16: =IF(OR(X16="",E16="",H16=""),"",IF(E16*H16+IF(O16="",0,O16)<=0,"",X16/(E16*H16+IF(O16="",0,O16)))) -> -0.10055556 | Z16: =IF(OR(Y16="",多次统计数据!$B$8=""),"",Y16-多次统计数据!$B$8) -> -0.22868665 | AA16: =IF(OR(I16="",M16="",M16<I16),"",M16-I16) -> 2 | AB16: =IF(OR(A16="",多次统计数据!$B$8="",多次统计数据!$B$6<=0,多次统计数据!$B$6>=1),"",1-POWER(1+多次统计数据!$B$8,-多次统计数据!$B$6/(1-多次统计数据!$B$6))) -> 0.11918507 | AC16: =IF(OR(AB16="",多次统计数据!$B$9=""),"",IF(多次统计数据!$B$9<AB16,"低于上限","达到或超过上限")) -> 低于上限 | AD16: 2-较差
A17: T2026016 | B17: 688981 | C17: 103093 | D17: 0.01 | E17: 16.25 | F17: =IF(OR(C17="",D17="",E17="",N17="",C17<=0,D17<=0,E17<=N17),"",ROUNDDOWN((C17*D17)/(E17-N17)/100,0)*100) -> 1300 | G17: =IF(OR(A17="",F17="",E17="",N17="",E17<=N17,账户数据!$B$7=""),"",IF(账户数据!$B$9+IF(H17="",F17*(E17-N17),0)>=账户数据!$B$7,"禁止开仓","允许开仓")) -> 禁止开仓 | H17: 200 | I17: 46143 | J17: 17.88 | K17: 15.44 | L17: =IF(K17="","",H17) -> 200 | M17: 46146 | N17: 15.5 | O17: 5 | P17: 0 | Q17: 趋势背离与蜡烛图共同确认 | R17: 止损设在15.50 | S17: 目标参考RSI | T17: 按计划成交 | U17: =IF(OR(E17="",J17="",E17<=0),"",(J17-E17)/E17) -> 0.10030769 | V17: =IF(OR(E17="",N17="",E17<=0),"",(E17-N17)/E17) -> 0.046153846 | W17: =IF(OR(U17="",V17="",V17<=0),"",U17/V17) -> 2.1733333 | X17: =IF(OR(K17="",L17="",E17="",H17=""),"",K17*L17-E17*H17-IF(O17="",0,O17)-IF(P17="",0,P17)) -> -167 | Y17: =IF(OR(X17="",E17="",H17=""),"",IF(E17*H17+IF(O17="",0,O17)<=0,"",X17/(E17*H17+IF(O17="",0,O17)))) -> -0.051305684 | Z17: =IF(OR(Y17="",多次统计数据!$B$8=""),"",Y17-多次统计数据!$B$8) -> -0.17943677 | AA17: =IF(OR(I17="",M17="",M17<I17),"",M17-I17) -> 3 | AB17: =IF(OR(A17="",多次统计数据!$B$8="",多次统计数据!$B$6<=0,多次统计数据!$B$6>=1),"",1-POWER(1+多次统计数据!$B$8,-多次统计数据!$B$6/(1-多次统计数据!$B$6))) -> 0.11918507 | AC17: =IF(OR(AB17="",多次统计数据!$B$9=""),"",IF(多次统计数据!$B$9<AB17,"低于上限","达到或超过上限")) -> 低于上限 | AD17: 2-较差
A18: T2026017 | B18: 000858 | C18: 102926 | D18: 0.01 | E18: 17.5 | F18: =IF(OR(C18="",D18="",E18="",N18="",C18<=0,D18<=0,E18<=N18),"",ROUNDDOWN((C18*D18)/(E18-N18)/100,0)*100) -> 1000 | G18: =IF(OR(A18="",F18="",E18="",N18="",E18<=N18,账户数据!$B$7=""),"",IF(账户数据!$B$9+IF(H18="",F18*(E18-N18),0)>=账户数据!$B$7,"禁止开仓","允许开仓")) -> 禁止开仓 | H18: 400 | I18: 46144 | J18: 19.25 | K18: 16.45 | L18: =IF(K18="","",H18) -> 400 | M18: 46148 | N18: 16.5 | O18: 5 | P18: 5 | Q18: ATR与趋势线共同确认 | R18: 止损设在16.50 | S18: 目标参考KDJ | T18: 按计划成交 | U18: =IF(OR(E18="",J18="",E18<=0),"",(J18-E18)/E18) -> 0.1 | V18: =IF(OR(E18="",N18="",E18<=0),"",(E18-N18)/E18) -> 0.057142857 | W18: =IF(OR(U18="",V18="",V18<=0),"",U18/V18) -> 1.75 | X18: =IF(OR(K18="",L18="",E18="",H18=""),"",K18*L18-E18*H18-IF(O18="",0,O18)-IF(P18="",0,P18)) -> -430 | Y18: =IF(OR(X18="",E18="",H18=""),"",IF(E18*H18+IF(O18="",0,O18)<=0,"",X18/(E18*H18+IF(O18="",0,O18)))) -> -0.061384725 | Z18: =IF(OR(Y18="",多次统计数据!$B$8=""),"",Y18-多次统计数据!$B$8) -> -0.18951582 | AA18: =IF(OR(I18="",M18="",M18<I18),"",M18-I18) -> 4 | AB18: =IF(OR(A18="",多次统计数据!$B$8="",多次统计数据!$B$6<=0,多次统计数据!$B$6>=1),"",1-POWER(1+多次统计数据!$B$8,-多次统计数据!$B$6/(1-多次统计数据!$B$6))) -> 0.11918507 | AC18: =IF(OR(AB18="",多次统计数据!$B$9=""),"",IF(多次统计数据!$B$9<AB18,"低于上限","达到或超过上限")) -> 低于上限 | AD18: 2-较差
A19: T2026018 | B19: 600036 | C19: 102496 | D19: 0.01 | E19: 18.75 | F19: =IF(OR(C19="",D19="",E19="",N19="",C19<=0,D19<=0,E19<=N19),"",ROUNDDOWN((C19*D19)/(E19-N19)/100,0)*100) -> 800 | G19: =IF(OR(A19="",F19="",E19="",N19="",E19<=N19,账户数据!$B$7=""),"",IF(账户数据!$B$9+IF(H19="",F19*(E19-N19),0)>=账户数据!$B$7,"禁止开仓","允许开仓")) -> 禁止开仓 | H19: 400 | I19: 46145 | J19: 20.62 | K19: 17.5 | L19: =IF(K19="","",H19) -> 400 | M19: 46150 | N19: 17.5 | O19: 0 | P19: 5 | Q19: 换手率与MACD共同确认 | R19: 止损设在17.50 | S19: 目标参考布林带 | T19: 按计划成交 | U19: =IF(OR(E19="",J19="",E19<=0),"",(J19-E19)/E19) -> 0.099733333 | V19: =IF(OR(E19="",N19="",E19<=0),"",(E19-N19)/E19) -> 0.066666667 | W19: =IF(OR(U19="",V19="",V19<=0),"",U19/V19) -> 1.496 | X19: =IF(OR(K19="",L19="",E19="",H19=""),"",K19*L19-E19*H19-IF(O19="",0,O19)-IF(P19="",0,P19)) -> -505 | Y19: =IF(OR(X19="",E19="",H19=""),"",IF(E19*H19+IF(O19="",0,O19)<=0,"",X19/(E19*H19+IF(O19="",0,O19)))) -> -0.067333333 | Z19: =IF(OR(Y19="",多次统计数据!$B$8=""),"",Y19-多次统计数据!$B$8) -> -0.19546442 | AA19: =IF(OR(I19="",M19="",M19<I19),"",M19-I19) -> 5 | AB19: =IF(OR(A19="",多次统计数据!$B$8="",多次统计数据!$B$6<=0,多次统计数据!$B$6>=1),"",1-POWER(1+多次统计数据!$B$8,-多次统计数据!$B$6/(1-多次统计数据!$B$6))) -> 0.11918507 | AC19: =IF(OR(AB19="",多次统计数据!$B$9=""),"",IF(多次统计数据!$B$9<AB19,"低于上限","达到或超过上限")) -> 低于上限 | AD19: 2-较差
A20: T2026019 | B20: 002415 | C20: 101991 | D20: 0.01 | E20: 20 | F20: =IF(OR(C20="",D20="",E20="",N20="",C20<=0,D20<=0,E20<=N20),"",ROUNDDOWN((C20*D20)/(E20-N20)/100,0)*100) -> 600 | G20: =IF(OR(A20="",F20="",E20="",N20="",E20<=N20,账户数据!$B$7=""),"",IF(账户数据!$B$9+IF(H20="",F20*(E20-N20),0)>=账户数据!$B$7,"禁止开仓","允许开仓")) -> 禁止开仓 | H20: 400 | I20: 46146 | J20: 22 | K20: 20 | L20: =IF(K20="","",H20) -> 400 | M20: 46152 | N20: 18.5 | O20: 0 | P20: 0 | Q20: 相对强弱与移动平均线共同确认 | R20: 止损设在18.50 | S20: 目标参考支撑位 | T20: 按计划成交 | U20: =IF(OR(E20="",J20="",E20<=0),"",(J20-E20)/E20) -> 0.1 | V20: =IF(OR(E20="",N20="",E20<=0),"",(E20-N20)/E20) -> 0.075 | W20: =IF(OR(U20="",V20="",V20<=0),"",U20/V20) -> 1.3333333 | X20: =IF(OR(K20="",L20="",E20="",H20=""),"",K20*L20-E20*H20-IF(O20="",0,O20)-IF(P20="",0,P20)) -> 0 | Y20: =IF(OR(X20="",E20="",H20=""),"",IF(E20*H20+IF(O20="",0,O20)<=0,"",X20/(E20*H20+IF(O20="",0,O20)))) -> 0 | Z20: =IF(OR(Y20="",多次统计数据!$B$8=""),"",Y20-多次统计数据!$B$8) -> -0.12813109 | AA20: =IF(OR(I20="",M20="",M20<I20),"",M20-I20) -> 6 | AB20: =IF(OR(A20="",多次统计数据!$B$8="",多次统计数据!$B$6<=0,多次统计数据!$B$6>=1),"",1-POWER(1+多次统计数据!$B$8,-多次统计数据!$B$6/(1-多次统计数据!$B$6))) -> 0.11918507 | AC20: =IF(OR(AB20="",多次统计数据!$B$9=""),"",IF(多次统计数据!$B$9<AB20,"低于上限","达到或超过上限")) -> 低于上限 | AD20: 3-一般
A21: T2026020 | B21: 601899 | C21: 101991 | D21: 0.01 | E21: 21.25 | F21: =IF(OR(C21="",D21="",E21="",N21="",C21<=0,D21<=0,E21<=N21),"",ROUNDDOWN((C21*D21)/(E21-N21)/100,0)*100) -> 1300 | G21: =IF(OR(A21="",F21="",E21="",N21="",E21<=N21,账户数据!$B$7=""),"",IF(账户数据!$B$9+IF(H21="",F21*(E21-N21),0)>=账户数据!$B$7,"禁止开仓","允许开仓")) -> 禁止开仓 | H21: 1300 | I21: 46147 | J21: 23.38 | L21: =IF(K21="","",H21) | N21: 20.5 | O21: 5 | P21: 0 | Q21: 板块共振与成交量共同确认 | R21: 止损设在20.50 | S21: 目标参考压力位 | U21: =IF(OR(E21="",J21="",E21<=0),"",(J21-E21)/E21) -> 0.10023529 | V21: =IF(OR(E21="",N21="",E21<=0),"",(E21-N21)/E21) -> 0.035294118 | W21: =IF(OR(U21="",V21="",V21<=0),"",U21/V21) -> 2.84 | X21: =IF(OR(K21="",L21="",E21="",H21=""),"",K21*L21-E21*H21-IF(O21="",0,O21)-IF(P21="",0,P21)) | Y21: =IF(OR(X21="",E21="",H21=""),"",IF(E21*H21+IF(O21="",0,O21)<=0,"",X21/(E21*H21+IF(O21="",0,O21)))) | Z21: =IF(OR(Y21="",多次统计数据!$B$8=""),"",Y21-多次统计数据!$B$8) | AA21: =IF(OR(I21="",M21="",M21<I21),"",M21-I21) | AB21: =IF(OR(A21="",多次统计数据!$B$8="",多次统计数据!$B$6<=0,多次统计数据!$B$6>=1),"",1-POWER(1+多次统计数据!$B$8,-多次统计数据!$B$6/(1-多次统计数据!$B$6))) -> 0.11918507 | AC21: =IF(OR(AB21="",多次统计数据!$B$9=""),"",IF(多次统计数据!$B$9<AB21,"低于上限","达到或超过上限")) -> 低于上限
A22: T2026021 | B22: 600519 | C22: 101991 | D22: 0.01 | E22: 22.5 | F22: =IF(OR(C22="",D22="",E22="",N22="",C22<=0,D22<=0,E22<=N22),"",ROUNDDOWN((C22*D22)/(E22-N22)/100,0)*100) -> 1000 | G22: =IF(OR(A22="",F22="",E22="",N22="",E22<=N22,账户数据!$B$7=""),"",IF(账户数据!$B$9+IF(H22="",F22*(E22-N22),0)>=账户数据!$B$7,"禁止开仓","允许开仓")) -> 禁止开仓 | H22: 200 | I22: 46148 | J22: 24.75 | K22: 25.2 | L22: =IF(K22="","",H22) -> 200 | M22: 46149 | N22: 21.5 | O22: 0 | P22: 5 | Q22: 蜡烛图与RSI共同确认 | R22: 止损设在21.50 | S22: 目标参考缺口 | T22: 按计划成交 | U22: =IF(OR(E22="",J22="",E22<=0),"",(J22-E22)/E22) -> 0.1 | V22: =IF(OR(E22="",N22="",E22<=0),"",(E22-N22)/E22) -> 0.044444444 | W22: =IF(OR(U22="",V22="",V22<=0),"",U22/V22) -> 2.25 | X22: =IF(OR(K22="",L22="",E22="",H22=""),"",K22*L22-E22*H22-IF(O22="",0,O22)-IF(P22="",0,P22)) -> 535 | Y22: =IF(OR(X22="",E22="",H22=""),"",IF(E22*H22+IF(O22="",0,O22)<=0,"",X22/(E22*H22+IF(O22="",0,O22)))) -> 0.11888889 | Z22: =IF(OR(Y22="",多次统计数据!$B$8=""),"",Y22-多次统计数据!$B$8) -> -0.0092422012 | AA22: =IF(OR(I22="",M22="",M22<I22),"",M22-I22) -> 1 | AB22: =IF(OR(A22="",多次统计数据!$B$8="",多次统计数据!$B$6<=0,多次统计数据!$B$6>=1),"",1-POWER(1+多次统计数据!$B$8,-多次统计数据!$B$6/(1-多次统计数据!$B$6))) -> 0.11918507 | AC22: =IF(OR(AB22="",多次统计数据!$B$9=""),"",IF(多次统计数据!$B$9<AB22,"低于上限","达到或超过上限")) -> 低于上限 | AD22: 4-良好
A23: T2026022 | B23: 000001 | C23: 102526 | D23: 0.01 | E23: 10 | F23: =IF(OR(C23="",D23="",E23="",N23="",C23<=0,D23<=0,E23<=N23),"",ROUNDDOWN((C23*D23)/(E23-N23)/100,0)*100) -> 800 | G23: =IF(OR(A23="",F23="",E23="",N23="",E23<=N23,账户数据!$B$7=""),"",IF(账户数据!$B$9+IF(H23="",F23*(E23-N23),0)>=账户数据!$B$7,"禁止开仓","允许开仓")) -> 禁止开仓 | H23: 300 | I23: 46149 | J23: 11 | K23: 11.3 | L23: =IF(K23="","",H23) -> 300 | M23: 46151 | N23: 8.75 | O23: 5 | P23: 5 | Q23: 趋势线与KDJ共同确认 | R23: 止损设在8.75 | S23: 目标参考形态突破 | T23: 按计划成交 | U23: =IF(OR(E23="",J23="",E23<=0),"",(J23-E23)/E23) -> 0.1 | V23: =IF(OR(E23="",N23="",E23<=0),"",(E23-N23)/E23) -> 0.125 | W23: =IF(OR(U23="",V23="",V23<=0),"",U23/V23) -> 0.8 | X23: =IF(OR(K23="",L23="",E23="",H23=""),"",K23*L23-E23*H23-IF(O23="",0,O23)-IF(P23="",0,P23)) -> 380 | Y23: =IF(OR(X23="",E23="",H23=""),"",IF(E23*H23+IF(O23="",0,O23)<=0,"",X23/(E23*H23+IF(O23="",0,O23)))) -> 0.12645591 | Z23: =IF(OR(Y23="",多次统计数据!$B$8=""),"",Y23-多次统计数据!$B$8) -> -0.0016751833 | AA23: =IF(OR(I23="",M23="",M23<I23),"",M23-I23) -> 2 | AB23: =IF(OR(A23="",多次统计数据!$B$8="",多次统计数据!$B$6<=0,多次统计数据!$B$6>=1),"",1-POWER(1+多次统计数据!$B$8,-多次统计数据!$B$6/(1-多次统计数据!$B$6))) -> 0.11918507 | AC23: =IF(OR(AB23="",多次统计数据!$B$9=""),"",IF(多次统计数据!$B$9<AB23,"低于上限","达到或超过上限")) -> 低于上限 | AD23: 4-良好
A24: T2026023 | B24: 300750 | C24: 102906 | D24: 0.01 | E24: 11.25 | F24: =IF(OR(C24="",D24="",E24="",N24="",C24<=0,D24<=0,E24<=N24),"",ROUNDDOWN((C24*D24)/(E24-N24)/100,0)*100) -> 600 | G24: =IF(OR(A24="",F24="",E24="",N24="",E24<=N24,账户数据!$B$7=""),"",IF(账户数据!$B$9+IF(H24="",F24*(E24-N24),0)>=账户数据!$B$7,"禁止开仓","允许开仓")) -> 禁止开仓 | H24: 300 | I24: 46150 | J24: 12.38 | K24: 12.83 | L24: =IF(K24="","",H24) -> 300 | M24: 46153 | N24: 9.75 | O24: 5 | P24: 5 | Q24: MACD与布林带共同确认 | R24: 止损设在9.75 | S24: 目标参考均线金叉 | T24: 按计划成交 | U24: =IF(OR(E24="",J24="",E24<=0),"",(J24-E24)/E24) -> 0.10044444 | V24: =IF(OR(E24="",N24="",E24<=0),"",(E24-N24)/E24) -> 0.13333333 | W24: =IF(OR(U24="",V24="",V24<=0),"",U24/V24) -> 0.75333333 | X24: =IF(OR(K24="",L24="",E24="",H24=""),"",K24*L24-E24*H24-IF(O24="",0,O24)-IF(P24="",0,P24)) -> 464 | Y24: =IF(OR(X24="",E24="",H24=""),"",IF(E24*H24+IF(O24="",0,O24)<=0,"",X24/(E24*H24+IF(O24="",0,O24)))) -> 0.13727811 | Z24: =IF(OR(Y24="",多次统计数据!$B$8=""),"",Y24-多次统计数据!$B$8) -> 0.0091470164 | AA24: =IF(OR(I24="",M24="",M24<I24),"",M24-I24) -> 3 | AB24: =IF(OR(A24="",多次统计数据!$B$8="",多次统计数据!$B$6<=0,多次统计数据!$B$6>=1),"",1-POWER(1+多次统计数据!$B$8,-多次统计数据!$B$6/(1-多次统计数据!$B$6))) -> 0.11918507 | AC24: =IF(OR(AB24="",多次统计数据!$B$9=""),"",IF(多次统计数据!$B$9<AB24,"低于上限","达到或超过上限")) -> 低于上限 | AD24: 4-良好
A25: T2026024 | B25: 002594 | C25: 103370 | D25: 0.01 | E25: 12.5 | F25: =IF(OR(C25="",D25="",E25="",N25="",C25<=0,D25<=0,E25<=N25),"",ROUNDDOWN((C25*D25)/(E25-N25)/100,0)*100) -> 1300 | G25: =IF(OR(A25="",F25="",E25="",N25="",E25<=N25,账户数据!$B$7=""),"",IF(账户数据!$B$9+IF(H25="",F25*(E25-N25),0)>=账户数据!$B$7,"禁止开仓","允许开仓")) -> 禁止开仓 | H25: 1000 | I25: 46151 | J25: 13.75 | K25: 14 | L25: =IF(K25="","",H25) -> 1000 | M25: 46155 | N25: 11.75 | O25: 0 | P25: 0 | Q25: 移动平均线与支撑位共同确认 | R25: 止损设在11.75 | S25: 目标参考均线死叉 | T25: 按计划成交 | U25: =IF(OR(E25="",J25="",E25<=0),"",(J25-E25)/E25) -> 0.1 | V25: =IF(OR(E25="",N25="",E25<=0),"",(E25-N25)/E25) -> 0.06 | W25: =IF(OR(U25="",V25="",V25<=0),"",U25/V25) -> 1.6666667 | X25: =IF(OR(K25="",L25="",E25="",H25=""),"",K25*L25-E25*H25-IF(O25="",0,O25)-IF(P25="",0,P25)) -> 1500 | Y25: =IF(OR(X25="",E25="",H25=""),"",IF(E25*H25+IF(O25="",0,O25)<=0,"",X25/(E25*H25+IF(O25="",0,O25)))) -> 0.12 | Z25: =IF(OR(Y25="",多次统计数据!$B$8=""),"",Y25-多次统计数据!$B$8) -> -0.0081310901 | AA25: =IF(OR(I25="",M25="",M25<I25),"",M25-I25) -> 4 | AB25: =IF(OR(A25="",多次统计数据!$B$8="",多次统计数据!$B$6<=0,多次统计数据!$B$6>=1),"",1-POWER(1+多次统计数据!$B$8,-多次统计数据!$B$6/(1-多次统计数据!$B$6))) -> 0.11918507 | AC25: =IF(OR(AB25="",多次统计数据!$B$9=""),"",IF(多次统计数据!$B$9<AB25,"低于上限","达到或超过上限")) -> 低于上限 | AD25: 4-良好
A26: T2026025 | B26: 601318 | C26: 104870 | D26: 0.01 | E26: 13.75 | F26: =IF(OR(C26="",D26="",E26="",N26="",C26<=0,D26<=0,E26<=N26),"",ROUNDDOWN((C26*D26)/(E26-N26)/100,0)*100) -> 1000 | G26: =IF(OR(A26="",F26="",E26="",N26="",E26<=N26,账户数据!$B$7=""),"",IF(账户数据!$B$9+IF(H26="",F26*(E26-N26),0)>=账户数据!$B$7,"禁止开仓","允许开仓")) -> 禁止开仓 | I26: 46152 | J26: 15.13 | L26: =IF(K26="","",H26) | N26: 12.75 | O26: 5 | P26: 5 | Q26: 成交量与压力位共同确认 | R26: 止损设在12.75 | S26: 目标参考量价背离 | U26: =IF(OR(E26="",J26="",E26<=0),"",(J26-E26)/E26) -> 0.10036364 | V26: =IF(OR(E26="",N26="",E26<=0),"",(E26-N26)/E26) -> 0.072727273 | W26: =IF(OR(U26="",V26="",V26<=0),"",U26/V26) -> 1.38 | X26: =IF(OR(K26="",L26="",E26="",H26=""),"",K26*L26-E26*H26-IF(O26="",0,O26)-IF(P26="",0,P26)) | Y26: =IF(OR(X26="",E26="",H26=""),"",IF(E26*H26+IF(O26="",0,O26)<=0,"",X26/(E26*H26+IF(O26="",0,O26)))) | Z26: =IF(OR(Y26="",多次统计数据!$B$8=""),"",Y26-多次统计数据!$B$8) | AA26: =IF(OR(I26="",M26="",M26<I26),"",M26-I26) | AB26: =IF(OR(A26="",多次统计数据!$B$8="",多次统计数据!$B$6<=0,多次统计数据!$B$6>=1),"",1-POWER(1+多次统计数据!$B$8,-多次统计数据!$B$6/(1-多次统计数据!$B$6))) -> 0.11918507 | AC26: =IF(OR(AB26="",多次统计数据!$B$9=""),"",IF(多次统计数据!$B$9<AB26,"低于上限","达到或超过上限")) -> 低于上限
A27: T2026026 | B27: 688981 | C27: 104870 | D27: 0.01 | E27: 15 | F27: =IF(OR(C27="",D27="",E27="",N27="",C27<=0,D27<=0,E27<=N27),"",ROUNDDOWN((C27*D27)/(E27-N27)/100,0)*100) -> 800 | G27: =IF(OR(A27="",F27="",E27="",N27="",E27<=N27,账户数据!$B$7=""),"",IF(账户数据!$B$9+IF(H27="",F27*(E27-N27),0)>=账户数据!$B$7,"禁止开仓","允许开仓")) -> 禁止开仓 | H27: 100 | I27: 46153 | J27: 16.5 | K27: 13.75 | L27: =IF(K27="","",H27) -> 100 | M27: 46159 | N27: 13.75 | O27: 5 | P27: 5 | Q27: RSI与缺口共同确认 | R27: 止损设在13.75 | S27: 目标参考趋势背离 | T27: 按计划成交 | U27: =IF(OR(E27="",J27="",E27<=0),"",(J27-E27)/E27) -> 0.1 | V27: =IF(OR(E27="",N27="",E27<=0),"",(E27-N27)/E27) -> 0.083333333 | W27: =IF(OR(U27="",V27="",V27<=0),"",U27/V27) -> 1.2 | X27: =IF(OR(K27="",L27="",E27="",H27=""),"",K27*L27-E27*H27-IF(O27="",0,O27)-IF(P27="",0,P27)) -> -135 | Y27: =IF(OR(X27="",E27="",H27=""),"",IF(E27*H27+IF(O27="",0,O27)<=0,"",X27/(E27*H27+IF(O27="",0,O27)))) -> -0.089700997 | Z27: =IF(OR(Y27="",多次统计数据!$B$8=""),"",Y27-多次统计数据!$B$8) -> -0.21783209 | AA27: =IF(OR(I27="",M27="",M27<I27),"",M27-I27) -> 6 | AB27: =IF(OR(A27="",多次统计数据!$B$8="",多次统计数据!$B$6<=0,多次统计数据!$B$6>=1),"",1-POWER(1+多次统计数据!$B$8,-多次统计数据!$B$6/(1-多次统计数据!$B$6))) -> 0.11918507 | AC27: =IF(OR(AB27="",多次统计数据!$B$9=""),"",IF(多次统计数据!$B$9<AB27,"低于上限","达到或超过上限")) -> 低于上限 | AD27: 2-较差
A28: T2026027 | B28: 000858 | C28: 104735 | D28: 0.01 | E28: 16.25 | F28: =IF(OR(C28="",D28="",E28="",N28="",C28<=0,D28<=0,E28<=N28),"",ROUNDDOWN((C28*D28)/(E28-N28)/100,0)*100) -> 600 | G28: =IF(OR(A28="",F28="",E28="",N28="",E28<=N28,账户数据!$B$7=""),"",IF(账户数据!$B$9+IF(H28="",F28*(E28-N28),0)>=账户数据!$B$7,"禁止开仓","允许开仓")) -> 禁止开仓 | H28: 200 | I28: 46154 | J28: 17.88 | K28: 14.75 | L28: =IF(K28="","",H28) -> 200 | M28: 46161 | N28: 14.75 | O28: 0 | P28: 5 | Q28: KDJ与形态突破共同确认 | R28: 止损设在14.75 | S28: 目标参考ATR | T28: 按计划成交 | U28: =IF(OR(E28="",J28="",E28<=0),"",(J28-E28)/E28) -> 0.10030769 | V28: =IF(OR(E28="",N28="",E28<=0),"",(E28-N28)/E28) -> 0.092307692 | W28: =IF(OR(U28="",V28="",V28<=0),"",U28/V28) -> 1.0866667 | X28: =IF(OR(K28="",L28="",E28="",H28=""),"",K28*L28-E28*H28-IF(O28="",0,O28)-IF(P28="",0,P28)) -> -305 | Y28: =IF(OR(X28="",E28="",H28=""),"",IF(E28*H28+IF(O28="",0,O28)<=0,"",X28/(E28*H28+IF(O28="",0,O28)))) -> -0.093846154 | Z28: =IF(OR(Y28="",多次统计数据!$B$8=""),"",Y28-多次统计数据!$B$8) -> -0.22197724 | AA28: =IF(OR(I28="",M28="",M28<I28),"",M28-I28) -> 7 | AB28: =IF(OR(A28="",多次统计数据!$B$8="",多次统计数据!$B$6<=0,多次统计数据!$B$6>=1),"",1-POWER(1+多次统计数据!$B$8,-多次统计数据!$B$6/(1-多次统计数据!$B$6))) -> 0.11918507 | AC28: =IF(OR(AB28="",多次统计数据!$B$9=""),"",IF(多次统计数据!$B$9<AB28,"低于上限","达到或超过上限")) -> 低于上限 | AD28: 2-较差
A29: T2026028 | B29: 600036 | C29: 104430 | D29: 0.01 | E29: 17.5 | F29: =IF(OR(C29="",D29="",E29="",N29="",C29<=0,D29<=0,E29<=N29),"",ROUNDDOWN((C29*D29)/(E29-N29)/100,0)*100) -> 1300 | G29: =IF(OR(A29="",F29="",E29="",N29="",E29<=N29,账户数据!$B$7=""),"",IF(账户数据!$B$9+IF(H29="",F29*(E29-N29),0)>=账户数据!$B$7,"禁止开仓","允许开仓")) -> 禁止开仓 | H29: 700 | I29: 46155 | J29: 19.25 | K29: 16.62 | L29: =IF(K29="","",H29) -> 700 | M29: 46156 | N29: 16.75 | O29: 5 | P29: 0 | Q29: 布林带与均线金叉共同确认 | R29: 止损设在16.75 | S29: 目标参考换手率 | T29: 按计划成交 | U29: =IF(OR(E29="",J29="",E29<=0),"",(J29-E29)/E29) -> 0.1 | V29: =IF(OR(E29="",N29="",E29<=0),"",(E29-N29)/E29) -> 0.042857143 | W29: =IF(OR(U29="",V29="",V29<=0),"",U29/V29) -> 2.3333333 | X29: =IF(OR(K29="",L29="",E29="",H29=""),"",K29*L29-E29*H29-IF(O29="",0,O29)-IF(P29="",0,P29)) -> -621 | Y29: =IF(OR(X29="",E29="",H29=""),"",IF(E29*H29+IF(O29="",0,O29)<=0,"",X29/(E29*H29+IF(O29="",0,O29)))) -> -0.050673195 | Z29: =IF(OR(Y29="",多次统计数据!$B$8=""),"",Y29-多次统计数据!$B$8) -> -0.17880428 | AA29: =IF(OR(I29="",M29="",M29<I29),"",M29-I29) -> 1 | AB29: =IF(OR(A29="",多次统计数据!$B$8="",多次统计数据!$B$6<=0,多次统计数据!$B$6>=1),"",1-POWER(1+多次统计数据!$B$8,-多次统计数据!$B$6/(1-多次统计数据!$B$6))) -> 0.11918507 | AC29: =IF(OR(AB29="",多次统计数据!$B$9=""),"",IF(多次统计数据!$B$9<AB29,"低于上限","达到或超过上限")) -> 低于上限 | AD29: 2-较差
A30: T2026029 | B30: 002415 | C30: 103809 | D30: 0.01 | E30: 18.75 | F30: =IF(OR(C30="",D30="",E30="",N30="",C30<=0,D30<=0,E30<=N30),"",ROUNDDOWN((C30*D30)/(E30-N30)/100,0)*100) -> 1000 | G30: =IF(OR(A30="",F30="",E30="",N30="",E30<=N30,账户数据!$B$7=""),"",IF(账户数据!$B$9+IF(H30="",F30*(E30-N30),0)>=账户数据!$B$7,"禁止开仓","允许开仓")) -> 禁止开仓 | H30: 800 | I30: 46156 | J30: 20.62 | K30: 18.75 | L30: =IF(K30="","",H30) -> 800 | M30: 46158 | N30: 17.75 | O30: 0 | P30: 0 | Q30: 支撑位与均线死叉共同确认 | R30: 止损设在17.75 | S30: 目标参考相对强弱 | T30: 按计划成交 | U30: =IF(OR(E30="",J30="",E30<=0),"",(J30-E30)/E30) -> 0.099733333 | V30: =IF(OR(E30="",N30="",E30<=0),"",(E30-N30)/E30) -> 0.053333333 | W30: =IF(OR(U30="",V30="",V30<=0),"",U30/V30) -> 1.87 | X30: =IF(OR(K30="",L30="",E30="",H30=""),"",K30*L30-E30*H30-IF(O30="",0,O30)-IF(P30="",0,P30)) -> 0 | Y30: =IF(OR(X30="",E30="",H30=""),"",IF(E30*H30+IF(O30="",0,O30)<=0,"",X30/(E30*H30+IF(O30="",0,O30)))) -> 0 | Z30: =IF(OR(Y30="",多次统计数据!$B$8=""),"",Y30-多次统计数据!$B$8) -> -0.12813109 | AA30: =IF(OR(I30="",M30="",M30<I30),"",M30-I30) -> 2 | AB30: =IF(OR(A30="",多次统计数据!$B$8="",多次统计数据!$B$6<=0,多次统计数据!$B$6>=1),"",1-POWER(1+多次统计数据!$B$8,-多次统计数据!$B$6/(1-多次统计数据!$B$6))) -> 0.11918507 | AC30: =IF(OR(AB30="",多次统计数据!$B$9=""),"",IF(多次统计数据!$B$9<AB30,"低于上限","达到或超过上限")) -> 低于上限 | AD30: 3-一般
A31: T2026030 | B31: 601899 | C31: 103809 | D31: 0.01 | E31: 20 | F31: =IF(OR(C31="",D31="",E31="",N31="",C31<=0,D31<=0,E31<=N31),"",ROUNDDOWN((C31*D31)/(E31-N31)/100,0)*100) -> 800 | G31: =IF(OR(A31="",F31="",E31="",N31="",E31<=N31,账户数据!$B$7=""),"",IF(账户数据!$B$9+IF(H31="",F31*(E31-N31),0)>=账户数据!$B$7,"禁止开仓","允许开仓")) -> 禁止开仓 | H31: 800 | I31: 46157 | J31: 22 | L31: =IF(K31="","",H31) | N31: 18.75 | O31: 0 | P31: 5 | Q31: 压力位与量价背离共同确认 | R31: 止损设在18.75 | S31: 目标参考板块共振 | U31: =IF(OR(E31="",J31="",E31<=0),"",(J31-E31)/E31) -> 0.1 | V31: =IF(OR(E31="",N31="",E31<=0),"",(E31-N31)/E31) -> 0.0625 | W31: =IF(OR(U31="",V31="",V31<=0),"",U31/V31) -> 1.6 | X31: =IF(OR(K31="",L31="",E31="",H31=""),"",K31*L31-E31*H31-IF(O31="",0,O31)-IF(P31="",0,P31)) | Y31: =IF(OR(X31="",E31="",H31=""),"",IF(E31*H31+IF(O31="",0,O31)<=0,"",X31/(E31*H31+IF(O31="",0,O31)))) | Z31: =IF(OR(Y31="",多次统计数据!$B$8=""),"",Y31-多次统计数据!$B$8) | AA31: =IF(OR(I31="",M31="",M31<I31),"",M31-I31) | AB31: =IF(OR(A31="",多次统计数据!$B$8="",多次统计数据!$B$6<=0,多次统计数据!$B$6>=1),"",1-POWER(1+多次统计数据!$B$8,-多次统计数据!$B$6/(1-多次统计数据!$B$6))) -> 0.11918507 | AC31: =IF(OR(AB31="",多次统计数据!$B$9=""),"",IF(多次统计数据!$B$9<AB31,"低于上限","达到或超过上限")) -> 低于上限
A32: T2026031 | B32: 600519 | C32: 103809 | D32: 0.01 | E32: 21.25 | F32: =IF(OR(C32="",D32="",E32="",N32="",C32<=0,D32<=0,E32<=N32),"",ROUNDDOWN((C32*D32)/(E32-N32)/100,0)*100) -> 600 | G32: =IF(OR(A32="",F32="",E32="",N32="",E32<=N32,账户数据!$B$7=""),"",IF(账户数据!$B$9+IF(H32="",F32*(E32-N32),0)>=账户数据!$B$7,"禁止开仓","允许开仓")) -> 禁止开仓 | H32: 100 | I32: 46158 | J32: 23.38 | K32: 24.01 | L32: =IF(K32="","",H32) -> 100 | M32: 46162 | N32: 19.75 | O32: 5 | P32: 5 | Q32: 缺口与趋势背离共同确认 | R32: 止损设在19.75 | S32: 目标参考蜡烛图 | T32: 按计划成交 | U32: =IF(OR(E32="",J32="",E32<=0),"",(J32-E32)/E32) -> 0.10023529 | V32: =IF(OR(E32="",N32="",E32<=0),"",(E32-N32)/E32) -> 0.070588235 | W32: =IF(OR(U32="",V32="",V32<=0),"",U32/V32) -> 1.42 | X32: =IF(OR(K32="",L32="",E32="",H32=""),"",K32*L32-E32*H32-IF(O32="",0,O32)-IF(P32="",0,P32)) -> 266 | Y32: =IF(OR(X32="",E32="",H32=""),"",IF(E32*H32+IF(O32="",0,O32)<=0,"",X32/(E32*H32+IF(O32="",0,O32)))) -> 0.12488263 | Z32: =IF(OR(Y32="",多次统计数据!$B$8=""),"",Y32-多次统计数据!$B$8) -> -0.003248461 | AA32: =IF(OR(I32="",M32="",M32<I32),"",M32-I32) -> 4 | AB32: =IF(OR(A32="",多次统计数据!$B$8="",多次统计数据!$B$6<=0,多次统计数据!$B$6>=1),"",1-POWER(1+多次统计数据!$B$8,-多次统计数据!$B$6/(1-多次统计数据!$B$6))) -> 0.11918507 | AC32: =IF(OR(AB32="",多次统计数据!$B$9=""),"",IF(多次统计数据!$B$9<AB32,"低于上限","达到或超过上限")) -> 低于上限 | AD32: 4-良好
A33: T2026032 | B33: 000001 | C33: 104075 | D33: 0.01 | E33: 22.5 | F33: =IF(OR(C33="",D33="",E33="",N33="",C33<=0,D33<=0,E33<=N33),"",ROUNDDOWN((C33*D33)/(E33-N33)/100,0)*100) -> 1300 | G33: =IF(OR(A33="",F33="",E33="",N33="",E33<=N33,账户数据!$B$7=""),"",IF(账户数据!$B$9+IF(H33="",F33*(E33-N33),0)>=账户数据!$B$7,"禁止开仓","允许开仓")) -> 禁止开仓 | H33: 500 | I33: 46159 | J33: 24.75 | K33: 25.65 | L33: =IF(K33="","",H33) -> 500 | M33: 46164 | N33: 21.75 | O33: 5 | P33: 0 | Q33: 形态突破与ATR共同确认 | R33: 止损设在21.75 | S33: 目标参考趋势线 | T33: 按计划成交 | U33: =IF(OR(E33="",J33="",E33<=0),"",(J33-E33)/E33) -> 0.1 | V33: =IF(OR(E33="",N33="",E33<=0),"",(E33-N33)/E33) -> 0.033333333 | W33: =IF(OR(U33="",V33="",V33<=0),"",U33/V33) -> 3 | X33: =IF(OR(K33="",L33="",E33="",H33=""),"",K33*L33-E33*H33-IF(O33="",0,O33)-IF(P33="",0,P33)) -> 1570 | Y33: =IF(OR(X33="",E33="",H33=""),"",IF(E33*H33+IF(O33="",0,O33)<=0,"",X33/(E33*H33+IF(O33="",0,O33)))) -> 0.13949356 | Z33: =IF(OR(Y33="",多次统计数据!$B$8=""),"",Y33-多次统计数据!$B$8) -> 0.011362468 | AA33: =IF(OR(I33="",M33="",M33<I33),"",M33-I33) -> 5 | AB33: =IF(OR(A33="",多次统计数据!$B$8="",多次统计数据!$B$6<=0,多次统计数据!$B$6>=1),"",1-POWER(1+多次统计数据!$B$8,-多次统计数据!$B$6/(1-多次统计数据!$B$6))) -> 0.11918507 | AC33: =IF(OR(AB33="",多次统计数据!$B$9=""),"",IF(多次统计数据!$B$9<AB33,"低于上限","达到或超过上限")) -> 低于上限 | AD33: 4-良好
A34: T2026033 | B34: 300750 | C34: 105645 | D34: 0.01 | E34: 10 | F34: =IF(OR(C34="",D34="",E34="",N34="",C34<=0,D34<=0,E34<=N34),"",ROUNDDOWN((C34*D34)/(E34-N34)/100,0)*100) -> 1000 | G34: =IF(OR(A34="",F34="",E34="",N34="",E34<=N34,账户数据!$B$7=""),"",IF(账户数据!$B$9+IF(H34="",F34*(E34-N34),0)>=账户数据!$B$7,"禁止开仓","允许开仓")) -> 禁止开仓 | H34: 600 | I34: 46160 | J34: 11 | K34: 11.2 | L34: =IF(K34="","",H34) -> 600 | M34: 46166 | N34: 9 | O34: 0 | P34: 5 | Q34: 均线金叉与换手率共同确认 | R34: 止损设在9.00 | S34: 目标参考MACD | T34: 按计划成交 | U34: =IF(OR(E34="",J34="",E34<=0),"",(J34-E34)/E34) -> 0.1 | V34: =IF(OR(E34="",N34="",E34<=0),"",(E34-N34)/E34) -> 0.1 | W34: =IF(OR(U34="",V34="",V34<=0),"",U34/V34) -> 1 | X34: =IF(OR(K34="",L34="",E34="",H34=""),"",K34*L34-E34*H34-IF(O34="",0,O34)-IF(P34="",0,P34)) -> 715 | Y34: =IF(OR(X34="",E34="",H34=""),"",IF(E34*H34+IF(O34="",0,O34)<=0,"",X34/(E34*H34+IF(O34="",0,O34)))) -> 0.11916667 | Z34: =IF(OR(Y34="",多次统计数据!$B$8=""),"",Y34-多次统计数据!$B$8) -> -0.0089644234 | AA34: =IF(OR(I34="",M34="",M34<I34),"",M34-I34) -> 6 | AB34: =IF(OR(A34="",多次统计数据!$B$8="",多次统计数据!$B$6<=0,多次统计数据!$B$6>=1),"",1-POWER(1+多次统计数据!$B$8,-多次统计数据!$B$6/(1-多次统计数据!$B$6))) -> 0.11918507 | AC34: =IF(OR(AB34="",多次统计数据!$B$9=""),"",IF(多次统计数据!$B$9<AB34,"低于上限","达到或超过上限")) -> 低于上限 | AD34: 4-良好
A35: T2026034 | B35: 002594 | C35: 106360 | D35: 0.01 | E35: 11.25 | F35: =IF(OR(C35="",D35="",E35="",N35="",C35<=0,D35<=0,E35<=N35),"",ROUNDDOWN((C35*D35)/(E35-N35)/100,0)*100) -> 800 | G35: =IF(OR(A35="",F35="",E35="",N35="",E35<=N35,账户数据!$B$7=""),"",IF(账户数据!$B$9+IF(H35="",F35*(E35-N35),0)>=账户数据!$B$7,"禁止开仓","允许开仓")) -> 禁止开仓 | H35: 600 | I35: 46161 | J35: 12.38 | K35: 12.71 | L35: =IF(K35="","",H35) -> 600 | M35: 46168 | N35: 10 | O35: 5 | P35: 5 | Q35: 均线死叉与相对强弱共同确认 | R35: 止损设在10.00 | S35: 目标参考移动平均线 | T35: 按计划成交 | U35: =IF(OR(E35="",J35="",E35<=0),"",(J35-E35)/E35) -> 0.10044444 | V35: =IF(OR(E35="",N35="",E35<=0),"",(E35-N35)/E35) -> 0.11111111 | W35: =IF(OR(U35="",V35="",V35<=0),"",U35/V35) -> 0.904 | X35: =IF(OR(K35="",L35="",E35="",H35=""),"",K35*L35-E35*H35-IF(O35="",0,O35)-IF(P35="",0,P35)) -> 866 | Y35: =IF(OR(X35="",E35="",H35=""),"",IF(E35*H35+IF(O35="",0,O35)<=0,"",X35/(E35*H35+IF(O35="",0,O35)))) -> 0.12820133 | Z35: =IF(OR(Y35="",多次统计数据!$B$8=""),"",Y35-多次统计数据!$B$8) -> 7.0242274e-05 | AA35: =IF(OR(I35="",M35="",M35<I35),"",M35-I35) -> 7 | AB35: =IF(OR(A35="",多次统计数据!$B$8="",多次统计数据!$B$6<=0,多次统计数据!$B$6>=1),"",1-POWER(1+多次统计数据!$B$8,-多次统计数据!$B$6/(1-多次统计数据!$B$6))) -> 0.11918507 | AC35: =IF(OR(AB35="",多次统计数据!$B$9=""),"",IF(多次统计数据!$B$9<AB35,"低于上限","达到或超过上限")) -> 低于上限 | AD35: 4-良好
A36: T2026035 | B36: 601318 | C36: 107226 | D36: 0.01 | E36: 12.5 | F36: =IF(OR(C36="",D36="",E36="",N36="",C36<=0,D36<=0,E36<=N36),"",ROUNDDOWN((C36*D36)/(E36-N36)/100,0)*100) -> 700 | G36: =IF(OR(A36="",F36="",E36="",N36="",E36<=N36,账户数据!$B$7=""),"",IF(账户数据!$B$9+IF(H36="",F36*(E36-N36),0)>=账户数据!$B$7,"禁止开仓","允许开仓")) -> 禁止开仓 | H36: 700 | I36: 46162 | J36: 13.75 | K36: 11 | L36: =IF(K36="","",H36) -> 700 | M36: 46163 | N36: 11 | O36: 5 | P36: 5 | Q36: 量价背离与板块共振共同确认 | R36: 止损设在11.00 | S36: 目标参考成交量 | T36: 按计划成交 | U36: =IF(OR(E36="",J36="",E36<=0),"",(J36-E36)/E36) -> 0.1 | V36: =IF(OR(E36="",N36="",E36<=0),"",(E36-N36)/E36) -> 0.12 | W36: =IF(OR(U36="",V36="",V36<=0),"",U36/V36) -> 0.83333333 | X36: =IF(OR(K36="",L36="",E36="",H36=""),"",K36*L36-E36*H36-IF(O36="",0,O36)-IF(P36="",0,P36)) -> -1060 | Y36: =IF(OR(X36="",E36="",H36=""),"",IF(E36*H36+IF(O36="",0,O36)<=0,"",X36/(E36*H36+IF(O36="",0,O36)))) -> -0.12107367 | Z36: =IF(OR(Y36="",多次统计数据!$B$8=""),"",Y36-多次统计数据!$B$8) -> -0.24920476 | AA36: =IF(OR(I36="",M36="",M36<I36),"",M36-I36) -> 1 | AB36: =IF(OR(A36="",多次统计数据!$B$8="",多次统计数据!$B$6<=0,多次统计数据!$B$6>=1),"",1-POWER(1+多次统计数据!$B$8,-多次统计数据!$B$6/(1-多次统计数据!$B$6))) -> 0.11918507 | AC36: =IF(OR(AB36="",多次统计数据!$B$9=""),"",IF(多次统计数据!$B$9<AB36,"低于上限","达到或超过上限")) -> 低于上限 | AD36: 2-较差
A37: T2026036 | B37: 688981 | C37: 106166 | D37: 0.01 | E37: 13.75 | F37: =IF(OR(C37="",D37="",E37="",N37="",C37<=0,D37<=0,E37<=N37),"",ROUNDDOWN((C37*D37)/(E37-N37)/100,0)*100) -> 1400 | G37: =IF(OR(A37="",F37="",E37="",N37="",E37<=N37,账户数据!$B$7=""),"",IF(账户数据!$B$9+IF(H37="",F37*(E37-N37),0)>=账户数据!$B$7,"禁止开仓","允许开仓")) -> 禁止开仓 | H37: 200 | I37: 46163 | J37: 15.13 | K37: 13 | L37: =IF(K37="","",H37) -> 200 | M37: 46165 | N37: 13 | O37: 0 | P37: 0 | Q37: 趋势背离与蜡烛图共同确认 | R37: 止损设在13.00 | S37: 目标参考RSI | T37: 按计划成交 | U37: =IF(OR(E37="",J37="",E37<=0),"",(J37-E37)/E37) -> 0.10036364 | V37: =IF(OR(E37="",N37="",E37<=0),"",(E37-N37)/E37) -> 0.054545455 | W37: =IF(OR(U37="",V37="",V37<=0),"",U37/V37) -> 1.84 | X37: =IF(OR(K37="",L37="",E37="",H37=""),"",K37*L37-E37*H37-IF(O37="",0,O37)-IF(P37="",0,P37)) -> -150 | Y37: =IF(OR(X37="",E37="",H37=""),"",IF(E37*H37+IF(O37="",0,O37)<=0,"",X37/(E37*H37+IF(O37="",0,O37)))) -> -0.054545455 | Z37: =IF(OR(Y37="",多次统计数据!$B$8=""),"",Y37-多次统计数据!$B$8) -> -0.18267654 | AA37: =IF(OR(I37="",M37="",M37<I37),"",M37-I37) -> 2 | AB37: =IF(OR(A37="",多次统计数据!$B$8="",多次统计数据!$B$6<=0,多次统计数据!$B$6>=1),"",1-POWER(1+多次统计数据!$B$8,-多次统计数据!$B$6/(1-多次统计数据!$B$6))) -> 0.11918507 | AC37: =IF(OR(AB37="",多次统计数据!$B$9=""),"",IF(多次统计数据!$B$9<AB37,"低于上限","达到或超过上限")) -> 低于上限 | AD37: 2-较差
A38: T2026037 | B38: 000858 | C38: 106016 | D38: 0.01 | E38: 15 | F38: =IF(OR(C38="",D38="",E38="",N38="",C38<=0,D38<=0,E38<=N38),"",ROUNDDOWN((C38*D38)/(E38-N38)/100,0)*100) -> 1000 | G38: =IF(OR(A38="",F38="",E38="",N38="",E38<=N38,账户数据!$B$7=""),"",IF(账户数据!$B$9+IF(H38="",F38*(E38-N38),0)>=账户数据!$B$7,"禁止开仓","允许开仓")) -> 禁止开仓 | H38: 400 | I38: 46164 | J38: 16.5 | K38: 14 | L38: =IF(K38="","",H38) -> 400 | M38: 46167 | N38: 14 | O38: 5 | P38: 5 | Q38: ATR与趋势线共同确认 | R38: 止损设在14.00 | S38: 目标参考KDJ | T38: 按计划成交 | U38: =IF(OR(E38="",J38="",E38<=0),"",(J38-E38)/E38) -> 0.1 | V38: =IF(OR(E38="",N38="",E38<=0),"",(E38-N38)/E38) -> 0.066666667 | W38: =IF(OR(U38="",V38="",V38<=0),"",U38/V38) -> 1.5 | X38: =IF(OR(K38="",L38="",E38="",H38=""),"",K38*L38-E38*H38-IF(O38="",0,O38)-IF(P38="",0,P38)) -> -410 | Y38: =IF(OR(X38="",E38="",H38=""),"",IF(E38*H38+IF(O38="",0,O38)<=0,"",X38/(E38*H38+IF(O38="",0,O38)))) -> -0.068276436 | Z38: =IF(OR(Y38="",多次统计数据!$B$8=""),"",Y38-多次统计数据!$B$8) -> -0.19640753 | AA38: =IF(OR(I38="",M38="",M38<I38),"",M38-I38) -> 3 | AB38: =IF(OR(A38="",多次统计数据!$B$8="",多次统计数据!$B$6<=0,多次统计数据!$B$6>=1),"",1-POWER(1+多次统计数据!$B$8,-多次统计数据!$B$6/(1-多次统计数据!$B$6))) -> 0.11918507 | AC38: =IF(OR(AB38="",多次统计数据!$B$9=""),"",IF(多次统计数据!$B$9<AB38,"低于上限","达到或超过上限")) -> 低于上限 | AD38: 2-较差
A39: T2026038 | B39: 600036 | C39: 105606 | D39: 0.01 | E39: 16.25 | F39: =IF(OR(C39="",D39="",E39="",N39="",C39<=0,D39<=0,E39<=N39),"",ROUNDDOWN((C39*D39)/(E39-N39)/100,0)*100) -> 800 | G39: =IF(OR(A39="",F39="",E39="",N39="",E39<=N39,账户数据!$B$7=""),"",IF(账户数据!$B$9+IF(H39="",F39*(E39-N39),0)>=账户数据!$B$7,"禁止开仓","允许开仓")) -> 禁止开仓 | H39: 400 | I39: 46165 | J39: 17.88 | K39: 15 | L39: =IF(K39="","",H39) -> 400 | M39: 46169 | N39: 15 | O39: 5 | P39: 5 | Q39: 换手率与MACD共同确认 | R39: 止损设在15.00 | S39: 目标参考布林带 | T39: 按计划成交 | U39: =IF(OR(E39="",J39="",E39<=0),"",(J39-E39)/E39) -> 0.10030769 | V39: =IF(OR(E39="",N39="",E39<=0),"",(E39-N39)/E39) -> 0.076923077 | W39: =IF(OR(U39="",V39="",V39<=0),"",U39/V39) -> 1.304 | X39: =IF(OR(K39="",L39="",E39="",H39=""),"",K39*L39-E39*H39-IF(O39="",0,O39)-IF(P39="",0,P39)) -> -510 | Y39: =IF(OR(X39="",E39="",H39=""),"",IF(E39*H39+IF(O39="",0,O39)<=0,"",X39/(E39*H39+IF(O39="",0,O39)))) -> -0.07840123 | Z39: =IF(OR(Y39="",多次统计数据!$B$8=""),"",Y39-多次统计数据!$B$8) -> -0.20653232 | AA39: =IF(OR(I39="",M39="",M39<I39),"",M39-I39) -> 4 | AB39: =IF(OR(A39="",多次统计数据!$B$8="",多次统计数据!$B$6<=0,多次统计数据!$B$6>=1),"",1-POWER(1+多次统计数据!$B$8,-多次统计数据!$B$6/(1-多次统计数据!$B$6))) -> 0.11918507 | AC39: =IF(OR(AB39="",多次统计数据!$B$9=""),"",IF(多次统计数据!$B$9<AB39,"低于上限","达到或超过上限")) -> 低于上限 | AD39: 2-较差
A40: T2026039 | B40: 002415 | C40: 105096 | D40: 0.01 | E40: 17.5 | F40: =IF(OR(C40="",D40="",E40="",N40="",C40<=0,D40<=0,E40<=N40),"",ROUNDDOWN((C40*D40)/(E40-N40)/100,0)*100) -> 700 | G40: =IF(OR(A40="",F40="",E40="",N40="",E40<=N40,账户数据!$B$7=""),"",IF(账户数据!$B$9+IF(H40="",F40*(E40-N40),0)>=账户数据!$B$7,"禁止开仓","允许开仓")) -> 禁止开仓 | H40: 500 | I40: 46166 | J40: 19.25 | K40: 17.5 | L40: =IF(K40="","",H40) -> 500 | M40: 46171 | N40: 16 | O40: 0 | P40: 0 | Q40: 相对强弱与移动平均线共同确认 | R40: 止损设在16.00 | S40: 目标参考支撑位 | T40: 按计划成交 | U40: =IF(OR(E40="",J40="",E40<=0),"",(J40-E40)/E40) -> 0.1 | V40: =IF(OR(E40="",N40="",E40<=0),"",(E40-N40)/E40) -> 0.085714286 | W40: =IF(OR(U40="",V40="",V40<=0),"",U40/V40) -> 1.1666667 | X40: =IF(OR(K40="",L40="",E40="",H40=""),"",K40*L40-E40*H40-IF(O40="",0,O40)-IF(P40="",0,P40)) -> 0 | Y40: =IF(OR(X40="",E40="",H40=""),"",IF(E40*H40+IF(O40="",0,O40)<=0,"",X40/(E40*H40+IF(O40="",0,O40)))) -> 0 | Z40: =IF(OR(Y40="",多次统计数据!$B$8=""),"",Y40-多次统计数据!$B$8) -> -0.12813109 | AA40: =IF(OR(I40="",M40="",M40<I40),"",M40-I40) -> 5 | AB40: =IF(OR(A40="",多次统计数据!$B$8="",多次统计数据!$B$6<=0,多次统计数据!$B$6>=1),"",1-POWER(1+多次统计数据!$B$8,-多次统计数据!$B$6/(1-多次统计数据!$B$6))) -> 0.11918507 | AC40: =IF(OR(AB40="",多次统计数据!$B$9=""),"",IF(多次统计数据!$B$9<AB40,"低于上限","达到或超过上限")) -> 低于上限 | AD40: 3-一般
A41: T2026040 | B41: 601899 | C41: 105096 | D41: 0.01 | E41: 18.75 | F41: =IF(OR(C41="",D41="",E41="",N41="",C41<=0,D41<=0,E41<=N41),"",ROUNDDOWN((C41*D41)/(E41-N41)/100,0)*100) -> 1400 | G41: =IF(OR(A41="",F41="",E41="",N41="",E41<=N41,账户数据!$B$7=""),"",IF(账户数据!$B$9+IF(H41="",F41*(E41-N41),0)>=账户数据!$B$7,"禁止开仓","允许开仓")) -> 禁止开仓 | H41: 1400 | I41: 46167 | J41: 20.62 | L41: =IF(K41="","",H41) | N41: 18 | O41: 5 | P41: 0 | Q41: 板块共振与成交量共同确认 | R41: 止损设在18.00 | S41: 目标参考压力位 | U41: =IF(OR(E41="",J41="",E41<=0),"",(J41-E41)/E41) -> 0.099733333 | V41: =IF(OR(E41="",N41="",E41<=0),"",(E41-N41)/E41) -> 0.04 | W41: =IF(OR(U41="",V41="",V41<=0),"",U41/V41) -> 2.4933333 | X41: =IF(OR(K41="",L41="",E41="",H41=""),"",K41*L41-E41*H41-IF(O41="",0,O41)-IF(P41="",0,P41)) | Y41: =IF(OR(X41="",E41="",H41=""),"",IF(E41*H41+IF(O41="",0,O41)<=0,"",X41/(E41*H41+IF(O41="",0,O41)))) | Z41: =IF(OR(Y41="",多次统计数据!$B$8=""),"",Y41-多次统计数据!$B$8) | AA41: =IF(OR(I41="",M41="",M41<I41),"",M41-I41) | AB41: =IF(OR(A41="",多次统计数据!$B$8="",多次统计数据!$B$6<=0,多次统计数据!$B$6>=1),"",1-POWER(1+多次统计数据!$B$8,-多次统计数据!$B$6/(1-多次统计数据!$B$6))) -> 0.11918507 | AC41: =IF(OR(AB41="",多次统计数据!$B$9=""),"",IF(多次统计数据!$B$9<AB41,"低于上限","达到或超过上限")) -> 低于上限
A42: T2026041 | B42: 600519 | C42: 105096 | D42: 0.01 | E42: 20 | F42: =IF(OR(C42="",D42="",E42="",N42="",C42<=0,D42<=0,E42<=N42),"",ROUNDDOWN((C42*D42)/(E42-N42)/100,0)*100) -> 1000 | G42: =IF(OR(A42="",F42="",E42="",N42="",E42<=N42,账户数据!$B$7=""),"",IF(账户数据!$B$9+IF(H42="",F42*(E42-N42),0)>=账户数据!$B$7,"禁止开仓","允许开仓")) -> 禁止开仓 | H42: 200 | I42: 46168 | J42: 22 | K42: 22.8 | L42: =IF(K42="","",H42) -> 200 | M42: 46175 | N42: 19 | O42: 5 | P42: 5 | Q42: 蜡烛图与RSI共同确认 | R42: 止损设在19.00 | S42: 目标参考缺口 | T42: 按计划成交 | U42: =IF(OR(E42="",J42="",E42<=0),"",(J42-E42)/E42) -> 0.1 | V42: =IF(OR(E42="",N42="",E42<=0),"",(E42-N42)/E42) -> 0.05 | W42: =IF(OR(U42="",V42="",V42<=0),"",U42/V42) -> 2 | X42: =IF(OR(K42="",L42="",E42="",H42=""),"",K42*L42-E42*H42-IF(O42="",0,O42)-IF(P42="",0,P42)) -> 550 | Y42: =IF(OR(X42="",E42="",H42=""),"",IF(E42*H42+IF(O42="",0,O42)<=0,"",X42/(E42*H42+IF(O42="",0,O42)))) -> 0.13732834 | Z42: =IF(OR(Y42="",多次统计数据!$B$8=""),"",Y42-多次统计数据!$B$8) -> 0.0091972495 | AA42: =IF(OR(I42="",M42="",M42<I42),"",M42-I42) -> 7 | AB42: =IF(OR(A42="",多次统计数据!$B$8="",多次统计数据!$B$6<=0,多次统计数据!$B$6>=1),"",1-POWER(1+多次统计数据!$B$8,-多次统计数据!$B$6/(1-多次统计数据!$B$6))) -> 0.11918507 | AC42: =IF(OR(AB42="",多次统计数据!$B$9=""),"",IF(多次统计数据!$B$9<AB42,"低于上限","达到或超过上限")) -> 低于上限 | AD42: 4-良好
A43: T2026042 | B43: 000001 | C43: 105646 | D43: 0.01 | E43: 21.25 | F43: =IF(OR(C43="",D43="",E43="",N43="",C43<=0,D43<=0,E43<=N43),"",ROUNDDOWN((C43*D43)/(E43-N43)/100,0)*100) -> 800 | G43: =IF(OR(A43="",F43="",E43="",N43="",E43<=N43,账户数据!$B$7=""),"",IF(账户数据!$B$9+IF(H43="",F43*(E43-N43),0)>=账户数据!$B$7,"禁止开仓","允许开仓")) -> 禁止开仓 | H43: 300 | I43: 46169 | J43: 23.38 | K43: 23.8 | L43: =IF(K43="","",H43) -> 300 | M43: 46170 | N43: 20 | O43: 0 | P43: 5 | Q43: 趋势线与KDJ共同确认 | R43: 止损设在20.00 | S43: 目标参考形态突破 | T43: 按计划成交 | U43: =IF(OR(E43="",J43="",E43<=0),"",(J43-E43)/E43) -> 0.10023529 | V43: =IF(OR(E43="",N43="",E43<=0),"",(E43-N43)/E43) -> 0.058823529 | W43: =IF(OR(U43="",V43="",V43<=0),"",U43/V43) -> 1.704 | X43: =IF(OR(K43="",L43="",E43="",H43=""),"",K43*L43-E43*H43-IF(O43="",0,O43)-IF(P43="",0,P43)) -> 760 | Y43: =IF(OR(X43="",E43="",H43=""),"",IF(E43*H43+IF(O43="",0,O43)<=0,"",X43/(E43*H43+IF(O43="",0,O43)))) -> 0.11921569 | Z43: =IF(OR(Y43="",多次统计数据!$B$8=""),"",Y43-多次统计数据!$B$8) -> -0.0089154038 | AA43: =IF(OR(I43="",M43="",M43<I43),"",M43-I43) -> 1 | AB43: =IF(OR(A43="",多次统计数据!$B$8="",多次统计数据!$B$6<=0,多次统计数据!$B$6>=1),"",1-POWER(1+多次统计数据!$B$8,-多次统计数据!$B$6/(1-多次统计数据!$B$6))) -> 0.11918507 | AC43: =IF(OR(AB43="",多次统计数据!$B$9=""),"",IF(多次统计数据!$B$9<AB43,"低于上限","达到或超过上限")) -> 低于上限 | AD43: 4-良好
A44: T2026043 | B44: 300750 | C44: 106406 | D44: 0.01 | E44: 22.5 | F44: =IF(OR(C44="",D44="",E44="",N44="",C44<=0,D44<=0,E44<=N44),"",ROUNDDOWN((C44*D44)/(E44-N44)/100,0)*100) -> 700 | G44: =IF(OR(A44="",F44="",E44="",N44="",E44<=N44,账户数据!$B$7=""),"",IF(账户数据!$B$9+IF(H44="",F44*(E44-N44),0)>=账户数据!$B$7,"禁止开仓","允许开仓")) -> 禁止开仓 | H44: 400 | I44: 46170 | J44: 24.75 | K44: 25.43 | L44: =IF(K44="","",H44) -> 400 | M44: 46172 | N44: 21 | O44: 5 | P44: 5 | Q44: MACD与布林带共同确认 | R44: 止损设在21.00 | S44: 目标参考均线金叉 | T44: 按计划成交 | U44: =IF(OR(E44="",J44="",E44<=0),"",(J44-E44)/E44) -> 0.1 | V44: =IF(OR(E44="",N44="",E44<=0),"",(E44-N44)/E44) -> 0.066666667 | W44: =IF(OR(U44="",V44="",V44<=0),"",U44/V44) -> 1.5 | X44: =IF(OR(K44="",L44="",E44="",H44=""),"",K44*L44-E44*H44-IF(O44="",0,O44)-IF(P44="",0,P44)) -> 1162 | Y44: =IF(OR(X44="",E44="",H44=""),"",IF(E44*H44+IF(O44="",0,O44)<=0,"",X44/(E44*H44+IF(O44="",0,O44)))) -> 0.12903942 | Z44: =IF(OR(Y44="",多次统计数据!$B$8=""),"",Y44-多次统计数据!$B$8) -> 0.00090833247 | AA44: =IF(OR(I44="",M44="",M44<I44),"",M44-I44) -> 2 | AB44: =IF(OR(A44="",多次统计数据!$B$8="",多次统计数据!$B$6<=0,多次统计数据!$B$6>=1),"",1-POWER(1+多次统计数据!$B$8,-多次统计数据!$B$6/(1-多次统计数据!$B$6))) -> 0.11918507 | AC44: =IF(OR(AB44="",多次统计数据!$B$9=""),"",IF(多次统计数据!$B$9<AB44,"低于上限","达到或超过上限")) -> 低于上限 | AD44: 4-良好
A45: T2026044 | B45: 002594 | C45: 107568 | D45: 0.01 | E45: 10 | F45: =IF(OR(C45="",D45="",E45="",N45="",C45<=0,D45<=0,E45<=N45),"",ROUNDDOWN((C45*D45)/(E45-N45)/100,0)*100) -> 1400 | G45: =IF(OR(A45="",F45="",E45="",N45="",E45<=N45,账户数据!$B$7=""),"",IF(账户数据!$B$9+IF(H45="",F45*(E45-N45),0)>=账户数据!$B$7,"禁止开仓","允许开仓")) -> 禁止开仓 | H45: 1100 | I45: 46171 | J45: 11 | K45: 11.4 | L45: =IF(K45="","",H45) -> 1100 | M45: 46174 | N45: 9.25 | O45: 5 | P45: 0 | Q45: 移动平均线与支撑位共同确认 | R45: 止损设在9.25 | S45: 目标参考均线死叉 | T45: 按计划成交 | U45: =IF(OR(E45="",J45="",E45<=0),"",(J45-E45)/E45) -> 0.1 | V45: =IF(OR(E45="",N45="",E45<=0),"",(E45-N45)/E45) -> 0.075 | W45: =IF(OR(U45="",V45="",V45<=0),"",U45/V45) -> 1.3333333 | X45: =IF(OR(K45="",L45="",E45="",H45=""),"",K45*L45-E45*H45-IF(O45="",0,O45)-IF(P45="",0,P45)) -> 1535 | Y45: =IF(OR(X45="",E45="",H45=""),"",IF(E45*H45+IF(O45="",0,O45)<=0,"",X45/(E45*H45+IF(O45="",0,O45)))) -> 0.13948205 | Z45: =IF(OR(Y45="",多次统计数据!$B$8=""),"",Y45-多次统计数据!$B$8) -> 0.011350964 | AA45: =IF(OR(I45="",M45="",M45<I45),"",M45-I45) -> 3 | AB45: =IF(OR(A45="",多次统计数据!$B$8="",多次统计数据!$B$6<=0,多次统计数据!$B$6>=1),"",1-POWER(1+多次统计数据!$B$8,-多次统计数据!$B$6/(1-多次统计数据!$B$6))) -> 0.11918507 | AC45: =IF(OR(AB45="",多次统计数据!$B$9=""),"",IF(多次统计数据!$B$9<AB45,"低于上限","达到或超过上限")) -> 低于上限 | AD45: 4-良好
A46: T2026045 | B46: 601318 | C46: 109103 | D46: 0.01 | E46: 11.25 | F46: =IF(OR(C46="",D46="",E46="",N46="",C46<=0,D46<=0,E46<=N46),"",ROUNDDOWN((C46*D46)/(E46-N46)/100,0)*100) -> 1000 | G46: =IF(OR(A46="",F46="",E46="",N46="",E46<=N46,账户数据!$B$7=""),"",IF(账户数据!$B$9+IF(H46="",F46*(E46-N46),0)>=账户数据!$B$7,"禁止开仓","允许开仓")) -> 禁止开仓 | H46: 1000 | I46: 46172 | J46: 12.38 | K46: 10.25 | L46: =IF(K46="","",H46) -> 1000 | M46: 46176 | N46: 10.25 | O46: 0 | P46: 5 | Q46: 成交量与压力位共同确认 | R46: 止损设在10.25 | S46: 目标参考量价背离 | T46: 按计划成交 | U46: =IF(OR(E46="",J46="",E46<=0),"",(J46-E46)/E46) -> 0.10044444 | V46: =IF(OR(E46="",N46="",E46<=0),"",(E46-N46)/E46) -> 0.088888889 | W46: =IF(OR(U46="",V46="",V46<=0),"",U46/V46) -> 1.13 | X46: =IF(OR(K46="",L46="",E46="",H46=""),"",K46*L46-E46*H46-IF(O46="",0,O46)-IF(P46="",0,P46)) -> -1005 | Y46: =IF(OR(X46="",E46="",H46=""),"",IF(E46*H46+IF(O46="",0,O46)<=0,"",X46/(E46*H46+IF(O46="",0,O46)))) -> -0.089333333 | Z46: =IF(OR(Y46="",多次统计数据!$B$8=""),"",Y46-多次统计数据!$B$8) -> -0.21746442 | AA46: =IF(OR(I46="",M46="",M46<I46),"",M46-I46) -> 4 | AB46: =IF(OR(A46="",多次统计数据!$B$8="",多次统计数据!$B$6<=0,多次统计数据!$B$6>=1),"",1-POWER(1+多次统计数据!$B$8,-多次统计数据!$B$6/(1-多次统计数据!$B$6))) -> 0.11918507 | AC46: =IF(OR(AB46="",多次统计数据!$B$9=""),"",IF(多次统计数据!$B$9<AB46,"低于上限","达到或超过上限")) -> 低于上限 | AD46: 2-较差
A47: T2026046 | B47: 688981 | C47: 108098 | D47: 0.01 | E47: 12.5 | F47: =IF(OR(C47="",D47="",E47="",N47="",C47<=0,D47<=0,E47<=N47),"",ROUNDDOWN((C47*D47)/(E47-N47)/100,0)*100) -> 800 | G47: =IF(OR(A47="",F47="",E47="",N47="",E47<=N47,账户数据!$B$7=""),"",IF(账户数据!$B$9+IF(H47="",F47*(E47-N47),0)>=账户数据!$B$7,"禁止开仓","允许开仓")) -> 禁止开仓 | H47: 100 | I47: 46173 | J47: 13.75 | K47: 11.25 | L47: =IF(K47="","",H47) -> 100 | M47: 46178 | N47: 11.25 | O47: 5 | P47: 5 | Q47: RSI与缺口共同确认 | R47: 止损设在11.25 | S47: 目标参考趋势背离 | T47: 按计划成交 | U47: =IF(OR(E47="",J47="",E47<=0),"",(J47-E47)/E47) -> 0.1 | V47: =IF(OR(E47="",N47="",E47<=0),"",(E47-N47)/E47) -> 0.1 | W47: =IF(OR(U47="",V47="",V47<=0),"",U47/V47) -> 1 | X47: =IF(OR(K47="",L47="",E47="",H47=""),"",K47*L47-E47*H47-IF(O47="",0,O47)-IF(P47="",0,P47)) -> -135 | Y47: =IF(OR(X47="",E47="",H47=""),"",IF(E47*H47+IF(O47="",0,O47)<=0,"",X47/(E47*H47+IF(O47="",0,O47)))) -> -0.10756972 | Z47: =IF(OR(Y47="",多次统计数据!$B$8=""),"",Y47-多次统计数据!$B$8) -> -0.23570081 | AA47: =IF(OR(I47="",M47="",M47<I47),"",M47-I47) -> 5 | AB47: =IF(OR(A47="",多次统计数据!$B$8="",多次统计数据!$B$6<=0,多次统计数据!$B$6>=1),"",1-POWER(1+多次统计数据!$B$8,-多次统计数据!$B$6/(1-多次统计数据!$B$6))) -> 0.11918507 | AC47: =IF(OR(AB47="",多次统计数据!$B$9=""),"",IF(多次统计数据!$B$9<AB47,"低于上限","达到或超过上限")) -> 低于上限 | AD47: 2-较差
A48: T2026047 | B48: 000858 | C48: 107963 | D48: 0.01 | E48: 13.75 | F48: =IF(OR(C48="",D48="",E48="",N48="",C48<=0,D48<=0,E48<=N48),"",ROUNDDOWN((C48*D48)/(E48-N48)/100,0)*100) -> 700 | G48: =IF(OR(A48="",F48="",E48="",N48="",E48<=N48,账户数据!$B$7=""),"",IF(账户数据!$B$9+IF(H48="",F48*(E48-N48),0)>=账户数据!$B$7,"禁止开仓","允许开仓")) -> 禁止开仓 | H48: 200 | I48: 46174 | J48: 15.13 | K48: 12.25 | L48: =IF(K48="","",H48) -> 200 | M48: 46180 | N48: 12.25 | O48: 5 | P48: 5 | Q48: KDJ与形态突破共同确认 | R48: 止损设在12.25 | S48: 目标参考ATR | T48: 按计划成交 | U48: =IF(OR(E48="",J48="",E48<=0),"",(J48-E48)/E48) -> 0.10036364 | V48: =IF(OR(E48="",N48="",E48<=0),"",(E48-N48)/E48) -> 0.10909091 | W48: =IF(OR(U48="",V48="",V48<=0),"",U48/V48) -> 0.92 | X48: =IF(OR(K48="",L48="",E48="",H48=""),"",K48*L48-E48*H48-IF(O48="",0,O48)-IF(P48="",0,P48)) -> -310 | Y48: =IF(OR(X48="",E48="",H48=""),"",IF(E48*H48+IF(O48="",0,O48)<=0,"",X48/(E48*H48+IF(O48="",0,O48)))) -> -0.11252269 | Z48: =IF(OR(Y48="",多次统计数据!$B$8=""),"",Y48-多次统计数据!$B$8) -> -0.24065378 | AA48: =IF(OR(I48="",M48="",M48<I48),"",M48-I48) -> 6 | AB48: =IF(OR(A48="",多次统计数据!$B$8="",多次统计数据!$B$6<=0,多次统计数据!$B$6>=1),"",1-POWER(1+多次统计数据!$B$8,-多次统计数据!$B$6/(1-多次统计数据!$B$6))) -> 0.11918507 | AC48: =IF(OR(AB48="",多次统计数据!$B$9=""),"",IF(多次统计数据!$B$9<AB48,"低于上限","达到或超过上限")) -> 低于上限 | AD48: 2-较差
A49: T2026048 | B49: 600036 | C49: 107653 | D49: 0.01 | E49: 15 | F49: =IF(OR(C49="",D49="",E49="",N49="",C49<=0,D49<=0,E49<=N49),"",ROUNDDOWN((C49*D49)/(E49-N49)/100,0)*100) -> 1400 | G49: =IF(OR(A49="",F49="",E49="",N49="",E49<=N49,账户数据!$B$7=""),"",IF(账户数据!$B$9+IF(H49="",F49*(E49-N49),0)>=账户数据!$B$7,"禁止开仓","允许开仓")) -> 禁止开仓 | H49: 800 | I49: 46175 | J49: 16.5 | K49: 14.25 | L49: =IF(K49="","",H49) -> 800 | M49: 46182 | N49: 14.25 | O49: 0 | P49: 0 | Q49: 布林带与均线金叉共同确认 | R49: 止损设在14.25 | S49: 目标参考换手率 | T49: 按计划成交 | U49: =IF(OR(E49="",J49="",E49<=0),"",(J49-E49)/E49) -> 0.1 | V49: =IF(OR(E49="",N49="",E49<=0),"",(E49-N49)/E49) -> 0.05 | W49: =IF(OR(U49="",V49="",V49<=0),"",U49/V49) -> 2 | X49: =IF(OR(K49="",L49="",E49="",H49=""),"",K49*L49-E49*H49-IF(O49="",0,O49)-IF(P49="",0,P49)) -> -600 | Y49: =IF(OR(X49="",E49="",H49=""),"",IF(E49*H49+IF(O49="",0,O49)<=0,"",X49/(E49*H49+IF(O49="",0,O49)))) -> -0.05 | Z49: =IF(OR(Y49="",多次统计数据!$B$8=""),"",Y49-多次统计数据!$B$8) -> -0.17813109 | AA49: =IF(OR(I49="",M49="",M49<I49),"",M49-I49) -> 7 | AB49: =IF(OR(A49="",多次统计数据!$B$8="",多次统计数据!$B$6<=0,多次统计数据!$B$6>=1),"",1-POWER(1+多次统计数据!$B$8,-多次统计数据!$B$6/(1-多次统计数据!$B$6))) -> 0.11918507 | AC49: =IF(OR(AB49="",多次统计数据!$B$9=""),"",IF(多次统计数据!$B$9<AB49,"低于上限","达到或超过上限")) -> 低于上限 | AD49: 2-较差
A50: T2026049 | B50: 002415 | C50: 107053 | D50: 0.01 | E50: 16.25 | F50: =IF(OR(C50="",D50="",E50="",N50="",C50<=0,D50<=0,E50<=N50),"",ROUNDDOWN((C50*D50)/(E50-N50)/100,0)*100) -> 1000 | G50: =IF(OR(A50="",F50="",E50="",N50="",E50<=N50,账户数据!$B$7=""),"",IF(账户数据!$B$9+IF(H50="",F50*(E50-N50),0)>=账户数据!$B$7,"禁止开仓","允许开仓")) -> 禁止开仓 | H50: 800 | I50: 46176 | J50: 17.88 | K50: 16.25 | L50: =IF(K50="","",H50) -> 800 | M50: 46177 | N50: 15.25 | O50: 0 | P50: 0 | Q50: 支撑位与均线死叉共同确认 | R50: 止损设在15.25 | S50: 目标参考相对强弱 | T50: 按计划成交 | U50: =IF(OR(E50="",J50="",E50<=0),"",(J50-E50)/E50) -> 0.10030769 | V50: =IF(OR(E50="",N50="",E50<=0),"",(E50-N50)/E50) -> 0.061538462 | W50: =IF(OR(U50="",V50="",V50<=0),"",U50/V50) -> 1.63 | X50: =IF(OR(K50="",L50="",E50="",H50=""),"",K50*L50-E50*H50-IF(O50="",0,O50)-IF(P50="",0,P50)) -> 0 | Y50: =IF(OR(X50="",E50="",H50=""),"",IF(E50*H50+IF(O50="",0,O50)<=0,"",X50/(E50*H50+IF(O50="",0,O50)))) -> 0 | Z50: =IF(OR(Y50="",多次统计数据!$B$8=""),"",Y50-多次统计数据!$B$8) -> -0.12813109 | AA50: =IF(OR(I50="",M50="",M50<I50),"",M50-I50) -> 1 | AB50: =IF(OR(A50="",多次统计数据!$B$8="",多次统计数据!$B$6<=0,多次统计数据!$B$6>=1),"",1-POWER(1+多次统计数据!$B$8,-多次统计数据!$B$6/(1-多次统计数据!$B$6))) -> 0.11918507 | AC50: =IF(OR(AB50="",多次统计数据!$B$9=""),"",IF(多次统计数据!$B$9<AB50,"低于上限","达到或超过上限")) -> 低于上限 | AD50: 3-一般
A51: T2026050 | B51: 601899 | C51: 107053 | D51: 0.01 | E51: 17.5 | F51: =IF(OR(C51="",D51="",E51="",N51="",C51<=0,D51<=0,E51<=N51),"",ROUNDDOWN((C51*D51)/(E51-N51)/100,0)*100) -> 800 | G51: =IF(OR(A51="",F51="",E51="",N51="",E51<=N51,账户数据!$B$7=""),"",IF(账户数据!$B$9+IF(H51="",F51*(E51-N51),0)>=账户数据!$B$7,"禁止开仓","允许开仓")) -> 禁止开仓 | I51: 46177 | J51: 19.25 | L51: =IF(K51="","",H51) | N51: 16.25 | O51: 5 | P51: 5 | Q51: 压力位与量价背离共同确认 | R51: 止损设在16.25 | S51: 目标参考板块共振 | U51: =IF(OR(E51="",J51="",E51<=0),"",(J51-E51)/E51) -> 0.1 | V51: =IF(OR(E51="",N51="",E51<=0),"",(E51-N51)/E51) -> 0.071428571 | W51: =IF(OR(U51="",V51="",V51<=0),"",U51/V51) -> 1.4 | X51: =IF(OR(K51="",L51="",E51="",H51=""),"",K51*L51-E51*H51-IF(O51="",0,O51)-IF(P51="",0,P51)) | Y51: =IF(OR(X51="",E51="",H51=""),"",IF(E51*H51+IF(O51="",0,O51)<=0,"",X51/(E51*H51+IF(O51="",0,O51)))) | Z51: =IF(OR(Y51="",多次统计数据!$B$8=""),"",Y51-多次统计数据!$B$8) | AA51: =IF(OR(I51="",M51="",M51<I51),"",M51-I51) | AB51: =IF(OR(A51="",多次统计数据!$B$8="",多次统计数据!$B$6<=0,多次统计数据!$B$6>=1),"",1-POWER(1+多次统计数据!$B$8,-多次统计数据!$B$6/(1-多次统计数据!$B$6))) -> 0.11918507 | AC51: =IF(OR(AB51="",多次统计数据!$B$9=""),"",IF(多次统计数据!$B$9<AB51,"低于上限","达到或超过上限")) -> 低于上限
A52: T2026051 | B52: 600519 | C52: 107053 | D52: 0.01 | E52: 18.75 | F52: =IF(OR(C52="",D52="",E52="",N52="",C52<=0,D52<=0,E52<=N52),"",ROUNDDOWN((C52*D52)/(E52-N52)/100,0)*100) -> 700 | G52: =IF(OR(A52="",F52="",E52="",N52="",E52<=N52,账户数据!$B$7=""),"",IF(账户数据!$B$9+IF(H52="",F52*(E52-N52),0)>=账户数据!$B$7,"禁止开仓","允许开仓")) -> 禁止开仓 | H52: 100 | I52: 46178 | J52: 20.62 | K52: 21 | L52: =IF(K52="","",H52) -> 100 | M52: 46181 | N52: 17.25 | O52: 0 | P52: 5 | Q52: 缺口与趋势背离共同确认 | R52: 止损设在17.25 | S52: 目标参考蜡烛图 | T52: 按计划成交 | U52: =IF(OR(E52="",J52="",E52<=0),"",(J52-E52)/E52) -> 0.099733333 | V52: =IF(OR(E52="",N52="",E52<=0),"",(E52-N52)/E52) -> 0.08 | W52: =IF(OR(U52="",V52="",V52<=0),"",U52/V52) -> 1.2466667 | X52: =IF(OR(K52="",L52="",E52="",H52=""),"",K52*L52-E52*H52-IF(O52="",0,O52)-IF(P52="",0,P52)) -> 220 | Y52: =IF(OR(X52="",E52="",H52=""),"",IF(E52*H52+IF(O52="",0,O52)<=0,"",X52/(E52*H52+IF(O52="",0,O52)))) -> 0.11733333 | Z52: =IF(OR(Y52="",多次统计数据!$B$8=""),"",Y52-多次统计数据!$B$8) -> -0.010797757 | AA52: =IF(OR(I52="",M52="",M52<I52),"",M52-I52) -> 3 | AB52: =IF(OR(A52="",多次统计数据!$B$8="",多次统计数据!$B$6<=0,多次统计数据!$B$6>=1),"",1-POWER(1+多次统计数据!$B$8,-多次统计数据!$B$6/(1-多次统计数据!$B$6))) -> 0.11918507 | AC52: =IF(OR(AB52="",多次统计数据!$B$9=""),"",IF(多次统计数据!$B$9<AB52,"低于上限","达到或超过上限")) -> 低于上限 | AD52: 4-良好
A53: T2026052 | B53: 000001 | C53: 107273 | D53: 0.01 | E53: 20 | F53: =IF(OR(C53="",D53="",E53="",N53="",C53<=0,D53<=0,E53<=N53),"",ROUNDDOWN((C53*D53)/(E53-N53)/100,0)*100) -> 1400 | G53: =IF(OR(A53="",F53="",E53="",N53="",E53<=N53,账户数据!$B$7=""),"",IF(账户数据!$B$9+IF(H53="",F53*(E53-N53),0)>=账户数据!$B$7,"禁止开仓","允许开仓")) -> 禁止开仓 | H53: 500 | I53: 46179 | J53: 22 | K53: 22.6 | L53: =IF(K53="","",H53) -> 500 | M53: 46183 | N53: 19.25 | O53: 5 | P53: 0 | Q53: 形态突破与ATR共同确认 | R53: 止损设在19.25 | S53: 目标参考趋势线 | T53: 按计划成交 | U53: =IF(OR(E53="",J53="",E53<=0),"",(J53-E53)/E53) -> 0.1 | V53: =IF(OR(E53="",N53="",E53<=0),"",(E53-N53)/E53) -> 0.0375 | W53: =IF(OR(U53="",V53="",V53<=0),"",U53/V53) -> 2.6666667 | X53: =IF(OR(K53="",L53="",E53="",H53=""),"",K53*L53-E53*H53-IF(O53="",0,O53)-IF(P53="",0,P53)) -> 1295 | Y53: =IF(OR(X53="",E53="",H53=""),"",IF(E53*H53+IF(O53="",0,O53)<=0,"",X53/(E53*H53+IF(O53="",0,O53)))) -> 0.12943528 | Z53: =IF(OR(Y53="",多次统计数据!$B$8=""),"",Y53-多次统计数据!$B$8) -> 0.0013041923 | AA53: =IF(OR(I53="",M53="",M53<I53),"",M53-I53) -> 4 | AB53: =IF(OR(A53="",多次统计数据!$B$8="",多次统计数据!$B$6<=0,多次统计数据!$B$6>=1),"",1-POWER(1+多次统计数据!$B$8,-多次统计数据!$B$6/(1-多次统计数据!$B$6))) -> 0.11918507 | AC53: =IF(OR(AB53="",多次统计数据!$B$9=""),"",IF(多次统计数据!$B$9<AB53,"低于上限","达到或超过上限")) -> 低于上限 | AD53: 4-良好
A54: T2026053 | B54: 300750 | C54: 108568 | D54: 0.01 | E54: 21.25 | F54: =IF(OR(C54="",D54="",E54="",N54="",C54<=0,D54<=0,E54<=N54),"",ROUNDDOWN((C54*D54)/(E54-N54)/100,0)*100) -> 1000 | G54: =IF(OR(A54="",F54="",E54="",N54="",E54<=N54,账户数据!$B$7=""),"",IF(账户数据!$B$9+IF(H54="",F54*(E54-N54),0)>=账户数据!$B$7,"禁止开仓","允许开仓")) -> 禁止开仓 | H54: 600 | I54: 46180 | J54: 23.38 | K54: 24.23 | L54: =IF(K54="","",H54) -> 600 | M54: 46185 | N54: 20.25 | O54: 5 | P54: 5 | Q54: 均线金叉与换手率共同确认 | R54: 止损设在20.25 | S54: 目标参考MACD | T54: 按计划成交 | U54: =IF(OR(E54="",J54="",E54<=0),"",(J54-E54)/E54) -> 0.10023529 | V54: =IF(OR(E54="",N54="",E54<=0),"",(E54-N54)/E54) -> 0.047058824 | W54: =IF(OR(U54="",V54="",V54<=0),"",U54/V54) -> 2.13 | X54: =IF(OR(K54="",L54="",E54="",H54=""),"",K54*L54-E54*H54-IF(O54="",0,O54)-IF(P54="",0,P54)) -> 1778 | Y54: =IF(OR(X54="",E54="",H54=""),"",IF(E54*H54+IF(O54="",0,O54)<=0,"",X54/(E54*H54+IF(O54="",0,O54)))) -> 0.13939632 | Z54: =IF(OR(Y54="",多次统计数据!$B$8=""),"",Y54-多次统计数据!$B$8) -> 0.011265225 | AA54: =IF(OR(I54="",M54="",M54<I54),"",M54-I54) -> 5 | AB54: =IF(OR(A54="",多次统计数据!$B$8="",多次统计数据!$B$6<=0,多次统计数据!$B$6>=1),"",1-POWER(1+多次统计数据!$B$8,-多次统计数据!$B$6/(1-多次统计数据!$B$6))) -> 0.11918507 | AC54: =IF(OR(AB54="",多次统计数据!$B$9=""),"",IF(多次统计数据!$B$9<AB54,"低于上限","达到或超过上限")) -> 低于上限 | AD54: 4-良好
A55: T2026054 | B55: 002594 | C55: 110346 | D55: 0.01 | E55: 22.5 | F55: =IF(OR(C55="",D55="",E55="",N55="",C55<=0,D55<=0,E55<=N55),"",ROUNDDOWN((C55*D55)/(E55-N55)/100,0)*100) -> 800 | G55: =IF(OR(A55="",F55="",E55="",N55="",E55<=N55,账户数据!$B$7=""),"",IF(账户数据!$B$9+IF(H55="",F55*(E55-N55),0)>=账户数据!$B$7,"禁止开仓","允许开仓")) -> 禁止开仓 | H55: 600 | I55: 46181 | J55: 24.75 | K55: 25.2 | L55: =IF(K55="","",H55) -> 600 | M55: 46187 | N55: 21.25 | O55: 0 | P55: 5 | Q55: 均线死叉与相对强弱共同确认 | R55: 止损设在21.25 | S55: 目标参考移动平均线 | T55: 按计划成交 | U55: =IF(OR(E55="",J55="",E55<=0),"",(J55-E55)/E55) -> 0.1 | V55: =IF(OR(E55="",N55="",E55<=0),"",(E55-N55)/E55) -> 0.055555556 | W55: =IF(OR(U55="",V55="",V55<=0),"",U55/V55) -> 1.8 | X55: =IF(OR(K55="",L55="",E55="",H55=""),"",K55*L55-E55*H55-IF(O55="",0,O55)-IF(P55="",0,P55)) -> 1615 | Y55: =IF(OR(X55="",E55="",H55=""),"",IF(E55*H55+IF(O55="",0,O55)<=0,"",X55/(E55*H55+IF(O55="",0,O55)))) -> 0.11962963 | Z55: =IF(OR(Y55="",多次统计数据!$B$8=""),"",Y55-多次统计数据!$B$8) -> -0.0085014604 | AA55: =IF(OR(I55="",M55="",M55<I55),"",M55-I55) -> 6 | AB55: =IF(OR(A55="",多次统计数据!$B$8="",多次统计数据!$B$6<=0,多次统计数据!$B$6>=1),"",1-POWER(1+多次统计数据!$B$8,-多次统计数据!$B$6/(1-多次统计数据!$B$6))) -> 0.11918507 | AC55: =IF(OR(AB55="",多次统计数据!$B$9=""),"",IF(多次统计数据!$B$9<AB55,"低于上限","达到或超过上限")) -> 低于上限 | AD55: 4-良好
A56: T2026055 | B56: 601318 | C56: 111961 | D56: 0.01 | E56: 10 | F56: =IF(OR(C56="",D56="",E56="",N56="",C56<=0,D56<=0,E56<=N56),"",ROUNDDOWN((C56*D56)/(E56-N56)/100,0)*100) -> 700 | G56: =IF(OR(A56="",F56="",E56="",N56="",E56<=N56,账户数据!$B$7=""),"",IF(账户数据!$B$9+IF(H56="",F56*(E56-N56),0)>=账户数据!$B$7,"禁止开仓","允许开仓")) -> 禁止开仓 | H56: 700 | I56: 46182 | J56: 11 | K56: 8.5 | L56: =IF(K56="","",H56) -> 700 | M56: 46189 | N56: 8.5 | O56: 5 | P56: 5 | Q56: 量价背离与板块共振共同确认 | R56: 止损设在8.50 | S56: 目标参考成交量 | T56: 按计划成交 | U56: =IF(OR(E56="",J56="",E56<=0),"",(J56-E56)/E56) -> 0.1 | V56: =IF(OR(E56="",N56="",E56<=0),"",(E56-N56)/E56) -> 0.15 | W56: =IF(OR(U56="",V56="",V56<=0),"",U56/V56) -> 0.66666667 | X56: =IF(OR(K56="",L56="",E56="",H56=""),"",K56*L56-E56*H56-IF(O56="",0,O56)-IF(P56="",0,P56)) -> -1060 | Y56: =IF(OR(X56="",E56="",H56=""),"",IF(E56*H56+IF(O56="",0,O56)<=0,"",X56/(E56*H56+IF(O56="",0,O56)))) -> -0.15132049 | Z56: =IF(OR(Y56="",多次统计数据!$B$8=""),"",Y56-多次统计数据!$B$8) -> -0.27945158 | AA56: =IF(OR(I56="",M56="",M56<I56),"",M56-I56) -> 7 | AB56: =IF(OR(A56="",多次统计数据!$B$8="",多次统计数据!$B$6<=0,多次统计数据!$B$6>=1),"",1-POWER(1+多次统计数据!$B$8,-多次统计数据!$B$6/(1-多次统计数据!$B$6))) -> 0.11918507 | AC56: =IF(OR(AB56="",多次统计数据!$B$9=""),"",IF(多次统计数据!$B$9<AB56,"低于上限","达到或超过上限")) -> 低于上限 | AD56: 2-较差
A57: T2026056 | B57: 688981 | C57: 110901 | D57: 0.01 | E57: 11.25 | F57: =IF(OR(C57="",D57="",E57="",N57="",C57<=0,D57<=0,E57<=N57),"",ROUNDDOWN((C57*D57)/(E57-N57)/100,0)*100) -> 1400 | G57: =IF(OR(A57="",F57="",E57="",N57="",E57<=N57,账户数据!$B$7=""),"",IF(账户数据!$B$9+IF(H57="",F57*(E57-N57),0)>=账户数据!$B$7,"禁止开仓","允许开仓")) -> 禁止开仓 | H57: 200 | I57: 46183 | J57: 12.38 | K57: 10.5 | L57: =IF(K57="","",H57) -> 200 | M57: 46184 | N57: 10.5 | O57: 5 | P57: 0 | Q57: 趋势背离与蜡烛图共同确认 | R57: 止损设在10.50 | S57: 目标参考RSI | T57: 按计划成交 | U57: =IF(OR(E57="",J57="",E57<=0),"",(J57-E57)/E57) -> 0.10044444 | V57: =IF(OR(E57="",N57="",E57<=0),"",(E57-N57)/E57) -> 0.066666667 | W57: =IF(OR(U57="",V57="",V57<=0),"",U57/V57) -> 1.5066667 | X57: =IF(OR(K57="",L57="",E57="",H57=""),"",K57*L57-E57*H57-IF(O57="",0,O57)-IF(P57="",0,P57)) -> -155 | Y57: =IF(OR(X57="",E57="",H57=""),"",IF(E57*H57+IF(O57="",0,O57)<=0,"",X57/(E57*H57+IF(O57="",0,O57)))) -> -0.068736142 | Z57: =IF(OR(Y57="",多次统计数据!$B$8=""),"",Y57-多次统计数据!$B$8) -> -0.19686723 | AA57: =IF(OR(I57="",M57="",M57<I57),"",M57-I57) -> 1 | AB57: =IF(OR(A57="",多次统计数据!$B$8="",多次统计数据!$B$6<=0,多次统计数据!$B$6>=1),"",1-POWER(1+多次统计数据!$B$8,-多次统计数据!$B$6/(1-多次统计数据!$B$6))) -> 0.11918507 | AC57: =IF(OR(AB57="",多次统计数据!$B$9=""),"",IF(多次统计数据!$B$9<AB57,"低于上限","达到或超过上限")) -> 低于上限 | AD57: 2-较差
A58: T2026057 | B58: 000858 | C58: 110746 | D58: 0.01 | E58: 12.5 | F58: =IF(OR(C58="",D58="",E58="",N58="",C58<=0,D58<=0,E58<=N58),"",ROUNDDOWN((C58*D58)/(E58-N58)/100,0)*100) -> 1100 | G58: =IF(OR(A58="",F58="",E58="",N58="",E58<=N58,账户数据!$B$7=""),"",IF(账户数据!$B$9+IF(H58="",F58*(E58-N58),0)>=账户数据!$B$7,"禁止开仓","允许开仓")) -> 禁止开仓 | H58: 400 | I58: 46184 | J58: 13.75 | K58: 11.5 | L58: =IF(K58="","",H58) -> 400 | M58: 46186 | N58: 11.5 | O58: 0 | P58: 5 | Q58: ATR与趋势线共同确认 | R58: 止损设在11.50 | S58: 目标参考KDJ | T58: 按计划成交 | U58: =IF(OR(E58="",J58="",E58<=0),"",(J58-E58)/E58) -> 0.1 | V58: =IF(OR(E58="",N58="",E58<=0),"",(E58-N58)/E58) -> 0.08 | W58: =IF(OR(U58="",V58="",V58<=0),"",U58/V58) -> 1.25 | X58: =IF(OR(K58="",L58="",E58="",H58=""),"",K58*L58-E58*H58-IF(O58="",0,O58)-IF(P58="",0,P58)) -> -405 | Y58: =IF(OR(X58="",E58="",H58=""),"",IF(E58*H58+IF(O58="",0,O58)<=0,"",X58/(E58*H58+IF(O58="",0,O58)))) -> -0.081 | Z58: =IF(OR(Y58="",多次统计数据!$B$8=""),"",Y58-多次统计数据!$B$8) -> -0.20913109 | AA58: =IF(OR(I58="",M58="",M58<I58),"",M58-I58) -> 2 | AB58: =IF(OR(A58="",多次统计数据!$B$8="",多次统计数据!$B$6<=0,多次统计数据!$B$6>=1),"",1-POWER(1+多次统计数据!$B$8,-多次统计数据!$B$6/(1-多次统计数据!$B$6))) -> 0.11918507 | AC58: =IF(OR(AB58="",多次统计数据!$B$9=""),"",IF(多次统计数据!$B$9<AB58,"低于上限","达到或超过上限")) -> 低于上限 | AD58: 2-较差
A59: T2026058 | B59: 600036 | C59: 110341 | D59: 0.01 | E59: 13.75 | F59: =IF(OR(C59="",D59="",E59="",N59="",C59<=0,D59<=0,E59<=N59),"",ROUNDDOWN((C59*D59)/(E59-N59)/100,0)*100) -> 800 | G59: =IF(OR(A59="",F59="",E59="",N59="",E59<=N59,账户数据!$B$7=""),"",IF(账户数据!$B$9+IF(H59="",F59*(E59-N59),0)>=账户数据!$B$7,"禁止开仓","允许开仓")) -> 禁止开仓 | H59: 400 | I59: 46185 | J59: 15.13 | K59: 12.5 | L59: =IF(K59="","",H59) -> 400 | M59: 46188 | N59: 12.5 | O59: 5 | P59: 5 | Q59: 换手率与MACD共同确认 | R59: 止损设在12.50 | S59: 目标参考布林带 | T59: 按计划成交 | U59: =IF(OR(E59="",J59="",E59<=0),"",(J59-E59)/E59) -> 0.10036364 | V59: =IF(OR(E59="",N59="",E59<=0),"",(E59-N59)/E59) -> 0.090909091 | W59: =IF(OR(U59="",V59="",V59<=0),"",U59/V59) -> 1.104 | X59: =IF(OR(K59="",L59="",E59="",H59=""),"",K59*L59-E59*H59-IF(O59="",0,O59)-IF(P59="",0,P59)) -> -510 | Y59: =IF(OR(X59="",E59="",H59=""),"",IF(E59*H59+IF(O59="",0,O59)<=0,"",X59/(E59*H59+IF(O59="",0,O59)))) -> -0.092643052 | Z59: =IF(OR(Y59="",多次统计数据!$B$8=""),"",Y59-多次统计数据!$B$8) -> -0.22077414 | AA59: =IF(OR(I59="",M59="",M59<I59),"",M59-I59) -> 3 | AB59: =IF(OR(A59="",多次统计数据!$B$8="",多次统计数据!$B$6<=0,多次统计数据!$B$6>=1),"",1-POWER(1+多次统计数据!$B$8,-多次统计数据!$B$6/(1-多次统计数据!$B$6))) -> 0.11918507 | AC59: =IF(OR(AB59="",多次统计数据!$B$9=""),"",IF(多次统计数据!$B$9<AB59,"低于上限","达到或超过上限")) -> 低于上限 | AD59: 2-较差
A60: T2026059 | B60: 002415 | C60: 109831 | D60: 0.01 | E60: 15 | F60: =IF(OR(C60="",D60="",E60="",N60="",C60<=0,D60<=0,E60<=N60),"",ROUNDDOWN((C60*D60)/(E60-N60)/100,0)*100) -> 700 | G60: =IF(OR(A60="",F60="",E60="",N60="",E60<=N60,账户数据!$B$7=""),"",IF(账户数据!$B$9+IF(H60="",F60*(E60-N60),0)>=账户数据!$B$7,"禁止开仓","允许开仓")) -> 禁止开仓 | H60: 500 | I60: 46186 | J60: 16.5 | K60: 15 | L60: =IF(K60="","",H60) -> 500 | M60: 46190 | N60: 13.5 | O60: 0 | P60: 0 | Q60: 相对强弱与移动平均线共同确认 | R60: 止损设在13.50 | S60: 目标参考支撑位 | T60: 按计划成交 | U60: =IF(OR(E60="",J60="",E60<=0),"",(J60-E60)/E60) -> 0.1 | V60: =IF(OR(E60="",N60="",E60<=0),"",(E60-N60)/E60) -> 0.1 | W60: =IF(OR(U60="",V60="",V60<=0),"",U60/V60) -> 1 | X60: =IF(OR(K60="",L60="",E60="",H60=""),"",K60*L60-E60*H60-IF(O60="",0,O60)-IF(P60="",0,P60)) -> 0 | Y60: =IF(OR(X60="",E60="",H60=""),"",IF(E60*H60+IF(O60="",0,O60)<=0,"",X60/(E60*H60+IF(O60="",0,O60)))) -> 0 | Z60: =IF(OR(Y60="",多次统计数据!$B$8=""),"",Y60-多次统计数据!$B$8) -> -0.12813109 | AA60: =IF(OR(I60="",M60="",M60<I60),"",M60-I60) -> 4 | AB60: =IF(OR(A60="",多次统计数据!$B$8="",多次统计数据!$B$6<=0,多次统计数据!$B$6>=1),"",1-POWER(1+多次统计数据!$B$8,-多次统计数据!$B$6/(1-多次统计数据!$B$6))) -> 0.11918507 | AC60: =IF(OR(AB60="",多次统计数据!$B$9=""),"",IF(多次统计数据!$B$9<AB60,"低于上限","达到或超过上限")) -> 低于上限 | AD60: 3-一般
A61: T2026060 | B61: 601899 | C61: 109831 | D61: 0.01 | E61: 16.25 | F61: =IF(OR(C61="",D61="",E61="",N61="",C61<=0,D61<=0,E61<=N61),"",ROUNDDOWN((C61*D61)/(E61-N61)/100,0)*100) -> 1400 | G61: =IF(OR(A61="",F61="",E61="",N61="",E61<=N61,账户数据!$B$7=""),"",IF(账户数据!$B$9+IF(H61="",F61*(E61-N61),0)>=账户数据!$B$7,"禁止开仓","允许开仓")) -> 禁止开仓 | H61: 1400 | I61: 46187 | J61: 17.88 | L61: =IF(K61="","",H61) | N61: 15.5 | O61: 0 | P61: 0 | Q61: 板块共振与成交量共同确认 | R61: 止损设在15.50 | S61: 目标参考压力位 | U61: =IF(OR(E61="",J61="",E61<=0),"",(J61-E61)/E61) -> 0.10030769 | V61: =IF(OR(E61="",N61="",E61<=0),"",(E61-N61)/E61) -> 0.046153846 | W61: =IF(OR(U61="",V61="",V61<=0),"",U61/V61) -> 2.1733333 | X61: =IF(OR(K61="",L61="",E61="",H61=""),"",K61*L61-E61*H61-IF(O61="",0,O61)-IF(P61="",0,P61)) | Y61: =IF(OR(X61="",E61="",H61=""),"",IF(E61*H61+IF(O61="",0,O61)<=0,"",X61/(E61*H61+IF(O61="",0,O61)))) | Z61: =IF(OR(Y61="",多次统计数据!$B$8=""),"",Y61-多次统计数据!$B$8) | AA61: =IF(OR(I61="",M61="",M61<I61),"",M61-I61) | AB61: =IF(OR(A61="",多次统计数据!$B$8="",多次统计数据!$B$6<=0,多次统计数据!$B$6>=1),"",1-POWER(1+多次统计数据!$B$8,-多次统计数据!$B$6/(1-多次统计数据!$B$6))) -> 0.11918507 | AC61: =IF(OR(AB61="",多次统计数据!$B$9=""),"",IF(多次统计数据!$B$9<AB61,"低于上限","达到或超过上限")) -> 低于上限
A62: T2026061 | B62: 600519 | C62: 109831 | D62: 0.01 | E62: 17.5 | F62: =IF(OR(C62="",D62="",E62="",N62="",C62<=0,D62<=0,E62<=N62),"",ROUNDDOWN((C62*D62)/(E62-N62)/100,0)*100) -> 1000 | G62: =IF(OR(A62="",F62="",E62="",N62="",E62<=N62,账户数据!$B$7=""),"",IF(账户数据!$B$9+IF(H62="",F62*(E62-N62),0)>=账户数据!$B$7,"禁止开仓","允许开仓")) -> 禁止开仓 | H62: 200 | I62: 46188 | J62: 19.25 | K62: 19.78 | L62: =IF(K62="","",H62) -> 200 | M62: 46194 | N62: 16.5 | O62: 5 | P62: 5 | Q62: 蜡烛图与RSI共同确认 | R62: 止损设在16.50 | S62: 目标参考缺口 | T62: 按计划成交 | U62: =IF(OR(E62="",J62="",E62<=0),"",(J62-E62)/E62) -> 0.1 | V62: =IF(OR(E62="",N62="",E62<=0),"",(E62-N62)/E62) -> 0.057142857 | W62: =IF(OR(U62="",V62="",V62<=0),"",U62/V62) -> 1.75 | X62: =IF(OR(K62="",L62="",E62="",H62=""),"",K62*L62-E62*H62-IF(O62="",0,O62)-IF(P62="",0,P62)) -> 446 | Y62: =IF(OR(X62="",E62="",H62=""),"",IF(E62*H62+IF(O62="",0,O62)<=0,"",X62/(E62*H62+IF(O62="",0,O62)))) -> 0.12724679 | Z62: =IF(OR(Y62="",多次统计数据!$B$8=""),"",Y62-多次统计数据!$B$8) -> -0.00088429977 | AA62: =IF(OR(I62="",M62="",M62<I62),"",M62-I62) -> 6 | AB62: =IF(OR(A62="",多次统计数据!$B$8="",多次统计数据!$B$6<=0,多次统计数据!$B$6>=1),"",1-POWER(1+多次统计数据!$B$8,-多次统计数据!$B$6/(1-多次统计数据!$B$6))) -> 0.11918507 | AC62: =IF(OR(AB62="",多次统计数据!$B$9=""),"",IF(多次统计数据!$B$9<AB62,"低于上限","达到或超过上限")) -> 低于上限 | AD62: 4-良好
A63: T2026062 | B63: 000001 | C63: 110277 | D63: 0.01 | E63: 18.75 | F63: =IF(OR(C63="",D63="",E63="",N63="",C63<=0,D63<=0,E63<=N63),"",ROUNDDOWN((C63*D63)/(E63-N63)/100,0)*100) -> 800 | G63: =IF(OR(A63="",F63="",E63="",N63="",E63<=N63,账户数据!$B$7=""),"",IF(账户数据!$B$9+IF(H63="",F63*(E63-N63),0)>=账户数据!$B$7,"禁止开仓","允许开仓")) -> 禁止开仓 | H63: 300 | I63: 46189 | J63: 20.62 | K63: 21.38 | L63: =IF(K63="","",H63) -> 300 | M63: 46196 | N63: 17.5 | O63: 5 | P63: 5 | Q63: 趋势线与KDJ共同确认 | R63: 止损设在17.50 | S63: 目标参考形态突破 | T63: 按计划成交 | U63: =IF(OR(E63="",J63="",E63<=0),"",(J63-E63)/E63) -> 0.099733333 | V63: =IF(OR(E63="",N63="",E63<=0),"",(E63-N63)/E63) -> 0.066666667 | W63: =IF(OR(U63="",V63="",V63<=0),"",U63/V63) -> 1.496 | X63: =IF(OR(K63="",L63="",E63="",H63=""),"",K63*L63-E63*H63-IF(O63="",0,O63)-IF(P63="",0,P63)) -> 779 | Y63: =IF(OR(X63="",E63="",H63=""),"",IF(E63*H63+IF(O63="",0,O63)<=0,"",X63/(E63*H63+IF(O63="",0,O63)))) -> 0.1383659 | Z63: =IF(OR(Y63="",多次统计数据!$B$8=""),"",Y63-多次统计数据!$B$8) -> 0.010234807 | AA63: =IF(OR(I63="",M63="",M63<I63),"",M63-I63) -> 7 | AB63: =IF(OR(A63="",多次统计数据!$B$8="",多次统计数据!$B$6<=0,多次统计数据!$B$6>=1),"",1-POWER(1+多次统计数据!$B$8,-多次统计数据!$B$6/(1-多次统计数据!$B$6))) -> 0.11918507 | AC63: =IF(OR(AB63="",多次统计数据!$B$9=""),"",IF(多次统计数据!$B$9<AB63,"低于上限","达到或超过上限")) -> 低于上限 | AD63: 4-良好
A64: T2026063 | B64: 300750 | C64: 111056 | D64: 0.01 | E64: 20 | F64: =IF(OR(C64="",D64="",E64="",N64="",C64<=0,D64<=0,E64<=N64),"",ROUNDDOWN((C64*D64)/(E64-N64)/100,0)*100) -> 700 | G64: =IF(OR(A64="",F64="",E64="",N64="",E64<=N64,账户数据!$B$7=""),"",IF(账户数据!$B$9+IF(H64="",F64*(E64-N64),0)>=账户数据!$B$7,"禁止开仓","允许开仓")) -> 禁止开仓 | H64: 400 | I64: 46190 | J64: 22 | K64: 22.4 | L64: =IF(K64="","",H64) -> 400 | M64: 46191 | N64: 18.5 | O64: 0 | P64: 5 | Q64: MACD与布林带共同确认 | R64: 止损设在18.50 | S64: 目标参考均线金叉 | T64: 按计划成交 | U64: =IF(OR(E64="",J64="",E64<=0),"",(J64-E64)/E64) -> 0.1 | V64: =IF(OR(E64="",N64="",E64<=0),"",(E64-N64)/E64) -> 0.075 | W64: =IF(OR(U64="",V64="",V64<=0),"",U64/V64) -> 1.3333333 | X64: =IF(OR(K64="",L64="",E64="",H64=""),"",K64*L64-E64*H64-IF(O64="",0,O64)-IF(P64="",0,P64)) -> 955 | Y64: =IF(OR(X64="",E64="",H64=""),"",IF(E64*H64+IF(O64="",0,O64)<=0,"",X64/(E64*H64+IF(O64="",0,O64)))) -> 0.119375 | Z64: =IF(OR(Y64="",多次统计数据!$B$8=""),"",Y64-多次统计数据!$B$8) -> -0.0087560901 | AA64: =IF(OR(I64="",M64="",M64<I64),"",M64-I64) -> 1 | AB64: =IF(OR(A64="",多次统计数据!$B$8="",多次统计数据!$B$6<=0,多次统计数据!$B$6>=1),"",1-POWER(1+多次统计数据!$B$8,-多次统计数据!$B$6/(1-多次统计数据!$B$6))) -> 0.11918507 | AC64: =IF(OR(AB64="",多次统计数据!$B$9=""),"",IF(多次统计数据!$B$9<AB64,"低于上限","达到或超过上限")) -> 低于上限 | AD64: 4-良好
A65: T2026064 | B65: 002594 | C65: 112011 | D65: 0.01 | E65: 21.25 | F65: =IF(OR(C65="",D65="",E65="",N65="",C65<=0,D65<=0,E65<=N65),"",ROUNDDOWN((C65*D65)/(E65-N65)/100,0)*100) -> 1400 | G65: =IF(OR(A65="",F65="",E65="",N65="",E65<=N65,账户数据!$B$7=""),"",IF(账户数据!$B$9+IF(H65="",F65*(E65-N65),0)>=账户数据!$B$7,"禁止开仓","允许开仓")) -> 禁止开仓 | H65: 1100 | I65: 46191 | J65: 23.38 | K65: 24.01 | L65: =IF(K65="","",H65) -> 1100 | M65: 46193 | N65: 20.5 | O65: 5 | P65: 0 | Q65: 移动平均线与支撑位共同确认 | R65: 止损设在20.50 | S65: 目标参考均线死叉 | T65: 按计划成交 | U65: =IF(OR(E65="",J65="",E65<=0),"",(J65-E65)/E65) -> 0.10023529 | V65: =IF(OR(E65="",N65="",E65<=0),"",(E65-N65)/E65) -> 0.035294118 | W65: =IF(OR(U65="",V65="",V65<=0),"",U65/V65) -> 2.84 | X65: =IF(OR(K65="",L65="",E65="",H65=""),"",K65*L65-E65*H65-IF(O65="",0,O65)-IF(P65="",0,P65)) -> 3031 | Y65: =IF(OR(X65="",E65="",H65=""),"",IF(E65*H65+IF(O65="",0,O65)<=0,"",X65/(E65*H65+IF(O65="",0,O65)))) -> 0.12964072 | Z65: =IF(OR(Y65="",多次统计数据!$B$8=""),"",Y65-多次统计数据!$B$8) -> 0.0015096285 | AA65: =IF(OR(I65="",M65="",M65<I65),"",M65-I65) -> 2 | AB65: =IF(OR(A65="",多次统计数据!$B$8="",多次统计数据!$B$6<=0,多次统计数据!$B$6>=1),"",1-POWER(1+多次统计数据!$B$8,-多次统计数据!$B$6/(1-多次统计数据!$B$6))) -> 0.11918507 | AC65: =IF(OR(AB65="",多次统计数据!$B$9=""),"",IF(多次统计数据!$B$9<AB65,"低于上限","达到或超过上限")) -> 低于上限 | AD65: 4-良好
A66: T2026065 | B66: 601318 | C66: 115042 | D66: 0.01 | E66: 22.5 | F66: =IF(OR(C66="",D66="",E66="",N66="",C66<=0,D66<=0,E66<=N66),"",ROUNDDOWN((C66*D66)/(E66-N66)/100,0)*100) -> 1100 | G66: =IF(OR(A66="",F66="",E66="",N66="",E66<=N66,账户数据!$B$7=""),"",IF(账户数据!$B$9+IF(H66="",F66*(E66-N66),0)>=账户数据!$B$7,"禁止开仓","允许开仓")) -> 禁止开仓 | H66: 1100 | I66: 46192 | J66: 24.75 | K66: 21.15 | L66: =IF(K66="","",H66) -> 1100 | M66: 46195 | N66: 21.5 | O66: 5 | P66: 5 | Q66: 成交量与压力位共同确认 | R66: 止损设在21.50 | S66: 目标参考量价背离 | T66: 按计划成交 | U66: =IF(OR(E66="",J66="",E66<=0),"",(J66-E66)/E66) -> 0.1 | V66: =IF(OR(E66="",N66="",E66<=0),"",(E66-N66)/E66) -> 0.044444444 | W66: =IF(OR(U66="",V66="",V66<=0),"",U66/V66) -> 2.25 | X66: =IF(OR(K66="",L66="",E66="",H66=""),"",K66*L66-E66*H66-IF(O66="",0,O66)-IF(P66="",0,P66)) -> -1495 | Y66: =IF(OR(X66="",E66="",H66=""),"",IF(E66*H66+IF(O66="",0,O66)<=0,"",X66/(E66*H66+IF(O66="",0,O66)))) -> -0.06039184 | Z66: =IF(OR(Y66="",多次统计数据!$B$8=""),"",Y66-多次统计数据!$B$8) -> -0.18852293 | AA66: =IF(OR(I66="",M66="",M66<I66),"",M66-I66) -> 3 | AB66: =IF(OR(A66="",多次统计数据!$B$8="",多次统计数据!$B$6<=0,多次统计数据!$B$6>=1),"",1-POWER(1+多次统计数据!$B$8,-多次统计数据!$B$6/(1-多次统计数据!$B$6))) -> 0.11918507 | AC66: =IF(OR(AB66="",多次统计数据!$B$9=""),"",IF(多次统计数据!$B$9<AB66,"低于上限","达到或超过上限")) -> 低于上限 | AD66: 2-较差
A67: T2026066 | B67: 688981 | C67: 113547 | D67: 0.01 | E67: 10 | F67: =IF(OR(C67="",D67="",E67="",N67="",C67<=0,D67<=0,E67<=N67),"",ROUNDDOWN((C67*D67)/(E67-N67)/100,0)*100) -> 900 | G67: =IF(OR(A67="",F67="",E67="",N67="",E67<=N67,账户数据!$B$7=""),"",IF(账户数据!$B$9+IF(H67="",F67*(E67-N67),0)>=账户数据!$B$7,"禁止开仓","允许开仓")) -> 禁止开仓 | H67: 100 | I67: 46193 | J67: 11 | K67: 8.75 | L67: =IF(K67="","",H67) -> 100 | M67: 46197 | N67: 8.75 | O67: 0 | P67: 5 | Q67: RSI与缺口共同确认 | R67: 止损设在8.75 | S67: 目标参考趋势背离 | T67: 按计划成交 | U67: =IF(OR(E67="",J67="",E67<=0),"",(J67-E67)/E67) -> 0.1 | V67: =IF(OR(E67="",N67="",E67<=0),"",(E67-N67)/E67) -> 0.125 | W67: =IF(OR(U67="",V67="",V67<=0),"",U67/V67) -> 0.8 | X67: =IF(OR(K67="",L67="",E67="",H67=""),"",K67*L67-E67*H67-IF(O67="",0,O67)-IF(P67="",0,P67)) -> -130 | Y67: =IF(OR(X67="",E67="",H67=""),"",IF(E67*H67+IF(O67="",0,O67)<=0,"",X67/(E67*H67+IF(O67="",0,O67)))) -> -0.13 | Z67: =IF(OR(Y67="",多次统计数据!$B$8=""),"",Y67-多次统计数据!$B$8) -> -0.25813109 | AA67: =IF(OR(I67="",M67="",M67<I67),"",M67-I67) -> 4 | AB67: =IF(OR(A67="",多次统计数据!$B$8="",多次统计数据!$B$6<=0,多次统计数据!$B$6>=1),"",1-POWER(1+多次统计数据!$B$8,-多次统计数据!$B$6/(1-多次统计数据!$B$6))) -> 0.11918507 | AC67: =IF(OR(AB67="",多次统计数据!$B$9=""),"",IF(多次统计数据!$B$9<AB67,"低于上限","达到或超过上限")) -> 低于上限 | AD67: 2-较差
A68: T2026067 | B68: 000858 | C68: 113417 | D68: 0.01 | E68: 11.25 | F68: =IF(OR(C68="",D68="",E68="",N68="",C68<=0,D68<=0,E68<=N68),"",ROUNDDOWN((C68*D68)/(E68-N68)/100,0)*100) -> 700 | G68: =IF(OR(A68="",F68="",E68="",N68="",E68<=N68,账户数据!$B$7=""),"",IF(账户数据!$B$9+IF(H68="",F68*(E68-N68),0)>=账户数据!$B$7,"禁止开仓","允许开仓")) -> 禁止开仓 | H68: 200 | I68: 46194 | J68: 12.38 | K68: 9.75 | L68: =IF(K68="","",H68) -> 200 | M68: 46199 | N68: 9.75 | O68: 5 | P68: 5 | Q68: KDJ与形态突破共同确认 | R68: 止损设在9.75 | S68: 目标参考ATR | T68: 按计划成交 | U68: =IF(OR(E68="",J68="",E68<=0),"",(J68-E68)/E68) -> 0.10044444 | V68: =IF(OR(E68="",N68="",E68<=0),"",(E68-N68)/E68) -> 0.13333333 | W68: =IF(OR(U68="",V68="",V68<=0),"",U68/V68) -> 0.75333333 | X68: =IF(OR(K68="",L68="",E68="",H68=""),"",K68*L68-E68*H68-IF(O68="",0,O68)-IF(P68="",0,P68)) -> -310 | Y68: =IF(OR(X68="",E68="",H68=""),"",IF(E68*H68+IF(O68="",0,O68)<=0,"",X68/(E68*H68+IF(O68="",0,O68)))) -> -0.13747228 | Z68: =IF(OR(Y68="",多次统计数据!$B$8=""),"",Y68-多次统计数据!$B$8) -> -0.26560337 | AA68: =IF(OR(I68="",M68="",M68<I68),"",M68-I68) -> 5 | AB68: =IF(OR(A68="",多次统计数据!$B$8="",多次统计数据!$B$6<=0,多次统计数据!$B$6>=1),"",1-POWER(1+多次统计数据!$B$8,-多次统计数据!$B$6/(1-多次统计数据!$B$6))) -> 0.11918507 | AC68: =IF(OR(AB68="",多次统计数据!$B$9=""),"",IF(多次统计数据!$B$9<AB68,"低于上限","达到或超过上限")) -> 低于上限 | AD68: 2-较差
A69: T2026068 | B69: 600036 | C69: 113107 | D69: 0.01 | E69: 12.5 | F69: =IF(OR(C69="",D69="",E69="",N69="",C69<=0,D69<=0,E69<=N69),"",ROUNDDOWN((C69*D69)/(E69-N69)/100,0)*100) -> 1500 | G69: =IF(OR(A69="",F69="",E69="",N69="",E69<=N69,账户数据!$B$7=""),"",IF(账户数据!$B$9+IF(H69="",F69*(E69-N69),0)>=账户数据!$B$7,"禁止开仓","允许开仓")) -> 禁止开仓 | H69: 900 | I69: 46195 | J69: 13.75 | K69: 11.75 | L69: =IF(K69="","",H69) -> 900 | M69: 46201 | N69: 11.75 | O69: 5 | P69: 0 | Q69: 布林带与均线金叉共同确认 | R69: 止损设在11.75 | S69: 目标参考换手率 | T69: 按计划成交 | U69: =IF(OR(E69="",J69="",E69<=0),"",(J69-E69)/E69) -> 0.1 | V69: =IF(OR(E69="",N69="",E69<=0),"",(E69-N69)/E69) -> 0.06 | W69: =IF(OR(U69="",V69="",V69<=0),"",U69/V69) -> 1.6666667 | X69: =IF(OR(K69="",L69="",E69="",H69=""),"",K69*L69-E69*H69-IF(O69="",0,O69)-IF(P69="",0,P69)) -> -680 | Y69: =IF(OR(X69="",E69="",H69=""),"",IF(E69*H69+IF(O69="",0,O69)<=0,"",X69/(E69*H69+IF(O69="",0,O69)))) -> -0.060417592 | Z69: =IF(OR(Y69="",多次统计数据!$B$8=""),"",Y69-多次统计数据!$B$8) -> -0.18854868 | AA69: =IF(OR(I69="",M69="",M69<I69),"",M69-I69) -> 6 | AB69: =IF(OR(A69="",多次统计数据!$B$8="",多次统计数据!$B$6<=0,多次统计数据!$B$6>=1),"",1-POWER(1+多次统计数据!$B$8,-多次统计数据!$B$6/(1-多次统计数据!$B$6))) -> 0.11918507 | AC69: =IF(OR(AB69="",多次统计数据!$B$9=""),"",IF(多次统计数据!$B$9<AB69,"低于上限","达到或超过上限")) -> 低于上限 | AD69: 2-较差
A70: T2026069 | B70: 002415 | C70: 112427 | D70: 0.01 | E70: 13.75 | F70: =IF(OR(C70="",D70="",E70="",N70="",C70<=0,D70<=0,E70<=N70),"",ROUNDDOWN((C70*D70)/(E70-N70)/100,0)*100) -> 1100 | G70: =IF(OR(A70="",F70="",E70="",N70="",E70<=N70,账户数据!$B$7=""),"",IF(账户数据!$B$9+IF(H70="",F70*(E70-N70),0)>=账户数据!$B$7,"禁止开仓","允许开仓")) -> 禁止开仓 | H70: 800 | I70: 46196 | J70: 15.13 | K70: 13.75 | L70: =IF(K70="","",H70) -> 800 | M70: 46203 | N70: 12.75 | O70: 0 | P70: 0 | Q70: 支撑位与均线死叉共同确认 | R70: 止损设在12.75 | S70: 目标参考相对强弱 | T70: 按计划成交 | U70: =IF(OR(E70="",J70="",E70<=0),"",(J70-E70)/E70) -> 0.10036364 | V70: =IF(OR(E70="",N70="",E70<=0),"",(E70-N70)/E70) -> 0.072727273 | W70: =IF(OR(U70="",V70="",V70<=0),"",U70/V70) -> 1.38 | X70: =IF(OR(K70="",L70="",E70="",H70=""),"",K70*L70-E70*H70-IF(O70="",0,O70)-IF(P70="",0,P70)) -> 0 | Y70: =IF(OR(X70="",E70="",H70=""),"",IF(E70*H70+IF(O70="",0,O70)<=0,"",X70/(E70*H70+IF(O70="",0,O70)))) -> 0 | Z70: =IF(OR(Y70="",多次统计数据!$B$8=""),"",Y70-多次统计数据!$B$8) -> -0.12813109 | AA70: =IF(OR(I70="",M70="",M70<I70),"",M70-I70) -> 7 | AB70: =IF(OR(A70="",多次统计数据!$B$8="",多次统计数据!$B$6<=0,多次统计数据!$B$6>=1),"",1-POWER(1+多次统计数据!$B$8,-多次统计数据!$B$6/(1-多次统计数据!$B$6))) -> 0.11918507 | AC70: =IF(OR(AB70="",多次统计数据!$B$9=""),"",IF(多次统计数据!$B$9<AB70,"低于上限","达到或超过上限")) -> 低于上限 | AD70: 3-一般
A71: T2026070 | B71: 601899 | C71: 112427 | D71: 0.01 | E71: 15 | F71: =IF(OR(C71="",D71="",E71="",N71="",C71<=0,D71<=0,E71<=N71),"",ROUNDDOWN((C71*D71)/(E71-N71)/100,0)*100) -> 800 | G71: =IF(OR(A71="",F71="",E71="",N71="",E71<=N71,账户数据!$B$7=""),"",IF(账户数据!$B$9+IF(H71="",F71*(E71-N71),0)>=账户数据!$B$7,"禁止开仓","允许开仓")) -> 禁止开仓 | H71: 800 | I71: 46197 | J71: 16.5 | L71: =IF(K71="","",H71) | N71: 13.75 | O71: 5 | P71: 5 | Q71: 压力位与量价背离共同确认 | R71: 止损设在13.75 | S71: 目标参考板块共振 | U71: =IF(OR(E71="",J71="",E71<=0),"",(J71-E71)/E71) -> 0.1 | V71: =IF(OR(E71="",N71="",E71<=0),"",(E71-N71)/E71) -> 0.083333333 | W71: =IF(OR(U71="",V71="",V71<=0),"",U71/V71) -> 1.2 | X71: =IF(OR(K71="",L71="",E71="",H71=""),"",K71*L71-E71*H71-IF(O71="",0,O71)-IF(P71="",0,P71)) | Y71: =IF(OR(X71="",E71="",H71=""),"",IF(E71*H71+IF(O71="",0,O71)<=0,"",X71/(E71*H71+IF(O71="",0,O71)))) | Z71: =IF(OR(Y71="",多次统计数据!$B$8=""),"",Y71-多次统计数据!$B$8) | AA71: =IF(OR(I71="",M71="",M71<I71),"",M71-I71) | AB71: =IF(OR(A71="",多次统计数据!$B$8="",多次统计数据!$B$6<=0,多次统计数据!$B$6>=1),"",1-POWER(1+多次统计数据!$B$8,-多次统计数据!$B$6/(1-多次统计数据!$B$6))) -> 0.11918507 | AC71: =IF(OR(AB71="",多次统计数据!$B$9=""),"",IF(多次统计数据!$B$9<AB71,"低于上限","达到或超过上限")) -> 低于上限
A72: T2026071 | B72: 600519 | C72: 112427 | D72: 0.01 | E72: 16.25 | F72: =IF(OR(C72="",D72="",E72="",N72="",C72<=0,D72<=0,E72<=N72),"",ROUNDDOWN((C72*D72)/(E72-N72)/100,0)*100) -> 700 | G72: =IF(OR(A72="",F72="",E72="",N72="",E72<=N72,账户数据!$B$7=""),"",IF(账户数据!$B$9+IF(H72="",F72*(E72-N72),0)>=账户数据!$B$7,"禁止开仓","允许开仓")) -> 禁止开仓 | H72: 100 | I72: 46198 | J72: 17.88 | K72: 18.53 | L72: =IF(K72="","",H72) -> 100 | M72: 46200 | N72: 14.75 | O72: 5 | P72: 5 | Q72: 缺口与趋势背离共同确认 | R72: 止损设在14.75 | S72: 目标参考蜡烛图 | T72: 按计划成交 | U72: =IF(OR(E72="",J72="",E72<=0),"",(J72-E72)/E72) -> 0.10030769 | V72: =IF(OR(E72="",N72="",E72<=0),"",(E72-N72)/E72) -> 0.092307692 | W72: =IF(OR(U72="",V72="",V72<=0),"",U72/V72) -> 1.0866667 | X72: =IF(OR(K72="",L72="",E72="",H72=""),"",K72*L72-E72*H72-IF(O72="",0,O72)-IF(P72="",0,P72)) -> 218 | Y72: =IF(OR(X72="",E72="",H72=""),"",IF(E72*H72+IF(O72="",0,O72)<=0,"",X72/(E72*H72+IF(O72="",0,O72)))) -> 0.13374233 | Z72: =IF(OR(Y72="",多次统计数据!$B$8=""),"",Y72-多次统计数据!$B$8) -> 0.0056112412 | AA72: =IF(OR(I72="",M72="",M72<I72),"",M72-I72) -> 2 | AB72: =IF(OR(A72="",多次统计数据!$B$8="",多次统计数据!$B$6<=0,多次统计数据!$B$6>=1),"",1-POWER(1+多次统计数据!$B$8,-多次统计数据!$B$6/(1-多次统计数据!$B$6))) -> 0.11918507 | AC72: =IF(OR(AB72="",多次统计数据!$B$9=""),"",IF(多次统计数据!$B$9<AB72,"低于上限","达到或超过上限")) -> 低于上限 | AD72: 4-良好
A73: T2026072 | B73: 000001 | C73: 112645 | D73: 0.01 | E73: 17.5 | F73: =IF(OR(C73="",D73="",E73="",N73="",C73<=0,D73<=0,E73<=N73),"",ROUNDDOWN((C73*D73)/(E73-N73)/100,0)*100) -> 1500 | G73: =IF(OR(A73="",F73="",E73="",N73="",E73<=N73,账户数据!$B$7=""),"",IF(账户数据!$B$9+IF(H73="",F73*(E73-N73),0)>=账户数据!$B$7,"禁止开仓","允许开仓")) -> 禁止开仓 | H73: 600 | I73: 46199 | J73: 19.25 | K73: 19.6 | L73: =IF(K73="","",H73) -> 600 | M73: 46202 | N73: 16.75 | O73: 0 | P73: 0 | Q73: 形态突破与ATR共同确认 | R73: 止损设在16.75 | S73: 目标参考趋势线 | T73: 按计划成交 | U73: =IF(OR(E73="",J73="",E73<=0),"",(J73-E73)/E73) -> 0.1 | V73: =IF(OR(E73="",N73="",E73<=0),"",(E73-N73)/E73) -> 0.042857143 | W73: =IF(OR(U73="",V73="",V73<=0),"",U73/V73) -> 2.3333333 | X73: =IF(OR(K73="",L73="",E73="",H73=""),"",K73*L73-E73*H73-IF(O73="",0,O73)-IF(P73="",0,P73)) -> 1260 | Y73: =IF(OR(X73="",E73="",H73=""),"",IF(E73*H73+IF(O73="",0,O73)<=0,"",X73/(E73*H73+IF(O73="",0,O73)))) -> 0.12 | Z73: =IF(OR(Y73="",多次统计数据!$B$8=""),"",Y73-多次统计数据!$B$8) -> -0.0081310901 | AA73: =IF(OR(I73="",M73="",M73<I73),"",M73-I73) -> 3 | AB73: =IF(OR(A73="",多次统计数据!$B$8="",多次统计数据!$B$6<=0,多次统计数据!$B$6>=1),"",1-POWER(1+多次统计数据!$B$8,-多次统计数据!$B$6/(1-多次统计数据!$B$6))) -> 0.11918507 | AC73: =IF(OR(AB73="",多次统计数据!$B$9=""),"",IF(多次统计数据!$B$9<AB73,"低于上限","达到或超过上限")) -> 低于上限 | AD73: 4-良好
A74: T2026073 | B74: 300750 | C74: 113905 | D74: 0.01 | E74: 18.75 | F74: =IF(OR(C74="",D74="",E74="",N74="",C74<=0,D74<=0,E74<=N74),"",ROUNDDOWN((C74*D74)/(E74-N74)/100,0)*100) -> 1100 | G74: =IF(OR(A74="",F74="",E74="",N74="",E74<=N74,账户数据!$B$7=""),"",IF(账户数据!$B$9+IF(H74="",F74*(E74-N74),0)>=账户数据!$B$7,"禁止开仓","允许开仓")) -> 禁止开仓 | H74: 600 | I74: 46200 | J74: 20.62 | K74: 21.19 | L74: =IF(K74="","",H74) -> 600 | M74: 46204 | N74: 17.75 | O74: 5 | P74: 5 | Q74: 均线金叉与换手率共同确认 | R74: 止损设在17.75 | S74: 目标参考MACD | T74: 按计划成交 | U74: =IF(OR(E74="",J74="",E74<=0),"",(J74-E74)/E74) -> 0.099733333 | V74: =IF(OR(E74="",N74="",E74<=0),"",(E74-N74)/E74) -> 0.053333333 | W74: =IF(OR(U74="",V74="",V74<=0),"",U74/V74) -> 1.87 | X74: =IF(OR(K74="",L74="",E74="",H74=""),"",K74*L74-E74*H74-IF(O74="",0,O74)-IF(P74="",0,P74)) -> 1454 | Y74: =IF(OR(X74="",E74="",H74=""),"",IF(E74*H74+IF(O74="",0,O74)<=0,"",X74/(E74*H74+IF(O74="",0,O74)))) -> 0.12918703 | Z74: =IF(OR(Y74="",多次统计数据!$B$8=""),"",Y74-多次统计数据!$B$8) -> 0.0010559379 | AA74: =IF(OR(I74="",M74="",M74<I74),"",M74-I74) -> 4 | AB74: =IF(OR(A74="",多次统计数据!$B$8="",多次统计数据!$B$6<=0,多次统计数据!$B$6>=1),"",1-POWER(1+多次统计数据!$B$8,-多次统计数据!$B$6/(1-多次统计数据!$B$6))) -> 0.11918507 | AC74: =IF(OR(AB74="",多次统计数据!$B$9=""),"",IF(多次统计数据!$B$9<AB74,"低于上限","达到或超过上限")) -> 低于上限 | AD74: 4-良好
A75: T2026074 | B75: 002594 | C75: 115359 | D75: 0.01 | E75: 20 | F75: =IF(OR(C75="",D75="",E75="",N75="",C75<=0,D75<=0,E75<=N75),"",ROUNDDOWN((C75*D75)/(E75-N75)/100,0)*100) -> 900 | G75: =IF(OR(A75="",F75="",E75="",N75="",E75<=N75,账户数据!$B$7=""),"",IF(账户数据!$B$9+IF(H75="",F75*(E75-N75),0)>=账户数据!$B$7,"禁止开仓","允许开仓")) -> 禁止开仓 | H75: 700 | I75: 46201 | J75: 22 | K75: 22.8 | L75: =IF(K75="","",H75) -> 700 | M75: 46206 | N75: 18.75 | O75: 5 | P75: 5 | Q75: 均线死叉与相对强弱共同确认 | R75: 止损设在18.75 | S75: 目标参考移动平均线 | T75: 按计划成交 | U75: =IF(OR(E75="",J75="",E75<=0),"",(J75-E75)/E75) -> 0.1 | V75: =IF(OR(E75="",N75="",E75<=0),"",(E75-N75)/E75) -> 0.0625 | W75: =IF(OR(U75="",V75="",V75<=0),"",U75/V75) -> 1.6 | X75: =IF(OR(K75="",L75="",E75="",H75=""),"",K75*L75-E75*H75-IF(O75="",0,O75)-IF(P75="",0,P75)) -> 1950 | Y75: =IF(OR(X75="",E75="",H75=""),"",IF(E75*H75+IF(O75="",0,O75)<=0,"",X75/(E75*H75+IF(O75="",0,O75)))) -> 0.13923599 | Z75: =IF(OR(Y75="",多次统计数据!$B$8=""),"",Y75-多次统计数据!$B$8) -> 0.011104897 | AA75: =IF(OR(I75="",M75="",M75<I75),"",M75-I75) -> 5 | AB75: =IF(OR(A75="",多次统计数据!$B$8="",多次统计数据!$B$6<=0,多次统计数据!$B$6>=1),"",1-POWER(1+多次统计数据!$B$8,-多次统计数据!$B$6/(1-多次统计数据!$B$6))) -> 0.11918507 | AC75: =IF(OR(AB75="",多次统计数据!$B$9=""),"",IF(多次统计数据!$B$9<AB75,"低于上限","达到或超过上限")) -> 低于上限 | AD75: 4-良好
A76: T2026075 | B76: 601318 | C76: 117309 | D76: 0.01 | E76: 21.25 | F76: =IF(OR(C76="",D76="",E76="",N76="",C76<=0,D76<=0,E76<=N76),"",ROUNDDOWN((C76*D76)/(E76-N76)/100,0)*100) -> 700 | G76: =IF(OR(A76="",F76="",E76="",N76="",E76<=N76,账户数据!$B$7=""),"",IF(账户数据!$B$9+IF(H76="",F76*(E76-N76),0)>=账户数据!$B$7,"禁止开仓","允许开仓")) -> 禁止开仓 | I76: 46202 | J76: 23.38 | L76: =IF(K76="","",H76) | N76: 19.75 | O76: 0 | P76: 5 | Q76: 量价背离与板块共振共同确认 | R76: 止损设在19.75 | S76: 目标参考成交量 | U76: =IF(OR(E76="",J76="",E76<=0),"",(J76-E76)/E76) -> 0.10023529 | V76: =IF(OR(E76="",N76="",E76<=0),"",(E76-N76)/E76) -> 0.070588235 | W76: =IF(OR(U76="",V76="",V76<=0),"",U76/V76) -> 1.42 | X76: =IF(OR(K76="",L76="",E76="",H76=""),"",K76*L76-E76*H76-IF(O76="",0,O76)-IF(P76="",0,P76)) | Y76: =IF(OR(X76="",E76="",H76=""),"",IF(E76*H76+IF(O76="",0,O76)<=0,"",X76/(E76*H76+IF(O76="",0,O76)))) | Z76: =IF(OR(Y76="",多次统计数据!$B$8=""),"",Y76-多次统计数据!$B$8) | AA76: =IF(OR(I76="",M76="",M76<I76),"",M76-I76) | AB76: =IF(OR(A76="",多次统计数据!$B$8="",多次统计数据!$B$6<=0,多次统计数据!$B$6>=1),"",1-POWER(1+多次统计数据!$B$8,-多次统计数据!$B$6/(1-多次统计数据!$B$6))) -> 0.11918507 | AC76: =IF(OR(AB76="",多次统计数据!$B$9=""),"",IF(多次统计数据!$B$9<AB76,"低于上限","达到或超过上限")) -> 低于上限
A77: T2026076 | B77: 688981 | C77: 117309 | D77: 0.01 | E77: 22.5 | F77: =IF(OR(C77="",D77="",E77="",N77="",C77<=0,D77<=0,E77<=N77),"",ROUNDDOWN((C77*D77)/(E77-N77)/100,0)*100) -> 1500 | G77: =IF(OR(A77="",F77="",E77="",N77="",E77<=N77,账户数据!$B$7=""),"",IF(账户数据!$B$9+IF(H77="",F77*(E77-N77),0)>=账户数据!$B$7,"禁止开仓","允许开仓")) -> 禁止开仓 | H77: 300 | I77: 46203 | J77: 24.75 | K77: 21.38 | L77: =IF(K77="","",H77) -> 300 | M77: 46210 | N77: 21.75 | O77: 5 | P77: 0 | Q77: 趋势背离与蜡烛图共同确认 | R77: 止损设在21.75 | S77: 目标参考RSI | T77: 按计划成交 | U77: =IF(OR(E77="",J77="",E77<=0),"",(J77-E77)/E77) -> 0.1 | V77: =IF(OR(E77="",N77="",E77<=0),"",(E77-N77)/E77) -> 0.033333333 | W77: =IF(OR(U77="",V77="",V77<=0),"",U77/V77) -> 3 | X77: =IF(OR(K77="",L77="",E77="",H77=""),"",K77*L77-E77*H77-IF(O77="",0,O77)-IF(P77="",0,P77)) -> -341 | Y77: =IF(OR(X77="",E77="",H77=""),"",IF(E77*H77+IF(O77="",0,O77)<=0,"",X77/(E77*H77+IF(O77="",0,O77)))) -> -0.050481125 | Z77: =IF(OR(Y77="",多次统计数据!$B$8=""),"",Y77-多次统计数据!$B$8) -> -0.17861222 | AA77: =IF(OR(I77="",M77="",M77<I77),"",M77-I77) -> 7 | AB77: =IF(OR(A77="",多次统计数据!$B$8="",多次统计数据!$B$6<=0,多次统计数据!$B$6>=1),"",1-POWER(1+多次统计数据!$B$8,-多次统计数据!$B$6/(1-多次统计数据!$B$6))) -> 0.11918507 | AC77: =IF(OR(AB77="",多次统计数据!$B$9=""),"",IF(多次统计数据!$B$9<AB77,"低于上限","达到或超过上限")) -> 低于上限 | AD77: 2-较差
A78: T2026077 | B78: 000858 | C78: 116968 | D78: 0.01 | E78: 10 | F78: =IF(OR(C78="",D78="",E78="",N78="",C78<=0,D78<=0,E78<=N78),"",ROUNDDOWN((C78*D78)/(E78-N78)/100,0)*100) -> 1100 | G78: =IF(OR(A78="",F78="",E78="",N78="",E78<=N78,账户数据!$B$7=""),"",IF(账户数据!$B$9+IF(H78="",F78*(E78-N78),0)>=账户数据!$B$7,"禁止开仓","允许开仓")) -> 禁止开仓 | H78: 400 | I78: 46204 | J78: 11 | K78: 9 | L78: =IF(K78="","",H78) -> 400 | M78: 46205 | N78: 9 | O78: 5 | P78: 5 | Q78: ATR与趋势线共同确认 | R78: 止损设在9.00 | S78: 目标参考KDJ | T78: 按计划成交 | U78: =IF(OR(E78="",J78="",E78<=0),"",(J78-E78)/E78) -> 0.1 | V78: =IF(OR(E78="",N78="",E78<=0),"",(E78-N78)/E78) -> 0.1 | W78: =IF(OR(U78="",V78="",V78<=0),"",U78/V78) -> 1 | X78: =IF(OR(K78="",L78="",E78="",H78=""),"",K78*L78-E78*H78-IF(O78="",0,O78)-IF(P78="",0,P78)) -> -410 | Y78: =IF(OR(X78="",E78="",H78=""),"",IF(E78*H78+IF(O78="",0,O78)<=0,"",X78/(E78*H78+IF(O78="",0,O78)))) -> -0.10237203 | Z78: =IF(OR(Y78="",多次统计数据!$B$8=""),"",Y78-多次统计数据!$B$8) -> -0.23050313 | AA78: =IF(OR(I78="",M78="",M78<I78),"",M78-I78) -> 1 | AB78: =IF(OR(A78="",多次统计数据!$B$8="",多次统计数据!$B$6<=0,多次统计数据!$B$6>=1),"",1-POWER(1+多次统计数据!$B$8,-多次统计数据!$B$6/(1-多次统计数据!$B$6))) -> 0.11918507 | AC78: =IF(OR(AB78="",多次统计数据!$B$9=""),"",IF(多次统计数据!$B$9<AB78,"低于上限","达到或超过上限")) -> 低于上限 | AD78: 2-较差
A79: T2026078 | B79: 600036 | C79: 116558 | D79: 0.01 | E79: 11.25 | F79: =IF(OR(C79="",D79="",E79="",N79="",C79<=0,D79<=0,E79<=N79),"",ROUNDDOWN((C79*D79)/(E79-N79)/100,0)*100) -> 900 | G79: =IF(OR(A79="",F79="",E79="",N79="",E79<=N79,账户数据!$B$7=""),"",IF(账户数据!$B$9+IF(H79="",F79*(E79-N79),0)>=账户数据!$B$7,"禁止开仓","允许开仓")) -> 禁止开仓 | H79: 500 | I79: 46205 | J79: 12.38 | K79: 10 | L79: =IF(K79="","",H79) -> 500 | M79: 46207 | N79: 10 | O79: 0 | P79: 5 | Q79: 换手率与MACD共同确认 | R79: 止损设在10.00 | S79: 目标参考布林带 | T79: 按计划成交 | U79: =IF(OR(E79="",J79="",E79<=0),"",(J79-E79)/E79) -> 0.10044444 | V79: =IF(OR(E79="",N79="",E79<=0),"",(E79-N79)/E79) -> 0.11111111 | W79: =IF(OR(U79="",V79="",V79<=0),"",U79/V79) -> 0.904 | X79: =IF(OR(K79="",L79="",E79="",H79=""),"",K79*L79-E79*H79-IF(O79="",0,O79)-IF(P79="",0,P79)) -> -630 | Y79: =IF(OR(X79="",E79="",H79=""),"",IF(E79*H79+IF(O79="",0,O79)<=0,"",X79/(E79*H79+IF(O79="",0,O79)))) -> -0.112 | Z79: =IF(OR(Y79="",多次统计数据!$B$8=""),"",Y79-多次统计数据!$B$8) -> -0.24013109 | AA79: =IF(OR(I79="",M79="",M79<I79),"",M79-I79) -> 2 | AB79: =IF(OR(A79="",多次统计数据!$B$8="",多次统计数据!$B$6<=0,多次统计数据!$B$6>=1),"",1-POWER(1+多次统计数据!$B$8,-多次统计数据!$B$6/(1-多次统计数据!$B$6))) -> 0.11918507 | AC79: =IF(OR(AB79="",多次统计数据!$B$9=""),"",IF(多次统计数据!$B$9<AB79,"低于上限","达到或超过上限")) -> 低于上限 | AD79: 2-较差
A80: T2026079 | B80: 002415 | C80: 115928 | D80: 0.01 | E80: 12.5 | F80: =IF(OR(C80="",D80="",E80="",N80="",C80<=0,D80<=0,E80<=N80),"",ROUNDDOWN((C80*D80)/(E80-N80)/100,0)*100) -> 700 | G80: =IF(OR(A80="",F80="",E80="",N80="",E80<=N80,账户数据!$B$7=""),"",IF(账户数据!$B$9+IF(H80="",F80*(E80-N80),0)>=账户数据!$B$7,"禁止开仓","允许开仓")) -> 禁止开仓 | H80: 500 | I80: 46206 | J80: 13.75 | K80: 12.5 | L80: =IF(K80="","",H80) -> 500 | M80: 46209 | N80: 11 | O80: 0 | P80: 0 | Q80: 相对强弱与移动平均线共同确认 | R80: 止损设在11.00 | S80: 目标参考支撑位 | T80: 按计划成交 | U80: =IF(OR(E80="",J80="",E80<=0),"",(J80-E80)/E80) -> 0.1 | V80: =IF(OR(E80="",N80="",E80<=0),"",(E80-N80)/E80) -> 0.12 | W80: =IF(OR(U80="",V80="",V80<=0),"",U80/V80) -> 0.83333333 | X80: =IF(OR(K80="",L80="",E80="",H80=""),"",K80*L80-E80*H80-IF(O80="",0,O80)-IF(P80="",0,P80)) -> 0 | Y80: =IF(OR(X80="",E80="",H80=""),"",IF(E80*H80+IF(O80="",0,O80)<=0,"",X80/(E80*H80+IF(O80="",0,O80)))) -> 0 | Z80: =IF(OR(Y80="",多次统计数据!$B$8=""),"",Y80-多次统计数据!$B$8) -> -0.12813109 | AA80: =IF(OR(I80="",M80="",M80<I80),"",M80-I80) -> 3 | AB80: =IF(OR(A80="",多次统计数据!$B$8="",多次统计数据!$B$6<=0,多次统计数据!$B$6>=1),"",1-POWER(1+多次统计数据!$B$8,-多次统计数据!$B$6/(1-多次统计数据!$B$6))) -> 0.11918507 | AC80: =IF(OR(AB80="",多次统计数据!$B$9=""),"",IF(多次统计数据!$B$9<AB80,"低于上限","达到或超过上限")) -> 低于上限 | AD80: 3-一般
A81: T2026080 | B81: 601899 | C81: 115928 | D81: 0.01 | E81: 13.75 | F81: =IF(OR(C81="",D81="",E81="",N81="",C81<=0,D81<=0,E81<=N81),"",ROUNDDOWN((C81*D81)/(E81-N81)/100,0)*100) -> 1500 | G81: =IF(OR(A81="",F81="",E81="",N81="",E81<=N81,账户数据!$B$7=""),"",IF(账户数据!$B$9+IF(H81="",F81*(E81-N81),0)>=账户数据!$B$7,"禁止开仓","允许开仓")) -> 禁止开仓 | H81: 1500 | I81: 46207 | J81: 15.13 | L81: =IF(K81="","",H81) | N81: 13 | O81: 5 | P81: 0 | Q81: 板块共振与成交量共同确认 | R81: 止损设在13.00 | S81: 目标参考压力位 | U81: =IF(OR(E81="",J81="",E81<=0),"",(J81-E81)/E81) -> 0.10036364 | V81: =IF(OR(E81="",N81="",E81<=0),"",(E81-N81)/E81) -> 0.054545455 | W81: =IF(OR(U81="",V81="",V81<=0),"",U81/V81) -> 1.84 | X81: =IF(OR(K81="",L81="",E81="",H81=""),"",K81*L81-E81*H81-IF(O81="",0,O81)-IF(P81="",0,P81)) | Y81: =IF(OR(X81="",E81="",H81=""),"",IF(E81*H81+IF(O81="",0,O81)<=0,"",X81/(E81*H81+IF(O81="",0,O81)))) | Z81: =IF(OR(Y81="",多次统计数据!$B$8=""),"",Y81-多次统计数据!$B$8) | AA81: =IF(OR(I81="",M81="",M81<I81),"",M81-I81) | AB81: =IF(OR(A81="",多次统计数据!$B$8="",多次统计数据!$B$6<=0,多次统计数据!$B$6>=1),"",1-POWER(1+多次统计数据!$B$8,-多次统计数据!$B$6/(1-多次统计数据!$B$6))) -> 0.11918507 | AC81: =IF(OR(AB81="",多次统计数据!$B$9=""),"",IF(多次统计数据!$B$9<AB81,"低于上限","达到或超过上限")) -> 低于上限
A82: T2026081 | B82: 600519 | C82: 115928 | D82: 0.01 | E82: 15 | F82: =IF(OR(C82="",D82="",E82="",N82="",C82<=0,D82<=0,E82<=N82),"",ROUNDDOWN((C82*D82)/(E82-N82)/100,0)*100) -> 1100 | G82: =IF(OR(A82="",F82="",E82="",N82="",E82<=N82,账户数据!$B$7=""),"",IF(账户数据!$B$9+IF(H82="",F82*(E82-N82),0)>=账户数据!$B$7,"禁止开仓","允许开仓")) -> 禁止开仓 | H82: 200 | I82: 46208 | J82: 16.5 | K82: 16.8 | L82: =IF(K82="","",H82) -> 200 | M82: 46213 | N82: 14 | O82: 0 | P82: 5 | Q82: 蜡烛图与RSI共同确认 | R82: 止损设在14.00 | S82: 目标参考缺口 | T82: 按计划成交 | U82: =IF(OR(E82="",J82="",E82<=0),"",(J82-E82)/E82) -> 0.1 | V82: =IF(OR(E82="",N82="",E82<=0),"",(E82-N82)/E82) -> 0.066666667 | W82: =IF(OR(U82="",V82="",V82<=0),"",U82/V82) -> 1.5 | X82: =IF(OR(K82="",L82="",E82="",H82=""),"",K82*L82-E82*H82-IF(O82="",0,O82)-IF(P82="",0,P82)) -> 355 | Y82: =IF(OR(X82="",E82="",H82=""),"",IF(E82*H82+IF(O82="",0,O82)<=0,"",X82/(E82*H82+IF(O82="",0,O82)))) -> 0.11833333 | Z82: =IF(OR(Y82="",多次统计数据!$B$8=""),"",Y82-多次统计数据!$B$8) -> -0.0097977567 | AA82: =IF(OR(I82="",M82="",M82<I82),"",M82-I82) -> 5 | AB82: =IF(OR(A82="",多次统计数据!$B$8="",多次统计数据!$B$6<=0,多次统计数据!$B$6>=1),"",1-POWER(1+多次统计数据!$B$8,-多次统计数据!$B$6/(1-多次统计数据!$B$6))) -> 0.11918507 | AC82: =IF(OR(AB82="",多次统计数据!$B$9=""),"",IF(多次统计数据!$B$9<AB82,"低于上限","达到或超过上限")) -> 低于上限 | AD82: 4-良好
A83: T2026082 | B83: 000001 | C83: 116283 | D83: 0.01 | E83: 16.25 | F83: =IF(OR(C83="",D83="",E83="",N83="",C83<=0,D83<=0,E83<=N83),"",ROUNDDOWN((C83*D83)/(E83-N83)/100,0)*100) -> 900 | G83: =IF(OR(A83="",F83="",E83="",N83="",E83<=N83,账户数据!$B$7=""),"",IF(账户数据!$B$9+IF(H83="",F83*(E83-N83),0)>=账户数据!$B$7,"禁止开仓","允许开仓")) -> 禁止开仓 | H83: 300 | I83: 46209 | J83: 17.88 | K83: 18.36 | L83: =IF(K83="","",H83) -> 300 | M83: 46215 | N83: 15 | O83: 5 | P83: 5 | Q83: 趋势线与KDJ共同确认 | R83: 止损设在15.00 | S83: 目标参考形态突破 | T83: 按计划成交 | U83: =IF(OR(E83="",J83="",E83<=0),"",(J83-E83)/E83) -> 0.10030769 | V83: =IF(OR(E83="",N83="",E83<=0),"",(E83-N83)/E83) -> 0.076923077 | W83: =IF(OR(U83="",V83="",V83<=0),"",U83/V83) -> 1.304 | X83: =IF(OR(K83="",L83="",E83="",H83=""),"",K83*L83-E83*H83-IF(O83="",0,O83)-IF(P83="",0,P83)) -> 623 | Y83: =IF(OR(X83="",E83="",H83=""),"",IF(E83*H83+IF(O83="",0,O83)<=0,"",X83/(E83*H83+IF(O83="",0,O83)))) -> 0.12766393 | Z83: =IF(OR(Y83="",多次统计数据!$B$8=""),"",Y83-多次统计数据!$B$8) -> -0.00046715565 | AA83: =IF(OR(I83="",M83="",M83<I83),"",M83-I83) -> 6 | AB83: =IF(OR(A83="",多次统计数据!$B$8="",多次统计数据!$B$6<=0,多次统计数据!$B$6>=1),"",1-POWER(1+多次统计数据!$B$8,-多次统计数据!$B$6/(1-多次统计数据!$B$6))) -> 0.11918507 | AC83: =IF(OR(AB83="",多次统计数据!$B$9=""),"",IF(多次统计数据!$B$9<AB83,"低于上限","达到或超过上限")) -> 低于上限 | AD83: 4-良好
A84: T2026083 | B84: 300750 | C84: 116906 | D84: 0.01 | E84: 17.5 | F84: =IF(OR(C84="",D84="",E84="",N84="",C84<=0,D84<=0,E84<=N84),"",ROUNDDOWN((C84*D84)/(E84-N84)/100,0)*100) -> 700 | G84: =IF(OR(A84="",F84="",E84="",N84="",E84<=N84,账户数据!$B$7=""),"",IF(账户数据!$B$9+IF(H84="",F84*(E84-N84),0)>=账户数据!$B$7,"禁止开仓","允许开仓")) -> 禁止开仓 | H84: 400 | I84: 46210 | J84: 19.25 | K84: 19.95 | L84: =IF(K84="","",H84) -> 400 | M84: 46217 | N84: 16 | O84: 5 | P84: 5 | Q84: MACD与布林带共同确认 | R84: 止损设在16.00 | S84: 目标参考均线金叉 | T84: 按计划成交 | U84: =IF(OR(E84="",J84="",E84<=0),"",(J84-E84)/E84) -> 0.1 | V84: =IF(OR(E84="",N84="",E84<=0),"",(E84-N84)/E84) -> 0.085714286 | W84: =IF(OR(U84="",V84="",V84<=0),"",U84/V84) -> 1.1666667 | X84: =IF(OR(K84="",L84="",E84="",H84=""),"",K84*L84-E84*H84-IF(O84="",0,O84)-IF(P84="",0,P84)) -> 970 | Y84: =IF(OR(X84="",E84="",H84=""),"",IF(E84*H84+IF(O84="",0,O84)<=0,"",X84/(E84*H84+IF(O84="",0,O84)))) -> 0.13847252 | Z84: =IF(OR(Y84="",多次统计数据!$B$8=""),"",Y84-多次统计数据!$B$8) -> 0.01034143 | AA84: =IF(OR(I84="",M84="",M84<I84),"",M84-I84) -> 7 | AB84: =IF(OR(A84="",多次统计数据!$B$8="",多次统计数据!$B$6<=0,多次统计数据!$B$6>=1),"",1-POWER(1+多次统计数据!$B$8,-多次统计数据!$B$6/(1-多次统计数据!$B$6))) -> 0.11918507 | AC84: =IF(OR(AB84="",多次统计数据!$B$9=""),"",IF(多次统计数据!$B$9<AB84,"低于上限","达到或超过上限")) -> 低于上限 | AD84: 4-良好
A85: T2026084 | B85: 002594 | C85: 117876 | D85: 0.01 | E85: 18.75 | F85: =IF(OR(C85="",D85="",E85="",N85="",C85<=0,D85<=0,E85<=N85),"",ROUNDDOWN((C85*D85)/(E85-N85)/100,0)*100) -> 1500 | G85: =IF(OR(A85="",F85="",E85="",N85="",E85<=N85,账户数据!$B$7=""),"",IF(账户数据!$B$9+IF(H85="",F85*(E85-N85),0)>=账户数据!$B$7,"禁止开仓","允许开仓")) -> 禁止开仓 | H85: 1200 | I85: 46211 | J85: 20.62 | K85: 21 | L85: =IF(K85="","",H85) -> 1200 | M85: 46212 | N85: 18 | O85: 0 | P85: 0 | Q85: 移动平均线与支撑位共同确认 | R85: 止损设在18.00 | S85: 目标参考均线死叉 | T85: 按计划成交 | U85: =IF(OR(E85="",J85="",E85<=0),"",(J85-E85)/E85) -> 0.099733333 | V85: =IF(OR(E85="",N85="",E85<=0),"",(E85-N85)/E85) -> 0.04 | W85: =IF(OR(U85="",V85="",V85<=0),"",U85/V85) -> 2.4933333 | X85: =IF(OR(K85="",L85="",E85="",H85=""),"",K85*L85-E85*H85-IF(O85="",0,O85)-IF(P85="",0,P85)) -> 2700 | Y85: =IF(OR(X85="",E85="",H85=""),"",IF(E85*H85+IF(O85="",0,O85)<=0,"",X85/(E85*H85+IF(O85="",0,O85)))) -> 0.12 | Z85: =IF(OR(Y85="",多次统计数据!$B$8=""),"",Y85-多次统计数据!$B$8) -> -0.0081310901 | AA85: =IF(OR(I85="",M85="",M85<I85),"",M85-I85) -> 1 | AB85: =IF(OR(A85="",多次统计数据!$B$8="",多次统计数据!$B$6<=0,多次统计数据!$B$6>=1),"",1-POWER(1+多次统计数据!$B$8,-多次统计数据!$B$6/(1-多次统计数据!$B$6))) -> 0.11918507 | AC85: =IF(OR(AB85="",多次统计数据!$B$9=""),"",IF(多次统计数据!$B$9<AB85,"低于上限","达到或超过上限")) -> 低于上限 | AD85: 4-良好
A86: T2026085 | B86: 601318 | C86: 120576 | D86: 0.01 | E86: 20 | F86: =IF(OR(C86="",D86="",E86="",N86="",C86<=0,D86<=0,E86<=N86),"",ROUNDDOWN((C86*D86)/(E86-N86)/100,0)*100) -> 1200 | G86: =IF(OR(A86="",F86="",E86="",N86="",E86<=N86,账户数据!$B$7=""),"",IF(账户数据!$B$9+IF(H86="",F86*(E86-N86),0)>=账户数据!$B$7,"禁止开仓","允许开仓")) -> 禁止开仓 | H86: 1200 | I86: 46212 | J86: 22 | K86: 18.8 | L86: =IF(K86="","",H86) -> 1200 | M86: 46214 | N86: 19 | O86: 5 | P86: 5 | Q86: 成交量与压力位共同确认 | R86: 止损设在19.00 | S86: 目标参考量价背离 | T86: 按计划成交 | U86: =IF(OR(E86="",J86="",E86<=0),"",(J86-E86)/E86) -> 0.1 | V86: =IF(OR(E86="",N86="",E86<=0),"",(E86-N86)/E86) -> 0.05 | W86: =IF(OR(U86="",V86="",V86<=0),"",U86/V86) -> 2 | X86: =IF(OR(K86="",L86="",E86="",H86=""),"",K86*L86-E86*H86-IF(O86="",0,O86)-IF(P86="",0,P86)) -> -1450 | Y86: =IF(OR(X86="",E86="",H86=""),"",IF(E86*H86+IF(O86="",0,O86)<=0,"",X86/(E86*H86+IF(O86="",0,O86)))) -> -0.060404082 | Z86: =IF(OR(Y86="",多次统计数据!$B$8=""),"",Y86-多次统计数据!$B$8) -> -0.18853517 | AA86: =IF(OR(I86="",M86="",M86<I86),"",M86-I86) -> 2 | AB86: =IF(OR(A86="",多次统计数据!$B$8="",多次统计数据!$B$6<=0,多次统计数据!$B$6>=1),"",1-POWER(1+多次统计数据!$B$8,-多次统计数据!$B$6/(1-多次统计数据!$B$6))) -> 0.11918507 | AC86: =IF(OR(AB86="",多次统计数据!$B$9=""),"",IF(多次统计数据!$B$9<AB86,"低于上限","达到或超过上限")) -> 低于上限 | AD86: 2-较差
A87: T2026086 | B87: 688981 | C87: 119126 | D87: 0.01 | E87: 21.25 | F87: =IF(OR(C87="",D87="",E87="",N87="",C87<=0,D87<=0,E87<=N87),"",ROUNDDOWN((C87*D87)/(E87-N87)/100,0)*100) -> 900 | G87: =IF(OR(A87="",F87="",E87="",N87="",E87<=N87,账户数据!$B$7=""),"",IF(账户数据!$B$9+IF(H87="",F87*(E87-N87),0)>=账户数据!$B$7,"禁止开仓","允许开仓")) -> 禁止开仓 | H87: 100 | I87: 46213 | J87: 23.38 | K87: 20 | L87: =IF(K87="","",H87) -> 100 | M87: 46216 | N87: 20 | O87: 5 | P87: 5 | Q87: RSI与缺口共同确认 | R87: 止损设在20.00 | S87: 目标参考趋势背离 | T87: 按计划成交 | U87: =IF(OR(E87="",J87="",E87<=0),"",(J87-E87)/E87) -> 0.10023529 | V87: =IF(OR(E87="",N87="",E87<=0),"",(E87-N87)/E87) -> 0.058823529 | W87: =IF(OR(U87="",V87="",V87<=0),"",U87/V87) -> 1.704 | X87: =IF(OR(K87="",L87="",E87="",H87=""),"",K87*L87-E87*H87-IF(O87="",0,O87)-IF(P87="",0,P87)) -> -135 | Y87: =IF(OR(X87="",E87="",H87=""),"",IF(E87*H87+IF(O87="",0,O87)<=0,"",X87/(E87*H87+IF(O87="",0,O87)))) -> -0.063380282 | Z87: =IF(OR(Y87="",多次统计数据!$B$8=""),"",Y87-多次统计数据!$B$8) -> -0.19151137 | AA87: =IF(OR(I87="",M87="",M87<I87),"",M87-I87) -> 3 | AB87: =IF(OR(A87="",多次统计数据!$B$8="",多次统计数据!$B$6<=0,多次统计数据!$B$6>=1),"",1-POWER(1+多次统计数据!$B$8,-多次统计数据!$B$6/(1-多次统计数据!$B$6))) -> 0.11918507 | AC87: =IF(OR(AB87="",多次统计数据!$B$9=""),"",IF(多次统计数据!$B$9<AB87,"低于上限","达到或超过上限")) -> 低于上限 | AD87: 2-较差
A88: T2026087 | B88: 000858 | C88: 118991 | D88: 0.01 | E88: 22.5 | F88: =IF(OR(C88="",D88="",E88="",N88="",C88<=0,D88<=0,E88<=N88),"",ROUNDDOWN((C88*D88)/(E88-N88)/100,0)*100) -> 700 | G88: =IF(OR(A88="",F88="",E88="",N88="",E88<=N88,账户数据!$B$7=""),"",IF(账户数据!$B$9+IF(H88="",F88*(E88-N88),0)>=账户数据!$B$7,"禁止开仓","允许开仓")) -> 禁止开仓 | H88: 200 | I88: 46214 | J88: 24.75 | K88: 21 | L88: =IF(K88="","",H88) -> 200 | M88: 46218 | N88: 21 | O88: 0 | P88: 5 | Q88: KDJ与形态突破共同确认 | R88: 止损设在21.00 | S88: 目标参考ATR | T88: 按计划成交 | U88: =IF(OR(E88="",J88="",E88<=0),"",(J88-E88)/E88) -> 0.1 | V88: =IF(OR(E88="",N88="",E88<=0),"",(E88-N88)/E88) -> 0.066666667 | W88: =IF(OR(U88="",V88="",V88<=0),"",U88/V88) -> 1.5 | X88: =IF(OR(K88="",L88="",E88="",H88=""),"",K88*L88-E88*H88-IF(O88="",0,O88)-IF(P88="",0,P88)) -> -305 | Y88: =IF(OR(X88="",E88="",H88=""),"",IF(E88*H88+IF(O88="",0,O88)<=0,"",X88/(E88*H88+IF(O88="",0,O88)))) -> -0.067777778 | Z88: =IF(OR(Y88="",多次统计数据!$B$8=""),"",Y88-多次统计数据!$B$8) -> -0.19590887 | AA88: =IF(OR(I88="",M88="",M88<I88),"",M88-I88) -> 4 | AB88: =IF(OR(A88="",多次统计数据!$B$8="",多次统计数据!$B$6<=0,多次统计数据!$B$6>=1),"",1-POWER(1+多次统计数据!$B$8,-多次统计数据!$B$6/(1-多次统计数据!$B$6))) -> 0.11918507 | AC88: =IF(OR(AB88="",多次统计数据!$B$9=""),"",IF(多次统计数据!$B$9<AB88,"低于上限","达到或超过上限")) -> 低于上限 | AD88: 2-较差
A89: T2026088 | B89: 600036 | C89: 118686 | D89: 0.01 | E89: 10 | F89: =IF(OR(C89="",D89="",E89="",N89="",C89<=0,D89<=0,E89<=N89),"",ROUNDDOWN((C89*D89)/(E89-N89)/100,0)*100) -> 1500 | G89: =IF(OR(A89="",F89="",E89="",N89="",E89<=N89,账户数据!$B$7=""),"",IF(账户数据!$B$9+IF(H89="",F89*(E89-N89),0)>=账户数据!$B$7,"禁止开仓","允许开仓")) -> 禁止开仓 | H89: 900 | I89: 46215 | J89: 11 | K89: 9.25 | L89: =IF(K89="","",H89) -> 900 | M89: 46220 | N89: 9.25 | O89: 5 | P89: 0 | Q89: 布林带与均线金叉共同确认 | R89: 止损设在9.25 | S89: 目标参考换手率 | T89: 按计划成交 | U89: =IF(OR(E89="",J89="",E89<=0),"",(J89-E89)/E89) -> 0.1 | V89: =IF(OR(E89="",N89="",E89<=0),"",(E89-N89)/E89) -> 0.075 | W89: =IF(OR(U89="",V89="",V89<=0),"",U89/V89) -> 1.3333333 | X89: =IF(OR(K89="",L89="",E89="",H89=""),"",K89*L89-E89*H89-IF(O89="",0,O89)-IF(P89="",0,P89)) -> -680 | Y89: =IF(OR(X89="",E89="",H89=""),"",IF(E89*H89+IF(O89="",0,O89)<=0,"",X89/(E89*H89+IF(O89="",0,O89)))) -> -0.075513604 | Z89: =IF(OR(Y89="",多次统计数据!$B$8=""),"",Y89-多次统计数据!$B$8) -> -0.20364469 | AA89: =IF(OR(I89="",M89="",M89<I89),"",M89-I89) -> 5 | AB89: =IF(OR(A89="",多次统计数据!$B$8="",多次统计数据!$B$6<=0,多次统计数据!$B$6>=1),"",1-POWER(1+多次统计数据!$B$8,-多次统计数据!$B$6/(1-多次统计数据!$B$6))) -> 0.11918507 | AC89: =IF(OR(AB89="",多次统计数据!$B$9=""),"",IF(多次统计数据!$B$9<AB89,"低于上限","达到或超过上限")) -> 低于上限 | AD89: 2-较差
A90: T2026089 | B90: 002415 | C90: 118006 | D90: 0.01 | E90: 11.25 | F90: =IF(OR(C90="",D90="",E90="",N90="",C90<=0,D90<=0,E90<=N90),"",ROUNDDOWN((C90*D90)/(E90-N90)/100,0)*100) -> 1100 | G90: =IF(OR(A90="",F90="",E90="",N90="",E90<=N90,账户数据!$B$7=""),"",IF(账户数据!$B$9+IF(H90="",F90*(E90-N90),0)>=账户数据!$B$7,"禁止开仓","允许开仓")) -> 禁止开仓 | H90: 800 | I90: 46216 | J90: 12.38 | K90: 11.25 | L90: =IF(K90="","",H90) -> 800 | M90: 46222 | N90: 10.25 | O90: 0 | P90: 0 | Q90: 支撑位与均线死叉共同确认 | R90: 止损设在10.25 | S90: 目标参考相对强弱 | T90: 按计划成交 | U90: =IF(OR(E90="",J90="",E90<=0),"",(J90-E90)/E90) -> 0.10044444 | V90: =IF(OR(E90="",N90="",E90<=0),"",(E90-N90)/E90) -> 0.088888889 | W90: =IF(OR(U90="",V90="",V90<=0),"",U90/V90) -> 1.13 | X90: =IF(OR(K90="",L90="",E90="",H90=""),"",K90*L90-E90*H90-IF(O90="",0,O90)-IF(P90="",0,P90)) -> 0 | Y90: =IF(OR(X90="",E90="",H90=""),"",IF(E90*H90+IF(O90="",0,O90)<=0,"",X90/(E90*H90+IF(O90="",0,O90)))) -> 0 | Z90: =IF(OR(Y90="",多次统计数据!$B$8=""),"",Y90-多次统计数据!$B$8) -> -0.12813109 | AA90: =IF(OR(I90="",M90="",M90<I90),"",M90-I90) -> 6 | AB90: =IF(OR(A90="",多次统计数据!$B$8="",多次统计数据!$B$6<=0,多次统计数据!$B$6>=1),"",1-POWER(1+多次统计数据!$B$8,-多次统计数据!$B$6/(1-多次统计数据!$B$6))) -> 0.11918507 | AC90: =IF(OR(AB90="",多次统计数据!$B$9=""),"",IF(多次统计数据!$B$9<AB90,"低于上限","达到或超过上限")) -> 低于上限 | AD90: 3-一般
A91: T2026090 | B91: 601899 | C91: 118006 | D91: 0.01 | E91: 12.5 | F91: =IF(OR(C91="",D91="",E91="",N91="",C91<=0,D91<=0,E91<=N91),"",ROUNDDOWN((C91*D91)/(E91-N91)/100,0)*100) -> 900 | G91: =IF(OR(A91="",F91="",E91="",N91="",E91<=N91,账户数据!$B$7=""),"",IF(账户数据!$B$9+IF(H91="",F91*(E91-N91),0)>=账户数据!$B$7,"禁止开仓","允许开仓")) -> 禁止开仓 | H91: 900 | I91: 46217 | J91: 13.75 | L91: =IF(K91="","",H91) | N91: 11.25 | O91: 0 | P91: 5 | Q91: 压力位与量价背离共同确认 | R91: 止损设在11.25 | S91: 目标参考板块共振 | U91: =IF(OR(E91="",J91="",E91<=0),"",(J91-E91)/E91) -> 0.1 | V91: =IF(OR(E91="",N91="",E91<=0),"",(E91-N91)/E91) -> 0.1 | W91: =IF(OR(U91="",V91="",V91<=0),"",U91/V91) -> 1 | X91: =IF(OR(K91="",L91="",E91="",H91=""),"",K91*L91-E91*H91-IF(O91="",0,O91)-IF(P91="",0,P91)) | Y91: =IF(OR(X91="",E91="",H91=""),"",IF(E91*H91+IF(O91="",0,O91)<=0,"",X91/(E91*H91+IF(O91="",0,O91)))) | Z91: =IF(OR(Y91="",多次统计数据!$B$8=""),"",Y91-多次统计数据!$B$8) | AA91: =IF(OR(I91="",M91="",M91<I91),"",M91-I91) | AB91: =IF(OR(A91="",多次统计数据!$B$8="",多次统计数据!$B$6<=0,多次统计数据!$B$6>=1),"",1-POWER(1+多次统计数据!$B$8,-多次统计数据!$B$6/(1-多次统计数据!$B$6))) -> 0.11918507 | AC91: =IF(OR(AB91="",多次统计数据!$B$9=""),"",IF(多次统计数据!$B$9<AB91,"低于上限","达到或超过上限")) -> 低于上限
A92: T2026091 | B92: 600519 | C92: 118006 | D92: 0.01 | E92: 13.75 | F92: =IF(OR(C92="",D92="",E92="",N92="",C92<=0,D92<=0,E92<=N92),"",ROUNDDOWN((C92*D92)/(E92-N92)/100,0)*100) -> 700 | G92: =IF(OR(A92="",F92="",E92="",N92="",E92<=N92,账户数据!$B$7=""),"",IF(账户数据!$B$9+IF(H92="",F92*(E92-N92),0)>=账户数据!$B$7,"禁止开仓","允许开仓")) -> 禁止开仓 | H92: 100 | I92: 46218 | J92: 15.13 | K92: 15.54 | L92: =IF(K92="","",H92) -> 100 | M92: 46219 | N92: 12.25 | O92: 5 | P92: 5 | Q92: 缺口与趋势背离共同确认 | R92: 止损设在12.25 | S92: 目标参考蜡烛图 | T92: 按计划成交 | U92: =IF(OR(E92="",J92="",E92<=0),"",(J92-E92)/E92) -> 0.10036364 | V92: =IF(OR(E92="",N92="",E92<=0),"",(E92-N92)/E92) -> 0.10909091 | W92: =IF(OR(U92="",V92="",V92<=0),"",U92/V92) -> 0.92 | X92: =IF(OR(K92="",L92="",E92="",H92=""),"",K92*L92-E92*H92-IF(O92="",0,O92)-IF(P92="",0,P92)) -> 169 | Y92: =IF(OR(X92="",E92="",H92=""),"",IF(E92*H92+IF(O92="",0,O92)<=0,"",X92/(E92*H92+IF(O92="",0,O92)))) -> 0.12246377 | Z92: =IF(OR(Y92="",多次统计数据!$B$8=""),"",Y92-多次统计数据!$B$8) -> -0.005667322 | AA92: =IF(OR(I92="",M92="",M92<I92),"",M92-I92) -> 1 | AB92: =IF(OR(A92="",多次统计数据!$B$8="",多次统计数据!$B$6<=0,多次统计数据!$B$6>=1),"",1-POWER(1+多次统计数据!$B$8,-多次统计数据!$B$6/(1-多次统计数据!$B$6))) -> 0.11918507 | AC92: =IF(OR(AB92="",多次统计数据!$B$9=""),"",IF(多次统计数据!$B$9<AB92,"低于上限","达到或超过上限")) -> 低于上限 | AD92: 4-良好
A93: T2026092 | B93: 000001 | C93: 118175 | D93: 0.01 | E93: 15 | F93: =IF(OR(C93="",D93="",E93="",N93="",C93<=0,D93<=0,E93<=N93),"",ROUNDDOWN((C93*D93)/(E93-N93)/100,0)*100) -> 1500 | G93: =IF(OR(A93="",F93="",E93="",N93="",E93<=N93,账户数据!$B$7=""),"",IF(账户数据!$B$9+IF(H93="",F93*(E93-N93),0)>=账户数据!$B$7,"禁止开仓","允许开仓")) -> 禁止开仓 | H93: 600 | I93: 46219 | J93: 16.5 | K93: 17.1 | L93: =IF(K93="","",H93) -> 600 | M93: 46221 | N93: 14.25 | O93: 5 | P93: 0 | Q93: 形态突破与ATR共同确认 | R93: 止损设在14.25 | S93: 目标参考趋势线 | T93: 按计划成交 | U93: =IF(OR(E93="",J93="",E93<=0),"",(J93-E93)/E93) -> 0.1 | V93: =IF(OR(E93="",N93="",E93<=0),"",(E93-N93)/E93) -> 0.05 | W93: =IF(OR(U93="",V93="",V93<=0),"",U93/V93) -> 2 | X93: =IF(OR(K93="",L93="",E93="",H93=""),"",K93*L93-E93*H93-IF(O93="",0,O93)-IF(P93="",0,P93)) -> 1255 | Y93: =IF(OR(X93="",E93="",H93=""),"",IF(E93*H93+IF(O93="",0,O93)<=0,"",X93/(E93*H93+IF(O93="",0,O93)))) -> 0.13936702 | Z93: =IF(OR(Y93="",多次统计数据!$B$8=""),"",Y93-多次统计数据!$B$8) -> 0.011235928 | AA93: =IF(OR(I93="",M93="",M93<I93),"",M93-I93) -> 2 | AB93: =IF(OR(A93="",多次统计数据!$B$8="",多次统计数据!$B$6<=0,多次统计数据!$B$6>=1),"",1-POWER(1+多次统计数据!$B$8,-多次统计数据!$B$6/(1-多次统计数据!$B$6))) -> 0.11918507 | AC93: =IF(OR(AB93="",多次统计数据!$B$9=""),"",IF(多次统计数据!$B$9<AB93,"低于上限","达到或超过上限")) -> 低于上限 | AD93: 4-良好
A94: T2026093 | B94: 300750 | C94: 119430 | D94: 0.01 | E94: 16.25 | F94: =IF(OR(C94="",D94="",E94="",N94="",C94<=0,D94<=0,E94<=N94),"",ROUNDDOWN((C94*D94)/(E94-N94)/100,0)*100) -> 1100 | G94: =IF(OR(A94="",F94="",E94="",N94="",E94<=N94,账户数据!$B$7=""),"",IF(账户数据!$B$9+IF(H94="",F94*(E94-N94),0)>=账户数据!$B$7,"禁止开仓","允许开仓")) -> 禁止开仓 | H94: 600 | I94: 46220 | J94: 17.88 | K94: 18.2 | L94: =IF(K94="","",H94) -> 600 | M94: 46223 | N94: 15.25 | O94: 0 | P94: 5 | Q94: 均线金叉与换手率共同确认 | R94: 止损设在15.25 | S94: 目标参考MACD | T94: 按计划成交 | U94: =IF(OR(E94="",J94="",E94<=0),"",(J94-E94)/E94) -> 0.10030769 | V94: =IF(OR(E94="",N94="",E94<=0),"",(E94-N94)/E94) -> 0.061538462 | W94: =IF(OR(U94="",V94="",V94<=0),"",U94/V94) -> 1.63 | X94: =IF(OR(K94="",L94="",E94="",H94=""),"",K94*L94-E94*H94-IF(O94="",0,O94)-IF(P94="",0,P94)) -> 1165 | Y94: =IF(OR(X94="",E94="",H94=""),"",IF(E94*H94+IF(O94="",0,O94)<=0,"",X94/(E94*H94+IF(O94="",0,O94)))) -> 0.11948718 | Z94: =IF(OR(Y94="",多次统计数据!$B$8=""),"",Y94-多次统计数据!$B$8) -> -0.0086439106 | AA94: =IF(OR(I94="",M94="",M94<I94),"",M94-I94) -> 3 | AB94: =IF(OR(A94="",多次统计数据!$B$8="",多次统计数据!$B$6<=0,多次统计数据!$B$6>=1),"",1-POWER(1+多次统计数据!$B$8,-多次统计数据!$B$6/(1-多次统计数据!$B$6))) -> 0.11918507 | AC94: =IF(OR(AB94="",多次统计数据!$B$9=""),"",IF(多次统计数据!$B$9<AB94,"低于上限","达到或超过上限")) -> 低于上限 | AD94: 4-良好
A95: T2026094 | B95: 002594 | C95: 120595 | D95: 0.01 | E95: 17.5 | F95: =IF(OR(C95="",D95="",E95="",N95="",C95<=0,D95<=0,E95<=N95),"",ROUNDDOWN((C95*D95)/(E95-N95)/100,0)*100) -> 900 | G95: =IF(OR(A95="",F95="",E95="",N95="",E95<=N95,账户数据!$B$7=""),"",IF(账户数据!$B$9+IF(H95="",F95*(E95-N95),0)>=账户数据!$B$7,"禁止开仓","允许开仓")) -> 禁止开仓 | H95: 700 | I95: 46221 | J95: 19.25 | K95: 19.78 | L95: =IF(K95="","",H95) -> 700 | M95: 46225 | N95: 16.25 | O95: 5 | P95: 5 | Q95: 均线死叉与相对强弱共同确认 | R95: 止损设在16.25 | S95: 目标参考移动平均线 | T95: 按计划成交 | U95: =IF(OR(E95="",J95="",E95<=0),"",(J95-E95)/E95) -> 0.1 | V95: =IF(OR(E95="",N95="",E95<=0),"",(E95-N95)/E95) -> 0.071428571 | W95: =IF(OR(U95="",V95="",V95<=0),"",U95/V95) -> 1.4 | X95: =IF(OR(K95="",L95="",E95="",H95=""),"",K95*L95-E95*H95-IF(O95="",0,O95)-IF(P95="",0,P95)) -> 1586 | Y95: =IF(OR(X95="",E95="",H95=""),"",IF(E95*H95+IF(O95="",0,O95)<=0,"",X95/(E95*H95+IF(O95="",0,O95)))) -> 0.12941656 | Z95: =IF(OR(Y95="",多次统计数据!$B$8=""),"",Y95-多次统计数据!$B$8) -> 0.0012854746 | AA95: =IF(OR(I95="",M95="",M95<I95),"",M95-I95) -> 4 | AB95: =IF(OR(A95="",多次统计数据!$B$8="",多次统计数据!$B$6<=0,多次统计数据!$B$6>=1),"",1-POWER(1+多次统计数据!$B$8,-多次统计数据!$B$6/(1-多次统计数据!$B$6))) -> 0.11918507 | AC95: =IF(OR(AB95="",多次统计数据!$B$9=""),"",IF(多次统计数据!$B$9<AB95,"低于上限","达到或超过上限")) -> 低于上限 | AD95: 4-良好
A96: T2026095 | B96: 601318 | C96: 122181 | D96: 0.01 | E96: 18.75 | F96: =IF(OR(C96="",D96="",E96="",N96="",C96<=0,D96<=0,E96<=N96),"",ROUNDDOWN((C96*D96)/(E96-N96)/100,0)*100) -> 800 | G96: =IF(OR(A96="",F96="",E96="",N96="",E96<=N96,账户数据!$B$7=""),"",IF(账户数据!$B$9+IF(H96="",F96*(E96-N96),0)>=账户数据!$B$7,"禁止开仓","允许开仓")) -> 禁止开仓 | H96: 800 | I96: 46222 | J96: 20.62 | K96: 17.25 | L96: =IF(K96="","",H96) -> 800 | M96: 46227 | N96: 17.25 | O96: 5 | P96: 5 | Q96: 量价背离与板块共振共同确认 | R96: 止损设在17.25 | S96: 目标参考成交量 | T96: 按计划成交 | U96: =IF(OR(E96="",J96="",E96<=0),"",(J96-E96)/E96) -> 0.099733333 | V96: =IF(OR(E96="",N96="",E96<=0),"",(E96-N96)/E96) -> 0.08 | W96: =IF(OR(U96="",V96="",V96<=0),"",U96/V96) -> 1.2466667 | X96: =IF(OR(K96="",L96="",E96="",H96=""),"",K96*L96-E96*H96-IF(O96="",0,O96)-IF(P96="",0,P96)) -> -1210 | Y96: =IF(OR(X96="",E96="",H96=""),"",IF(E96*H96+IF(O96="",0,O96)<=0,"",X96/(E96*H96+IF(O96="",0,O96)))) -> -0.080639787 | Z96: =IF(OR(Y96="",多次统计数据!$B$8=""),"",Y96-多次统计数据!$B$8) -> -0.20877088 | AA96: =IF(OR(I96="",M96="",M96<I96),"",M96-I96) -> 5 | AB96: =IF(OR(A96="",多次统计数据!$B$8="",多次统计数据!$B$6<=0,多次统计数据!$B$6>=1),"",1-POWER(1+多次统计数据!$B$8,-多次统计数据!$B$6/(1-多次统计数据!$B$6))) -> 0.11918507 | AC96: =IF(OR(AB96="",多次统计数据!$B$9=""),"",IF(多次统计数据!$B$9<AB96,"低于上限","达到或超过上限")) -> 低于上限 | AD96: 2-较差
A97: T2026096 | B97: 688981 | C97: 120971 | D97: 0.01 | E97: 20 | F97: =IF(OR(C97="",D97="",E97="",N97="",C97<=0,D97<=0,E97<=N97),"",ROUNDDOWN((C97*D97)/(E97-N97)/100,0)*100) -> 1600 | G97: =IF(OR(A97="",F97="",E97="",N97="",E97<=N97,账户数据!$B$7=""),"",IF(账户数据!$B$9+IF(H97="",F97*(E97-N97),0)>=账户数据!$B$7,"禁止开仓","允许开仓")) -> 禁止开仓 | H97: 300 | I97: 46223 | J97: 22 | K97: 19 | L97: =IF(K97="","",H97) -> 300 | M97: 46227 | N97: 19.25 | O97: 0 | P97: 0 | Q97: 趋势背离与蜡烛图共同确认 | R97: 止损设在19.25 | S97: 目标参考RSI | T97: 按计划成交 | U97: =IF(OR(E97="",J97="",E97<=0),"",(J97-E97)/E97) -> 0.1 | V97: =IF(OR(E97="",N97="",E97<=0),"",(E97-N97)/E97) -> 0.0375 | W97: =IF(OR(U97="",V97="",V97<=0),"",U97/V97) -> 2.6666667 | X97: =IF(OR(K97="",L97="",E97="",H97=""),"",K97*L97-E97*H97-IF(O97="",0,O97)-IF(P97="",0,P97)) -> -300 | Y97: =IF(OR(X97="",E97="",H97=""),"",IF(E97*H97+IF(O97="",0,O97)<=0,"",X97/(E97*H97+IF(O97="",0,O97)))) -> -0.05 | Z97: =IF(OR(Y97="",多次统计数据!$B$8=""),"",Y97-多次统计数据!$B$8) -> -0.17813109 | AA97: =IF(OR(I97="",M97="",M97<I97),"",M97-I97) -> 4 | AB97: =IF(OR(A97="",多次统计数据!$B$8="",多次统计数据!$B$6<=0,多次统计数据!$B$6>=1),"",1-POWER(1+多次统计数据!$B$8,-多次统计数据!$B$6/(1-多次统计数据!$B$6))) -> 0.11918507 | AC97: =IF(OR(AB97="",多次统计数据!$B$9=""),"",IF(多次统计数据!$B$9<AB97,"低于上限","达到或超过上限")) -> 低于上限 | AD97: 2-较差
A98: T2026097 | B98: 000858 | C98: 120671 | D98: 0.01 | E98: 21.25 | F98: =IF(OR(C98="",D98="",E98="",N98="",C98<=0,D98<=0,E98<=N98),"",ROUNDDOWN((C98*D98)/(E98-N98)/100,0)*100) -> 1200 | G98: =IF(OR(A98="",F98="",E98="",N98="",E98<=N98,账户数据!$B$7=""),"",IF(账户数据!$B$9+IF(H98="",F98*(E98-N98),0)>=账户数据!$B$7,"禁止开仓","允许开仓")) -> 禁止开仓 | H98: 400 | I98: 46224 | J98: 23.38 | K98: 19.97 | L98: =IF(K98="","",H98) -> 400 | M98: 46227 | N98: 20.25 | O98: 5 | P98: 5 | Q98: ATR与趋势线共同确认 | R98: 止损设在20.25 | S98: 目标参考KDJ | T98: 按计划成交 | U98: =IF(OR(E98="",J98="",E98<=0),"",(J98-E98)/E98) -> 0.10023529 | V98: =IF(OR(E98="",N98="",E98<=0),"",(E98-N98)/E98) -> 0.047058824 | W98: =IF(OR(U98="",V98="",V98<=0),"",U98/V98) -> 2.13 | X98: =IF(OR(K98="",L98="",E98="",H98=""),"",K98*L98-E98*H98-IF(O98="",0,O98)-IF(P98="",0,P98)) -> -522 | Y98: =IF(OR(X98="",E98="",H98=""),"",IF(E98*H98+IF(O98="",0,O98)<=0,"",X98/(E98*H98+IF(O98="",0,O98)))) -> -0.061375661 | Z98: =IF(OR(Y98="",多次统计数据!$B$8=""),"",Y98-多次统计数据!$B$8) -> -0.18950675 | AA98: =IF(OR(I98="",M98="",M98<I98),"",M98-I98) -> 3 | AB98: =IF(OR(A98="",多次统计数据!$B$8="",多次统计数据!$B$6<=0,多次统计数据!$B$6>=1),"",1-POWER(1+多次统计数据!$B$8,-多次统计数据!$B$6/(1-多次统计数据!$B$6))) -> 0.11918507 | AC98: =IF(OR(AB98="",多次统计数据!$B$9=""),"",IF(多次统计数据!$B$9<AB98,"低于上限","达到或超过上限")) -> 低于上限 | AD98: 2-较差
A99: T2026098 | B99: 600036 | C99: 120149 | D99: 0.01 | E99: 22.5 | F99: =IF(OR(C99="",D99="",E99="",N99="",C99<=0,D99<=0,E99<=N99),"",ROUNDDOWN((C99*D99)/(E99-N99)/100,0)*100) -> 900 | G99: =IF(OR(A99="",F99="",E99="",N99="",E99<=N99,账户数据!$B$7=""),"",IF(账户数据!$B$9+IF(H99="",F99*(E99-N99),0)>=账户数据!$B$7,"禁止开仓","允许开仓")) -> 禁止开仓 | H99: 500 | I99: 46225 | J99: 24.75 | K99: 21.25 | L99: =IF(K99="","",H99) -> 500 | M99: 46226 | N99: 21.25 | O99: 5 | P99: 5 | Q99: 换手率与MACD共同确认 | R99: 止损设在21.25 | S99: 目标参考布林带 | T99: 按计划成交 | U99: =IF(OR(E99="",J99="",E99<=0),"",(J99-E99)/E99) -> 0.1 | V99: =IF(OR(E99="",N99="",E99<=0),"",(E99-N99)/E99) -> 0.055555556 | W99: =IF(OR(U99="",V99="",V99<=0),"",U99/V99) -> 1.8 | X99: =IF(OR(K99="",L99="",E99="",H99=""),"",K99*L99-E99*H99-IF(O99="",0,O99)-IF(P99="",0,P99)) -> -635 | Y99: =IF(OR(X99="",E99="",H99=""),"",IF(E99*H99+IF(O99="",0,O99)<=0,"",X99/(E99*H99+IF(O99="",0,O99)))) -> -0.056419369 | Z99: =IF(OR(Y99="",多次统计数据!$B$8=""),"",Y99-多次统计数据!$B$8) -> -0.18455046 | AA99: =IF(OR(I99="",M99="",M99<I99),"",M99-I99) -> 1 | AB99: =IF(OR(A99="",多次统计数据!$B$8="",多次统计数据!$B$6<=0,多次统计数据!$B$6>=1),"",1-POWER(1+多次统计数据!$B$8,-多次统计数据!$B$6/(1-多次统计数据!$B$6))) -> 0.11918507 | AC99: =IF(OR(AB99="",多次统计数据!$B$9=""),"",IF(多次统计数据!$B$9<AB99,"低于上限","达到或超过上限")) -> 低于上限 | AD99: 2-较差
A100: T2026099 | B100: 002415 | C100: 119514 | D100: 0.01 | E100: 10 | F100: =IF(OR(C100="",D100="",E100="",N100="",C100<=0,D100<=0,E100<=N100),"",ROUNDDOWN((C100*D100)/(E100-N100)/100,0)*100) -> 700 | G100: =IF(OR(A100="",F100="",E100="",N100="",E100<=N100,账户数据!$B$7=""),"",IF(账户数据!$B$9+IF(H100="",F100*(E100-N100),0)>=账户数据!$B$7,"禁止开仓","允许开仓")) -> 禁止开仓 | H100: 500 | I100: 46226 | J100: 11 | K100: 10 | L100: =IF(K100="","",H100) -> 500 | M100: 46227 | N100: 8.5 | O100: 0 | P100: 0 | Q100: 相对强弱与移动平均线共同确认 | R100: 止损设在8.50 | S100: 目标参考支撑位 | T100: 按计划成交 | U100: =IF(OR(E100="",J100="",E100<=0),"",(J100-E100)/E100) -> 0.1 | V100: =IF(OR(E100="",N100="",E100<=0),"",(E100-N100)/E100) -> 0.15 | W100: =IF(OR(U100="",V100="",V100<=0),"",U100/V100) -> 0.66666667 | X100: =IF(OR(K100="",L100="",E100="",H100=""),"",K100*L100-E100*H100-IF(O100="",0,O100)-IF(P100="",0,P100)) -> 0 | Y100: =IF(OR(X100="",E100="",H100=""),"",IF(E100*H100+IF(O100="",0,O100)<=0,"",X100/(E100*H100+IF(O100="",0,O100)))) -> 0 | Z100: =IF(OR(Y100="",多次统计数据!$B$8=""),"",Y100-多次统计数据!$B$8) -> -0.12813109 | AA100: =IF(OR(I100="",M100="",M100<I100),"",M100-I100) -> 1 | AB100: =IF(OR(A100="",多次统计数据!$B$8="",多次统计数据!$B$6<=0,多次统计数据!$B$6>=1),"",1-POWER(1+多次统计数据!$B$8,-多次统计数据!$B$6/(1-多次统计数据!$B$6))) -> 0.11918507 | AC100: =IF(OR(AB100="",多次统计数据!$B$9=""),"",IF(多次统计数据!$B$9<AB100,"低于上限","达到或超过上限")) -> 低于上限 | AD100: 3-一般
...

Sheet 买入理由
A1: 交易编号 | B1: 股票代码 | C1: 所属板块 | D1: 阶段 | E1: 记录日期 | F1: 技术指标1 | G1: 技术指标2 | H1: 技术指标3 | I1: 综述
A2: T2026001 | B2: 600519 | C2: 消费 | D2: 买入 | E2: 46128 | F2: 蜡烛图 | G2: RSI | H2: 缺口 | I2: win场景，第1笔逐步验证数据
A3: T2026002 | B3: 000001 | C3: 银行 | D3: 买入 | E3: 46129 | F3: 趋势线 | G3: KDJ | H3: 形态突破 | I3: win场景，第2笔逐步验证数据
A4: T2026003 | B4: 300750 | C4: 新能源 | D4: 买入 | E4: 46130 | F4: MACD | G4: 布林带 | H4: 均线金叉 | I4: win场景，第3笔逐步验证数据
A5: T2026004 | B5: 002594 | C5: 汽车 | D5: 买入 | E5: 46131 | F5: 移动平均线 | G5: 支撑位 | H5: 均线死叉 | I5: win场景，第4笔逐步验证数据
A6: T2026005 | B6: 601318 | C6: 保险 | D6: 买入 | E6: 46132 | F6: 成交量 | G6: 压力位 | H6: 量价背离 | I6: loss场景，第5笔逐步验证数据
A7: T2026006 | B7: 688981 | C7: 半导体 | D7: 买入 | E7: 46133 | F7: RSI | G7: 缺口 | H7: 趋势背离 | I7: loss场景，第6笔逐步验证数据
A8: T2026007 | B8: 000858 | C8: 食品饮料 | D8: 买入 | E8: 46134 | F8: KDJ | G8: 形态突破 | H8: ATR | I8: loss场景，第7笔逐步验证数据
A9: T2026008 | B9: 600036 | C9: 金融 | D9: 买入 | E9: 46135 | F9: 布林带 | G9: 均线金叉 | H9: 换手率 | I9: loss场景，第8笔逐步验证数据
A10: T2026009 | B10: 002415 | C10: 电子 | D10: 买入 | E10: 46136 | F10: 支撑位 | G10: 均线死叉 | H10: 相对强弱 | I10: flat场景，第9笔逐步验证数据
A11: T2026010 | B11: 601899 | C11: 资源 | D11: 买入 | E11: 46137 | F11: 压力位 | G11: 量价背离 | H11: 板块共振 | I11: open场景，第10笔逐步验证数据
A12: T2026011 | B12: 600519 | C12: 消费 | D12: 买入 | E12: 46138 | F12: 缺口 | G12: 趋势背离 | H12: 蜡烛图 | I12: win场景，第11笔逐步验证数据
A13: T2026012 | B13: 000001 | C13: 银行 | D13: 买入 | E13: 46139 | F13: 形态突破 | G13: ATR | H13: 趋势线 | I13: win场景，第12笔逐步验证数据
... A101: T2026100 | B101: 601899 | C101: 资源 | D101: 买入 | E101: 46227 | F101: 板块共振 | G101: 成交量 | H101: 压力位 | I101: candidate场景，第100笔逐步验证数据

Sheet 多次统计数据
A1: 指标 | B1: 当前统计 | C1: 口径说明
A2: 已完成交易数 | B2: =COUNT(单次交易!M2:M201) -> 88 | C2: 存在卖出日期的交易
A3: 盈利交易数 | B3: =COUNTIF(单次交易!X2:X201,">0") -> 40 | C3: 实际盈亏金额大于0
A4: 亏损交易数 | B4: =COUNTIF(单次交易!X2:X201,"<0") -> 38 | C4: 实际盈亏金额小于0
A5: 持平交易数 | B5: =COUNTIFS(单次交易!M2:M201,"<>",单次交易!X2:X201,"=0") -> 10 | C5: 已卖出且实际盈亏为0；不进入胜负样本
A6: 盈利概率 | B6: =IFERROR(B3/(B3+B4),"") -> 0.51282051 | C6: 盈利数÷胜负交易数
A7: 亏损概率 | B7: =IFERROR(B4/(B3+B4),"") -> 0.48717949 | C7: 亏损数÷胜负交易数
A8: 平均盈利百分比 | B8: =IFERROR(AVERAGEIF(单次交易!X2:X201,">0",单次交易!Y2:Y201),"") -> 0.12813109 | C8: 盈利交易实际收益率的平均值
A9: 平均亏损百分比 | B9: =IFERROR(-AVERAGEIF(单次交易!X2:X201,"<0",单次交易!Y2:Y201),"") -> 0.079689039 | C9: 以正数显示亏损幅度
A10: 盈利的持有总天数 | B10: =SUMIF(单次交易!X2:X201,">0",单次交易!AA2:AA201) -> 155 | C10: 自然日
A11: 亏损的持有总天数 | B11: =SUMIF(单次交易!X2:X201,"<0",单次交易!AA2:AA201) -> 144 | C11: 自然日
A12: 平均交易金额 | B12: =IFERROR(SUMPRODUCT(单次交易!E2:E201,单次交易!H2:H201)/COUNT(单次交易!H2:H201),"") -> 8902.3438 | C12: 买入价×实际买入股数的平均值，包含未卖出交易
A13: 期望收益率 | B13: =IF(OR(B6="",B7="",B8="",B9=""),"",B6*B8-B7*B9) -> 0.026885386 | C13: 盈利贡献减亏损贡献
A14: 迄今为止的复利净利润率 | B14: =IF(OR(B3+B4=0,B8="",B9=""),"",POWER(1+B8,B3)*POWER(1-B9,B4)-1) -> 4.2953822 | C14: 基于历史平均盈亏率的几何复利模拟

Sheet 账户数据
A1: 指标 | B1: 值 | C1: 录入/计算说明
A2: 初始总金额 | B2: 100000 | C2: 手动输入；当前金额从此值开始累计
A3: 当前总金额 | B3: =IF(B2="","",B2+SUM(单次交易!X2:X201)) -> 119514 | C3: 初始总金额＋全部已实现盈亏
A4: 单次交易允许的亏损比例 | B4: 0.01 | C4: 默认1%，可调整；开仓时复制为交易快照
A5: 单次交易允许的亏损金额 | B5: =IF(B3="","",B3*B4) -> 1195.14 | C5: 当前总金额×单次允许亏损比例
A6: 当月允许最大亏损比例 | B6: 0.05 | C6: 默认5%，可调整
A7: 当月允许最大亏损金额 | B7: =IF(B3="","",B3*B6) -> 5975.7 | C7: 当前总金额×当月最大亏损比例
A8: 当月亏损金额 | B8: =SUMIFS(单次交易!X2:X201,单次交易!X2:X201,"<0",单次交易!M2:M201,">="&EOMONTH(TODAY(),-1)+1,单次交易!M2:M201,"<="&EOMONTH(TODAY(),0)) -> -6618 | C8: 按卖出日期统计本月已实现亏损，保留负号
A9: 当前未平仓理论亏损 | B9: =IFERROR(SUMPRODUCT((单次交易!M2:M201="")*(单次交易!H2:H201>0)*(单次交易!E2:E201>单次交易!N2:N201)*单次交易!H2:H201*(单次交易!E2:E201-单次交易!N2:N201)),0) -> 8325 | C9: 未填写卖出日期的实际持仓×买入价与止损价之差
A10: 当月剩余可开仓风险额度 | B10: =IF(OR(B7="",B9=""),"",B7-B9) -> -2349.3 | C10: 当月允许最大亏损金额－当前未平仓理论亏损

Sheet 目标收益
A1: 指标 | B1: 值 | C1: 口径说明
A2: 总金额 | B2: =账户数据!B3 -> 119514 | C2: 来自账户当前总金额
A3: 目标收益率 | B3: 0.1 | C3: 手动输入
A4: 目标收益金额 | B4: =IF(OR(B2="",B3=""),"",B2*B3) -> 11951.4 | C4: 总金额×目标收益率
A5: 平均交易金额 | B5: =多次统计数据!B12 -> 8902.3438 | C5: 来自历史交易统计
A6: 历史期望收益率 | B6: =多次统计数据!B13 -> 0.026885386 | C6: 来自历史胜率与平均盈亏
A7: 所需投资笔数 | B7: =IF(OR(B4="",B5="",B6="",B5<=0,B6<=0),"暂不可计算",ROUNDUP(B4/(B5*B6),0)) -> 50 | C7: 向上取整；历史期望收益率不为正时不计算

Sheet 技术指标
A1: 技术指标 | B1: 分类 | C1: 说明
A2: 蜡烛图 | B2: 价格形态 | C2: 观察实体、上下影线及组合形态
A3: 趋势线 | B3: 趋势 | C3: 连接关键高点或低点判断趋势方向
A4: MACD | B4: 动量 | C4: 观察快慢线、信号线和柱状图
A5: 移动平均线 | B5: 趋势 | C5: 观察价格与不同周期均线的位置关系
A6: 成交量 | B6: 量价 | C6: 确认突破、回调和趋势的参与强度
A7: RSI | B7: 动量 | C7: 衡量相对强弱及超买超卖状态
A8: KDJ | B8: 动量 | C8: 观察随机指标交叉和极值区域
A9: 布林带 | B9: 波动 | C9: 观察价格相对中轨和上下轨的位置
A10: 支撑位 | B10: 关键价位 | C10: 记录预期获得买盘支撑的价格区域
A11: 压力位 | B11: 关键价位 | C11: 记录预期遇到卖压的价格区域
A12: 缺口 | B12: 价格形态 | C12: 观察跳空缺口是否回补或延续
... A21: 板块共振 | B21: 市场环境 | C21: 确认个股信号与所属板块方向一致
