Workbook
Name _AccountRiskLimit: 账户数据!$B$7
Name _LockStatus: 账户数据!$B$23
Name _TradeIds: 单次交易!$A$2:$A$201

Sheet 单次交易
A1: 交易编号 | B1: 股票代码 | C1: 买入时账户金额 | D1: 本次允许亏损比例 | E1: 第一批买入价 | F1: 买入建议股数 | G1: 开仓风险告警 | H1: 第一批买入股数 | I1: 首次买入日期 | J1: 期望卖出价 | K1: 实际卖出价（填写） | L1: 最终卖出股数（自动） | M1: 卖出日期（填写） | N1: 止损价 | O1: 买入总费用 | P1: 卖出费用（填写） | Q1: 买入价的由来 | R1: 止损价的由来 | S1: 期望卖出价的由来 | T1: 实际卖出价的由来 | U1: 期望盈利比例 | V1: 期望止损比例 | W1: 盈亏比 | X1: 加权后实际盈亏 | Y1: 单笔仓位收益率 | Z1: 账户收益率与平均盈利率差值 | AA1: 持有天数 | AB1: 复利容许平均亏损上限 | AC1: 复利风险判断 | AD1: 交易打分评价 | AE1: 实际账户收益率 | AF1: 列1 | AG1: 交易预期类型 | AH1: 预期持有周期 | AI1: 预期选择理由 | AJ1: 周期匹配检查 | AK1: 已执行加仓次数 | AL1: 加仓总股数 | AM1: 最近加仓价 | AN1: 最新加仓止损价 | AO1: 实际加权买入价 | AP1: 最终持仓股数 | AQ1: 当前净止损风险 | AR1: 加仓规则检查
A2: 1 | B2: 新和成 | C2: 100000 | D2: 0.02 | E2: 4.15 | F2: =IF(OR(C2="",D2="",E2="",N2="",C2<=0,D2<=0,E2<=N2),"",ROUNDDOWN((C2*D2)/(E2-N2)/100,0)*100) -> 6600 | G2: =IF(A2="","",IF(H2<>"","已开仓",IF(账户数据!$B$23="已锁仓","禁止开仓：连续亏损达到上限",IF(账户数据!$B$23="解锁信息不完整","禁止开仓：请完整填写解锁信息",IF(OR(F2="",E2="",N2="",E2<=N2,账户数据!$B$7=""),"",IF(OR(AG2="",AH2="",AI2=""),"禁止开仓：交易预期未填写完整",IF(账户数据!$B$9+F2*(E2-N2)>=账户数据!$B$7,"禁止开仓：风险额度不足",IF(AJ2="周期与交易预期不匹配，请重新确认",IF(账户数据!$B$23="接近锁仓","允许开仓（接近锁仓；周期需复核）","允许开仓（周期需复核）"),IF(账户数据!$B$23="接近锁仓","允许开仓（接近锁仓）","允许开仓"))))))))) -> 已开仓 | H2: 6000 | I2: 42609 | J2: 5 | K2: 4 | L2: =IF(AP2="","",AP2) -> 10500 | M2: 42671 | N2: 3.85 | U2: =IF(OR(AO2="",J2="",AO2<=0),"",(J2-AO2)/AO2) -> 0.16952551 | V2: =IF(OR(AO2="",N2="",AO2<=0),"",(AO2-N2)/AO2) -> 0.09946536 | W2: =IF(OR(U2="",V2="",V2<=0),"",U2/V2) -> 1.7043673 | X2: =IF(OR(K2="",L2="",AO2="",AP2=""),"",(K2-AO2)*L2-IF(O2="",0,O2)-IF(P2="",0,P2)) -> -2890 | Y2: =IF(OR(X2="",AO2="",L2=""),"",IF(AO2*L2+IF(O2="",0,O2)<=0,"",X2/(AO2*L2+IF(O2="",0,O2)))) -> -0.064379595 | Z2: =IF(OR(AE2="",多次统计数据!$B$8=""),"",AE2-多次统计数据!$B$8) -> -0.12710997 | AA2: =IF(OR(I2="",M2="",M2<I2),"",M2-I2) -> 62 | AB2: =IF(OR(A2="",多次统计数据!$B$8="",多次统计数据!$B$6<=0,多次统计数据!$B$6>=1),"",1-POWER(1+多次统计数据!$B$8,-多次统计数据!$B$6/(1-多次统计数据!$B$6))) -> 0.096508292 | AC2: =IF(OR(AB2="",多次统计数据!$B$9=""),"",IF(多次统计数据!$B$9<AB2,"低于上限","达到或超过上限")) -> 低于上限 | AE2: =IF(OR(X2="",C2="",C2<=0),"",X2/C2) -> -0.0289 | AG2: 趋势波段 | AH2: 11～20个交易日 | AI2: 吸筹冲新高 | AJ2: =IF(OR(AG2="",AH2=""),"",IF(OR(AND(AG2="短期博反弹",OR(AH2="1～3个交易日",AH2="4～10个交易日")),AND(AG2="突破冲新高",OR(AH2="4～10个交易日",AH2="11～20个交易日")),AND(AG2="趋势波段",OR(AH2="11～20个交易日",AH2="21～60个交易日",AH2="60个交易日以上"))),"匹配","周期与交易预期不匹配，请重新确认")) -> 匹配 | AK2: =IF(A2="","",COUNTIFS(加仓管理!$A$2:$A$1001,A2,加仓管理!$G$2:$G$1001,">0")) -> 2 | AL2: =IF(A2="","",SUMIFS(加仓管理!$G$2:$G$1001,加仓管理!$A$2:$A$1001,A2)) -> 4500 | AM2: =IF(AK2=0,"",IFERROR(LOOKUP(2,1/((加仓管理!$A$2:$A$1001=A2)*(加仓管理!$G$2:$G$1001>0)),加仓管理!$D$2:$D$1001),"")) -> 4.57 | AN2: =IF(AK2=0,"",IFERROR(LOOKUP(2,1/((加仓管理!$A$2:$A$1001=A2)*(加仓管理!$G$2:$G$1001>0)),加仓管理!$E$2:$E$1001),"")) -> 4 | AO2: =IF(OR(A2="",H2="",H2<=0),"",(E2*H2+SUMIFS(加仓管理!$H$2:$H$1001,加仓管理!$A$2:$A$1001,A2))/AP2) -> 4.2752381 | AP2: =IF(OR(A2="",H2="",H2<=0),"",H2+AL2) -> 10500 | AQ2: =IF(A2="","",IF(M2<>"",0,IF(OR(H2="",N2=""),"",MAX((E2*H2+SUMIFS(加仓管理!$H$2:$H$1001,加仓管理!$A$2:$A$1001,A2))-MAX(N2,AN2)*AP2,0)))) -> 0 | AR2: =IF(A2="","",IF(OR(E2="",H2=""),"违规：首次买入价格或股数缺失",IF(COUNTIFS(加仓管理!$A$2:$A$1001,A2,加仓管理!$R$2:$R$1001,"违规*")>0,"违规：请检查加仓管理表",IF(SUM($AQ$2:$AQ$201)>账户数据!$B$7,"预警：超过账户风险上限",IF(COUNTIFS(加仓管理!$A$2:$A$1001,A2,加仓管理!$N$2:$N$1001,">0",加仓管理!$G$2:$G$1001,"")>0,"提示：存在待执行加仓计划","通过"))))) -> 违规：请检查加仓管理表
A3: 2 | B3: 新和成 | C3: 97110 | D3: 0.02 | E3: 3.7 | F3: =IF(OR(C3="",D3="",E3="",N3="",C3<=0,D3<=0,E3<=N3),"",ROUNDDOWN((C3*D3)/(E3-N3)/100,0)*100) -> 4800 | G3: =IF(A3="","",IF(H3<>"","已开仓",IF(账户数据!$B$23="已锁仓","禁止开仓：连续亏损达到上限",IF(账户数据!$B$23="解锁信息不完整","禁止开仓：请完整填写解锁信息",IF(OR(F3="",E3="",N3="",E3<=N3,账户数据!$B$7=""),"",IF(OR(AG3="",AH3="",AI3=""),"禁止开仓：交易预期未填写完整",IF(账户数据!$B$9+F3*(E3-N3)>=账户数据!$B$7,"禁止开仓：风险额度不足",IF(AJ3="周期与交易预期不匹配，请重新确认",IF(账户数据!$B$23="接近锁仓","允许开仓（接近锁仓；周期需复核）","允许开仓（周期需复核）"),IF(账户数据!$B$23="接近锁仓","允许开仓（接近锁仓）","允许开仓"))))))))) -> 已开仓 | H3: 4800 | I3: 42697 | J3: 4.2 | K3: 3.26 | L3: =IF(AP3="","",AP3) -> 4800 | M3: 42706 | N3: 3.3 | U3: =IF(OR(AO3="",J3="",AO3<=0),"",(J3-AO3)/AO3) -> 0.13513514 | V3: =IF(OR(AO3="",N3="",AO3<=0),"",(AO3-N3)/AO3) -> 0.10810811 | W3: =IF(OR(U3="",V3="",V3<=0),"",U3/V3) -> 1.25 | X3: =IF(OR(K3="",L3="",AO3="",AP3=""),"",(K3-AO3)*L3-IF(O3="",0,O3)-IF(P3="",0,P3)) -> -2112 | Y3: =IF(OR(X3="",AO3="",L3=""),"",IF(AO3*L3+IF(O3="",0,O3)<=0,"",X3/(AO3*L3+IF(O3="",0,O3)))) -> -0.11891892 | Z3: =IF(OR(AE3="",多次统计数据!$B$8=""),"",AE3-多次统计数据!$B$8) -> -0.1199585 | AA3: =IF(OR(I3="",M3="",M3<I3),"",M3-I3) -> 9 | AB3: =IF(OR(A3="",多次统计数据!$B$8="",多次统计数据!$B$6<=0,多次统计数据!$B$6>=1),"",1-POWER(1+多次统计数据!$B$8,-多次统计数据!$B$6/(1-多次统计数据!$B$6))) -> 0.096508292 | AC3: =IF(OR(AB3="",多次统计数据!$B$9=""),"",IF(多次统计数据!$B$9<AB3,"低于上限","达到或超过上限")) -> 低于上限 | AE3: =IF(OR(X3="",C3="",C3<=0),"",X3/C3) -> -0.021748533 | AG3: 趋势波段 | AH3: 11～20个交易日 | AI3: 吸筹冲新高 | AJ3: =IF(OR(AG3="",AH3=""),"",IF(OR(AND(AG3="短期博反弹",OR(AH3="1～3个交易日",AH3="4～10个交易日")),AND(AG3="突破冲新高",OR(AH3="4～10个交易日",AH3="11～20个交易日")),AND(AG3="趋势波段",OR(AH3="11～20个交易日",AH3="21～60个交易日",AH3="60个交易日以上"))),"匹配","周期与交易预期不匹配，请重新确认")) -> 匹配 | AK3: =IF(A3="","",COUNTIFS(加仓管理!$A$2:$A$1001,A3,加仓管理!$G$2:$G$1001,">0")) -> 0 | AL3: =IF(A3="","",SUMIFS(加仓管理!$G$2:$G$1001,加仓管理!$A$2:$A$1001,A3)) -> 0 | AM3: =IF(AK3=0,"",IFERROR(LOOKUP(2,1/((加仓管理!$A$2:$A$1001=A3)*(加仓管理!$G$2:$G$1001>0)),加仓管理!$D$2:$D$1001),"")) | AN3: =IF(AK3=0,"",IFERROR(LOOKUP(2,1/((加仓管理!$A$2:$A$1001=A3)*(加仓管理!$G$2:$G$1001>0)),加仓管理!$E$2:$E$1001),"")) | AO3: =IF(OR(A3="",H3="",H3<=0),"",(E3*H3+SUMIFS(加仓管理!$H$2:$H$1001,加仓管理!$A$2:$A$1001,A3))/AP3) -> 3.7 | AP3: =IF(OR(A3="",H3="",H3<=0),"",H3+AL3) -> 4800 | AQ3: =IF(A3="","",IF(M3<>"",0,IF(OR(H3="",N3=""),"",MAX((E3*H3+SUMIFS(加仓管理!$H$2:$H$1001,加仓管理!$A$2:$A$1001,A3))-MAX(N3,AN3)*AP3,0)))) -> 0 | AR3: =IF(A3="","",IF(OR(E3="",H3=""),"违规：首次买入价格或股数缺失",IF(COUNTIFS(加仓管理!$A$2:$A$1001,A3,加仓管理!$R$2:$R$1001,"违规*")>0,"违规：请检查加仓管理表",IF(SUM($AQ$2:$AQ$201)>账户数据!$B$7,"预警：超过账户风险上限",IF(COUNTIFS(加仓管理!$A$2:$A$1001,A3,加仓管理!$N$2:$N$1001,">0",加仓管理!$G$2:$G$1001,"")>0,"提示：存在待执行加仓计划","通过"))))) -> 通过
A4: 3 | B4: 新和成 | C4: 94998 | D4: 0.02 | E4: 3.12 | F4: =IF(OR(C4="",D4="",E4="",N4="",C4<=0,D4<=0,E4<=N4),"",ROUNDDOWN((C4*D4)/(E4-N4)/100,0)*100) -> 15800 | G4: =IF(A4="","",IF(H4<>"","已开仓",IF(账户数据!$B$23="已锁仓","禁止开仓：连续亏损达到上限",IF(账户数据!$B$23="解锁信息不完整","禁止开仓：请完整填写解锁信息",IF(OR(F4="",E4="",N4="",E4<=N4,账户数据!$B$7=""),"",IF(OR(AG4="",AH4="",AI4=""),"禁止开仓：交易预期未填写完整",IF(账户数据!$B$9+F4*(E4-N4)>=账户数据!$B$7,"禁止开仓：风险额度不足",IF(AJ4="周期与交易预期不匹配，请重新确认",IF(账户数据!$B$23="接近锁仓","允许开仓（接近锁仓；周期需复核）","允许开仓（周期需复核）"),IF(账户数据!$B$23="接近锁仓","允许开仓（接近锁仓）","允许开仓"))))))))) -> 已开仓 | H4: 10000 | I4: 42797 | J4: 3.5 | K4: 2.83 | L4: =IF(AP4="","",AP4) -> 10000 | M4: 42809 | N4: 3 | U4: =IF(OR(AO4="",J4="",AO4<=0),"",(J4-AO4)/AO4) -> 0.12179487 | V4: =IF(OR(AO4="",N4="",AO4<=0),"",(AO4-N4)/AO4) -> 0.038461538 | W4: =IF(OR(U4="",V4="",V4<=0),"",U4/V4) -> 3.1666667 | X4: =IF(OR(K4="",L4="",AO4="",AP4=""),"",(K4-AO4)*L4-IF(O4="",0,O4)-IF(P4="",0,P4)) -> -2900 | Y4: =IF(OR(X4="",AO4="",L4=""),"",IF(AO4*L4+IF(O4="",0,O4)<=0,"",X4/(AO4*L4+IF(O4="",0,O4)))) -> -0.092948718 | Z4: =IF(OR(AE4="",多次统计数据!$B$8=""),"",AE4-多次统计数据!$B$8) -> -0.12873692 | AA4: =IF(OR(I4="",M4="",M4<I4),"",M4-I4) -> 12 | AB4: =IF(OR(A4="",多次统计数据!$B$8="",多次统计数据!$B$6<=0,多次统计数据!$B$6>=1),"",1-POWER(1+多次统计数据!$B$8,-多次统计数据!$B$6/(1-多次统计数据!$B$6))) -> 0.096508292 | AC4: =IF(OR(AB4="",多次统计数据!$B$9=""),"",IF(多次统计数据!$B$9<AB4,"低于上限","达到或超过上限")) -> 低于上限 | AE4: =IF(OR(X4="",C4="",C4<=0),"",X4/C4) -> -0.030526958 | AG4: 短期博反弹 | AH4: 4～10个交易日 | AI4: 反弹 | AJ4: =IF(OR(AG4="",AH4=""),"",IF(OR(AND(AG4="短期博反弹",OR(AH4="1～3个交易日",AH4="4～10个交易日")),AND(AG4="突破冲新高",OR(AH4="4～10个交易日",AH4="11～20个交易日")),AND(AG4="趋势波段",OR(AH4="11～20个交易日",AH4="21～60个交易日",AH4="60个交易日以上"))),"匹配","周期与交易预期不匹配，请重新确认")) -> 匹配 | AK4: =IF(A4="","",COUNTIFS(加仓管理!$A$2:$A$1001,A4,加仓管理!$G$2:$G$1001,">0")) -> 0 | AL4: =IF(A4="","",SUMIFS(加仓管理!$G$2:$G$1001,加仓管理!$A$2:$A$1001,A4)) -> 0 | AM4: =IF(AK4=0,"",IFERROR(LOOKUP(2,1/((加仓管理!$A$2:$A$1001=A4)*(加仓管理!$G$2:$G$1001>0)),加仓管理!$D$2:$D$1001),"")) | AN4: =IF(AK4=0,"",IFERROR(LOOKUP(2,1/((加仓管理!$A$2:$A$1001=A4)*(加仓管理!$G$2:$G$1001>0)),加仓管理!$E$2:$E$1001),"")) | AO4: =IF(OR(A4="",H4="",H4<=0),"",(E4*H4+SUMIFS(加仓管理!$H$2:$H$1001,加仓管理!$A$2:$A$1001,A4))/AP4) -> 3.12 | AP4: =IF(OR(A4="",H4="",H4<=0),"",H4+AL4) -> 10000 | AQ4: =IF(A4="","",IF(M4<>"",0,IF(OR(H4="",N4=""),"",MAX((E4*H4+SUMIFS(加仓管理!$H$2:$H$1001,加仓管理!$A$2:$A$1001,A4))-MAX(N4,AN4)*AP4,0)))) -> 0 | AR4: =IF(A4="","",IF(OR(E4="",H4=""),"违规：首次买入价格或股数缺失",IF(COUNTIFS(加仓管理!$A$2:$A$1001,A4,加仓管理!$R$2:$R$1001,"违规*")>0,"违规：请检查加仓管理表",IF(SUM($AQ$2:$AQ$201)>账户数据!$B$7,"预警：超过账户风险上限",IF(COUNTIFS(加仓管理!$A$2:$A$1001,A4,加仓管理!$N$2:$N$1001,">0",加仓管理!$G$2:$G$1001,"")>0,"提示：存在待执行加仓计划","通过"))))) -> 通过
A5: 4 | B5: 新和成 | C5: 92098 | D5: 0.02 | E5: 3.15 | F5: =IF(OR(C5="",D5="",E5="",N5="",C5<=0,D5<=0,E5<=N5),"",ROUNDDOWN((C5*D5)/(E5-N5)/100,0)*100) -> 12200 | G5: =IF(A5="","",IF(H5<>"","已开仓",IF(账户数据!$B$23="已锁仓","禁止开仓：连续亏损达到上限",IF(账户数据!$B$23="解锁信息不完整","禁止开仓：请完整填写解锁信息",IF(OR(F5="",E5="",N5="",E5<=N5,账户数据!$B$7=""),"",IF(OR(AG5="",AH5="",AI5=""),"禁止开仓：交易预期未填写完整",IF(账户数据!$B$9+F5*(E5-N5)>=账户数据!$B$7,"禁止开仓：风险额度不足",IF(AJ5="周期与交易预期不匹配，请重新确认",IF(账户数据!$B$23="接近锁仓","允许开仓（接近锁仓；周期需复核）","允许开仓（周期需复核）"),IF(账户数据!$B$23="接近锁仓","允许开仓（接近锁仓）","允许开仓"))))))))) -> 已开仓 | H5: 10000 | I5: 42817 | J5: 3.5 | K5: 3.76 | L5: =IF(AP5="","",AP5) -> 33000 | M5: 42970 | N5: 3 | U5: =IF(OR(AO5="",J5="",AO5<=0),"",(J5-AO5)/AO5) -> 0.29950495 | V5: =IF(OR(AO5="",N5="",AO5<=0),"",(AO5-N5)/AO5) -> -0.11386139 | W5: =IF(OR(U5="",V5="",V5<=0),"",U5/V5) | X5: =IF(OR(K5="",L5="",AO5="",AP5=""),"",(K5-AO5)*L5-IF(O5="",0,O5)-IF(P5="",0,P5)) -> 35200 | Y5: =IF(OR(X5="",AO5="",L5=""),"",IF(AO5*L5+IF(O5="",0,O5)<=0,"",X5/(AO5*L5+IF(O5="",0,O5)))) -> 0.3960396 | Z5: =IF(OR(AE5="",多次统计数据!$B$8=""),"",AE5-多次统计数据!$B$8) -> 0.2839916 | AA5: =IF(OR(I5="",M5="",M5<I5),"",M5-I5) -> 153 | AB5: =IF(OR(A5="",多次统计数据!$B$8="",多次统计数据!$B$6<=0,多次统计数据!$B$6>=1),"",1-POWER(1+多次统计数据!$B$8,-多次统计数据!$B$6/(1-多次统计数据!$B$6))) -> 0.096508292 | AC5: =IF(OR(AB5="",多次统计数据!$B$9=""),"",IF(多次统计数据!$B$9<AB5,"低于上限","达到或超过上限")) -> 低于上限 | AE5: =IF(OR(X5="",C5="",C5<=0),"",X5/C5) -> 0.38220157 | AG5: 趋势波段 | AH5: 11～20个交易日 | AI5: 吸筹 | AJ5: =IF(OR(AG5="",AH5=""),"",IF(OR(AND(AG5="短期博反弹",OR(AH5="1～3个交易日",AH5="4～10个交易日")),AND(AG5="突破冲新高",OR(AH5="4～10个交易日",AH5="11～20个交易日")),AND(AG5="趋势波段",OR(AH5="11～20个交易日",AH5="21～60个交易日",AH5="60个交易日以上"))),"匹配","周期与交易预期不匹配，请重新确认")) -> 匹配 | AK5: =IF(A5="","",COUNTIFS(加仓管理!$A$2:$A$1001,A5,加仓管理!$G$2:$G$1001,">0")) -> 4 | AL5: =IF(A5="","",SUMIFS(加仓管理!$G$2:$G$1001,加仓管理!$A$2:$A$1001,A5)) -> 23000 | AM5: =IF(AK5=0,"",IFERROR(LOOKUP(2,1/((加仓管理!$A$2:$A$1001=A5)*(加仓管理!$G$2:$G$1001>0)),加仓管理!$D$2:$D$1001),"")) -> 2.16 | AN5: =IF(AK5=0,"",IFERROR(LOOKUP(2,1/((加仓管理!$A$2:$A$1001=A5)*(加仓管理!$G$2:$G$1001>0)),加仓管理!$E$2:$E$1001),"")) -> 2 | AO5: =IF(OR(A5="",H5="",H5<=0),"",(E5*H5+SUMIFS(加仓管理!$H$2:$H$1001,加仓管理!$A$2:$A$1001,A5))/AP5) -> 2.6933333 | AP5: =IF(OR(A5="",H5="",H5<=0),"",H5+AL5) -> 33000 | AQ5: =IF(A5="","",IF(M5<>"",0,IF(OR(H5="",N5=""),"",MAX((E5*H5+SUMIFS(加仓管理!$H$2:$H$1001,加仓管理!$A$2:$A$1001,A5))-MAX(N5,AN5)*AP5,0)))) -> 0 | AR5: =IF(A5="","",IF(OR(E5="",H5=""),"违规：首次买入价格或股数缺失",IF(COUNTIFS(加仓管理!$A$2:$A$1001,A5,加仓管理!$R$2:$R$1001,"违规*")>0,"违规：请检查加仓管理表",IF(SUM($AQ$2:$AQ$201)>账户数据!$B$7,"预警：超过账户风险上限",IF(COUNTIFS(加仓管理!$A$2:$A$1001,A5,加仓管理!$N$2:$N$1001,">0",加仓管理!$G$2:$G$1001,"")>0,"提示：存在待执行加仓计划","通过"))))) -> 违规：请检查加仓管理表
A6: 5 | B6: 新和成 | C6: 127298 | D6: 0.02 | E6: 4.39 | F6: =IF(OR(C6="",D6="",E6="",N6="",C6<=0,D6<=0,E6<=N6),"",ROUNDDOWN((C6*D6)/(E6-N6)/100,0)*100) -> 6500 | G6: =IF(A6="","",IF(H6<>"","已开仓",IF(账户数据!$B$23="已锁仓","禁止开仓：连续亏损达到上限",IF(账户数据!$B$23="解锁信息不完整","禁止开仓：请完整填写解锁信息",IF(OR(F6="",E6="",N6="",E6<=N6,账户数据!$B$7=""),"",IF(OR(AG6="",AH6="",AI6=""),"禁止开仓：交易预期未填写完整",IF(账户数据!$B$9+F6*(E6-N6)>=账户数据!$B$7,"禁止开仓：风险额度不足",IF(AJ6="周期与交易预期不匹配，请重新确认",IF(账户数据!$B$23="接近锁仓","允许开仓（接近锁仓；周期需复核）","允许开仓（周期需复核）"),IF(账户数据!$B$23="接近锁仓","允许开仓（接近锁仓）","允许开仓"))))))))) -> 已开仓 | H6: 6500 | I6: 42979 | J6: 5 | K6: 5.38 | L6: =IF(AP6="","",AP6) -> 9000 | M6: 43003 | N6: 4 | U6: =IF(OR(AO6="",J6="",AO6<=0),"",(J6-AO6)/AO6) -> 0.1282437 | V6: =IF(OR(AO6="",N6="",AO6<=0),"",(AO6-N6)/AO6) -> 0.097405039 | W6: =IF(OR(U6="",V6="",V6<=0),"",U6/V6) -> 1.3166023 | X6: =IF(OR(K6="",L6="",AO6="",AP6=""),"",(K6-AO6)*L6-IF(O6="",0,O6)-IF(P6="",0,P6)) -> 8535 | Y6: =IF(OR(X6="",AO6="",L6=""),"",IF(AO6*L6+IF(O6="",0,O6)<=0,"",X6/(AO6*L6+IF(O6="",0,O6)))) -> 0.21399022 | Z6: =IF(OR(AE6="",多次统计数据!$B$8=""),"",AE6-多次统计数据!$B$8) -> -0.031162565 | AA6: =IF(OR(I6="",M6="",M6<I6),"",M6-I6) -> 24 | AB6: =IF(OR(A6="",多次统计数据!$B$8="",多次统计数据!$B$6<=0,多次统计数据!$B$6>=1),"",1-POWER(1+多次统计数据!$B$8,-多次统计数据!$B$6/(1-多次统计数据!$B$6))) -> 0.096508292 | AC6: =IF(OR(AB6="",多次统计数据!$B$9=""),"",IF(多次统计数据!$B$9<AB6,"低于上限","达到或超过上限")) -> 低于上限 | AE6: =IF(OR(X6="",C6="",C6<=0),"",X6/C6) -> 0.067047401 | AG6: 突破冲新高 | AH6: 4～10个交易日 | AI6: 新高 | AJ6: =IF(OR(AG6="",AH6=""),"",IF(OR(AND(AG6="短期博反弹",OR(AH6="1～3个交易日",AH6="4～10个交易日")),AND(AG6="突破冲新高",OR(AH6="4～10个交易日",AH6="11～20个交易日")),AND(AG6="趋势波段",OR(AH6="11～20个交易日",AH6="21～60个交易日",AH6="60个交易日以上"))),"匹配","周期与交易预期不匹配，请重新确认")) -> 匹配 | AK6: =IF(A6="","",COUNTIFS(加仓管理!$A$2:$A$1001,A6,加仓管理!$G$2:$G$1001,">0")) -> 1 | AL6: =IF(A6="","",SUMIFS(加仓管理!$G$2:$G$1001,加仓管理!$A$2:$A$1001,A6)) -> 2500 | AM6: =IF(AK6=0,"",IFERROR(LOOKUP(2,1/((加仓管理!$A$2:$A$1001=A6)*(加仓管理!$G$2:$G$1001>0)),加仓管理!$D$2:$D$1001),"")) -> 4.54 | AN6: =IF(AK6=0,"",IFERROR(LOOKUP(2,1/((加仓管理!$A$2:$A$1001=A6)*(加仓管理!$G$2:$G$1001>0)),加仓管理!$E$2:$E$1001),"")) -> 4 | AO6: =IF(OR(A6="",H6="",H6<=0),"",(E6*H6+SUMIFS(加仓管理!$H$2:$H$1001,加仓管理!$A$2:$A$1001,A6))/AP6) -> 4.4316667 | AP6: =IF(OR(A6="",H6="",H6<=0),"",H6+AL6) -> 9000 | AQ6: =IF(A6="","",IF(M6<>"",0,IF(OR(H6="",N6=""),"",MAX((E6*H6+SUMIFS(加仓管理!$H$2:$H$1001,加仓管理!$A$2:$A$1001,A6))-MAX(N6,AN6)*AP6,0)))) -> 0 | AR6: =IF(A6="","",IF(OR(E6="",H6=""),"违规：首次买入价格或股数缺失",IF(COUNTIFS(加仓管理!$A$2:$A$1001,A6,加仓管理!$R$2:$R$1001,"违规*")>0,"违规：请检查加仓管理表",IF(SUM($AQ$2:$AQ$201)>账户数据!$B$7,"预警：超过账户风险上限",IF(COUNTIFS(加仓管理!$A$2:$A$1001,A6,加仓管理!$N$2:$N$1001,">0",加仓管理!$G$2:$G$1001,"")>0,"提示：存在待执行加仓计划","通过"))))) -> 违规：请检查加仓管理表
A7: 6 | B7: 新和成 | C7: 135833 | D7: 0.02 | E7: 5.65 | F7: =IF(OR(C7="",D7="",E7="",N7="",C7<=0,D7<=0,E7<=N7),"",ROUNDDOWN((C7*D7)/(E7-N7)/100,0)*100) -> 5600 | G7: =IF(A7="","",IF(H7<>"","已开仓",IF(账户数据!$B$23="已锁仓","禁止开仓：连续亏损达到上限",IF(账户数据!$B$23="解锁信息不完整","禁止开仓：请完整填写解锁信息",IF(OR(F7="",E7="",N7="",E7<=N7,账户数据!$B$7=""),"",IF(OR(AG7="",AH7="",AI7=""),"禁止开仓：交易预期未填写完整",IF(账户数据!$B$9+F7*(E7-N7)>=账户数据!$B$7,"禁止开仓：风险额度不足",IF(AJ7="周期与交易预期不匹配，请重新确认",IF(账户数据!$B$23="接近锁仓","允许开仓（接近锁仓；周期需复核）","允许开仓（周期需复核）"),IF(账户数据!$B$23="接近锁仓","允许开仓（接近锁仓）","允许开仓"))))))))) -> 已开仓 | H7: 5600 | I7: 43038 | J7: 6 | K7: 6.48 | L7: =IF(AP7="","",AP7) -> 7600 | M7: 43052 | N7: 5.17 | U7: =IF(OR(AO7="",J7="",AO7<=0),"",(J7-AO7)/AO7) -> 0.04875805 | V7: =IF(OR(AO7="",N7="",AO7<=0),"",(AO7-N7)/AO7) -> 0.096320147 | W7: =IF(OR(U7="",V7="",V7<=0),"",U7/V7) -> 0.50620821 | X7: =IF(OR(K7="",L7="",AO7="",AP7=""),"",(K7-AO7)*L7-IF(O7="",0,O7)-IF(P7="",0,P7)) -> 5768 | Y7: =IF(OR(X7="",AO7="",L7=""),"",IF(AO7*L7+IF(O7="",0,O7)<=0,"",X7/(AO7*L7+IF(O7="",0,O7)))) -> 0.13265869 | Z7: =IF(OR(AE7="",多次统计数据!$B$8=""),"",AE7-多次统计数据!$B$8) -> -0.055746058 | AA7: =IF(OR(I7="",M7="",M7<I7),"",M7-I7) -> 14 | AB7: =IF(OR(A7="",多次统计数据!$B$8="",多次统计数据!$B$6<=0,多次统计数据!$B$6>=1),"",1-POWER(1+多次统计数据!$B$8,-多次统计数据!$B$6/(1-多次统计数据!$B$6))) -> 0.096508292 | AC7: =IF(OR(AB7="",多次统计数据!$B$9=""),"",IF(多次统计数据!$B$9<AB7,"低于上限","达到或超过上限")) -> 低于上限 | AE7: =IF(OR(X7="",C7="",C7<=0),"",X7/C7) -> 0.042463908 | AG7: 突破冲新高 | AH7: 4～10个交易日 | AI7: 新高 | AJ7: =IF(OR(AG7="",AH7=""),"",IF(OR(AND(AG7="短期博反弹",OR(AH7="1～3个交易日",AH7="4～10个交易日")),AND(AG7="突破冲新高",OR(AH7="4～10个交易日",AH7="11～20个交易日")),AND(AG7="趋势波段",OR(AH7="11～20个交易日",AH7="21～60个交易日",AH7="60个交易日以上"))),"匹配","周期与交易预期不匹配，请重新确认")) -> 匹配 | AK7: =IF(A7="","",COUNTIFS(加仓管理!$A$2:$A$1001,A7,加仓管理!$G$2:$G$1001,">0")) -> 1 | AL7: =IF(A7="","",SUMIFS(加仓管理!$G$2:$G$1001,加仓管理!$A$2:$A$1001,A7)) -> 2000 | AM7: =IF(AK7=0,"",IFERROR(LOOKUP(2,1/((加仓管理!$A$2:$A$1001=A7)*(加仓管理!$G$2:$G$1001>0)),加仓管理!$D$2:$D$1001),"")) -> 5.92 | AN7: =IF(AK7=0,"",IFERROR(LOOKUP(2,1/((加仓管理!$A$2:$A$1001=A7)*(加仓管理!$G$2:$G$1001>0)),加仓管理!$E$2:$E$1001),"")) -> 5.5 | AO7: =IF(OR(A7="",H7="",H7<=0),"",(E7*H7+SUMIFS(加仓管理!$H$2:$H$1001,加仓管理!$A$2:$A$1001,A7))/AP7) -> 5.7210526 | AP7: =IF(OR(A7="",H7="",H7<=0),"",H7+AL7) -> 7600 | AQ7: =IF(A7="","",IF(M7<>"",0,IF(OR(H7="",N7=""),"",MAX((E7*H7+SUMIFS(加仓管理!$H$2:$H$1001,加仓管理!$A$2:$A$1001,A7))-MAX(N7,AN7)*AP7,0)))) -> 0 | AR7: =IF(A7="","",IF(OR(E7="",H7=""),"违规：首次买入价格或股数缺失",IF(COUNTIFS(加仓管理!$A$2:$A$1001,A7,加仓管理!$R$2:$R$1001,"违规*")>0,"违规：请检查加仓管理表",IF(SUM($AQ$2:$AQ$201)>账户数据!$B$7,"预警：超过账户风险上限",IF(COUNTIFS(加仓管理!$A$2:$A$1001,A7,加仓管理!$N$2:$N$1001,">0",加仓管理!$G$2:$G$1001,"")>0,"提示：存在待执行加仓计划","通过"))))) -> 违规：请检查加仓管理表
A8: 7 | B8: 新和成 | C8: 141601 | D8: 0.02 | E8: 10.93 | F8: =IF(OR(C8="",D8="",E8="",N8="",C8<=0,D8<=0,E8<=N8),"",ROUNDDOWN((C8*D8)/(E8-N8)/100,0)*100) -> 3000 | G8: =IF(A8="","",IF(H8<>"","已开仓",IF(账户数据!$B$23="已锁仓","禁止开仓：连续亏损达到上限",IF(账户数据!$B$23="解锁信息不完整","禁止开仓：请完整填写解锁信息",IF(OR(F8="",E8="",N8="",E8<=N8,账户数据!$B$7=""),"",IF(OR(AG8="",AH8="",AI8=""),"禁止开仓：交易预期未填写完整",IF(账户数据!$B$9+F8*(E8-N8)>=账户数据!$B$7,"禁止开仓：风险额度不足",IF(AJ8="周期与交易预期不匹配，请重新确认",IF(账户数据!$B$23="接近锁仓","允许开仓（接近锁仓；周期需复核）","允许开仓（周期需复核）"),IF(账户数据!$B$23="接近锁仓","允许开仓（接近锁仓）","允许开仓"))))))))) -> 已开仓 | H8: 3000 | I8: 43244 | J8: 13 | K8: 9.92 | L8: =IF(AP8="","",AP8) -> 3000 | M8: 43249 | N8: 10 | U8: =IF(OR(AO8="",J8="",AO8<=0),"",(J8-AO8)/AO8) -> 0.18938701 | V8: =IF(OR(AO8="",N8="",AO8<=0),"",(AO8-N8)/AO8) -> 0.085086917 | W8: =IF(OR(U8="",V8="",V8<=0),"",U8/V8) -> 2.2258065 | X8: =IF(OR(K8="",L8="",AO8="",AP8=""),"",(K8-AO8)*L8-IF(O8="",0,O8)-IF(P8="",0,P8)) -> -3030 | Y8: =IF(OR(X8="",AO8="",L8=""),"",IF(AO8*L8+IF(O8="",0,O8)<=0,"",X8/(AO8*L8+IF(O8="",0,O8)))) -> -0.092406221 | Z8: =IF(OR(AE8="",多次统计数据!$B$8=""),"",AE8-多次统计数据!$B$8) -> -0.11960812 | AA8: =IF(OR(I8="",M8="",M8<I8),"",M8-I8) -> 5 | AB8: =IF(OR(A8="",多次统计数据!$B$8="",多次统计数据!$B$6<=0,多次统计数据!$B$6>=1),"",1-POWER(1+多次统计数据!$B$8,-多次统计数据!$B$6/(1-多次统计数据!$B$6))) -> 0.096508292 | AC8: =IF(OR(AB8="",多次统计数据!$B$9=""),"",IF(多次统计数据!$B$9<AB8,"低于上限","达到或超过上限")) -> 低于上限 | AE8: =IF(OR(X8="",C8="",C8<=0),"",X8/C8) -> -0.021398154 | AG8: 趋势波段 | AH8: 11～20个交易日 | AI8: 吸筹 | AJ8: =IF(OR(AG8="",AH8=""),"",IF(OR(AND(AG8="短期博反弹",OR(AH8="1～3个交易日",AH8="4～10个交易日")),AND(AG8="突破冲新高",OR(AH8="4～10个交易日",AH8="11～20个交易日")),AND(AG8="趋势波段",OR(AH8="11～20个交易日",AH8="21～60个交易日",AH8="60个交易日以上"))),"匹配","周期与交易预期不匹配，请重新确认")) -> 匹配 | AK8: =IF(A8="","",COUNTIFS(加仓管理!$A$2:$A$1001,A8,加仓管理!$G$2:$G$1001,">0")) -> 0 | AL8: =IF(A8="","",SUMIFS(加仓管理!$G$2:$G$1001,加仓管理!$A$2:$A$1001,A8)) -> 0 | AM8: =IF(AK8=0,"",IFERROR(LOOKUP(2,1/((加仓管理!$A$2:$A$1001=A8)*(加仓管理!$G$2:$G$1001>0)),加仓管理!$D$2:$D$1001),"")) | AN8: =IF(AK8=0,"",IFERROR(LOOKUP(2,1/((加仓管理!$A$2:$A$1001=A8)*(加仓管理!$G$2:$G$1001>0)),加仓管理!$E$2:$E$1001),"")) | AO8: =IF(OR(A8="",H8="",H8<=0),"",(E8*H8+SUMIFS(加仓管理!$H$2:$H$1001,加仓管理!$A$2:$A$1001,A8))/AP8) -> 10.93 | AP8: =IF(OR(A8="",H8="",H8<=0),"",H8+AL8) -> 3000 | AQ8: =IF(A8="","",IF(M8<>"",0,IF(OR(H8="",N8=""),"",MAX((E8*H8+SUMIFS(加仓管理!$H$2:$H$1001,加仓管理!$A$2:$A$1001,A8))-MAX(N8,AN8)*AP8,0)))) -> 0 | AR8: =IF(A8="","",IF(OR(E8="",H8=""),"违规：首次买入价格或股数缺失",IF(COUNTIFS(加仓管理!$A$2:$A$1001,A8,加仓管理!$R$2:$R$1001,"违规*")>0,"违规：请检查加仓管理表",IF(SUM($AQ$2:$AQ$201)>账户数据!$B$7,"预警：超过账户风险上限",IF(COUNTIFS(加仓管理!$A$2:$A$1001,A8,加仓管理!$N$2:$N$1001,">0",加仓管理!$G$2:$G$1001,"")>0,"提示：存在待执行加仓计划","通过"))))) -> 通过
A9: 8 | B9: 新和成 | C9: 138571 | D9: 0.02 | E9: 7.54 | F9: =IF(OR(C9="",D9="",E9="",N9="",C9<=0,D9<=0,E9<=N9),"",ROUNDDOWN((C9*D9)/(E9-N9)/100,0)*100) -> 5100 | G9: =IF(A9="","",IF(H9<>"","已开仓",IF(账户数据!$B$23="已锁仓","禁止开仓：连续亏损达到上限",IF(账户数据!$B$23="解锁信息不完整","禁止开仓：请完整填写解锁信息",IF(OR(F9="",E9="",N9="",E9<=N9,账户数据!$B$7=""),"",IF(OR(AG9="",AH9="",AI9=""),"禁止开仓：交易预期未填写完整",IF(账户数据!$B$9+F9*(E9-N9)>=账户数据!$B$7,"禁止开仓：风险额度不足",IF(AJ9="周期与交易预期不匹配，请重新确认",IF(账户数据!$B$23="接近锁仓","允许开仓（接近锁仓；周期需复核）","允许开仓（周期需复核）"),IF(账户数据!$B$23="接近锁仓","允许开仓（接近锁仓）","允许开仓"))))))))) -> 已开仓 | H9: 4000 | I9: 43523 | J9: 9 | K9: 8.47 | L9: =IF(AP9="","",AP9) -> 11500 | M9: 43545 | N9: 7 | U9: =IF(OR(AO9="",J9="",AO9<=0),"",(J9-AO9)/AO9) -> 0.10065401 | V9: =IF(OR(AO9="",N9="",AO9<=0),"",(AO9-N9)/AO9) -> 0.14393577 | W9: =IF(OR(U9="",V9="",V9<=0),"",U9/V9) -> 0.69929812 | X9: =IF(OR(K9="",L9="",AO9="",AP9=""),"",(K9-AO9)*L9-IF(O9="",0,O9)-IF(P9="",0,P9)) -> 3370 | Y9: =IF(OR(X9="",AO9="",L9=""),"",IF(AO9*L9+IF(O9="",0,O9)<=0,"",X9/(AO9*L9+IF(O9="",0,O9)))) -> 0.03583772 | Z9: =IF(OR(AE9="",多次统计数据!$B$8=""),"",AE9-多次统计数据!$B$8) -> -0.073890303 | AA9: =IF(OR(I9="",M9="",M9<I9),"",M9-I9) -> 22 | AB9: =IF(OR(A9="",多次统计数据!$B$8="",多次统计数据!$B$6<=0,多次统计数据!$B$6>=1),"",1-POWER(1+多次统计数据!$B$8,-多次统计数据!$B$6/(1-多次统计数据!$B$6))) -> 0.096508292 | AC9: =IF(OR(AB9="",多次统计数据!$B$9=""),"",IF(多次统计数据!$B$9<AB9,"低于上限","达到或超过上限")) -> 低于上限 | AE9: =IF(OR(X9="",C9="",C9<=0),"",X9/C9) -> 0.024319663 | AG9: 短期博反弹 | AH9: 4～10个交易日 | AI9: 吸筹 | AJ9: =IF(OR(AG9="",AH9=""),"",IF(OR(AND(AG9="短期博反弹",OR(AH9="1～3个交易日",AH9="4～10个交易日")),AND(AG9="突破冲新高",OR(AH9="4～10个交易日",AH9="11～20个交易日")),AND(AG9="趋势波段",OR(AH9="11～20个交易日",AH9="21～60个交易日",AH9="60个交易日以上"))),"匹配","周期与交易预期不匹配，请重新确认")) -> 匹配 | AK9: =IF(A9="","",COUNTIFS(加仓管理!$A$2:$A$1001,A9,加仓管理!$G$2:$G$1001,">0")) -> 4 | AL9: =IF(A9="","",SUMIFS(加仓管理!$G$2:$G$1001,加仓管理!$A$2:$A$1001,A9)) -> 7500 | AM9: =IF(AK9=0,"",IFERROR(LOOKUP(2,1/((加仓管理!$A$2:$A$1001=A9)*(加仓管理!$G$2:$G$1001>0)),加仓管理!$D$2:$D$1001),"")) -> 9.32 | AN9: =IF(AK9=0,"",IFERROR(LOOKUP(2,1/((加仓管理!$A$2:$A$1001=A9)*(加仓管理!$G$2:$G$1001>0)),加仓管理!$E$2:$E$1001),"")) -> 8.5 | AO9: =IF(OR(A9="",H9="",H9<=0),"",(E9*H9+SUMIFS(加仓管理!$H$2:$H$1001,加仓管理!$A$2:$A$1001,A9))/AP9) -> 8.1769565 | AP9: =IF(OR(A9="",H9="",H9<=0),"",H9+AL9) -> 11500 | AQ9: =IF(A9="","",IF(M9<>"",0,IF(OR(H9="",N9=""),"",MAX((E9*H9+SUMIFS(加仓管理!$H$2:$H$1001,加仓管理!$A$2:$A$1001,A9))-MAX(N9,AN9)*AP9,0)))) -> 0 | AR9: =IF(A9="","",IF(OR(E9="",H9=""),"违规：首次买入价格或股数缺失",IF(COUNTIFS(加仓管理!$A$2:$A$1001,A9,加仓管理!$R$2:$R$1001,"违规*")>0,"违规：请检查加仓管理表",IF(SUM($AQ$2:$AQ$201)>账户数据!$B$7,"预警：超过账户风险上限",IF(COUNTIFS(加仓管理!$A$2:$A$1001,A9,加仓管理!$N$2:$N$1001,">0",加仓管理!$G$2:$G$1001,"")>0,"提示：存在待执行加仓计划","通过"))))) -> 违规：请检查加仓管理表
A10: 9 | B10: 新和成 | C10: 141941 | D10: 0.02 | E10: 8.02 | F10: =IF(OR(C10="",D10="",E10="",N10="",C10<=0,D10<=0,E10<=N10),"",ROUNDDOWN((C10*D10)/(E10-N10)/100,0)*100) -> 3900 | G10: =IF(A10="","",IF(H10<>"","已开仓",IF(账户数据!$B$23="已锁仓","禁止开仓：连续亏损达到上限",IF(账户数据!$B$23="解锁信息不完整","禁止开仓：请完整填写解锁信息",IF(OR(F10="",E10="",N10="",E10<=N10,账户数据!$B$7=""),"",IF(OR(AG10="",AH10="",AI10=""),"禁止开仓：交易预期未填写完整",IF(账户数据!$B$9+F10*(E10-N10)>=账户数据!$B$7,"禁止开仓：风险额度不足",IF(AJ10="周期与交易预期不匹配，请重新确认",IF(账户数据!$B$23="接近锁仓","允许开仓（接近锁仓；周期需复核）","允许开仓（周期需复核）"),IF(账户数据!$B$23="接近锁仓","允许开仓（接近锁仓）","允许开仓"))))))))) -> 已开仓 | H10: 3000 | I10: 43550 | J10: 9 | K10: 10.18 | L10: =IF(AP10="","",AP10) -> 11000 | M10: 43572 | N10: 7.3 | U10: =IF(OR(AO10="",J10="",AO10<=0),"",(J10-AO10)/AO10) -> 0.011029412 | V10: =IF(OR(AO10="",N10="",AO10<=0),"",(AO10-N10)/AO10) -> 0.17994281 | W10: =IF(OR(U10="",V10="",V10<=0),"",U10/V10) -> 0.061293984 | X10: =IF(OR(K10="",L10="",AO10="",AP10=""),"",(K10-AO10)*L10-IF(O10="",0,O10)-IF(P10="",0,P10)) -> 14060 | Y10: =IF(OR(X10="",AO10="",L10=""),"",IF(AO10*L10+IF(O10="",0,O10)<=0,"",X10/(AO10*L10+IF(O10="",0,O10)))) -> 0.1435866 | Z10: =IF(OR(AE10="",多次统计数据!$B$8=""),"",AE10-多次统计数据!$B$8) -> 0.00084527524 | AA10: =IF(OR(I10="",M10="",M10<I10),"",M10-I10) -> 22 | AB10: =IF(OR(A10="",多次统计数据!$B$8="",多次统计数据!$B$6<=0,多次统计数据!$B$6>=1),"",1-POWER(1+多次统计数据!$B$8,-多次统计数据!$B$6/(1-多次统计数据!$B$6))) -> 0.096508292 | AC10: =IF(OR(AB10="",多次统计数据!$B$9=""),"",IF(多次统计数据!$B$9<AB10,"低于上限","达到或超过上限")) -> 低于上限 | AE10: =IF(OR(X10="",C10="",C10<=0),"",X10/C10) -> 0.099055241 | AG10: 趋势波段 | AH10: 11～20个交易日 | AI10: 吸筹 | AJ10: =IF(OR(AG10="",AH10=""),"",IF(OR(AND(AG10="短期博反弹",OR(AH10="1～3个交易日",AH10="4～10个交易日")),AND(AG10="突破冲新高",OR(AH10="4～10个交易日",AH10="11～20个交易日")),AND(AG10="趋势波段",OR(AH10="11～20个交易日",AH10="21～60个交易日",AH10="60个交易日以上"))),"匹配","周期与交易预期不匹配，请重新确认")) -> 匹配 | AK10: =IF(A10="","",COUNTIFS(加仓管理!$A$2:$A$1001,A10,加仓管理!$G$2:$G$1001,">0")) -> 4 | AL10: =IF(A10="","",SUMIFS(加仓管理!$G$2:$G$1001,加仓管理!$A$2:$A$1001,A10)) -> 8000 | AM10: =IF(AK10=0,"",IFERROR(LOOKUP(2,1/((加仓管理!$A$2:$A$1001=A10)*(加仓管理!$G$2:$G$1001>0)),加仓管理!$D$2:$D$1001),"")) -> 9.69 | AN10: =IF(AK10=0,"",IFERROR(LOOKUP(2,1/((加仓管理!$A$2:$A$1001=A10)*(加仓管理!$G$2:$G$1001>0)),加仓管理!$E$2:$E$1001),"")) -> 9 | AO10: =IF(OR(A10="",H10="",H10<=0),"",(E10*H10+SUMIFS(加仓管理!$H$2:$H$1001,加仓管理!$A$2:$A$1001,A10))/AP10) -> 8.9018182 | AP10: =IF(OR(A10="",H10="",H10<=0),"",H10+AL10) -> 11000 | AQ10: =IF(A10="","",IF(M10<>"",0,IF(OR(H10="",N10=""),"",MAX((E10*H10+SUMIFS(加仓管理!$H$2:$H$1001,加仓管理!$A$2:$A$1001,A10))-MAX(N10,AN10)*AP10,0)))) -> 0 | AR10: =IF(A10="","",IF(OR(E10="",H10=""),"违规：首次买入价格或股数缺失",IF(COUNTIFS(加仓管理!$A$2:$A$1001,A10,加仓管理!$R$2:$R$1001,"违规*")>0,"违规：请检查加仓管理表",IF(SUM($AQ$2:$AQ$201)>账户数据!$B$7,"预警：超过账户风险上限",IF(COUNTIFS(加仓管理!$A$2:$A$1001,A10,加仓管理!$N$2:$N$1001,">0",加仓管理!$G$2:$G$1001,"")>0,"提示：存在待执行加仓计划","通过"))))) -> 违规：请检查加仓管理表
A11: 10 | B11: 新和成 | C11: 156001 | D11: 0.02 | E11: 9.07 | F11: =IF(OR(C11="",D11="",E11="",N11="",C11<=0,D11<=0,E11<=N11),"",ROUNDDOWN((C11*D11)/(E11-N11)/100,0)*100) -> 5400 | G11: =IF(A11="","",IF(H11<>"","已开仓",IF(账户数据!$B$23="已锁仓","禁止开仓：连续亏损达到上限",IF(账户数据!$B$23="解锁信息不完整","禁止开仓：请完整填写解锁信息",IF(OR(F11="",E11="",N11="",E11<=N11,账户数据!$B$7=""),"",IF(OR(AG11="",AH11="",AI11=""),"禁止开仓：交易预期未填写完整",IF(账户数据!$B$9+F11*(E11-N11)>=账户数据!$B$7,"禁止开仓：风险额度不足",IF(AJ11="周期与交易预期不匹配，请重新确认",IF(账户数据!$B$23="接近锁仓","允许开仓（接近锁仓；周期需复核）","允许开仓（周期需复核）"),IF(账户数据!$B$23="接近锁仓","允许开仓（接近锁仓）","允许开仓"))))))))) -> 已开仓 | H11: 2000 | I11: 43598 | J11: 10 | K11: 8.48 | L11: =IF(AP11="","",AP11) -> 4000 | M11: 43602 | N11: 8.5 | U11: =IF(OR(AO11="",J11="",AO11<=0),"",(J11-AO11)/AO11) -> 0.083423619 | V11: =IF(OR(AO11="",N11="",AO11<=0),"",(AO11-N11)/AO11) -> 0.079089924 | W11: =IF(OR(U11="",V11="",V11<=0),"",U11/V11) -> 1.0547945 | X11: =IF(OR(K11="",L11="",AO11="",AP11=""),"",(K11-AO11)*L11-IF(O11="",0,O11)-IF(P11="",0,P11)) -> -3000 | Y11: =IF(OR(X11="",AO11="",L11=""),"",IF(AO11*L11+IF(O11="",0,O11)<=0,"",X11/(AO11*L11+IF(O11="",0,O11)))) -> -0.081256771 | Z11: =IF(OR(AE11="",多次统计数据!$B$8=""),"",AE11-多次统计数据!$B$8) -> -0.11744061 | AA11: =IF(OR(I11="",M11="",M11<I11),"",M11-I11) -> 4 | AB11: =IF(OR(A11="",多次统计数据!$B$8="",多次统计数据!$B$6<=0,多次统计数据!$B$6>=1),"",1-POWER(1+多次统计数据!$B$8,-多次统计数据!$B$6/(1-多次统计数据!$B$6))) -> 0.096508292 | AC11: =IF(OR(AB11="",多次统计数据!$B$9=""),"",IF(多次统计数据!$B$9<AB11,"低于上限","达到或超过上限")) -> 低于上限 | AE11: =IF(OR(X11="",C11="",C11<=0),"",X11/C11) -> -0.019230646 | AG11: 短期博反弹 | AH11: 4～10个交易日 | AI11: 吸筹 | AJ11: =IF(OR(AG11="",AH11=""),"",IF(OR(AND(AG11="短期博反弹",OR(AH11="1～3个交易日",AH11="4～10个交易日")),AND(AG11="突破冲新高",OR(AH11="4～10个交易日",AH11="11～20个交易日")),AND(AG11="趋势波段",OR(AH11="11～20个交易日",AH11="21～60个交易日",AH11="60个交易日以上"))),"匹配","周期与交易预期不匹配，请重新确认")) -> 匹配 | AK11: =IF(A11="","",COUNTIFS(加仓管理!$A$2:$A$1001,A11,加仓管理!$G$2:$G$1001,">0")) -> 1 | AL11: =IF(A11="","",SUMIFS(加仓管理!$G$2:$G$1001,加仓管理!$A$2:$A$1001,A11)) -> 2000 | AM11: =IF(AK11=0,"",IFERROR(LOOKUP(2,1/((加仓管理!$A$2:$A$1001=A11)*(加仓管理!$G$2:$G$1001>0)),加仓管理!$D$2:$D$1001),"")) -> 9.39 | AN11: =IF(AK11=0,"",IFERROR(LOOKUP(2,1/((加仓管理!$A$2:$A$1001=A11)*(加仓管理!$G$2:$G$1001>0)),加仓管理!$E$2:$E$1001),"")) -> 9 | AO11: =IF(OR(A11="",H11="",H11<=0),"",(E11*H11+SUMIFS(加仓管理!$H$2:$H$1001,加仓管理!$A$2:$A$1001,A11))/AP11) -> 9.23 | AP11: =IF(OR(A11="",H11="",H11<=0),"",H11+AL11) -> 4000 | AQ11: =IF(A11="","",IF(M11<>"",0,IF(OR(H11="",N11=""),"",MAX((E11*H11+SUMIFS(加仓管理!$H$2:$H$1001,加仓管理!$A$2:$A$1001,A11))-MAX(N11,AN11)*AP11,0)))) -> 0 | AR11: =IF(A11="","",IF(OR(E11="",H11=""),"违规：首次买入价格或股数缺失",IF(COUNTIFS(加仓管理!$A$2:$A$1001,A11,加仓管理!$R$2:$R$1001,"违规*")>0,"违规：请检查加仓管理表",IF(SUM($AQ$2:$AQ$201)>账户数据!$B$7,"预警：超过账户风险上限",IF(COUNTIFS(加仓管理!$A$2:$A$1001,A11,加仓管理!$N$2:$N$1001,">0",加仓管理!$G$2:$G$1001,"")>0,"提示：存在待执行加仓计划","通过"))))) -> 违规：请检查加仓管理表
A12: 11 | B12: 新和成 | C12: 153001 | D12: 0.02 | E12: 8.92 | F12: =IF(OR(C12="",D12="",E12="",N12="",C12<=0,D12<=0,E12<=N12),"",ROUNDDOWN((C12*D12)/(E12-N12)/100,0)*100) -> 7200 | G12: =IF(A12="","",IF(H12<>"","已开仓",IF(账户数据!$B$23="已锁仓","禁止开仓：连续亏损达到上限",IF(账户数据!$B$23="解锁信息不完整","禁止开仓：请完整填写解锁信息",IF(OR(F12="",E12="",N12="",E12<=N12,账户数据!$B$7=""),"",IF(OR(AG12="",AH12="",AI12=""),"禁止开仓：交易预期未填写完整",IF(账户数据!$B$9+F12*(E12-N12)>=账户数据!$B$7,"禁止开仓：风险额度不足",IF(AJ12="周期与交易预期不匹配，请重新确认",IF(账户数据!$B$23="接近锁仓","允许开仓（接近锁仓；周期需复核）","允许开仓（周期需复核）"),IF(账户数据!$B$23="接近锁仓","允许开仓（接近锁仓）","允许开仓"))))))))) -> 已开仓 | H12: 4000 | I12: 43609 | J12: 10 | K12: 11.07 | L12: =IF(AP12="","",AP12) -> 15000 | M12: 43731 | N12: 8.5 | U12: =IF(OR(AO12="",J12="",AO12<=0),"",(J12-AO12)/AO12) -> 0.07434465 | V12: =IF(OR(AO12="",N12="",AO12<=0),"",(AO12-N12)/AO12) -> 0.086807048 | W12: =IF(OR(U12="",V12="",V12<=0),"",U12/V12) -> 0.85643564 | X12: =IF(OR(K12="",L12="",AO12="",AP12=""),"",(K12-AO12)*L12-IF(O12="",0,O12)-IF(P12="",0,P12)) -> 26430 | Y12: =IF(OR(X12="",AO12="",L12=""),"",IF(AO12*L12+IF(O12="",0,O12)<=0,"",X12/(AO12*L12+IF(O12="",0,O12)))) -> 0.18929953 | Z12: =IF(OR(AE12="",多次统计数据!$B$8=""),"",AE12-多次统计数据!$B$8) -> 0.074534003 | AA12: =IF(OR(I12="",M12="",M12<I12),"",M12-I12) -> 122 | AB12: =IF(OR(A12="",多次统计数据!$B$8="",多次统计数据!$B$6<=0,多次统计数据!$B$6>=1),"",1-POWER(1+多次统计数据!$B$8,-多次统计数据!$B$6/(1-多次统计数据!$B$6))) -> 0.096508292 | AC12: =IF(OR(AB12="",多次统计数据!$B$9=""),"",IF(多次统计数据!$B$9<AB12,"低于上限","达到或超过上限")) -> 低于上限 | AE12: =IF(OR(X12="",C12="",C12<=0),"",X12/C12) -> 0.17274397 | AG12: 趋势波段 | AH12: 11～20个交易日 | AI12: 吸筹 | AJ12: =IF(OR(AG12="",AH12=""),"",IF(OR(AND(AG12="短期博反弹",OR(AH12="1～3个交易日",AH12="4～10个交易日")),AND(AG12="突破冲新高",OR(AH12="4～10个交易日",AH12="11～20个交易日")),AND(AG12="趋势波段",OR(AH12="11～20个交易日",AH12="21～60个交易日",AH12="60个交易日以上"))),"匹配","周期与交易预期不匹配，请重新确认")) -> 匹配 | AK12: =IF(A12="","",COUNTIFS(加仓管理!$A$2:$A$1001,A12,加仓管理!$G$2:$G$1001,">0")) -> 4 | AL12: =IF(A12="","",SUMIFS(加仓管理!$G$2:$G$1001,加仓管理!$A$2:$A$1001,A12)) -> 11000 | AM12: =IF(AK12=0,"",IFERROR(LOOKUP(2,1/((加仓管理!$A$2:$A$1001=A12)*(加仓管理!$G$2:$G$1001>0)),加仓管理!$D$2:$D$1001),"")) -> 9.84 | AN12: =IF(AK12=0,"",IFERROR(LOOKUP(2,1/((加仓管理!$A$2:$A$1001=A12)*(加仓管理!$G$2:$G$1001>0)),加仓管理!$E$2:$E$1001),"")) -> 9.5 | AO12: =IF(OR(A12="",H12="",H12<=0),"",(E12*H12+SUMIFS(加仓管理!$H$2:$H$1001,加仓管理!$A$2:$A$1001,A12))/AP12) -> 9.308 | AP12: =IF(OR(A12="",H12="",H12<=0),"",H12+AL12) -> 15000 | AQ12: =IF(A12="","",IF(M12<>"",0,IF(OR(H12="",N12=""),"",MAX((E12*H12+SUMIFS(加仓管理!$H$2:$H$1001,加仓管理!$A$2:$A$1001,A12))-MAX(N12,AN12)*AP12,0)))) -> 0 | AR12: =IF(A12="","",IF(OR(E12="",H12=""),"违规：首次买入价格或股数缺失",IF(COUNTIFS(加仓管理!$A$2:$A$1001,A12,加仓管理!$R$2:$R$1001,"违规*")>0,"违规：请检查加仓管理表",IF(SUM($AQ$2:$AQ$201)>账户数据!$B$7,"预警：超过账户风险上限",IF(COUNTIFS(加仓管理!$A$2:$A$1001,A12,加仓管理!$N$2:$N$1001,">0",加仓管理!$G$2:$G$1001,"")>0,"提示：存在待执行加仓计划","通过"))))) -> 违规：请检查加仓管理表
A13: 12 | B13: 新和成 | C13: 179431 | D13: 0.02 | E13: 10.17 | F13: =IF(OR(C13="",D13="",E13="",N13="",C13<=0,D13<=0,E13<=N13),"",ROUNDDOWN((C13*D13)/(E13-N13)/100,0)*100) -> 5300 | G13: =IF(A13="","",IF(H13<>"","已开仓",IF(账户数据!$B$23="已锁仓","禁止开仓：连续亏损达到上限",IF(账户数据!$B$23="解锁信息不完整","禁止开仓：请完整填写解锁信息",IF(OR(F13="",E13="",N13="",E13<=N13,账户数据!$B$7=""),"",IF(OR(AG13="",AH13="",AI13=""),"禁止开仓：交易预期未填写完整",IF(账户数据!$B$9+F13*(E13-N13)>=账户数据!$B$7,"禁止开仓：风险额度不足",IF(AJ13="周期与交易预期不匹配，请重新确认",IF(账户数据!$B$23="接近锁仓","允许开仓（接近锁仓；周期需复核）","允许开仓（周期需复核）"),IF(账户数据!$B$23="接近锁仓","允许开仓（接近锁仓）","允许开仓"))))))))) -> 已开仓 | H13: 2000 | I13: 43755 | J13: 11 | K13: 9.55 | L13: =IF(AP13="","",AP13) -> 2000 | M13: 43767 | N13: 9.5 | U13: =IF(OR(AO13="",J13="",AO13<=0),"",(J13-AO13)/AO13) -> 0.081612586 | V13: =IF(OR(AO13="",N13="",AO13<=0),"",(AO13-N13)/AO13) -> 0.065880039 | W13: =IF(OR(U13="",V13="",V13<=0),"",U13/V13) -> 1.238806 | X13: =IF(OR(K13="",L13="",AO13="",AP13=""),"",(K13-AO13)*L13-IF(O13="",0,O13)-IF(P13="",0,P13)) -> -1240 | Y13: =IF(OR(X13="",AO13="",L13=""),"",IF(AO13*L13+IF(O13="",0,O13)<=0,"",X13/(AO13*L13+IF(O13="",0,O13)))) -> -0.060963618 | Z13: =IF(OR(AE13="",多次统计数据!$B$8=""),"",AE13-多次统计数据!$B$8) -> -0.1051207 | AA13: =IF(OR(I13="",M13="",M13<I13),"",M13-I13) -> 12 | AB13: =IF(OR(A13="",多次统计数据!$B$8="",多次统计数据!$B$6<=0,多次统计数据!$B$6>=1),"",1-POWER(1+多次统计数据!$B$8,-多次统计数据!$B$6/(1-多次统计数据!$B$6))) -> 0.096508292 | AC13: =IF(OR(AB13="",多次统计数据!$B$9=""),"",IF(多次统计数据!$B$9<AB13,"低于上限","达到或超过上限")) -> 低于上限 | AE13: =IF(OR(X13="",C13="",C13<=0),"",X13/C13) -> -0.0069107345 | AG13: 短期博反弹 | AH13: 4～10个交易日 | AI13: 反弹 | AJ13: =IF(OR(AG13="",AH13=""),"",IF(OR(AND(AG13="短期博反弹",OR(AH13="1～3个交易日",AH13="4～10个交易日")),AND(AG13="突破冲新高",OR(AH13="4～10个交易日",AH13="11～20个交易日")),AND(AG13="趋势波段",OR(AH13="11～20个交易日",AH13="21～60个交易日",AH13="60个交易日以上"))),"匹配","周期与交易预期不匹配，请重新确认")) -> 匹配 | AK13: =IF(A13="","",COUNTIFS(加仓管理!$A$2:$A$1001,A13,加仓管理!$G$2:$G$1001,">0")) -> 0 | AL13: =IF(A13="","",SUMIFS(加仓管理!$G$2:$G$1001,加仓管理!$A$2:$A$1001,A13)) -> 0 | AM13: =IF(AK13=0,"",IFERROR(LOOKUP(2,1/((加仓管理!$A$2:$A$1001=A13)*(加仓管理!$G$2:$G$1001>0)),加仓管理!$D$2:$D$1001),"")) | AN13: =IF(AK13=0,"",IFERROR(LOOKUP(2,1/((加仓管理!$A$2:$A$1001=A13)*(加仓管理!$G$2:$G$1001>0)),加仓管理!$E$2:$E$1001),"")) | AO13: =IF(OR(A13="",H13="",H13<=0),"",(E13*H13+SUMIFS(加仓管理!$H$2:$H$1001,加仓管理!$A$2:$A$1001,A13))/AP13) -> 10.17 | AP13: =IF(OR(A13="",H13="",H13<=0),"",H13+AL13) -> 2000 | AQ13: =IF(A13="","",IF(M13<>"",0,IF(OR(H13="",N13=""),"",MAX((E13*H13+SUMIFS(加仓管理!$H$2:$H$1001,加仓管理!$A$2:$A$1001,A13))-MAX(N13,AN13)*AP13,0)))) -> 0 | AR13: =IF(A13="","",IF(OR(E13="",H13=""),"违规：首次买入价格或股数缺失",IF(COUNTIFS(加仓管理!$A$2:$A$1001,A13,加仓管理!$R$2:$R$1001,"违规*")>0,"违规：请检查加仓管理表",IF(SUM($AQ$2:$AQ$201)>账户数据!$B$7,"预警：超过账户风险上限",IF(COUNTIFS(加仓管理!$A$2:$A$1001,A13,加仓管理!$N$2:$N$1001,">0",加仓管理!$G$2:$G$1001,"")>0,"提示：存在待执行加仓计划","通过"))))) -> 通过
... A101: 99 | B101: 爱尔眼科 | C101: 1145478 | D101: 0.02 | E101: 20.46 | F101: =IF(OR(C101="",D101="",E101="",N101="",C101<=0,D101<=0,E101<=N101),"",ROUNDDOWN((C101*D101)/(E101-N101)/100,0)*100) -> 6600 | G101: =IF(A101="","",IF(H101<>"","已开仓",IF(账户数据!$B$23="已锁仓","禁止开仓：连续亏损达到上限",IF(账户数据!$B$23="解锁信息不完整","禁止开仓：请完整填写解锁信息",IF(OR(F101="",E101="",N101="",E101<=N101,账户数据!$B$7=""),"",IF(OR(AG101="",AH101="",AI101=""),"禁止开仓：交易预期未填写完整",IF(账户数据!$B$9+F101*(E101-N101)>=账户数据!$B$7,"禁止开仓：风险额度不足",IF(AJ101="周期与交易预期不匹配，请重新确认",IF(账户数据!$B$23="接近锁仓","允许开仓（接近锁仓；周期需复核）","允许开仓（周期需复核）"),IF(账户数据!$B$23="接近锁仓","允许开仓（接近锁仓）","允许开仓"))))))))) -> 已开仓 | H101: 5000 | I101: 44021 | J101: 22 | K101: 21.08 | L101: =IF(AP101="","",AP101) -> 5000 | M101: 44027 | N101: 17 | U101: =IF(OR(AO101="",J101="",AO101<=0),"",(J101-AO101)/AO101) -> 0.075268817 | V101: =IF(OR(AO101="",N101="",AO101<=0),"",(AO101-N101)/AO101) -> 0.16911046 | W101: =IF(OR(U101="",V101="",V101<=0),"",U101/V101) -> 0.44508671 | X101: =IF(OR(K101="",L101="",AO101="",AP101=""),"",(K101-AO101)*L101-IF(O101="",0,O101)-IF(P101="",0,P101)) -> 3100 | Y101: =IF(OR(X101="",AO101="",L101=""),"",IF(AO101*L101+IF(O101="",0,O101)<=0,"",X101/(AO101*L101+IF(O101="",0,O101)))) -> 0.03030303 | Z101: =IF(OR(AE101="",多次统计数据!$B$8=""),"",AE101-多次统计数据!$B$8) -> -0.095503672 | AA101: =IF(OR(I101="",M101="",M101<I101),"",M101-I101) -> 6 | AB101: =IF(OR(A101="",多次统计数据!$B$8="",多次统计数据!$B$6<=0,多次统计数据!$B$6>=1),"",1-POWER(1+多次统计数据!$B$8,-多次统计数据!$B$6/(1-多次统计数据!$B$6))) -> 0.096508292 | AC101: =IF(OR(AB101="",多次统计数据!$B$9=""),"",IF(多次统计数据!$B$9<AB101,"低于上限","达到或超过上限")) -> 低于上限 | AE101: =IF(OR(X101="",C101="",C101<=0),"",X101/C101) -> 0.0027062938 | AG101: 短期博反弹 | AH101: 4～10个交易日 | AI101: 反弹 | AJ101: =IF(OR(AG101="",AH101=""),"",IF(OR(AND(AG101="短期博反弹",OR(AH101="1～3个交易日",AH101="4～10个交易日")),AND(AG101="突破冲新高",OR(AH101="4～10个交易日",AH101="11～20个交易日")),AND(AG101="趋势波段",OR(AH101="11～20个交易日",AH101="21～60个交易日",AH101="60个交易日以上"))),"匹配","周期与交易预期不匹配，请重新确认")) -> 匹配 | AK101: =IF(A101="","",COUNTIFS(加仓管理!$A$2:$A$1001,A101,加仓管理!$G$2:$G$1001,">0")) -> 0 | AL101: =IF(A101="","",SUMIFS(加仓管理!$G$2:$G$1001,加仓管理!$A$2:$A$1001,A101)) -> 0 | AM101: =IF(AK101=0,"",IFERROR(LOOKUP(2,1/((加仓管理!$A$2:$A$1001=A101)*(加仓管理!$G$2:$G$1001>0)),加仓管理!$D$2:$D$1001),"")) | AN101: =IF(AK101=0,"",IFERROR(LOOKUP(2,1/((加仓管理!$A$2:$A$1001=A101)*(加仓管理!$G$2:$G$1001>0)),加仓管理!$E$2:$E$1001),"")) | AO101: =IF(OR(A101="",H101="",H101<=0),"",(E101*H101+SUMIFS(加仓管理!$H$2:$H$1001,加仓管理!$A$2:$A$1001,A101))/AP101) -> 20.46 | AP101: =IF(OR(A101="",H101="",H101<=0),"",H101+AL101) -> 5000 | AQ101: =IF(A101="","",IF(M101<>"",0,IF(OR(H101="",N101=""),"",MAX((E101*H101+SUMIFS(加仓管理!$H$2:$H$1001,加仓管理!$A$2:$A$1001,A101))-MAX(N101,AN101)*AP101,0)))) -> 0 | AR101: =IF(A101="","",IF(OR(E101="",H101=""),"违规：首次买入价格或股数缺失",IF(COUNTIFS(加仓管理!$A$2:$A$1001,A101,加仓管理!$R$2:$R$1001,"违规*")>0,"违规：请检查加仓管理表",IF(SUM($AQ$2:$AQ$201)>账户数据!$B$7,"预警：超过账户风险上限",IF(COUNTIFS(加仓管理!$A$2:$A$1001,A101,加仓管理!$N$2:$N$1001,">0",加仓管理!$G$2:$G$1001,"")>0,"提示：存在待执行加仓计划","通过"))))) -> 通过
F102: =IF(OR(C102="",D102="",E102="",N102="",C102<=0,D102<=0,E102<=N102),"",ROUNDDOWN((C102*D102)/(E102-N102)/100,0)*100) | G102: =IF(A102="","",IF(H102<>"","已开仓",IF(账户数据!$B$23="已锁仓","禁止开仓：连续亏损达到上限",IF(账户数据!$B$23="解锁信息不完整","禁止开仓：请完整填写解锁信息",IF(OR(F102="",E102="",N102="",E102<=N102,账户数据!$B$7=""),"",IF(OR(AG102="",AH102="",AI102=""),"禁止开仓：交易预期未填写完整",IF(账户数据!$B$9+F102*(E102-N102)>=账户数据!$B$7,"禁止开仓：风险额度不足",IF(AJ102="周期与交易预期不匹配，请重新确认",IF(账户数据!$B$23="接近锁仓","允许开仓（接近锁仓；周期需复核）","允许开仓（周期需复核）"),IF(账户数据!$B$23="接近锁仓","允许开仓（接近锁仓）","允许开仓"))))))))) | L102: =IF(AP102="","",AP102) | U102: =IF(OR(AO102="",J102="",AO102<=0),"",(J102-AO102)/AO102) | V102: =IF(OR(AO102="",N102="",AO102<=0),"",(AO102-N102)/AO102) | W102: =IF(OR(U102="",V102="",V102<=0),"",U102/V102) | X102: =IF(OR(K102="",L102="",AO102="",AP102=""),"",(K102-AO102)*L102-IF(O102="",0,O102)-IF(P102="",0,P102)) | Y102: =IF(OR(X102="",AO102="",L102=""),"",IF(AO102*L102+IF(O102="",0,O102)<=0,"",X102/(AO102*L102+IF(O102="",0,O102)))) | Z102: =IF(OR(AE102="",多次统计数据!$B$8=""),"",AE102-多次统计数据!$B$8) | AA102: =IF(OR(I102="",M102="",M102<I102),"",M102-I102) | AB102: =IF(OR(A102="",多次统计数据!$B$8="",多次统计数据!$B$6<=0,多次统计数据!$B$6>=1),"",1-POWER(1+多次统计数据!$B$8,-多次统计数据!$B$6/(1-多次统计数据!$B$6))) | AC102: =IF(OR(AB102="",多次统计数据!$B$9=""),"",IF(多次统计数据!$B$9<AB102,"低于上限","达到或超过上限")) | AE102: =IF(OR(X102="",C102="",C102<=0),"",X102/C102) | AJ102: =IF(OR(AG102="",AH102=""),"",IF(OR(AND(AG102="短期博反弹",OR(AH102="1～3个交易日",AH102="4～10个交易日")),AND(AG102="突破冲新高",OR(AH102="4～10个交易日",AH102="11～20个交易日")),AND(AG102="趋势波段",OR(AH102="11～20个交易日",AH102="21～60个交易日",AH102="60个交易日以上"))),"匹配","周期与交易预期不匹配，请重新确认")) | AK102: =IF(A102="","",COUNTIFS(加仓管理!$A$2:$A$1001,A102,加仓管理!$G$2:$G$1001,">0")) | AL102: =IF(A102="","",SUMIFS(加仓管理!$G$2:$G$1001,加仓管理!$A$2:$A$1001,A102)) | AM102: =IF(AK102=0,"",IFERROR(LOOKUP(2,1/((加仓管理!$A$2:$A$1001=A102)*(加仓管理!$G$2:$G$1001>0)),加仓管理!$D$2:$D$1001),"")) | AN102: =IF(AK102=0,"",IFERROR(LOOKUP(2,1/((加仓管理!$A$2:$A$1001=A102)*(加仓管理!$G$2:$G$1001>0)),加仓管理!$E$2:$E$1001),"")) | AO102: =IF(OR(A102="",H102="",H102<=0),"",(E102*H102+SUMIFS(加仓管理!$H$2:$H$1001,加仓管理!$A$2:$A$1001,A102))/AP102) | AP102: =IF(OR(A102="",H102="",H102<=0),"",H102+AL102) | AQ102: =IF(A102="","",IF(M102<>"",0,IF(OR(H102="",N102=""),"",MAX((E102*H102+SUMIFS(加仓管理!$H$2:$H$1001,加仓管理!$A$2:$A$1001,A102))-MAX(N102,AN102)*AP102,0)))) | AR102: =IF(A102="","",IF(OR(E102="",H102=""),"违规：首次买入价格或股数缺失",IF(COUNTIFS(加仓管理!$A$2:$A$1001,A102,加仓管理!$R$2:$R$1001,"违规*")>0,"违规：请检查加仓管理表",IF(SUM($AQ$2:$AQ$201)>账户数据!$B$7,"预警：超过账户风险上限",IF(COUNTIFS(加仓管理!$A$2:$A$1001,A102,加仓管理!$N$2:$N$1001,">0",加仓管理!$G$2:$G$1001,"")>0,"提示：存在待执行加仓计划","通过")))))
F103: =IF(OR(C103="",D103="",E103="",N103="",C103<=0,D103<=0,E103<=N103),"",ROUNDDOWN((C103*D103)/(E103-N103)/100,0)*100) | G103: =IF(A103="","",IF(H103<>"","已开仓",IF(账户数据!$B$23="已锁仓","禁止开仓：连续亏损达到上限",IF(账户数据!$B$23="解锁信息不完整","禁止开仓：请完整填写解锁信息",IF(OR(F103="",E103="",N103="",E103<=N103,账户数据!$B$7=""),"",IF(OR(AG103="",AH103="",AI103=""),"禁止开仓：交易预期未填写完整",IF(账户数据!$B$9+F103*(E103-N103)>=账户数据!$B$7,"禁止开仓：风险额度不足",IF(AJ103="周期与交易预期不匹配，请重新确认",IF(账户数据!$B$23="接近锁仓","允许开仓（接近锁仓；周期需复核）","允许开仓（周期需复核）"),IF(账户数据!$B$23="接近锁仓","允许开仓（接近锁仓）","允许开仓"))))))))) | L103: =IF(AP103="","",AP103) | U103: =IF(OR(AO103="",J103="",AO103<=0),"",(J103-AO103)/AO103) | V103: =IF(OR(AO103="",N103="",AO103<=0),"",(AO103-N103)/AO103) | W103: =IF(OR(U103="",V103="",V103<=0),"",U103/V103) | X103: =IF(OR(K103="",L103="",AO103="",AP103=""),"",(K103-AO103)*L103-IF(O103="",0,O103)-IF(P103="",0,P103)) | Y103: =IF(OR(X103="",AO103="",L103=""),"",IF(AO103*L103+IF(O103="",0,O103)<=0,"",X103/(AO103*L103+IF(O103="",0,O103)))) | Z103: =IF(OR(AE103="",多次统计数据!$B$8=""),"",AE103-多次统计数据!$B$8) | AA103: =IF(OR(I103="",M103="",M103<I103),"",M103-I103) | AB103: =IF(OR(A103="",多次统计数据!$B$8="",多次统计数据!$B$6<=0,多次统计数据!$B$6>=1),"",1-POWER(1+多次统计数据!$B$8,-多次统计数据!$B$6/(1-多次统计数据!$B$6))) | AC103: =IF(OR(AB103="",多次统计数据!$B$9=""),"",IF(多次统计数据!$B$9<AB103,"低于上限","达到或超过上限")) | AE103: =IF(OR(X103="",C103="",C103<=0),"",X103/C103) | AJ103: =IF(OR(AG103="",AH103=""),"",IF(OR(AND(AG103="短期博反弹",OR(AH103="1～3个交易日",AH103="4～10个交易日")),AND(AG103="突破冲新高",OR(AH103="4～10个交易日",AH103="11～20个交易日")),AND(AG103="趋势波段",OR(AH103="11～20个交易日",AH103="21～60个交易日",AH103="60个交易日以上"))),"匹配","周期与交易预期不匹配，请重新确认")) | AK103: =IF(A103="","",COUNTIFS(加仓管理!$A$2:$A$1001,A103,加仓管理!$G$2:$G$1001,">0")) | AL103: =IF(A103="","",SUMIFS(加仓管理!$G$2:$G$1001,加仓管理!$A$2:$A$1001,A103)) | AM103: =IF(AK103=0,"",IFERROR(LOOKUP(2,1/((加仓管理!$A$2:$A$1001=A103)*(加仓管理!$G$2:$G$1001>0)),加仓管理!$D$2:$D$1001),"")) | AN103: =IF(AK103=0,"",IFERROR(LOOKUP(2,1/((加仓管理!$A$2:$A$1001=A103)*(加仓管理!$G$2:$G$1001>0)),加仓管理!$E$2:$E$1001),"")) | AO103: =IF(OR(A103="",H103="",H103<=0),"",(E103*H103+SUMIFS(加仓管理!$H$2:$H$1001,加仓管理!$A$2:$A$1001,A103))/AP103) | AP103: =IF(OR(A103="",H103="",H103<=0),"",H103+AL103) | AQ103: =IF(A103="","",IF(M103<>"",0,IF(OR(H103="",N103=""),"",MAX((E103*H103+SUMIFS(加仓管理!$H$2:$H$1001,加仓管理!$A$2:$A$1001,A103))-MAX(N103,AN103)*AP103,0)))) | AR103: =IF(A103="","",IF(OR(E103="",H103=""),"违规：首次买入价格或股数缺失",IF(COUNTIFS(加仓管理!$A$2:$A$1001,A103,加仓管理!$R$2:$R$1001,"违规*")>0,"违规：请检查加仓管理表",IF(SUM($AQ$2:$AQ$201)>账户数据!$B$7,"预警：超过账户风险上限",IF(COUNTIFS(加仓管理!$A$2:$A$1001,A103,加仓管理!$N$2:$N$1001,">0",加仓管理!$G$2:$G$1001,"")>0,"提示：存在待执行加仓计划","通过")))))
F104: =IF(OR(C104="",D104="",E104="",N104="",C104<=0,D104<=0,E104<=N104),"",ROUNDDOWN((C104*D104)/(E104-N104)/100,0)*100) | G104: =IF(A104="","",IF(H104<>"","已开仓",IF(账户数据!$B$23="已锁仓","禁止开仓：连续亏损达到上限",IF(账户数据!$B$23="解锁信息不完整","禁止开仓：请完整填写解锁信息",IF(OR(F104="",E104="",N104="",E104<=N104,账户数据!$B$7=""),"",IF(OR(AG104="",AH104="",AI104=""),"禁止开仓：交易预期未填写完整",IF(账户数据!$B$9+F104*(E104-N104)>=账户数据!$B$7,"禁止开仓：风险额度不足",IF(AJ104="周期与交易预期不匹配，请重新确认",IF(账户数据!$B$23="接近锁仓","允许开仓（接近锁仓；周期需复核）","允许开仓（周期需复核）"),IF(账户数据!$B$23="接近锁仓","允许开仓（接近锁仓）","允许开仓"))))))))) | L104: =IF(AP104="","",AP104) | U104: =IF(OR(AO104="",J104="",AO104<=0),"",(J104-AO104)/AO104) | V104: =IF(OR(AO104="",N104="",AO104<=0),"",(AO104-N104)/AO104) | W104: =IF(OR(U104="",V104="",V104<=0),"",U104/V104) | X104: =IF(OR(K104="",L104="",AO104="",AP104=""),"",(K104-AO104)*L104-IF(O104="",0,O104)-IF(P104="",0,P104)) | Y104: =IF(OR(X104="",AO104="",L104=""),"",IF(AO104*L104+IF(O104="",0,O104)<=0,"",X104/(AO104*L104+IF(O104="",0,O104)))) | Z104: =IF(OR(AE104="",多次统计数据!$B$8=""),"",AE104-多次统计数据!$B$8) | AA104: =IF(OR(I104="",M104="",M104<I104),"",M104-I104) | AB104: =IF(OR(A104="",多次统计数据!$B$8="",多次统计数据!$B$6<=0,多次统计数据!$B$6>=1),"",1-POWER(1+多次统计数据!$B$8,-多次统计数据!$B$6/(1-多次统计数据!$B$6))) | AC104: =IF(OR(AB104="",多次统计数据!$B$9=""),"",IF(多次统计数据!$B$9<AB104,"低于上限","达到或超过上限")) | AE104: =IF(OR(X104="",C104="",C104<=0),"",X104/C104) | AJ104: =IF(OR(AG104="",AH104=""),"",IF(OR(AND(AG104="短期博反弹",OR(AH104="1～3个交易日",AH104="4～10个交易日")),AND(AG104="突破冲新高",OR(AH104="4～10个交易日",AH104="11～20个交易日")),AND(AG104="趋势波段",OR(AH104="11～20个交易日",AH104="21～60个交易日",AH104="60个交易日以上"))),"匹配","周期与交易预期不匹配，请重新确认")) | AK104: =IF(A104="","",COUNTIFS(加仓管理!$A$2:$A$1001,A104,加仓管理!$G$2:$G$1001,">0")) | AL104: =IF(A104="","",SUMIFS(加仓管理!$G$2:$G$1001,加仓管理!$A$2:$A$1001,A104)) | AM104: =IF(AK104=0,"",IFERROR(LOOKUP(2,1/((加仓管理!$A$2:$A$1001=A104)*(加仓管理!$G$2:$G$1001>0)),加仓管理!$D$2:$D$1001),"")) | AN104: =IF(AK104=0,"",IFERROR(LOOKUP(2,1/((加仓管理!$A$2:$A$1001=A104)*(加仓管理!$G$2:$G$1001>0)),加仓管理!$E$2:$E$1001),"")) | AO104: =IF(OR(A104="",H104="",H104<=0),"",(E104*H104+SUMIFS(加仓管理!$H$2:$H$1001,加仓管理!$A$2:$A$1001,A104))/AP104) | AP104: =IF(OR(A104="",H104="",H104<=0),"",H104+AL104) | AQ104: =IF(A104="","",IF(M104<>"",0,IF(OR(H104="",N104=""),"",MAX((E104*H104+SUMIFS(加仓管理!$H$2:$H$1001,加仓管理!$A$2:$A$1001,A104))-MAX(N104,AN104)*AP104,0)))) | AR104: =IF(A104="","",IF(OR(E104="",H104=""),"违规：首次买入价格或股数缺失",IF(COUNTIFS(加仓管理!$A$2:$A$1001,A104,加仓管理!$R$2:$R$1001,"违规*")>0,"违规：请检查加仓管理表",IF(SUM($AQ$2:$AQ$201)>账户数据!$B$7,"预警：超过账户风险上限",IF(COUNTIFS(加仓管理!$A$2:$A$1001,A104,加仓管理!$N$2:$N$1001,">0",加仓管理!$G$2:$G$1001,"")>0,"提示：存在待执行加仓计划","通过")))))
F105: =IF(OR(C105="",D105="",E105="",N105="",C105<=0,D105<=0,E105<=N105),"",ROUNDDOWN((C105*D105)/(E105-N105)/100,0)*100) | G105: =IF(A105="","",IF(H105<>"","已开仓",IF(账户数据!$B$23="已锁仓","禁止开仓：连续亏损达到上限",IF(账户数据!$B$23="解锁信息不完整","禁止开仓：请完整填写解锁信息",IF(OR(F105="",E105="",N105="",E105<=N105,账户数据!$B$7=""),"",IF(OR(AG105="",AH105="",AI105=""),"禁止开仓：交易预期未填写完整",IF(账户数据!$B$9+F105*(E105-N105)>=账户数据!$B$7,"禁止开仓：风险额度不足",IF(AJ105="周期与交易预期不匹配，请重新确认",IF(账户数据!$B$23="接近锁仓","允许开仓（接近锁仓；周期需复核）","允许开仓（周期需复核）"),IF(账户数据!$B$23="接近锁仓","允许开仓（接近锁仓）","允许开仓"))))))))) | L105: =IF(AP105="","",AP105) | U105: =IF(OR(AO105="",J105="",AO105<=0),"",(J105-AO105)/AO105) | V105: =IF(OR(AO105="",N105="",AO105<=0),"",(AO105-N105)/AO105) | W105: =IF(OR(U105="",V105="",V105<=0),"",U105/V105) | X105: =IF(OR(K105="",L105="",AO105="",AP105=""),"",(K105-AO105)*L105-IF(O105="",0,O105)-IF(P105="",0,P105)) | Y105: =IF(OR(X105="",AO105="",L105=""),"",IF(AO105*L105+IF(O105="",0,O105)<=0,"",X105/(AO105*L105+IF(O105="",0,O105)))) | Z105: =IF(OR(AE105="",多次统计数据!$B$8=""),"",AE105-多次统计数据!$B$8) | AA105: =IF(OR(I105="",M105="",M105<I105),"",M105-I105) | AB105: =IF(OR(A105="",多次统计数据!$B$8="",多次统计数据!$B$6<=0,多次统计数据!$B$6>=1),"",1-POWER(1+多次统计数据!$B$8,-多次统计数据!$B$6/(1-多次统计数据!$B$6))) | AC105: =IF(OR(AB105="",多次统计数据!$B$9=""),"",IF(多次统计数据!$B$9<AB105,"低于上限","达到或超过上限")) | AE105: =IF(OR(X105="",C105="",C105<=0),"",X105/C105) | AJ105: =IF(OR(AG105="",AH105=""),"",IF(OR(AND(AG105="短期博反弹",OR(AH105="1～3个交易日",AH105="4～10个交易日")),AND(AG105="突破冲新高",OR(AH105="4～10个交易日",AH105="11～20个交易日")),AND(AG105="趋势波段",OR(AH105="11～20个交易日",AH105="21～60个交易日",AH105="60个交易日以上"))),"匹配","周期与交易预期不匹配，请重新确认")) | AK105: =IF(A105="","",COUNTIFS(加仓管理!$A$2:$A$1001,A105,加仓管理!$G$2:$G$1001,">0")) | AL105: =IF(A105="","",SUMIFS(加仓管理!$G$2:$G$1001,加仓管理!$A$2:$A$1001,A105)) | AM105: =IF(AK105=0,"",IFERROR(LOOKUP(2,1/((加仓管理!$A$2:$A$1001=A105)*(加仓管理!$G$2:$G$1001>0)),加仓管理!$D$2:$D$1001),"")) | AN105: =IF(AK105=0,"",IFERROR(LOOKUP(2,1/((加仓管理!$A$2:$A$1001=A105)*(加仓管理!$G$2:$G$1001>0)),加仓管理!$E$2:$E$1001),"")) | AO105: =IF(OR(A105="",H105="",H105<=0),"",(E105*H105+SUMIFS(加仓管理!$H$2:$H$1001,加仓管理!$A$2:$A$1001,A105))/AP105) | AP105: =IF(OR(A105="",H105="",H105<=0),"",H105+AL105) | AQ105: =IF(A105="","",IF(M105<>"",0,IF(OR(H105="",N105=""),"",MAX((E105*H105+SUMIFS(加仓管理!$H$2:$H$1001,加仓管理!$A$2:$A$1001,A105))-MAX(N105,AN105)*AP105,0)))) | AR105: =IF(A105="","",IF(OR(E105="",H105=""),"违规：首次买入价格或股数缺失",IF(COUNTIFS(加仓管理!$A$2:$A$1001,A105,加仓管理!$R$2:$R$1001,"违规*")>0,"违规：请检查加仓管理表",IF(SUM($AQ$2:$AQ$201)>账户数据!$B$7,"预警：超过账户风险上限",IF(COUNTIFS(加仓管理!$A$2:$A$1001,A105,加仓管理!$N$2:$N$1001,">0",加仓管理!$G$2:$G$1001,"")>0,"提示：存在待执行加仓计划","通过")))))
F106: =IF(OR(C106="",D106="",E106="",N106="",C106<=0,D106<=0,E106<=N106),"",ROUNDDOWN((C106*D106)/(E106-N106)/100,0)*100) | G106: =IF(A106="","",IF(H106<>"","已开仓",IF(账户数据!$B$23="已锁仓","禁止开仓：连续亏损达到上限",IF(账户数据!$B$23="解锁信息不完整","禁止开仓：请完整填写解锁信息",IF(OR(F106="",E106="",N106="",E106<=N106,账户数据!$B$7=""),"",IF(OR(AG106="",AH106="",AI106=""),"禁止开仓：交易预期未填写完整",IF(账户数据!$B$9+F106*(E106-N106)>=账户数据!$B$7,"禁止开仓：风险额度不足",IF(AJ106="周期与交易预期不匹配，请重新确认",IF(账户数据!$B$23="接近锁仓","允许开仓（接近锁仓；周期需复核）","允许开仓（周期需复核）"),IF(账户数据!$B$23="接近锁仓","允许开仓（接近锁仓）","允许开仓"))))))))) | L106: =IF(AP106="","",AP106) | U106: =IF(OR(AO106="",J106="",AO106<=0),"",(J106-AO106)/AO106) | V106: =IF(OR(AO106="",N106="",AO106<=0),"",(AO106-N106)/AO106) | W106: =IF(OR(U106="",V106="",V106<=0),"",U106/V106) | X106: =IF(OR(K106="",L106="",AO106="",AP106=""),"",(K106-AO106)*L106-IF(O106="",0,O106)-IF(P106="",0,P106)) | Y106: =IF(OR(X106="",AO106="",L106=""),"",IF(AO106*L106+IF(O106="",0,O106)<=0,"",X106/(AO106*L106+IF(O106="",0,O106)))) | Z106: =IF(OR(AE106="",多次统计数据!$B$8=""),"",AE106-多次统计数据!$B$8) | AA106: =IF(OR(I106="",M106="",M106<I106),"",M106-I106) | AB106: =IF(OR(A106="",多次统计数据!$B$8="",多次统计数据!$B$6<=0,多次统计数据!$B$6>=1),"",1-POWER(1+多次统计数据!$B$8,-多次统计数据!$B$6/(1-多次统计数据!$B$6))) | AC106: =IF(OR(AB106="",多次统计数据!$B$9=""),"",IF(多次统计数据!$B$9<AB106,"低于上限","达到或超过上限")) | AE106: =IF(OR(X106="",C106="",C106<=0),"",X106/C106) | AJ106: =IF(OR(AG106="",AH106=""),"",IF(OR(AND(AG106="短期博反弹",OR(AH106="1～3个交易日",AH106="4～10个交易日")),AND(AG106="突破冲新高",OR(AH106="4～10个交易日",AH106="11～20个交易日")),AND(AG106="趋势波段",OR(AH106="11～20个交易日",AH106="21～60个交易日",AH106="60个交易日以上"))),"匹配","周期与交易预期不匹配，请重新确认")) | AK106: =IF(A106="","",COUNTIFS(加仓管理!$A$2:$A$1001,A106,加仓管理!$G$2:$G$1001,">0")) | AL106: =IF(A106="","",SUMIFS(加仓管理!$G$2:$G$1001,加仓管理!$A$2:$A$1001,A106)) | AM106: =IF(AK106=0,"",IFERROR(LOOKUP(2,1/((加仓管理!$A$2:$A$1001=A106)*(加仓管理!$G$2:$G$1001>0)),加仓管理!$D$2:$D$1001),"")) | AN106: =IF(AK106=0,"",IFERROR(LOOKUP(2,1/((加仓管理!$A$2:$A$1001=A106)*(加仓管理!$G$2:$G$1001>0)),加仓管理!$E$2:$E$1001),"")) | AO106: =IF(OR(A106="",H106="",H106<=0),"",(E106*H106+SUMIFS(加仓管理!$H$2:$H$1001,加仓管理!$A$2:$A$1001,A106))/AP106) | AP106: =IF(OR(A106="",H106="",H106<=0),"",H106+AL106) | AQ106: =IF(A106="","",IF(M106<>"",0,IF(OR(H106="",N106=""),"",MAX((E106*H106+SUMIFS(加仓管理!$H$2:$H$1001,加仓管理!$A$2:$A$1001,A106))-MAX(N106,AN106)*AP106,0)))) | AR106: =IF(A106="","",IF(OR(E106="",H106=""),"违规：首次买入价格或股数缺失",IF(COUNTIFS(加仓管理!$A$2:$A$1001,A106,加仓管理!$R$2:$R$1001,"违规*")>0,"违规：请检查加仓管理表",IF(SUM($AQ$2:$AQ$201)>账户数据!$B$7,"预警：超过账户风险上限",IF(COUNTIFS(加仓管理!$A$2:$A$1001,A106,加仓管理!$N$2:$N$1001,">0",加仓管理!$G$2:$G$1001,"")>0,"提示：存在待执行加仓计划","通过")))))
F107: =IF(OR(C107="",D107="",E107="",N107="",C107<=0,D107<=0,E107<=N107),"",ROUNDDOWN((C107*D107)/(E107-N107)/100,0)*100) | G107: =IF(A107="","",IF(H107<>"","已开仓",IF(账户数据!$B$23="已锁仓","禁止开仓：连续亏损达到上限",IF(账户数据!$B$23="解锁信息不完整","禁止开仓：请完整填写解锁信息",IF(OR(F107="",E107="",N107="",E107<=N107,账户数据!$B$7=""),"",IF(OR(AG107="",AH107="",AI107=""),"禁止开仓：交易预期未填写完整",IF(账户数据!$B$9+F107*(E107-N107)>=账户数据!$B$7,"禁止开仓：风险额度不足",IF(AJ107="周期与交易预期不匹配，请重新确认",IF(账户数据!$B$23="接近锁仓","允许开仓（接近锁仓；周期需复核）","允许开仓（周期需复核）"),IF(账户数据!$B$23="接近锁仓","允许开仓（接近锁仓）","允许开仓"))))))))) | L107: =IF(AP107="","",AP107) | U107: =IF(OR(AO107="",J107="",AO107<=0),"",(J107-AO107)/AO107) | V107: =IF(OR(AO107="",N107="",AO107<=0),"",(AO107-N107)/AO107) | W107: =IF(OR(U107="",V107="",V107<=0),"",U107/V107) | X107: =IF(OR(K107="",L107="",AO107="",AP107=""),"",(K107-AO107)*L107-IF(O107="",0,O107)-IF(P107="",0,P107)) | Y107: =IF(OR(X107="",AO107="",L107=""),"",IF(AO107*L107+IF(O107="",0,O107)<=0,"",X107/(AO107*L107+IF(O107="",0,O107)))) | Z107: =IF(OR(AE107="",多次统计数据!$B$8=""),"",AE107-多次统计数据!$B$8) | AA107: =IF(OR(I107="",M107="",M107<I107),"",M107-I107) | AB107: =IF(OR(A107="",多次统计数据!$B$8="",多次统计数据!$B$6<=0,多次统计数据!$B$6>=1),"",1-POWER(1+多次统计数据!$B$8,-多次统计数据!$B$6/(1-多次统计数据!$B$6))) | AC107: =IF(OR(AB107="",多次统计数据!$B$9=""),"",IF(多次统计数据!$B$9<AB107,"低于上限","达到或超过上限")) | AE107: =IF(OR(X107="",C107="",C107<=0),"",X107/C107) | AJ107: =IF(OR(AG107="",AH107=""),"",IF(OR(AND(AG107="短期博反弹",OR(AH107="1～3个交易日",AH107="4～10个交易日")),AND(AG107="突破冲新高",OR(AH107="4～10个交易日",AH107="11～20个交易日")),AND(AG107="趋势波段",OR(AH107="11～20个交易日",AH107="21～60个交易日",AH107="60个交易日以上"))),"匹配","周期与交易预期不匹配，请重新确认")) | AK107: =IF(A107="","",COUNTIFS(加仓管理!$A$2:$A$1001,A107,加仓管理!$G$2:$G$1001,">0")) | AL107: =IF(A107="","",SUMIFS(加仓管理!$G$2:$G$1001,加仓管理!$A$2:$A$1001,A107)) | AM107: =IF(AK107=0,"",IFERROR(LOOKUP(2,1/((加仓管理!$A$2:$A$1001=A107)*(加仓管理!$G$2:$G$1001>0)),加仓管理!$D$2:$D$1001),"")) | AN107: =IF(AK107=0,"",IFERROR(LOOKUP(2,1/((加仓管理!$A$2:$A$1001=A107)*(加仓管理!$G$2:$G$1001>0)),加仓管理!$E$2:$E$1001),"")) | AO107: =IF(OR(A107="",H107="",H107<=0),"",(E107*H107+SUMIFS(加仓管理!$H$2:$H$1001,加仓管理!$A$2:$A$1001,A107))/AP107) | AP107: =IF(OR(A107="",H107="",H107<=0),"",H107+AL107) | AQ107: =IF(A107="","",IF(M107<>"",0,IF(OR(H107="",N107=""),"",MAX((E107*H107+SUMIFS(加仓管理!$H$2:$H$1001,加仓管理!$A$2:$A$1001,A107))-MAX(N107,AN107)*AP107,0)))) | AR107: =IF(A107="","",IF(OR(E107="",H107=""),"违规：首次买入价格或股数缺失",IF(COUNTIFS(加仓管理!$A$2:$A$1001,A107,加仓管理!$R$2:$R$1001,"违规*")>0,"违规：请检查加仓管理表",IF(SUM($AQ$2:$AQ$201)>账户数据!$B$7,"预警：超过账户风险上限",IF(COUNTIFS(加仓管理!$A$2:$A$1001,A107,加仓管理!$N$2:$N$1001,">0",加仓管理!$G$2:$G$1001,"")>0,"提示：存在待执行加仓计划","通过")))))
F108: =IF(OR(C108="",D108="",E108="",N108="",C108<=0,D108<=0,E108<=N108),"",ROUNDDOWN((C108*D108)/(E108-N108)/100,0)*100) | G108: =IF(A108="","",IF(H108<>"","已开仓",IF(账户数据!$B$23="已锁仓","禁止开仓：连续亏损达到上限",IF(账户数据!$B$23="解锁信息不完整","禁止开仓：请完整填写解锁信息",IF(OR(F108="",E108="",N108="",E108<=N108,账户数据!$B$7=""),"",IF(OR(AG108="",AH108="",AI108=""),"禁止开仓：交易预期未填写完整",IF(账户数据!$B$9+F108*(E108-N108)>=账户数据!$B$7,"禁止开仓：风险额度不足",IF(AJ108="周期与交易预期不匹配，请重新确认",IF(账户数据!$B$23="接近锁仓","允许开仓（接近锁仓；周期需复核）","允许开仓（周期需复核）"),IF(账户数据!$B$23="接近锁仓","允许开仓（接近锁仓）","允许开仓"))))))))) | L108: =IF(AP108="","",AP108) | U108: =IF(OR(AO108="",J108="",AO108<=0),"",(J108-AO108)/AO108) | V108: =IF(OR(AO108="",N108="",AO108<=0),"",(AO108-N108)/AO108) | W108: =IF(OR(U108="",V108="",V108<=0),"",U108/V108) | X108: =IF(OR(K108="",L108="",AO108="",AP108=""),"",(K108-AO108)*L108-IF(O108="",0,O108)-IF(P108="",0,P108)) | Y108: =IF(OR(X108="",AO108="",L108=""),"",IF(AO108*L108+IF(O108="",0,O108)<=0,"",X108/(AO108*L108+IF(O108="",0,O108)))) | Z108: =IF(OR(AE108="",多次统计数据!$B$8=""),"",AE108-多次统计数据!$B$8) | AA108: =IF(OR(I108="",M108="",M108<I108),"",M108-I108) | AB108: =IF(OR(A108="",多次统计数据!$B$8="",多次统计数据!$B$6<=0,多次统计数据!$B$6>=1),"",1-POWER(1+多次统计数据!$B$8,-多次统计数据!$B$6/(1-多次统计数据!$B$6))) | AC108: =IF(OR(AB108="",多次统计数据!$B$9=""),"",IF(多次统计数据!$B$9<AB108,"低于上限","达到或超过上限")) | AE108: =IF(OR(X108="",C108="",C108<=0),"",X108/C108) | AJ108: =IF(OR(AG108="",AH108=""),"",IF(OR(AND(AG108="短期博反弹",OR(AH108="1～3个交易日",AH108="4～10个交易日")),AND(AG108="突破冲新高",OR(AH108="4～10个交易日",AH108="11～20个交易日")),AND(AG108="趋势波段",OR(AH108="11～20个交易日",AH108="21～60个交易日",AH108="60个交易日以上"))),"匹配","周期与交易预期不匹配，请重新确认")) | AK108: =IF(A108="","",COUNTIFS(加仓管理!$A$2:$A$1001,A108,加仓管理!$G$2:$G$1001,">0")) | AL108: =IF(A108="","",SUMIFS(加仓管理!$G$2:$G$1001,加仓管理!$A$2:$A$1001,A108)) | AM108: =IF(AK108=0,"",IFERROR(LOOKUP(2,1/((加仓管理!$A$2:$A$1001=A108)*(加仓管理!$G$2:$G$1001>0)),加仓管理!$D$2:$D$1001),"")) | AN108: =IF(AK108=0,"",IFERROR(LOOKUP(2,1/((加仓管理!$A$2:$A$1001=A108)*(加仓管理!$G$2:$G$1001>0)),加仓管理!$E$2:$E$1001),"")) | AO108: =IF(OR(A108="",H108="",H108<=0),"",(E108*H108+SUMIFS(加仓管理!$H$2:$H$1001,加仓管理!$A$2:$A$1001,A108))/AP108) | AP108: =IF(OR(A108="",H108="",H108<=0),"",H108+AL108) | AQ108: =IF(A108="","",IF(M108<>"",0,IF(OR(H108="",N108=""),"",MAX((E108*H108+SUMIFS(加仓管理!$H$2:$H$1001,加仓管理!$A$2:$A$1001,A108))-MAX(N108,AN108)*AP108,0)))) | AR108: =IF(A108="","",IF(OR(E108="",H108=""),"违规：首次买入价格或股数缺失",IF(COUNTIFS(加仓管理!$A$2:$A$1001,A108,加仓管理!$R$2:$R$1001,"违规*")>0,"违规：请检查加仓管理表",IF(SUM($AQ$2:$AQ$201)>账户数据!$B$7,"预警：超过账户风险上限",IF(COUNTIFS(加仓管理!$A$2:$A$1001,A108,加仓管理!$N$2:$N$1001,">0",加仓管理!$G$2:$G$1001,"")>0,"提示：存在待执行加仓计划","通过")))))
F109: =IF(OR(C109="",D109="",E109="",N109="",C109<=0,D109<=0,E109<=N109),"",ROUNDDOWN((C109*D109)/(E109-N109)/100,0)*100) | G109: =IF(A109="","",IF(H109<>"","已开仓",IF(账户数据!$B$23="已锁仓","禁止开仓：连续亏损达到上限",IF(账户数据!$B$23="解锁信息不完整","禁止开仓：请完整填写解锁信息",IF(OR(F109="",E109="",N109="",E109<=N109,账户数据!$B$7=""),"",IF(OR(AG109="",AH109="",AI109=""),"禁止开仓：交易预期未填写完整",IF(账户数据!$B$9+F109*(E109-N109)>=账户数据!$B$7,"禁止开仓：风险额度不足",IF(AJ109="周期与交易预期不匹配，请重新确认",IF(账户数据!$B$23="接近锁仓","允许开仓（接近锁仓；周期需复核）","允许开仓（周期需复核）"),IF(账户数据!$B$23="接近锁仓","允许开仓（接近锁仓）","允许开仓"))))))))) | L109: =IF(AP109="","",AP109) | U109: =IF(OR(AO109="",J109="",AO109<=0),"",(J109-AO109)/AO109) | V109: =IF(OR(AO109="",N109="",AO109<=0),"",(AO109-N109)/AO109) | W109: =IF(OR(U109="",V109="",V109<=0),"",U109/V109) | X109: =IF(OR(K109="",L109="",AO109="",AP109=""),"",(K109-AO109)*L109-IF(O109="",0,O109)-IF(P109="",0,P109)) | Y109: =IF(OR(X109="",AO109="",L109=""),"",IF(AO109*L109+IF(O109="",0,O109)<=0,"",X109/(AO109*L109+IF(O109="",0,O109)))) | Z109: =IF(OR(AE109="",多次统计数据!$B$8=""),"",AE109-多次统计数据!$B$8) | AA109: =IF(OR(I109="",M109="",M109<I109),"",M109-I109) | AB109: =IF(OR(A109="",多次统计数据!$B$8="",多次统计数据!$B$6<=0,多次统计数据!$B$6>=1),"",1-POWER(1+多次统计数据!$B$8,-多次统计数据!$B$6/(1-多次统计数据!$B$6))) | AC109: =IF(OR(AB109="",多次统计数据!$B$9=""),"",IF(多次统计数据!$B$9<AB109,"低于上限","达到或超过上限")) | AE109: =IF(OR(X109="",C109="",C109<=0),"",X109/C109) | AJ109: =IF(OR(AG109="",AH109=""),"",IF(OR(AND(AG109="短期博反弹",OR(AH109="1～3个交易日",AH109="4～10个交易日")),AND(AG109="突破冲新高",OR(AH109="4～10个交易日",AH109="11～20个交易日")),AND(AG109="趋势波段",OR(AH109="11～20个交易日",AH109="21～60个交易日",AH109="60个交易日以上"))),"匹配","周期与交易预期不匹配，请重新确认")) | AK109: =IF(A109="","",COUNTIFS(加仓管理!$A$2:$A$1001,A109,加仓管理!$G$2:$G$1001,">0")) | AL109: =IF(A109="","",SUMIFS(加仓管理!$G$2:$G$1001,加仓管理!$A$2:$A$1001,A109)) | AM109: =IF(AK109=0,"",IFERROR(LOOKUP(2,1/((加仓管理!$A$2:$A$1001=A109)*(加仓管理!$G$2:$G$1001>0)),加仓管理!$D$2:$D$1001),"")) | AN109: =IF(AK109=0,"",IFERROR(LOOKUP(2,1/((加仓管理!$A$2:$A$1001=A109)*(加仓管理!$G$2:$G$1001>0)),加仓管理!$E$2:$E$1001),"")) | AO109: =IF(OR(A109="",H109="",H109<=0),"",(E109*H109+SUMIFS(加仓管理!$H$2:$H$1001,加仓管理!$A$2:$A$1001,A109))/AP109) | AP109: =IF(OR(A109="",H109="",H109<=0),"",H109+AL109) | AQ109: =IF(A109="","",IF(M109<>"",0,IF(OR(H109="",N109=""),"",MAX((E109*H109+SUMIFS(加仓管理!$H$2:$H$1001,加仓管理!$A$2:$A$1001,A109))-MAX(N109,AN109)*AP109,0)))) | AR109: =IF(A109="","",IF(OR(E109="",H109=""),"违规：首次买入价格或股数缺失",IF(COUNTIFS(加仓管理!$A$2:$A$1001,A109,加仓管理!$R$2:$R$1001,"违规*")>0,"违规：请检查加仓管理表",IF(SUM($AQ$2:$AQ$201)>账户数据!$B$7,"预警：超过账户风险上限",IF(COUNTIFS(加仓管理!$A$2:$A$1001,A109,加仓管理!$N$2:$N$1001,">0",加仓管理!$G$2:$G$1001,"")>0,"提示：存在待执行加仓计划","通过")))))
F110: =IF(OR(C110="",D110="",E110="",N110="",C110<=0,D110<=0,E110<=N110),"",ROUNDDOWN((C110*D110)/(E110-N110)/100,0)*100) | G110: =IF(A110="","",IF(H110<>"","已开仓",IF(账户数据!$B$23="已锁仓","禁止开仓：连续亏损达到上限",IF(账户数据!$B$23="解锁信息不完整","禁止开仓：请完整填写解锁信息",IF(OR(F110="",E110="",N110="",E110<=N110,账户数据!$B$7=""),"",IF(OR(AG110="",AH110="",AI110=""),"禁止开仓：交易预期未填写完整",IF(账户数据!$B$9+F110*(E110-N110)>=账户数据!$B$7,"禁止开仓：风险额度不足",IF(AJ110="周期与交易预期不匹配，请重新确认",IF(账户数据!$B$23="接近锁仓","允许开仓（接近锁仓；周期需复核）","允许开仓（周期需复核）"),IF(账户数据!$B$23="接近锁仓","允许开仓（接近锁仓）","允许开仓"))))))))) | L110: =IF(AP110="","",AP110) | U110: =IF(OR(AO110="",J110="",AO110<=0),"",(J110-AO110)/AO110) | V110: =IF(OR(AO110="",N110="",AO110<=0),"",(AO110-N110)/AO110) | W110: =IF(OR(U110="",V110="",V110<=0),"",U110/V110) | X110: =IF(OR(K110="",L110="",AO110="",AP110=""),"",(K110-AO110)*L110-IF(O110="",0,O110)-IF(P110="",0,P110)) | Y110: =IF(OR(X110="",AO110="",L110=""),"",IF(AO110*L110+IF(O110="",0,O110)<=0,"",X110/(AO110*L110+IF(O110="",0,O110)))) | Z110: =IF(OR(AE110="",多次统计数据!$B$8=""),"",AE110-多次统计数据!$B$8) | AA110: =IF(OR(I110="",M110="",M110<I110),"",M110-I110) | AB110: =IF(OR(A110="",多次统计数据!$B$8="",多次统计数据!$B$6<=0,多次统计数据!$B$6>=1),"",1-POWER(1+多次统计数据!$B$8,-多次统计数据!$B$6/(1-多次统计数据!$B$6))) | AC110: =IF(OR(AB110="",多次统计数据!$B$9=""),"",IF(多次统计数据!$B$9<AB110,"低于上限","达到或超过上限")) | AE110: =IF(OR(X110="",C110="",C110<=0),"",X110/C110) | AJ110: =IF(OR(AG110="",AH110=""),"",IF(OR(AND(AG110="短期博反弹",OR(AH110="1～3个交易日",AH110="4～10个交易日")),AND(AG110="突破冲新高",OR(AH110="4～10个交易日",AH110="11～20个交易日")),AND(AG110="趋势波段",OR(AH110="11～20个交易日",AH110="21～60个交易日",AH110="60个交易日以上"))),"匹配","周期与交易预期不匹配，请重新确认")) | AK110: =IF(A110="","",COUNTIFS(加仓管理!$A$2:$A$1001,A110,加仓管理!$G$2:$G$1001,">0")) | AL110: =IF(A110="","",SUMIFS(加仓管理!$G$2:$G$1001,加仓管理!$A$2:$A$1001,A110)) | AM110: =IF(AK110=0,"",IFERROR(LOOKUP(2,1/((加仓管理!$A$2:$A$1001=A110)*(加仓管理!$G$2:$G$1001>0)),加仓管理!$D$2:$D$1001),"")) | AN110: =IF(AK110=0,"",IFERROR(LOOKUP(2,1/((加仓管理!$A$2:$A$1001=A110)*(加仓管理!$G$2:$G$1001>0)),加仓管理!$E$2:$E$1001),"")) | AO110: =IF(OR(A110="",H110="",H110<=0),"",(E110*H110+SUMIFS(加仓管理!$H$2:$H$1001,加仓管理!$A$2:$A$1001,A110))/AP110) | AP110: =IF(OR(A110="",H110="",H110<=0),"",H110+AL110) | AQ110: =IF(A110="","",IF(M110<>"",0,IF(OR(H110="",N110=""),"",MAX((E110*H110+SUMIFS(加仓管理!$H$2:$H$1001,加仓管理!$A$2:$A$1001,A110))-MAX(N110,AN110)*AP110,0)))) | AR110: =IF(A110="","",IF(OR(E110="",H110=""),"违规：首次买入价格或股数缺失",IF(COUNTIFS(加仓管理!$A$2:$A$1001,A110,加仓管理!$R$2:$R$1001,"违规*")>0,"违规：请检查加仓管理表",IF(SUM($AQ$2:$AQ$201)>账户数据!$B$7,"预警：超过账户风险上限",IF(COUNTIFS(加仓管理!$A$2:$A$1001,A110,加仓管理!$N$2:$N$1001,">0",加仓管理!$G$2:$G$1001,"")>0,"提示：存在待执行加仓计划","通过")))))
F111: =IF(OR(C111="",D111="",E111="",N111="",C111<=0,D111<=0,E111<=N111),"",ROUNDDOWN((C111*D111)/(E111-N111)/100,0)*100) | G111: =IF(A111="","",IF(H111<>"","已开仓",IF(账户数据!$B$23="已锁仓","禁止开仓：连续亏损达到上限",IF(账户数据!$B$23="解锁信息不完整","禁止开仓：请完整填写解锁信息",IF(OR(F111="",E111="",N111="",E111<=N111,账户数据!$B$7=""),"",IF(OR(AG111="",AH111="",AI111=""),"禁止开仓：交易预期未填写完整",IF(账户数据!$B$9+F111*(E111-N111)>=账户数据!$B$7,"禁止开仓：风险额度不足",IF(AJ111="周期与交易预期不匹配，请重新确认",IF(账户数据!$B$23="接近锁仓","允许开仓（接近锁仓；周期需复核）","允许开仓（周期需复核）"),IF(账户数据!$B$23="接近锁仓","允许开仓（接近锁仓）","允许开仓"))))))))) | L111: =IF(AP111="","",AP111) | U111: =IF(OR(AO111="",J111="",AO111<=0),"",(J111-AO111)/AO111) | V111: =IF(OR(AO111="",N111="",AO111<=0),"",(AO111-N111)/AO111) | W111: =IF(OR(U111="",V111="",V111<=0),"",U111/V111) | X111: =IF(OR(K111="",L111="",AO111="",AP111=""),"",(K111-AO111)*L111-IF(O111="",0,O111)-IF(P111="",0,P111)) | Y111: =IF(OR(X111="",AO111="",L111=""),"",IF(AO111*L111+IF(O111="",0,O111)<=0,"",X111/(AO111*L111+IF(O111="",0,O111)))) | Z111: =IF(OR(AE111="",多次统计数据!$B$8=""),"",AE111-多次统计数据!$B$8) | AA111: =IF(OR(I111="",M111="",M111<I111),"",M111-I111) | AB111: =IF(OR(A111="",多次统计数据!$B$8="",多次统计数据!$B$6<=0,多次统计数据!$B$6>=1),"",1-POWER(1+多次统计数据!$B$8,-多次统计数据!$B$6/(1-多次统计数据!$B$6))) | AC111: =IF(OR(AB111="",多次统计数据!$B$9=""),"",IF(多次统计数据!$B$9<AB111,"低于上限","达到或超过上限")) | AE111: =IF(OR(X111="",C111="",C111<=0),"",X111/C111) | AJ111: =IF(OR(AG111="",AH111=""),"",IF(OR(AND(AG111="短期博反弹",OR(AH111="1～3个交易日",AH111="4～10个交易日")),AND(AG111="突破冲新高",OR(AH111="4～10个交易日",AH111="11～20个交易日")),AND(AG111="趋势波段",OR(AH111="11～20个交易日",AH111="21～60个交易日",AH111="60个交易日以上"))),"匹配","周期与交易预期不匹配，请重新确认")) | AK111: =IF(A111="","",COUNTIFS(加仓管理!$A$2:$A$1001,A111,加仓管理!$G$2:$G$1001,">0")) | AL111: =IF(A111="","",SUMIFS(加仓管理!$G$2:$G$1001,加仓管理!$A$2:$A$1001,A111)) | AM111: =IF(AK111=0,"",IFERROR(LOOKUP(2,1/((加仓管理!$A$2:$A$1001=A111)*(加仓管理!$G$2:$G$1001>0)),加仓管理!$D$2:$D$1001),"")) | AN111: =IF(AK111=0,"",IFERROR(LOOKUP(2,1/((加仓管理!$A$2:$A$1001=A111)*(加仓管理!$G$2:$G$1001>0)),加仓管理!$E$2:$E$1001),"")) | AO111: =IF(OR(A111="",H111="",H111<=0),"",(E111*H111+SUMIFS(加仓管理!$H$2:$H$1001,加仓管理!$A$2:$A$1001,A111))/AP111) | AP111: =IF(OR(A111="",H111="",H111<=0),"",H111+AL111) | AQ111: =IF(A111="","",IF(M111<>"",0,IF(OR(H111="",N111=""),"",MAX((E111*H111+SUMIFS(加仓管理!$H$2:$H$1001,加仓管理!$A$2:$A$1001,A111))-MAX(N111,AN111)*AP111,0)))) | AR111: =IF(A111="","",IF(OR(E111="",H111=""),"违规：首次买入价格或股数缺失",IF(COUNTIFS(加仓管理!$A$2:$A$1001,A111,加仓管理!$R$2:$R$1001,"违规*")>0,"违规：请检查加仓管理表",IF(SUM($AQ$2:$AQ$201)>账户数据!$B$7,"预警：超过账户风险上限",IF(COUNTIFS(加仓管理!$A$2:$A$1001,A111,加仓管理!$N$2:$N$1001,">0",加仓管理!$G$2:$G$1001,"")>0,"提示：存在待执行加仓计划","通过")))))
F112: =IF(OR(C112="",D112="",E112="",N112="",C112<=0,D112<=0,E112<=N112),"",ROUNDDOWN((C112*D112)/(E112-N112)/100,0)*100) | G112: =IF(A112="","",IF(H112<>"","已开仓",IF(账户数据!$B$23="已锁仓","禁止开仓：连续亏损达到上限",IF(账户数据!$B$23="解锁信息不完整","禁止开仓：请完整填写解锁信息",IF(OR(F112="",E112="",N112="",E112<=N112,账户数据!$B$7=""),"",IF(OR(AG112="",AH112="",AI112=""),"禁止开仓：交易预期未填写完整",IF(账户数据!$B$9+F112*(E112-N112)>=账户数据!$B$7,"禁止开仓：风险额度不足",IF(AJ112="周期与交易预期不匹配，请重新确认",IF(账户数据!$B$23="接近锁仓","允许开仓（接近锁仓；周期需复核）","允许开仓（周期需复核）"),IF(账户数据!$B$23="接近锁仓","允许开仓（接近锁仓）","允许开仓"))))))))) | L112: =IF(AP112="","",AP112) | U112: =IF(OR(AO112="",J112="",AO112<=0),"",(J112-AO112)/AO112) | V112: =IF(OR(AO112="",N112="",AO112<=0),"",(AO112-N112)/AO112) | W112: =IF(OR(U112="",V112="",V112<=0),"",U112/V112) | X112: =IF(OR(K112="",L112="",AO112="",AP112=""),"",(K112-AO112)*L112-IF(O112="",0,O112)-IF(P112="",0,P112)) | Y112: =IF(OR(X112="",AO112="",L112=""),"",IF(AO112*L112+IF(O112="",0,O112)<=0,"",X112/(AO112*L112+IF(O112="",0,O112)))) | Z112: =IF(OR(AE112="",多次统计数据!$B$8=""),"",AE112-多次统计数据!$B$8) | AA112: =IF(OR(I112="",M112="",M112<I112),"",M112-I112) | AB112: =IF(OR(A112="",多次统计数据!$B$8="",多次统计数据!$B$6<=0,多次统计数据!$B$6>=1),"",1-POWER(1+多次统计数据!$B$8,-多次统计数据!$B$6/(1-多次统计数据!$B$6))) | AC112: =IF(OR(AB112="",多次统计数据!$B$9=""),"",IF(多次统计数据!$B$9<AB112,"低于上限","达到或超过上限")) | AE112: =IF(OR(X112="",C112="",C112<=0),"",X112/C112) | AJ112: =IF(OR(AG112="",AH112=""),"",IF(OR(AND(AG112="短期博反弹",OR(AH112="1～3个交易日",AH112="4～10个交易日")),AND(AG112="突破冲新高",OR(AH112="4～10个交易日",AH112="11～20个交易日")),AND(AG112="趋势波段",OR(AH112="11～20个交易日",AH112="21～60个交易日",AH112="60个交易日以上"))),"匹配","周期与交易预期不匹配，请重新确认")) | AK112: =IF(A112="","",COUNTIFS(加仓管理!$A$2:$A$1001,A112,加仓管理!$G$2:$G$1001,">0")) | AL112: =IF(A112="","",SUMIFS(加仓管理!$G$2:$G$1001,加仓管理!$A$2:$A$1001,A112)) | AM112: =IF(AK112=0,"",IFERROR(LOOKUP(2,1/((加仓管理!$A$2:$A$1001=A112)*(加仓管理!$G$2:$G$1001>0)),加仓管理!$D$2:$D$1001),"")) | AN112: =IF(AK112=0,"",IFERROR(LOOKUP(2,1/((加仓管理!$A$2:$A$1001=A112)*(加仓管理!$G$2:$G$1001>0)),加仓管理!$E$2:$E$1001),"")) | AO112: =IF(OR(A112="",H112="",H112<=0),"",(E112*H112+SUMIFS(加仓管理!$H$2:$H$1001,加仓管理!$A$2:$A$1001,A112))/AP112) | AP112: =IF(OR(A112="",H112="",H112<=0),"",H112+AL112) | AQ112: =IF(A112="","",IF(M112<>"",0,IF(OR(H112="",N112=""),"",MAX((E112*H112+SUMIFS(加仓管理!$H$2:$H$1001,加仓管理!$A$2:$A$1001,A112))-MAX(N112,AN112)*AP112,0)))) | AR112: =IF(A112="","",IF(OR(E112="",H112=""),"违规：首次买入价格或股数缺失",IF(COUNTIFS(加仓管理!$A$2:$A$1001,A112,加仓管理!$R$2:$R$1001,"违规*")>0,"违规：请检查加仓管理表",IF(SUM($AQ$2:$AQ$201)>账户数据!$B$7,"预警：超过账户风险上限",IF(COUNTIFS(加仓管理!$A$2:$A$1001,A112,加仓管理!$N$2:$N$1001,">0",加仓管理!$G$2:$G$1001,"")>0,"提示：存在待执行加仓计划","通过")))))
F113: =IF(OR(C113="",D113="",E113="",N113="",C113<=0,D113<=0,E113<=N113),"",ROUNDDOWN((C113*D113)/(E113-N113)/100,0)*100) | G113: =IF(A113="","",IF(H113<>"","已开仓",IF(账户数据!$B$23="已锁仓","禁止开仓：连续亏损达到上限",IF(账户数据!$B$23="解锁信息不完整","禁止开仓：请完整填写解锁信息",IF(OR(F113="",E113="",N113="",E113<=N113,账户数据!$B$7=""),"",IF(OR(AG113="",AH113="",AI113=""),"禁止开仓：交易预期未填写完整",IF(账户数据!$B$9+F113*(E113-N113)>=账户数据!$B$7,"禁止开仓：风险额度不足",IF(AJ113="周期与交易预期不匹配，请重新确认",IF(账户数据!$B$23="接近锁仓","允许开仓（接近锁仓；周期需复核）","允许开仓（周期需复核）"),IF(账户数据!$B$23="接近锁仓","允许开仓（接近锁仓）","允许开仓"))))))))) | L113: =IF(AP113="","",AP113) | U113: =IF(OR(AO113="",J113="",AO113<=0),"",(J113-AO113)/AO113) | V113: =IF(OR(AO113="",N113="",AO113<=0),"",(AO113-N113)/AO113) | W113: =IF(OR(U113="",V113="",V113<=0),"",U113/V113) | X113: =IF(OR(K113="",L113="",AO113="",AP113=""),"",(K113-AO113)*L113-IF(O113="",0,O113)-IF(P113="",0,P113)) | Y113: =IF(OR(X113="",AO113="",L113=""),"",IF(AO113*L113+IF(O113="",0,O113)<=0,"",X113/(AO113*L113+IF(O113="",0,O113)))) | Z113: =IF(OR(AE113="",多次统计数据!$B$8=""),"",AE113-多次统计数据!$B$8) | AA113: =IF(OR(I113="",M113="",M113<I113),"",M113-I113) | AB113: =IF(OR(A113="",多次统计数据!$B$8="",多次统计数据!$B$6<=0,多次统计数据!$B$6>=1),"",1-POWER(1+多次统计数据!$B$8,-多次统计数据!$B$6/(1-多次统计数据!$B$6))) | AC113: =IF(OR(AB113="",多次统计数据!$B$9=""),"",IF(多次统计数据!$B$9<AB113,"低于上限","达到或超过上限")) | AE113: =IF(OR(X113="",C113="",C113<=0),"",X113/C113) | AJ113: =IF(OR(AG113="",AH113=""),"",IF(OR(AND(AG113="短期博反弹",OR(AH113="1～3个交易日",AH113="4～10个交易日")),AND(AG113="突破冲新高",OR(AH113="4～10个交易日",AH113="11～20个交易日")),AND(AG113="趋势波段",OR(AH113="11～20个交易日",AH113="21～60个交易日",AH113="60个交易日以上"))),"匹配","周期与交易预期不匹配，请重新确认")) | AK113: =IF(A113="","",COUNTIFS(加仓管理!$A$2:$A$1001,A113,加仓管理!$G$2:$G$1001,">0")) | AL113: =IF(A113="","",SUMIFS(加仓管理!$G$2:$G$1001,加仓管理!$A$2:$A$1001,A113)) | AM113: =IF(AK113=0,"",IFERROR(LOOKUP(2,1/((加仓管理!$A$2:$A$1001=A113)*(加仓管理!$G$2:$G$1001>0)),加仓管理!$D$2:$D$1001),"")) | AN113: =IF(AK113=0,"",IFERROR(LOOKUP(2,1/((加仓管理!$A$2:$A$1001=A113)*(加仓管理!$G$2:$G$1001>0)),加仓管理!$E$2:$E$1001),"")) | AO113: =IF(OR(A113="",H113="",H113<=0),"",(E113*H113+SUMIFS(加仓管理!$H$2:$H$1001,加仓管理!$A$2:$A$1001,A113))/AP113) | AP113: =IF(OR(A113="",H113="",H113<=0),"",H113+AL113) | AQ113: =IF(A113="","",IF(M113<>"",0,IF(OR(H113="",N113=""),"",MAX((E113*H113+SUMIFS(加仓管理!$H$2:$H$1001,加仓管理!$A$2:$A$1001,A113))-MAX(N113,AN113)*AP113,0)))) | AR113: =IF(A113="","",IF(OR(E113="",H113=""),"违规：首次买入价格或股数缺失",IF(COUNTIFS(加仓管理!$A$2:$A$1001,A113,加仓管理!$R$2:$R$1001,"违规*")>0,"违规：请检查加仓管理表",IF(SUM($AQ$2:$AQ$201)>账户数据!$B$7,"预警：超过账户风险上限",IF(COUNTIFS(加仓管理!$A$2:$A$1001,A113,加仓管理!$N$2:$N$1001,">0",加仓管理!$G$2:$G$1001,"")>0,"提示：存在待执行加仓计划","通过")))))
... F201: =IF(OR(C201="",D201="",E201="",N201="",C201<=0,D201<=0,E201<=N201),"",ROUNDDOWN((C201*D201)/(E201-N201)/100,0)*100) | G201: =IF(A201="","",IF(H201<>"","已开仓",IF(账户数据!$B$23="已锁仓","禁止开仓：连续亏损达到上限",IF(账户数据!$B$23="解锁信息不完整","禁止开仓：请完整填写解锁信息",IF(OR(F201="",E201="",N201="",E201<=N201,账户数据!$B$7=""),"",IF(OR(AG201="",AH201="",AI201=""),"禁止开仓：交易预期未填写完整",IF(账户数据!$B$9+F201*(E201-N201)>=账户数据!$B$7,"禁止开仓：风险额度不足",IF(AJ201="周期与交易预期不匹配，请重新确认",IF(账户数据!$B$23="接近锁仓","允许开仓（接近锁仓；周期需复核）","允许开仓（周期需复核）"),IF(账户数据!$B$23="接近锁仓","允许开仓（接近锁仓）","允许开仓"))))))))) | L201: =IF(AP201="","",AP201) | U201: =IF(OR(AO201="",J201="",AO201<=0),"",(J201-AO201)/AO201) | V201: =IF(OR(AO201="",N201="",AO201<=0),"",(AO201-N201)/AO201) | W201: =IF(OR(U201="",V201="",V201<=0),"",U201/V201) | X201: =IF(OR(K201="",L201="",AO201="",AP201=""),"",(K201-AO201)*L201-IF(O201="",0,O201)-IF(P201="",0,P201)) | Y201: =IF(OR(X201="",AO201="",L201=""),"",IF(AO201*L201+IF(O201="",0,O201)<=0,"",X201/(AO201*L201+IF(O201="",0,O201)))) | Z201: =IF(OR(AE201="",多次统计数据!$B$8=""),"",AE201-多次统计数据!$B$8) | AA201: =IF(OR(I201="",M201="",M201<I201),"",M201-I201) | AB201: =IF(OR(A201="",多次统计数据!$B$8="",多次统计数据!$B$6<=0,多次统计数据!$B$6>=1),"",1-POWER(1+多次统计数据!$B$8,-多次统计数据!$B$6/(1-多次统计数据!$B$6))) | AC201: =IF(OR(AB201="",多次统计数据!$B$9=""),"",IF(多次统计数据!$B$9<AB201,"低于上限","达到或超过上限")) | AE201: =IF(OR(X201="",C201="",C201<=0),"",X201/C201) | AJ201: =IF(OR(AG201="",AH201=""),"",IF(OR(AND(AG201="短期博反弹",OR(AH201="1～3个交易日",AH201="4～10个交易日")),AND(AG201="突破冲新高",OR(AH201="4～10个交易日",AH201="11～20个交易日")),AND(AG201="趋势波段",OR(AH201="11～20个交易日",AH201="21～60个交易日",AH201="60个交易日以上"))),"匹配","周期与交易预期不匹配，请重新确认")) | AK201: =IF(A201="","",COUNTIFS(加仓管理!$A$2:$A$1001,A201,加仓管理!$G$2:$G$1001,">0")) | AL201: =IF(A201="","",SUMIFS(加仓管理!$G$2:$G$1001,加仓管理!$A$2:$A$1001,A201)) | AM201: =IF(AK201=0,"",IFERROR(LOOKUP(2,1/((加仓管理!$A$2:$A$1001=A201)*(加仓管理!$G$2:$G$1001>0)),加仓管理!$D$2:$D$1001),"")) | AN201: =IF(AK201=0,"",IFERROR(LOOKUP(2,1/((加仓管理!$A$2:$A$1001=A201)*(加仓管理!$G$2:$G$1001>0)),加仓管理!$E$2:$E$1001),"")) | AO201: =IF(OR(A201="",H201="",H201<=0),"",(E201*H201+SUMIFS(加仓管理!$H$2:$H$1001,加仓管理!$A$2:$A$1001,A201))/AP201) | AP201: =IF(OR(A201="",H201="",H201<=0),"",H201+AL201) | AQ201: =IF(A201="","",IF(M201<>"",0,IF(OR(H201="",N201=""),"",MAX((E201*H201+SUMIFS(加仓管理!$H$2:$H$1001,加仓管理!$A$2:$A$1001,A201))-MAX(N201,AN201)*AP201,0)))) | AR201: =IF(A201="","",IF(OR(E201="",H201=""),"违规：首次买入价格或股数缺失",IF(COUNTIFS(加仓管理!$A$2:$A$1001,A201,加仓管理!$R$2:$R$1001,"违规*")>0,"违规：请检查加仓管理表",IF(SUM($AQ$2:$AQ$201)>账户数据!$B$7,"预警：超过账户风险上限",IF(COUNTIFS(加仓管理!$A$2:$A$1001,A201,加仓管理!$N$2:$N$1001,">0",加仓管理!$G$2:$G$1001,"")>0,"提示：存在待执行加仓计划","通过")))))

Sheet 加仓管理
A1: 交易编号 | B1: 加仓序号(1-5) | C1: 加仓日期 | D1: 加仓价 | E1: 新止损价 | F1: 本次风险预算金额 | G1: 实际加仓股数 | H1: 本次买入金额 | I1: 加仓前持仓股数 | J1: 加仓前持仓成本 | K1: 新止损下底仓锁定利润 | L1: 风险允许股数 | M1: 金字塔上限股数 | N1: 建议加仓股数 | O1: 加仓后累计股数 | P1: 加仓后加权成本 | Q1: 加仓后止损风险 | R1: 规则检查
A2: 1 | B2: 1 | C2: 42657 | D2: 4.34 | E2: 4 | F2: 1 | G2: 2500 | H2: =IF(OR(A2="",D2="",G2=""),"",D2*G2) -> 10850 | I2: =IF(OR(A2="",B2=""),"",IFERROR(LOOKUP(2,1/(单次交易!$A$2:$A$201=A2),单次交易!$H$2:$H$201),0)+SUMIFS($G$2:$G$1001,$A$2:$A$1001,A2,$B$2:$B$1001,"<"&B2)) -> 6000 | J2: =IF(OR(A2="",B2=""),"",IFERROR(LOOKUP(2,1/(单次交易!$A$2:$A$201=A2),单次交易!$E$2:$E$201)*LOOKUP(2,1/(单次交易!$A$2:$A$201=A2),单次交易!$H$2:$H$201),0)+SUMIFS($H$2:$H$1001,$A$2:$A$1001,A2,$B$2:$B$1001,"<"&B2)) -> 24900 | K2: =IF(OR(E2="",I2="",J2=""),"",MAX(E2*I2-J2,0)) -> 0 | L2: =IF(OR(D2="",E2="",F2="",D2<=E2),"",FLOOR((F2+K2)/(D2-E2),100)) -> 0 | M2: =IF(OR(A2="",B2="",L2=""),"",IF(B2=1,L2,IFERROR(SUMIFS($G$2:$G$1001,$A$2:$A$1001,A2,$B$2:$B$1001,B2-1),0))) -> 0 | N2: =IF(OR(L2="",M2=""),"",MIN(L2,M2)) -> 0 | O2: =IF(OR(I2="",G2=""),"",I2+G2) -> 8500 | P2: =IF(OR(O2="",O2=0),"",(J2+H2)/O2) -> 4.2058824 | Q2: =IF(OR(O2="",E2=""),"",MAX(J2+H2-E2*O2,0)) -> 1750 | R2: =IF(A2="","",IF(COUNTIF(_TradeIds,A2)=0,"违规：交易编号不存在",IF(OR(B2="",B2<1,B2>5,B2<>INT(B2)),"违规：加仓序号须为1到5的整数",IF(COUNTIFS($A$2:$A$1001,A2,$B$2:$B$1001,B2)>1,"违规：同一交易的加仓序号重复",IF(OR(D2="",E2="",F2=""),"计划不完整：请填写加仓价、新止损价和风险预算",IF(OR(D2<=0,E2<=0,F2<=0,D2<=E2),"违规：加仓价必须高于新止损价，金额须大于0",IF(AND(B2>1,COUNTIFS($A$2:$A$1001,A2,$B$2:$B$1001,B2-1,$G$2:$G$1001,">0")=0),"违规：须先完成上一次加仓",IF(AND(B2>1,E2<SUMIFS($E$2:$E$1001,$A$2:$A$1001,A2,$B$2:$B$1001,B2-1)),"违规：新止损价不得低于上一次",IF(AND(B2>1,F2>SUMIFS($F$2:$F$1001,$A$2:$A$1001,A2,$B$2:$B$1001,B2-1)),"违规：风险预算须逐次不增加",IF(OR(_LockStatus="已锁仓",_LockStatus="解锁信息不完整"),"违规：锁仓期间禁止加仓",IF(G2="","计划可执行：建议股数见N列",IF(OR(G2<=0,G2<>INT(G2),MOD(G2,100)<>0),"违规：实际股数须为100股整数倍",IF(G2>N2,"违规：实际股数超过风险或金字塔上限",IF(AND(B2>1,G2>SUMIFS($G$2:$G$1001,$A$2:$A$1001,A2,$B$2:$B$1001,B2-1)),"违规：加仓股数须逐次不增加",IF(Q2>F2,"违规：止损风险超过本次预算","通过"))))))))))))))) -> 违规：实际股数超过风险或金字塔上限
A3: 1 | B3: 2 | C3: 42662 | D3: 4.57 | E3: 4 | F3: 1 | G3: 2000 | H3: =IF(OR(A3="",D3="",G3=""),"",D3*G3) -> 9140 | I3: =IF(OR(A3="",B3=""),"",IFERROR(LOOKUP(2,1/(单次交易!$A$2:$A$201=A3),单次交易!$H$2:$H$201),0)+SUMIFS($G$2:$G$1001,$A$2:$A$1001,A3,$B$2:$B$1001,"<"&B3)) -> 8500 | J3: =IF(OR(A3="",B3=""),"",IFERROR(LOOKUP(2,1/(单次交易!$A$2:$A$201=A3),单次交易!$E$2:$E$201)*LOOKUP(2,1/(单次交易!$A$2:$A$201=A3),单次交易!$H$2:$H$201),0)+SUMIFS($H$2:$H$1001,$A$2:$A$1001,A3,$B$2:$B$1001,"<"&B3)) -> 35750 | K3: =IF(OR(E3="",I3="",J3=""),"",MAX(E3*I3-J3,0)) -> 0 | L3: =IF(OR(D3="",E3="",F3="",D3<=E3),"",FLOOR((F3+K3)/(D3-E3),100)) -> 0 | M3: =IF(OR(A3="",B3="",L3=""),"",IF(B3=1,L3,IFERROR(SUMIFS($G$2:$G$1001,$A$2:$A$1001,A3,$B$2:$B$1001,B3-1),0))) -> 2500 | N3: =IF(OR(L3="",M3=""),"",MIN(L3,M3)) -> 0 | O3: =IF(OR(I3="",G3=""),"",I3+G3) -> 10500 | P3: =IF(OR(O3="",O3=0),"",(J3+H3)/O3) -> 4.2752381 | Q3: =IF(OR(O3="",E3=""),"",MAX(J3+H3-E3*O3,0)) -> 2890 | R3: =IF(A3="","",IF(COUNTIF(_TradeIds,A3)=0,"违规：交易编号不存在",IF(OR(B3="",B3<1,B3>5,B3<>INT(B3)),"违规：加仓序号须为1到5的整数",IF(COUNTIFS($A$2:$A$1001,A3,$B$2:$B$1001,B3)>1,"违规：同一交易的加仓序号重复",IF(OR(D3="",E3="",F3=""),"计划不完整：请填写加仓价、新止损价和风险预算",IF(OR(D3<=0,E3<=0,F3<=0,D3<=E3),"违规：加仓价必须高于新止损价，金额须大于0",IF(AND(B3>1,COUNTIFS($A$2:$A$1001,A3,$B$2:$B$1001,B3-1,$G$2:$G$1001,">0")=0),"违规：须先完成上一次加仓",IF(AND(B3>1,E3<SUMIFS($E$2:$E$1001,$A$2:$A$1001,A3,$B$2:$B$1001,B3-1)),"违规：新止损价不得低于上一次",IF(AND(B3>1,F3>SUMIFS($F$2:$F$1001,$A$2:$A$1001,A3,$B$2:$B$1001,B3-1)),"违规：风险预算须逐次不增加",IF(OR(_LockStatus="已锁仓",_LockStatus="解锁信息不完整"),"违规：锁仓期间禁止加仓",IF(G3="","计划可执行：建议股数见N列",IF(OR(G3<=0,G3<>INT(G3),MOD(G3,100)<>0),"违规：实际股数须为100股整数倍",IF(G3>N3,"违规：实际股数超过风险或金字塔上限",IF(AND(B3>1,G3>SUMIFS($G$2:$G$1001,$A$2:$A$1001,A3,$B$2:$B$1001,B3-1)),"违规：加仓股数须逐次不增加",IF(Q3>F3,"违规：止损风险超过本次预算","通过"))))))))))))))) -> 违规：实际股数超过风险或金字塔上限
A4: 4 | B4: 1 | C4: 42824 | D4: 2.92 | E4: 2.8 | F4: 1 | G4: 5000 | H4: =IF(OR(A4="",D4="",G4=""),"",D4*G4) -> 14600 | I4: =IF(OR(A4="",B4=""),"",IFERROR(LOOKUP(2,1/(单次交易!$A$2:$A$201=A4),单次交易!$H$2:$H$201),0)+SUMIFS($G$2:$G$1001,$A$2:$A$1001,A4,$B$2:$B$1001,"<"&B4)) -> 10000 | J4: =IF(OR(A4="",B4=""),"",IFERROR(LOOKUP(2,1/(单次交易!$A$2:$A$201=A4),单次交易!$E$2:$E$201)*LOOKUP(2,1/(单次交易!$A$2:$A$201=A4),单次交易!$H$2:$H$201),0)+SUMIFS($H$2:$H$1001,$A$2:$A$1001,A4,$B$2:$B$1001,"<"&B4)) -> 31500 | K4: =IF(OR(E4="",I4="",J4=""),"",MAX(E4*I4-J4,0)) -> 0 | L4: =IF(OR(D4="",E4="",F4="",D4<=E4),"",FLOOR((F4+K4)/(D4-E4),100)) -> 0 | M4: =IF(OR(A4="",B4="",L4=""),"",IF(B4=1,L4,IFERROR(SUMIFS($G$2:$G$1001,$A$2:$A$1001,A4,$B$2:$B$1001,B4-1),0))) -> 0 | N4: =IF(OR(L4="",M4=""),"",MIN(L4,M4)) -> 0 | O4: =IF(OR(I4="",G4=""),"",I4+G4) -> 15000 | P4: =IF(OR(O4="",O4=0),"",(J4+H4)/O4) -> 3.0733333 | Q4: =IF(OR(O4="",E4=""),"",MAX(J4+H4-E4*O4,0)) -> 4100 | R4: =IF(A4="","",IF(COUNTIF(_TradeIds,A4)=0,"违规：交易编号不存在",IF(OR(B4="",B4<1,B4>5,B4<>INT(B4)),"违规：加仓序号须为1到5的整数",IF(COUNTIFS($A$2:$A$1001,A4,$B$2:$B$1001,B4)>1,"违规：同一交易的加仓序号重复",IF(OR(D4="",E4="",F4=""),"计划不完整：请填写加仓价、新止损价和风险预算",IF(OR(D4<=0,E4<=0,F4<=0,D4<=E4),"违规：加仓价必须高于新止损价，金额须大于0",IF(AND(B4>1,COUNTIFS($A$2:$A$1001,A4,$B$2:$B$1001,B4-1,$G$2:$G$1001,">0")=0),"违规：须先完成上一次加仓",IF(AND(B4>1,E4<SUMIFS($E$2:$E$1001,$A$2:$A$1001,A4,$B$2:$B$1001,B4-1)),"违规：新止损价不得低于上一次",IF(AND(B4>1,F4>SUMIFS($F$2:$F$1001,$A$2:$A$1001,A4,$B$2:$B$1001,B4-1)),"违规：风险预算须逐次不增加",IF(OR(_LockStatus="已锁仓",_LockStatus="解锁信息不完整"),"违规：锁仓期间禁止加仓",IF(G4="","计划可执行：建议股数见N列",IF(OR(G4<=0,G4<>INT(G4),MOD(G4,100)<>0),"违规：实际股数须为100股整数倍",IF(G4>N4,"违规：实际股数超过风险或金字塔上限",IF(AND(B4>1,G4>SUMIFS($G$2:$G$1001,$A$2:$A$1001,A4,$B$2:$B$1001,B4-1)),"违规：加仓股数须逐次不增加",IF(Q4>F4,"违规：止损风险超过本次预算","通过"))))))))))))))) -> 违规：实际股数超过风险或金字塔上限
A5: 4 | B5: 2 | C5: 42843 | D5: 2.55 | E5: 2.3 | F5: 1 | G5: 6000 | H5: =IF(OR(A5="",D5="",G5=""),"",D5*G5) -> 15300 | I5: =IF(OR(A5="",B5=""),"",IFERROR(LOOKUP(2,1/(单次交易!$A$2:$A$201=A5),单次交易!$H$2:$H$201),0)+SUMIFS($G$2:$G$1001,$A$2:$A$1001,A5,$B$2:$B$1001,"<"&B5)) -> 15000 | J5: =IF(OR(A5="",B5=""),"",IFERROR(LOOKUP(2,1/(单次交易!$A$2:$A$201=A5),单次交易!$E$2:$E$201)*LOOKUP(2,1/(单次交易!$A$2:$A$201=A5),单次交易!$H$2:$H$201),0)+SUMIFS($H$2:$H$1001,$A$2:$A$1001,A5,$B$2:$B$1001,"<"&B5)) -> 46100 | K5: =IF(OR(E5="",I5="",J5=""),"",MAX(E5*I5-J5,0)) -> 0 | L5: =IF(OR(D5="",E5="",F5="",D5<=E5),"",FLOOR((F5+K5)/(D5-E5),100)) -> 0 | M5: =IF(OR(A5="",B5="",L5=""),"",IF(B5=1,L5,IFERROR(SUMIFS($G$2:$G$1001,$A$2:$A$1001,A5,$B$2:$B$1001,B5-1),0))) -> 5000 | N5: =IF(OR(L5="",M5=""),"",MIN(L5,M5)) -> 0 | O5: =IF(OR(I5="",G5=""),"",I5+G5) -> 21000 | P5: =IF(OR(O5="",O5=0),"",(J5+H5)/O5) -> 2.9238095 | Q5: =IF(OR(O5="",E5=""),"",MAX(J5+H5-E5*O5,0)) -> 13100 | R5: =IF(A5="","",IF(COUNTIF(_TradeIds,A5)=0,"违规：交易编号不存在",IF(OR(B5="",B5<1,B5>5,B5<>INT(B5)),"违规：加仓序号须为1到5的整数",IF(COUNTIFS($A$2:$A$1001,A5,$B$2:$B$1001,B5)>1,"违规：同一交易的加仓序号重复",IF(OR(D5="",E5="",F5=""),"计划不完整：请填写加仓价、新止损价和风险预算",IF(OR(D5<=0,E5<=0,F5<=0,D5<=E5),"违规：加仓价必须高于新止损价，金额须大于0",IF(AND(B5>1,COUNTIFS($A$2:$A$1001,A5,$B$2:$B$1001,B5-1,$G$2:$G$1001,">0")=0),"违规：须先完成上一次加仓",IF(AND(B5>1,E5<SUMIFS($E$2:$E$1001,$A$2:$A$1001,A5,$B$2:$B$1001,B5-1)),"违规：新止损价不得低于上一次",IF(AND(B5>1,F5>SUMIFS($F$2:$F$1001,$A$2:$A$1001,A5,$B$2:$B$1001,B5-1)),"违规：风险预算须逐次不增加",IF(OR(_LockStatus="已锁仓",_LockStatus="解锁信息不完整"),"违规：锁仓期间禁止加仓",IF(G5="","计划可执行：建议股数见N列",IF(OR(G5<=0,G5<>INT(G5),MOD(G5,100)<>0),"违规：实际股数须为100股整数倍",IF(G5>N5,"违规：实际股数超过风险或金字塔上限",IF(AND(B5>1,G5>SUMIFS($G$2:$G$1001,$A$2:$A$1001,A5,$B$2:$B$1001,B5-1)),"违规：加仓股数须逐次不增加",IF(Q5>F5,"违规：止损风险超过本次预算","通过"))))))))))))))) -> 违规：新止损价不得低于上一次
A6: 4 | B6: 3 | C6: 42852 | D6: 2.42 | E6: 2.3 | F6: 1 | G6: 6000 | H6: =IF(OR(A6="",D6="",G6=""),"",D6*G6) -> 14520 | I6: =IF(OR(A6="",B6=""),"",IFERROR(LOOKUP(2,1/(单次交易!$A$2:$A$201=A6),单次交易!$H$2:$H$201),0)+SUMIFS($G$2:$G$1001,$A$2:$A$1001,A6,$B$2:$B$1001,"<"&B6)) -> 21000 | J6: =IF(OR(A6="",B6=""),"",IFERROR(LOOKUP(2,1/(单次交易!$A$2:$A$201=A6),单次交易!$E$2:$E$201)*LOOKUP(2,1/(单次交易!$A$2:$A$201=A6),单次交易!$H$2:$H$201),0)+SUMIFS($H$2:$H$1001,$A$2:$A$1001,A6,$B$2:$B$1001,"<"&B6)) -> 61400 | K6: =IF(OR(E6="",I6="",J6=""),"",MAX(E6*I6-J6,0)) -> 0 | L6: =IF(OR(D6="",E6="",F6="",D6<=E6),"",FLOOR((F6+K6)/(D6-E6),100)) -> 0 | M6: =IF(OR(A6="",B6="",L6=""),"",IF(B6=1,L6,IFERROR(SUMIFS($G$2:$G$1001,$A$2:$A$1001,A6,$B$2:$B$1001,B6-1),0))) -> 6000 | N6: =IF(OR(L6="",M6=""),"",MIN(L6,M6)) -> 0 | O6: =IF(OR(I6="",G6=""),"",I6+G6) -> 27000 | P6: =IF(OR(O6="",O6=0),"",(J6+H6)/O6) -> 2.8118519 | Q6: =IF(OR(O6="",E6=""),"",MAX(J6+H6-E6*O6,0)) -> 13820 | R6: =IF(A6="","",IF(COUNTIF(_TradeIds,A6)=0,"违规：交易编号不存在",IF(OR(B6="",B6<1,B6>5,B6<>INT(B6)),"违规：加仓序号须为1到5的整数",IF(COUNTIFS($A$2:$A$1001,A6,$B$2:$B$1001,B6)>1,"违规：同一交易的加仓序号重复",IF(OR(D6="",E6="",F6=""),"计划不完整：请填写加仓价、新止损价和风险预算",IF(OR(D6<=0,E6<=0,F6<=0,D6<=E6),"违规：加仓价必须高于新止损价，金额须大于0",IF(AND(B6>1,COUNTIFS($A$2:$A$1001,A6,$B$2:$B$1001,B6-1,$G$2:$G$1001,">0")=0),"违规：须先完成上一次加仓",IF(AND(B6>1,E6<SUMIFS($E$2:$E$1001,$A$2:$A$1001,A6,$B$2:$B$1001,B6-1)),"违规：新止损价不得低于上一次",IF(AND(B6>1,F6>SUMIFS($F$2:$F$1001,$A$2:$A$1001,A6,$B$2:$B$1001,B6-1)),"违规：风险预算须逐次不增加",IF(OR(_LockStatus="已锁仓",_LockStatus="解锁信息不完整"),"违规：锁仓期间禁止加仓",IF(G6="","计划可执行：建议股数见N列",IF(OR(G6<=0,G6<>INT(G6),MOD(G6,100)<>0),"违规：实际股数须为100股整数倍",IF(G6>N6,"违规：实际股数超过风险或金字塔上限",IF(AND(B6>1,G6>SUMIFS($G$2:$G$1001,$A$2:$A$1001,A6,$B$2:$B$1001,B6-1)),"违规：加仓股数须逐次不增加",IF(Q6>F6,"违规：止损风险超过本次预算","通过"))))))))))))))) -> 违规：实际股数超过风险或金字塔上限
A7: 4 | B7: 4 | C7: 42860 | D7: 2.16 | E7: 2 | F7: 1 | G7: 6000 | H7: =IF(OR(A7="",D7="",G7=""),"",D7*G7) -> 12960 | I7: =IF(OR(A7="",B7=""),"",IFERROR(LOOKUP(2,1/(单次交易!$A$2:$A$201=A7),单次交易!$H$2:$H$201),0)+SUMIFS($G$2:$G$1001,$A$2:$A$1001,A7,$B$2:$B$1001,"<"&B7)) -> 27000 | J7: =IF(OR(A7="",B7=""),"",IFERROR(LOOKUP(2,1/(单次交易!$A$2:$A$201=A7),单次交易!$E$2:$E$201)*LOOKUP(2,1/(单次交易!$A$2:$A$201=A7),单次交易!$H$2:$H$201),0)+SUMIFS($H$2:$H$1001,$A$2:$A$1001,A7,$B$2:$B$1001,"<"&B7)) -> 75920 | K7: =IF(OR(E7="",I7="",J7=""),"",MAX(E7*I7-J7,0)) -> 0 | L7: =IF(OR(D7="",E7="",F7="",D7<=E7),"",FLOOR((F7+K7)/(D7-E7),100)) -> 0 | M7: =IF(OR(A7="",B7="",L7=""),"",IF(B7=1,L7,IFERROR(SUMIFS($G$2:$G$1001,$A$2:$A$1001,A7,$B$2:$B$1001,B7-1),0))) -> 6000 | N7: =IF(OR(L7="",M7=""),"",MIN(L7,M7)) -> 0 | O7: =IF(OR(I7="",G7=""),"",I7+G7) -> 33000 | P7: =IF(OR(O7="",O7=0),"",(J7+H7)/O7) -> 2.6933333 | Q7: =IF(OR(O7="",E7=""),"",MAX(J7+H7-E7*O7,0)) -> 22880 | R7: =IF(A7="","",IF(COUNTIF(_TradeIds,A7)=0,"违规：交易编号不存在",IF(OR(B7="",B7<1,B7>5,B7<>INT(B7)),"违规：加仓序号须为1到5的整数",IF(COUNTIFS($A$2:$A$1001,A7,$B$2:$B$1001,B7)>1,"违规：同一交易的加仓序号重复",IF(OR(D7="",E7="",F7=""),"计划不完整：请填写加仓价、新止损价和风险预算",IF(OR(D7<=0,E7<=0,F7<=0,D7<=E7),"违规：加仓价必须高于新止损价，金额须大于0",IF(AND(B7>1,COUNTIFS($A$2:$A$1001,A7,$B$2:$B$1001,B7-1,$G$2:$G$1001,">0")=0),"违规：须先完成上一次加仓",IF(AND(B7>1,E7<SUMIFS($E$2:$E$1001,$A$2:$A$1001,A7,$B$2:$B$1001,B7-1)),"违规：新止损价不得低于上一次",IF(AND(B7>1,F7>SUMIFS($F$2:$F$1001,$A$2:$A$1001,A7,$B$2:$B$1001,B7-1)),"违规：风险预算须逐次不增加",IF(OR(_LockStatus="已锁仓",_LockStatus="解锁信息不完整"),"违规：锁仓期间禁止加仓",IF(G7="","计划可执行：建议股数见N列",IF(OR(G7<=0,G7<>INT(G7),MOD(G7,100)<>0),"违规：实际股数须为100股整数倍",IF(G7>N7,"违规：实际股数超过风险或金字塔上限",IF(AND(B7>1,G7>SUMIFS($G$2:$G$1001,$A$2:$A$1001,A7,$B$2:$B$1001,B7-1)),"违规：加仓股数须逐次不增加",IF(Q7>F7,"违规：止损风险超过本次预算","通过"))))))))))))))) -> 违规：新止损价不得低于上一次
A8: 5 | B8: 1 | C8: 42993 | D8: 4.54 | E8: 4 | F8: 1 | G8: 2500 | H8: =IF(OR(A8="",D8="",G8=""),"",D8*G8) -> 11350 | I8: =IF(OR(A8="",B8=""),"",IFERROR(LOOKUP(2,1/(单次交易!$A$2:$A$201=A8),单次交易!$H$2:$H$201),0)+SUMIFS($G$2:$G$1001,$A$2:$A$1001,A8,$B$2:$B$1001,"<"&B8)) -> 6500 | J8: =IF(OR(A8="",B8=""),"",IFERROR(LOOKUP(2,1/(单次交易!$A$2:$A$201=A8),单次交易!$E$2:$E$201)*LOOKUP(2,1/(单次交易!$A$2:$A$201=A8),单次交易!$H$2:$H$201),0)+SUMIFS($H$2:$H$1001,$A$2:$A$1001,A8,$B$2:$B$1001,"<"&B8)) -> 28535 | K8: =IF(OR(E8="",I8="",J8=""),"",MAX(E8*I8-J8,0)) -> 0 | L8: =IF(OR(D8="",E8="",F8="",D8<=E8),"",FLOOR((F8+K8)/(D8-E8),100)) -> 0 | M8: =IF(OR(A8="",B8="",L8=""),"",IF(B8=1,L8,IFERROR(SUMIFS($G$2:$G$1001,$A$2:$A$1001,A8,$B$2:$B$1001,B8-1),0))) -> 0 | N8: =IF(OR(L8="",M8=""),"",MIN(L8,M8)) -> 0 | O8: =IF(OR(I8="",G8=""),"",I8+G8) -> 9000 | P8: =IF(OR(O8="",O8=0),"",(J8+H8)/O8) -> 4.4316667 | Q8: =IF(OR(O8="",E8=""),"",MAX(J8+H8-E8*O8,0)) -> 3885 | R8: =IF(A8="","",IF(COUNTIF(_TradeIds,A8)=0,"违规：交易编号不存在",IF(OR(B8="",B8<1,B8>5,B8<>INT(B8)),"违规：加仓序号须为1到5的整数",IF(COUNTIFS($A$2:$A$1001,A8,$B$2:$B$1001,B8)>1,"违规：同一交易的加仓序号重复",IF(OR(D8="",E8="",F8=""),"计划不完整：请填写加仓价、新止损价和风险预算",IF(OR(D8<=0,E8<=0,F8<=0,D8<=E8),"违规：加仓价必须高于新止损价，金额须大于0",IF(AND(B8>1,COUNTIFS($A$2:$A$1001,A8,$B$2:$B$1001,B8-1,$G$2:$G$1001,">0")=0),"违规：须先完成上一次加仓",IF(AND(B8>1,E8<SUMIFS($E$2:$E$1001,$A$2:$A$1001,A8,$B$2:$B$1001,B8-1)),"违规：新止损价不得低于上一次",IF(AND(B8>1,F8>SUMIFS($F$2:$F$1001,$A$2:$A$1001,A8,$B$2:$B$1001,B8-1)),"违规：风险预算须逐次不增加",IF(OR(_LockStatus="已锁仓",_LockStatus="解锁信息不完整"),"违规：锁仓期间禁止加仓",IF(G8="","计划可执行：建议股数见N列",IF(OR(G8<=0,G8<>INT(G8),MOD(G8,100)<>0),"违规：实际股数须为100股整数倍",IF(G8>N8,"违规：实际股数超过风险或金字塔上限",IF(AND(B8>1,G8>SUMIFS($G$2:$G$1001,$A$2:$A$1001,A8,$B$2:$B$1001,B8-1)),"违规：加仓股数须逐次不增加",IF(Q8>F8,"违规：止损风险超过本次预算","通过"))))))))))))))) -> 违规：实际股数超过风险或金字塔上限
A9: 6 | B9: 1 | C9: 43042 | D9: 5.92 | E9: 5.5 | F9: 1 | G9: 2000 | H9: =IF(OR(A9="",D9="",G9=""),"",D9*G9) -> 11840 | I9: =IF(OR(A9="",B9=""),"",IFERROR(LOOKUP(2,1/(单次交易!$A$2:$A$201=A9),单次交易!$H$2:$H$201),0)+SUMIFS($G$2:$G$1001,$A$2:$A$1001,A9,$B$2:$B$1001,"<"&B9)) -> 5600 | J9: =IF(OR(A9="",B9=""),"",IFERROR(LOOKUP(2,1/(单次交易!$A$2:$A$201=A9),单次交易!$E$2:$E$201)*LOOKUP(2,1/(单次交易!$A$2:$A$201=A9),单次交易!$H$2:$H$201),0)+SUMIFS($H$2:$H$1001,$A$2:$A$1001,A9,$B$2:$B$1001,"<"&B9)) -> 31640 | K9: =IF(OR(E9="",I9="",J9=""),"",MAX(E9*I9-J9,0)) -> 0 | L9: =IF(OR(D9="",E9="",F9="",D9<=E9),"",FLOOR((F9+K9)/(D9-E9),100)) -> 0 | M9: =IF(OR(A9="",B9="",L9=""),"",IF(B9=1,L9,IFERROR(SUMIFS($G$2:$G$1001,$A$2:$A$1001,A9,$B$2:$B$1001,B9-1),0))) -> 0 | N9: =IF(OR(L9="",M9=""),"",MIN(L9,M9)) -> 0 | O9: =IF(OR(I9="",G9=""),"",I9+G9) -> 7600 | P9: =IF(OR(O9="",O9=0),"",(J9+H9)/O9) -> 5.7210526 | Q9: =IF(OR(O9="",E9=""),"",MAX(J9+H9-E9*O9,0)) -> 1680 | R9: =IF(A9="","",IF(COUNTIF(_TradeIds,A9)=0,"违规：交易编号不存在",IF(OR(B9="",B9<1,B9>5,B9<>INT(B9)),"违规：加仓序号须为1到5的整数",IF(COUNTIFS($A$2:$A$1001,A9,$B$2:$B$1001,B9)>1,"违规：同一交易的加仓序号重复",IF(OR(D9="",E9="",F9=""),"计划不完整：请填写加仓价、新止损价和风险预算",IF(OR(D9<=0,E9<=0,F9<=0,D9<=E9),"违规：加仓价必须高于新止损价，金额须大于0",IF(AND(B9>1,COUNTIFS($A$2:$A$1001,A9,$B$2:$B$1001,B9-1,$G$2:$G$1001,">0")=0),"违规：须先完成上一次加仓",IF(AND(B9>1,E9<SUMIFS($E$2:$E$1001,$A$2:$A$1001,A9,$B$2:$B$1001,B9-1)),"违规：新止损价不得低于上一次",IF(AND(B9>1,F9>SUMIFS($F$2:$F$1001,$A$2:$A$1001,A9,$B$2:$B$1001,B9-1)),"违规：风险预算须逐次不增加",IF(OR(_LockStatus="已锁仓",_LockStatus="解锁信息不完整"),"违规：锁仓期间禁止加仓",IF(G9="","计划可执行：建议股数见N列",IF(OR(G9<=0,G9<>INT(G9),MOD(G9,100)<>0),"违规：实际股数须为100股整数倍",IF(G9>N9,"违规：实际股数超过风险或金字塔上限",IF(AND(B9>1,G9>SUMIFS($G$2:$G$1001,$A$2:$A$1001,A9,$B$2:$B$1001,B9-1)),"违规：加仓股数须逐次不增加",IF(Q9>F9,"违规：止损风险超过本次预算","通过"))))))))))))))) -> 违规：实际股数超过风险或金字塔上限
A10: 8 | B10: 1 | C10: 43525 | D10: 7.71 | E10: 7.5 | F10: 1 | G10: 2000 | H10: =IF(OR(A10="",D10="",G10=""),"",D10*G10) -> 15420 | I10: =IF(OR(A10="",B10=""),"",IFERROR(LOOKUP(2,1/(单次交易!$A$2:$A$201=A10),单次交易!$H$2:$H$201),0)+SUMIFS($G$2:$G$1001,$A$2:$A$1001,A10,$B$2:$B$1001,"<"&B10)) -> 4000 | J10: =IF(OR(A10="",B10=""),"",IFERROR(LOOKUP(2,1/(单次交易!$A$2:$A$201=A10),单次交易!$E$2:$E$201)*LOOKUP(2,1/(单次交易!$A$2:$A$201=A10),单次交易!$H$2:$H$201),0)+SUMIFS($H$2:$H$1001,$A$2:$A$1001,A10,$B$2:$B$1001,"<"&B10)) -> 30160 | K10: =IF(OR(E10="",I10="",J10=""),"",MAX(E10*I10-J10,0)) -> 0 | L10: =IF(OR(D10="",E10="",F10="",D10<=E10),"",FLOOR((F10+K10)/(D10-E10),100)) -> 0 | M10: =IF(OR(A10="",B10="",L10=""),"",IF(B10=1,L10,IFERROR(SUMIFS($G$2:$G$1001,$A$2:$A$1001,A10,$B$2:$B$1001,B10-1),0))) -> 0 | N10: =IF(OR(L10="",M10=""),"",MIN(L10,M10)) -> 0 | O10: =IF(OR(I10="",G10=""),"",I10+G10) -> 6000 | P10: =IF(OR(O10="",O10=0),"",(J10+H10)/O10) -> 7.5966667 | Q10: =IF(OR(O10="",E10=""),"",MAX(J10+H10-E10*O10,0)) -> 580 | R10: =IF(A10="","",IF(COUNTIF(_TradeIds,A10)=0,"违规：交易编号不存在",IF(OR(B10="",B10<1,B10>5,B10<>INT(B10)),"违规：加仓序号须为1到5的整数",IF(COUNTIFS($A$2:$A$1001,A10,$B$2:$B$1001,B10)>1,"违规：同一交易的加仓序号重复",IF(OR(D10="",E10="",F10=""),"计划不完整：请填写加仓价、新止损价和风险预算",IF(OR(D10<=0,E10<=0,F10<=0,D10<=E10),"违规：加仓价必须高于新止损价，金额须大于0",IF(AND(B10>1,COUNTIFS($A$2:$A$1001,A10,$B$2:$B$1001,B10-1,$G$2:$G$1001,">0")=0),"违规：须先完成上一次加仓",IF(AND(B10>1,E10<SUMIFS($E$2:$E$1001,$A$2:$A$1001,A10,$B$2:$B$1001,B10-1)),"违规：新止损价不得低于上一次",IF(AND(B10>1,F10>SUMIFS($F$2:$F$1001,$A$2:$A$1001,A10,$B$2:$B$1001,B10-1)),"违规：风险预算须逐次不增加",IF(OR(_LockStatus="已锁仓",_LockStatus="解锁信息不完整"),"违规：锁仓期间禁止加仓",IF(G10="","计划可执行：建议股数见N列",IF(OR(G10<=0,G10<>INT(G10),MOD(G10,100)<>0),"违规：实际股数须为100股整数倍",IF(G10>N10,"违规：实际股数超过风险或金字塔上限",IF(AND(B10>1,G10>SUMIFS($G$2:$G$1001,$A$2:$A$1001,A10,$B$2:$B$1001,B10-1)),"违规：加仓股数须逐次不增加",IF(Q10>F10,"违规：止损风险超过本次预算","通过"))))))))))))))) -> 违规：实际股数超过风险或金字塔上限
A11: 8 | B11: 2 | C11: 43530 | D11: 8.18 | E11: 7.8 | F11: 1 | G11: 2000 | H11: =IF(OR(A11="",D11="",G11=""),"",D11*G11) -> 16360 | I11: =IF(OR(A11="",B11=""),"",IFERROR(LOOKUP(2,1/(单次交易!$A$2:$A$201=A11),单次交易!$H$2:$H$201),0)+SUMIFS($G$2:$G$1001,$A$2:$A$1001,A11,$B$2:$B$1001,"<"&B11)) -> 6000 | J11: =IF(OR(A11="",B11=""),"",IFERROR(LOOKUP(2,1/(单次交易!$A$2:$A$201=A11),单次交易!$E$2:$E$201)*LOOKUP(2,1/(单次交易!$A$2:$A$201=A11),单次交易!$H$2:$H$201),0)+SUMIFS($H$2:$H$1001,$A$2:$A$1001,A11,$B$2:$B$1001,"<"&B11)) -> 45580 | K11: =IF(OR(E11="",I11="",J11=""),"",MAX(E11*I11-J11,0)) -> 1220 | L11: =IF(OR(D11="",E11="",F11="",D11<=E11),"",FLOOR((F11+K11)/(D11-E11),100)) -> 3200 | M11: =IF(OR(A11="",B11="",L11=""),"",IF(B11=1,L11,IFERROR(SUMIFS($G$2:$G$1001,$A$2:$A$1001,A11,$B$2:$B$1001,B11-1),0))) -> 2000 | N11: =IF(OR(L11="",M11=""),"",MIN(L11,M11)) -> 2000 | O11: =IF(OR(I11="",G11=""),"",I11+G11) -> 8000 | P11: =IF(OR(O11="",O11=0),"",(J11+H11)/O11) -> 7.7425 | Q11: =IF(OR(O11="",E11=""),"",MAX(J11+H11-E11*O11,0)) -> 0 | R11: =IF(A11="","",IF(COUNTIF(_TradeIds,A11)=0,"违规：交易编号不存在",IF(OR(B11="",B11<1,B11>5,B11<>INT(B11)),"违规：加仓序号须为1到5的整数",IF(COUNTIFS($A$2:$A$1001,A11,$B$2:$B$1001,B11)>1,"违规：同一交易的加仓序号重复",IF(OR(D11="",E11="",F11=""),"计划不完整：请填写加仓价、新止损价和风险预算",IF(OR(D11<=0,E11<=0,F11<=0,D11<=E11),"违规：加仓价必须高于新止损价，金额须大于0",IF(AND(B11>1,COUNTIFS($A$2:$A$1001,A11,$B$2:$B$1001,B11-1,$G$2:$G$1001,">0")=0),"违规：须先完成上一次加仓",IF(AND(B11>1,E11<SUMIFS($E$2:$E$1001,$A$2:$A$1001,A11,$B$2:$B$1001,B11-1)),"违规：新止损价不得低于上一次",IF(AND(B11>1,F11>SUMIFS($F$2:$F$1001,$A$2:$A$1001,A11,$B$2:$B$1001,B11-1)),"违规：风险预算须逐次不增加",IF(OR(_LockStatus="已锁仓",_LockStatus="解锁信息不完整"),"违规：锁仓期间禁止加仓",IF(G11="","计划可执行：建议股数见N列",IF(OR(G11<=0,G11<>INT(G11),MOD(G11,100)<>0),"违规：实际股数须为100股整数倍",IF(G11>N11,"违规：实际股数超过风险或金字塔上限",IF(AND(B11>1,G11>SUMIFS($G$2:$G$1001,$A$2:$A$1001,A11,$B$2:$B$1001,B11-1)),"违规：加仓股数须逐次不增加",IF(Q11>F11,"违规：止损风险超过本次预算","通过"))))))))))))))) -> 通过
A12: 8 | B12: 3 | C12: 43531 | D12: 8.97 | E12: 8.2 | F12: 1 | G12: 1500 | H12: =IF(OR(A12="",D12="",G12=""),"",D12*G12) -> 13455 | I12: =IF(OR(A12="",B12=""),"",IFERROR(LOOKUP(2,1/(单次交易!$A$2:$A$201=A12),单次交易!$H$2:$H$201),0)+SUMIFS($G$2:$G$1001,$A$2:$A$1001,A12,$B$2:$B$1001,"<"&B12)) -> 8000 | J12: =IF(OR(A12="",B12=""),"",IFERROR(LOOKUP(2,1/(单次交易!$A$2:$A$201=A12),单次交易!$E$2:$E$201)*LOOKUP(2,1/(单次交易!$A$2:$A$201=A12),单次交易!$H$2:$H$201),0)+SUMIFS($H$2:$H$1001,$A$2:$A$1001,A12,$B$2:$B$1001,"<"&B12)) -> 61940 | K12: =IF(OR(E12="",I12="",J12=""),"",MAX(E12*I12-J12,0)) -> 3660 | L12: =IF(OR(D12="",E12="",F12="",D12<=E12),"",FLOOR((F12+K12)/(D12-E12),100)) -> 4700 | M12: =IF(OR(A12="",B12="",L12=""),"",IF(B12=1,L12,IFERROR(SUMIFS($G$2:$G$1001,$A$2:$A$1001,A12,$B$2:$B$1001,B12-1),0))) -> 2000 | N12: =IF(OR(L12="",M12=""),"",MIN(L12,M12)) -> 2000 | O12: =IF(OR(I12="",G12=""),"",I12+G12) -> 9500 | P12: =IF(OR(O12="",O12=0),"",(J12+H12)/O12) -> 7.9363158 | Q12: =IF(OR(O12="",E12=""),"",MAX(J12+H12-E12*O12,0)) -> 0 | R12: =IF(A12="","",IF(COUNTIF(_TradeIds,A12)=0,"违规：交易编号不存在",IF(OR(B12="",B12<1,B12>5,B12<>INT(B12)),"违规：加仓序号须为1到5的整数",IF(COUNTIFS($A$2:$A$1001,A12,$B$2:$B$1001,B12)>1,"违规：同一交易的加仓序号重复",IF(OR(D12="",E12="",F12=""),"计划不完整：请填写加仓价、新止损价和风险预算",IF(OR(D12<=0,E12<=0,F12<=0,D12<=E12),"违规：加仓价必须高于新止损价，金额须大于0",IF(AND(B12>1,COUNTIFS($A$2:$A$1001,A12,$B$2:$B$1001,B12-1,$G$2:$G$1001,">0")=0),"违规：须先完成上一次加仓",IF(AND(B12>1,E12<SUMIFS($E$2:$E$1001,$A$2:$A$1001,A12,$B$2:$B$1001,B12-1)),"违规：新止损价不得低于上一次",IF(AND(B12>1,F12>SUMIFS($F$2:$F$1001,$A$2:$A$1001,A12,$B$2:$B$1001,B12-1)),"违规：风险预算须逐次不增加",IF(OR(_LockStatus="已锁仓",_LockStatus="解锁信息不完整"),"违规：锁仓期间禁止加仓",IF(G12="","计划可执行：建议股数见N列",IF(OR(G12<=0,G12<>INT(G12),MOD(G12,100)<>0),"违规：实际股数须为100股整数倍",IF(G12>N12,"违规：实际股数超过风险或金字塔上限",IF(AND(B12>1,G12>SUMIFS($G$2:$G$1001,$A$2:$A$1001,A12,$B$2:$B$1001,B12-1)),"违规：加仓股数须逐次不增加",IF(Q12>F12,"违规：止损风险超过本次预算","通过"))))))))))))))) -> 通过
A13: 8 | B13: 4 | C13: 43535 | D13: 9.32 | E13: 8.5 | F13: 1 | G13: 2000 | H13: =IF(OR(A13="",D13="",G13=""),"",D13*G13) -> 18640 | I13: =IF(OR(A13="",B13=""),"",IFERROR(LOOKUP(2,1/(单次交易!$A$2:$A$201=A13),单次交易!$H$2:$H$201),0)+SUMIFS($G$2:$G$1001,$A$2:$A$1001,A13,$B$2:$B$1001,"<"&B13)) -> 9500 | J13: =IF(OR(A13="",B13=""),"",IFERROR(LOOKUP(2,1/(单次交易!$A$2:$A$201=A13),单次交易!$E$2:$E$201)*LOOKUP(2,1/(单次交易!$A$2:$A$201=A13),单次交易!$H$2:$H$201),0)+SUMIFS($H$2:$H$1001,$A$2:$A$1001,A13,$B$2:$B$1001,"<"&B13)) -> 75395 | K13: =IF(OR(E13="",I13="",J13=""),"",MAX(E13*I13-J13,0)) -> 5355 | L13: =IF(OR(D13="",E13="",F13="",D13<=E13),"",FLOOR((F13+K13)/(D13-E13),100)) -> 6500 | M13: =IF(OR(A13="",B13="",L13=""),"",IF(B13=1,L13,IFERROR(SUMIFS($G$2:$G$1001,$A$2:$A$1001,A13,$B$2:$B$1001,B13-1),0))) -> 1500 | N13: =IF(OR(L13="",M13=""),"",MIN(L13,M13)) -> 1500 | O13: =IF(OR(I13="",G13=""),"",I13+G13) -> 11500 | P13: =IF(OR(O13="",O13=0),"",(J13+H13)/O13) -> 8.1769565 | Q13: =IF(OR(O13="",E13=""),"",MAX(J13+H13-E13*O13,0)) -> 0 | R13: =IF(A13="","",IF(COUNTIF(_TradeIds,A13)=0,"违规：交易编号不存在",IF(OR(B13="",B13<1,B13>5,B13<>INT(B13)),"违规：加仓序号须为1到5的整数",IF(COUNTIFS($A$2:$A$1001,A13,$B$2:$B$1001,B13)>1,"违规：同一交易的加仓序号重复",IF(OR(D13="",E13="",F13=""),"计划不完整：请填写加仓价、新止损价和风险预算",IF(OR(D13<=0,E13<=0,F13<=0,D13<=E13),"违规：加仓价必须高于新止损价，金额须大于0",IF(AND(B13>1,COUNTIFS($A$2:$A$1001,A13,$B$2:$B$1001,B13-1,$G$2:$G$1001,">0")=0),"违规：须先完成上一次加仓",IF(AND(B13>1,E13<SUMIFS($E$2:$E$1001,$A$2:$A$1001,A13,$B$2:$B$1001,B13-1)),"违规：新止损价不得低于上一次",IF(AND(B13>1,F13>SUMIFS($F$2:$F$1001,$A$2:$A$1001,A13,$B$2:$B$1001,B13-1)),"违规：风险预算须逐次不增加",IF(OR(_LockStatus="已锁仓",_LockStatus="解锁信息不完整"),"违规：锁仓期间禁止加仓",IF(G13="","计划可执行：建议股数见N列",IF(OR(G13<=0,G13<>INT(G13),MOD(G13,100)<>0),"违规：实际股数须为100股整数倍",IF(G13>N13,"违规：实际股数超过风险或金字塔上限",IF(AND(B13>1,G13>SUMIFS($G$2:$G$1001,$A$2:$A$1001,A13,$B$2:$B$1001,B13-1)),"违规：加仓股数须逐次不增加",IF(Q13>F13,"违规：止损风险超过本次预算","通过"))))))))))))))) -> 违规：实际股数超过风险或金字塔上限
... A158: 71 | B158: 3 | C158: 46171 | D158: 36.37 | E158: 35 | F158: 1 | G158: 2500 | H158: =IF(OR(A158="",D158="",G158=""),"",D158*G158) -> 90925 | I158: =IF(OR(A158="",B158=""),"",IFERROR(LOOKUP(2,1/(单次交易!$A$2:$A$201=A158),单次交易!$H$2:$H$201),0)+SUMIFS($G$2:$G$1001,$A$2:$A$1001,A158,$B$2:$B$1001,"<"&B158)) -> 16800 | J158: =IF(OR(A158="",B158=""),"",IFERROR(LOOKUP(2,1/(单次交易!$A$2:$A$201=A158),单次交易!$E$2:$E$201)*LOOKUP(2,1/(单次交易!$A$2:$A$201=A158),单次交易!$H$2:$H$201),0)+SUMIFS($H$2:$H$1001,$A$2:$A$1001,A158,$B$2:$B$1001,"<"&B158)) -> 569328 | K158: =IF(OR(E158="",I158="",J158=""),"",MAX(E158*I158-J158,0)) -> 18672 | L158: =IF(OR(D158="",E158="",F158="",D158<=E158),"",FLOOR((F158+K158)/(D158-E158),100)) -> 13600 | M158: =IF(OR(A158="",B158="",L158=""),"",IF(B158=1,L158,IFERROR(SUMIFS($G$2:$G$1001,$A$2:$A$1001,A158,$B$2:$B$1001,B158-1),0))) -> 5000 | N158: =IF(OR(L158="",M158=""),"",MIN(L158,M158)) -> 5000 | O158: =IF(OR(I158="",G158=""),"",I158+G158) -> 19300 | P158: =IF(OR(O158="",O158=0),"",(J158+H158)/O158) -> 34.21 | Q158: =IF(OR(O158="",E158=""),"",MAX(J158+H158-E158*O158,0)) -> 0 | R158: =IF(A158="","",IF(COUNTIF(_TradeIds,A158)=0,"违规：交易编号不存在",IF(OR(B158="",B158<1,B158>5,B158<>INT(B158)),"违规：加仓序号须为1到5的整数",IF(COUNTIFS($A$2:$A$1001,A158,$B$2:$B$1001,B158)>1,"违规：同一交易的加仓序号重复",IF(OR(D158="",E158="",F158=""),"计划不完整：请填写加仓价、新止损价和风险预算",IF(OR(D158<=0,E158<=0,F158<=0,D158<=E158),"违规：加仓价必须高于新止损价，金额须大于0",IF(AND(B158>1,COUNTIFS($A$2:$A$1001,A158,$B$2:$B$1001,B158-1,$G$2:$G$1001,">0")=0),"违规：须先完成上一次加仓",IF(AND(B158>1,E158<SUMIFS($E$2:$E$1001,$A$2:$A$1001,A158,$B$2:$B$1001,B158-1)),"违规：新止损价不得低于上一次",IF(AND(B158>1,F158>SUMIFS($F$2:$F$1001,$A$2:$A$1001,A158,$B$2:$B$1001,B158-1)),"违规：风险预算须逐次不增加",IF(OR(_LockStatus="已锁仓",_LockStatus="解锁信息不完整"),"违规：锁仓期间禁止加仓",IF(G158="","计划可执行：建议股数见N列",IF(OR(G158<=0,G158<>INT(G158),MOD(G158,100)<>0),"违规：实际股数须为100股整数倍",IF(G158>N158,"违规：实际股数超过风险或金字塔上限",IF(AND(B158>1,G158>SUMIFS($G$2:$G$1001,$A$2:$A$1001,A158,$B$2:$B$1001,B158-1)),"违规：加仓股数须逐次不增加",IF(Q158>F158,"违规：止损风险超过本次预算","通过"))))))))))))))) -> 通过
A159: 72 | B159: 1 | C159: 46184 | D159: 38.08 | E159: 36 | F159: 1 | G159: 2500 | H159: =IF(OR(A159="",D159="",G159=""),"",D159*G159) -> 95200 | J159: =IF(OR(A159="",B159=""),"",IFERROR(LOOKUP(2,1/(单次交易!$A$2:$A$201=A159),单次交易!$E$2:$E$201)*LOOKUP(2,1/(单次交易!$A$2:$A$201=A159),单次交易!$H$2:$H$201),0)+SUMIFS($H$2:$H$1001,$A$2:$A$1001,A159,$B$2:$B$1001,"<"&B159)) -> 370600 | K159: =IF(OR(E159="",I159="",J159=""),"",MAX(E159*I159-J159,0)) -> #VALUE! | L159: =IF(OR(D159="",E159="",F159="",D159<=E159),"",FLOOR((F159+K159)/(D159-E159),100)) -> #VALUE! | M159: =IF(OR(A159="",B159="",L159=""),"",IF(B159=1,L159,IFERROR(SUMIFS($G$2:$G$1001,$A$2:$A$1001,A159,$B$2:$B$1001,B159-1),0))) -> #VALUE! | N159: =IF(OR(L159="",M159=""),"",MIN(L159,M159)) -> #VALUE! | O159: =IF(OR(I159="",G159=""),"",I159+G159) -> #VALUE! | P159: =IF(OR(O159="",O159=0),"",(J159+H159)/O159) -> #VALUE! | Q159: =IF(OR(O159="",E159=""),"",MAX(J159+H159-E159*O159,0)) -> #VALUE! | R159: =IF(A159="","",IF(COUNTIF(_TradeIds,A159)=0,"违规：交易编号不存在",IF(OR(B159="",B159<1,B159>5,B159<>INT(B159)),"违规：加仓序号须为1到5的整数",IF(COUNTIFS($A$2:$A$1001,A159,$B$2:$B$1001,B159)>1,"违规：同一交易的加仓序号重复",IF(OR(D159="",E159="",F159=""),"计划不完整：请填写加仓价、新止损价和风险预算",IF(OR(D159<=0,E159<=0,F159<=0,D159<=E159),"违规：加仓价必须高于新止损价，金额须大于0",IF(AND(B159>1,COUNTIFS($A$2:$A$1001,A159,$B$2:$B$1001,B159-1,$G$2:$G$1001,">0")=0),"违规：须先完成上一次加仓",IF(AND(B159>1,E159<SUMIFS($E$2:$E$1001,$A$2:$A$1001,A159,$B$2:$B$1001,B159-1)),"违规：新止损价不得低于上一次",IF(AND(B159>1,F159>SUMIFS($F$2:$F$1001,$A$2:$A$1001,A159,$B$2:$B$1001,B159-1)),"违规：风险预算须逐次不增加",IF(OR(_LockStatus="已锁仓",_LockStatus="解锁信息不完整"),"违规：锁仓期间禁止加仓",IF(G159="","计划可执行：建议股数见N列",IF(OR(G159<=0,G159<>INT(G159),MOD(G159,100)<>0),"违规：实际股数须为100股整数倍",IF(G159>N159,"违规：实际股数超过风险或金字塔上限",IF(AND(B159>1,G159>SUMIFS($G$2:$G$1001,$A$2:$A$1001,A159,$B$2:$B$1001,B159-1)),"违规：加仓股数须逐次不增加",IF(Q159>F159,"违规：止损风险超过本次预算","通过"))))))))))))))) -> #VALUE!
A160: 72 | B160: 2 | C160: 46220 | D160: 35.62 | E160: 33 | F160: 1 | G160: 5000 | H160: =IF(OR(A160="",D160="",G160=""),"",D160*G160) -> 178100 | I160: =IF(OR(A160="",B160=""),"",IFERROR(LOOKUP(2,1/(单次交易!$A$2:$A$201=A160),单次交易!$H$2:$H$201),0)+SUMIFS($G$2:$G$1001,$A$2:$A$1001,A160,$B$2:$B$1001,"<"&B160)) -> 12500 | J160: =IF(OR(A160="",B160=""),"",IFERROR(LOOKUP(2,1/(单次交易!$A$2:$A$201=A160),单次交易!$E$2:$E$201)*LOOKUP(2,1/(单次交易!$A$2:$A$201=A160),单次交易!$H$2:$H$201),0)+SUMIFS($H$2:$H$1001,$A$2:$A$1001,A160,$B$2:$B$1001,"<"&B160)) -> 465800 | K160: =IF(OR(E160="",I160="",J160=""),"",MAX(E160*I160-J160,0)) -> 0 | L160: =IF(OR(D160="",E160="",F160="",D160<=E160),"",FLOOR((F160+K160)/(D160-E160),100)) -> 0 | M160: =IF(OR(A160="",B160="",L160=""),"",IF(B160=1,L160,IFERROR(SUMIFS($G$2:$G$1001,$A$2:$A$1001,A160,$B$2:$B$1001,B160-1),0))) -> 2500 | N160: =IF(OR(L160="",M160=""),"",MIN(L160,M160)) -> 0 | O160: =IF(OR(I160="",G160=""),"",I160+G160) -> 17500 | P160: =IF(OR(O160="",O160=0),"",(J160+H160)/O160) -> 36.794286 | Q160: =IF(OR(O160="",E160=""),"",MAX(J160+H160-E160*O160,0)) -> 66400 | R160: =IF(A160="","",IF(COUNTIF(_TradeIds,A160)=0,"违规：交易编号不存在",IF(OR(B160="",B160<1,B160>5,B160<>INT(B160)),"违规：加仓序号须为1到5的整数",IF(COUNTIFS($A$2:$A$1001,A160,$B$2:$B$1001,B160)>1,"违规：同一交易的加仓序号重复",IF(OR(D160="",E160="",F160=""),"计划不完整：请填写加仓价、新止损价和风险预算",IF(OR(D160<=0,E160<=0,F160<=0,D160<=E160),"违规：加仓价必须高于新止损价，金额须大于0",IF(AND(B160>1,COUNTIFS($A$2:$A$1001,A160,$B$2:$B$1001,B160-1,$G$2:$G$1001,">0")=0),"违规：须先完成上一次加仓",IF(AND(B160>1,E160<SUMIFS($E$2:$E$1001,$A$2:$A$1001,A160,$B$2:$B$1001,B160-1)),"违规：新止损价不得低于上一次",IF(AND(B160>1,F160>SUMIFS($F$2:$F$1001,$A$2:$A$1001,A160,$B$2:$B$1001,B160-1)),"违规：风险预算须逐次不增加",IF(OR(_LockStatus="已锁仓",_LockStatus="解锁信息不完整"),"违规：锁仓期间禁止加仓",IF(G160="","计划可执行：建议股数见N列",IF(OR(G160<=0,G160<>INT(G160),MOD(G160,100)<>0),"违规：实际股数须为100股整数倍",IF(G160>N160,"违规：实际股数超过风险或金字塔上限",IF(AND(B160>1,G160>SUMIFS($G$2:$G$1001,$A$2:$A$1001,A160,$B$2:$B$1001,B160-1)),"违规：加仓股数须逐次不增加",IF(Q160>F160,"违规：止损风险超过本次预算","通过"))))))))))))))) -> 违规：新止损价不得低于上一次
A161: 74 | B161: 1 | C161: 42108 | D161: 2.41 | E161: 2.1 | F161: 1 | G161: 25000 | H161: =IF(OR(A161="",D161="",G161=""),"",D161*G161) -> 60250 | I161: =IF(OR(A161="",B161=""),"",IFERROR(LOOKUP(2,1/(单次交易!$A$2:$A$201=A161),单次交易!$H$2:$H$201),0)+SUMIFS($G$2:$G$1001,$A$2:$A$1001,A161,$B$2:$B$1001,"<"&B161)) -> 58700 | J161: =IF(OR(A161="",B161=""),"",IFERROR(LOOKUP(2,1/(单次交易!$A$2:$A$201=A161),单次交易!$E$2:$E$201)*LOOKUP(2,1/(单次交易!$A$2:$A$201=A161),单次交易!$H$2:$H$201),0)+SUMIFS($H$2:$H$1001,$A$2:$A$1001,A161,$B$2:$B$1001,"<"&B161)) -> 125031 | K161: =IF(OR(E161="",I161="",J161=""),"",MAX(E161*I161-J161,0)) -> 0 | L161: =IF(OR(D161="",E161="",F161="",D161<=E161),"",FLOOR((F161+K161)/(D161-E161),100)) -> 0 | M161: =IF(OR(A161="",B161="",L161=""),"",IF(B161=1,L161,IFERROR(SUMIFS($G$2:$G$1001,$A$2:$A$1001,A161,$B$2:$B$1001,B161-1),0))) -> 0 | N161: =IF(OR(L161="",M161=""),"",MIN(L161,M161)) -> 0 | O161: =IF(OR(I161="",G161=""),"",I161+G161) -> 83700 | P161: =IF(OR(O161="",O161=0),"",(J161+H161)/O161) -> 2.213632 | Q161: =IF(OR(O161="",E161=""),"",MAX(J161+H161-E161*O161,0)) -> 9511 | R161: =IF(A161="","",IF(COUNTIF(_TradeIds,A161)=0,"违规：交易编号不存在",IF(OR(B161="",B161<1,B161>5,B161<>INT(B161)),"违规：加仓序号须为1到5的整数",IF(COUNTIFS($A$2:$A$1001,A161,$B$2:$B$1001,B161)>1,"违规：同一交易的加仓序号重复",IF(OR(D161="",E161="",F161=""),"计划不完整：请填写加仓价、新止损价和风险预算",IF(OR(D161<=0,E161<=0,F161<=0,D161<=E161),"违规：加仓价必须高于新止损价，金额须大于0",IF(AND(B161>1,COUNTIFS($A$2:$A$1001,A161,$B$2:$B$1001,B161-1,$G$2:$G$1001,">0")=0),"违规：须先完成上一次加仓",IF(AND(B161>1,E161<SUMIFS($E$2:$E$1001,$A$2:$A$1001,A161,$B$2:$B$1001,B161-1)),"违规：新止损价不得低于上一次",IF(AND(B161>1,F161>SUMIFS($F$2:$F$1001,$A$2:$A$1001,A161,$B$2:$B$1001,B161-1)),"违规：风险预算须逐次不增加",IF(OR(_LockStatus="已锁仓",_LockStatus="解锁信息不完整"),"违规：锁仓期间禁止加仓",IF(G161="","计划可执行：建议股数见N列",IF(OR(G161<=0,G161<>INT(G161),MOD(G161,100)<>0),"违规：实际股数须为100股整数倍",IF(G161>N161,"违规：实际股数超过风险或金字塔上限",IF(AND(B161>1,G161>SUMIFS($G$2:$G$1001,$A$2:$A$1001,A161,$B$2:$B$1001,B161-1)),"违规：加仓股数须逐次不增加",IF(Q161>F161,"违规：止损风险超过本次预算","通过"))))))))))))))) -> 违规：实际股数超过风险或金字塔上限
A162: 74 | B162: 2 | C162: 42109 | D162: 2.52 | E162: 2.2 | F162: 1 | G162: 50000 | H162: =IF(OR(A162="",D162="",G162=""),"",D162*G162) -> 126000 | I162: =IF(OR(A162="",B162=""),"",IFERROR(LOOKUP(2,1/(单次交易!$A$2:$A$201=A162),单次交易!$H$2:$H$201),0)+SUMIFS($G$2:$G$1001,$A$2:$A$1001,A162,$B$2:$B$1001,"<"&B162)) -> 83700 | J162: =IF(OR(A162="",B162=""),"",IFERROR(LOOKUP(2,1/(单次交易!$A$2:$A$201=A162),单次交易!$E$2:$E$201)*LOOKUP(2,1/(单次交易!$A$2:$A$201=A162),单次交易!$H$2:$H$201),0)+SUMIFS($H$2:$H$1001,$A$2:$A$1001,A162,$B$2:$B$1001,"<"&B162)) -> 185281 | K162: =IF(OR(E162="",I162="",J162=""),"",MAX(E162*I162-J162,0)) -> 0 | L162: =IF(OR(D162="",E162="",F162="",D162<=E162),"",FLOOR((F162+K162)/(D162-E162),100)) -> 0 | M162: =IF(OR(A162="",B162="",L162=""),"",IF(B162=1,L162,IFERROR(SUMIFS($G$2:$G$1001,$A$2:$A$1001,A162,$B$2:$B$1001,B162-1),0))) -> 25000 | N162: =IF(OR(L162="",M162=""),"",MIN(L162,M162)) -> 0 | O162: =IF(OR(I162="",G162=""),"",I162+G162) -> 133700 | P162: =IF(OR(O162="",O162=0),"",(J162+H162)/O162) -> 2.3282049 | Q162: =IF(OR(O162="",E162=""),"",MAX(J162+H162-E162*O162,0)) -> 17141 | R162: =IF(A162="","",IF(COUNTIF(_TradeIds,A162)=0,"违规：交易编号不存在",IF(OR(B162="",B162<1,B162>5,B162<>INT(B162)),"违规：加仓序号须为1到5的整数",IF(COUNTIFS($A$2:$A$1001,A162,$B$2:$B$1001,B162)>1,"违规：同一交易的加仓序号重复",IF(OR(D162="",E162="",F162=""),"计划不完整：请填写加仓价、新止损价和风险预算",IF(OR(D162<=0,E162<=0,F162<=0,D162<=E162),"违规：加仓价必须高于新止损价，金额须大于0",IF(AND(B162>1,COUNTIFS($A$2:$A$1001,A162,$B$2:$B$1001,B162-1,$G$2:$G$1001,">0")=0),"违规：须先完成上一次加仓",IF(AND(B162>1,E162<SUMIFS($E$2:$E$1001,$A$2:$A$1001,A162,$B$2:$B$1001,B162-1)),"违规：新止损价不得低于上一次",IF(AND(B162>1,F162>SUMIFS($F$2:$F$1001,$A$2:$A$1001,A162,$B$2:$B$1001,B162-1)),"违规：风险预算须逐次不增加",IF(OR(_LockStatus="已锁仓",_LockStatus="解锁信息不完整"),"违规：锁仓期间禁止加仓",IF(G162="","计划可执行：建议股数见N列",IF(OR(G162<=0,G162<>INT(G162),MOD(G162,100)<>0),"违规：实际股数须为100股整数倍",IF(G162>N162,"违规：实际股数超过风险或金字塔上限",IF(AND(B162>1,G162>SUMIFS($G$2:$G$1001,$A$2:$A$1001,A162,$B$2:$B$1001,B162-1)),"违规：加仓股数须逐次不增加",IF(Q162>F162,"违规：止损风险超过本次预算","通过"))))))))))))))) -> 违规：实际股数超过风险或金字塔上限
A163: 75 | B163: 1 | C163: 42146 | D163: 2.72 | E163: 2.5 | F163: 1 | G163: 25000 | H163: =IF(OR(A163="",D163="",G163=""),"",D163*G163) -> 68000 | I163: =IF(OR(A163="",B163=""),"",IFERROR(LOOKUP(2,1/(单次交易!$A$2:$A$201=A163),单次交易!$H$2:$H$201),0)+SUMIFS($G$2:$G$1001,$A$2:$A$1001,A163,$B$2:$B$1001,"<"&B163)) -> 71600 | J163: =IF(OR(A163="",B163=""),"",IFERROR(LOOKUP(2,1/(单次交易!$A$2:$A$201=A163),单次交易!$E$2:$E$201)*LOOKUP(2,1/(单次交易!$A$2:$A$201=A163),单次交易!$H$2:$H$201),0)+SUMIFS($H$2:$H$1001,$A$2:$A$1001,A163,$B$2:$B$1001,"<"&B163)) -> 186876 | K163: =IF(OR(E163="",I163="",J163=""),"",MAX(E163*I163-J163,0)) -> 0 | L163: =IF(OR(D163="",E163="",F163="",D163<=E163),"",FLOOR((F163+K163)/(D163-E163),100)) -> 0 | M163: =IF(OR(A163="",B163="",L163=""),"",IF(B163=1,L163,IFERROR(SUMIFS($G$2:$G$1001,$A$2:$A$1001,A163,$B$2:$B$1001,B163-1),0))) -> 0 | N163: =IF(OR(L163="",M163=""),"",MIN(L163,M163)) -> 0 | O163: =IF(OR(I163="",G163=""),"",I163+G163) -> 96600 | P163: =IF(OR(O163="",O163=0),"",(J163+H163)/O163) -> 2.6384679 | Q163: =IF(OR(O163="",E163=""),"",MAX(J163+H163-E163*O163,0)) -> 13376 | R163: =IF(A163="","",IF(COUNTIF(_TradeIds,A163)=0,"违规：交易编号不存在",IF(OR(B163="",B163<1,B163>5,B163<>INT(B163)),"违规：加仓序号须为1到5的整数",IF(COUNTIFS($A$2:$A$1001,A163,$B$2:$B$1001,B163)>1,"违规：同一交易的加仓序号重复",IF(OR(D163="",E163="",F163=""),"计划不完整：请填写加仓价、新止损价和风险预算",IF(OR(D163<=0,E163<=0,F163<=0,D163<=E163),"违规：加仓价必须高于新止损价，金额须大于0",IF(AND(B163>1,COUNTIFS($A$2:$A$1001,A163,$B$2:$B$1001,B163-1,$G$2:$G$1001,">0")=0),"违规：须先完成上一次加仓",IF(AND(B163>1,E163<SUMIFS($E$2:$E$1001,$A$2:$A$1001,A163,$B$2:$B$1001,B163-1)),"违规：新止损价不得低于上一次",IF(AND(B163>1,F163>SUMIFS($F$2:$F$1001,$A$2:$A$1001,A163,$B$2:$B$1001,B163-1)),"违规：风险预算须逐次不增加",IF(OR(_LockStatus="已锁仓",_LockStatus="解锁信息不完整"),"违规：锁仓期间禁止加仓",IF(G163="","计划可执行：建议股数见N列",IF(OR(G163<=0,G163<>INT(G163),MOD(G163,100)<>0),"违规：实际股数须为100股整数倍",IF(G163>N163,"违规：实际股数超过风险或金字塔上限",IF(AND(B163>1,G163>SUMIFS($G$2:$G$1001,$A$2:$A$1001,A163,$B$2:$B$1001,B163-1)),"违规：加仓股数须逐次不增加",IF(Q163>F163,"违规：止损风险超过本次预算","通过"))))))))))))))) -> 违规：实际股数超过风险或金字塔上限
A164: 75 | B164: 2 | C164: 42152 | D164: 2.73 | E164: 2.5 | F164: 1 | G164: 25000 | H164: =IF(OR(A164="",D164="",G164=""),"",D164*G164) -> 68250 | I164: =IF(OR(A164="",B164=""),"",IFERROR(LOOKUP(2,1/(单次交易!$A$2:$A$201=A164),单次交易!$H$2:$H$201),0)+SUMIFS($G$2:$G$1001,$A$2:$A$1001,A164,$B$2:$B$1001,"<"&B164)) -> 96600 | J164: =IF(OR(A164="",B164=""),"",IFERROR(LOOKUP(2,1/(单次交易!$A$2:$A$201=A164),单次交易!$E$2:$E$201)*LOOKUP(2,1/(单次交易!$A$2:$A$201=A164),单次交易!$H$2:$H$201),0)+SUMIFS($H$2:$H$1001,$A$2:$A$1001,A164,$B$2:$B$1001,"<"&B164)) -> 254876 | K164: =IF(OR(E164="",I164="",J164=""),"",MAX(E164*I164-J164,0)) -> 0 | L164: =IF(OR(D164="",E164="",F164="",D164<=E164),"",FLOOR((F164+K164)/(D164-E164),100)) -> 0 | M164: =IF(OR(A164="",B164="",L164=""),"",IF(B164=1,L164,IFERROR(SUMIFS($G$2:$G$1001,$A$2:$A$1001,A164,$B$2:$B$1001,B164-1),0))) -> 25000 | N164: =IF(OR(L164="",M164=""),"",MIN(L164,M164)) -> 0 | O164: =IF(OR(I164="",G164=""),"",I164+G164) -> 121600 | P164: =IF(OR(O164="",O164=0),"",(J164+H164)/O164) -> 2.6572862 | Q164: =IF(OR(O164="",E164=""),"",MAX(J164+H164-E164*O164,0)) -> 19126 | R164: =IF(A164="","",IF(COUNTIF(_TradeIds,A164)=0,"违规：交易编号不存在",IF(OR(B164="",B164<1,B164>5,B164<>INT(B164)),"违规：加仓序号须为1到5的整数",IF(COUNTIFS($A$2:$A$1001,A164,$B$2:$B$1001,B164)>1,"违规：同一交易的加仓序号重复",IF(OR(D164="",E164="",F164=""),"计划不完整：请填写加仓价、新止损价和风险预算",IF(OR(D164<=0,E164<=0,F164<=0,D164<=E164),"违规：加仓价必须高于新止损价，金额须大于0",IF(AND(B164>1,COUNTIFS($A$2:$A$1001,A164,$B$2:$B$1001,B164-1,$G$2:$G$1001,">0")=0),"违规：须先完成上一次加仓",IF(AND(B164>1,E164<SUMIFS($E$2:$E$1001,$A$2:$A$1001,A164,$B$2:$B$1001,B164-1)),"违规：新止损价不得低于上一次",IF(AND(B164>1,F164>SUMIFS($F$2:$F$1001,$A$2:$A$1001,A164,$B$2:$B$1001,B164-1)),"违规：风险预算须逐次不增加",IF(OR(_LockStatus="已锁仓",_LockStatus="解锁信息不完整"),"违规：锁仓期间禁止加仓",IF(G164="","计划可执行：建议股数见N列",IF(OR(G164<=0,G164<>INT(G164),MOD(G164,100)<>0),"违规：实际股数须为100股整数倍",IF(G164>N164,"违规：实际股数超过风险或金字塔上限",IF(AND(B164>1,G164>SUMIFS($G$2:$G$1001,$A$2:$A$1001,A164,$B$2:$B$1001,B164-1)),"违规：加仓股数须逐次不增加",IF(Q164>F164,"违规：止损风险超过本次预算","通过"))))))))))))))) -> 违规：实际股数超过风险或金字塔上限
A165: 75 | B165: 3 | C165: 42156 | D165: 3.5 | E165: 3.2 | F165: 1 | G165: 25000 | H165: =IF(OR(A165="",D165="",G165=""),"",D165*G165) -> 87500 | I165: =IF(OR(A165="",B165=""),"",IFERROR(LOOKUP(2,1/(单次交易!$A$2:$A$201=A165),单次交易!$H$2:$H$201),0)+SUMIFS($G$2:$G$1001,$A$2:$A$1001,A165,$B$2:$B$1001,"<"&B165)) -> 121600 | J165: =IF(OR(A165="",B165=""),"",IFERROR(LOOKUP(2,1/(单次交易!$A$2:$A$201=A165),单次交易!$E$2:$E$201)*LOOKUP(2,1/(单次交易!$A$2:$A$201=A165),单次交易!$H$2:$H$201),0)+SUMIFS($H$2:$H$1001,$A$2:$A$1001,A165,$B$2:$B$1001,"<"&B165)) -> 323126 | K165: =IF(OR(E165="",I165="",J165=""),"",MAX(E165*I165-J165,0)) -> 65994 | L165: =IF(OR(D165="",E165="",F165="",D165<=E165),"",FLOOR((F165+K165)/(D165-E165),100)) -> 219900 | M165: =IF(OR(A165="",B165="",L165=""),"",IF(B165=1,L165,IFERROR(SUMIFS($G$2:$G$1001,$A$2:$A$1001,A165,$B$2:$B$1001,B165-1),0))) -> 25000 | N165: =IF(OR(L165="",M165=""),"",MIN(L165,M165)) -> 25000 | O165: =IF(OR(I165="",G165=""),"",I165+G165) -> 146600 | P165: =IF(OR(O165="",O165=0),"",(J165+H165)/O165) -> 2.8009959 | Q165: =IF(OR(O165="",E165=""),"",MAX(J165+H165-E165*O165,0)) -> 0 | R165: =IF(A165="","",IF(COUNTIF(_TradeIds,A165)=0,"违规：交易编号不存在",IF(OR(B165="",B165<1,B165>5,B165<>INT(B165)),"违规：加仓序号须为1到5的整数",IF(COUNTIFS($A$2:$A$1001,A165,$B$2:$B$1001,B165)>1,"违规：同一交易的加仓序号重复",IF(OR(D165="",E165="",F165=""),"计划不完整：请填写加仓价、新止损价和风险预算",IF(OR(D165<=0,E165<=0,F165<=0,D165<=E165),"违规：加仓价必须高于新止损价，金额须大于0",IF(AND(B165>1,COUNTIFS($A$2:$A$1001,A165,$B$2:$B$1001,B165-1,$G$2:$G$1001,">0")=0),"违规：须先完成上一次加仓",IF(AND(B165>1,E165<SUMIFS($E$2:$E$1001,$A$2:$A$1001,A165,$B$2:$B$1001,B165-1)),"违规：新止损价不得低于上一次",IF(AND(B165>1,F165>SUMIFS($F$2:$F$1001,$A$2:$A$1001,A165,$B$2:$B$1001,B165-1)),"违规：风险预算须逐次不增加",IF(OR(_LockStatus="已锁仓",_LockStatus="解锁信息不完整"),"违规：锁仓期间禁止加仓",IF(G165="","计划可执行：建议股数见N列",IF(OR(G165<=0,G165<>INT(G165),MOD(G165,100)<>0),"违规：实际股数须为100股整数倍",IF(G165>N165,"违规：实际股数超过风险或金字塔上限",IF(AND(B165>1,G165>SUMIFS($G$2:$G$1001,$A$2:$A$1001,A165,$B$2:$B$1001,B165-1)),"违规：加仓股数须逐次不增加",IF(Q165>F165,"违规：止损风险超过本次预算","通过"))))))))))))))) -> 通过
A166: 78 | B166: 1 | C166: 42192 | D166: 2.49 | E166: 2.2 | F166: 1 | G166: 50000 | H166: =IF(OR(A166="",D166="",G166=""),"",D166*G166) -> 124500 | I166: =IF(OR(A166="",B166=""),"",IFERROR(LOOKUP(2,1/(单次交易!$A$2:$A$201=A166),单次交易!$H$2:$H$201),0)+SUMIFS($G$2:$G$1001,$A$2:$A$1001,A166,$B$2:$B$1001,"<"&B166)) -> 58300 | J166: =IF(OR(A166="",B166=""),"",IFERROR(LOOKUP(2,1/(单次交易!$A$2:$A$201=A166),单次交易!$E$2:$E$201)*LOOKUP(2,1/(单次交易!$A$2:$A$201=A166),单次交易!$H$2:$H$201),0)+SUMIFS($H$2:$H$1001,$A$2:$A$1001,A166,$B$2:$B$1001,"<"&B166)) -> 167321 | K166: =IF(OR(E166="",I166="",J166=""),"",MAX(E166*I166-J166,0)) -> 0 | L166: =IF(OR(D166="",E166="",F166="",D166<=E166),"",FLOOR((F166+K166)/(D166-E166),100)) -> 0 | M166: =IF(OR(A166="",B166="",L166=""),"",IF(B166=1,L166,IFERROR(SUMIFS($G$2:$G$1001,$A$2:$A$1001,A166,$B$2:$B$1001,B166-1),0))) -> 0 | N166: =IF(OR(L166="",M166=""),"",MIN(L166,M166)) -> 0 | O166: =IF(OR(I166="",G166=""),"",I166+G166) -> 108300 | P166: =IF(OR(O166="",O166=0),"",(J166+H166)/O166) -> 2.6945614 | Q166: =IF(OR(O166="",E166=""),"",MAX(J166+H166-E166*O166,0)) -> 53561 | R166: =IF(A166="","",IF(COUNTIF(_TradeIds,A166)=0,"违规：交易编号不存在",IF(OR(B166="",B166<1,B166>5,B166<>INT(B166)),"违规：加仓序号须为1到5的整数",IF(COUNTIFS($A$2:$A$1001,A166,$B$2:$B$1001,B166)>1,"违规：同一交易的加仓序号重复",IF(OR(D166="",E166="",F166=""),"计划不完整：请填写加仓价、新止损价和风险预算",IF(OR(D166<=0,E166<=0,F166<=0,D166<=E166),"违规：加仓价必须高于新止损价，金额须大于0",IF(AND(B166>1,COUNTIFS($A$2:$A$1001,A166,$B$2:$B$1001,B166-1,$G$2:$G$1001,">0")=0),"违规：须先完成上一次加仓",IF(AND(B166>1,E166<SUMIFS($E$2:$E$1001,$A$2:$A$1001,A166,$B$2:$B$1001,B166-1)),"违规：新止损价不得低于上一次",IF(AND(B166>1,F166>SUMIFS($F$2:$F$1001,$A$2:$A$1001,A166,$B$2:$B$1001,B166-1)),"违规：风险预算须逐次不增加",IF(OR(_LockStatus="已锁仓",_LockStatus="解锁信息不完整"),"违规：锁仓期间禁止加仓",IF(G166="","计划可执行：建议股数见N列",IF(OR(G166<=0,G166<>INT(G166),MOD(G166,100)<>0),"违规：实际股数须为100股整数倍",IF(G166>N166,"违规：实际股数超过风险或金字塔上限",IF(AND(B166>1,G166>SUMIFS($G$2:$G$1001,$A$2:$A$1001,A166,$B$2:$B$1001,B166-1)),"违规：加仓股数须逐次不增加",IF(Q166>F166,"违规：止损风险超过本次预算","通过"))))))))))))))) -> 违规：实际股数超过风险或金字塔上限
A167: 78 | B167: 2 | C167: 42195 | D167: 2.82 | E167: 2.5 | F167: 1 | G167: 25000 | H167: =IF(OR(A167="",D167="",G167=""),"",D167*G167) -> 70500 | I167: =IF(OR(A167="",B167=""),"",IFERROR(LOOKUP(2,1/(单次交易!$A$2:$A$201=A167),单次交易!$H$2:$H$201),0)+SUMIFS($G$2:$G$1001,$A$2:$A$1001,A167,$B$2:$B$1001,"<"&B167)) -> 108300 | J167: =IF(OR(A167="",B167=""),"",IFERROR(LOOKUP(2,1/(单次交易!$A$2:$A$201=A167),单次交易!$E$2:$E$201)*LOOKUP(2,1/(单次交易!$A$2:$A$201=A167),单次交易!$H$2:$H$201),0)+SUMIFS($H$2:$H$1001,$A$2:$A$1001,A167,$B$2:$B$1001,"<"&B167)) -> 291821 | K167: =IF(OR(E167="",I167="",J167=""),"",MAX(E167*I167-J167,0)) -> 0 | L167: =IF(OR(D167="",E167="",F167="",D167<=E167),"",FLOOR((F167+K167)/(D167-E167),100)) -> 0 | M167: =IF(OR(A167="",B167="",L167=""),"",IF(B167=1,L167,IFERROR(SUMIFS($G$2:$G$1001,$A$2:$A$1001,A167,$B$2:$B$1001,B167-1),0))) -> 50000 | N167: =IF(OR(L167="",M167=""),"",MIN(L167,M167)) -> 0 | O167: =IF(OR(I167="",G167=""),"",I167+G167) -> 133300 | P167: =IF(OR(O167="",O167=0),"",(J167+H167)/O167) -> 2.718087 | Q167: =IF(OR(O167="",E167=""),"",MAX(J167+H167-E167*O167,0)) -> 29071 | R167: =IF(A167="","",IF(COUNTIF(_TradeIds,A167)=0,"违规：交易编号不存在",IF(OR(B167="",B167<1,B167>5,B167<>INT(B167)),"违规：加仓序号须为1到5的整数",IF(COUNTIFS($A$2:$A$1001,A167,$B$2:$B$1001,B167)>1,"违规：同一交易的加仓序号重复",IF(OR(D167="",E167="",F167=""),"计划不完整：请填写加仓价、新止损价和风险预算",IF(OR(D167<=0,E167<=0,F167<=0,D167<=E167),"违规：加仓价必须高于新止损价，金额须大于0",IF(AND(B167>1,COUNTIFS($A$2:$A$1001,A167,$B$2:$B$1001,B167-1,$G$2:$G$1001,">0")=0),"违规：须先完成上一次加仓",IF(AND(B167>1,E167<SUMIFS($E$2:$E$1001,$A$2:$A$1001,A167,$B$2:$B$1001,B167-1)),"违规：新止损价不得低于上一次",IF(AND(B167>1,F167>SUMIFS($F$2:$F$1001,$A$2:$A$1001,A167,$B$2:$B$1001,B167-1)),"违规：风险预算须逐次不增加",IF(OR(_LockStatus="已锁仓",_LockStatus="解锁信息不完整"),"违规：锁仓期间禁止加仓",IF(G167="","计划可执行：建议股数见N列",IF(OR(G167<=0,G167<>INT(G167),MOD(G167,100)<>0),"违规：实际股数须为100股整数倍",IF(G167>N167,"违规：实际股数超过风险或金字塔上限",IF(AND(B167>1,G167>SUMIFS($G$2:$G$1001,$A$2:$A$1001,A167,$B$2:$B$1001,B167-1)),"违规：加仓股数须逐次不增加",IF(Q167>F167,"违规：止损风险超过本次预算","通过"))))))))))))))) -> 违规：实际股数超过风险或金字塔上限
A168: 78 | B168: 3 | C168: 42200 | D168: 2.86 | E168: 2.5 | F168: 1 | G168: 25000 | H168: =IF(OR(A168="",D168="",G168=""),"",D168*G168) -> 71500 | I168: =IF(OR(A168="",B168=""),"",IFERROR(LOOKUP(2,1/(单次交易!$A$2:$A$201=A168),单次交易!$H$2:$H$201),0)+SUMIFS($G$2:$G$1001,$A$2:$A$1001,A168,$B$2:$B$1001,"<"&B168)) -> 133300 | J168: =IF(OR(A168="",B168=""),"",IFERROR(LOOKUP(2,1/(单次交易!$A$2:$A$201=A168),单次交易!$E$2:$E$201)*LOOKUP(2,1/(单次交易!$A$2:$A$201=A168),单次交易!$H$2:$H$201),0)+SUMIFS($H$2:$H$1001,$A$2:$A$1001,A168,$B$2:$B$1001,"<"&B168)) -> 362321 | K168: =IF(OR(E168="",I168="",J168=""),"",MAX(E168*I168-J168,0)) -> 0 | L168: =IF(OR(D168="",E168="",F168="",D168<=E168),"",FLOOR((F168+K168)/(D168-E168),100)) -> 0 | M168: =IF(OR(A168="",B168="",L168=""),"",IF(B168=1,L168,IFERROR(SUMIFS($G$2:$G$1001,$A$2:$A$1001,A168,$B$2:$B$1001,B168-1),0))) -> 25000 | N168: =IF(OR(L168="",M168=""),"",MIN(L168,M168)) -> 0 | O168: =IF(OR(I168="",G168=""),"",I168+G168) -> 158300 | P168: =IF(OR(O168="",O168=0),"",(J168+H168)/O168) -> 2.7404991 | Q168: =IF(OR(O168="",E168=""),"",MAX(J168+H168-E168*O168,0)) -> 38071 | R168: =IF(A168="","",IF(COUNTIF(_TradeIds,A168)=0,"违规：交易编号不存在",IF(OR(B168="",B168<1,B168>5,B168<>INT(B168)),"违规：加仓序号须为1到5的整数",IF(COUNTIFS($A$2:$A$1001,A168,$B$2:$B$1001,B168)>1,"违规：同一交易的加仓序号重复",IF(OR(D168="",E168="",F168=""),"计划不完整：请填写加仓价、新止损价和风险预算",IF(OR(D168<=0,E168<=0,F168<=0,D168<=E168),"违规：加仓价必须高于新止损价，金额须大于0",IF(AND(B168>1,COUNTIFS($A$2:$A$1001,A168,$B$2:$B$1001,B168-1,$G$2:$G$1001,">0")=0),"违规：须先完成上一次加仓",IF(AND(B168>1,E168<SUMIFS($E$2:$E$1001,$A$2:$A$1001,A168,$B$2:$B$1001,B168-1)),"违规：新止损价不得低于上一次",IF(AND(B168>1,F168>SUMIFS($F$2:$F$1001,$A$2:$A$1001,A168,$B$2:$B$1001,B168-1)),"违规：风险预算须逐次不增加",IF(OR(_LockStatus="已锁仓",_LockStatus="解锁信息不完整"),"违规：锁仓期间禁止加仓",IF(G168="","计划可执行：建议股数见N列",IF(OR(G168<=0,G168<>INT(G168),MOD(G168,100)<>0),"违规：实际股数须为100股整数倍",IF(G168>N168,"违规：实际股数超过风险或金字塔上限",IF(AND(B168>1,G168>SUMIFS($G$2:$G$1001,$A$2:$A$1001,A168,$B$2:$B$1001,B168-1)),"违规：加仓股数须逐次不增加",IF(Q168>F168,"违规：止损风险超过本次预算","通过"))))))))))))))) -> 违规：实际股数超过风险或金字塔上限
A169: 80 | B169: 1 | C169: 42244 | D169: 2.3 | E169: 2.1 | F169: 1 | G169: 25000 | H169: =IF(OR(A169="",D169="",G169=""),"",D169*G169) -> 57500 | I169: =IF(OR(A169="",B169=""),"",IFERROR(LOOKUP(2,1/(单次交易!$A$2:$A$201=A169),单次交易!$H$2:$H$201),0)+SUMIFS($G$2:$G$1001,$A$2:$A$1001,A169,$B$2:$B$1001,"<"&B169)) -> 103300 | J169: =IF(OR(A169="",B169=""),"",IFERROR(LOOKUP(2,1/(单次交易!$A$2:$A$201=A169),单次交易!$E$2:$E$201)*LOOKUP(2,1/(单次交易!$A$2:$A$201=A169),单次交易!$H$2:$H$201),0)+SUMIFS($H$2:$H$1001,$A$2:$A$1001,A169,$B$2:$B$1001,"<"&B169)) -> 200402 | K169: =IF(OR(E169="",I169="",J169=""),"",MAX(E169*I169-J169,0)) -> 16528 | L169: =IF(OR(D169="",E169="",F169="",D169<=E169),"",FLOOR((F169+K169)/(D169-E169),100)) -> 82600 | M169: =IF(OR(A169="",B169="",L169=""),"",IF(B169=1,L169,IFERROR(SUMIFS($G$2:$G$1001,$A$2:$A$1001,A169,$B$2:$B$1001,B169-1),0))) -> 82600 | N169: =IF(OR(L169="",M169=""),"",MIN(L169,M169)) -> 82600 | O169: =IF(OR(I169="",G169=""),"",I169+G169) -> 128300 | P169: =IF(OR(O169="",O169=0),"",(J169+H169)/O169) -> 2.0101481 | Q169: =IF(OR(O169="",E169=""),"",MAX(J169+H169-E169*O169,0)) -> 0 | R169: =IF(A169="","",IF(COUNTIF(_TradeIds,A169)=0,"违规：交易编号不存在",IF(OR(B169="",B169<1,B169>5,B169<>INT(B169)),"违规：加仓序号须为1到5的整数",IF(COUNTIFS($A$2:$A$1001,A169,$B$2:$B$1001,B169)>1,"违规：同一交易的加仓序号重复",IF(OR(D169="",E169="",F169=""),"计划不完整：请填写加仓价、新止损价和风险预算",IF(OR(D169<=0,E169<=0,F169<=0,D169<=E169),"违规：加仓价必须高于新止损价，金额须大于0",IF(AND(B169>1,COUNTIFS($A$2:$A$1001,A169,$B$2:$B$1001,B169-1,$G$2:$G$1001,">0")=0),"违规：须先完成上一次加仓",IF(AND(B169>1,E169<SUMIFS($E$2:$E$1001,$A$2:$A$1001,A169,$B$2:$B$1001,B169-1)),"违规：新止损价不得低于上一次",IF(AND(B169>1,F169>SUMIFS($F$2:$F$1001,$A$2:$A$1001,A169,$B$2:$B$1001,B169-1)),"违规：风险预算须逐次不增加",IF(OR(_LockStatus="已锁仓",_LockStatus="解锁信息不完整"),"违规：锁仓期间禁止加仓",IF(G169="","计划可执行：建议股数见N列",IF(OR(G169<=0,G169<>INT(G169),MOD(G169,100)<>0),"违规：实际股数须为100股整数倍",IF(G169>N169,"违规：实际股数超过风险或金字塔上限",IF(AND(B169>1,G169>SUMIFS($G$2:$G$1001,$A$2:$A$1001,A169,$B$2:$B$1001,B169-1)),"违规：加仓股数须逐次不增加",IF(Q169>F169,"违规：止损风险超过本次预算","通过"))))))))))))))) -> 通过
A170: 80 | B170: 2 | C170: 42249 | D170: 2.46 | E170: 2.2 | F170: 1 | G170: 25000 | H170: =IF(OR(A170="",D170="",G170=""),"",D170*G170) -> 61500 | I170: =IF(OR(A170="",B170=""),"",IFERROR(LOOKUP(2,1/(单次交易!$A$2:$A$201=A170),单次交易!$H$2:$H$201),0)+SUMIFS($G$2:$G$1001,$A$2:$A$1001,A170,$B$2:$B$1001,"<"&B170)) -> 128300 | J170: =IF(OR(A170="",B170=""),"",IFERROR(LOOKUP(2,1/(单次交易!$A$2:$A$201=A170),单次交易!$E$2:$E$201)*LOOKUP(2,1/(单次交易!$A$2:$A$201=A170),单次交易!$H$2:$H$201),0)+SUMIFS($H$2:$H$1001,$A$2:$A$1001,A170,$B$2:$B$1001,"<"&B170)) -> 257902 | K170: =IF(OR(E170="",I170="",J170=""),"",MAX(E170*I170-J170,0)) -> 24358 | L170: =IF(OR(D170="",E170="",F170="",D170<=E170),"",FLOOR((F170+K170)/(D170-E170),100)) -> 93600 | M170: =IF(OR(A170="",B170="",L170=""),"",IF(B170=1,L170,IFERROR(SUMIFS($G$2:$G$1001,$A$2:$A$1001,A170,$B$2:$B$1001,B170-1),0))) -> 25000 | N170: =IF(OR(L170="",M170=""),"",MIN(L170,M170)) -> 25000 | O170: =IF(OR(I170="",G170=""),"",I170+G170) -> 153300 | P170: =IF(OR(O170="",O170=0),"",(J170+H170)/O170) -> 2.0835095 | Q170: =IF(OR(O170="",E170=""),"",MAX(J170+H170-E170*O170,0)) -> 0 | R170: =IF(A170="","",IF(COUNTIF(_TradeIds,A170)=0,"违规：交易编号不存在",IF(OR(B170="",B170<1,B170>5,B170<>INT(B170)),"违规：加仓序号须为1到5的整数",IF(COUNTIFS($A$2:$A$1001,A170,$B$2:$B$1001,B170)>1,"违规：同一交易的加仓序号重复",IF(OR(D170="",E170="",F170=""),"计划不完整：请填写加仓价、新止损价和风险预算",IF(OR(D170<=0,E170<=0,F170<=0,D170<=E170),"违规：加仓价必须高于新止损价，金额须大于0",IF(AND(B170>1,COUNTIFS($A$2:$A$1001,A170,$B$2:$B$1001,B170-1,$G$2:$G$1001,">0")=0),"违规：须先完成上一次加仓",IF(AND(B170>1,E170<SUMIFS($E$2:$E$1001,$A$2:$A$1001,A170,$B$2:$B$1001,B170-1)),"违规：新止损价不得低于上一次",IF(AND(B170>1,F170>SUMIFS($F$2:$F$1001,$A$2:$A$1001,A170,$B$2:$B$1001,B170-1)),"违规：风险预算须逐次不增加",IF(OR(_LockStatus="已锁仓",_LockStatus="解锁信息不完整"),"违规：锁仓期间禁止加仓",IF(G170="","计划可执行：建议股数见N列",IF(OR(G170<=0,G170<>INT(G170),MOD(G170,100)<>0),"违规：实际股数须为100股整数倍",IF(G170>N170,"违规：实际股数超过风险或金字塔上限",IF(AND(B170>1,G170>SUMIFS($G$2:$G$1001,$A$2:$A$1001,A170,$B$2:$B$1001,B170-1)),"违规：加仓股数须逐次不增加",IF(Q170>F170,"违规：止损风险超过本次预算","通过"))))))))))))))) -> 通过
A171: 81 | B171: 1 | C171: 42307 | D171: 2.93 | E171: 2.6 | F171: 1 | G171: 100000 | H171: =IF(OR(A171="",D171="",G171=""),"",D171*G171) -> 293000 | I171: =IF(OR(A171="",B171=""),"",IFERROR(LOOKUP(2,1/(单次交易!$A$2:$A$201=A171),单次交易!$H$2:$H$201),0)+SUMIFS($G$2:$G$1001,$A$2:$A$1001,A171,$B$2:$B$1001,"<"&B171)) -> 58100 | J171: =IF(OR(A171="",B171=""),"",IFERROR(LOOKUP(2,1/(单次交易!$A$2:$A$201=A171),单次交易!$E$2:$E$201)*LOOKUP(2,1/(单次交易!$A$2:$A$201=A171),单次交易!$H$2:$H$201),0)+SUMIFS($H$2:$H$1001,$A$2:$A$1001,A171,$B$2:$B$1001,"<"&B171)) -> 169652 | K171: =IF(OR(E171="",I171="",J171=""),"",MAX(E171*I171-J171,0)) -> 0 | L171: =IF(OR(D171="",E171="",F171="",D171<=E171),"",FLOOR((F171+K171)/(D171-E171),100)) -> 0 | M171: =IF(OR(A171="",B171="",L171=""),"",IF(B171=1,L171,IFERROR(SUMIFS($G$2:$G$1001,$A$2:$A$1001,A171,$B$2:$B$1001,B171-1),0))) -> 0 | N171: =IF(OR(L171="",M171=""),"",MIN(L171,M171)) -> 0 | O171: =IF(OR(I171="",G171=""),"",I171+G171) -> 158100 | P171: =IF(OR(O171="",O171=0),"",(J171+H171)/O171) -> 2.9263251 | Q171: =IF(OR(O171="",E171=""),"",MAX(J171+H171-E171*O171,0)) -> 51592 | R171: =IF(A171="","",IF(COUNTIF(_TradeIds,A171)=0,"违规：交易编号不存在",IF(OR(B171="",B171<1,B171>5,B171<>INT(B171)),"违规：加仓序号须为1到5的整数",IF(COUNTIFS($A$2:$A$1001,A171,$B$2:$B$1001,B171)>1,"违规：同一交易的加仓序号重复",IF(OR(D171="",E171="",F171=""),"计划不完整：请填写加仓价、新止损价和风险预算",IF(OR(D171<=0,E171<=0,F171<=0,D171<=E171),"违规：加仓价必须高于新止损价，金额须大于0",IF(AND(B171>1,COUNTIFS($A$2:$A$1001,A171,$B$2:$B$1001,B171-1,$G$2:$G$1001,">0")=0),"违规：须先完成上一次加仓",IF(AND(B171>1,E171<SUMIFS($E$2:$E$1001,$A$2:$A$1001,A171,$B$2:$B$1001,B171-1)),"违规：新止损价不得低于上一次",IF(AND(B171>1,F171>SUMIFS($F$2:$F$1001,$A$2:$A$1001,A171,$B$2:$B$1001,B171-1)),"违规：风险预算须逐次不增加",IF(OR(_LockStatus="已锁仓",_LockStatus="解锁信息不完整"),"违规：锁仓期间禁止加仓",IF(G171="","计划可执行：建议股数见N列",IF(OR(G171<=0,G171<>INT(G171),MOD(G171,100)<>0),"违规：实际股数须为100股整数倍",IF(G171>N171,"违规：实际股数超过风险或金字塔上限",IF(AND(B171>1,G171>SUMIFS($G$2:$G$1001,$A$2:$A$1001,A171,$B$2:$B$1001,B171-1)),"违规：加仓股数须逐次不增加",IF(Q171>F171,"违规：止损风险超过本次预算","通过"))))))))))))))) -> 违规：实际股数超过风险或金字塔上限
... A199: 98 | B199: 2 | C199: 43992 | D199: 18.38 | E199: 17.18 | F199: 1 | G199: 10000 | H199: =IF(OR(A199="",D199="",G199=""),"",D199*G199) -> 183800 | I199: =IF(OR(A199="",B199=""),"",IFERROR(LOOKUP(2,1/(单次交易!$A$2:$A$201=A199),单次交易!$H$2:$H$201),0)+SUMIFS($G$2:$G$1001,$A$2:$A$1001,A199,$B$2:$B$1001,"<"&B199)) -> 27400 | J199: =IF(OR(A199="",B199=""),"",IFERROR(LOOKUP(2,1/(单次交易!$A$2:$A$201=A199),单次交易!$E$2:$E$201)*LOOKUP(2,1/(单次交易!$A$2:$A$201=A199),单次交易!$H$2:$H$201),0)+SUMIFS($H$2:$H$1001,$A$2:$A$1001,A199,$B$2:$B$1001,"<"&B199)) -> 453854 | K199: =IF(OR(E199="",I199="",J199=""),"",MAX(E199*I199-J199,0)) -> 16878 | L199: =IF(OR(D199="",E199="",F199="",D199<=E199),"",FLOOR((F199+K199)/(D199-E199),100)) -> 14000 | M199: =IF(OR(A199="",B199="",L199=""),"",IF(B199=1,L199,IFERROR(SUMIFS($G$2:$G$1001,$A$2:$A$1001,A199,$B$2:$B$1001,B199-1),0))) -> 10000 | N199: =IF(OR(L199="",M199=""),"",MIN(L199,M199)) -> 10000 | O199: =IF(OR(I199="",G199=""),"",I199+G199) -> 37400 | P199: =IF(OR(O199="",O199=0),"",(J199+H199)/O199) -> 17.049572 | Q199: =IF(OR(O199="",E199=""),"",MAX(J199+H199-E199*O199,0)) -> 0 | R199: =IF(A199="","",IF(COUNTIF(_TradeIds,A199)=0,"违规：交易编号不存在",IF(OR(B199="",B199<1,B199>5,B199<>INT(B199)),"违规：加仓序号须为1到5的整数",IF(COUNTIFS($A$2:$A$1001,A199,$B$2:$B$1001,B199)>1,"违规：同一交易的加仓序号重复",IF(OR(D199="",E199="",F199=""),"计划不完整：请填写加仓价、新止损价和风险预算",IF(OR(D199<=0,E199<=0,F199<=0,D199<=E199),"违规：加仓价必须高于新止损价，金额须大于0",IF(AND(B199>1,COUNTIFS($A$2:$A$1001,A199,$B$2:$B$1001,B199-1,$G$2:$G$1001,">0")=0),"违规：须先完成上一次加仓",IF(AND(B199>1,E199<SUMIFS($E$2:$E$1001,$A$2:$A$1001,A199,$B$2:$B$1001,B199-1)),"违规：新止损价不得低于上一次",IF(AND(B199>1,F199>SUMIFS($F$2:$F$1001,$A$2:$A$1001,A199,$B$2:$B$1001,B199-1)),"违规：风险预算须逐次不增加",IF(OR(_LockStatus="已锁仓",_LockStatus="解锁信息不完整"),"违规：锁仓期间禁止加仓",IF(G199="","计划可执行：建议股数见N列",IF(OR(G199<=0,G199<>INT(G199),MOD(G199,100)<>0),"违规：实际股数须为100股整数倍",IF(G199>N199,"违规：实际股数超过风险或金字塔上限",IF(AND(B199>1,G199>SUMIFS($G$2:$G$1001,$A$2:$A$1001,A199,$B$2:$B$1001,B199-1)),"违规：加仓股数须逐次不增加",IF(Q199>F199,"违规：止损风险超过本次预算","通过"))))))))))))))) -> 通过
A200: 98 | B200: 3 | C200: 44000 | D200: 19.49 | E200: 18.38 | F200: 1 | H200: =IF(OR(A200="",D200="",G200=""),"",D200*G200) | I200: =IF(OR(A200="",B200=""),"",IFERROR(LOOKUP(2,1/(单次交易!$A$2:$A$201=A200),单次交易!$H$2:$H$201),0)+SUMIFS($G$2:$G$1001,$A$2:$A$1001,A200,$B$2:$B$1001,"<"&B200)) -> 37400 | J200: =IF(OR(A200="",B200=""),"",IFERROR(LOOKUP(2,1/(单次交易!$A$2:$A$201=A200),单次交易!$E$2:$E$201)*LOOKUP(2,1/(单次交易!$A$2:$A$201=A200),单次交易!$H$2:$H$201),0)+SUMIFS($H$2:$H$1001,$A$2:$A$1001,A200,$B$2:$B$1001,"<"&B200)) -> 637654 | K200: =IF(OR(E200="",I200="",J200=""),"",MAX(E200*I200-J200,0)) -> 49758 | L200: =IF(OR(D200="",E200="",F200="",D200<=E200),"",FLOOR((F200+K200)/(D200-E200),100)) -> 44800 | M200: =IF(OR(A200="",B200="",L200=""),"",IF(B200=1,L200,IFERROR(SUMIFS($G$2:$G$1001,$A$2:$A$1001,A200,$B$2:$B$1001,B200-1),0))) -> 10000 | N200: =IF(OR(L200="",M200=""),"",MIN(L200,M200)) -> 10000 | O200: =IF(OR(I200="",G200=""),"",I200+G200) | P200: =IF(OR(O200="",O200=0),"",(J200+H200)/O200) | Q200: =IF(OR(O200="",E200=""),"",MAX(J200+H200-E200*O200,0)) | R200: =IF(A200="","",IF(COUNTIF(_TradeIds,A200)=0,"违规：交易编号不存在",IF(OR(B200="",B200<1,B200>5,B200<>INT(B200)),"违规：加仓序号须为1到5的整数",IF(COUNTIFS($A$2:$A$1001,A200,$B$2:$B$1001,B200)>1,"违规：同一交易的加仓序号重复",IF(OR(D200="",E200="",F200=""),"计划不完整：请填写加仓价、新止损价和风险预算",IF(OR(D200<=0,E200<=0,F200<=0,D200<=E200),"违规：加仓价必须高于新止损价，金额须大于0",IF(AND(B200>1,COUNTIFS($A$2:$A$1001,A200,$B$2:$B$1001,B200-1,$G$2:$G$1001,">0")=0),"违规：须先完成上一次加仓",IF(AND(B200>1,E200<SUMIFS($E$2:$E$1001,$A$2:$A$1001,A200,$B$2:$B$1001,B200-1)),"违规：新止损价不得低于上一次",IF(AND(B200>1,F200>SUMIFS($F$2:$F$1001,$A$2:$A$1001,A200,$B$2:$B$1001,B200-1)),"违规：风险预算须逐次不增加",IF(OR(_LockStatus="已锁仓",_LockStatus="解锁信息不完整"),"违规：锁仓期间禁止加仓",IF(G200="","计划可执行：建议股数见N列",IF(OR(G200<=0,G200<>INT(G200),MOD(G200,100)<>0),"违规：实际股数须为100股整数倍",IF(G200>N200,"违规：实际股数超过风险或金字塔上限",IF(AND(B200>1,G200>SUMIFS($G$2:$G$1001,$A$2:$A$1001,A200,$B$2:$B$1001,B200-1)),"违规：加仓股数须逐次不增加",IF(Q200>F200,"违规：止损风险超过本次预算","通过"))))))))))))))) -> 计划可执行：建议股数见N列
H201: =IF(OR(A201="",D201="",G201=""),"",D201*G201) | I201: =IF(OR(A201="",B201=""),"",IFERROR(LOOKUP(2,1/(单次交易!$A$2:$A$201=A201),单次交易!$H$2:$H$201),0)+SUMIFS($G$2:$G$1001,$A$2:$A$1001,A201,$B$2:$B$1001,"<"&B201)) | J201: =IF(OR(A201="",B201=""),"",IFERROR(LOOKUP(2,1/(单次交易!$A$2:$A$201=A201),单次交易!$E$2:$E$201)*LOOKUP(2,1/(单次交易!$A$2:$A$201=A201),单次交易!$H$2:$H$201),0)+SUMIFS($H$2:$H$1001,$A$2:$A$1001,A201,$B$2:$B$1001,"<"&B201)) | K201: =IF(OR(E201="",I201="",J201=""),"",MAX(E201*I201-J201,0)) | L201: =IF(OR(D201="",E201="",F201="",D201<=E201),"",FLOOR((F201+K201)/(D201-E201),100)) | M201: =IF(OR(A201="",B201="",L201=""),"",IF(B201=1,L201,IFERROR(SUMIFS($G$2:$G$1001,$A$2:$A$1001,A201,$B$2:$B$1001,B201-1),0))) | N201: =IF(OR(L201="",M201=""),"",MIN(L201,M201)) | O201: =IF(OR(I201="",G201=""),"",I201+G201) | P201: =IF(OR(O201="",O201=0),"",(J201+H201)/O201) | Q201: =IF(OR(O201="",E201=""),"",MAX(J201+H201-E201*O201,0)) | R201: =IF(A201="","",IF(COUNTIF(_TradeIds,A201)=0,"违规：交易编号不存在",IF(OR(B201="",B201<1,B201>5,B201<>INT(B201)),"违规：加仓序号须为1到5的整数",IF(COUNTIFS($A$2:$A$1001,A201,$B$2:$B$1001,B201)>1,"违规：同一交易的加仓序号重复",IF(OR(D201="",E201="",F201=""),"计划不完整：请填写加仓价、新止损价和风险预算",IF(OR(D201<=0,E201<=0,F201<=0,D201<=E201),"违规：加仓价必须高于新止损价，金额须大于0",IF(AND(B201>1,COUNTIFS($A$2:$A$1001,A201,$B$2:$B$1001,B201-1,$G$2:$G$1001,">0")=0),"违规：须先完成上一次加仓",IF(AND(B201>1,E201<SUMIFS($E$2:$E$1001,$A$2:$A$1001,A201,$B$2:$B$1001,B201-1)),"违规：新止损价不得低于上一次",IF(AND(B201>1,F201>SUMIFS($F$2:$F$1001,$A$2:$A$1001,A201,$B$2:$B$1001,B201-1)),"违规：风险预算须逐次不增加",IF(OR(_LockStatus="已锁仓",_LockStatus="解锁信息不完整"),"违规：锁仓期间禁止加仓",IF(G201="","计划可执行：建议股数见N列",IF(OR(G201<=0,G201<>INT(G201),MOD(G201,100)<>0),"违规：实际股数须为100股整数倍",IF(G201>N201,"违规：实际股数超过风险或金字塔上限",IF(AND(B201>1,G201>SUMIFS($G$2:$G$1001,$A$2:$A$1001,A201,$B$2:$B$1001,B201-1)),"违规：加仓股数须逐次不增加",IF(Q201>F201,"违规：止损风险超过本次预算","通过")))))))))))))))
H202: =IF(OR(A202="",D202="",G202=""),"",D202*G202) | I202: =IF(OR(A202="",B202=""),"",IFERROR(LOOKUP(2,1/(单次交易!$A$2:$A$201=A202),单次交易!$H$2:$H$201),0)+SUMIFS($G$2:$G$1001,$A$2:$A$1001,A202,$B$2:$B$1001,"<"&B202)) | J202: =IF(OR(A202="",B202=""),"",IFERROR(LOOKUP(2,1/(单次交易!$A$2:$A$201=A202),单次交易!$E$2:$E$201)*LOOKUP(2,1/(单次交易!$A$2:$A$201=A202),单次交易!$H$2:$H$201),0)+SUMIFS($H$2:$H$1001,$A$2:$A$1001,A202,$B$2:$B$1001,"<"&B202)) | K202: =IF(OR(E202="",I202="",J202=""),"",MAX(E202*I202-J202,0)) | L202: =IF(OR(D202="",E202="",F202="",D202<=E202),"",FLOOR((F202+K202)/(D202-E202),100)) | M202: =IF(OR(A202="",B202="",L202=""),"",IF(B202=1,L202,IFERROR(SUMIFS($G$2:$G$1001,$A$2:$A$1001,A202,$B$2:$B$1001,B202-1),0))) | N202: =IF(OR(L202="",M202=""),"",MIN(L202,M202)) | O202: =IF(OR(I202="",G202=""),"",I202+G202) | P202: =IF(OR(O202="",O202=0),"",(J202+H202)/O202) | Q202: =IF(OR(O202="",E202=""),"",MAX(J202+H202-E202*O202,0)) | R202: =IF(A202="","",IF(COUNTIF(_TradeIds,A202)=0,"违规：交易编号不存在",IF(OR(B202="",B202<1,B202>5,B202<>INT(B202)),"违规：加仓序号须为1到5的整数",IF(COUNTIFS($A$2:$A$1001,A202,$B$2:$B$1001,B202)>1,"违规：同一交易的加仓序号重复",IF(OR(D202="",E202="",F202=""),"计划不完整：请填写加仓价、新止损价和风险预算",IF(OR(D202<=0,E202<=0,F202<=0,D202<=E202),"违规：加仓价必须高于新止损价，金额须大于0",IF(AND(B202>1,COUNTIFS($A$2:$A$1001,A202,$B$2:$B$1001,B202-1,$G$2:$G$1001,">0")=0),"违规：须先完成上一次加仓",IF(AND(B202>1,E202<SUMIFS($E$2:$E$1001,$A$2:$A$1001,A202,$B$2:$B$1001,B202-1)),"违规：新止损价不得低于上一次",IF(AND(B202>1,F202>SUMIFS($F$2:$F$1001,$A$2:$A$1001,A202,$B$2:$B$1001,B202-1)),"违规：风险预算须逐次不增加",IF(OR(_LockStatus="已锁仓",_LockStatus="解锁信息不完整"),"违规：锁仓期间禁止加仓",IF(G202="","计划可执行：建议股数见N列",IF(OR(G202<=0,G202<>INT(G202),MOD(G202,100)<>0),"违规：实际股数须为100股整数倍",IF(G202>N202,"违规：实际股数超过风险或金字塔上限",IF(AND(B202>1,G202>SUMIFS($G$2:$G$1001,$A$2:$A$1001,A202,$B$2:$B$1001,B202-1)),"违规：加仓股数须逐次不增加",IF(Q202>F202,"违规：止损风险超过本次预算","通过")))))))))))))))
H203: =IF(OR(A203="",D203="",G203=""),"",D203*G203) | I203: =IF(OR(A203="",B203=""),"",IFERROR(LOOKUP(2,1/(单次交易!$A$2:$A$201=A203),单次交易!$H$2:$H$201),0)+SUMIFS($G$2:$G$1001,$A$2:$A$1001,A203,$B$2:$B$1001,"<"&B203)) | J203: =IF(OR(A203="",B203=""),"",IFERROR(LOOKUP(2,1/(单次交易!$A$2:$A$201=A203),单次交易!$E$2:$E$201)*LOOKUP(2,1/(单次交易!$A$2:$A$201=A203),单次交易!$H$2:$H$201),0)+SUMIFS($H$2:$H$1001,$A$2:$A$1001,A203,$B$2:$B$1001,"<"&B203)) | K203: =IF(OR(E203="",I203="",J203=""),"",MAX(E203*I203-J203,0)) | L203: =IF(OR(D203="",E203="",F203="",D203<=E203),"",FLOOR((F203+K203)/(D203-E203),100)) | M203: =IF(OR(A203="",B203="",L203=""),"",IF(B203=1,L203,IFERROR(SUMIFS($G$2:$G$1001,$A$2:$A$1001,A203,$B$2:$B$1001,B203-1),0))) | N203: =IF(OR(L203="",M203=""),"",MIN(L203,M203)) | O203: =IF(OR(I203="",G203=""),"",I203+G203) | P203: =IF(OR(O203="",O203=0),"",(J203+H203)/O203) | Q203: =IF(OR(O203="",E203=""),"",MAX(J203+H203-E203*O203,0)) | R203: =IF(A203="","",IF(COUNTIF(_TradeIds,A203)=0,"违规：交易编号不存在",IF(OR(B203="",B203<1,B203>5,B203<>INT(B203)),"违规：加仓序号须为1到5的整数",IF(COUNTIFS($A$2:$A$1001,A203,$B$2:$B$1001,B203)>1,"违规：同一交易的加仓序号重复",IF(OR(D203="",E203="",F203=""),"计划不完整：请填写加仓价、新止损价和风险预算",IF(OR(D203<=0,E203<=0,F203<=0,D203<=E203),"违规：加仓价必须高于新止损价，金额须大于0",IF(AND(B203>1,COUNTIFS($A$2:$A$1001,A203,$B$2:$B$1001,B203-1,$G$2:$G$1001,">0")=0),"违规：须先完成上一次加仓",IF(AND(B203>1,E203<SUMIFS($E$2:$E$1001,$A$2:$A$1001,A203,$B$2:$B$1001,B203-1)),"违规：新止损价不得低于上一次",IF(AND(B203>1,F203>SUMIFS($F$2:$F$1001,$A$2:$A$1001,A203,$B$2:$B$1001,B203-1)),"违规：风险预算须逐次不增加",IF(OR(_LockStatus="已锁仓",_LockStatus="解锁信息不完整"),"违规：锁仓期间禁止加仓",IF(G203="","计划可执行：建议股数见N列",IF(OR(G203<=0,G203<>INT(G203),MOD(G203,100)<>0),"违规：实际股数须为100股整数倍",IF(G203>N203,"违规：实际股数超过风险或金字塔上限",IF(AND(B203>1,G203>SUMIFS($G$2:$G$1001,$A$2:$A$1001,A203,$B$2:$B$1001,B203-1)),"违规：加仓股数须逐次不增加",IF(Q203>F203,"违规：止损风险超过本次预算","通过")))))))))))))))
H204: =IF(OR(A204="",D204="",G204=""),"",D204*G204) | I204: =IF(OR(A204="",B204=""),"",IFERROR(LOOKUP(2,1/(单次交易!$A$2:$A$201=A204),单次交易!$H$2:$H$201),0)+SUMIFS($G$2:$G$1001,$A$2:$A$1001,A204,$B$2:$B$1001,"<"&B204)) | J204: =IF(OR(A204="",B204=""),"",IFERROR(LOOKUP(2,1/(单次交易!$A$2:$A$201=A204),单次交易!$E$2:$E$201)*LOOKUP(2,1/(单次交易!$A$2:$A$201=A204),单次交易!$H$2:$H$201),0)+SUMIFS($H$2:$H$1001,$A$2:$A$1001,A204,$B$2:$B$1001,"<"&B204)) | K204: =IF(OR(E204="",I204="",J204=""),"",MAX(E204*I204-J204,0)) | L204: =IF(OR(D204="",E204="",F204="",D204<=E204),"",FLOOR((F204+K204)/(D204-E204),100)) | M204: =IF(OR(A204="",B204="",L204=""),"",IF(B204=1,L204,IFERROR(SUMIFS($G$2:$G$1001,$A$2:$A$1001,A204,$B$2:$B$1001,B204-1),0))) | N204: =IF(OR(L204="",M204=""),"",MIN(L204,M204)) | O204: =IF(OR(I204="",G204=""),"",I204+G204) | P204: =IF(OR(O204="",O204=0),"",(J204+H204)/O204) | Q204: =IF(OR(O204="",E204=""),"",MAX(J204+H204-E204*O204,0)) | R204: =IF(A204="","",IF(COUNTIF(_TradeIds,A204)=0,"违规：交易编号不存在",IF(OR(B204="",B204<1,B204>5,B204<>INT(B204)),"违规：加仓序号须为1到5的整数",IF(COUNTIFS($A$2:$A$1001,A204,$B$2:$B$1001,B204)>1,"违规：同一交易的加仓序号重复",IF(OR(D204="",E204="",F204=""),"计划不完整：请填写加仓价、新止损价和风险预算",IF(OR(D204<=0,E204<=0,F204<=0,D204<=E204),"违规：加仓价必须高于新止损价，金额须大于0",IF(AND(B204>1,COUNTIFS($A$2:$A$1001,A204,$B$2:$B$1001,B204-1,$G$2:$G$1001,">0")=0),"违规：须先完成上一次加仓",IF(AND(B204>1,E204<SUMIFS($E$2:$E$1001,$A$2:$A$1001,A204,$B$2:$B$1001,B204-1)),"违规：新止损价不得低于上一次",IF(AND(B204>1,F204>SUMIFS($F$2:$F$1001,$A$2:$A$1001,A204,$B$2:$B$1001,B204-1)),"违规：风险预算须逐次不增加",IF(OR(_LockStatus="已锁仓",_LockStatus="解锁信息不完整"),"违规：锁仓期间禁止加仓",IF(G204="","计划可执行：建议股数见N列",IF(OR(G204<=0,G204<>INT(G204),MOD(G204,100)<>0),"违规：实际股数须为100股整数倍",IF(G204>N204,"违规：实际股数超过风险或金字塔上限",IF(AND(B204>1,G204>SUMIFS($G$2:$G$1001,$A$2:$A$1001,A204,$B$2:$B$1001,B204-1)),"违规：加仓股数须逐次不增加",IF(Q204>F204,"违规：止损风险超过本次预算","通过")))))))))))))))
H205: =IF(OR(A205="",D205="",G205=""),"",D205*G205) | I205: =IF(OR(A205="",B205=""),"",IFERROR(LOOKUP(2,1/(单次交易!$A$2:$A$201=A205),单次交易!$H$2:$H$201),0)+SUMIFS($G$2:$G$1001,$A$2:$A$1001,A205,$B$2:$B$1001,"<"&B205)) | J205: =IF(OR(A205="",B205=""),"",IFERROR(LOOKUP(2,1/(单次交易!$A$2:$A$201=A205),单次交易!$E$2:$E$201)*LOOKUP(2,1/(单次交易!$A$2:$A$201=A205),单次交易!$H$2:$H$201),0)+SUMIFS($H$2:$H$1001,$A$2:$A$1001,A205,$B$2:$B$1001,"<"&B205)) | K205: =IF(OR(E205="",I205="",J205=""),"",MAX(E205*I205-J205,0)) | L205: =IF(OR(D205="",E205="",F205="",D205<=E205),"",FLOOR((F205+K205)/(D205-E205),100)) | M205: =IF(OR(A205="",B205="",L205=""),"",IF(B205=1,L205,IFERROR(SUMIFS($G$2:$G$1001,$A$2:$A$1001,A205,$B$2:$B$1001,B205-1),0))) | N205: =IF(OR(L205="",M205=""),"",MIN(L205,M205)) | O205: =IF(OR(I205="",G205=""),"",I205+G205) | P205: =IF(OR(O205="",O205=0),"",(J205+H205)/O205) | Q205: =IF(OR(O205="",E205=""),"",MAX(J205+H205-E205*O205,0)) | R205: =IF(A205="","",IF(COUNTIF(_TradeIds,A205)=0,"违规：交易编号不存在",IF(OR(B205="",B205<1,B205>5,B205<>INT(B205)),"违规：加仓序号须为1到5的整数",IF(COUNTIFS($A$2:$A$1001,A205,$B$2:$B$1001,B205)>1,"违规：同一交易的加仓序号重复",IF(OR(D205="",E205="",F205=""),"计划不完整：请填写加仓价、新止损价和风险预算",IF(OR(D205<=0,E205<=0,F205<=0,D205<=E205),"违规：加仓价必须高于新止损价，金额须大于0",IF(AND(B205>1,COUNTIFS($A$2:$A$1001,A205,$B$2:$B$1001,B205-1,$G$2:$G$1001,">0")=0),"违规：须先完成上一次加仓",IF(AND(B205>1,E205<SUMIFS($E$2:$E$1001,$A$2:$A$1001,A205,$B$2:$B$1001,B205-1)),"违规：新止损价不得低于上一次",IF(AND(B205>1,F205>SUMIFS($F$2:$F$1001,$A$2:$A$1001,A205,$B$2:$B$1001,B205-1)),"违规：风险预算须逐次不增加",IF(OR(_LockStatus="已锁仓",_LockStatus="解锁信息不完整"),"违规：锁仓期间禁止加仓",IF(G205="","计划可执行：建议股数见N列",IF(OR(G205<=0,G205<>INT(G205),MOD(G205,100)<>0),"违规：实际股数须为100股整数倍",IF(G205>N205,"违规：实际股数超过风险或金字塔上限",IF(AND(B205>1,G205>SUMIFS($G$2:$G$1001,$A$2:$A$1001,A205,$B$2:$B$1001,B205-1)),"违规：加仓股数须逐次不增加",IF(Q205>F205,"违规：止损风险超过本次预算","通过")))))))))))))))
H206: =IF(OR(A206="",D206="",G206=""),"",D206*G206) | I206: =IF(OR(A206="",B206=""),"",IFERROR(LOOKUP(2,1/(单次交易!$A$2:$A$201=A206),单次交易!$H$2:$H$201),0)+SUMIFS($G$2:$G$1001,$A$2:$A$1001,A206,$B$2:$B$1001,"<"&B206)) | J206: =IF(OR(A206="",B206=""),"",IFERROR(LOOKUP(2,1/(单次交易!$A$2:$A$201=A206),单次交易!$E$2:$E$201)*LOOKUP(2,1/(单次交易!$A$2:$A$201=A206),单次交易!$H$2:$H$201),0)+SUMIFS($H$2:$H$1001,$A$2:$A$1001,A206,$B$2:$B$1001,"<"&B206)) | K206: =IF(OR(E206="",I206="",J206=""),"",MAX(E206*I206-J206,0)) | L206: =IF(OR(D206="",E206="",F206="",D206<=E206),"",FLOOR((F206+K206)/(D206-E206),100)) | M206: =IF(OR(A206="",B206="",L206=""),"",IF(B206=1,L206,IFERROR(SUMIFS($G$2:$G$1001,$A$2:$A$1001,A206,$B$2:$B$1001,B206-1),0))) | N206: =IF(OR(L206="",M206=""),"",MIN(L206,M206)) | O206: =IF(OR(I206="",G206=""),"",I206+G206) | P206: =IF(OR(O206="",O206=0),"",(J206+H206)/O206) | Q206: =IF(OR(O206="",E206=""),"",MAX(J206+H206-E206*O206,0)) | R206: =IF(A206="","",IF(COUNTIF(_TradeIds,A206)=0,"违规：交易编号不存在",IF(OR(B206="",B206<1,B206>5,B206<>INT(B206)),"违规：加仓序号须为1到5的整数",IF(COUNTIFS($A$2:$A$1001,A206,$B$2:$B$1001,B206)>1,"违规：同一交易的加仓序号重复",IF(OR(D206="",E206="",F206=""),"计划不完整：请填写加仓价、新止损价和风险预算",IF(OR(D206<=0,E206<=0,F206<=0,D206<=E206),"违规：加仓价必须高于新止损价，金额须大于0",IF(AND(B206>1,COUNTIFS($A$2:$A$1001,A206,$B$2:$B$1001,B206-1,$G$2:$G$1001,">0")=0),"违规：须先完成上一次加仓",IF(AND(B206>1,E206<SUMIFS($E$2:$E$1001,$A$2:$A$1001,A206,$B$2:$B$1001,B206-1)),"违规：新止损价不得低于上一次",IF(AND(B206>1,F206>SUMIFS($F$2:$F$1001,$A$2:$A$1001,A206,$B$2:$B$1001,B206-1)),"违规：风险预算须逐次不增加",IF(OR(_LockStatus="已锁仓",_LockStatus="解锁信息不完整"),"违规：锁仓期间禁止加仓",IF(G206="","计划可执行：建议股数见N列",IF(OR(G206<=0,G206<>INT(G206),MOD(G206,100)<>0),"违规：实际股数须为100股整数倍",IF(G206>N206,"违规：实际股数超过风险或金字塔上限",IF(AND(B206>1,G206>SUMIFS($G$2:$G$1001,$A$2:$A$1001,A206,$B$2:$B$1001,B206-1)),"违规：加仓股数须逐次不增加",IF(Q206>F206,"违规：止损风险超过本次预算","通过")))))))))))))))
H207: =IF(OR(A207="",D207="",G207=""),"",D207*G207) | I207: =IF(OR(A207="",B207=""),"",IFERROR(LOOKUP(2,1/(单次交易!$A$2:$A$201=A207),单次交易!$H$2:$H$201),0)+SUMIFS($G$2:$G$1001,$A$2:$A$1001,A207,$B$2:$B$1001,"<"&B207)) | J207: =IF(OR(A207="",B207=""),"",IFERROR(LOOKUP(2,1/(单次交易!$A$2:$A$201=A207),单次交易!$E$2:$E$201)*LOOKUP(2,1/(单次交易!$A$2:$A$201=A207),单次交易!$H$2:$H$201),0)+SUMIFS($H$2:$H$1001,$A$2:$A$1001,A207,$B$2:$B$1001,"<"&B207)) | K207: =IF(OR(E207="",I207="",J207=""),"",MAX(E207*I207-J207,0)) | L207: =IF(OR(D207="",E207="",F207="",D207<=E207),"",FLOOR((F207+K207)/(D207-E207),100)) | M207: =IF(OR(A207="",B207="",L207=""),"",IF(B207=1,L207,IFERROR(SUMIFS($G$2:$G$1001,$A$2:$A$1001,A207,$B$2:$B$1001,B207-1),0))) | N207: =IF(OR(L207="",M207=""),"",MIN(L207,M207)) | O207: =IF(OR(I207="",G207=""),"",I207+G207) | P207: =IF(OR(O207="",O207=0),"",(J207+H207)/O207) | Q207: =IF(OR(O207="",E207=""),"",MAX(J207+H207-E207*O207,0)) | R207: =IF(A207="","",IF(COUNTIF(_TradeIds,A207)=0,"违规：交易编号不存在",IF(OR(B207="",B207<1,B207>5,B207<>INT(B207)),"违规：加仓序号须为1到5的整数",IF(COUNTIFS($A$2:$A$1001,A207,$B$2:$B$1001,B207)>1,"违规：同一交易的加仓序号重复",IF(OR(D207="",E207="",F207=""),"计划不完整：请填写加仓价、新止损价和风险预算",IF(OR(D207<=0,E207<=0,F207<=0,D207<=E207),"违规：加仓价必须高于新止损价，金额须大于0",IF(AND(B207>1,COUNTIFS($A$2:$A$1001,A207,$B$2:$B$1001,B207-1,$G$2:$G$1001,">0")=0),"违规：须先完成上一次加仓",IF(AND(B207>1,E207<SUMIFS($E$2:$E$1001,$A$2:$A$1001,A207,$B$2:$B$1001,B207-1)),"违规：新止损价不得低于上一次",IF(AND(B207>1,F207>SUMIFS($F$2:$F$1001,$A$2:$A$1001,A207,$B$2:$B$1001,B207-1)),"违规：风险预算须逐次不增加",IF(OR(_LockStatus="已锁仓",_LockStatus="解锁信息不完整"),"违规：锁仓期间禁止加仓",IF(G207="","计划可执行：建议股数见N列",IF(OR(G207<=0,G207<>INT(G207),MOD(G207,100)<>0),"违规：实际股数须为100股整数倍",IF(G207>N207,"违规：实际股数超过风险或金字塔上限",IF(AND(B207>1,G207>SUMIFS($G$2:$G$1001,$A$2:$A$1001,A207,$B$2:$B$1001,B207-1)),"违规：加仓股数须逐次不增加",IF(Q207>F207,"违规：止损风险超过本次预算","通过")))))))))))))))
H208: =IF(OR(A208="",D208="",G208=""),"",D208*G208) | I208: =IF(OR(A208="",B208=""),"",IFERROR(LOOKUP(2,1/(单次交易!$A$2:$A$201=A208),单次交易!$H$2:$H$201),0)+SUMIFS($G$2:$G$1001,$A$2:$A$1001,A208,$B$2:$B$1001,"<"&B208)) | J208: =IF(OR(A208="",B208=""),"",IFERROR(LOOKUP(2,1/(单次交易!$A$2:$A$201=A208),单次交易!$E$2:$E$201)*LOOKUP(2,1/(单次交易!$A$2:$A$201=A208),单次交易!$H$2:$H$201),0)+SUMIFS($H$2:$H$1001,$A$2:$A$1001,A208,$B$2:$B$1001,"<"&B208)) | K208: =IF(OR(E208="",I208="",J208=""),"",MAX(E208*I208-J208,0)) | L208: =IF(OR(D208="",E208="",F208="",D208<=E208),"",FLOOR((F208+K208)/(D208-E208),100)) | M208: =IF(OR(A208="",B208="",L208=""),"",IF(B208=1,L208,IFERROR(SUMIFS($G$2:$G$1001,$A$2:$A$1001,A208,$B$2:$B$1001,B208-1),0))) | N208: =IF(OR(L208="",M208=""),"",MIN(L208,M208)) | O208: =IF(OR(I208="",G208=""),"",I208+G208) | P208: =IF(OR(O208="",O208=0),"",(J208+H208)/O208) | Q208: =IF(OR(O208="",E208=""),"",MAX(J208+H208-E208*O208,0)) | R208: =IF(A208="","",IF(COUNTIF(_TradeIds,A208)=0,"违规：交易编号不存在",IF(OR(B208="",B208<1,B208>5,B208<>INT(B208)),"违规：加仓序号须为1到5的整数",IF(COUNTIFS($A$2:$A$1001,A208,$B$2:$B$1001,B208)>1,"违规：同一交易的加仓序号重复",IF(OR(D208="",E208="",F208=""),"计划不完整：请填写加仓价、新止损价和风险预算",IF(OR(D208<=0,E208<=0,F208<=0,D208<=E208),"违规：加仓价必须高于新止损价，金额须大于0",IF(AND(B208>1,COUNTIFS($A$2:$A$1001,A208,$B$2:$B$1001,B208-1,$G$2:$G$1001,">0")=0),"违规：须先完成上一次加仓",IF(AND(B208>1,E208<SUMIFS($E$2:$E$1001,$A$2:$A$1001,A208,$B$2:$B$1001,B208-1)),"违规：新止损价不得低于上一次",IF(AND(B208>1,F208>SUMIFS($F$2:$F$1001,$A$2:$A$1001,A208,$B$2:$B$1001,B208-1)),"违规：风险预算须逐次不增加",IF(OR(_LockStatus="已锁仓",_LockStatus="解锁信息不完整"),"违规：锁仓期间禁止加仓",IF(G208="","计划可执行：建议股数见N列",IF(OR(G208<=0,G208<>INT(G208),MOD(G208,100)<>0),"违规：实际股数须为100股整数倍",IF(G208>N208,"违规：实际股数超过风险或金字塔上限",IF(AND(B208>1,G208>SUMIFS($G$2:$G$1001,$A$2:$A$1001,A208,$B$2:$B$1001,B208-1)),"违规：加仓股数须逐次不增加",IF(Q208>F208,"违规：止损风险超过本次预算","通过")))))))))))))))
H209: =IF(OR(A209="",D209="",G209=""),"",D209*G209) | I209: =IF(OR(A209="",B209=""),"",IFERROR(LOOKUP(2,1/(单次交易!$A$2:$A$201=A209),单次交易!$H$2:$H$201),0)+SUMIFS($G$2:$G$1001,$A$2:$A$1001,A209,$B$2:$B$1001,"<"&B209)) | J209: =IF(OR(A209="",B209=""),"",IFERROR(LOOKUP(2,1/(单次交易!$A$2:$A$201=A209),单次交易!$E$2:$E$201)*LOOKUP(2,1/(单次交易!$A$2:$A$201=A209),单次交易!$H$2:$H$201),0)+SUMIFS($H$2:$H$1001,$A$2:$A$1001,A209,$B$2:$B$1001,"<"&B209)) | K209: =IF(OR(E209="",I209="",J209=""),"",MAX(E209*I209-J209,0)) | L209: =IF(OR(D209="",E209="",F209="",D209<=E209),"",FLOOR((F209+K209)/(D209-E209),100)) | M209: =IF(OR(A209="",B209="",L209=""),"",IF(B209=1,L209,IFERROR(SUMIFS($G$2:$G$1001,$A$2:$A$1001,A209,$B$2:$B$1001,B209-1),0))) | N209: =IF(OR(L209="",M209=""),"",MIN(L209,M209)) | O209: =IF(OR(I209="",G209=""),"",I209+G209) | P209: =IF(OR(O209="",O209=0),"",(J209+H209)/O209) | Q209: =IF(OR(O209="",E209=""),"",MAX(J209+H209-E209*O209,0)) | R209: =IF(A209="","",IF(COUNTIF(_TradeIds,A209)=0,"违规：交易编号不存在",IF(OR(B209="",B209<1,B209>5,B209<>INT(B209)),"违规：加仓序号须为1到5的整数",IF(COUNTIFS($A$2:$A$1001,A209,$B$2:$B$1001,B209)>1,"违规：同一交易的加仓序号重复",IF(OR(D209="",E209="",F209=""),"计划不完整：请填写加仓价、新止损价和风险预算",IF(OR(D209<=0,E209<=0,F209<=0,D209<=E209),"违规：加仓价必须高于新止损价，金额须大于0",IF(AND(B209>1,COUNTIFS($A$2:$A$1001,A209,$B$2:$B$1001,B209-1,$G$2:$G$1001,">0")=0),"违规：须先完成上一次加仓",IF(AND(B209>1,E209<SUMIFS($E$2:$E$1001,$A$2:$A$1001,A209,$B$2:$B$1001,B209-1)),"违规：新止损价不得低于上一次",IF(AND(B209>1,F209>SUMIFS($F$2:$F$1001,$A$2:$A$1001,A209,$B$2:$B$1001,B209-1)),"违规：风险预算须逐次不增加",IF(OR(_LockStatus="已锁仓",_LockStatus="解锁信息不完整"),"违规：锁仓期间禁止加仓",IF(G209="","计划可执行：建议股数见N列",IF(OR(G209<=0,G209<>INT(G209),MOD(G209,100)<>0),"违规：实际股数须为100股整数倍",IF(G209>N209,"违规：实际股数超过风险或金字塔上限",IF(AND(B209>1,G209>SUMIFS($G$2:$G$1001,$A$2:$A$1001,A209,$B$2:$B$1001,B209-1)),"违规：加仓股数须逐次不增加",IF(Q209>F209,"违规：止损风险超过本次预算","通过")))))))))))))))
H210: =IF(OR(A210="",D210="",G210=""),"",D210*G210) | I210: =IF(OR(A210="",B210=""),"",IFERROR(LOOKUP(2,1/(单次交易!$A$2:$A$201=A210),单次交易!$H$2:$H$201),0)+SUMIFS($G$2:$G$1001,$A$2:$A$1001,A210,$B$2:$B$1001,"<"&B210)) | J210: =IF(OR(A210="",B210=""),"",IFERROR(LOOKUP(2,1/(单次交易!$A$2:$A$201=A210),单次交易!$E$2:$E$201)*LOOKUP(2,1/(单次交易!$A$2:$A$201=A210),单次交易!$H$2:$H$201),0)+SUMIFS($H$2:$H$1001,$A$2:$A$1001,A210,$B$2:$B$1001,"<"&B210)) | K210: =IF(OR(E210="",I210="",J210=""),"",MAX(E210*I210-J210,0)) | L210: =IF(OR(D210="",E210="",F210="",D210<=E210),"",FLOOR((F210+K210)/(D210-E210),100)) | M210: =IF(OR(A210="",B210="",L210=""),"",IF(B210=1,L210,IFERROR(SUMIFS($G$2:$G$1001,$A$2:$A$1001,A210,$B$2:$B$1001,B210-1),0))) | N210: =IF(OR(L210="",M210=""),"",MIN(L210,M210)) | O210: =IF(OR(I210="",G210=""),"",I210+G210) | P210: =IF(OR(O210="",O210=0),"",(J210+H210)/O210) | Q210: =IF(OR(O210="",E210=""),"",MAX(J210+H210-E210*O210,0)) | R210: =IF(A210="","",IF(COUNTIF(_TradeIds,A210)=0,"违规：交易编号不存在",IF(OR(B210="",B210<1,B210>5,B210<>INT(B210)),"违规：加仓序号须为1到5的整数",IF(COUNTIFS($A$2:$A$1001,A210,$B$2:$B$1001,B210)>1,"违规：同一交易的加仓序号重复",IF(OR(D210="",E210="",F210=""),"计划不完整：请填写加仓价、新止损价和风险预算",IF(OR(D210<=0,E210<=0,F210<=0,D210<=E210),"违规：加仓价必须高于新止损价，金额须大于0",IF(AND(B210>1,COUNTIFS($A$2:$A$1001,A210,$B$2:$B$1001,B210-1,$G$2:$G$1001,">0")=0),"违规：须先完成上一次加仓",IF(AND(B210>1,E210<SUMIFS($E$2:$E$1001,$A$2:$A$1001,A210,$B$2:$B$1001,B210-1)),"违规：新止损价不得低于上一次",IF(AND(B210>1,F210>SUMIFS($F$2:$F$1001,$A$2:$A$1001,A210,$B$2:$B$1001,B210-1)),"违规：风险预算须逐次不增加",IF(OR(_LockStatus="已锁仓",_LockStatus="解锁信息不完整"),"违规：锁仓期间禁止加仓",IF(G210="","计划可执行：建议股数见N列",IF(OR(G210<=0,G210<>INT(G210),MOD(G210,100)<>0),"违规：实际股数须为100股整数倍",IF(G210>N210,"违规：实际股数超过风险或金字塔上限",IF(AND(B210>1,G210>SUMIFS($G$2:$G$1001,$A$2:$A$1001,A210,$B$2:$B$1001,B210-1)),"违规：加仓股数须逐次不增加",IF(Q210>F210,"违规：止损风险超过本次预算","通过")))))))))))))))
H211: =IF(OR(A211="",D211="",G211=""),"",D211*G211) | I211: =IF(OR(A211="",B211=""),"",IFERROR(LOOKUP(2,1/(单次交易!$A$2:$A$201=A211),单次交易!$H$2:$H$201),0)+SUMIFS($G$2:$G$1001,$A$2:$A$1001,A211,$B$2:$B$1001,"<"&B211)) | J211: =IF(OR(A211="",B211=""),"",IFERROR(LOOKUP(2,1/(单次交易!$A$2:$A$201=A211),单次交易!$E$2:$E$201)*LOOKUP(2,1/(单次交易!$A$2:$A$201=A211),单次交易!$H$2:$H$201),0)+SUMIFS($H$2:$H$1001,$A$2:$A$1001,A211,$B$2:$B$1001,"<"&B211)) | K211: =IF(OR(E211="",I211="",J211=""),"",MAX(E211*I211-J211,0)) | L211: =IF(OR(D211="",E211="",F211="",D211<=E211),"",FLOOR((F211+K211)/(D211-E211),100)) | M211: =IF(OR(A211="",B211="",L211=""),"",IF(B211=1,L211,IFERROR(SUMIFS($G$2:$G$1001,$A$2:$A$1001,A211,$B$2:$B$1001,B211-1),0))) | N211: =IF(OR(L211="",M211=""),"",MIN(L211,M211)) | O211: =IF(OR(I211="",G211=""),"",I211+G211) | P211: =IF(OR(O211="",O211=0),"",(J211+H211)/O211) | Q211: =IF(OR(O211="",E211=""),"",MAX(J211+H211-E211*O211,0)) | R211: =IF(A211="","",IF(COUNTIF(_TradeIds,A211)=0,"违规：交易编号不存在",IF(OR(B211="",B211<1,B211>5,B211<>INT(B211)),"违规：加仓序号须为1到5的整数",IF(COUNTIFS($A$2:$A$1001,A211,$B$2:$B$1001,B211)>1,"违规：同一交易的加仓序号重复",IF(OR(D211="",E211="",F211=""),"计划不完整：请填写加仓价、新止损价和风险预算",IF(OR(D211<=0,E211<=0,F211<=0,D211<=E211),"违规：加仓价必须高于新止损价，金额须大于0",IF(AND(B211>1,COUNTIFS($A$2:$A$1001,A211,$B$2:$B$1001,B211-1,$G$2:$G$1001,">0")=0),"违规：须先完成上一次加仓",IF(AND(B211>1,E211<SUMIFS($E$2:$E$1001,$A$2:$A$1001,A211,$B$2:$B$1001,B211-1)),"违规：新止损价不得低于上一次",IF(AND(B211>1,F211>SUMIFS($F$2:$F$1001,$A$2:$A$1001,A211,$B$2:$B$1001,B211-1)),"违规：风险预算须逐次不增加",IF(OR(_LockStatus="已锁仓",_LockStatus="解锁信息不完整"),"违规：锁仓期间禁止加仓",IF(G211="","计划可执行：建议股数见N列",IF(OR(G211<=0,G211<>INT(G211),MOD(G211,100)<>0),"违规：实际股数须为100股整数倍",IF(G211>N211,"违规：实际股数超过风险或金字塔上限",IF(AND(B211>1,G211>SUMIFS($G$2:$G$1001,$A$2:$A$1001,A211,$B$2:$B$1001,B211-1)),"违规：加仓股数须逐次不增加",IF(Q211>F211,"违规：止损风险超过本次预算","通过")))))))))))))))
H212: =IF(OR(A212="",D212="",G212=""),"",D212*G212) | I212: =IF(OR(A212="",B212=""),"",IFERROR(LOOKUP(2,1/(单次交易!$A$2:$A$201=A212),单次交易!$H$2:$H$201),0)+SUMIFS($G$2:$G$1001,$A$2:$A$1001,A212,$B$2:$B$1001,"<"&B212)) | J212: =IF(OR(A212="",B212=""),"",IFERROR(LOOKUP(2,1/(单次交易!$A$2:$A$201=A212),单次交易!$E$2:$E$201)*LOOKUP(2,1/(单次交易!$A$2:$A$201=A212),单次交易!$H$2:$H$201),0)+SUMIFS($H$2:$H$1001,$A$2:$A$1001,A212,$B$2:$B$1001,"<"&B212)) | K212: =IF(OR(E212="",I212="",J212=""),"",MAX(E212*I212-J212,0)) | L212: =IF(OR(D212="",E212="",F212="",D212<=E212),"",FLOOR((F212+K212)/(D212-E212),100)) | M212: =IF(OR(A212="",B212="",L212=""),"",IF(B212=1,L212,IFERROR(SUMIFS($G$2:$G$1001,$A$2:$A$1001,A212,$B$2:$B$1001,B212-1),0))) | N212: =IF(OR(L212="",M212=""),"",MIN(L212,M212)) | O212: =IF(OR(I212="",G212=""),"",I212+G212) | P212: =IF(OR(O212="",O212=0),"",(J212+H212)/O212) | Q212: =IF(OR(O212="",E212=""),"",MAX(J212+H212-E212*O212,0)) | R212: =IF(A212="","",IF(COUNTIF(_TradeIds,A212)=0,"违规：交易编号不存在",IF(OR(B212="",B212<1,B212>5,B212<>INT(B212)),"违规：加仓序号须为1到5的整数",IF(COUNTIFS($A$2:$A$1001,A212,$B$2:$B$1001,B212)>1,"违规：同一交易的加仓序号重复",IF(OR(D212="",E212="",F212=""),"计划不完整：请填写加仓价、新止损价和风险预算",IF(OR(D212<=0,E212<=0,F212<=0,D212<=E212),"违规：加仓价必须高于新止损价，金额须大于0",IF(AND(B212>1,COUNTIFS($A$2:$A$1001,A212,$B$2:$B$1001,B212-1,$G$2:$G$1001,">0")=0),"违规：须先完成上一次加仓",IF(AND(B212>1,E212<SUMIFS($E$2:$E$1001,$A$2:$A$1001,A212,$B$2:$B$1001,B212-1)),"违规：新止损价不得低于上一次",IF(AND(B212>1,F212>SUMIFS($F$2:$F$1001,$A$2:$A$1001,A212,$B$2:$B$1001,B212-1)),"违规：风险预算须逐次不增加",IF(OR(_LockStatus="已锁仓",_LockStatus="解锁信息不完整"),"违规：锁仓期间禁止加仓",IF(G212="","计划可执行：建议股数见N列",IF(OR(G212<=0,G212<>INT(G212),MOD(G212,100)<>0),"违规：实际股数须为100股整数倍",IF(G212>N212,"违规：实际股数超过风险或金字塔上限",IF(AND(B212>1,G212>SUMIFS($G$2:$G$1001,$A$2:$A$1001,A212,$B$2:$B$1001,B212-1)),"违规：加仓股数须逐次不增加",IF(Q212>F212,"违规：止损风险超过本次预算","通过")))))))))))))))
... H1001: =IF(OR(A1001="",D1001="",G1001=""),"",D1001*G1001) | I1001: =IF(OR(A1001="",B1001=""),"",IFERROR(LOOKUP(2,1/(单次交易!$A$2:$A$201=A1001),单次交易!$H$2:$H$201),0)+SUMIFS($G$2:$G$1001,$A$2:$A$1001,A1001,$B$2:$B$1001,"<"&B1001)) | J1001: =IF(OR(A1001="",B1001=""),"",IFERROR(LOOKUP(2,1/(单次交易!$A$2:$A$201=A1001),单次交易!$E$2:$E$201)*LOOKUP(2,1/(单次交易!$A$2:$A$201=A1001),单次交易!$H$2:$H$201),0)+SUMIFS($H$2:$H$1001,$A$2:$A$1001,A1001,$B$2:$B$1001,"<"&B1001)) | K1001: =IF(OR(E1001="",I1001="",J1001=""),"",MAX(E1001*I1001-J1001,0)) | L1001: =IF(OR(D1001="",E1001="",F1001="",D1001<=E1001),"",FLOOR((F1001+K1001)/(D1001-E1001),100)) | M1001: =IF(OR(A1001="",B1001="",L1001=""),"",IF(B1001=1,L1001,IFERROR(SUMIFS($G$2:$G$1001,$A$2:$A$1001,A1001,$B$2:$B$1001,B1001-1),0))) | N1001: =IF(OR(L1001="",M1001=""),"",MIN(L1001,M1001)) | O1001: =IF(OR(I1001="",G1001=""),"",I1001+G1001) | P1001: =IF(OR(O1001="",O1001=0),"",(J1001+H1001)/O1001) | Q1001: =IF(OR(O1001="",E1001=""),"",MAX(J1001+H1001-E1001*O1001,0)) | R1001: =IF(A1001="","",IF(COUNTIF(_TradeIds,A1001)=0,"违规：交易编号不存在",IF(OR(B1001="",B1001<1,B1001>5,B1001<>INT(B1001)),"违规：加仓序号须为1到5的整数",IF(COUNTIFS($A$2:$A$1001,A1001,$B$2:$B$1001,B1001)>1,"违规：同一交易的加仓序号重复",IF(OR(D1001="",E1001="",F1001=""),"计划不完整：请填写加仓价、新止损价和风险预算",IF(OR(D1001<=0,E1001<=0,F1001<=0,D1001<=E1001),"违规：加仓价必须高于新止损价，金额须大于0",IF(AND(B1001>1,COUNTIFS($A$2:$A$1001,A1001,$B$2:$B$1001,B1001-1,$G$2:$G$1001,">0")=0),"违规：须先完成上一次加仓",IF(AND(B1001>1,E1001<SUMIFS($E$2:$E$1001,$A$2:$A$1001,A1001,$B$2:$B$1001,B1001-1)),"违规：新止损价不得低于上一次",IF(AND(B1001>1,F1001>SUMIFS($F$2:$F$1001,$A$2:$A$1001,A1001,$B$2:$B$1001,B1001-1)),"违规：风险预算须逐次不增加",IF(OR(_LockStatus="已锁仓",_LockStatus="解锁信息不完整"),"违规：锁仓期间禁止加仓",IF(G1001="","计划可执行：建议股数见N列",IF(OR(G1001<=0,G1001<>INT(G1001),MOD(G1001,100)<>0),"违规：实际股数须为100股整数倍",IF(G1001>N1001,"违规：实际股数超过风险或金字塔上限",IF(AND(B1001>1,G1001>SUMIFS($G$2:$G$1001,$A$2:$A$1001,A1001,$B$2:$B$1001,B1001-1)),"违规：加仓股数须逐次不增加",IF(Q1001>F1001,"违规：止损风险超过本次预算","通过")))))))))))))))

Sheet 多次统计数据
A1: 指标 | B1: 当前统计 | C1: 口径说明
A2: 已完成交易数 | B2: =COUNT(单次交易!M2:M201) -> 100 | C2: 存在卖出日期的交易
A3: 盈利交易数 | B3: =COUNTIF(单次交易!X2:X201,">0") -> 52 | C3: 实际盈亏金额大于0
A4: 亏损交易数 | B4: =COUNTIF(单次交易!X2:X201,"<0") -> 48 | C4: 实际盈亏金额小于0
A5: 持平交易数 | B5: =COUNTIFS(单次交易!M2:M201,"<>",单次交易!X2:X201,"=0") -> 0 | C5: 已卖出且实际盈亏为0；不进入胜负样本
A6: 盈利概率 | B6: =IFERROR(B3/(B3+B4),"") -> 0.52 | C6: 盈利数÷胜负交易数
A7: 亏损概率 | B7: =IFERROR(B4/(B3+B4),"") -> 0.48 | C7: 亏损数÷胜负交易数
A8: 平均盈利百分比 | B8: =IFERROR(AVERAGEIF(单次交易!X2:X201,">0",单次交易!AE2:AE201),"") -> 0.098209966 | C8: 盈利交易实际账户收益率的平均值
A9: 平均亏损百分比 | B9: =IFERROR(-AVERAGEIF(单次交易!X2:X201,"<0",单次交易!AE2:AE201),"") -> 0.043183794 | C9: 亏损交易实际账户收益率绝对值的平均值
A10: 盈利的持有总天数 | B10: =SUMIF(单次交易!X2:X201,">0",单次交易!AA2:AA201) -> 4652 | C10: 自然日
A11: 亏损的持有总天数 | B11: =SUMIF(单次交易!X2:X201,"<0",单次交易!AA2:AA201) -> 3008 | C11: 自然日
A12: 平均交易金额 | B12: =IFERROR(SUMPRODUCT(单次交易!AO2:AO201,单次交易!AP2:AP201)/COUNT(单次交易!AP2:AP201),"") -> 315542.75 | C12: 实际加权买入价×累计买入股数的平均值，包含未卖出交易
A13: 期望收益率 | B13: =IF(OR(B6="",B7="",B8="",B9=""),"",B6*B8-B7*B9) -> 0.030340961 | C13: 盈利贡献减亏损贡献
A14: 迄今为止的复利净利润率 | B14: =IF(COUNT(单次交易!AE2:AE201)=0,"",EXP(SUMPRODUCT(IFERROR(LN(1+单次交易!AE2:AE201),0)))-1) -> 10.615736 | C14: 按每笔实际账户收益率逐笔连乘

Sheet 账户数据
A1: 指标 | B1: 值 | C1: 录入/计算说明
A2: 初始总金额 | B2: 100000 | C2: 手动输入；当前金额从此值开始累计
A3: 当前总金额 | B3: =IF(B2="","",B2+SUM(单次交易!X2:X201)) -> 1148578 | C3: 初始总金额＋全部已实现盈亏
A4: 单次交易允许的亏损比例 | B4: 0.02 | C4: 默认1%，可调整；开仓时复制为交易快照
A5: 单次交易允许的亏损金额 | B5: =IF(B3="","",B3*B4) -> 22971.56 | C5: 当前总金额×单次允许亏损比例
A6: 当月允许最大亏损比例 | B6: 0.06 | C6: 默认5%，可调整
A7: 当月允许最大亏损金额 | B7: =IF(B3="","",B3*B6) -> 68914.68 | C7: 当前总金额×当月最大亏损比例
A8: 当月亏损金额 | B8: =SUMIFS(单次交易!X2:X201,单次交易!X2:X201,"<0",单次交易!M2:M201,">="&EOMONTH(TODAY(),-1)+1,单次交易!M2:M201,"<="&EOMONTH(TODAY(),0)) -> 0 | C8: 按卖出日期统计本月已实现亏损，保留负号
A9: 当前未平仓理论亏损 | B9: =IFERROR(SUM(单次交易!AQ2:AQ201),0) -> 0 | C9: 未平仓三批持仓按当前有效止损计算的风险合计
A10: 当月剩余可开仓风险额度 | B10: =IF(OR(B7="",B9=""),"",B7-B9) -> 68914.68 | C10: 当月允许最大亏损金额－当前未平仓理论亏损
A11: 账户实际累计收益率 | B11: =IF(OR(B2="",B3="",B2<=0),"",B3/B2-1) -> 10.48578 | C11: 当前总金额÷初始总金额－1；无入金出金时为账户权威累计收益
A13: 连续亏损锁仓比例 | B13: 0.06 | C13: 从最近盈利或有效手动解锁后的下一笔开始累计；默认6%
A14: 最近盈利记录序号 | B14: =IFERROR(LOOKUP(2,1/((单次交易!$M$2:$M$201<>"")*(单次交易!$X$2:$X$201>0)),ROW(单次交易!$X$2:$X$201)-1),0) -> 100 | C14: 按工作表记录顺序查找最近一笔已平仓盈利交易
A15: 最近已完成记录序号 | B15: =IFERROR(LOOKUP(2,1/(单次交易!$M$2:$M$201<>""),ROW(单次交易!$M$2:$M$201)-1),0) -> 100 | C15: 按工作表记录顺序查找最后一笔已平仓交易
A16: 手动解锁截至记录序号 | B16: 98 | C16: 锁仓复盘后填写当前最近已完成记录序号；须同时填写解锁原因
A17: 手动解锁原因 | B17: 解锁 | C17: 例如：已完成复盘，开始新的模拟周期
A18: 当前周期起点序号 | B18: =MAX(B14,IF(AND(ISNUMBER(B16),B16>=1,B16<=B15,B17<>""),B16,0)) -> 100 | C18: 取最近盈利序号与有效手动解锁序号中的较大值
A19: 周期起点账户金额 | B19: =IF(B2="","",IF(B18=0,B2,B2+SUM(单次交易!$X$2:INDEX(单次交易!$X:$X,B18+1)))) -> 1148578 | C19: 初始金额加上周期起点及以前的全部已实现盈亏
A20: 当前周期累计亏损 | B20: =IF(B18>=B15,0,-SUMPRODUCT((ROW(单次交易!$X$2:$X$201)-1>B18)*(单次交易!$M$2:$M$201<>"")*(IFERROR(单次交易!$X$2:$X$201,0)<0)*IFERROR(单次交易!$X$2:$X$201,0))) -> 0 | C20: 仅累计周期起点之后的已平仓亏损；盈利会自动成为新起点
A21: 连续亏损比例 | B21: =IF(OR(B19="",B19<=0),"",B20/B19) -> 0 | C21: 当前周期累计亏损÷周期起点账户金额
A22: 锁仓风险使用率 | B22: =IF(OR(B13="",B13<=0,B21=""),"",B21/B13) -> 0 | C22: 达到80%预警，达到100%锁仓
A23: 连续亏损锁仓状态 | B23: =IF(OR(AND(B16<>"",B17=""),AND(B16="",B17<>""),AND(B16<>"",OR(NOT(ISNUMBER(B16)),B16<1,B16>B15,B16<>INT(B16)))),"解锁信息不完整",IF(B22>=1,"已锁仓",IF(B22>=0.8,"接近锁仓","正常"))) -> 正常 | C23: 锁仓时禁止新开仓；有效手动解锁后从下一笔重新累计

Sheet 目标收益
A1: 指标 | B1: 值 | C1: 口径说明
A2: 总金额 | B2: =账户数据!B3 -> 1148578 | C2: 来自账户当前总金额
A3: 目标收益率 | B3: 0.1 | C3: 手动输入
A4: 目标收益金额 | B4: =IF(OR(B2="",B3=""),"",B2*B3) -> 114857.8 | C4: 总金额×目标收益率
A5: 平均交易金额 | B5: =多次统计数据!B12 -> 315542.75 | C5: 来自历史交易统计
A6: 历史期望收益率 | B6: =多次统计数据!B13 -> 0.030340961 | C6: 来自历史胜率与平均盈亏
A7: 所需投资笔数 | B7: =IF(OR(B3="",B6="",B3<=0,B6<=0),"暂不可计算",ROUNDUP(LN(1+B3)/LN(1+B6),0)) -> 4 | C7: 按目标收益率与历史账户期望收益率复利计算并向上取整

Sheet Sheet1
