Workbook
Name _AccountRiskLimit: 账户数据!$B$7
Name _LockStatus: 账户数据!$B$23
Name _TradeIds: 单次交易!$A$2:$A$201

Sheet 单次交易
A1: 交易编号 | B1: 股票代码 | C1: 买入时账户金额 | D1: 本次允许亏损比例 | E1: 第一批买入价 | F1: 买入建议股数 | G1: 开仓风险告警 | H1: 第一批买入股数 | I1: 首次买入日期 | J1: 期望卖出价 | K1: 实际卖出价（填写） | L1: 最终卖出股数（自动） | M1: 卖出日期（填写） | N1: 止损价 | O1: 买入总费用 | P1: 卖出费用（填写） | Q1: 买入价的由来 | R1: 止损价的由来 | S1: 期望卖出价的由来 | T1: 实际卖出价的由来 | U1: 期望盈利比例 | V1: 期望止损比例 | W1: 盈亏比 | X1: 加权后实际盈亏 | Y1: 单笔仓位收益率 | Z1: 账户收益率与平均盈利率差值 | AA1: 持有天数 | AB1: 复利容许平均亏损上限 | AC1: 复利风险判断 | AD1: 交易打分评价 | AE1: 实际账户收益率 | AF1: 列1 | AG1: 交易预期类型 | AH1: 预期持有周期 | AI1: 预期选择理由 | AJ1: 周期匹配检查 | AK1: 已执行加仓次数 | AL1: 加仓总股数 | AM1: 最近加仓价 | AN1: 最新加仓止损价 | AO1: 实际加权买入价 | AP1: 最终持仓股数 | AQ1: 当前净止损风险 | AR1: 加仓规则检查
A2: 1 | B2: 中国卫通 | C2: 100000 | D2: 0.02 | E2: 20.87 | F2: =IF(OR(C2="",D2="",E2="",N2="",C2<=0,D2<=0,E2<=N2),"",ROUNDDOWN((C2*D2)/(E2-N2)/100,0)*100) -> 1100 | G2: =IF(A2="","",IF(H2<>"","已开仓",IF(账户数据!$B$23="已锁仓","禁止开仓：连续亏损达到上限",IF(账户数据!$B$23="解锁信息不完整","禁止开仓：请完整填写解锁信息",IF(OR(F2="",E2="",N2="",E2<=N2,账户数据!$B$7=""),"",IF(OR(AG2="",AH2="",AI2=""),"禁止开仓：交易预期未填写完整",IF(账户数据!$B$9+F2*(E2-N2)>=账户数据!$B$7,"禁止开仓：风险额度不足",IF(AJ2="周期与交易预期不匹配，请重新确认",IF(账户数据!$B$23="接近锁仓","允许开仓（接近锁仓；周期需复核）","允许开仓（周期需复核）"),IF(账户数据!$B$23="接近锁仓","允许开仓（接近锁仓）","允许开仓"))))))))) -> 已开仓 | H2: 1100 | I2: 44020 | J2: 24 | K2: 21.57 | L2: =IF(AP2="","",AP2) -> 2600 | M2: 44036 | N2: 19.17 | U2: =IF(OR(AO2="",J2="",AO2<=0),"",(J2-AO2)/AO2) -> 0.088872215 | V2: =IF(OR(AO2="",N2="",AO2<=0),"",(AO2-N2)/AO2) -> 0.13026332 | W2: =IF(OR(U2="",V2="",V2<=0),"",U2/V2) -> 0.6822505 | X2: =IF(OR(K2="",L2="",AO2="",AP2=""),"",(K2-AO2)*L2-IF(O2="",0,O2)-IF(P2="",0,P2)) -> -1225 | Y2: =IF(OR(X2="",AO2="",L2=""),"",IF(AO2*L2+IF(O2="",0,O2)<=0,"",X2/(AO2*L2+IF(O2="",0,O2)))) -> -0.021376097 | Z2: =IF(OR(AE2="",多次统计数据!$B$8=""),"",AE2-多次统计数据!$B$8) -> -0.12246267 | AA2: =IF(OR(I2="",M2="",M2<I2),"",M2-I2) -> 16 | AB2: =IF(OR(A2="",多次统计数据!$B$8="",多次统计数据!$B$6<=0,多次统计数据!$B$6>=1),"",1-POWER(1+多次统计数据!$B$8,-多次统计数据!$B$6/(1-多次统计数据!$B$6))) -> 0.081520133 | AC2: =IF(OR(AB2="",多次统计数据!$B$9=""),"",IF(多次统计数据!$B$9<AB2,"低于上限","达到或超过上限")) -> 低于上限 | AE2: =IF(OR(X2="",C2="",C2<=0),"",X2/C2) -> -0.01225 | AG2: 突破冲新高 | AH2: 4～10个交易日 | AI2: 新高 | AJ2: =IF(OR(AG2="",AH2=""),"",IF(OR(AND(AG2="短期博反弹",OR(AH2="1～3个交易日",AH2="4～10个交易日")),AND(AG2="突破冲新高",OR(AH2="4～10个交易日",AH2="11～20个交易日")),AND(AG2="趋势波段",OR(AH2="11～20个交易日",AH2="21～60个交易日",AH2="60个交易日以上"))),"匹配","周期与交易预期不匹配，请重新确认")) -> 匹配 | AK2: =IF(A2="","",COUNTIFS(加仓管理!$A$2:$A$1001,A2,加仓管理!$G$2:$G$1001,">0")) -> 2 | AL2: =IF(A2="","",SUMIFS(加仓管理!$G$2:$G$1001,加仓管理!$A$2:$A$1001,A2)) -> 1500 | AM2: =IF(AK2=0,"",IFERROR(LOOKUP(2,1/((加仓管理!$A$2:$A$1001=A2)*(加仓管理!$G$2:$G$1001>0)),加仓管理!$D$2:$D$1001),"")) -> 24 | AN2: =IF(AK2=0,"",IFERROR(LOOKUP(2,1/((加仓管理!$A$2:$A$1001=A2)*(加仓管理!$G$2:$G$1001>0)),加仓管理!$E$2:$E$1001),"")) -> 22 | AO2: =IF(OR(A2="",H2="",H2<=0),"",(E2*H2+SUMIFS(加仓管理!$H$2:$H$1001,加仓管理!$A$2:$A$1001,A2))/AP2) -> 22.041154 | AP2: =IF(OR(A2="",H2="",H2<=0),"",H2+AL2) -> 2600 | AQ2: =IF(A2="","",IF(M2<>"",0,IF(OR(H2="",N2=""),"",MAX((E2*H2+SUMIFS(加仓管理!$H$2:$H$1001,加仓管理!$A$2:$A$1001,A2))-MAX(N2,AN2)*AP2,0)))) -> 0 | AR2: =IF(A2="","",IF(OR(E2="",H2=""),"违规：首次买入价格或股数缺失",IF(COUNTIFS(加仓管理!$A$2:$A$1001,A2,加仓管理!$R$2:$R$1001,"违规*")>0,"违规：请检查加仓管理表",IF(SUM($AQ$2:$AQ$201)>账户数据!$B$7,"预警：超过账户风险上限",IF(COUNTIFS(加仓管理!$A$2:$A$1001,A2,加仓管理!$N$2:$N$1001,">0",加仓管理!$G$2:$G$1001,"")>0,"提示：存在待执行加仓计划","通过"))))) -> 违规：请检查加仓管理表
A3: 2 | B3: 中国卫通 | C3: 98775 | D3: 0.02 | E3: 17.88 | F3: =IF(OR(C3="",D3="",E3="",N3="",C3<=0,D3<=0,E3<=N3),"",ROUNDDOWN((C3*D3)/(E3-N3)/100,0)*100) -> 1400 | G3: =IF(A3="","",IF(H3<>"","已开仓",IF(账户数据!$B$23="已锁仓","禁止开仓：连续亏损达到上限",IF(账户数据!$B$23="解锁信息不完整","禁止开仓：请完整填写解锁信息",IF(OR(F3="",E3="",N3="",E3<=N3,账户数据!$B$7=""),"",IF(OR(AG3="",AH3="",AI3=""),"禁止开仓：交易预期未填写完整",IF(账户数据!$B$9+F3*(E3-N3)>=账户数据!$B$7,"禁止开仓：风险额度不足",IF(AJ3="周期与交易预期不匹配，请重新确认",IF(账户数据!$B$23="接近锁仓","允许开仓（接近锁仓；周期需复核）","允许开仓（周期需复核）"),IF(账户数据!$B$23="接近锁仓","允许开仓（接近锁仓）","允许开仓"))))))))) -> 已开仓 | H3: 1000 | I3: 44176 | J3: 20 | K3: 15.56 | L3: =IF(AP3="","",AP3) -> 3000 | M3: 44235 | N3: 16.5 | U3: =IF(OR(AO3="",J3="",AO3<=0),"",(J3-AO3)/AO3) -> 0.1082379 | V3: =IF(OR(AO3="",N3="",AO3<=0),"",(AO3-N3)/AO3) -> 0.085703731 | W3: =IF(OR(U3="",V3="",V3<=0),"",U3/V3) -> 1.262931 | X3: =IF(OR(K3="",L3="",AO3="",AP3=""),"",(K3-AO3)*L3-IF(O3="",0,O3)-IF(P3="",0,P3)) -> -7460 | Y3: =IF(OR(X3="",AO3="",L3=""),"",IF(AO3*L3+IF(O3="",0,O3)<=0,"",X3/(AO3*L3+IF(O3="",0,O3)))) -> -0.13779091 | Z3: =IF(OR(AE3="",多次统计数据!$B$8=""),"",AE3-多次统计数据!$B$8) -> -0.18573785 | AA3: =IF(OR(I3="",M3="",M3<I3),"",M3-I3) -> 59 | AB3: =IF(OR(A3="",多次统计数据!$B$8="",多次统计数据!$B$6<=0,多次统计数据!$B$6>=1),"",1-POWER(1+多次统计数据!$B$8,-多次统计数据!$B$6/(1-多次统计数据!$B$6))) -> 0.081520133 | AC3: =IF(OR(AB3="",多次统计数据!$B$9=""),"",IF(多次统计数据!$B$9<AB3,"低于上限","达到或超过上限")) -> 低于上限 | AE3: =IF(OR(X3="",C3="",C3<=0),"",X3/C3) -> -0.075525183 | AG3: 短期博反弹 | AH3: 4～10个交易日 | AI3: 吸筹 | AJ3: =IF(OR(AG3="",AH3=""),"",IF(OR(AND(AG3="短期博反弹",OR(AH3="1～3个交易日",AH3="4～10个交易日")),AND(AG3="突破冲新高",OR(AH3="4～10个交易日",AH3="11～20个交易日")),AND(AG3="趋势波段",OR(AH3="11～20个交易日",AH3="21～60个交易日",AH3="60个交易日以上"))),"匹配","周期与交易预期不匹配，请重新确认")) -> 匹配 | AK3: =IF(A3="","",COUNTIFS(加仓管理!$A$2:$A$1001,A3,加仓管理!$G$2:$G$1001,">0")) -> 2 | AL3: =IF(A3="","",SUMIFS(加仓管理!$G$2:$G$1001,加仓管理!$A$2:$A$1001,A3)) -> 2000 | AM3: =IF(AK3=0,"",IFERROR(LOOKUP(2,1/((加仓管理!$A$2:$A$1001=A3)*(加仓管理!$G$2:$G$1001>0)),加仓管理!$D$2:$D$1001),"")) -> 17.21 | AN3: =IF(AK3=0,"",IFERROR(LOOKUP(2,1/((加仓管理!$A$2:$A$1001=A3)*(加仓管理!$G$2:$G$1001>0)),加仓管理!$E$2:$E$1001),"")) -> 16.5 | AO3: =IF(OR(A3="",H3="",H3<=0),"",(E3*H3+SUMIFS(加仓管理!$H$2:$H$1001,加仓管理!$A$2:$A$1001,A3))/AP3) -> 18.046667 | AP3: =IF(OR(A3="",H3="",H3<=0),"",H3+AL3) -> 3000 | AQ3: =IF(A3="","",IF(M3<>"",0,IF(OR(H3="",N3=""),"",MAX((E3*H3+SUMIFS(加仓管理!$H$2:$H$1001,加仓管理!$A$2:$A$1001,A3))-MAX(N3,AN3)*AP3,0)))) -> 0 | AR3: =IF(A3="","",IF(OR(E3="",H3=""),"违规：首次买入价格或股数缺失",IF(COUNTIFS(加仓管理!$A$2:$A$1001,A3,加仓管理!$R$2:$R$1001,"违规*")>0,"违规：请检查加仓管理表",IF(SUM($AQ$2:$AQ$201)>账户数据!$B$7,"预警：超过账户风险上限",IF(COUNTIFS(加仓管理!$A$2:$A$1001,A3,加仓管理!$N$2:$N$1001,">0",加仓管理!$G$2:$G$1001,"")>0,"提示：存在待执行加仓计划","通过"))))) -> 违规：请检查加仓管理表
A4: 3 | B4: 中国卫通 | C4: 91315 | D4: 0.02 | E4: 15.12 | F4: =IF(OR(C4="",D4="",E4="",N4="",C4<=0,D4<=0,E4<=N4),"",ROUNDDOWN((C4*D4)/(E4-N4)/100,0)*100) -> 2900 | G4: =IF(A4="","",IF(H4<>"","已开仓",IF(账户数据!$B$23="已锁仓","禁止开仓：连续亏损达到上限",IF(账户数据!$B$23="解锁信息不完整","禁止开仓：请完整填写解锁信息",IF(OR(F4="",E4="",N4="",E4<=N4,账户数据!$B$7=""),"",IF(OR(AG4="",AH4="",AI4=""),"禁止开仓：交易预期未填写完整",IF(账户数据!$B$9+F4*(E4-N4)>=账户数据!$B$7,"禁止开仓：风险额度不足",IF(AJ4="周期与交易预期不匹配，请重新确认",IF(账户数据!$B$23="接近锁仓","允许开仓（接近锁仓；周期需复核）","允许开仓（周期需复核）"),IF(账户数据!$B$23="接近锁仓","允许开仓（接近锁仓）","允许开仓"))))))))) -> 已开仓 | H4: 2900 | I4: 44264 | J4: 18 | K4: 13.94 | L4: =IF(AP4="","",AP4) -> 5700 | M4: 44434 | N4: 14.5 | U4: =IF(OR(AO4="",J4="",AO4<=0),"",(J4-AO4)/AO4) -> 0.13534509 | V4: =IF(OR(AO4="",N4="",AO4<=0),"",(AO4-N4)/AO4) -> 0.085416459 | W4: =IF(OR(U4="",V4="",V4<=0),"",U4/V4) -> 1.5845317 | X4: =IF(OR(K4="",L4="",AO4="",AP4=""),"",(K4-AO4)*L4-IF(O4="",0,O4)-IF(P4="",0,P4)) -> -10911 | Y4: =IF(OR(X4="",AO4="",L4=""),"",IF(AO4*L4+IF(O4="",0,O4)<=0,"",X4/(AO4*L4+IF(O4="",0,O4)))) -> -0.12073831 | Z4: =IF(OR(AE4="",多次统计数据!$B$8=""),"",AE4-多次统计数据!$B$8) -> -0.22970016 | AA4: =IF(OR(I4="",M4="",M4<I4),"",M4-I4) -> 170 | AB4: =IF(OR(A4="",多次统计数据!$B$8="",多次统计数据!$B$6<=0,多次统计数据!$B$6>=1),"",1-POWER(1+多次统计数据!$B$8,-多次统计数据!$B$6/(1-多次统计数据!$B$6))) -> 0.081520133 | AC4: =IF(OR(AB4="",多次统计数据!$B$9=""),"",IF(多次统计数据!$B$9<AB4,"低于上限","达到或超过上限")) -> 低于上限 | AE4: =IF(OR(X4="",C4="",C4<=0),"",X4/C4) -> -0.11948749 | AG4: 短期博反弹 | AH4: 4～10个交易日 | AI4: 吸筹 | AJ4: =IF(OR(AG4="",AH4=""),"",IF(OR(AND(AG4="短期博反弹",OR(AH4="1～3个交易日",AH4="4～10个交易日")),AND(AG4="突破冲新高",OR(AH4="4～10个交易日",AH4="11～20个交易日")),AND(AG4="趋势波段",OR(AH4="11～20个交易日",AH4="21～60个交易日",AH4="60个交易日以上"))),"匹配","周期与交易预期不匹配，请重新确认")) -> 匹配 | AK4: =IF(A4="","",COUNTIFS(加仓管理!$A$2:$A$1001,A4,加仓管理!$G$2:$G$1001,">0")) -> 3 | AL4: =IF(A4="","",SUMIFS(加仓管理!$G$2:$G$1001,加仓管理!$A$2:$A$1001,A4)) -> 2800 | AM4: =IF(AK4=0,"",IFERROR(LOOKUP(2,1/((加仓管理!$A$2:$A$1001=A4)*(加仓管理!$G$2:$G$1001>0)),加仓管理!$D$2:$D$1001),"")) -> 15.42 | AN4: =IF(AK4=0,"",IFERROR(LOOKUP(2,1/((加仓管理!$A$2:$A$1001=A4)*(加仓管理!$G$2:$G$1001>0)),加仓管理!$E$2:$E$1001),"")) -> 14.81 | AO4: =IF(OR(A4="",H4="",H4<=0),"",(E4*H4+SUMIFS(加仓管理!$H$2:$H$1001,加仓管理!$A$2:$A$1001,A4))/AP4) -> 15.854211 | AP4: =IF(OR(A4="",H4="",H4<=0),"",H4+AL4) -> 5700 | AQ4: =IF(A4="","",IF(M4<>"",0,IF(OR(H4="",N4=""),"",MAX((E4*H4+SUMIFS(加仓管理!$H$2:$H$1001,加仓管理!$A$2:$A$1001,A4))-MAX(N4,AN4)*AP4,0)))) -> 0 | AR4: =IF(A4="","",IF(OR(E4="",H4=""),"违规：首次买入价格或股数缺失",IF(COUNTIFS(加仓管理!$A$2:$A$1001,A4,加仓管理!$R$2:$R$1001,"违规*")>0,"违规：请检查加仓管理表",IF(SUM($AQ$2:$AQ$201)>账户数据!$B$7,"预警：超过账户风险上限",IF(COUNTIFS(加仓管理!$A$2:$A$1001,A4,加仓管理!$N$2:$N$1001,">0",加仓管理!$G$2:$G$1001,"")>0,"提示：存在待执行加仓计划","通过"))))) -> 违规：请检查加仓管理表
A5: 4 | B5: 中国卫通 | C5: 80404 | D5: 0.02 | E5: 15.62 | F5: =IF(OR(C5="",D5="",E5="",N5="",C5<=0,D5<=0,E5<=N5),"",ROUNDDOWN((C5*D5)/(E5-N5)/100,0)*100) -> 2500 | G5: =IF(A5="","",IF(H5<>"","已开仓",IF(账户数据!$B$23="已锁仓","禁止开仓：连续亏损达到上限",IF(账户数据!$B$23="解锁信息不完整","禁止开仓：请完整填写解锁信息",IF(OR(F5="",E5="",N5="",E5<=N5,账户数据!$B$7=""),"",IF(OR(AG5="",AH5="",AI5=""),"禁止开仓：交易预期未填写完整",IF(账户数据!$B$9+F5*(E5-N5)>=账户数据!$B$7,"禁止开仓：风险额度不足",IF(AJ5="周期与交易预期不匹配，请重新确认",IF(账户数据!$B$23="接近锁仓","允许开仓（接近锁仓；周期需复核）","允许开仓（周期需复核）"),IF(账户数据!$B$23="接近锁仓","允许开仓（接近锁仓）","允许开仓"))))))))) -> 已开仓 | H5: 2500 | I5: 44799 | J5: 10.59 | K5: 10.59 | L5: =IF(AP5="","",AP5) -> 4900 | M5: 44799 | N5: 15 | U5: =IF(OR(AO5="",J5="",AO5<=0),"",(J5-AO5)/AO5) -> -0.34779166 | V5: =IF(OR(AO5="",N5="",AO5<=0),"",(AO5-N5)/AO5) -> 0.076192152 | W5: =IF(OR(U5="",V5="",V5<=0),"",U5/V5) -> -4.5646651 | X5: =IF(OR(K5="",L5="",AO5="",AP5=""),"",(K5-AO5)*L5-IF(O5="",0,O5)-IF(P5="",0,P5)) -> -27671 | Y5: =IF(OR(X5="",AO5="",L5=""),"",IF(AO5*L5+IF(O5="",0,O5)<=0,"",X5/(AO5*L5+IF(O5="",0,O5)))) -> -0.34779166 | Z5: =IF(OR(AE5="",多次统计数据!$B$8=""),"",AE5-多次统计数据!$B$8) -> -0.45436221 | AA5: =IF(OR(I5="",M5="",M5<I5),"",M5-I5) -> 0 | AB5: =IF(OR(A5="",多次统计数据!$B$8="",多次统计数据!$B$6<=0,多次统计数据!$B$6>=1),"",1-POWER(1+多次统计数据!$B$8,-多次统计数据!$B$6/(1-多次统计数据!$B$6))) -> 0.081520133 | AC5: =IF(OR(AB5="",多次统计数据!$B$9=""),"",IF(多次统计数据!$B$9<AB5,"低于上限","达到或超过上限")) -> 低于上限 | AE5: =IF(OR(X5="",C5="",C5<=0),"",X5/C5) -> -0.34414954 | AG5: 短期博反弹 | AH5: 4～10个交易日 | AI5: 反弹 | AJ5: =IF(OR(AG5="",AH5=""),"",IF(OR(AND(AG5="短期博反弹",OR(AH5="1～3个交易日",AH5="4～10个交易日")),AND(AG5="突破冲新高",OR(AH5="4～10个交易日",AH5="11～20个交易日")),AND(AG5="趋势波段",OR(AH5="11～20个交易日",AH5="21～60个交易日",AH5="60个交易日以上"))),"匹配","周期与交易预期不匹配，请重新确认")) -> 匹配 | AK5: =IF(A5="","",COUNTIFS(加仓管理!$A$2:$A$1001,A5,加仓管理!$G$2:$G$1001,">0")) -> 3 | AL5: =IF(A5="","",SUMIFS(加仓管理!$G$2:$G$1001,加仓管理!$A$2:$A$1001,A5)) -> 2400 | AM5: =IF(AK5=0,"",IFERROR(LOOKUP(2,1/((加仓管理!$A$2:$A$1001=A5)*(加仓管理!$G$2:$G$1001>0)),加仓管理!$D$2:$D$1001),"")) -> 16.08 | AN5: =IF(AK5=0,"",IFERROR(LOOKUP(2,1/((加仓管理!$A$2:$A$1001=A5)*(加仓管理!$G$2:$G$1001>0)),加仓管理!$E$2:$E$1001),"")) -> 16 | AO5: =IF(OR(A5="",H5="",H5<=0),"",(E5*H5+SUMIFS(加仓管理!$H$2:$H$1001,加仓管理!$A$2:$A$1001,A5))/AP5) -> 16.237143 | AP5: =IF(OR(A5="",H5="",H5<=0),"",H5+AL5) -> 4900 | AQ5: =IF(A5="","",IF(M5<>"",0,IF(OR(H5="",N5=""),"",MAX((E5*H5+SUMIFS(加仓管理!$H$2:$H$1001,加仓管理!$A$2:$A$1001,A5))-MAX(N5,AN5)*AP5,0)))) -> 0 | AR5: =IF(A5="","",IF(OR(E5="",H5=""),"违规：首次买入价格或股数缺失",IF(COUNTIFS(加仓管理!$A$2:$A$1001,A5,加仓管理!$R$2:$R$1001,"违规*")>0,"违规：请检查加仓管理表",IF(SUM($AQ$2:$AQ$201)>账户数据!$B$7,"预警：超过账户风险上限",IF(COUNTIFS(加仓管理!$A$2:$A$1001,A5,加仓管理!$N$2:$N$1001,">0",加仓管理!$G$2:$G$1001,"")>0,"提示：存在待执行加仓计划","通过"))))) -> 违规：请检查加仓管理表
A6: 5 | B6: 中国卫通 | C6: 52733 | D6: 0.02 | E6: 10.59 | F6: =IF(OR(C6="",D6="",E6="",N6="",C6<=0,D6<=0,E6<=N6),"",ROUNDDOWN((C6*D6)/(E6-N6)/100,0)*100) -> 1700 | G6: =IF(A6="","",IF(H6<>"","已开仓",IF(账户数据!$B$23="已锁仓","禁止开仓：连续亏损达到上限",IF(账户数据!$B$23="解锁信息不完整","禁止开仓：请完整填写解锁信息",IF(OR(F6="",E6="",N6="",E6<=N6,账户数据!$B$7=""),"",IF(OR(AG6="",AH6="",AI6=""),"禁止开仓：交易预期未填写完整",IF(账户数据!$B$9+F6*(E6-N6)>=账户数据!$B$7,"禁止开仓：风险额度不足",IF(AJ6="周期与交易预期不匹配，请重新确认",IF(账户数据!$B$23="接近锁仓","允许开仓（接近锁仓；周期需复核）","允许开仓（周期需复核）"),IF(账户数据!$B$23="接近锁仓","允许开仓（接近锁仓）","允许开仓"))))))))) -> 已开仓 | H6: 1700 | I6: 44707 | J6: 12 | K6: 11.29 | L6: =IF(AP6="","",AP6) -> 4700 | M6: 44925 | N6: 10 | U6: =IF(OR(AO6="",J6="",AO6<=0),"",(J6-AO6)/AO6) -> 0.09063485 | V6: =IF(OR(AO6="",N6="",AO6<=0),"",(AO6-N6)/AO6) -> 0.091137625 | W6: =IF(OR(U6="",V6="",V6<=0),"",U6/V6) -> 0.99448334 | X6: =IF(OR(K6="",L6="",AO6="",AP6=""),"",(K6-AO6)*L6-IF(O6="",0,O6)-IF(P6="",0,P6)) -> 1350 | Y6: =IF(OR(X6="",AO6="",L6=""),"",IF(AO6*L6+IF(O6="",0,O6)<=0,"",X6/(AO6*L6+IF(O6="",0,O6)))) -> 0.026105621 | Z6: =IF(OR(AE6="",多次统计数据!$B$8=""),"",AE6-多次统计数据!$B$8) -> -0.084612001 | AA6: =IF(OR(I6="",M6="",M6<I6),"",M6-I6) -> 218 | AB6: =IF(OR(A6="",多次统计数据!$B$8="",多次统计数据!$B$6<=0,多次统计数据!$B$6>=1),"",1-POWER(1+多次统计数据!$B$8,-多次统计数据!$B$6/(1-多次统计数据!$B$6))) -> 0.081520133 | AC6: =IF(OR(AB6="",多次统计数据!$B$9=""),"",IF(多次统计数据!$B$9<AB6,"低于上限","达到或超过上限")) -> 低于上限 | AE6: =IF(OR(X6="",C6="",C6<=0),"",X6/C6) -> 0.025600668 | AG6: 趋势波段 | AH6: 11～20个交易日 | AI6: 吸筹 | AJ6: =IF(OR(AG6="",AH6=""),"",IF(OR(AND(AG6="短期博反弹",OR(AH6="1～3个交易日",AH6="4～10个交易日")),AND(AG6="突破冲新高",OR(AH6="4～10个交易日",AH6="11～20个交易日")),AND(AG6="趋势波段",OR(AH6="11～20个交易日",AH6="21～60个交易日",AH6="60个交易日以上"))),"匹配","周期与交易预期不匹配，请重新确认")) -> 匹配 | AK6: =IF(A6="","",COUNTIFS(加仓管理!$A$2:$A$1001,A6,加仓管理!$G$2:$G$1001,">0")) -> 2 | AL6: =IF(A6="","",SUMIFS(加仓管理!$G$2:$G$1001,加仓管理!$A$2:$A$1001,A6)) -> 3000 | AM6: =IF(AK6=0,"",IFERROR(LOOKUP(2,1/((加仓管理!$A$2:$A$1001=A6)*(加仓管理!$G$2:$G$1001>0)),加仓管理!$D$2:$D$1001),"")) -> 10.66 | AN6: =IF(AK6=0,"",IFERROR(LOOKUP(2,1/((加仓管理!$A$2:$A$1001=A6)*(加仓管理!$G$2:$G$1001>0)),加仓管理!$E$2:$E$1001),"")) -> 10 | AO6: =IF(OR(A6="",H6="",H6<=0),"",(E6*H6+SUMIFS(加仓管理!$H$2:$H$1001,加仓管理!$A$2:$A$1001,A6))/AP6) -> 11.002766 | AP6: =IF(OR(A6="",H6="",H6<=0),"",H6+AL6) -> 4700 | AQ6: =IF(A6="","",IF(M6<>"",0,IF(OR(H6="",N6=""),"",MAX((E6*H6+SUMIFS(加仓管理!$H$2:$H$1001,加仓管理!$A$2:$A$1001,A6))-MAX(N6,AN6)*AP6,0)))) -> 0 | AR6: =IF(A6="","",IF(OR(E6="",H6=""),"违规：首次买入价格或股数缺失",IF(COUNTIFS(加仓管理!$A$2:$A$1001,A6,加仓管理!$R$2:$R$1001,"违规*")>0,"违规：请检查加仓管理表",IF(SUM($AQ$2:$AQ$201)>账户数据!$B$7,"预警：超过账户风险上限",IF(COUNTIFS(加仓管理!$A$2:$A$1001,A6,加仓管理!$N$2:$N$1001,">0",加仓管理!$G$2:$G$1001,"")>0,"提示：存在待执行加仓计划","通过"))))) -> 违规：请检查加仓管理表
A7: 6 | B7: 中国卫通 | C7: 54083 | D7: 0.02 | E7: 12.5 | F7: =IF(OR(C7="",D7="",E7="",N7="",C7<=0,D7<=0,E7<=N7),"",ROUNDDOWN((C7*D7)/(E7-N7)/100,0)*100) -> 1000 | G7: =IF(A7="","",IF(H7<>"","已开仓",IF(账户数据!$B$23="已锁仓","禁止开仓：连续亏损达到上限",IF(账户数据!$B$23="解锁信息不完整","禁止开仓：请完整填写解锁信息",IF(OR(F7="",E7="",N7="",E7<=N7,账户数据!$B$7=""),"",IF(OR(AG7="",AH7="",AI7=""),"禁止开仓：交易预期未填写完整",IF(账户数据!$B$9+F7*(E7-N7)>=账户数据!$B$7,"禁止开仓：风险额度不足",IF(AJ7="周期与交易预期不匹配，请重新确认",IF(账户数据!$B$23="接近锁仓","允许开仓（接近锁仓；周期需复核）","允许开仓（周期需复核）"),IF(账户数据!$B$23="接近锁仓","允许开仓（接近锁仓）","允许开仓"))))))))) -> 已开仓 | H7: 1000 | I7: 44943 | J7: 13 | K7: 16.89 | L7: =IF(AP7="","",AP7) -> 3000 | M7: 44988 | N7: 11.5 | U7: =IF(OR(AO7="",J7="",AO7<=0),"",(J7-AO7)/AO7) -> -0.07648591 | V7: =IF(OR(AO7="",N7="",AO7<=0),"",(AO7-N7)/AO7) -> 0.18304523 | W7: =IF(OR(U7="",V7="",V7<=0),"",U7/V7) -> -0.41785252 | X7: =IF(OR(K7="",L7="",AO7="",AP7=""),"",(K7-AO7)*L7-IF(O7="",0,O7)-IF(P7="",0,P7)) -> 8440 | Y7: =IF(OR(X7="",AO7="",L7=""),"",IF(AO7*L7+IF(O7="",0,O7)<=0,"",X7/(AO7*L7+IF(O7="",0,O7)))) -> 0.19985792 | Z7: =IF(OR(AE7="",多次统计数据!$B$8=""),"",AE7-多次统计数据!$B$8) -> 0.045843763 | AA7: =IF(OR(I7="",M7="",M7<I7),"",M7-I7) -> 45 | AB7: =IF(OR(A7="",多次统计数据!$B$8="",多次统计数据!$B$6<=0,多次统计数据!$B$6>=1),"",1-POWER(1+多次统计数据!$B$8,-多次统计数据!$B$6/(1-多次统计数据!$B$6))) -> 0.081520133 | AC7: =IF(OR(AB7="",多次统计数据!$B$9=""),"",IF(多次统计数据!$B$9<AB7,"低于上限","达到或超过上限")) -> 低于上限 | AE7: =IF(OR(X7="",C7="",C7<=0),"",X7/C7) -> 0.15605643 | AG7: 趋势波段 | AH7: 11～20个交易日 | AI7: 吸筹 | AJ7: =IF(OR(AG7="",AH7=""),"",IF(OR(AND(AG7="短期博反弹",OR(AH7="1～3个交易日",AH7="4～10个交易日")),AND(AG7="突破冲新高",OR(AH7="4～10个交易日",AH7="11～20个交易日")),AND(AG7="趋势波段",OR(AH7="11～20个交易日",AH7="21～60个交易日",AH7="60个交易日以上"))),"匹配","周期与交易预期不匹配，请重新确认")) -> 匹配 | AK7: =IF(A7="","",COUNTIFS(加仓管理!$A$2:$A$1001,A7,加仓管理!$G$2:$G$1001,">0")) -> 2 | AL7: =IF(A7="","",SUMIFS(加仓管理!$G$2:$G$1001,加仓管理!$A$2:$A$1001,A7)) -> 2000 | AM7: =IF(AK7=0,"",IFERROR(LOOKUP(2,1/((加仓管理!$A$2:$A$1001=A7)*(加仓管理!$G$2:$G$1001>0)),加仓管理!$D$2:$D$1001),"")) -> 15.71 | AN7: =IF(AK7=0,"",IFERROR(LOOKUP(2,1/((加仓管理!$A$2:$A$1001=A7)*(加仓管理!$G$2:$G$1001>0)),加仓管理!$E$2:$E$1001),"")) -> 14.02 | AO7: =IF(OR(A7="",H7="",H7<=0),"",(E7*H7+SUMIFS(加仓管理!$H$2:$H$1001,加仓管理!$A$2:$A$1001,A7))/AP7) -> 14.076667 | AP7: =IF(OR(A7="",H7="",H7<=0),"",H7+AL7) -> 3000 | AQ7: =IF(A7="","",IF(M7<>"",0,IF(OR(H7="",N7=""),"",MAX((E7*H7+SUMIFS(加仓管理!$H$2:$H$1001,加仓管理!$A$2:$A$1001,A7))-MAX(N7,AN7)*AP7,0)))) -> 0 | AR7: =IF(A7="","",IF(OR(E7="",H7=""),"违规：首次买入价格或股数缺失",IF(COUNTIFS(加仓管理!$A$2:$A$1001,A7,加仓管理!$R$2:$R$1001,"违规*")>0,"违规：请检查加仓管理表",IF(SUM($AQ$2:$AQ$201)>账户数据!$B$7,"预警：超过账户风险上限",IF(COUNTIFS(加仓管理!$A$2:$A$1001,A7,加仓管理!$N$2:$N$1001,">0",加仓管理!$G$2:$G$1001,"")>0,"提示：存在待执行加仓计划","通过"))))) -> 违规：请检查加仓管理表
A8: 7 | B8: 中国卫通 | C8: 62523 | D8: 0.02 | E8: 18.63 | F8: =IF(OR(C8="",D8="",E8="",N8="",C8<=0,D8<=0,E8<=N8),"",ROUNDDOWN((C8*D8)/(E8-N8)/100,0)*100) -> 1100 | G8: =IF(A8="","",IF(H8<>"","已开仓",IF(账户数据!$B$23="已锁仓","禁止开仓：连续亏损达到上限",IF(账户数据!$B$23="解锁信息不完整","禁止开仓：请完整填写解锁信息",IF(OR(F8="",E8="",N8="",E8<=N8,账户数据!$B$7=""),"",IF(OR(AG8="",AH8="",AI8=""),"禁止开仓：交易预期未填写完整",IF(账户数据!$B$9+F8*(E8-N8)>=账户数据!$B$7,"禁止开仓：风险额度不足",IF(AJ8="周期与交易预期不匹配，请重新确认",IF(账户数据!$B$23="接近锁仓","允许开仓（接近锁仓；周期需复核）","允许开仓（周期需复核）"),IF(账户数据!$B$23="接近锁仓","允许开仓（接近锁仓）","允许开仓"))))))))) -> 已开仓 | H8: 1100 | I8: 45041 | J8: 20 | K8: 17.74 | L8: =IF(AP8="","",AP8) -> 1100 | M8: 45044 | N8: 17.5 | U8: =IF(OR(AO8="",J8="",AO8<=0),"",(J8-AO8)/AO8) -> 0.073537305 | V8: =IF(OR(AO8="",N8="",AO8<=0),"",(AO8-N8)/AO8) -> 0.060654858 | W8: =IF(OR(U8="",V8="",V8<=0),"",U8/V8) -> 1.2123894 | X8: =IF(OR(K8="",L8="",AO8="",AP8=""),"",(K8-AO8)*L8-IF(O8="",0,O8)-IF(P8="",0,P8)) -> -979 | Y8: =IF(OR(X8="",AO8="",L8=""),"",IF(AO8*L8+IF(O8="",0,O8)<=0,"",X8/(AO8*L8+IF(O8="",0,O8)))) -> -0.04777241 | Z8: =IF(OR(AE8="",多次统计数据!$B$8=""),"",AE8-多次统计数据!$B$8) -> -0.12587091 | AA8: =IF(OR(I8="",M8="",M8<I8),"",M8-I8) -> 3 | AB8: =IF(OR(A8="",多次统计数据!$B$8="",多次统计数据!$B$6<=0,多次统计数据!$B$6>=1),"",1-POWER(1+多次统计数据!$B$8,-多次统计数据!$B$6/(1-多次统计数据!$B$6))) -> 0.081520133 | AC8: =IF(OR(AB8="",多次统计数据!$B$9=""),"",IF(多次统计数据!$B$9<AB8,"低于上限","达到或超过上限")) -> 低于上限 | AE8: =IF(OR(X8="",C8="",C8<=0),"",X8/C8) -> -0.015658238 | AG8: 短期博反弹 | AH8: 4～10个交易日 | AI8: 反弹 | AJ8: =IF(OR(AG8="",AH8=""),"",IF(OR(AND(AG8="短期博反弹",OR(AH8="1～3个交易日",AH8="4～10个交易日")),AND(AG8="突破冲新高",OR(AH8="4～10个交易日",AH8="11～20个交易日")),AND(AG8="趋势波段",OR(AH8="11～20个交易日",AH8="21～60个交易日",AH8="60个交易日以上"))),"匹配","周期与交易预期不匹配，请重新确认")) -> 匹配 | AK8: =IF(A8="","",COUNTIFS(加仓管理!$A$2:$A$1001,A8,加仓管理!$G$2:$G$1001,">0")) -> 0 | AL8: =IF(A8="","",SUMIFS(加仓管理!$G$2:$G$1001,加仓管理!$A$2:$A$1001,A8)) -> 0 | AM8: =IF(AK8=0,"",IFERROR(LOOKUP(2,1/((加仓管理!$A$2:$A$1001=A8)*(加仓管理!$G$2:$G$1001>0)),加仓管理!$D$2:$D$1001),"")) | AN8: =IF(AK8=0,"",IFERROR(LOOKUP(2,1/((加仓管理!$A$2:$A$1001=A8)*(加仓管理!$G$2:$G$1001>0)),加仓管理!$E$2:$E$1001),"")) | AO8: =IF(OR(A8="",H8="",H8<=0),"",(E8*H8+SUMIFS(加仓管理!$H$2:$H$1001,加仓管理!$A$2:$A$1001,A8))/AP8) -> 18.63 | AP8: =IF(OR(A8="",H8="",H8<=0),"",H8+AL8) -> 1100 | AQ8: =IF(A8="","",IF(M8<>"",0,IF(OR(H8="",N8=""),"",MAX((E8*H8+SUMIFS(加仓管理!$H$2:$H$1001,加仓管理!$A$2:$A$1001,A8))-MAX(N8,AN8)*AP8,0)))) -> 0 | AR8: =IF(A8="","",IF(OR(E8="",H8=""),"违规：首次买入价格或股数缺失",IF(COUNTIFS(加仓管理!$A$2:$A$1001,A8,加仓管理!$R$2:$R$1001,"违规*")>0,"违规：请检查加仓管理表",IF(SUM($AQ$2:$AQ$201)>账户数据!$B$7,"预警：超过账户风险上限",IF(COUNTIFS(加仓管理!$A$2:$A$1001,A8,加仓管理!$N$2:$N$1001,">0",加仓管理!$G$2:$G$1001,"")>0,"提示：存在待执行加仓计划","通过"))))) -> 通过
A9: 8 | B9: 中国卫通 | C9: 61544 | D9: 0.02 | E9: 20.42 | F9: =IF(OR(C9="",D9="",E9="",N9="",C9<=0,D9<=0,E9<=N9),"",ROUNDDOWN((C9*D9)/(E9-N9)/100,0)*100) -> 1300 | G9: =IF(A9="","",IF(H9<>"","已开仓",IF(账户数据!$B$23="已锁仓","禁止开仓：连续亏损达到上限",IF(账户数据!$B$23="解锁信息不完整","禁止开仓：请完整填写解锁信息",IF(OR(F9="",E9="",N9="",E9<=N9,账户数据!$B$7=""),"",IF(OR(AG9="",AH9="",AI9=""),"禁止开仓：交易预期未填写完整",IF(账户数据!$B$9+F9*(E9-N9)>=账户数据!$B$7,"禁止开仓：风险额度不足",IF(AJ9="周期与交易预期不匹配，请重新确认",IF(账户数据!$B$23="接近锁仓","允许开仓（接近锁仓；周期需复核）","允许开仓（周期需复核）"),IF(账户数据!$B$23="接近锁仓","允许开仓（接近锁仓）","允许开仓"))))))))) -> 已开仓 | H9: 1300 | I9: 45103 | J9: 24 | K9: 19.71 | L9: =IF(AP9="","",AP9) -> 1300 | M9: 45112 | N9: 19.5 | U9: =IF(OR(AO9="",J9="",AO9<=0),"",(J9-AO9)/AO9) -> 0.17531832 | V9: =IF(OR(AO9="",N9="",AO9<=0),"",(AO9-N9)/AO9) -> 0.045053869 | W9: =IF(OR(U9="",V9="",V9<=0),"",U9/V9) -> 3.8913043 | X9: =IF(OR(K9="",L9="",AO9="",AP9=""),"",(K9-AO9)*L9-IF(O9="",0,O9)-IF(P9="",0,P9)) -> -923 | Y9: =IF(OR(X9="",AO9="",L9=""),"",IF(AO9*L9+IF(O9="",0,O9)<=0,"",X9/(AO9*L9+IF(O9="",0,O9)))) -> -0.034769833 | Z9: =IF(OR(AE9="",多次统计数据!$B$8=""),"",AE9-多次统计数据!$B$8) -> -0.12521007 | AA9: =IF(OR(I9="",M9="",M9<I9),"",M9-I9) -> 9 | AB9: =IF(OR(A9="",多次统计数据!$B$8="",多次统计数据!$B$6<=0,多次统计数据!$B$6>=1),"",1-POWER(1+多次统计数据!$B$8,-多次统计数据!$B$6/(1-多次统计数据!$B$6))) -> 0.081520133 | AC9: =IF(OR(AB9="",多次统计数据!$B$9=""),"",IF(多次统计数据!$B$9<AB9,"低于上限","达到或超过上限")) -> 低于上限 | AE9: =IF(OR(X9="",C9="",C9<=0),"",X9/C9) -> -0.0149974 | AG9: 趋势波段 | AH9: 11～20个交易日 | AI9: 吸筹 | AJ9: =IF(OR(AG9="",AH9=""),"",IF(OR(AND(AG9="短期博反弹",OR(AH9="1～3个交易日",AH9="4～10个交易日")),AND(AG9="突破冲新高",OR(AH9="4～10个交易日",AH9="11～20个交易日")),AND(AG9="趋势波段",OR(AH9="11～20个交易日",AH9="21～60个交易日",AH9="60个交易日以上"))),"匹配","周期与交易预期不匹配，请重新确认")) -> 匹配 | AK9: =IF(A9="","",COUNTIFS(加仓管理!$A$2:$A$1001,A9,加仓管理!$G$2:$G$1001,">0")) -> 0 | AL9: =IF(A9="","",SUMIFS(加仓管理!$G$2:$G$1001,加仓管理!$A$2:$A$1001,A9)) -> 0 | AM9: =IF(AK9=0,"",IFERROR(LOOKUP(2,1/((加仓管理!$A$2:$A$1001=A9)*(加仓管理!$G$2:$G$1001>0)),加仓管理!$D$2:$D$1001),"")) | AN9: =IF(AK9=0,"",IFERROR(LOOKUP(2,1/((加仓管理!$A$2:$A$1001=A9)*(加仓管理!$G$2:$G$1001>0)),加仓管理!$E$2:$E$1001),"")) | AO9: =IF(OR(A9="",H9="",H9<=0),"",(E9*H9+SUMIFS(加仓管理!$H$2:$H$1001,加仓管理!$A$2:$A$1001,A9))/AP9) -> 20.42 | AP9: =IF(OR(A9="",H9="",H9<=0),"",H9+AL9) -> 1300 | AQ9: =IF(A9="","",IF(M9<>"",0,IF(OR(H9="",N9=""),"",MAX((E9*H9+SUMIFS(加仓管理!$H$2:$H$1001,加仓管理!$A$2:$A$1001,A9))-MAX(N9,AN9)*AP9,0)))) -> 0 | AR9: =IF(A9="","",IF(OR(E9="",H9=""),"违规：首次买入价格或股数缺失",IF(COUNTIFS(加仓管理!$A$2:$A$1001,A9,加仓管理!$R$2:$R$1001,"违规*")>0,"违规：请检查加仓管理表",IF(SUM($AQ$2:$AQ$201)>账户数据!$B$7,"预警：超过账户风险上限",IF(COUNTIFS(加仓管理!$A$2:$A$1001,A9,加仓管理!$N$2:$N$1001,">0",加仓管理!$G$2:$G$1001,"")>0,"提示：存在待执行加仓计划","通过"))))) -> 通过
A10: 9 | B10: 中国卫通 | C10: 60621 | D10: 0.02 | E10: 19.79 | F10: =IF(OR(C10="",D10="",E10="",N10="",C10<=0,D10<=0,E10<=N10),"",ROUNDDOWN((C10*D10)/(E10-N10)/100,0)*100) -> 900 | G10: =IF(A10="","",IF(H10<>"","已开仓",IF(账户数据!$B$23="已锁仓","禁止开仓：连续亏损达到上限",IF(账户数据!$B$23="解锁信息不完整","禁止开仓：请完整填写解锁信息",IF(OR(F10="",E10="",N10="",E10<=N10,账户数据!$B$7=""),"",IF(OR(AG10="",AH10="",AI10=""),"禁止开仓：交易预期未填写完整",IF(账户数据!$B$9+F10*(E10-N10)>=账户数据!$B$7,"禁止开仓：风险额度不足",IF(AJ10="周期与交易预期不匹配，请重新确认",IF(账户数据!$B$23="接近锁仓","允许开仓（接近锁仓；周期需复核）","允许开仓（周期需复核）"),IF(账户数据!$B$23="接近锁仓","允许开仓（接近锁仓）","允许开仓"))))))))) -> 已开仓 | H10: 900 | I10: 45181 | J10: 23 | K10: 16.91 | L10: =IF(AP10="","",AP10) -> 900 | M10: 45188 | N10: 18.5 | U10: =IF(OR(AO10="",J10="",AO10<=0),"",(J10-AO10)/AO10) -> 0.16220313 | V10: =IF(OR(AO10="",N10="",AO10<=0),"",(AO10-N10)/AO10) -> 0.065184437 | W10: =IF(OR(U10="",V10="",V10<=0),"",U10/V10) -> 2.4883721 | X10: =IF(OR(K10="",L10="",AO10="",AP10=""),"",(K10-AO10)*L10-IF(O10="",0,O10)-IF(P10="",0,P10)) -> -2592 | Y10: =IF(OR(X10="",AO10="",L10=""),"",IF(AO10*L10+IF(O10="",0,O10)<=0,"",X10/(AO10*L10+IF(O10="",0,O10)))) -> -0.14552804 | Z10: =IF(OR(AE10="",多次统计数据!$B$8=""),"",AE10-多次统计数据!$B$8) -> -0.15297013 | AA10: =IF(OR(I10="",M10="",M10<I10),"",M10-I10) -> 7 | AB10: =IF(OR(A10="",多次统计数据!$B$8="",多次统计数据!$B$6<=0,多次统计数据!$B$6>=1),"",1-POWER(1+多次统计数据!$B$8,-多次统计数据!$B$6/(1-多次统计数据!$B$6))) -> 0.081520133 | AC10: =IF(OR(AB10="",多次统计数据!$B$9=""),"",IF(多次统计数据!$B$9<AB10,"低于上限","达到或超过上限")) -> 低于上限 | AE10: =IF(OR(X10="",C10="",C10<=0),"",X10/C10) -> -0.04275746 | AG10: 趋势波段 | AH10: 11～20个交易日 | AI10: 吸筹 | AJ10: =IF(OR(AG10="",AH10=""),"",IF(OR(AND(AG10="短期博反弹",OR(AH10="1～3个交易日",AH10="4～10个交易日")),AND(AG10="突破冲新高",OR(AH10="4～10个交易日",AH10="11～20个交易日")),AND(AG10="趋势波段",OR(AH10="11～20个交易日",AH10="21～60个交易日",AH10="60个交易日以上"))),"匹配","周期与交易预期不匹配，请重新确认")) -> 匹配 | AK10: =IF(A10="","",COUNTIFS(加仓管理!$A$2:$A$1001,A10,加仓管理!$G$2:$G$1001,">0")) -> 0 | AL10: =IF(A10="","",SUMIFS(加仓管理!$G$2:$G$1001,加仓管理!$A$2:$A$1001,A10)) -> 0 | AM10: =IF(AK10=0,"",IFERROR(LOOKUP(2,1/((加仓管理!$A$2:$A$1001=A10)*(加仓管理!$G$2:$G$1001>0)),加仓管理!$D$2:$D$1001),"")) | AN10: =IF(AK10=0,"",IFERROR(LOOKUP(2,1/((加仓管理!$A$2:$A$1001=A10)*(加仓管理!$G$2:$G$1001>0)),加仓管理!$E$2:$E$1001),"")) | AO10: =IF(OR(A10="",H10="",H10<=0),"",(E10*H10+SUMIFS(加仓管理!$H$2:$H$1001,加仓管理!$A$2:$A$1001,A10))/AP10) -> 19.79 | AP10: =IF(OR(A10="",H10="",H10<=0),"",H10+AL10) -> 900 | AQ10: =IF(A10="","",IF(M10<>"",0,IF(OR(H10="",N10=""),"",MAX((E10*H10+SUMIFS(加仓管理!$H$2:$H$1001,加仓管理!$A$2:$A$1001,A10))-MAX(N10,AN10)*AP10,0)))) -> 0 | AR10: =IF(A10="","",IF(OR(E10="",H10=""),"违规：首次买入价格或股数缺失",IF(COUNTIFS(加仓管理!$A$2:$A$1001,A10,加仓管理!$R$2:$R$1001,"违规*")>0,"违规：请检查加仓管理表",IF(SUM($AQ$2:$AQ$201)>账户数据!$B$7,"预警：超过账户风险上限",IF(COUNTIFS(加仓管理!$A$2:$A$1001,A10,加仓管理!$N$2:$N$1001,">0",加仓管理!$G$2:$G$1001,"")>0,"提示：存在待执行加仓计划","通过"))))) -> 通过
A11: 10 | B11: 中国卫通 | C11: 58029 | D11: 0.02 | E11: 15.27 | F11: =IF(OR(C11="",D11="",E11="",N11="",C11<=0,D11<=0,E11<=N11),"",ROUNDDOWN((C11*D11)/(E11-N11)/100,0)*100) -> 1500 | G11: =IF(A11="","",IF(H11<>"","已开仓",IF(账户数据!$B$23="已锁仓","禁止开仓：连续亏损达到上限",IF(账户数据!$B$23="解锁信息不完整","禁止开仓：请完整填写解锁信息",IF(OR(F11="",E11="",N11="",E11<=N11,账户数据!$B$7=""),"",IF(OR(AG11="",AH11="",AI11=""),"禁止开仓：交易预期未填写完整",IF(账户数据!$B$9+F11*(E11-N11)>=账户数据!$B$7,"禁止开仓：风险额度不足",IF(AJ11="周期与交易预期不匹配，请重新确认",IF(账户数据!$B$23="接近锁仓","允许开仓（接近锁仓；周期需复核）","允许开仓（周期需复核）"),IF(账户数据!$B$23="接近锁仓","允许开仓（接近锁仓）","允许开仓"))))))))) -> 已开仓 | H11: 1500 | I11: 45502 | J11: 18 | K11: 16.33 | L11: =IF(AP11="","",AP11) -> 3500 | M11: 45512 | N11: 14.5 | U11: =IF(OR(AO11="",J11="",AO11<=0),"",(J11-AO11)/AO11) -> 0.094415009 | V11: =IF(OR(AO11="",N11="",AO11<=0),"",(AO11-N11)/AO11) -> 0.11838791 | W11: =IF(OR(U11="",V11="",V11<=0),"",U11/V11) -> 0.7975055 | X11: =IF(OR(K11="",L11="",AO11="",AP11=""),"",(K11-AO11)*L11-IF(O11="",0,O11)-IF(P11="",0,P11)) -> -410 | Y11: =IF(OR(X11="",AO11="",L11=""),"",IF(AO11*L11+IF(O11="",0,O11)<=0,"",X11/(AO11*L11+IF(O11="",0,O11)))) -> -0.0071223834 | Z11: =IF(OR(AE11="",多次统计数据!$B$8=""),"",AE11-多次统计数据!$B$8) -> -0.1172781 | AA11: =IF(OR(I11="",M11="",M11<I11),"",M11-I11) -> 10 | AB11: =IF(OR(A11="",多次统计数据!$B$8="",多次统计数据!$B$6<=0,多次统计数据!$B$6>=1),"",1-POWER(1+多次统计数据!$B$8,-多次统计数据!$B$6/(1-多次统计数据!$B$6))) -> 0.081520133 | AC11: =IF(OR(AB11="",多次统计数据!$B$9=""),"",IF(多次统计数据!$B$9<AB11,"低于上限","达到或超过上限")) -> 低于上限 | AE11: =IF(OR(X11="",C11="",C11<=0),"",X11/C11) -> -0.0070654328 | AG11: 趋势波段 | AH11: 11～20个交易日 | AI11: 吸筹 | AJ11: =IF(OR(AG11="",AH11=""),"",IF(OR(AND(AG11="短期博反弹",OR(AH11="1～3个交易日",AH11="4～10个交易日")),AND(AG11="突破冲新高",OR(AH11="4～10个交易日",AH11="11～20个交易日")),AND(AG11="趋势波段",OR(AH11="11～20个交易日",AH11="21～60个交易日",AH11="60个交易日以上"))),"匹配","周期与交易预期不匹配，请重新确认")) -> 匹配 | AK11: =IF(A11="","",COUNTIFS(加仓管理!$A$2:$A$1001,A11,加仓管理!$G$2:$G$1001,">0")) -> 2 | AL11: =IF(A11="","",SUMIFS(加仓管理!$G$2:$G$1001,加仓管理!$A$2:$A$1001,A11)) -> 2000 | AM11: =IF(AK11=0,"",IFERROR(LOOKUP(2,1/((加仓管理!$A$2:$A$1001=A11)*(加仓管理!$G$2:$G$1001>0)),加仓管理!$D$2:$D$1001),"")) -> 17.86 | AN11: =IF(AK11=0,"",IFERROR(LOOKUP(2,1/((加仓管理!$A$2:$A$1001=A11)*(加仓管理!$G$2:$G$1001>0)),加仓管理!$E$2:$E$1001),"")) -> 16.5 | AO11: =IF(OR(A11="",H11="",H11<=0),"",(E11*H11+SUMIFS(加仓管理!$H$2:$H$1001,加仓管理!$A$2:$A$1001,A11))/AP11) -> 16.447143 | AP11: =IF(OR(A11="",H11="",H11<=0),"",H11+AL11) -> 3500 | AQ11: =IF(A11="","",IF(M11<>"",0,IF(OR(H11="",N11=""),"",MAX((E11*H11+SUMIFS(加仓管理!$H$2:$H$1001,加仓管理!$A$2:$A$1001,A11))-MAX(N11,AN11)*AP11,0)))) -> 0 | AR11: =IF(A11="","",IF(OR(E11="",H11=""),"违规：首次买入价格或股数缺失",IF(COUNTIFS(加仓管理!$A$2:$A$1001,A11,加仓管理!$R$2:$R$1001,"违规*")>0,"违规：请检查加仓管理表",IF(SUM($AQ$2:$AQ$201)>账户数据!$B$7,"预警：超过账户风险上限",IF(COUNTIFS(加仓管理!$A$2:$A$1001,A11,加仓管理!$N$2:$N$1001,">0",加仓管理!$G$2:$G$1001,"")>0,"提示：存在待执行加仓计划","通过"))))) -> 通过
A12: 11 | B12: 中国卫通 | C12: 57619 | D12: 0.02 | E12: 20.34 | F12: =IF(OR(C12="",D12="",E12="",N12="",C12<=0,D12<=0,E12<=N12),"",ROUNDDOWN((C12*D12)/(E12-N12)/100,0)*100) -> 1300 | G12: =IF(A12="","",IF(H12<>"","已开仓",IF(账户数据!$B$23="已锁仓","禁止开仓：连续亏损达到上限",IF(账户数据!$B$23="解锁信息不完整","禁止开仓：请完整填写解锁信息",IF(OR(F12="",E12="",N12="",E12<=N12,账户数据!$B$7=""),"",IF(OR(AG12="",AH12="",AI12=""),"禁止开仓：交易预期未填写完整",IF(账户数据!$B$9+F12*(E12-N12)>=账户数据!$B$7,"禁止开仓：风险额度不足",IF(AJ12="周期与交易预期不匹配，请重新确认",IF(账户数据!$B$23="接近锁仓","允许开仓（接近锁仓；周期需复核）","允许开仓（周期需复核）"),IF(账户数据!$B$23="接近锁仓","允许开仓（接近锁仓）","允许开仓"))))))))) -> 已开仓 | H12: 1300 | I12: 45603 | J12: 24 | K12: 26.66 | L12: =IF(AP12="","",AP12) -> 1800 | M12: 45608 | N12: 19.5 | U12: =IF(OR(AO12="",J12="",AO12<=0),"",(J12-AO12)/AO12) -> 0.14795918 | V12: =IF(OR(AO12="",N12="",AO12<=0),"",(AO12-N12)/AO12) -> 0.067283163 | W12: =IF(OR(U12="",V12="",V12<=0),"",U12/V12) -> 2.1990521 | X12: =IF(OR(K12="",L12="",AO12="",AP12=""),"",(K12-AO12)*L12-IF(O12="",0,O12)-IF(P12="",0,P12)) -> 10356 | Y12: =IF(OR(X12="",AO12="",L12=""),"",IF(AO12*L12+IF(O12="",0,O12)<=0,"",X12/(AO12*L12+IF(O12="",0,O12)))) -> 0.27519133 | Z12: =IF(OR(AE12="",多次统计数据!$B$8=""),"",AE12-多次统计数据!$B$8) -> 0.069519711 | AA12: =IF(OR(I12="",M12="",M12<I12),"",M12-I12) -> 5 | AB12: =IF(OR(A12="",多次统计数据!$B$8="",多次统计数据!$B$6<=0,多次统计数据!$B$6>=1),"",1-POWER(1+多次统计数据!$B$8,-多次统计数据!$B$6/(1-多次统计数据!$B$6))) -> 0.081520133 | AC12: =IF(OR(AB12="",多次统计数据!$B$9=""),"",IF(多次统计数据!$B$9<AB12,"低于上限","达到或超过上限")) -> 低于上限 | AE12: =IF(OR(X12="",C12="",C12<=0),"",X12/C12) -> 0.17973238 | AG12: 突破冲新高 | AH12: 4～10个交易日 | AI12: 新高 | AJ12: =IF(OR(AG12="",AH12=""),"",IF(OR(AND(AG12="短期博反弹",OR(AH12="1～3个交易日",AH12="4～10个交易日")),AND(AG12="突破冲新高",OR(AH12="4～10个交易日",AH12="11～20个交易日")),AND(AG12="趋势波段",OR(AH12="11～20个交易日",AH12="21～60个交易日",AH12="60个交易日以上"))),"匹配","周期与交易预期不匹配，请重新确认")) -> 匹配 | AK12: =IF(A12="","",COUNTIFS(加仓管理!$A$2:$A$1001,A12,加仓管理!$G$2:$G$1001,">0")) -> 1 | AL12: =IF(A12="","",SUMIFS(加仓管理!$G$2:$G$1001,加仓管理!$A$2:$A$1001,A12)) -> 500 | AM12: =IF(AK12=0,"",IFERROR(LOOKUP(2,1/((加仓管理!$A$2:$A$1001=A12)*(加仓管理!$G$2:$G$1001>0)),加仓管理!$D$2:$D$1001),"")) -> 22.38 | AN12: =IF(AK12=0,"",IFERROR(LOOKUP(2,1/((加仓管理!$A$2:$A$1001=A12)*(加仓管理!$G$2:$G$1001>0)),加仓管理!$E$2:$E$1001),"")) -> 20 | AO12: =IF(OR(A12="",H12="",H12<=0),"",(E12*H12+SUMIFS(加仓管理!$H$2:$H$1001,加仓管理!$A$2:$A$1001,A12))/AP12) -> 20.906667 | AP12: =IF(OR(A12="",H12="",H12<=0),"",H12+AL12) -> 1800 | AQ12: =IF(A12="","",IF(M12<>"",0,IF(OR(H12="",N12=""),"",MAX((E12*H12+SUMIFS(加仓管理!$H$2:$H$1001,加仓管理!$A$2:$A$1001,A12))-MAX(N12,AN12)*AP12,0)))) -> 0 | AR12: =IF(A12="","",IF(OR(E12="",H12=""),"违规：首次买入价格或股数缺失",IF(COUNTIFS(加仓管理!$A$2:$A$1001,A12,加仓管理!$R$2:$R$1001,"违规*")>0,"违规：请检查加仓管理表",IF(SUM($AQ$2:$AQ$201)>账户数据!$B$7,"预警：超过账户风险上限",IF(COUNTIFS(加仓管理!$A$2:$A$1001,A12,加仓管理!$N$2:$N$1001,">0",加仓管理!$G$2:$G$1001,"")>0,"提示：存在待执行加仓计划","通过"))))) -> 违规：请检查加仓管理表
A13: 12 | B13: 中国卫通 | C13: 67975 | D13: 0.02 | E13: 20.46 | F13: =IF(OR(C13="",D13="",E13="",N13="",C13<=0,D13<=0,E13<=N13),"",ROUNDDOWN((C13*D13)/(E13-N13)/100,0)*100) -> 1400 | G13: =IF(A13="","",IF(H13<>"","已开仓",IF(账户数据!$B$23="已锁仓","禁止开仓：连续亏损达到上限",IF(账户数据!$B$23="解锁信息不完整","禁止开仓：请完整填写解锁信息",IF(OR(F13="",E13="",N13="",E13<=N13,账户数据!$B$7=""),"",IF(OR(AG13="",AH13="",AI13=""),"禁止开仓：交易预期未填写完整",IF(账户数据!$B$9+F13*(E13-N13)>=账户数据!$B$7,"禁止开仓：风险额度不足",IF(AJ13="周期与交易预期不匹配，请重新确认",IF(账户数据!$B$23="接近锁仓","允许开仓（接近锁仓；周期需复核）","允许开仓（周期需复核）"),IF(账户数据!$B$23="接近锁仓","允许开仓（接近锁仓）","允许开仓"))))))))) -> 已开仓 | H13: 1400 | I13: 45734 | J13: 24 | K13: 22.03 | L13: =IF(AP13="","",AP13) -> 3000 | M13: 45910 | N13: 19.5 | U13: =IF(OR(AO13="",J13="",AO13<=0),"",(J13-AO13)/AO13) -> 0.095790339 | V13: =IF(OR(AO13="",N13="",AO13<=0),"",(AO13-N13)/AO13) -> 0.10967035 | W13: =IF(OR(U13="",V13="",V13<=0),"",U13/V13) -> 0.8734388 | X13: =IF(OR(K13="",L13="",AO13="",AP13=""),"",(K13-AO13)*L13-IF(O13="",0,O13)-IF(P13="",0,P13)) -> 384 | Y13: =IF(OR(X13="",AO13="",L13=""),"",IF(AO13*L13+IF(O13="",0,O13)<=0,"",X13/(AO13*L13+IF(O13="",0,O13)))) -> 0.0058442151 | Z13: =IF(OR(AE13="",多次统计数据!$B$8=""),"",AE13-多次统计数据!$B$8) -> -0.10456353 | AA13: =IF(OR(I13="",M13="",M13<I13),"",M13-I13) -> 176 | AB13: =IF(OR(A13="",多次统计数据!$B$8="",多次统计数据!$B$6<=0,多次统计数据!$B$6>=1),"",1-POWER(1+多次统计数据!$B$8,-多次统计数据!$B$6/(1-多次统计数据!$B$6))) -> 0.081520133 | AC13: =IF(OR(AB13="",多次统计数据!$B$9=""),"",IF(多次统计数据!$B$9<AB13,"低于上限","达到或超过上限")) -> 低于上限 | AE13: =IF(OR(X13="",C13="",C13<=0),"",X13/C13) -> 0.0056491357 | AG13: 趋势波段 | AH13: 11～20个交易日 | AI13: 吸筹 | AJ13: =IF(OR(AG13="",AH13=""),"",IF(OR(AND(AG13="短期博反弹",OR(AH13="1～3个交易日",AH13="4～10个交易日")),AND(AG13="突破冲新高",OR(AH13="4～10个交易日",AH13="11～20个交易日")),AND(AG13="趋势波段",OR(AH13="11～20个交易日",AH13="21～60个交易日",AH13="60个交易日以上"))),"匹配","周期与交易预期不匹配，请重新确认")) -> 匹配 | AK13: =IF(A13="","",COUNTIFS(加仓管理!$A$2:$A$1001,A13,加仓管理!$G$2:$G$1001,">0")) -> 2 | AL13: =IF(A13="","",SUMIFS(加仓管理!$G$2:$G$1001,加仓管理!$A$2:$A$1001,A13)) -> 1600 | AM13: =IF(AK13=0,"",IFERROR(LOOKUP(2,1/((加仓管理!$A$2:$A$1001=A13)*(加仓管理!$G$2:$G$1001>0)),加仓管理!$D$2:$D$1001),"")) -> 25.27 | AN13: =IF(AK13=0,"",IFERROR(LOOKUP(2,1/((加仓管理!$A$2:$A$1001=A13)*(加仓管理!$G$2:$G$1001>0)),加仓管理!$E$2:$E$1001),"")) -> 23 | AO13: =IF(OR(A13="",H13="",H13<=0),"",(E13*H13+SUMIFS(加仓管理!$H$2:$H$1001,加仓管理!$A$2:$A$1001,A13))/AP13) -> 21.902 | AP13: =IF(OR(A13="",H13="",H13<=0),"",H13+AL13) -> 3000 | AQ13: =IF(A13="","",IF(M13<>"",0,IF(OR(H13="",N13=""),"",MAX((E13*H13+SUMIFS(加仓管理!$H$2:$H$1001,加仓管理!$A$2:$A$1001,A13))-MAX(N13,AN13)*AP13,0)))) -> 0 | AR13: =IF(A13="","",IF(OR(E13="",H13=""),"违规：首次买入价格或股数缺失",IF(COUNTIFS(加仓管理!$A$2:$A$1001,A13,加仓管理!$R$2:$R$1001,"违规*")>0,"违规：请检查加仓管理表",IF(SUM($AQ$2:$AQ$201)>账户数据!$B$7,"预警：超过账户风险上限",IF(COUNTIFS(加仓管理!$A$2:$A$1001,A13,加仓管理!$N$2:$N$1001,">0",加仓管理!$G$2:$G$1001,"")>0,"提示：存在待执行加仓计划","通过"))))) -> 违规：请检查加仓管理表
... A136: 135 | B136: 亿纬锂能 | C136: 1235288 | D136: 0.02 | E136: 35.39 | F136: =IF(OR(C136="",D136="",E136="",N136="",C136<=0,D136<=0,E136<=N136),"",ROUNDDOWN((C136*D136)/(E136-N136)/100,0)*100) -> 13000 | G136: =IF(A136="","",IF(H136<>"","已开仓",IF(账户数据!$B$23="已锁仓","禁止开仓：连续亏损达到上限",IF(账户数据!$B$23="解锁信息不完整","禁止开仓：请完整填写解锁信息",IF(OR(F136="",E136="",N136="",E136<=N136,账户数据!$B$7=""),"",IF(OR(AG136="",AH136="",AI136=""),"禁止开仓：交易预期未填写完整",IF(账户数据!$B$9+F136*(E136-N136)>=账户数据!$B$7,"禁止开仓：风险额度不足",IF(AJ136="周期与交易预期不匹配，请重新确认",IF(账户数据!$B$23="接近锁仓","允许开仓（接近锁仓；周期需复核）","允许开仓（周期需复核）"),IF(账户数据!$B$23="接近锁仓","允许开仓（接近锁仓）","允许开仓"))))))))) -> 已开仓 | H136: 13000 | I136: 45512 | J136: 40 | K136: 32.99 | L136: =IF(AP136="","",AP136) -> 13000 | M136: 45526 | N136: 33.5 | U136: =IF(OR(AO136="",J136="",AO136<=0),"",(J136-AO136)/AO136) -> 0.13026279 | V136: =IF(OR(AO136="",N136="",AO136<=0),"",(AO136-N136)/AO136) -> 0.053404917 | W136: =IF(OR(U136="",V136="",V136<=0),"",U136/V136) -> 2.4391534 | X136: =IF(OR(K136="",L136="",AO136="",AP136=""),"",(K136-AO136)*L136-IF(O136="",0,O136)-IF(P136="",0,P136)) -> -31200 | Y136: =IF(OR(X136="",AO136="",L136=""),"",IF(AO136*L136+IF(O136="",0,O136)<=0,"",X136/(AO136*L136+IF(O136="",0,O136)))) -> -0.067815767 | Z136: =IF(OR(AE136="",多次统计数据!$B$8=""),"",AE136-多次统计数据!$B$8) -> -0.13546994 | AA136: =IF(OR(I136="",M136="",M136<I136),"",M136-I136) -> 14 | AB136: =IF(OR(A136="",多次统计数据!$B$8="",多次统计数据!$B$6<=0,多次统计数据!$B$6>=1),"",1-POWER(1+多次统计数据!$B$8,-多次统计数据!$B$6/(1-多次统计数据!$B$6))) -> 0.081520133 | AC136: =IF(OR(AB136="",多次统计数据!$B$9=""),"",IF(多次统计数据!$B$9<AB136,"低于上限","达到或超过上限")) -> 低于上限 | AE136: =IF(OR(X136="",C136="",C136<=0),"",X136/C136) -> -0.025257268 | AG136: 趋势波段 | AH136: 11～20个交易日 | AI136: 吸筹 | AJ136: =IF(OR(AG136="",AH136=""),"",IF(OR(AND(AG136="短期博反弹",OR(AH136="1～3个交易日",AH136="4～10个交易日")),AND(AG136="突破冲新高",OR(AH136="4～10个交易日",AH136="11～20个交易日")),AND(AG136="趋势波段",OR(AH136="11～20个交易日",AH136="21～60个交易日",AH136="60个交易日以上"))),"匹配","周期与交易预期不匹配，请重新确认")) -> 匹配 | AK136: =IF(A136="","",COUNTIFS(加仓管理!$A$2:$A$1001,A136,加仓管理!$G$2:$G$1001,">0")) -> 0 | AL136: =IF(A136="","",SUMIFS(加仓管理!$G$2:$G$1001,加仓管理!$A$2:$A$1001,A136)) -> 0 | AM136: =IF(AK136=0,"",IFERROR(LOOKUP(2,1/((加仓管理!$A$2:$A$1001=A136)*(加仓管理!$G$2:$G$1001>0)),加仓管理!$D$2:$D$1001),"")) | AN136: =IF(AK136=0,"",IFERROR(LOOKUP(2,1/((加仓管理!$A$2:$A$1001=A136)*(加仓管理!$G$2:$G$1001>0)),加仓管理!$E$2:$E$1001),"")) | AO136: =IF(OR(A136="",H136="",H136<=0),"",(E136*H136+SUMIFS(加仓管理!$H$2:$H$1001,加仓管理!$A$2:$A$1001,A136))/AP136) -> 35.39 | AP136: =IF(OR(A136="",H136="",H136<=0),"",H136+AL136) -> 13000 | AQ136: =IF(A136="","",IF(M136<>"",0,IF(OR(H136="",N136=""),"",MAX((E136*H136+SUMIFS(加仓管理!$H$2:$H$1001,加仓管理!$A$2:$A$1001,A136))-MAX(N136,AN136)*AP136,0)))) -> 0 | AR136: =IF(A136="","",IF(OR(E136="",H136=""),"违规：首次买入价格或股数缺失",IF(COUNTIFS(加仓管理!$A$2:$A$1001,A136,加仓管理!$R$2:$R$1001,"违规*")>0,"违规：请检查加仓管理表",IF(SUM($AQ$2:$AQ$201)>账户数据!$B$7,"预警：超过账户风险上限",IF(COUNTIFS(加仓管理!$A$2:$A$1001,A136,加仓管理!$N$2:$N$1001,">0",加仓管理!$G$2:$G$1001,"")>0,"提示：存在待执行加仓计划","通过"))))) -> 通过
A137: 136 | B137: 亿纬锂能 | C137: 1204088 | D137: 0.02 | E137: 31.25 | F137: =IF(OR(C137="",D137="",E137="",N137="",C137<=0,D137<=0,E137<=N137),"",ROUNDDOWN((C137*D137)/(E137-N137)/100,0)*100) -> 10700 | G137: =IF(A137="","",IF(H137<>"","已开仓",IF(账户数据!$B$23="已锁仓","禁止开仓：连续亏损达到上限",IF(账户数据!$B$23="解锁信息不完整","禁止开仓：请完整填写解锁信息",IF(OR(F137="",E137="",N137="",E137<=N137,账户数据!$B$7=""),"",IF(OR(AG137="",AH137="",AI137=""),"禁止开仓：交易预期未填写完整",IF(账户数据!$B$9+F137*(E137-N137)>=账户数据!$B$7,"禁止开仓：风险额度不足",IF(AJ137="周期与交易预期不匹配，请重新确认",IF(账户数据!$B$23="接近锁仓","允许开仓（接近锁仓；周期需复核）","允许开仓（周期需复核）"),IF(账户数据!$B$23="接近锁仓","允许开仓（接近锁仓）","允许开仓"))))))))) -> 已开仓 | H137: 10000 | I137: 45527 | J137: 35 | K137: 31.35 | L137: =IF(AP137="","",AP137) -> 10000 | N137: 29 | U137: =IF(OR(AO137="",J137="",AO137<=0),"",(J137-AO137)/AO137) -> 0.12 | V137: =IF(OR(AO137="",N137="",AO137<=0),"",(AO137-N137)/AO137) -> 0.072 | W137: =IF(OR(U137="",V137="",V137<=0),"",U137/V137) -> 1.6666667 | X137: =IF(OR(K137="",L137="",AO137="",AP137=""),"",(K137-AO137)*L137-IF(O137="",0,O137)-IF(P137="",0,P137)) -> 1000 | Y137: =IF(OR(X137="",AO137="",L137=""),"",IF(AO137*L137+IF(O137="",0,O137)<=0,"",X137/(AO137*L137+IF(O137="",0,O137)))) -> 0.0032 | Z137: =IF(OR(AE137="",多次统计数据!$B$8=""),"",AE137-多次统计数据!$B$8) -> -0.10938216 | AA137: =IF(OR(I137="",M137="",M137<I137),"",M137-I137) | AB137: =IF(OR(A137="",多次统计数据!$B$8="",多次统计数据!$B$6<=0,多次统计数据!$B$6>=1),"",1-POWER(1+多次统计数据!$B$8,-多次统计数据!$B$6/(1-多次统计数据!$B$6))) -> 0.081520133 | AC137: =IF(OR(AB137="",多次统计数据!$B$9=""),"",IF(多次统计数据!$B$9<AB137,"低于上限","达到或超过上限")) -> 低于上限 | AE137: =IF(OR(X137="",C137="",C137<=0),"",X137/C137) -> 0.00083050408 | AG137: 短期博反弹 | AH137: 4～10个交易日 | AI137: 反弹 | AJ137: =IF(OR(AG137="",AH137=""),"",IF(OR(AND(AG137="短期博反弹",OR(AH137="1～3个交易日",AH137="4～10个交易日")),AND(AG137="突破冲新高",OR(AH137="4～10个交易日",AH137="11～20个交易日")),AND(AG137="趋势波段",OR(AH137="11～20个交易日",AH137="21～60个交易日",AH137="60个交易日以上"))),"匹配","周期与交易预期不匹配，请重新确认")) -> 匹配 | AK137: =IF(A137="","",COUNTIFS(加仓管理!$A$2:$A$1001,A137,加仓管理!$G$2:$G$1001,">0")) -> 0 | AL137: =IF(A137="","",SUMIFS(加仓管理!$G$2:$G$1001,加仓管理!$A$2:$A$1001,A137)) -> 0 | AM137: =IF(AK137=0,"",IFERROR(LOOKUP(2,1/((加仓管理!$A$2:$A$1001=A137)*(加仓管理!$G$2:$G$1001>0)),加仓管理!$D$2:$D$1001),"")) | AN137: =IF(AK137=0,"",IFERROR(LOOKUP(2,1/((加仓管理!$A$2:$A$1001=A137)*(加仓管理!$G$2:$G$1001>0)),加仓管理!$E$2:$E$1001),"")) | AO137: =IF(OR(A137="",H137="",H137<=0),"",(E137*H137+SUMIFS(加仓管理!$H$2:$H$1001,加仓管理!$A$2:$A$1001,A137))/AP137) -> 31.25 | AP137: =IF(OR(A137="",H137="",H137<=0),"",H137+AL137) -> 10000 | AQ137: =IF(A137="","",IF(M137<>"",0,IF(OR(H137="",N137=""),"",MAX((E137*H137+SUMIFS(加仓管理!$H$2:$H$1001,加仓管理!$A$2:$A$1001,A137))-MAX(N137,AN137)*AP137,0)))) -> 22500 | AR137: =IF(A137="","",IF(OR(E137="",H137=""),"违规：首次买入价格或股数缺失",IF(COUNTIFS(加仓管理!$A$2:$A$1001,A137,加仓管理!$R$2:$R$1001,"违规*")>0,"违规：请检查加仓管理表",IF(SUM($AQ$2:$AQ$201)>账户数据!$B$7,"预警：超过账户风险上限",IF(COUNTIFS(加仓管理!$A$2:$A$1001,A137,加仓管理!$N$2:$N$1001,">0",加仓管理!$G$2:$G$1001,"")>0,"提示：存在待执行加仓计划","通过"))))) -> 通过
F138: =IF(OR(C138="",D138="",E138="",N138="",C138<=0,D138<=0,E138<=N138),"",ROUNDDOWN((C138*D138)/(E138-N138)/100,0)*100) | G138: =IF(A138="","",IF(H138<>"","已开仓",IF(账户数据!$B$23="已锁仓","禁止开仓：连续亏损达到上限",IF(账户数据!$B$23="解锁信息不完整","禁止开仓：请完整填写解锁信息",IF(OR(F138="",E138="",N138="",E138<=N138,账户数据!$B$7=""),"",IF(OR(AG138="",AH138="",AI138=""),"禁止开仓：交易预期未填写完整",IF(账户数据!$B$9+F138*(E138-N138)>=账户数据!$B$7,"禁止开仓：风险额度不足",IF(AJ138="周期与交易预期不匹配，请重新确认",IF(账户数据!$B$23="接近锁仓","允许开仓（接近锁仓；周期需复核）","允许开仓（周期需复核）"),IF(账户数据!$B$23="接近锁仓","允许开仓（接近锁仓）","允许开仓"))))))))) | L138: =IF(AP138="","",AP138) | U138: =IF(OR(AO138="",J138="",AO138<=0),"",(J138-AO138)/AO138) | V138: =IF(OR(AO138="",N138="",AO138<=0),"",(AO138-N138)/AO138) | W138: =IF(OR(U138="",V138="",V138<=0),"",U138/V138) | X138: =IF(OR(K138="",L138="",AO138="",AP138=""),"",(K138-AO138)*L138-IF(O138="",0,O138)-IF(P138="",0,P138)) | Y138: =IF(OR(X138="",AO138="",L138=""),"",IF(AO138*L138+IF(O138="",0,O138)<=0,"",X138/(AO138*L138+IF(O138="",0,O138)))) | Z138: =IF(OR(AE138="",多次统计数据!$B$8=""),"",AE138-多次统计数据!$B$8) | AA138: =IF(OR(I138="",M138="",M138<I138),"",M138-I138) | AB138: =IF(OR(A138="",多次统计数据!$B$8="",多次统计数据!$B$6<=0,多次统计数据!$B$6>=1),"",1-POWER(1+多次统计数据!$B$8,-多次统计数据!$B$6/(1-多次统计数据!$B$6))) | AC138: =IF(OR(AB138="",多次统计数据!$B$9=""),"",IF(多次统计数据!$B$9<AB138,"低于上限","达到或超过上限")) | AE138: =IF(OR(X138="",C138="",C138<=0),"",X138/C138) | AJ138: =IF(OR(AG138="",AH138=""),"",IF(OR(AND(AG138="短期博反弹",OR(AH138="1～3个交易日",AH138="4～10个交易日")),AND(AG138="突破冲新高",OR(AH138="4～10个交易日",AH138="11～20个交易日")),AND(AG138="趋势波段",OR(AH138="11～20个交易日",AH138="21～60个交易日",AH138="60个交易日以上"))),"匹配","周期与交易预期不匹配，请重新确认")) | AK138: =IF(A138="","",COUNTIFS(加仓管理!$A$2:$A$1001,A138,加仓管理!$G$2:$G$1001,">0")) | AL138: =IF(A138="","",SUMIFS(加仓管理!$G$2:$G$1001,加仓管理!$A$2:$A$1001,A138)) | AM138: =IF(AK138=0,"",IFERROR(LOOKUP(2,1/((加仓管理!$A$2:$A$1001=A138)*(加仓管理!$G$2:$G$1001>0)),加仓管理!$D$2:$D$1001),"")) | AN138: =IF(AK138=0,"",IFERROR(LOOKUP(2,1/((加仓管理!$A$2:$A$1001=A138)*(加仓管理!$G$2:$G$1001>0)),加仓管理!$E$2:$E$1001),"")) | AO138: =IF(OR(A138="",H138="",H138<=0),"",(E138*H138+SUMIFS(加仓管理!$H$2:$H$1001,加仓管理!$A$2:$A$1001,A138))/AP138) | AP138: =IF(OR(A138="",H138="",H138<=0),"",H138+AL138) | AQ138: =IF(A138="","",IF(M138<>"",0,IF(OR(H138="",N138=""),"",MAX((E138*H138+SUMIFS(加仓管理!$H$2:$H$1001,加仓管理!$A$2:$A$1001,A138))-MAX(N138,AN138)*AP138,0)))) | AR138: =IF(A138="","",IF(OR(E138="",H138=""),"违规：首次买入价格或股数缺失",IF(COUNTIFS(加仓管理!$A$2:$A$1001,A138,加仓管理!$R$2:$R$1001,"违规*")>0,"违规：请检查加仓管理表",IF(SUM($AQ$2:$AQ$201)>账户数据!$B$7,"预警：超过账户风险上限",IF(COUNTIFS(加仓管理!$A$2:$A$1001,A138,加仓管理!$N$2:$N$1001,">0",加仓管理!$G$2:$G$1001,"")>0,"提示：存在待执行加仓计划","通过")))))
F139: =IF(OR(C139="",D139="",E139="",N139="",C139<=0,D139<=0,E139<=N139),"",ROUNDDOWN((C139*D139)/(E139-N139)/100,0)*100) | G139: =IF(A139="","",IF(H139<>"","已开仓",IF(账户数据!$B$23="已锁仓","禁止开仓：连续亏损达到上限",IF(账户数据!$B$23="解锁信息不完整","禁止开仓：请完整填写解锁信息",IF(OR(F139="",E139="",N139="",E139<=N139,账户数据!$B$7=""),"",IF(OR(AG139="",AH139="",AI139=""),"禁止开仓：交易预期未填写完整",IF(账户数据!$B$9+F139*(E139-N139)>=账户数据!$B$7,"禁止开仓：风险额度不足",IF(AJ139="周期与交易预期不匹配，请重新确认",IF(账户数据!$B$23="接近锁仓","允许开仓（接近锁仓；周期需复核）","允许开仓（周期需复核）"),IF(账户数据!$B$23="接近锁仓","允许开仓（接近锁仓）","允许开仓"))))))))) | L139: =IF(AP139="","",AP139) | U139: =IF(OR(AO139="",J139="",AO139<=0),"",(J139-AO139)/AO139) | V139: =IF(OR(AO139="",N139="",AO139<=0),"",(AO139-N139)/AO139) | W139: =IF(OR(U139="",V139="",V139<=0),"",U139/V139) | X139: =IF(OR(K139="",L139="",AO139="",AP139=""),"",(K139-AO139)*L139-IF(O139="",0,O139)-IF(P139="",0,P139)) | Y139: =IF(OR(X139="",AO139="",L139=""),"",IF(AO139*L139+IF(O139="",0,O139)<=0,"",X139/(AO139*L139+IF(O139="",0,O139)))) | Z139: =IF(OR(AE139="",多次统计数据!$B$8=""),"",AE139-多次统计数据!$B$8) | AA139: =IF(OR(I139="",M139="",M139<I139),"",M139-I139) | AB139: =IF(OR(A139="",多次统计数据!$B$8="",多次统计数据!$B$6<=0,多次统计数据!$B$6>=1),"",1-POWER(1+多次统计数据!$B$8,-多次统计数据!$B$6/(1-多次统计数据!$B$6))) | AC139: =IF(OR(AB139="",多次统计数据!$B$9=""),"",IF(多次统计数据!$B$9<AB139,"低于上限","达到或超过上限")) | AE139: =IF(OR(X139="",C139="",C139<=0),"",X139/C139) | AJ139: =IF(OR(AG139="",AH139=""),"",IF(OR(AND(AG139="短期博反弹",OR(AH139="1～3个交易日",AH139="4～10个交易日")),AND(AG139="突破冲新高",OR(AH139="4～10个交易日",AH139="11～20个交易日")),AND(AG139="趋势波段",OR(AH139="11～20个交易日",AH139="21～60个交易日",AH139="60个交易日以上"))),"匹配","周期与交易预期不匹配，请重新确认")) | AK139: =IF(A139="","",COUNTIFS(加仓管理!$A$2:$A$1001,A139,加仓管理!$G$2:$G$1001,">0")) | AL139: =IF(A139="","",SUMIFS(加仓管理!$G$2:$G$1001,加仓管理!$A$2:$A$1001,A139)) | AM139: =IF(AK139=0,"",IFERROR(LOOKUP(2,1/((加仓管理!$A$2:$A$1001=A139)*(加仓管理!$G$2:$G$1001>0)),加仓管理!$D$2:$D$1001),"")) | AN139: =IF(AK139=0,"",IFERROR(LOOKUP(2,1/((加仓管理!$A$2:$A$1001=A139)*(加仓管理!$G$2:$G$1001>0)),加仓管理!$E$2:$E$1001),"")) | AO139: =IF(OR(A139="",H139="",H139<=0),"",(E139*H139+SUMIFS(加仓管理!$H$2:$H$1001,加仓管理!$A$2:$A$1001,A139))/AP139) | AP139: =IF(OR(A139="",H139="",H139<=0),"",H139+AL139) | AQ139: =IF(A139="","",IF(M139<>"",0,IF(OR(H139="",N139=""),"",MAX((E139*H139+SUMIFS(加仓管理!$H$2:$H$1001,加仓管理!$A$2:$A$1001,A139))-MAX(N139,AN139)*AP139,0)))) | AR139: =IF(A139="","",IF(OR(E139="",H139=""),"违规：首次买入价格或股数缺失",IF(COUNTIFS(加仓管理!$A$2:$A$1001,A139,加仓管理!$R$2:$R$1001,"违规*")>0,"违规：请检查加仓管理表",IF(SUM($AQ$2:$AQ$201)>账户数据!$B$7,"预警：超过账户风险上限",IF(COUNTIFS(加仓管理!$A$2:$A$1001,A139,加仓管理!$N$2:$N$1001,">0",加仓管理!$G$2:$G$1001,"")>0,"提示：存在待执行加仓计划","通过")))))
F140: =IF(OR(C140="",D140="",E140="",N140="",C140<=0,D140<=0,E140<=N140),"",ROUNDDOWN((C140*D140)/(E140-N140)/100,0)*100) | G140: =IF(A140="","",IF(H140<>"","已开仓",IF(账户数据!$B$23="已锁仓","禁止开仓：连续亏损达到上限",IF(账户数据!$B$23="解锁信息不完整","禁止开仓：请完整填写解锁信息",IF(OR(F140="",E140="",N140="",E140<=N140,账户数据!$B$7=""),"",IF(OR(AG140="",AH140="",AI140=""),"禁止开仓：交易预期未填写完整",IF(账户数据!$B$9+F140*(E140-N140)>=账户数据!$B$7,"禁止开仓：风险额度不足",IF(AJ140="周期与交易预期不匹配，请重新确认",IF(账户数据!$B$23="接近锁仓","允许开仓（接近锁仓；周期需复核）","允许开仓（周期需复核）"),IF(账户数据!$B$23="接近锁仓","允许开仓（接近锁仓）","允许开仓"))))))))) | L140: =IF(AP140="","",AP140) | U140: =IF(OR(AO140="",J140="",AO140<=0),"",(J140-AO140)/AO140) | V140: =IF(OR(AO140="",N140="",AO140<=0),"",(AO140-N140)/AO140) | W140: =IF(OR(U140="",V140="",V140<=0),"",U140/V140) | X140: =IF(OR(K140="",L140="",AO140="",AP140=""),"",(K140-AO140)*L140-IF(O140="",0,O140)-IF(P140="",0,P140)) | Y140: =IF(OR(X140="",AO140="",L140=""),"",IF(AO140*L140+IF(O140="",0,O140)<=0,"",X140/(AO140*L140+IF(O140="",0,O140)))) | Z140: =IF(OR(AE140="",多次统计数据!$B$8=""),"",AE140-多次统计数据!$B$8) | AA140: =IF(OR(I140="",M140="",M140<I140),"",M140-I140) | AB140: =IF(OR(A140="",多次统计数据!$B$8="",多次统计数据!$B$6<=0,多次统计数据!$B$6>=1),"",1-POWER(1+多次统计数据!$B$8,-多次统计数据!$B$6/(1-多次统计数据!$B$6))) | AC140: =IF(OR(AB140="",多次统计数据!$B$9=""),"",IF(多次统计数据!$B$9<AB140,"低于上限","达到或超过上限")) | AE140: =IF(OR(X140="",C140="",C140<=0),"",X140/C140) | AJ140: =IF(OR(AG140="",AH140=""),"",IF(OR(AND(AG140="短期博反弹",OR(AH140="1～3个交易日",AH140="4～10个交易日")),AND(AG140="突破冲新高",OR(AH140="4～10个交易日",AH140="11～20个交易日")),AND(AG140="趋势波段",OR(AH140="11～20个交易日",AH140="21～60个交易日",AH140="60个交易日以上"))),"匹配","周期与交易预期不匹配，请重新确认")) | AK140: =IF(A140="","",COUNTIFS(加仓管理!$A$2:$A$1001,A140,加仓管理!$G$2:$G$1001,">0")) | AL140: =IF(A140="","",SUMIFS(加仓管理!$G$2:$G$1001,加仓管理!$A$2:$A$1001,A140)) | AM140: =IF(AK140=0,"",IFERROR(LOOKUP(2,1/((加仓管理!$A$2:$A$1001=A140)*(加仓管理!$G$2:$G$1001>0)),加仓管理!$D$2:$D$1001),"")) | AN140: =IF(AK140=0,"",IFERROR(LOOKUP(2,1/((加仓管理!$A$2:$A$1001=A140)*(加仓管理!$G$2:$G$1001>0)),加仓管理!$E$2:$E$1001),"")) | AO140: =IF(OR(A140="",H140="",H140<=0),"",(E140*H140+SUMIFS(加仓管理!$H$2:$H$1001,加仓管理!$A$2:$A$1001,A140))/AP140) | AP140: =IF(OR(A140="",H140="",H140<=0),"",H140+AL140) | AQ140: =IF(A140="","",IF(M140<>"",0,IF(OR(H140="",N140=""),"",MAX((E140*H140+SUMIFS(加仓管理!$H$2:$H$1001,加仓管理!$A$2:$A$1001,A140))-MAX(N140,AN140)*AP140,0)))) | AR140: =IF(A140="","",IF(OR(E140="",H140=""),"违规：首次买入价格或股数缺失",IF(COUNTIFS(加仓管理!$A$2:$A$1001,A140,加仓管理!$R$2:$R$1001,"违规*")>0,"违规：请检查加仓管理表",IF(SUM($AQ$2:$AQ$201)>账户数据!$B$7,"预警：超过账户风险上限",IF(COUNTIFS(加仓管理!$A$2:$A$1001,A140,加仓管理!$N$2:$N$1001,">0",加仓管理!$G$2:$G$1001,"")>0,"提示：存在待执行加仓计划","通过")))))
F141: =IF(OR(C141="",D141="",E141="",N141="",C141<=0,D141<=0,E141<=N141),"",ROUNDDOWN((C141*D141)/(E141-N141)/100,0)*100) | G141: =IF(A141="","",IF(H141<>"","已开仓",IF(账户数据!$B$23="已锁仓","禁止开仓：连续亏损达到上限",IF(账户数据!$B$23="解锁信息不完整","禁止开仓：请完整填写解锁信息",IF(OR(F141="",E141="",N141="",E141<=N141,账户数据!$B$7=""),"",IF(OR(AG141="",AH141="",AI141=""),"禁止开仓：交易预期未填写完整",IF(账户数据!$B$9+F141*(E141-N141)>=账户数据!$B$7,"禁止开仓：风险额度不足",IF(AJ141="周期与交易预期不匹配，请重新确认",IF(账户数据!$B$23="接近锁仓","允许开仓（接近锁仓；周期需复核）","允许开仓（周期需复核）"),IF(账户数据!$B$23="接近锁仓","允许开仓（接近锁仓）","允许开仓"))))))))) | L141: =IF(AP141="","",AP141) | U141: =IF(OR(AO141="",J141="",AO141<=0),"",(J141-AO141)/AO141) | V141: =IF(OR(AO141="",N141="",AO141<=0),"",(AO141-N141)/AO141) | W141: =IF(OR(U141="",V141="",V141<=0),"",U141/V141) | X141: =IF(OR(K141="",L141="",AO141="",AP141=""),"",(K141-AO141)*L141-IF(O141="",0,O141)-IF(P141="",0,P141)) | Y141: =IF(OR(X141="",AO141="",L141=""),"",IF(AO141*L141+IF(O141="",0,O141)<=0,"",X141/(AO141*L141+IF(O141="",0,O141)))) | Z141: =IF(OR(AE141="",多次统计数据!$B$8=""),"",AE141-多次统计数据!$B$8) | AA141: =IF(OR(I141="",M141="",M141<I141),"",M141-I141) | AB141: =IF(OR(A141="",多次统计数据!$B$8="",多次统计数据!$B$6<=0,多次统计数据!$B$6>=1),"",1-POWER(1+多次统计数据!$B$8,-多次统计数据!$B$6/(1-多次统计数据!$B$6))) | AC141: =IF(OR(AB141="",多次统计数据!$B$9=""),"",IF(多次统计数据!$B$9<AB141,"低于上限","达到或超过上限")) | AE141: =IF(OR(X141="",C141="",C141<=0),"",X141/C141) | AJ141: =IF(OR(AG141="",AH141=""),"",IF(OR(AND(AG141="短期博反弹",OR(AH141="1～3个交易日",AH141="4～10个交易日")),AND(AG141="突破冲新高",OR(AH141="4～10个交易日",AH141="11～20个交易日")),AND(AG141="趋势波段",OR(AH141="11～20个交易日",AH141="21～60个交易日",AH141="60个交易日以上"))),"匹配","周期与交易预期不匹配，请重新确认")) | AK141: =IF(A141="","",COUNTIFS(加仓管理!$A$2:$A$1001,A141,加仓管理!$G$2:$G$1001,">0")) | AL141: =IF(A141="","",SUMIFS(加仓管理!$G$2:$G$1001,加仓管理!$A$2:$A$1001,A141)) | AM141: =IF(AK141=0,"",IFERROR(LOOKUP(2,1/((加仓管理!$A$2:$A$1001=A141)*(加仓管理!$G$2:$G$1001>0)),加仓管理!$D$2:$D$1001),"")) | AN141: =IF(AK141=0,"",IFERROR(LOOKUP(2,1/((加仓管理!$A$2:$A$1001=A141)*(加仓管理!$G$2:$G$1001>0)),加仓管理!$E$2:$E$1001),"")) | AO141: =IF(OR(A141="",H141="",H141<=0),"",(E141*H141+SUMIFS(加仓管理!$H$2:$H$1001,加仓管理!$A$2:$A$1001,A141))/AP141) | AP141: =IF(OR(A141="",H141="",H141<=0),"",H141+AL141) | AQ141: =IF(A141="","",IF(M141<>"",0,IF(OR(H141="",N141=""),"",MAX((E141*H141+SUMIFS(加仓管理!$H$2:$H$1001,加仓管理!$A$2:$A$1001,A141))-MAX(N141,AN141)*AP141,0)))) | AR141: =IF(A141="","",IF(OR(E141="",H141=""),"违规：首次买入价格或股数缺失",IF(COUNTIFS(加仓管理!$A$2:$A$1001,A141,加仓管理!$R$2:$R$1001,"违规*")>0,"违规：请检查加仓管理表",IF(SUM($AQ$2:$AQ$201)>账户数据!$B$7,"预警：超过账户风险上限",IF(COUNTIFS(加仓管理!$A$2:$A$1001,A141,加仓管理!$N$2:$N$1001,">0",加仓管理!$G$2:$G$1001,"")>0,"提示：存在待执行加仓计划","通过")))))
F142: =IF(OR(C142="",D142="",E142="",N142="",C142<=0,D142<=0,E142<=N142),"",ROUNDDOWN((C142*D142)/(E142-N142)/100,0)*100) | G142: =IF(A142="","",IF(H142<>"","已开仓",IF(账户数据!$B$23="已锁仓","禁止开仓：连续亏损达到上限",IF(账户数据!$B$23="解锁信息不完整","禁止开仓：请完整填写解锁信息",IF(OR(F142="",E142="",N142="",E142<=N142,账户数据!$B$7=""),"",IF(OR(AG142="",AH142="",AI142=""),"禁止开仓：交易预期未填写完整",IF(账户数据!$B$9+F142*(E142-N142)>=账户数据!$B$7,"禁止开仓：风险额度不足",IF(AJ142="周期与交易预期不匹配，请重新确认",IF(账户数据!$B$23="接近锁仓","允许开仓（接近锁仓；周期需复核）","允许开仓（周期需复核）"),IF(账户数据!$B$23="接近锁仓","允许开仓（接近锁仓）","允许开仓"))))))))) | L142: =IF(AP142="","",AP142) | U142: =IF(OR(AO142="",J142="",AO142<=0),"",(J142-AO142)/AO142) | V142: =IF(OR(AO142="",N142="",AO142<=0),"",(AO142-N142)/AO142) | W142: =IF(OR(U142="",V142="",V142<=0),"",U142/V142) | X142: =IF(OR(K142="",L142="",AO142="",AP142=""),"",(K142-AO142)*L142-IF(O142="",0,O142)-IF(P142="",0,P142)) | Y142: =IF(OR(X142="",AO142="",L142=""),"",IF(AO142*L142+IF(O142="",0,O142)<=0,"",X142/(AO142*L142+IF(O142="",0,O142)))) | Z142: =IF(OR(AE142="",多次统计数据!$B$8=""),"",AE142-多次统计数据!$B$8) | AA142: =IF(OR(I142="",M142="",M142<I142),"",M142-I142) | AB142: =IF(OR(A142="",多次统计数据!$B$8="",多次统计数据!$B$6<=0,多次统计数据!$B$6>=1),"",1-POWER(1+多次统计数据!$B$8,-多次统计数据!$B$6/(1-多次统计数据!$B$6))) | AC142: =IF(OR(AB142="",多次统计数据!$B$9=""),"",IF(多次统计数据!$B$9<AB142,"低于上限","达到或超过上限")) | AE142: =IF(OR(X142="",C142="",C142<=0),"",X142/C142) | AJ142: =IF(OR(AG142="",AH142=""),"",IF(OR(AND(AG142="短期博反弹",OR(AH142="1～3个交易日",AH142="4～10个交易日")),AND(AG142="突破冲新高",OR(AH142="4～10个交易日",AH142="11～20个交易日")),AND(AG142="趋势波段",OR(AH142="11～20个交易日",AH142="21～60个交易日",AH142="60个交易日以上"))),"匹配","周期与交易预期不匹配，请重新确认")) | AK142: =IF(A142="","",COUNTIFS(加仓管理!$A$2:$A$1001,A142,加仓管理!$G$2:$G$1001,">0")) | AL142: =IF(A142="","",SUMIFS(加仓管理!$G$2:$G$1001,加仓管理!$A$2:$A$1001,A142)) | AM142: =IF(AK142=0,"",IFERROR(LOOKUP(2,1/((加仓管理!$A$2:$A$1001=A142)*(加仓管理!$G$2:$G$1001>0)),加仓管理!$D$2:$D$1001),"")) | AN142: =IF(AK142=0,"",IFERROR(LOOKUP(2,1/((加仓管理!$A$2:$A$1001=A142)*(加仓管理!$G$2:$G$1001>0)),加仓管理!$E$2:$E$1001),"")) | AO142: =IF(OR(A142="",H142="",H142<=0),"",(E142*H142+SUMIFS(加仓管理!$H$2:$H$1001,加仓管理!$A$2:$A$1001,A142))/AP142) | AP142: =IF(OR(A142="",H142="",H142<=0),"",H142+AL142) | AQ142: =IF(A142="","",IF(M142<>"",0,IF(OR(H142="",N142=""),"",MAX((E142*H142+SUMIFS(加仓管理!$H$2:$H$1001,加仓管理!$A$2:$A$1001,A142))-MAX(N142,AN142)*AP142,0)))) | AR142: =IF(A142="","",IF(OR(E142="",H142=""),"违规：首次买入价格或股数缺失",IF(COUNTIFS(加仓管理!$A$2:$A$1001,A142,加仓管理!$R$2:$R$1001,"违规*")>0,"违规：请检查加仓管理表",IF(SUM($AQ$2:$AQ$201)>账户数据!$B$7,"预警：超过账户风险上限",IF(COUNTIFS(加仓管理!$A$2:$A$1001,A142,加仓管理!$N$2:$N$1001,">0",加仓管理!$G$2:$G$1001,"")>0,"提示：存在待执行加仓计划","通过")))))
F143: =IF(OR(C143="",D143="",E143="",N143="",C143<=0,D143<=0,E143<=N143),"",ROUNDDOWN((C143*D143)/(E143-N143)/100,0)*100) | G143: =IF(A143="","",IF(H143<>"","已开仓",IF(账户数据!$B$23="已锁仓","禁止开仓：连续亏损达到上限",IF(账户数据!$B$23="解锁信息不完整","禁止开仓：请完整填写解锁信息",IF(OR(F143="",E143="",N143="",E143<=N143,账户数据!$B$7=""),"",IF(OR(AG143="",AH143="",AI143=""),"禁止开仓：交易预期未填写完整",IF(账户数据!$B$9+F143*(E143-N143)>=账户数据!$B$7,"禁止开仓：风险额度不足",IF(AJ143="周期与交易预期不匹配，请重新确认",IF(账户数据!$B$23="接近锁仓","允许开仓（接近锁仓；周期需复核）","允许开仓（周期需复核）"),IF(账户数据!$B$23="接近锁仓","允许开仓（接近锁仓）","允许开仓"))))))))) | L143: =IF(AP143="","",AP143) | U143: =IF(OR(AO143="",J143="",AO143<=0),"",(J143-AO143)/AO143) | V143: =IF(OR(AO143="",N143="",AO143<=0),"",(AO143-N143)/AO143) | W143: =IF(OR(U143="",V143="",V143<=0),"",U143/V143) | X143: =IF(OR(K143="",L143="",AO143="",AP143=""),"",(K143-AO143)*L143-IF(O143="",0,O143)-IF(P143="",0,P143)) | Y143: =IF(OR(X143="",AO143="",L143=""),"",IF(AO143*L143+IF(O143="",0,O143)<=0,"",X143/(AO143*L143+IF(O143="",0,O143)))) | Z143: =IF(OR(AE143="",多次统计数据!$B$8=""),"",AE143-多次统计数据!$B$8) | AA143: =IF(OR(I143="",M143="",M143<I143),"",M143-I143) | AB143: =IF(OR(A143="",多次统计数据!$B$8="",多次统计数据!$B$6<=0,多次统计数据!$B$6>=1),"",1-POWER(1+多次统计数据!$B$8,-多次统计数据!$B$6/(1-多次统计数据!$B$6))) | AC143: =IF(OR(AB143="",多次统计数据!$B$9=""),"",IF(多次统计数据!$B$9<AB143,"低于上限","达到或超过上限")) | AE143: =IF(OR(X143="",C143="",C143<=0),"",X143/C143) | AJ143: =IF(OR(AG143="",AH143=""),"",IF(OR(AND(AG143="短期博反弹",OR(AH143="1～3个交易日",AH143="4～10个交易日")),AND(AG143="突破冲新高",OR(AH143="4～10个交易日",AH143="11～20个交易日")),AND(AG143="趋势波段",OR(AH143="11～20个交易日",AH143="21～60个交易日",AH143="60个交易日以上"))),"匹配","周期与交易预期不匹配，请重新确认")) | AK143: =IF(A143="","",COUNTIFS(加仓管理!$A$2:$A$1001,A143,加仓管理!$G$2:$G$1001,">0")) | AL143: =IF(A143="","",SUMIFS(加仓管理!$G$2:$G$1001,加仓管理!$A$2:$A$1001,A143)) | AM143: =IF(AK143=0,"",IFERROR(LOOKUP(2,1/((加仓管理!$A$2:$A$1001=A143)*(加仓管理!$G$2:$G$1001>0)),加仓管理!$D$2:$D$1001),"")) | AN143: =IF(AK143=0,"",IFERROR(LOOKUP(2,1/((加仓管理!$A$2:$A$1001=A143)*(加仓管理!$G$2:$G$1001>0)),加仓管理!$E$2:$E$1001),"")) | AO143: =IF(OR(A143="",H143="",H143<=0),"",(E143*H143+SUMIFS(加仓管理!$H$2:$H$1001,加仓管理!$A$2:$A$1001,A143))/AP143) | AP143: =IF(OR(A143="",H143="",H143<=0),"",H143+AL143) | AQ143: =IF(A143="","",IF(M143<>"",0,IF(OR(H143="",N143=""),"",MAX((E143*H143+SUMIFS(加仓管理!$H$2:$H$1001,加仓管理!$A$2:$A$1001,A143))-MAX(N143,AN143)*AP143,0)))) | AR143: =IF(A143="","",IF(OR(E143="",H143=""),"违规：首次买入价格或股数缺失",IF(COUNTIFS(加仓管理!$A$2:$A$1001,A143,加仓管理!$R$2:$R$1001,"违规*")>0,"违规：请检查加仓管理表",IF(SUM($AQ$2:$AQ$201)>账户数据!$B$7,"预警：超过账户风险上限",IF(COUNTIFS(加仓管理!$A$2:$A$1001,A143,加仓管理!$N$2:$N$1001,">0",加仓管理!$G$2:$G$1001,"")>0,"提示：存在待执行加仓计划","通过")))))
F144: =IF(OR(C144="",D144="",E144="",N144="",C144<=0,D144<=0,E144<=N144),"",ROUNDDOWN((C144*D144)/(E144-N144)/100,0)*100) | G144: =IF(A144="","",IF(H144<>"","已开仓",IF(账户数据!$B$23="已锁仓","禁止开仓：连续亏损达到上限",IF(账户数据!$B$23="解锁信息不完整","禁止开仓：请完整填写解锁信息",IF(OR(F144="",E144="",N144="",E144<=N144,账户数据!$B$7=""),"",IF(OR(AG144="",AH144="",AI144=""),"禁止开仓：交易预期未填写完整",IF(账户数据!$B$9+F144*(E144-N144)>=账户数据!$B$7,"禁止开仓：风险额度不足",IF(AJ144="周期与交易预期不匹配，请重新确认",IF(账户数据!$B$23="接近锁仓","允许开仓（接近锁仓；周期需复核）","允许开仓（周期需复核）"),IF(账户数据!$B$23="接近锁仓","允许开仓（接近锁仓）","允许开仓"))))))))) | L144: =IF(AP144="","",AP144) | U144: =IF(OR(AO144="",J144="",AO144<=0),"",(J144-AO144)/AO144) | V144: =IF(OR(AO144="",N144="",AO144<=0),"",(AO144-N144)/AO144) | W144: =IF(OR(U144="",V144="",V144<=0),"",U144/V144) | X144: =IF(OR(K144="",L144="",AO144="",AP144=""),"",(K144-AO144)*L144-IF(O144="",0,O144)-IF(P144="",0,P144)) | Y144: =IF(OR(X144="",AO144="",L144=""),"",IF(AO144*L144+IF(O144="",0,O144)<=0,"",X144/(AO144*L144+IF(O144="",0,O144)))) | Z144: =IF(OR(AE144="",多次统计数据!$B$8=""),"",AE144-多次统计数据!$B$8) | AA144: =IF(OR(I144="",M144="",M144<I144),"",M144-I144) | AB144: =IF(OR(A144="",多次统计数据!$B$8="",多次统计数据!$B$6<=0,多次统计数据!$B$6>=1),"",1-POWER(1+多次统计数据!$B$8,-多次统计数据!$B$6/(1-多次统计数据!$B$6))) | AC144: =IF(OR(AB144="",多次统计数据!$B$9=""),"",IF(多次统计数据!$B$9<AB144,"低于上限","达到或超过上限")) | AE144: =IF(OR(X144="",C144="",C144<=0),"",X144/C144) | AJ144: =IF(OR(AG144="",AH144=""),"",IF(OR(AND(AG144="短期博反弹",OR(AH144="1～3个交易日",AH144="4～10个交易日")),AND(AG144="突破冲新高",OR(AH144="4～10个交易日",AH144="11～20个交易日")),AND(AG144="趋势波段",OR(AH144="11～20个交易日",AH144="21～60个交易日",AH144="60个交易日以上"))),"匹配","周期与交易预期不匹配，请重新确认")) | AK144: =IF(A144="","",COUNTIFS(加仓管理!$A$2:$A$1001,A144,加仓管理!$G$2:$G$1001,">0")) | AL144: =IF(A144="","",SUMIFS(加仓管理!$G$2:$G$1001,加仓管理!$A$2:$A$1001,A144)) | AM144: =IF(AK144=0,"",IFERROR(LOOKUP(2,1/((加仓管理!$A$2:$A$1001=A144)*(加仓管理!$G$2:$G$1001>0)),加仓管理!$D$2:$D$1001),"")) | AN144: =IF(AK144=0,"",IFERROR(LOOKUP(2,1/((加仓管理!$A$2:$A$1001=A144)*(加仓管理!$G$2:$G$1001>0)),加仓管理!$E$2:$E$1001),"")) | AO144: =IF(OR(A144="",H144="",H144<=0),"",(E144*H144+SUMIFS(加仓管理!$H$2:$H$1001,加仓管理!$A$2:$A$1001,A144))/AP144) | AP144: =IF(OR(A144="",H144="",H144<=0),"",H144+AL144) | AQ144: =IF(A144="","",IF(M144<>"",0,IF(OR(H144="",N144=""),"",MAX((E144*H144+SUMIFS(加仓管理!$H$2:$H$1001,加仓管理!$A$2:$A$1001,A144))-MAX(N144,AN144)*AP144,0)))) | AR144: =IF(A144="","",IF(OR(E144="",H144=""),"违规：首次买入价格或股数缺失",IF(COUNTIFS(加仓管理!$A$2:$A$1001,A144,加仓管理!$R$2:$R$1001,"违规*")>0,"违规：请检查加仓管理表",IF(SUM($AQ$2:$AQ$201)>账户数据!$B$7,"预警：超过账户风险上限",IF(COUNTIFS(加仓管理!$A$2:$A$1001,A144,加仓管理!$N$2:$N$1001,">0",加仓管理!$G$2:$G$1001,"")>0,"提示：存在待执行加仓计划","通过")))))
F145: =IF(OR(C145="",D145="",E145="",N145="",C145<=0,D145<=0,E145<=N145),"",ROUNDDOWN((C145*D145)/(E145-N145)/100,0)*100) | G145: =IF(A145="","",IF(H145<>"","已开仓",IF(账户数据!$B$23="已锁仓","禁止开仓：连续亏损达到上限",IF(账户数据!$B$23="解锁信息不完整","禁止开仓：请完整填写解锁信息",IF(OR(F145="",E145="",N145="",E145<=N145,账户数据!$B$7=""),"",IF(OR(AG145="",AH145="",AI145=""),"禁止开仓：交易预期未填写完整",IF(账户数据!$B$9+F145*(E145-N145)>=账户数据!$B$7,"禁止开仓：风险额度不足",IF(AJ145="周期与交易预期不匹配，请重新确认",IF(账户数据!$B$23="接近锁仓","允许开仓（接近锁仓；周期需复核）","允许开仓（周期需复核）"),IF(账户数据!$B$23="接近锁仓","允许开仓（接近锁仓）","允许开仓"))))))))) | L145: =IF(AP145="","",AP145) | U145: =IF(OR(AO145="",J145="",AO145<=0),"",(J145-AO145)/AO145) | V145: =IF(OR(AO145="",N145="",AO145<=0),"",(AO145-N145)/AO145) | W145: =IF(OR(U145="",V145="",V145<=0),"",U145/V145) | X145: =IF(OR(K145="",L145="",AO145="",AP145=""),"",(K145-AO145)*L145-IF(O145="",0,O145)-IF(P145="",0,P145)) | Y145: =IF(OR(X145="",AO145="",L145=""),"",IF(AO145*L145+IF(O145="",0,O145)<=0,"",X145/(AO145*L145+IF(O145="",0,O145)))) | Z145: =IF(OR(AE145="",多次统计数据!$B$8=""),"",AE145-多次统计数据!$B$8) | AA145: =IF(OR(I145="",M145="",M145<I145),"",M145-I145) | AB145: =IF(OR(A145="",多次统计数据!$B$8="",多次统计数据!$B$6<=0,多次统计数据!$B$6>=1),"",1-POWER(1+多次统计数据!$B$8,-多次统计数据!$B$6/(1-多次统计数据!$B$6))) | AC145: =IF(OR(AB145="",多次统计数据!$B$9=""),"",IF(多次统计数据!$B$9<AB145,"低于上限","达到或超过上限")) | AE145: =IF(OR(X145="",C145="",C145<=0),"",X145/C145) | AJ145: =IF(OR(AG145="",AH145=""),"",IF(OR(AND(AG145="短期博反弹",OR(AH145="1～3个交易日",AH145="4～10个交易日")),AND(AG145="突破冲新高",OR(AH145="4～10个交易日",AH145="11～20个交易日")),AND(AG145="趋势波段",OR(AH145="11～20个交易日",AH145="21～60个交易日",AH145="60个交易日以上"))),"匹配","周期与交易预期不匹配，请重新确认")) | AK145: =IF(A145="","",COUNTIFS(加仓管理!$A$2:$A$1001,A145,加仓管理!$G$2:$G$1001,">0")) | AL145: =IF(A145="","",SUMIFS(加仓管理!$G$2:$G$1001,加仓管理!$A$2:$A$1001,A145)) | AM145: =IF(AK145=0,"",IFERROR(LOOKUP(2,1/((加仓管理!$A$2:$A$1001=A145)*(加仓管理!$G$2:$G$1001>0)),加仓管理!$D$2:$D$1001),"")) | AN145: =IF(AK145=0,"",IFERROR(LOOKUP(2,1/((加仓管理!$A$2:$A$1001=A145)*(加仓管理!$G$2:$G$1001>0)),加仓管理!$E$2:$E$1001),"")) | AO145: =IF(OR(A145="",H145="",H145<=0),"",(E145*H145+SUMIFS(加仓管理!$H$2:$H$1001,加仓管理!$A$2:$A$1001,A145))/AP145) | AP145: =IF(OR(A145="",H145="",H145<=0),"",H145+AL145) | AQ145: =IF(A145="","",IF(M145<>"",0,IF(OR(H145="",N145=""),"",MAX((E145*H145+SUMIFS(加仓管理!$H$2:$H$1001,加仓管理!$A$2:$A$1001,A145))-MAX(N145,AN145)*AP145,0)))) | AR145: =IF(A145="","",IF(OR(E145="",H145=""),"违规：首次买入价格或股数缺失",IF(COUNTIFS(加仓管理!$A$2:$A$1001,A145,加仓管理!$R$2:$R$1001,"违规*")>0,"违规：请检查加仓管理表",IF(SUM($AQ$2:$AQ$201)>账户数据!$B$7,"预警：超过账户风险上限",IF(COUNTIFS(加仓管理!$A$2:$A$1001,A145,加仓管理!$N$2:$N$1001,">0",加仓管理!$G$2:$G$1001,"")>0,"提示：存在待执行加仓计划","通过")))))
F146: =IF(OR(C146="",D146="",E146="",N146="",C146<=0,D146<=0,E146<=N146),"",ROUNDDOWN((C146*D146)/(E146-N146)/100,0)*100) | G146: =IF(A146="","",IF(H146<>"","已开仓",IF(账户数据!$B$23="已锁仓","禁止开仓：连续亏损达到上限",IF(账户数据!$B$23="解锁信息不完整","禁止开仓：请完整填写解锁信息",IF(OR(F146="",E146="",N146="",E146<=N146,账户数据!$B$7=""),"",IF(OR(AG146="",AH146="",AI146=""),"禁止开仓：交易预期未填写完整",IF(账户数据!$B$9+F146*(E146-N146)>=账户数据!$B$7,"禁止开仓：风险额度不足",IF(AJ146="周期与交易预期不匹配，请重新确认",IF(账户数据!$B$23="接近锁仓","允许开仓（接近锁仓；周期需复核）","允许开仓（周期需复核）"),IF(账户数据!$B$23="接近锁仓","允许开仓（接近锁仓）","允许开仓"))))))))) | L146: =IF(AP146="","",AP146) | U146: =IF(OR(AO146="",J146="",AO146<=0),"",(J146-AO146)/AO146) | V146: =IF(OR(AO146="",N146="",AO146<=0),"",(AO146-N146)/AO146) | W146: =IF(OR(U146="",V146="",V146<=0),"",U146/V146) | X146: =IF(OR(K146="",L146="",AO146="",AP146=""),"",(K146-AO146)*L146-IF(O146="",0,O146)-IF(P146="",0,P146)) | Y146: =IF(OR(X146="",AO146="",L146=""),"",IF(AO146*L146+IF(O146="",0,O146)<=0,"",X146/(AO146*L146+IF(O146="",0,O146)))) | Z146: =IF(OR(AE146="",多次统计数据!$B$8=""),"",AE146-多次统计数据!$B$8) | AA146: =IF(OR(I146="",M146="",M146<I146),"",M146-I146) | AB146: =IF(OR(A146="",多次统计数据!$B$8="",多次统计数据!$B$6<=0,多次统计数据!$B$6>=1),"",1-POWER(1+多次统计数据!$B$8,-多次统计数据!$B$6/(1-多次统计数据!$B$6))) | AC146: =IF(OR(AB146="",多次统计数据!$B$9=""),"",IF(多次统计数据!$B$9<AB146,"低于上限","达到或超过上限")) | AE146: =IF(OR(X146="",C146="",C146<=0),"",X146/C146) | AJ146: =IF(OR(AG146="",AH146=""),"",IF(OR(AND(AG146="短期博反弹",OR(AH146="1～3个交易日",AH146="4～10个交易日")),AND(AG146="突破冲新高",OR(AH146="4～10个交易日",AH146="11～20个交易日")),AND(AG146="趋势波段",OR(AH146="11～20个交易日",AH146="21～60个交易日",AH146="60个交易日以上"))),"匹配","周期与交易预期不匹配，请重新确认")) | AK146: =IF(A146="","",COUNTIFS(加仓管理!$A$2:$A$1001,A146,加仓管理!$G$2:$G$1001,">0")) | AL146: =IF(A146="","",SUMIFS(加仓管理!$G$2:$G$1001,加仓管理!$A$2:$A$1001,A146)) | AM146: =IF(AK146=0,"",IFERROR(LOOKUP(2,1/((加仓管理!$A$2:$A$1001=A146)*(加仓管理!$G$2:$G$1001>0)),加仓管理!$D$2:$D$1001),"")) | AN146: =IF(AK146=0,"",IFERROR(LOOKUP(2,1/((加仓管理!$A$2:$A$1001=A146)*(加仓管理!$G$2:$G$1001>0)),加仓管理!$E$2:$E$1001),"")) | AO146: =IF(OR(A146="",H146="",H146<=0),"",(E146*H146+SUMIFS(加仓管理!$H$2:$H$1001,加仓管理!$A$2:$A$1001,A146))/AP146) | AP146: =IF(OR(A146="",H146="",H146<=0),"",H146+AL146) | AQ146: =IF(A146="","",IF(M146<>"",0,IF(OR(H146="",N146=""),"",MAX((E146*H146+SUMIFS(加仓管理!$H$2:$H$1001,加仓管理!$A$2:$A$1001,A146))-MAX(N146,AN146)*AP146,0)))) | AR146: =IF(A146="","",IF(OR(E146="",H146=""),"违规：首次买入价格或股数缺失",IF(COUNTIFS(加仓管理!$A$2:$A$1001,A146,加仓管理!$R$2:$R$1001,"违规*")>0,"违规：请检查加仓管理表",IF(SUM($AQ$2:$AQ$201)>账户数据!$B$7,"预警：超过账户风险上限",IF(COUNTIFS(加仓管理!$A$2:$A$1001,A146,加仓管理!$N$2:$N$1001,">0",加仓管理!$G$2:$G$1001,"")>0,"提示：存在待执行加仓计划","通过")))))
F147: =IF(OR(C147="",D147="",E147="",N147="",C147<=0,D147<=0,E147<=N147),"",ROUNDDOWN((C147*D147)/(E147-N147)/100,0)*100) | G147: =IF(A147="","",IF(H147<>"","已开仓",IF(账户数据!$B$23="已锁仓","禁止开仓：连续亏损达到上限",IF(账户数据!$B$23="解锁信息不完整","禁止开仓：请完整填写解锁信息",IF(OR(F147="",E147="",N147="",E147<=N147,账户数据!$B$7=""),"",IF(OR(AG147="",AH147="",AI147=""),"禁止开仓：交易预期未填写完整",IF(账户数据!$B$9+F147*(E147-N147)>=账户数据!$B$7,"禁止开仓：风险额度不足",IF(AJ147="周期与交易预期不匹配，请重新确认",IF(账户数据!$B$23="接近锁仓","允许开仓（接近锁仓；周期需复核）","允许开仓（周期需复核）"),IF(账户数据!$B$23="接近锁仓","允许开仓（接近锁仓）","允许开仓"))))))))) | L147: =IF(AP147="","",AP147) | U147: =IF(OR(AO147="",J147="",AO147<=0),"",(J147-AO147)/AO147) | V147: =IF(OR(AO147="",N147="",AO147<=0),"",(AO147-N147)/AO147) | W147: =IF(OR(U147="",V147="",V147<=0),"",U147/V147) | X147: =IF(OR(K147="",L147="",AO147="",AP147=""),"",(K147-AO147)*L147-IF(O147="",0,O147)-IF(P147="",0,P147)) | Y147: =IF(OR(X147="",AO147="",L147=""),"",IF(AO147*L147+IF(O147="",0,O147)<=0,"",X147/(AO147*L147+IF(O147="",0,O147)))) | Z147: =IF(OR(AE147="",多次统计数据!$B$8=""),"",AE147-多次统计数据!$B$8) | AA147: =IF(OR(I147="",M147="",M147<I147),"",M147-I147) | AB147: =IF(OR(A147="",多次统计数据!$B$8="",多次统计数据!$B$6<=0,多次统计数据!$B$6>=1),"",1-POWER(1+多次统计数据!$B$8,-多次统计数据!$B$6/(1-多次统计数据!$B$6))) | AC147: =IF(OR(AB147="",多次统计数据!$B$9=""),"",IF(多次统计数据!$B$9<AB147,"低于上限","达到或超过上限")) | AE147: =IF(OR(X147="",C147="",C147<=0),"",X147/C147) | AJ147: =IF(OR(AG147="",AH147=""),"",IF(OR(AND(AG147="短期博反弹",OR(AH147="1～3个交易日",AH147="4～10个交易日")),AND(AG147="突破冲新高",OR(AH147="4～10个交易日",AH147="11～20个交易日")),AND(AG147="趋势波段",OR(AH147="11～20个交易日",AH147="21～60个交易日",AH147="60个交易日以上"))),"匹配","周期与交易预期不匹配，请重新确认")) | AK147: =IF(A147="","",COUNTIFS(加仓管理!$A$2:$A$1001,A147,加仓管理!$G$2:$G$1001,">0")) | AL147: =IF(A147="","",SUMIFS(加仓管理!$G$2:$G$1001,加仓管理!$A$2:$A$1001,A147)) | AM147: =IF(AK147=0,"",IFERROR(LOOKUP(2,1/((加仓管理!$A$2:$A$1001=A147)*(加仓管理!$G$2:$G$1001>0)),加仓管理!$D$2:$D$1001),"")) | AN147: =IF(AK147=0,"",IFERROR(LOOKUP(2,1/((加仓管理!$A$2:$A$1001=A147)*(加仓管理!$G$2:$G$1001>0)),加仓管理!$E$2:$E$1001),"")) | AO147: =IF(OR(A147="",H147="",H147<=0),"",(E147*H147+SUMIFS(加仓管理!$H$2:$H$1001,加仓管理!$A$2:$A$1001,A147))/AP147) | AP147: =IF(OR(A147="",H147="",H147<=0),"",H147+AL147) | AQ147: =IF(A147="","",IF(M147<>"",0,IF(OR(H147="",N147=""),"",MAX((E147*H147+SUMIFS(加仓管理!$H$2:$H$1001,加仓管理!$A$2:$A$1001,A147))-MAX(N147,AN147)*AP147,0)))) | AR147: =IF(A147="","",IF(OR(E147="",H147=""),"违规：首次买入价格或股数缺失",IF(COUNTIFS(加仓管理!$A$2:$A$1001,A147,加仓管理!$R$2:$R$1001,"违规*")>0,"违规：请检查加仓管理表",IF(SUM($AQ$2:$AQ$201)>账户数据!$B$7,"预警：超过账户风险上限",IF(COUNTIFS(加仓管理!$A$2:$A$1001,A147,加仓管理!$N$2:$N$1001,">0",加仓管理!$G$2:$G$1001,"")>0,"提示：存在待执行加仓计划","通过")))))
F148: =IF(OR(C148="",D148="",E148="",N148="",C148<=0,D148<=0,E148<=N148),"",ROUNDDOWN((C148*D148)/(E148-N148)/100,0)*100) | G148: =IF(A148="","",IF(H148<>"","已开仓",IF(账户数据!$B$23="已锁仓","禁止开仓：连续亏损达到上限",IF(账户数据!$B$23="解锁信息不完整","禁止开仓：请完整填写解锁信息",IF(OR(F148="",E148="",N148="",E148<=N148,账户数据!$B$7=""),"",IF(OR(AG148="",AH148="",AI148=""),"禁止开仓：交易预期未填写完整",IF(账户数据!$B$9+F148*(E148-N148)>=账户数据!$B$7,"禁止开仓：风险额度不足",IF(AJ148="周期与交易预期不匹配，请重新确认",IF(账户数据!$B$23="接近锁仓","允许开仓（接近锁仓；周期需复核）","允许开仓（周期需复核）"),IF(账户数据!$B$23="接近锁仓","允许开仓（接近锁仓）","允许开仓"))))))))) | L148: =IF(AP148="","",AP148) | U148: =IF(OR(AO148="",J148="",AO148<=0),"",(J148-AO148)/AO148) | V148: =IF(OR(AO148="",N148="",AO148<=0),"",(AO148-N148)/AO148) | W148: =IF(OR(U148="",V148="",V148<=0),"",U148/V148) | X148: =IF(OR(K148="",L148="",AO148="",AP148=""),"",(K148-AO148)*L148-IF(O148="",0,O148)-IF(P148="",0,P148)) | Y148: =IF(OR(X148="",AO148="",L148=""),"",IF(AO148*L148+IF(O148="",0,O148)<=0,"",X148/(AO148*L148+IF(O148="",0,O148)))) | Z148: =IF(OR(AE148="",多次统计数据!$B$8=""),"",AE148-多次统计数据!$B$8) | AA148: =IF(OR(I148="",M148="",M148<I148),"",M148-I148) | AB148: =IF(OR(A148="",多次统计数据!$B$8="",多次统计数据!$B$6<=0,多次统计数据!$B$6>=1),"",1-POWER(1+多次统计数据!$B$8,-多次统计数据!$B$6/(1-多次统计数据!$B$6))) | AC148: =IF(OR(AB148="",多次统计数据!$B$9=""),"",IF(多次统计数据!$B$9<AB148,"低于上限","达到或超过上限")) | AE148: =IF(OR(X148="",C148="",C148<=0),"",X148/C148) | AJ148: =IF(OR(AG148="",AH148=""),"",IF(OR(AND(AG148="短期博反弹",OR(AH148="1～3个交易日",AH148="4～10个交易日")),AND(AG148="突破冲新高",OR(AH148="4～10个交易日",AH148="11～20个交易日")),AND(AG148="趋势波段",OR(AH148="11～20个交易日",AH148="21～60个交易日",AH148="60个交易日以上"))),"匹配","周期与交易预期不匹配，请重新确认")) | AK148: =IF(A148="","",COUNTIFS(加仓管理!$A$2:$A$1001,A148,加仓管理!$G$2:$G$1001,">0")) | AL148: =IF(A148="","",SUMIFS(加仓管理!$G$2:$G$1001,加仓管理!$A$2:$A$1001,A148)) | AM148: =IF(AK148=0,"",IFERROR(LOOKUP(2,1/((加仓管理!$A$2:$A$1001=A148)*(加仓管理!$G$2:$G$1001>0)),加仓管理!$D$2:$D$1001),"")) | AN148: =IF(AK148=0,"",IFERROR(LOOKUP(2,1/((加仓管理!$A$2:$A$1001=A148)*(加仓管理!$G$2:$G$1001>0)),加仓管理!$E$2:$E$1001),"")) | AO148: =IF(OR(A148="",H148="",H148<=0),"",(E148*H148+SUMIFS(加仓管理!$H$2:$H$1001,加仓管理!$A$2:$A$1001,A148))/AP148) | AP148: =IF(OR(A148="",H148="",H148<=0),"",H148+AL148) | AQ148: =IF(A148="","",IF(M148<>"",0,IF(OR(H148="",N148=""),"",MAX((E148*H148+SUMIFS(加仓管理!$H$2:$H$1001,加仓管理!$A$2:$A$1001,A148))-MAX(N148,AN148)*AP148,0)))) | AR148: =IF(A148="","",IF(OR(E148="",H148=""),"违规：首次买入价格或股数缺失",IF(COUNTIFS(加仓管理!$A$2:$A$1001,A148,加仓管理!$R$2:$R$1001,"违规*")>0,"违规：请检查加仓管理表",IF(SUM($AQ$2:$AQ$201)>账户数据!$B$7,"预警：超过账户风险上限",IF(COUNTIFS(加仓管理!$A$2:$A$1001,A148,加仓管理!$N$2:$N$1001,">0",加仓管理!$G$2:$G$1001,"")>0,"提示：存在待执行加仓计划","通过")))))
F149: =IF(OR(C149="",D149="",E149="",N149="",C149<=0,D149<=0,E149<=N149),"",ROUNDDOWN((C149*D149)/(E149-N149)/100,0)*100) | G149: =IF(A149="","",IF(H149<>"","已开仓",IF(账户数据!$B$23="已锁仓","禁止开仓：连续亏损达到上限",IF(账户数据!$B$23="解锁信息不完整","禁止开仓：请完整填写解锁信息",IF(OR(F149="",E149="",N149="",E149<=N149,账户数据!$B$7=""),"",IF(OR(AG149="",AH149="",AI149=""),"禁止开仓：交易预期未填写完整",IF(账户数据!$B$9+F149*(E149-N149)>=账户数据!$B$7,"禁止开仓：风险额度不足",IF(AJ149="周期与交易预期不匹配，请重新确认",IF(账户数据!$B$23="接近锁仓","允许开仓（接近锁仓；周期需复核）","允许开仓（周期需复核）"),IF(账户数据!$B$23="接近锁仓","允许开仓（接近锁仓）","允许开仓"))))))))) | L149: =IF(AP149="","",AP149) | U149: =IF(OR(AO149="",J149="",AO149<=0),"",(J149-AO149)/AO149) | V149: =IF(OR(AO149="",N149="",AO149<=0),"",(AO149-N149)/AO149) | W149: =IF(OR(U149="",V149="",V149<=0),"",U149/V149) | X149: =IF(OR(K149="",L149="",AO149="",AP149=""),"",(K149-AO149)*L149-IF(O149="",0,O149)-IF(P149="",0,P149)) | Y149: =IF(OR(X149="",AO149="",L149=""),"",IF(AO149*L149+IF(O149="",0,O149)<=0,"",X149/(AO149*L149+IF(O149="",0,O149)))) | Z149: =IF(OR(AE149="",多次统计数据!$B$8=""),"",AE149-多次统计数据!$B$8) | AA149: =IF(OR(I149="",M149="",M149<I149),"",M149-I149) | AB149: =IF(OR(A149="",多次统计数据!$B$8="",多次统计数据!$B$6<=0,多次统计数据!$B$6>=1),"",1-POWER(1+多次统计数据!$B$8,-多次统计数据!$B$6/(1-多次统计数据!$B$6))) | AC149: =IF(OR(AB149="",多次统计数据!$B$9=""),"",IF(多次统计数据!$B$9<AB149,"低于上限","达到或超过上限")) | AE149: =IF(OR(X149="",C149="",C149<=0),"",X149/C149) | AJ149: =IF(OR(AG149="",AH149=""),"",IF(OR(AND(AG149="短期博反弹",OR(AH149="1～3个交易日",AH149="4～10个交易日")),AND(AG149="突破冲新高",OR(AH149="4～10个交易日",AH149="11～20个交易日")),AND(AG149="趋势波段",OR(AH149="11～20个交易日",AH149="21～60个交易日",AH149="60个交易日以上"))),"匹配","周期与交易预期不匹配，请重新确认")) | AK149: =IF(A149="","",COUNTIFS(加仓管理!$A$2:$A$1001,A149,加仓管理!$G$2:$G$1001,">0")) | AL149: =IF(A149="","",SUMIFS(加仓管理!$G$2:$G$1001,加仓管理!$A$2:$A$1001,A149)) | AM149: =IF(AK149=0,"",IFERROR(LOOKUP(2,1/((加仓管理!$A$2:$A$1001=A149)*(加仓管理!$G$2:$G$1001>0)),加仓管理!$D$2:$D$1001),"")) | AN149: =IF(AK149=0,"",IFERROR(LOOKUP(2,1/((加仓管理!$A$2:$A$1001=A149)*(加仓管理!$G$2:$G$1001>0)),加仓管理!$E$2:$E$1001),"")) | AO149: =IF(OR(A149="",H149="",H149<=0),"",(E149*H149+SUMIFS(加仓管理!$H$2:$H$1001,加仓管理!$A$2:$A$1001,A149))/AP149) | AP149: =IF(OR(A149="",H149="",H149<=0),"",H149+AL149) | AQ149: =IF(A149="","",IF(M149<>"",0,IF(OR(H149="",N149=""),"",MAX((E149*H149+SUMIFS(加仓管理!$H$2:$H$1001,加仓管理!$A$2:$A$1001,A149))-MAX(N149,AN149)*AP149,0)))) | AR149: =IF(A149="","",IF(OR(E149="",H149=""),"违规：首次买入价格或股数缺失",IF(COUNTIFS(加仓管理!$A$2:$A$1001,A149,加仓管理!$R$2:$R$1001,"违规*")>0,"违规：请检查加仓管理表",IF(SUM($AQ$2:$AQ$201)>账户数据!$B$7,"预警：超过账户风险上限",IF(COUNTIFS(加仓管理!$A$2:$A$1001,A149,加仓管理!$N$2:$N$1001,">0",加仓管理!$G$2:$G$1001,"")>0,"提示：存在待执行加仓计划","通过")))))
... F201: =IF(OR(C201="",D201="",E201="",N201="",C201<=0,D201<=0,E201<=N201),"",ROUNDDOWN((C201*D201)/(E201-N201)/100,0)*100) | G201: =IF(A201="","",IF(H201<>"","已开仓",IF(账户数据!$B$23="已锁仓","禁止开仓：连续亏损达到上限",IF(账户数据!$B$23="解锁信息不完整","禁止开仓：请完整填写解锁信息",IF(OR(F201="",E201="",N201="",E201<=N201,账户数据!$B$7=""),"",IF(OR(AG201="",AH201="",AI201=""),"禁止开仓：交易预期未填写完整",IF(账户数据!$B$9+F201*(E201-N201)>=账户数据!$B$7,"禁止开仓：风险额度不足",IF(AJ201="周期与交易预期不匹配，请重新确认",IF(账户数据!$B$23="接近锁仓","允许开仓（接近锁仓；周期需复核）","允许开仓（周期需复核）"),IF(账户数据!$B$23="接近锁仓","允许开仓（接近锁仓）","允许开仓"))))))))) | L201: =IF(AP201="","",AP201) | U201: =IF(OR(AO201="",J201="",AO201<=0),"",(J201-AO201)/AO201) | V201: =IF(OR(AO201="",N201="",AO201<=0),"",(AO201-N201)/AO201) | W201: =IF(OR(U201="",V201="",V201<=0),"",U201/V201) | X201: =IF(OR(K201="",L201="",AO201="",AP201=""),"",(K201-AO201)*L201-IF(O201="",0,O201)-IF(P201="",0,P201)) | Y201: =IF(OR(X201="",AO201="",L201=""),"",IF(AO201*L201+IF(O201="",0,O201)<=0,"",X201/(AO201*L201+IF(O201="",0,O201)))) | Z201: =IF(OR(AE201="",多次统计数据!$B$8=""),"",AE201-多次统计数据!$B$8) | AA201: =IF(OR(I201="",M201="",M201<I201),"",M201-I201) | AB201: =IF(OR(A201="",多次统计数据!$B$8="",多次统计数据!$B$6<=0,多次统计数据!$B$6>=1),"",1-POWER(1+多次统计数据!$B$8,-多次统计数据!$B$6/(1-多次统计数据!$B$6))) | AC201: =IF(OR(AB201="",多次统计数据!$B$9=""),"",IF(多次统计数据!$B$9<AB201,"低于上限","达到或超过上限")) | AE201: =IF(OR(X201="",C201="",C201<=0),"",X201/C201) | AJ201: =IF(OR(AG201="",AH201=""),"",IF(OR(AND(AG201="短期博反弹",OR(AH201="1～3个交易日",AH201="4～10个交易日")),AND(AG201="突破冲新高",OR(AH201="4～10个交易日",AH201="11～20个交易日")),AND(AG201="趋势波段",OR(AH201="11～20个交易日",AH201="21～60个交易日",AH201="60个交易日以上"))),"匹配","周期与交易预期不匹配，请重新确认")) | AK201: =IF(A201="","",COUNTIFS(加仓管理!$A$2:$A$1001,A201,加仓管理!$G$2:$G$1001,">0")) | AL201: =IF(A201="","",SUMIFS(加仓管理!$G$2:$G$1001,加仓管理!$A$2:$A$1001,A201)) | AM201: =IF(AK201=0,"",IFERROR(LOOKUP(2,1/((加仓管理!$A$2:$A$1001=A201)*(加仓管理!$G$2:$G$1001>0)),加仓管理!$D$2:$D$1001),"")) | AN201: =IF(AK201=0,"",IFERROR(LOOKUP(2,1/((加仓管理!$A$2:$A$1001=A201)*(加仓管理!$G$2:$G$1001>0)),加仓管理!$E$2:$E$1001),"")) | AO201: =IF(OR(A201="",H201="",H201<=0),"",(E201*H201+SUMIFS(加仓管理!$H$2:$H$1001,加仓管理!$A$2:$A$1001,A201))/AP201) | AP201: =IF(OR(A201="",H201="",H201<=0),"",H201+AL201) | AQ201: =IF(A201="","",IF(M201<>"",0,IF(OR(H201="",N201=""),"",MAX((E201*H201+SUMIFS(加仓管理!$H$2:$H$1001,加仓管理!$A$2:$A$1001,A201))-MAX(N201,AN201)*AP201,0)))) | AR201: =IF(A201="","",IF(OR(E201="",H201=""),"违规：首次买入价格或股数缺失",IF(COUNTIFS(加仓管理!$A$2:$A$1001,A201,加仓管理!$R$2:$R$1001,"违规*")>0,"违规：请检查加仓管理表",IF(SUM($AQ$2:$AQ$201)>账户数据!$B$7,"预警：超过账户风险上限",IF(COUNTIFS(加仓管理!$A$2:$A$1001,A201,加仓管理!$N$2:$N$1001,">0",加仓管理!$G$2:$G$1001,"")>0,"提示：存在待执行加仓计划","通过")))))

Sheet 加仓管理
A1: 交易编号 | B1: 加仓序号(1-5) | C1: 加仓日期 | D1: 加仓价 | E1: 新止损价 | F1: 本次风险预算金额 | G1: 实际加仓股数 | H1: 本次买入金额 | I1: 加仓前持仓股数 | J1: 加仓前持仓成本 | K1: 新止损下底仓锁定利润 | L1: 风险允许股数 | M1: 金字塔上限股数 | N1: 建议加仓股数 | O1: 加仓后累计股数 | P1: 加仓后加权成本 | Q1: 加仓后止损风险 | R1: 规则检查
A2: 1 | B2: 1 | C2: 44028 | D2: 20.7 | E2: 19.5 | F2: 1 | G2: 500 | H2: =IF(OR(A2="",D2="",G2=""),"",D2*G2) -> 10350 | I2: =IF(OR(A2="",B2=""),"",IFERROR(LOOKUP(2,1/(单次交易!$A$2:$A$201=A2),单次交易!$H$2:$H$201),0)+SUMIFS($G$2:$G$1001,$A$2:$A$1001,A2,$B$2:$B$1001,"<"&B2)) -> 1100 | J2: =IF(OR(A2="",B2=""),"",IFERROR(LOOKUP(2,1/(单次交易!$A$2:$A$201=A2),单次交易!$E$2:$E$201)*LOOKUP(2,1/(单次交易!$A$2:$A$201=A2),单次交易!$H$2:$H$201),0)+SUMIFS($H$2:$H$1001,$A$2:$A$1001,A2,$B$2:$B$1001,"<"&B2)) -> 22957 | K2: =IF(OR(E2="",I2="",J2=""),"",MAX(E2*I2-J2,0)) -> 0 | L2: =IF(OR(D2="",E2="",F2="",D2<=E2),"",FLOOR((F2+K2)/(D2-E2),100)) -> 0 | M2: =IF(OR(A2="",B2="",L2=""),"",IF(B2=1,L2,IFERROR(SUMIFS($G$2:$G$1001,$A$2:$A$1001,A2,$B$2:$B$1001,B2-1),0))) -> 0 | N2: =IF(OR(L2="",M2=""),"",MIN(L2,M2)) -> 0 | O2: =IF(OR(I2="",G2=""),"",I2+G2) -> 1600 | P2: =IF(OR(O2="",O2=0),"",(J2+H2)/O2) -> 20.816875 | Q2: =IF(OR(O2="",E2=""),"",MAX(J2+H2-E2*O2,0)) -> 2107 | R2: =IF(A2="","",IF(COUNTIF(_TradeIds,A2)=0,"违规：交易编号不存在",IF(OR(B2="",B2<1,B2>5,B2<>INT(B2)),"违规：加仓序号须为1到5的整数",IF(COUNTIFS($A$2:$A$1001,A2,$B$2:$B$1001,B2)>1,"违规：同一交易的加仓序号重复",IF(OR(D2="",E2="",F2=""),"计划不完整：请填写加仓价、新止损价和风险预算",IF(OR(D2<=0,E2<=0,F2<=0,D2<=E2),"违规：加仓价必须高于新止损价，金额须大于0",IF(AND(B2>1,COUNTIFS($A$2:$A$1001,A2,$B$2:$B$1001,B2-1,$G$2:$G$1001,">0")=0),"违规：须先完成上一次加仓",IF(AND(B2>1,E2<SUMIFS($E$2:$E$1001,$A$2:$A$1001,A2,$B$2:$B$1001,B2-1)),"违规：新止损价不得低于上一次",IF(AND(B2>1,F2>SUMIFS($F$2:$F$1001,$A$2:$A$1001,A2,$B$2:$B$1001,B2-1)),"违规：风险预算须逐次不增加",IF(OR(_LockStatus="已锁仓",_LockStatus="解锁信息不完整"),"违规：锁仓期间禁止加仓",IF(G2="","计划可执行：建议股数见N列",IF(OR(G2<=0,G2<>INT(G2),MOD(G2,100)<>0),"违规：实际股数须为100股整数倍",IF(G2>N2,"违规：实际股数超过风险或金字塔上限",IF(AND(B2>1,G2>SUMIFS($G$2:$G$1001,$A$2:$A$1001,A2,$B$2:$B$1001,B2-1)),"违规：加仓股数须逐次不增加",IF(Q2>F2,"违规：止损风险超过本次预算","通过"))))))))))))))) -> 违规：实际股数超过风险或金字塔上限
A3: 1 | B3: 2 | C3: 44032 | D3: 24 | E3: 22 | F3: 1 | G3: 1000 | H3: =IF(OR(A3="",D3="",G3=""),"",D3*G3) -> 24000 | I3: =IF(OR(A3="",B3=""),"",IFERROR(LOOKUP(2,1/(单次交易!$A$2:$A$201=A3),单次交易!$H$2:$H$201),0)+SUMIFS($G$2:$G$1001,$A$2:$A$1001,A3,$B$2:$B$1001,"<"&B3)) -> 1600 | J3: =IF(OR(A3="",B3=""),"",IFERROR(LOOKUP(2,1/(单次交易!$A$2:$A$201=A3),单次交易!$E$2:$E$201)*LOOKUP(2,1/(单次交易!$A$2:$A$201=A3),单次交易!$H$2:$H$201),0)+SUMIFS($H$2:$H$1001,$A$2:$A$1001,A3,$B$2:$B$1001,"<"&B3)) -> 33307 | K3: =IF(OR(E3="",I3="",J3=""),"",MAX(E3*I3-J3,0)) -> 1893 | L3: =IF(OR(D3="",E3="",F3="",D3<=E3),"",FLOOR((F3+K3)/(D3-E3),100)) -> 900 | M3: =IF(OR(A3="",B3="",L3=""),"",IF(B3=1,L3,IFERROR(SUMIFS($G$2:$G$1001,$A$2:$A$1001,A3,$B$2:$B$1001,B3-1),0))) -> 500 | N3: =IF(OR(L3="",M3=""),"",MIN(L3,M3)) -> 500 | O3: =IF(OR(I3="",G3=""),"",I3+G3) -> 2600 | P3: =IF(OR(O3="",O3=0),"",(J3+H3)/O3) -> 22.041154 | Q3: =IF(OR(O3="",E3=""),"",MAX(J3+H3-E3*O3,0)) -> 107 | R3: =IF(A3="","",IF(COUNTIF(_TradeIds,A3)=0,"违规：交易编号不存在",IF(OR(B3="",B3<1,B3>5,B3<>INT(B3)),"违规：加仓序号须为1到5的整数",IF(COUNTIFS($A$2:$A$1001,A3,$B$2:$B$1001,B3)>1,"违规：同一交易的加仓序号重复",IF(OR(D3="",E3="",F3=""),"计划不完整：请填写加仓价、新止损价和风险预算",IF(OR(D3<=0,E3<=0,F3<=0,D3<=E3),"违规：加仓价必须高于新止损价，金额须大于0",IF(AND(B3>1,COUNTIFS($A$2:$A$1001,A3,$B$2:$B$1001,B3-1,$G$2:$G$1001,">0")=0),"违规：须先完成上一次加仓",IF(AND(B3>1,E3<SUMIFS($E$2:$E$1001,$A$2:$A$1001,A3,$B$2:$B$1001,B3-1)),"违规：新止损价不得低于上一次",IF(AND(B3>1,F3>SUMIFS($F$2:$F$1001,$A$2:$A$1001,A3,$B$2:$B$1001,B3-1)),"违规：风险预算须逐次不增加",IF(OR(_LockStatus="已锁仓",_LockStatus="解锁信息不完整"),"违规：锁仓期间禁止加仓",IF(G3="","计划可执行：建议股数见N列",IF(OR(G3<=0,G3<>INT(G3),MOD(G3,100)<>0),"违规：实际股数须为100股整数倍",IF(G3>N3,"违规：实际股数超过风险或金字塔上限",IF(AND(B3>1,G3>SUMIFS($G$2:$G$1001,$A$2:$A$1001,A3,$B$2:$B$1001,B3-1)),"违规：加仓股数须逐次不增加",IF(Q3>F3,"违规：止损风险超过本次预算","通过"))))))))))))))) -> 违规：实际股数超过风险或金字塔上限
A4: 2 | B4: 1 | C4: 44200 | D4: 19.05 | E4: 18 | F4: 1 | G4: 1000 | H4: =IF(OR(A4="",D4="",G4=""),"",D4*G4) -> 19050 | I4: =IF(OR(A4="",B4=""),"",IFERROR(LOOKUP(2,1/(单次交易!$A$2:$A$201=A4),单次交易!$H$2:$H$201),0)+SUMIFS($G$2:$G$1001,$A$2:$A$1001,A4,$B$2:$B$1001,"<"&B4)) -> 1000 | J4: =IF(OR(A4="",B4=""),"",IFERROR(LOOKUP(2,1/(单次交易!$A$2:$A$201=A4),单次交易!$E$2:$E$201)*LOOKUP(2,1/(单次交易!$A$2:$A$201=A4),单次交易!$H$2:$H$201),0)+SUMIFS($H$2:$H$1001,$A$2:$A$1001,A4,$B$2:$B$1001,"<"&B4)) -> 17880 | K4: =IF(OR(E4="",I4="",J4=""),"",MAX(E4*I4-J4,0)) -> 120 | L4: =IF(OR(D4="",E4="",F4="",D4<=E4),"",FLOOR((F4+K4)/(D4-E4),100)) -> 100 | M4: =IF(OR(A4="",B4="",L4=""),"",IF(B4=1,L4,IFERROR(SUMIFS($G$2:$G$1001,$A$2:$A$1001,A4,$B$2:$B$1001,B4-1),0))) -> 100 | N4: =IF(OR(L4="",M4=""),"",MIN(L4,M4)) -> 100 | O4: =IF(OR(I4="",G4=""),"",I4+G4) -> 2000 | P4: =IF(OR(O4="",O4=0),"",(J4+H4)/O4) -> 18.465 | Q4: =IF(OR(O4="",E4=""),"",MAX(J4+H4-E4*O4,0)) -> 930 | R4: =IF(A4="","",IF(COUNTIF(_TradeIds,A4)=0,"违规：交易编号不存在",IF(OR(B4="",B4<1,B4>5,B4<>INT(B4)),"违规：加仓序号须为1到5的整数",IF(COUNTIFS($A$2:$A$1001,A4,$B$2:$B$1001,B4)>1,"违规：同一交易的加仓序号重复",IF(OR(D4="",E4="",F4=""),"计划不完整：请填写加仓价、新止损价和风险预算",IF(OR(D4<=0,E4<=0,F4<=0,D4<=E4),"违规：加仓价必须高于新止损价，金额须大于0",IF(AND(B4>1,COUNTIFS($A$2:$A$1001,A4,$B$2:$B$1001,B4-1,$G$2:$G$1001,">0")=0),"违规：须先完成上一次加仓",IF(AND(B4>1,E4<SUMIFS($E$2:$E$1001,$A$2:$A$1001,A4,$B$2:$B$1001,B4-1)),"违规：新止损价不得低于上一次",IF(AND(B4>1,F4>SUMIFS($F$2:$F$1001,$A$2:$A$1001,A4,$B$2:$B$1001,B4-1)),"违规：风险预算须逐次不增加",IF(OR(_LockStatus="已锁仓",_LockStatus="解锁信息不完整"),"违规：锁仓期间禁止加仓",IF(G4="","计划可执行：建议股数见N列",IF(OR(G4<=0,G4<>INT(G4),MOD(G4,100)<>0),"违规：实际股数须为100股整数倍",IF(G4>N4,"违规：实际股数超过风险或金字塔上限",IF(AND(B4>1,G4>SUMIFS($G$2:$G$1001,$A$2:$A$1001,A4,$B$2:$B$1001,B4-1)),"违规：加仓股数须逐次不增加",IF(Q4>F4,"违规：止损风险超过本次预算","通过"))))))))))))))) -> 违规：实际股数超过风险或金字塔上限
A5: 2 | B5: 2 | C5: 44222 | D5: 17.21 | E5: 16.5 | F5: 1 | G5: 1000 | H5: =IF(OR(A5="",D5="",G5=""),"",D5*G5) -> 17210 | I5: =IF(OR(A5="",B5=""),"",IFERROR(LOOKUP(2,1/(单次交易!$A$2:$A$201=A5),单次交易!$H$2:$H$201),0)+SUMIFS($G$2:$G$1001,$A$2:$A$1001,A5,$B$2:$B$1001,"<"&B5)) -> 2000 | J5: =IF(OR(A5="",B5=""),"",IFERROR(LOOKUP(2,1/(单次交易!$A$2:$A$201=A5),单次交易!$E$2:$E$201)*LOOKUP(2,1/(单次交易!$A$2:$A$201=A5),单次交易!$H$2:$H$201),0)+SUMIFS($H$2:$H$1001,$A$2:$A$1001,A5,$B$2:$B$1001,"<"&B5)) -> 36930 | K5: =IF(OR(E5="",I5="",J5=""),"",MAX(E5*I5-J5,0)) -> 0 | L5: =IF(OR(D5="",E5="",F5="",D5<=E5),"",FLOOR((F5+K5)/(D5-E5),100)) -> 0 | M5: =IF(OR(A5="",B5="",L5=""),"",IF(B5=1,L5,IFERROR(SUMIFS($G$2:$G$1001,$A$2:$A$1001,A5,$B$2:$B$1001,B5-1),0))) -> 1000 | N5: =IF(OR(L5="",M5=""),"",MIN(L5,M5)) -> 0 | O5: =IF(OR(I5="",G5=""),"",I5+G5) -> 3000 | P5: =IF(OR(O5="",O5=0),"",(J5+H5)/O5) -> 18.046667 | Q5: =IF(OR(O5="",E5=""),"",MAX(J5+H5-E5*O5,0)) -> 4640 | R5: =IF(A5="","",IF(COUNTIF(_TradeIds,A5)=0,"违规：交易编号不存在",IF(OR(B5="",B5<1,B5>5,B5<>INT(B5)),"违规：加仓序号须为1到5的整数",IF(COUNTIFS($A$2:$A$1001,A5,$B$2:$B$1001,B5)>1,"违规：同一交易的加仓序号重复",IF(OR(D5="",E5="",F5=""),"计划不完整：请填写加仓价、新止损价和风险预算",IF(OR(D5<=0,E5<=0,F5<=0,D5<=E5),"违规：加仓价必须高于新止损价，金额须大于0",IF(AND(B5>1,COUNTIFS($A$2:$A$1001,A5,$B$2:$B$1001,B5-1,$G$2:$G$1001,">0")=0),"违规：须先完成上一次加仓",IF(AND(B5>1,E5<SUMIFS($E$2:$E$1001,$A$2:$A$1001,A5,$B$2:$B$1001,B5-1)),"违规：新止损价不得低于上一次",IF(AND(B5>1,F5>SUMIFS($F$2:$F$1001,$A$2:$A$1001,A5,$B$2:$B$1001,B5-1)),"违规：风险预算须逐次不增加",IF(OR(_LockStatus="已锁仓",_LockStatus="解锁信息不完整"),"违规：锁仓期间禁止加仓",IF(G5="","计划可执行：建议股数见N列",IF(OR(G5<=0,G5<>INT(G5),MOD(G5,100)<>0),"违规：实际股数须为100股整数倍",IF(G5>N5,"违规：实际股数超过风险或金字塔上限",IF(AND(B5>1,G5>SUMIFS($G$2:$G$1001,$A$2:$A$1001,A5,$B$2:$B$1001,B5-1)),"违规：加仓股数须逐次不增加",IF(Q5>F5,"违规：止损风险超过本次预算","通过"))))))))))))))) -> 违规：新止损价不得低于上一次
A6: 3 | B6: 1 | C6: 44295 | D6: 17.3 | E6: 16.5 | F6: 1 | G6: 1000 | H6: =IF(OR(A6="",D6="",G6=""),"",D6*G6) -> 17300 | I6: =IF(OR(A6="",B6=""),"",IFERROR(LOOKUP(2,1/(单次交易!$A$2:$A$201=A6),单次交易!$H$2:$H$201),0)+SUMIFS($G$2:$G$1001,$A$2:$A$1001,A6,$B$2:$B$1001,"<"&B6)) -> 2900 | J6: =IF(OR(A6="",B6=""),"",IFERROR(LOOKUP(2,1/(单次交易!$A$2:$A$201=A6),单次交易!$E$2:$E$201)*LOOKUP(2,1/(单次交易!$A$2:$A$201=A6),单次交易!$H$2:$H$201),0)+SUMIFS($H$2:$H$1001,$A$2:$A$1001,A6,$B$2:$B$1001,"<"&B6)) -> 43848 | K6: =IF(OR(E6="",I6="",J6=""),"",MAX(E6*I6-J6,0)) -> 4002 | L6: =IF(OR(D6="",E6="",F6="",D6<=E6),"",FLOOR((F6+K6)/(D6-E6),100)) -> 5000 | M6: =IF(OR(A6="",B6="",L6=""),"",IF(B6=1,L6,IFERROR(SUMIFS($G$2:$G$1001,$A$2:$A$1001,A6,$B$2:$B$1001,B6-1),0))) -> 5000 | N6: =IF(OR(L6="",M6=""),"",MIN(L6,M6)) -> 5000 | O6: =IF(OR(I6="",G6=""),"",I6+G6) -> 3900 | P6: =IF(OR(O6="",O6=0),"",(J6+H6)/O6) -> 15.678974 | Q6: =IF(OR(O6="",E6=""),"",MAX(J6+H6-E6*O6,0)) -> 0 | R6: =IF(A6="","",IF(COUNTIF(_TradeIds,A6)=0,"违规：交易编号不存在",IF(OR(B6="",B6<1,B6>5,B6<>INT(B6)),"违规：加仓序号须为1到5的整数",IF(COUNTIFS($A$2:$A$1001,A6,$B$2:$B$1001,B6)>1,"违规：同一交易的加仓序号重复",IF(OR(D6="",E6="",F6=""),"计划不完整：请填写加仓价、新止损价和风险预算",IF(OR(D6<=0,E6<=0,F6<=0,D6<=E6),"违规：加仓价必须高于新止损价，金额须大于0",IF(AND(B6>1,COUNTIFS($A$2:$A$1001,A6,$B$2:$B$1001,B6-1,$G$2:$G$1001,">0")=0),"违规：须先完成上一次加仓",IF(AND(B6>1,E6<SUMIFS($E$2:$E$1001,$A$2:$A$1001,A6,$B$2:$B$1001,B6-1)),"违规：新止损价不得低于上一次",IF(AND(B6>1,F6>SUMIFS($F$2:$F$1001,$A$2:$A$1001,A6,$B$2:$B$1001,B6-1)),"违规：风险预算须逐次不增加",IF(OR(_LockStatus="已锁仓",_LockStatus="解锁信息不完整"),"违规：锁仓期间禁止加仓",IF(G6="","计划可执行：建议股数见N列",IF(OR(G6<=0,G6<>INT(G6),MOD(G6,100)<>0),"违规：实际股数须为100股整数倍",IF(G6>N6,"违规：实际股数超过风险或金字塔上限",IF(AND(B6>1,G6>SUMIFS($G$2:$G$1001,$A$2:$A$1001,A6,$B$2:$B$1001,B6-1)),"违规：加仓股数须逐次不增加",IF(Q6>F6,"违规：止损风险超过本次预算","通过"))))))))))))))) -> 通过
A7: 3 | B7: 2 | C7: 44302 | D7: 18.35 | E7: 17 | F7: 1 | G7: 500 | H7: =IF(OR(A7="",D7="",G7=""),"",D7*G7) -> 9175 | I7: =IF(OR(A7="",B7=""),"",IFERROR(LOOKUP(2,1/(单次交易!$A$2:$A$201=A7),单次交易!$H$2:$H$201),0)+SUMIFS($G$2:$G$1001,$A$2:$A$1001,A7,$B$2:$B$1001,"<"&B7)) -> 3900 | J7: =IF(OR(A7="",B7=""),"",IFERROR(LOOKUP(2,1/(单次交易!$A$2:$A$201=A7),单次交易!$E$2:$E$201)*LOOKUP(2,1/(单次交易!$A$2:$A$201=A7),单次交易!$H$2:$H$201),0)+SUMIFS($H$2:$H$1001,$A$2:$A$1001,A7,$B$2:$B$1001,"<"&B7)) -> 61148 | K7: =IF(OR(E7="",I7="",J7=""),"",MAX(E7*I7-J7,0)) -> 5152 | L7: =IF(OR(D7="",E7="",F7="",D7<=E7),"",FLOOR((F7+K7)/(D7-E7),100)) -> 3800 | M7: =IF(OR(A7="",B7="",L7=""),"",IF(B7=1,L7,IFERROR(SUMIFS($G$2:$G$1001,$A$2:$A$1001,A7,$B$2:$B$1001,B7-1),0))) -> 1000 | N7: =IF(OR(L7="",M7=""),"",MIN(L7,M7)) -> 1000 | O7: =IF(OR(I7="",G7=""),"",I7+G7) -> 4400 | P7: =IF(OR(O7="",O7=0),"",(J7+H7)/O7) -> 15.9825 | Q7: =IF(OR(O7="",E7=""),"",MAX(J7+H7-E7*O7,0)) -> 0 | R7: =IF(A7="","",IF(COUNTIF(_TradeIds,A7)=0,"违规：交易编号不存在",IF(OR(B7="",B7<1,B7>5,B7<>INT(B7)),"违规：加仓序号须为1到5的整数",IF(COUNTIFS($A$2:$A$1001,A7,$B$2:$B$1001,B7)>1,"违规：同一交易的加仓序号重复",IF(OR(D7="",E7="",F7=""),"计划不完整：请填写加仓价、新止损价和风险预算",IF(OR(D7<=0,E7<=0,F7<=0,D7<=E7),"违规：加仓价必须高于新止损价，金额须大于0",IF(AND(B7>1,COUNTIFS($A$2:$A$1001,A7,$B$2:$B$1001,B7-1,$G$2:$G$1001,">0")=0),"违规：须先完成上一次加仓",IF(AND(B7>1,E7<SUMIFS($E$2:$E$1001,$A$2:$A$1001,A7,$B$2:$B$1001,B7-1)),"违规：新止损价不得低于上一次",IF(AND(B7>1,F7>SUMIFS($F$2:$F$1001,$A$2:$A$1001,A7,$B$2:$B$1001,B7-1)),"违规：风险预算须逐次不增加",IF(OR(_LockStatus="已锁仓",_LockStatus="解锁信息不完整"),"违规：锁仓期间禁止加仓",IF(G7="","计划可执行：建议股数见N列",IF(OR(G7<=0,G7<>INT(G7),MOD(G7,100)<>0),"违规：实际股数须为100股整数倍",IF(G7>N7,"违规：实际股数超过风险或金字塔上限",IF(AND(B7>1,G7>SUMIFS($G$2:$G$1001,$A$2:$A$1001,A7,$B$2:$B$1001,B7-1)),"违规：加仓股数须逐次不增加",IF(Q7>F7,"违规：止损风险超过本次预算","通过"))))))))))))))) -> 通过
A8: 3 | B8: 3 | C8: 44316 | D8: 15.42 | E8: 14.81 | F8: 1 | G8: 1300 | H8: =IF(OR(A8="",D8="",G8=""),"",D8*G8) -> 20046 | I8: =IF(OR(A8="",B8=""),"",IFERROR(LOOKUP(2,1/(单次交易!$A$2:$A$201=A8),单次交易!$H$2:$H$201),0)+SUMIFS($G$2:$G$1001,$A$2:$A$1001,A8,$B$2:$B$1001,"<"&B8)) -> 4400 | J8: =IF(OR(A8="",B8=""),"",IFERROR(LOOKUP(2,1/(单次交易!$A$2:$A$201=A8),单次交易!$E$2:$E$201)*LOOKUP(2,1/(单次交易!$A$2:$A$201=A8),单次交易!$H$2:$H$201),0)+SUMIFS($H$2:$H$1001,$A$2:$A$1001,A8,$B$2:$B$1001,"<"&B8)) -> 70323 | K8: =IF(OR(E8="",I8="",J8=""),"",MAX(E8*I8-J8,0)) -> 0 | L8: =IF(OR(D8="",E8="",F8="",D8<=E8),"",FLOOR((F8+K8)/(D8-E8),100)) -> 0 | M8: =IF(OR(A8="",B8="",L8=""),"",IF(B8=1,L8,IFERROR(SUMIFS($G$2:$G$1001,$A$2:$A$1001,A8,$B$2:$B$1001,B8-1),0))) -> 500 | N8: =IF(OR(L8="",M8=""),"",MIN(L8,M8)) -> 0 | O8: =IF(OR(I8="",G8=""),"",I8+G8) -> 5700 | P8: =IF(OR(O8="",O8=0),"",(J8+H8)/O8) -> 15.854211 | Q8: =IF(OR(O8="",E8=""),"",MAX(J8+H8-E8*O8,0)) -> 5952 | R8: =IF(A8="","",IF(COUNTIF(_TradeIds,A8)=0,"违规：交易编号不存在",IF(OR(B8="",B8<1,B8>5,B8<>INT(B8)),"违规：加仓序号须为1到5的整数",IF(COUNTIFS($A$2:$A$1001,A8,$B$2:$B$1001,B8)>1,"违规：同一交易的加仓序号重复",IF(OR(D8="",E8="",F8=""),"计划不完整：请填写加仓价、新止损价和风险预算",IF(OR(D8<=0,E8<=0,F8<=0,D8<=E8),"违规：加仓价必须高于新止损价，金额须大于0",IF(AND(B8>1,COUNTIFS($A$2:$A$1001,A8,$B$2:$B$1001,B8-1,$G$2:$G$1001,">0")=0),"违规：须先完成上一次加仓",IF(AND(B8>1,E8<SUMIFS($E$2:$E$1001,$A$2:$A$1001,A8,$B$2:$B$1001,B8-1)),"违规：新止损价不得低于上一次",IF(AND(B8>1,F8>SUMIFS($F$2:$F$1001,$A$2:$A$1001,A8,$B$2:$B$1001,B8-1)),"违规：风险预算须逐次不增加",IF(OR(_LockStatus="已锁仓",_LockStatus="解锁信息不完整"),"违规：锁仓期间禁止加仓",IF(G8="","计划可执行：建议股数见N列",IF(OR(G8<=0,G8<>INT(G8),MOD(G8,100)<>0),"违规：实际股数须为100股整数倍",IF(G8>N8,"违规：实际股数超过风险或金字塔上限",IF(AND(B8>1,G8>SUMIFS($G$2:$G$1001,$A$2:$A$1001,A8,$B$2:$B$1001,B8-1)),"违规：加仓股数须逐次不增加",IF(Q8>F8,"违规：止损风险超过本次预算","通过"))))))))))))))) -> 违规：新止损价不得低于上一次
A9: 4 | B9: 1 | C9: 44440 | D9: 17.2 | E9: 16.5 | F9: 1 | G9: 1000 | H9: =IF(OR(A9="",D9="",G9=""),"",D9*G9) -> 17200 | I9: =IF(OR(A9="",B9=""),"",IFERROR(LOOKUP(2,1/(单次交易!$A$2:$A$201=A9),单次交易!$H$2:$H$201),0)+SUMIFS($G$2:$G$1001,$A$2:$A$1001,A9,$B$2:$B$1001,"<"&B9)) -> 2500 | J9: =IF(OR(A9="",B9=""),"",IFERROR(LOOKUP(2,1/(单次交易!$A$2:$A$201=A9),单次交易!$E$2:$E$201)*LOOKUP(2,1/(单次交易!$A$2:$A$201=A9),单次交易!$H$2:$H$201),0)+SUMIFS($H$2:$H$1001,$A$2:$A$1001,A9,$B$2:$B$1001,"<"&B9)) -> 39050 | K9: =IF(OR(E9="",I9="",J9=""),"",MAX(E9*I9-J9,0)) -> 2200 | L9: =IF(OR(D9="",E9="",F9="",D9<=E9),"",FLOOR((F9+K9)/(D9-E9),100)) -> 3100 | M9: =IF(OR(A9="",B9="",L9=""),"",IF(B9=1,L9,IFERROR(SUMIFS($G$2:$G$1001,$A$2:$A$1001,A9,$B$2:$B$1001,B9-1),0))) -> 3100 | N9: =IF(OR(L9="",M9=""),"",MIN(L9,M9)) -> 3100 | O9: =IF(OR(I9="",G9=""),"",I9+G9) -> 3500 | P9: =IF(OR(O9="",O9=0),"",(J9+H9)/O9) -> 16.071429 | Q9: =IF(OR(O9="",E9=""),"",MAX(J9+H9-E9*O9,0)) -> 0 | R9: =IF(A9="","",IF(COUNTIF(_TradeIds,A9)=0,"违规：交易编号不存在",IF(OR(B9="",B9<1,B9>5,B9<>INT(B9)),"违规：加仓序号须为1到5的整数",IF(COUNTIFS($A$2:$A$1001,A9,$B$2:$B$1001,B9)>1,"违规：同一交易的加仓序号重复",IF(OR(D9="",E9="",F9=""),"计划不完整：请填写加仓价、新止损价和风险预算",IF(OR(D9<=0,E9<=0,F9<=0,D9<=E9),"违规：加仓价必须高于新止损价，金额须大于0",IF(AND(B9>1,COUNTIFS($A$2:$A$1001,A9,$B$2:$B$1001,B9-1,$G$2:$G$1001,">0")=0),"违规：须先完成上一次加仓",IF(AND(B9>1,E9<SUMIFS($E$2:$E$1001,$A$2:$A$1001,A9,$B$2:$B$1001,B9-1)),"违规：新止损价不得低于上一次",IF(AND(B9>1,F9>SUMIFS($F$2:$F$1001,$A$2:$A$1001,A9,$B$2:$B$1001,B9-1)),"违规：风险预算须逐次不增加",IF(OR(_LockStatus="已锁仓",_LockStatus="解锁信息不完整"),"违规：锁仓期间禁止加仓",IF(G9="","计划可执行：建议股数见N列",IF(OR(G9<=0,G9<>INT(G9),MOD(G9,100)<>0),"违规：实际股数须为100股整数倍",IF(G9>N9,"违规：实际股数超过风险或金字塔上限",IF(AND(B9>1,G9>SUMIFS($G$2:$G$1001,$A$2:$A$1001,A9,$B$2:$B$1001,B9-1)),"违规：加仓股数须逐次不增加",IF(Q9>F9,"违规：止损风险超过本次预算","通过"))))))))))))))) -> 通过
A10: 4 | B10: 2 | C10: 44449 | D10: 16.88 | E10: 16 | F10: 1 | G10: 1000 | H10: =IF(OR(A10="",D10="",G10=""),"",D10*G10) -> 16880 | I10: =IF(OR(A10="",B10=""),"",IFERROR(LOOKUP(2,1/(单次交易!$A$2:$A$201=A10),单次交易!$H$2:$H$201),0)+SUMIFS($G$2:$G$1001,$A$2:$A$1001,A10,$B$2:$B$1001,"<"&B10)) -> 3500 | J10: =IF(OR(A10="",B10=""),"",IFERROR(LOOKUP(2,1/(单次交易!$A$2:$A$201=A10),单次交易!$E$2:$E$201)*LOOKUP(2,1/(单次交易!$A$2:$A$201=A10),单次交易!$H$2:$H$201),0)+SUMIFS($H$2:$H$1001,$A$2:$A$1001,A10,$B$2:$B$1001,"<"&B10)) -> 56250 | K10: =IF(OR(E10="",I10="",J10=""),"",MAX(E10*I10-J10,0)) -> 0 | L10: =IF(OR(D10="",E10="",F10="",D10<=E10),"",FLOOR((F10+K10)/(D10-E10),100)) -> 0 | M10: =IF(OR(A10="",B10="",L10=""),"",IF(B10=1,L10,IFERROR(SUMIFS($G$2:$G$1001,$A$2:$A$1001,A10,$B$2:$B$1001,B10-1),0))) -> 1000 | N10: =IF(OR(L10="",M10=""),"",MIN(L10,M10)) -> 0 | O10: =IF(OR(I10="",G10=""),"",I10+G10) -> 4500 | P10: =IF(OR(O10="",O10=0),"",(J10+H10)/O10) -> 16.251111 | Q10: =IF(OR(O10="",E10=""),"",MAX(J10+H10-E10*O10,0)) -> 1130 | R10: =IF(A10="","",IF(COUNTIF(_TradeIds,A10)=0,"违规：交易编号不存在",IF(OR(B10="",B10<1,B10>5,B10<>INT(B10)),"违规：加仓序号须为1到5的整数",IF(COUNTIFS($A$2:$A$1001,A10,$B$2:$B$1001,B10)>1,"违规：同一交易的加仓序号重复",IF(OR(D10="",E10="",F10=""),"计划不完整：请填写加仓价、新止损价和风险预算",IF(OR(D10<=0,E10<=0,F10<=0,D10<=E10),"违规：加仓价必须高于新止损价，金额须大于0",IF(AND(B10>1,COUNTIFS($A$2:$A$1001,A10,$B$2:$B$1001,B10-1,$G$2:$G$1001,">0")=0),"违规：须先完成上一次加仓",IF(AND(B10>1,E10<SUMIFS($E$2:$E$1001,$A$2:$A$1001,A10,$B$2:$B$1001,B10-1)),"违规：新止损价不得低于上一次",IF(AND(B10>1,F10>SUMIFS($F$2:$F$1001,$A$2:$A$1001,A10,$B$2:$B$1001,B10-1)),"违规：风险预算须逐次不增加",IF(OR(_LockStatus="已锁仓",_LockStatus="解锁信息不完整"),"违规：锁仓期间禁止加仓",IF(G10="","计划可执行：建议股数见N列",IF(OR(G10<=0,G10<>INT(G10),MOD(G10,100)<>0),"违规：实际股数须为100股整数倍",IF(G10>N10,"违规：实际股数超过风险或金字塔上限",IF(AND(B10>1,G10>SUMIFS($G$2:$G$1001,$A$2:$A$1001,A10,$B$2:$B$1001,B10-1)),"违规：加仓股数须逐次不增加",IF(Q10>F10,"违规：止损风险超过本次预算","通过"))))))))))))))) -> 违规：新止损价不得低于上一次
A11: 4 | B11: 3 | C11: 44453 | D11: 16.08 | E11: 16 | F11: 1 | G11: 400 | H11: =IF(OR(A11="",D11="",G11=""),"",D11*G11) -> 6432 | I11: =IF(OR(A11="",B11=""),"",IFERROR(LOOKUP(2,1/(单次交易!$A$2:$A$201=A11),单次交易!$H$2:$H$201),0)+SUMIFS($G$2:$G$1001,$A$2:$A$1001,A11,$B$2:$B$1001,"<"&B11)) -> 4500 | J11: =IF(OR(A11="",B11=""),"",IFERROR(LOOKUP(2,1/(单次交易!$A$2:$A$201=A11),单次交易!$E$2:$E$201)*LOOKUP(2,1/(单次交易!$A$2:$A$201=A11),单次交易!$H$2:$H$201),0)+SUMIFS($H$2:$H$1001,$A$2:$A$1001,A11,$B$2:$B$1001,"<"&B11)) -> 73130 | K11: =IF(OR(E11="",I11="",J11=""),"",MAX(E11*I11-J11,0)) -> 0 | L11: =IF(OR(D11="",E11="",F11="",D11<=E11),"",FLOOR((F11+K11)/(D11-E11),100)) -> 0 | M11: =IF(OR(A11="",B11="",L11=""),"",IF(B11=1,L11,IFERROR(SUMIFS($G$2:$G$1001,$A$2:$A$1001,A11,$B$2:$B$1001,B11-1),0))) -> 1000 | N11: =IF(OR(L11="",M11=""),"",MIN(L11,M11)) -> 0 | O11: =IF(OR(I11="",G11=""),"",I11+G11) -> 4900 | P11: =IF(OR(O11="",O11=0),"",(J11+H11)/O11) -> 16.237143 | Q11: =IF(OR(O11="",E11=""),"",MAX(J11+H11-E11*O11,0)) -> 1162 | R11: =IF(A11="","",IF(COUNTIF(_TradeIds,A11)=0,"违规：交易编号不存在",IF(OR(B11="",B11<1,B11>5,B11<>INT(B11)),"违规：加仓序号须为1到5的整数",IF(COUNTIFS($A$2:$A$1001,A11,$B$2:$B$1001,B11)>1,"违规：同一交易的加仓序号重复",IF(OR(D11="",E11="",F11=""),"计划不完整：请填写加仓价、新止损价和风险预算",IF(OR(D11<=0,E11<=0,F11<=0,D11<=E11),"违规：加仓价必须高于新止损价，金额须大于0",IF(AND(B11>1,COUNTIFS($A$2:$A$1001,A11,$B$2:$B$1001,B11-1,$G$2:$G$1001,">0")=0),"违规：须先完成上一次加仓",IF(AND(B11>1,E11<SUMIFS($E$2:$E$1001,$A$2:$A$1001,A11,$B$2:$B$1001,B11-1)),"违规：新止损价不得低于上一次",IF(AND(B11>1,F11>SUMIFS($F$2:$F$1001,$A$2:$A$1001,A11,$B$2:$B$1001,B11-1)),"违规：风险预算须逐次不增加",IF(OR(_LockStatus="已锁仓",_LockStatus="解锁信息不完整"),"违规：锁仓期间禁止加仓",IF(G11="","计划可执行：建议股数见N列",IF(OR(G11<=0,G11<>INT(G11),MOD(G11,100)<>0),"违规：实际股数须为100股整数倍",IF(G11>N11,"违规：实际股数超过风险或金字塔上限",IF(AND(B11>1,G11>SUMIFS($G$2:$G$1001,$A$2:$A$1001,A11,$B$2:$B$1001,B11-1)),"违规：加仓股数须逐次不增加",IF(Q11>F11,"违规：止损风险超过本次预算","通过"))))))))))))))) -> 违规：实际股数超过风险或金字塔上限
A12: 5 | B12: 1 | C12: 44826 | D12: 12.39 | E12: 11.5 | F12: 1 | G12: 1000 | H12: =IF(OR(A12="",D12="",G12=""),"",D12*G12) -> 12390 | I12: =IF(OR(A12="",B12=""),"",IFERROR(LOOKUP(2,1/(单次交易!$A$2:$A$201=A12),单次交易!$H$2:$H$201),0)+SUMIFS($G$2:$G$1001,$A$2:$A$1001,A12,$B$2:$B$1001,"<"&B12)) -> 1700 | J12: =IF(OR(A12="",B12=""),"",IFERROR(LOOKUP(2,1/(单次交易!$A$2:$A$201=A12),单次交易!$E$2:$E$201)*LOOKUP(2,1/(单次交易!$A$2:$A$201=A12),单次交易!$H$2:$H$201),0)+SUMIFS($H$2:$H$1001,$A$2:$A$1001,A12,$B$2:$B$1001,"<"&B12)) -> 18003 | K12: =IF(OR(E12="",I12="",J12=""),"",MAX(E12*I12-J12,0)) -> 1547 | L12: =IF(OR(D12="",E12="",F12="",D12<=E12),"",FLOOR((F12+K12)/(D12-E12),100)) -> 1700 | M12: =IF(OR(A12="",B12="",L12=""),"",IF(B12=1,L12,IFERROR(SUMIFS($G$2:$G$1001,$A$2:$A$1001,A12,$B$2:$B$1001,B12-1),0))) -> 1700 | N12: =IF(OR(L12="",M12=""),"",MIN(L12,M12)) -> 1700 | O12: =IF(OR(I12="",G12=""),"",I12+G12) -> 2700 | P12: =IF(OR(O12="",O12=0),"",(J12+H12)/O12) -> 11.256667 | Q12: =IF(OR(O12="",E12=""),"",MAX(J12+H12-E12*O12,0)) -> 0 | R12: =IF(A12="","",IF(COUNTIF(_TradeIds,A12)=0,"违规：交易编号不存在",IF(OR(B12="",B12<1,B12>5,B12<>INT(B12)),"违规：加仓序号须为1到5的整数",IF(COUNTIFS($A$2:$A$1001,A12,$B$2:$B$1001,B12)>1,"违规：同一交易的加仓序号重复",IF(OR(D12="",E12="",F12=""),"计划不完整：请填写加仓价、新止损价和风险预算",IF(OR(D12<=0,E12<=0,F12<=0,D12<=E12),"违规：加仓价必须高于新止损价，金额须大于0",IF(AND(B12>1,COUNTIFS($A$2:$A$1001,A12,$B$2:$B$1001,B12-1,$G$2:$G$1001,">0")=0),"违规：须先完成上一次加仓",IF(AND(B12>1,E12<SUMIFS($E$2:$E$1001,$A$2:$A$1001,A12,$B$2:$B$1001,B12-1)),"违规：新止损价不得低于上一次",IF(AND(B12>1,F12>SUMIFS($F$2:$F$1001,$A$2:$A$1001,A12,$B$2:$B$1001,B12-1)),"违规：风险预算须逐次不增加",IF(OR(_LockStatus="已锁仓",_LockStatus="解锁信息不完整"),"违规：锁仓期间禁止加仓",IF(G12="","计划可执行：建议股数见N列",IF(OR(G12<=0,G12<>INT(G12),MOD(G12,100)<>0),"违规：实际股数须为100股整数倍",IF(G12>N12,"违规：实际股数超过风险或金字塔上限",IF(AND(B12>1,G12>SUMIFS($G$2:$G$1001,$A$2:$A$1001,A12,$B$2:$B$1001,B12-1)),"违规：加仓股数须逐次不增加",IF(Q12>F12,"违规：止损风险超过本次预算","通过"))))))))))))))) -> 通过
A13: 5 | B13: 2 | C13: 44825 | D13: 10.66 | E13: 10 | F13: 1 | G13: 2000 | H13: =IF(OR(A13="",D13="",G13=""),"",D13*G13) -> 21320 | I13: =IF(OR(A13="",B13=""),"",IFERROR(LOOKUP(2,1/(单次交易!$A$2:$A$201=A13),单次交易!$H$2:$H$201),0)+SUMIFS($G$2:$G$1001,$A$2:$A$1001,A13,$B$2:$B$1001,"<"&B13)) -> 2700 | J13: =IF(OR(A13="",B13=""),"",IFERROR(LOOKUP(2,1/(单次交易!$A$2:$A$201=A13),单次交易!$E$2:$E$201)*LOOKUP(2,1/(单次交易!$A$2:$A$201=A13),单次交易!$H$2:$H$201),0)+SUMIFS($H$2:$H$1001,$A$2:$A$1001,A13,$B$2:$B$1001,"<"&B13)) -> 30393 | K13: =IF(OR(E13="",I13="",J13=""),"",MAX(E13*I13-J13,0)) -> 0 | L13: =IF(OR(D13="",E13="",F13="",D13<=E13),"",FLOOR((F13+K13)/(D13-E13),100)) -> 0 | M13: =IF(OR(A13="",B13="",L13=""),"",IF(B13=1,L13,IFERROR(SUMIFS($G$2:$G$1001,$A$2:$A$1001,A13,$B$2:$B$1001,B13-1),0))) -> 1000 | N13: =IF(OR(L13="",M13=""),"",MIN(L13,M13)) -> 0 | O13: =IF(OR(I13="",G13=""),"",I13+G13) -> 4700 | P13: =IF(OR(O13="",O13=0),"",(J13+H13)/O13) -> 11.002766 | Q13: =IF(OR(O13="",E13=""),"",MAX(J13+H13-E13*O13,0)) -> 4713 | R13: =IF(A13="","",IF(COUNTIF(_TradeIds,A13)=0,"违规：交易编号不存在",IF(OR(B13="",B13<1,B13>5,B13<>INT(B13)),"违规：加仓序号须为1到5的整数",IF(COUNTIFS($A$2:$A$1001,A13,$B$2:$B$1001,B13)>1,"违规：同一交易的加仓序号重复",IF(OR(D13="",E13="",F13=""),"计划不完整：请填写加仓价、新止损价和风险预算",IF(OR(D13<=0,E13<=0,F13<=0,D13<=E13),"违规：加仓价必须高于新止损价，金额须大于0",IF(AND(B13>1,COUNTIFS($A$2:$A$1001,A13,$B$2:$B$1001,B13-1,$G$2:$G$1001,">0")=0),"违规：须先完成上一次加仓",IF(AND(B13>1,E13<SUMIFS($E$2:$E$1001,$A$2:$A$1001,A13,$B$2:$B$1001,B13-1)),"违规：新止损价不得低于上一次",IF(AND(B13>1,F13>SUMIFS($F$2:$F$1001,$A$2:$A$1001,A13,$B$2:$B$1001,B13-1)),"违规：风险预算须逐次不增加",IF(OR(_LockStatus="已锁仓",_LockStatus="解锁信息不完整"),"违规：锁仓期间禁止加仓",IF(G13="","计划可执行：建议股数见N列",IF(OR(G13<=0,G13<>INT(G13),MOD(G13,100)<>0),"违规：实际股数须为100股整数倍",IF(G13>N13,"违规：实际股数超过风险或金字塔上限",IF(AND(B13>1,G13>SUMIFS($G$2:$G$1001,$A$2:$A$1001,A13,$B$2:$B$1001,B13-1)),"违规：加仓股数须逐次不增加",IF(Q13>F13,"违规：止损风险超过本次预算","通过"))))))))))))))) -> 违规：新止损价不得低于上一次
... A131: 131 | B131: 1 | C131: 45447 | D131: 42.5 | E131: 40 | F131: 1 | G131: 3000 | H131: =IF(OR(A131="",D131="",G131=""),"",D131*G131) -> 127500 | I131: =IF(OR(A131="",B131=""),"",IFERROR(LOOKUP(2,1/(单次交易!$A$2:$A$201=A131),单次交易!$H$2:$H$201),0)+SUMIFS($G$2:$G$1001,$A$2:$A$1001,A131,$B$2:$B$1001,"<"&B131)) -> 5400 | J131: =IF(OR(A131="",B131=""),"",IFERROR(LOOKUP(2,1/(单次交易!$A$2:$A$201=A131),单次交易!$E$2:$E$201)*LOOKUP(2,1/(单次交易!$A$2:$A$201=A131),单次交易!$H$2:$H$201),0)+SUMIFS($H$2:$H$1001,$A$2:$A$1001,A131,$B$2:$B$1001,"<"&B131)) -> 213678 | K131: =IF(OR(E131="",I131="",J131=""),"",MAX(E131*I131-J131,0)) -> 2322 | L131: =IF(OR(D131="",E131="",F131="",D131<=E131),"",FLOOR((F131+K131)/(D131-E131),100)) -> 900 | M131: =IF(OR(A131="",B131="",L131=""),"",IF(B131=1,L131,IFERROR(SUMIFS($G$2:$G$1001,$A$2:$A$1001,A131,$B$2:$B$1001,B131-1),0))) -> 900 | N131: =IF(OR(L131="",M131=""),"",MIN(L131,M131)) -> 900 | O131: =IF(OR(I131="",G131=""),"",I131+G131) -> 8400 | P131: =IF(OR(O131="",O131=0),"",(J131+H131)/O131) -> 40.616429 | Q131: =IF(OR(O131="",E131=""),"",MAX(J131+H131-E131*O131,0)) -> 5178 | R131: =IF(A131="","",IF(COUNTIF(_TradeIds,A131)=0,"违规：交易编号不存在",IF(OR(B131="",B131<1,B131>5,B131<>INT(B131)),"违规：加仓序号须为1到5的整数",IF(COUNTIFS($A$2:$A$1001,A131,$B$2:$B$1001,B131)>1,"违规：同一交易的加仓序号重复",IF(OR(D131="",E131="",F131=""),"计划不完整：请填写加仓价、新止损价和风险预算",IF(OR(D131<=0,E131<=0,F131<=0,D131<=E131),"违规：加仓价必须高于新止损价，金额须大于0",IF(AND(B131>1,COUNTIFS($A$2:$A$1001,A131,$B$2:$B$1001,B131-1,$G$2:$G$1001,">0")=0),"违规：须先完成上一次加仓",IF(AND(B131>1,E131<SUMIFS($E$2:$E$1001,$A$2:$A$1001,A131,$B$2:$B$1001,B131-1)),"违规：新止损价不得低于上一次",IF(AND(B131>1,F131>SUMIFS($F$2:$F$1001,$A$2:$A$1001,A131,$B$2:$B$1001,B131-1)),"违规：风险预算须逐次不增加",IF(OR(_LockStatus="已锁仓",_LockStatus="解锁信息不完整"),"违规：锁仓期间禁止加仓",IF(G131="","计划可执行：建议股数见N列",IF(OR(G131<=0,G131<>INT(G131),MOD(G131,100)<>0),"违规：实际股数须为100股整数倍",IF(G131>N131,"违规：实际股数超过风险或金字塔上限",IF(AND(B131>1,G131>SUMIFS($G$2:$G$1001,$A$2:$A$1001,A131,$B$2:$B$1001,B131-1)),"违规：加仓股数须逐次不增加",IF(Q131>F131,"违规：止损风险超过本次预算","通过"))))))))))))))) -> 违规：实际股数超过风险或金字塔上限
H132: =IF(OR(A132="",D132="",G132=""),"",D132*G132) | I132: =IF(OR(A132="",B132=""),"",IFERROR(LOOKUP(2,1/(单次交易!$A$2:$A$201=A132),单次交易!$H$2:$H$201),0)+SUMIFS($G$2:$G$1001,$A$2:$A$1001,A132,$B$2:$B$1001,"<"&B132)) | J132: =IF(OR(A132="",B132=""),"",IFERROR(LOOKUP(2,1/(单次交易!$A$2:$A$201=A132),单次交易!$E$2:$E$201)*LOOKUP(2,1/(单次交易!$A$2:$A$201=A132),单次交易!$H$2:$H$201),0)+SUMIFS($H$2:$H$1001,$A$2:$A$1001,A132,$B$2:$B$1001,"<"&B132)) | K132: =IF(OR(E132="",I132="",J132=""),"",MAX(E132*I132-J132,0)) | L132: =IF(OR(D132="",E132="",F132="",D132<=E132),"",FLOOR((F132+K132)/(D132-E132),100)) | M132: =IF(OR(A132="",B132="",L132=""),"",IF(B132=1,L132,IFERROR(SUMIFS($G$2:$G$1001,$A$2:$A$1001,A132,$B$2:$B$1001,B132-1),0))) | N132: =IF(OR(L132="",M132=""),"",MIN(L132,M132)) | O132: =IF(OR(I132="",G132=""),"",I132+G132) | P132: =IF(OR(O132="",O132=0),"",(J132+H132)/O132) | Q132: =IF(OR(O132="",E132=""),"",MAX(J132+H132-E132*O132,0)) | R132: =IF(A132="","",IF(COUNTIF(_TradeIds,A132)=0,"违规：交易编号不存在",IF(OR(B132="",B132<1,B132>5,B132<>INT(B132)),"违规：加仓序号须为1到5的整数",IF(COUNTIFS($A$2:$A$1001,A132,$B$2:$B$1001,B132)>1,"违规：同一交易的加仓序号重复",IF(OR(D132="",E132="",F132=""),"计划不完整：请填写加仓价、新止损价和风险预算",IF(OR(D132<=0,E132<=0,F132<=0,D132<=E132),"违规：加仓价必须高于新止损价，金额须大于0",IF(AND(B132>1,COUNTIFS($A$2:$A$1001,A132,$B$2:$B$1001,B132-1,$G$2:$G$1001,">0")=0),"违规：须先完成上一次加仓",IF(AND(B132>1,E132<SUMIFS($E$2:$E$1001,$A$2:$A$1001,A132,$B$2:$B$1001,B132-1)),"违规：新止损价不得低于上一次",IF(AND(B132>1,F132>SUMIFS($F$2:$F$1001,$A$2:$A$1001,A132,$B$2:$B$1001,B132-1)),"违规：风险预算须逐次不增加",IF(OR(_LockStatus="已锁仓",_LockStatus="解锁信息不完整"),"违规：锁仓期间禁止加仓",IF(G132="","计划可执行：建议股数见N列",IF(OR(G132<=0,G132<>INT(G132),MOD(G132,100)<>0),"违规：实际股数须为100股整数倍",IF(G132>N132,"违规：实际股数超过风险或金字塔上限",IF(AND(B132>1,G132>SUMIFS($G$2:$G$1001,$A$2:$A$1001,A132,$B$2:$B$1001,B132-1)),"违规：加仓股数须逐次不增加",IF(Q132>F132,"违规：止损风险超过本次预算","通过")))))))))))))))
H133: =IF(OR(A133="",D133="",G133=""),"",D133*G133) | I133: =IF(OR(A133="",B133=""),"",IFERROR(LOOKUP(2,1/(单次交易!$A$2:$A$201=A133),单次交易!$H$2:$H$201),0)+SUMIFS($G$2:$G$1001,$A$2:$A$1001,A133,$B$2:$B$1001,"<"&B133)) | J133: =IF(OR(A133="",B133=""),"",IFERROR(LOOKUP(2,1/(单次交易!$A$2:$A$201=A133),单次交易!$E$2:$E$201)*LOOKUP(2,1/(单次交易!$A$2:$A$201=A133),单次交易!$H$2:$H$201),0)+SUMIFS($H$2:$H$1001,$A$2:$A$1001,A133,$B$2:$B$1001,"<"&B133)) | K133: =IF(OR(E133="",I133="",J133=""),"",MAX(E133*I133-J133,0)) | L133: =IF(OR(D133="",E133="",F133="",D133<=E133),"",FLOOR((F133+K133)/(D133-E133),100)) | M133: =IF(OR(A133="",B133="",L133=""),"",IF(B133=1,L133,IFERROR(SUMIFS($G$2:$G$1001,$A$2:$A$1001,A133,$B$2:$B$1001,B133-1),0))) | N133: =IF(OR(L133="",M133=""),"",MIN(L133,M133)) | O133: =IF(OR(I133="",G133=""),"",I133+G133) | P133: =IF(OR(O133="",O133=0),"",(J133+H133)/O133) | Q133: =IF(OR(O133="",E133=""),"",MAX(J133+H133-E133*O133,0)) | R133: =IF(A133="","",IF(COUNTIF(_TradeIds,A133)=0,"违规：交易编号不存在",IF(OR(B133="",B133<1,B133>5,B133<>INT(B133)),"违规：加仓序号须为1到5的整数",IF(COUNTIFS($A$2:$A$1001,A133,$B$2:$B$1001,B133)>1,"违规：同一交易的加仓序号重复",IF(OR(D133="",E133="",F133=""),"计划不完整：请填写加仓价、新止损价和风险预算",IF(OR(D133<=0,E133<=0,F133<=0,D133<=E133),"违规：加仓价必须高于新止损价，金额须大于0",IF(AND(B133>1,COUNTIFS($A$2:$A$1001,A133,$B$2:$B$1001,B133-1,$G$2:$G$1001,">0")=0),"违规：须先完成上一次加仓",IF(AND(B133>1,E133<SUMIFS($E$2:$E$1001,$A$2:$A$1001,A133,$B$2:$B$1001,B133-1)),"违规：新止损价不得低于上一次",IF(AND(B133>1,F133>SUMIFS($F$2:$F$1001,$A$2:$A$1001,A133,$B$2:$B$1001,B133-1)),"违规：风险预算须逐次不增加",IF(OR(_LockStatus="已锁仓",_LockStatus="解锁信息不完整"),"违规：锁仓期间禁止加仓",IF(G133="","计划可执行：建议股数见N列",IF(OR(G133<=0,G133<>INT(G133),MOD(G133,100)<>0),"违规：实际股数须为100股整数倍",IF(G133>N133,"违规：实际股数超过风险或金字塔上限",IF(AND(B133>1,G133>SUMIFS($G$2:$G$1001,$A$2:$A$1001,A133,$B$2:$B$1001,B133-1)),"违规：加仓股数须逐次不增加",IF(Q133>F133,"违规：止损风险超过本次预算","通过")))))))))))))))
H134: =IF(OR(A134="",D134="",G134=""),"",D134*G134) | I134: =IF(OR(A134="",B134=""),"",IFERROR(LOOKUP(2,1/(单次交易!$A$2:$A$201=A134),单次交易!$H$2:$H$201),0)+SUMIFS($G$2:$G$1001,$A$2:$A$1001,A134,$B$2:$B$1001,"<"&B134)) | J134: =IF(OR(A134="",B134=""),"",IFERROR(LOOKUP(2,1/(单次交易!$A$2:$A$201=A134),单次交易!$E$2:$E$201)*LOOKUP(2,1/(单次交易!$A$2:$A$201=A134),单次交易!$H$2:$H$201),0)+SUMIFS($H$2:$H$1001,$A$2:$A$1001,A134,$B$2:$B$1001,"<"&B134)) | K134: =IF(OR(E134="",I134="",J134=""),"",MAX(E134*I134-J134,0)) | L134: =IF(OR(D134="",E134="",F134="",D134<=E134),"",FLOOR((F134+K134)/(D134-E134),100)) | M134: =IF(OR(A134="",B134="",L134=""),"",IF(B134=1,L134,IFERROR(SUMIFS($G$2:$G$1001,$A$2:$A$1001,A134,$B$2:$B$1001,B134-1),0))) | N134: =IF(OR(L134="",M134=""),"",MIN(L134,M134)) | O134: =IF(OR(I134="",G134=""),"",I134+G134) | P134: =IF(OR(O134="",O134=0),"",(J134+H134)/O134) | Q134: =IF(OR(O134="",E134=""),"",MAX(J134+H134-E134*O134,0)) | R134: =IF(A134="","",IF(COUNTIF(_TradeIds,A134)=0,"违规：交易编号不存在",IF(OR(B134="",B134<1,B134>5,B134<>INT(B134)),"违规：加仓序号须为1到5的整数",IF(COUNTIFS($A$2:$A$1001,A134,$B$2:$B$1001,B134)>1,"违规：同一交易的加仓序号重复",IF(OR(D134="",E134="",F134=""),"计划不完整：请填写加仓价、新止损价和风险预算",IF(OR(D134<=0,E134<=0,F134<=0,D134<=E134),"违规：加仓价必须高于新止损价，金额须大于0",IF(AND(B134>1,COUNTIFS($A$2:$A$1001,A134,$B$2:$B$1001,B134-1,$G$2:$G$1001,">0")=0),"违规：须先完成上一次加仓",IF(AND(B134>1,E134<SUMIFS($E$2:$E$1001,$A$2:$A$1001,A134,$B$2:$B$1001,B134-1)),"违规：新止损价不得低于上一次",IF(AND(B134>1,F134>SUMIFS($F$2:$F$1001,$A$2:$A$1001,A134,$B$2:$B$1001,B134-1)),"违规：风险预算须逐次不增加",IF(OR(_LockStatus="已锁仓",_LockStatus="解锁信息不完整"),"违规：锁仓期间禁止加仓",IF(G134="","计划可执行：建议股数见N列",IF(OR(G134<=0,G134<>INT(G134),MOD(G134,100)<>0),"违规：实际股数须为100股整数倍",IF(G134>N134,"违规：实际股数超过风险或金字塔上限",IF(AND(B134>1,G134>SUMIFS($G$2:$G$1001,$A$2:$A$1001,A134,$B$2:$B$1001,B134-1)),"违规：加仓股数须逐次不增加",IF(Q134>F134,"违规：止损风险超过本次预算","通过")))))))))))))))
H135: =IF(OR(A135="",D135="",G135=""),"",D135*G135) | I135: =IF(OR(A135="",B135=""),"",IFERROR(LOOKUP(2,1/(单次交易!$A$2:$A$201=A135),单次交易!$H$2:$H$201),0)+SUMIFS($G$2:$G$1001,$A$2:$A$1001,A135,$B$2:$B$1001,"<"&B135)) | J135: =IF(OR(A135="",B135=""),"",IFERROR(LOOKUP(2,1/(单次交易!$A$2:$A$201=A135),单次交易!$E$2:$E$201)*LOOKUP(2,1/(单次交易!$A$2:$A$201=A135),单次交易!$H$2:$H$201),0)+SUMIFS($H$2:$H$1001,$A$2:$A$1001,A135,$B$2:$B$1001,"<"&B135)) | K135: =IF(OR(E135="",I135="",J135=""),"",MAX(E135*I135-J135,0)) | L135: =IF(OR(D135="",E135="",F135="",D135<=E135),"",FLOOR((F135+K135)/(D135-E135),100)) | M135: =IF(OR(A135="",B135="",L135=""),"",IF(B135=1,L135,IFERROR(SUMIFS($G$2:$G$1001,$A$2:$A$1001,A135,$B$2:$B$1001,B135-1),0))) | N135: =IF(OR(L135="",M135=""),"",MIN(L135,M135)) | O135: =IF(OR(I135="",G135=""),"",I135+G135) | P135: =IF(OR(O135="",O135=0),"",(J135+H135)/O135) | Q135: =IF(OR(O135="",E135=""),"",MAX(J135+H135-E135*O135,0)) | R135: =IF(A135="","",IF(COUNTIF(_TradeIds,A135)=0,"违规：交易编号不存在",IF(OR(B135="",B135<1,B135>5,B135<>INT(B135)),"违规：加仓序号须为1到5的整数",IF(COUNTIFS($A$2:$A$1001,A135,$B$2:$B$1001,B135)>1,"违规：同一交易的加仓序号重复",IF(OR(D135="",E135="",F135=""),"计划不完整：请填写加仓价、新止损价和风险预算",IF(OR(D135<=0,E135<=0,F135<=0,D135<=E135),"违规：加仓价必须高于新止损价，金额须大于0",IF(AND(B135>1,COUNTIFS($A$2:$A$1001,A135,$B$2:$B$1001,B135-1,$G$2:$G$1001,">0")=0),"违规：须先完成上一次加仓",IF(AND(B135>1,E135<SUMIFS($E$2:$E$1001,$A$2:$A$1001,A135,$B$2:$B$1001,B135-1)),"违规：新止损价不得低于上一次",IF(AND(B135>1,F135>SUMIFS($F$2:$F$1001,$A$2:$A$1001,A135,$B$2:$B$1001,B135-1)),"违规：风险预算须逐次不增加",IF(OR(_LockStatus="已锁仓",_LockStatus="解锁信息不完整"),"违规：锁仓期间禁止加仓",IF(G135="","计划可执行：建议股数见N列",IF(OR(G135<=0,G135<>INT(G135),MOD(G135,100)<>0),"违规：实际股数须为100股整数倍",IF(G135>N135,"违规：实际股数超过风险或金字塔上限",IF(AND(B135>1,G135>SUMIFS($G$2:$G$1001,$A$2:$A$1001,A135,$B$2:$B$1001,B135-1)),"违规：加仓股数须逐次不增加",IF(Q135>F135,"违规：止损风险超过本次预算","通过")))))))))))))))
H136: =IF(OR(A136="",D136="",G136=""),"",D136*G136) | I136: =IF(OR(A136="",B136=""),"",IFERROR(LOOKUP(2,1/(单次交易!$A$2:$A$201=A136),单次交易!$H$2:$H$201),0)+SUMIFS($G$2:$G$1001,$A$2:$A$1001,A136,$B$2:$B$1001,"<"&B136)) | J136: =IF(OR(A136="",B136=""),"",IFERROR(LOOKUP(2,1/(单次交易!$A$2:$A$201=A136),单次交易!$E$2:$E$201)*LOOKUP(2,1/(单次交易!$A$2:$A$201=A136),单次交易!$H$2:$H$201),0)+SUMIFS($H$2:$H$1001,$A$2:$A$1001,A136,$B$2:$B$1001,"<"&B136)) | K136: =IF(OR(E136="",I136="",J136=""),"",MAX(E136*I136-J136,0)) | L136: =IF(OR(D136="",E136="",F136="",D136<=E136),"",FLOOR((F136+K136)/(D136-E136),100)) | M136: =IF(OR(A136="",B136="",L136=""),"",IF(B136=1,L136,IFERROR(SUMIFS($G$2:$G$1001,$A$2:$A$1001,A136,$B$2:$B$1001,B136-1),0))) | N136: =IF(OR(L136="",M136=""),"",MIN(L136,M136)) | O136: =IF(OR(I136="",G136=""),"",I136+G136) | P136: =IF(OR(O136="",O136=0),"",(J136+H136)/O136) | Q136: =IF(OR(O136="",E136=""),"",MAX(J136+H136-E136*O136,0)) | R136: =IF(A136="","",IF(COUNTIF(_TradeIds,A136)=0,"违规：交易编号不存在",IF(OR(B136="",B136<1,B136>5,B136<>INT(B136)),"违规：加仓序号须为1到5的整数",IF(COUNTIFS($A$2:$A$1001,A136,$B$2:$B$1001,B136)>1,"违规：同一交易的加仓序号重复",IF(OR(D136="",E136="",F136=""),"计划不完整：请填写加仓价、新止损价和风险预算",IF(OR(D136<=0,E136<=0,F136<=0,D136<=E136),"违规：加仓价必须高于新止损价，金额须大于0",IF(AND(B136>1,COUNTIFS($A$2:$A$1001,A136,$B$2:$B$1001,B136-1,$G$2:$G$1001,">0")=0),"违规：须先完成上一次加仓",IF(AND(B136>1,E136<SUMIFS($E$2:$E$1001,$A$2:$A$1001,A136,$B$2:$B$1001,B136-1)),"违规：新止损价不得低于上一次",IF(AND(B136>1,F136>SUMIFS($F$2:$F$1001,$A$2:$A$1001,A136,$B$2:$B$1001,B136-1)),"违规：风险预算须逐次不增加",IF(OR(_LockStatus="已锁仓",_LockStatus="解锁信息不完整"),"违规：锁仓期间禁止加仓",IF(G136="","计划可执行：建议股数见N列",IF(OR(G136<=0,G136<>INT(G136),MOD(G136,100)<>0),"违规：实际股数须为100股整数倍",IF(G136>N136,"违规：实际股数超过风险或金字塔上限",IF(AND(B136>1,G136>SUMIFS($G$2:$G$1001,$A$2:$A$1001,A136,$B$2:$B$1001,B136-1)),"违规：加仓股数须逐次不增加",IF(Q136>F136,"违规：止损风险超过本次预算","通过")))))))))))))))
H137: =IF(OR(A137="",D137="",G137=""),"",D137*G137) | I137: =IF(OR(A137="",B137=""),"",IFERROR(LOOKUP(2,1/(单次交易!$A$2:$A$201=A137),单次交易!$H$2:$H$201),0)+SUMIFS($G$2:$G$1001,$A$2:$A$1001,A137,$B$2:$B$1001,"<"&B137)) | J137: =IF(OR(A137="",B137=""),"",IFERROR(LOOKUP(2,1/(单次交易!$A$2:$A$201=A137),单次交易!$E$2:$E$201)*LOOKUP(2,1/(单次交易!$A$2:$A$201=A137),单次交易!$H$2:$H$201),0)+SUMIFS($H$2:$H$1001,$A$2:$A$1001,A137,$B$2:$B$1001,"<"&B137)) | K137: =IF(OR(E137="",I137="",J137=""),"",MAX(E137*I137-J137,0)) | L137: =IF(OR(D137="",E137="",F137="",D137<=E137),"",FLOOR((F137+K137)/(D137-E137),100)) | M137: =IF(OR(A137="",B137="",L137=""),"",IF(B137=1,L137,IFERROR(SUMIFS($G$2:$G$1001,$A$2:$A$1001,A137,$B$2:$B$1001,B137-1),0))) | N137: =IF(OR(L137="",M137=""),"",MIN(L137,M137)) | O137: =IF(OR(I137="",G137=""),"",I137+G137) | P137: =IF(OR(O137="",O137=0),"",(J137+H137)/O137) | Q137: =IF(OR(O137="",E137=""),"",MAX(J137+H137-E137*O137,0)) | R137: =IF(A137="","",IF(COUNTIF(_TradeIds,A137)=0,"违规：交易编号不存在",IF(OR(B137="",B137<1,B137>5,B137<>INT(B137)),"违规：加仓序号须为1到5的整数",IF(COUNTIFS($A$2:$A$1001,A137,$B$2:$B$1001,B137)>1,"违规：同一交易的加仓序号重复",IF(OR(D137="",E137="",F137=""),"计划不完整：请填写加仓价、新止损价和风险预算",IF(OR(D137<=0,E137<=0,F137<=0,D137<=E137),"违规：加仓价必须高于新止损价，金额须大于0",IF(AND(B137>1,COUNTIFS($A$2:$A$1001,A137,$B$2:$B$1001,B137-1,$G$2:$G$1001,">0")=0),"违规：须先完成上一次加仓",IF(AND(B137>1,E137<SUMIFS($E$2:$E$1001,$A$2:$A$1001,A137,$B$2:$B$1001,B137-1)),"违规：新止损价不得低于上一次",IF(AND(B137>1,F137>SUMIFS($F$2:$F$1001,$A$2:$A$1001,A137,$B$2:$B$1001,B137-1)),"违规：风险预算须逐次不增加",IF(OR(_LockStatus="已锁仓",_LockStatus="解锁信息不完整"),"违规：锁仓期间禁止加仓",IF(G137="","计划可执行：建议股数见N列",IF(OR(G137<=0,G137<>INT(G137),MOD(G137,100)<>0),"违规：实际股数须为100股整数倍",IF(G137>N137,"违规：实际股数超过风险或金字塔上限",IF(AND(B137>1,G137>SUMIFS($G$2:$G$1001,$A$2:$A$1001,A137,$B$2:$B$1001,B137-1)),"违规：加仓股数须逐次不增加",IF(Q137>F137,"违规：止损风险超过本次预算","通过")))))))))))))))
H138: =IF(OR(A138="",D138="",G138=""),"",D138*G138) | I138: =IF(OR(A138="",B138=""),"",IFERROR(LOOKUP(2,1/(单次交易!$A$2:$A$201=A138),单次交易!$H$2:$H$201),0)+SUMIFS($G$2:$G$1001,$A$2:$A$1001,A138,$B$2:$B$1001,"<"&B138)) | J138: =IF(OR(A138="",B138=""),"",IFERROR(LOOKUP(2,1/(单次交易!$A$2:$A$201=A138),单次交易!$E$2:$E$201)*LOOKUP(2,1/(单次交易!$A$2:$A$201=A138),单次交易!$H$2:$H$201),0)+SUMIFS($H$2:$H$1001,$A$2:$A$1001,A138,$B$2:$B$1001,"<"&B138)) | K138: =IF(OR(E138="",I138="",J138=""),"",MAX(E138*I138-J138,0)) | L138: =IF(OR(D138="",E138="",F138="",D138<=E138),"",FLOOR((F138+K138)/(D138-E138),100)) | M138: =IF(OR(A138="",B138="",L138=""),"",IF(B138=1,L138,IFERROR(SUMIFS($G$2:$G$1001,$A$2:$A$1001,A138,$B$2:$B$1001,B138-1),0))) | N138: =IF(OR(L138="",M138=""),"",MIN(L138,M138)) | O138: =IF(OR(I138="",G138=""),"",I138+G138) | P138: =IF(OR(O138="",O138=0),"",(J138+H138)/O138) | Q138: =IF(OR(O138="",E138=""),"",MAX(J138+H138-E138*O138,0)) | R138: =IF(A138="","",IF(COUNTIF(_TradeIds,A138)=0,"违规：交易编号不存在",IF(OR(B138="",B138<1,B138>5,B138<>INT(B138)),"违规：加仓序号须为1到5的整数",IF(COUNTIFS($A$2:$A$1001,A138,$B$2:$B$1001,B138)>1,"违规：同一交易的加仓序号重复",IF(OR(D138="",E138="",F138=""),"计划不完整：请填写加仓价、新止损价和风险预算",IF(OR(D138<=0,E138<=0,F138<=0,D138<=E138),"违规：加仓价必须高于新止损价，金额须大于0",IF(AND(B138>1,COUNTIFS($A$2:$A$1001,A138,$B$2:$B$1001,B138-1,$G$2:$G$1001,">0")=0),"违规：须先完成上一次加仓",IF(AND(B138>1,E138<SUMIFS($E$2:$E$1001,$A$2:$A$1001,A138,$B$2:$B$1001,B138-1)),"违规：新止损价不得低于上一次",IF(AND(B138>1,F138>SUMIFS($F$2:$F$1001,$A$2:$A$1001,A138,$B$2:$B$1001,B138-1)),"违规：风险预算须逐次不增加",IF(OR(_LockStatus="已锁仓",_LockStatus="解锁信息不完整"),"违规：锁仓期间禁止加仓",IF(G138="","计划可执行：建议股数见N列",IF(OR(G138<=0,G138<>INT(G138),MOD(G138,100)<>0),"违规：实际股数须为100股整数倍",IF(G138>N138,"违规：实际股数超过风险或金字塔上限",IF(AND(B138>1,G138>SUMIFS($G$2:$G$1001,$A$2:$A$1001,A138,$B$2:$B$1001,B138-1)),"违规：加仓股数须逐次不增加",IF(Q138>F138,"违规：止损风险超过本次预算","通过")))))))))))))))
H139: =IF(OR(A139="",D139="",G139=""),"",D139*G139) | I139: =IF(OR(A139="",B139=""),"",IFERROR(LOOKUP(2,1/(单次交易!$A$2:$A$201=A139),单次交易!$H$2:$H$201),0)+SUMIFS($G$2:$G$1001,$A$2:$A$1001,A139,$B$2:$B$1001,"<"&B139)) | J139: =IF(OR(A139="",B139=""),"",IFERROR(LOOKUP(2,1/(单次交易!$A$2:$A$201=A139),单次交易!$E$2:$E$201)*LOOKUP(2,1/(单次交易!$A$2:$A$201=A139),单次交易!$H$2:$H$201),0)+SUMIFS($H$2:$H$1001,$A$2:$A$1001,A139,$B$2:$B$1001,"<"&B139)) | K139: =IF(OR(E139="",I139="",J139=""),"",MAX(E139*I139-J139,0)) | L139: =IF(OR(D139="",E139="",F139="",D139<=E139),"",FLOOR((F139+K139)/(D139-E139),100)) | M139: =IF(OR(A139="",B139="",L139=""),"",IF(B139=1,L139,IFERROR(SUMIFS($G$2:$G$1001,$A$2:$A$1001,A139,$B$2:$B$1001,B139-1),0))) | N139: =IF(OR(L139="",M139=""),"",MIN(L139,M139)) | O139: =IF(OR(I139="",G139=""),"",I139+G139) | P139: =IF(OR(O139="",O139=0),"",(J139+H139)/O139) | Q139: =IF(OR(O139="",E139=""),"",MAX(J139+H139-E139*O139,0)) | R139: =IF(A139="","",IF(COUNTIF(_TradeIds,A139)=0,"违规：交易编号不存在",IF(OR(B139="",B139<1,B139>5,B139<>INT(B139)),"违规：加仓序号须为1到5的整数",IF(COUNTIFS($A$2:$A$1001,A139,$B$2:$B$1001,B139)>1,"违规：同一交易的加仓序号重复",IF(OR(D139="",E139="",F139=""),"计划不完整：请填写加仓价、新止损价和风险预算",IF(OR(D139<=0,E139<=0,F139<=0,D139<=E139),"违规：加仓价必须高于新止损价，金额须大于0",IF(AND(B139>1,COUNTIFS($A$2:$A$1001,A139,$B$2:$B$1001,B139-1,$G$2:$G$1001,">0")=0),"违规：须先完成上一次加仓",IF(AND(B139>1,E139<SUMIFS($E$2:$E$1001,$A$2:$A$1001,A139,$B$2:$B$1001,B139-1)),"违规：新止损价不得低于上一次",IF(AND(B139>1,F139>SUMIFS($F$2:$F$1001,$A$2:$A$1001,A139,$B$2:$B$1001,B139-1)),"违规：风险预算须逐次不增加",IF(OR(_LockStatus="已锁仓",_LockStatus="解锁信息不完整"),"违规：锁仓期间禁止加仓",IF(G139="","计划可执行：建议股数见N列",IF(OR(G139<=0,G139<>INT(G139),MOD(G139,100)<>0),"违规：实际股数须为100股整数倍",IF(G139>N139,"违规：实际股数超过风险或金字塔上限",IF(AND(B139>1,G139>SUMIFS($G$2:$G$1001,$A$2:$A$1001,A139,$B$2:$B$1001,B139-1)),"违规：加仓股数须逐次不增加",IF(Q139>F139,"违规：止损风险超过本次预算","通过")))))))))))))))
H140: =IF(OR(A140="",D140="",G140=""),"",D140*G140) | I140: =IF(OR(A140="",B140=""),"",IFERROR(LOOKUP(2,1/(单次交易!$A$2:$A$201=A140),单次交易!$H$2:$H$201),0)+SUMIFS($G$2:$G$1001,$A$2:$A$1001,A140,$B$2:$B$1001,"<"&B140)) | J140: =IF(OR(A140="",B140=""),"",IFERROR(LOOKUP(2,1/(单次交易!$A$2:$A$201=A140),单次交易!$E$2:$E$201)*LOOKUP(2,1/(单次交易!$A$2:$A$201=A140),单次交易!$H$2:$H$201),0)+SUMIFS($H$2:$H$1001,$A$2:$A$1001,A140,$B$2:$B$1001,"<"&B140)) | K140: =IF(OR(E140="",I140="",J140=""),"",MAX(E140*I140-J140,0)) | L140: =IF(OR(D140="",E140="",F140="",D140<=E140),"",FLOOR((F140+K140)/(D140-E140),100)) | M140: =IF(OR(A140="",B140="",L140=""),"",IF(B140=1,L140,IFERROR(SUMIFS($G$2:$G$1001,$A$2:$A$1001,A140,$B$2:$B$1001,B140-1),0))) | N140: =IF(OR(L140="",M140=""),"",MIN(L140,M140)) | O140: =IF(OR(I140="",G140=""),"",I140+G140) | P140: =IF(OR(O140="",O140=0),"",(J140+H140)/O140) | Q140: =IF(OR(O140="",E140=""),"",MAX(J140+H140-E140*O140,0)) | R140: =IF(A140="","",IF(COUNTIF(_TradeIds,A140)=0,"违规：交易编号不存在",IF(OR(B140="",B140<1,B140>5,B140<>INT(B140)),"违规：加仓序号须为1到5的整数",IF(COUNTIFS($A$2:$A$1001,A140,$B$2:$B$1001,B140)>1,"违规：同一交易的加仓序号重复",IF(OR(D140="",E140="",F140=""),"计划不完整：请填写加仓价、新止损价和风险预算",IF(OR(D140<=0,E140<=0,F140<=0,D140<=E140),"违规：加仓价必须高于新止损价，金额须大于0",IF(AND(B140>1,COUNTIFS($A$2:$A$1001,A140,$B$2:$B$1001,B140-1,$G$2:$G$1001,">0")=0),"违规：须先完成上一次加仓",IF(AND(B140>1,E140<SUMIFS($E$2:$E$1001,$A$2:$A$1001,A140,$B$2:$B$1001,B140-1)),"违规：新止损价不得低于上一次",IF(AND(B140>1,F140>SUMIFS($F$2:$F$1001,$A$2:$A$1001,A140,$B$2:$B$1001,B140-1)),"违规：风险预算须逐次不增加",IF(OR(_LockStatus="已锁仓",_LockStatus="解锁信息不完整"),"违规：锁仓期间禁止加仓",IF(G140="","计划可执行：建议股数见N列",IF(OR(G140<=0,G140<>INT(G140),MOD(G140,100)<>0),"违规：实际股数须为100股整数倍",IF(G140>N140,"违规：实际股数超过风险或金字塔上限",IF(AND(B140>1,G140>SUMIFS($G$2:$G$1001,$A$2:$A$1001,A140,$B$2:$B$1001,B140-1)),"违规：加仓股数须逐次不增加",IF(Q140>F140,"违规：止损风险超过本次预算","通过")))))))))))))))
H141: =IF(OR(A141="",D141="",G141=""),"",D141*G141) | I141: =IF(OR(A141="",B141=""),"",IFERROR(LOOKUP(2,1/(单次交易!$A$2:$A$201=A141),单次交易!$H$2:$H$201),0)+SUMIFS($G$2:$G$1001,$A$2:$A$1001,A141,$B$2:$B$1001,"<"&B141)) | J141: =IF(OR(A141="",B141=""),"",IFERROR(LOOKUP(2,1/(单次交易!$A$2:$A$201=A141),单次交易!$E$2:$E$201)*LOOKUP(2,1/(单次交易!$A$2:$A$201=A141),单次交易!$H$2:$H$201),0)+SUMIFS($H$2:$H$1001,$A$2:$A$1001,A141,$B$2:$B$1001,"<"&B141)) | K141: =IF(OR(E141="",I141="",J141=""),"",MAX(E141*I141-J141,0)) | L141: =IF(OR(D141="",E141="",F141="",D141<=E141),"",FLOOR((F141+K141)/(D141-E141),100)) | M141: =IF(OR(A141="",B141="",L141=""),"",IF(B141=1,L141,IFERROR(SUMIFS($G$2:$G$1001,$A$2:$A$1001,A141,$B$2:$B$1001,B141-1),0))) | N141: =IF(OR(L141="",M141=""),"",MIN(L141,M141)) | O141: =IF(OR(I141="",G141=""),"",I141+G141) | P141: =IF(OR(O141="",O141=0),"",(J141+H141)/O141) | Q141: =IF(OR(O141="",E141=""),"",MAX(J141+H141-E141*O141,0)) | R141: =IF(A141="","",IF(COUNTIF(_TradeIds,A141)=0,"违规：交易编号不存在",IF(OR(B141="",B141<1,B141>5,B141<>INT(B141)),"违规：加仓序号须为1到5的整数",IF(COUNTIFS($A$2:$A$1001,A141,$B$2:$B$1001,B141)>1,"违规：同一交易的加仓序号重复",IF(OR(D141="",E141="",F141=""),"计划不完整：请填写加仓价、新止损价和风险预算",IF(OR(D141<=0,E141<=0,F141<=0,D141<=E141),"违规：加仓价必须高于新止损价，金额须大于0",IF(AND(B141>1,COUNTIFS($A$2:$A$1001,A141,$B$2:$B$1001,B141-1,$G$2:$G$1001,">0")=0),"违规：须先完成上一次加仓",IF(AND(B141>1,E141<SUMIFS($E$2:$E$1001,$A$2:$A$1001,A141,$B$2:$B$1001,B141-1)),"违规：新止损价不得低于上一次",IF(AND(B141>1,F141>SUMIFS($F$2:$F$1001,$A$2:$A$1001,A141,$B$2:$B$1001,B141-1)),"违规：风险预算须逐次不增加",IF(OR(_LockStatus="已锁仓",_LockStatus="解锁信息不完整"),"违规：锁仓期间禁止加仓",IF(G141="","计划可执行：建议股数见N列",IF(OR(G141<=0,G141<>INT(G141),MOD(G141,100)<>0),"违规：实际股数须为100股整数倍",IF(G141>N141,"违规：实际股数超过风险或金字塔上限",IF(AND(B141>1,G141>SUMIFS($G$2:$G$1001,$A$2:$A$1001,A141,$B$2:$B$1001,B141-1)),"违规：加仓股数须逐次不增加",IF(Q141>F141,"违规：止损风险超过本次预算","通过")))))))))))))))
H142: =IF(OR(A142="",D142="",G142=""),"",D142*G142) | I142: =IF(OR(A142="",B142=""),"",IFERROR(LOOKUP(2,1/(单次交易!$A$2:$A$201=A142),单次交易!$H$2:$H$201),0)+SUMIFS($G$2:$G$1001,$A$2:$A$1001,A142,$B$2:$B$1001,"<"&B142)) | J142: =IF(OR(A142="",B142=""),"",IFERROR(LOOKUP(2,1/(单次交易!$A$2:$A$201=A142),单次交易!$E$2:$E$201)*LOOKUP(2,1/(单次交易!$A$2:$A$201=A142),单次交易!$H$2:$H$201),0)+SUMIFS($H$2:$H$1001,$A$2:$A$1001,A142,$B$2:$B$1001,"<"&B142)) | K142: =IF(OR(E142="",I142="",J142=""),"",MAX(E142*I142-J142,0)) | L142: =IF(OR(D142="",E142="",F142="",D142<=E142),"",FLOOR((F142+K142)/(D142-E142),100)) | M142: =IF(OR(A142="",B142="",L142=""),"",IF(B142=1,L142,IFERROR(SUMIFS($G$2:$G$1001,$A$2:$A$1001,A142,$B$2:$B$1001,B142-1),0))) | N142: =IF(OR(L142="",M142=""),"",MIN(L142,M142)) | O142: =IF(OR(I142="",G142=""),"",I142+G142) | P142: =IF(OR(O142="",O142=0),"",(J142+H142)/O142) | Q142: =IF(OR(O142="",E142=""),"",MAX(J142+H142-E142*O142,0)) | R142: =IF(A142="","",IF(COUNTIF(_TradeIds,A142)=0,"违规：交易编号不存在",IF(OR(B142="",B142<1,B142>5,B142<>INT(B142)),"违规：加仓序号须为1到5的整数",IF(COUNTIFS($A$2:$A$1001,A142,$B$2:$B$1001,B142)>1,"违规：同一交易的加仓序号重复",IF(OR(D142="",E142="",F142=""),"计划不完整：请填写加仓价、新止损价和风险预算",IF(OR(D142<=0,E142<=0,F142<=0,D142<=E142),"违规：加仓价必须高于新止损价，金额须大于0",IF(AND(B142>1,COUNTIFS($A$2:$A$1001,A142,$B$2:$B$1001,B142-1,$G$2:$G$1001,">0")=0),"违规：须先完成上一次加仓",IF(AND(B142>1,E142<SUMIFS($E$2:$E$1001,$A$2:$A$1001,A142,$B$2:$B$1001,B142-1)),"违规：新止损价不得低于上一次",IF(AND(B142>1,F142>SUMIFS($F$2:$F$1001,$A$2:$A$1001,A142,$B$2:$B$1001,B142-1)),"违规：风险预算须逐次不增加",IF(OR(_LockStatus="已锁仓",_LockStatus="解锁信息不完整"),"违规：锁仓期间禁止加仓",IF(G142="","计划可执行：建议股数见N列",IF(OR(G142<=0,G142<>INT(G142),MOD(G142,100)<>0),"违规：实际股数须为100股整数倍",IF(G142>N142,"违规：实际股数超过风险或金字塔上限",IF(AND(B142>1,G142>SUMIFS($G$2:$G$1001,$A$2:$A$1001,A142,$B$2:$B$1001,B142-1)),"违规：加仓股数须逐次不增加",IF(Q142>F142,"违规：止损风险超过本次预算","通过")))))))))))))))
H143: =IF(OR(A143="",D143="",G143=""),"",D143*G143) | I143: =IF(OR(A143="",B143=""),"",IFERROR(LOOKUP(2,1/(单次交易!$A$2:$A$201=A143),单次交易!$H$2:$H$201),0)+SUMIFS($G$2:$G$1001,$A$2:$A$1001,A143,$B$2:$B$1001,"<"&B143)) | J143: =IF(OR(A143="",B143=""),"",IFERROR(LOOKUP(2,1/(单次交易!$A$2:$A$201=A143),单次交易!$E$2:$E$201)*LOOKUP(2,1/(单次交易!$A$2:$A$201=A143),单次交易!$H$2:$H$201),0)+SUMIFS($H$2:$H$1001,$A$2:$A$1001,A143,$B$2:$B$1001,"<"&B143)) | K143: =IF(OR(E143="",I143="",J143=""),"",MAX(E143*I143-J143,0)) | L143: =IF(OR(D143="",E143="",F143="",D143<=E143),"",FLOOR((F143+K143)/(D143-E143),100)) | M143: =IF(OR(A143="",B143="",L143=""),"",IF(B143=1,L143,IFERROR(SUMIFS($G$2:$G$1001,$A$2:$A$1001,A143,$B$2:$B$1001,B143-1),0))) | N143: =IF(OR(L143="",M143=""),"",MIN(L143,M143)) | O143: =IF(OR(I143="",G143=""),"",I143+G143) | P143: =IF(OR(O143="",O143=0),"",(J143+H143)/O143) | Q143: =IF(OR(O143="",E143=""),"",MAX(J143+H143-E143*O143,0)) | R143: =IF(A143="","",IF(COUNTIF(_TradeIds,A143)=0,"违规：交易编号不存在",IF(OR(B143="",B143<1,B143>5,B143<>INT(B143)),"违规：加仓序号须为1到5的整数",IF(COUNTIFS($A$2:$A$1001,A143,$B$2:$B$1001,B143)>1,"违规：同一交易的加仓序号重复",IF(OR(D143="",E143="",F143=""),"计划不完整：请填写加仓价、新止损价和风险预算",IF(OR(D143<=0,E143<=0,F143<=0,D143<=E143),"违规：加仓价必须高于新止损价，金额须大于0",IF(AND(B143>1,COUNTIFS($A$2:$A$1001,A143,$B$2:$B$1001,B143-1,$G$2:$G$1001,">0")=0),"违规：须先完成上一次加仓",IF(AND(B143>1,E143<SUMIFS($E$2:$E$1001,$A$2:$A$1001,A143,$B$2:$B$1001,B143-1)),"违规：新止损价不得低于上一次",IF(AND(B143>1,F143>SUMIFS($F$2:$F$1001,$A$2:$A$1001,A143,$B$2:$B$1001,B143-1)),"违规：风险预算须逐次不增加",IF(OR(_LockStatus="已锁仓",_LockStatus="解锁信息不完整"),"违规：锁仓期间禁止加仓",IF(G143="","计划可执行：建议股数见N列",IF(OR(G143<=0,G143<>INT(G143),MOD(G143,100)<>0),"违规：实际股数须为100股整数倍",IF(G143>N143,"违规：实际股数超过风险或金字塔上限",IF(AND(B143>1,G143>SUMIFS($G$2:$G$1001,$A$2:$A$1001,A143,$B$2:$B$1001,B143-1)),"违规：加仓股数须逐次不增加",IF(Q143>F143,"违规：止损风险超过本次预算","通过")))))))))))))))
... H1001: =IF(OR(A1001="",D1001="",G1001=""),"",D1001*G1001) | I1001: =IF(OR(A1001="",B1001=""),"",IFERROR(LOOKUP(2,1/(单次交易!$A$2:$A$201=A1001),单次交易!$H$2:$H$201),0)+SUMIFS($G$2:$G$1001,$A$2:$A$1001,A1001,$B$2:$B$1001,"<"&B1001)) | J1001: =IF(OR(A1001="",B1001=""),"",IFERROR(LOOKUP(2,1/(单次交易!$A$2:$A$201=A1001),单次交易!$E$2:$E$201)*LOOKUP(2,1/(单次交易!$A$2:$A$201=A1001),单次交易!$H$2:$H$201),0)+SUMIFS($H$2:$H$1001,$A$2:$A$1001,A1001,$B$2:$B$1001,"<"&B1001)) | K1001: =IF(OR(E1001="",I1001="",J1001=""),"",MAX(E1001*I1001-J1001,0)) | L1001: =IF(OR(D1001="",E1001="",F1001="",D1001<=E1001),"",FLOOR((F1001+K1001)/(D1001-E1001),100)) | M1001: =IF(OR(A1001="",B1001="",L1001=""),"",IF(B1001=1,L1001,IFERROR(SUMIFS($G$2:$G$1001,$A$2:$A$1001,A1001,$B$2:$B$1001,B1001-1),0))) | N1001: =IF(OR(L1001="",M1001=""),"",MIN(L1001,M1001)) | O1001: =IF(OR(I1001="",G1001=""),"",I1001+G1001) | P1001: =IF(OR(O1001="",O1001=0),"",(J1001+H1001)/O1001) | Q1001: =IF(OR(O1001="",E1001=""),"",MAX(J1001+H1001-E1001*O1001,0)) | R1001: =IF(A1001="","",IF(COUNTIF(_TradeIds,A1001)=0,"违规：交易编号不存在",IF(OR(B1001="",B1001<1,B1001>5,B1001<>INT(B1001)),"违规：加仓序号须为1到5的整数",IF(COUNTIFS($A$2:$A$1001,A1001,$B$2:$B$1001,B1001)>1,"违规：同一交易的加仓序号重复",IF(OR(D1001="",E1001="",F1001=""),"计划不完整：请填写加仓价、新止损价和风险预算",IF(OR(D1001<=0,E1001<=0,F1001<=0,D1001<=E1001),"违规：加仓价必须高于新止损价，金额须大于0",IF(AND(B1001>1,COUNTIFS($A$2:$A$1001,A1001,$B$2:$B$1001,B1001-1,$G$2:$G$1001,">0")=0),"违规：须先完成上一次加仓",IF(AND(B1001>1,E1001<SUMIFS($E$2:$E$1001,$A$2:$A$1001,A1001,$B$2:$B$1001,B1001-1)),"违规：新止损价不得低于上一次",IF(AND(B1001>1,F1001>SUMIFS($F$2:$F$1001,$A$2:$A$1001,A1001,$B$2:$B$1001,B1001-1)),"违规：风险预算须逐次不增加",IF(OR(_LockStatus="已锁仓",_LockStatus="解锁信息不完整"),"违规：锁仓期间禁止加仓",IF(G1001="","计划可执行：建议股数见N列",IF(OR(G1001<=0,G1001<>INT(G1001),MOD(G1001,100)<>0),"违规：实际股数须为100股整数倍",IF(G1001>N1001,"违规：实际股数超过风险或金字塔上限",IF(AND(B1001>1,G1001>SUMIFS($G$2:$G$1001,$A$2:$A$1001,A1001,$B$2:$B$1001,B1001-1)),"违规：加仓股数须逐次不增加",IF(Q1001>F1001,"违规：止损风险超过本次预算","通过")))))))))))))))

Sheet 多次统计数据
A1: 指标 | B1: 当前统计 | C1: 口径说明
A2: 已完成交易数 | B2: =COUNT(单次交易!M2:M201) -> 135 | C2: 存在卖出日期的交易
A3: 盈利交易数 | B3: =COUNTIF(单次交易!X2:X201,">0") -> 61 | C3: 实际盈亏金额大于0
A4: 亏损交易数 | B4: =COUNTIF(单次交易!X2:X201,"<0") -> 75 | C4: 实际盈亏金额小于0
A5: 持平交易数 | B5: =COUNTIFS(单次交易!M2:M201,"<>",单次交易!X2:X201,"=0") -> 0 | C5: 已卖出且实际盈亏为0；不进入胜负样本
A6: 盈利概率 | B6: =IFERROR(B3/(B3+B4),"") -> 0.44852941 | C6: 盈利数÷胜负交易数
A7: 亏损概率 | B7: =IFERROR(B4/(B3+B4),"") -> 0.55147059 | C7: 亏损数÷胜负交易数
A8: 平均盈利百分比 | B8: =IFERROR(AVERAGEIF(单次交易!X2:X201,">0",单次交易!AE2:AE201),"") -> 0.11021267 | C8: 盈利交易实际账户收益率的平均值
A9: 平均亏损百分比 | B9: =IFERROR(-AVERAGEIF(单次交易!X2:X201,"<0",单次交易!AE2:AE201),"") -> 0.043964917 | C9: 亏损交易实际账户收益率绝对值的平均值
A10: 盈利的持有总天数 | B10: =SUMIF(单次交易!X2:X201,">0",单次交易!AA2:AA201) -> 3050 | C10: 自然日
A11: 亏损的持有总天数 | B11: =SUMIF(单次交易!X2:X201,"<0",单次交易!AA2:AA201) -> 2226 | C11: 自然日
A12: 平均交易金额 | B12: =IFERROR(SUMPRODUCT(单次交易!AO2:AO201,单次交易!AP2:AP201)/COUNT(单次交易!AP2:AP201),"") -> 176472.65 | C12: 实际加权买入价×累计买入股数的平均值，包含未卖出交易
A13: 期望收益率 | B13: =IF(OR(B6="",B7="",B8="",B9=""),"",B6*B8-B7*B9) -> 0.025188265 | C13: 盈利贡献减亏损贡献
A14: 迄今为止的复利净利润率 | B14: =IF(COUNT(单次交易!AE2:AE201)=0,"",EXP(SUMPRODUCT(IFERROR(LN(1+单次交易!AE2:AE201),0)))-1) -> 0.020801943 | C14: 按每笔实际账户收益率逐笔连乘

Sheet 账户数据
A1: 指标 | B1: 值 | C1: 录入/计算说明
A2: 初始总金额 | B2: 100000 | C2: 手动输入；当前金额从此值开始累计
A3: 当前总金额 | B3: =IF(B2="","",B2+SUM(单次交易!X2:X201)) -> 1205088 | C3: 初始总金额＋全部已实现盈亏
A4: 单次交易允许的亏损比例 | B4: 0.02 | C4: 默认1%，可调整；开仓时复制为交易快照
A5: 单次交易允许的亏损金额 | B5: =IF(B3="","",B3*B4) -> 24101.76 | C5: 当前总金额×单次允许亏损比例
A6: 当月允许最大亏损比例 | B6: 0.06 | C6: 默认5%，可调整
A7: 当月允许最大亏损金额 | B7: =IF(B3="","",B3*B6) -> 72305.28 | C7: 当前总金额×当月最大亏损比例
A8: 当月亏损金额 | B8: =SUMIFS(单次交易!X2:X201,单次交易!X2:X201,"<0",单次交易!M2:M201,">="&EOMONTH(TODAY(),-1)+1,单次交易!M2:M201,"<="&EOMONTH(TODAY(),0)) -> 0 | C8: 按卖出日期统计本月已实现亏损，保留负号
A9: 当前未平仓理论亏损 | B9: =IFERROR(SUM(单次交易!AQ2:AQ201),0) -> 22500 | C9: 未平仓三批持仓按当前有效止损计算的风险合计
A10: 当月剩余可开仓风险额度 | B10: =IF(OR(B7="",B9=""),"",B7-B9) -> 49805.28 | C10: 当月允许最大亏损金额－当前未平仓理论亏损
A11: 账户实际累计收益率 | B11: =IF(OR(B2="",B3="",B2<=0),"",B3/B2-1) -> 11.05088 | C11: 当前总金额÷初始总金额－1；无入金出金时为账户权威累计收益
A13: 连续亏损锁仓比例 | B13: 0.06 | C13: 从最近盈利或有效手动解锁后的下一笔开始累计；默认6%
A14: 最近盈利记录序号 | B14: =IFERROR(LOOKUP(2,1/((单次交易!$M$2:$M$201<>"")*(单次交易!$X$2:$X$201>0)),ROW(单次交易!$X$2:$X$201)-1),0) -> 134 | C14: 按工作表记录顺序查找最近一笔已平仓盈利交易
A15: 最近已完成记录序号 | B15: =IFERROR(LOOKUP(2,1/(单次交易!$M$2:$M$201<>""),ROW(单次交易!$M$2:$M$201)-1),0) -> 135 | C15: 按工作表记录顺序查找最后一笔已平仓交易
A16: 手动解锁截至记录序号 | B16: 118 | C16: 锁仓复盘后填写当前最近已完成记录序号；须同时填写解锁原因
A17: 手动解锁原因 | B17: 解锁 | C17: 例如：已完成复盘，开始新的模拟周期
A18: 当前周期起点序号 | B18: =MAX(B14,IF(AND(ISNUMBER(B16),B16>=1,B16<=B15,B17<>""),B16,0)) -> 134 | C18: 取最近盈利序号与有效手动解锁序号中的较大值
A19: 周期起点账户金额 | B19: =IF(B2="","",IF(B18=0,B2,B2+SUM(单次交易!$X$2:INDEX(单次交易!$X:$X,B18+1)))) -> 1235288 | C19: 初始金额加上周期起点及以前的全部已实现盈亏
A20: 当前周期累计亏损 | B20: =IF(B18>=B15,0,-SUMPRODUCT((ROW(单次交易!$X$2:$X$201)-1>B18)*(单次交易!$M$2:$M$201<>"")*(IFERROR(单次交易!$X$2:$X$201,0)<0)*IFERROR(单次交易!$X$2:$X$201,0))) -> 3255 | C20: 仅累计周期起点之后的已平仓亏损；盈利会自动成为新起点
A21: 连续亏损比例 | B21: =IF(OR(B19="",B19<=0),"",B20/B19) -> 0.002635013 | C21: 当前周期累计亏损÷周期起点账户金额
A22: 锁仓风险使用率 | B22: =IF(OR(B13="",B13<=0,B21=""),"",B21/B13) -> 0.043916884 | C22: 达到80%预警，达到100%锁仓
A23: 连续亏损锁仓状态 | B23: =IF(OR(AND(B16<>"",B17=""),AND(B16="",B17<>""),AND(B16<>"",OR(NOT(ISNUMBER(B16)),B16<1,B16>B15,B16<>INT(B16)))),"解锁信息不完整",IF(B22>=1,"已锁仓",IF(B22>=0.8,"接近锁仓","正常"))) -> 正常 | C23: 锁仓时禁止新开仓；有效手动解锁后从下一笔重新累计

Sheet 目标收益
A1: 指标 | B1: 值 | C1: 口径说明
A2: 总金额 | B2: =账户数据!B3 -> 1205088 | C2: 来自账户当前总金额
A3: 目标收益率 | B3: 0.1 | C3: 手动输入
A4: 目标收益金额 | B4: =IF(OR(B2="",B3=""),"",B2*B3) -> 120508.8 | C4: 总金额×目标收益率
A5: 平均交易金额 | B5: =多次统计数据!B12 -> 176472.65 | C5: 来自历史交易统计
A6: 历史期望收益率 | B6: =多次统计数据!B13 -> 0.025188265 | C6: 来自历史胜率与平均盈亏
A7: 所需投资笔数 | B7: =IF(OR(B3="",B6="",B3<=0,B6<=0),"暂不可计算",ROUNDUP(LN(1+B3)/LN(1+B6),0)) -> 4 | C7: 按目标收益率与历史账户期望收益率复利计算并向上取整
